[{"job_id": "100003009053112", "location_code": "hk", "company": "Changjiang Securities International Financial Group Limited", "job_title": "Dealer", "description": "Job Responsibilities:\n\nVerify and execute trade orders of securities and futures products for global market in accurate and timely manner\nAssist to perform day-end processing for trade reconciliation and settlement\nProvide quality services in answering client\u2019s enquiries with trade related matters\nMonitor clients\u2019 risks and perform risk control\nSupport system testing and UAT\nTake up ad hoc assignments as required\nFresh graduates are also welcome\n\nRequirements:\n\n\nUniversity graduates preferably in Finance or Business related disciplines\n1 to 3 years relevant experience in financial institutions or brokerage firms\nHolder of SFC licenses RA1 and RA2\nFamiliar with the relevant rules of regulated bodies and exchanges in trading\nDetail minded, able to work effectively under pressure and be a team player\nStrong PC skills and online trading\nGood command of Putonghua, English and Cantonese\nWilling to work day/night shift and Hong Kong public holidays\nImmediate available is preferred\n\nWe offer 5-days work with good career prospect and remuneration package for the right candidate.\u00a0Salary will be commensurate with qualifications and experience.\u00a0Interested parties please apply with\u00a0full resume (both Chinese and English versions)\u00a0with\u00a0current and expected salary\u00a0by clicking 'Apply Now'.\n\nAll personal data will be used for recruitment purpose only and treated in strict confidence.", "employment_types": ["Full Time", "Permanent"], "selling_points": [], "locations": ["Sheung Wan"], "categories": ["Banking / Finance", "Dealing & Trading", "Equities / Capital Markets", "Order Processing & Operation / Settlement"], "post_time": "2022-01-17T05:53:25Z", "salary": {"currency": null, "max": null, "min": null, "period": "monthly", "term": null}, "salary_visible": false, "title_keywords": ["dealer"], "responsibilities": ["control", "uat", "monitor", "quality", "testing", "ad hoc assignments"], "requirements": {"degrees": [], "majors": [], "languages": ["cantonese", "putonghua", "english"], "language_level": ["good command"], "hard_skills": ["pc skills"], "soft_skills": ["work effectively", "team player", "under pressure"], "languages_combined": [{"language": "cantonese", "language_level": ["good command"]}, {"language": "putonghua", "language_level": ["good command"]}, {"language": "english", "language_level": ["good command"]}]}, "experience_required": {"duration": ["1 to 3 years"], "field": ["brokerage", "financial institutions", "relevant experience"]}}, {"job_id": "100003009054370", "location_code": "hk", "company": "Bright Smart Securities International (H.K.) Limited", "job_title": "Dealing Officer (Day/Night shift allowance $4,000)", "description": "Responsibilities:\n\n\nExecute dealing orders for global securities and futures market;\nHandle daily phone/online enquiries and perform clients\u2019 account instructions;\nMonitor client\u2019s orders and margin level, conduct margin call when necessary;\nMatch daily transaction records and trade position and compile various trading reports;\nAssist in daily operation of dealing room and ad hoc duties.\u00a0\n\nRequirement & Qualifications:\n\n\nHolder of SFC license RA1 and RA2 is an advantage;\nMinimum 1 year relevant experience in stocks, futures & options;\nGeneral knowledge in global stocks and futures trading;\nFamiliar with Sharp Point system is a plus;\nGood team player,\u00a0able to work under pressure\u00a0and willing to learn;\nProblem-solving skills and customer-oriented;\nGood command of spoken and written English and Chinese including Putonghua;\nWilling to work night shift from 4:30pm-1:00am or 12:15am-8:45am with allowance (HK$4,000);\nCandidates with\u00a0more experience will be considered as Senior officer.\n\n\u00a0We Offer:\n\nCompetitive remuneration package\n5 Days Work & Bank Holidays\nAttendance Bonus\nMeal Allowance\nDiscretionary Bonus\nMedical Insurance\nOn the Job Training\n\nWe provide attractive remuneration package and fringe benefits for the right candidate.\n\nInterested parties please send detailed resume with current and expected salaries to\u00a0Human Resources Department by clicking\u00a0\"Apply Now\"\u00a0or\u00a0fax to: 2530 2218.\n\nAll information collected will be used for recruitment purpose only, only shortlisted candidates will be notified.\u00a0Welcome to visit our website:\u00a0http://www.bsgroup.com.hk\u00a0for more information.", "employment_types": ["Full Time", "Permanent"], "selling_points": [], "locations": ["Central"], "categories": ["Banking / Finance", "Investment", "Financial Services", "Dealing & Trading"], "post_time": "2022-01-17T09:18:36Z", "salary": {"currency": null, "max": null, "min": null, "period": "monthly", "term": null}, "salary_visible": false, "title_keywords": ["officer"], "responsibilities": ["daily operation", "ad hoc duties", "monitor", "reports"], "requirements": {"degrees": [], "majors": [], "languages": ["putonghua", "english", "chinese"], "language_level": ["good command"], "hard_skills": ["problem-solving skills", "plus", "sfc license"], "soft_skills": ["good team player", "willing to learn", "customer-oriented", "problem-solving skills", "work under pressure"], "languages_combined": [{"language": "putonghua", "language_level": ["good command"]}, {"language": "english", "language_level": ["good command"]}, {"language": "chinese", "language_level": ["good command"]}]}, "experience_required": {"duration": ["minimum 1 year"], "field": ["relevant experience"]}}, {"job_id": "100003009054451", "location_code": "hk", "company": "China Everbright Securities International Company Limited", "job_title": "Sales Support, Private Client Services", "description": "Job Responsibilities\n\nTo receive and execute clients\u2019 orders in bonds, funds and structured products with counterparties;\nTo deal with clients and sales teams to initiate trades and execute trades, including but not limited to rate quotes, repos and other hedging derivatives;\nTo act as a middle office staff to support sales teams in account opening, client onboarding and servicing, and product settlement;\nTo handle trading and price enquiry platforms eg Ayers, Bloomberg, iFast etc;\nJob Requirements\n\nDegree holder with 3 years dealing and operational support experience in financial products (e.g. Bonds, Funds and Structured Products);\nHolder of SFC License for RA1;\nHardworking and keen on learning new knowledge;\nAccurate, detail-minded, responsible and self-motivated;\nA team player with sound communication skills;\nProficiency in both spoken and written English and Chinese (including Mandarin);\nExperience in bank dealing desk is preferable;\nImmediately available is highly preferred\n\nAttractive remuneration will be offered to the right candidate. Interested parties you may call telephone no. 3196 6253 for more details.\n\nPersonal data collected is for recruitment purpose only.", "employment_types": ["Full Time", "Permanent"], "selling_points": [], "locations": ["Causeway Bay"], "categories": ["Banking / Finance", "Investment", "Dealing & Trading", "Wealth Management"], "post_time": "2022-01-17T09:35:48Z", "salary": {"currency": null, "max": null, "min": null, "period": "monthly", "term": null}, "salary_visible": false, "title_keywords": ["sales"], "responsibilities": ["account opening", "teams"], "requirements": {"degrees": ["degree holder"], "majors": [], "languages": ["english", "chinese", "mandarin"], "language_level": ["proficiency"], "hard_skills": ["sfc license"], "soft_skills": ["detail-minded", "communication skills", "self-motivated", "accurate", "responsible", "keen", "learning", "team player", "structured", "hardworking"], "languages_combined": [{"language": "english", "language_level": ["proficiency"]}, {"language": "chinese", "language_level": ["proficiency"]}, {"language": "mandarin", "language_level": []}]}, "experience_required": {"duration": ["3 years"], "field": ["financial"]}}, {"job_id": "100003009051749", "location_code": "hk", "company": "", "job_title": "Investment Specialist", "description": "\u00a0Ref:\u00a0SS/PCS/170122DB/23\n\nResponsibilities\n\n\nProvide professional customer services and sales support to investment consultants such as account opening, insurance application & policies service, and answering customer enquiries\nHandle daily routine in settlement of various types of investment products, particularly wealth management products\nParticipate in company\u2019s marketing, promotion and new sales staff recruitment activities\nSupport various administrative & clerical tasks, data entry and document filing\nAssist in training of new sales supporting staffs\n\nRequirements\n\u00a0\u00a0\n\nBachelor in any related discipline\nAttain qualification of SFC license and insurance intermediary (HKSI and IIQE papers) preferred\nGood team player with excellent interpersonal and communication skills\nStrong sense of responsibility and able to work independently\nProficiency in MS Office applications\nGood command of both written and spoken English and Chinese.\u00a0 Fluency in Putonghua will be an advantage\n\nWe offer a competitive remuneration package to the right candidate. If you are interested in the post, please send your resume together with your present and expected salaries by clicking \u201cApply Now\u201d.\u00a0\n\n\nFor more information about China Everbright Securities International Company Limited, please visit www.ebshk.com.\n\nWe are an equal opportunity employer and welcome applications from all qualified candidates. All applications will be treated in the strictest confidence. Personal data provided will be used for recruitment purposes only. The job applicant will assume all or any risks arising out of or in connection with the job application transmission process prior to our actual receipt of the same including but not limited to accidental or unauthorized loss or disclosure of personal information, to which we will not be responsible in any way.\n\nUnder the Personal Data (Privacy) Ordinance, you may request access to, and / or correction of your personal data in relation to your application. If you wish to do so, please email to us.", "employment_types": ["Full Time"], "selling_points": [], "locations": ["Central & Western Area"], "categories": ["Banking / Finance", "Financial Services", "Dealing & Trading", "Fund Management"], "post_time": "2022-01-17T00:07:49Z", "salary": {"currency": null, "max": null, "min": null, "period": "monthly", "term": null}, "salary_visible": false, "title_keywords": ["specialist"], "responsibilities": ["document filing", "management", "data entry", "customer enquiries", "account opening", "policies", "customer services", "recruitment", "insurance"], "requirements": {"degrees": ["bachelor"], "majors": [], "languages": ["putonghua", "english", "chinese"], "language_level": ["fluency", "advantage", "good command"], "hard_skills": ["hksi", "iiqe", "sfc license", "ms office"], "soft_skills": ["communication skills", "good team player", "work independently", "sense of responsibility", "interpersonal"], "languages_combined": [{"language": "putonghua", "language_level": ["fluency", "advantage"]}, {"language": "english", "language_level": ["good command"]}, {"language": "chinese", "language_level": ["good command"]}]}, "experience_required": {"duration": [], "field": []}}, {"job_id": "100003009054523", "location_code": "hk", "company": "Magic Compass Pty Limited", "job_title": "Responsible Officer (Type 1 & 7)", "description": "Job Descriptions:\n\nResponsible for operating an electronic trading platform for matching client orders and handle the account of Automated Trading Services\nEnsure all business activities and daily operations are in full compliance with SFC rules and regulations, company policies and guidelines\nAssist the license application for the company, and liaise with the SFC and response to the queries raised by the SFC\nProvide advice on risk management of strategic activities and operations\nPerform other ad-hoc projects and assignments upon required\n\nJob Requirements:\n\nBachelor degree or above\nHolder of SFC license for both Type 1 and 7 regulated activities simultaneously\nRelevant working experience in SFC licensed or automated trading services firms\nWell-versed of SFC, regulations and guidelines of relevant regulatory authorities\nPrevious working experience in Chinese enterprises is highly preferable\nFlexible,\u00a0able to independently coordinate arrangements, communicate and implement the tasks assigned\nFluent in English and Chinese, Mandarin is a huge plus\n\n\nAll personal information provided by applicant will be treated in strict confidence and used solely for recruitment purposes. The personal information will be used strictly in accordance with Magic Compass Pty Limited's personal data policies, a copy of which will be provided upon request. It is possible that information about the applicant or the applicant\u2019s application will be shared with Magic Compass Pty Limited and its related companies. Magic Compass Pty Limited will retain all applications no longer than 24 months after which the documents will be destroyed.", "employment_types": ["Full Time", "Permanent"], "selling_points": ["Well-versed of SFC with automated trading services", "Responsible Officer Type 1 & Type 7", "Stable Working Environment"], "locations": ["Wan Chai"], "categories": ["Banking / Finance", "Financial Services", "Dealing & Trading", "Information Technology (IT)", "Network & System"], "post_time": "2022-01-17T09:53:28Z", "salary": {"currency": null, "max": null, "min": null, "period": "monthly", "term": null}, "salary_visible": false, "title_keywords": ["responsible officer"], "responsibilities": ["regulations", "management", "guidelines", "policies", "operations", "compliance", "daily operations", "provide advice", "license application", "liaise with", "ad-hoc projects", "business activities"], "requirements": {"degrees": ["degree or above", "bachelor"], "majors": [], "languages": ["english", "chinese", "mandarin"], "language_level": ["fluent"], "hard_skills": ["no", "plus", "sfc license", "compass"], "soft_skills": ["flexible", "independently", "confidence"], "languages_combined": [{"language": "english", "language_level": ["fluent"]}, {"language": "chinese", "language_level": ["fluent"]}, {"language": "mandarin", "language_level": []}]}, "experience_required": {"duration": [], "field": ["trading", "relevant working experience"]}}, {"job_id": "100003009051915", "location_code": "hk", "company": "CMB Wing Lung Bank Limited", "job_title": "Senior Securities Manager/Securities Manager (Digital Banking Department)", "description": "Responsibilities:\n\nExeute US market securities dealing orders\nHandle clients' phone-in enquiries and comments\nEnsure all dealing activities are complied with internal policy and requlatory requirements\nAssist in daliy operations\n\nRequirements:\n\nDegree holder\nMinimum 2 years' working experience of securities trading\nPasses in Hong Kong Securities & Investment Institute Licensing Examinations\nProficient in both English and Chinese; fluency in Putonghua an advantage\nGood communication and interpersonal skills", "employment_types": ["Full Time", "Permanent"], "selling_points": ["US Stock Market", "Dealing Room", "Customer Services"], "locations": ["Not Specified"], "categories": ["Banking / Finance", "Dealing & Trading"], "post_time": "2022-01-17T01:31:32Z", "salary": {"currency": null, "max": null, "min": null, "period": "monthly", "term": null}, "salary_visible": false, "title_keywords": ["manager"], "responsibilities": ["operations", "comments"], "requirements": {"degrees": ["degree holder"], "majors": [], "languages": ["putonghua", "english", "chinese"], "language_level": ["fluency", "advantage", "proficient"], "hard_skills": [], "soft_skills": ["communication and interpersonal skills"], "languages_combined": [{"language": "putonghua", "language_level": ["fluency", "advantage"]}, {"language": "english", "language_level": ["proficient"]}, {"language": "chinese", "language_level": ["proficient"]}]}, "experience_required": {"duration": ["minimum 2 years"], "field": ["securities", "trading"]}}, {"job_id": "100003009054465", "location_code": "hk", "company": "Taipei Fubon Commercial Bank Co., Ltd", "job_title": "Investment Product Specialist", "description": "Responsibilities:\n\nAssist in developing new financial products in response to the needs of clients\nAssist in projects like operational flow design and system enhancement\u00a0\nProvide support for financial products pricing and dealing\nProvide market update and product solution to internal clients\n\nRequirements:\n\n\nUniversity graduate in Finance, Economics or related discipline\n1 year working experience\nGood knowledge of financial products\nMeticulous, independent, well organized with strong analytical mind and able to work under pressure\nGood team player and self-motivated\nGood command of both written and spoken English and Chinese, fluent in Mandarin is a must\n\nInterested applicants, please send your full resume with date of availability, current and expected salary in MS WORD format by clicking \"APPLY NOW\".\n\nAll information received will be used for recruitment purposes only.\u00a0", "employment_types": ["Full Time", "Permanent"], "selling_points": ["Developing new financial products", "1 year relevant experience in banking industry", "Double pay plus discretionary bonus"], "locations": ["Tsim Sha Tsui"], "categories": ["Banking / Finance", "Corporate Banking", "Investment", "Dealing & Trading"], "post_time": "2022-01-17T09:40:16Z", "salary": {"currency": null, "max": null, "min": null, "period": "monthly", "term": null}, "salary_visible": false, "title_keywords": ["product specialist"], "responsibilities": ["provide support", "developing", "design"], "requirements": {"degrees": ["university graduate"], "majors": ["finance", "economics"], "languages": ["english", "chinese", "mandarin"], "language_level": ["good command", "fluent"], "hard_skills": ["ms word"], "soft_skills": ["meticulous", "good team player", "self-motivated", "independent", "well organized", "analytical mind", "work under pressure"], "languages_combined": [{"language": "english", "language_level": ["fluent", "good command"]}, {"language": "chinese", "language_level": ["fluent", "good command"]}, {"language": "mandarin", "language_level": ["fluent", "good command"]}]}, "experience_required": {"duration": ["1 year"], "field": []}}, {"job_id": "100003009052394", "location_code": "hk", "company": "Hong Kong Huafa Investment Holdings Limited", "job_title": "International Trade Supervisor \u570b\u969b\u8cbf\u6613\u4e3b\u4efb", "description": "Job Responsibilities\n\nexecute dealing orders for global securities and futures market and monitor margin level\nmatch daily transaction records and trade position and compile various trading reports\ncarry out FX dealing operation and ad hoc duties\nmanage portfolio risk within assigned limits\n\nJob Requirement\n\n\nDiploma /Tertiary educated with at least 3 years\u2019 relevant experience in dealing /trading work of securities, bonds and FX\nexperience in banking environment preferred\u00a0\nwilling to handle trade orders after office hours and during public holidays when overseas markets are open\nteam player and\u00a0able to work under pressure\nexcellent integrity, self-motivated and responsible\ngood analytical skill and good command of English and Chinese\n\nWe work 5 days per week.\n\n\nInterested parties, please click \"APPLY NOW\" and attach with your application letter and full resume.\u00a0\n\nFor further information of the Wharf Group, please visit our website:\u00a0www.wharfholdings.com", "employment_types": ["Full Time", "Permanent"], "selling_points": ["Support International Trade Team", "Negotiating trade details", "Maintain good relations with trading partners"], "locations": ["Central"], "categories": ["Banking / Finance", "Dealing & Trading", "Sales, CS & Business Devpt", "Business Development", "Merchandising & Purchasing", "Procurement / Purchasing / Sourcing"], "post_time": "2022-01-17T02:56:21Z", "salary": {"currency": null, "max": null, "min": null, "period": "monthly", "term": null}, "salary_visible": false, "title_keywords": ["supervisor"], "responsibilities": ["ad hoc duties", "monitor", "reports"], "requirements": {"degrees": ["diploma"], "majors": [], "languages": ["english", "chinese"], "language_level": ["good command", "good"], "hard_skills": ["analytical skill"], "soft_skills": ["self-motivated", "analytical skill", "responsible", "integrity", "team player", "work under pressure"], "languages_combined": [{"language": "english", "language_level": ["good command", "good"]}, {"language": "chinese", "language_level": ["good command", "good"]}]}, "experience_required": {"duration": ["at least 3 years"], "field": ["securities", "relevant experience", "trading", "banking"]}}, {"job_id": "100003009047604", "location_code": "hk", "company": "Zhongpu International Futures Co., Limited", "job_title": "Senior Dealer / Dealer / Dealer Trainee", "description": "\u5de5\u4f5c\u8077\u8cac\n\n\u5354\u52a9\u90e8\u9580\u843d\u5be6\u5e74\u5ea6\u71df\u696d\u984d\u3001\u5229\u6f64\u6307\u6a19\u7b49\u7684\u7d93\u71df\u6307\u6a19\n\u8ca0\u8cac\u8cbf\u6613\u5168\u6d41\u7a0b\u64cd\u4f5c\uff0c\u5305\u62ec\u78ba\u5b9a\u8cbf\u6613\u8a73\u60c5\u3001\u8349\u64ec\u8cbf\u6613\u5408\u540c\u3001\u63d0\u4ea4\u5167\u90e8\u5be9\u6279\u3001\u76e3\u7763\u8cbf\u6613\u843d\u5be6\u60c5\u6cc1\u7b49\n\u8207\u8cbf\u6613\u5925\u4f34\u53ca\u5176\u4ed6\u5167\u5916\u90e8\u55ae\u4f4d\u7dad\u6301\u826f\u597d\u7684\u5408\u4f5c\u95dc\u4fc2\n\u8ca0\u8cac\u90e8\u9580\u7684\u6587\u6a94\u7ba1\u7406\u5de5\u4f5c\n\u5b8c\u6210\u4e0a\u7d1a\u4ea4\u8fa6\u7684\u5176\u5b83\u5de5\u4f5c\n\u4efb\u8077\u8cc7\u683c\n\n\u5927\u5b78\u672c\u79d1\u6216\u4ee5\u4e0a\u5b78\u6b77\uff0c\u4fee\u8b80\u570b\u969b\u8cbf\u6613\u3001\u5546\u696d\u3001\u7d93\u6fdf\u6216\u76f8\u95dc\u5c08\u696d\n2\u5e74\u6216\u4ee5\u4e0a\u76f8\u95dc\u5de5\u4f5c\u7d93\u9a57\uff0c\u66fe\u5f9e\u4e8b\u570b\u969b\u8cbf\u6613\u3001\u5927\u5b97\u5546\u54c1\u8cbf\u6613\u3001\u9280\u884c\u7d50\u69cb\u6027\u878d\u8cc7\u5de5\u4f5c\u512a\u5148\uff0c\u5177\u5099\u570b\u6709\u4f01\u696d\uff0f\u4e2d\u8cc7\u4f01\u696d\u5de5\u4f5c\u7d93\u9a57\u8005\u512a\u5148\n\u826f\u597d\u7684\u5546\u696d\u982d\u8166\u548c\u5206\u6790\u80fd\u529b\n\u7cb5\u8a9e\u3001\u666e\u901a\u8a71\u6d41\u5229\uff0c\u826f\u597d\u7684\u4e2d\u82f1\u6587\u8b80\u5beb\u80fd\u529b\n\u6027\u683c\u7a4d\u6975\u4e3b\u52d5\uff0c\u5177\u8cac\u4efb\u5fc3\n\u5177\u5099\u826f\u597d\u7684\u6e9d\u901a\u3001\u8ac7\u5224\u3001\u5354\u8abf\u80fd\u529b\uff0c\u80fd\u5920\u540c\u6642\u8655\u7406\u591a\u9805\u4efb\u52d9\u4e26\u5728\u58d3\u529b\u4e0b\u5de5\u5b8c\u6210\u4f5c\uff0c\u5177\u5099\u826f\u597d\u7684\u8077\u696d\u9053\u5fb7\n\u80fd\u7d14\u719f\u64cd\u4f5cMicrosoft Office\u7b49\u7684\u8fa6\u516c\u8edf\u4ef6\nJob Description\n\nAssist in achieving the KPIs of the department, such as sales turnover, profit and other targets\nSupport the team in trade administration matters, such as negotiating trade details, drafting contracts, applying for internal approval, monitoring and implementation of trade, etc.\nMaintain good relations with trading partners and other related parties\nResponsible in administrative documentation and file management\nComplete other tasks as assigned\nJob Specification\n\nBachelor\u2019s degree in international trade, business, economics or other related fields\n2 years of relevant work experience in international trading, commodity trading and bank structured financing are preferred\nExposure to Chinese state-owned enterprises/ Chinese enterprises would be desirable\nProficient command of Chinese and English\nProactive and responsible character\nExcellent communication, negotiation and coordination skills. Be able to handle multiple tasks at the same time and complete work under pressure. With good professional ethics\nProficient to use Microsoft Office and other office software proficiently\nWe offer attractive remuneration package to the right candidates, including year-end double pay, discretionary bonus, allowances, group medical insurance, annual health check, and etc. Interested parties please apply directly by clicking \u201cApply Now\u201d.", "employment_types": ["Full Time", "Permanent"], "selling_points": [], "locations": ["Kwun Tong"], "categories": ["Banking / Finance", "Dealing & Trading"], "post_time": "2022-01-14T03:33:45Z", "salary": {"currency": null, "max": null, "min": null, "period": "monthly", "term": null}, "salary_visible": false, "title_keywords": ["dealer trainee", "dealer"], "responsibilities": ["year-end", "software", "work under pressure", "contracts", "monitoring", "implementation", "communication", "other tasks", "maintain", "coordination", "documentation", "kpis", "insurance", "file management", "support the team", "administration"], "requirements": {"degrees": ["degree", "bachelor"], "majors": ["economics", "business"], "languages": ["english", "chinese"], "language_level": ["proficient"], "hard_skills": ["documentation", "office software", "microsoft office"], "soft_skills": ["proactive", "negotiation", "responsible", "coordination skills", "communication", "handle multiple tasks", "structured", "work under pressure"], "languages_combined": [{"language": "english", "language_level": ["proficient"]}, {"language": "chinese", "language_level": ["proficient"]}]}, "experience_required": {"duration": ["2 years"], "field": ["financing", "trading"]}}, {"job_id": "100003009050358", "location_code": "hk", "company": "China Everbright Securities International Company Limited", "job_title": "Dealer/Senior Dealer, FX", "description": "-\u00a0 \u00a0Execute dealing orders for\u00a0global\u00a0futures and securities market;\n\n-\u00a0 \u00a0Handle client\u2019s account opening\n\n-\u00a0 \u00a0Provide customer service, handle inquiries and ensure trading system stability\n\n-\u00a0 \u00a0Risk monitoring and handling margin calls\n\n-\u00a0 \u00a0Perform day-end processing and related tasks\n\n-\u00a0 \u00a0Assist senior management in any ad-hoc projects assigned.\n\nRequirements:\n\n-\u00a0 \u00a0Degree holder in Finance/Business or related disciplines\n\n-\u00a0 \u00a0Holder of SFC license RA1 and RA2\n\n-\u00a0 \u00a0Fresh graduate will also be considered, passed HKSI Licensing Examination Paper 1,7 and 9 is an advantage\n\n-\u00a0 \u00a0Excellent interpersonal and communication skills, customer oriented\n\n-\u00a0 \u00a0Good command of Chinese and English, fluent in Putonghua is an advantage\n\n-\u00a0 \u00a0Good team player and willing to learn\n\n-\u00a0 \u00a0Night shift and able to work in shift (including public holidays) required\n\n-\u00a0 \u00a0Fast response, independently and able to work under pressure\n\n-\u00a0 \u00a0Immediate available is preferred", "employment_types": ["Full Time", "Permanent"], "selling_points": [], "locations": ["Causeway Bay"], "categories": ["Banking / Finance", "Retail Banking", "Treasury", "Dealing & Trading"], "post_time": "2022-01-14T10:12:06Z", "salary": {"currency": null, "max": null, "min": null, "period": "monthly", "term": null}, "salary_visible": false, "title_keywords": ["dealer"], "responsibilities": ["provide customer service", "ad-hoc projects", "account opening", "system stability", "communication", "risk monitoring", "senior management", "work under pressure"], "requirements": {"degrees": ["fresh graduate", "degree holder"], "majors": ["related disciplines", "finance", "business"], "languages": ["putonghua", "english", "chinese"], "language_level": ["advantage", "good command", "fluent"], "hard_skills": ["account opening", "hksi", "processing", "sfc license"], "soft_skills": ["communication skills", "good team player", "independently", "willing to learn", "customer service", "interpersonal", "work under pressure"], "languages_combined": [{"language": "putonghua", "language_level": ["fluent", "advantage", "good command"]}, {"language": "english", "language_level": ["advantage", "good command"]}, {"language": "chinese", "language_level": ["advantage", "good command"]}]}, "experience_required": {"duration": [], "field": []}}, {"job_id": "100003009054760", "location_code": "hk", "company": "BOCI-Prudential Trustee Limited", "job_title": "Senior Administrator, Unit Trust", "description": "Ref: D/EBSHKFX/140122DB/61\n\u00a0\n\n\nResponsibilities\n\n\nHandle the execution and operation functions on Forex\nProvide general assistance to clients over the phone or via the web\nSit on the Forex desk and support the client on-boarding process\nHandle account opening and prepare\u00a0various reports\nMaintain good relationship with existing clients\n\nRequirements\n\nSecondary school graduate or above\nMinimum 1 year's relevant experience\u00a0in foreign exchange\nHolder of SFC\u00a0license for\u00a0Type 3\u00a0regulated activity\u00a0preferred\nGood interpersonal skills and detail-oriented\nGood command of both written and spoken English and Chinese. Fluency in Putonghua an advantage\nShift duty may require\nCandidate with more experience will be considered as Senior\u00a0Dealer.\n\n\n\nWe offer a competitive remuneration package to the right candidate. If you are interested in the post, please send your resume together with\u00a0your present\u00a0and\u00a0expected salaries\u00a0by clicking\u00a0\u201cApply Now\u201d.\n\n\nFor more information about China Everbright Securities International Company Limited, please visit\u00a0www.ebshk.com.\n\nWe are an equal opportunity employer\u00a0and welcome applications from all qualified candidates. All applications will be treated in the strictest confidence. Personal data provided will be used for recruitment purposes only. The job applicant will assume all or any risks arising out of or in connection with the job application transmission process prior to our actual receipt of the same including but not limited to accidental or unauthorized loss or disclosure of personal information, to which we will not be responsible in any way.\n\u00a0\nUnder the Personal Data (Privacy) Ordinance, you may request access to, and / or correction of your personal data in relation to your application. If you wish to do so, please email to us.", "employment_types": ["Full Time", "Permanent"], "selling_points": ["Handle daily unit trust order, payment settlement", "Liaise with fund houses / distributors", "Assist in set up new fund groups for new business"], "locations": ["Tin Hau"], "categories": ["Banking / Finance", "Financial Services", "Dealing & Trading", "Order Processing & Operation / Settlement"], "post_time": "2022-01-17T10:57:40Z", "salary": {"currency": null, "max": null, "min": null, "period": "monthly", "term": null}, "salary_visible": false, "title_keywords": ["administrator"], "responsibilities": ["account opening", "reports", "maintain good relationship"], "requirements": {"degrees": [], "majors": [], "languages": ["putonghua", "english", "chinese"], "language_level": ["fluency", "advantage", "good command"], "hard_skills": ["sfc license", "exchange"], "soft_skills": ["interpersonal skills", "detail-oriented"], "languages_combined": [{"language": "putonghua", "language_level": ["fluency", "advantage"]}, {"language": "english", "language_level": ["good command"]}, {"language": "chinese", "language_level": ["good command"]}]}, "experience_required": {"duration": ["minimum 1 year"], "field": ["relevant experience"]}}, {"job_id": "100003009054607", "location_code": "hk", "company": "Asia Progress Executive Limited", "job_title": "Associate, Fixed Income Trader - PRC Securities Brokerage firm", "description": "Responsibilities:\n\nHandle daily unit trust order, including subscription, redemption, switching, transfer, dividend and reinvestment\nLiaise with Fund Houses or Distributors (including Overseas and Mainland China) for routine operation issues\nHandle payment settlement with clients or Finance, including autopay instruction with banks\nPrint and dispatch contract notes, advice, statements and reports to unit holders, distributors or fund houses\nAssist the team supervisor to set up new fund groups for new business\nGeneral clerical support to the team\nHandle ad hoc assignment as required\n\nRequirements:\n\nDegree holder in Business Administration, Finance,\u00a0Economics, Banking\u00a0or related disciplines\nAt least 1 year working experience specialist in Fund Transfer Agent, Investor Service and Fund Administration is preferred\nTeam player with excellent interpersonal and presentation skills\nGood at problem-solving, customer focused and communication skills\nAble to work independently and under pressure\nProficient in PC applications including Excel, Word, PowerPoint and Chinese Word Processing\nGood command of both written and spoken English, Chinese and Mandarin\nCandidate with\u00a0more experience will be considered as Assistant Supervisor\n\nWe offer attractive remuneration package & benefits to the right candidates. Interested candidates, please send your application letter & resume with current & expected salary\u00a0by mail to Human Resources Department, 12/F., Citicorp Centre, 18 Whitfield Road, Causeway Bay, Hong Kong.\u00a0Or by direct application, please visit our career page at\u00a0http://www.bocpt.com.\n\nWe are an equal opportunities employer and is committed to equality, ethics, inclusivity, diversity and transparency. Information provided will be treated in strict confidence and only be used for recruitment related purposes. Applicants who are not contacted within 6 weeks may consider their application unsuccessful. Applications will also be considered for other suitable positions available in our Group. Unsuccessful applications will be kept in our file for a period of one year\u00a0and which will be destroyed after the said period of retention.", "employment_types": ["Full Time"], "selling_points": ["Responsible for fixed income trading for DCM Team", "Deg 3yrs fixed income trader / equity products", "Familiar w/ fixed income and equity markets"], "locations": ["Central & Western Area"], "categories": ["Banking / Finance", "Treasury", "Dealing & Trading", "Equities / Capital Markets"], "post_time": "2022-01-17T10:13:58Z", "salary": {"currency": null, "max": null, "min": null, "period": "monthly", "term": null}, "salary_visible": false, "title_keywords": ["associate"], "responsibilities": ["ad hoc assignment", "clerical support", "payment", "reports", "liaise with", "autopay"], "requirements": {"degrees": ["degree holder"], "majors": ["related disciplines", "finance", "economics", "business administration"], "languages": ["english", "chinese", "mandarin"], "language_level": ["good command", "proficient"], "hard_skills": ["excel", "chinese word processing", "problem-solving", "word", "powerpoint", "pc applications"], "soft_skills": ["communication skills", "work independently", "under pressure", "focused", "problem-solving", "presentation skills", "team player", "interpersonal"], "languages_combined": [{"language": "english", "language_level": ["good command"]}, {"language": "chinese", "language_level": ["good command", "proficient"]}, {"language": "mandarin", "language_level": ["good command"]}]}, "experience_required": {"duration": ["at least 1 year"], "field": ["administration"]}}, {"job_id": "100003009049824", "location_code": "hk", "company": "Phillip Securities Group", "job_title": "Dealer", "description": "Our client is PRC\u00a0Top Tier Chinese Investment Bank/ Securities Brokerage . \u00a0To cope with the rapid business expansion, they are now inviting high caliber candidates to join the team\n\nAssociate, Fixed Income Trader - PRC Securities Brokerage firm\u00a0\n\nJob Responsibilities\n\nBe responsible for fixed income\u00a0trading for client accounts\nWork as part of the DCM team to provide real-time market\u00a0colour,\u00a0identify\u00a0investment opportunities, and implement effective trades\u00a0derive profits\n\u00a0Assist in client marketing and day to day client communication\nMaintain and develop new trading instruments and other relevant\u00a0products to enhance investment returns\n\nRequirements:\n\n\u00a0Degree holder in Finance, business or any similar field\n\u00a0 3 - 5 years of relevant trading experience in fixed income or equity\n\u00a0 Familiar with the fixed income and equity markets ecosystem\n\u00a0 Solid understanding of investment products and trading strategies\n\u00a0 Ability to work accurately under stress;\n\u00a0 Fast learner, proactive and quick reaction to market changes\n\u00a0 Proficiency in written and spoken English and Chinese including Putonghua.\n\nPlease send full resume with\u00a0present & expected\u00a0salary to expedite sourcing\u00a0in\u00a0MS-WORD\u00a0format by clicking \u201cAPPLY NOW\u201d\n\nPlease quote our reference in your application\n\nPersonal data provided by job applicants will be used strictly in accordance with the employer\u2019s personal data policies, a copy of which will be provided upon request\n\nAll information provided will be used for recruitment purpose only", "employment_types": ["Full Time", "Permanent"], "selling_points": ["Training", "Dealing", "Bonus"], "locations": ["Central & Western Area"], "categories": ["Banking / Finance", "Financial Services", "Dealing & Trading", "Equities / Capital Markets"], "post_time": "2022-01-15T03:50:38Z", "salary": {"currency": null, "max": null, "min": null, "period": "monthly", "term": null}, "salary_visible": false, "title_keywords": ["dealer"], "responsibilities": ["communication", "maintain", "investment returns", "develop"], "requirements": {"degrees": ["degree holder"], "majors": ["finance", "business"], "languages": ["putonghua", "english", "chinese"], "language_level": ["proficiency"], "hard_skills": ["ms-word", "investment products"], "soft_skills": ["proactive", "fast learner"], "languages_combined": [{"language": "putonghua", "language_level": ["proficiency"]}, {"language": "english", "language_level": ["proficiency"]}, {"language": "chinese", "language_level": ["proficiency"]}]}, "experience_required": {"duration": ["3 - 5 years"], "field": ["trading"]}}, {"job_id": "100003009050298", "location_code": "hk", "company": "Vegasoul Capital Management (Asia) Limited", "job_title": "Quantitative Researcher - attractive salary!", "description": "We believe that each individual has his own unique strength and experience and we commit in providing opportunities and developing our staff to their fullest potential.\u00a0 We are seeking passionate individuals to join our dynamic Dealing Team.\u00a0 You will be provided with comprehensive training to develop your dealing and marketing skills.\u00a0 Besides providing execution services to clients, you are required to\n\ncontact clients, provide them with market updates, review their portfolio and recommend appropriate investment ideas\nconduct\u00a0workshops to educate\u00a0investors on new products and\u00a0services\nresearch on listed companies and\u00a0provide periodic presentations and recommendations\n\nPreferably, you should:\n\nHave enthusiasm in developing your career in financial market\nHave knowledge in stock market and/or derivatives market which is an advantage\nBe self-motivated and willing to take challenges\nHave passed HKSI LE or equivalent\n\nIf you are looking for an environment of\u00a0growth and opportunity, please\u00a0email your resume or apply through JobsDB, stating your present and expected salary to Personnel & Administration Department. Salary will be commensurate with qualifications and experience.\n\n\"All personal data collection is for recruitment purposes. The data provided by job applicants will be used strictly in accordance with the employer's personal data policies, a copy of which will be provided immediately upon request.\"", "employment_types": ["Full Time", "Permanent"], "selling_points": [], "locations": ["Not Specified"], "categories": ["Banking / Finance", "Analyst", "Dealing & Trading", "Fund Management"], "post_time": "2022-01-14T10:04:17Z", "salary": {"currency": null, "max": null, "min": null, "period": "monthly", "term": null}, "salary_visible": false, "title_keywords": ["researcher"], "responsibilities": ["ideas", "data", "policies", "review", "developing", "presentations", "develop", "recruitment", "contact", "personal data", "administration"], "requirements": {"degrees": [], "majors": [], "languages": [], "language_level": [], "hard_skills": ["marketing skills", "hksi", "presentations", "dynamic", "workshops"], "soft_skills": ["passionate", "self-motivated", "unique", "comprehensive", "dynamic"], "languages_combined": []}, "experience_required": {"duration": [], "field": ["developing"]}}, {"job_id": "100003009051030", "location_code": "hk", "company": "The Wharf Group", "job_title": "Dealers (Securities & FX)", "description": "Senior Dealer (Job ID 2828)\nResponsibilities\n\nTo be a team member of Securities Services Department\nTo handle securities transactions as well as provide timely and efficient securities services to customers\nTo prepare various daily/monthly trading statistics reports as required\nTo alert the supervisors when any suspicious transaction is identified during order execution\nTo perform any administrative duties and handle any ad hoc tasks assigned by the supervisors\nRequirements\n\nHKCEE/HKDSE or above, with 5 subjects, including Chinese, English and Mathematics at Level 2/Attained/Grade E or above\nA minimum of 1 year\u2019 working experience in securities dealing\nPassed HKSI Licensing Examination Paper 1, 7 & 8\nSelf-motivated and able to work under pressure\nProficiency in both spoken and written English and Chinese, Putonghua a plus\nGood knowledge of MS Office\n(Fresh university graduates with less working experience will also be considered)\nPlease apply online via the BEA Careers website at\u00a0https://careers.hkbea.com/psp/hcmprd/EMPLOYEE/HRMS/c/HRS_HRAM.HRS_APP_SCHJOB.GBL?Page=HRS_APP_JBPST&Action=UFOCUS=Applicant&SiteId=1&JobOpeningId=2828&PostingSeq=1\u00a0or by clicking the \"Apply Now\" button below. Kindly note that if you are a new user, you have to first create your User Profile before you can apply.\n\nPersonal data provided by job applicants will be used for recruitment purposes only and will be treated in accordance with the Bank's Personal Information Collection (Employees) Statement and Privacy Policy Statement. Applicants who are not invited for interviews within six weeks may consider their applications unsuccessful and the personal data collected will be destroyed after six months.", "employment_types": ["Full Time", "Permanent"], "selling_points": [], "locations": ["Central"], "categories": ["Banking / Finance", "Investment", "Dealing & Trading", "Equities / Capital Markets"], "post_time": "2022-01-15T01:17:14Z", "salary": {"currency": null, "max": null, "min": null, "period": null, "term": null}, "salary_visible": false, "title_keywords": [], "responsibilities": ["administrative duties", "reports", "ad hoc tasks", "transactions"], "requirements": {"degrees": ["hkdse"], "majors": ["mathematics"], "languages": ["putonghua", "english", "chinese"], "language_level": ["proficiency"], "hard_skills": ["plus", "c", "hksi", "ms office"], "soft_skills": ["self-motivated", "work under pressure"], "languages_combined": [{"language": "putonghua", "language_level": ["proficiency"]}, {"language": "english", "language_level": ["proficiency"]}, {"language": "chinese", "language_level": ["proficiency"]}]}, "experience_required": {"duration": ["minimum of 1 year"], "field": ["securities"]}}, {"job_id": "100003009052439", "location_code": "hk", "company": "PeopleSearch Ltd", "job_title": "Global Markets Operations Analyst", "description": "Our client, an European bank, is seeking a Global market operation analyst, focusing on handling global market daily operation.\n\nResponsibilities:\n\n\nPerform day-to-day settlement operations to ensure timely settlement and the firm\u2019s compliant with regulatory requirements and ratio. To support funding liquidity and daily positions for the branch\nResolve any Front-office to Back-office/Nostro breaks\nPerform day-to-day core operational support functions to Front Office including trade validation of FX/MM/Bonds/OTC Derivatives/Loans\nPrepare MIS/KPIs for senior management reporting\n\n\nRequirements:\n\nUniversity degree in relevant subject would be an advantage\nRequires to rotate and work on Hong Kong holidays and China business weekends\nMinimum 3-5 years of experience in Global Markets operations\nExperience in SWIFT, RTGS, CLS and other settlement related systems is an advantage\nStrong analytical skills and ability to learn quickly new knowledge such as systems and policies, with good adaptability to constantly changing environment\nFluent in English and Chinese\u00a0\n\nInterested applicants please send your full resume (in Word format) together with present and expected salary to Raymond Lam", "employment_types": ["Full Time", "Permanent", "Temporary"], "selling_points": ["Global market exposure", "Attractive package and benefits", "Excellent employee development and career growth"], "locations": ["Central & Western Area"], "categories": ["Banking / Finance", "Financial Services", "Dealing & Trading"], "post_time": "2022-01-17T03:02:14Z", "salary": {"currency": null, "max": null, "min": null, "period": "monthly", "term": null}, "salary_visible": false, "title_keywords": ["operations analyst"], "responsibilities": ["reporting", "operational support", "operations", "regulatory requirements", "kpis", "senior management", "timely settlement"], "requirements": {"degrees": ["university degree"], "majors": [], "languages": ["english", "chinese"], "language_level": ["fluent"], "hard_skills": ["swift", "word", "analytical skills"], "soft_skills": ["adaptability", "analytical skills"], "languages_combined": [{"language": "english", "language_level": ["fluent"]}, {"language": "chinese", "language_level": ["fluent"]}]}, "experience_required": {"duration": ["minimum 3-5 years"], "field": ["related"]}}, {"job_id": "100003009049244", "location_code": "hk", "company": "Shanghai Commercial Bank Ltd", "job_title": "Securities & Futures Dealer", "description": "Responsibilities:\n\nExecute trading orders accurately and efficiently\nCultivate and deepen relationship with existing customers\nSolicit new business opportunities from branch referrals\nFacilitate daily dealing administrations and prepare related documents\nMonitor clients orders and margin level and conduct margin call and margin report\nSupport system testing and UAT\nHandle ad hoc duties as assigned\n\nRequirements:\n\nPost-secondary educated with at least 5 years work experience in related field\nQualified individual to carry out regulated activities (Type 1 and 2) under SFO\nStrong knowledge in Global Stocks, Futures, Options and Commodities, etc\nGood command of both spoken English and Chinese including Putonghua\nWilling to work on holiday (compensation leave will be offered)\nShift duty is required including public holiday (major shift from 6:45am to 4:00pm)\nWorking location: TST\n\nAttractive remuneration package will be offered to the right candidates. Interested parties please click \"Apply Now\" to submit your full resume with current and expected salary to the Human Resources Division.\n\nPlease visit us at www.shacombank.com.hk for more information about our Bank.\n\nAll personal data collected will be used for recruitment related purposes strictly in accordance with the Bank's personal data policies, a copy of which will be provided immediately upon request by contacting our Personal Data Compliance Officer. Applicants who are not contacted within two months may consider their applications unsuccessful and the personal data collected from the applicants will be retained for no longer than two years from the date of rejection during which the applicants may be considered for other suitable positions within the Bank.", "employment_types": ["Full Time", "Permanent"], "selling_points": ["Execute trading orders accurately and efficiently", "Solicit new business opportunities", "Facilitate daily dealing administrations"], "locations": ["Not Specified"], "categories": ["Banking / Finance", "Investment", "Dealing & Trading", "Others"], "post_time": "2022-01-15T03:50:14Z", "salary": {"currency": null, "max": null, "min": null, "period": "monthly", "term": null}, "salary_visible": false, "title_keywords": ["dealer"], "responsibilities": ["ad hoc duties", "uat", "related documents", "business opportunities", "monitor", "testing", "report"], "requirements": {"degrees": [], "majors": [], "languages": ["putonghua", "english", "chinese"], "language_level": ["good command"], "hard_skills": ["sfo"], "soft_skills": [], "languages_combined": [{"language": "putonghua", "language_level": ["good command"]}, {"language": "english", "language_level": ["good command"]}, {"language": "chinese", "language_level": ["good command"]}]}, "experience_required": {"duration": ["at least 5 years"], "field": ["related"]}}, {"job_id": "100003009043598", "location_code": "hk", "company": "Minmetals Financial Services", "job_title": "Futures Dealer", "description": "Job Duties:\u00a0\n\n\u00a0Provide Futures quotations, handle customer\u00a0inquiries and execute clients\u2019 orders;\n\u00a0Prepare daily dealing related reports and documents;\n\u00a0Comply with procedures, policies and regulatory requirements.\n\nRequirements:\n\nNIGHT SHIFT\u00a0and able to work in shift (including public holidays) is required.\u00a0\nHolder of / eligible to apply for the SFC RA2\u00a0license\nPreferably with 1 year working\u00a0experience in global futures market;\nDegree holder in Business, Finance;\nGood interpersonal and communication skills (fluent in Mandarin is a must);\nEfficient, task-oriented and attentive to details;\nFast response and able to work under pressure;\nImmediate preferable.\u00a0\n\nWe offer competitive remuneration packages to the right candidate.\u00a0Interested parties please email your resume with\u00a0CURRENT SALARY & EXPECTED SALARY & AVAILABLE DATE\u00a0for\u00a0interview.\n\n\u00a0(Personal data collected will be used for recruitment purpose only)", "employment_types": ["Full Time"], "selling_points": [], "locations": ["Sheung Wan"], "categories": ["Banking / Finance", "Dealing & Trading"], "post_time": "2022-01-12T23:19:20Z", "salary": {"currency": null, "max": null, "min": null, "period": "monthly", "term": null}, "salary_visible": false, "title_keywords": ["dealer"], "responsibilities": ["customer inquiries", "policies", "regulatory requirements", "procedures", "reports"], "requirements": {"degrees": ["degree holder"], "majors": ["finance", "business"], "languages": ["mandarin"], "language_level": ["fluent", "good"], "hard_skills": [], "soft_skills": ["efficient", "communication skills", "attentive to details", "interpersonal", "work under pressure"], "languages_combined": [{"language": "mandarin", "language_level": ["fluent", "good"]}]}, "experience_required": {"duration": ["1 year"], "field": []}}, {"job_id": "100003009052530", "location_code": "hk", "company": "SALT Consulting International Company Limited", "job_title": "Securities & FX Traders / Dealer / Sales; FX Derivatives Product Manager; Bonds Trader", "description": "We are inviting applications for a number of Bank Openings.\n\nWe are assisting our Personal Banking, Investment Banking and Corporate Banking clients in recruiting\n\nSecurities Dealers\nFX traders / dealers\nFX sales\nBonds trader\nALM trader\nFX Derivatives Product Manager\n\nCandidates with relevant experience are welcome to apply.", "employment_types": ["Full Time"], "selling_points": ["FX traders", "Bonds dealer", "Securities Dealer"], "locations": ["Central"], "categories": ["Banking / Finance", "Dealing & Trading"], "post_time": "2022-01-17T03:19:33Z", "salary": {"currency": null, "max": null, "min": null, "period": "monthly", "term": null}, "salary_visible": false, "title_keywords": ["product manager", "dealer", "sales"], "responsibilities": ["banking"], "requirements": {"degrees": [], "majors": [], "languages": [], "language_level": [], "hard_skills": [], "soft_skills": [], "languages_combined": []}, "experience_required": {"duration": [], "field": ["relevant experience"]}}, {"job_id": "100003009048372", "location_code": "hk", "company": "Fortune (HK) Securities Limited", "job_title": "Customer Service Officer \u5ba2\u6237\u670d\u52a1\u4e3b\u4efb", "description": "Responsibilities:\n\n\n\nHandle and execute FX conversion mainly\nAssist in placing overseas equities, futures, option orders\nExecute trade orders on a timely and accurate manner\nProvide high quality services in answering client\u2019s enquires regarding trades and orders\nLiaise with relevant internal departments and external parties such as banks and brokers\nHandle daily dealing operations\nTake up other ad-hoc projects and assigned duties\nRequirements:\n\n\nHolder of SFC RA1 and RA2 licenses or passed HKSI Licensing Examination Paper 1,7,8 and 9 is an advantage\nMinimum 1 year relevant experience in stocks, futures & options\nStrong knowledge in FX, followed by Overseas Equities, Futures, Option\nGood team player and willing to learn\nGood command of spoken English, Cantonese and Mandarin\nGood communication skills, independent, detail-minded and able to work under pressure\nImmediate available is preferred\n\nWhat We Offer:\u00a0\nCompetitive Salary\nMedical and Dental Benefits\nYear End Performance bonus\nShift allowance and holiday allowance\nExposure on foreign markets & global futures market trading\n\nInterested candidates are invited to send a comprehensive resume stating current and expected salaries to\u00a0Head of Human Resources, UOB Kay Hian (Hong Kong) Limited, 6/F Harcourt House, 39 Gloucester Road, Wan Chai, Hong Kong\u00a0or email by clicking the below \"Apply Now\" button", "employment_types": ["Full Time", "Permanent"], "selling_points": ["Write press releases to promote company products", "Perform KYC to comply with SFC for account opening", "Proficient in both spoken & written Eng. & Chinese"], "locations": ["Sheung Wan"], "categories": ["Banking / Finance", "Investment", "Financial Services", "Dealing & Trading"], "post_time": "2022-01-14T06:26:30Z", "salary": {"currency": null, "max": null, "min": null, "period": "monthly", "term": null}, "salary_visible": false, "title_keywords": ["customer service officer"], "responsibilities": ["operations", "external parties", "quality", "liaise with", "ad-hoc projects"], "requirements": {"degrees": [], "majors": [], "languages": ["cantonese", "english", "mandarin"], "language_level": ["good command"], "hard_skills": ["hksi"], "soft_skills": ["detail-minded", "communication skills", "good team player", "independent", "willing to learn", "work under pressure"], "languages_combined": [{"language": "cantonese", "language_level": ["good command"]}, {"language": "english", "language_level": ["good command"]}, {"language": "mandarin", "language_level": ["good command"]}]}, "experience_required": {"duration": ["minimum 1 year"], "field": ["relevant experience"]}}, {"job_id": "100003009044868", "location_code": "hk", "company": "GOLDHORSE SECURITIES LIMITED", "job_title": "Junior / Senior Dealer \u2013 Night Shift", "description": "Job Description\n\nDeliver prompt and quality customer support services to clients and ensure smooth client onboarding;\nPerform KYC to comply with SFC for account opening procedures;\nHandle enquiries from frontline and internal departments;\nWrite press releases to promote company products;\nHandle other related ad hoc tasks and assignments.\n\nRequirements :\n\nBachelor Degree or above in any discipline\n1-2 year\u2019s working experience\nHigh proficiency in both spoken and written English and Chinese and fluency in Putonghua\nExcellent computer skills in MS Word, MS Excel and MS PowerPoint\nEnergetic, creative, well-organized and attentive to details", "employment_types": ["Full Time", "Permanent"], "selling_points": [], "locations": ["Sheung Wan"], "categories": ["Banking / Finance", "Financial Services", "Dealing & Trading"], "post_time": "2022-01-13T06:30:25Z", "salary": {"currency": null, "max": null, "min": null, "period": "monthly", "term": null}, "salary_visible": false, "title_keywords": ["dealer", "junior"], "responsibilities": ["account opening", "support services", "quality", "procedures", "ad hoc tasks", "handle enquiries", "kyc"], "requirements": {"degrees": ["degree or above", "bachelor"], "majors": [], "languages": ["putonghua", "english", "chinese"], "language_level": ["fluency", "proficiency"], "hard_skills": ["ms powerpoint", "ms excel", "computer skills", "ms word"], "soft_skills": ["energetic", "well-organized", "creative", "attentive to details"], "languages_combined": [{"language": "putonghua", "language_level": ["proficiency"]}, {"language": "english", "language_level": ["proficiency", "fluency"]}, {"language": "chinese", "language_level": ["proficiency", "fluency"]}]}, "experience_required": {"duration": ["1-2 year"], "field": []}}, {"job_id": "100003009045869", "location_code": "hk", "company": "Haitong International Securities Group Limited", "job_title": "SBL Trader - Prime Brokerage (Ref:JDB/PB/SBLT)", "description": "Responsibilities:\n\nResponsible for the operational support of Equities trading for Global Market (U.S.) and structured products\nMonitor the trading system, support the CS team to handle client\u2019s inquiries\nSupport client's offline orders\nReport system or trading fault to IT team\nCommunicate with U.S broker to solve order related problem\nPreliminary risk monitoring and handle margin calls\n\nRequirements:\n\n\nOTC experience preferred\nHolder of SFC type 1 license\nDegree or above with a minimum of 2 years of relevant experience in the financial industry /securities firm\nGood command of written and spoken English and Chinese (Mandarin and Cantonese)\nWilling to work on night shift and work on public holiday\nImmediate available is preferred", "employment_types": ["Full Time", "Permanent"], "selling_points": [], "locations": ["Central"], "categories": ["Banking / Finance", "Financial Services", "Dealing & Trading", "Others"], "post_time": "2022-01-13T08:58:39Z", "salary": {"currency": null, "max": null, "min": null, "period": null, "term": null}, "salary_visible": false, "title_keywords": [], "responsibilities": ["communicate with", "operational support", "monitor", "risk monitoring", "report"], "requirements": {"degrees": ["degree or above"], "majors": [], "languages": ["cantonese", "english", "chinese", "mandarin"], "language_level": ["good command"], "hard_skills": [], "soft_skills": [], "languages_combined": [{"language": "cantonese", "language_level": ["good command"]}, {"language": "english", "language_level": ["good command"]}, {"language": "chinese", "language_level": ["good command"]}, {"language": "mandarin", "language_level": ["good command"]}]}, "experience_required": {"duration": ["minimum of 2 years"], "field": ["securities firm", "financial industry", "relevant experience"]}}, {"job_id": "100003009050307", "location_code": "hk", "company": "Premier Q Securities Limited", "job_title": "Responsible Officer (Type 1 & 7)", "description": "The Job\n\nTrading Prime Brokerage products, SBL/Repo/HKPO\nResponsible for the daily trade monitoring, verification process including but not limited to the investigation, escalation and resolution of the exceptions\nResponsible for trade maintenance and lifecycle events of Exchange-Traded and Detla one products throughout the lifecycle of the transactions\nPerform daily activities related to collateral agreement, trades and positions reconciliation\nAssist in implementing policies, procedures and internal controls, ad-hoc reporting and other administrative duties\nEnhance and Maintain Prime brokerage systems\n\nRequirements:\n\nBachelor degree in Accounting, Business Administration, Finance or other related disciplines\nStrong in IT Excel VBA / Phyton coding is a must Good exposure to various Prime Brokerage products e.g. SBL and Repo.\nWorking knowledge in transaction management, including trade and position reconciliations is required\nExperience in position management, including corporate actions management and P&L reporting\nGood command of both written & spoken English and Chinese, including Putonghua\nWe provide attractive remuneration package and fringe benefits for the right candidate. Interested parties please send detailed resume with current and expected salaries to\u00a0Human Resources Department i) by mail: 22/F, Li Po Chun Chambers, 189 Des Voeux Road Central, HK; ii) by fax: 2537 5431;\u00a0iii) by getting application method through the Job Opportunities Section of our Corporate website:\u00a0www.htisec.com; or iv) by using \"APPLY NOW\".\n\n\nPlease quote the reference in the application. If application is submitted in hard copy format, it should be placed in a sealed envelope marked \u201cConfidential\u201d. All applications will be treated in strict confidence and personal data provided by job applications will be used for recruitment purposes only. A copy of our Personal Information Collection Statement will be available upon request.", "employment_types": ["Full Time", "Permanent"], "selling_points": [], "locations": ["Wan Chai"], "categories": ["Banking / Finance", "Financial Services", "Dealing & Trading", "Information Technology (IT)", "Network & System"], "post_time": "2022-01-14T10:06:54Z", "salary": {"currency": null, "max": null, "min": null, "period": "monthly", "term": null}, "salary_visible": false, "title_keywords": ["responsible officer"], "responsibilities": ["ad-hoc", "reporting", "maintenance", "brokerage", "policies", "monitoring", "procedures", "systems", "investigation", "transactions", "resolution", "maintain", "administrative duties"], "requirements": {"degrees": ["degree", "bachelor"], "majors": ["related disciplines", "finance", "accounting", "business administration"], "languages": ["putonghua", "english", "chinese"], "language_level": ["good command"], "hard_skills": ["excel", "vba", "sbl"], "soft_skills": [], "languages_combined": [{"language": "putonghua", "language_level": ["good command"]}, {"language": "english", "language_level": ["good command"]}, {"language": "chinese", "language_level": ["good command"]}]}, "experience_required": {"duration": [], "field": ["management"]}}, {"job_id": "100003009053861", "location_code": "hk", "company": "Sinolink Securities (Hong Kong) Company Limited", "job_title": "Dealer (Day/Night-Shift) \u4ea4\u6613\u54e1 (\u65e5\u73ed/\u591c\u73ed-\u8f2a\u73ed)", "description": "\nResponsibilities:\n\n\n\nHandle enquiries and execute securities and futures orders\nCarry out routine works for day-to-day dealing operations\nMonitor client\u2019s portfolio, credit level and perform margin calls\nWilling to work\u00a0on\u00a0shift and public holidays\nTake up other ad-hoc projects and assigned duties\n\n\n\u5de5\u4f5c\u5167\u5bb9\uff1a\n\n\n\n\u8655\u7406\u5ba2\u6236\u67e5\u8a62\u53ca\u57f7\u884c\u8b49\u5238\u53ca\u671f\u8ca8\u4ea4\u6613\n\u8ca0\u8cac\u65e5\u5e38\u76e4\u623f\u904b\u4f5c\n\u76e3\u63a7\u5ba2\u6236\u7684\u6295\u8cc7\u7d44\u5408\uff0c\u4fe1\u7528\u6c34\u5e73\u548c\u57f7\u884c\u4fdd\u8b49\u91d1\u901a\u77e5\n\u9700\u8981\u8f2a\u73ed\u53ca\u65bc\u5047\u671f\u4e0a\u73ed\n\u8655\u7406\u7a81\u767c\u4e8b\u4ef6\u00a0\n\nRequirements:\n\n\n\nAssociate degree or above, Degree in Business, Economic, Finance or Accounting is an advantage\nQualified to be registered as licensed representative in RA1 and/or RA 2 under SFC or passed the\u00a0HKSI Licensing Examination preferred;\nGood team player with good communication & interpersonal skills\nSelf-motivated, responsible, able to work under pressure and able to work in night shift\nGood command of written and spoken English and Chinese, proficiency in Putonghua is necessary\nFresh graduate is welcomed, related experience is an advantage\nImmediate availability is preferred\n\n\u8981\u6c42\uff1a\n\n\n\n\u5927\u5c08\u6216\u4ee5\u4e0a\u5b78\u6b77\uff0c\u5de5\u5546\u3001\u7d93\u6fdf\u3001\u91d1\u878d\u6216\u6703\u8a08\u985e\u5c08\u696d\u512a\u5148\n\u5177\u9999\u6e2f\u8b49\u76e3\u6703\u7b2c1\u985e\u53ca\u7b2c2\u985e\u4ea4\u6613\u6301\u724c\u4ee3\u8868\u8cc7\u683c\u6216HKSI\u8cc7\u683c\u8003\u8a66\u5408\u683c\n\u826f\u597d\u4eba\u969b\u95dc\u4fc2, \u6e9d\u901a\u6280\u5de7\n\u9032\u53d6\u610f\u8b58\u5f37\u3001\u76e1\u8cac\u3001\u80fd\u5920\u5728\u58d3\u529b\u4e0b\u5de5\u4f5c\u53ca\u63a5\u53d7\u665a\u73ed\u5de5\u4f5c\n\u826f\u597d\u7684\u4e2d\u82f1\u6587\u66f8\u5beb\u548c\u53e3\u8a9e\u80fd\u529b\uff0c\u6d41\u5229\u666e\u901a\u8a71\n\u6b61\u8fce\u61c9\u5c46\u751f\u61c9\u8058\uff0c\u64c1\u6709\u76f8\u95dc\u7d93\u9a57\u8005\u512a\u5148\n\u53ef\u7acb\u5373\u5165\u8077\u8005\u512a\u5148", "employment_types": ["Full Time"], "selling_points": [], "locations": ["Sheung Wan"], "categories": ["Banking / Finance", "Dealing & Trading"], "post_time": "2022-01-17T07:40:07Z", "salary": {"currency": null, "max": null, "min": null, "period": "monthly", "term": null}, "salary_visible": false, "title_keywords": ["dealer"], "responsibilities": ["handle enquiries", "ad-hoc projects", "monitor", "operations"], "requirements": {"degrees": ["degree or above", "degree", "fresh graduate"], "majors": ["finance", "business", "accounting"], "languages": ["putonghua", "english", "chinese"], "language_level": ["proficiency", "good command"], "hard_skills": ["hksi"], "soft_skills": ["good team player", "self-motivated", "responsible", "communication", "interpersonal skills", "work under pressure"], "languages_combined": [{"language": "putonghua", "language_level": ["proficiency", "good command"]}, {"language": "english", "language_level": ["proficiency", "good command"]}, {"language": "chinese", "language_level": ["proficiency", "good command"]}]}, "experience_required": {"duration": [], "field": ["related"]}}, {"job_id": "100003009049984", "location_code": "hk", "company": "The Bank of East Asia, Limited", "job_title": "Senior Dealer", "description": "Senior Dealer (Job ID 2828)\nResponsibilities\n\nTo be a team member of Securities Services Department\nTo handle securities transactions as well as provide timely and efficient securities services to customers\nTo prepare various daily/monthly trading statistics reports as required\nTo alert the supervisors when any suspicious transaction is identified during order execution\nTo perform any administrative duties and handle any ad hoc tasks assigned by the supervisors\nRequirements\n\nHKCEE/HKDSE or above, with 5 subjects, including Chinese, English and Mathematics at Level 2/Attained/Grade E or above\nA minimum of 1 year\u2019 working experience in securities dealing\nPassed HKSI Licensing Examination Paper 1, 7 & 8\nSelf-motivated and able to work under pressure\nProficiency in both spoken and written English and Chinese, Putonghua a plus\nGood knowledge of MS Office\n(Fresh university graduates with less working experience will also be considered)\nPlease apply online via the BEA Careers website at\u00a0https://careers.hkbea.com/psp/hcmprd/EMPLOYEE/HRMS/c/HRS_HRAM.HRS_APP_SCHJOB.GBL?Page=HRS_APP_JBPST&Action=UFOCUS=Applicant&SiteId=1&JobOpeningId=2828&PostingSeq=1\u00a0or by clicking the \"Apply Now\" button below. Kindly note that if you are a new user, you have to first create your User Profile before you can apply.\n\nPersonal data provided by job applicants will be used for recruitment purposes only and will be treated in accordance with the Bank's Personal Information Collection (Employees) Statement and Privacy Policy Statement. Applicants who are not invited for interviews within six weeks may consider their applications unsuccessful and the personal data collected will be destroyed after six months.", "employment_types": ["Full Time", "Permanent"], "selling_points": ["Handle securities transactions", "Prepare trading statistics reports", "Min 1 yr. working experience in securities dealing"], "locations": ["Central"], "categories": ["Banking / Finance", "Financial Services", "Dealing & Trading", "Equities / Capital Markets"], "post_time": "2022-01-14T09:35:41Z", "salary": {"currency": null, "max": null, "min": null, "period": null, "term": null}, "salary_visible": false, "title_keywords": ["dealer"], "responsibilities": ["administrative duties", "reports", "ad hoc tasks", "transactions"], "requirements": {"degrees": ["hkdse"], "majors": ["mathematics"], "languages": ["putonghua", "english", "chinese"], "language_level": ["proficiency"], "hard_skills": ["plus", "c", "hksi", "ms office"], "soft_skills": ["self-motivated", "work under pressure"], "languages_combined": [{"language": "putonghua", "language_level": ["proficiency"]}, {"language": "english", "language_level": ["proficiency"]}, {"language": "chinese", "language_level": ["proficiency"]}]}, "experience_required": {"duration": ["minimum of 1 year"], "field": ["securities"]}}, {"job_id": "100003009050232", "location_code": "hk", "company": "China Galaxy International Financial Holdings Limited", "job_title": "Dealing Officer, Global Markets Department", "description": "Job\u00a0Duties :\n\n\nPerform trade execution in securities, futures and options in HK and Global markets;\nHandle\u00a0client\u2019s enquiries and assist in dealing operation;\nPerform trade\u00a0monitoring\u00a0to ensure all the transactions are in compliance with SFC Hong Kong and relevant market\u2019s regulations;\nAd hoc duties assigned by supervisor, including, but not limited to, system testing, market rehearsal and assist in new products/services rollout;\nUndertake risk monitoring and perform margin call/force liquidation.\n\n\n\n\u00a0Requirements :\n\n\nDiploma/ Higher Diploma/ Degree holder in Finance, Economics or related disciplines with at least three years of relevant working experiences;\nWilling to work on shifts and public holidays;\nGood written command of Chinese and English, verbally fluent in Putonghua is an advantage;\nSound understanding in algo order types;\nFamiliar with trading systems such as i-Asia, Sharp-Point, J-Trader, NSTD and Bloomberg is a definite advantage;\nCandidates with programming background is a plus;\nCandidates with less experience will also be considered.\n\nWe offer attractive remuneration package and fringe benefits to the right candidate. Interested applicants please send detailed resume stating present & expected salaries and date of availability to Human Resources & Administration Department by email.\n\nAll applications will be treated in the strictest confidence and personal data collected will be used for recruitment purpose only.", "employment_types": ["Full Time"], "selling_points": [], "locations": ["Sheung Wan"], "categories": ["Banking / Finance", "Dealing & Trading"], "post_time": "2022-01-14T09:59:17Z", "salary": {"currency": null, "max": null, "min": null, "period": "monthly", "term": null}, "salary_visible": false, "title_keywords": ["officer"], "responsibilities": ["regulations", "ad hoc duties", "compliance", "monitoring", "transactions", "testing", "risk monitoring"], "requirements": {"degrees": ["diploma", "degree holder"], "majors": ["related disciplines", "finance", "economics"], "languages": ["putonghua", "english", "chinese"], "language_level": ["advantage", "fluent", "good"], "hard_skills": ["plus", "bloomberg", "programming"], "soft_skills": [], "languages_combined": [{"language": "putonghua", "language_level": ["fluent", "advantage", "good"]}, {"language": "english", "language_level": ["advantage", "good"]}, {"language": "chinese", "language_level": ["advantage", "good"]}]}, "experience_required": {"duration": ["at least three years"], "field": ["related", "finance"]}}, {"job_id": "100003009041098", "location_code": "hk", "company": "Shanxi Securities International Financial Holdings Limited", "job_title": "Dealer / Senior Dealer", "description": "Responsibilities:\n\n\u2022 Verify and execute trade orders of securities and futures products for local and global markets\n\u2022 Manage orders from both internal and external customers\n\u2022 Monitor portfolio of client accounts and perform margin call\n\u2022 Provide customer services, handle customer enquiries and related support to clients\n\u2022 Formulate policies & procedures and control operation risk\n\u2022 Assist development of new products, functionalities and services\n\u2022 Work with team members to assure competence and on-going improvement of productivity\n\u2022 Assist in ad-hoc projects and carry out other duties and responsibilities as assigned by management\n\nRequirements:\n\n\u2022 Bachelor\u2019s degree or above in Economics, Finance or other relevant disciplines\n\u2022 Minimum 1-3 years of dealing experience\n\u2022 Holder of SFC license RA1 and RA2\n\u2022 Familiar with the trading systems SP Trader and Esunny is preferred\n\u2022 Willing to work on night shift/other shift and work on public holiday\n\u2022 Strong analytical, communications and interpersonal skills\n\u2022 Knowledgeable about the associated compliance processes and standard operating procedures\n\u2022 Good command in spoken and written English and Chinese (fluency in Putonghua)\n\u2022 Proficiency in computer applications such as Bloomberg, MS-Excel, Word and PowerPoint\n\u2022 Candidates with more experience will be considered as Senior Dealer\n\nWe offer competitive remuneration packages to the right candidate. Interested parties please submit your resume stating current and expected salaries to Human Resources Department (1). by post to Unit A, 29/F., Tower 1, Admiralty Centre, 18 Harcourt Road, Admiralty, Hong Kong; or (2). by using \"Apply Now\" button. All applications will be treated in strict confidence and personal data provided by job applications will be used for recruitment purposes only.", "employment_types": ["Full Time", "Permanent"], "selling_points": [], "locations": ["Admiralty"], "categories": ["Banking / Finance", "Financial Services", "Dealing & Trading", "Order Processing & Operation / Settlement"], "post_time": "2022-01-12T03:27:00Z", "salary": {"currency": null, "max": null, "min": null, "period": "monthly", "term": null}, "salary_visible": false, "title_keywords": ["dealer"], "responsibilities": ["internal and external customers", "control", "management", "handle customer enquiries", "other duties", "policies", "monitor", "procedures", "customer services", "ad-hoc projects"], "requirements": {"degrees": ["degree or above", "bachelor"], "majors": ["finance", "economics"], "languages": ["putonghua", "english", "chinese"], "language_level": ["fluency", "good command"], "hard_skills": ["bloomberg", "word", "powerpoint", "ms-excel", "sfc license"], "soft_skills": ["interpersonal skills"], "languages_combined": [{"language": "putonghua", "language_level": ["fluency", "good command"]}, {"language": "english", "language_level": ["fluency", "good command"]}, {"language": "chinese", "language_level": ["fluency", "good command"]}]}, "experience_required": {"duration": ["minimum 1-3 years"], "field": []}}, {"job_id": "100003009051838", "location_code": "hk", "company": "The Great Eagle Group of Companies", "job_title": "Manager - Treasury", "description": "Responsibilities:\n\nResponsible for routine treasury and loan transactions execution and administration including loan documentation negotiation, treasury dealing, KYC and compliance monitoring and relevant treasury reporting\nAssist in fund raising in bank loan market and international debt capital market\nAssist in managing all treasury functions including corporate liquidity, forex hedging, cash flow forecast and risk management\nDrive process and system improvement to increase data integrity and security\nAssist in managing banking relationship\nHandle ad hoc works as assigned by management\n\nRequirements:\n\nDegree holder in Accounting, Finance or other related disciplines\nHolder of CPA or CFA is an advantage\nMinimum 10 years\u2019 experience with corporate treasury, in-depth knowledge of debt, forex, derivative and cash management \u00a0\nStrong analytical and problem solving skills\nGood communication, presentation and interpersonal skills\nResponsible, well-organized, detail-minded, independent and able to work under pressure\nGood team player, willing to learn and take up new tasks\nProficiency in MS Office Applications\nGood command of both spoken and written\u00a0English\u00a0and Chinese (including Putonghua)\n\nSalary and benefits will be commensurate with qualifications and experience.\u00a0 Interested parties, please send a full resume with present and expected salary, and date available to The Human Resources Department, 32/F., Great Eagle Centre, 23 Harbour Road, Wanchai, Hong Kong or e-mail to us.\u00a0\u00a0(Please quote the reference no. on the envelope and the covering letter.)\n\nTo know more about us, please visit our websites at http://www.greateagle.com.hk\n\nWe are an equal opportunity employer and welcome applications from all qualified candidates.\n\nPersonal data collected will be treated in strict confidence and used only for recruitment-related purpose. Applicants who have not heard from us within four weeks may consider their applications unsuccessful. All personal data will be destroyed after 12 months.", "employment_types": ["Full Time", "Permanent"], "selling_points": ["Manage all corporate treasury functions", "Fund raising, debt capital market", "Holder of CPA or CFA is an advantage"], "locations": ["Wan Chai"], "categories": ["Accounting", "Consulting", "Banking / Finance", "Loan", "Dealing & Trading"], "post_time": "2022-01-17T01:20:52Z", "salary": {"currency": null, "max": null, "min": null, "period": "monthly", "term": null}, "salary_visible": false, "title_keywords": ["manager"], "responsibilities": ["reporting", "management", "ad hoc", "data", "compliance", "monitoring", "banking", "transactions", "cash flow", "forecast", "kyc", "documentation", "administration"], "requirements": {"degrees": ["degree holder"], "majors": ["related disciplines", "finance", "accounting"], "languages": ["putonghua", "english", "chinese"], "language_level": ["good command"], "hard_skills": ["cfa", "cpa", "problem solving skills", "ms office"], "soft_skills": ["detail-minded", "good team player", "independent", "responsible", "well-organized", "willing to learn", "communication", "analytical and problem solving skills", "interpersonal skills", "presentation", "work under pressure"], "languages_combined": [{"language": "putonghua", "language_level": ["good command"]}, {"language": "english", "language_level": ["good command"]}, {"language": "chinese", "language_level": ["good command"]}]}, "experience_required": {"duration": ["minimum 10 years"], "field": ["management"]}}, {"job_id": "100003009044712", "location_code": "hk", "company": "UOB Kay Hian (Hong Kong) Limited", "job_title": "FX Dealer", "description": "Responsibilities:\n\n\n\nHandle and execute FX conversion mainly\nAssist in placing overseas equities, futures, option orders\nExecute trade orders on a timely and accurate manner\nProvide high quality services in answering client\u2019s enquires regarding trades and orders\nLiaise with relevant internal departments and external parties such as banks and brokers\nHandle daily dealing operations\nTake up other ad-hoc projects and assigned duties\nRequirements:\n\n\nHolder of SFC RA1 and RA2 licenses or passed HKSI Licensing Examination Paper 1,7,8 and 9 is an advantage\nMinimum 1 year relevant experience in stocks, futures & options\nStrong knowledge in FX, followed by Overseas Equities, Futures, Option\nGood team player and willing to learn\nGood command of spoken English, Cantonese and Mandarin\nGood communication skills, independent, detail-minded and able to work under pressure\nImmediate available is preferred\n\nWhat We Offer:\u00a0\nCompetitive Salary\nMedical and Dental Benefits\nYear End Performance bonus\nShift allowance and holiday allowance\nExposure on foreign markets & global futures market trading\n\nInterested candidates are invited to send a comprehensive resume stating current and expected salaries to\u00a0Head of Human Resources, UOB Kay Hian (Hong Kong) Limited, 6/F Harcourt House, 39 Gloucester Road, Wan Chai, Hong Kong\u00a0or email by clicking the below \"Apply Now\" button", "employment_types": ["Full Time", "Permanent"], "selling_points": [], "locations": ["Wan Chai"], "categories": ["Banking / Finance", "Investment", "Financial Services", "Dealing & Trading"], "post_time": "2022-01-13T05:40:42Z", "salary": {"currency": null, "max": null, "min": null, "period": "monthly", "term": null}, "salary_visible": false, "title_keywords": ["dealer"], "responsibilities": ["operations", "external parties", "quality", "liaise with", "ad-hoc projects"], "requirements": {"degrees": [], "majors": [], "languages": ["cantonese", "english", "mandarin"], "language_level": ["good command"], "hard_skills": ["hksi"], "soft_skills": ["detail-minded", "communication skills", "good team player", "independent", "willing to learn", "work under pressure"], "languages_combined": [{"language": "cantonese", "language_level": ["good command"]}, {"language": "english", "language_level": ["good command"]}, {"language": "mandarin", "language_level": ["good command"]}]}, "experience_required": {"duration": ["minimum 1 year"], "field": ["relevant experience"]}}, {"job_id": "100003009049177", "location_code": "hk", "company": "Shanghai Commercial Bank Ltd", "job_title": "Relationship Officer, Securities Services", "description": "Responsibilities:\n\nExecute securities trade orders in Kwai Ching\nProvide efficient and excellent services to customers\nSolicit business opportunities through cross-selling banking products\nAcquire and cultivate new and existing customer relationship in accordance with the branch target segments\n\nRequirements:\n\nPost-secondary educated with 1 year of securities dealing experience\nCompleted HKSI examinations and qualified to register for RA1 & 4\nSelf-motivated with strong interpersonal and communication skills\nGood command of spoken and written English and Chinese, including Putonghua\n\n(Fresh graduates who completed HKSI examinations will be considered and training will be provided)\n\nAttractive remuneration package will be offered to the right candidates. Interested parties please click \"Apply Now\" to submit your full resume with current and expected salary to the Human Resources Division.\n\nPlease visit us at www.shacombank.com.hk for more information about our Bank.\n\nAll personal data collected will be used for recruitment related purposes strictly in accordance with the Bank's personal data policies, a copy of which will be provided immediately upon request by contacting our Personal Data Compliance Officer. Applicants who are not contacted within two months may consider their applications unsuccessful and the personal data collected from the applicants will be retained for no longer than two years from the date of rejection during which the applicants may be considered for other suitable positions within the Bank.", "employment_types": ["Full Time", "Permanent"], "selling_points": ["Execute securities trade orders in branch or Ctr", "Provide efficient & excellent service to customers", "Cross-selling and making referrals to sales team"], "locations": ["Not Specified"], "categories": ["Banking / Finance", "Investment", "Financial Services", "Dealing & Trading"], "post_time": "2022-01-15T03:50:10Z", "salary": {"currency": null, "max": null, "min": null, "period": "monthly", "term": null}, "salary_visible": false, "title_keywords": ["officer"], "responsibilities": ["business opportunities", "banking"], "requirements": {"degrees": [], "majors": [], "languages": ["putonghua", "english", "chinese"], "language_level": ["good command"], "hard_skills": ["hksi"], "soft_skills": ["communication skills", "self-motivated", "interpersonal"], "languages_combined": [{"language": "putonghua", "language_level": ["good command"]}, {"language": "english", "language_level": ["good command"]}, {"language": "chinese", "language_level": ["good command"]}]}, "experience_required": {"duration": ["1 year"], "field": ["securities"]}}, {"job_id": "100003009050102", "location_code": "hk", "company": "HANSEL INTERNATIONAL Executive Search Limited", "job_title": "HY Flow Trader - Senior Associate/AVP", "description": "Our client is a Chinese Investment Bank with SFC license in type 1, 4, 6, 9 regulated activities. They are currently looking for a HY Flow Trader to join their FICC Sales & Trading desk\u00a0\n\nResponsibilities:\n\nResponsible for High Yield bonds with main focus on Chinese Local Government Financing Vehicles and Property markets\nSupport the development on fixed income products such as structured products and derivatives together with sales team on both primary issuance and secondary market\nMaintain excellent external relationship with brokers and liquidity providers, and internal relationship with other related departments of the Company\n\nRequirements:\n\nHas obtained a bachelor\u2019s degree\nMinimum 3 years\u2019 credit trading experience\nChinese HY credits experience is a big advantage\nExcellent communications and negotiation skills with both internal and external key stakeholders\nBe proactive and can work under pressure\nFluent in both Mandarin and English\n\nFor interested candidate please send us your CV with current and expected salary.\u00a0 All personal information collected will be strictly used for recruitment purpose only.", "employment_types": ["Full Time"], "selling_points": ["Fixed Income Sales and Trading", "Flow Trading", "LGFV and Property Sector"], "locations": ["Central"], "categories": ["Banking / Finance", "Financial Services", "Dealing & Trading"], "post_time": "2022-01-14T09:47:07Z", "salary": {"currency": null, "max": null, "min": null, "period": "monthly", "term": null}, "salary_visible": false, "title_keywords": ["senior associate"], "responsibilities": ["maintain", "sales team"], "requirements": {"degrees": ["degree", "bachelor"], "majors": [], "languages": ["english", "chinese", "mandarin"], "language_level": ["advantage", "fluent"], "hard_skills": ["hy"], "soft_skills": ["negotiation skills", "proactive", "work under pressure"], "languages_combined": [{"language": "english", "language_level": ["fluent"]}, {"language": "chinese", "language_level": ["advantage"]}, {"language": "mandarin", "language_level": ["fluent"]}]}, "experience_required": {"duration": ["minimum 3 years"], "field": ["trading"]}}, {"job_id": "100003009047773", "location_code": "hk", "company": "Public Bank (Hong Kong) Ltd", "job_title": "Assistant Dealing Manager (Ref: JD-DM)", "description": "Assist in supervision of the dealing operation\nAssist in monitoring of the securities trading activities\nAssist in compiling product documentation, manuals and guidelines\nKnowledge and exposure on wealth products an added advantage\nParticipate in system enhancement/integration projects and other ad hoc operational projects\nCo-operate with all relevant departments to ensure compliance in all operational areas\nUniversity degree holder with minimum 5 years experience in securities industry\nTo apply, interested parties please follow the application methods available in the Bank\u2019s career website\u00a0https://www.publicbank.com.hk/en/aboutus/careeropportunities. You can send us your resume quoting our job reference number together with present &\u00a0expected salary (a must)\u00a0to the Human Resources Department by email or fax at\u00a02815 3157\u00a0or by post to\u00a0Human Resources Department, 12/F, Public Bank Centre, 120 Des Voeux Road Central, Hong Kong. You may also visit our career website for other career opportunities available within our Group.\n\n\nPersonal data collected will be used for recruitment purpose only and will be treated in accordance with the Bank\u2019s Personal Information Collection Statement, a copy of which has been available in the Bank\u2019s career website.", "employment_types": ["Full Time", "Permanent"], "selling_points": [], "locations": ["Not Specified"], "categories": ["Banking / Finance", "Investment", "Dealing & Trading", "Others"], "post_time": "2022-01-15T03:49:07Z", "salary": {"currency": null, "max": null, "min": null, "period": null, "term": null}, "salary_visible": false, "title_keywords": ["manager", "assistant"], "responsibilities": ["ad hoc", "guidelines", "monitoring", "ensure compliance", "co-operate with", "documentation"], "requirements": {"degrees": ["university degree"], "majors": [], "languages": [], "language_level": [], "hard_skills": ["documentation", "integration"], "soft_skills": [], "languages_combined": []}, "experience_required": {"duration": ["minimum 5 years"], "field": ["securities industry"]}}, {"job_id": "100003009050209", "location_code": "hk", "company": "Capital Advisory Limited", "job_title": "Associate \u2013 Merger & Acquisition", "description": "Responsibilities\nHandle finance projects including IPOs, mergers and acquisitions, and other management advisory projects\n\u00a0Support and communicate in the internal control, auditing, accounting and tax assignments of the projects\nAssist in deals support, such as reviewing target financials, business operation materials and involve in liaising deals structure\nLiaise with other professional parties to support the implementation of projects\n\u00a0Perform ad-hoc assignments\n\nRequirements\n\nDegree holder or above in Accounting, Finance, Business Administration is preferred\n1-2 years working experience in accounting firm\n\u00a0Good command of spoken and written English, Mandarin and Cantonese\n\u00a0Proficiency in Excel\n\u00a0Hardworking and willing to learn new knowledge on top of accounting\n\u00a0Immediate available preferred\nFresh graduates will also be considered\u00a0\nA good opportunity to allow audit junior to transit to capital market\n\nWe offer\n\n\u00a05-days work\n\u00a0Study and examination leave\n\u00a0Discretionary bonus\nDouble pay\nAnnual leave\n\nInterested parties please send your resume with expected salary and availability by clicking \"Apply Now\". All personal data collected will be used for recruitment purpose only.", "employment_types": ["Full Time", "Permanent"], "selling_points": ["Study and examination leave;  5-days work", "Discretionary bonus; Annual leave ; Bank holiday", "Sheung Wan MTR station; Double pay"], "locations": ["Sheung Wan"], "categories": ["Accounting", "Consulting", "Banking / Finance", "Dealing & Trading", "Equities / Capital Markets"], "post_time": "2022-01-14T09:56:47Z", "salary": {"currency": "HKD", "max": 24999, "min": 20000, "period": "monthly", "term": null}, "salary_visible": true, "title_keywords": ["associate"], "responsibilities": ["tax", "business operation", "management", "ad-hoc assignments", "implementation of projects", "liaise with", "auditing", "internal control"], "requirements": {"degrees": ["degree holder"], "majors": ["finance", "accounting", "business administration"], "languages": ["cantonese", "english", "mandarin"], "language_level": ["good command"], "hard_skills": ["excel"], "soft_skills": ["willing to learn", "hardworking"], "languages_combined": [{"language": "cantonese", "language_level": ["good command"]}, {"language": "english", "language_level": ["good command"]}, {"language": "mandarin", "language_level": ["good command"]}]}, "experience_required": {"duration": ["1-2 years"], "field": ["accounting"]}}, {"job_id": "100003009039630", "location_code": "hk", "company": "Roctec Securities Company Limited", "job_title": "Securities and Futures Dealer", "description": "-\u00a0 \u00a0 \u00a0 \u00a0 \u00a0 Licensed with SFC as representative of Type I & Type II\n\n-\u00a0\u00a0\u00a0\u00a0\u00a0\u00a0\u00a0\u00a0\u00a0 Execute securities and futures orders\n\n-\u00a0\u00a0\u00a0\u00a0\u00a0\u00a0\u00a0\u00a0\u00a0 Provide customer service and enquiries\n\n-\u00a0\u00a0\u00a0\u00a0\u00a0\u00a0\u00a0\u00a0\u00a0 Risk monitoring of client account and margin call\n\n-\u00a0\u00a0\u00a0\u00a0\u00a0\u00a0\u00a0\u00a0\u00a0 Handle account opening\n\n-\u00a0 \u00a0 \u00a0 \u00a0 \u00a0 5 day work", "employment_types": ["Full Time"], "selling_points": [], "locations": ["Central"], "categories": ["Banking / Finance", "Dealing & Trading"], "post_time": "2022-01-11T10:16:54Z", "salary": {"currency": null, "max": null, "min": null, "period": "monthly", "term": null}, "salary_visible": false, "title_keywords": ["dealer"], "responsibilities": ["provide customer service", "account opening", "risk monitoring"], "requirements": {"degrees": [], "majors": [], "languages": [], "language_level": [], "hard_skills": ["account opening"], "soft_skills": ["customer service"], "languages_combined": []}, "experience_required": {"duration": [], "field": []}}, {"job_id": "100003009043422", "location_code": "hk", "company": "Reticle Search International Limited", "job_title": "Treasury Dealer", "description": "Our client is a\u00a0financial institution, now they are looking for a\u00a0Treasury Dealer to join their team.\n\n\n\nResponsibilities\n\nPerform execution of trade orders\nPerform different executions of Money Market instruments, including inter-banking MM lending & borrowing, CD/Bills, MTN/Bonds & FX Swap\nAssist in cash & liquidity management, including cash flow and money market position management\nAssist in the monitoring of Bank\u2019s liquidity risk & market risk exposure; assisting in meeting regulatory and internal limits for all key risk indicators\nConduct market research and analysis about the latest interest rate trend and other market movements \u00a0\nAssist in ad-hoc projects, for example, business initiatives discussion with Business Units\n\nRequirements\n\nDegree holder in business, finance or related disciplines\nAt least 1 year of experience in Treasury function within a financial institution, dealing experiences are preferable. Fresh graduates will also be considered.\nTeam player but at the same time with independent, critical and analytical thinking skills\nPositive attitude with high standards of integrity and ethic\nInterested parties please apply with CV with current and expected salary. All information is strictly used for recruitment purposes only.", "employment_types": ["Permanent"], "selling_points": ["Immediate available is highly preferred", "Fresh graduate will also be considered", "Dealing experiences are preferable"], "locations": ["Not Specified"], "categories": ["Banking / Finance", "Treasury", "Financial Services", "Dealing & Trading"], "post_time": "2022-01-12T23:26:20Z", "salary": {"currency": null, "max": null, "min": null, "period": "monthly", "term": null}, "salary_visible": false, "title_keywords": ["dealer"], "responsibilities": ["management", "business initiatives", "conduct market research", "monitoring", "analysis", "cash flow", "banking", "ad-hoc projects"], "requirements": {"degrees": ["degree holder"], "majors": ["related disciplines", "finance", "business"], "languages": [], "language_level": [], "hard_skills": [], "soft_skills": ["positive attitude", "team player", "independent", "integrity"], "languages_combined": []}, "experience_required": {"duration": ["at least 1 year"], "field": ["financial"]}}, {"job_id": "100003009050112", "location_code": "hk", "company": "Don Nelson Recruitment Limited", "job_title": "Hong Kong Listed Bank - \u5ba2\u6236\u670d\u52d9\u4e3b\u4efb (\u8b49\u5238\u90e8)   (\u5e95\u85aa\u53ef\u905428K) \u56fa\u5b9a\u5de5\u4f5c\u6642\u9593", "description": "\u82f1\u570b\u8001\u724c\u9280\u884c -\u00a0\u5ba2\u6236\u670d\u52d9\u4e3b\u4efb (\u8b49\u5238\u90e8)\u00a0\u00a0\n\n\u8077\u8cac:\n\n\u65bc\u5ba2\u6236\u670d\u52d9\u71b1\u7dda\u5167,\u5c31\u5ba2\u6236\u7684\u67e5\u8a62,\u5feb\u901f\u5c0b\u627e\u89e3\u6c7a\u554f\u984c\u7684\u65b9\u6cd5\u4ee5\u53ca\u89e3\u7b54\u6709\u95dc\u90e8\u9580\u7684\u67e5\u8a62\u8207\u53ca\u8f49\u4ecb\u610f\u898b\u6216\u6295\u8a34\n\n\u5167\u5bb9:\n\n\u4e2d\u4e94\u6703\u8003/\u6587\u6191\u8a66\u00a0\u5168\u79d1\u5408\u683c\u00a0\u6216\u4ee5\u4e0a\u7a0b\u5ea6 ,\u6b61\u8fce\u6709\u8208\u8da3\u65bc\u5ba2\u6236\u670d\u52d9\u696d\u6216\u9280\u884c\u696d\u767c\u5c55\u53ca\u61c9\u5c46\u7562\u696d\u751f\n\u5177\u5099\u57fa\u672c\u5ba2\u6236\u670d\u52d9\u7d93\u9a57, \u7d93\u9a57\u8c50\u5bcc\u8005\u53ef\u53d7\u8058\u70ba\u9ad8\u7d1a\u5ba2\u6236\u670d\u52d9\u4e3b\u4efb\n\u5e95\u85aa$22,000 \u8d77,\u00a0 \u6709\u8b49\u5238\u7d93\u9a57\u8005\u5f9e\u512a\n\u826f\u597d\u6649\u5347\u6a5f\u6703\n\u5df2\u8003\u53d6HKSI 1, 7, 8\u724c\u7167, \u63d0\u4f9b\u5728\u8077\u57f9\u8a13\n2\u5e74\u5f8c\u8868\u73fe\u7406\u60f3\u8005\u53ef\u6649\u5347\u70ba - \u5ba2\u6236\u670d\u52d9\u526f\u7d93\u7406 (\u5e95\u85aa\u52a0\u734e\u91d1\u6708\u5165\u7d04$28,000 - $30,000)\n\u5b8c\u5584\u5728\u8077\u57f9\u8a13 (3\u500b\u6708)\n\u65fa\u89d2\u5340\u5de5\u4f5c\u00a0\n\u4e94\u5929\u5de5\u4f5c, \u6bcf\u5929\u5de5\u4f5c8\u5c0f\u6642\n\u6bcf\u5468\u5de5\u4f5c39.5\u5c0f\u6642\n\n\u54e1\u5de5\u798f\u5229:\n\n18\u5929\u5e74\u5047\u53ca\u984d\u5916\u6709\u85aa\u5047(\u5982\u5a5a\u5047\u3001\u751f\u65e5\u5047\u3001\u7522\u5047)\n\u5168\u65b9\u4f4d\u91ab\u7642\u4fdd\u96aa, \u5305\u62ec\u4fdd\u969c\u4f60\u672c\u4eba\u53ca\u914d\u5076\u3001\u5b50\u5973,\u4fdd\u969c\u7bc4\u570d\u6db5\u84cb\u8dcc\u6253\u3001\u8eab\u9ad4\u6aa2\u67e5\u3001\u7259\u79d1\u4fdd\u969c\n\u4f4e\u606f\u54e1\u5de5\u7269\u696d\u6309\u63ed\u8cb8\u6b3e,\u8cb8\u6b3e\u984d\u53ef\u9054\u7269\u696d\u4f30\u50f9\u6216\u552e\u50f9100%\n\u5404\u7a2e\u9280\u884c\u670d\u52d9\u53ca\u7522\u54c1\u7684\u54e1\u5de5\u512a\u60e0,\u5305\u62ec\u8cb8\u6b3e\u3001\u4fe1\u8cb8\u3001\u4fe1\u7528\u5361\n\u6700\u9ad8\u53ef\u905413%\u7684\u5f37\u7a4d\u91d1\u50f1\u4e3b\u4f9b\u6b3e\n\u652f\u63f4\u54e1\u5de5\u8003\u53d6\u5de5\u4f5c\u6240\u9700\u7684\u76f8\u95dc\u5c08\u696d\u8cc7\u683c\n\nPersonal data provided by job applicants will be used strictly in accordance with the employer's personal data policies and for recruitment purposes only.", "employment_types": ["Full Time", "Permanent"], "selling_points": ["\u5e95\u85aa$22,000 \u8d77,  \u6709\u8b49\u5238\u7d93\u9a57\u8005\u512a\u5148", "\u5ba2\u6236\u670d\u52d9\u526f\u7d93\u7406 (\u5e95\u85aa\u52a0\u734e\u91d1\u6708\u5165\u7d04$28,000 - $30,000)", "\u5df2\u8003\u53d6HKSI 1, 7, 8\u724c\u7167"], "locations": ["Not Specified"], "categories": ["Banking / Finance", "Retail Banking", "Dealing & Trading", "Sales, CS & Business Devpt", "Call Centre"], "post_time": "2022-01-15T03:50:50Z", "salary": {"currency": "HKD", "max": 24999, "min": 20000, "period": "monthly", "term": null}, "salary_visible": true, "title_keywords": ["\u5ba2\u6236\u670d\u52d9\u4e3b\u4efb"], "responsibilities": ["policies", "personal data", "recruitment"], "requirements": {"degrees": [], "majors": [], "languages": [], "language_level": [], "hard_skills": [], "soft_skills": [], "languages_combined": []}, "experience_required": {"duration": [], "field": []}}, {"job_id": "100003009050879", "location_code": "hk", "company": "PT Investment Corporation Limited", "job_title": "BUSINESS DEVELOPMENT MANAGER", "description": "You will report to the COO. Key responsibilities include:\n\nBusiness development in international trade for commodities\nHandling and negotiation of hedging contracts\nGather market intelligence of major competitors\nBusiness travel to Mainland China is required\nPerform ad hoc tasks as assigned\n\nRequirements:\n\nBachelor Degree or above in Business Management, Economics, Finance or Quantitative Disciplines\n5 years or more relevant experience in commodities trading and hedging\nGood knowledge in financial markets\nFamiliar with PRC markets, trading techniques and financial products\nFluent in English, Putonghua and Shanghainese\u00a0\n\nInterested parties please send full resume with current and expected salaries, availability and right to work status by clicking \u201cApply Now\u201d.\u00a0 Applicants not invited for interview within 2 weeks may consider their applications unsuccessful. Data collected will only be used for recruitment purpose.\u00a0\n\nPersonal data will be used for recruitment purpose only.", "employment_types": ["Full Time"], "selling_points": [], "locations": ["Sheung Wan"], "categories": ["Banking / Finance", "Dealing & Trading", "Sales, CS & Business Devpt", "Business Development"], "post_time": "2022-01-14T11:37:46Z", "salary": {"currency": null, "max": null, "min": null, "period": "monthly", "term": null}, "salary_visible": false, "title_keywords": ["business development manager"], "responsibilities": ["contracts", "ad hoc tasks"], "requirements": {"degrees": ["degree or above", "bachelor"], "majors": ["finance", "economics", "business"], "languages": ["putonghua", "english"], "language_level": ["fluent"], "hard_skills": ["business management"], "soft_skills": [], "languages_combined": [{"language": "putonghua", "language_level": ["fluent"]}, {"language": "english", "language_level": ["fluent"]}]}, "experience_required": {"duration": ["5 years"], "field": ["relevant experience", "trading"]}}, {"job_id": "100003009045872", "location_code": "hk", "company": "Yue Xiu Securities Holdings Limited", "job_title": "Associate /Senior Associate, Capital Markets Department", "description": "We offer attractive remuneration package,\u00a05-day work, competitive fringe benefits (wedding leave, body check, group medical insurance, dental insurance etc.) and excellent career development opportunity to the right candidate.\n\nResponsibilities\n\n\nWork closely with teammates\u00a0to go through whole process of deal execution\nBuild relationships with issuers and peers for more quality deals\nManage\u00a0existing clients and develop new investors\n\nRequirements\n\nDegree holder in Finance, Economics, Accounting or related discipline\nMinimum 1-3 years\u2019 relevant experience in\u00a0capital markets\nProficiency in computer applications such as Bloomberg, PowerPoint, Excel and Word\nGood communication skills of Chinese and English\nWillingness to work extra hours to meet deadline\n\n\u5d17\u4f4d\u8077\u8cac\n\n\u64c1\u6709\u826f\u597d\u7684\u9805\u76ee\u57f7\u884c\u80fd\u529b\u8207\u5408\u4f5c\u7cbe\u795e\n\u8207\u767c\u884c\u65b9\u53ca\u540c\u696d\u5efa\u7acb\u826f\u597d\u7684\u5408\u4f5c\u95dc\u4fc2\uff0c\u4ee5\u5f15\u5165\u66f4\u591a\u512a\u8cea\u9805\u76ee\n\u7dad\u6301\u5ba2\u6236\u95dc\u4fc2\uff0c\u4e26\u6709\u80fd\u529b\u767c\u5c55\u65b0\u7684\u5ba2\u6236\n\u5b8c\u6210\u9818\u5c0e\u4ea4\u8fa6\u7684\u5176\u4ed6\u5de5\u4f5c\n\n\u00a0\u4efb\u8077\u8981\u6c42\n\n\u5927\u5b78\u672c\u79d1\u53ca\u4ee5\u4e0a\u5b78\u6b77\uff0c\u91d1\u878d\u3001\u7d93\u6fdf\u3001\u6703\u8a08\u7b49\u76f8\u95dc\u5c08\u696d\n\u5177\u67091\u20143\u5e74\u8cc7\u672c\u5e02\u5834\u9805\u76ee\u76f8\u95dc\u5de5\u4f5c\u7d93\u9a57\n\u80fd\u719f\u7df4\u4f7f\u7528Bloomberg\u3001PowerPoint\u3001Excel\u548cWord\u7b49\u8fa6\u516c\u8edf\u4ef6\n\u826f\u597d\u7684\u4e2d\u82f1\u6587\u6e9d\u901a\u6280\u5de7\n\u6297\u58d3\u80fd\u529b\u5f37\uff0c\u5728\u898f\u5b9a\u7684\u6642\u9593\u5167\u5b8c\u6210\u5de5\u4f5c\u6216\u5fc5\u8981\u6642\u52a0\u73ed\u5b8c\u6210\u4efb\u52d9\n\nInterested parties please send CV, to the Human Resources Department by clicking \"Apply Now\".\n\nApplicants not invited for interviews within six weeks may consider their applications unsuccessful. Our Company is an equal opportunity employer. Personal data collected will be used for recruitment purpose only.\n\nAll information provided will be treated confidentially.", "employment_types": ["Full Time", "Permanent"], "selling_points": ["Capital markets", "Degree holder", "5-day work, attractive remuneration"], "locations": ["Wan Chai"], "categories": ["Banking / Finance", "Investment", "Dealing & Trading", "Equities / Capital Markets"], "post_time": "2022-01-13T08:59:35Z", "salary": {"currency": null, "max": null, "min": null, "period": "monthly", "term": null}, "salary_visible": false, "title_keywords": ["senior associate", "associate"], "responsibilities": ["quality", "develop"], "requirements": {"degrees": ["degree holder"], "majors": ["finance", "economics", "accounting"], "languages": ["english", "chinese"], "language_level": ["good"], "hard_skills": ["excel", "word", "bloomberg", "powerpoint"], "soft_skills": ["communication skills", "willingness to work"], "languages_combined": [{"language": "english", "language_level": ["good"]}, {"language": "chinese", "language_level": ["good"]}]}, "experience_required": {"duration": ["minimum 1-3 years"], "field": ["capital markets", "relevant experience"]}}, {"job_id": "100003009038000", "location_code": "hk", "company": "China Everbright Securities International Company Limited", "job_title": "Senior Dealer, Securities Broking", "description": "Ref: SD/SB/110122DB/44\u00a0\n\n\nResponsibilities\n\n\nHandle daily dealing operation for precious metals, FX, mutual fund, global equities, futures and options\nPerform efficient and accurate order executions and reconciliation with internal and external customers/counterparties\nPerform credit check before execution and strictly follow dealing manual on related issues\nHandle market and trade enquiries\nPerform system UAT and handle ad-hoc assignments\n\nRequirements\n\nDegree holder in Banking & Finance or related discipline is preferred\n3\u00a0- 5 years of relevant dealing experience\nHolder of SFC license for Type 1 and Type 2 regulated activities, Type 3 is preferred\nHands-on experience in Sharp Point, J-traders, TT, etc., with knowledge in market information providers such as Reuters and Bloomberg\nProficiency in MS Office applications\nGood command of both written and spoken English and Chinese and fluent in Putonghua\nShift duty is required\nCandidate with less experience will be considered as 'Dealer'\nWe offer competitive remuneration package to the right candidate. If you are interested in the post, please send your resume together with\u00a0your present\u00a0&\u00a0expected salaries\u00a0and\u00a0availability\u00a0by clicking\u00a0\u201cApply Now\u201d.\u00a0\nFor more information about\u00a0China Everbright Securities International Company Limited, please visit\u00a0www.ebshk.com.\n\nWe are an equal opportunity employer and welcome applications from all qualified candidates. All applications will be treated in the strictest confidence. Personal data provided will be used for recruitment purposes only. The job applicant will assume all or any risks arising out of or in connection with the job application transmission process prior to our actual receipt of the same including but not limited to accidental or unauthorized loss or disclosure of personal information, to which we will not be responsible in any way.\n\nUnder the Personal Data (Privacy) Ordinance, you may request access to, and / or correction of your personal data in relation to your application. If you wish to do so, please email to us.\n", "employment_types": ["Full Time", "Permanent"], "selling_points": [], "locations": ["Causeway Bay"], "categories": ["Banking / Finance", "Investment", "Dealing & Trading", "Equities / Capital Markets"], "post_time": "2022-01-11T04:32:27Z", "salary": {"currency": null, "max": null, "min": null, "period": "monthly", "term": null}, "salary_visible": false, "title_keywords": ["dealer"], "responsibilities": ["internal and external customers", "credit check", "ad-hoc assignments", "uat"], "requirements": {"degrees": ["degree holder"], "majors": ["finance"], "languages": ["putonghua", "english", "chinese"], "language_level": ["good command", "fluent"], "hard_skills": ["bloomberg", "sfc license", "ms office"], "soft_skills": ["hands-on"], "languages_combined": [{"language": "putonghua", "language_level": ["good command"]}, {"language": "english", "language_level": ["fluent", "good command"]}, {"language": "chinese", "language_level": ["fluent", "good command"]}]}, "experience_required": {"duration": ["3 - 5 years"], "field": []}}, {"job_id": "100003009046569", "location_code": "hk", "company": "DBS Bank Ltd", "job_title": "Senior Officer, Specialist, Customer Centre, Consumer Banking (Licensed)", "description": "Job Highlights:\n\nTo lead global equity market electronic trading and settlement system projects implementation\nFamiliar with dealing systems such as Ayers, AFE, Bloomberg, FIS, Infocast, and the HKEX infrastructure\nGood knowledge of SFC/HKMA requirements on securities trading system and front-to-back business flow\n\nResponsibilities:\n\nCollect business/user requirements, critically evaluate options gathered from multiple sources, and participate in quality peer reviews to deliver technical solution to address business needs.\nProject management to plan and oversee projects, monitor progress, ensure inter-dependencies are identified by keeping track of milestones / deliverables to ensure each party concerned completes related tasks in a timely manner \u00a0\u00a0\nCoordinate with and facilitate between System Owners, Business Owners, ITD, OPS, L&C and other relevant units (cross-functional) on the overall project rollout, communications, testing etc. to meet the business objective, analyze/deliver the functional requirements in waterfall/agile framework and facilitate the resolution of issues effectively\nCoordinate internal/business review and get business signoff for related project documentation and clearance including, but not limited to, project cost, plan, specifications, NPAP, project assessment. Etc.\nRegular update on project progress to the project team and key stakeholders, highlight items / key project risks for senior attention and seek guidance accordingly\nResponsible for end-to-end planning and execution of business case, acceptance testing, change management, training & communications\nResponsible for redefining business process and driving the target operating model design\nPost project completion, review with respective System Owners, Business Owners, ITD and other units concerned on the outcome whether business objective has been achieved / further fine-tuning required\n\nRequirements:\n\n\u200bUniversity degree / Diploma holder in Information Technology or business related disciplines\nAt least 5 years in business analysis/digital project management experience especially in securities/banking/finance industry\nFamiliar with SFC/HKMA related trading system front-to-back business flow\nGood problem solving, communication and interpersonal skills\nStrong analytical mindset\nExcellent client-facing and internal communication skills organizational skills including attention to detail and multi-tasking skills\nGood command of spoken and written English and Chinese", "employment_types": ["Full Time"], "selling_points": ["With HKSI license 1,7,8", "Experience in securities trading preferable", "Experience in customer services is an advantage"], "locations": ["Kwun Tong"], "categories": ["Banking / Finance", "Dealing & Trading", "Sales, CS & Business Devpt", "Call Centre"], "post_time": "2022-01-13T14:26:00Z", "salary": {"currency": null, "max": null, "min": null, "period": "monthly", "term": null}, "salary_visible": false, "title_keywords": ["specialist", "senior officer"], "responsibilities": ["monitor progress", "quality", "design", "business process", "plan", "project documentation", "project progress", "testing", "resolution", "guidance", "cost", "change management", "review", "coordinate with", "specifications", "a timely manner", "evaluate", "project management", "coordinate", "planning"], "requirements": {"degrees": ["diploma holder", "degree"], "majors": ["related disciplines", "business", "information technology"], "languages": ["english", "chinese"], "language_level": ["good command"], "hard_skills": ["hkma", "project management", "analysis", "problem solving"], "soft_skills": ["communication skills", "organizational skills", "problem solving", "project management", "communication and interpersonal skills", "attention to detail", "multi-tasking skills", "client-facing"], "languages_combined": [{"language": "english", "language_level": ["good command"]}, {"language": "chinese", "language_level": ["good command"]}]}, "experience_required": {"duration": ["at least 5 years"], "field": ["finance industry", "project management", "banking", "business analysis", "digital", "securities"]}}, {"job_id": "100003009050148", "location_code": "hk", "company": "OCBC Wing Hang Bank Limited", "job_title": "Business Analyst -- Securities Brokerage Trading and Settlement Systems", "description": "Global Banking and Markets \u2013 Global Markets\n\nHang Seng's Global Markets business provides superior service, fully integrated solutions and 24-hour global markets coverage. Our support framework is substantial. Our advanced technologies deliver quick access to key markets. Our capital strength allows us to tailor competitively-priced solutions for specific client business around the world. We provide a full spectrum of treasury services to our customers, including foreign exchange, interest rate risk management, derivatives products, capital markets instruments, as well as market intelligence on global trends and key developments.\n\nWe are currently seeking a high caliber professional to join our department as\u00a0Chief Dealer, Foreign Exchange.\n\u00a0\u00a0\n\nPrincipal responsibilities\n\nManage the G7, XAU and short term interest rate tradng position in order to meet personal financial goals and ensure trading within limit;\nHandle Foreign Exchange Margin operations in accordance with the business plans and policies;\nA significant portion of the position is expected to be mid-shift (1345 to 2300) and provide back up to relevant team members when required;\nEnsure deal executions with both internal desks and external inter-bank counterparties follow the Bank\u2019s internal procedures and are compliant with regulations;\nProvide support for new business initiative and interaction with both middle office and internal support functions;\nHandle daily reports for FX department;\nPerform ad hoc tasks or projects as assigned.\n\nRequirements:\n\nUniversity degree in Banking, Finance, Economics or related discipline;\nMinimum of five or more years of relevant work experience;\nStable, able to perform mid-shift and work responsibly in a dynamic environment;\nCreative with strong analytical skill and sensitive to figures;\nProficiency in computer applications such as Bloomberg, Reuters and EBS;\nProficiency in both English and Chinese, fluency in Putonghua an advantage;\nHigh level of customer centricity mindset with dedication to deliver exceptional quality services for customers\n\nIf you would like to explore other opportunities at Hang Seng Hong Kong, please visit www.hangseng.com/careers/ for details.\n\n\nThe health and safety of our employees and candidates is very important to us. Due to the current situation related to the Novel Coronavirus (2019-nCoV), we\u2019re leveraging our digital capabilities to ensure we can continue to recruit top talent at the HSBC Group. \u00a0As your application progresses, you may be asked to use one of our digital tools to help you through your recruitment journey.\u00a0 If so, one of our \u00a0Resourcing colleagues will explain how our video-interviewing technology will be used throughout the recruitment process and will be on hand to answer any questions you might have.\n\nAll information provided by applicants will be used only for recruitment purposes and will be used strictly in accordance with the Bank's personal data policies, a copy of which may be obtained by the applicant upon request. Unless otherwise instructed in writing by the applicant concerned, applicants may be considered for other suitable positions within the Bank and its related companies. The personal data of unsuccessful job applicants may be retained for a maximum of two years from the date when the job application is rejected and such data may be retained for a longer period if there is a subsisting reason that obliges the Bank to do so, after which the personal data will be destroyed.", "employment_types": ["Full Time", "Permanent"], "selling_points": ["Trading & settlement system projects", "5 yrs in business analysis/digital project manage", "Familiar with SFC/HKMA related trading system"], "locations": ["Sheung Wan"], "categories": ["Banking / Finance", "Dealing & Trading", "Equities / Capital Markets", "Information Technology (IT)", "IT Project Management / Team Lead"], "post_time": "2022-01-14T09:52:10Z", "salary": {"currency": null, "max": null, "min": null, "period": "monthly", "term": null}, "salary_visible": false, "title_keywords": ["business analyst"], "responsibilities": ["regulations", "provide support", "operations", "policies", "procedures", "ad hoc tasks", "business plans", "daily reports"], "requirements": {"degrees": ["university degree"], "majors": ["finance", "economics"], "languages": ["putonghua", "english", "chinese"], "language_level": ["fluency", "advantage", "proficiency"], "hard_skills": ["analytical skill", "dynamic", "bloomberg", "reason"], "soft_skills": ["novel", "analytical skill", "dynamic environment", "sensitive to figures", "stable", "creative"], "languages_combined": [{"language": "putonghua", "language_level": ["fluency"]}, {"language": "english", "language_level": ["proficiency", "fluency", "advantage"]}, {"language": "chinese", "language_level": ["proficiency", "fluency", "advantage"]}]}, "experience_required": {"duration": [], "field": []}}, {"job_id": "100003009048431", "location_code": "hk", "company": "Hang Seng Bank Ltd", "job_title": "Senior Dealer I, Foreign Exchange", "description": "Our client is an international investment institution and they are looking for a high calibre candidate to join the trading team for daily Operational support (with exposure in client-facing).\n\n\n\nResponsibilities\n\nProvide complete support to the front office for the smooth running of the desk\nEnsure timely input of trades into trading systems\nResolve any trade queries received internally and externally, and ensure any trade discrepancies are resolved in a timely manner\nKeep trade records up to date.\nUpdate real-time manual / electronic whiteboards with market data\nProvide input on various projects for brokers and traders\nProvide trade details to brokers and traders on a daily basis\nGive live quotes to traders through the messaging systems\nMonitor markets and follow financial news and developments\nUnderstand the underlying products being traded and keep up to date with knowledge of new products / procedures\nLiaise with clients, (via telephone and face to face) to understand the business objectives of your clients as to provide a reliable and efficient broking service\nDevelop new business with existing clients and onboard new clients following the correct process with the Client Onboarding team\u00a0\n\nRequirements\n\nSound years of working experience (Working in the financial industry is an advantage)\nEffectively bilingual, fluent Mandarin is a must\nStrong interest in financial markets\nExcellent communications skills for interacting with people passionately\nAble to work independently in a fast-paced and highly intense environment is an advantage\nWorking in the aviation industry is an advantage", "employment_types": ["Full Time", "Permanent"], "selling_points": [], "locations": ["Not Specified"], "categories": ["Banking / Finance", "Dealing & Trading"], "post_time": "2022-01-14T06:33:21Z", "salary": {"currency": null, "max": null, "min": null, "period": "monthly", "term": null}, "salary_visible": false, "title_keywords": ["dealer"], "responsibilities": ["liaise with clients", "develop new business", "systems", "monitor", "a timely manner", "procedures", "market data"], "requirements": {"degrees": [], "majors": [], "languages": ["mandarin"], "language_level": ["fluent"], "hard_skills": [], "soft_skills": ["work independently"], "languages_combined": [{"language": "mandarin", "language_level": ["fluent"]}]}, "experience_required": {"duration": [], "field": ["financial industry"]}}, {"job_id": "100003009046316", "location_code": "hk", "company": "Pacific Focus Consultancy Limited", "job_title": "Operations Support", "description": "Ref:SADS/EBSIP/110122DB/63\n\nResponsibilities\n\n\nProvide\u00a0dealing, trading and sales support services to the team,\u00a0including order placement, centralized dealing transactions, etc.\nProvide support for wealth management business generation; trade execution and reconciliation including unit trust, HK and overseas securities, futures and options, etc. accurately and efficiently\nAssist to follow up on trading account related documents with the wealth management specialists (the account managers), and conduct joint calls, if necessary\nFollow up with the account managers on pre and post trade documents to ensure all trade orders comply with the procedures, policies and regulatory requirements\nMonitor outstanding orders and margin risk control\nOther ad-hoc duties and projects assigned by the supervisor and management\nRequirements\n\nDiploma in Business or any related discipline\nMinimum 4 years\u2019 relevant working experience in securities dealing and sales support areas, preferably in banks or Independent Financial Advisor (IFA)\nHolder of SFC license for Type 1 regulated activity\nGood interpersonal skills and detail-oriented\nGood command of both written and spoken English, Chinese, and Putonghua\nWe offer a competitive remuneration package to the right candidate. If you are interested in the post, please send your resume together with\u00a0your present\u00a0and\u00a0expected salaries\u00a0by clicking\u00a0\u201cApply Now\u201d.\u00a0\n\n\n\nFor more information about China Everbright Securities International Company Limited, please visit\u00a0www.ebshk.com.\n\nWe are an equal opportunity employer and welcome applications from all qualified candidates. All applications will be treated in the strictest confidence. Personal data provided will be used for recruitment purposes only. The job applicant will assume all or any risks arising out of or in connection with the job application transmission process prior to our actual receipt of the same including but not limited to accidental or unauthorized loss or disclosure of personal information, to which we will not be responsible in any way.\n\nUnder the Personal Data (Privacy) Ordinance, you may request access to, and / or correction of your personal data in relation to your application. If you wish to do so, please email to us.", "employment_types": ["Full Time"], "selling_points": ["5-day work, attractive benefits", "Large scale international firm", "Great career exposure"], "locations": ["Wan Chai"], "categories": ["Banking / Finance", "Financial Services", "Dealing & Trading", "Order Processing & Operation / Settlement"], "post_time": "2022-01-13T10:25:38Z", "salary": {"currency": null, "max": null, "min": null, "period": "monthly", "term": null}, "salary_visible": false, "title_keywords": ["operations"], "responsibilities": ["provide support", "management", "control", "related documents", "policies", "regulatory requirements", "support services", "procedures", "monitor", "transactions", "ad-hoc duties"], "requirements": {"degrees": ["diploma"], "majors": ["business"], "languages": ["putonghua", "english", "chinese"], "language_level": ["good command"], "hard_skills": ["sales support", "sfc license"], "soft_skills": ["independent", "interpersonal skills", "detail-oriented"], "languages_combined": [{"language": "putonghua", "language_level": ["good command"]}, {"language": "english", "language_level": ["good command"]}, {"language": "chinese", "language_level": ["good command"]}]}, "experience_required": {"duration": ["minimum 4 years"], "field": ["securities", "sales support", "relevant working experience", "financial"]}}, {"job_id": "100003009043972", "location_code": "hk", "company": "Osmium Consulting Group Limited", "job_title": "Fixed Income Trader", "description": "Responsibilities:\n\nProvide professional advice and services to corporate and/or wholesale clients on FX price quotation, and execute foreign exchange dealing transactions;\nProvide SPOT FX and FX option price quotation and execute clients' orders;\nDevelop strategic plans for business and client development to achieve the sales target;\nComply to all legal and compliance codes and regulations, and is able to take remedial measures to minimize operational risk.\u00a0\n\nRequirements:\n\nDegree holder in Business, Finance, Economics or related discipline(s), with 2-5 years relevant\u00a0remittance or banking/financial working experience.\nAble to work in a fast-paced & dynamic environment, well-organized and with strong interpersonal communication and people management skill.\nExcellent strategic mindset with strong business acumen and broad business perspective.\nExcellent command of both spoken and written Cantonese, English and Mandarin.\nStrong PC skills in MS Office including Excel, Word and PowerPoint.\nCandidate with less experience will be considered as Junior Sales Dealer.\nWe offer 5-day workweek, career prospects and attractive package for the right candidate.\u00a0 If you would like to take the challenge to stretch your ability and form part of our team, please send your full career details, together with your current and expected salary by e-mail to us.\n\n\nFor further information, please visit our website: http://www.kvbgc.com\n\nInformation provided will be treated in the strictest confidence and used only for recruitment related purposes. All applications will be destroyed after 6 months. Only short-listed candidates will be contacted.", "employment_types": ["Full Time", "Permanent"], "selling_points": ["Fixed Income Trader", "Buy-side FI", "SFC License Type 9"], "locations": ["Central & Western Area"], "categories": ["Banking / Finance", "Dealing & Trading", "Equities / Capital Markets", "Asset Management"], "post_time": "2022-01-13T02:38:15Z", "salary": {"currency": null, "max": null, "min": null, "period": "monthly", "term": null}, "salary_visible": false, "title_keywords": [], "responsibilities": ["regulations", "strategic plans", "sales target", "quotation", "compliance", "transactions", "develop"], "requirements": {"degrees": ["degree holder"], "majors": ["finance", "business", "economics"], "languages": ["cantonese", "english", "mandarin"], "language_level": ["excellent"], "hard_skills": ["excel", "word", "acumen", "powerpoint", "dynamic", "pc skills", "ms office"], "soft_skills": ["dynamic environment", "well-organized", "communication", "business acumen", "interpersonal"], "languages_combined": [{"language": "cantonese", "language_level": ["excellent"]}, {"language": "english", "language_level": ["excellent"]}, {"language": "mandarin", "language_level": ["excellent"]}]}, "experience_required": {"duration": ["2-5 years"], "field": ["related", "finance", "business", "banking", "financial"]}}, {"job_id": "100003009040189", "location_code": "hk", "company": "KVB Trading (Hong Kong) Limited", "job_title": "Sales Dealer (FX)", "description": "Job Description\n\nSupport daily operation duties for all asset types (equities, fixed income, Futures, Swap, derivatives..etc.)\u00a0 including trade capture, settlement, corporate action processing, payment processing, distribution processing, cash management and forecasting\nReconcile cash and trade activity between the Trustee/Prime broker/custodian and portfolio accounting system daily, including daily activity break clearing.\nReconciles weekly facility and monthly position data between the Trustee and portfolio accounting system, including follow-up with the Trustee.\nProcess operational activity accurately for each portfolio investment in the portfolio accounting system\nMaintain direct communication with various internal departments to coordinate trading, settlement, ensure accurate and timely reporting, and maintain compliance with the policy.\nWork professionally with team and coworkers.\nOther projects and duties as assigned.\n\nRequirement\n\nUniversity degree holder at least, Graduate in Finance / Accounting are preferable\n1-2 year + solid experience in operational experience either in a custodial, trustee,\u00a0 asset management\nProduct knowledge on bonds, derivatives, equities, and swap\nExperience in handling NAV calculation on private funds, hedge funds\nSelf-motivated, Detail-Oriented, patient and responsible\nAble to work under pressure and good at time management\nProficient in VBA will be an advantage\nGood command of both written and spoken in English and Chinese\nImmediately Available is highly preferred", "employment_types": ["Full Time", "Permanent"], "selling_points": ["Provide professional services to clients", "Foreign exchange and remittance service", "Good business exposure and career development"], "locations": ["Admiralty"], "categories": ["Banking / Finance", "Dealing & Trading"], "post_time": "2022-01-12T01:48:09Z", "salary": {"currency": null, "max": null, "min": null, "period": "monthly", "term": null}, "salary_visible": false, "title_keywords": ["dealer", "sales"], "responsibilities": ["reporting", "management", "data", "compliance", "daily operation", "communication", "coordinate", "payment", "maintain", "forecasting"], "requirements": {"degrees": ["university degree"], "majors": ["finance", "accounting"], "languages": ["english", "chinese"], "language_level": ["good command"], "hard_skills": ["vba"], "soft_skills": ["self-motivated", "responsible", "detail-oriented", "patient", "time management", "work under pressure"], "languages_combined": [{"language": "english", "language_level": ["good command"]}, {"language": "chinese", "language_level": ["good command"]}]}, "experience_required": {"duration": ["1-2 year"], "field": ["asset management"]}}, {"job_id": "100003009044694", "location_code": "hk", "company": "Bitget Singapore", "job_title": "Regional Campaign and Assets Operations Manager(Remote)", "description": "REQUIREMENTS\n\nCandidates with 1-3 years working experience from any industries and or potential U /DSE / Diploma / ASSO / IVE / YIJIN FRESH GRADS who are interesting in FINANCIAL FIELDS are considered;\n\nSkillful knowledge in Excel;\n\nWilling to learn and to do attitude, sedate under pressure, attentive, reliable, hard-working and self-disciplined;\n\n9 hours daily SHIFT required, Mondays to Fridays only.\n\nJOB DESCRIPTION\n\nTo monitor and control trading risks;\n\nTo quote financial products\u2019 price and execute trading orders;\n\nTo handle clients\u2019 enquiries;\n\nTo prepare trading documents;\n\nNON-SALES role, no outdoor duties required.\n\nWe offer attractive benefits and remuneration package including first-tier working environment, 13 months salary, performance and discretionary bonus, 5 day work, full medical and dental insurance coverage scheme, prospective career promotion, education allowance, birthday allowance, free overseas sight-seeing trip etc. Interested parities please send your CV with current and expected salary by clicking \u201cAPPLY NOW\u201d.", "employment_types": ["Full Time"], "selling_points": [], "locations": ["Not Specified"], "categories": ["Banking / Finance", "Dealing & Trading"], "post_time": "2022-01-14T08:57:40Z", "salary": {"currency": null, "max": null, "min": null, "period": "monthly", "term": null}, "salary_visible": false, "title_keywords": ["operations"], "responsibilities": ["control", "insurance", "monitor"], "requirements": {"degrees": ["diploma", "dse"], "majors": [], "languages": [], "language_level": [], "hard_skills": ["excel"], "soft_skills": ["attentive", "under pressure", "willing to learn", "hard-working", "reliable"], "languages_combined": []}, "experience_required": {"duration": ["1-3 years"], "field": ["financial"]}}, {"job_id": "100003009039274", "location_code": "hk", "company": "Silver Talent Corporation Limited", "job_title": "Dealer (Double Pay+5 Days + FRESH Grads WELCOME)", "description": "\u00a0Ref:\u00a0VP/IA/130122DB/37\n\nResponsibilities\n\n\nAssist the Head of Internal Audit in overseeing and managing information technology audit function of the Group\nPrepare annual audit plan in particular for assessing the IT risks of the Group\nExecute the audit assignments in accordance with the approved annual audit plan and ensure the quality of audit work\nCommunicate with relevant parties on audit findings, ensure prompt follow-up actions on outstanding areas and coordinate with auditees for practicable and efficient control improvement measures\nProvide internal consultancy services on IT governance, security, internal controls and risk management procedures\nCoordinate with external auditors / consultants and regulatory bodies if necessary\u00a0\nRequirements\n\u00a0\nDegree holder in Information Technology or related discipline, with relevant professional qualifications such as CISA and / or HKICPA is highly preferred\nOver 8 years\u2019 external / internal IT audit and / or IT technical experience obtained from financial institutions\nExperience in leading, planning and executing risk-based IT-related internal audits and risk control assessments\nKnowledge of business operations and regulatory requirements in financial industry\nTechnical knowledge ofrisk and control in various IT domains such as IT infrastructure, Cybersecurity, SDLC as well as other key areas including BCP/IT-DR, project management, database and technology risk framework\nHands on experience in data analysis, data presentation and business intelligence (BI) using Excel, VBA, Python, etc.\nStrong communication skills,attentive to details and able to work independently\nGood command of both written and spoken English and Chinese (Cantonese and Putonghua) and possess good report writing skills\nWe offer a competitive remuneration package to the right candidate. If you are interested in the post, please send your resume together with your present and expected salaries by clicking \u201cApply Now\u201d.\u00a0\n\n\nFor more information about China Everbright Securities International Company Limited, please visit www.ebshk.com.\n\nWe are an equal opportunity employer and welcome applications from all qualified candidates. All applications will be treated in the strictest confidence. Personal data provided will be used for recruitment purposes only. The job applicant will assume all or any risks arising out of or in connection with the job application transmission process prior to our actual receipt of the same including but not limited to accidental or unauthorized loss or disclosure of personal information, to which we will not be responsible in any way.\n\nUnder the Personal Data (Privacy) Ordinance, you may request access to, and / or correction of your personal data in relation to your application. If you wish to do so, please email to us.", "employment_types": ["Full Time"], "selling_points": ["DEALING ROOM", "DOUBLE PAY", "5 DAYS"], "locations": ["Tsim Sha Tsui"], "categories": ["Banking / Finance", "Dealing & Trading"], "post_time": "2022-01-11T09:15:42Z", "salary": {"currency": null, "max": null, "min": null, "period": "monthly", "term": null}, "salary_visible": false, "title_keywords": ["dealer"], "responsibilities": ["communicate with", "control", "management", "internal audit", "annual audit", "quality", "audit", "coordinate with", "procedures", "plan", "external auditors"], "requirements": {"degrees": ["degree holder"], "majors": ["information technology"], "languages": ["cantonese", "putonghua", "english", "chinese"], "language_level": ["good command", "good"], "hard_skills": ["excel", "vba", "bi", "professional qualifications", "analysis", "writing skills", "project management", "sdlc", "python", "business intelligence", "hkicpa"], "soft_skills": ["communication skills", "work independently", "attentive to details", "writing skills", "project management", "hands on", "presentation"], "languages_combined": [{"language": "cantonese", "language_level": ["good command", "good"]}, {"language": "putonghua", "language_level": ["good command", "good"]}, {"language": "english", "language_level": ["good command", "good"]}, {"language": "chinese", "language_level": ["good command", "good"]}]}, "experience_required": {"duration": ["8 years"], "field": ["related", "audit", "data analysis", "it", "business", "financial institutions", "planning"]}}, {"job_id": "100003009045890", "location_code": "hk", "company": "China Everbright Securities International Company Limited", "job_title": "Vice President, Internal Audit (IT Audit)", "description": "The Role\n\nMiddle office role between front and back office to facilitate efficient and effective brokerage business flow.\n\nKey Accountabilities\n\nWork closely with settlement teams for trade and product support\nMaintain daily operation of website, announcement on products and trading updates\nLiaise with front and back office to ensure an efficient and effective daily business flow\nFacilitate the whole business process for products including equities, derivatives and OTC\n\nSkills & Experience\n\nDegree in finance or business-related disciplines\n1-3 years of experience in bank / brokerage\nSFC type 1 and 2 preferred\nStrong language skills, including written Chinese and spoken Mandarin\nExcellent communication and interpersonal skills\nAbility to multitask and prioritize workload\nStrong in MS Excel, Word and PowerPoint\n\nOther Information\n\nNotes to applicants:\n1. Please apply in strict confidence with full resume, academic record, current and expected salaries.\n2. The personal data provided will be used for consideration of recruitment only. All personal data of unsuccessful candidate will be destroyed within 24 months.\n3. Candidates with Enhanced Competency Framework (ECF): please state on the CV.\n\nAbout BOCI\n\nAs a leading investment bank in China and Hong Kong region, the investment banking arm of Bank of China, BOC International Holdings Limited (\u201cBOCI\u201d), is now seeking highly motivated, creative and success-oriented professional who would like to pursue the career in our group.\u00a0", "employment_types": ["Full Time", "Permanent"], "selling_points": [], "locations": ["Causeway Bay"], "categories": ["Banking / Finance", "Investment", "Dealing & Trading", "Wealth Management"], "post_time": "2022-01-13T09:02:27Z", "salary": {"currency": null, "max": null, "min": null, "period": "monthly", "term": null}, "salary_visible": false, "title_keywords": ["vice president"], "responsibilities": ["brokerage", "daily operation", "teams", "back office", "website", "communication", "maintain", "business process", "recruitment", "banking", "liaise with", "personal data"], "requirements": {"degrees": ["degree"], "majors": ["related disciplines", "finance", "business"], "languages": ["chinese", "mandarin"], "language_level": [], "hard_skills": ["ms excel", "word", "powerpoint"], "soft_skills": ["efficient", "confidence", "prioritize", "communication and interpersonal skills", "motivated", "ability to multitask", "creative"], "languages_combined": [{"language": "chinese", "language_level": []}, {"language": "mandarin", "language_level": []}]}, "experience_required": {"duration": ["1-3 years"], "field": ["brokerage"]}}, {"job_id": "100003009044825", "location_code": "hk", "company": "BOCI", "job_title": "Associate, Middle Office, Securities Brokerage", "description": "Junior Trading Analyst\n\nAt Eclipse, we monitor thousands of listed derivatives every day. Strong trading automation and analytics are crucial to ensure we capitalise on profitable opportunities. Our trading analysts are responsible for providing valuable tools along with data driven insights to enhance our trading. The successful candidate will be a junior member of the team based in our headquarters in Hong Kong.\n\nResponsibilities and Duties\u00a0\n\nWork with traders to identify and solve technical trading problems, and implement automated solutions\nWork with quants to conduct detailed trading research by collecting and analysing data from various sources\nWork with developers to improve the efficiency and algorithms of our in-house trading software\n\nWhat you offer\n\nBachelor's degree or higher in Mathematics, Engineering, Computer Science, Finance, or similar discipline\nDemonstrated quantitative and problem-solving abilities\nIntellectual curiosity and a genuine interest in trading and financial markets\nExperience in a \u201cgeneral purpose\u201d programming language - Python (preferred), Julia, R or Matlab\nExcellent written and verbal communication skills\nPreferred:\nexperience in the trading division of a proprietary trading company or bank\nexperience in data analysis or statistics, and SQL\nexperience using Excel and writing VBA\nexperience working in Linux environment\n\nWhat we offer\n\nTraining in derivatives pricing, trading strategies and systems\nA multi-cultural environment with reasonable work hours\nAn innovative company, encouraging the exploration of new technologies and ideas\nA flat management structure, where everyone\u2019s voice is valued\nHands-on experience in the most exciting part of the financial industry, with a direct impact on trading\n\nAll information provided will be treated in strict confidence and used solely for recruitment purposes.\nDue to the high number of responses that we receive, we are only able to respond to successful applicants.", "employment_types": ["Full Time"], "selling_points": ["Middle office role for our brokerage business", "1-3 years of securities experience", "Knowledge in business flow in securities"], "locations": ["Sheung Wan"], "categories": ["Banking / Finance", "Dealing & Trading", "Equities / Capital Markets"], "post_time": "2022-01-13T06:25:58Z", "salary": {"currency": null, "max": null, "min": null, "period": "monthly", "term": null}, "salary_visible": false, "title_keywords": ["associate"], "responsibilities": ["software", "data"], "requirements": {"degrees": [], "majors": [], "languages": [], "language_level": [], "hard_skills": [], "soft_skills": [], "languages_combined": []}, "experience_required": {"duration": [], "field": []}}, {"job_id": "100003009044607", "location_code": "hk", "company": "Eclipse Trading", "job_title": "Junior Trading Analyst", "description": "Job Responsibilities\n\n\nResponsible for formulating and implementing sales and marketing strategies to promote trade finance products to customers\nMaintain key customer list and monitor sales performance\nPrepare management reports on key account preference and market analysis\nPreparing product promotional and training materials for both internal and external parties\nJob Requirements\n\n\nUniversity graduate with major in business management, finance, economics or related disciplines\nMinimum 3 years of relevant banking experiences; Experience of trade finance product development is preferred\u00a0 \u00a0 \u00a0\nGood knowledge on CDCS/CITF/CSDG will be an advantage\nProficiency in MS Office applications, inclusive of Excel, Word, PowerPoint\nSelf-motivated with Excellent communication and negotiation skills\nStrong command of both written and spoken Chinese, including Putonghua\nCandidate with more experience may be considered as Associate Director.\n", "employment_types": ["Full Time", "Permanent"], "selling_points": ["Bachelor\u2019s degree in a quantitative discipline", "Training in derivatives pricing", "Competitive salary and bonus"], "locations": ["Causeway Bay"], "categories": ["Banking / Finance", "Analyst", "Dealing & Trading", "Equities / Capital Markets"], "post_time": "2022-01-13T04:49:41Z", "salary": {"currency": null, "max": null, "min": null, "period": "monthly", "term": null}, "salary_visible": false, "title_keywords": ["analyst", "junior"], "responsibilities": ["marketing strategies", "sales performance", "internal and external parties", "monitor", "management reports", "maintain", "market analysis"], "requirements": {"degrees": ["university graduate"], "majors": ["related disciplines", "finance", "business", "economics"], "languages": ["putonghua", "chinese"], "language_level": [], "hard_skills": ["business management", "excel", "word", "powerpoint", "ms office"], "soft_skills": ["communication", "self-motivated", "negotiation skills"], "languages_combined": [{"language": "putonghua", "language_level": []}, {"language": "chinese", "language_level": []}]}, "experience_required": {"duration": ["minimum 3 years"], "field": ["finance", "product development", "banking experiences"]}}, {"job_id": "100003009046678", "location_code": "hk", "company": "Industrial and Commercial Bank of China (Asia) Limited", "job_title": "Product Manager (Trade Finance - Product Sales)", "description": "\u00a0Ref:\u00a0SA/HS/120122DB/22\n\nResponsibilities\n\n\nParticipate in formulating and executing sales and marketing strategies for wealth management products\nSupport Corporate teams and provide front-line service to clients\nFacilitate sales and marketing activities to achieve sales targets and other corporate objectives\nParticipate in various marketing, promotion and customer retention activities and programs\nTake part in ad hoc projects and assignments, if needed\nRequirements\n\nDiploma or Degree holder in relevant discipline\nMinimum 5 years\u2019 work experience in financial industry with at least 3 years\u2019 relevant experience in front office or dealing desk preferred\nHolder of SFC licences for Type 1, Type 2 and Type 3 regulated activities and CIB licence\nKnowledge of wealth management and OTC products\nGood team player with excellent interpersonal and communication skills\nStrong sense of responsibility and able to work independently\nProficiency in MS Office applications\nGood command of both written and spoken English and Chinese. Fluency in Putonghua an advantage\nWe offer a competitive remuneration package to the right candidate. If you are interested in the post, please send your resume together with your present and expected salaries by clicking \u201cApply Now\u201d.\u00a0\n\n\nFor more information about China Everbright Securities International Company Limited, please visit www.ebshk.com.\n\nWe are an equal opportunity employer and welcome applications from all qualified candidates. All applications will be treated in the strictest confidence. Personal data provided will be used for recruitment purposes only. The job applicant will assume all or any risks arising out of or in connection with the job application transmission process prior to our actual receipt of the same including but not limited to accidental or unauthorized loss or disclosure of personal information, to which we will not be responsible in any way.\n\nUnder the Personal Data (Privacy) Ordinance, you may request access to, and / or correction of your personal data in relation to your application. If you wish to do so, please email to us.", "employment_types": ["Full Time", "Permanent"], "selling_points": [], "locations": ["Kwun Tong"], "categories": ["Banking / Finance", "Dealing & Trading"], "post_time": "2022-01-13T18:54:17Z", "salary": {"currency": null, "max": null, "min": null, "period": "monthly", "term": null}, "salary_visible": false, "title_keywords": ["sales", "product manager"], "responsibilities": ["management", "marketing strategies", "teams", "ad hoc projects", "executing"], "requirements": {"degrees": ["diploma", "degree holder"], "majors": [], "languages": ["putonghua", "english", "chinese"], "language_level": ["fluency", "advantage", "good command"], "hard_skills": ["ms office"], "soft_skills": ["communication skills", "good team player", "work independently", "sense of responsibility", "interpersonal"], "languages_combined": [{"language": "putonghua", "language_level": ["fluency", "advantage"]}, {"language": "english", "language_level": ["good command"]}, {"language": "chinese", "language_level": ["good command"]}]}, "experience_required": {"duration": ["at least 3 years", "minimum 5 years"], "field": ["financial industry", "relevant experience"]}}, {"job_id": "100003009043268", "location_code": "hk", "company": "China Everbright Securities International Company Limited", "job_title": "RM / Senior Associate to AVP, Corporate Team (Wealth Management Products)", "description": "Job Responsibilities\n\n\nResponsible for promoting RMB related business and increase the market share of RMB related products (including trade finance and other business areas) of the bank\nWork closely with various departments for business promotion and products management\nPrepare management reports on RMB business performance and market analysis\nPreparing product promotional and training materials for both internal and external parties\n\n\nJob Requirements\n\n\nUniversity graduate with major in business management, finance, economics or related disciplines\nMinimum 3 years of banking experience in trade finance or RMB related products experience in banking industry\nGood knowledge on trade finance and RMB related products, CDCS/CITF/CSDG will be an advantage\nProficiency in MS Office applications, inclusive of Excel, Word, PowerPoint\nSelf-motivated with Excellent communication and negotiation skills\nStrong command of both written and spoken Chinese, including Putonghua\nCandidate with more experience may be considered as Associate Director.\n", "employment_types": ["Full Time", "Permanent"], "selling_points": [], "locations": ["Causeway Bay"], "categories": ["Banking / Finance", "Investment", "Dealing & Trading", "Wealth Management"], "post_time": "2022-01-12T10:26:13Z", "salary": {"currency": null, "max": null, "min": null, "period": "monthly", "term": null}, "salary_visible": false, "title_keywords": ["senior associate", "wealth management"], "responsibilities": ["management", "market analysis", "internal and external parties", "management reports"], "requirements": {"degrees": ["university graduate"], "majors": ["related disciplines", "finance", "business", "economics"], "languages": ["putonghua", "chinese"], "language_level": [], "hard_skills": ["business management", "excel", "word", "powerpoint", "ms office"], "soft_skills": ["communication", "self-motivated", "negotiation skills"], "languages_combined": [{"language": "putonghua", "language_level": []}, {"language": "chinese", "language_level": []}]}, "experience_required": {"duration": ["minimum 3 years"], "field": ["related", "finance", "banking industry", "banking experience"]}}, {"job_id": "100003009035995", "location_code": "hk", "company": "Bright Smart Securities International (H.K.) Limited", "job_title": "Customer Service Officer", "description": "Responsibilities:\n\n\nExecute dealing orders for global securities and futures market;\nHandle daily phone/online enquiries and perform clients\u2019 account instructions;\nMonitor client\u2019s orders and margin level, conduct margin call when necessary;\nMatch daily transaction records and trade position and compile various trading reports;\nAssist in daily operation of dealing room and ad hoc duties.\u00a0\n\nRequirement & Qualifications:\n\n\nDiploma holder or above;\nHolder of SFC license RA1 and RA2 is an advantage;\nBasic knowledge in global stocks and futures trading;\nFamiliar with Sharp Point system is a plus;\nGood team player,\u00a0able to work under pressure\u00a0and willing to learn;\nCandidates with\u00a0less\u00a0experience will be considered as Trainee.\n\n\u00a0We Offer:\n\nCompetitive remuneration package\n5 Days Work & Bank Holidays\nAttendance Bonus\nMeal Allowance\nDiscretionary Bonus\nMedical Insurance\nOn the Job Training\n\nWe provide attractive remuneration package and fringe benefits for the right candidate.\n\nInterested parties please send detailed resume with current and expected salaries to\u00a0Human Resources Department by clicking\u00a0\"Apply Now\"\u00a0or\u00a0fax to: 2530 2218.\n\nAll information collected will be used for recruitment purpose only, only shortlisted candidates will be notified.\u00a0Welcome to visit our website:\u00a0http://www.bsgroup.com.hk\u00a0for more information.", "employment_types": ["Full Time", "Permanent"], "selling_points": [], "locations": ["Central"], "categories": ["Banking / Finance", "Investment", "Financial Services", "Dealing & Trading"], "post_time": "2022-01-10T09:02:29Z", "salary": {"currency": null, "max": null, "min": null, "period": "monthly", "term": null}, "salary_visible": false, "title_keywords": ["customer service officer"], "responsibilities": ["daily operation", "ad hoc duties", "monitor", "reports"], "requirements": {"degrees": ["diploma holder"], "majors": [], "languages": [], "language_level": [], "hard_skills": ["plus", "basic", "sfc license"], "soft_skills": ["good team player", "willing to learn", "work under pressure"], "languages_combined": []}, "experience_required": {"duration": [], "field": []}}, {"job_id": "100003009046104", "location_code": "hk", "company": "\u4ee5\u592a\u8b49\u5238\u6709\u9650\u516c\u53f8", "job_title": "Settlement Manager", "description": "Responsibilities\n\nHandle daily equities settlement tasks\nPerform settlement functions including trade matching, customers fund deposit and withdrawal, SI, corporate actions, and other CCASS operations\nAssist in system modification and UAT testing\nLiaise with brokers, in-house departments to follow up any issues and enquiry\nHandle ad-hoc projects as assigned\n\nRequirements\n\nDegree holder with 3-5 years relevant experience in the settlement of HK, China Connect & Global equities market\nFamiliar with the operation of CCASS and Hundsun settlement system\u00a0\nKnowledge in local regulatory and compliance guidelines in related issues is preferable\u00a0\nGood communication and interpersonal skills\u00a0\nProficiency in spoken and written Mandarin , Cantonese and English\u00a0", "employment_types": ["Full Time", "Permanent"], "selling_points": ["CCASS & DCASS", "Hundsun & 2Go", "HK & China Connect Global Equities Market"], "locations": ["Wan Chai"], "categories": ["Banking / Finance", "Dealing & Trading", "Equities / Capital Markets", "Order Processing & Operation / Settlement"], "post_time": "2022-01-13T09:37:41Z", "salary": {"currency": null, "max": null, "min": null, "period": "monthly", "term": null}, "salary_visible": false, "title_keywords": ["settlement manager"], "responsibilities": ["operations", "uat testing", "system modification", "liaise with", "ad-hoc projects"], "requirements": {"degrees": ["degree holder"], "majors": [], "languages": ["cantonese", "english", "mandarin"], "language_level": ["proficiency"], "hard_skills": ["ccass"], "soft_skills": ["communication and interpersonal skills"], "languages_combined": [{"language": "cantonese", "language_level": ["proficiency"]}, {"language": "english", "language_level": ["proficiency"]}, {"language": "mandarin", "language_level": ["proficiency"]}]}, "experience_required": {"duration": ["3-5 years"], "field": ["relevant experience"]}}, {"job_id": "100003009044749", "location_code": "hk", "company": "\u5546\u805a\u74b0\u7403\u6709\u9650\u516c\u53f8", "job_title": "Operation Manager (Crypto Exchange)", "description": "Job Descriptions\n\nBe responsible for cryptocurrency exchange, trade life cycle events, resolving queries\nProvide trade reports\nPerform ad hoc task as assigned\n\nJob Requirements\n\nDSE or above education\n3 years or above in daily trading operations on Cryptocurrency exchange, blockchain or financial industry\nStrong analytical skills and general knowledge of Cryptocurrency activity\nGood command of Cantonese, English and Mandarin\nDetail-minded, strong communication and problem-solving skills\nImmediately available is preferred\n\nWe offer attractive remuneration package with 5-days work week, medical insurance, double pay, attractive commission scheme and bank holidays to the right candidate.\u00a0 Interested parties, please email full resume with expected and current salary by clicking \u201cApply Now\u201d below.\u00a0\n\nAll personal data collected will be kept confidential and used for recruitment purpose only.\u00a0", "employment_types": ["Full Time"], "selling_points": [], "locations": ["Tsim Sha Tsui"], "categories": ["Banking / Finance", "Financial Services", "Dealing & Trading"], "post_time": "2022-01-13T06:20:14Z", "salary": {"currency": null, "max": null, "min": null, "period": "monthly", "term": null}, "salary_visible": false, "title_keywords": ["operation manager"], "responsibilities": ["ad hoc", "reports"], "requirements": {"degrees": ["dse"], "majors": [], "languages": ["cantonese", "english", "mandarin"], "language_level": ["good command"], "hard_skills": ["blockchain", "scheme", "analytical skills", "cryptocurrency", "problem-solving skills", "exchange"], "soft_skills": ["detail-minded", "problem-solving skills", "communication", "analytical skills"], "languages_combined": [{"language": "cantonese", "language_level": ["good command"]}, {"language": "english", "language_level": ["good command"]}, {"language": "mandarin", "language_level": ["good command"]}]}, "experience_required": {"duration": [], "field": []}}, {"job_id": "100003009042508", "location_code": "hk", "company": "China Tonghai Securities Limited", "job_title": "Associate / AVP / Vice President \u2013 Equity Capital Market", "description": "Job Responsibilities:\n\n\n\nAssess, structure and execute a wide range of Capital Market transactions, including but not limited, pre-IPO financing, IPO transactions, block trade, rights issues, new share issues, share placements, convertibles issues and other equity-linked transactions.\nPrepare documents for necessary internal approval.\nDevelop and expand client base including institutional fund houses, investment banks, listed companies and high-net-worth clients in local and PRC markets.\nPrepare business plans and pitch books to support the team in deal pitching.\nAssist roadshows and fund raising on Capital Market activities and ad hoc projects.\u00a0\n\nJob Requirements:\n\n\nBachelor degree holder with\u00a03 - 5 years of experience in capital market.\nHands-on experience in underwriting of Hong Kong IPO and Capital Market transactions (in particular, in the capacity of lead/sole underwriter/placing agent).\nReal-life experience in dealing with the exchange, the SFC and other brokers (in particular, submission to the exchange).\nSolid financial statement analysis, structuring and valuation skills.\nKnowledge in MS Excel formula and Bloomberg mnemonics.\nCFA level 1 is a plus.\nWorking knowledge in convertible securities is a plus.\nFluent written and oral Mandarin, Cantonese and English.\nAble to work as a team player while functioning independently.\nStrong initiative and follow through, organized, conscientious and efficient.\nProactive, efficient, and works well under pressure.\nGood connection with institutional clients is an advantage\nCandidates with more experience will also be considered\n\nWe offer attractive salary, benefits and 5-day workweek to the successful applicant. Please send your resume with present and expected salary to the Group Human Resources Manager. (Please quote the job reference number on the email subject line.)\u00a0\n\nPersonal Data collected will be used for recruitment purposes only.", "employment_types": ["Full Time", "Permanent"], "selling_points": ["5 days work at Central", "Education Allowance, Medical, Dental and Insurance", "Equity Capital Market experience"], "locations": ["Central"], "categories": ["Banking / Finance", "Financial Services", "Dealing & Trading", "Equities / Capital Markets"], "post_time": "2022-01-12T07:50:34Z", "salary": {"currency": null, "max": null, "min": null, "period": "monthly", "term": null}, "salary_visible": false, "title_keywords": ["vice president", "associate"], "responsibilities": ["business plans", "transactions", "develop", "client base", "ad hoc projects", "prepare documents", "support the team"], "requirements": {"degrees": ["bachelor degree holder"], "majors": [], "languages": ["cantonese", "english", "mandarin"], "language_level": ["fluent"], "hard_skills": ["plus", "bloomberg", "cfa", "analysis", "ms excel", "exchange"], "soft_skills": ["efficient", "organized", "oral", "independently", "under pressure", "work as a team", "hands-on", "conscientious", "proactive", "initiative"], "languages_combined": [{"language": "cantonese", "language_level": ["fluent"]}, {"language": "english", "language_level": ["fluent"]}, {"language": "mandarin", "language_level": ["fluent"]}]}, "experience_required": {"duration": ["3 - 5 years"], "field": ["underwriting"]}}, {"job_id": "100003009043266", "location_code": "hk", "company": "Harbridge Partners Limited", "job_title": "Head of Private Trust", "description": "Title:\u00a0 \u00a0 \u00a0 \u00a0 \u00a0 \u00a0 \u00a0 \u00a0 \u00a0 \u00a0 \u00a0 \u00a0 \u00a0Head of Private Trust\n\nLocation:\u00a0\u00a0\u00a0\u00a0\u00a0 \u00a0\u00a0\u00a0\u00a0\u00a0\u00a0\u00a0\u00a0\u00a0\u00a0 Hong Kong\n\nBackground: \u00a0\u00a0\u00a0\u00a0\u00a0\u00a0\u00a0\u00a0\u00a0\n\nOur client is an established Asian banking and financial services group with strong Asia presence and growth plans and is looking to hire Head of Private Trust positions.\n\nResponsibilities:\n\nFormulate the goals, objectives and business plan of the Private Trust business sector\nDesign and devise business plan effectively for promoting and securing trust services to high net worth private trust clients (both bank and non-bank channels)\nLead the team to ensure smooth delivery of trust administration and customer relationship work\nCollaborate and communicate with both internal and external stakeholders\nTrain and develop subordinates so that staff can perform up to the required standard and successors can be identified\nPerform ad-hoc assignments as required\n\nRequirements:\n\nDegree in Law, Accounting or business related disciplines, preferably with professional qualification such as HKCIS, CPA, TEP, ACCA\nMin 5 years of solid experience in private trust business with 3 years in managerial role preferred\nSound knowledge in trust set-up and routine administrative operation\nCapability to draw up effective marketing plan independently\nGood business acumen with innovative ideas\nMarketing experience in Mainland China market is an advantage\nFluency in both written and spoken English and Chinese, Putonghua is a must\nImmediately available is highly preferred\n\nWork Benefits/ Work Environment:\n\nGreat Career progression.\nGreat Training and Career Path\nGreat\u00a0MPF Pension Scheme\nGood Work Life Balance\nGreat working hours\n\nHarbridge Partners Limited\nEmployment Agency Licence:\u00a0 65522", "employment_types": ["Full Time", "Permanent"], "selling_points": ["Private Trust,Head,HKCIS,CPA,TEP ACCA,Lead Team,HK", "Formulate the goals,Objectives&Business plan", "Trust administration,Customer relationship work"], "locations": ["Central & Western Area"], "categories": ["Banking / Finance", "Financial Services", "Dealing & Trading", "Order Processing & Operation / Settlement"], "post_time": "2022-01-12T23:26:18Z", "salary": {"currency": null, "max": null, "min": null, "period": "monthly", "term": null}, "salary_visible": false, "title_keywords": [], "responsibilities": ["collaborate", "communicate with", "ad-hoc assignments", "design", "develop", "business plan", "administration"], "requirements": {"degrees": ["degree"], "majors": ["business", "related disciplines", "accounting", "law"], "languages": ["putonghua", "english", "chinese"], "language_level": ["fluency"], "hard_skills": ["cpa", "acca", "acumen"], "soft_skills": ["business acumen", "independently", "innovative"], "languages_combined": [{"language": "putonghua", "language_level": ["fluency"]}, {"language": "english", "language_level": ["fluency"]}, {"language": "chinese", "language_level": ["fluency"]}]}, "experience_required": {"duration": ["3 years", "min 5 years"], "field": ["managerial", "business", "marketing"]}}, {"job_id": "100003009033745", "location_code": "hk", "company": "OliveX (HK) Limited", "job_title": "Cryptocurrency Investment trader", "description": "Everyone at OliveX stands behind these core values:\n\nFun \u2013 when you are winning, you have more fun. Not just beer pong and chilled atmosphere. It\u2019s fun when you work hard and achieve something while laughing.\nFit \u2013 fit means no excess. Ties in with resourcefulness. Also, super PLUS if the person is into fitness\nFab \u2013 feeling fabulous means being confident without being arrogant, being fab means you are unafraid of other people misunderstanding you. Stand for something. Don\u2019t play it safe. Take a stance so people remember you.\n\nGiven our rapid business expansion, we are now hiring an Cryptocurrency Investment trader to support with overseeing the day-to-day crypto investment and other ad-hoc projects to help grow our market share in Asia Pacific Region. You will work closely with the Head of Group Finance and\u00a0to gain revenue for our company.\n\nWhat you will be doing\n\n\nConduct in-depth reviews and evaluation in the cryptocurrency currency such as USDT, USDC, ETH, sector by use of various valuation techniques and tools, statistical models, and quantitative analysis\nPrepare the crypto investment proposal and report\nAdvise the Finance team with investment strategies using crypto assets to make profitable strategic investment decisions to yield high ROIs on investment project portfolios\nMonitor the performance of crypto currency by conducting in -depth reviews and evaluation\nPrepare daily monitoring and monthly monitoring and reports on crypto portfolio investment results\nHandle other ad-hoc duties as assigned by the manager\nWho you are\nDegree holder in Accounting / Finance /Economics or related disciplines\nAt least 1-2 years experiences in trading experience preferably gained in FinTech companies managing portfolios\u00a0of crypto assets investments\nEnthusiasm in crypto currency market\nIntellectual curiosity and a genuine interest in trading and financial markets\nAbility to multi-task, organize, and prioritize work\nSelf-motivated with can do attitude and timely delivery of results\nGood command of both spoken and written English & Cantonese\nShort notice and immediately available is highly preferred\n\nWhat we offer\n\n\n\nWe offer an attractive remuneration package\n15 days of annual leave\nGroup medical and life insurance, personal accident insurance\nFlexible work from home schedule", "employment_types": ["Full Time", "Permanent"], "selling_points": ["Accounting career growth with listed company", "Young, dynamic & fun corporate culture", "5 Days Work Week, Work from Home Option"], "locations": ["Pok Fu Lam"], "categories": ["Banking / Finance", "Analyst", "Dealing & Trading"], "post_time": "2022-01-10T01:44:47Z", "salary": {"currency": null, "max": null, "min": null, "period": "monthly", "term": null}, "salary_visible": false, "title_keywords": [], "responsibilities": ["valuation", "investment strategies", "monthly monitoring", "ad-hoc duties", "analysis", "investment proposal", "finance team", "monitor the performance", "evaluation", "reports", "ad-hoc projects", "daily monitoring", "report"], "requirements": {"degrees": ["degree holder"], "majors": ["related disciplines", "finance", "accounting", "economics"], "languages": ["cantonese", "english"], "language_level": ["good command"], "hard_skills": ["no", "plus", "crypto", "crypto currency", "fun", "cryptocurrency", "analysis", "make", "safe", "rapid"], "soft_skills": ["confident", "self-motivated", "multi-task", "timely", "prioritize", "ad-hoc duties", "genuine"], "languages_combined": [{"language": "cantonese", "language_level": ["good command"]}, {"language": "english", "language_level": ["good command"]}]}, "experience_required": {"duration": ["at least 1-2 years"], "field": ["trading"]}}, {"job_id": "100003009039607", "location_code": "hk", "company": "Well Link Securities Limited", "job_title": "\u9999\u6e2f\u53ca\u7f8e\u570b\u80a1\u7968\u7d50\u7b97\u4e3b\u4efb", "description": "\u5de5\u4f5c\u8077\u8cac\uff1a\n1\u3001\u5c65\u884c\u7f8e\u80a1\u53ca\u6e2f\u80a1\u65e5\u5e38\u4ea4\u6613\u5de5\u4f5c\u8077\u80fd\uff0c\u78ba\u4fdd\u4ea4\u6613\u7d50\u7b97\u5de5\u4f5c\u53ca\u6642\u3001\u6e96\u78ba\u548c\u9ad8\u6548\u9032\u884c\uff1b\n2\u3001\u5728\u4e0a\u7d1a\u6307\u5c0e\u4e0b\uff0c\u6bcf\u65e5\u958b\u76e4\u524d\uff0c\u5c0d\u7576\u65e5\u4ea4\u6613\u9032\u884c\u9810\u5099\u5de5\u4f5c\uff1b\n3\u3001\u5728\u4ea4\u6613\u7d50\u7b97\u5f8c\uff0c\u5c0d\u6bcf\u5929\u4ea4\u6613\u9032\u884c\u8907\u76e4\u548c\u7e3d\u7d50\u5de5\u4f5c\uff1b\n4\u3001\u9700\u8981\u6280\u5de7\u3001\u6052\u5fc3\u3001\u8010\u5fc3\u3001\u7d30\u5fc3\u548c\u5c08\u6ce8\uff0c\u5c0d\u7f8e\u80a1\u548c\u6e2f\u80a1\u7684\u6ce2\u6bb5\u6027\u64cd\u4f5c\uff0c\u5177\u609f\u6027\u548c\u654f\u611f\u6027\uff1b\n5\u3001\u5584\u65bc\u7e3d\u7d50\u548c\u63d0\u5347\uff0c\u80fd\u5c0d\u7f8e\u80a1\u548c\u6e2f\u80a1\u7684\u6700\u65b0\u8da8\u52e2\u548c\u8b8a\u5316\uff0c\u53ca\u6642\u958b\u5c55\u898f\u5f8b\u7e3d\u7d50\uff1b\n6\u3001\u5177\u6311\u6230\u6027\u548c\u8da3\u5473\u6027\u5de5\u4f5c\u6c1b\u570d\uff0c\u80fd\u63d0\u5347\u500b\u4eba\u6295\u8cc7\u7d20\u990a\uff0c\u5f9e\u5e2b\u5f92\u5236\u57f9\u8a13\u4e0b\u64c1\u6709\u5ee3\u95ca\u7684\u8077\u696d\u767c\u5c55\u524d\u666f\uff0c\u57f9\u990a\u8d70\u5411\u672a\u4f86\u91d1\u9818\u7684\u5de5\u4f5c\u5e73\u81fa\uff1b\n7\u3001\u5c65\u884c\u5f8c\u81fa\u7cfb\u7d71\u7684\u65e5\u5e38\u7dad\u8b77\u548c\u64cd\u4f5c\u5de5\u4f5c\uff1b\n8\u3001\u5b8c\u6210\u4e0a\u7d1a\u5b89\u6392\u7684\u5176\u4ed6\u5de5\u4f5c\u4efb\u52d9\u3002\n\n\u5de5\u4f5c\u5730\u9ede\uff1a\u4e0a\u74b0\n\n\u4efb\u8077\u8981\u6c42\uff1a\n1\u3001\u5177\u6709\u4e00\u5e74\u4ee5\u4e0a\u76f8\u95dc\u5de5\u4f5c\u7d93\u9a57\u512a\u5148\n2\u3001\u77ad\u89e3\u9999\u6e2f\u548c\u7f8e\u570b\u80a1\u7968\u7684\u7522\u54c1\u8207\u7d50\u7b97\u77e5\u8b58\n3\u3001\u5177\u6709\u5927\u5b78\u5546\u79d1/\u91d1\u878d/\u7d93\u6fdf\u6216\u76f8\u95dc\u5c08\u696d\u7684\u5b78\u58eb\u5b78\u4f4d\n4\u3001\u7a4d\u6975\u4e3b\u52d5\uff0c\u826f\u597d\u6578\u5b57\u548c\u7d30\u7bc0\u610f\u8b58\n5\u3001\u719f\u7df4\u4f7f\u7528Word\u3001Excel\u53ca\u4e2d\u6587\u6587\u5b57\u8655\u7406\u80fd\u529b\n6\u3001\u638c\u63e1\u6d41\u5229\u7684\u7cb5\u8a9e\u548c\u666e\u901a\u8a71", "employment_types": ["Full Time"], "selling_points": ["\u4e86\u89e3\u6e2f\u80a1\u53ca\u7f8e\u80a1\u5e02\u5834", "\u5927\u5b78\u5546\u79d1/\u91d1\u878d/\u7d93\u6fdf\u6216\u76f8\u95dc\u5c08\u696d\u7684\u5b78\u58eb\u5b78\u4f4d", "\u5177\u6311\u6230\u6027\u548c\u8da3\u5473\u6027\u5de5\u4f5c\u6c1b\u570d"], "locations": ["Sheung Wan"], "categories": ["Banking / Finance", "Dealing & Trading"], "post_time": "2022-01-11T10:12:19Z", "salary": {"currency": null, "max": null, "min": null, "period": "monthly", "term": null}, "salary_visible": false, "title_keywords": [], "responsibilities": [], "requirements": {"degrees": [], "majors": [], "languages": [], "language_level": [], "hard_skills": [], "soft_skills": [], "languages_combined": []}, "experience_required": {"duration": [], "field": []}}, {"job_id": "100003009036038", "location_code": "hk", "company": "Grandly Financial Services Limited", "job_title": "Dealing /Customer Service Officer", "description": "Responsibilities Include:\n\nDealing and Risk-Control: Closely monitor global securities and futures markets and assist with market analysis, order execution, risk-control etc.\nCustomer Service(CS): Directly service clients to provide investment information, professional customer service, account opening, and client relationship management.\nMarket\u00a0Analysis:\u00a0:\u00a0Thoroughly\u00a0analyze\u00a0latest market developments and trends to produce research reports, investment recommendations, published presentations etc.\nComplete daily workflow and ad-hoc projects as assigned.\n\nRequirements\uff1a\n\n\nFluent in Cantonese, Mandarin and\u00a0English .\n\nDegree holder major in finance related disciplines.\n\nQuick learner and team player with great attitude.\n\nWork experience in the securities and futures industry highly preferred.\n\nFamiliarity with Ayers Trading System, Esunny Trading System and Bloomberg preferred.\nRecent graduates will be considered", "employment_types": ["Full Time"], "selling_points": ["SFC Type 1, 2 front office role", "Experienced professional team", "Fast growing platform with considerable salary"], "locations": ["Wan Chai"], "categories": ["Banking / Finance", "Financial Services", "Dealing & Trading", "Equities / Capital Markets"], "post_time": "2022-01-11T01:45:59Z", "salary": {"currency": null, "max": null, "min": null, "period": "monthly", "term": null}, "salary_visible": false, "title_keywords": ["customer service officer"], "responsibilities": ["control", "management", "account opening", "monitor", "presentations", "market analysis", "customer service", "reports", "ad-hoc projects"], "requirements": {"degrees": ["degree holder"], "majors": ["related disciplines", "finance"], "languages": ["cantonese", "english", "mandarin"], "language_level": ["fluent"], "hard_skills": ["bloomberg"], "soft_skills": ["team player", "quick learner"], "languages_combined": [{"language": "cantonese", "language_level": ["fluent"]}, {"language": "english", "language_level": ["fluent"]}, {"language": "mandarin", "language_level": ["fluent"]}]}, "experience_required": {"duration": [], "field": ["securities"]}}, {"job_id": "100003009031372", "location_code": "hk", "company": "Zeal Asset Management Limited", "job_title": "Dealing - Dealer", "description": "Job Description:\n\nHandle trade execution with high degree of accuracy and efficiency.\nMonitor portfolio cash activity and investment restrictions.\nResponsible for daily dealing operation.\nHandle inquiries across the team with respect of trading issue.\nPerform other non-trading related duties as assigned.\n\nRequirements:\n\nBachelor degree with major in Finance\nSound knowledge in Hong Kong, China A and US markets\nMinimum 3-6 years working experience\nObtain SFC license Type 1, 4, 9 or passed the HKSI Licensing Examination.\nWilling to work on night shift and public holiday.\nExcellent communication with fluent English, Mandarin and Cantonese as well as good command of written English and Chinese.\nA good team player with excellent working attitude\nAble to handle multi-task and work under high pressure environment.\nSelf-motivated, work independent and detail-oriented.\nProficient with Bloomberg, MS Excel and/or other programming languages will be an advantage.\n\nPlease email your resume together with a cover letter, current salary and your expected salary to us.\u00a0 Please also quote the applied position on the email subject.", "employment_types": ["Full Time"], "selling_points": [], "locations": ["Central"], "categories": ["Banking / Finance", "Dealing & Trading"], "post_time": "2022-01-07T19:20:38Z", "salary": {"currency": null, "max": null, "min": null, "period": "monthly", "term": null}, "salary_visible": false, "title_keywords": ["dealer"], "responsibilities": ["monitor"], "requirements": {"degrees": ["degree", "bachelor"], "majors": ["finance"], "languages": ["cantonese", "english", "chinese", "mandarin"], "language_level": ["excellent", "good command", "fluent"], "hard_skills": ["bloomberg", "hksi", "ms excel", "programming", "sfc license"], "soft_skills": ["good team player", "self-motivated", "multi-task", "independent", "detail-oriented", "communication", "work under high pressure"], "languages_combined": [{"language": "cantonese", "language_level": ["excellent", "good command", "fluent"]}, {"language": "english", "language_level": ["excellent", "good command", "fluent"]}, {"language": "chinese", "language_level": ["excellent", "good command", "fluent"]}, {"language": "mandarin", "language_level": ["excellent", "good command", "fluent"]}]}, "experience_required": {"duration": ["minimum 3-6 years"], "field": []}}, {"job_id": "100003009039326", "location_code": "hk", "company": "BOCI", "job_title": "Analyst, Treasury Dealing - Asset & Liability Management", "description": "The Role\n\nAnalyst, Treasury Dealing - Asset & Liability Management\n\nKey Accountabilities\n\nAssist in the Group's daily treasury functions which included and not limited to forecasting, monitoring and controlling cash management activities; FX & MM dealing;\nAssist in setting up, review & update, and the implementation of Group treasury related policies, guidelines, procedures and manuals;\nPrepare reports in relation to treasury dealing activities and/ or market news/ development;\nAssist in preparing materials for managerial meetings;\nAssist in maintaining back relationships;\nAssist in preparing business budgets and annual forecasts planning in relation to Group treasury;\nParticipate in ad hoc projects and strategic plans in relation to Group treasury; and\nSuch other duties as shall be directed by your superiors form time to time.\n\nSkills & Experience\n\nDegree holder in Economics/ Finance/ Information System/ Statistics or equivalent; with a recognized professional qualification (such as CFA, FRM or equivalent) preferred\nRelevant experience/ exposure in financial institutions an added advantage; fresh graduate will also be considered\nRelevant knowledge in FX & Money Markets;\nProficient in MS Office; Knowledge in VBA an added advantage\nA team player, self-starter, mature, detailed oriented and able to work under pressure; excellent figures sense\nExcellent interpersonal and communication skills\nGood command of spoken and written English and Chinese\n\nOther Information\n\nNotes to applicants:\n\nPlease apply in strict confidence with full resume, academic record, current and expected salaries.\nThe personal data provided will be used for consideration of recruitment only. All personal data of unsuccessful candidate will be destroyed within 24 months.\nCandidates with Enhanced Competency Framework (ECF): please state on the CV.\n\nAbout BOCI\n\nAs a leading investment bank in China and Hong Kong region, the investment banking arm of Bank of China, BOC International Holdings Limited (\u201cBOCI\u201d), is now seeking highly motivated, creative and success-oriented professional who would like to pursue the career in our group.", "employment_types": ["Full Time"], "selling_points": ["Group treasury", "FX & MM dealing", "Investment Banking"], "locations": ["Sheung Wan"], "categories": ["Accounting", "Admin & HR", "Clerical / Admin Staff", "Banking / Finance", "Dealing & Trading"], "post_time": "2022-01-11T09:25:51Z", "salary": {"currency": null, "max": null, "min": null, "period": "monthly", "term": null}, "salary_visible": false, "title_keywords": ["analyst"], "responsibilities": ["communication", "personal data", "work under pressure", "maintaining", "other duties", "implementation", "banking", "forecasting", "management", "review", "monitoring", "procedures", "budgets", "strategic plans", "guidelines", "policies", "ad hoc projects", "recruitment", "prepare reports", "planning"], "requirements": {"degrees": ["fresh graduate", "degree holder"], "majors": ["finance", "economics", "statistics"], "languages": ["english", "chinese"], "language_level": ["good command"], "hard_skills": ["vba", "cfa", "information system", "frm", "ms office"], "soft_skills": ["communication skills", "confidence", "detailed oriented", "mature", "motivated", "team player", "creative", "interpersonal", "work under pressure"], "languages_combined": [{"language": "english", "language_level": ["good command"]}, {"language": "chinese", "language_level": ["good command"]}]}, "experience_required": {"duration": [], "field": ["financial institutions", "relevant experience"]}}, {"job_id": "100003009038175", "location_code": "hk", "company": "Ethan Capital Management Limited", "job_title": "Senior Analyst- Finance and Operation", "description": "Responsibilities:\n\nAssist on daily operations including Trade transaction Reconciliation, Accounting and Compliance, etc.\nPerform daily position reconciliation, preparing payment, check the accuracy and completeness of transaction orders, monthly NAV statement of the funds, etc.\nPrepare monthly financial statement for the Company and liaise with auditors for annual audit.\nPrepare KYC documents and handle the enquiries from investors and other external parties.\nHandle ad-hoc tasks as assigned.\nRequirements:\nBachelor Degree in Accounting or Finance or related disciplines; CPA holder is highly preferable\nMinimum 3 years working experiences, prior working experiences in asset management / financial institution / Big-4 CPA firm is preferable\nMinimum 1 year working experience in trade reconciliation and settlement is highly preferable\nProficiency in MS Office (Word, Excel and PowerPoint)\nGood command of written and spoken English and Mandarin\nA team player with good analytical, problem-solving, communications and interpersonal skills\nCandidate with less experience will be considered as Analyst\nWe offer attractive remuneration and benefits. Interested, qualified candidates please send your full resume, stating present, expected salary and availability, to Human Resources Department, Ethan Capital Management Limited, Charoen Pokphand Group, 21st Floor, Fast East Finance Centre, 16 Harcourt Road, Hong Kong or\u00a0apply online\u00a0by clicking\u00a0\"Apply Now\".\n\nThe information provided in an application will only be used for the purpose of consideration for appointment by Charoen Pokphand Group.\u00a0Applicants not contacted within 8 weeks from the closing date may assume that their applications are unsuccessful.\u00a0 Unsuccessful applications will be kept for a maximum period of 24 months.\n\n\u00a0", "employment_types": ["Full Time"], "selling_points": ["Analyst, Finance and Operation", "Fund position reconciliation, settlement", "Administration"], "locations": ["Central"], "categories": ["Accounting", "Finance / Accounting Manager", "Financial Analyst", "Banking / Finance", "Dealing & Trading"], "post_time": "2022-01-11T05:51:20Z", "salary": {"currency": null, "max": null, "min": null, "period": "monthly", "term": null}, "salary_visible": false, "title_keywords": ["senior analyst"], "responsibilities": ["annual audit", "ad-hoc tasks", "compliance", "external parties", "payment", "daily operations", "kyc", "liaise with", "financial statement"], "requirements": {"degrees": ["degree", "bachelor"], "majors": ["related disciplines", "finance", "accounting"], "languages": ["english", "mandarin"], "language_level": ["good command"], "hard_skills": ["excel", "problem-solving", "word", "powerpoint", "cpa", "ms office"], "soft_skills": ["problem-solving", "team player", "interpersonal skills"], "languages_combined": [{"language": "english", "language_level": ["good command"]}, {"language": "mandarin", "language_level": ["good command"]}]}, "experience_required": {"duration": ["minimum 1 year", "minimum 3 years"], "field": ["cpa firm", "financial", "asset management"]}}, {"job_id": "100003009036763", "location_code": "hk", "company": "Industrial and Commercial Bank of China (Asia) Limited", "job_title": "FX Dealer (Night Shift), Global Markets (Treasury)", "description": "Job Responsibilities:\nCarry out routine FX dealing operation and achieve individual budget\nHandle client trade requests and orders, and manage portfolio risk within assigned limits\nPerform night shift duties from 6pm-4am or 10pm-8am\nProvide support to team members\nRequirements:\nDegree holder or above\nMinimum 1 years' relevant experience\nDedicated and willing to work on night shift\nHigh proficiency in professional computer applications\nFluent in both spoken and written English and Chinese, including Putonghua\nCandidates with less experiences will be considered for junior position", "employment_types": ["Full Time", "Permanent"], "selling_points": [], "locations": ["Central"], "categories": ["Banking / Finance", "Treasury", "Dealing & Trading", "Order Processing & Operation / Settlement"], "post_time": "2022-01-10T13:38:06Z", "salary": {"currency": null, "max": null, "min": null, "period": "monthly", "term": null}, "salary_visible": false, "title_keywords": ["dealer"], "responsibilities": ["provide support", "budget"], "requirements": {"degrees": ["degree holder"], "majors": [], "languages": ["putonghua", "english", "chinese"], "language_level": ["fluent"], "hard_skills": [], "soft_skills": [], "languages_combined": [{"language": "putonghua", "language_level": ["fluent"]}, {"language": "english", "language_level": ["fluent"]}, {"language": "chinese", "language_level": ["fluent"]}]}, "experience_required": {"duration": ["minimum 1 years"], "field": ["relevant experience"]}}, {"job_id": "100003009035601", "location_code": "hk", "company": "Platinum Broking Company Limited", "job_title": "BROKING SUPPORT", "description": "Responsibilities:\n\nLiaise with Sales and Research department to provide investment service including daily morning notes to clients.\nAssist research analysts in research report production by collecting and analyzing data generated from various external sources.\nFollow up several companies in one specific sector allocated by research head, draft daily news analysis, research reports and provide investment ideas within the coverage sector.\nMaintain and update internal databases including industry database, IPO database and clients database on regular basis.\nCollaborate with middle and back office departments to ensure the smooth operation of the Dealing room.\nEngage in ad-hoc requests from directors.\u00a0\n\nRequirement:\n\nUniversity graduates majored in quantitative or finance subjects.\nPrevious experience in research or broking support preferred.\nProficient in spoken and written English, Cantonese and Mandarin.\nPC literate with the ability to work under pressure and independently.\nFresh graduates will also be considered.\n\nOur company provide:\n\nMedical insurance (including spouse and children)\nDental insurance\nLife insurance\nPerformance bonus\nStudy leave\nBank Holiday\n\nWe offer competitive compensation package to the right candidate.\u00a0 Please click 'Apply Now'\u00a0to apply with a detailed resume to us together with your current and expected salary information.\n\n(All applications will be treated in strictly confidential. Applicants who are not invited for an interview within 2 months may consider that their applications are unsuccessful.)", "employment_types": ["Full Time", "Permanent"], "selling_points": [], "locations": ["Central"], "categories": ["Banking / Finance", "Financial Services", "Dealing & Trading", "Equities / Capital Markets"], "post_time": "2022-01-10T07:49:54Z", "salary": {"currency": null, "max": null, "min": null, "period": "monthly", "term": null}, "salary_visible": false, "title_keywords": [], "responsibilities": ["collaborate with", "ideas", "data", "ad-hoc requests", "analysis", "back office", "maintain", "reports", "databases", "database", "liaise with", "report"], "requirements": {"degrees": [], "majors": [], "languages": ["cantonese", "english", "mandarin"], "language_level": ["proficient"], "hard_skills": ["pc literate"], "soft_skills": ["independently", "work under pressure"], "languages_combined": [{"language": "cantonese", "language_level": ["proficient"]}, {"language": "english", "language_level": ["proficient"]}, {"language": "mandarin", "language_level": ["proficient"]}]}, "experience_required": {"duration": [], "field": ["research"]}}, {"job_id": "100003009035955", "location_code": "hk", "company": "IDS Medical Systems (Hong Kong) Company Limited", "job_title": "Finance Executive", "description": "Job\u00a0Responsibilities:\n\n\nMaintain accounting records, reports and files in an organized manner.\nTake on and manage ad-hoc financial assignments and handle other tasks as required by the superior.\nFiling and sorting of documents.\nResponsible for staff claims.\nMaintain account ledgers by verifying and posting account transaction.\nAssist in other accounting areas such as account receivables, account payables, fixed assets and bank reconciliations.\nResponsible for routine data processing and voucher input.\nPreparing the order payment of bank.\nAssisting the logistics department in reconciling discrepancies between accounting records and physical stock records.\nAssist in month end / interim / year end closing.\nAny other duties and responsibilities as and when assigned by immediate superior or management.\n\nQualifications:\n\nMinimum 2 years relevant experience.\nProficiency in MS Word, Excel formulas and experience in use of ERP system.\nUniversity graduated with Major in Accountancy, Finance or similar discipline or above.\nGood command of Cantonese & English.\nCan work independently or as part of team.\nStrong attention to details with high accuracy.\n\nWe offer comprehensive fringe benefits including medical, life and personal accident insurance to the right candidates. Interested parties, please submit your application by clicking Apply Now.", "employment_types": ["Full Time", "Permanent"], "selling_points": ["Minimum 2 or above of relevant experience", "Experience in sales distribution/ manufacturing", "Good exposure to accounting systems"], "locations": ["Shatin Area"], "categories": ["Accounting", "Accountant", "Accounting Clerk / Supervisor", "Banking / Finance", "Dealing & Trading"], "post_time": "2022-01-10T08:59:43Z", "salary": {"currency": null, "max": null, "min": null, "period": "monthly", "term": null}, "salary_visible": false, "title_keywords": ["executive"], "responsibilities": ["ad-hoc", "any other duties", "management", "bank reconciliations", "data processing", "other tasks", "payment", "maintain", "reports", "logistics"], "requirements": {"degrees": [], "majors": [], "languages": ["cantonese", "english"], "language_level": ["good command"], "hard_skills": ["excel", "erp system", "processing", "ms word"], "soft_skills": ["organized", "work independently", "responsible", "attention to details", "superior"], "languages_combined": [{"language": "cantonese", "language_level": ["good command"]}, {"language": "english", "language_level": ["good command"]}]}, "experience_required": {"duration": ["minimum 2 years"], "field": ["erp system", "relevant experience"]}}, {"job_id": "100003009050913", "location_code": "hk", "company": "Bank of Communications Co., Ltd. Hong Kong Branch", "job_title": "Relationship Manager (Financial Institutions Department)", "description": "Career Level\nMiddle\nQualification\nDegree\nYears of Experience\n8 years\nJob Type\nFull Time, Permanent\nJob Functions\nBanking / Finance, Corporate Banking, Treasury, Dealing & Trading", "employment_types": ["Full Time", "Permanent"], "selling_points": [], "locations": ["Not Specified"], "categories": ["Banking / Finance", "Corporate Banking", "Treasury", "Dealing & Trading"], "post_time": "2022-01-14T11:45:51Z", "salary": {"currency": null, "max": null, "min": null, "period": null, "term": null}, "salary_visible": false, "title_keywords": ["relationship manager"], "responsibilities": ["banking"], "requirements": {"degrees": ["degree"], "majors": [], "languages": [], "language_level": [], "hard_skills": [], "soft_skills": [], "languages_combined": []}, "experience_required": {"duration": [], "field": []}}, {"job_id": "100003009039865", "location_code": "hk", "company": "Industrial and Commercial Bank of China (Asia) Limited", "job_title": "Securities Product Development  - Securities Business Department", "description": "Responsibilities:\n\nConduct research and bring in new fin-tech concepts on securities products\nEngage in projects on securities products enhancement.\nResponsible for planning, directing and coordinating activities of cross teams to deliver product enhancements in accordance with the department strategic plan\nWork closely with parties to understand product features, operation flow and liaise with parties on development and implementation\nProvide training to related parties\nAssists in developing and manage the project schedule to achieve milestones, deliverable and timeline\nAssists in developing internal policies and procedures\nRequirements:\n\nUniversity graduate with major in Business Administration/Finance/Information Technology/Computer Science or related disciplines\n2-5 years of experience in product management and development with sound knowledge in Banking and Finance, especially in Securities (Cash/Margin) products would be an advantage\nExperience in working in Fintech, e-Commerce related tech companies will also be considered\nGood Communication, Interpersonal and analytical skill\nAbility to work independently and under pressure with efficiency\nGood Time and project management skills to handle multiple task concurrently", "employment_types": ["Permanent"], "selling_points": [], "locations": ["Kwun Tong"], "categories": ["Banking / Finance", "Retail Banking", "Dealing & Trading"], "post_time": "2022-01-11T12:51:29Z", "salary": {"currency": null, "max": null, "min": null, "period": null, "term": null}, "salary_visible": false, "title_keywords": ["product development"], "responsibilities": ["provide training", "policies", "teams", "implementation", "developing", "procedures", "schedule", "plan", "liaise with", "conduct research", "planning"], "requirements": {"degrees": ["university graduate"], "majors": ["business administration", "finance", "information technology", "related disciplines", "computer science"], "languages": [], "language_level": [], "hard_skills": ["project management", "analytical skill", "e-commerce"], "soft_skills": ["analytical skill", "work independently", "under pressure", "project management skills", "communication", "handle multiple task", "interpersonal"], "languages_combined": []}, "experience_required": {"duration": ["2-5 years"], "field": ["e-commerce", "related", "development", "finance", "tech", "product management", "banking", "securities"]}}, {"job_id": "100003009042404", "location_code": "hk", "company": "SALT Consulting International Company Limited", "job_title": "FX Product Manager, Bonds Trader, Bonds Sales, FX dealers, ALM trader", "description": "We are inviting applications for a number of Bank Openings.\n\nWe are assisting our Banking clients in recruiting\n\nFX Product Manager\nBonds Sales\nBonds Trader\nFX dealers\nALM Trader\n\nCandidates with relevant experience are welcome to apply.", "employment_types": ["Full Time"], "selling_points": ["FX traders / FX Product Manager", "Bonds dealer,", "Bonds Sales"], "locations": ["Central"], "categories": ["Banking / Finance", "Dealing & Trading"], "post_time": "2022-01-12T07:19:52Z", "salary": {"currency": null, "max": null, "min": null, "period": "monthly", "term": null}, "salary_visible": false, "title_keywords": ["sales", "product manager"], "responsibilities": ["banking"], "requirements": {"degrees": [], "majors": [], "languages": [], "language_level": [], "hard_skills": [], "soft_skills": [], "languages_combined": []}, "experience_required": {"duration": [], "field": ["relevant experience"]}}, {"job_id": "100003009038850", "location_code": "hk", "company": "Ambition", "job_title": "AVP - Product Control", "description": "Top-tier Investment Bank\nExcellent package and benefits\nOpen to big4\n\nOur client, a top-tier Investment Bank with strong business operations across the globle, is looking for a Product Controller in AVP level to support their business.\n\nReporting to Executive Director, Product Control, you are responsible for the following but not limited to:\n\nSpecialise in Equities in the APAC markets\nPrepare daily P&L and balance sheet report and ensure the accuracy of trade bookings\nConduct FOBO reconciliations and resolve any related issues on timely basis\nReview risk profiles, booking methodologies, as well as valuation models for complex structured trades\nLiaise with internal stakeholders to drive control and efficiency improvements\n\nTo qualify, individuals must possess:\n\nUniversity degree holder in Accounting or equivalent disciplines with professional accounting qualification\nMinimum 5 years of relevant experience, preferably with Equities experience\nStrong interpersonal, communication and presentation skills\nExcellent communication skills with fluency in both Chinese and English\nStrong analytic skills and control mindset\nImmediately available is preferred\n\nInterested parties, send your updated resume to rita.lee@ambition.com.hk or click \"Apply Now\".\n\nOnly shortlisted candidates would be notified.\n\n#LI-BF\n\n#BUILDINGBETTERFUTURES\n\nIf this job isn't quite right for you, but you know someone who would be great at this role, why not take advantage of our referral scheme? We offer HKD1000 in Apple gift cards for every referred candidate who we place in a role. Terms & Conditions Apply. https://www.ambition.com.hk/refer-a-friend", "employment_types": ["Full Time", "Permanent"], "selling_points": ["Top-tier Investment Bank", "Excellent package and benefits", "Immediately available preferred"], "locations": ["Not Specified"], "categories": ["Banking / Finance", "Dealing & Trading", "Equities / Capital Markets", "Others"], "post_time": "2022-01-11T07:56:28Z", "salary": {"currency": null, "max": null, "min": null, "period": "monthly", "term": null}, "salary_visible": false, "title_keywords": [], "responsibilities": [], "requirements": {"degrees": [], "majors": [], "languages": [], "language_level": [], "hard_skills": [], "soft_skills": [], "languages_combined": []}, "experience_required": {"duration": [], "field": []}}, {"job_id": "100003009037587", "location_code": "hk", "company": "ConnectedGroup Limited", "job_title": "Associate, Trade Surveillance (12-month Contract)", "description": "Our Client is one of the world's major financial institutions with strong presence in Hong Kong market operating to cover a range of service for diverse products, including, equity, securities, derivatives, etc.\n\nYou will be joining its Operation Department and working in a highly international and dynamic environment.\n\nResponsibilities:\n\nPerform daily surveillance alerts and reports generated in SMARTS system for equities and derivatives products\nInvestigate trading activities and suspicious behaviors, and take part in market surveillance projects\nReview trading activities that are complying with trading rules, clearing rules and other regulatory policies\nCommunicate and interact with stakeholders, participants, external vendors and internal business units on surveillance domain\n\nRequirements:\n\nBachelor's Degree in Finance, Business Administration, or related disciplines\nWorking experience in financial institutions, with strong understanding in securities and derivatives markets\nExperience in trade surveillance and reporting system, i.e. SMARTS\nExperience in front office, middle office, risk management role, etc. with strong understanding in trade processing & operation is a plus\nGood command of written and spoken English and Chinese (Cantonese and Mandarin)\n\nFor those who are interested, please submit your latest profile (in WORD Format) to raman.hong@connectedgroup.com. Only qualified candidates will be contacted.\n\nFor more job opportunities, please visit our web-site: www.connectedgroup.com.", "employment_types": ["Full Time", "Contract"], "selling_points": ["Trade Operations Control", "Multi-national Environment", "Chance for Conversion to Perm"], "locations": ["Not Specified"], "categories": ["Banking / Finance", "Dealing & Trading", "Order Processing & Operation / Settlement", "Risk Management"], "post_time": "2022-01-11T03:13:24Z", "salary": {"currency": null, "max": null, "min": null, "period": "monthly", "term": null}, "salary_visible": false, "title_keywords": ["associate"], "responsibilities": ["policies", "review", "reports"], "requirements": {"degrees": ["degree", "bachelor"], "majors": ["related disciplines", "finance", "business administration"], "languages": ["cantonese", "english", "chinese", "mandarin"], "language_level": ["good command"], "hard_skills": ["plus", "processing", "word", "web"], "soft_skills": [], "languages_combined": [{"language": "cantonese", "language_level": ["good command"]}, {"language": "english", "language_level": ["good command"]}, {"language": "chinese", "language_level": ["good command"]}, {"language": "mandarin", "language_level": ["good command"]}]}, "experience_required": {"duration": [], "field": ["risk management", "financial institutions", "securities"]}}, {"job_id": "100003009039226", "location_code": "hk", "company": "Conners Consulting Limited", "job_title": "VP/SVP/AD of Institutional Sales (IANG is welcome, Native Mandarin, 3 headcounts)", "description": "Our client, a well-established investment firm to invite high caliber candidates to join their company.\n\nResponsibilities:\n\nLeading Institutional Sales team for daily operations;\nMaintain and build the business relationship with the above institutional accounts;\nProvide research service to clients, including market updates, arrange conference call and collect client\u2019s feedback;\nCoordinate roadshow and corporate access for the above clients;\nMaintain smooth operations and adhere to stringent procedures and high standard of compliance;\nReview client feedback periodically and propose a continuous improvement plan to enhance client satisfaction.\n\nRequirements:\n\nAt least 8-year institutional sales trading experience; \u00a0\nDegree in Economics, Finance or Business related disciplines;\nIndependent, attentive to details, and highly motivated;\nCustomer-oriented and proactive with effective communications skills;\nGood team player with excellent interpersonal skills;\nExcellent command of English and Chinese, Native Mandarin is preferred;\n\nTo apply, please send your detailed resume or contact Boei Yan at 3460 2012 for a confidential discussion.\nOnly shortlisted candidates will be notified.\u00a0\nApplicants who are not contacted within two weeks may consider their applications unsuccessful.\nAll data collected will be used for recruitment purpose only & will be used strictly confidential.\n\nConners Consulting Limited 2005 Kai Tak Commercial Building 317 Des Voeux Road Central Hong Kong\nTel: (852) 3996 8090\u00a0 \u00a0 \u00a0 \u00a0\u00a0\nWebsite:\u00a0http://www.connersconsulting.com/\u00a0", "employment_types": ["Full Time", "Permanent"], "selling_points": ["Leading Institutional Sales team", "Maintain existing institutional client", "Native Mandarin, IANG is welcome"], "locations": ["Central"], "categories": ["Banking / Finance", "Investment", "Dealing & Trading", "Equities / Capital Markets"], "post_time": "2022-01-11T09:05:42Z", "salary": {"currency": null, "max": null, "min": null, "period": "monthly", "term": null}, "salary_visible": false, "title_keywords": ["sales"], "responsibilities": ["operations", "compliance", "procedures", "review", "coordinate", "daily operations", "maintain", "sales team", "plan"], "requirements": {"degrees": ["degree"], "majors": ["business", "finance", "related disciplines", "economics"], "languages": ["english", "chinese", "mandarin"], "language_level": ["native", "excellent"], "hard_skills": [], "soft_skills": ["good team player", "independent", "attentive to details", "customer-oriented", "motivated", "interpersonal skills", "proactive", "detailed"], "languages_combined": [{"language": "english", "language_level": ["native", "excellent"]}, {"language": "chinese", "language_level": ["native", "excellent"]}, {"language": "mandarin", "language_level": ["native", "excellent"]}]}, "experience_required": {"duration": ["at least 8-year"], "field": ["trading", "institutional sales"]}}, {"job_id": "100003009039864", "location_code": "hk", "company": "Industrial and Commercial Bank of China (Asia) Limited", "job_title": "Compliance Manager (Securities Business)", "description": "Responsibilities:\n\nEvaluate securities business activities and products to identify any potential compliance risk and operational risk\nDisseminate laws and regulations issued by regulators and coordinate gap analysis with business units\nHandle compliance-related requests and/or reporting requirements\nCollaborate with business/ operations teams to establish sound internal controls to mitigate the associated risks\nWork with group compliance to keep abreast of and adhere to the updated group policies and requirements\nWork with internal parties to facilitate regulatory examinations\nReply to questionnaires, surveys, investigations and other regulatory enquiries\nPrepare training to and promote compliance awareness among colleagues\nHandle ad-hoc projects as assigned\nRequirements:\n\nUniversity graduate with major in Business, Accounting, Finance, Law or related disciplines\nMinimum 3 years experience in Compliance, Internal Control, Risk Management, or internal Audit in Financial Industry\nHolder of HKSI Paper: 1, 7 and 8 is preferable\nFamiliar with Banking Ordinance, SFO and relevant rules, codes and guidelines issued by HKMA and SFC\nWell-verse in Regulatory requirements such as HKMA and SFC\nAbility to work independently and work under pressure efficiently\nAnalytical with attention to details\nGood command of verbal and written Chinese and English (including Putonghua)", "employment_types": ["Permanent"], "selling_points": [], "locations": ["Kwun Tong"], "categories": ["Banking / Finance", "Dealing & Trading", "Professional Services", "Legal & Compliance"], "post_time": "2022-01-11T12:50:31Z", "salary": {"currency": null, "max": null, "min": null, "period": null, "term": null}, "salary_visible": false, "title_keywords": ["compliance manager"], "responsibilities": ["regulations", "reporting", "collaborate with", "operations", "analysis", "compliance", "teams", "policies", "evaluate", "coordinate", "internal parties", "ad-hoc projects", "business activities"], "requirements": {"degrees": ["university graduate"], "majors": ["law", "finance", "related disciplines", "business", "accounting"], "languages": ["putonghua", "english", "chinese"], "language_level": ["good command"], "hard_skills": ["hkma", "hksi paper", "internal control", "sfo", "codes"], "soft_skills": ["work independently", "attention to details", "work under pressure"], "languages_combined": [{"language": "putonghua", "language_level": ["good command"]}, {"language": "english", "language_level": ["good command"]}, {"language": "chinese", "language_level": ["good command"]}]}, "experience_required": {"duration": ["minimum 3 years"], "field": ["risk management", "compliance", "financial industry", "audit"]}}, {"job_id": "100003009038699", "location_code": "hk", "company": "Spidernet Recruitment Services", "job_title": "Sales Assistant / Client Service Officer (Private Bank)", "description": "Requirement\u00a0\u00a0\u00a0 \u00a0 \u00a0 \u00a0\u00a0\n\nDegree holder with fluent spoken English and Mandarin\n3 -6 yrs Sales Assistant / RM Assistant experience in Private Bank / Wealth Management to serve High Net Worth Clients\nStrong investment product knowledge / advisory Service / account opening\u00a0\nKnowledge in Risk management / Legal & Regulatory in an advantage\nJob Purpose\n\n\nTo provide Sales and administrative services to clients and Relationship Manager in relation to client onboarding, investments and transactions by coordinating between the relevant support and operations functions\n\nResponsibilities\n\nHandle administrative work for Relationship Managers and liaise with relevant departments to execute transactions\nAnswer queries from RMs on transactional activity, operations, systems and resolve successfully\nAssist RMs in marketing and executing investment products\nAssist RMs in monitoring clients'position\nHandle all client documents and reporting comply with internal process standards\nHighlight suspicious activities/behavior of clients and staff e.g. account\u00a0irregularities .Attend all Private Bank Compliance and other training\nTo alert and assist RMs in marketing investment products whenever appropriate\nTo play a significant role in minimizing operational losses Handle clients' enquiries\u00a0/needs\u00a0and assist in servicing their requirement\nUnderstand the Bank's CDD/AML framework.\n\u00a0Highlight any suspicious transactions to RM's,team leader's and Compliance.\nAssist RMs in preparing information /documentation for COD submission\nTo establish good rapport with clients and service their needs effectively and on a timely basis\nTo input the deadline to the systems or raise appropriate deal tickets and complete the task\u00a0at high\u00a0efficiency,\u00a0high accuracy,fast speed and minimal errors\nSupport for RMs when they are away from office\nAble to update the spreadsheet of the clients'positions\n\nAttractive remuneration and fringe benefits will be offered to the successful candidate.\n\nInterested candidates should apply with detailed resume, present and expected salaries by clicking the Apply Now button.\n\nAll information received will be treated in strict confidence and used for recruitment purpose only.\n\nOnly shortlisted candidates will be notified.\n\n\n", "employment_types": ["Full Time", "Permanent"], "selling_points": ["Degree, fluent English and Mandarin, HKSI Type 1", "3 yrs Sales Assistant exp in Private Bank", "Solid exp to serve high net worth clients"], "locations": ["Central"], "categories": ["Banking / Finance", "Investment", "Private Banking", "Dealing & Trading"], "post_time": "2022-01-11T07:39:31Z", "salary": {"currency": null, "max": null, "min": null, "period": "monthly", "term": null}, "salary_visible": false, "title_keywords": ["officer", "sales assistant"], "responsibilities": ["reporting", "documentation", "irregularities", "administrative work", "aml", "operations", "cdd", "systems", "monitoring", "compliance", "transactions", "executing", "liaise with"], "requirements": {"degrees": ["degree holder"], "majors": [], "languages": ["english", "mandarin"], "language_level": ["fluent"], "hard_skills": ["account opening"], "soft_skills": [], "languages_combined": [{"language": "english", "language_level": ["fluent"]}, {"language": "mandarin", "language_level": ["fluent"]}]}, "experience_required": {"duration": [], "field": ["management"]}}, {"job_id": "100003009042457", "location_code": "hk", "company": "Bank of Communications Trustee Limited", "job_title": "Fund Administrator, Transfer Agency Team", "description": "Key Responsibilities:\n\nPerform settlement functions including investor subscription and redemption, dividend distribution\nPerform client account opening and conduct KYC (know your client) / AML (Anti-Money Laundering) checking\nPerform order processing and data input and product master update\nSupport the on-going in-house system enhancement and improvement\nPerform ad-hoc assignments as required\n\nJob Requirements:\n\nDiploma in business related disciplines with minimum 1 year\u2019s working experience in banking or financial services industry\u00a0 \u00a0\nGood understanding in bank / fund operations is preferable\nSelf-motivated, detail-oriented, ability to work independently and under pressure\nFresh graduate in business related disciplines may also be considered\nProficiency in PC skills including Microsoft Word, Excel and PowerPoint\nGood command of Chinese and English (Putonghua is preferred)\nImmediately available is highly preferred\n\n\n", "employment_types": ["Full Time", "Permanent"], "selling_points": ["Perform ad-hoc assignments as required", "Diploma in business related", "1 year\u2019s working experience"], "locations": ["Not Specified"], "categories": ["Banking / Finance", "Dealing & Trading", "Fund Management", "Order Processing & Operation / Settlement"], "post_time": "2022-01-12T07:37:31Z", "salary": {"currency": null, "max": null, "min": null, "period": "monthly", "term": null}, "salary_visible": false, "title_keywords": ["administrator"], "responsibilities": ["aml", "account opening", "ad-hoc assignments", "checking", "data input", "order processing", "kyc"], "requirements": {"degrees": ["diploma", "fresh graduate"], "majors": ["related disciplines", "business"], "languages": ["putonghua", "english", "chinese"], "language_level": ["good command"], "hard_skills": ["excel", "pc skills", "microsoft word", "powerpoint"], "soft_skills": ["self-motivated", "under pressure", "work independently", "detail-oriented"], "languages_combined": [{"language": "putonghua", "language_level": ["good command"]}, {"language": "english", "language_level": ["good command"]}, {"language": "chinese", "language_level": ["good command"]}]}, "experience_required": {"duration": ["minimum 1 year"], "field": ["related", "financial services industry", "business", "banking"]}}, {"job_id": "100003009032104", "location_code": "hk", "company": "Emperor Capital Group", "job_title": "Investment Officer (Securities and Futures - Dealing/ Trader)", "description": "Job Duties\n\nResponsible for executing variety investment orders includes global securities and futures, bonds, funds etc. in efficient and accurate manner\nAssist to conduct trade surveillance\nPerform risk control against clients\u2019 account margin level, work closely with Credit Risk Control team\nLiaise with counterparties in executing trade orders\nProvide general supports to clients\u2019 enquiries\nParticipate in daily operations\nParticipate in different projects and assigned ad hoc tasks\nRequirments\n\nHigher diploma or above in Finance or related discipline\n1 year relevant experi`ence (with solid experience in dealing desk will be an advantage)\nHolder of SFC license RA1 and RA2 or equivalent\nProficient in written & spoken English and Chinese\u00a0\nNight shift and work on public holidays is required\nFresh graduates are welcome\n\n\n\nWe offer\u00a05-day-work\u00a0week\u00a0with competitive remuneration and benefit packages to the right candidate. Interested parties please send your application letter, resume, expected salary and availability to Human Resources Department, 28/F, Emperor Group Centre, 288 Hennessy Road, Wanchai, Hong Kong or\u00a0by clicking the\u00a0Apply Now\u00a0button below.\n\nWe are an equal opportunity employer & welcome applications from all qualified candidates. The information provided will be treated in strict confidence & be used only for consideration of your application for relevant / similar posts within the Emperor Group. Applicants not hearing from us within four weeks may consider their applications unsuccessful. We may retain the unsuccessful applications for a maximum period of\u00a024 months", "employment_types": ["Full Time", "Permanent"], "selling_points": ["Welcome new joiner to the financial field", "Exposure to variety of global investment products", "Challenging job in the fast changing market"], "locations": ["Wan Chai"], "categories": ["Banking / Finance", "Investment", "Financial Services", "Dealing & Trading"], "post_time": "2022-01-07T10:52:27Z", "salary": {"currency": null, "max": null, "min": null, "period": null, "term": null}, "salary_visible": false, "title_keywords": ["officer"], "responsibilities": ["control", "ad hoc tasks", "daily operations", "executing", "liaise with"], "requirements": {"degrees": ["higher diploma or above"], "majors": ["finance"], "languages": ["english", "chinese"], "language_level": ["proficient"], "hard_skills": ["sfc license"], "soft_skills": [], "languages_combined": [{"language": "english", "language_level": ["proficient"]}, {"language": "chinese", "language_level": ["proficient"]}]}, "experience_required": {"duration": ["1 year"], "field": []}}, {"job_id": "100003009036761", "location_code": "hk", "company": "Industrial and Commercial Bank of China (Asia) Limited", "job_title": "Senior Global Markets Sales, Fixed Income", "description": "Job Responsibilities\nExplore new Fixed Income end clients and assist OIC to complete on-boarding process if necessary\nClosely Cooperate with Fixed Income trading team to provide trading services to end clients\nHandle daily fixed income transactions and meet budget and Other KPI\nCommunicate with Institutional Banking RM and Corporate Banking RM to provide marketing assistance and expertise if needed.\nCross sell new products, propose new ideas and review existing working procedures\nWork closely with other related departments for the purposes of business exploration, risk management and cooperation\nJob Requirements\nUniversity Degree or above preferably with major in Finance, Economics, Business or relevant disciplines\n5 years or above of solid experience in Fixed Income Product sales\nHolder of SFC Type 1, 4 licenses is a must\uf06c\nEstablished relationship and experience in dealing with major fixed income investors including asset managers, insurance companies, bank treasury desk and Chinese onshore banks\nHighly self-motivated; ability to work individually and with a team, able to work under pressure and be a good team player\nSophisticated knowledge of Fixed Income, with focus on Asian G3 credit, CNY/CNH bond and HKD bond market; Knowledge of other financial instrument and products, such as FX and derivatives, is a plus\nProfound knowledge of professional systems such as Bloomberg, Wind etc\nGood analytical and communication skills\nFluent in both spoken and written English and Chinese, including Mandarin\u00a0", "employment_types": ["Permanent"], "selling_points": [], "locations": ["Central"], "categories": ["Banking / Finance", "Treasury", "Financial Services", "Dealing & Trading"], "post_time": "2022-01-10T13:37:47Z", "salary": {"currency": null, "max": null, "min": null, "period": "monthly", "term": null}, "salary_visible": false, "title_keywords": ["sales"], "responsibilities": ["communicate with", "management", "ideas", "budget", "review", "procedures", "transactions", "banking", "cooperate with"], "requirements": {"degrees": ["degree or above"], "majors": ["business", "finance", "economics"], "languages": ["english", "chinese", "mandarin"], "language_level": ["fluent"], "hard_skills": ["focus", "bloomberg", "plus"], "soft_skills": ["sophisticated", "communication skills", "good team player", "self-motivated", "focus", "work under pressure"], "languages_combined": [{"language": "english", "language_level": ["fluent"]}, {"language": "chinese", "language_level": ["fluent"]}, {"language": "mandarin", "language_level": ["fluent"]}]}, "experience_required": {"duration": ["5 years"], "field": ["insurance"]}}, {"job_id": "100003009034529", "location_code": "hk", "company": "Osmium Consulting Group Limited", "job_title": "Reconciliation / Settlement Analyst ( Morning Shift ) | Fintech", "description": "Responsibilities\n\nTransactions bookkeeping and reconciliation of accounts\nVerify data from different reporting tools by daily/ weekly/ monthly basis\nOngoing monitoring of digital asset balances at specific cut-off times and checking digital asset movement\nInvolvement in preparing daily, weekly ,monthly treasury reports\nSupport in the development and streamline of workflows\nCoordinate with internal and external parties to handle day-to-day duties\nAssist in ad hoc tasks as assigned\n\nRequirements\n\nDegree or above in finance, accounting or economics\nExperience in Bank, FinTech, cryptocurrency and blockchain will also be considered\nAble to demonstrate basic data analytical skill and programming experiences\nThe habit of paying painstaking attention to details, correct data and following procedures meticulously\nCapable to work in a challenging, fast-paced team-oriented environment\nProficient in excel formula is a plus\nWork shift : Thursday to Monday , public holidays (Five-Day Work Week) 9am-6pm", "employment_types": ["Full Time", "Permanent"], "selling_points": ["Welcome Settlement / Reconciliation / Dealer apply", "Fast Growth Fintech Startup", "20+ Annual Leaves, Bonus, Shares"], "locations": ["Sai Ying Pun"], "categories": ["Banking / Finance", "Dealing & Trading", "Information Technology (IT)", "Support", "Order Processing & Operation / Settlement"], "post_time": "2022-01-10T03:35:38Z", "salary": {"currency": null, "max": null, "min": null, "period": "monthly", "term": null}, "salary_visible": false, "title_keywords": ["analyst"], "responsibilities": ["reporting", "data", "monitoring", "coordinate with", "checking", "transactions", "internal and external parties", "ad hoc tasks", "reports"], "requirements": {"degrees": ["degree or above"], "majors": ["finance", "accounting", "economics"], "languages": [], "language_level": [], "hard_skills": ["blockchain", "excel", "analytical skill", "plus", "basic", "programming", "cryptocurrency"], "soft_skills": ["analytical skill", "capable", "painstaking", "attention to details"], "languages_combined": []}, "experience_required": {"duration": [], "field": ["programming", "analytical"]}}, {"job_id": "100003009024687", "location_code": "hk", "company": "Southwest Securities (HK) Brokerage Limited", "job_title": "Dealer", "description": "Job Responsibilities:\n\n\nHandle dealing orders of securities and futures for global market\nMonitor portfolio of client accounts and ensure all the executions & practices are compliance with internal risk control policies\nPerform day-end processing and related tasks\nAble to work in shift under special circumstance\nComplete ad-hoc tasks as required by management\n\nJob Requirements:\n\n\n\nUniversity Degree holder or above in Finance, Economics, Accounting or related discipline\nHolder of SFC license RA1 and RA2 is a must\nMinimum 2 years' relevant experience in sizable financial institutions or brokerage firms\nDetail oriented, strong sense of responsibility and able to work under pressure\nGood communication skill and proficiency in Bloomberg, MS Office and Chinese Word processing\nGood command of both spoken and written English and Chinese as well as fluency in Mandarin\nImmediate available is preferred\n\nAttractive package will be offered to the right candidate.\u00a0 Interested parties please send both Chinese & English resume with current and expected salary to the Human Resources Department at 40/F., Lee Garden One, 33 Hysan Avenue, Causeway Bay, Hong Kong or email.\n\nData collected will be used for recruitment purpose only.", "employment_types": ["Full Time", "Permanent"], "selling_points": ["Handle dealing orders of securities and futures", "Holder of SFC license RA1 and RA2 is a must", "Minimum 2 years' relevant experience"], "locations": ["Causeway Bay"], "categories": ["Banking / Finance", "Dealing & Trading"], "post_time": "2022-01-06T16:07:56Z", "salary": {"currency": null, "max": null, "min": null, "period": "monthly", "term": null}, "salary_visible": false, "title_keywords": ["dealer"], "responsibilities": ["control", "management", "policies", "ad-hoc tasks", "compliance", "monitor"], "requirements": {"degrees": ["university degree"], "majors": ["finance", "economics", "accounting"], "languages": ["english", "chinese", "mandarin"], "language_level": ["fluency", "proficiency", "good command", "good"], "hard_skills": ["chinese word processing", "bloomberg", "sfc license", "ms office"], "soft_skills": ["work under pressure", "detail oriented", "communication skill", "sense of responsibility"], "languages_combined": [{"language": "english", "language_level": ["good command", "good"]}, {"language": "chinese", "language_level": ["proficiency", "good command", "good", "good"]}, {"language": "mandarin", "language_level": ["fluency", "good command", "good"]}]}, "experience_required": {"duration": ["minimum 2 years"], "field": ["brokerage", "financial institutions", "relevant experience"]}}, {"job_id": "100003009029658", "location_code": "hk", "company": "Rui Da International Finance Holding Limited", "job_title": "Global Futures Dealer/Management Trainee", "description": "Responsibilities:\n\nOperate and monitor Futures trading platform\nResponsible Futures quotation and execution for\u00a0client\u2019s\u00a0orders\nMonitor client\u2019s position and responsible for margin calls\nIdentify potential market risks and report the issues to senior management\nResponsible for account opening and customer enquiries\nPreparation for dealing reports and market commentary\nPreparation for Monthly and Quarterly Margin Calls Report and Client Money Report\nFamiliar with compliance procedures, policies and regulatory requirements\nHandle and assist in ad-hoc projects as assigned\u00a0\n\nRequirements:\n\nPassed HKSI LE paper 1,7,9 or a SFC Type 2 Licensee\nFresh graduates\u00a0who have passed\u00a0HKSI LE paper 1,7,9 will also be considered\nFluent Putonghua speaking is a MUST\nWilling to work in shift on rotational basis and public holidays\nPreference will be given to those candidates who can be immediate available\nCandidates with no relevant working experience will consider as Management Trainee\n\n\u61c9\u5fb5\u8005\u9808\u5177\u5099\u4ee5\u4e0b\u5176\u4e2d\u4e00\u9805\u5c08\u696d\u8cc7\u683c\uff1a\n1. \u6301\u6709\u9999\u6e2f\u8b49\u76e3\u6703\u7b2c2\u985e\u53d7\u898f\u7ba1\u6d3b\u52d5 - \u671f\u8ca8\u5408\u7d04\u4ea4\u6613\u7684\u4ee3\u8868\u724c\u7167; \u6216\n2. \u5df2\u8003\u7372\u9999\u6e2f\u8b49\u5dfb\u5b78\u9662\u8cc7\u683c\u8003\u8a66\u5377\u4e00\uff0c\u5377\u4e03\u53ca\u5377\u4e5d\u5408\u683c; \u6216\n3. \u5176\u5b78\u6b77\u53ef\u88ab\u8c41\u514d\u9999\u6e2f\u8b49\u5dfb\u5b78\u9662\u8cc7\u683c\u8003\u8a66\u5377\u4e00\uff0c\u5377\u4e03\u53ca\u5377\u4e5d; \u6216\n4. \u5176\u5b78\u6b77\u53ef\u88ab\u8c41\u514d\u9999\u6e2f\u8b49\u5dfb\u5b78\u9662\u8cc7\u683c\u8003\u8a66\u5377\u4e03\u53ca\u5377\u4e5d\u3002", "employment_types": ["Full Time"], "selling_points": [], "locations": ["Wan Chai"], "categories": ["Banking / Finance", "Dealing & Trading", "Others", "Student / Fresh Graduate / No Experience"], "post_time": "2022-01-07T05:57:43Z", "salary": {"currency": null, "max": null, "min": null, "period": "monthly", "term": null}, "salary_visible": false, "title_keywords": ["management trainee", "dealer"], "responsibilities": ["ad-hoc projects", "customer enquiries", "account opening", "policies", "quotation", "monitor", "compliance", "procedures", "regulatory requirements", "reports", "senior management", "report"], "requirements": {"degrees": [], "majors": [], "languages": ["putonghua"], "language_level": ["fluent"], "hard_skills": ["no", "hksi"], "soft_skills": [], "languages_combined": [{"language": "putonghua", "language_level": ["fluent"]}]}, "experience_required": {"duration": [], "field": ["management", "relevant working experience"]}}, {"job_id": "100003009028863", "location_code": "hk", "company": "Cornerstone Global Partners", "job_title": "Night Shift Dealer", "description": "Our client, a PRC leading Securities firm, is looking for a night shift dealer to join:\u00a0\n\nResponsibilities\n\nSupport client on-boarding in a professional manner to compliant with relevant rules and regulations\nHandle different types of clients enquiry for trading\nHandle securities trading\nObtain feedback from clients on the service delivered and recommend improvement plan as appropriate\nAssist in ad-hoc projects as assigned\n\nRequirements\n\nHolder of SFC Type 1 is a must\nRelevant experience in account opening and client service in securities firm\nNight shift experience is highly preferred\nFamiliar with local and global securities\nKnowledge in fund operation will be an advantage\nProactive, patient, good services attitude, strong communication skills, detail-oriented and a good team player\nGood command of\u00a0written and spoken Cantonese, Mandarin and English\nImmediate available is preferred\nWorking hours: 9:00pm \u2013 6:00am", "employment_types": ["Full Time"], "selling_points": ["5 days work", "work life balance", "Central"], "locations": ["Central"], "categories": ["Banking / Finance", "Dealing & Trading"], "post_time": "2022-01-07T03:25:18Z", "salary": {"currency": null, "max": null, "min": null, "period": "monthly", "term": null}, "salary_visible": false, "title_keywords": ["dealer"], "responsibilities": ["regulations", "ad-hoc projects", "professional manner", "plan"], "requirements": {"degrees": [], "majors": [], "languages": ["cantonese", "english", "mandarin"], "language_level": ["good command"], "hard_skills": ["account opening"], "soft_skills": ["communication skills", "good team player", "detail-oriented", "patient", "proactive"], "languages_combined": [{"language": "cantonese", "language_level": ["good command"]}, {"language": "english", "language_level": ["good command"]}, {"language": "mandarin", "language_level": ["good command"]}]}, "experience_required": {"duration": [], "field": ["securities firm", "relevant experience"]}}, {"job_id": "100003009038529", "location_code": "hk", "company": "Conners Consulting Limited", "job_title": "AD, Sales Trading (Top tier Investment Bank, Attractive Package)", "description": "Our client, a well-established investment bank to invite high calibre candidates to join their company.\n\nResponsibilities:\n\n\nSales trading coverage of different assigned accounts, including QDII, hedge fund & long-only\nProvide daily market updates and information for institutional clients\nProvide trade ideas and market in-house research products to institutional clients\nWork closely with dealers for best execution. Liaise with middle office and settlement team to ensure smooth settlement for all post trade issues\n\nRequirement:\n\nBachelor degree in Finance or relevant discipline\nAt least 8 years\u2019 working experience in sales trading role\u00a0\nStrong attention to detail, high degree of accuracy and ability to multi-task\nKnowledge of the HK/CH market and regulatory rules\nCapable of writing market notes and market summary\nSystem knowledge: Fidessa and Bloomberg\nExcellent spoken and written English and Chinese including Mandarin;\n\nTo apply, please send your detailed resume or contact Boei Yan at 3460 2012 for a confidential discussion.\nOnly shortlisted candidates will be notified.\u00a0\nApplicants who are not contacted within two weeks may consider their applications unsuccessful.\nAll data collected will be used for recruitment purpose only & will be used strictly confidential.\n\nConners Consulting Limited 2005 Kai Tak Commercial Building 317 Des Voeux Road Central Hong Kong\nTel: (852) 3996 8090\u00a0 \u00a0 \u00a0 \u00a0\u00a0\nWebsite:\u00a0http://www.connersconsulting.com/", "employment_types": ["Full Time", "Permanent"], "selling_points": ["Sales and Trading in HK market, QDII, hedge fund", "Assist in building trading platform", "Attractive remuneration package, strong platform"], "locations": ["Central"], "categories": ["Banking / Finance", "Investment", "Dealing & Trading", "Equities / Capital Markets"], "post_time": "2022-01-11T07:14:35Z", "salary": {"currency": null, "max": null, "min": null, "period": "monthly", "term": null}, "salary_visible": false, "title_keywords": ["sales"], "responsibilities": ["liaise with", "trade issues", "ideas"], "requirements": {"degrees": ["degree", "bachelor"], "majors": ["finance"], "languages": ["english", "chinese", "mandarin"], "language_level": ["excellent"], "hard_skills": ["bloomberg", "ch"], "soft_skills": ["multi-task", "capable", "attention to detail", "detailed"], "languages_combined": [{"language": "english", "language_level": ["excellent"]}, {"language": "chinese", "language_level": ["excellent"]}, {"language": "mandarin", "language_level": ["excellent"]}]}, "experience_required": {"duration": ["at least 8 years"], "field": ["trading"]}}, {"job_id": "100003009035740", "location_code": "hk", "company": "Michael Page", "job_title": "VP, Fixed Income", "description": "Fixed income salesperson responsible for targeting Taiwanese Financial Institutional clients\n\nClient Details\n\nForeign securities brokerage that offers a wide range of fixed income products\n\nDescription\n\nAssist the team head to promote teamwork, boost morale, enhance productivity and ensure talent needs and capabilities are developed to support long term development goals\nGuide the team to achieve the designated sales and trading profit target as well as client accounts target\nAchieve collaboration targets with internal teams such as deal referrals and joint client visits\nParticipate in coaching and developing programs of junior team members\nWork on ad-hoc projects as assigned\n\nProfile\n\nBachelor's holder in finance, business administration or relevant discipline\nSolid working experience in Fixed Income Sales areas preferably in sizeable financial institutions with good securities and financial investment products knowledge\nGood understanding of SFC regulations and guidelines as well as related regulations and legislations, and important concepts\nAble to perform and multi-task in a dynamic, fast paced and challenging environment\nGood negotiation, presentation and written/verbal communication skills\nFluent in both Chinese including Mandarin, and English\n\nJob Offer\n\nGood remuneration package\n\nTo apply online please click the 'Apply' button below. For a confidential discussion about this role please contact Pearl Chiu on +852 3412 4816.", "employment_types": ["Full Time", "Permanent"], "selling_points": ["Solid fixed income sales experience", "Expertise in flow credit products", "Possess extensive client network"], "locations": ["Not Specified"], "categories": ["Banking / Finance", "Dealing & Trading"], "post_time": "2022-01-10T08:20:15Z", "salary": {"currency": null, "max": null, "min": null, "period": "monthly", "term": null}, "salary_visible": false, "title_keywords": [], "responsibilities": ["regulations", "profit target", "brokerage", "guidelines", "teams", "developing", "communication", "contact", "ad-hoc projects", "legislations", "administration"], "requirements": {"degrees": ["bachelor"], "majors": ["finance", "business administration"], "languages": ["english", "chinese", "mandarin"], "language_level": ["fluent"], "hard_skills": ["pearl", "dynamic", "investment products"], "soft_skills": ["communication skills", "multi-task", "negotiation", "responsible", "teamwork", "dynamic", "presentation"], "languages_combined": [{"language": "english", "language_level": ["fluent"]}, {"language": "chinese", "language_level": ["fluent"]}, {"language": "mandarin", "language_level": ["fluent"]}]}, "experience_required": {"duration": [], "field": ["investment", "financial institutions", "securities", "financial"]}}, {"job_id": "100003009037417", "location_code": "hk", "company": "ProJob21.com Limited", "job_title": "Regional Trade Support Analyst/Associate, Global Asset Manager", "description": "Dynamic Trade Support & Portfolio Support\nComprehensive & Competitive Benefits\nGlobal PWM & Asset Management platform\n\nRepresenting multiple Global Private Banks and Asset Management Groups in searching for potential talents to be part of their regional middle office & front office support team!\n\n\nJob Duties\n\nEnsure timely production of trade booking/reconciliation; continuous monitoring of corporate action/operations issues\nTackle front office traders / portfolio managers enquiries related to trade related aspects\nActive participation in continuous process/system enhancement to cater for innovation, new markets/products initiatives\n\nRequirements\n\nWell qualified graduate in Mathematics/Financial Engineering with 4 years+ middle office/trader support experience earned from International Banks and Financial Institutions.\nGood understanding of global investment products in particular with Equities Derivatives, Fixed Income and investment funds.\nIT savvy with good proficiency in Excel and VBA\nProactive personality with sound analytical and interpersonal skill with proven exposure in working for traders\nAdaptive to working in a highly multi-cultural and dynamic trading environment\n\n\n\nInterested candidates, please email your update resume (in MS WORD format) with current and expected salary to us soonest.\n\nAlso come visit ProJOB21 www.ProJob21.com to discover other exciting career opportunities!\n\nAll information received will be kept in strict confidence and used for employment-related purposes only.", "employment_types": ["Full Time"], "selling_points": [], "locations": ["Not Specified"], "categories": ["Banking / Finance", "Private Banking", "Dealing & Trading", "Order Processing & Operation / Settlement"], "post_time": "2022-01-11T02:44:56Z", "salary": {"currency": null, "max": null, "min": null, "period": "monthly", "term": null}, "salary_visible": false, "title_keywords": ["analyst", "associate", "manager"], "responsibilities": [], "requirements": {"degrees": [], "majors": [], "languages": [], "language_level": [], "hard_skills": [], "soft_skills": [], "languages_combined": []}, "experience_required": {"duration": [], "field": []}}, {"job_id": "100003007407150", "location_code": "hk", "company": "Resource Solutions Consulting Hong Kong Limited", "job_title": "Executive Secretary, 6-month contract (temp to perm opportunity)", "description": "About Our Client\n\nOur client is a prestigious international bank with a long history of providing corporate banking solutions to businesses and to large local companies, financial institutions and multinationals. We look for talented, tenacious individuals who are hungry to progress and eager to grow their knowledge.\n\nKey Responsibilities:\n\nAssist the Head of FIC and other FIC teams to efficiently organize their agenda; in particular their business trip (hotel, air ticket, visa, etc.), client and internal meetings, conference call, etc, and organize regional/territory meetings/seminars\nSchedule and co\u2010ordinate meetings and facilities which may include travel and lodging arrangements\nPrepare monthly activity reporting when requested, travelling and coming clients meetings report and any ad\u2010hoc documents and presentation materials, statistical, planning reports, or business reporting\nMaintenance and adequate/optimize filing of documents\nReceive, handle and transfer phone calls and messages within the department promptly and courteously.\nKeep confidential and sensitive reports / analysis / clients information / other information to the Bank.\nResponsible for general administration, including stationery, office furniture, equipment etc\nSelect and circulate the newspaper clippings within the department\nSubmit the overtime claim and absence reports regularly.\nAssist in logistic matters involved with external/internal visitors. Ensure trouble free visits (access badges, meeting schedule, airport pick up, hotel booking when necessary)\nArrange for visa applications\nDirect contribution to the team's operational permanent control framework\n\nQualifications:\n\nBachelor Degree\n3-5 years of relevant experiences in banking and finance\nStrong interpersonal skills\nOrganized and able to work independently and under pressure\nGood communication skills, verbal and written\nFluent in spoken and written English and Chinese\nImmediate available preferred\n\nValues and Diversity\n\nDynamic working gives everyone at our client the opportunity to integrate professional and personal lives, if you have a need for flexibility then please discuss this with the hiring manager. They are an equal opportunity employer and are opposed to discrimination on any grounds. It is the policy of our client to ensure equal employment opportunity without discrimination or harassment on the basis of race, colour, creed, religion, national origin, alienage or citizenship status, age, sex, sexual orientation, gender identity or expression, marital or domestic/civil partnership status, disability, veteran status, genetic information, or any other basis protected by law.", "employment_types": ["Full Time", "Temporary", "Contract"], "selling_points": ["International Investment Bank", "Work with a global team", "Immediate Available preferred"], "locations": ["Central"], "categories": ["Admin & HR", "Secretary", "Banking / Finance", "Dealing & Trading", "Equities / Capital Markets"], "post_time": "2022-01-11T03:41:14Z", "salary": {"currency": null, "max": null, "min": null, "period": "monthly", "term": null}, "salary_visible": false, "title_keywords": ["executive secretary"], "responsibilities": ["administration", "reporting", "control", "maintenance", "analysis", "teams", "stationery", "communication", "planning", "reports", "schedule", "business trip", "banking", "booking", "phone calls", "report"], "requirements": {"degrees": ["degree", "bachelor"], "majors": [], "languages": ["english", "chinese"], "language_level": ["fluent"], "hard_skills": ["analysis", "dynamic", "maintenance"], "soft_skills": ["organized", "work independently", "communication skills", "under pressure", "responsible", "dynamic", "interpersonal skills", "sensitive", "presentation", "tenacious"], "languages_combined": [{"language": "english", "language_level": ["fluent"]}, {"language": "chinese", "language_level": ["fluent"]}]}, "experience_required": {"duration": ["3-5 years"], "field": ["finance", "banking"]}}, {"job_id": "100003009027837", "location_code": "hk", "company": "Conners Consulting Limited", "job_title": "Dealer Treasury, Night Shift (Retail Bank Double Pay Bonus Perm Job)", "description": "Dealer (Job ID3339)\nResponsibilities\nTo be a team member of the Currencies & Interest Rates Trading Department\nProvide FX, Forwards and Swap quotation to different business units\nEngage in interbank dealing to manage the FX and gap exposures arising from customer transactions\nPrepare various business reports and perform operational duties\nTrade in the FX market to meet the assigned annual target\nParticipate in ad-hoc projects\nRequirements\nUniversity graduate with a minimum of 1 year\u2019 experience in FX market\nFamiliar with treasury systems such as Refinitive, Bloomberg and Murex\nProficiency in computer applications such as Excel VBA\nA good team player who can also work independently and under pressure\nSelf-motivated and detail-minded with strong communication and analytical skill\nWilling to perform shift duty, including night and holiday shifts\nProficiency in both spoken and written English and Chinese\nSound knowledge of interest rate products is a plus\nSenior position may be considered for applicants with more experience and knowledge\nPlease apply online via the BEA Careers website at\u00a0https://careers.hkbea.com/psp/hcmprd/EMPLOYEE/HRMS/c/HRS_HRAM.HRS_APP_SCHJOB.GBL?Page=HRS_APP_JBPST&Action=UFOCUS=Applicant&SiteId=1&JobOpeningId=3339&PostingSeq=1 or by clicking the \"Apply Now\" button below. Kindly note that if you are a new user, you have to first create your User Profile before you can apply.\nPersonal data provided by job applicants will be used for recruitment purposes only and will be treated in accordance with the Bank's Personal Information Collection (Employees) Statement and Privacy Policy Statement. Applicants who are not invited for interviews within six weeks may consider their applications unsuccessful and the personal data collected will be destroyed after six months.", "employment_types": ["Full Time", "Permanent"], "selling_points": ["Treasury deal execution bonds, FX and derivatives", "Minimum 2 years' work experience in related field", "SFC license type 1"], "locations": ["Central"], "categories": ["Banking / Finance", "Dealing & Trading"], "post_time": "2022-01-06T15:21:52Z", "salary": {"currency": null, "max": null, "min": null, "period": "monthly", "term": null}, "salary_visible": false, "title_keywords": ["dealer"], "responsibilities": ["quotation", "transactions", "reports", "ad-hoc projects", "operational duties"], "requirements": {"degrees": ["university graduate"], "majors": [], "languages": ["english", "chinese"], "language_level": ["proficiency"], "hard_skills": ["excel", "vba", "analytical skill", "plus", "bloomberg", "c"], "soft_skills": ["detail-minded", "good team player", "work independently", "under pressure", "self-motivated", "analytical skill", "communication"], "languages_combined": [{"language": "english", "language_level": ["proficiency"]}, {"language": "chinese", "language_level": ["proficiency"]}]}, "experience_required": {"duration": ["minimum of 1 year"], "field": []}}, {"job_id": "100003009034133", "location_code": "hk", "company": "Tiger Brokers (HK) Global Limited", "job_title": "Senior AML Compliance Officer", "description": "Responsibilities\n\nSupervise the daily settlement and clearing operation\nMonitor the operational activities in respect to the requirements of SFC, Stamp Duty Office, IRD, HKEx etc.;\nHandle all settlement process related to IPO subscription (e.g. IPO financing, placement booking settlement with placing agents, prepare all necessary documents to external parties etc.)\nProcess corporate actions; monitor investor holdings and total positions within CCASS / DCASS\n\nRequirements\n\nBachelor Degree or above in Finance, Business Administration or other related disciplines\n5 years or above relevant experience in brokerage firms, Banking or financial industry, in which 3 years are in managerial level\nSolid experience in HK and Asia equities and futures settlement\nFull competence and a strong knowledge in CCASS/DCASS operation\nAble to work independently and work under pressure to meet deadline\nCandidates with less experience will be considered as Settlement Officer\n\n\n\nWe offer\u00a05-day-work\u00a0week\u00a0with competitive remuneration & benefit packages to the right candidate.\u00a0Interested parties please apply with your application letter, resume, expected salary via our online application platform by clicking the\u00a0\"Apply Now\"\u00a0button or by post to Group Human Resources Department, 28/F, Emperor Group Centre, 288 Hennessy Road, Wanchai, Hong Kong.\n\nWe are an equal opportunity employer & welcome applications from all qualified candidates. The information provided will be treated in strict confidence & be used only for consideration of your application for relevant / similar posts within the Emperor Group. Applicants not hearing from us within four weeks may consider their applications unsuccessful. We may retain the unsuccessful applications for a maximum period of\u00a024 months.", "employment_types": ["Full Time"], "selling_points": ["Support AML/CFT and sanctions operations", "Perform transaction monitoring", "Conduct AML/CFT and CDD reviews"], "locations": ["Central"], "categories": ["Banking / Finance", "Financial Services", "Dealing & Trading", "Professional Services", "Legal & Compliance"], "post_time": "2022-01-10T02:54:23Z", "salary": {"currency": null, "max": null, "min": null, "period": "monthly", "term": null}, "salary_visible": false, "title_keywords": ["officer", "aml compliance"], "responsibilities": ["settlement process", "external parties", "monitor", "booking"], "requirements": {"degrees": ["degree or above", "bachelor"], "majors": ["related disciplines", "finance", "business administration"], "languages": [], "language_level": [], "hard_skills": ["dcass", "ccass"], "soft_skills": ["work independently", "work under pressure"], "languages_combined": []}, "experience_required": {"duration": ["5 years", "3 years"], "field": ["managerial", "brokerage", "financial industry", "relevant experience", "banking"]}}, {"job_id": "100003009036008", "location_code": "hk", "company": "Emperor Capital Group", "job_title": "Assistant Settlement Manager/ Settlement Officer", "description": "Our client is western internet broker currently looking for a shift dealer to join their team.\u00a0\n\nJob Responsibilities:\n\nExecute dealing orders for local, global securities (US stock mainly)\u00a0\nHandle client\u2019s enquiries\nPerform risk control and monitor client\u2019s trading positions in changing market conditions;\nAssist in daily-operation and prepare the related documents\n\u00a0Perform any other duties as assigned from time to time\nJob Requirements:\nMinimum 2 years of dealing experience in securities transactions;\nHolder of SFC Type 1 license\nWillingness to perform shift duties, including weekends and public holidays if required (shift allowance will be provided)\nGood team player with good communication skill\nGood command of written English and Chinese\nFor interested candidates, please send us your full resume with your current and expected salary. \u00a0All information collected will be strictly used for recruitment purpose only.", "employment_types": ["Full Time", "Permanent"], "selling_points": ["Solid exp in equities and futures settlement", "Degree or above", "Knowledge in CCASS/DCASS operation"], "locations": ["Wan Chai"], "categories": ["Banking / Finance", "Financial Services", "Dealing & Trading", "Order Processing & Operation / Settlement"], "post_time": "2022-01-10T09:04:14Z", "salary": {"currency": null, "max": null, "min": null, "period": "monthly", "term": null}, "salary_visible": false, "title_keywords": ["settlement manager", "officer", "assistant"], "responsibilities": ["related documents", "any other duties", "control", "monitor"], "requirements": {"degrees": [], "majors": [], "languages": ["english", "chinese"], "language_level": ["good command"], "hard_skills": [], "soft_skills": ["good team player", "communication skill"], "languages_combined": [{"language": "english", "language_level": ["good command"]}, {"language": "chinese", "language_level": ["good command"]}]}, "experience_required": {"duration": ["minimum 2 years"], "field": ["securities"]}}, {"job_id": "100003008677687", "location_code": "hk", "company": "Jinrui Futures (Hong Kong) Limited", "job_title": "Dealer", "description": "Securities Services Department\n\nAccount Servicing & Administration Officer\u00a0(Job ID: 3301)\n\nResponsibilities\n\nTo be a team member of Securities Services Department\nTo handle customers\u2019 enquiries via hotline, walk-in, emails and letters on securities account related matters\nTo handle the operations and maintenance of trading accounts\nTo conduct regular customer review and customer due diligence in compliance with regulatory requirements\nTo provide administration support and handle any ad hoc tasks assigned by the supervisor\n\nRequirements\n\nUniversity graduates or Higher Diploma in Business Administration or related disciplines\nMinimum of 1 year\u2019s working experience in securities or banking industries\nKnowledge in securities industry with understanding of relevant practice, rules and regulations in SEHK and SFC preferred\nPass in the Insurance Intermediaries Qualifying Examination or Hong Kong Securities Institute Licencing Examinations is an advantage\nSelf-motivated and able to work under pressure\nProficiency in both spoken and written English and Chinese, Putonghua will be a plus\nGood knowledge of MS Office\n\n\nPlease apply online via the BEA Careers website at https://careers.hkbea.com/psp/hcmprd/EMPLOYEE/HRMS/c/HRS_HRAM.HRS_APP_SCHJOB.GBL?Page=HRS_APP_JBPST&Action=U&FOCUS=Applicant&SiteId=1&JobOpeningId=3301&PostingSeq=1 or by clicking the Apply Now button. Kindly note that if you are a new user, you have to first create your User Profile before you can apply.\n\nPersonal data provided by job applicants will be used for recruitment purposes only and will be treated in accordance with the Bank's Personal Data Policy, which is available upon request. Applicants who are not invited for interviews within six weeks may consider their applications unsuccessful and the personal data collected will be destroyed after six months.", "employment_types": ["Full Time", "Permanent"], "selling_points": ["Exposure on global futures market trading", "Holder of SFC (Type1,2) licenses", "Work on shift and public holidays"], "locations": ["Wan Chai"], "categories": ["Banking / Finance", "Dealing & Trading", "Others", "Sales, CS & Business Devpt", "Customer Service - Supervisor / Officer"], "post_time": "2022-01-06T08:24:13Z", "salary": {"currency": null, "max": null, "min": null, "period": "monthly", "term": null}, "salary_visible": false, "title_keywords": ["dealer"], "responsibilities": ["maintenance", "operations", "regulatory requirements", "review", "letters", "compliance", "ad hoc tasks", "customer due diligence", "administration"], "requirements": {"degrees": ["diploma"], "majors": ["related disciplines", "business administration"], "languages": ["putonghua", "english", "chinese"], "language_level": ["proficiency"], "hard_skills": ["sehk", "plus", "c", "ms office"], "soft_skills": ["self-motivated", "work under pressure"], "languages_combined": [{"language": "putonghua", "language_level": ["proficiency"]}, {"language": "english", "language_level": ["proficiency"]}, {"language": "chinese", "language_level": ["proficiency"]}]}, "experience_required": {"duration": ["minimum of 1 year"], "field": ["securities", "banking"]}}, {"job_id": "100003009031713", "location_code": "hk", "company": "The Bank of East Asia, Limited", "job_title": "Account Servicing & Administration Officer", "description": "Our client, a well-known bank in Hong Kong, is looking for a high caliber to join the group.\n\nKey Responsibilities\u00a0 \u00a0\n\nExecute trading orders accurately and efficiently\nCultivate and deepen relationship with existing customers\nSolicit new business opportunities from branch referrals\nFacilitate daily dealing administrations and prepare related documents\nMonitor clients orders and margin level and conduct margin call and margin report\nSupport system testing and UAT\nHandle ad hoc duties as assigned\n\nRequirements\n\nDiploma in Finance or related disciplines\nProficient in MS Word, Excel and Power Point\nHolder of SFC (Type1,2) licenses\u00a0is an advantage\nGood command of written English and Chinese, including Putonghua\n\u00a0With good interpersonal and communication\u00a0skills\n\nTo apply, please send your detailed resume to winnie[at]connersconsulting[dot]com or contact Winnie Lai at 3618 8348 for a confidential discussion.\n\nOnly shortlisted candidates will be notified.\n\nApplicants who are not contacted within two weeks may consider their applications unsuccessful.\n\nAll data collected will be used for recruitment purpose only & will be used strictly confidential.\n\n\nConners Consulting Limited\n\n2005 Kai Tak Commercial Building 317 Des Voeux Road Central Hong Kong\n\nTel: (852) 3996 8090\u00a0\u00a0\u00a0\u00a0\u00a0\u00a0 Website:\u00a0www.connersconsulting.com", "employment_types": ["Full Time", "Permanent"], "selling_points": ["Handle customers' enquiries on securities account", "Operate & maintain trading accounts", "University graduates with exp. in securities/bank"], "locations": ["Central"], "categories": ["Banking / Finance", "Financial Services", "Dealing & Trading", "Equities / Capital Markets"], "post_time": "2022-01-07T19:20:48Z", "salary": {"currency": null, "max": null, "min": null, "period": null, "term": null}, "salary_visible": false, "title_keywords": ["administration officer"], "responsibilities": ["ad hoc duties", "uat", "related documents", "business opportunities", "monitor", "testing", "report"], "requirements": {"degrees": ["diploma"], "majors": ["related disciplines", "finance"], "languages": ["putonghua", "english", "chinese"], "language_level": ["good command"], "hard_skills": ["power point", "excel", "ms word"], "soft_skills": ["communication skills", "interpersonal", "detailed"], "languages_combined": [{"language": "putonghua", "language_level": ["good command"]}, {"language": "english", "language_level": ["good command"]}, {"language": "chinese", "language_level": ["good command"]}]}, "experience_required": {"duration": [], "field": []}}, {"job_id": "100003009027081", "location_code": "hk", "company": "Conners Consulting Limited", "job_title": "Dealer, Night Shift (Bank job)", "description": "Responsibilities\n\nSupport client on-boarding in a professional manner to compliant with relevant rules and regulations\nHandle different types of clients enquiry for trading\nHandle securities trading\nObtain feedback from clients on the service delivered and recommend improvement plan as appropriate\nAssist in ad-hoc projects as assigned\n\nRequirements\n\nHolder of SFC Type 1 is a must\nRelevant experience in account opening and client service in securities firm\nNight shift experience is highly preferred\nFamiliar with local and global securities\nKnowledge in fund operation will be an advantage\nProactive, patient, good services attitude, strong communication skills, detail-oriented and a good team player\nGood command of\u00a0written and spoken Cantonese, Mandarin and English\nImmediate available is preferred\nWorking hours: 9:00pm \u2013 6:00am\n\nWe offer competitive remuneration package & career prospects to the right candidate. Interest parties please apply with resume showing availability, current and expected salary by clicking \u201cApply Now\u201d.\n\nAll personal data collected will be kept confidential and used for recruitment purpose only.\n\n\n\n", "employment_types": ["Full Time", "Permanent"], "selling_points": ["Dealer, Night Shift", "Holder of SFC license RA1 and RA2 is a must", "5 years work experience in related field"], "locations": ["Central & Western Area"], "categories": ["Banking / Finance", "Investment", "Dealing & Trading"], "post_time": "2022-01-06T09:05:38Z", "salary": {"currency": null, "max": null, "min": null, "period": "monthly", "term": null}, "salary_visible": false, "title_keywords": ["dealer"], "responsibilities": ["regulations", "ad-hoc projects", "professional manner", "plan"], "requirements": {"degrees": [], "majors": [], "languages": ["cantonese", "english", "mandarin"], "language_level": ["good command"], "hard_skills": ["account opening"], "soft_skills": ["communication skills", "good team player", "detail-oriented", "patient", "proactive"], "languages_combined": [{"language": "cantonese", "language_level": ["good command"]}, {"language": "english", "language_level": ["good command"]}, {"language": "mandarin", "language_level": ["good command"]}]}, "experience_required": {"duration": [], "field": ["securities firm", "relevant experience"]}}, {"job_id": "100003009007216", "location_code": "hk", "company": "Webull Securities Limited", "job_title": "Dealer (Night)", "description": "Build a successful career path, focus on capital market's execution, work closely with portfolio managers\n\nClient Details\n\nOur company is a well-known asset management company with over 20 years history, it manages multi-asset platforms such as private equity, finance and asset management. The client manages more than USD 15 billion of capital and over 250 staff over the world. Currently, they are looking for an execution trader to support the portfolio manager.\n\nDescription\n\nConduct market research and communicate with portfolio manager on a regular basis\nBuild and maintain good relationships with sell-side analysts\nExecute dealing orders from portfolio manager\nConduct regular review on the market risk level\nEnsure efficient order execution\n\nProfile\n\nBachelor's Degree holder in Finance or related field\n2 years dealing experience\nExperienced in Bloomberg and Wind\nSFC type 1 and 9\nFluent in Mandarin, English and Cantonese\nAble to work under pressure, detail-oriented, multi-tasking\n\nJob Offer\n\nCompetitive remuneration package with annual bonus\n18 days annual leave\nFive days' work\nGreat career progression opportunity\nMPF, medical insurance\n\nTo apply online please click the 'Apply' button below. For a confidential discussion about this role please contact Joanie Lau on +852 3602 2458.", "employment_types": ["Full Time"], "selling_points": ["Fintech Company", "Dealer", "Competitive Remuneration Package"], "locations": ["Sheung Wan"], "categories": ["Banking / Finance", "Dealing & Trading"], "post_time": "2022-01-06T08:52:46Z", "salary": {"currency": null, "max": null, "min": null, "period": "monthly", "term": null}, "salary_visible": false, "title_keywords": ["dealer"], "responsibilities": ["communicate with", "mpf", "work under pressure", "conduct market research", "regular review", "maintain", "contact", "insurance", "asset management"], "requirements": {"degrees": ["bachelor", "degree holder"], "majors": ["finance"], "languages": ["cantonese", "english", "mandarin"], "language_level": ["fluent"], "hard_skills": ["focus", "bloomberg", "private equity"], "soft_skills": ["efficient", "detail-oriented", "multi-tasking", "focus", "work under pressure"], "languages_combined": [{"language": "cantonese", "language_level": ["fluent"]}, {"language": "english", "language_level": ["fluent"]}, {"language": "mandarin", "language_level": ["fluent"]}]}, "experience_required": {"duration": ["2 years"], "field": []}}, {"job_id": "100003009026651", "location_code": "hk", "company": "Page Personnel", "job_title": "Trader ( Execution) - Asset Management", "description": "Business Manager (Securities Services) (Job ID: 3190)\n\n\nResponsibilities\n\nTo be a team member of Securities Services Department\nTo handle securities transactions as well as provide timely and efficient securities services to customers\nTo assist the Section Head in planning, leading, coordinating and controlling the dealing operations\nTo ensure all daily transactions and relevant controls are performed accurately and properly accordingly to the Bank\u2019s standard procedures\nTo handle any ad hoc tasks assigned by the Section Head\nRequirements\n\nUniversity degree, preferably major in business, finance or related disciplines\nMinimum of 5 years working experience in securities sector or related areas covering the following:\nAt least 2 years in supervision of subordinates for dealing operations\nSound knowledge in securities market and understanding of relevant policies, procedures, practices of relevant regulatory bodies\nA team player with good interpersonal skills, analytical skills and risk awareness\nSelf-motivated and able to work under pressure\nProficiency in both spoken and written English and Chinese, Putonghua is a plus\nPlease apply online via the BEA Careers website at\u00a0https://careers.hkbea.com/psp/hcmprd/EMPLOYEE/HRMS/c/HRS_HRAM.HRS_APP_SCHJOB.GBL?Page=HRS_APP_JBPST&Action=UFOCUS=Applicant&SiteId=1&JobOpeningId=3190&PostingSeq=1 or by clicking the \"Apply Now\" button below. Kindly note that if you are a new user, you have to first create your User Profile before you can apply.\n\nPersonal data provided by job applicants will be used for recruitment purposes only and will be treated in accordance with the Bank's Personal Information Collection (Employees) Statement and Privacy Policy Statement. Applicants who are not invited for interviews within six weeks may consider their applications unsuccessful and the personal data collected will be destroyed after six months.", "employment_types": ["Full Time", "Permanent"], "selling_points": ["Build a successful career path", "Focus on capital market's execution", "Work closely with portfolio managers"], "locations": ["Not Specified"], "categories": ["Banking / Finance", "Financial Services", "Dealing & Trading", "Equities / Capital Markets"], "post_time": "2022-01-06T08:27:31Z", "salary": {"currency": null, "max": null, "min": null, "period": "monthly", "term": null}, "salary_visible": false, "title_keywords": ["asset management"], "responsibilities": ["operations", "ad hoc tasks", "procedures", "transactions", "planning"], "requirements": {"degrees": ["university degree"], "majors": ["related disciplines", "finance", "business"], "languages": ["putonghua", "english", "chinese"], "language_level": ["proficiency"], "hard_skills": ["plus", "c", "analytical skills"], "soft_skills": ["self-motivated", "analytical skills", "interpersonal skills", "team player", "work under pressure"], "languages_combined": [{"language": "putonghua", "language_level": ["proficiency"]}, {"language": "english", "language_level": ["proficiency"]}, {"language": "chinese", "language_level": ["proficiency"]}]}, "experience_required": {"duration": ["minimum of 5 years"], "field": ["related", "securities"]}}, {"job_id": "100003009026171", "location_code": "hk", "company": "The Bank of East Asia, Limited", "job_title": "Business Manager (Securities Services)", "description": "Responsibilities\n\n\nManage HK and US trade settlement and clearing work for Hong Kong exchanges and Clearing Ltd, and other exchanges\nHandle corporate actions, custodian services, cash management and IPO applications to the customers\nCoordinate work within company and between regulatory bodies\nLead team members on daily operations\nReport operational irregularities and recommend corrective actions to management\nAssist in Project and system implementation work\n\nRequirements\n\nDegree holder with min. 5 year\u2019s working experience in Securities either local market or oversea markets\nKnowledge in CCASS and Custodian Management\nRelevant experience in handling exchange traded securities settlement operations\nRelevant experience in performing project and system testing\nHard working, self-motivated and good sense of responsibility\nGood command of English and Chinese\n\nWe offer attractive remuneration to successful candidates.\u00a0Interested parties \u2013 please send your application with full resume, availability and expected salary by clicking 'Apply Now'.\u00a0\n\nAll information collected will be kept in strict confidence and used for recruitment purpose only.", "employment_types": ["Full Time", "Permanent"], "selling_points": ["Provide timely and efficient securities services", "Supervise subordinates for dealing operations", "University graduates with 5 years' work experience"], "locations": ["Central"], "categories": ["Banking / Finance", "Dealing & Trading", "Equities / Capital Markets", "Others"], "post_time": "2022-01-07T19:19:29Z", "salary": {"currency": null, "max": null, "min": null, "period": null, "term": null}, "salary_visible": false, "title_keywords": ["manager"], "responsibilities": ["management", "irregularities", "implementation", "coordinate", "daily operations", "report"], "requirements": {"degrees": ["degree holder"], "majors": [], "languages": ["english", "chinese"], "language_level": ["good command"], "hard_skills": ["ccass", "exchange"], "soft_skills": ["hard working", "self-motivated", "sense of responsibility"], "languages_combined": [{"language": "english", "language_level": ["good command"]}, {"language": "chinese", "language_level": ["good command"]}]}, "experience_required": {"duration": ["5 year"], "field": ["securities", "settlement operations", "relevant experience", "testing"]}}, {"job_id": "100003009031541", "location_code": "hk", "company": "Sofi Securities (Hong Kong) Limited", "job_title": "Senior Specialist,Operations", "description": "Our client, a well-known retail bank in Hong Kong, is looking for a high calibre to join the group.\n\nResponsibilities:\n\nTreasury deal executions including foreign exchange, derivatives and bonds transactions\nProvide customer service and inquiries\nPerform system UAT and Handle ad-hoc assignments\n\nRequirements:\n\nPost-secondary educated with at least 3 years work experience in related field\nQualified individual to carry out regulated activities (Type 1) under SFC\nStrong knowledge in foreign exchange, derivatives and bonds etc\nGood command of both spoken English and Chinese including Putonghua\n\nTo apply, please send your detailed resume or contact Timothy Wong at 3990 3179 for a confidential discussion.\n\nOnly shortlisted candidates will be notified.\n\nApplicants who are not contacted within two weeks may consider their applications unsuccessful.\n\nAll data collected will be used for recruitment purpose only & will be used strictly confidential.\n\nConners Consulting Limited 2005 Kai Tak Commercial Building 317 Des Voeux Road Central Hong Kong.\n\nTel: (852) 3996 8090\n\nWebsite: www.connersconsulting.com", "employment_types": ["Full Time", "Permanent"], "selling_points": [], "locations": ["Central & Western Area"], "categories": ["Banking / Finance", "Financial Services", "Dealing & Trading", "Order Processing & Operation / Settlement"], "post_time": "2022-01-07T09:26:29Z", "salary": {"currency": null, "max": null, "min": null, "period": "monthly", "term": null}, "salary_visible": false, "title_keywords": ["operations", "senior specialist"], "responsibilities": ["provide customer service", "ad-hoc assignments", "uat", "transactions"], "requirements": {"degrees": [], "majors": [], "languages": ["putonghua", "english", "chinese"], "language_level": ["good command"], "hard_skills": ["exchange"], "soft_skills": ["detailed"], "languages_combined": [{"language": "putonghua", "language_level": ["good command"]}, {"language": "english", "language_level": ["good command"]}, {"language": "chinese", "language_level": ["good command"]}]}, "experience_required": {"duration": ["at least 3 years"], "field": ["related"]}}, {"job_id": "100003009021380", "location_code": "hk", "company": "Mayfair & Ayers Financial Group Limited", "job_title": "Junior Dealer/ Dealer Trainee", "description": "Responsibilities\n\nManage securities and futures trading, as well as product inquiries\u00a0\nMaintain and update the latest margin requirement for futures and commodities trading\u00a0\nManage customer enquiries and provide quality service\nUndertake risk monitoring and handle margin calls\nRequirements\nDegree holder in Business, Finance\nAt least 1 years relevant experience is preferred\nHolder HKSI LE 1 & 2 or equivalent is preferable\nSound knowledge in Hong Kong stock market and derivatives market\nStrong Communication / interpersonal / analytical skills\nResult oriented and self-motivated to attain goals. Must be a Team Player\nGood command of both spoken and written English and Chinese (Cantonese and Putonghua)\nWilling to work in night shift and able to work on public holidays\nFresh graduates will also be considered as Dealer Trainee\n\nWe offer 5-day work week; excellent career development & prospects and a competitive package.\n\nInterested parties should send their application letter; full resume and stating present and expected salary with by e-mail\u00a0(Quoting the above position in the email subject.)\n\nInformation provided will be treated in strict confidence and only be used for recruitment-related purposes.", "employment_types": ["Full Time"], "selling_points": ["At least 1 years relevant experience", "Holder HKSI LE 1 & 2 or equivalent is preferable", "Fresh graduates will also be considered"], "locations": ["Central"], "categories": ["Banking / Finance", "Dealing & Trading"], "post_time": "2022-01-05T03:49:00Z", "salary": {"currency": null, "max": null, "min": null, "period": "hourly", "term": null}, "salary_visible": false, "title_keywords": ["dealer trainee", "dealer", "junior"], "responsibilities": ["customer enquiries", "risk monitoring", "maintain", "quality"], "requirements": {"degrees": ["degree holder"], "majors": ["finance", "business"], "languages": ["cantonese", "putonghua", "english", "chinese"], "language_level": ["good command"], "hard_skills": ["hksi", "analytical skills"], "soft_skills": ["self-motivated", "analytical skills", "communication", "result oriented", "team player", "interpersonal"], "languages_combined": [{"language": "cantonese", "language_level": ["good command"]}, {"language": "putonghua", "language_level": ["good command"]}, {"language": "english", "language_level": ["good command"]}, {"language": "chinese", "language_level": ["good command"]}]}, "experience_required": {"duration": ["at least 1 years"], "field": ["relevant experience"]}}, {"job_id": "100003009031345", "location_code": "hk", "company": "Computershare Hong Kong Investor Services Limited", "job_title": "Client Services Associate, Georgeson", "description": "Our client is one of the fastest growing Cryptocurrency Derivative Exchanges in the world\u00a0who is\u00a0looking to hire an HR & Admin Manager / Executive (C&B focus) to join their team in Hong Kong.\n\nLocation: Causeway Bay\n\n\nResponsibilities:\n\nPerform all rounded HR Generalist duties with a focus on compensation & benefits and daily operations.\nExecute C&B administrative duties including payroll and benefits administration, tax filing, MPF administration, leave administration and other HR related services.\nCompile regular HR related statistics and reports for management\u2019s review.\nMaintain HRIS system and ensure that records are up to date and accurate.\nAssist in formulating and implementing C&B programs including but not limited to annual salary and performance reviews, incentive and retirement schemes, insurance plans and budget planning.\nAssist in other ad hoc tasks and projects as assigned.\n\nRequirements:\n\nBachelor Degree in Human Resources or a business related discipline.\nAt least 3 years of C&B and administration experience.\nWell versed in Hong Kong Employment Ordinance and other HR related ordinances.\nStrong communication and stakeholder management skills.\nA strong team player, self-motivated and detail-oriented.\nStrong analytical skills with the ability to adopt a logical problem solving approach.\nAbility to think outside the box.\nHighly detail-oriented person with passion for customer service, able to multi-task and prioritise.\nProficiency in MS Office and HRIS applications.\nFluency in spoken and written English and Chinese (Mandarin and Cantonese).\n\nPersonal data provided by job applicants will be used strictly in accordance with the employer's personal data policies and for recruitment purposes only.", "employment_types": ["Full Time", "Permanent"], "selling_points": ["Great role for someone who enjoys client servicing", "A plus to have Japanese or Korean language skills", "Excellent culture, company benefits and perks!"], "locations": ["Wan Chai"], "categories": ["Banking / Finance", "Financial Services", "Dealing & Trading", "Asset Management"], "post_time": "2022-01-07T09:13:50Z", "salary": {"currency": null, "max": null, "min": null, "period": "monthly", "term": null}, "salary_visible": false, "title_keywords": ["client services associate"], "responsibilities": [], "requirements": {"degrees": [], "majors": [], "languages": [], "language_level": [], "hard_skills": [], "soft_skills": [], "languages_combined": []}, "experience_required": {"duration": [], "field": []}}, {"job_id": "100003009017693", "location_code": "hk", "company": "Chief Group Limited", "job_title": "Sales & Trading Specialist, Derivatives Business", "description": "Our client is an leading Internet Broker in HK, with SFC Type 1, 2, 4, 5, 9 License.\n\nJob Description\n\nCollaborate with senior leadership to understand the organizations goals and strategy related to staffing, recruiting, Compensation & Benefits and retention.\u00a0\nWork directly with business stakeholders and provide HRBP service including recruitment, employee relations, talent review, remuneration review, performance management, talent development etc.\nBe one of the driver on change and transformation initiatives,such as HRIS implementation project, etc.\nIdentify and implement employee engagement opportunities and activities to build and sustain a positive and productive workforce\nImplement and review HR policies and procedures to support the Company\u2019s needs\n\nJob Requirements\n\nBachelor\u2019s degree in HR, Business Management or related disciplines\n6+ years\u2019\u00a0solid experience in Human Resources management and HRIS\nFamiliar with Hong Kong Employment ordinance\nResponsible, agile, adaptive to changes and resilient\nGood command of both spoken and written English and Chinese, including Mandarin\nProficiency in MS Office applications, particularly Excel", "employment_types": ["Full Time", "Permanent"], "selling_points": ["Excellent development opportunities", "Attractive package", "Training Sponsorship"], "locations": ["Sheung Wan"], "categories": ["Banking / Finance", "Financial Services", "Dealing & Trading", "Others"], "post_time": "2022-01-04T01:44:30Z", "salary": {"currency": null, "max": null, "min": null, "period": "monthly", "term": null}, "salary_visible": false, "title_keywords": ["specialist", "sales"], "responsibilities": ["collaborate with", "management", "policies", "hr", "review", "procedures", "implementation", "recruitment"], "requirements": {"degrees": ["degree", "bachelor"], "majors": ["related disciplines", "business"], "languages": ["english", "chinese", "mandarin"], "language_level": ["good command"], "hard_skills": ["business management", "excel", "hong kong employment ordinance", "agile", "ms office"], "soft_skills": ["agile", "responsible"], "languages_combined": [{"language": "english", "language_level": ["good command"]}, {"language": "chinese", "language_level": ["good command"]}, {"language": "mandarin", "language_level": ["good command"]}]}, "experience_required": {"duration": ["6+ years"], "field": ["management", "human resources"]}}, {"job_id": "100003009017675", "location_code": "hk", "company": "Chief Group Limited", "job_title": "Executive, Investment Service", "description": "Our client, one of the AI-driven pharmaceutical R&D companies located at Science Park is recruiting a high-caliber candidate joining their HK office. A job description is as follows: -\u00a0\n\n\nDegree holder in any disciplines\u00a0\nMinimum a few years of secretarial / PA working experience (fresh graduate maybe considered)\nGood command of spoken & written English and Chinese (Cantonese & Mandarin)\u00a0\nGood interpersonal & communication skill\u00a0\nHands on experience in MS office and google\u00a0\nConfident in serving senior management executives and expatriates\u00a0\nImmediate available or short notice for interview and work\u00a0\u00a0\n\nPersonal data provided by job applicants will be used strictly in accordance with the employer's personal data policies and for recruitment purposes only.", "employment_types": ["Full Time", "Permanent"], "selling_points": ["Professional investment service", "Career development & learning opportunities", "Scholarships & training Sponsorship"], "locations": ["Not Specified"], "categories": ["Banking / Finance", "Financial Services", "Dealing & Trading", "Others", "Student / Fresh Graduate / No Experience"], "post_time": "2022-01-04T01:40:29Z", "salary": {"currency": null, "max": null, "min": null, "period": "monthly", "term": null}, "salary_visible": false, "title_keywords": ["executive"], "responsibilities": ["policies", "communication", "recruitment", "personal data", "senior management"], "requirements": {"degrees": ["fresh graduate", "degree holder"], "majors": ["any disciplines"], "languages": ["cantonese", "english", "chinese", "mandarin"], "language_level": ["good command"], "hard_skills": ["r&d", "ms office", "ai"], "soft_skills": ["confident", "communication skill", "driven", "hands on", "interpersonal"], "languages_combined": [{"language": "cantonese", "language_level": ["good command"]}, {"language": "english", "language_level": ["good command"]}, {"language": "chinese", "language_level": ["good command"]}, {"language": "mandarin", "language_level": ["good command"]}]}, "experience_required": {"duration": [], "field": ["secretarial"]}}, {"job_id": "100003009025012", "location_code": "hk", "company": "CSC Securities (HK) Ltd", "job_title": "Administrative Assistant in Brokerage Department (5 days work)", "description": "Responsibilities:\n- Provide clerical and operation support to Brokerage Department.\n- Assist in handling account opening document and provide customer services.\n- Prepare daily, weekly and monthly Sales Analysis Reports.\n- Assist in IPO / placement subscription and allotment.\n- Assist in administrative work and ad hoc duties assigned by supervisors.\n\n\nRequirements:\n- Diploma holder or above, major in business related disciplines.\n- 1-2 years' relevant working experience in banking or finance field, fresh graduate or candidates without relevant experience will also be considered.\n- Licensed with SFC \"Type 1- Dealing in securities\" is preferred.\n- PC knowledge and Chinese word & excel processing is essential.\n- Good command of spoken and written English, Cantonese & Mandarin.\n\n\nWe offer competitive remuneration packages to the right candidate.\u00a0 Please send your application with full career details, current and expected salary to us by e-mail or by mail to: The Human Resources Department, CSC Securities (HK) Limited, 3/F, FWD Financial Centre, 308 Des Voeux Road Central, Hong Kong.\n\n\nData collected would be used for recruitment purpose only and will be retained for not more than 2 years.", "employment_types": ["Full Time", "Permanent"], "selling_points": ["Fresh graduates will be considered", "Licensed with SFC Type 1 is preferred", "Immediately available is preferred"], "locations": ["Sheung Wan"], "categories": ["Banking / Finance", "Dealing & Trading", "Others", "Student / Fresh Graduate / No Experience", "Sales, CS & Business Devpt", "Sales Administration"], "post_time": "2022-01-06T03:08:52Z", "salary": {"currency": null, "max": null, "min": null, "period": null, "term": null}, "salary_visible": false, "title_keywords": ["administrative assistant"], "responsibilities": ["ad hoc duties", "administrative work", "analysis reports", "brokerage", "account opening", "customer services"], "requirements": {"degrees": ["diploma holder", "fresh graduate"], "majors": ["related disciplines", "finance", "business"], "languages": ["cantonese", "english", "chinese", "mandarin"], "language_level": ["good command"], "hard_skills": ["excel", "pc knowledge", "processing", "word"], "soft_skills": [], "languages_combined": [{"language": "cantonese", "language_level": ["good command"]}, {"language": "english", "language_level": ["good command"]}, {"language": "chinese", "language_level": []}, {"language": "mandarin", "language_level": ["good command"]}]}, "experience_required": {"duration": ["1-2 years"], "field": ["finance", "relevant experience", "relevant working experience", "banking"]}}]