[{"job_id": "100003009052277", "location_code": "hk", "company": "Surrich International Company Limited", "job_title": "\u6295\u8d44\u52a9\u7406 Research Assistant", "description": "1\uff09\u534f\u52a9\u6295\u8d44\u7ecf\u7406\u505a\u597d\u6743\u76ca\u5e02\u573a\u548c\u503a\u5238\u5e02\u573a\u7684\u6295\u8d44\u7814\u7a76\uff0c\u534f\u52a9\u5236\u5b9a\u80a1\u7968\u3001\u503a\u5238\u7684\u6295\u8d44\u8ba1\u5212\u3001\u6295\u8d44\u7b56\u7565\u3002\n\nAssist investment managers in the investment research of equity market and bond market, including formulating investment plans and investment strategies for stocks and bonds.\n\n2\uff09\u8fdb\u884c\u884c\u4e1a\u548c\u516c\u53f8\u7684\u57fa\u672c\u9762\u7814\u7a76\uff0c\u6316\u6398\u6295\u8d44\u673a\u4f1a\uff1b\n\nFollow up, research and analyze the fundamentals of industries and companies, and explore investment opportunities;\n\n3\uff09\u534f\u52a9\u6295\u8d44\u7ecf\u7406\u8ddf\u8e2a\u6301\u4ed3\u4e2a\u80a1\uff0c\u5e76\u63d0\u51fa\u6295\u8d44\u5efa\u8bae\uff1b\n\nHelp investment managers keep track of individual stocks held and make investment recommendations independently;\n\n4\uff09\u4fdd\u6301\u4e0e\u5e02\u573a\u4e2d\u5176\u4ed6\u673a\u6784\u6295\u8d44\u8005\u3001\u4e0a\u5e02\u516c\u53f8\u3001\u7814\u7a76\u5458\u7684\u7d27\u5bc6\u8054\u7cfb\u548c\u6c9f\u901a\uff1b\n\nMaintain close contact and communication with other institutional investors, listed companies, and researchers in the market;\n\n5\uff09\u5b8c\u6210\u90e8\u95e8\u548c\u516c\u53f8\u4ea4\u529e\u7684\u5176\u4ed6\u4e8b\u9879\u3002\n\nOrganize the implementation and completion of other matters assigned by the department and the company.", "employment_types": ["Full Time"], "selling_points": ["\u91cd\u70b9\u9662\u6821\u91d1\u878d\u53ca\u76f8\u5173\u4e13\u4e1a\u7855\u58eb\u53ca\u4ee5\u4e0a\u5b66\u5386\uff1b", "\u5bf9\u8bc1\u5238\u6295\u8d44\u4e1a\u52a1\u53ca\u6295\u8d44\u7ba1\u7406\u5de5\u4f5c\u62b1\u6709\u70ed\u5ff1\uff0c\u5177\u6709\u826f\u597d\u7684\u7814\u7a76\u3001\u5206\u6790\u3001\u5224\u65ad\u80fd\u529b\uff1b", "\u5177\u6709\u656c\u4e1a\u7cbe\u795e\uff0c\u6709\u8f83\u5f3a\u7684\u6c9f\u901a\u4ea4\u6d41\u3001\u56e2\u961f\u534f\u4f5c\u7b49\u80fd\u529b\uff0c\u5177\u6709\u8f83\u5f3a\u7684\u518d\u5b66\u4e60\u80fd\u529b\u3002"], "locations": ["Wan Chai"], "categories": ["Banking / Finance", "Investment", "Equities / Capital Markets", "Others"], "post_time": "2022-01-17T02:40:07Z", "salary": {"currency": null, "max": null, "min": null, "period": "monthly", "term": null}, "salary_visible": false, "title_keywords": ["research assistant"], "responsibilities": ["investment strategies", "implementation", "communication", "maintain", "contact", "plans"], "requirements": {"degrees": [], "majors": [], "languages": [], "language_level": [], "hard_skills": ["make"], "soft_skills": ["communication", "independently"], "languages_combined": []}, "experience_required": {"duration": [], "field": []}}, {"job_id": "100003009040268", "location_code": "hk", "company": "SBI China Capital Holdings Limited", "job_title": "Vice President, Equity Capital Market (ECM)", "description": "We offer attractive remuneration package,\u00a05-day work, competitive fringe benefits (wedding leave, body check, group medical insurance, dental insurance etc.) and excellent career development opportunity to the right candidate.\n\n\nResponsibilities\u00a0\n\nPrepare various investment and market reports on different companies, mainly focusing on China/HK\u00a0 Consumer Sector;\nProvide support to our research team for the daily stock commentary in Chinese and English;\nConduct research and analysis of industries/companies independently and provide analysis reports\nProvide research supports to institutional clients and top management;\nAssist in ad hoc projects and assignments.\n\n\n\n\u00a0Requirements\n\nBachelor degree or above in Finance, Economics, Accounting or a related discipline with\u00a01-2\u00a0years of relevant experiences in a sell side or buy side institutions;\nProficient in managing Microsoft applications in MS Office and experience in handling Bloomberg is an advantage\nGood communication and strong sense of responsibility\nExcellent command of written and spoken English and Chinese (including Mandarin)\nCFA candidate is an advantage\n\nInterested parties please send CV, to the Human Resources Department by clicking \"Apply Now\".\n\nApplicants not invited for interviews within six weeks may consider their applications unsuccessful. Our Company is an equal opportunity employer. Personal data collected will be used for recruitment purpose only.\n\nAll information provided will be treated confidentially.", "employment_types": ["Full Time"], "selling_points": ["Type 1 and 4 SFC License holder", "Equity Capital Market (ECM)", "Holder of IANG visa welcome"], "locations": ["Central"], "categories": ["Banking / Finance", "Equities / Capital Markets"], "post_time": "2022-01-12T02:03:48Z", "salary": {"currency": null, "max": null, "min": null, "period": "monthly", "term": null}, "salary_visible": false, "title_keywords": ["vice president"], "responsibilities": ["provide support", "management", "analysis reports", "analysis", "reports", "ad hoc projects", "conduct research"], "requirements": {"degrees": ["degree or above", "bachelor"], "majors": ["finance", "economics", "accounting"], "languages": ["english", "chinese", "mandarin"], "language_level": ["excellent"], "hard_skills": ["cfa", "bloomberg", "microsoft applications", "ms office"], "soft_skills": ["communication", "sense of responsibility"], "languages_combined": [{"language": "english", "language_level": ["excellent"]}, {"language": "chinese", "language_level": ["excellent"]}, {"language": "mandarin", "language_level": ["excellent"]}]}, "experience_required": {"duration": ["1-2 years"], "field": ["related", "finance", "accounting"]}}, {"job_id": "100003009045873", "location_code": "hk", "company": "Yue Xiu Securities Holdings Limited", "job_title": "Research Analyst , Consumer sector", "description": "Responsibilities\nHandle finance projects including IPOs, mergers and acquisitions, and other management advisory projects\n\u00a0Support and communicate in the internal control, auditing, accounting and tax assignments of the projects\nAssist in deals support, such as reviewing target financials, business operation materials and involve in liaising deals structure\nLiaise with other professional parties to support the implementation of projects\n\u00a0Perform ad-hoc assignments\n\nRequirements\n\nDegree holder or above in Accounting, Finance, Business Administration is preferred\n1-2 years working experience in accounting firm\n\u00a0Good command of spoken and written English, Mandarin and Cantonese\n\u00a0Proficiency in Excel\n\u00a0Hardworking and willing to learn new knowledge on top of accounting\n\u00a0Immediate available preferred\nFresh graduates will also be considered\u00a0\nA good opportunity to allow audit junior to transit to capital market\n\nWe offer\n\n\u00a05-days work\n\u00a0Study and examination leave\n\u00a0Discretionary bonus\nDouble pay\nAnnual leave\n\nInterested parties please send your resume with expected salary and availability by clicking \"Apply Now\". All personal data collected will be used for recruitment purpose only.", "employment_types": ["Full Time", "Part Time", "Permanent"], "selling_points": ["Investment and market reports,Consumer Sector", "1-2 years of research experience", "Bachelor degree or above"], "locations": ["Wan Chai"], "categories": ["Banking / Finance", "Analyst", "Financial Services", "Equities / Capital Markets"], "post_time": "2022-01-13T08:59:35Z", "salary": {"currency": null, "max": null, "min": null, "period": "monthly", "term": null}, "salary_visible": false, "title_keywords": ["research analyst"], "responsibilities": ["tax", "business operation", "management", "ad-hoc assignments", "implementation of projects", "liaise with", "auditing", "internal control"], "requirements": {"degrees": ["degree holder"], "majors": ["finance", "accounting", "business administration"], "languages": ["cantonese", "english", "mandarin"], "language_level": ["good command"], "hard_skills": ["excel"], "soft_skills": ["willing to learn", "hardworking"], "languages_combined": [{"language": "cantonese", "language_level": ["good command"]}, {"language": "english", "language_level": ["good command"]}, {"language": "mandarin", "language_level": ["good command"]}]}, "experience_required": {"duration": ["1-2 years"], "field": ["accounting"]}}, {"job_id": "100003009050209", "location_code": "hk", "company": "Capital Advisory Limited", "job_title": "Associate \u2013 Merger & Acquisition", "description": "Reporting to the Team Head, you will provide support on User Acceptance Test (UAT) and Quality Assurance (QA) in different projects with key focus on e-banking and mobile banking. You will assist in designing UAT test cases and performing UAT testing according to the pre-defined test cases.\nTo meet the challenge, you should have the following qualifications and attributes:\nMatriculated or attained the HKDSE, preferably with 1-2 years of work experience\nKnowledge of general banking products and experience of software testing is preferred\nA team player with good interpersonal skill\nCandidate with more experience will be considered as Test Specialist.\n* Fresh graduates of Industrial / System Engineering / Management / IT or other related disciplines are welcome to apply\nPlease note that only shortlisted candidates will be notified.", "employment_types": ["Full Time", "Permanent"], "selling_points": ["Study and examination leave;  5-days work", "Discretionary bonus; Annual leave ; Bank holiday", "Sheung Wan MTR station; Double pay"], "locations": ["Sheung Wan"], "categories": ["Accounting", "Consulting", "Banking / Finance", "Dealing & Trading", "Equities / Capital Markets"], "post_time": "2022-01-14T09:56:47Z", "salary": {"currency": "HKD", "max": 24999, "min": 20000, "period": "monthly", "term": null}, "salary_visible": true, "title_keywords": ["associate"], "responsibilities": ["reporting", "provide support", "management", "uat", "software", "quality", "designing", "uat testing", "testing", "banking"], "requirements": {"degrees": ["hkdse"], "majors": [], "languages": [], "language_level": [], "hard_skills": ["mobile", "focus"], "soft_skills": ["focus", "team player", "interpersonal skill"], "languages_combined": []}, "experience_required": {"duration": ["1-2 years"], "field": ["testing", "banking"]}}, {"job_id": "100003009047780", "location_code": "hk", "company": "China Everbright Securities International Company Limited", "job_title": "Senior / Analyst, Derivatives Operations (Settlement)", "description": "Quantitative Research for Systematic Trading\n\nThe role of the QR Systematic Trading group is to identify opportunities to transform, automate and optimize our trading operations and to define and implement cutting-edge next generation analytics to support this business transformation. We cover all equities businesses and work closely with traders to develop data-driven solutions such as algorithmic strategies (high to low frequency), trading signals, risk models, portfolio optimization, flow categorization and clustering - and to combine them into automated trading processes or trading algorithms.\n\nWe are looking for a strong candidate to support APAC Volatility, Delta 1 and Internal Market Making desks. Communication skills and drive are critical for this role as we expect the candidate to actively engage with the business and act as a culture carrier for modern data-driven methods and business automation.\n\nRoles And Responsibilities Include\n\nWork closely with Equity Volatility trading desks to build analytics and data-driven processes that automate and optimize derivatives trading quantitatively. This includes: alpha research for volatility, optimal hedging for option portfolios, listed option algorithmic execution, derivatives market making, volatility analytics\nBuild trading analytics and algorithmic trading strategies such as portfolio optimization, index arbitrage, statistical arbitrage and market making strategies (on Equity cash, Futures, ETFs) for the Delta 1 and Cash trading desks.\nIdentify business opportunities and contribute to the entire lifecycle from idea generation to production: perform research, design prototype, implement analytics and strategies, monitor daily usage and analyze performance\nSupport trading activity by investigating model and algorithm behavior (scenarios and post trade analysis, historical behavior)\nDevise hedging and trading strategies and build execution logic\nQualifications\n\nPhD or Master's Degree in a quantitative discipline from a top-tier institution\nExperience in systematic quantitative trading in Equity or related asset classes\nStrong written and verbal communication skills, ability to convey the ideas behind complex research in a clear and precise manner\nA thorough understanding of algorithmic trading, market making, index and statistical arbitrage\nGood expertise in statistical modelling & optimization, including standard models, linear, convex & conic optimization)\nA strong coding background with proficiency in Python and relevant quantitative packages (numpy, pandas). Ability to manipulate and analyze complex, large scale, high-dimensionality data from multiple sources. Knowledge of KDB/Q expected.\nKnowledge of derivatives pricing and risk management theory (vanilla options and volatility products) is a plus\nWe recognize that our people are our strength and the diverse talents they bring to our global workforce are directly linked to our success. We are an equal opportunity employer and place a high value on diversity and inclusion at our company. We do not discriminate on the basis of any protected attribute, including race, religion, color, national origin, gender, sexual orientation, gender identity, gender expression, age, marital or veteran status, pregnancy or disability, or any other basis protected under applicable law. In accordance with applicable law, we make reasonable accommodations for applicants' and employees' religious practices and beliefs, as well as any mental health or physical disability needs.\n\nInterested parties please click \u201cApply Now\u201d to apply job.\n\nAll applications applied through our system will be delivered directly to the advertiser and privacy of personal data of the applicant will be ensured with security.", "employment_types": ["Full Time", "Permanent"], "selling_points": [], "locations": ["Causeway Bay"], "categories": ["Banking / Finance", "Equities / Capital Markets", "Others", "Order Processing & Operation / Settlement"], "post_time": "2022-01-14T04:30:46Z", "salary": {"currency": null, "max": null, "min": null, "period": "monthly", "term": null}, "salary_visible": false, "title_keywords": ["analyst", "operations"], "responsibilities": ["management", "clustering", "ideas", "identify business opportunities", "data", "operations", "analysis", "monitor", "design", "develop", "communication", "coding"], "requirements": {"degrees": ["degree", "master"], "majors": [], "languages": [], "language_level": [], "hard_skills": ["python", "make", "analysis", "plus"], "soft_skills": ["communication skills", "cutting-edge", "systematic", "clear", "diverse", "thorough", "precise", "driven"], "languages_combined": []}, "experience_required": {"duration": [], "field": ["related", "trading"]}}, {"job_id": "100003009047361", "location_code": "hk", "company": "JPMorgan Chase Bank, N.A.", "job_title": "CIB QR - Quantitative Research - Systematic Trading - Vice President", "description": "Responsibilities:\n\nParticipate in generating growth strategy for derivative products like crypto exchange or financial products and carry out execution\nBe sharp and sensitive to industry developments, monitor feedback from communities and conduct corresponding solutions\nSupport to develop campaign strategies (objective, process, execution and reporting) to acquire and retarget users\nHandle back office and operation and provide operation reports to CEO and Shareholders\nSupport other business units with customer liaison, accurately document customer requests and advice and provide feedback to the management team\nQA the site to ensure customer facing content and merchandising are accurate and clearly stated\nSupport any special cases or ad hoc tasks\nBuild cohesion and connectivity between the business team, engineering team and compliance team\n\nRequirements:\n\n5-year work experiences or above at a financial institution, VC-funded tech start-up or a high-growth technology company is preferred\nAbility to manage and execute multiple work streams and have an owner\u2019s mindset \u201croll up your sleeves\u201d\nExcellent organizational and managerial skills\nFluency in spoken and written Mandarin and English\nPositive, enthusiastic and passionate for customer service and crypto industry\nStrong sense of team mentality with high level of honesty and integrity\nStrong communication skills, fast learner and able to meet deadlines\nPersonal or professional experience with cryptocurrency is definitely a plus", "employment_types": ["Full Time"], "selling_points": [], "locations": ["Not Specified"], "categories": ["Banking / Finance", "Equities / Capital Markets", "Others", "Management", "General Management"], "post_time": "2022-01-14T02:54:28Z", "salary": {"currency": null, "max": null, "min": null, "period": "monthly", "term": null}, "salary_visible": false, "title_keywords": ["vice president"], "responsibilities": ["reporting", "management team", "compliance", "monitor", "back office", "merchandising", "develop", "ad hoc tasks", "reports", "customer requests"], "requirements": {"degrees": [], "majors": [], "languages": ["english", "mandarin"], "language_level": ["fluency"], "hard_skills": ["plus", "crypto", "vc", "cryptocurrency"], "soft_skills": ["passionate", "communication skills", "organizational", "integrity", "customer service", "enthusiastic", "meet deadlines", "fast learner", "positive"], "languages_combined": [{"language": "english", "language_level": ["fluency"]}, {"language": "mandarin", "language_level": ["fluency"]}]}, "experience_required": {"duration": ["5-year"], "field": ["tech", "financial"]}}, {"job_id": "100003009049848", "location_code": "hk", "company": "Aloha Fintech Limited", "job_title": "Operations Manager (Financial / Fintech)", "description": "Job Responsibilities:\n\nCaptured the market price from Bloomberg and Reuters to feed into the valuation systems\nAnalyse and execute the corporate action event (dividend, spin off, shares split etc)\nHandle the research and implementation of corporate actions for equities (e.g. increases and decreases of capital stocks, IPOs, M&A activities, dividend payments, stock splits, spin-offs, etc.)\nClosely work with Europe and North America offices regarding market data enquires\nTake charge of different projects to develop the team in Hong Kong\n\nRequirements:\n\nExperience in VBA/SQL will be an advantage\nKnowledge in treasury product's. and treasury system (such as Murex system) and financial statement analysis is an advantage\nFluent in English, Mandarin and Cantonese.\n1+ years relevant experience", "employment_types": ["Full Time"], "selling_points": ["Work life balance", "Great career path in Fintech / Blockchain", "Competitive remunerartion package"], "locations": ["Tsim Sha Tsui"], "categories": ["Banking / Finance", "Equities / Capital Markets", "Others", "Order Processing & Operation / Settlement"], "post_time": "2022-01-14T09:19:02Z", "salary": {"currency": null, "max": null, "min": null, "period": "monthly", "term": null}, "salary_visible": false, "title_keywords": ["operations manager"], "responsibilities": ["valuation", "systems", "implementation", "develop", "payments", "market data", "analyse"], "requirements": {"degrees": [], "majors": [], "languages": ["cantonese", "english", "mandarin"], "language_level": ["fluent"], "hard_skills": ["sql", "vba", "analysis"], "soft_skills": [], "languages_combined": [{"language": "cantonese", "language_level": ["fluent"]}, {"language": "english", "language_level": ["fluent"]}, {"language": "mandarin", "language_level": ["fluent"]}]}, "experience_required": {"duration": ["1+ years"], "field": ["sql", "relevant experience"]}}, {"job_id": "100003009046468", "location_code": "hk", "company": "Randstad Hong Kong Limited", "job_title": "Market Data Analyst - 32k", "description": "Ref: SA/OPD/140122DB/16\u00a0\n\nResponsibilities\n\nHandle daily settlement of\u00a0OTC Derivatives and Structured Products\nPrepare and check internal vouchers, trade confirmations and settlement & payment instructions\nLiaise with brokers and clients to perform pre-matching of settlement instructions\u00a0\nFollow up failed trade settlement cases with counterparties and clients\nPerform stock & cash reconciliation\nHandle enquiries and documents review requests from both internal and external parties\nParticipate in new projects and ad-hoc assignments including new products roll-out, system enhancement UAT, etc\n\nRequirements\n\nDegree holder in Economics, Banking and Finance, Business Administration or related disciplines preferred\n2 - 3 years' relevant experience in settlement, experience in OTC Derivatives & Structured Products preferred\nProficiency in MS Office applications and preferably Chinese Word Processing\nKnowledge in VBA macro, MS Access programming will be a strong advantage\nGood command of both written and spoken English and Chinese. Fluency in Putonghua preferred.\nCandidate with\u00a0more experience will be considered as 'Associate'\n\nWe offer a competitive remuneration package to the right candidate. If you are interested in the post, please send your resume together with your present and expected salaries by clicking \u201cApply Now\u201d.\u00a0\n\nFor more information about China Everbright Securities International Company Limited, please visit www.ebshk.com.\n\u00a0\n\n\nWe are an equal opportunity employer and welcome applications from all qualified candidates. All applications will be treated in the strictest confidence. Personal data provided will be used for recruitment purposes only. The job applicant will assume all or any risks arising out of or in connection with the job application transmission process prior to our actual receipt of the same including but not limited to accidental or unauthorized loss or disclosure of personal information, to which we will not be responsible in any way.\n\nUnder the Personal Data (Privacy) Ordinance, you may request access to, and / or correction of your personal data in relation to your application. If you wish to do so, please email to us.", "employment_types": ["Full Time", "Permanent"], "selling_points": ["Foreign Bank", "VBA/ SQL preferred", "1+ years experience"], "locations": ["Not Specified"], "categories": ["Banking / Finance", "Treasury", "Equities / Capital Markets", "Others"], "post_time": "2022-01-13T11:30:54Z", "salary": {"currency": "HKD", "max": 29999, "min": 20000, "period": "monthly", "term": null}, "salary_visible": true, "title_keywords": ["data analyst"], "responsibilities": ["uat", "ad-hoc assignments", "review", "internal and external parties", "handle enquiries", "payment", "liaise with"], "requirements": {"degrees": ["degree holder"], "majors": ["related disciplines", "finance", "economics", "business administration"], "languages": ["putonghua", "english", "chinese"], "language_level": ["fluency", "proficiency", "good command"], "hard_skills": ["vba", "macro", "chinese word processing", "programming", "ms office"], "soft_skills": ["structured"], "languages_combined": [{"language": "putonghua", "language_level": ["fluency"]}, {"language": "english", "language_level": ["good command"]}, {"language": "chinese", "language_level": ["proficiency", "good command"]}]}, "experience_required": {"duration": ["2 - 3 years"], "field": ["relevant experience"]}}, {"job_id": "100003009048851", "location_code": "hk", "company": "China Everbright Securities International Company Limited", "job_title": "Senior Analyst, OTC Products Operations (Settlement)", "description": "Reporting to the Fund Manager, you will:\n\nBe responsible for fixed income and equity trading for funds and client accounts\nWork as part of the investment team to provide real-time market colour, identify investment opportunities, and implement effective trades to derive profits\nAssist in the portfolio management of funds and client accounts\nAssist in client marketing and day to day client communication\nMaintain and develop new trading instruments and other relevant products to enhance investment returns\n\nRequirements:\n\n3 - 5 years of relevant trading experience in fixed income or equity\nPrefer degree in business, finance or any similar field;\nFamiliar with the fixed income and equity markets ecosystem\nSolid understanding of investment products, trading strategies and risk management\nAbility to work accurately under stress;\nFast learner, proactive and quick reaction to market changes\nFluent in English and Mandarin", "employment_types": ["Full Time", "Permanent"], "selling_points": [], "locations": ["Causeway Bay"], "categories": ["Banking / Finance", "Financial Services", "Equities / Capital Markets", "Order Processing & Operation / Settlement"], "post_time": "2022-01-14T07:27:14Z", "salary": {"currency": null, "max": null, "min": null, "period": "monthly", "term": null}, "salary_visible": false, "title_keywords": ["operations", "senior analyst"], "responsibilities": ["reporting", "management", "develop", "communication", "maintain", "investment returns"], "requirements": {"degrees": ["degree"], "majors": ["finance", "business"], "languages": ["english", "mandarin"], "language_level": ["fluent"], "hard_skills": ["investment products"], "soft_skills": ["communication", "proactive", "fast learner", "responsible"], "languages_combined": [{"language": "english", "language_level": ["fluent"]}, {"language": "mandarin", "language_level": ["fluent"]}]}, "experience_required": {"duration": ["3 - 5 years"], "field": ["trading"]}}, {"job_id": "100003009048019", "location_code": "hk", "company": "China Everbright Securities International Company Limited", "job_title": "Associate, Derivatives Operations (Settlement)", "description": "Ref: ASSO/OPD/140122DB/16\n\nResponsibilities\u00a0\u00a0\n\nPrepare and check internal vouchers, trade confirmations, settlement & payment instructions for listed derivatives (Futures, Options)\nHandle pre-matching of settlement instructions\nEnsure all trading processing (including Futures & Options settlement via DCASS terminal) are completed correctly and properly\nLiaise with internal and external counterparts (Exchanges, brokers etc.) on booking, position and settlement issues\nHandle inquiries from external and internal clients and take appropriate follow up actions\nConduct user acceptance test for system enhancement\nPerform ad-hoc duties as assigned by supervisor\u00a0\u00a0\u00a0\n\nRequirements\u00a0\u00a0\n\nHigher Diploma or above\n3 years or above settlement experience\u00a0in\u00a0financial industry\u00a0\nSolid experience in DCASS operations preferred\nSelf-disciplined and able to work independently\nGood command of both written and spoken English and Chinese.\u00a0 Fluency in Putonghua will be an advantage\nProficiency in MS Office and Chinese Word Processing\nCandidate with more experience will be considered as 'Senior Associate'\n\nWe offer a competitive remuneration package to the right candidate. If you are interested in the post, please send your resume together with your present and expected salaries by clicking \u201cApply Now\u201d.\u00a0\n\nFor more information about China Everbright Securities International Company Limited, please visit www.ebshk.com.\n\n\n\nWe are an equal opportunity employer and welcome applications from all qualified candidates. All applications will be treated in the strictest confidence. Personal data provided will be used for recruitment purposes only. The job applicant will assume all or any risks arising out of or in connection with the job application transmission process prior to our actual receipt of the same including but not limited to accidental or unauthorized loss or disclosure of personal information, to which we will not be responsible in any way.\n\nUnder the Personal Data (Privacy) Ordinance, you may request access to, and / or correction of your personal data in relation to your application. If you wish to do so, please email to us.", "employment_types": ["Full Time", "Permanent"], "selling_points": [], "locations": ["Causeway Bay"], "categories": ["Banking / Finance", "Equities / Capital Markets", "Order Processing & Operation / Settlement", "Wealth Management"], "post_time": "2022-01-14T04:32:00Z", "salary": {"currency": null, "max": null, "min": null, "period": "monthly", "term": null}, "salary_visible": false, "title_keywords": ["operations", "associate"], "responsibilities": ["payment", "booking", "ad-hoc duties", "liaise with", "settlement issues"], "requirements": {"degrees": ["higher diploma or above"], "majors": [], "languages": ["putonghua", "english", "chinese"], "language_level": ["fluency", "advantage", "proficiency", "good command"], "hard_skills": ["dcass", "chinese word processing", "ms office"], "soft_skills": ["work independently"], "languages_combined": [{"language": "putonghua", "language_level": ["fluency", "advantage"]}, {"language": "english", "language_level": ["good command"]}, {"language": "chinese", "language_level": ["proficiency", "good command"]}]}, "experience_required": {"duration": ["3 years"], "field": ["financial industry"]}}, {"job_id": "100003009048864", "location_code": "hk", "company": "China Everbright Securities International Company Limited", "job_title": "Assistant Vice President, OTC Products Operations (Settlement)", "description": "Responsibilities:\nFormulate the goals, objectives and business operations of the Private Trust Administration Department\nLead the private trust administration team for effective delivery of trust administration and customer relationship work\nReview and renew trust legal documents before execution\nProvide operational support to frontline business team\nCoordinate well with both internal and external stakeholders\nTrain and develop subordinates so that staff can perform up to the required standard and successors can be identified\nEnsure and improve efficiency and effectiveness of the team\nRequirements:\nDegree holder in law, accounting, business related discipline or possess relevant professional qualifications such as TEP, CPA or ACIS\nAt least 10 years of solid experience in handling trust administration with 5 years in supervisory role preferred\nGood knowledge in trust set-up and routine administrative operation\nFluency in both written and spoken English and Chinese, Putonghua is a must\nProficient in MS Office and Chinese word processing\nImmediately available is highly preferred\nPlease click \"Apply Now\" to submit your application.\nPersonal data collected will be used for recruitment purpose only.", "employment_types": ["Full Time", "Permanent"], "selling_points": [], "locations": ["Causeway Bay"], "categories": ["Banking / Finance", "Equities / Capital Markets", "Order Processing & Operation / Settlement", "Wealth Management"], "post_time": "2022-01-14T07:30:36Z", "salary": {"currency": null, "max": null, "min": null, "period": "monthly", "term": null}, "salary_visible": false, "title_keywords": ["operations", "assistant vice president"], "responsibilities": ["operational support", "operations", "review", "develop", "coordinate", "administration"], "requirements": {"degrees": ["degree holder"], "majors": ["business", "accounting", "law"], "languages": ["putonghua", "english", "chinese"], "language_level": ["fluency", "proficient"], "hard_skills": ["cpa", "chinese word processing", "ms office", "professional qualifications"], "soft_skills": [], "languages_combined": [{"language": "putonghua", "language_level": ["fluency"]}, {"language": "english", "language_level": ["fluency"]}, {"language": "chinese", "language_level": ["fluency", "proficient"]}]}, "experience_required": {"duration": ["at least 10 years", "5 years"], "field": ["supervisory", "administration"]}}, {"job_id": "100003009050828", "location_code": "hk", "company": "Bank of Communications Trustee Limited", "job_title": "Head of Private Trust Administration", "description": "Liaise, check and handle offshore markets settlement, such as bonds and unit trust settlement, dividend or interest distribution\nCheck and update share deposit / withdrawal entries, cash movement and G/L accounting entries\nReview corporate announcement to ensure entitlement details or corporate actions are recorded and to be done as scheduled\nPerform entitlements taking up and distribution of dividend, bonus, cash offer, open offer and warrants/rights etc.\nParticipate in User Acceptance Testing and other ad-hoc projects\nSecondary education or above with minimum 5 years\u2019 experience in shares operations / settlement of offshore markets\nFamiliar with CCASS operations\nKnowledge on liaising with Clearstream Banking Agent for settlement support is an advantage\nGood communication skills in both English and Chinese\n\n\n\nTo apply, interested parties please follow the application methods available in the Bank\u2019s career website https://www.publicbank.com.hk/en/aboutus/careeropportunities. You can send us your resume quoting our job reference number together with present & expected salary (a must) to the Human Resources Department by email or fax at 2815 3157 or by post to Human Resources Department, 12/F, Public Bank Centre, 120 Des Voeux Road Central, Hong Kong. You may also visit our career website for other career opportunities available within our Group.\n\nPersonal data collected will be used for recruitment purpose only and will be treated in accordance with the Bank\u2019s Personal Information Collection Statement, a copy of which has been available in the Bank\u2019s career website.", "employment_types": ["Full Time", "Permanent"], "selling_points": ["Lead the private trust administration", "Degree holder in law, accounting, business", "At least 10 years of solid experience"], "locations": ["Not Specified"], "categories": ["Banking / Finance", "Financial Services", "Equities / Capital Markets", "Order Processing & Operation / Settlement"], "post_time": "2022-01-14T11:31:01Z", "salary": {"currency": null, "max": null, "min": null, "period": "monthly", "term": null}, "salary_visible": false, "title_keywords": [], "responsibilities": ["liaise", "operations", "review", "liaising with", "testing", "communication", "banking", "ad-hoc projects"], "requirements": {"degrees": ["secondary education"], "majors": [], "languages": ["english", "chinese"], "language_level": ["good"], "hard_skills": ["ccass"], "soft_skills": ["communication skills"], "languages_combined": [{"language": "english", "language_level": ["good"]}, {"language": "chinese", "language_level": ["good"]}]}, "experience_required": {"duration": ["minimum 5 years"], "field": ["education"]}}, {"job_id": "100003009047775", "location_code": "hk", "company": "Public Bank (Hong Kong) Ltd", "job_title": "Shares Operations Officer (Ref: JD-SHO)", "description": "We offer attractive remuneration package,\u00a05-day work, competitive fringe benefits (wedding leave, body check, group medical insurance, dental insurance etc.) and excellent career development opportunity to the right candidate.\n\nResponsibilities\n\n\nWork closely with teammates\u00a0to go through whole process of deal execution\nBuild relationships with issuers and peers for more quality deals\nManage\u00a0existing clients and develop new investors\n\nRequirements\n\nDegree holder in Finance, Economics, Accounting or related discipline\nMinimum 1-3 years\u2019 relevant experience in\u00a0capital markets\nProficiency in computer applications such as Bloomberg, PowerPoint, Excel and Word\nGood communication skills of Chinese and English\nWillingness to work extra hours to meet deadline\n\n\u5d17\u4f4d\u8077\u8cac\n\n\u64c1\u6709\u826f\u597d\u7684\u9805\u76ee\u57f7\u884c\u80fd\u529b\u8207\u5408\u4f5c\u7cbe\u795e\n\u8207\u767c\u884c\u65b9\u53ca\u540c\u696d\u5efa\u7acb\u826f\u597d\u7684\u5408\u4f5c\u95dc\u4fc2\uff0c\u4ee5\u5f15\u5165\u66f4\u591a\u512a\u8cea\u9805\u76ee\n\u7dad\u6301\u5ba2\u6236\u95dc\u4fc2\uff0c\u4e26\u6709\u80fd\u529b\u767c\u5c55\u65b0\u7684\u5ba2\u6236\n\u5b8c\u6210\u9818\u5c0e\u4ea4\u8fa6\u7684\u5176\u4ed6\u5de5\u4f5c\n\n\u00a0\u4efb\u8077\u8981\u6c42\n\n\u5927\u5b78\u672c\u79d1\u53ca\u4ee5\u4e0a\u5b78\u6b77\uff0c\u91d1\u878d\u3001\u7d93\u6fdf\u3001\u6703\u8a08\u7b49\u76f8\u95dc\u5c08\u696d\n\u5177\u67091\u20143\u5e74\u8cc7\u672c\u5e02\u5834\u9805\u76ee\u76f8\u95dc\u5de5\u4f5c\u7d93\u9a57\n\u80fd\u719f\u7df4\u4f7f\u7528Bloomberg\u3001PowerPoint\u3001Excel\u548cWord\u7b49\u8fa6\u516c\u8edf\u4ef6\n\u826f\u597d\u7684\u4e2d\u82f1\u6587\u6e9d\u901a\u6280\u5de7\n\u6297\u58d3\u80fd\u529b\u5f37\uff0c\u5728\u898f\u5b9a\u7684\u6642\u9593\u5167\u5b8c\u6210\u5de5\u4f5c\u6216\u5fc5\u8981\u6642\u52a0\u73ed\u5b8c\u6210\u4efb\u52d9\n\nInterested parties please send CV, to the Human Resources Department by clicking \"Apply Now\".\n\nApplicants not invited for interviews within six weeks may consider their applications unsuccessful. Our Company is an equal opportunity employer. Personal data collected will be used for recruitment purpose only.\n\nAll information provided will be treated confidentially.", "employment_types": ["Full Time", "Permanent"], "selling_points": [], "locations": ["Not Specified"], "categories": ["Banking / Finance", "Investment", "Equities / Capital Markets", "Order Processing & Operation / Settlement"], "post_time": "2022-01-15T03:49:08Z", "salary": {"currency": null, "max": null, "min": null, "period": null, "term": null}, "salary_visible": false, "title_keywords": ["operations officer"], "responsibilities": ["quality", "develop"], "requirements": {"degrees": ["degree holder"], "majors": ["finance", "economics", "accounting"], "languages": ["english", "chinese"], "language_level": ["good"], "hard_skills": ["excel", "word", "bloomberg", "powerpoint"], "soft_skills": ["communication skills", "willingness to work"], "languages_combined": [{"language": "english", "language_level": ["good"]}, {"language": "chinese", "language_level": ["good"]}]}, "experience_required": {"duration": ["minimum 1-3 years"], "field": ["capital markets", "relevant experience"]}}, {"job_id": "100003009045872", "location_code": "hk", "company": "Yue Xiu Securities Holdings Limited", "job_title": "Associate /Senior Associate, Capital Markets Department", "description": "About the Company: KPay (kpay-group.com) is a leading digital payment gateway company founded in 2020 by a team of serial entrepreneurs who have successful exited their previous ventures. We currently have a hundred-person team based in Hong Kong. We have aggressive plans to expand across Asia next year and are looking to build out the strategy and investments team, which reports directly to the founders.\n\nOur culture is nimble, entrepreneurial, and fun.\n\nJob Duties:\n\u2022 Conduct company, industry, market, and economic research and monitoring\n\u2022 Financial modelling and analysis\n\u2022 Develop presentation materials in both English and Chinese\n\nJob Requirements :\n\u2022 Relevant work experience (under 5 years) in financial services (PE/VC/hedge funds), investment banking, strategy / management consulting, accounting, digital assets (crypto), or internet start-ups (in particular, fintech involved with payments and/or lending), big data\n\u2022 Excellent communication and interpersonal skills\n\u2022 Excellent written and spoken English and Chinese\n\u2022 Proficiency in MS Word, Excel, PowerPoint, and Chinese word processing\n\u2022 Ability to interact and build relationships with senior management\n\n", "employment_types": ["Full Time", "Permanent"], "selling_points": ["Capital markets", "Degree holder", "5-day work, attractive remuneration"], "locations": ["Wan Chai"], "categories": ["Banking / Finance", "Investment", "Dealing & Trading", "Equities / Capital Markets"], "post_time": "2022-01-13T08:59:35Z", "salary": {"currency": null, "max": null, "min": null, "period": "monthly", "term": null}, "salary_visible": false, "title_keywords": ["senior associate", "associate"], "responsibilities": ["analysis", "monitoring", "develop"], "requirements": {"degrees": [], "majors": [], "languages": ["english", "chinese"], "language_level": ["excellent", "proficiency"], "hard_skills": ["excel", "crypto", "vc", "chinese word processing", "powerpoint", "pe", "ms word"], "soft_skills": ["communication and interpersonal skills"], "languages_combined": [{"language": "english", "language_level": ["excellent"]}, {"language": "chinese", "language_level": ["excellent", "proficiency"]}]}, "experience_required": {"duration": ["5 years"], "field": ["management", "consulting", "financial services", "investment", "banking", "digital", "accounting"]}}, {"job_id": "100003009044302", "location_code": "hk", "company": "KPay Merchant Service Limited", "job_title": "Senior Research Analyst (Fintech/Digital Payment/SaaS)", "description": "The Role\n\nNon-sales client support role in our brokerage business.\n\nKey Accountabilities\n\nSupport our securities and derivatives brokerage services\nAssist and manage the daily operation of the brokerage team\nProvide customer services and execute trades (equities, derivatives, OTC, etc.)\nAssist in trading and dealing streamlining projects\n\nSkills & Experience\n\nDiploma or above in relevant disciplines\nStrong language skills including spoken Mandarin\nPractical knowledge in financial products\nAt least 3-5 years of experience in securities broker / bank\nSFC type 1 and 2 preferred\n\nOther Information\n\nNotes to applicants:\n1. Please apply in strict confidence with full resume, academic record, current and expected salaries.\n2. The personal data provided will be used for consideration of recruitment only. All personal data of unsuccessful candidate will be destroyed within 24 months.\n3. Candidates with Enhanced Competency Framework (ECF): please state on the CV.\n\nAbout BOCI\n\nAs a leading investment bank in China and Hong Kong region, the investment banking arm of Bank of China, BOC International Holdings Limited (\u201cBOCI\u201d), is now seeking highly motivated, creative and success-oriented professional who would like to pursue the career in our group.\u00a0", "employment_types": ["Full Time", "Permanent"], "selling_points": ["Fast growing fintech firm", "Newly establish team", "Great employment package"], "locations": ["Kwun Tong"], "categories": ["Banking / Finance", "Analyst", "Investment", "Equities / Capital Markets"], "post_time": "2022-01-13T03:42:39Z", "salary": {"currency": null, "max": null, "min": null, "period": "monthly", "term": null}, "salary_visible": false, "title_keywords": ["research analyst"], "responsibilities": ["brokerage", "daily operation", "customer services", "recruitment", "banking", "personal data"], "requirements": {"degrees": ["diploma or above"], "majors": [], "languages": ["mandarin"], "language_level": [], "hard_skills": [], "soft_skills": ["motivated", "confidence", "creative"], "languages_combined": [{"language": "mandarin", "language_level": []}]}, "experience_required": {"duration": ["at least 3-5 years"], "field": ["securities"]}}, {"job_id": "100003009042508", "location_code": "hk", "company": "China Tonghai Securities Limited", "job_title": "Associate / AVP / Vice President \u2013 Equity Capital Market", "description": "Job Responsibilities:\n\n\n\nAssess, structure and execute a wide range of Capital Market transactions, including but not limited, pre-IPO financing, IPO transactions, block trade, rights issues, new share issues, share placements, convertibles issues and other equity-linked transactions.\nPrepare documents for necessary internal approval.\nDevelop and expand client base including institutional fund houses, investment banks, listed companies and high-net-worth clients in local and PRC markets.\nPrepare business plans and pitch books to support the team in deal pitching.\nAssist roadshows and fund raising on Capital Market activities and ad hoc projects.\u00a0\n\nJob Requirements:\n\n\nBachelor degree holder with\u00a03 - 5 years of experience in capital market.\nHands-on experience in underwriting of Hong Kong IPO and Capital Market transactions (in particular, in the capacity of lead/sole underwriter/placing agent).\nReal-life experience in dealing with the exchange, the SFC and other brokers (in particular, submission to the exchange).\nSolid financial statement analysis, structuring and valuation skills.\nKnowledge in MS Excel formula and Bloomberg mnemonics.\nCFA level 1 is a plus.\nWorking knowledge in convertible securities is a plus.\nFluent written and oral Mandarin, Cantonese and English.\nAble to work as a team player while functioning independently.\nStrong initiative and follow through, organized, conscientious and efficient.\nProactive, efficient, and works well under pressure.\nGood connection with institutional clients is an advantage\nCandidates with more experience will also be considered\n\nWe offer attractive salary, benefits and 5-day workweek to the successful applicant. Please send your resume with present and expected salary to the Group Human Resources Manager. (Please quote the job reference number on the email subject line.)\u00a0\n\nPersonal Data collected will be used for recruitment purposes only.", "employment_types": ["Full Time", "Permanent"], "selling_points": ["5 days work at Central", "Education Allowance, Medical, Dental and Insurance", "Equity Capital Market experience"], "locations": ["Central"], "categories": ["Banking / Finance", "Financial Services", "Dealing & Trading", "Equities / Capital Markets"], "post_time": "2022-01-12T07:50:34Z", "salary": {"currency": null, "max": null, "min": null, "period": "monthly", "term": null}, "salary_visible": false, "title_keywords": ["vice president", "associate"], "responsibilities": ["business plans", "transactions", "develop", "client base", "ad hoc projects", "prepare documents", "support the team"], "requirements": {"degrees": ["bachelor degree holder"], "majors": [], "languages": ["cantonese", "english", "mandarin"], "language_level": ["fluent"], "hard_skills": ["plus", "bloomberg", "cfa", "analysis", "ms excel", "exchange"], "soft_skills": ["efficient", "organized", "oral", "independently", "under pressure", "work as a team", "hands-on", "conscientious", "proactive", "initiative"], "languages_combined": [{"language": "cantonese", "language_level": ["fluent"]}, {"language": "english", "language_level": ["fluent"]}, {"language": "mandarin", "language_level": ["fluent"]}]}, "experience_required": {"duration": ["3 - 5 years"], "field": ["underwriting"]}}, {"job_id": "100003009044825", "location_code": "hk", "company": "BOCI", "job_title": "Associate, Middle Office, Securities Brokerage", "description": "The Role\n\nMiddle office role between front and back office to facilitate efficient and effective brokerage business flow.\n\nKey Accountabilities\n\nWork closely with settlement teams for trade and product support\nMaintain daily operation of website, announcement on products and trading updates\nLiaise with front and back office to ensure an efficient and effective daily business flow\nFacilitate the whole business process for products including equities, derivatives and OTC\n\nSkills & Experience\n\nDegree in finance or business-related disciplines\n1-3 years of experience in bank / brokerage\nSFC type 1 and 2 preferred\nStrong language skills, including written Chinese and spoken Mandarin\nExcellent communication and interpersonal skills\nAbility to multitask and prioritize workload\nStrong in MS Excel, Word and PowerPoint\n\nOther Information\n\nNotes to applicants:\n1. Please apply in strict confidence with full resume, academic record, current and expected salaries.\n2. The personal data provided will be used for consideration of recruitment only. All personal data of unsuccessful candidate will be destroyed within 24 months.\n3. Candidates with Enhanced Competency Framework (ECF): please state on the CV.\n\nAbout BOCI\n\nAs a leading investment bank in China and Hong Kong region, the investment banking arm of Bank of China, BOC International Holdings Limited (\u201cBOCI\u201d), is now seeking highly motivated, creative and success-oriented professional who would like to pursue the career in our group.\u00a0", "employment_types": ["Full Time"], "selling_points": ["Middle office role for our brokerage business", "1-3 years of securities experience", "Knowledge in business flow in securities"], "locations": ["Sheung Wan"], "categories": ["Banking / Finance", "Dealing & Trading", "Equities / Capital Markets"], "post_time": "2022-01-13T06:25:58Z", "salary": {"currency": null, "max": null, "min": null, "period": "monthly", "term": null}, "salary_visible": false, "title_keywords": ["associate"], "responsibilities": ["brokerage", "daily operation", "teams", "back office", "website", "communication", "maintain", "business process", "recruitment", "banking", "liaise with", "personal data"], "requirements": {"degrees": ["degree"], "majors": ["related disciplines", "finance", "business"], "languages": ["chinese", "mandarin"], "language_level": [], "hard_skills": ["ms excel", "word", "powerpoint"], "soft_skills": ["efficient", "confidence", "prioritize", "communication and interpersonal skills", "motivated", "ability to multitask", "creative"], "languages_combined": [{"language": "chinese", "language_level": []}, {"language": "mandarin", "language_level": []}]}, "experience_required": {"duration": ["1-3 years"], "field": ["brokerage"]}}, {"job_id": "100003009043866", "location_code": "hk", "company": "Social Tech Investment HK Limited", "job_title": "Compliance Manager \u5408\u898f\u7d93\u7406\uff0830-60K\uff09", "description": "Responsibilities:\n\nProvide in-house legal support according to company directions, policies and procedures.\nConduct legal research for projects.\nUpdate compliance policies and procedures, and information on regulatory requirements.\nLiaise with external professionals and other regulatory bodies.\nHandle SFC licensing matters and enquiries and prepare various reports as required.\nConduct AML, compliance and operation risks review, including the monitoring of sales activities and perform account transaction review.\nPerform ad hoc projects as required.\n\nRequirement:\n\nCompliance experience related to fin-tech brokerage business is preferred.\nDegree holder or above in Law or related discipline is preferred.\n3 years' work experience in legal firm, experience as a Legal Executive in law firm or financial institutions is preferred.\nGood understanding of SFC codes and regulatory requirement of license 149 business.\nResponsible, well-organized and able to work independently.\nA team player with strong communication and analytical skills as well as high degree of professional maturity.\nKnowledge of securities and investment products and their operation is an advantage but not compulsory.\nFluent in both spoken and written English, Cantonese and Mandarin.\nLegal Degree\u00a0\u00a0is preferred.\n\n\u5d17\u4f4d\u8077\u8cac\uff1a\n\n\u6309\u96c6\u5718\u8b49\u7b56\u53ca\u6307\u793a\u63d0\u4f9b\u6cd5\u898f\u652f\u63f4\u3002\n\u70ba\u5404\u7a2e\u696d\u52d9\u9700\u6c42\u63d0\u4f9b\u5408\u898f\u8a55\u4f30\u3002\n\u7dad\u8b77\u53ca\u66f4\u65b0\u516c\u53f8\u5408\u898f\u8b49\u7b56\u53ca\u6d41\u7a0b, \u96a8\u6642\u7559\u610f\u76e3\u7ba1\u90e8\u9580\u8981\u6c42\u66f4\u65b0\u5408\u898f\u624b\u518a\u3002\n\u8207\u5916\u90e8\u76e3\u7ba1\u6a5f\u69cb\u53ca\u5c08\u696d\u8cc7\u683c\u6a5f\u69cb\u63a5\u6d3d\u3002\n\u8655\u7406\u8b49\u76e3\u724c\u7167\u76f8\u95dc\u4e8b\u52d9\u53ca\u8b49\u76e3\u67e5\u8a62\u4e26\u6309\u5176\u9700\u6c42\u63d0\u4f9b\u76f8\u95dc\u5831\u544a\u53ca\u6587\u4ef6\u3002\n\u57f7\u884c\u53cd\u6d17\u9ed1\u9322, \u5408\u898f\u53ca\u71df\u904b\u98a8\u96aa\u7b49\u8a55\u4f30, \u4f8b\u5982\u516c\u53f8\u92b7\u552e\u6d3b\u52d5, \u5e33\u6236\u4ea4\u6613\u76e3\u63a7\u7b49\u3002\n\u5354\u52a9\u516c\u53f8\u8655\u7406\u5176\u4ed6\u9700\u6c42\u3002\n\n\u8981\u6c42\uff1a\n\n\u91d1\u878d\u79d1\u6280\u5238\u5546\u76f8\u95dc\u5408\u898f\u7d93\u9a57\u512a\u5148\u3002\n\u5927\u5b78\u6216\u4ee5\u4e0a\u7562\u696d, \u6cd5\u5f8b\u53ca\u76f8\u95dc\u5b78\u4f4d\u512a\u5148\u3002\n3\u5e74\u5f8b\u6240\u6216\u8b49\u5238\u516c\u53f8\u5408\u898f\u90e8\u7d93\u9a57\u512a\u5148\u3002\n\u77ad\u89e3\u8b49\u76e3\u689d\u4f8b\u53ca\u8981\u6c42\u4e26\u5c0d1,4,9\u724c\u7167\u696d\u52d9\u4e4b\u5408\u898f\u8981\u6c42\u719f\u6089\u3002\n\u6709\u8cac\u4efb\u611f, \u505a\u4e8b\u6709\u689d\u7406\u53ca\u80fd\u7368\u7acb\u5de5\u4f5c\u3002\n\u5c08\u696d\u540c\u6642\u9700\u80fd\u8207\u516c\u53f8\u5718\u968a\u4ea4\u6d41\u6e9d\u901a\u3002\n\u5c0d\u8b49\u5238\u53ca\u5404\u7a2e\u6295\u8cc7\u7522\u54c1\u77ad\u89e3\u512a\u5148\u3002\n\u6d41\u5229\u82f1\u8a9e, \u7cb5\u8a9e\u53ca\u666e\u901a\u8a71\u3002\n\u6301\u6cd5\u5f8b\u5b78\u4f4d\u512a\u5148\u3002", "employment_types": ["Full Time"], "selling_points": ["20 Annual Leave\u3001Double Pay", "5 Day Work", "Compliance"], "locations": ["Admiralty"], "categories": ["Banking / Finance", "Equities / Capital Markets"], "post_time": "2022-01-13T02:14:50Z", "salary": {"currency": null, "max": null, "min": null, "period": "monthly", "term": null}, "salary_visible": false, "title_keywords": ["compliance manager"], "responsibilities": ["sales activities", "aml", "policies", "regulatory requirements", "compliance", "procedures", "review", "monitoring", "reports", "ad hoc projects", "liaise with"], "requirements": {"degrees": ["degree", "degree holder"], "majors": ["law"], "languages": ["cantonese", "english", "mandarin"], "language_level": ["fluent"], "hard_skills": ["investment products", "analytical skills", "codes"], "soft_skills": ["work independently", "responsible", "well-organized", "analytical skills", "communication", "team player"], "languages_combined": [{"language": "cantonese", "language_level": ["fluent"]}, {"language": "english", "language_level": ["fluent"]}, {"language": "mandarin", "language_level": ["fluent"]}]}, "experience_required": {"duration": ["3 years"], "field": ["legal", "related", "brokerage", "tech", "compliance", "business", "financial institutions"]}}, {"job_id": "100003009044607", "location_code": "hk", "company": "Eclipse Trading", "job_title": "Junior Trading Analyst", "description": "Junior Trading Analyst\n\nAt Eclipse, we monitor thousands of listed derivatives every day. Strong trading automation and analytics are crucial to ensure we capitalise on profitable opportunities. Our trading analysts are responsible for providing valuable tools along with data driven insights to enhance our trading. The successful candidate will be a junior member of the team based in our headquarters in Hong Kong.\n\nResponsibilities and Duties\u00a0\n\nWork with traders to identify and solve technical trading problems, and implement automated solutions\nWork with quants to conduct detailed trading research by collecting and analysing data from various sources\nWork with developers to improve the efficiency and algorithms of our in-house trading software\n\nWhat you offer\n\nBachelor's degree or higher in Mathematics, Engineering, Computer Science, Finance, or similar discipline\nDemonstrated quantitative and problem-solving abilities\nIntellectual curiosity and a genuine interest in trading and financial markets\nExperience in a \u201cgeneral purpose\u201d programming language - Python (preferred), Julia, R or Matlab\nExcellent written and verbal communication skills\nPreferred:\nexperience in the trading division of a proprietary trading company or bank\nexperience in data analysis or statistics, and SQL\nexperience using Excel and writing VBA\nexperience working in Linux environment\n\nWhat we offer\n\nTraining in derivatives pricing, trading strategies and systems\nA multi-cultural environment with reasonable work hours\nAn innovative company, encouraging the exploration of new technologies and ideas\nA flat management structure, where everyone\u2019s voice is valued\nHands-on experience in the most exciting part of the financial industry, with a direct impact on trading\n\nAll information provided will be treated in strict confidence and used solely for recruitment purposes.\nDue to the high number of responses that we receive, we are only able to respond to successful applicants.", "employment_types": ["Full Time", "Permanent"], "selling_points": ["Bachelor\u2019s degree in a quantitative discipline", "Training in derivatives pricing", "Competitive salary and bonus"], "locations": ["Causeway Bay"], "categories": ["Banking / Finance", "Analyst", "Dealing & Trading", "Equities / Capital Markets"], "post_time": "2022-01-13T04:49:41Z", "salary": {"currency": null, "max": null, "min": null, "period": "monthly", "term": null}, "salary_visible": false, "title_keywords": ["analyst", "junior"], "responsibilities": ["software", "data"], "requirements": {"degrees": [], "majors": [], "languages": [], "language_level": [], "hard_skills": [], "soft_skills": [], "languages_combined": []}, "experience_required": {"duration": [], "field": []}}, {"job_id": "100003009039452", "location_code": "hk", "company": "Avant Meats Company Limited", "job_title": "Director/VP, Finance (Startup)", "description": "Director/VP, Finance (Startup)\n\nThe role is suitable for a great team player who is also proactive, driven, results-oriented, a dedicated high performer, and a keen learner. It offers abundant space for fast personal and professional growth. The role is also earmarked for development into a leadership role with the Company.\n\nPosition:\n\n\nOne full-time role based in either Hong Kong or Singapore (with possible travel in the region and beyond)\nFor Hong Kong, applicants should have existing right to work in Hong Kong without requiring employment visa sponsorship\nFor Singapore, we can consider non-Singapore permanent residents if the applicant is already based in Singapore\n\n\nQualifications & Experiences:\n\nBachelor\u2019s degree with a minimum of 5 years of relevant work experience or a master\u2019s degree with a minimum of 2 years of relevant work experience. Major in finance, accounting, or economics preferred, candidates with law qualifications are highly advantageous\nCandidates with proven track records in start-up fundraising will be a great fit\nPrior work experiences in venture capital, private equity, family office or other institutional investors highly preferrable\nFamiliarity with different international accounting principles advantageous\nWorking understanding of tax systems of Hong Kong and Singapore welcome\nJob responsibilities:\n\nReport to the CEO:\n\nFundraising & Investor Relations\n\nConduct business and market analysis\nGenerate pitches and prepare due diligence materials, including financial models, cap tables, data rooms, investment memos, analyses of the market, product/technology business models, risk factors, competitive analyses, etc.\nFormulate a strategy for scouting potential investors\nUndertake guided and independent research to identify and screen potential investors\nSystemically build up a database of potential investors, prioritising investors to approach\nAnalyse target investors to ascertain the best way to connect and interact with potential investors\nInitiate leads and facilitate the whole process to drive investment in close cooperation with the CEO\nManage meetings and document flow with potential investors to accelerate deals\nProvide input to assist negotiations and review transaction documents\nManage fundraising process from leads to execution, provide ongoing update and review\nManage, administer, compile, and keep systematic records of corporate and investment documents and communications with investors\nSetup system for methodical compilation and preparation of monthly management accounts, investor reports, and reply to questions from investors in close cooperation with the CEO\nSupport other ad hoc business needs\nCorporate Finance\n\nStrategise mid-term and long-term funding approaches, corporate structure and capital structuring, capital budgeting, working capital and tax planning\nMonitor and take ownership of group cash flows, accounting by supervising daily bookkeeping activities, monthly and quarterly reporting, preparing financial statements and audits\n\nTraits:\nHigh level of integrity, respectfulness, loyalty, and professionalism\u00a0\nSustainability mission-driven and aligned\u00a0\nGreat team player\nExceptional communication and people skills including demonstrated ability to communicate with business executives and VC Partners\nExcellent analytical and quantitative skills with the ability to build financial models from scratch and conduct sensitivity studies\nKnowledge of cap tables, start-up financing, and growth metrics\nHighly conversant with practices and terms of investment transaction documents\nGreat skills with MS Excel and PowerPoint, CRMs, project management tools, etc.\nA demonstrated interest in technology\nAbility to thrive in an unstructured environment with incomplete data, fast pace and with a steep learning curve\nHighly organised, shown to meet tight deadlines along with consistently excellent accuracy and attention to detail\nAdvanced problem-solving skills and ability to think strategically, analytically, and creatively\n\nPragmatic, can-do spirit, able to go outside of comfort zone\nOpen to and can learn from feedback through developing steps for improvement\nSelf-motivated, inquisitive, durable, entrepreneurial in spirit\nAble to work independently and take full ownership of tasks and milestones, focusing on delivering timely results\nMethodical, detail-minded, and rigorous in documentation, including digitisation of data\n\n\u00a0Salary & Benefits:\n\n5-day week\nCompetitive compensation commensurate with qualifications and experiences\nMedical insurance\n\nPerformance-based discretionary bonus\nAll applications received will be used exclusively for employment purposes only. Please apply by sending your resume and a cover letter to us. Please include your expected salary and date of availability.\n", "employment_types": ["Full Time", "Permanent"], "selling_points": [], "locations": ["Shatin Area"], "categories": ["Banking / Finance", "Corporate Finance", "Equities / Capital Markets", "Management", "Top Executives (CEO, CFO, CTO, GM, MD etc.)"], "post_time": "2022-01-13T02:43:35Z", "salary": {"currency": null, "max": null, "min": null, "period": "monthly", "term": null}, "salary_visible": false, "title_keywords": ["director"], "responsibilities": ["supervising", "data", "budgeting", "financial statements", "communication", "database", "due diligence", "communications with", "ad hoc", "financial models", "monitor", "developing", "reports", "analyse", "setup", "report", "reporting", "management", "review", "market analysis", "audits", "documentation", "tax", "communicate with", "systems", "project management", "investment transaction", "planning"], "requirements": {"degrees": ["degree", "bachelor", "master"], "majors": [], "languages": [], "language_level": [], "hard_skills": ["vc", "setup system", "analysis", "scratch", "powerpoint", "project management", "ms excel", "documentation", "problem-solving skills", "go", "venture capital", "private equity"], "soft_skills": ["meet tight deadlines", "sensitivity", "communication", "team player", "leadership", "detail-minded", "independent", "keen", "integrity", "systematic", "work independently", "attention to detail", "think strategically", "can-do", "problem-solving skills", "driven", "self-motivated", "advanced", "timely", "project management", "learning", "organised", "methodical", "proactive"], "languages_combined": []}, "experience_required": {"duration": ["minimum of 2 years", "minimum of 5 years"], "field": ["venture capital"]}}, {"job_id": "100003009043965", "location_code": "hk", "company": "Ambition", "job_title": "Equities Project Manager - Global Investment Bank", "description": "APAC Market Coverage\nGrowing Equities Business\nGlobal Investment Bank\n\nOur client is a global investment banking group with a strong presence in Asia Pacific. To support a growing Equities and Prime business, our client is looking for a high calibre and experienced Project Manager to lead and execute regional new business initiatives across Asia for their Global Markets Operations.\n\nReporting to the Head of the team, you will be responsible for planning and implementing different new business ideas across different functions to support their growth. You will take on hands-on approach in all end to end aspects of the projects. You will also monitor and control post implementation environments. You must have a clear understanding of the whole operations trade lifecycle process within an investment banking environment, and be able to liaise with different stakeholders across the business in different markets. Attention to detail, ability to multi-task and strong relationship management are key skills necessary to be successful.\n\nTo qualify, individuals must possess:\n\n\nBachelor degree, with relevant project certifications (Six Sigma, Prince2, etc) would be preferred\nAt least 10 years' experience within investment banking, with a mixture of Operations / Middle Office AND Projects skills\nExcellent knowledge of front to back processes within an investment banking environment, running process, automation, and system improvement initiatives\nHighly efficient and energetic, not afraid to get their hands dirty\nMUST HAVE Equities and Prime Brokerage product exposure\nNear native English language fluency, Cantonese a plus\nAsian market coverage a pre-requisite\n\nInterested parties, please send your resume to Rhoda.Rivera@ambition.com.hk or click APPLY NOW quoting RR247301.\n\nDue to volume of applications, ONLY SHORTLISTED CANDIDATES WILL BE NOTIFIED.\n\n#LI-RR1\n#BuildingBetterFutures\n\n\nIf this job isn't quite right for you, but you know someone who would be great at this role, why not take advantage of our referral scheme? We offer HKD1000 in Apple gift cards for every referred candidate who we place in a role. Terms & Conditions Apply. https://www.ambition.com.hk/refer-a-friend", "employment_types": ["Full Time", "Permanent"], "selling_points": ["APAC Market Coverage", "Growing Equities Business", "Global Investment Bank"], "locations": ["Not Specified"], "categories": ["Banking / Finance", "Investment", "Equities / Capital Markets", "Order Processing & Operation / Settlement"], "post_time": "2022-01-13T02:36:47Z", "salary": {"currency": null, "max": null, "min": null, "period": "monthly", "term": null}, "salary_visible": false, "title_keywords": ["project manager"], "responsibilities": ["reporting", "control", "business initiatives", "ideas", "management", "operations", "brokerage", "monitor", "implementation", "banking", "liaise with", "planning"], "requirements": {"degrees": ["degree", "bachelor"], "majors": [], "languages": ["cantonese", "english"], "language_level": ["fluency", "native"], "hard_skills": ["six sigma", "plus"], "soft_skills": ["efficient", "multi-task", "responsible", "clear", "hands-on", "attention to detail", "energetic"], "languages_combined": [{"language": "cantonese", "language_level": ["native"]}, {"language": "english", "language_level": ["fluency", "native"]}]}, "experience_required": {"duration": ["at least 10 years"], "field": ["investment", "banking"]}}, {"job_id": "100003009037807", "location_code": "hk", "company": "CHINA INDUSTRIAL SECURITIES INTERNATIONAL FINANCIAL GROUP LIMITED", "job_title": "\u5168\u7403\u5e02\u573a\u90e8\u9500\u552e\u52a9\u7406", "description": "\uff08\u4e00\uff09\u5d17\u4f4d\u8077\u8cac\n\n1\u3001\u8207\u6a5f\u69cb\u92b7\u552e\u5718\u968a\u7dca\u5bc6\u5408\u4f5c\uff0c\u5354\u52a9\u9032\u884c\u65b0\u5ba2\u6236\u958b\u767c\uff0c\u5c24\u5176\u662f\u505a\u597d\u958b\u6236\u6a94\u7684\u6e96\u5099\u548c\u6e9d\u901a\u5de5\u4f5c\uff0c\u5354\u52a9\u89e3\u6c7a\u56e0\u5730\u57df\u5dee\u7570\u53ca\u76e3\u7ba1\u8981\u6c42\u4e0d\u540c\u7522\u751f\u7684\u76f8\u95dc\u554f\u984c\uff1b\n\n2\u3001\u8207\u9999\u6e2f\u5ba2\u670d\u90e8\u3001\u904b\u71df\u90e8\u53ca\u76f8\u95dc\u90e8\u9580\u5c0d\u63a5\uff0c\u63d0\u5347\u5ba2\u6236\u7684\u670d\u52d9\u9ad4\u9a57\uff0c\u5de5\u4f5c\u7bc4\u570d\u5305\u62ec\u4f46\u4e0d\u9650\u65bc\u5ba2\u6236\u958b\u6236\u53ca\u4ea4\u6613\u524d\u76f8\u95dc\u8a2d\u7f6e\u53ca\u984d\u5ea6\u7533\u8acb\u3001\u5e33\u6236\u6052\u5e38\u7dad\u8b77\u3001\u8cc7\u6599\u66f4\u65b0\u4fee\u6539\u53ca\u5176\u4ed6\u76f8\u95dc\u4e8b\u5b9c\uff1b\n\n3\u3001\u61c9\u5ba2\u6236\u5c0d\u4ea4\u6613\u5546\u8a55\u5be9\u7684\u9700\u8981\uff0c\u5354\u52a9\u5b8c\u6210\u76e1\u8abf\u53ca\u76f8\u95dc\u4e8b\u5b9c\uff0c\u4ee5\u53ca\u8ca1\u52d9\u8cc7\u6599\u5305\u9001\u53ca\u76f8\u95dc\u5b9a\u671f\u5be9\u6838\u4e8b\u5b9c\u3002\n\n4\u3001\u4f5c\u70ba\u7b26\u5408\u516c\u53f8\u5167\u63a7\u7ba1\u7406\u5236\u5ea6\u8981\u6c42\u7684\u586b\u5831\u4eba\uff0c\u5354\u52a9\u8655\u7406\u90e8\u9580\u76f8\u95dc\u7d71\u8a08\u3001\u5f59\u5831\u53ca\u81ea\u67e5\u5e95\u7a3f\u5de5\u4f5c\uff1b\n\n5\u3001\u5fc5\u8981\u6642\u5354\u52a9\u570b\u5167\u92b7\u552e\u70ba\u5ba2\u6236\u5b89\u6392\u9999\u6e2f\u53ca\u5883\u5916\u5730\u5340\u6703\u8b70\u3001\u8abf\u7814\u6d3b\u52d5\u6216\u76f8\u95dc\u63a5\u5f85\u4e8b\u5b9c\uff1b\n\n6\u3001\u6839\u64da\u9700\u8981\u57f7\u884c\u4efb\u4f55\u81e8\u6642\u5206\u914d\u5de5\u4f5c\u3002\n\n\uff08\u4e8c\uff09\u5d17\u4f4d\u8981\u6c42\n\n1\u3001\u672c\u79d1\u4ee5\u4e0a\u5b78\u6b77\uff0c\u7ba1\u7406\u3001\u91d1\u878d\u3001\u7d93\u6fdf\u5b78\u6216\u4efb\u4f55\u76f8\u95dc\u5b78\u79d1\u7684\u5b78\u4f4d\uff1b\n\n2\u30015\u5e74\u4ee5\u4e0a\u5de5\u4f5c\u7d93\u9a57\uff0c3\u5e74\u4ee5\u4e0a\u76f8\u95dc\u91d1\u878d\u6a5f\u69cb\u5de5\u4f5c\u7d93\u9a57\uff1b\n\n3\u3001\u5c0d\u9999\u6e2f\u8b49\u5238\u5e02\u5834\u548c\u7522\u54c1\u6709\u4e00\u5b9a\u7684\u77ad\u89e3\uff1b\n\n4\u3001\u826f\u597d\u7684\u6e9d\u901a\u3001\u6f14\u793a\u80fd\u529b\uff0c\u5305\u62ec\u66f8\u9762\u548c\u53e3\u982d\u8868\u9054\u65b9\u9762\uff1b\n\n5\u3001\u4e3b\u52d5\u3001\u8ca0\u8cac\uff0c\u5177\u5099\u8f03\u5f37\u7684\u5718\u968a\u5408\u4f5c\u80fd\u529b\u548c\u4eba\u969b\u4ea4\u5f80\u80fd\u529b\uff1b\n\n6\u3001\u5177\u5099\u826f\u597d\u7684MS Office \u96fb\u8166\u61c9\u7528\u6280\u80fd\uff0c\u7cbe\u901a\u4e2d\u82f1\u6587\u53e3\u8a9e\u548c\u66f8\u9762\u8a9e\uff0c\u5305\u62ec\u666e\u901a\u8a71\u3002", "employment_types": ["Full Time"], "selling_points": ["\u4e2d\u8d44\u8bc1\u5238\u516c\u53f8", "5\u5e74\u4ee5\u4e0a\u5de5\u4f5c\u7ecf\u9a8c", "\u91d1\u878d\u76f8\u5173\u4e13\u4e1a"], "locations": ["Sheung Wan"], "categories": ["Banking / Finance", "Retail Banking", "Equities / Capital Markets", "Sales, CS & Business Devpt", "Sales Administration"], "post_time": "2022-01-11T03:55:18Z", "salary": {"currency": null, "max": null, "min": null, "period": "monthly", "term": null}, "salary_visible": false, "title_keywords": [], "responsibilities": [], "requirements": {"degrees": [], "majors": [], "languages": [], "language_level": [], "hard_skills": [], "soft_skills": [], "languages_combined": []}, "experience_required": {"duration": [], "field": []}}, {"job_id": "100003009046104", "location_code": "hk", "company": "\u4ee5\u592a\u8b49\u5238\u6709\u9650\u516c\u53f8", "job_title": "Settlement Manager", "description": "Responsibilities\n\nHandle daily equities settlement tasks\nPerform settlement functions including trade matching, customers fund deposit and withdrawal, SI, corporate actions, and other CCASS operations\nAssist in system modification and UAT testing\nLiaise with brokers, in-house departments to follow up any issues and enquiry\nHandle ad-hoc projects as assigned\n\nRequirements\n\nDegree holder with 3-5 years relevant experience in the settlement of HK, China Connect & Global equities market\nFamiliar with the operation of CCASS and Hundsun settlement system\u00a0\nKnowledge in local regulatory and compliance guidelines in related issues is preferable\u00a0\nGood communication and interpersonal skills\u00a0\nProficiency in spoken and written Mandarin , Cantonese and English\u00a0", "employment_types": ["Full Time", "Permanent"], "selling_points": ["CCASS & DCASS", "Hundsun & 2Go", "HK & China Connect Global Equities Market"], "locations": ["Wan Chai"], "categories": ["Banking / Finance", "Dealing & Trading", "Equities / Capital Markets", "Order Processing & Operation / Settlement"], "post_time": "2022-01-13T09:37:41Z", "salary": {"currency": null, "max": null, "min": null, "period": "monthly", "term": null}, "salary_visible": false, "title_keywords": ["settlement manager"], "responsibilities": ["operations", "uat testing", "system modification", "liaise with", "ad-hoc projects"], "requirements": {"degrees": ["degree holder"], "majors": [], "languages": ["cantonese", "english", "mandarin"], "language_level": ["proficiency"], "hard_skills": ["ccass"], "soft_skills": ["communication and interpersonal skills"], "languages_combined": [{"language": "cantonese", "language_level": ["proficiency"]}, {"language": "english", "language_level": ["proficiency"]}, {"language": "mandarin", "language_level": ["proficiency"]}]}, "experience_required": {"duration": ["3-5 years"], "field": ["relevant experience"]}}, {"job_id": "100003009042621", "location_code": "hk", "company": "iCareer Consultants Limited", "job_title": "Investment Manager, Family Office", "description": "Job Description\nMy client is a boutique size family office which is looking for an investment manager to manage investment and deals on equities, stocks, bonds portfolio, etc. Knowledge in Bloomberg Terminal is a plus.\n\n\nJob Responsibilities\n\nManage portfolio consisted of public and private equities, bonds, stocks, and alternative assets and prove portfolio performance. Directly report to Director;\nPrepare in-depth market research on investment projects;\nPerform quantitative and qualitative analysis;\n\u2022 Provide trading ideas and get involved in investment process;\n\u2022 Assist in origination and evaluation of investment deals\nJob Requirements\nDegree in investment/ finance related disciplines preferred. Open to candidate with an education background in Law, Mathematics, Statistics, Physics and Engineering\nProficient in financial modelling. Knowledge in programming language such as Python is a bonus\nAt least 5 years experience in finance industry\nStrong cognitive skills and highly adaptable\nResult-oriented and concise communication\n\n\n\nOur client offers attractive remuneration package to the right candidate.\nPlease click \u201cAPPLY NOW\u201d to submit your application.\nOr apply through this link:\u00a0https://icareer.com.hk/job-126.php\n\nFor more jobs opportunities, please visit our website at www.icareer.com.hk\nAll information collected will be kept in strict confidence and will be used for recruitment purpose only.", "employment_types": ["Full Time", "Permanent"], "selling_points": ["Boutique Family Office", "Attractive remuneration package", "Friendly Working Environment"], "locations": ["Not Specified"], "categories": ["Banking / Finance", "Investment", "Private Banking", "Equities / Capital Markets"], "post_time": "2022-01-12T08:12:33Z", "salary": {"currency": null, "max": null, "min": null, "period": "monthly", "term": null}, "salary_visible": false, "title_keywords": ["investment manager"], "responsibilities": ["ideas", "analysis", "market research", "evaluation", "report"], "requirements": {"degrees": ["degree"], "majors": ["related disciplines", "finance"], "languages": [], "language_level": [], "hard_skills": ["python", "programming", "php"], "soft_skills": ["adaptable", "communication", "confidence", "result-oriented"], "languages_combined": []}, "experience_required": {"duration": ["at least 5 years"], "field": ["finance industry"]}}, {"job_id": "100003009048139", "location_code": "hk", "company": "Michael Page", "job_title": "Head of Equities Compliance - European Investment Bank", "description": "Independent contributor role to be part of the global markets compliance team. This role will focus on providing compliance advisory to the business for their equity derivatives and structured products business.\n\nClient Details\n\nMy client is one of the largest European based corporate investment banks in the world. They have businesses in global markets, private wealth management, asset management, and corporate bank. They have a strong footprint in Asia for their global markets business including fixed income, prime brokerages, equities, and structured products.\n\nDescription\n\nreport directly to the Head of Financial Markets Compliance APAC\nindependent contributor role\nwork closely with other global markets compliance colleagues\nprovide compliance advisory to the business for equity derivatives and structured products\nmain point of contact with the SFC\nbe aware and maintain updated compliance matters for their global markets business\n\nProfile\n\nminimum 10+ years of global markets compliance experience\npreferably strong product knowledge in equity derivatives and structured products\nopen to candidates within the legal field and/or securities/brokerage firms\nmust be able to work independently\nmust be currently located in HK\nfluency in english is a must\n\nJob Offer\n\nsenior level head role\nwork alongside high calibre staff for compliance\ngreat work culture\nglobal presence\n\nTo apply online please click the 'Apply' button below. For a confidential discussion about this role please contact Monica Wong on +852 2848 9520.", "employment_types": ["Full Time", "Permanent"], "selling_points": ["Looking for equities derivatives candidates !", "Looking for structured products candidates !", "senior level compliance role !"], "locations": ["Not Specified"], "categories": ["Banking / Finance", "Financial Services", "Equities / Capital Markets", "Professional Services", "Legal & Compliance"], "post_time": "2022-01-14T05:16:03Z", "salary": {"currency": "HKD", "max": null, "min": 160000, "period": "monthly", "term": null}, "salary_visible": true, "title_keywords": [], "responsibilities": ["management", "brokerage", "compliance", "asset management", "maintain", "contact", "report"], "requirements": {"degrees": [], "majors": [], "languages": ["english"], "language_level": ["fluency"], "hard_skills": ["focus"], "soft_skills": ["focus", "structured", "independent", "work independently"], "languages_combined": [{"language": "english", "language_level": ["fluency"]}]}, "experience_required": {"duration": ["minimum 10+ years"], "field": ["compliance"]}}, {"job_id": "100003009042782", "location_code": "hk", "company": "Guosen Securities (HK) Financial Holdings Company, Limited", "job_title": "Vice President - Debt Capital Market (DCM)", "description": "Responsibilities:\n\nTo provide Clients with pitches, proposals, presentations and analyses related to potential bond issuance\nTo assist in the creation of marketing material, execution of public fixed income issuance and financial models\nTo assist in providing clients with information pertaining to market updates, pricing, issuance strategy, regulatory changes and liability management recommendations\nWith Bond Syndicate, collate data and assist pricing of new issues\nWorking closely with internal partners such as Coverage / and Sales & Brokerage teams to understand client needs\nJoint responsibility for execution of all active lead transactions with DCM legal and bond syndicate\nJoint responsibility for execution of all transactions with DCM legal and bond syndicate\nTo assist superior in administrative tasks involving all internal requirements\nTo perform ad hoc projects as required\n\n\u00a0Requirements:\n\nDegree holder in Finance or other related disciplines\nAt least 5 years experience in Debt Capital Markets\nKnowledge in Debt Capital Markets Product\nGood command of written and spoken English and Chinese, fluency in Putonghua\nExcellent communication skills and strong inter personal and presentation skills\nIndependent, self-initiative, good interpersonal skills and analytical ability\n\n\u00a0Attractive remuneration will be offered to the right candidate.\u00a0 Interested parties please email your full resume with present & expected salary and date of availability to hrm @guosen.com.hk or via \"Apply Now\".\n\n\u00a0Personal data collected would be used for recruitment purpose only.", "employment_types": ["Full Time", "Permanent"], "selling_points": ["Debt Capital Markets", "pitches, proposals, presentations and analyses", "At least 5 years experience"], "locations": ["Admiralty"], "categories": ["Banking / Finance", "Financial Services", "Equities / Capital Markets", "Wealth Management"], "post_time": "2022-01-12T08:49:33Z", "salary": {"currency": null, "max": null, "min": null, "period": "monthly", "term": null}, "salary_visible": false, "title_keywords": ["vice president"], "responsibilities": ["management", "data", "financial models", "brokerage", "teams", "presentations", "transactions", "ad hoc projects", "administrative tasks", "marketing material"], "requirements": {"degrees": ["degree holder"], "majors": ["related disciplines", "finance"], "languages": ["putonghua", "english", "chinese"], "language_level": ["fluency", "good command"], "hard_skills": [], "soft_skills": ["communication skills", "independent", "presentation skills", "self-initiative", "interpersonal skills"], "languages_combined": [{"language": "putonghua", "language_level": ["fluency", "good command"]}, {"language": "english", "language_level": ["fluency", "good command"]}, {"language": "chinese", "language_level": ["fluency", "good command"]}]}, "experience_required": {"duration": ["at least 5 years"], "field": ["capital markets"]}}, {"job_id": "100003009046408", "location_code": "hk", "company": "Pinpoint Asia Limited", "job_title": "Asia IT Project Manager (Equities / Fixed Income) - Leading Investment Bank", "description": "Our client, a leading investment bank is looking for IT Project Managers to manage their Asia Transformation Programme, they are looking for candidates in 2 streams: Equities or Fixed Income.\u00a0 The selected candidate will be working with various business and technology stakeholders in driving the whole project lifecycle.\n\nResponsibilities:\n\nExecute and manage the IT program by supporting the program management office, including project management and business analysis.\nWork with the business and IT development managers to oversee and track the portfolio of technology projects being delivered for front office sales and trading.\nCreate project plans and proactively track progress and changes.\nMonitor and manage program risks, issues, assumptions, and dependencies\nPrepare materials for relevant program governance forums.\nPresent updates to stakeholders and other members of senior management teams that identify progress and salient issues.\nWork with technology silos, operations, and finance in coordinating front to backtesting.\nLead and implement the projects from end to end delivery.\nManage complex operational, organization, and technical issues in the program and propose appropriate solutions.\nIdentify project risk and mitigate business risk.\n\nRequirements:\n\nAround 8 years of working experience with a major management consultancy or in the financial trading industry.\nStrong financial services industry knowledge and understanding of sales and trading, finance, operations, technology, or internal audit.\nStrong knowledge of Asian financial trading markets and exchanges, ideally with the associated regulations in the region.\nWorking experience with the Asia Markets says Mainland China or Japan is a great plus.\nKnowledge of securities, equities, fixed income, and derivatives.\nHands-on project management and change management skills\nStrong analytical and problem-solving skills.\nGood technical and operational experience in Project Lifecycle.\nStrong organizational skills to manage multiple demands and change priorities.\nGreat personality to work effectively with all levels of stakeholders across the organization.\nExcellent written and verbal communication skills in English. Additional Asian language skills would be very helpful.\nBachelor's degree from a reputed University.\n\nIf this outstanding opportunity sounds like your next career move, please send your resume in Word format to Danny Kwan at resume(at)pinpointasia(dot)com and put Asia IT Project Manager (Equities / Fixed Income) - Leading Investment Bank in the subject header.\n\nData provided is for recruitment purposes only.", "employment_types": ["Full Time"], "selling_points": ["Tier-1 Investment Bank", "Regional IT Change Programme", "Programme office position"], "locations": ["Not Specified"], "categories": ["Banking / Finance", "Equities / Capital Markets", "Information Technology (IT)", "IT Project Management / Team Lead", "Product Management / Business Analyst"], "post_time": "2022-01-13T10:53:07Z", "salary": {"currency": "HKD", "max": 119999, "min": 70000, "period": "monthly", "term": null}, "salary_visible": true, "title_keywords": ["it project manager"], "responsibilities": ["management", "operations", "monitor", "teams", "project management", "business analysis", "plans", "senior management"], "requirements": {"degrees": ["degree", "bachelor"], "majors": [], "languages": ["english"], "language_level": ["excellent"], "hard_skills": ["problem-solving skills", "project management", "plus", "word"], "soft_skills": ["work effectively", "organizational skills", "communication skills", "project management", "hands-on", "problem-solving skills"], "languages_combined": [{"language": "english", "language_level": ["excellent"]}]}, "experience_required": {"duration": ["8 years"], "field": ["management", "trading", "financial"]}}, {"job_id": "100003009044168", "location_code": "hk", "company": "Morgan McKinley", "job_title": "IBD Compliance Advisory - Leading Investment Bank", "description": "About the Company\n\nOur client is a leading US-based investment bank looking for a driven individual with compliance or legal experience within investment banking, securities, or law firm to join their APAC Investment Banking Division to offer advice to the team on regulatory and compliance issues as well as to effectively implement control and surveillance mechanisms according to external regulations and internal policies. The selected candidate will get the chance to work with a range of stakeholders from various internal departments. Candidates with relevant experience speaking fluent English and Mandarin are welcome.\n\nResponsibilities\n\n- Provide advice to the Investment Banking Division on compliance, regulatory, and reputational issues, as well as on new business initiatives and significant business changes impacting the firm\n- Design and implement controls and surveillance programmes in adherence to laws, regulations, and firm policies\n\n- Investigate transactions and activities of bankers and perform analysis to minimise risks.\n- Ensure that appropriate policies and procedures are in place for the Investment Banking Division in response to regulatory and business changes while working closely with Legal and other businesses\n- Liaise with regulators on inspections and enquiries\n- Prepare and deliver training to the Investment Banking Division on internal policies and procedures, as well as laws, regulations, and risks.", "employment_types": ["Full Time", "Permanent"], "selling_points": ["Legal or compliance experience in investment bank", "Exposure to equity capital markets and M&A", "Immediate availability is preferred"], "locations": ["Central & Western Area"], "categories": ["Banking / Finance", "Equities / Capital Markets", "Professional Services", "Legal & Compliance"], "post_time": "2022-01-13T03:16:51Z", "salary": {"currency": "HKD", "max": 69999, "min": 55000, "period": "monthly", "term": null}, "salary_visible": true, "title_keywords": [], "responsibilities": ["regulations", "control", "business initiatives", "policies", "analysis", "compliance", "procedures", "design", "transactions", "provide advice", "banking", "liaise with"], "requirements": {"degrees": [], "majors": [], "languages": ["english", "mandarin"], "language_level": ["fluent"], "hard_skills": ["analysis"], "soft_skills": ["driven"], "languages_combined": [{"language": "english", "language_level": ["fluent"]}, {"language": "mandarin", "language_level": ["fluent"]}]}, "experience_required": {"duration": [], "field": ["legal", "compliance", "relevant experience", "investment", "banking", "securities", "investment bank", "team"]}}, {"job_id": "100003009043527", "location_code": "hk", "company": "Randstad Hong Kong Limited", "job_title": "Finance Director | Investment Group (SFC Type 1, 2, 4, 6, 9)", "description": "about the company.\n\nOur client is a highly respected SFC licensed investment company with substantial growth in Asia Pacific. They offer wide range of services including securities and future trading, asset management, investment advisory etc. Currently, they are hiring a Finance Director to manage their Financial Reporting team in Hong Kong.\nabout the team.\nThe company offers a friendly work culture. Work life balance, stable Finance team. You will work with a strong leadership team with a forward looking vision. Reporting to the Head of Finance, you will manage a team of 4-5 in Hong Kong.\nabout the job.\nReporting directly to the CFO, you will:\nLead and manage a team on financial control and reporting activities under Type 1, 2, 4, 6, 9\nReview reporting packs prepared by team members including Head Office reporting, annual and statutory reports\nReview and prepare group consolidation of HK listed investment entities\nCheck and ensure quality submission of FRR returns and regulatory reports according to Client Money Rules\nEnhance existing accounting processes for structured products, equities, derivatives etc.\nDrive initiatives to streamline work-flow through automation and process improvement projects\nKey point of contact with internal and external auditors\nskills & experiences required.\nDegree holder in Accounting, Finance or related discipline\nQualified member of HKICPA, ACCA or CPA Aus\nMinimum 15 years or above in Financial Control, Financial Reporting gained from SFC licensed corporations\nPrior experience in HK listed financial institution is a definite advantage\nGood product knowledge in equities, derivatives, structured products etc\nKnowledgeable in SFC regulatory requirements including FRR, Client Money Rules\nExcellent presentation and interpersonal skills, able to effectively lead a medium sized team\nGood command of English, Mandarin and Cantonese\nhow to apply.\n\nTo apply online, please click on the link below. Alternatively, for a confidential discussion please contact Mimi Chak on + 852 2232 3420 or email: mimi.chak@randstad.com.hk", "employment_types": ["Full Time", "Permanent"], "selling_points": ["Leading SFC licensed financial services", "Supervise reporting team", "FRR, client money, financial control & reporting"], "locations": ["Not Specified"], "categories": ["Accounting", "Financial Controller", "Banking / Finance", "Financial Services", "Equities / Capital Markets"], "post_time": "2022-01-12T16:07:42Z", "salary": {"currency": "HKD", "max": 119999, "min": 90000, "period": "monthly", "term": null}, "salary_visible": true, "title_keywords": ["director"], "responsibilities": ["reporting", "control", "regulatory requirements", "review", "quality", "external auditors", "reports", "finance team", "financial reporting", "contact", "asset management"], "requirements": {"degrees": ["degree holder"], "majors": ["finance", "accounting"], "languages": ["cantonese", "english", "mandarin"], "language_level": ["good command"], "hard_skills": ["cpa", "acca", "frr", "hkicpa"], "soft_skills": ["friendly", "interpersonal skills", "stable", "structured", "leadership", "presentation"], "languages_combined": [{"language": "cantonese", "language_level": ["good command"]}, {"language": "english", "language_level": ["good command"]}, {"language": "mandarin", "language_level": ["good command"]}]}, "experience_required": {"duration": [], "field": ["financial"]}}, {"job_id": "100003009035531", "location_code": "hk", "company": "Hong Kong Zhongcai Finance Investment Limited", "job_title": "Research Analyst", "description": "Job Description:\n\nPrepare daily & monthly commentary report for portfolio companies\nPrepare detailed research reports for portfolio companies on a regular basis\nConduct company visits, site visits and channel check on covered companies\nPrepare financial models and valuations\nParticipate in ad-hoc project assigned by supervisors\n\n\n\nJob Requirements:\n\nDegree holder in Economic, Finance, Accounting or related disciplines from top ranking schools is preferred\n1-2 years of research experience from buy-side and/or sell-side institutions, candidates with multi-industrial knowledge is a plus\nPassion in financial market, good business sense, logical thinking and continuous learning attitude is a must\nSelf-driven, detail-oriented with good communication skills. Fluency in Mandarin is a must\nLow frequency travel\u00a0to\u00a0China is required\nCPA, CFA holder will be a plus, but\u00a0not\u00a0must\n\nWe offer competitive remuneration package to right candidates. Interested parties please click the\u00a0Apply Now\u00a0with detailed resume including current and expected salary.", "employment_types": ["Full Time", "Permanent"], "selling_points": [], "locations": ["Central"], "categories": ["Banking / Finance", "Analyst", "Investment", "Equities / Capital Markets"], "post_time": "2022-01-10T07:34:12Z", "salary": {"currency": null, "max": null, "min": null, "period": "monthly", "term": null}, "salary_visible": false, "title_keywords": ["research analyst"], "responsibilities": ["ad-hoc", "financial models", "reports", "report"], "requirements": {"degrees": ["degree holder"], "majors": ["related disciplines", "finance", "accounting"], "languages": ["mandarin"], "language_level": ["fluency"], "hard_skills": ["cfa", "cpa", "plus"], "soft_skills": ["communication skills", "business sense", "passion in", "detail-oriented", "learning", "driven"], "languages_combined": [{"language": "mandarin", "language_level": ["fluency"]}]}, "experience_required": {"duration": ["1-2 years"], "field": ["research"]}}, {"job_id": "100003009035668", "location_code": "hk", "company": "Shanxi Securities International Financial Holdings Limited", "job_title": "Research Associate", "description": "Responsibilities:\n\nCarry out quantitative research on specific sectors and/ or portfolio of companies\u00a0\nBuild up financial modeling and valuation\u00a0\u00a0\nWrite corresponding research report\nVisit company sites/management\nInteract constantly with sales team or the other department to promote the company\u2019s business\nPrepare presentation material in investment seminars\n\nAssist in ad-hoc projects and carry out any other duties and responsibility as assigned by management\n\nRequirements:\n\nBachelor degree or above holders from leading university, specialization in Accounting, Finance, Economics , or related discipline\u00a0\nWith recognized professional qualifications such as CFA and CPA members/candidates is an advantage\n\n3 years or above experiences of research analysis, or relevant industry experience ( TMT, pharmaceuticals, health and real estate )\nSFC Licensed Type 4 holder\nFinancial modeling skill\nFamiliar with investment methods as well as domestic and international accounting standards\nMature, independent and self motivated team player, ability to work under pressure\nExpert knowledge of key external databases e.g. Bloomberg, Thomson Reuters and Wind etc.\nExcellent command of both spoken and written English and Chinese (fluency in Putonghua)\nWe offer competitive remuneration packages\u00a0to the right candidate.\u00a0Interested parties please submit\u00a0your\u00a0resume to Human Resources Department (1). by post to\u00a0Unit A, 29/F., Tower 1, Admiralty Centre, 18 Harcourt Road, Admiralty,\u00a0Hong Kong; or (2). by using\u00a0\"Apply Now\"\u00a0button.\u00a0All applications will be treated in strict confidence and personal data provided by job applications will be used for recruitment purposes only.", "employment_types": ["Full Time", "Permanent"], "selling_points": [], "locations": ["Admiralty"], "categories": ["Banking / Finance", "Analyst", "Financial Services", "Equities / Capital Markets"], "post_time": "2022-01-10T08:05:15Z", "salary": {"currency": null, "max": null, "min": null, "period": "monthly", "term": null}, "salary_visible": false, "title_keywords": ["research associate"], "responsibilities": ["valuation", "management", "any other duties", "financial modeling", "sales team", "ad-hoc projects", "report"], "requirements": {"degrees": ["degree or above", "bachelor"], "majors": ["finance", "accounting", "economics"], "languages": ["putonghua", "english", "chinese"], "language_level": ["fluency", "excellent"], "hard_skills": ["bloomberg", "professional qualifications", "cfa", "analysis", "cpa", "databases"], "soft_skills": ["independent", "mature", "self motivated", "team player", "work under pressure"], "languages_combined": [{"language": "putonghua", "language_level": ["fluency", "excellent"]}, {"language": "english", "language_level": ["excellent"]}, {"language": "chinese", "language_level": ["excellent"]}]}, "experience_required": {"duration": ["3 years"], "field": ["research"]}}, {"job_id": "100003009036661", "location_code": "hk", "company": "Mergermarket Consulting Limited", "job_title": "Acuris - Research Associate - AVCJ", "description": "The Asian Venture Capital Journal (AVCJ)\u2019s research division is looking to hire a full time research associate to be based in Hong Kong.\n\n\u00a0AVCJ is the leading information and data provider for private equity and venture capital in Asia. Part of the product consists of a historical database of Asian private equity and venture capital (PE&VC) maintained on a daily basis by a team of analysts and deal researchers.\n\nAVCJ is part of Acuris, London-headquartered financial media company whose products and services provide the advisory and corporate community with actionable intelligence and data.\n\nThe position will be responsible for supporting the Research team in its maintenance tasks. The role will primarily involve researching and processing information as well as offering unique opportunities to get full exposure to the Asian PE markets.\n\n\u00a0KEY RESPONSIBILITIES AND OBJECTIVES:\n\nMaintaining and expanding the historical PE database to ensure it reflects and provides a consistent high standard of data and analysis\nInterpreting financial data and other financial information in relation to PE transactions\nAnalyzing specific transactions to determine whether they meet the database inclusion criteria\nUpdating the database to ensure that deal records, company records and individual profiles are accurate and comprehensive\nDeveloping relationships with private equity firms in order to understand their investment activities and strategies\nProviding support to the team on the research publications\nCANDIDATE SPECIFICATION:\nThe ideal candidate will have:\nBachelor\u2019s degree, preferably in economics or finance\nUnderstanding of financial statements\nProficient in written and spoken English, business level in Japanese\nGood computer skills (especially Excel); Other programming language such as python and SQL is a plus.\nHighly numerate\nKeen interest in the Private Equity industry\nAbility to work both independently and as part of a team\nAble to work towards deadlines.\u00a0\n\nCandidates\u00a0of various background will be considered and attractive remuneration including generous staff benefits will be offered.\n\n\u00a0Data collected will only be used for job application processing. Applicants not invited for interview within two weeks from the posting date may assume their applications unsuccessful. All related information will be kept up to 12 months and all personal data will be destroyed afterwards.\n\nAcuris is fully committed to a policy of non-discrimination and to promoting equality of opportunity in employment on grounds of merit, experience, skills and aptitude in order to maximise the full potential of both existing and prospective employees.", "employment_types": ["Full Time", "Permanent"], "selling_points": ["Data Research", "Developing relationships with private equity firms", "Fresh graduates are welcome"], "locations": ["Central"], "categories": ["Banking / Finance", "Equities / Capital Markets"], "post_time": "2022-01-11T08:05:38Z", "salary": {"currency": null, "max": null, "min": null, "period": "monthly", "term": null}, "salary_visible": false, "title_keywords": ["research associate"], "responsibilities": ["maintaining", "data", "analysis", "developing", "transactions", "maintenance tasks", "financial statements", "database", "providing support"], "requirements": {"degrees": ["degree", "bachelor"], "majors": ["finance", "economics"], "languages": ["japanese", "english"], "language_level": ["proficient"], "hard_skills": ["excel", "plus", "maintenance", "analysis", "sql", "computer skills", "pe", "programming", "python", "processing", "venture capital", "private equity"], "soft_skills": ["independently", "responsible", "keen", "unique", "comprehensive", "accurate", "ideal"], "languages_combined": [{"language": "japanese", "language_level": ["proficient"]}, {"language": "english", "language_level": []}]}, "experience_required": {"duration": [], "field": []}}, {"job_id": "100003009046964", "location_code": "hk", "company": "China Construction Bank (Asia) Corporation Limited", "job_title": "Senior Relationship Manager, Corporate Banking II (Big 4 Candidates are welcomed)", "description": "Main Responsibilities :\n\nAssist in achieving the overall financial and business targets set by the Bank and maintaining the quality of lending\nLiaise with the Bank\u2019s other Divisions, CCBC domestic and overseas branches to achieve cross selling and risk control\nCommunicate with Risk Management /Operations /Legal and Compliance etc. for efficient internal approval while meeting the respective compliance requirements\nAssist in managing a substantial loan portfolio of blue chips (mainly in areas entrusted to her / his team) to derive maximum profitability for the Bank while maintaining the quality of the lending\nTake initiative to recommend new products that suit the customer\u2019s needs and maintain high standard of service so as to continually expanding the customer base by means of attracting new and retaining existing clients\nKeep regular contacts with other financial institutions to collect the information of the existing customers of the Bank in covered areas for risk monitoring, identify banking opportunities and make recommendation to the Bank and/or CCBC relevant branches\nConduct regular KYC assessment on a timely basis and to ensure client onboarding activity is complied with the AML policy and procedures\nTimely report of the work progress\n\nRequirements :\n\nUniversity degree in business or related disciplines\nMinimum 5 years\u2019 relevant banking experience\nStrong marketing skills with an ability to sell banking services to a competitive market in a highly motivated and profitable manner\nNetwork of relationships with corporate customers and financial institutions\nSound credit analysis skills relating to corporate, sovereign and bank debt\nGood command of both English and Chinese, including Putonghua\nWilling to travel\n\nApplicants who are not contacted within 8 weeks may consider their applications unsuccessful and their personal data will be retained by the bank for a period up to two years.\n\nAll information provided by applicants will be used for recruitment purposes only and will be used strictly in accordance with the bank\u2019s personal data policies, a copy of which will be provided upon request.", "employment_types": ["Full Time"], "selling_points": [], "locations": ["Not Specified"], "categories": ["Banking / Finance", "Financial Services", "Equities / Capital Markets", "Others"], "post_time": "2022-01-14T01:53:23Z", "salary": {"currency": null, "max": null, "min": null, "period": "monthly", "term": null}, "salary_visible": false, "title_keywords": ["senior relationship manager"], "responsibilities": ["communicate with", "control", "management", "make recommendation", "aml", "maintaining", "operations", "kyc", "compliance", "quality", "procedures", "risk monitoring", "maintain", "banking", "liaise with", "report"], "requirements": {"degrees": ["university degree"], "majors": ["related disciplines", "business"], "languages": ["putonghua", "english", "chinese"], "language_level": ["good command"], "hard_skills": ["credit analysis", "marketing skills"], "soft_skills": ["motivated"], "languages_combined": [{"language": "putonghua", "language_level": ["good command"]}, {"language": "english", "language_level": ["good command"]}, {"language": "chinese", "language_level": ["good command"]}]}, "experience_required": {"duration": ["minimum 5 years"], "field": ["banking experience"]}}, {"job_id": "100003009043827", "location_code": "hk", "company": "Darwin Rhodes (Hong Kong) Company Limited", "job_title": "Development Engineer", "description": "Job Description\nThe candidate will work at improving controls over the Equity Derivatives trading and/or operations tools\nThis will involve analyzing, understanding existing tools (Excel/VBA) and either re-design/re-write them in a target framework in Java or partially re-design them to start the path towards demise\nDevelopers are required to have day to day interaction with the structuring or trading desk and will work on local and global tactical and semi strategic platforms.\nManage end to end Projects, such as requirement gathering, development, UAT, deployment and support\nFollow up with users during the UAT phases\nWrite test cases and documentation\nSupport users post deployment\nThe Development Engineer is mainly responsible forBuilding out strategic Structured Products platforms. Dev ops and production support.\nIs an excellent communicator, and are comfortable communicating directly with the Sales/Trading Desk and internal Technology teams and are able to range up and down the detail depending on your audience.\nIs responsible to handle all phases of development (requirements analysis through to implementation to testing automation), establishing solid relationships and trust built on proven delivery.\nEssential Requirements\u00a0(Experience, skills, competencies etc)\nGood knowledge of Object Oriented Languages (Java, .Net) , Python scripting and VBA\nExperience of using either Relational databases (Oracle, MSSQL) or noSql databases (Mongo)\nA real inclination for test driven development\nGood skills with web services such as SOAP or RESTFUL and web based applications\nExcellent communication skills in English both spoken and written\nAbility to work in a complex and global environment.\nAbility to own the entire project cycle\nAgile working methods\nExperience of equity derivatives products either Derivative Pricing or Risk Management\nMotivation towards understanding further the equity derivatives business\nDesirable Skills\nKnowledge of Google Cloud would be advantagous\nGrowth mindset, adaptable to agile development", "employment_types": ["Contract"], "selling_points": ["8 to 10 years of experience required", "Flexible working arrangements", "Benefits"], "locations": ["Not Specified"], "categories": ["Banking / Finance", "Equities / Capital Markets"], "post_time": "2022-01-13T02:06:08Z", "salary": {"currency": null, "max": null, "min": null, "period": "monthly", "term": null}, "salary_visible": false, "title_keywords": ["engineer"], "responsibilities": ["management", "uat", "operations", "analysis", "teams", "implementation", "design", "testing", "communication", "agile development", "databases", "documentation"], "requirements": {"degrees": [], "majors": [], "languages": ["english"], "language_level": ["excellent"], "hard_skills": ["excel", "vba", "java", "agile", "web", "analysis", "mssql", "python", "deployment", "databases", "documentation", "web services", "oracle"], "soft_skills": ["communication skills", "agile", "responsible", "adaptable", "communicator", "structured", "driven"], "languages_combined": [{"language": "english", "language_level": ["excellent"]}]}, "experience_required": {"duration": [], "field": ["risk management"]}}, {"job_id": "100003009042390", "location_code": "hk", "company": "Page Personnel", "job_title": "Client Servicing/Operation - European Investment Bank", "description": "Our client is a top-tier European investment bank. With over 100 years of history, they have a strong reputation among the global financial institutions. They are now looking for a candidate with at least 3 years of experience in operations in Bank to join them.\n\nClient Details\n\nOur client is a top-tier European investment bank. With over 100 years of history, they have a strong reputation among the global financial institutions. They have launched Hong Kong office for more than 20 years with over 500 employees. They provide a complete range of capital markets, structured finance, corporate banking solutions and services.\n\nThey are now looking for a candidate with at least 3 years of experience in operations in Bank to join them. The candidate would be responsible for handle margin calls and operation related to collateral management. The company provide competitive salary and fringe benefits. The candidate would also enjoy large exposure in this globally renowned company.\n\nDescription\n\nHandle the Margin calls including notification, confirmation and settlement\nPerform calls reconciliation and follow-up on unusual counter parties behaviour and margin call discrepancies\nSetup contracts into the systems and participate to contracts negotiations\nCoordinate with Front Office, Market Activity Monitoring department and other concerned departments to setup client desk and issue Mark-to-Market statements to clients\nHandle Audit confirmation for capital market transactions booked in Hong Kong\n\nProfile\n\nBachelor degree holder, preferably major in finance related discipline\nAt least 3 years of experience in bank operations\nCandidate with experience in Collateral Management would be advantaged\nExcellent communication in English\nSelf-motivated and able to work under tight deadline and fast-paced environment\nGood understanding of financial markets fundamentals and financial products especially fixed income products\n\nJob Offer\n\nTop-tier Investment Bank\nMNC Business\nWell-established Team\nAnnual Leave: 15 days +\nMedical Benefits\nCompetitive Bonus\nCareer Exposure\n\nTo apply online please click the 'Apply' button below. For a confidential discussion about this role please contact Janet CHang on +852 3602 2459.", "employment_types": ["Full Time", "Permanent"], "selling_points": ["Collateral Management", "Mark-To-Market Reporting", "Competitive Pay"], "locations": ["Not Specified"], "categories": ["Banking / Finance", "Investment", "Financial Services", "Equities / Capital Markets"], "post_time": "2022-01-12T07:17:39Z", "salary": {"currency": "HKD", "max": 34999, "min": 30000, "period": "monthly", "term": null}, "salary_visible": true, "title_keywords": [], "responsibilities": ["operations", "management", "banking"], "requirements": {"degrees": [], "majors": [], "languages": [], "language_level": [], "hard_skills": [], "soft_skills": ["structured", "responsible"], "languages_combined": []}, "experience_required": {"duration": ["at least 3 years"], "field": []}}, {"job_id": "100003009034291", "location_code": "hk", "company": "Zhongrong PT Securities Limited", "job_title": "Analyst/Associate \u2013 Capital Markets", "description": "Job Description:\n\n\nA general capital markets role covering both investment banking and deal-driven investment, and with products exposure to both fixed income and equity.\nSector focus will be mainly in energy (renewable energy, new infrastructure and ESG) and real estate.\nAssess potential deals, prepare pitch book and conduct\u00a0financial\u00a0due diligence.\nConduct fundamental analysis on potential investment opportunities and prepare investment memo.\nVisualize data and present analytical insights to business team and management to facilitate business decisions.\nHandle other ad-hoc projects per senior management request.\n\nRequirements:\n\n\nBachelor\u2019s degree in Accounting and Finance or related disciplines are preferred. Other disciplines should be able to demonstrate competency in financial analysis.\n1-2 years\u2019 experience in financial industry is preferable\nSelf-motivated and proactive\nStrong team spirit and good communication skills\nSolid in corporate finance and accounting analysis\nAnalytical and logical thinking\nCandidate with more experience will be considered as Associate", "employment_types": ["Full Time", "Permanent"], "selling_points": ["Analysis on potential investment opportunities", "Analytical and logical thinking", "Self-motivated and proactive"], "locations": ["Tsim Sha Tsui"], "categories": ["Banking / Finance", "Analyst", "Investment", "Equities / Capital Markets"], "post_time": "2022-01-10T03:05:47Z", "salary": {"currency": null, "max": null, "min": null, "period": "monthly", "term": null}, "salary_visible": false, "title_keywords": ["analyst", "associate"], "responsibilities": ["due diligence", "management", "memo", "data", "analysis", "infrastructure", "banking", "ad-hoc projects", "senior management"], "requirements": {"degrees": ["degree", "bachelor"], "majors": ["related disciplines", "finance", "accounting"], "languages": [], "language_level": [], "hard_skills": ["financial analysis", "analysis"], "soft_skills": ["communication skills", "self-motivated", "proactive", "team spirit"], "languages_combined": []}, "experience_required": {"duration": ["1-2 years"], "field": ["financial industry"]}}, {"job_id": "100003009034333", "location_code": "hk", "company": "Page Personnel", "job_title": "Execution Analyst - Debt Capital Markets", "description": "Perform a range of corporate functions for debt capital markets.\nHandling financial modelling and due diligence.\n\nClient Details\n\nMy client is one of the leading Chinese commercial banks with a strong presence in capital markets. They are operating under SFC Type 1,4,6,9 license. They provide a range of financial services to commercial and corporate clients and are now looking for a Junior Execution Analyst to join their IBD team.\n\nDescription\n\nResponsible for performing a wide range of corporate finance functions for debt financing business such as developing financial models and financial due diligence, preparing pitch books and presenting proposals to clients;\nProvide financial advisory to clients, and be involved in client meetings and road shows\nPerform financial analysis on various industries within Asia\nOriginate and execute proposals for Chinese clients\nDrafting documentations and presentations\n\nProfile\n\nUniversity Degree with excellent academic background, preferably with CPA or CFA qualification\nWith over 1-2 years work experience in similar capacity; work experience in credit rating agencies is highly preferred\nExcellent analytical, financial modelling, research, communication and presentation skills\nAble to work under pressure and meet tight deadlines\nAttention to details and ability to work in teams\nProficiency in MS Excel, PowerPoint and Word\nProficient in using Bloomberg and other financial information providers\nStrong written and spoken English and Chinese (Putonghua and Cantonese)\n\nJob Offer\n\n18 Annual Leave\nMPF\nMedical\nOther good benefits\n\nTo apply online please click the 'Apply' button below. For a confidential discussion about this role please contact Matt O'Shaughnessy on +852 3602 2438", "employment_types": ["Full Time", "Permanent"], "selling_points": ["High performing Chinese investment bank divison", "Junior role open to 1-2 years experience", "Attractive package and brand name"], "locations": ["Not Specified"], "categories": ["Banking / Finance", "Credit Analysis / Approval", "Corporate Finance", "Equities / Capital Markets"], "post_time": "2022-01-10T03:11:18Z", "salary": {"currency": "HKD", "max": 34999, "min": 30000, "period": "monthly", "term": null}, "salary_visible": true, "title_keywords": ["analyst"], "responsibilities": ["due diligence", "mpf", "financial models", "teams", "developing", "presentations", "financial analysis", "communication", "work under pressure"], "requirements": {"degrees": ["university degree"], "majors": [], "languages": ["cantonese", "putonghua", "english", "chinese"], "language_level": [], "hard_skills": ["bloomberg", "cfa", "word", "presentations", "powerpoint", "financial analysis", "cpa", "ms excel", "documentations"], "soft_skills": ["meet tight deadlines", "responsible", "communication", "presentation skills", "attention to details", "work under pressure"], "languages_combined": [{"language": "cantonese", "language_level": []}, {"language": "putonghua", "language_level": []}, {"language": "english", "language_level": []}, {"language": "chinese", "language_level": []}]}, "experience_required": {"duration": ["1-2 years"], "field": []}}, {"job_id": "100003009045816", "location_code": "hk", "company": "ConnectedGroup Limited", "job_title": "Training and Development Manager (Financial Services)", "description": "Our client is a listed financial services organization headquartered in Hong Kong. Due to current transformation they are looking for a new member to join their Human Resources team.\n\nInvestment banking\nFast-paced culture\nStrategic L&D\n\nThe role\n\nReporting to the Head of Learning and Development, this position will be a key player in supporting the implementation of programs to help develop young and future talents within the organization and its delivery. You will be accountable for analyzing and assessing training trends that matches current needs, business strategy and company compliance. You will also develop and build a strong relationship with both internal and external stakeholders. Ad-hoc projects will be assigned as needed.\n\nThe candidate\n\nDegree qualification or above with a minimum of 7 years of experience related to training and development. Exposure to multinational companies will be highly advantageous.\nStrong project management and analytical skills with a problem solving mindset and detail oriented.\nHighly adaptable and able to thrive in a fast-paced and result oriented environment.\nExcellent communication and interpersonal skills with a proactive ability to build and manage stakeholders relationship.\nCommitted and mature with high level of integrity.\nExcellent command in both written and spoken Chinese and English.\n\nInterested parties, please apply the job online or contact Eunice Lei Ho directly via eunice.leiho@connectedgroup.com for more information. Please note that only short-listed candidates will be notified. All information gathered will be treated in strict confidence and solely used for recruitment purposes.", "employment_types": ["Full Time", "Permanent"], "selling_points": ["Investment banking", "Fast-paced culture", "Strategic L&D role"], "locations": ["Not Specified"], "categories": ["Banking / Finance", "Financial Services", "Equities / Capital Markets", "Admin & HR", "HR Director / Manager"], "post_time": "2022-01-13T08:47:50Z", "salary": {"currency": null, "max": null, "min": null, "period": "monthly", "term": null}, "salary_visible": false, "title_keywords": ["manager"], "responsibilities": ["reporting", "compliance", "implementation", "develop", "communication", "project management", "banking", "ad-hoc projects"], "requirements": {"degrees": ["degree"], "majors": [], "languages": ["english", "chinese"], "language_level": ["excellent"], "hard_skills": ["problem solving", "project management", "analytical skills"], "soft_skills": ["adaptable", "detail oriented", "integrity", "accountable", "mature", "analytical skills", "problem solving", "project management", "result oriented", "learning", "communication and interpersonal skills", "committed", "proactive"], "languages_combined": [{"language": "english", "language_level": ["excellent"]}, {"language": "chinese", "language_level": ["excellent"]}]}, "experience_required": {"duration": ["minimum of 7 years"], "field": ["related", "development", "training"]}}, {"job_id": "100003009036187", "location_code": "hk", "company": "China Cinda (HK) Holdings Company Limited", "job_title": "\u8d44\u672c\u5e02\u573a\u90e8\u80a1\u7968\u7ec4\u5408\u6295\u8d44\u7ecf\u7406", "description": "\u8d44\u672c\u5e02\u573a\u90e8\u80a1\u7968\u7ec4\u5408\u6295\u8d44\u7ecf\u7406\n\n\u62db\u8058\u4eba\u6570\uff1a1\u4eba\n\n\uff08\u4e00\uff09\u5c97\u4f4d\u63cf\u8ff0\n\n1\u3001\u534f\u52a9\u90e8\u95e8\u8d1f\u8d23\u4eba\u7ba1\u7406\u516c\u53f8\u81ea\u8425\u80a1\u7968\u7ec4\u5408\uff0c\u63d0\u51fa\u4ea4\u6613\u7b56\u7565\n\n2\u3001\u4e0e\u7814\u7a76\u5458\u5408\u4f5c\u5206\u6790\u53d1\u73b0\u80a1\u7968\u5e02\u573a\u4e0a\u7684\u4ea4\u6613\u673a\u4f1a\uff0c\u5e76\u5b8c\u6210\u6295\u8d44\u62a5\u544a\u3002\n\n3\u3001\u5b8c\u6210\u516c\u53f8\u4ea4\u7ed9\u7684\u5176\u4ed6\u5de5\u4f5c\n\n\n\n\uff08\u4e8c\uff09\u4efb\u804c\u8981\u6c42\n\n1\u3001\u672c\u79d1\u5b66\u5386\u4ee5\u4e0a\uff0c\u5177\u6709CFA\u6216FRM\u8bc1\u4e66\u4f18\u5148\u8003\u8651\uff1b\n\n2\u3001\u5177\u67093\u5e74\u4ee5\u4e0a\u80a1\u7968\u7ec4\u5408\u7ba1\u7406\u7ecf\u9a8c\uff0c\u5177\u6709\u826f\u597d\u7684\u4e1a\u7ee9\u8bb0\u5f55\n\n3\u3001\u6709\u5bf9\u51b2\u57fa\u91d1\u5de5\u4f5c\u7ecf\u9a8c\u66f4\u4f73\n\n\n\n\uff08\u4e09\uff09\u5de5\u4f5c\u5730\u533a\n\n\u9999\u6e2f\u4e2d\u73af", "employment_types": ["Full Time", "Permanent"], "selling_points": ["Bachelor's degree or above", "CFA/FRM is preferred", "Hedge fund experience is appreciated"], "locations": ["Central"], "categories": ["Banking / Finance", "Equities / Capital Markets"], "post_time": "2022-01-10T09:36:07Z", "salary": {"currency": null, "max": null, "min": null, "period": "monthly", "term": null}, "salary_visible": false, "title_keywords": [], "responsibilities": [], "requirements": {"degrees": [], "majors": [], "languages": [], "language_level": [], "hard_skills": [], "soft_skills": [], "languages_combined": []}, "experience_required": {"duration": [], "field": []}}, {"job_id": "100003009038529", "location_code": "hk", "company": "Conners Consulting Limited", "job_title": "AD, Sales Trading (Top tier Investment Bank, Attractive Package)", "description": "Our client, a well-established investment bank to invite high calibre candidates to join their company.\n\nResponsibilities:\n\n\nSales trading coverage of different assigned accounts, including QDII, hedge fund & long-only\nProvide daily market updates and information for institutional clients\nProvide trade ideas and market in-house research products to institutional clients\nWork closely with dealers for best execution. Liaise with middle office and settlement team to ensure smooth settlement for all post trade issues\n\nRequirement:\n\nBachelor degree in Finance or relevant discipline\nAt least 8 years\u2019 working experience in sales trading role\u00a0\nStrong attention to detail, high degree of accuracy and ability to multi-task\nKnowledge of the HK/CH market and regulatory rules\nCapable of writing market notes and market summary\nSystem knowledge: Fidessa and Bloomberg\nExcellent spoken and written English and Chinese including Mandarin;\n\nTo apply, please send your detailed resume or contact Boei Yan at 3460 2012 for a confidential discussion.\nOnly shortlisted candidates will be notified.\u00a0\nApplicants who are not contacted within two weeks may consider their applications unsuccessful.\nAll data collected will be used for recruitment purpose only & will be used strictly confidential.\n\nConners Consulting Limited 2005 Kai Tak Commercial Building 317 Des Voeux Road Central Hong Kong\nTel: (852) 3996 8090\u00a0 \u00a0 \u00a0 \u00a0\u00a0\nWebsite:\u00a0http://www.connersconsulting.com/", "employment_types": ["Full Time", "Permanent"], "selling_points": ["Sales and Trading in HK market, QDII, hedge fund", "Assist in building trading platform", "Attractive remuneration package, strong platform"], "locations": ["Central"], "categories": ["Banking / Finance", "Investment", "Dealing & Trading", "Equities / Capital Markets"], "post_time": "2022-01-11T07:14:35Z", "salary": {"currency": null, "max": null, "min": null, "period": "monthly", "term": null}, "salary_visible": false, "title_keywords": ["sales"], "responsibilities": ["liaise with", "trade issues", "ideas"], "requirements": {"degrees": ["degree", "bachelor"], "majors": ["finance"], "languages": ["english", "chinese", "mandarin"], "language_level": ["excellent"], "hard_skills": ["bloomberg", "ch"], "soft_skills": ["multi-task", "capable", "attention to detail", "detailed"], "languages_combined": [{"language": "english", "language_level": ["excellent"]}, {"language": "chinese", "language_level": ["excellent"]}, {"language": "mandarin", "language_level": ["excellent"]}]}, "experience_required": {"duration": ["at least 8 years"], "field": ["trading"]}}, {"job_id": "100003009043408", "location_code": "hk", "company": "Ambition", "job_title": "Associate / Senior Associate, Trade Support", "description": "Convenient Working location\nExcellent career path\nWork life balance\n\nOur client is a well-established investment bank with strong global presence. In order to cope with the company growth, they are currently looking for a Trade Support to join the Operations team.\n\nAs a Trade Support, you are responsible for the following but not limited to:\n\nPerform trade matching and reconciliation for Equities products for APAC market\nResolve any trade breaks with internal stakeholders such as Traders and settlement team\nHandle trade-related clients' enquiries\nParticipate in system enhancement such as UAT testing if necessary\n\nTo qualify, individual must possess:\n\nUniversity degree holder in Accounting or equivalent disciplines\nOver 2 years of middle office operations experience in financial services industry\nExperience in Stock connect would be an advantage\nA good team player, willing to learn and able to work under high pressure\nStrong interpersonal, communication and presentation skills\nExcellent communication skills with fluency in Cantonese and English\n\nInterested parties, send your updated resume to rita.lee@ambition.com.hk or click \"Apply Now\" .\n\nOnly shortlisted candidates would be notified.\n\nIf this job isn't quite right for you, but you know someone who would be great at this role, why not take advantage of our referral scheme? We offer HKD1000 in Apple gift cards for every referred candidate who we place in a role. Terms & Conditions Apply. https://www.ambition.com.hk/refer-a-friend", "employment_types": ["Full Time", "Permanent"], "selling_points": ["Convenient Working location", "Excellent career path", "Work life balance"], "locations": ["Not Specified"], "categories": ["Banking / Finance", "Equities / Capital Markets", "Others", "Asset Management"], "post_time": "2022-01-12T11:32:41Z", "salary": {"currency": null, "max": null, "min": null, "period": "monthly", "term": null}, "salary_visible": false, "title_keywords": ["senior associate", "associate"], "responsibilities": ["communication", "operations", "uat testing"], "requirements": {"degrees": ["university degree"], "majors": ["accounting"], "languages": ["cantonese", "english"], "language_level": ["fluency", "excellent"], "hard_skills": [], "soft_skills": ["communication skills", "good team player", "responsible", "willing to learn", "communication", "presentation skills", "work under high pressure", "interpersonal"], "languages_combined": [{"language": "cantonese", "language_level": ["fluency", "excellent"]}, {"language": "english", "language_level": ["fluency", "excellent"]}]}, "experience_required": {"duration": ["2 years"], "field": ["financial services industry"]}}, {"job_id": "100003009036147", "location_code": "hk", "company": "China Cinda (HK) Holdings Company Limited", "job_title": "\u8d44\u672c\u5e02\u573a\u90e8\u80a1\u7968\u4ea4\u6613\u5458", "description": "\u8d44\u672c\u5e02\u573a\u90e8\u80a1\u7968\u4ea4\u6613\u5458\n\n\u62db\u8058\u4eba\u6570\uff1a1\u4eba\n\n\uff08\u4e00\uff09\u5c97\u4f4d\u63cf\u8ff0\n\n1\u3001\u534f\u52a9\u7ba1\u7406\u81ea\u8425\u80a1\u7968\u7ec4\u5408\u4ea4\u6613\n\n2\u3001\u7814\u7a76\u5e76\u5b9e\u73b0\u91cf\u5316\u4ea4\u6613\u7b56\u7565\n\n3\u3001\u5b8c\u6210\u516c\u53f8\u4ea4\u7ed9\u7684\u5176\u4ed6\u5de5\u4f5c\n\n\n\n\uff08\u4e8c\uff09\u4efb\u804c\u8981\u6c42\n\n1\u3001\u672c\u79d1\u5b66\u5386\u4ee5\u4e0a\uff0c\u5177\u6709CFA\u6216FRM\u8bc1\u4e66\u4f18\u5148\u8003\u8651\uff1b\n\n2\u3001\u5177\u67093\u5e74\u4ee5\u4e0a\u81ea\u8425\u80a1\u7968\u4ea4\u6613\u7ecf\u9a8c\uff0c\u5177\u6709\u826f\u597d\u7684\u4e1a\u7ee9\u8bb0\u5f55\n\n3\u3001\u6709\u91cf\u5316\u4ea4\u6613\u5de5\u4f5c\u7ecf\u9a8c\u66f4\u4f73\n\n\n\n\uff08\u4e09\uff09\u5de5\u4f5c\u5730\u533a\n\n\u9999\u6e2f\u4e2d\u73af", "employment_types": ["Full Time", "Permanent"], "selling_points": ["Bachelor's degree or above", "CFA/FRM is preferred", "Quantitative trading experience is appreciated"], "locations": ["Central"], "categories": ["Banking / Finance", "Equities / Capital Markets"], "post_time": "2022-01-10T09:27:54Z", "salary": {"currency": null, "max": null, "min": null, "period": "monthly", "term": null}, "salary_visible": false, "title_keywords": [], "responsibilities": [], "requirements": {"degrees": [], "majors": [], "languages": [], "language_level": [], "hard_skills": [], "soft_skills": [], "languages_combined": []}, "experience_required": {"duration": [], "field": []}}, {"job_id": "100003009039283", "location_code": "hk", "company": "Gravitas Recruitment Group", "job_title": "PBMO Analyst", "description": "Our client is expanding the middle office with increasing volume in the prime brokerage business.\n\nRole & requirements:\n\nManage trade lifecycle for ETF/Equity Derivatives/Exotics in HK and other Asia markets\nWork with trading, trader assistant, product control and market risk on resolving any queries\nKnowledgeable of Asia Equities markets and equity derivatives products\nPreferably min. 2-3 years of relevant experience in trade support/middle office function\nStrong mindset of continuous process improvement\nStrong communication skill, especially to speak fluently in English\n\nWHY APPLY?\n\nThis supporting team playing function will be sitting on the trading floor. The scope and exposure is broad in the fast pace business.", "employment_types": ["Full Time", "Permanent"], "selling_points": ["Globally leading investment bank", "Perm", "Competitive career prospect"], "locations": ["Not Specified"], "categories": ["Banking / Finance", "Analyst", "Equities / Capital Markets", "Order Processing & Operation / Settlement"], "post_time": "2022-01-11T09:17:35Z", "salary": {"currency": "HKD", "max": 54999, "min": 35000, "period": "monthly", "term": null}, "salary_visible": true, "title_keywords": ["analyst"], "responsibilities": ["communication", "brokerage", "control"], "requirements": {"degrees": [], "majors": [], "languages": ["english"], "language_level": [], "hard_skills": [], "soft_skills": ["communication skill"], "languages_combined": [{"language": "english", "language_level": []}]}, "experience_required": {"duration": ["2-3 years"], "field": ["relevant experience"]}}, {"job_id": "100003009046296", "location_code": "hk", "company": "Ambition", "job_title": "VP/ Director, Markets Compliance", "description": "Our client, a leading investment bank, is looking for a VP, Markets Compliance for their team.\n\nResponsibilities:\n\nAssess regulatory and compliance risk for new products and business activities\n\nProvide compliance related advisory to various business units\n\nPerform Desk Reviews and lead independent reviews when necessary\n\nTrain equities staff regarding structured products\n\nCoordinate and liaising with various stakeholders as well as develop the Compliance Program\n\nRequirements:\n\nUniversity graduate from a related discipline\n\nFamiliar with FICC and/or Equities market structures and products\n\nMinimum of 7 years experience in GBM APAC Compliance\n\nStrong communicator, and proficiency in English/Chinese\n\nContact Elaine CHU on (852) 3103 4366 or elaine.chu@ambition.com.hk / APPLY NOW by clicking the button below\n\nIf this job isn't quite right for you, but you know someone who would be great at this role, why not take advantage of our referral scheme? We offer HKD1000 in Apple gift cards for every referred candidate who we place in a role. Terms & Conditions Apply. https://www.ambition.com.hk/refer-a-friend", "employment_types": ["Full Time", "Permanent"], "selling_points": ["", "", ""], "locations": ["Not Specified"], "categories": ["Banking / Finance", "Investment", "Equities / Capital Markets"], "post_time": "2022-01-13T10:21:58Z", "salary": {"currency": "HKD", "max": 89999, "min": 70000, "period": "monthly", "term": null}, "salary_visible": true, "title_keywords": ["director"], "responsibilities": ["compliance", "liaising with", "develop", "coordinate", "business activities"], "requirements": {"degrees": ["university graduate"], "majors": [], "languages": ["english", "chinese"], "language_level": ["proficiency"], "hard_skills": ["scheme"], "soft_skills": ["communicator"], "languages_combined": [{"language": "english", "language_level": ["proficiency"]}, {"language": "chinese", "language_level": ["proficiency"]}]}, "experience_required": {"duration": ["minimum of 7 years"], "field": ["compliance"]}}, {"job_id": "100003009038364", "location_code": "hk", "company": "Nautilus Technology Limited", "job_title": "Junior Quantitative Developer", "description": "Job Responsibilities:\n\nResponsible for integrating data from various back-end services and databases\nWorking with Senior Management and real traders to design, model and generate algorithm ideas.\nAnalyze unique proprietary data sets.\n\nRequirements:\n\nBachelor Degree in Math, CS, Stats, Physics, or related field\n1-3 years of coding experience\nOutstanding programming ability in C++ and Python\nStrong command of both written and spoken English and Chinese (Especially in Mandarin)\n\nNice to have:\n\nKnowledge of UNIX operating systems (we use Linux), system/processor performance, and network communication\nExperience with low latency programming", "employment_types": ["Full Time", "Permanent"], "selling_points": [], "locations": ["Tsim Sha Tsui"], "categories": ["Banking / Finance", "Analyst", "Corporate Finance", "Equities / Capital Markets"], "post_time": "2022-01-11T06:44:20Z", "salary": {"currency": null, "max": null, "min": null, "period": "monthly", "term": null}, "salary_visible": false, "title_keywords": ["developer", "junior"], "responsibilities": ["ideas", "data", "design", "databases", "senior management"], "requirements": {"degrees": ["degree", "bachelor"], "majors": ["math", "physics"], "languages": ["english", "chinese", "mandarin"], "language_level": [], "hard_skills": ["linux", "c++", "nice", "programming", "python", "math"], "soft_skills": ["communication"], "languages_combined": [{"language": "english", "language_level": []}, {"language": "chinese", "language_level": []}, {"language": "mandarin", "language_level": []}]}, "experience_required": {"duration": ["1-3 years"], "field": ["programming"]}}, {"job_id": "100003009042080", "location_code": "hk", "company": "The Bank of East Asia, Limited", "job_title": "Senior Manager, Head of Investor Relations", "description": "Senior Manager, Head of Investor Relations (Job ID 3116)\nResponsibilities\nTo be the lead of Investor Relations Section\nTo support the development of the investor relations function of the bank Group\nTo assist in refining investor relations strategy and developing investor relations communications\nTo establish and maintain relationships with the investment community\nTo create presentations and other communication materials to analysts and investors\nTo organize conferences, road shows, briefings, result conference calls and investor events and function\nRequirements\nUniversity graduate, preferably major in business or finance\n10 years or above experience in banking, credit agency , capital markets, or sell side analyst\nStrong analytical, communication , and presentation skills\nGood command of both written and spoken English, Chinese, including Putonghua\nGood relationship-building skills with the investment community\nGood collaborative skill in working with internal and external stakeholders\nSkills in data analysis, presentation and data visualization, financial modelling and research\nExperiences in events preparation\nPlease apply online via the BEA Careers website at\u00a0https://careers.hkbea.com/psp/hcmprd/EMPLOYEE/HRMS/c/HRS_HRAM.HRS_APP_SCHJOB.GBL?Page=HRS_APP_JBPST&Action=UFOCUS=Applicant&SiteId=1&JobOpeningId=3116&PostingSeq=1 or by clicking the \"Apply Now\" button below. Kindly note that if you are a new user, you have to first create your User Profile before you can apply.\nPersonal data provided by job applicants will be used for recruitment purposes only and will be treated in accordance with the Bank's Personal Information Collection (Employees) Statement and Privacy Policy Statement. Applicants who are not invited for interviews within six weeks may consider their applications unsuccessful and the personal data collected will be destroyed after six months.", "employment_types": ["Full Time", "Permanent"], "selling_points": ["Support the development of the investor relations", "University graduate", "10 years or above experience in banking"], "locations": ["Not Specified"], "categories": ["Banking / Finance", "Investment", "Equities / Capital Markets"], "post_time": "2022-01-12T05:58:56Z", "salary": {"currency": null, "max": null, "min": null, "period": "monthly", "term": null}, "salary_visible": false, "title_keywords": ["senior manager"], "responsibilities": ["maintain relationships", "developing", "presentations", "communication", "conferences"], "requirements": {"degrees": ["university graduate"], "majors": ["finance", "business"], "languages": ["putonghua", "english", "chinese"], "language_level": ["good command"], "hard_skills": ["analysis", "c", "data visualization"], "soft_skills": ["communication", "presentation skills", "presentation", "collaborative"], "languages_combined": [{"language": "putonghua", "language_level": ["good command"]}, {"language": "english", "language_level": ["good command"]}, {"language": "chinese", "language_level": ["good command"]}]}, "experience_required": {"duration": ["10 years"], "field": ["agency", "capital markets", "banking"]}}, {"job_id": "100003009035601", "location_code": "hk", "company": "Platinum Broking Company Limited", "job_title": "BROKING SUPPORT", "description": "Responsibilities:\n\nLiaise with Sales and Research department to provide investment service including daily morning notes to clients.\nAssist research analysts in research report production by collecting and analyzing data generated from various external sources.\nFollow up several companies in one specific sector allocated by research head, draft daily news analysis, research reports and provide investment ideas within the coverage sector.\nMaintain and update internal databases including industry database, IPO database and clients database on regular basis.\nCollaborate with middle and back office departments to ensure the smooth operation of the Dealing room.\nEngage in ad-hoc requests from directors.\u00a0\n\nRequirement:\n\nUniversity graduates majored in quantitative or finance subjects.\nPrevious experience in research or broking support preferred.\nProficient in spoken and written English, Cantonese and Mandarin.\nPC literate with the ability to work under pressure and independently.\nFresh graduates will also be considered.\n\nOur company provide:\n\nMedical insurance (including spouse and children)\nDental insurance\nLife insurance\nPerformance bonus\nStudy leave\nBank Holiday\n\nWe offer competitive compensation package to the right candidate.\u00a0 Please click 'Apply Now'\u00a0to apply with a detailed resume to us together with your current and expected salary information.\n\n(All applications will be treated in strictly confidential. Applicants who are not invited for an interview within 2 months may consider that their applications are unsuccessful.)", "employment_types": ["Full Time", "Permanent"], "selling_points": [], "locations": ["Central"], "categories": ["Banking / Finance", "Financial Services", "Dealing & Trading", "Equities / Capital Markets"], "post_time": "2022-01-10T07:49:54Z", "salary": {"currency": null, "max": null, "min": null, "period": "monthly", "term": null}, "salary_visible": false, "title_keywords": [], "responsibilities": ["collaborate with", "ideas", "data", "ad-hoc requests", "analysis", "back office", "maintain", "reports", "databases", "database", "liaise with", "report"], "requirements": {"degrees": [], "majors": [], "languages": ["cantonese", "english", "mandarin"], "language_level": ["proficient"], "hard_skills": ["pc literate"], "soft_skills": ["independently", "work under pressure"], "languages_combined": [{"language": "cantonese", "language_level": ["proficient"]}, {"language": "english", "language_level": ["proficient"]}, {"language": "mandarin", "language_level": ["proficient"]}]}, "experience_required": {"duration": [], "field": ["research"]}}, {"job_id": "100003009037146", "location_code": "hk", "company": "Ethos BeathChapman Hong Kong Limited", "job_title": "Project Manager (Equity Derivatives)", "description": "The Role:\nClient is a market-leading Global Bank, based here in Hong Kong. They are currently hiring into their Equity Derivatives team to work on a Trade Flow Automation Program.\n\nRequirements:\n\nMust have experience working with Equity Derivatives, ideally on Automation projects\nCan be relied upon to assess the current state of their trade flows and assess pain points, suggest solutions\nIdeal candidates will have experience as a Project Manager\nStrong communicator \u2013 must be articulate and confident in interacting with senior stakeholders\nBeathChapman Pte Ltd\n\n", "employment_types": ["Full Time", "Permanent"], "selling_points": ["One of Hong Kong\u2019s leading banks", "Dynamic international working environment", "Attractive salary"], "locations": ["Central & Western Area"], "categories": ["Banking / Finance", "Financial Services", "Equities / Capital Markets"], "post_time": "2022-01-11T01:58:13Z", "salary": {"currency": "HKD", "max": 69999, "min": 55000, "period": "monthly", "term": null}, "salary_visible": true, "title_keywords": ["project manager"], "responsibilities": [], "requirements": {"degrees": [], "majors": [], "languages": [], "language_level": [], "hard_skills": [], "soft_skills": ["confident", "articulate", "communicator", "ideal"], "languages_combined": []}, "experience_required": {"duration": [], "field": []}}, {"job_id": "100003009043095", "location_code": "hk", "company": "Morgan McKinley", "job_title": "M&A Origination (Europe, US and ASEAN)", "description": "An M&A house is looking to expand its business in Europe, Southeast Asia and the USA regions. Minimum 4 years of experience. Fluent in English plus any other European language is an advantage.\n\nDescription:\n\nOrigination: Lead the M&A Cross-border business to grow in Europe, Southeast Asia and the USA with no limitation on sectors coverage\nConduct research on targeted clients and identify development opportunities\nRelationship management with potential clients, attend business trips and meetings as required\nConduct financial analysis, due diligence, marketing materials and transactional documents\n\nRequirements:\n\nMinimum 4 years of experience in Financial Services; with strong connections with potential M&A clients in Europe, the USA or Southeast Asia\nMust be fluent or native in English; Fluency in other European languages is a bonus", "employment_types": ["Full Time", "Permanent"], "selling_points": ["any other European language is an advantage", "Cross border M&A", "Based in Hong Kong"], "locations": ["Not Specified"], "categories": ["Banking / Finance", "Corporate Finance", "Financial Services", "Equities / Capital Markets"], "post_time": "2022-01-12T09:48:38Z", "salary": {"currency": null, "max": null, "min": null, "period": "monthly", "term": null}, "salary_visible": false, "title_keywords": [], "responsibilities": ["due diligence", "management", "financial analysis", "marketing materials", "conduct research"], "requirements": {"degrees": [], "majors": [], "languages": ["english"], "language_level": ["native", "fluent"], "hard_skills": [], "soft_skills": [], "languages_combined": [{"language": "english", "language_level": ["fluent", "fluent", "native"]}]}, "experience_required": {"duration": ["minimum 4 years"], "field": ["financial services"]}}, {"job_id": "100003009030926", "location_code": "hk", "company": "BOCOM International Holdings Company Limited", "job_title": "Sales Support, Institutional Sales Dept", "description": "Job Purpose\n\nTo intensively co-ordinate with both corporate and institutional clients and help to plan and organize the corporate events.\u00a0\n\nKey Responsibilities\u00a0\n\n\u00a0 \u00a0 \u00a0 Maintain and update client database and company information by means of Bloomberg and/or other sources of materials\n\u00a0 \u00a0 \u00a0 Schedule clients and internal meetings and arrange the necessary facilities in a professional manner\n\u00a0 \u00a0 \u00a0 Assist the team to co-ordinate end-to-end Roadshow and Conference events\n\u00a0 \u00a0 \u00a0 Provide on-site management of events where necessary\n\u00a0 \u00a0 \u00a0 Arrange production and delivery of presentation material\n\nRequirements\n\n\u00a0\u00a0\u00a0\u00a0\u00a0 University degree of above in a business related disciplines\n\u00a0\u00a0\u00a0\u00a0\u00a0 Minimum 1 year experience in finance or banking industry. Prior Corporate Access / Equity Research / Equity Sales experience will be an advantage\n\u00a0\u00a0\u00a0\u00a0\u00a0 Strong sense in team work and self-motivated, with communication and interpersonal skills\n\u00a0\u00a0\u00a0\u00a0\u00a0 Online marketing experience through WeChat is a plus\n\u00a0\u00a0\u00a0\u00a0\u00a0 Ability to work under pressure in fast-paced environment\n\u00a0\u00a0\u00a0\u00a0\u00a0 Excellent computer skills in MS Office including Excel & PowerPoint\n\u00a0\u00a0\u00a0\u00a0\u00a0 Proficiency in written and spoken English and Chinese including Putonghua", "employment_types": ["Full Time"], "selling_points": ["Institutional Sales Support", "Exposure to FI and Corporate Clients", "Marketing and Event Management"], "locations": ["Central"], "categories": ["Banking / Finance", "Equities / Capital Markets"], "post_time": "2022-01-07T08:38:59Z", "salary": {"currency": null, "max": null, "min": null, "period": "monthly", "term": null}, "salary_visible": false, "title_keywords": ["sales"], "responsibilities": ["professional manner", "site management", "maintain", "schedule", "database"], "requirements": {"degrees": ["university degree"], "majors": ["related disciplines", "business"], "languages": ["putonghua", "english", "chinese"], "language_level": ["proficiency"], "hard_skills": ["excel", "plus", "powerpoint", "wechat", "computer skills", "ms office"], "soft_skills": ["fast-paced environment", "self-motivated", "communication and interpersonal skills", "work under pressure"], "languages_combined": [{"language": "putonghua", "language_level": ["proficiency"]}, {"language": "english", "language_level": ["proficiency"]}, {"language": "chinese", "language_level": ["proficiency"]}]}, "experience_required": {"duration": ["minimum 1 year"], "field": ["finance", "equity research", "marketing", "banking industry"]}}, {"job_id": "100003009039800", "location_code": "hk", "company": "Hays", "job_title": "CBBC & Warrant Operation and System Manager", "description": "\n\nYour new role\n\nManage daily Bull/ Bear Contract (CBBC) and Warrants trade operations, and ensure all tasks are completed accurately within schedule.\nResponsible for offering the first line of defence for the Trading desk's franchise risk and risk in ensuring that the trade bookings are correctly reflected in both Front and Back Office systems and tie out with the Counterparty.\nSupport and Participate in trading operation related projects and system enhancements.\nReview and Analyse weekly performance and key metrics reports.\n\n\nWhat you'll need to succeed\n\nUniversity Degree in the related field.\n8+ years of working experiences in the trading operation business with solid knowledge in CBBC and Warrants.\nExcellent Excel skills with solid technical knowledge in VBA.\nProficiency in verbal and written English and Chinese.\nCandidate with less experience will also be considered.\n\n\nWhat you need to do now\nIf you're interested in this role, click 'apply now' to forward an up-to-date copy of your CV, or call Keith Ho now @ 2230 7474. Alternatively, you can also share Keith your updated CV to keith.ho@hays.com.hk.\nIf this job isn't quite right for you but you are looking for a new position, please contact us for a confidential discussion on your career.", "employment_types": ["Full Time", "Permanent"], "selling_points": ["Trade Operation", "CBBC, Warrant, Option", "Leading Financial Institution"], "locations": ["Not Specified"], "categories": ["Banking / Finance", "Equities / Capital Markets", "Others", "Order Processing & Operation / Settlement"], "post_time": "2022-01-11T11:27:26Z", "salary": {"currency": null, "max": null, "min": null, "period": "monthly", "term": null}, "salary_visible": false, "title_keywords": ["system manager"], "responsibilities": ["operations", "review", "systems", "back office", "reports", "schedule", "contact", "analyse"], "requirements": {"degrees": ["university degree"], "majors": [], "languages": ["english", "chinese"], "language_level": ["proficiency"], "hard_skills": ["vba", "excel", "bookings", "tie"], "soft_skills": ["interested in", "responsible"], "languages_combined": [{"language": "english", "language_level": ["proficiency"]}, {"language": "chinese", "language_level": ["proficiency"]}]}, "experience_required": {"duration": ["8+ years"], "field": ["business", "operation", "trading"]}}, {"job_id": "100003009037279", "location_code": "hk", "company": "Inspire Executive Limited", "job_title": "Head of ECM-Leading Chinese-based Securities Firm", "description": "Our client is one of the leading Chinese securities firms. They are looking for ECM Head to join their team. Experienced ECM Banker (D-ED Level) are welcome. Base HK\n\n\n\nJob description:\n\nOverview and managing the equity capital market business and expansion\nHeavily involve in business development including liaising with syndicate brokers\nECM Deal Execution and Origination\nHigh level management including strategy planning, goal setting, team building as well as management\nLiaise and report to group management on an operational basis\n\nRequirements:\n\nAt least 10 years of experience in ECM \uff08D-ED Level\uff09\nExcellent command in English and Chinese, Mandarin is a must\nSelf motivated, and have strong leadership skills", "employment_types": ["Full Time"], "selling_points": ["Capital Markets/ECM/Equity Capital Markets", "Investment Banking", "Deal Origination/Execution"], "locations": ["Central & Western Area"], "categories": ["Banking / Finance", "Equities / Capital Markets"], "post_time": "2022-01-11T02:18:13Z", "salary": {"currency": null, "max": null, "min": null, "period": "monthly", "term": null}, "salary_visible": false, "title_keywords": [], "responsibilities": ["liaise", "management", "liaising with", "planning", "report"], "requirements": {"degrees": [], "majors": [], "languages": ["english", "chinese", "mandarin"], "language_level": ["excellent"], "hard_skills": [], "soft_skills": ["self motivated", "leadership skills"], "languages_combined": [{"language": "english", "language_level": ["excellent"]}, {"language": "chinese", "language_level": ["excellent"]}, {"language": "mandarin", "language_level": ["excellent"]}]}, "experience_required": {"duration": ["at least 10 years"], "field": []}}, {"job_id": "100003009040374", "location_code": "hk", "company": "Asia Progress Executive Limited", "job_title": "Associate, Fixed Income Trader", "description": "Our client is PRC\u00a0Top Tier Chinese Investment Bank/ Securities Brokerage . \u00a0To cope with the rapid business expansion, they are now inviting high caliber candidates to join the team\n\nAssociate, Fixed Income Trader\u00a0\n\nJob Responsibilities\n\nBe responsible for fixed income\u00a0trading for client accounts\nWork as part of the DCM team to provide real-time market\u00a0colour,\u00a0identify\u00a0investment opportunities, and implement effective trades\u00a0derive profits\n\u00a0Assist in client marketing and day to day client communication\nMaintain and develop new trading instruments and other relevant\u00a0products to enhance investment returns\n\nRequirements:\n\n\u00a0Degree holder in Finance, business or any similar field\n\u00a0 3 - 5 years of relevant trading experience in fixed income or equity\n\u00a0 Familiar with the fixed income and equity markets ecosystem\n\u00a0 Solid understanding of investment products and trading strategies\n\u00a0 Ability to work accurately under stress;\n\u00a0 Fast learner, proactive and quick reaction to market changes\n\u00a0 Proficiency in written and spoken English and Chinese including Putonghua.\n\nPlease send full resume with\u00a0present & expected\u00a0salary to expedite sourcing\u00a0in\u00a0MS-WORD\u00a0format by clicking \u201cAPPLY NOW\u201d\n\nPlease quote our reference in your application\n\nPersonal data provided by job applicants will be used strictly in accordance with the employer\u2019s personal data policies, a copy of which will be provided upon request\n\nAll information provided will be used for recruitment purpose only", "employment_types": ["Full Time"], "selling_points": ["Responsible for fixed income trading for DCM Team", "Deg 3yrs fixed income trader / equity products", "Familiar w/ fixed income and equity markets"], "locations": ["Central & Western Area"], "categories": ["Banking / Finance", "Treasury", "Dealing & Trading", "Equities / Capital Markets"], "post_time": "2022-01-12T04:55:29Z", "salary": {"currency": null, "max": null, "min": null, "period": "monthly", "term": null}, "salary_visible": false, "title_keywords": ["associate"], "responsibilities": ["communication", "maintain", "investment returns", "develop"], "requirements": {"degrees": ["degree holder"], "majors": ["finance", "business"], "languages": ["putonghua", "english", "chinese"], "language_level": ["proficiency"], "hard_skills": ["ms-word", "investment products"], "soft_skills": ["proactive", "fast learner"], "languages_combined": [{"language": "putonghua", "language_level": ["proficiency"]}, {"language": "english", "language_level": ["proficiency"]}, {"language": "chinese", "language_level": ["proficiency"]}]}, "experience_required": {"duration": ["3 - 5 years"], "field": ["trading"]}}, {"job_id": "100003009039226", "location_code": "hk", "company": "Conners Consulting Limited", "job_title": "VP/SVP/AD of Institutional Sales (IANG is welcome, Native Mandarin, 3 headcounts)", "description": "Our client, a well-established investment firm to invite high caliber candidates to join their company.\n\nResponsibilities:\n\nLeading Institutional Sales team for daily operations;\nMaintain and build the business relationship with the above institutional accounts;\nProvide research service to clients, including market updates, arrange conference call and collect client\u2019s feedback;\nCoordinate roadshow and corporate access for the above clients;\nMaintain smooth operations and adhere to stringent procedures and high standard of compliance;\nReview client feedback periodically and propose a continuous improvement plan to enhance client satisfaction.\n\nRequirements:\n\nAt least 8-year institutional sales trading experience; \u00a0\nDegree in Economics, Finance or Business related disciplines;\nIndependent, attentive to details, and highly motivated;\nCustomer-oriented and proactive with effective communications skills;\nGood team player with excellent interpersonal skills;\nExcellent command of English and Chinese, Native Mandarin is preferred;\n\nTo apply, please send your detailed resume or contact Boei Yan at 3460 2012 for a confidential discussion.\nOnly shortlisted candidates will be notified.\u00a0\nApplicants who are not contacted within two weeks may consider their applications unsuccessful.\nAll data collected will be used for recruitment purpose only & will be used strictly confidential.\n\nConners Consulting Limited 2005 Kai Tak Commercial Building 317 Des Voeux Road Central Hong Kong\nTel: (852) 3996 8090\u00a0 \u00a0 \u00a0 \u00a0\u00a0\nWebsite:\u00a0http://www.connersconsulting.com/\u00a0", "employment_types": ["Full Time", "Permanent"], "selling_points": ["Leading Institutional Sales team", "Maintain existing institutional client", "Native Mandarin, IANG is welcome"], "locations": ["Central"], "categories": ["Banking / Finance", "Investment", "Dealing & Trading", "Equities / Capital Markets"], "post_time": "2022-01-11T09:05:42Z", "salary": {"currency": null, "max": null, "min": null, "period": "monthly", "term": null}, "salary_visible": false, "title_keywords": ["sales"], "responsibilities": ["operations", "compliance", "procedures", "review", "coordinate", "daily operations", "maintain", "sales team", "plan"], "requirements": {"degrees": ["degree"], "majors": ["business", "finance", "related disciplines", "economics"], "languages": ["english", "chinese", "mandarin"], "language_level": ["native", "excellent"], "hard_skills": [], "soft_skills": ["good team player", "independent", "attentive to details", "customer-oriented", "motivated", "interpersonal skills", "proactive", "detailed"], "languages_combined": [{"language": "english", "language_level": ["native", "excellent"]}, {"language": "chinese", "language_level": ["native", "excellent"]}, {"language": "mandarin", "language_level": ["native", "excellent"]}]}, "experience_required": {"duration": ["at least 8-year"], "field": ["trading", "institutional sales"]}}, {"job_id": "100003009035545", "location_code": "hk", "company": "E.SUN Commercial Bank, Ltd.", "job_title": "Treasury Sales, Corporate Banking", "description": "Job Duties:\n\nResponsible for sales & marketing on treasury products, maintaining clients\u2019 relationship and provide marketing ideas, promoting treasury products and executing clients\u2019 order.\nIn collaboration with Relationship Managers to provide hedging / investment solutions and fulfill clients\u2019 needs.\nProactively support treasury product team and ideas on FX options, Interest rates derivatives or structured products.\nEnsure all sales activities in compliance with the Bank\u2019s guidelines.\n\nRequirement:\n\nMinimum 1~2 years of working experience in treasury marketing or related field.\nBachelor degree or higher in Finance, Economics or related discipline.\nSelf-motivated with strong communication, interpersonal and analytical skills.\n\nWe offer an attractive remuneration package including five-day workweek, double pay, medical insurance coverage, performance bonus, OT allowance, public holiday, excellent career development opportunities, and other benefit packages to the right candidate. Interested parties please forward your resume including a Chinese self-introduction with current and expected salary to Human Resources Department by \"APPLY NOW\".\u00a0\n\nPlease visit our website at https://www.esunbank.com.tw/bank/corporate/overseas-branch/overseas-branch/hong-kong for more information.\u00a0\n\nAll information received will be kept strictly confidential and only for employment-related purposes.", "employment_types": ["Full Time", "Permanent"], "selling_points": ["Sales & marketing on treasury products", "Young and Energetic Working Culture", "One of the Leading Bank in Taiwan"], "locations": ["Tsim Sha Tsui"], "categories": ["Banking / Finance", "Corporate Banking", "Treasury", "Equities / Capital Markets"], "post_time": "2022-01-10T07:36:39Z", "salary": {"currency": null, "max": null, "min": null, "period": "monthly", "term": null}, "salary_visible": false, "title_keywords": ["sales"], "responsibilities": ["sales activities", "ideas", "maintaining", "guidelines", "compliance", "executing"], "requirements": {"degrees": ["degree", "bachelor"], "majors": ["finance", "economics"], "languages": [], "language_level": [], "hard_skills": ["analytical skills"], "soft_skills": ["communication", "self-motivated", "interpersonal", "analytical skills"], "languages_combined": []}, "experience_required": {"duration": ["minimum 1~2 years"], "field": ["related", "marketing"]}}, {"job_id": "100003009039503", "location_code": "hk", "company": "Mergermarket Consulting Limited", "job_title": "Acuris - Mergermarket - Hong Kong Financial Reporter", "description": "Acuris (an ION company) is looking for a motivated, experienced reporter to join\u00a0the Hong Kong Mergermarket team to write market-moving scoops and in-depth executive interviews for both listed and private enterprises. The Hong Kong bureau produces not only high-profile M&A scoops, but also engages SME fundraising or start-up origination coverage.\u00a0\nCandidates with an established source network is preferred.\u00a0 \u00a0\n\nKey responsibilities:\n\nInterview Hong Kong-based public and private companies, startup to unicorns regarding M&A strategies and market trends\u00a0and write stories in English\nChasing deals and scoops ahead of competitors\nTake charge of allocated sectors and remain informed on companies, deals, activities, and trends \u00a0\nCommunicate and cooperate with local and regional team members\u00a0\nMaintain and expand source network that includes corporate executives, bankers, advisors, lawyers\u00a0\nResponsible for reaching out to executives or PR and IRs to arrange interview.\nSkills & Requirements:\n\nWork independently\u00a0\nGood understanding of basic financial and legal concepts\nPassionate and aggressive in financial investigative reporting\nSolid financial reporting experience is highly preferred. Fresh graduate would also be considered.\nStrong language skills - fluency in English, Cantonese and Mandarin.\nGood time management skills", "employment_types": ["Full Time", "Permanent"], "selling_points": ["Financial investigative reporting", "Knowledge of M&A strategies", "Knowledge of Market trends"], "locations": ["Central"], "categories": ["Banking / Finance", "Equities / Capital Markets"], "post_time": "2022-01-11T09:56:38Z", "salary": {"currency": null, "max": null, "min": null, "period": "monthly", "term": null}, "salary_visible": false, "title_keywords": ["hong kong financial reporter"], "responsibilities": ["maintain", "cooperate with"], "requirements": {"degrees": ["fresh graduate"], "majors": [], "languages": ["cantonese", "english", "mandarin"], "language_level": ["fluency"], "hard_skills": ["basic"], "soft_skills": ["passionate", "work independently", "time management skills"], "languages_combined": [{"language": "cantonese", "language_level": ["fluency"]}, {"language": "english", "language_level": ["fluency"]}, {"language": "mandarin", "language_level": ["fluency"]}]}, "experience_required": {"duration": [], "field": ["financial"]}}, {"job_id": "100003009035462", "location_code": "hk", "company": "Delta Asia Securities Limited", "job_title": "Settlement Manager (Ref.:STM_220110_JD983)", "description": "Responsibilities\n\n\nPerform daily settlement functions for Hong Kong & Overseas equity markets, Hong Kong & Overseas Futures markets, Stock Options, Bonds & Funds\nSupport on settlement functions including trade matching, customers fund deposit and withdrawal, SI, corporate actions, stock pledge processing, IPO and placement and other CCASS operations etc.\nHandle client account maintenance and ensure information is accurately and timely updated\nParticipate in system implementation projects in particular UAT and system migration\nEnsure operation procedures being in compliance with applicable regulatory requirements\n\nRequirements\n\n\nDiploma / Degree holder\n8+ years relevant experience in brokerage firm\nWith experience in system enhancement project is a plus\nProficient in MS Office and Chinese Word Processing\nResponsible, self-motivated, independent & able to work under pressure\nGood command of written and spoken English and Chinese\nImmediate available is highly preferred\n\nThe Candidate\u00a0with less experience\u00a0will be considered as Assistant Settlement Manager.\n\n\n\nApplication\n\nWe offer\u00a0competitive\u00a0remuneration and fringe benefits\u00a0including but not limited to the followings:\n\n15-20 days' Annual Leave\nCaring Leave (including birthday leave, graduation leave, wedding leave, volunteer leave, children \u00a0graduation leave, children wedding leave, etc.)\n\nInterested parties, please click \"APPLY NOW\". For more information or enquiry, please contact us at +852 9882 7957.\n\nAll information provided will be treated in strict confidence and only be used for recruitment purpose.\n\nWebsite: www.delta-asia.com", "employment_types": ["Full Time", "Permanent"], "selling_points": ["5-day work with competitive remuneration package", "15-20 days AL, birthday leave, wedding leave, etc.", "Immediately available is highly preferred"], "locations": ["Wan Chai"], "categories": ["Banking / Finance", "Financial Services", "Equities / Capital Markets", "Order Processing & Operation / Settlement"], "post_time": "2022-01-10T07:17:02Z", "salary": {"currency": null, "max": null, "min": null, "period": "monthly", "term": null}, "salary_visible": false, "title_keywords": ["settlement manager"], "responsibilities": ["uat", "operations", "regulatory requirements", "compliance", "procedures", "implementation", "migration", "account maintenance"], "requirements": {"degrees": ["diploma", "degree holder"], "majors": [], "languages": ["english", "chinese"], "language_level": ["good command", "proficient"], "hard_skills": ["plus", "chinese word processing", "ms office"], "soft_skills": ["self-motivated", "independent", "responsible", "work under pressure"], "languages_combined": [{"language": "english", "language_level": ["good command"]}, {"language": "chinese", "language_level": ["good command", "proficient"]}]}, "experience_required": {"duration": ["8+ years"], "field": ["brokerage", "relevant experience"]}}, {"job_id": "100003009038017", "location_code": "hk", "company": "Manpower Services (Hong Kong) Limited", "job_title": "Full Stack Engineer-Onsite with HSBC", "description": "Onsite with HSBC \u2013 Full Stack Engineer\n\nAs one of the world\u2019s largest banking and financial services organisations, HSBC has been connecting customers to opportunities since 1865. With operations in 64 countries and territories, HSBC\u2019s unparalleled international network links developed and emerging markets, and spans the world\u2019s largest and fastest-growing trade corridors. The bank serves more than 40 million customers through its commercial, retail, investment and private banking businesses, which are supported by operational and functional teams around the world.\n\n\u00a0We\u2019re currently seeking an experienced professional to join the HSBC APAC Fixed Income eTrading\u00a0team.\n\nTitle:\u00a0APAC Fixed Income eTrading Full Stack Engineer Global Banking & Markets, FICC IT\n\nPosition Type: Contract\n\nBudget: Upto 83k/month\n\nGlobal Debt Markets, EM Rates & BSM (Balance Sheet Management) IT at HSBC is a global asset class covering Front to Back IT services for 4 main business lines: BSM, Rates, Credit & Emerging Markets. It is a global team of over 400 people with a strong presence in London, Hong Kong, New York, Paris, Toronto, Guangzhou, Pune and Bangalore. The team is responsible for : - Pre trade systems allowing orders, market data streaming, market negotiations, Algo trading, live risk - A suite of primary trading systems, which support the trading and risk management capabilities of the desks, as well as all upstream & downstream connectivity and data feeds for all business functions - The generation of the p&l and risk numbers for the Fixed Income and BSM business - Tools which allow display/enrichment of data produced by relevant systems\n\nWorking in Fixed Income eTrading team, the candidate will be in charge of work items requiring\n\n1) To be the major team member in eTrading team in HK to build the strategic solution for Fixed Income trading.\n\n2) To be able to work DevOps to support the Front Office Traders.\n\n3) To build applications which provide traders with a UI for connecting to different markets for FI electronic trading.\n\n4) To support business in the region for etrading / algo trading related requests.\n\n5) Work with local and global IT team closely to deliver the technology roadmap.\n\n6) Build and maintain the global infrastructure environment as a part of the team.\n\nRequirements\n\nUniversity graduate with a degree in computer science, information technology or a business background\nBackground in delivering front end tools in investment banking\nKDB/Java/Javascript/Python hands-on experience in Linux/Unix\nION Trading technology is a plus\nHaving knowledge for Fixed Income knowledge is a plus\nAble to work with global teams and navigate in an international environment\nSeeks solutions and is creative with it. Confronts blocking issues\nMust speak/write fluent English\nGood inter-personal skills, well organised and with and ability to multi-task / switch context easily\n\nIf you are interested in this role, click \u201capply\u201d, else, you may also directly send your updated resume to Shwetha at shwetha.vineeth@manpowergrc.hk\n\nHSBC is committed to building a work culture where everyone is valued, respected and opinions count. They take pride in providing a workplace that fosters continuous professional development, collaboration and supporting people to be at their best in an inclusive and diverse environment", "employment_types": ["Contract"], "selling_points": ["Full Stack Engineer", "Onsite with HSBC", "Contract Position"], "locations": ["Central"], "categories": ["Banking / Finance", "Equities / Capital Markets", "Information Technology (IT)", "Application Specialist - Software", "Software Development"], "post_time": "2022-01-11T04:35:31Z", "salary": {"currency": null, "max": null, "min": null, "period": "monthly", "term": null}, "salary_visible": false, "title_keywords": ["engineer"], "responsibilities": ["management", "data", "operations", "budget", "teams", "systems", "p&l", "infrastructure", "maintain", "banking", "market data", "ui", "balance sheet"], "requirements": {"degrees": ["university graduate", "degree"], "majors": ["business", "computer science", "information technology"], "languages": ["english"], "language_level": ["fluent"], "hard_skills": ["linux", "java", "plus", "devops", "switch", "javascript", "python"], "soft_skills": ["multi-task", "creative", "responsible", "interested in", "inter-personal skills", "committed", "hands-on", "diverse", "organised", "team member"], "languages_combined": [{"language": "english", "language_level": ["fluent"]}]}, "experience_required": {"duration": [], "field": []}}, {"job_id": "100003009038655", "location_code": "hk", "company": "Asia Progress Executive Limited", "job_title": "Middle office/Operation - Wealth Management Local Business Support ( Private Banking )", "description": "Our client is a reputable international Private Banking /Wealth Management To cope with the rapid business expansion, they are now inviting high caliber candidates to join the team.\n\n\nMiddle office/ Operation - Wealth Management Local Business Support\n( Private Banking )\u00a0\n\nPosition Purpose\nThis position offer the opportunity to join our client service section in our operations platform to provide business support to the front office staff, ensure the completeness of the daily pre-operational control and contribute to operational permanent control framework. As this is a transversal role, the candidate is expected to cover BAU activities.\n\nResponsibilities\u00a0\n\n\n\nDirect Responsibilities\n\nTo be customer-focused and maintain a high quality service standard in liaison with RM/ MA / RPC (Regional Processing Centre) / ISPL\u00a0 and other stakeholders.\nHandle general inquiries from RM/MA, RPC & ISPL related to BAU issue.\nTo prepare and review daily reporting.\nTo handle daily operations in fund and securities transfer.\nTo monitor trade and prepare reporting for CIES account\nTo handle daily operations in corporate actions, IPO, placement & disclosure.\nTo provide support to the BAU team as assigned by section head/ department head.\n\n\nContributing Responsibilities\n\nTo assist section head to perform daily pre-operational control of RM/MA\u2019s & client\u2019s instructions and ensure the transactions are handled properly in accordance with the bank procedures/guidelines.\nTo coordinate with RPC/ISPL for timely execution of client\u2019s instructions.\nTo handle cash deposit/withdrawal, local and foreign cheque clearing, FPS & Autopay clearing and Loan & Deposit processing\nTo perform account administrative tasks.\nTo handle daily operations in securities transfer and physical scrip depository/withdrawal.\nTo perform pre-operational checking for all securities transaction instruction and follow up queries with RPC, ISPL, custodian, front office or counterparties if necessary.\nTo closely coordinate with RPC for Corporate Action news and ensure timely execution of front office instructions. Monitor and review RMs/Clients\u2019 election on Corporate actions and Event Summary to RPC for further processing.\nPerform pre-operation check on payment instructions received from FO.\nDeceased account handling.\nReport distribution to RM/MA\nPerform cheque book order\nPerform IVS inward cheque clearing\nPerform MRCS autopay clearing\nPerform FPS clearing\nLoan & Deposit Processing\nMaintain warehouse record and arrange shipment of daily transaction files to warehouse regularly\nTo prepare management reporting.\nTo participate in project and ad hoc assignments e.g. new system implementation, UAT, BCP and DR.\nDirect contribution to operational permanent control framework.\nContribute to the implementation of operational permanent control policies and procedures in day-to-day business activities, such as Control Plan.\nComply with regulatory requirements and internal guidelines.\nContribute to the reporting of all incidents according to the Incident Management.\n\nTechnical & Behavioral Competencies\n\nRelevant working experience in payment and securities operations, ideally have checker experience.\nGood knowledge in account operations and general banking operations\nEffective communications skills.\nGood written and spoken English.\nGood in MS Office applications (Excel, Word, PowerPoint\u2026etc).\nTake initiatives, responsible and motivated. Willing to work overtime if required.\nGood interpersonal skill, attentive to details and accuracy.\nCommitted to customers, diligent, adaptability to changing environment\n\nSpecific Qualifications (if required)\n\nDegree holder in Business Studies (e.g. Accountancy & Finance)\nwith at least 5 years relevant Private banking experience.\nExperience in middle & back office operations in a sizable financial institution is\u00a0\u00a0\n\nPlease send full resume with\u00a0present & expected\u00a0salary to expedite sourcing\u00a0in\u00a0MS-WORD\u00a0format by clicking \u201cAPPLY NOW\u201d\nPlease quote our reference in your application\nPersonal data provided by job applicants will be used strictly in accordance with the employer\u2019s personal data policies, a copy of which will be provided upon request\nAll information provided will be used for recruitment purpose only", "employment_types": ["Full Time"], "selling_points": ["Degree 5yrs Private Banking Operation, US mkts", "daily operations in fund and securities transfer.", "exp in US stock /US Markets,transfer payments"], "locations": ["Central & Western Area"], "categories": ["Banking / Finance", "Private Banking", "Equities / Capital Markets", "Order Processing & Operation / Settlement"], "post_time": "2022-01-11T07:35:40Z", "salary": {"currency": null, "max": null, "min": null, "period": "monthly", "term": null}, "salary_visible": false, "title_keywords": ["wealth management", "private banking"], "responsibilities": ["service standard", "operations", "regulatory requirements", "quality", "transactions", "payment", "maintain", "plan", "personal data", "control", "uat", "new system implementation", "monitor", "implementation", "banking", "autopay", "business activities", "report", "reporting", "management", "provide support", "review", "procedures", "coordinate with", "checking", "daily operations", "management reporting", "administrative tasks", "guidelines", "policies", "back office", "recruitment", "ad hoc assignments"], "requirements": {"degrees": ["degree holder"], "majors": ["business"], "languages": ["english"], "language_level": ["good"], "hard_skills": ["excel", "ms-word", "word", "powerpoint", "rapid", "system implementation", "processing", "ms office"], "soft_skills": ["work overtime", "customer-focused", "responsible", "attentive to details", "timely", "diligent", "interpersonal skill", "committed", "motivated", "adaptability"], "languages_combined": [{"language": "english", "language_level": ["good"]}]}, "experience_required": {"duration": ["at least 5 years"], "field": ["securities", "relevant working experience", "banking experience", "financial"]}}, {"job_id": "100003007407150", "location_code": "hk", "company": "Resource Solutions Consulting Hong Kong Limited", "job_title": "Executive Secretary, 6-month contract (temp to perm opportunity)", "description": "About Our Client\n\nOur client is a prestigious international bank with a long history of providing corporate banking solutions to businesses and to large local companies, financial institutions and multinationals. We look for talented, tenacious individuals who are hungry to progress and eager to grow their knowledge.\n\nKey Responsibilities:\n\nAssist the Head of FIC and other FIC teams to efficiently organize their agenda; in particular their business trip (hotel, air ticket, visa, etc.), client and internal meetings, conference call, etc, and organize regional/territory meetings/seminars\nSchedule and co\u2010ordinate meetings and facilities which may include travel and lodging arrangements\nPrepare monthly activity reporting when requested, travelling and coming clients meetings report and any ad\u2010hoc documents and presentation materials, statistical, planning reports, or business reporting\nMaintenance and adequate/optimize filing of documents\nReceive, handle and transfer phone calls and messages within the department promptly and courteously.\nKeep confidential and sensitive reports / analysis / clients information / other information to the Bank.\nResponsible for general administration, including stationery, office furniture, equipment etc\nSelect and circulate the newspaper clippings within the department\nSubmit the overtime claim and absence reports regularly.\nAssist in logistic matters involved with external/internal visitors. Ensure trouble free visits (access badges, meeting schedule, airport pick up, hotel booking when necessary)\nArrange for visa applications\nDirect contribution to the team's operational permanent control framework\n\nQualifications:\n\nBachelor Degree\n3-5 years of relevant experiences in banking and finance\nStrong interpersonal skills\nOrganized and able to work independently and under pressure\nGood communication skills, verbal and written\nFluent in spoken and written English and Chinese\nImmediate available preferred\n\nValues and Diversity\n\nDynamic working gives everyone at our client the opportunity to integrate professional and personal lives, if you have a need for flexibility then please discuss this with the hiring manager. They are an equal opportunity employer and are opposed to discrimination on any grounds. It is the policy of our client to ensure equal employment opportunity without discrimination or harassment on the basis of race, colour, creed, religion, national origin, alienage or citizenship status, age, sex, sexual orientation, gender identity or expression, marital or domestic/civil partnership status, disability, veteran status, genetic information, or any other basis protected by law.", "employment_types": ["Full Time", "Temporary", "Contract"], "selling_points": ["International Investment Bank", "Work with a global team", "Immediate Available preferred"], "locations": ["Central"], "categories": ["Admin & HR", "Secretary", "Banking / Finance", "Dealing & Trading", "Equities / Capital Markets"], "post_time": "2022-01-11T03:41:14Z", "salary": {"currency": null, "max": null, "min": null, "period": "monthly", "term": null}, "salary_visible": false, "title_keywords": ["executive secretary"], "responsibilities": ["administration", "reporting", "control", "maintenance", "analysis", "teams", "stationery", "communication", "planning", "reports", "schedule", "business trip", "banking", "booking", "phone calls", "report"], "requirements": {"degrees": ["degree", "bachelor"], "majors": [], "languages": ["english", "chinese"], "language_level": ["fluent"], "hard_skills": ["analysis", "dynamic", "maintenance"], "soft_skills": ["organized", "work independently", "communication skills", "under pressure", "responsible", "dynamic", "interpersonal skills", "sensitive", "presentation", "tenacious"], "languages_combined": [{"language": "english", "language_level": ["fluent"]}, {"language": "chinese", "language_level": ["fluent"]}]}, "experience_required": {"duration": ["3-5 years"], "field": ["finance", "banking"]}}, {"job_id": "100003009033302", "location_code": "hk", "company": "Fillture Group Limited", "job_title": "Corporate Finance Analyst / Assistant to CFO", "description": "Our client is a HK listed company. They are now looking for a Corporate Finance Analyst / Assistant to their CFO.\n\nResponsibilities:\n\nReporting to CFO, conduct financial and business analysis,\u00a0financial modelling and industry research etc\nProvide support the group's investment decisions, financing\u00a0projects and communications with investors\nWork with other members of the Company, incl. IR team, Corporate Development\u00a0team for the execution of finance and investment projects on worldwide\u00a0basis. And ensure all actions are in compliance of relevant regulations,\u00a0policies and guidelines.\nProvide regular progress and management reports on the\u00a0undergoing projects.\nAssist in ad hoc corporate projects, strategic planning, and other\u00a0assignments from supervisor(s)\nRequirements:\nBachelor Degree Holder in Accounting, Economics, Business Administration or equivalent is a MUST\n5 years of work experience in equity research or financial media is preferred\nCandidates with financial modelling and business valuation experience is an added advantage\nWorking experience in renowned MNC in a regional capacity will be an added advantage\nPrior experience in sizable and complex businesses, excel (pivot table, VBA) and great communication skills\nFluency in English, Mandarin is essential to this role\n\nApply for this job:\n\nInterested candidate please CLICK apply button to apply online or send your resume in MS word format to Fillture Group Limited\n\nFor more information please contact\u00a0Danvis Lau\u00a0+852 2814 9388.\n\nPlease note that only shortlisted candidate will be notified. All information will be treated in strict confidence and solely used for recruitment purposes.", "employment_types": ["Full Time", "Permanent"], "selling_points": ["HK Listed Company", "CFO Assistant", "Financial Modelling & Business Analysis"], "locations": ["Central & Western Area"], "categories": ["Accounting", "Financial Analyst", "Banking / Finance", "Corporate Finance", "Equities / Capital Markets"], "post_time": "2022-01-09T05:51:31Z", "salary": {"currency": null, "max": null, "min": null, "period": "monthly", "term": null}, "salary_visible": false, "title_keywords": ["analyst", "cfo", "assistant", "corporate finance"], "responsibilities": ["regulations", "reporting", "communications with", "provide support", "ad hoc", "strategic planning", "guidelines", "policies", "compliance", "financial and business analysis", "management reports"], "requirements": {"degrees": ["bachelor degree holder"], "majors": ["economics", "accounting", "business administration"], "languages": ["english", "mandarin"], "language_level": ["fluency"], "hard_skills": ["vba", "excel", "pivot table", "ms word"], "soft_skills": ["communication skills", "confidence"], "languages_combined": [{"language": "english", "language_level": ["fluency"]}, {"language": "mandarin", "language_level": ["fluency"]}]}, "experience_required": {"duration": ["5 years"], "field": ["equity research", "business", "media", "financial"]}}, {"job_id": "100003009030285", "location_code": "hk", "company": "Central Wealth Securities Investment Limited", "job_title": "Debt Capital Markets Professionals", "description": "Central Wealth Securities Investment Limited\n\nPosition\u00a0\u00a0\u00a0\u00a0 :\u00a0\u00a0\u00a0\u00a0 Debt Capital Markets professionals\n\nWe are recruiting various levels of high calibre industry professionals to fill our positions in Debt Capital Markets Department.\n\nThe right candidate should have relevant knowledge and experience in handlingbond issuance projects in the PRC, providing bond financing services, conducting due diligence, credit analysis, rating assessment, etc.\u00a0 In addition to excellent technical knowledge, analytical skills and business sense, the candidate must be able to connect and build trust with the clients and other stakeholders.\u00a0 Fluency in Mandarin and English is needed.", "employment_types": ["Full Time", "Permanent"], "selling_points": ["Handling bond issuance projects", "Conducting due diligence", "Projects in the PRC"], "locations": ["Admiralty"], "categories": ["Banking / Finance", "Investment", "Financial Services", "Equities / Capital Markets"], "post_time": "2022-01-07T07:09:07Z", "salary": {"currency": null, "max": null, "min": null, "period": "monthly", "term": null}, "salary_visible": false, "title_keywords": [], "responsibilities": ["due diligence", "analysis"], "requirements": {"degrees": [], "majors": [], "languages": ["english", "mandarin"], "language_level": ["fluency"], "hard_skills": ["credit analysis", "analytical skills"], "soft_skills": ["business sense", "analytical skills"], "languages_combined": [{"language": "english", "language_level": ["fluency"]}, {"language": "mandarin", "language_level": ["fluency"]}]}, "experience_required": {"duration": [], "field": ["financing"]}}, {"job_id": "100003009041259", "location_code": "hk", "company": "ConnectedGroup Limited", "job_title": "VP- AML Compliance", "description": "Our client, an esteemed Investment Bank, is looking for an VP- AML to cope with the business expansion. This incumbent is being the MLRO and reports to the Head of Compliance directly.\n\nResponsibilities:\n\nDevelop and maintain an AML/CFT compliance program and control framework that is compliant with local AML/CFT legislation, rules and regulations issued by the SFC and relevant authorities as well as firm policies.\nBeing the MLRO, act as the central reference point for suspicious transaction reporting, and as the main point of contact with the Joint Financial Intelligence Unit or law enforcement\nProvide oversight to ensure day to day functions of AML Compliance are conducted effectively including, but not limited to, AML/CFT governance; customer name screening; transactions screening and approval functions; AML/CFT advisory and client risk assessment; AML/CFT transaction monitoring function. Working with front, middle and back office staff to ensure that appropriate controls, surveillance reports and procedures are in place to support and monitor any new business/product and that such procedures are as consistent as possible with group standards and procedures.\nProvide guidance, advice and risk-based solutions to the business on their responsibility to comply with all relevant AML laws, regulations and related firm policies.\nManage any internal/external audits & reviews on the local AML Compliance program. * Develop, deliver and track AML/CTF training\n\nRequirements:\n\nUniversity graduated in Finance or business administration or relevant disciplines.\nMinimum 8 years relevant AML experience gained from an international bank environment\nGood knowledge of financial markets and preferably with regional exposures.\nStrong communication and interpersonal skills\nSelf- motivated and innovative.\nFluency in written and spoken English and Chinese.", "employment_types": ["Full Time", "Permanent"], "selling_points": ["An Esteemed Investment Bank", "New Additional Headcount", "Attractive Remuneration"], "locations": ["Not Specified"], "categories": ["Banking / Finance", "Financial Services", "Equities / Capital Markets", "Others"], "post_time": "2022-01-12T03:39:36Z", "salary": {"currency": null, "max": null, "min": null, "period": "monthly", "term": null}, "salary_visible": false, "title_keywords": ["aml compliance"], "responsibilities": ["regulations", "reporting", "control", "aml", "policies", "compliance", "monitoring", "back office", "transactions", "develop", "procedures", "monitor", "maintain", "reports", "contact", "audits", "provide guidance"], "requirements": {"degrees": [], "majors": [], "languages": ["english", "chinese"], "language_level": ["fluency"], "hard_skills": ["aml"], "soft_skills": ["motivated", "communication and interpersonal skills", "innovative"], "languages_combined": [{"language": "english", "language_level": ["fluency"]}, {"language": "chinese", "language_level": ["fluency"]}]}, "experience_required": {"duration": ["minimum 8 years"], "field": []}}, {"job_id": "100003009038850", "location_code": "hk", "company": "Ambition", "job_title": "AVP - Product Control", "description": "Top-tier Investment Bank\nExcellent package and benefits\nOpen to big4\n\nOur client, a top-tier Investment Bank with strong business operations across the globle, is looking for a Product Controller in AVP level to support their business.\n\nReporting to Executive Director, Product Control, you are responsible for the following but not limited to:\n\nSpecialise in Equities in the APAC markets\nPrepare daily P&L and balance sheet report and ensure the accuracy of trade bookings\nConduct FOBO reconciliations and resolve any related issues on timely basis\nReview risk profiles, booking methodologies, as well as valuation models for complex structured trades\nLiaise with internal stakeholders to drive control and efficiency improvements\n\nTo qualify, individuals must possess:\n\nUniversity degree holder in Accounting or equivalent disciplines with professional accounting qualification\nMinimum 5 years of relevant experience, preferably with Equities experience\nStrong interpersonal, communication and presentation skills\nExcellent communication skills with fluency in both Chinese and English\nStrong analytic skills and control mindset\nImmediately available is preferred\n\nInterested parties, send your updated resume to rita.lee@ambition.com.hk or click \"Apply Now\".\n\nOnly shortlisted candidates would be notified.\n\n#LI-BF\n\n#BUILDINGBETTERFUTURES\n\nIf this job isn't quite right for you, but you know someone who would be great at this role, why not take advantage of our referral scheme? We offer HKD1000 in Apple gift cards for every referred candidate who we place in a role. Terms & Conditions Apply. https://www.ambition.com.hk/refer-a-friend", "employment_types": ["Full Time", "Permanent"], "selling_points": ["Top-tier Investment Bank", "Excellent package and benefits", "Immediately available preferred"], "locations": ["Not Specified"], "categories": ["Banking / Finance", "Dealing & Trading", "Equities / Capital Markets", "Others"], "post_time": "2022-01-11T07:56:28Z", "salary": {"currency": null, "max": null, "min": null, "period": "monthly", "term": null}, "salary_visible": false, "title_keywords": [], "responsibilities": [], "requirements": {"degrees": [], "majors": [], "languages": [], "language_level": [], "hard_skills": [], "soft_skills": [], "languages_combined": []}, "experience_required": {"duration": [], "field": []}}, {"job_id": "100003009036038", "location_code": "hk", "company": "Grandly Financial Services Limited", "job_title": "Dealing /Customer Service Officer", "description": "Responsibilities Include:\n\nDealing and Risk-Control: Closely monitor global securities and futures markets and assist with market analysis, order execution, risk-control etc.\nCustomer Service(CS): Directly service clients to provide investment information, professional customer service, account opening, and client relationship management.\nMarket\u00a0Analysis:\u00a0:\u00a0Thoroughly\u00a0analyze\u00a0latest market developments and trends to produce research reports, investment recommendations, published presentations etc.\nComplete daily workflow and ad-hoc projects as assigned.\n\nRequirements\uff1a\n\n\nFluent in Cantonese, Mandarin and\u00a0English .\n\nDegree holder major in finance related disciplines.\n\nQuick learner and team player with great attitude.\n\nWork experience in the securities and futures industry highly preferred.\n\nFamiliarity with Ayers Trading System, Esunny Trading System and Bloomberg preferred.\nRecent graduates will be considered", "employment_types": ["Full Time"], "selling_points": ["SFC Type 1, 2 front office role", "Experienced professional team", "Fast growing platform with considerable salary"], "locations": ["Wan Chai"], "categories": ["Banking / Finance", "Financial Services", "Dealing & Trading", "Equities / Capital Markets"], "post_time": "2022-01-11T01:45:59Z", "salary": {"currency": null, "max": null, "min": null, "period": "monthly", "term": null}, "salary_visible": false, "title_keywords": ["customer service officer"], "responsibilities": ["control", "management", "account opening", "monitor", "presentations", "market analysis", "customer service", "reports", "ad-hoc projects"], "requirements": {"degrees": ["degree holder"], "majors": ["related disciplines", "finance"], "languages": ["cantonese", "english", "mandarin"], "language_level": ["fluent"], "hard_skills": ["bloomberg"], "soft_skills": ["team player", "quick learner"], "languages_combined": [{"language": "cantonese", "language_level": ["fluent"]}, {"language": "english", "language_level": ["fluent"]}, {"language": "mandarin", "language_level": ["fluent"]}]}, "experience_required": {"duration": [], "field": ["securities"]}}, {"job_id": "100003009034120", "location_code": "hk", "company": "Randstad Hong Kong Limited", "job_title": "Financial Markets Operation Associate (up to 50k)", "description": "about the company.\n\nOur client is a top tier foreign bank. They are looking for an operations candidate to build up their operations functions in Hong Kong office.\nabout the job.\nAs an operations associate, you will be:\nsupport traders on trade settlement activities management\nensure efficient settlement and clearing of trades\nSupport projects by UAT testing prior to project delivery with the trading system IT teams\nUpdate and optimize existing processes and procedures.\nMaintain close communication with head quarter and other offices across different time zones\nskills & experiences required.\n5+ years of experience in handling derivatives, FX, fixed income products, collateral activities/margin calls and securities financing.\nGood knowledge of Microsoft Office and Excel (VBA, Macros, pivot tables, dynamic tables, etc.)\nKnowledge of Murex, Euroclear, Bony, Swift, ISM, Bloomberg or Refinitiv systems desirable\n\nTo apply online please click the Apply button below. For a confidential discussion, feel free to contact Gladys Chan on +852 2232 3492 or email gladys.chan@randstad.com.hk", "employment_types": ["Full Time", "Permanent"], "selling_points": [], "locations": ["Not Specified"], "categories": ["Banking / Finance", "Equities / Capital Markets", "Others", "Order Processing & Operation / Settlement"], "post_time": "2022-01-10T02:44:16Z", "salary": {"currency": "HKD", "max": 44999, "min": 35000, "period": "monthly", "term": null}, "salary_visible": true, "title_keywords": ["associate"], "responsibilities": ["support projects", "management", "operations", "systems", "uat testing", "teams", "procedures", "communication", "maintain", "contact"], "requirements": {"degrees": [], "majors": [], "languages": [], "language_level": [], "hard_skills": ["excel", "vba", "bloomberg", "microsoft office", "dynamic", "swift"], "soft_skills": ["efficient", "dynamic", "communication"], "languages_combined": []}, "experience_required": {"duration": ["5+ years"], "field": ["securities", "financing"]}}, {"job_id": "100003009036182", "location_code": "hk", "company": "Fubon Bank (Hong Kong) Limited", "job_title": "Assistant Manager / Supervisor, Capital Management & ALCO Support, Financial Control Division", "description": "Responsibilities:\n\nPerform CAR projection, capital planning, monitoring and management\nAssist in coordinate and perform internal capital assessment process & capital stress testing\nAssist in review of policies, guidelines and procedures relating to capital management and capital stress testing\nPerform ad-hoc assignment assigned by management\n\nRequirements:\n\nUniversity degree in a related discipline, with a recognized qualification such as HKICPA, ACCA, CFA and FRM an advantage\nMinimum 3 years finance-related banking experience\nAble to work under pressure and attentive to details with strong communication, interpersonal and analytical skills\nSound knowledge of application software, such as Microsoft Excel and Powerpoint\nProficiency in English and Chinese, fluency in Putonghua an advantage\nLess working experience will be considered for the post of \u2018Supervisor\u2019\n\n\n\nPlease send your application with full resume indicating current and expected salary, and quoting the above reference no.\n\nFor other vacancies, please visit our website:\u00a0http://www.fubonbank.com.hk/\n\n*All personal data provided by job applicants will be used for recruitment purposes only in accordance with the Bank\u2019s Personal Data Information Collection Statement, a copy of which is available on our website:\u00a0http://www.fubonbank.com.hk/web/html/sh_careers_e.html", "employment_types": ["Permanent"], "selling_points": ["13 Month Pay", "Medical Benefits", "Insurance Benefits"], "locations": ["Central"], "categories": ["Banking / Finance", "Financial Services", "Equities / Capital Markets", "Asset Management"], "post_time": "2022-01-10T09:35:45Z", "salary": {"currency": null, "max": null, "min": null, "period": "monthly", "term": null}, "salary_visible": false, "title_keywords": ["assistant manager", "supervisor"], "responsibilities": ["ad-hoc", "management", "guidelines", "policies", "monitoring", "review", "procedures", "testing", "coordinate", "planning"], "requirements": {"degrees": ["university degree"], "majors": [], "languages": ["putonghua", "english", "chinese"], "language_level": ["fluency", "advantage", "proficiency"], "hard_skills": ["acca", "no", "web", "cfa", "powerpoint", "analytical skills", "microsoft excel", "html", "frm", "hkicpa"], "soft_skills": ["attentive to details", "analytical skills", "communication", "interpersonal", "work under pressure"], "languages_combined": [{"language": "putonghua", "language_level": ["fluency"]}, {"language": "english", "language_level": ["proficiency", "fluency", "advantage"]}, {"language": "chinese", "language_level": ["proficiency", "fluency", "advantage"]}]}, "experience_required": {"duration": ["minimum 3 years"], "field": ["related", "finance", "banking experience"]}}, {"job_id": "100003009033743", "location_code": "hk", "company": "Hays", "job_title": "TMT Director", "description": "Your new company\n\nMy client is one of the largest PRC Securities firm with over 100 branch offices across all major cities in China, North America, and UK. Within 15 years, the capital of the company has increased from HK$1 million to HK$4103million. The company currently has around 350 employees in Hong Kong. To accommodate the growing business, the team is looking to hire more people to lead the corporate finance & capital markets team.\n\nWhat you'll need to succeed\n\n\nOver of 6 years of solid investment banking experience in reputable financial institutions. Senior candidate must have proven track records in deal origination and solid experience in client coverage (Preferably in Fintech or TMT sector)\nExperiences in handling IPO transactions in the role of a sponsor or in vetting IPO applications in the role of regulator\nAbility to maintain good stakeholder/client relationship and develop new business\nAbility to lead junior staff in deal origination and marketing activities.\nExcellent command of spoken and written English and Chinese (including Mandarin)\nCandidate with Big 4 audit experience an advantage\n\n\nWhat you'll get in return\n\nThis role provides you management opportunity in a vivid and lively platform. You will have exposure to high portfolios and projects from Greater China's top firms. In addition, you will be working in a resourceful company in the top blooming sector in the industry.\n\nWhat you need to do now\n\nIf you're interested in this role, click 'apply now' or forward an up-to-date MS Word copy of your CV to Frondia.Hsu@hays.com.hk\n\nIf this job isn't quite right for you but you are looking for a new position, please contact us for a confidential discussion on your career.\nhttps://hk.joblum.com/job/team-head-china-business-international-private/334718", "employment_types": ["Full Time", "Permanent"], "selling_points": ["Management opportunity in a lively platform", "Exposure to high portfolios and projects", "Resourceful company in the top blooming sector"], "locations": ["Not Specified"], "categories": ["Banking / Finance", "Corporate Finance", "Financial Services", "Equities / Capital Markets"], "post_time": "2022-01-10T01:44:16Z", "salary": {"currency": null, "max": null, "min": null, "period": "monthly", "term": null}, "salary_visible": false, "title_keywords": ["director"], "responsibilities": ["management", "develop new business", "audit", "transactions", "maintain", "contact", "banking"], "requirements": {"degrees": [], "majors": [], "languages": ["english", "chinese", "mandarin"], "language_level": ["excellent"], "hard_skills": ["ms word"], "soft_skills": ["interested in", "vivid", "resourceful"], "languages_combined": [{"language": "english", "language_level": ["excellent"]}, {"language": "chinese", "language_level": ["excellent"]}, {"language": "mandarin", "language_level": ["excellent"]}]}, "experience_required": {"duration": ["of 6 years"], "field": ["banking experience", "big 4", "investment", "audit experience", "financial institutions"]}}, {"job_id": "100003009034295", "location_code": "hk", "company": "Page Personnel", "job_title": "Account Opening/KYC Analyst - MNC Brokerage", "description": "Perform KYC checking for account opening for retail & institutional clients.\nJoin a leading brokerage firm that is always expanding the business.\n\nClient Details\n\nOur client is a company that operates a digital trading platform that allows access to electronic brokering services that caters to the needs of professional and frequent traders, institutional investors, financial advisors, and introducing brokers.\n\nDescription\n\n* Correspond to inquiries and concerns externally with clients via in-person meetings, telephone, e-mail and on-line chat; internally to sales representatives and customer service representatives\n* Research and resolve a wide variety of client question/issues on the account opening process\n* Multi task with a strong emphasis on AML and KYC knowledge while dealing with incoming customer queries\n* Learn all aspects of the Brokerage platform /policy and offer alternatives and options to satisfy customer concerns while complying with policies, practices and procedures\n* Work closely with Legal and Compliance, Program Developers, and Project Managers to ensure compliance with new and existing procedures and regulatory requirements.\n\nProfile\n\n* Bachelor's degree\n* 2-3 years in Customer Service and/or Financial Service preferred. Fresh graduates who are motivated will also be considered\n* Excellent written and oral communication skills in English/Cantonese/Mandarin\n* Basic understanding of brokerage regulations and rules that govern client accounts\n* Demonstrates experience in handling client concerns and issues with tact and diplomacy\n* Ability to work independently and effectively as part of a team, while handling multiple tasks and responsibilities simultaneously\n\nJob Offer\n\n18 AL\nMedical\nMPF\nAnnual bonus\nOther MNC benefits\n\nTo apply online please click the 'Apply' button below. For a confidential discussion about this role please contact Matt O'Shaughnessy on +852 3602 2438", "employment_types": ["Full Time", "Permanent"], "selling_points": ["Join a leading MNC financial services company", "International culture", "Stable working hours"], "locations": ["Not Specified"], "categories": ["Banking / Finance", "Financial Services", "Equities / Capital Markets", "Risk Management"], "post_time": "2022-01-10T03:06:13Z", "salary": {"currency": "HKD", "max": 29999, "min": 20000, "period": "monthly", "term": null}, "salary_visible": true, "title_keywords": ["analyst"], "responsibilities": ["regulations", "aml", "mpf", "account opening", "brokerage", "policies", "procedures", "checking", "compliance", "ensure compliance", "regulatory requirements", "communication", "customer service", "kyc", "customer queries"], "requirements": {"degrees": ["degree", "bachelor"], "majors": [], "languages": ["cantonese", "english", "mandarin"], "language_level": ["excellent"], "hard_skills": ["account opening", "basic", "aml", "kyc"], "soft_skills": ["communication skills", "oral", "work independently", "multiple tasks", "motivated", "customer service"], "languages_combined": [{"language": "cantonese", "language_level": ["excellent"]}, {"language": "english", "language_level": ["excellent"]}, {"language": "mandarin", "language_level": ["excellent"]}]}, "experience_required": {"duration": [], "field": []}}, {"job_id": "100003009038839", "location_code": "hk", "company": "Ambition", "job_title": "Treasury Product Control Manager- URGENT HIRING", "description": "Well-established Foreign Bank\n\nExcellent package and benefits\n\nConvenient working location\n\nOur client is a well-established foreign bank with strong presence in APAC, they are now looking for a Product Control Manager to support their business.\n\nReporting to Executive Director, Product Control, you are responsible for the following but not limited to:\n\nSpecialise in Treasury products in the APAC markets\n\nPrepare daily P&L and balance sheet report and ensure the accuracy of trade bookings\n\nConduct timely reconciliations and resolve any related issues on timely basis\n\nAssist in various projects sucha s new product launch and due diligence\n\nLiaise with internal stakeholders to drive control and efficiency improvements\n\nTo qualify, individuals must possess:\n\nUniversity degree holder in Accounting or equivalent disciplines with professional accounting qualification\n\nMinimum 6 years of relevant experience, preferably with treasury products experience\n\nStrong interpersonal, communication and presentation skills\n\nExcellent communication skills with fluency in both Cantonese, and English\n\nStrong analytic skills and control mindset\n\nInterested parties, send your updated resume to rita.lee@ambition.com.hk or click \"Apply Now\".\n\nOnly shortlisted candidates would be notified.\n\n#LI-BF\n\n#BUILDINGBETTERFUTURES\n\nIf this job isn't quite right for you, but you know someone who would be great at this role, why not take advantage of our referral scheme? We offer HKD1000 in Apple gift cards for every referred candidate who we place in a role. Terms & Conditions Apply. https://www.ambition.com.hk/refer-a-friend", "employment_types": ["Full Time", "Permanent"], "selling_points": ["Well-established Foreign Bank", "Excellent package and benefits", "Convenient working location"], "locations": ["Not Specified"], "categories": ["Banking / Finance", "Treasury", "Equities / Capital Markets", "Others"], "post_time": "2022-01-11T07:55:28Z", "salary": {"currency": null, "max": null, "min": null, "period": "monthly", "term": null}, "salary_visible": false, "title_keywords": ["manager"], "responsibilities": [], "requirements": {"degrees": [], "majors": [], "languages": [], "language_level": [], "hard_skills": [], "soft_skills": [], "languages_combined": []}, "experience_required": {"duration": [], "field": []}}, {"job_id": "100003009037727", "location_code": "hk", "company": "Asia Progress Executive Limited", "job_title": "Administration officer/Corporate Affairs - PRC Securities Brokerage", "description": "Our client is PRC\u00a0 Securities Brokerage;\u00a0To cope with the rapid\u00a0business expansion, they are now inviting high caliber candidates to join the team\n\n\n\nAdministration Officer / Corporate Affairs\u00a0-PRC\u00a0 Securities Brokerage\u00a0\n\nJob Description\n\nThe candidate should be degree holder and have three years relevant exp;\nPerform all-round administration support for our securities business\nCoordinate of the administrative work of various teams and external parties to ensure smooth daily operation\nLead a tea lady and receptionist\nPerform ad hoc projects and duties as assigned\nRequirement\u00a0\n\n-Degree holder\u00a0\n-with at 3 yrs Admin officer /must work in\u00a0 Securities firm /or\u00a0 Financial Services co./Or banking industry\u00a0\n-Fluent English, Cantonese and Mandarin\u00a0\n\n\n\nPlease send full resume with\u00a0present & expected\u00a0salary to expedite sourcing\u00a0in\u00a0MS-WORD\u00a0format by clicking \u201cAPPLY NOW\u201d\nPlease quote our reference in your application\nPersonal data provided by job applicants will be used strictly in accordance with the employer\u2019s personal data policies, a copy of which will be provided upon request\nAll information provided will be used for recruitment purpose only", "employment_types": ["Full Time"], "selling_points": ["Deg 3 years relevant of Admin exp in Securities co", "Perform all-round administration support", "Coordinate adm work of various teams lead tea lady"], "locations": ["Central & Western Area"], "categories": ["Admin & HR", "Administration / Operation Manager", "Banking / Finance", "Financial Services", "Equities / Capital Markets"], "post_time": "2022-01-11T05:00:34Z", "salary": {"currency": null, "max": null, "min": null, "period": "monthly", "term": null}, "salary_visible": false, "title_keywords": ["administration officer"], "responsibilities": ["administrative work", "external parties", "teams", "daily operation", "coordinate", "ad hoc projects", "administration"], "requirements": {"degrees": [], "majors": [], "languages": ["cantonese", "english", "mandarin"], "language_level": [], "hard_skills": ["ms-word"], "soft_skills": [], "languages_combined": [{"language": "cantonese", "language_level": []}, {"language": "english", "language_level": []}, {"language": "mandarin", "language_level": []}]}, "experience_required": {"duration": [], "field": []}}, {"job_id": "100003009034403", "location_code": "hk", "company": "Page Personnel", "job_title": "Customer Service Officer - Brokerage", "description": "Handle client servicing duties including account enquiries, account openings, perform outbound calls for follow-ups.\nCall Center position with strong product and career exposure.\n\nClient Details\n\nMy client is a capital markets and investment group that focuses on alternative investments, corporate finance, asset management, securities, capital markets, and wealth management for corporate and institutional clients. They operate in 20+ countries and are a leading name in the market. They are looking to expand their team to hire 2 Officers/Assistant Managers for branch brokerage services.\n\nDescription\n\nHandle inbound customer enquiries by phone or email related to marketing, products, services, stock trading and any other enquiries from clients.\nAssist in account openings and perform KYC and CDD checking.\nFacilitate customers deposits and withdrawals for securities trading.\nPerform business support duties such as administration, daily reports, system check etc...\nPerform outbound calls in relation to sales, marketing, service, and audit checks.\nAssist in ad-hoc duties when required.\n\nProfile\n\nBachelor degree holder in any discipline.\nMinimum of 1 year working experience in call centre/business support in securities/brokerage industry.\nHolder of HKSI 1,7,8 or SFC licenses.\nStrong communication and listening skills.\nGood computer knowledge of MS applications.\nExcellent language skills in Cantonese, Mandarin, and English.\n\nJob Offer\n\n20 Days annual leave\nMPF\nMedical\nDiscretionary Bonus\n\nTo apply online please click the 'Apply' button below. For a confidential discussion about this role please contact Matt O'Shaughnessy on +852 3602 2438", "employment_types": ["Full Time", "Permanent"], "selling_points": ["Client servicing role for institutional clients", "Leading MNC company", "HKSI 1,7,8 license required"], "locations": ["Not Specified"], "categories": ["Banking / Finance", "Financial Services", "Equities / Capital Markets", "Sales, CS & Business Devpt", "Customer Service - Supervisor / Officer"], "post_time": "2022-01-10T03:19:14Z", "salary": {"currency": "HKD", "max": 29999, "min": 20000, "period": "monthly", "term": null}, "salary_visible": true, "title_keywords": ["customer service officer"], "responsibilities": ["administration", "management", "mpf", "ad-hoc duties", "customer enquiries", "brokerage", "cdd", "checking", "audit", "communication", "contact", "kyc", "daily reports", "asset management"], "requirements": {"degrees": ["bachelor degree holder"], "majors": [], "languages": ["cantonese", "english", "mandarin"], "language_level": ["excellent"], "hard_skills": ["cdd", "ms applications", "hksi", "kyc"], "soft_skills": ["communication", "ad-hoc duties"], "languages_combined": [{"language": "cantonese", "language_level": ["excellent"]}, {"language": "english", "language_level": ["excellent"]}, {"language": "mandarin", "language_level": ["excellent"]}]}, "experience_required": {"duration": ["minimum of 1 year"], "field": ["brokerage", "securities", "business support"]}}, {"job_id": "100003009035595", "location_code": "hk", "company": "Hays", "job_title": "Regional IBD Compliance Manager (Up to 80k)", "description": "You will work under the IBD Compliance team, starting with a 6-months contract with high chance to renew\n\nYour new company\nMy client is a leading bank with overseas investment business across the globe.\n\nYour new role\n\nAdvice compliance and regulatory matters to the Investment Banking Division/Capital Markets\nReview M&A transactions and new business initiatives from a compliance perspective\nMaintain, update and modify firm's compliance policies and procedures to adhere with latest regulatory requirements and standards\nRespond to regulatory inquiries, inspections and investigations procedures such as testing and monitoring controls and surveillance\n\n\nWhat you'll need to succeed\n\nBachelor's Degree holder in Law /Legal /Accounting/ Finance or related disciplines\nAt least 5 years of related experience within compliance in an investment bank or law firm\nProficient in English and Mandarin with good communication skills\nTeam player and able to work effectively with minimal supervision\nExposure in Capital Markets/M&A is preferred\n\n\nWhat you'll get in return\n\nDevelop your career with a top tier investment bank\nPrime office location\nHigh salary incentives\n\n\nWhat you need to do now\nIf you're interested in this role, click 'apply now' to forward an up-to-date copy of your CV to avery.lam@hays.com.hk, or call Avery Lam at 2230 7931 now. If this job isn't quite right for you but you are looking for a new position, please contact us for a confidential discussion on your career.", "employment_types": ["Full Time", "Temporary"], "selling_points": ["Develop your career with a leading investment bank", "Prime office location", "High salary incentives"], "locations": ["Not Specified"], "categories": ["Banking / Finance", "Equities / Capital Markets"], "post_time": "2022-01-10T07:49:17Z", "salary": {"currency": null, "max": null, "min": null, "period": "monthly", "term": null}, "salary_visible": false, "title_keywords": ["compliance manager"], "responsibilities": ["business initiatives", "policies", "regulatory requirements", "review", "compliance", "procedures", "transactions", "testing", "monitoring", "communication", "develop", "maintain", "contact", "banking"], "requirements": {"degrees": ["bachelor", "degree holder"], "majors": ["related disciplines", "finance", "accounting", "law"], "languages": ["english", "mandarin"], "language_level": ["good", "proficient"], "hard_skills": [], "soft_skills": ["work effectively", "communication skills", "team player", "interested in"], "languages_combined": [{"language": "english", "language_level": ["proficient", "good"]}, {"language": "mandarin", "language_level": ["proficient", "good"]}]}, "experience_required": {"duration": ["at least 5 years"], "field": ["related", "compliance", "investment bank"]}}, {"job_id": "100003009034325", "location_code": "hk", "company": "Page Personnel", "job_title": "Relationship Manager - Securities Brokerage", "description": "Expand client base with new and potential clients to drive digital sales.\nResponsible for on boarding and managing new clients.\n\nClient Details\n\nMy client is a global investment bank that is licensed by the SFC and is focusing on online trading and investments across international financial markets. They are now looking for a digital sales analyst to increase business in the digital segment.\n\nDescription\n\nHandle client on boarding and managing new clients.\nExecute sales strategies for different client segments.\nClosing of leads and sales pipeline management.\nPerform cold calls to new or potential clients to expand the business.\nAttend internal and external events such as roadshows and seminars to network.\nDigital sales account management.\n\nProfile\n\nBachelor degree holder.\nAt least 1-2 years of experience in a financial institutional in related Front Office position.\nPreferably holding SFC 1,2,3 licenses.\nStrong sales track record and existing network of clients in Hong Kong.\nFamiliar with OTC Derivatives and Exchange Traded Products.\nFluent in English, Mandarin, and Cantonese.\nExcellent client servicing skills and proactive follow-ups.\nComfortable with performing outbound calls and sales through the phone.\n\nJob Offer\n\n18 Annual Leave\nMPF\nMedical\nBonus\n\nTo apply online please click the 'Apply' button below. For a confidential discussion about this role please contact Matt O'Shaughnessy on +852 3602 2438", "employment_types": ["Full Time", "Permanent"], "selling_points": ["Base salary + commission", "SFC 1,2,3 preferred", "UHNW and HNW clients"], "locations": ["Not Specified"], "categories": ["Banking / Finance", "Financial Services", "Equities / Capital Markets", "Sales, CS & Business Devpt", "Business Development"], "post_time": "2022-01-10T03:10:13Z", "salary": {"currency": null, "max": null, "min": null, "period": "monthly", "term": null}, "salary_visible": false, "title_keywords": ["relationship manager"], "responsibilities": ["management", "client base", "contact", "mpf"], "requirements": {"degrees": ["bachelor degree holder"], "majors": [], "languages": ["cantonese", "english", "mandarin"], "language_level": ["fluent"], "hard_skills": ["exchange"], "soft_skills": ["proactive", "responsible"], "languages_combined": [{"language": "cantonese", "language_level": ["fluent"]}, {"language": "english", "language_level": ["fluent"]}, {"language": "mandarin", "language_level": ["fluent"]}]}, "experience_required": {"duration": ["at least 1-2 years"], "field": ["related", "financial"]}}, {"job_id": "100003009034597", "location_code": "hk", "company": "Ambition", "job_title": "VP - Product Control, Equity Business Finance", "description": "Equity Business Finance Function Focused\nOpen to Trade Support Candidates\nIndividual Contributor Role\n\nOur client is an internationally renowned banking group with presence across Asia Pacific. They are now seeking an experienced Finance professional to join their Product Control team.\n\nReporting to the team lead, you will work closely with onshore and offshore teams, acting as subject-matter-expert on Equity Finance product, and provide strategic input on P&L analysis, reconciliation, management reporting, and disclosure reporting and other tasks required by the business from the team. You will also drive different projects for the business to provide operational and system efficiencies. You will have sensitivity with numbers, and understanding of different internal policies and external regulations to update relevant processes and related business lines.\n\nTo qualify, individuals must possess:\n\n\nBachelor's degree in Finance, Accounting, or other related discipline\n10-12 years' relevant experience in product control with in a sizeable financial institution\nOpen to financial products including Equity, FICC, etc.\nAttention to detail and a highly analytical mindset\nStrong communication and interpersonal skills, with excellent technical accounting knowledge\nMust already be based in Hong Kong\n\nInterested parties, please send your updated resume to Rhoda.Rivera@ambition.com.hk quoting RR251685 or click APPLY NOW.\n\nOnly shortlisted candidates will be notified.\n\n#LI-RR1\n#BuildingBetterFutures\n\n\nIf this job isn't quite right for you, but you know someone who would be great at this role, why not take advantage of our referral scheme? We offer HKD1000 in Apple gift cards for every referred candidate who we place in a role. Terms & Conditions Apply. https://www.ambition.com.hk/refer-a-friend", "employment_types": ["Full Time", "Permanent"], "selling_points": ["Equity Business Function Focused", "Open to Trade Support Candidates", "Individual Contributor Role"], "locations": ["Not Specified"], "categories": ["Accounting", "Financial Controller", "Banking / Finance", "Investment", "Equities / Capital Markets"], "post_time": "2022-01-10T03:46:16Z", "salary": {"currency": null, "max": null, "min": null, "period": "monthly", "term": null}, "salary_visible": false, "title_keywords": [], "responsibilities": ["regulations", "reporting", "control", "policies", "analysis", "teams", "p&l", "communication", "other tasks", "management reporting", "banking"], "requirements": {"degrees": ["degree", "bachelor"], "majors": ["finance", "accounting"], "languages": [], "language_level": [], "hard_skills": ["analysis"], "soft_skills": ["sensitivity", "communication and interpersonal skills", "attention to detail", "focused"], "languages_combined": []}, "experience_required": {"duration": ["10-12 years"], "field": ["relevant experience", "financial"]}}, {"job_id": "100003009036762", "location_code": "hk", "company": "Industrial and Commercial Bank of China (Asia) Limited", "job_title": "Senior Fixed Income Sales Manager, Global Capital Financing", "description": "Job Responsibilities\nAssist the team head in fixed income distribution to achieve annual business targets and develop strong customer distribution channel\nTo perform the functions of marketing, customer service, order taking, dealing duties and team administration\nHandle all inquiries from customers, external counterparts and internal colleagues\nWork closely with Relationship Managers on trading account set up and limit application\nProvide idea and deliver solution to assist formulating and implementing distribution strategies/programs\nTo study feasibility of new products, ideas and to keep abreast of market development\nTo take up ad hoc assignment when required.\u00a0\nJob Requirements\nUniversity graduate with major in Economics, Finance and Business, preferably with MBA /CFA\nHolder of SFC Type 1 & 4 licenses\n3 year of relevant fixed income experience\nSound knowledge of bonds pricing and bonds marketing\nExperience in managing bonds transactions for private banking institutions, banks, financial institutions and asset managers in Hong Kong and China is preferable\nGood presentation and interpersonal skills\u2022Strong analytical mind and numerical senses\nSelf-motivated, responsible and result-oriented\nAble to work under pressure, independently and be a good team player\nFluent in both written and spoken English and Chinese, including Putonghua", "employment_types": ["Full Time", "Permanent"], "selling_points": [], "locations": ["Central"], "categories": ["Banking / Finance", "Treasury", "Financial Services", "Equities / Capital Markets"], "post_time": "2022-01-10T13:37:47Z", "salary": {"currency": null, "max": null, "min": null, "period": "monthly", "term": null}, "salary_visible": false, "title_keywords": ["sales manager"], "responsibilities": ["ideas", "ad hoc assignment", "develop", "customer service", "order taking", "administration"], "requirements": {"degrees": ["university graduate"], "majors": ["business", "finance", "economics"], "languages": ["putonghua", "english", "chinese"], "language_level": ["fluent"], "hard_skills": ["cfa"], "soft_skills": ["result-oriented", "self-motivated", "independently", "good team player", "responsible", "presentation", "analytical mind", "interpersonal", "work under pressure"], "languages_combined": [{"language": "putonghua", "language_level": ["fluent"]}, {"language": "english", "language_level": ["fluent"]}, {"language": "chinese", "language_level": ["fluent"]}]}, "experience_required": {"duration": ["3 year"], "field": ["financial institutions", "banking"]}}, {"job_id": "100003009034998", "location_code": "hk", "company": "Asia Progress Executive Limited", "job_title": "Associate Credit Risk - Credit Department - Securities Brokerage", "description": "Our client is a Securities Brokerage. To cope with the rapid business expansion, they are now inviting high caliber candidates to join the team\n\nAssociate Credit Risk -\u00a0Credit Department - Securities Brokerage\u00a0\n\n\nJob Description\n\nTo monitor client\u2019s margin level and conduct margin calls\nAssist in gathering and analyzing market information, to help monitor the performance of credit facilities utilization to identify early signs of credit deterioration\nUpload information regarding IPOs to the Company\u2019s website\nTo prepare and update various daily and monthly credit report\n\nRequirements\n\nUniversity degree or above\nAt least 3 years in relevant working experience in securities brokerage\nStrong interpersonal skills which enable close cooperation with other departments\nAbility to work under pressure in fast-paced environment\nProficiency in written and spoken English and Chinese including Putonghua.\n\n\nPlease send full resume with\u00a0present & expected\u00a0salary to expedite sourcing\u00a0in\u00a0MS-WORD\u00a0format by clicking \u201cAPPLY NOW\u201d\n\nPlease quote our reference in your application\n\nPersonal data provided by job applicants will be used strictly in accordance with the employer\u2019s personal data policies, a copy of which will be provided upon request\n\nAll information provided will be used for recruitment purpose only", "employment_types": ["Full Time"], "selling_points": ["handle Credit Margin financing, Margin call", "Degree w/ min. 3yrs exp. in securities brokerage", "Securities Brokerage"], "locations": ["Central & Western Area"], "categories": ["Banking / Finance", "Financial Services", "Equities / Capital Markets", "Risk Management"], "post_time": "2022-01-10T05:04:06Z", "salary": {"currency": null, "max": null, "min": null, "period": "monthly", "term": null}, "salary_visible": false, "title_keywords": ["associate"], "responsibilities": ["market information", "monitor", "website", "monitor the performance", "report"], "requirements": {"degrees": ["degree or above"], "majors": [], "languages": ["putonghua", "english", "chinese"], "language_level": ["proficiency"], "hard_skills": ["ms-word"], "soft_skills": ["fast-paced environment", "interpersonal skills", "work under pressure"], "languages_combined": [{"language": "putonghua", "language_level": ["proficiency"]}, {"language": "english", "language_level": ["proficiency"]}, {"language": "chinese", "language_level": ["proficiency"]}]}, "experience_required": {"duration": ["at least 3 years"], "field": ["securities brokerage", "relevant working experience"]}}, {"job_id": "100003009024683", "location_code": "hk", "company": "Value Search Asia Limited", "job_title": "MIDDLE OFFICE ANALYST, PRIME BROKERAGE", "description": "Our client is a multinational bank with a diversified business operation. They are now looking for a strong Prime Brokerage Analyst to join their team in Hong Kong.\n\nYou will be handling trades including but not limited to equity, equity link securities, fixed income and repo transactions etc. You will be responsible for projects, UATs for new products and new clients\u2019 trading by maintaining good settlement practices. You will also be supporting new clients accounts and products initiatives. You will build a strong relationship with teams including Sales and Trading, Client Service Reps, Execution/ Financing Middle Offices, etc.\n\nTo qualify, you should have a degree in Finance, Banking and/ or other related disciplines, along with solid client facing and trade settlement experiences preferably Prime Brokerage clients. You should have a strong knowledge in front to back operational procedures dealing with Hedge Fund and Asset Management clients. Familiar with front to back cash trades flows for equities and fixed income products, cash trade settlement cycle, market rules and regulations for APAC markets are highly preferred.\n\nTo apply for this job\n\nContact: Chloe quoting job ref: VSA-1548\n\nTelephone: 852 - 2525 8820", "employment_types": ["Full Time", "Permanent"], "selling_points": ["International Prime Brokerage", "APAC Settlement/ Middle Office Experience", "Cash Equities Experience"], "locations": ["Central"], "categories": ["Banking / Finance", "Dealing & Trading", "Equities / Capital Markets", "Order Processing & Operation / Settlement"], "post_time": "2022-01-06T02:10:59Z", "salary": {"currency": "HKD", "max": 29999, "min": 20000, "period": "monthly", "term": null}, "salary_visible": true, "title_keywords": ["analyst"], "responsibilities": ["regulations", "business operation", "maintaining", "brokerage", "teams", "transactions", "operational procedures", "contact", "banking", "asset management"], "requirements": {"degrees": ["degree"], "majors": ["related disciplines", "finance"], "languages": [], "language_level": [], "hard_skills": [], "soft_skills": ["responsible"], "languages_combined": []}, "experience_required": {"duration": [], "field": ["related", "finance", "brokerage", "banking"]}}, {"job_id": "100003009028472", "location_code": "hk", "company": "Value Search Asia Limited", "job_title": "ANALYST, CLIENT SERVICE - INVESTMENT BANK", "description": "Our client is a multinational bank with a diversified business operation. They are now looking for a Client Service Analyst to join their Prime Brokerage Asset Servicing Team in Hong Kong.\n\nReporting to the Regional Head, you will be handling asset servicing queries from prime clients to Asset Servicing Client Service Group. You will be on-boarding new prime clients, conducting account reviews and managing through monthly calls. You will also be supporting clients and businesses in Asia regions primarily for asset services ranging from Equities to Fixed Income. You will engage in infrastructure leads including but not limited to Finance, IT, front office, vendors, custodians, etc.\n\nTo qualify, you should have a bachelor\u2019s degree or equivalent, along with solid Middle Office or Asset Servicing experiences preferably with International Financial firms. You should have a strong knowledge in Risk and Asset Servicing, and good understanding of Corporate Action Events, Dividends, Coupons and Conversions. Familiar with PBMO, settlements, trade support, cycle and flow are highly preferred. You should have strong communication skills in English and Cantonese.\n\nTo apply for this job\n\nContact: Cherry\u00a0quoting job ref: JobsDB-1551\n\nTelephone: 852 - 2525 8820", "employment_types": ["Full Time", "Permanent"], "selling_points": ["Asset Servicing/ Prime Brokerage", "Equities & Fixed Income Post Trade", "Good English Communication Required"], "locations": ["Central"], "categories": ["Banking / Finance", "Financial Services", "Equities / Capital Markets", "Sales, CS & Business Devpt", "Account Servicing"], "post_time": "2022-01-07T02:22:38Z", "salary": {"currency": null, "max": null, "min": null, "period": "monthly", "term": null}, "salary_visible": false, "title_keywords": ["analyst"], "responsibilities": ["business operation", "reporting", "brokerage", "infrastructure", "communication", "contact"], "requirements": {"degrees": ["degree", "bachelor"], "majors": [], "languages": ["cantonese", "english"], "language_level": [], "hard_skills": [], "soft_skills": ["communication skills"], "languages_combined": [{"language": "cantonese", "language_level": []}, {"language": "english", "language_level": []}]}, "experience_required": {"duration": [], "field": ["financial"]}}, {"job_id": "100003009035188", "location_code": "hk", "company": "Gravitas Recruitment Group", "job_title": "Global Trading Technology Team - Senior Java Developer", "description": "Seeking a Java Developer with a want to work within a front office industry leading team in the Global Trading Technology team. Global Technology will allow you to solve some of the most interesting and complex challenges in the financial industry to helping the global business and its customers succeed.\n\nWHY APPLY?\n\nHands on development with design input into trading strategies, analytics engine, market data handlers, and testing strategies.\nWork in a front office environment and gaining exposure to the trading desk and quantitative teams.\nPartner with Product, Quants and Trading Desk in delivering rapid client customisation's and fast lane solutions.\n\nWHAT DO YOU NEED?\n\nExperience in delivering trade execution strategies and/or trading analytics for equity markets.\nAt least 3 - 5 years of experience in development of Equity products in a global financial services company.\nExpert proficiency with computer technologies including Java, Linux, and OO Design with a focus on performance, re-usability, test automation and flexibility for customisation's.\n\nFeel like you need a new work environment? Want to work in and industry leading team with all the latest technology? Well do not hesitate to send through your most up to date CV and avoid any chance of missing out on this opportunity.\n\nPlease send through all expressions of interest with updated CV to a.suter@gravitasgroup.com", "employment_types": ["Full Time", "Permanent"], "selling_points": ["Java Developer", "Global Finance Market", "OMS Algo Trading Application"], "locations": ["Not Specified"], "categories": ["Banking / Finance", "Equities / Capital Markets", "Information Technology (IT)", "Software Development"], "post_time": "2022-01-10T06:22:15Z", "salary": {"currency": "HKD", "max": 119999, "min": 90000, "period": "monthly", "term": null}, "salary_visible": true, "title_keywords": ["developer"], "responsibilities": ["market data", "teams", "design", "testing"], "requirements": {"degrees": [], "majors": [], "languages": [], "language_level": [], "hard_skills": ["linux", "java", "focus", "rapid"], "soft_skills": ["focus", "hands on"], "languages_combined": []}, "experience_required": {"duration": ["at least 3 - 5 years"], "field": ["development", "financial services", "trading"]}}, {"job_id": "100003009028592", "location_code": "hk", "company": "Industrial Bank Co., Ltd.", "job_title": "Team Head of Relationship Management, Capital Market Department", "description": "Responsibilities:\n\nActively involves in structuring and executing tailor-made financing solutions for loans, bridge financing, M&A, Syndicated loan\uff0cproject financing and other capital financing activities or capital raising exercises;\nProactively engage in post deal monitoring and participate in loan restructuring process when necessary\nInvolve in deal execution including documentation, coordination, and negotiation with internal and external working parties and regulatory bodies;\nAssist senior team members in assessing potential deals, developing new businesses and maintaining client relationships;\nPerform other job duties as assigned from time to time.\u00a0\n\n\u00a0Requirements\n\nUniversity degree holder in Finance, Economics, Accounting or related discipline;\nMinimum 7 years of related working experience in structured finance;\u00a0\nStrong accounting background, big four background is preferred;\nStrong communication skills in English and Chinese (includes Mandarin), with a proactive approach ;\nAble to demonstrate commitment to technical excellence, flexibility and the ability to manage multiple activities and deadlines.\n\nPlease enclose full C.V. with present and expected salary to the Head of Human Resources, Industrial Bank Co., Ltd. Hong Kong Branch, 12/F, One International Finance Centre, 1 Harbour View Street, Central, Hong Kong or\u00a0apply directly by clicking \u201cApply Now\u201d.\n\nPersonal data provided by job applicants will be used for recruitment purpose only. Applicants who are not contacted within 8 weeks may consider their applications unsuccessful. All data of unsuccessful applicants will be destroyed in 12 months.", "employment_types": ["Full Time", "Permanent"], "selling_points": ["financial analysis", "7 years of related working experience", "Structured Finance"], "locations": ["Central"], "categories": ["Accounting", "Financial Analyst", "Banking / Finance", "Equities / Capital Markets"], "post_time": "2022-01-07T02:37:47Z", "salary": {"currency": null, "max": null, "min": null, "period": "monthly", "term": null}, "salary_visible": false, "title_keywords": [], "responsibilities": ["maintaining", "monitoring", "developing", "executing", "coordination", "documentation"], "requirements": {"degrees": ["university degree"], "majors": ["finance", "economics", "accounting"], "languages": ["english", "chinese", "mandarin"], "language_level": [], "hard_skills": ["harbour", "c"], "soft_skills": ["communication skills", "structured", "proactive"], "languages_combined": [{"language": "english", "language_level": []}, {"language": "chinese", "language_level": []}, {"language": "mandarin", "language_level": []}]}, "experience_required": {"duration": ["minimum 7 years"], "field": ["related", "finance"]}}, {"job_id": "100003009027349", "location_code": "hk", "company": "Haitong International Securities Group Limited", "job_title": "Research Assistant \u2013 Equity Research (Ref: JDB/ER/RA)", "description": "The Job:\n\nAssist in data mining, modeling for equities research\nAssist in drafting research reports;\nProvide research support for Hong Kong and Taiwan Technology sector\nPerform any other duties as assigned from time to time.\n\nRequirements:\n\nWe support local hire with solid relevant working experience in HK.\n\n1-2 years\u2019 relevant experience from buy, sell side, industry\nDegree holder or above, preferably with Accounting or Finance related qualifications;\nStrong presentation skills in written and spoken English and Chinese, and competent spoken Putonghua preferred\nPositive working attitude with strong initiative and dedication.\n\nWe are committed to build a team of competence individuals who have acquired relevant local solid working experience and with diversified exposure to work together with us. Applicants who do not hear from us within 6 weeks may consider their applications unsuccessful.\n\nWe provide attractive remuneration package and fringe benefits for the right candidate. Interested parties please send detailed resume with current and expected salaries to\u00a0Human Resources Department i) by mail: 22/F, Li Po Chun Chambers, 189 Des Voeux Road Central, HK; ii) by fax: 2537 5431;\u00a0or iii) by using \"APPLY NOW\".\n\nPlease quote the reference in the application. If application is submitted in hard copy format, it should be placed in a sealed envelope marked \u201cConfidential\u201d. All applications will be treated in strict confidence and personal data provided by job applications will be used for recruitment purposes only. A copy of our Personal Information Collection Statement will be available upon request.", "employment_types": ["Full Time", "Permanent"], "selling_points": [], "locations": ["Sheung Wan"], "categories": ["Banking / Finance", "Financial Services", "Equities / Capital Markets", "Others"], "post_time": "2022-01-06T09:46:27Z", "salary": {"currency": null, "max": null, "min": null, "period": null, "term": null}, "salary_visible": false, "title_keywords": ["research assistant"], "responsibilities": ["data mining", "any other duties", "research support", "reports"], "requirements": {"degrees": ["degree holder"], "majors": ["finance", "accounting"], "languages": ["putonghua", "english", "chinese"], "language_level": [], "hard_skills": [], "soft_skills": ["competent", "positive working attitude", "presentation skills", "committed", "initiative"], "languages_combined": [{"language": "putonghua", "language_level": []}, {"language": "english", "language_level": []}, {"language": "chinese", "language_level": []}]}, "experience_required": {"duration": ["1-2 years"], "field": ["relevant experience", "relevant working experience", "team"]}}, {"job_id": "100003009031282", "location_code": "hk", "company": "Capital Advisory Limited", "job_title": "Assistant - Audit Assoicate / Trainee (Fresh graduate welcome)", "description": "Responsibilities\n\nu\u00a0 Assist finance projects including IPOs, mergers and \u00a0\u00a0acquisitions, and other\u00a0 \u00a0 \u00a0 \u00a0 \u00a0 \u00a0 \u00a0 \u00a0 \u00a0 management advisory projects\n\nu\u00a0 Support and communicate in the internal controls, auditing, accounting and tax\u00a0 \u00a0 \u00a0 \u00a0 \u00a0 \u00a0 \u00a0 assignments of the projects\n\nu\u00a0 Assist in deals support, such as reviewing target financials, business operation\u00a0 \u00a0 \u00a0 \u00a0 \u00a0 \u00a0 \u00a0 materials and involve in liaising deals structure\n\nu\u00a0 Liaise with other professional parties to support the implementation of projects\n\nu\u00a0 A good opportunity to allow audit junior to transit to capital market\n\nu\u00a0 Perform ad-hoc assignments\n\nRequirements\n\nu\u00a0 Degree holder or above in Accounting, Finance or Business Administration is\u00a0 \u00a0 \u00a0 \u00a0 \u00a0 \u00a0 \u00a0 \u00a0 \u00a0 preferred\n\nu\u00a0 Fresh graduates will also be considered\n\nu\u00a0 1-2 years working experience in accounting firm preferable,\n\nu\u00a0 Good command of spoken and written English, Mandarin and Cantonese\n\nu\u00a0 Proficiency in Excel\n\nu\u00a0 Hardworking and willing to learn new knowledge on top of accounting\n\nu\u00a0 Immediate available preferred\n\nWe offer\n\nu\u00a0 5-days work\n\nu\u00a0 Study and examination leave\n\nu\u00a0 Discretionary bonus\n\nu\u00a0 Double pay\n\nu\u00a0 Annual leave\n\nInterested parties please send your resume with expected salary and availability by clicking \"Apply Now\". All personal data collected will be used for recruitment purpose only.", "employment_types": ["Full Time", "Permanent"], "selling_points": ["Study and examination leave;  5-days work", "Discretionary bonus; Annual leave ; Bank holiday", "Sheung Wan MTR station; Double pay"], "locations": ["Sheung Wan"], "categories": ["Accounting", "Consulting", "Banking / Finance", "Dealing & Trading", "Equities / Capital Markets"], "post_time": "2022-01-07T09:08:12Z", "salary": {"currency": null, "max": null, "min": null, "period": "monthly", "term": null}, "salary_visible": false, "title_keywords": ["assistant", "trainee"], "responsibilities": ["tax", "business operation", "management", "ad-hoc assignments", "audit", "implementation of projects", "liaise with", "auditing"], "requirements": {"degrees": ["degree holder"], "majors": ["finance", "accounting", "business administration"], "languages": ["cantonese", "english", "mandarin"], "language_level": ["good command"], "hard_skills": ["excel"], "soft_skills": ["willing to learn", "hardworking"], "languages_combined": [{"language": "cantonese", "language_level": ["good command"]}, {"language": "english", "language_level": ["good command"]}, {"language": "mandarin", "language_level": ["good command"]}]}, "experience_required": {"duration": ["1-2 years"], "field": ["accounting"]}}, {"job_id": "100003009029404", "location_code": "hk", "company": "Fulbright Securities Limited", "job_title": "Senior Officer, Operations Department", "description": "Responsibilities:\n\n\nProvide all rounded support in the Operations Department including answering inquiries, conducting KYC and system administration;\nResponsible for Capital Investment Entrant Scheme procedures and Stock Borrowing and Lending Transactions;\nParticipate in originating, structuring and executing ECM transactions included but not limited to share placements and rights issues;\nHandle IPO margin financing;\nHandle and support Account Managers in daily operation;\nAssist to revamp the workflow and ensure that all requests are align with regulatory requirements and internal policies;\nPerform all other duties as assigned by seniors from time to time.\n\nRequirements:\n\nTertiary educated;\nAt least 3 years\u2019 experiences in customer services, client onboarding, or AML/KYC field, preferably in the fields of banking and finance;\nHolder of SFC Type 1 (Dealing in Securities) and Type 2 (Dealing in Futures Contracts) is definitely advantageous;\nHigh level of customer service orientation;\nSociable with good communication and interpersonal skills;\nMulti-tasking and problem-solving skills;\nMature, patient, cheerful and detail-minded;\nFluent in Cantonese and Putonghua is a must;\nCandidate with less experience can be considered as Officer.\nSalary and fringe benefits for the post will be highly competitive, commensurate with qualifications and experience. Interested candidates please send your resume, last and expected salary to the Human Resources and Administration by clicking \"Apply Now\".\nData collected will be used for recruitment purpose only.\u00a0For more details, please visit us at\u00a0www.ffg.com.hk.", "employment_types": ["Full Time", "Permanent"], "selling_points": [], "locations": ["Kowloon Bay"], "categories": ["Banking / Finance", "Financial Services", "Equities / Capital Markets", "Others"], "post_time": "2022-01-07T05:02:43Z", "salary": {"currency": null, "max": null, "min": null, "period": "monthly", "term": null}, "salary_visible": false, "title_keywords": ["senior officer", "operations"], "responsibilities": ["revamp", "other duties", "operations", "regulatory requirements", "policies", "procedures", "daily operation", "transactions", "executing", "kyc", "administration"], "requirements": {"degrees": [], "majors": [], "languages": ["cantonese", "putonghua"], "language_level": ["fluent"], "hard_skills": ["problem-solving skills", "aml", "kyc"], "soft_skills": ["detail-minded", "cheerful", "sociable", "mature", "patient", "multi-tasking", "customer service", "communication and interpersonal skills", "problem-solving skills"], "languages_combined": [{"language": "cantonese", "language_level": ["fluent"]}, {"language": "putonghua", "language_level": ["fluent"]}]}, "experience_required": {"duration": ["at least 3 years"], "field": ["finance", "banking", "customer services"]}}, {"job_id": "100003009026171", "location_code": "hk", "company": "The Bank of East Asia, Limited", "job_title": "Business Manager (Securities Services)", "description": "Business Manager (Securities Services) (Job ID: 3190)\n\n\nResponsibilities\n\nTo be a team member of Securities Services Department\nTo handle securities transactions as well as provide timely and efficient securities services to customers\nTo assist the Section Head in planning, leading, coordinating and controlling the dealing operations\nTo ensure all daily transactions and relevant controls are performed accurately and properly accordingly to the Bank\u2019s standard procedures\nTo handle any ad hoc tasks assigned by the Section Head\nRequirements\n\nUniversity degree, preferably major in business, finance or related disciplines\nMinimum of 5 years working experience in securities sector or related areas covering the following:\nAt least 2 years in supervision of subordinates for dealing operations\nSound knowledge in securities market and understanding of relevant policies, procedures, practices of relevant regulatory bodies\nA team player with good interpersonal skills, analytical skills and risk awareness\nSelf-motivated and able to work under pressure\nProficiency in both spoken and written English and Chinese, Putonghua is a plus\nPlease apply online via the BEA Careers website at\u00a0https://careers.hkbea.com/psp/hcmprd/EMPLOYEE/HRMS/c/HRS_HRAM.HRS_APP_SCHJOB.GBL?Page=HRS_APP_JBPST&Action=UFOCUS=Applicant&SiteId=1&JobOpeningId=3190&PostingSeq=1 or by clicking the \"Apply Now\" button below. Kindly note that if you are a new user, you have to first create your User Profile before you can apply.\n\nPersonal data provided by job applicants will be used for recruitment purposes only and will be treated in accordance with the Bank's Personal Information Collection (Employees) Statement and Privacy Policy Statement. Applicants who are not invited for interviews within six weeks may consider their applications unsuccessful and the personal data collected will be destroyed after six months.", "employment_types": ["Full Time", "Permanent"], "selling_points": ["Provide timely and efficient securities services", "Supervise subordinates for dealing operations", "University graduates with 5 years' work experience"], "locations": ["Central"], "categories": ["Banking / Finance", "Dealing & Trading", "Equities / Capital Markets", "Others"], "post_time": "2022-01-07T19:19:29Z", "salary": {"currency": null, "max": null, "min": null, "period": null, "term": null}, "salary_visible": false, "title_keywords": ["manager"], "responsibilities": ["operations", "ad hoc tasks", "procedures", "transactions", "planning"], "requirements": {"degrees": ["university degree"], "majors": ["related disciplines", "finance", "business"], "languages": ["putonghua", "english", "chinese"], "language_level": ["proficiency"], "hard_skills": ["plus", "c", "analytical skills"], "soft_skills": ["self-motivated", "analytical skills", "interpersonal skills", "team player", "work under pressure"], "languages_combined": [{"language": "putonghua", "language_level": ["proficiency"]}, {"language": "english", "language_level": ["proficiency"]}, {"language": "chinese", "language_level": ["proficiency"]}]}, "experience_required": {"duration": ["minimum of 5 years"], "field": ["related", "securities"]}}, {"job_id": "100003009032107", "location_code": "hk", "company": "First Shanghai Securities Ltd", "job_title": "Sales Manager - Institutional Sales", "description": "Job Responsibilities:\n\nCustomer relationship maintenance\nNew clients development under the background of the Greater Bay Area Financial Link\n\nJob Requirements:\n\nDegree holder in Finance, Business Administration or related\u00a0disciplines\nMinimum\u00a03-5 years solid experience in customer services or futures / securities or relevant industry\nSelf-motivated, responsible and able to work independently\nExcellent interpersonal skill\nBasic understanding of equity market\n\nWe offer attractive package including 5 days work, Year-end bonus and medical insurance to the right candidate. Please apply with full resume stating present & expected salary and date available to: The Human Resources Manager by clicking APPLY NOW.\n\n(Personal data collected would be used for recruitment purpose only.)", "employment_types": ["Full Time", "Permanent"], "selling_points": [], "locations": ["Central & Western Area"], "categories": ["Banking / Finance", "Financial Services", "Equities / Capital Markets", "Others"], "post_time": "2022-01-07T10:14:51Z", "salary": {"currency": null, "max": null, "min": null, "period": "monthly", "term": null}, "salary_visible": false, "title_keywords": ["sales", "sales manager"], "responsibilities": ["maintenance"], "requirements": {"degrees": ["degree holder"], "majors": ["related disciplines", "finance", "business administration"], "languages": [], "language_level": [], "hard_skills": ["basic"], "soft_skills": ["self-motivated", "work independently", "responsible", "interpersonal skill"], "languages_combined": []}, "experience_required": {"duration": ["minimum 3-5 years"], "field": ["securities", "customer services"]}}, {"job_id": "100003009031713", "location_code": "hk", "company": "The Bank of East Asia, Limited", "job_title": "Account Servicing & Administration Officer", "description": "Securities Services Department\n\nAccount Servicing & Administration Officer\u00a0(Job ID: 3301)\n\nResponsibilities\n\nTo be a team member of Securities Services Department\nTo handle customers\u2019 enquiries via hotline, walk-in, emails and letters on securities account related matters\nTo handle the operations and maintenance of trading accounts\nTo conduct regular customer review and customer due diligence in compliance with regulatory requirements\nTo provide administration support and handle any ad hoc tasks assigned by the supervisor\n\nRequirements\n\nUniversity graduates or Higher Diploma in Business Administration or related disciplines\nMinimum of 1 year\u2019s working experience in securities or banking industries\nKnowledge in securities industry with understanding of relevant practice, rules and regulations in SEHK and SFC preferred\nPass in the Insurance Intermediaries Qualifying Examination or Hong Kong Securities Institute Licencing Examinations is an advantage\nSelf-motivated and able to work under pressure\nProficiency in both spoken and written English and Chinese, Putonghua will be a plus\nGood knowledge of MS Office\n\n\nPlease apply online via the BEA Careers website at https://careers.hkbea.com/psp/hcmprd/EMPLOYEE/HRMS/c/HRS_HRAM.HRS_APP_SCHJOB.GBL?Page=HRS_APP_JBPST&Action=U&FOCUS=Applicant&SiteId=1&JobOpeningId=3301&PostingSeq=1 or by clicking the Apply Now button. Kindly note that if you are a new user, you have to first create your User Profile before you can apply.\n\nPersonal data provided by job applicants will be used for recruitment purposes only and will be treated in accordance with the Bank's Personal Data Policy, which is available upon request. Applicants who are not invited for interviews within six weeks may consider their applications unsuccessful and the personal data collected will be destroyed after six months.", "employment_types": ["Full Time", "Permanent"], "selling_points": ["Handle customers' enquiries on securities account", "Operate & maintain trading accounts", "University graduates with exp. in securities/bank"], "locations": ["Central"], "categories": ["Banking / Finance", "Financial Services", "Dealing & Trading", "Equities / Capital Markets"], "post_time": "2022-01-07T19:20:48Z", "salary": {"currency": null, "max": null, "min": null, "period": null, "term": null}, "salary_visible": false, "title_keywords": ["administration officer"], "responsibilities": ["maintenance", "operations", "regulatory requirements", "review", "letters", "compliance", "ad hoc tasks", "customer due diligence", "administration"], "requirements": {"degrees": ["diploma"], "majors": ["related disciplines", "business administration"], "languages": ["putonghua", "english", "chinese"], "language_level": ["proficiency"], "hard_skills": ["sehk", "plus", "c", "ms office"], "soft_skills": ["self-motivated", "work under pressure"], "languages_combined": [{"language": "putonghua", "language_level": ["proficiency"]}, {"language": "english", "language_level": ["proficiency"]}, {"language": "chinese", "language_level": ["proficiency"]}]}, "experience_required": {"duration": ["minimum of 1 year"], "field": ["securities", "banking"]}}, {"job_id": "100003009033074", "location_code": "hk", "company": "AXA China Region Insurnace Company Limited", "job_title": "AXA\u8d22\u5bcc\u7ba1\u7406\u7ecf\u7406 Wealth Management Manager - \u6b22\u8fce\u6b63\u5728\u9999\u6e2f\u7684 IANG \u53ca\u51c6 IANG \u7533\u8bf7", "description": "AXA Academy ( \u5b89\u76db\u4e13\u4e1a\u57f9\u8bad\u5b66\u9662 ) \u4e3a\u672a\u6765\u7cbe\u82f1\u7684\u60a8\u63d0\u4f9b\u72ec\u7279\u4e00\u7ad9\u5f0f\u57f9\u8bad\uff0c\u795d\u60a8\u6253\u9020\u5feb\u901f\u6210\u529f\u4e4b\u8def\uff0c\u65e9\u65e5\u8dfb\u8eab\u6210\u4e3a\u4e1a\u754c\u516c\u8ba4\u56fd\u9645\u6700\u9ad8\u8363\u8a89\u7684\u767e\u4e07\u5706\u684c\u4f1a [ Million Dollar Round Table ] \u4f1a\u5458\u53ca\u66f4\u9ad8\u8d44\u683c\u3002\n\n\u6211\u4eec\u671f\u5f85\u6709\u5fd7\u5728\u5927\u5b66\u6bd5\u4e1a\u540e\u521b\u4e00\u756a\u4e8b\u4e1a\u53ca\u5e74\u9752\u6709\u62fc\u52b2\u7684\u4eba\u58eb\u52a0\u5165\u6211\u4eec\u7684\u4e13\u4e1a\u56e2\u961f\uff0c\u4e3a\u6211\u4eec\u7684\u5ba2\u6237\u63d0\u4f9b\u5168\u9762\u7684\u4fdd\u969c\u53ca\u7406\u8d22\u65b9\u6848\uff0c\u5305\u62ec\u8d22\u52a1\u89c4\u5212\u3001\u50a8\u84c4\u7ba1\u7406\u3001\u9000\u4f11\u89c4\u5212\u3001\u533b\u7597\u53ca\u5371\u75be\u4fdd\u969c\u3001\u5b50\u5973\u6559\u80b2\u57fa\u91d1\u7b49\u3002\n\n\n\u533a\u57df\u80cc\u666f\uff1a\n\n\n\u8d85\u8fc720\u5e74\u53d1\u5c55\u5927\u4e2d\u534e\u5730\u533a\u5e02\u573a\u7ecf\u9a8c\uff0c\u533a\u57df\u4eba\u6570\u8fbe200\u4eba\n\u6210\u5458\u6765\u81ea\u4e0d\u540c\u4e13\u4e1a\u80cc\u666f\uff0c\u6709\u524d\u5f8b\u5e08\uff0c\u94f6\u884c\u5bb6\uff0c\u5546\u4eba\uff0cIT\u4e13\u4e1a\u4eba\u58eb\u7b49\u7b49\uff0c\u65e0\u8bba\u5bf9\u9ad8\u7aef\u5ba2\u6237\u6216\u662f\u4e2d\u4ea7\u5ba2\u6237\u9500\u552e\u90fd\u6709\u4e30\u5bcc\u7ecf\u9a8c\n\n\u7533\u8bf7\u4eba\u8981\u6c42\uff1a\n\n\n\u5982\u7533\u8bf7\u4eba\u4e3a\u300c \u975e\u672c\u5730\u6bd5\u4e1a\u5927\u5b66\u751f \u300d\uff0c\u9700\u8981\u5148\u62e5\u6709\u5728\u9999\u6e2f\u5408\u6cd5\u7684\u5de5\u4f5c\u6743\u9650 ( \u7b7e\u8bc1\u8eab\u5206\u4e66 / \u53d7\u517b\u4eba\u7b7e\u8bc1 / IANG \u5de5\u4f5c\u7b7e\u8bc1 )\n\u5e94\u5c4a\u5927\u5b66\u6bd5\u4e1a\u751f\u5728\u6301\u6709\u6709\u6548\u7684 IANG \u7b7e\u8bc1\u524d\u4f1a\u5b89\u6392\u5148\u4ee5\u5b9e\u4e60\u751f\u8eab\u5206\u63d0\u524d\u8fdb\u884c\u4e0a\u5c97\u524d\u57f9\u8bad\u53ca\u5de5\u4f5c\u6307\u5bfc\n\u5927\u5b66\u672c\u79d1\u6bd5\u4e1a\u6216\u4ee5\u4e0a\u5b66\u5386\n\u6d41\u5229\u666e\u901a\u8bdd\u4f5c\u65e5\u5e38\u6c9f\u901a\n\n\u5de5\u4f5c\u5185\u5bb9\uff1a\n\n\u4e3a\u5ba2\u6237\u63d0\u4f9b\u5168\u9762\u7684\u4fdd\u969c\u53ca\u7406\u8d22\u65b9\u6848\uff0c\u5305\u62ec\u8d22\u52a1\u89c4\u5212\u3001\u50a8\u84c4\u7ba1\u7406\u3001\u9000\u4f11\u89c4\u5212\u3001\u533b\u7597\u53ca\u5371\u75be\u4fdd\u969c\u3001\u5b50\u5973\u6559\u80b2\u57fa\u91d1\u7b49\n\u5f00\u62d3\u5e76\u7ef4\u62a4\u5927\u4e2d\u534e\u91cd\u75be\u9669\u7b49\u533b\u7597\u4fdd\u969c\u5e02\u573a\u53ca\u5ba2\u6237\u5173\u7cfb\uff0c\u4e3b\u8981\u9762\u5411\u56fd\u5185\u5ba3\u4f20\u9999\u6e2f\u7684\u79c1\u8425\u533b\u7597\u4f53\u5236\n\u63a8\u5e7f\u591a\u5143\u8d27\u5e01\u50a8\u84c4\u914d\u7f6e\u65b9\u6848\uff0c\u5305\u62ec\u4eba\u6c11\u5e01\u3001\u7f8e\u5143\u2026\n\u534f\u52a9\u5e26\u9886\u53ca\u62db\u52df\u65b0\u540c\u4e8b\uff0c\u65e5\u5e38\u591a\u5206\u4eab\u5de5\u4f5c\u7ecf\u9a8c\uff0c\u7ef4\u7cfb\u826f\u597d\u7684\u56e2\u961f\u6c14\u6c1b\n\n\u4f60\u6703\u7372\u5f97\u4ec0\u9ebd\uff1f\n\n\u5168\u9762\u7684\u4e13\u4e1a\u57f9\u8bad\u8bfe\u7a0b ( \u5c06\u7531\u300c\u00a0\u5b89\u76db\u4e13\u4e1a\u57f9\u8bad\u5b66\u9662 \u300d\u5168\u529b\u652f\u6301 )\n\u5b8c\u5584\u53ef\u89c2\u7684\u6536\u5165: \u6bcf\u6708\u6d25\u8d34 $15000-$50000 (\u89c6\u4e4e\u8fc7\u5f80\u5de5\u4f5c\u7ecf\u9a8c)+\u4f63\u91d1+\u5b63\u5ea6\u5956\u91d1+\u5e74\u7ec8\u5956\u91d1\n\u7075\u6d3b\u5f39\u6027\u7684\u5de5\u4f5c\u65f6\u95f4\n\u8868\u73b0\u8fbe\u76ee\u6807\u540c\u4e8b\u5c06\u4f1a\u83b7\u8d5e\u52a9\u6765\u56de\u673a\u7968\u53ca\u9152\u5e97\u4f4f\u5bbf\u51fa\u5e2d\u53c2\u4e0e\u6d77\u5916\u7684\u4e1a\u52a1\u76db\u4f1a\n\u516c\u5e73\u6e05\u6670\u7684\u664b\u5347\u673a\u5236\n\n\u6709\u610f\u8005,\u00a0\u8bf7\u9a6c\u4e0a\u70b9\u6309\u00a0\"Apply Now\" \u6216\u5fae\u4fe1\u4f60\u7684\u7b80\u5386\u7ed9\u8d75\u5c0f\u59d0 \uff08Wechat ID: saladjai \uff09", "employment_types": ["Full Time", "Part Time"], "selling_points": ["\u5e74\u8f7b\u4e0a\u8fdb\u7684\u5b66\u58eb/\u7855\u58eb\u751f\u56e2\u961f\uff0c\u4e2d\u6e2f\u56e2\u961f\u5173\u7cfb\u878d\u6d3d\uff0c\u4e92\u76f8\u5206\u4eab\u5b66\u4e60\u4e00\u8d77\u6210\u957f", "\u6709\u5174\u8da3\u4e8e\u91d1\u878d\u6295\u8d44\u7406\u8d22\u4e09\u65b9\u9762\u7684\u53d1\u5c55\uff0c\u6d3b\u5b66\u6d3b\u7528\u589e\u503c\u81ea\u6211\uff0c\u4e3a\u8ffd\u6c42\u68a6\u60f3\u884c\u7684\u201c\u7b2c\u4e00\u6b65\u201d", "\u533a\u57df\u8d85\u8fc720\u5e74\u53d1\u5c55\u5927\u4e2d\u534e\u5730\u533a\u5e02\u573a\u7ecf\u9a8c\uff0c\u65e0\u8bba\u5bf9\u9ad8\u7aef\u5ba2\u6237\u6216\u662f\u4e2d\u4ea7\u5ba2\u6237\u9500\u552e\u90fd\u6709\u4e30\u5bcc\u7ecf\u9a8c"], "locations": ["Kwun Tong"], "categories": ["Banking / Finance", "Investment", "Corporate Finance", "Equities / Capital Markets"], "post_time": "2022-01-08T07:34:51Z", "salary": {"currency": "HKD", "max": 44999, "min": 30000, "period": "monthly", "term": null}, "salary_visible": true, "title_keywords": ["wealth management manager"], "responsibilities": [], "requirements": {"degrees": [], "majors": [], "languages": [], "language_level": [], "hard_skills": ["id", "wechat"], "soft_skills": [], "languages_combined": []}, "experience_required": {"duration": [], "field": []}}, {"job_id": "100003009028417", "location_code": "hk", "company": "Hays", "job_title": "Securities Processing Operation Business Analyst", "description": "Your new company\n\nA reputable bank is looking for a Business Analyst to join their Securities Operations Division\n\n\nYour new role\n\nCollect and document requirement, analyse data of in-place procedures to find ways to improve operations\nEvaluate operations procedures and processes\nIdentify deficiencies and areas for improvement and redesign\nApply statistical analysis, simulations, and predictive modelling to analyse current procedures\nPartner with key business and technology representatives in order to drive business requirements, testing and overall delivery\nWork closely with IT to ensure that business requirements are translated into technical specifications and systematic solutions where required\nIdentify solutions for the enhancement, development and implementation of scalable and robust operating models and solutions, ensuring alignment to strategic business initiatives\n\n\nWhat you'll need to succeed\n\n5+ years of relevant working experiences in the banking industry\nBachelor Degree in the related area\nExcellent understanding of the end to end project lifecycle, from initiation through to delivery as well as business transformation frameworks, agile mythologies and best practice\nFamiliar with Securities operations and equip with past experiences in post trade system enhancement or replacement\nProficient in both written and spoken English and Chinese Cantonese and Mandarin\n\n\nWhat you need to do now\nIf you're interested in this role, click 'apply now' to forward an up-to-date copy of your CV. Alternatively, you can also share Keith Ho you CV to keith.ho@hays.com.hk , or call Keith now @ 22307474.\nIf this job isn't quite right for you but you are looking for a new position, please contact us for a confidential discussion on your career.", "employment_types": ["Full Time", "Permanent"], "selling_points": ["Business Analyst", "Securities Processing Operation", "Operation and System Enhancement"], "locations": ["Not Specified"], "categories": ["Banking / Finance", "Financial Services", "Equities / Capital Markets", "Others"], "post_time": "2022-01-07T02:14:39Z", "salary": {"currency": null, "max": null, "min": null, "period": "monthly", "term": null}, "salary_visible": false, "title_keywords": ["business analyst"], "responsibilities": ["business initiatives", "data", "operations", "analysis", "procedures", "implementation", "testing", "evaluate", "specifications", "contact", "banking", "analyse"], "requirements": {"degrees": ["degree", "bachelor"], "majors": [], "languages": ["cantonese", "english", "chinese", "mandarin"], "language_level": ["proficient"], "hard_skills": ["statistical analysis", "agile"], "soft_skills": ["robust", "interested in", "agile", "systematic"], "languages_combined": [{"language": "cantonese", "language_level": ["proficient"]}, {"language": "english", "language_level": []}, {"language": "chinese", "language_level": []}, {"language": "mandarin", "language_level": ["proficient"]}]}, "experience_required": {"duration": ["5+ years"], "field": ["banking industry", "securities"]}}, {"job_id": "100003009032989", "location_code": "hk", "company": "China Everbright Securities International Company Limited", "job_title": "Assistant Vice President/Vice President, Equities Operations", "description": "Ref: VP/OPD/080122DB/16\u00a0\n\nResponsibilities\n\nManage daily operations of the Equities Operations team, products coverage including all equities in Hong Kong, US and other overseas markets\nCollaborate and work diligently with key internal and external stakeholders such as compliance, regulators, sales team, and dealing team\nParticipate and support new business/initiatives from various Business Divisions\nManage resources across different teams ensuring all teams under the management are operated in the best capacity and efficiency\nStreamline operations workflows and provide constructive suggestions/solutions on system enhancement and development\nProvide coaching, constructive feedback to individuals for staff development and team building\nSupervise daily tasks and activities of the team and to ensure compliance of both internal and external procedures and policies\nAuthorize and approve internal vouchers, trade confirmations, settlement & payment instructions and relevant documents\nParticipate and oversee UAT on system enhancements\nFollow up failed trade settlements and handle mismatched or discrepancies with counterparties\nParticipate ad-hoc tasks assigned\n\nRequirements\n\nDegree holder or Business Administration or related disciplines\n\nMinimum 8 years\u2019 experience in financial services industry\nGood knowledge and experience in organization effectiveness and operations management\nStrong leadership and problem solving skills\nGood command of both written and spoken English and Chinese. Fluency in Putonghua an advantage\nCandidate with more experience will be considered as Vice President.\n\n\n\nWe offer a competitive remuneration package to the right candidate. If you are interested in the post, please send your resume together with your present and expected salaries by clicking \u201cApply Now\u201d.\u00a0\n\nFor more information about China Everbright Securities International Company Limited, please visit www.ebshk.com\n\nWe are an equal opportunity employer and welcome applications from all qualified candidates. All applications will be treated in the strictest confidence. Personal data provided will be used for recruitment purposes only. The job applicant will assume all or any risks arising out of or in connection with the job application transmission process prior to our actual receipt of the same including but not limited to accidental or unauthorized loss or disclosure of personal information, to which we will not be responsible in any way.\n\nUnder the Personal Data (Privacy) Ordinance, you may request access to, and / or correction of your personal data in relation to your application. If you wish to do so, please email to us.", "employment_types": ["Full Time", "Permanent"], "selling_points": [], "locations": ["Causeway Bay"], "categories": ["Banking / Finance", "Financial Services", "Equities / Capital Markets", "Order Processing & Operation / Settlement"], "post_time": "2022-01-08T05:16:14Z", "salary": {"currency": null, "max": null, "min": null, "period": "monthly", "term": null}, "salary_visible": false, "title_keywords": ["vice president", "operations", "assistant vice president"], "responsibilities": ["collaborate", "management", "uat", "operations", "policies", "compliance", "teams", "procedures", "ad-hoc tasks", "ensure compliance", "payment", "sales team", "manage daily operations"], "requirements": {"degrees": ["degree holder"], "majors": ["related disciplines", "business administration"], "languages": ["putonghua", "english", "chinese"], "language_level": ["fluency", "advantage", "good command"], "hard_skills": ["problem solving skills"], "soft_skills": ["problem solving skills", "leadership"], "languages_combined": [{"language": "putonghua", "language_level": ["fluency", "advantage"]}, {"language": "english", "language_level": ["good command"]}, {"language": "chinese", "language_level": ["good command"]}]}, "experience_required": {"duration": ["minimum 8 years"], "field": ["financial services industry", "operations management"]}}, {"job_id": "100003009026699", "location_code": "hk", "company": "ADECCO", "job_title": "Equity, Trade Support (6- month contract, Bank)", "description": "Our client is the leading banking in Hong Kong, they are looking for a Equity Middle Office Trading Support for 6 months contract.\n\nJob Responsibilities :\n\nManage daily trade booking and amendments/cancellations\nHandle daily trade queries with internal stakeholders\nMonitor & Manage trade life cycle bookings\nHandle and respond to queries and ad-hoc request from various support functions\nJob Requirements :\u00a0\n\nBachelor Degree in related discipline\nWith 3-5 years of strong experience in an investment banking environment, preferably middle office or trade processing role\nKnowledge in OTC Equity Derivatives, CBS, Prime Finance products and the trade life cycles\nAbility to pick up complex system quickly, work effectively under pressure and a fast learner\nStrong proficiency in MS Excel, VBA knowledge is an advantage\nIf you're interested in this role, please\u00a0CLICK HERE\u00a0to apply the position via Adecco website with your CV.\n\nPlease note that only shortlisted candidates will be notified. All information gathered will be treated in strict confidence and solely used for recruitment purposes.", "employment_types": ["Full Time", "Temporary", "Contract"], "selling_points": ["Middle office / Trading Support", "OTC Equity Derivatives /CBS, Prime Finance", "6 months contract, location : Central"], "locations": ["Central"], "categories": ["Banking / Finance", "Equities / Capital Markets"], "post_time": "2022-01-06T08:31:11Z", "salary": {"currency": null, "max": null, "min": null, "period": "monthly", "term": null}, "salary_visible": false, "title_keywords": [], "responsibilities": ["ad-hoc", "daily trade booking", "monitor"], "requirements": {"degrees": ["degree", "bachelor"], "majors": [], "languages": [], "language_level": [], "hard_skills": ["vba", "ms excel", "processing"], "soft_skills": ["work effectively", "confidence", "under pressure", "interested in", "fast learner"], "languages_combined": []}, "experience_required": {"duration": ["3-5 years"], "field": ["investment", "banking"]}}, {"job_id": "100003009020983", "location_code": "hk", "company": "Prince Group Holdings Limited", "job_title": "Investment Associate - Private Equity", "description": "Responsibilities:\n\nSupport team head in forming investment strategy and the roadmap\nConduct in-depth industry research and propose investment ideas mainly in Europe and US markets\nScreen investment opportunities and prepare analysis report\nDeal execution, including due diligence, coordination, negotiation and documentation\nManage portfolio companies and deal with post-investment activities when needed\n\nRequirements:\n\n\nBachelor\u2019s degree holder with Finance or other business-related disciplines\nMinimum of 5 years of relevant working experience in investment sector, good financial modelling skills\nBe able to conduct business meetings in both English and Chinese. Spoken and written Mandarin at native level is preferred\nFlexible enough to go beyond PE investment, e.g. property, fund of fund, private credit etc. Willing to learn and take responsibilities\nComfortable with different time zone working environment and willing to travel abroad when needed\nBe able to work under pressure with tight timeline or multi-task when needed\nLess qualified candidates will be considered the analyst role", "employment_types": ["Full Time"], "selling_points": ["Support team head in forming investment strategy", "Flexible enough to go beyond PE investment", "Relevant working experience in investment sector"], "locations": ["Central"], "categories": ["Banking / Finance", "Analyst", "Investment", "Equities / Capital Markets"], "post_time": "2022-01-05T02:46:58Z", "salary": {"currency": null, "max": null, "min": null, "period": "monthly", "term": null}, "salary_visible": false, "title_keywords": ["investment associate"], "responsibilities": ["due diligence", "ideas", "analysis report", "coordination", "documentation"], "requirements": {"degrees": ["bachelor", "degree holder"], "majors": ["related disciplines", "finance", "business"], "languages": ["english", "chinese", "mandarin"], "language_level": ["native"], "hard_skills": ["go", "pe"], "soft_skills": ["flexible", "willing to learn", "multi-task", "work under pressure"], "languages_combined": [{"language": "english", "language_level": []}, {"language": "chinese", "language_level": []}, {"language": "mandarin", "language_level": ["native"]}]}, "experience_required": {"duration": ["minimum of 5 years"], "field": ["investment", "relevant working experience", "financial"]}}, {"job_id": "100003009020174", "location_code": "hk", "company": "Ping An of China Securities (Hong Kong) Co Ltd", "job_title": "Analyst/Associate, Global Capital Markets (DCM)", "description": "Responsibilities:\n\nCompose pitch book and originate new client pitching\nOriginate transaction initiatives and maintain client relationship\nDrive capital markets transaction executions, able and willing to collaborate with teams for sales efforts\nConduct credit analysis and ratings assessment of existing and potential new issuers\nMaintain good relationship with both issuers and investors\n\nRequirements:\n\nDegree holder in Finance or relevant discipline\nExcellent analytical skills and presentation skills with \u201ccan do\u201d attitude\nProficiency in written and spoken English and Chinese\n2021 Fresh graduate is welcome\u00a0\n\nWe offer attractive remuneration package and fringe benefits to the right candidate. Interested applicants please send detailed resume stating present & expected salary and date of availability to Human Resources Department. To apply for this position, please click the \u201cAPPLY NOW\u201d.\u00a0\n\nAll applications will be treated in the strict confidence and personal data collected will be used for recruitment purpose only.\n\n*We do not accept solicitations from recruitment agencies*\n", "employment_types": ["Full Time", "Permanent"], "selling_points": ["DCM", "Good Career Prospect", "Fresh graduate is welcome"], "locations": ["Central"], "categories": ["Banking / Finance", "Financial Services", "Equities / Capital Markets"], "post_time": "2022-01-04T10:06:17Z", "salary": {"currency": null, "max": null, "min": null, "period": "monthly", "term": null}, "salary_visible": false, "title_keywords": ["analyst", "associate"], "responsibilities": ["collaborate with", "analysis", "teams", "maintain good relationship", "maintain"], "requirements": {"degrees": ["fresh graduate", "degree holder"], "majors": ["finance"], "languages": ["english", "chinese"], "language_level": ["proficiency"], "hard_skills": ["analytical skills"], "soft_skills": ["presentation skills", "analytical skills"], "languages_combined": [{"language": "english", "language_level": ["proficiency"]}, {"language": "chinese", "language_level": ["proficiency"]}]}, "experience_required": {"duration": [], "field": []}}, {"job_id": "100003009032082", "location_code": "hk", "company": "Randstad Hong Kong Limited", "job_title": "Counterparty Credit Risk, VP/SVP - Investment Bank", "description": "about the company\n\nOur client is a prestigious foreign investment bank provides capital markets, global markets, corporate finance and securities services to institutional clients across the globe.\n\nabout the team.\n\nThe Bank promotes work-life balance and stability. You will work with colleagues from all over the world, an international and dynamic work culture.\n\nabout the job\n\nYou will:\n\nAssess credit risk associated with business propositions across the region\nFormulate and develop credit risk management policies and procedures\nPerform high quality risk assessment on counterparty risk based on financial environment and credit background of clients\nDaily control and monitoring of credit exposure against limits and parameters\nSet up the counterparty credit risk desk for other regions\nskills & experiences required\nMinimum 8 years experience in credit risk management preferable from Global Markets and Banking\nGood knowledge in equity products, fixed income and derivatives\nExcellent project management experience\nGood command of English and Chinese", "employment_types": ["Full Time", "Permanent"], "selling_points": [], "locations": ["Not Specified"], "categories": ["Banking / Finance", "Credit Analysis / Approval", "Equities / Capital Markets", "Risk Management"], "post_time": "2022-01-07T10:11:45Z", "salary": {"currency": "HKD", "max": 89999, "min": 70000, "period": "monthly", "term": null}, "salary_visible": true, "title_keywords": [], "responsibilities": ["management", "control", "policies", "monitoring", "procedures", "quality", "develop", "project management", "banking"], "requirements": {"degrees": [], "majors": [], "languages": ["english", "chinese"], "language_level": ["good command"], "hard_skills": ["project management", "dynamic"], "soft_skills": ["project management", "dynamic"], "languages_combined": [{"language": "english", "language_level": ["good command"]}, {"language": "chinese", "language_level": ["good command"]}]}, "experience_required": {"duration": ["minimum 8 years"], "field": ["project management", "management", "credit risk", "banking"]}}, {"job_id": "100003009025048", "location_code": "hk", "company": "Soochow Securities (International) Financial Holdings Limited", "job_title": "Settlement Manager", "description": "Responsibilities:\nPerform daily settlement operation, including securities, futures & options, asset management, corporate actions and other CCASS/DCASS operations;\nMonitor day-to-day settlement procedures;\nCommunicating with internal parties & foreign brokers to solve the settlement problems;\nImplement system modification and enhancement tasks to meet business needs and UAT testing;\nIPO & EIPO Apply Process;\nHandle daily securities settlement of Corporate Action and Dividend;\nRights Issue, Conditional & Unconditional, Redemption, Corp Voting Instruction;\nPerform ad hoc assignments/duties as assigned.\nRequirements:\nDegree holder in Finance or related disciplines;\n7 years' working experience\u00a0or above, with good understanding of the settlement duties of Hong Kong market and China Connect markets;\nSolid knowledge in equity & equity-related products is required; product knowledge on Stock Options is an advantage;\nHighly self-motivated with good attention to details;\nKnowledge of excel and some programming skills are preferred;\nGood interpersonal and communication skills;\nGood command of written and spoken Chinese and English, including Putonghua;\nRemuneration:\nWe offers competitive remuneration package and promising career opportunities to the successful candidates.\nApply Method:\nInterested parties, please send full resume (both in English and Chinese) with current and expected salary and the date of availability to our email address underneath. Information provided will be treated in strict confidence and only be used for recruitment purpose.\nWelcome to learn more about Soochow Securities (Hong Kong) Financial Holdings Ltd. at http://www.dwzq.com.hk/\n\nPersonal data collected will be used for recruitment purpose only", "employment_types": ["Full Time", "Permanent"], "selling_points": ["Monitor day-to-day settlement procedures", "IPO & EIPO Apply Process", "7 years' working experience"], "locations": ["Not Specified"], "categories": ["Banking / Finance", "Equities / Capital Markets", "Order Processing & Operation / Settlement", "Asset Management"], "post_time": "2022-01-06T03:16:30Z", "salary": {"currency": null, "max": null, "min": null, "period": "monthly", "term": null}, "salary_visible": false, "title_keywords": ["settlement manager"], "responsibilities": ["operations", "monitor", "procedures", "uat testing", "communicating with", "system modification", "ad hoc assignments", "internal parties", "asset management"], "requirements": {"degrees": ["degree holder"], "majors": ["related disciplines", "finance"], "languages": ["putonghua", "english", "chinese"], "language_level": ["good command"], "hard_skills": ["excel", "programming"], "soft_skills": ["communication skills", "self-motivated", "interpersonal", "attention to details"], "languages_combined": [{"language": "putonghua", "language_level": ["good command"]}, {"language": "english", "language_level": ["good command"]}, {"language": "chinese", "language_level": ["good command"]}]}, "experience_required": {"duration": ["7 years"], "field": ["settlement duties"]}}, {"job_id": "100003009026651", "location_code": "hk", "company": "Page Personnel", "job_title": "Trader ( Execution) - Asset Management", "description": "Build a successful career path, focus on capital market's execution, work closely with portfolio managers\n\nClient Details\n\nOur company is a well-known asset management company with over 20 years history, it manages multi-asset platforms such as private equity, finance and asset management. The client manages more than USD 15 billion of capital and over 250 staff over the world. Currently, they are looking for an execution trader to support the portfolio manager.\n\nDescription\n\nConduct market research and communicate with portfolio manager on a regular basis\nBuild and maintain good relationships with sell-side analysts\nExecute dealing orders from portfolio manager\nConduct regular review on the market risk level\nEnsure efficient order execution\n\nProfile\n\nBachelor's Degree holder in Finance or related field\n2 years dealing experience\nExperienced in Bloomberg and Wind\nSFC type 1 and 9\nFluent in Mandarin, English and Cantonese\nAble to work under pressure, detail-oriented, multi-tasking\n\nJob Offer\n\nCompetitive remuneration package with annual bonus\n18 days annual leave\nFive days' work\nGreat career progression opportunity\nMPF, medical insurance\n\nTo apply online please click the 'Apply' button below. For a confidential discussion about this role please contact Joanie Lau on +852 3602 2458.", "employment_types": ["Full Time", "Permanent"], "selling_points": ["Build a successful career path", "Focus on capital market's execution", "Work closely with portfolio managers"], "locations": ["Not Specified"], "categories": ["Banking / Finance", "Financial Services", "Dealing & Trading", "Equities / Capital Markets"], "post_time": "2022-01-06T08:27:31Z", "salary": {"currency": null, "max": null, "min": null, "period": "monthly", "term": null}, "salary_visible": false, "title_keywords": ["asset management"], "responsibilities": ["communicate with", "mpf", "work under pressure", "conduct market research", "regular review", "maintain", "contact", "insurance", "asset management"], "requirements": {"degrees": ["bachelor", "degree holder"], "majors": ["finance"], "languages": ["cantonese", "english", "mandarin"], "language_level": ["fluent"], "hard_skills": ["focus", "bloomberg", "private equity"], "soft_skills": ["efficient", "detail-oriented", "multi-tasking", "focus", "work under pressure"], "languages_combined": [{"language": "cantonese", "language_level": ["fluent"]}, {"language": "english", "language_level": ["fluent"]}, {"language": "mandarin", "language_level": ["fluent"]}]}, "experience_required": {"duration": ["2 years"], "field": []}}, {"job_id": "100003009027022", "location_code": "hk", "company": "KCG Securities Asia Limited", "job_title": "Settlement Officer (5 Days)", "description": "Responsibilities:\n\n\n- Handle daily cash and product arrangement with counterparties & clients\n\n- Handle daily booking and settlement process of Securities and OTC product\n\n- Liaise with front office, brokers, IT and/or custodians to resolve trade and settlement issues\n\n- Prepare daily reconciliation reports to Supervisor\n\n- Provide other administrative support for the department\n\n- Handle ad hoc projects as assigned\n\n- Daily trade documents filing\n\n- Assist in system modification and UAT testing\n\n\n\nRequirements:\n\n\n- At least 1-2 years relevant working experience\n\n- Good PC knowledge including Excel and MS Word\n\n- Good command of written and spoken English, Cantonese and Mandarin\n\n- To be patience, willing to learn, detail-minded, initiative and teamwork concept\n\n- To delivery excellent operation service within the company.\n\n\n\nWe offer Performance Bonus, Group Medical & Dental.\n\nInterested candidates please send your\u00a0resume and\u00a0expected salary\u00a0to us.\n\n*Personal information collected is for recruitment purpose only.", "employment_types": ["Full Time", "Permanent"], "selling_points": [], "locations": ["Central"], "categories": ["Banking / Finance", "Financial Services", "Equities / Capital Markets", "Order Processing & Operation / Settlement"], "post_time": "2022-01-06T09:01:09Z", "salary": {"currency": null, "max": null, "min": null, "period": "monthly", "term": null}, "salary_visible": false, "title_keywords": ["officer"], "responsibilities": ["administrative support", "settlement process", "trade documents filing", "uat testing", "system modification", "handle daily cash", "product arrangement", "ad hoc projects", "liaise with", "resolve trade and settlement issues", "daily reconciliation reports", "handle daily booking"], "requirements": {"degrees": [], "majors": [], "languages": ["cantonese", "english", "mandarin"], "language_level": ["good command"], "hard_skills": ["excel", "pc knowledge", "ms word"], "soft_skills": ["detail-minded", "teamwork", "willing to learn", "patience", "initiative"], "languages_combined": [{"language": "cantonese", "language_level": ["good command"]}, {"language": "english", "language_level": ["good command"]}, {"language": "mandarin", "language_level": ["good command"]}]}, "experience_required": {"duration": ["at least 1-2 years"], "field": ["relevant working experience"]}}, {"job_id": "100003009032373", "location_code": "hk", "company": "Welend Limited", "job_title": "Senior Officer, Capital Markets", "description": "WeLab is a leading fintech company in Asia, \u00a0which operates one of first licensed digital banks in Asia \u2013 WeLab Bank, as well as multiple leading online financial services businesses including WeLend and WeLab Bank in Hong Kong, WeLab Digital (\u6211\u6765\u6570\u79d1), Taoxinji (\u6dd8\u65b0\u673a), Wallet Gugu (\u94b1\u5939\u8c37\u8c37) and Tianmian Tech (\u5929\u5195\u79d1\u6280)\u00a0in Mainland China and Maucash in Indonesia. WeLab aims to bring joy to everyone\u2019s financial journey. We strive to improve people\u2019s lives by reinventing financial services through game-changing technology. We put our people first, whether it\u2019s our customers or our employees.\n\nWe are an energetic and passionate team that can deliver and execute. We are looking for other intellectually curious, open-minded and smart-working individuals who are just as passionate as we are about making financial services enjoyable. Now you have the opportunity to join us on our journey to achieve our vision and be part of building a better financial future for everyone.\n\nAbout you:\n\nYou're a go-getter with mad juggling skills (or multiple hats) who can thrive in a fast-paced, agile environment\nYou have a strong thirst for knowledge and are driven to find solutions that don't exist yet\nYou are comfortable with ambiguity and extremely resourceful (in your past life you could've been a detective)\nYou always find a way to get things done without sacrificing the quality of your work, integrity and values. No task is off limits for you.\nYou are humble and prioritize the success of the team over your own with an eagerness to help those around you\nYou don't shy away from challenges and have the ability to bounce back from setbacks\n\nWhat you\u2019ll do and what success looks like in this role\n\nDiligently support Capital Markets Team to formulate and execute short-term and long-term strategies for establishing sustainable, low-cost funding from multiple sources;\nEfficiently conduct market research and analysis on the macro-economic, capital markets transactions and competitor analysis to explore potential funding partners and new Capital Markets initiatives;\nProactively handles deal execution process, including due diligence, documentation, drafting of presentation, reporting and meeting minutes;\nPrepare funding / cashflow models and sensitivity analysis for potential capital markets initiatives;\nWork with the relevant internal teams as a good Team Player to formulate and execute on execution plans relating to operations / IT systems including but not limited to new product & funding launch, portfolio management, reporting and monitoring;\nProfessionally assist in managing day-to-day effective communication with all stakeholders;\nHandle other ad hoc capital markets projects\n\nWhat is required and what we\u2019re looking for\n\nBachelor degree in Business Administration, Finance, Accounting or related discipline from a top tier university;\nAt least 3 - 6 years work experience in corporate finance / debt capital markets in reputable banks, investment firms or corporates;\nGood interpersonal and communication skills\u00a0to closely work with internal and external stakeholders;\nStrong analytical skills and highly self-motivated to take up challenges;\nAttention to details and be able to meet tight deadlines in a fast-paced business environment;\nProficient in Microsoft Office (Words, Excel, PowerPoint & Outlook)\u00a0and\nExcellent command of spoken and written English and Chinese\nCandidate with more experience will be considered as Assistant Manager, Capital Markets\n\nWeLab perks:\n\nCompetitive salary\nLearning and development stipend, because we value lifelong learning and believe the best way to invest in our employees is to encourage them to continue to learn\nWork hard and laugh lots (chicken wings and french toast, etc.) with a high-performing, fun and diverse team\nHappiness Dollars for spending on anything that makes you happy\nCoffee stipend\nConveniently located office surrounded by diverse and delicious lunch options\nLively office with gaming consoles and a ping pong table\nFun extracurricular activities with your colleagues like hiking, yoga, badminton, wine tasting, dragon boat racing, rock climbing, etc.\nEmployee referral bonuses\n\nAwards & recognition:\n\nFinancial Times (FT) 2020 Asia-Pacific High-Growth Companies \u2013 #2 ranked company\n2020 CNBC Disruptor 50 List - #11, only company included from Hong Kong and just one of five from Asia\n\nWe offer competitive salary package to the successful candidate.\u00a0If you are interested in joining this exciting team, please apply with resume via the \"Apply\" button below.\n\nAll information provided by applicants will be used for recruitment purposes only. Information of unsuccessful applicants will be destroyed within 24 months of receipt.\u00a0", "employment_types": ["Full Time", "Permanent"], "selling_points": ["5 days work for leading fintech in hk", "Great exposure on funding process", "Collaborative working environment"], "locations": ["Quarry Bay"], "categories": ["Banking / Finance", "Analyst", "Financial Services", "Equities / Capital Markets"], "post_time": "2022-01-07T10:57:13Z", "salary": {"currency": null, "max": null, "min": null, "period": "monthly", "term": null}, "salary_visible": false, "title_keywords": ["senior officer"], "responsibilities": ["due diligence", "cost", "reporting", "management", "ad hoc", "operations", "analysis", "conduct market research", "quality", "teams", "transactions", "systems", "monitoring", "communication", "documentation", "plans", "administration"], "requirements": {"degrees": ["degree", "bachelor"], "majors": ["finance", "accounting", "business administration"], "languages": ["english", "french", "chinese"], "language_level": ["excellent"], "hard_skills": ["excel", "no", "macro", "joy", "agile", "words", "microsoft office", "fun", "analysis", "powerpoint", "analytical skills", "outlook", "documentation", "go", "mad"], "soft_skills": ["meet tight deadlines", "agile", "sensitivity", "communication", "integrity", "diverse", "interpersonal", "presentation", "passionate", "communication skills", "good team player", "open-minded", "prioritize", "analytical skills", "attention to details", "energetic", "driven", "self-motivated", "resourceful", "learning", "business environment"], "languages_combined": [{"language": "english", "language_level": ["excellent"]}, {"language": "french", "language_level": []}, {"language": "chinese", "language_level": ["excellent"]}]}, "experience_required": {"duration": ["at least 3 - 6 years"], "field": ["capital markets", "investment", "corporate finance"]}}, {"job_id": "100003009019678", "location_code": "hk", "company": "Mergermarket Consulting Limited", "job_title": "Data Analyst (Korean Speaking)", "description": "Mergermarket (a division of ION Analytics) is a global provider of in-depth analysis and forward-looking information on corporate strategy and M&A activity for investment banks, private equity firms, advisors and corporate clients.\n\nThe position offers unique opportunities to get full exposure to M&A markets and to familiarize on Equity Capital Market activities in overall Asia. The role will primarily involve researching, evaluating and pricing mergers and acquisitions as well as producing in-depth sector and country reports.\n\nMain duties and responsibilities include:\n\nPerforming desktop research on real-time M&A transactions\nInterpreting financial data and other financial information in relation to M&A transactions\nContributing to and producing reports and data for publications based on this research using specialized knowledge of the M&A arena and the financial markets;\nQuality checking the historical database to ensure it reflects and provides a consistent high standard of data and analysis\nAnalyzing specific transactions to determine whether or not they meet the database inclusion criteria\nCleaning and updating the database to ensure that deal records, company records and individual profiles are accurate and comprehensive\nTracking and updating a specific universe of private equity firms in terms of their activity.\nFollowing qualifications are expected for an ideal candidate:\n\nFluency, including knowledge of business terminology, in English and Korean;\nA Business, Finance, Economics degree or equivalent preferred but not essential;\nDetail-oriented, diligent and with a genuine interest in M&A/Corporate Finance\nUnderstanding of financial statements;\nGood computer skills (especially Excel); Other programming language such as python is a plus.\nHighly numerate;\nKnowledge of research methodologies;", "employment_types": ["Full Time", "Permanent"], "selling_points": ["Data Research", "Cross teamwork with data engineers & practitioners", "Fresh Graduates are welcome"], "locations": ["Central"], "categories": ["Banking / Finance", "Equities / Capital Markets"], "post_time": "2022-01-04T08:22:47Z", "salary": {"currency": null, "max": null, "min": null, "period": "monthly", "term": null}, "salary_visible": false, "title_keywords": ["data analyst"], "responsibilities": ["quality checking", "data", "analysis", "transactions", "financial statements", "reports", "database", "cleaning", "tracking"], "requirements": {"degrees": ["degree"], "majors": ["finance", "business", "economics"], "languages": ["english", "korean"], "language_level": ["fluency"], "hard_skills": ["excel", "plus", "analysis", "computer skills", "programming", "python", "private equity"], "soft_skills": ["diligent", "unique", "detail-oriented", "genuine", "comprehensive", "accurate", "ideal"], "languages_combined": [{"language": "english", "language_level": ["fluency"]}, {"language": "korean", "language_level": ["fluency"]}]}, "experience_required": {"duration": [], "field": []}}, {"job_id": "100003009019660", "location_code": "hk", "company": "Mergermarket Consulting Limited", "job_title": "Data Analyst (Japanese Speaking)", "description": "Mergermarket (a division of ION Analytics) is a global provider of in-depth analysis and forward-looking information on corporate strategy and M&A activity for investment banks, private equity firms, advisors and corporate clients.\n\nThe position offers unique opportunities to get full exposure to M&A markets and to familiarize on Equity Capital Market activities in overall Asia. The role will primarily involve researching, evaluating and pricing mergers and acquisitions as well as producing in-depth sector and country reports.\n\nMain duties and responsibilities include:\n\nPerforming desktop research on real-time M&A transactions\nInterpreting financial data and other financial information in relation to M&A transactions\nContributing to and producing reports and data for publications based on this research using specialized knowledge of the M&A arena and the financial markets;\nQuality checking the historical database to ensure it reflects and provides a consistent high standard of data and analysis\nAnalyzing specific transactions to determine whether or not they meet the database inclusion criteria\nCleaning and updating the database to ensure that deal records, company records and individual profiles are accurate and comprehensive\nTracking and updating a specific universe of private equity firms in terms of their activity.\nFollowing qualifications are expected for an ideal candidate:\n\nFluency, including knowledge of business terminology, in English and Japanese;\nA Business, Finance, Economics degree or equivalent preferred but not essential;\nDetail-oriented, diligent and with a genuine interest in M&A/Corporate Finance\nUnderstanding of financial statements;\nGood computer skills (especially Excel); Other programming language such as python is a plus.\nHighly numerate;\nKnowledge of research methodologies", "employment_types": ["Full Time", "Permanent"], "selling_points": ["Data Research", "Cross teamwork with data engineers & practitioners", "Fresh Graduates are welcome"], "locations": ["Central"], "categories": ["Banking / Finance", "Equities / Capital Markets"], "post_time": "2022-01-04T08:18:12Z", "salary": {"currency": null, "max": null, "min": null, "period": "monthly", "term": null}, "salary_visible": false, "title_keywords": ["data analyst"], "responsibilities": ["quality checking", "data", "analysis", "transactions", "financial statements", "reports", "database", "cleaning", "tracking"], "requirements": {"degrees": ["degree"], "majors": ["finance", "business", "economics"], "languages": ["japanese", "english"], "language_level": ["fluency"], "hard_skills": ["excel", "plus", "analysis", "computer skills", "programming", "python", "private equity"], "soft_skills": ["diligent", "unique", "detail-oriented", "genuine", "comprehensive", "accurate", "ideal"], "languages_combined": [{"language": "japanese", "language_level": ["fluency"]}, {"language": "english", "language_level": ["fluency"]}]}, "experience_required": {"duration": [], "field": []}}]