[{"job_id": "100003009053585", "location_code": "hk", "company": "OSMA Consulting Limited", "job_title": "Analyst \u5206\u6790\u5e08", "description": "Our client is an innovation and technology focus venture capital fund partnership with reputable universities in Hong Kong, the founder belongs a reputable local family office. They are currently looking for qualified individual to join the team assisting deal execution and fund operation.\u00a0\n\n\n\nResponsibilities:\nPerform fundamental, in-depth industry research analysis (TMT, Fin-tech);\n\nResearch involves spreadsheet modeling, interviewing management teams and extensive research with potential target companies;\nAssist senior members to perform DD and execution on potential deals;\nAssist in maintaining relations with existing LPs and pitching for new LPs;\nLiaise with councils and fund admin to monitor the fund operation.\n\n\u00a0Requirements:\n\nDegree or above;\nWork with passion, critical thinking and creativity;\nCFA/CPA is a plus\nCommand of Bloomberg or Wind is a plus\nHigh integrity, good communication skill", "employment_types": ["Full Time"], "selling_points": ["Venture capital", "Excellent deal exposure", "Attractive package"], "locations": ["Central"], "categories": ["Banking / Finance", "Analyst", "Financial Services", "Professional Services", "Business Analysis / Data Analysis"], "post_time": "2022-01-17T07:14:55Z", "salary": {"currency": null, "max": null, "min": null, "period": "monthly", "term": null}, "salary_visible": false, "title_keywords": ["analyst"], "responsibilities": ["management teams", "maintaining", "monitor", "liaise with", "research analysis"], "requirements": {"degrees": ["degree or above"], "majors": [], "languages": [], "language_level": [], "hard_skills": ["cfa", "plus", "bloomberg", "cpa"], "soft_skills": ["communication skill", "integrity"], "languages_combined": []}, "experience_required": {"duration": [], "field": []}}, {"job_id": "100003009052097", "location_code": "hk", "company": "AVISTA Valuation Advisory Limited", "job_title": "Analyst / Senior Analyst", "description": "Service: Business Valuation\n\nLocation: Hong Kong\n\nJob Description and Responsibilities:\n\nPerform valuations for deal transaction and financial reporting purposes (such as purchase price allocation) under HKFRS, IFRS and US GAAP\nEngage in M&A advisory, financial modeling and other business consulting projects\nProduce and analyze financial model and business information\nConduct data collection and market research\nAssist in preparing proposal and presentation materials for potential valuation leads\n\nRequirements:\n\nUniversity graduates;\nProfessional qualification in Accounting (e.g. HKICPA / ACCA) or CFA would be an advantage;\n1 to 2 years relevant experience in M&A, audit or valuation related position. Experience in international valuation firm would be a plus.\nGood team player with the ability to work independently;\nProficiency in both verbal and written English and Mandarin is essential;\nGood understanding in valuation-related accounting standards (such as intangible assets and purchase price allocation issues) and valuation of financial instruments will be a plus;\nSound technical knowledge and the capability to apply up-to-date valuation methodologies;\nExcellent research, financial modelling and financial analytical skills;\nExcellent interpersonal and communication skills;\nShort business trip to PRC may be required.\nBenefit: We offer attractive remuneration package including a 5-day work week, medical insurance, study leave and good career prospect to the suitable candidate.\n\n\nApplication Procedure: Please send CV with expected salary by clicking \"Apply Now\".\n\nPersonal data will be used for recruitment purpose only.", "employment_types": ["Full Time", "Permanent"], "selling_points": ["Business valuation & financial reporting", "M&A advisory, financial modeling, IPO", "HKICPA/ACCA/CFA will be a plus"], "locations": ["Wan Chai"], "categories": ["Accounting", "Financial Analyst", "Banking / Finance", "Analyst", "Financial Services"], "post_time": "2022-01-17T02:05:31Z", "salary": {"currency": null, "max": null, "min": null, "period": "monthly", "term": null}, "salary_visible": false, "title_keywords": ["analyst", "senior analyst"], "responsibilities": ["valuation", "consulting", "financial modeling", "market research", "purchase", "financial reporting", "data collection"], "requirements": {"degrees": [], "majors": [], "languages": ["english", "mandarin"], "language_level": ["proficiency"], "hard_skills": ["acca", "plus", "cfa", "financial analytical skills", "hkicpa"], "soft_skills": ["communication skills", "good team player", "work independently", "analytical skills", "interpersonal"], "languages_combined": [{"language": "english", "language_level": ["proficiency"]}, {"language": "mandarin", "language_level": ["proficiency"]}]}, "experience_required": {"duration": ["1 to 2 years"], "field": ["related", "relevant experience", "audit"]}}, {"job_id": "100003009054816", "location_code": "hk", "company": "Essence International Financial Holdings Limited", "job_title": "\u516c\u53f8\u8463\u4e8b\u8fa6\u516c\u5ba4\u79d8\u66f8 \uff08\u8077\u7d1a\uff1a\u9ad8\u7d1a\u4e3b\u4efb\uff09", "description": "\u5d17\u4f4d\u8077\u8cac\uff1a\n\n\n\u5206\u6790\u3001\u6574\u7406\u53ca\u7de8\u5beb\u516c\u53f8\u6708\u5ea6\u3001\u5b63\u5ea6\u3001\u5e74\u5ea6\u5de5\u4f5c\u7e3d\u7d50\u3002\n\u8ca0\u8cac\u6703\u8b70\u7ba1\u7406\uff0c\u5305\u62ec\u4f46\u4e0d\u9650\u65bc\u6703\u8b70\u901a\u77e5\u3001\u6703\u8b70\u8a18\u9304\u3001\u6574\u7406\u6703\u8b70\u7d00\u8981\u3002\n\u516c\u53f8\u5927\u4e8b\u8a18\u3001\u516c\u53f8\u767c\u5c55\u898f\u5283\u8abf\u7814\u3001\u6536\u96c6\u7d93\u71df\u8cc7\u6599\u914d\u5408\u6bcd\u516c\u53f8\u9700\u8981\u9032\u884c\u696d\u52d9\u6230\u7565\u5206\u6790\u53ca\u540c\u696d\u6bd4\u8f03\u5206\u6790\u3002\n\u6bcd\u516c\u53f8\u4e0b\u767c\u7684\u5176\u4ed6\u5404\u985e\u6587\u5b57\u6750\u6599\u6574\u7406\u3001\u8d77\u8349\u53ca\u532f\u7e3d\u5de5\u4f5c\uff0c\u4e26\u5f62\u6210\u5831\u544a\u3002\n\u4e0a\u7d1a\u4ea4\u8fa6\u7684\u81e8\u6642\u6027\u5de5\u4f5c\u7684\u57f7\u884c\u8207\u56de\u994b\uff0c\u53ca\u5b8c\u6210\u9818\u5c0e\u4ea4\u8fa6\u7684\u5176\u4ed6\u5de5\u4f5c\n\n\u4efb\u8077\u8981\u6c42\uff1a\n\n\u5de5\u5546\u7ba1\u7406\u3001\u6cd5\u5f8b\u3001\u91d1\u878d\u3001\u8ca1\u52d9\u7b49\u6709\u95dc\u5c08\u696d\u672c\u79d1\u6216\u7814\u7a76\u751f\u4ee5\u4e0a\u5b78\u6b77\uff1b\n\u8f03\u597d\u7684\u6587\u5b57\u5beb\u4f5c\u80fd\u529b\uff0c\u80fd\u5920\u64b0\u5beb\u5404\u985e\u8fa6\u516c\u6587\u4ef6\u53ca\u5354\u52a9\u7de8\u5236\u5206\u6790\u5831\u544a\uff1b\u80fd\u5920\u719f\u7df4\u904b\u7528\u8fa6\u516c\u8edf\u9ad4\u53caOFFICE\u8fa6\u516c\u8edf\u9ad4\uff0c\u5c24\u5176PPT\uff1b\n\u5177\u5099\u826f\u597d\u7684\u7406\u89e3\u529b\u548c\u6e9d\u901a\u8868\u9054\u80fd\u529b\uff0c\u5177\u8cac\u4efb\u611f\uff0c\u4e0d\u4ecb\u610f\u52a0\u73ed\u5de5\u4f5c\uff1b\n\u5177\u6709\u8f03\u5f37\u7684\u7d9c\u5408\u5206\u6790\u3001\u7d44\u7e54\u5354\u8abf\u3001\u6e9d\u901a\u53ca\u7368\u7acb\u601d\u8003\u80fd\u529b\uff0c\u53c3\u8b00\u7b56\u5283\u53ca\u5354\u52a9\u9818\u5c0e\u4e3b\u6301\u8d77\u8349\u6709\u95dc\u5de5\u4f5c\u898f\u5283\u3001\u5236\u5ea6\u3001\u8fa6\u6cd5\u3001\u7a0b\u5e8f\u7684\u80fd\u529b\uff1b\n\u5177\u50993-5\u5e74\u4ee5\u4e0a\u6709\u95dc\u8463\u79d8\u6216\u76f8\u95dc\u5de5\u4f5c\u7d93\u9a57\uff0c\u64c1\u6709\u4e2d\u8cc7\u9280\u884c\u6216\u91d1\u878d\u6a5f\u69cb\u5de5\u4f5c\u53ca\u4e2d\u5927\u578b\u516c\u53f8\u8463\u4e8b\u6703\u8fa6\u516c\u5ba4\u3001\u76e3\u4e8b\u6703\u8fa6\u516c\u5ba4\u5de5\u4f5c\u7d93\u9a57\u512a\u5148\u8003\u616e\u3002\n\u7d93\u9a57\u8c50\u5bcc\u8005\uff0c\u8077\u7d1a\u53ef\u8003\u616e\u70ba\u52a9\u7406\u7d93\u7406\u3002\n\n\nWe offer attractive package to the right candidate. Interested parties please apply with full resume both in English and Chinese (including current and expected salary) to\u00a0us.\u00a0\n\nPersonal data collected will be used for recruitment-related purposes only.", "employment_types": ["Full Time", "Permanent"], "selling_points": ["\u5206\u6790\u3001\u6574\u7406\u53ca\u7de8\u5beb\u5de5\u4f5c\u5831\u544a", "\u8207\u6bcd\u516c\u53f8\u63a5\u6d3d\uff0c\u5b8c\u6210\u6709\u95dc\u5de5\u4f5c", "\u5177\u50993-5\u5e74\u4ee5\u4e0a\u6709\u95dc\u8463\u79d8\u6216\u76f8\u95dc\u5de5\u4f5c\u7d93\u9a57"], "locations": ["Central"], "categories": ["Admin & HR", "Administration / Operation Manager", "Secretary", "Banking / Finance", "Financial Services"], "post_time": "2022-01-17T11:21:22Z", "salary": {"currency": null, "max": null, "min": null, "period": "monthly", "term": null}, "salary_visible": false, "title_keywords": [], "responsibilities": [], "requirements": {"degrees": [], "majors": [], "languages": [], "language_level": [], "hard_skills": [], "soft_skills": [], "languages_combined": []}, "experience_required": {"duration": [], "field": []}}, {"job_id": "100003009051972", "location_code": "hk", "company": "Lucion International Financial Limited", "job_title": "Director/ Executive Director of PE Investment", "description": "Responsibilities\n\nEstablish and lead the PE team, build up internal policy on high standards\nResponsible for deals to meet the profit target, also to create and maintain good investor relations by effective ways\nOversee whole process of investment, including due diligence, valuation, deal structuring, transaction document negotiation & drafting and closing\nUndertake the post-deal monitoring of the investments through performance review, analysis on capital deployment and performance\nLiaise with the investment departments, external partners, lawyers, accountants, bankers, service provider and other professional parties throughout the whole process\nFollow-up investment performance and post-investment management\n\nRequirement\n\nBachelor's Degree or above in Economics, Investment, Finance or relevant disciplines\nMinimum 6 years working experience and at least 3 years in asset management, PE, investment banking or relevant financial institutions are preferred\nMember of CPA/CFA/ FRM is advantageous\nHigh level of multi-tasking and time management skill are required\nResult-oriented and willing to work under high pressure\nStrong investor management skills\nExcellent command in spoken and written English and Chinese (including Putonghua)\n\nRemuneration and Benefits:\u00a0Salary will be commensurate with qualifications and experience. A competitive remuneration and benefits package, including annual leave, medical benefits, will be offered.", "employment_types": ["Full Time", "Permanent"], "selling_points": ["CPA/CFA/ FRM", "Economics, Investment, Finance or relevant discipl", "PE Investment"], "locations": ["Central"], "categories": ["Banking / Finance", "Investment", "Financial Services"], "post_time": "2022-01-17T01:41:49Z", "salary": {"currency": null, "max": null, "min": null, "period": "monthly", "term": null}, "salary_visible": false, "title_keywords": ["executive director", "director"], "responsibilities": ["due diligence", "valuation", "management", "profit target", "analysis", "monitoring", "review", "maintain", "liaise with"], "requirements": {"degrees": ["degree or above", "bachelor"], "majors": ["finance", "economics"], "languages": ["putonghua", "english", "chinese"], "language_level": ["excellent"], "hard_skills": ["cfa", "cpa", "pe", "frm"], "soft_skills": ["result-oriented", "multi-tasking", "work under high pressure", "time management skill"], "languages_combined": [{"language": "putonghua", "language_level": ["excellent"]}, {"language": "english", "language_level": ["excellent"]}, {"language": "chinese", "language_level": ["excellent"]}]}, "experience_required": {"duration": ["at least 3 years", "minimum 6 years"], "field": ["financial institutions", "banking", "investment", "asset management"]}}, {"job_id": "100003009052133", "location_code": "hk", "company": "BOCOM International Holdings Company Limited", "job_title": "Contract Customer Assistant, Equity Business (under 1-year Renewable Agency Contract)", "description": "Job Purpose\n\nProvide full range of client account services proactively to clients\nBe competent in handling all client service related enquiries\nMonitor potential risks of clients\u2019 accounts\nJob Descriptions\n\nPerform and follow up with account opening duties, like conducting KYC, AML and due diligence checks, etc., to ensure smooth and proper process of client onboarding and in compliance with internal and external policies and regulations.\nProvide quality services, for example, answering clients enquires, handling transaction matters, and performing other administrative tasks\nCollaborate with internal parties to provide effective and efficient client services and support\nHandle and assist in ad-hoc assignments/ projects as and when required\nJob Requirement\n\nBachelor degree or above in Business Administration, Management or Finance related discipline\nMinimum 2 years\u2019 relevant experience in client servicing, gained in financial services industry\nKnowledge on SFC requirements an advantage\nExcellent client service mindset\nGood interpersonal and communication skills; attentive to details\nAble to work under pressure and independently; with outstanding spirit of team work\nProficient PC skills in Microsoft Windows and Office\nGood command of written and spoken English and Chinese with fluency in Cantonese and Mandarin.\n\nApplication\n\n\u00a0If you are interested in this job opportunity, please send your application with a detailed resume including current and expected salary, latest bonus and availability by clicking \"Apply Now\".\u00a0\n\n*Information provided by applicants will be treated in the strictest confidence and will be solely used for recruitment purposes.", "employment_types": ["Contract"], "selling_points": ["Customer Services", "Account Opening Experience", "Customer Due Diligence"], "locations": ["Central"], "categories": ["Banking / Finance", "Financial Services", "Sales, CS & Business Devpt", "Call Centre", "Account Servicing"], "post_time": "2022-01-17T02:12:19Z", "salary": {"currency": null, "max": null, "min": null, "period": "monthly", "term": null}, "salary_visible": false, "title_keywords": ["assistant"], "responsibilities": ["regulations", "due diligence", "collaborate with", "aml", "account opening", "policies", "compliance", "quality", "ad-hoc assignments", "kyc", "administrative tasks", "internal parties"], "requirements": {"degrees": ["degree or above", "bachelor"], "majors": ["finance", "business administration"], "languages": ["cantonese", "english", "chinese", "mandarin"], "language_level": ["fluency", "good command"], "hard_skills": ["pc skills"], "soft_skills": ["communication skills", "independently", "confidence", "attentive to details", "interested in", "detailed", "interpersonal", "work under pressure"], "languages_combined": [{"language": "cantonese", "language_level": ["fluency", "good command"]}, {"language": "english", "language_level": ["fluency", "good command"]}, {"language": "chinese", "language_level": ["fluency", "good command"]}, {"language": "mandarin", "language_level": ["fluency", "good command"]}]}, "experience_required": {"duration": ["minimum 2 years"], "field": ["financial services industry", "relevant experience"]}}, {"job_id": "100003009052045", "location_code": "hk", "company": "BOCOM International Holdings Company Limited", "job_title": "Sales Associate (Supporting role), Fund Business", "description": "\nKey Responsibilities\n\u2022 Prepare and execute client onboarding and dealing documentation as well as address client enquiry\u00a0\n\u2022 Build and maintain solid and long-lasting client relationships\n\u2022 Assist to plan and deliver sales and marketing seminars and activities in order to capture business opportunities and tighten bonding with clients\n\u2022 Proactively follow up with clients to learn their thoughts and provide investors' feedback to fund managers\n\u2022 Assist Department Head in identifying business opportunities of mutual funds and other asset management products for cross-border financial institutions and corporate clients and implement business development initiatives to expand fund resources\n\u2022 Work on ad-hoc reports and presentations etc in a timely manner\n\nRequirements\n\u2022 2 years\u2019 experience in client services, sales or business development in banking or asset management industry, with passes in HKSI LE Exams/ License to perform RA type 9 activity\n\u2022 Bachelor Degree or above in Finance, Economics, Marketing or equivalent disciplines\n\u2022 Proven experience in handling client onboarding documentation, KYC and due diligence process\n\u2022 Solid knowledge of financial products and markets, experience in a sales or business development role in asset management company a plus\n\u2022 Self-motivated, team player with excellent communication, interpersonal and presentation skills\n\u2022 Good command of spoken Cantonese, and written English and Chinese with fluency in Mandarin\n\u2022 Candidate with more experiences will be considered as Senior Associate", "employment_types": ["Full Time"], "selling_points": ["-", "-", "-"], "locations": ["Central"], "categories": ["Banking / Finance", "Corporate Banking", "Financial Services", "Asset Management"], "post_time": "2022-01-17T01:56:34Z", "salary": {"currency": null, "max": null, "min": null, "period": "monthly", "term": null}, "salary_visible": false, "title_keywords": ["sales associate"], "responsibilities": ["ad-hoc", "business opportunities", "a timely manner", "presentations", "maintain", "reports", "plan", "documentation", "asset management"], "requirements": {"degrees": ["degree or above", "bachelor"], "majors": ["finance", "economics", "marketing"], "languages": ["cantonese", "english", "chinese", "mandarin"], "language_level": ["fluency", "good command"], "hard_skills": ["plus", "hksi", "ra type", "kyc", "documentation"], "soft_skills": ["self-motivated", "communication", "presentation skills", "team player", "interpersonal"], "languages_combined": [{"language": "cantonese", "language_level": ["good command"]}, {"language": "english", "language_level": ["fluency", "good command"]}, {"language": "chinese", "language_level": ["fluency", "good command"]}, {"language": "mandarin", "language_level": ["fluency", "good command"]}]}, "experience_required": {"duration": ["2 years"], "field": ["business development", "asset management", "financial", "banking"]}}, {"job_id": "100003009052400", "location_code": "hk", "company": "Luk Fook Financial Services Limited", "job_title": "Relationship Manager", "description": "Job Descriptions\n\nProvide professional services to our high net worth client base\nDevelop new prospects on insurance brokerage business\nHandle after-sales services and maintain good relationship with clients\nWe provide intensive training to new entry\nWe have high net worth client base\nWe offer flexible working hours and help you achieve financial freedom\n\nJob requirements\n\n\nNo relevant experience is required\nSelf-motivated, sales driven, customer focused and can work under pressure\n\nGood interpersonal skills and out-going\nWilling to learn\n\nInformation collected is for recruitment purpose only. All applications will be treated strictly confidential.", "employment_types": ["Full Time"], "selling_points": ["Professional Financial Services", "High Net Worth Client Base", "Flexible Working Hours and Financial Freedom"], "locations": ["Sheung Wan"], "categories": ["Banking / Finance", "Investment", "Financial Services", "Wealth Management"], "post_time": "2022-01-17T02:57:32Z", "salary": {"currency": null, "max": null, "min": null, "period": "monthly", "term": null}, "salary_visible": false, "title_keywords": ["relationship manager"], "responsibilities": ["brokerage", "maintain good relationship", "develop", "client base", "insurance"], "requirements": {"degrees": [], "majors": [], "languages": [], "language_level": [], "hard_skills": [], "soft_skills": [], "languages_combined": []}, "experience_required": {"duration": [], "field": []}}, {"job_id": "100003009051530", "location_code": "hk", "company": "Morgan Half International (Hong Kong) Limited", "job_title": "Assistant Manager - KYC / CDD / AML / Compliance / Client Onboarding", "description": "Job Description\n\nOur client is a multinational and fast growing professional firm in fund services, private wealth management and corporate services\u00a0 is currently seeking an experienced KYC / AML / Client onboarding candidate to support their business expansion which has grown well organically despite the pandemic.\u00a0\n\nResponsibilities:\n\nHandle day-to-day matters on client on-boarding\u00a0\nConduct KYC /AML checks and documentations, sanction list screening\nReview due diligence documents on existing and new files\nKeep abreast of new updates on compliance policy for various jurisdictions\nAssist with ad-hoc projects as assigned\n\nRequirements:\n\nUniversity degree in Accounting, Finance or a related discipline\n4 years of work experience in AML / KYC in bank or other professional firm.\nGood communications, interpersonal and problem solving skills\nGood verbal and written communication skills \u2013 Cantonese, English and Mandarin.\nTo apply online, please click \"Apply Now\" button below. For any inquiries, please email info @morganhalf.com", "employment_types": ["Full Time", "Permanent"], "selling_points": ["Well establish and dynamic working environment", "Offshore jurisdiction exposure", "4 years KYC / CDD experience"], "locations": ["Not Specified"], "categories": ["Banking / Finance", "Financial Services", "Others", "Professional Services", "Legal & Compliance"], "post_time": "2022-01-16T08:10:58Z", "salary": {"currency": null, "max": null, "min": null, "period": "monthly", "term": null}, "salary_visible": false, "title_keywords": ["assistant manager"], "responsibilities": ["due diligence", "management", "aml", "review", "compliance", "kyc", "ad-hoc projects"], "requirements": {"degrees": ["university degree"], "majors": ["finance", "accounting"], "languages": ["cantonese", "english", "mandarin"], "language_level": ["good"], "hard_skills": ["problem solving skills", "aml", "kyc"], "soft_skills": ["communication skills", "problem solving skills", "interpersonal"], "languages_combined": [{"language": "cantonese", "language_level": ["good"]}, {"language": "english", "language_level": ["good"]}, {"language": "mandarin", "language_level": ["good"]}]}, "experience_required": {"duration": ["4 years"], "field": []}}, {"job_id": "100003009052438", "location_code": "hk", "company": "Kingkey Securities Group Limited", "job_title": "Accounting Officer", "description": "Handle daily accounting functions, assist in the monthly management accounts and reconciliations of A/R & A/P\nAssist in preparing and monitoring the daily and monthly FRR under the Securities and Futures Ordinance \u201cSFO\u201d\nPerform month-end closing & prepare periodic schedules\nLiaise with banks, auditors and other regulators\nPerform ad hoc assignments as required\n\n\u00a0Requirements:\n\nBachelor Degree in accounting or finance or equivalent is preferred\n3\u00a0years relevant accounting experience in securities firms\nSolid experience in securities accounting, SFC Financial Resources Rules and Financial Returns are advantages\nGood command of both spoken and written English and Chinese\nEnthusiastic, detail-minded, mature with positive attitude and a good team player", "employment_types": ["Full Time", "Permanent"], "selling_points": [], "locations": ["Wan Chai"], "categories": ["Accounting", "Accounting Clerk / Supervisor", "Banking / Finance", "Financial Services"], "post_time": "2022-01-17T03:02:57Z", "salary": {"currency": null, "max": null, "min": null, "period": "monthly", "term": null}, "salary_visible": false, "title_keywords": ["accounting officer"], "responsibilities": ["management", "schedules", "monitoring", "reconciliations", "month-end closing", "ad hoc assignments", "liaise with", "daily accounting"], "requirements": {"degrees": ["degree", "bachelor"], "majors": ["finance", "accounting"], "languages": ["english", "chinese"], "language_level": ["good command"], "hard_skills": ["r", "securities and futures ordinance", "frr", "sfo"], "soft_skills": ["detail-minded", "good team player", "mature", "positive attitude", "enthusiastic"], "languages_combined": [{"language": "english", "language_level": ["good command"]}, {"language": "chinese", "language_level": ["good command"]}]}, "experience_required": {"duration": ["3 years"], "field": ["accounting experience", "securities firms", "securities", "accounting", "financial"]}}, {"job_id": "100003009052441", "location_code": "hk", "company": "Haitong International Securities Group Limited", "job_title": "Quantitative Analyst (VP to SVP) - Trading (Ref. no.: JDB/TRD/QA/VP_SVP)", "description": "Core Job Responsibilities:\n\nDeveloping and Supporting Quantitative models for HTI's cash equities agency trading platform.\n\nDetails:\n\nHaitong International has a suite of existing quantitative models which feed into the algorithmic trading engine including volume forecasts, fair value estimation and volatility forecasts;\nWe are looking for a mid-level quantitative analyst with R/Python skills who is capable of maintaining and further developing these models;\nThey will also be responsible for developing new models in time;\nThis person will be the key contact for model related questions and may be required to explain functionality to clients;\nFuture responsibilities include working on proprietary trading strategies.\n\nProgramming Skills (In order of importance):\n\nJava, R, Python, q/KDB.\n\nRequirements :\n\nExcellent academic record of bachelor's degree (or above) from a top university, major in Computer Science, engineering or other quantitative related discipline;\nA PhD/Masters that focuses on Machine Learning/Data Science/Computer Science/Physics/Mathematics/Statistics is an advantage;\nDynamic Linear Models experience;\nFamiliarity with Neural Nets and other ML techniques;\nIndependent research experience;\nHighly motivated and competitive;\nLearning curiosity & agility;\nA good communicator and team player.\n\n\n\n\nWe are committed to build a team of competence individuals who have acquired relevant local solid working experience and with diversified exposure to work together with us. Applicants who do not hear from us within 6 weeks may consider their applications unsuccessful.\n\nWe provide attractive remuneration package and fringe benefits for the right candidate. Interested parties please send detailed resume with current and expected salaries to\u00a0Human Resources Department i) by mail: 22/F, Li Po Chun Chambers, 189 Des Voeux Road Central, HK; ii) by fax: 2537 5431;\u00a0or iii) by using \"APPLY NOW\".\n\nPlease quote the reference in the application. If application is submitted in hard copy format, it should be placed in a sealed envelope marked \u201cConfidential\u201d. All applications will be treated in strict confidence and personal data provided by job applications will be used for recruitment purposes only. A copy of our Personal Information Collection Statement will be available upon request.", "employment_types": ["Full Time", "Permanent"], "selling_points": [], "locations": ["Central"], "categories": ["Banking / Finance", "Financial Services", "Information Technology (IT)", "Support", "Software Development"], "post_time": "2022-01-17T03:02:17Z", "salary": {"currency": null, "max": null, "min": null, "period": null, "term": null}, "salary_visible": false, "title_keywords": ["analyst"], "responsibilities": ["contact", "developing", "maintaining"], "requirements": {"degrees": ["degree", "bachelor"], "majors": ["engineering", "computer science"], "languages": [], "language_level": [], "hard_skills": ["ml", "dynamic"], "soft_skills": ["independent", "committed", "motivated", "dynamic", "learning", "team player", "communicator"], "languages_combined": []}, "experience_required": {"duration": [], "field": ["research", "team"]}}, {"job_id": "100003009054309", "location_code": "hk", "company": "Infinity Asset Management Limited", "job_title": "Management Trainee - Digital Marketing Executive", "description": "Job Descriptions:\n\n1.\u00a0Assist in asset management business;\n\n2.\u00a0Work with the team to execute business development plans by preparing presentations ;\n\n3.\u00a0Assist in fund administration and daily operations;\n\n4.\u00a0Any ad hoc tasks relating to asset management.\n\n5.Formulating marketing strategy and execution plan;\n\n6.Advertising design on platforms including Facebook, Linkedin and Wechat etc;\n\n7.Develop and edit the publicity material (e.g. newsletter, leaflet and brochure);\n\nQualifications:\n\n1.\u00a0Bachelor's degree holder in Finance or Economic or Accounting or Business Administration\u00a0 \u00a0\u00a0\n\n2.\u00a0High level of Microsoft Office Proficiency, such as Word, Excel, PowerPoint\n\n3.\u00a0Strong written and oral communication skills in English, Cantonese, Putonghua\n\n4.\u00a01-2 years working experience preferred / fresh graduates would also be considered\n\nInterested parties please send your\u00a0RESUME with\u00a0AVAILABILITY & EXPECTED SALARY\u00a0to \"Apply Now\".\u00a0All applications received will be used strictly for hiring purposes only.\u00a0\n\n\n\nAbout\u00a0Infinity Asset Management Limited\n\nInfinity Asset Management is a Hong Kong based fast growing asset management company. Our company aims to develop external asset management and hedge fund business in Hong Kong. We provide opportunities to candidates with the ambition to obtain experience in the high-net-worth wealth management industry.", "employment_types": ["Full Time"], "selling_points": ["Asset Management", "Hedge Fund", "5 working days"], "locations": ["Wan Chai"], "categories": ["Banking / Finance", "Financial Services", "Fund Management", "Asset Management"], "post_time": "2022-01-17T09:06:13Z", "salary": {"currency": null, "max": null, "min": null, "period": "monthly", "term": null}, "salary_visible": false, "title_keywords": ["management trainee", "digital marketing executive"], "responsibilities": ["advertising", "leaflet", "ad hoc tasks", "presentations", "design", "develop", "communication", "daily operations", "asset management", "plan", "plans", "facebook", "administration"], "requirements": {"degrees": ["bachelor", "degree holder"], "majors": ["finance", "accounting", "business administration"], "languages": ["cantonese", "putonghua", "english"], "language_level": [], "hard_skills": ["excel", "microsoft office", "word", "presentations", "wechat", "powerpoint", "facebook"], "soft_skills": ["communication skills", "oral"], "languages_combined": [{"language": "cantonese", "language_level": []}, {"language": "putonghua", "language_level": []}, {"language": "english", "language_level": []}]}, "experience_required": {"duration": ["1-2 years"], "field": []}}, {"job_id": "100003009054597", "location_code": "hk", "company": "MUFG Bank, Ltd.", "job_title": "Analyst - Client Service and Agency Department - Asian Investment Banking Division", "description": "Job Responsibilities\n\nTo provide quality agent bank services to the customers and the lenders for the transactions originated in Asia Pacific region including corporate loans, export credit agency facilities, etc.\nHandle full set of agent bank services including, among others, conditions precedent documents, drawdown, rollover and payments, withholding tax, waiver, amendments, etc.\nLiaise with internal and external parties ensuring services to be performed in accordance with the documents, internal procedures and external regulatory requirements.\u00a0 \u00a0 \u00a0 \u00a0 \u00a0 \u00a0 \u00a0 \u00a0 \u00a0 \u00a0 \u00a0 \u00a0 \u00a0 \u00a0 \u00a0 \u00a0 \u00a0 \u00a0 \u00a0 \u00a0 \u00a0 \u00a0 \u00a0 \u00a0 \u00a0 \u00a0 \u00a0 \u00a0 \u00a0 \u00a0 \u00a0 \u00a0 \u00a0 \u00a0 \u00a0 \u00a0 \u00a0 \u00a0 \u00a0 \u00a0 \u00a0\n\nJob Requirements\n\nA degree holder (finance related degrees preferable);\n1-2 years\u2019 banking experience (preferable);\u00a0\nGood command of written and spoken English, Chinese & Putonghua\n\nWe regret to inform that only shortlisted applicants will be notified. Personal data collected will be used for recruitment purposes only.For our Privacy Policy, please visit: https://www.bk.mufg.jp/global/privacy/index.html", "employment_types": ["Full Time", "Permanent"], "selling_points": ["Multinational Bank", "Stable Environment", "Attractive Benefits"], "locations": ["Central"], "categories": ["Banking / Finance", "Financial Services"], "post_time": "2022-01-17T10:11:27Z", "salary": {"currency": null, "max": null, "min": null, "period": null, "term": null}, "salary_visible": false, "title_keywords": ["analyst"], "responsibilities": ["tax", "regulatory requirements", "internal and external parties", "quality", "procedures", "transactions", "payments", "liaise with"], "requirements": {"degrees": ["degree holder"], "majors": ["finance"], "languages": ["putonghua", "english", "chinese"], "language_level": ["good command"], "hard_skills": ["inform", "html"], "soft_skills": [], "languages_combined": [{"language": "putonghua", "language_level": ["good command"]}, {"language": "english", "language_level": ["good command"]}, {"language": "chinese", "language_level": ["good command"]}]}, "experience_required": {"duration": ["1-2 years"], "field": ["banking experience"]}}, {"job_id": "100003009054741", "location_code": "hk", "company": "Cheuk Hang Growth", "job_title": "Investment Trainee", "description": "Job Descriptions:\n\n\u2022 Understand customer needs and recommend tailor-made financial solutions, enabling customers to enjoy the full benefits of our comprehensive range of products and services\n\u2022 Provide comprehensive and professional financial services such as Risk Management Planning, Investment Planning, Wealth Management, Retirement Planning\n\u00a0\u2022 Offer proactive and personalized financial services of the company to the customers\n\u2022 Support the company\u2019s initiatives as and when necessary\n*Subject to prescribed conditions and qualifications.\n\nCandidate Requirement\n\u2022 Academic qualification equivalent or higher than Level 2 in 5 subjects in HKDSE, including a language subject (Chinese/English) and Mathematics\n\u00a0\u2022 Strong communication and interpersonal skills\n\u2022 High degree of credibility and integrity\n\u2022 Passionate and interested in exploring and experiencing the financial worldWhat are we offering\n\u2022 Monthly allowance up to 12 months plus attractive sales commission and quarterly & annual bonus\n\u2022 A well-structured and comprehensive training program by our company and our team of industry renowned mentors, conducted in different languages\n\u00a0\u2022 Ongoing product training courses and managerial training courses to suit your need in every step of your career\n\u2022 Practical support to help you achieve your career goal\n\u00a0\u2022 Awards and incentives to reward agent including Annual Award Presentation and Overseas Conventions for high achievers\n\u2022 Long term development of your career path customized to your personal goals", "employment_types": ["Full Time", "Part Time", "Permanent", "Internship"], "selling_points": [], "locations": ["Central & Western Area"], "categories": ["Banking / Finance", "Investment", "Financial Services", "Insurance", "Insurance Agent / Broker"], "post_time": "2022-01-17T10:50:51Z", "salary": {"currency": "HKD", "max": 29999, "min": 20000, "period": "monthly", "term": null}, "salary_visible": true, "title_keywords": ["investment trainee"], "responsibilities": ["understand customer needs", "management", "planning"], "requirements": {"degrees": [], "majors": [], "languages": [], "language_level": [], "hard_skills": [], "soft_skills": [], "languages_combined": []}, "experience_required": {"duration": [], "field": []}}, {"job_id": "100003009053962", "location_code": "hk", "company": "CMB International Capital Corporation Limited", "job_title": "Customer Services Officer \u2013 Equities Department (1-Year Contract)", "description": "Major Responsibilities:\n\nResponsible for providing quality customer service to the Company clients from HK and China market;\nCoordinate with cross-department counterparts to enhance operation efficiency and customer experience.\nEstablish good relationship with clients\nHandle incoming telephone calls/Enquiry from electronic platform and greet visitors in a professional and courteous manner;\nHandling account opening and margin financing procedures;\n\n\u00a0Qualifications & Requirements:\n\nDegree Holder with major in Business, Finance or related disciplines;\n1 year of relevant experience in the similar position preferably;\nHolder of SFC Type 1 License is preferred;\nTactful customer services skills and good problem solving abilities;\nGood communication and interpersonal skills;\nGood written and spoken English and Chinese, with excellent command of Putonghua", "employment_types": ["Full Time", "Contract"], "selling_points": ["Customer Services", "SFC Type 1 License", "Brokerage"], "locations": ["Central"], "categories": ["Banking / Finance", "Financial Services", "Sales, CS & Business Devpt", "Customer Service - Supervisor / Officer"], "post_time": "2022-01-17T07:51:29Z", "salary": {"currency": null, "max": null, "min": null, "period": "monthly", "term": null}, "salary_visible": false, "title_keywords": ["customer services officer"], "responsibilities": ["account opening", "quality", "coordinate with", "procedures", "good relationship", "customer service"], "requirements": {"degrees": ["degree holder"], "majors": ["related disciplines", "finance", "business"], "languages": ["putonghua", "english", "chinese"], "language_level": ["excellent", "good"], "hard_skills": ["problem solving"], "soft_skills": ["problem solving", "communication and interpersonal skills", "tactful", "customer services skills"], "languages_combined": [{"language": "putonghua", "language_level": ["excellent", "good"]}, {"language": "english", "language_level": ["excellent", "good"]}, {"language": "chinese", "language_level": ["excellent", "good"]}]}, "experience_required": {"duration": ["1 year"], "field": ["relevant experience"]}}, {"job_id": "100003009052113", "location_code": "hk", "company": "AVISTA PRO-WIS Risk Advisory Limited", "job_title": "Senior Environmental Consultant (ESG Advisory Services)", "description": "Service: Environmental, Social and Governance (\u201cESG\u201d) Reporting, Sustainability Target Setting, ESG Risk Assessment\nLocation: Hong Kong\n\nJob Description and Responsibilities:\n\nPerform environmental KPI calculation, data analysis and technical research\nPropose environmental management / reduction strategies and deliver such professional advice to clients for follow up actions\nJoin the company team in sustainability research and product development through building know-how, information analysis, benchmarking, market intelligence and solution partnerships\nPerform\u00a0ESG consulting services, conduct ESG benchmarking, ESG due diligence, sustainability strategy development, target setting, carbon management, sustainability rating\nPrepare sustainability/ ESG report and assurance for our clients listed\u00a0in Hong Kong\nAssist in ESG improvement opportunities\u00a0and\u00a0provide value-added recommendations\u00a0\nManage client relationships and consultancy projects in HK, China and overseas.\n\nRequirements:\n\nPractical experience in ESG consulting, sustainability strategy development, target setting, carbon management, sustainability rating\nIn-depth knowledge in climate / environmental science, ESG, TCFD, green building, environmental legislation\nDegree holder in Environmental Studies (Engineering, Science or Management) or related subjects\nLocal or overseas professional qualification(s) preferred (e.g. CEM)\nExcellent command in written and spoken English and Chinese (Cantonese & Mandarin)\nGood team player with the ability to work independently\nExcellent research and analytical skills with attention to detail\nExcellent interpersonal and communication skills with flexibility\nProficiency in computer skills such as word processing, presentation software, data analysis and research documentation;\nTravelling is required\n\nCandidates with more experience will be considered as Assistant Manager\n\nBenefit: We offer attractive remuneration package including a 5-day work week, medical insurance and good career prospect to the suitable candidate.\n\nApplication Procedure: Please send CV with expected salary by clicking \"Apply Now\".\n\nPersonal data will be used for recruitment purpose only.", "employment_types": ["Full Time", "Permanent"], "selling_points": ["ESG consulting, sustainability target setting", "Knowledge in climate/environmental science,TCFD", "More experience will be considered as AM"], "locations": ["Wan Chai"], "categories": ["Accounting", "Consulting", "Banking / Finance", "Financial Services", "Professional Services", "Business Consultancy"], "post_time": "2022-01-17T02:07:37Z", "salary": {"currency": null, "max": null, "min": null, "period": "monthly", "term": null}, "salary_visible": false, "title_keywords": ["senior environmental consultant"], "responsibilities": ["due diligence", "management", "consulting", "analysis", "data analysis", "carbon management", "report"], "requirements": {"degrees": ["degree holder"], "majors": ["science", "engineering"], "languages": ["cantonese", "english", "chinese", "mandarin"], "language_level": ["excellent"], "hard_skills": ["analysis", "word processing", "analytical skills", "computer skills", "documentation"], "soft_skills": ["communication skills", "good team player", "work independently", "presentation", "analytical skills", "attention to detail", "interpersonal"], "languages_combined": [{"language": "cantonese", "language_level": ["excellent"]}, {"language": "english", "language_level": ["excellent"]}, {"language": "chinese", "language_level": ["excellent"]}, {"language": "mandarin", "language_level": ["excellent"]}]}, "experience_required": {"duration": [], "field": ["development", "management", "consulting", "sustainability"]}}, {"job_id": "100003009052670", "location_code": "hk", "company": "Hua Nan Commercial Bank, Ltd.", "job_title": "AML Officer (TM team in Compliance Department)", "description": "Jobs Descriptions\n\u2022\u00a0Conduct transaction monitoring and investigation\n\u2022\u00a0Prepare suspicious transaction reports\n\u2022\u00a0Liaise with business and operations on AML/CFT compliance issues\n\u2022 Deal with\u00a0 name screening and\u00a0 sanction related matters\n\u2022\u00a0Deal with\u00a0 \u00a0the\u00a0 \u00a0affairs\u00a0 \u00a0assigned\u00a0 \u00a0by the\u00a0 \u00a0supervisor\n\u2022\u00a0\u57f7\u884c\u4ea4\u6613\u76e3\u63a7\u53ca\u8abf\u67e5\n\u2022\u00a0\u6e96\u5099\u53ef\u7591\u4ea4\u6613\u5831\u544a\n\u2022\u00a0\u8207\u696d\u52d9\u53ca\u4f5c\u696d\u90e8\u9580\u806f\u7e6b\u95dc\u65bcAML/CFT\u4e4b\u5408\u898f\u4e8b\u5b9c\n\u2022 \u8655\u7406\u540d\u7a31\u6aa2\u6838\u53ca\u5236\u88c1\u6709\u95dc\u4e8b\u52d9\n\u2022\u00a0\u8655\u7406\u4e3b\u7ba1\u4ea4\u8fa6\u7684\u4e8b\u52d9\n\nRequirements\n\u2022\u00a0\u00a0Bachelor Degree holder in Finance, Risk Management, Law, Accounting, Business Administration or related disciplines\n\u2022\u00a0Fresh graduates\u00a0 \u00a0are\u00a0 \u00a0welcome,\u00a0 while\u00a0 \u00a0at least 1 year\u00a0 of banking industry experience\u00a0 will be preferable\n\u2022\u00a0Candidate with EXCEL functional skills will be preferable\n\u2022 Fair knowledge in anti-money laundering related regulations, guidelines and practices\n\u2022\u00a0Good interpersonal communication skills and active working attitude\n\u2022\u00a0Excellent analytical and writing skills\n\u2022\u00a0Great time management and ability to work under pressure\n\u2022\u00a0Proficient in both spoken and written English and Chinese (including Putonghua)\n\u2022\u00a0\u5927\u5b78\u7562\u696d\uff0c\u4e3b\u4fee\u8ca1\u52d9\u3001\u98a8\u7ba1\u3001\u6cd5\u5f8b\u3001\u6703\u8a08\u3001\u5546\u696d\u7ba1\u7406\u7b49\u5b78\u79d1\n\u2022\u00a0\u6b61\u8fce\u61c9\u5c46\u7562\u696d\u751f\uff0c\u60df\u81f3\u5c111\u5e74\u9280\u884c\u696d\u76f8\u95dc\u7d93\u9a57\u8005\u5c07\u512a\u5148\u8003\u616e\n\u2022\u00a0\u5177\u5099EXCEL\u51fd\u6578\u8655\u7406\u80fd\u529b\u8005\u512a\u5148\u8003\u616e\n\u2022\u00a0\u5c0d\u65bcAML\u898f\u7bc4\u3001\u6307\u5f15\u53ca\u5be6\u52d9\u5177\u5099\u5408\u7406\u6c34\u6e96\u7684\u77e5\u8b58\n\u2022\u00a0\u826f\u597d\u7684\u4eba\u969b\u6e9d\u901a\u6280\u5de7\u53ca\u7a4d\u6975\u7684\u5de5\u4f5c\u614b\u5ea6\n\u2022\u00a0\u512a\u79c0\u7684\u5206\u6790\u53ca\u64b0\u5beb\u6280\u5de7\n\u2022\u00a0\u826f\u597d\u6642\u9593\u7ba1\u7406\u80fd\u529b\u53ca\u6297\u58d3\u6027\n\u2022\u00a0\u4e2d\u82f1\u6587\uff08\u5305\u62ec\u666e\u901a\u8a71\uff09\u8b80\u5beb\u6d41\u5229", "employment_types": ["Full Time", "Permanent"], "selling_points": [], "locations": ["Wan Chai"], "categories": ["Banking / Finance", "Retail Banking", "Financial Services", "Risk Management"], "post_time": "2022-01-17T03:40:55Z", "salary": {"currency": null, "max": null, "min": null, "period": "monthly", "term": null}, "salary_visible": false, "title_keywords": ["officer"], "responsibilities": ["aml", "operations", "monitoring", "compliance", "investigation", "reports", "liaise with"], "requirements": {"degrees": ["bachelor degree holder"], "majors": ["risk management", "business administration", "law", "finance", "related disciplines", "accounting"], "languages": ["putonghua", "english", "chinese"], "language_level": ["proficient"], "hard_skills": ["excel", "anti-money laundering", "writing skills"], "soft_skills": ["communication skills", "active", "writing skills", "time management", "interpersonal", "work under pressure"], "languages_combined": [{"language": "putonghua", "language_level": []}, {"language": "english", "language_level": ["proficient"]}, {"language": "chinese", "language_level": ["proficient"]}]}, "experience_required": {"duration": ["at least 1 year"], "field": ["banking industry"]}}, {"job_id": "100003009051749", "location_code": "hk", "company": "", "job_title": "Investment Specialist", "description": "Job Responsibilities\n\nTo receive and execute clients\u2019 orders in bonds, funds and structured products with counterparties;\nTo deal with clients and sales teams to initiate trades and execute trades, including but not limited to rate quotes, repos and other hedging derivatives;\nTo act as a middle office staff to support sales teams in account opening, client onboarding and servicing, and product settlement;\nTo handle trading and price enquiry platforms eg Ayers, Bloomberg, iFast etc;\nJob Requirements\n\nDegree holder with 3 years dealing and operational support experience in financial products (e.g. Bonds, Funds and Structured Products);\nHolder of SFC License for RA1;\nHardworking and keen on learning new knowledge;\nAccurate, detail-minded, responsible and self-motivated;\nA team player with sound communication skills;\nProficiency in both spoken and written English and Chinese (including Mandarin);\nExperience in bank dealing desk is preferable;\nImmediately available is highly preferred\n\nAttractive remuneration will be offered to the right candidate. Interested parties you may call telephone no. 3196 6253 for more details.\n\nPersonal data collected is for recruitment purpose only.", "employment_types": ["Full Time"], "selling_points": [], "locations": ["Central & Western Area"], "categories": ["Banking / Finance", "Financial Services", "Dealing & Trading", "Fund Management"], "post_time": "2022-01-17T00:07:49Z", "salary": {"currency": null, "max": null, "min": null, "period": "monthly", "term": null}, "salary_visible": false, "title_keywords": ["specialist"], "responsibilities": ["account opening", "teams"], "requirements": {"degrees": ["degree holder"], "majors": [], "languages": ["english", "chinese", "mandarin"], "language_level": ["proficiency"], "hard_skills": ["sfc license"], "soft_skills": ["detail-minded", "communication skills", "self-motivated", "accurate", "responsible", "keen", "learning", "team player", "structured", "hardworking"], "languages_combined": [{"language": "english", "language_level": ["proficiency"]}, {"language": "chinese", "language_level": ["proficiency"]}, {"language": "mandarin", "language_level": []}]}, "experience_required": {"duration": ["3 years"], "field": ["financial"]}}, {"job_id": "100003009051621", "location_code": "hk", "company": "MFP Consultant Co.", "job_title": "Customer Service Officer", "description": "A FinTech group is looking for General Manager to join their team. This role will be\u00a0develop action plan for consumer business to improve productivity, make recommendations on modification of procedures and application of technology to enhance operational efficiency and minimize operational risk.\n\nResponsibilities:\n\nFormulate the business plan, corporate strategies and policies according to the group annual objectives, monitoring their implementation and timely report to CEO.\nMonitor the achievement status of KPI\u2019s closely, analyze and make suggestions to different departments and subordinates to improve performance.\nReport the business performance to CEO regularly, adjust business strategies in a timely manner according to the actual operating situation.\nParticipate in thematic meetings in order to discuss the operation matters and development of various projects.\nReview and approve for the staffing plan, performance evaluation and make recommendations based on the result of appraisal.\nEssential to promote and establish a good communication and working atmosphere.\nKeep updated in industry news and local policies, organize various departments to conduct market research and new product development.\nRequirements:\n\nBachelor degree or above, majoring in Business Administration, Finance, Economics, or the relevant\n10 years or above working experience in Finance companies or banks; preferably the relevant experience in running mortgage and unsecured personal loan business\n\u00a0At least 5 years role as senior executive position of Finance companies or banks\nFamiliar with the financial market crossing Mainland and Hong Kong, good connections with target clients, strong financial business development capability\nCompetence in FinTech is necessary; Sales-oriented with strong marketing skills\nExcellent team management capability and cross-cultural communication and coordination capability\nGood computer skills and experienced in MS Office applications\nFluent in written and spoken English & Mandarin\nActive and Open-minded; Process work in a timely, punctual manner\n\nApply for this job:\n\nInterested candidate please CLICK apply button to apply online or send your resume in MS word format to Fillture Group Limited\n\nFor more information, please contact\u00a0Danvis Lau\u00a0+852 2814 9388.\n\nPlease note that only shortlisted candidate will be notified. All information will be treated in strict confidence and solely used for recruitment purposes.", "employment_types": ["Full Time", "Permanent", "Internship"], "selling_points": ["-Customer relations \u2013 Sales & Support", "-Minimum 1 year working experience", "-Attractive income"], "locations": ["Quarry Bay"], "categories": ["Banking / Finance", "Financial Services", "Marketing / Public Relations", "Public Relations - General / Support", "Sales, CS & Business Devpt", "Retail Sales"], "post_time": "2022-01-16T15:11:01Z", "salary": {"currency": "HKD", "max": 29999, "min": 17000, "period": "monthly", "term": null}, "salary_visible": true, "title_keywords": ["customer service officer"], "responsibilities": ["make recommendations", "policies", "conduct market research", "monitoring", "monitor", "implementation", "a timely manner", "review", "communication", "plan", "evaluation", "business plan", "report"], "requirements": {"degrees": ["degree or above", "bachelor"], "majors": ["finance", "economics", "business administration"], "languages": ["english", "mandarin"], "language_level": ["fluent"], "hard_skills": ["ms word", "marketing skills", "computer skills", "ms office"], "soft_skills": ["confidence", "open-minded", "timely", "communication", "coordination", "active"], "languages_combined": [{"language": "english", "language_level": ["fluent"]}, {"language": "mandarin", "language_level": ["fluent"]}]}, "experience_required": {"duration": ["10 years"], "field": ["loan business", "finance", "relevant experience"]}}, {"job_id": "100003009051622", "location_code": "hk", "company": "MFP Consultant Co.", "job_title": "Customer Service Manager", "description": "Main Responsibilities\n\nAssist Relationship Managers in delivering quality wealth management services to company existing high-net-worth clients\nBuild and maintain stable and long term relationship with existing clients\nUnderstand clients' investment needs and proactively identify new business opportunities by providing professional investment advice\nGrow revenues and AUM by working closely with product development specialist\nOffer professional services in promoting products in compliance with sales process policy and procedure\u00a0\n\nBasic requirements\n\nBachelor degree in Finance, Accounting or relevant discipline is preferred\n1 years of experience as a Sales / CS role in banking and finance industry\nPass in HKSI Type 1 Licensing Examination is a preferred\nProactive, mature, independent, self-initiative, sales-driven, client-focused\nExcellent interpersonal, persuasive and communication skills\nTitle would be adjusted based on candidate's relevant experience", "employment_types": ["Full Time", "Permanent"], "selling_points": ["-Customer relations \u2013 Sales & Support", "-Minimum 3 year working experience", "-Attractive income"], "locations": ["Quarry Bay"], "categories": ["Banking / Finance", "Financial Services", "Marketing / Public Relations", "Public Relations - General / Support", "Sales, CS & Business Devpt", "Retail Sales"], "post_time": "2022-01-16T15:15:42Z", "salary": {"currency": null, "max": null, "min": null, "period": "monthly", "term": null}, "salary_visible": false, "title_keywords": ["customer service manager"], "responsibilities": ["management", "business opportunities", "compliance", "quality", "maintain"], "requirements": {"degrees": ["degree", "bachelor"], "majors": ["finance", "accounting"], "languages": [], "language_level": [], "hard_skills": ["basic", "hksi"], "soft_skills": ["communication skills", "independent", "persuasive", "focused", "interpersonal", "mature", "self-initiative", "proactive", "driven"], "languages_combined": []}, "experience_required": {"duration": ["1 years"], "field": ["relevant experience", "cs", "finance industry", "banking"]}}, {"job_id": "100003009054764", "location_code": "hk", "company": "Fillture Group Limited", "job_title": "General Manager - FinTech", "description": "Job Responsibilities\n\n\nPerform a checker role on customer due diligence and ongoing monitoring for Octopus wallet and merchant customers (tasks including on boarding, name screening,trigger event review, etc.)\nProvide supervision and guidance to junior staff so as to improve the quality of deliverables\nConduct regular high-risk review to existing customers (both individuals and merchants)and trigger event reviews (where necessary)\nGather relevant information and prepare regular reports for management review and for regulatory reporting\nContribute to the review, standardization and rollout of policies, procedures, processes and systems if necessary\nPerform ad-hoc tasks as assigned by the management and assist other team members where necessary\nRequirements\n\n\nDegree holder preferably in Risk Management, Engineering or Computer Science discipline\nAt least 3years of relevant experience in financial services industry with sound experience in AML Compliance\nKnowledgeable in Payment Systems and Stored Value Facilities Ordinance/Banking Ordinance and HKMA\u2019s AML Guideline is a plus\nProficient in MS PowerPoint,Word and Excel (hands-on experience in MS Excel functions e.g. Pivot tables, VLOOKUP etc. is an advantage)\nAttentive to details and multi-tasking\nQuick learner and proactive with can-do attitude\nAble to provide quality work under tight schedule and minimal supervision\nGood communication, interpersonal and problem-solving skills\nGood command of written and spoken English and Chinese\n\nWe offer successful candidate an attractive remuneration package and excellent career prospects. Interested parties please send your resume, present and expected salary, contact details and quoting the reference number by clicking \"Apply Now\"Visit our web site:\u00a0http://www.octopus.com.hk/\n\nThe personal data collected will be used for recruitment purposes only. If you are not contacted by us within six weeks, you may consider your application unsuccessful. Personal data with an unsuccessful applicant will be destroyed 12 months after rejection of the application. During this retention period, you have the right to request for correction or destruction of your personal data at any time. Any request for the correction or destruction of personal data should be addressed in writing to our Human Resources & Administration Department.\n\nOctopus is an equal opportunity employer and all employment decisions and Human Resources policies are administered; especially those relating to recruitment & selection, compensation & benefits, promotion & transfer, training & development and termination & redundancy; without discrimination on the basis of age, race, colour, religion, sex, national origin, marital status, pregnancy, physical and mental disability and family status but on genuine occupational qualification, job performance, employees\u2019 ability and internal/ external relativities.", "employment_types": ["Full Time", "Permanent"], "selling_points": ["FinTech Company", "Experienced in consumer loans", "Attractive Salary Package and Benefits"], "locations": ["Central & Western Area"], "categories": ["Banking / Finance", "Loan", "Financial Services", "Management", "General Management"], "post_time": "2022-01-17T10:58:45Z", "salary": {"currency": null, "max": null, "min": null, "period": "monthly", "term": null}, "salary_visible": false, "title_keywords": ["general manager"], "responsibilities": ["guidance", "reporting", "management", "policies", "ad-hoc tasks", "review", "monitoring", "quality", "provide supervision", "procedures", "systems", "customer due diligence", "regular reports for management"], "requirements": {"degrees": ["degree holder"], "majors": ["risk management", "engineering", "computer science"], "languages": ["english", "chinese"], "language_level": ["good command"], "hard_skills": ["excel", "plus", "aml", "hkma", "vlookup", "word", "ms excel", "problem-solving skills", "ms powerpoint"], "soft_skills": ["attentive to details", "can-do attitude", "quick learner", "communication", "multi-tasking", "hands-on", "problem-solving skills", "proactive", "interpersonal"], "languages_combined": [{"language": "english", "language_level": ["good command"]}, {"language": "chinese", "language_level": ["good command"]}]}, "experience_required": {"duration": [], "field": ["financial services industry", "compliance", "relevant experience"]}}, {"job_id": "100003009051298", "location_code": "hk", "company": "Hang Tang International Capital Management Limited", "job_title": "Client Services Officer / Senior Client Services Officer", "description": "Service: Business Valuation\nLocation: Hong Kong\n\nScope:\n\nWe are looking for fresh graduates to join our expanding business valuation team of our Hong Kong office. Our analysts will have the opportunities to have a wide range of exposure to various industries of our listed and unlisted clients for different valuation needs. Our business valuation services include:\n\nPerforming valuations for financial reporting purposes, such as equity investments, tangible & intangible assets and financial instruments valuations)\nProviding valuations for transaction purposes such as potential acquisitions and disposals of businesses\nAdvising companies and stakeholders in relation to valuation related matters\n\nResponsibilities:\n\nAnalysts will work as a team in general, with our director, managers and other senior analysts. You are expected to:\n\nAnalyze historical and forecasted financial information provided by clients\nConduct research on comparable financial data and other project-related business and industry information\nProvide assistance to senior colleagues in constructing valuation models and compiling valuation reports\nPrepare valuation analysis and supporting information for discussions and negotiations with clients and other stakeholders involved\nAssist in preparing proposals and presentation materials for potential valuation and consulting leads\nBuild relationships and conduct direct contacts with existing and prospective clients as well as other professional teams (such as sponsors, auditors, financial advisors, lawyers, etc.)\n\nRequirements:\n\nUniversity graduates in all disciplines, preferable with finance and/or accounting degree\nSelf-motivated team player with the ability to work independently in a fast-paced environment\nProficiency in both verbal and written English, Cantonese and Mandarin is essential\nDemonstrate interest in business valuation\nStrong research, financial modeling and financial analytical skills\nExcellent interpersonal and communication skills\nExperience in valuation related fields is a plus\nShort business trips to PRC may be required\n\nBenefits: We offer attractive remuneration package including a 5-day work week, medical insurance and good career prospect to the suitable candidate.\n\nApplication Procedure: Please send your CV with expected salary by clicking \"Apply Now\".\n\nPersonal data will be used for recruitment purpose only.", "employment_types": ["Full Time"], "selling_points": ["Good career path", "Year end bonus", "Asset management"], "locations": ["Central"], "categories": ["Banking / Finance", "Investment", "Financial Services", "Asset Management"], "post_time": "2022-01-15T07:25:41Z", "salary": {"currency": null, "max": null, "min": null, "period": "monthly", "term": null}, "salary_visible": false, "title_keywords": ["client services officer"], "responsibilities": ["valuation", "consulting", "data", "analysis", "teams", "reports", "provide assistance", "conduct research"], "requirements": {"degrees": ["degree"], "majors": ["finance", "accounting"], "languages": ["cantonese", "english", "mandarin"], "language_level": ["proficiency"], "hard_skills": ["plus", "financial analytical skills"], "soft_skills": ["communication skills", "self-motivated", "work independently", "fast-paced environment", "analytical skills", "team player", "interpersonal"], "languages_combined": [{"language": "cantonese", "language_level": ["proficiency"]}, {"language": "english", "language_level": ["proficiency"]}, {"language": "mandarin", "language_level": ["proficiency"]}]}, "experience_required": {"duration": [], "field": ["related"]}}, {"job_id": "100003009051928", "location_code": "hk", "company": "Octopus Holdings Limited", "job_title": "AML Compliance Specialist (1-year contract) REF: OCL/RMC/2021-210", "description": "I. KEY OBJECTIVES FOR THE ROLE\n\n\n\nThe Research Analyst/Senior Research Analyst will be responsible for performing fundamental credit analysis for IG corporates. The analyst is expected to provide accurate and timely credit analysis and provide investment recommendations. The analyst will also be assigned sector and/or regional coverage. Depending on the skill set and experience of the individual, there may be flexibility for the coverage responsibilities. The goal is for the analyst to be the in-house expert in his or her area of coverage. The analyst is also expected to be collaborative and work as part of a team of research analysts and portfolio managers. The successful candidate will be a self-starter, be able to take on responsibilities and projects as needed and serve as a mentor for more junior team members.\n\nII. KEY RESPONSIBILITIES\u00a0\n\nPerform fundamental credit analysis and valuations for IG credits in various sectors.\nPublish credit reports and provide investment recommendations.\nPerform industry reviews and discuss sector outlook and strategy.\nMonitor existing holdings and internal research databases.\nActively participate in roadshow/conferences/issuer meetings.\u00a0\n\nIII. QUALIFICATIONS\n\n\n\nBachelor\u2019s degree required, masters and/or CFA desirable.\n5-10 years of proven experience in Corporate Credit Analysis, in either the IG or HY space, either the buy or sell side. Experience at an established institution are viewed favorably but not required.\nStrong credit/financial analysis skills and solid understanding of market dynamics.\nSuperior oral and written communication skills with the ability to clearly and concisely communicate investment recommendations both verbally and in writing.\nStrong team player who is able to help with special projects/initiatives as needed.\nAbility to work in a fast paced and changing environment.\nStrong computer and data management skills.\nFluency in Mandarin preferred.", "employment_types": ["Contract"], "selling_points": ["Provide supervision and guidance to junior staff", "Degree holder preferably in Risk Management", "At least 3 years of relevant experience"], "locations": ["Kowloon Bay"], "categories": ["Banking / Finance", "Financial Services", "Professional Services", "Legal & Compliance", "Risk Management"], "post_time": "2022-01-17T01:32:42Z", "salary": {"currency": null, "max": null, "min": null, "period": "monthly", "term": null}, "salary_visible": false, "title_keywords": ["specialist", "aml compliance"], "responsibilities": ["management", "data", "analysis", "monitor", "financial analysis", "communication", "conferences", "reports", "databases"], "requirements": {"degrees": ["degree", "bachelor"], "majors": [], "languages": ["mandarin"], "language_level": ["fluency"], "hard_skills": ["data management", "cfa", "financial analysis", "goal", "outlook", "databases", "credit analysis", "hy"], "soft_skills": ["communication skills", "oral", "responsible", "timely", "collaborative", "team player", "accurate", "superior"], "languages_combined": [{"language": "mandarin", "language_level": ["fluency"]}]}, "experience_required": {"duration": ["5-10 years"], "field": []}}, {"job_id": "100003009052099", "location_code": "hk", "company": "AVISTA Valuation Advisory Limited", "job_title": "Analyst (2021 / 2022 Graduate Position)", "description": "Job Responsibilities:\u00a0 \u00a0\nDemonstrate commitment to regulatory requirements and guidelines with a high level of ethical standard\nPerform\u00a0 day-to-day\u00a0 customer\u00a0 due\u00a0 diligence\u00a0 checking/review/approval\u00a0 (e.g.\u00a0 data\u00a0 input,\u00a0 name screening, company search, risk assessment of customers, reviewing supporting documents of application for Octopus Wallet account and merchant businesses, etc) according to the established procedures and guidelines\nConduct and coordinate periodic review for accounts with higher risk level\nPrepare regular reports with analysis for management reporting\nPerform ad-hoc tasks as assigned\nJob Requirements:\nUniversity Degree holder in Accounting, Information Technology or related disciplines is a plus. Fresh graduates will also be considered\nRelevant work experience in financial services industry is a plus\nProficient in MS Excel and MS Word\nAttentive to details with strong analytical skills \u00a0\nSelf-starter with integrity\nSensitive to numbers with a high level of accuracy\nGood communication skills and interpersonal skills for handling internal and external parties\nProactive with can-do attitude\nImmediately available or in short-notice period candidate is a plus\nWe offer successful candidate an attractive remuneration package and excellent career prospects. Interested parties please send your resume, present and expected salary, contact details and quoting the reference number by clicking \"Apply Now\"\n\nVisit our web site:\u00a0http://www.octopus.com.hk/\nPersonal data collected will be used for recruitment purpose only. If you are not contacted within six weeks, you may consider your application unsuccessful. Our Company will retain your application for a maximum of one year.\n\nOctopus is an equal opportunity employer and all employment decisions and Human Resources policies are administered; especially those relating to recruitment & selection, compensation & benefits, promotion & transfer, training & development and termination & redundancy; without discrimination on the basis of age, race, colour, religion, sex, national origin, marital status, pregnancy, physical and mental disability and family status but on genuine occupational qualification, job performance, employees\u2019 ability and internal/ external relativities.", "employment_types": ["Full Time", "Permanent"], "selling_points": ["Valuations for financial reporting and transaction", "Analyze historical and forecasted financial info", "Fresh graduates are welcome"], "locations": ["Wan Chai"], "categories": ["Accounting", "Financial Analyst", "Banking / Finance", "Analyst", "Financial Services"], "post_time": "2022-01-17T02:05:32Z", "salary": {"currency": null, "max": null, "min": null, "period": "monthly", "term": null}, "salary_visible": false, "title_keywords": ["analyst"], "responsibilities": ["data", "guidelines", "regulatory requirements", "analysis", "review", "procedures", "checking", "ad-hoc tasks", "coordinate", "reports", "management reporting", "company search"], "requirements": {"degrees": ["university degree"], "majors": ["related disciplines", "accounting", "information technology"], "languages": [], "language_level": [], "hard_skills": ["plus", "ms excel", "analytical skills", "ms word"], "soft_skills": ["communication skills", "attentive to details", "can-do attitude", "integrity", "analytical skills", "interpersonal skills", "sensitive to numbers", "proactive"], "languages_combined": []}, "experience_required": {"duration": [], "field": ["financial services industry"]}}, {"job_id": "100003009053072", "location_code": "hk", "company": "Taiping Financial Holdings Company Limited", "job_title": "Fixed Income - Research Analyst/Senior Research Analyst", "description": "RESPONSIBILITIES\n\nIdentifies and cultivates prospects and/or clients.\nInitiates and follows up on new business opportunities.\nLeads new business meetings and closes sales to institutional investors.\nLeverages the organization\u2019s relationship with existing institutional accounts by developing and executing proactive, creative, and ongoing contact initiatives.\nDevelops and maintains relationships clients.\nActs as a liaison to the group companies to ensure active, enthusiastic support of the sales and marketing process.\n\n\u00a0REQUIREMENTS\n\nBachelor\u2019s degree or above in Finance, Economics, or related disciplines\nAbove 5 years experience in sales, client relationship or business development in equity market for Institution Sales in Securities Brokerage firm.\nFamiliar with hedge funds & other trading house\nFluent in both written and spoken Cantonese, Mandarin and English.\n\n\u00a0A competitive remuneration package will be offered. Please send your detailed resume, including present and expected salary as well as availability date, to Human Resources Department, SinoPac Securities (Asia) Limited, 7/F., Lee Garden Three, 1 Sunning Road, Causeway Bay, Hong Kong or by clicking \u201cApply Now\u201d.\n\nAll personal data collected will be used for recruitment purpose only and will be kept strictly confidential. Only short-listed candidates will be notified.", "employment_types": ["Full Time", "Permanent"], "selling_points": [], "locations": ["Tin Hau"], "categories": ["Banking / Finance", "Analyst", "Financial Services", "Others"], "post_time": "2022-01-17T05:35:29Z", "salary": {"currency": null, "max": null, "min": null, "period": "monthly", "term": null}, "salary_visible": false, "title_keywords": ["research analyst"], "responsibilities": ["contact", "business opportunities", "executing", "developing"], "requirements": {"degrees": ["degree or above", "bachelor"], "majors": ["related disciplines", "finance", "economics"], "languages": ["cantonese", "english", "mandarin"], "language_level": ["fluent"], "hard_skills": [], "soft_skills": ["detailed"], "languages_combined": [{"language": "cantonese", "language_level": ["fluent"]}, {"language": "english", "language_level": ["fluent"]}, {"language": "mandarin", "language_level": ["fluent"]}]}, "experience_required": {"duration": ["5 years"], "field": ["business development", "securities brokerage"]}}, {"job_id": "100003009051927", "location_code": "hk", "company": "Octopus Holdings Limited", "job_title": "AML Compliance Assistant, CDD & Monitoring (1-year) Ref: OCL/RMC/2021-132", "description": "Key Responsibilities:\u00a0\n\nHandle daily on-boarding and periodic file reviews of client due diligence (\u201cCDD\u201d) matters in various onshore and offshore jurisdictions\nConduct research from public information system to collect and verify due diligence information\nManage and mentor a team of junior staff (both in HK & Foshan), provide guidance and assistance on handling complicated cases and daily operations of the Client Acceptance Team\nReview due diligence information supplied by client and conduct client risk assessments\nCommunicate closely with business on CDD requirements and attend to client enquiries\nIdentify and escalate CDD issues to Business and Group Compliance where necessary\nMaintain and update the Group\u2019s Customer Due Diligence Information System\nProvide advice on the development and implementation of compliance policies, procedures and monitoring programs on AML related activities, compliance manual and core control documents that meet regulatory requirements\nImplement and maintain Group\u2019s Compliance Policies & Procedures\nHandle any ad hoc duties as assigned\nKey Requirements:\n\nDegree\u00a0holder\u00a0in Business Law, Law, Finance or related discipline\n1 - 2 years of relevant compliance experience in handling KYC / CDD functions for corporate clients / accounts\u00a0\nA good team player with good communications skill\u00a0\nKnowledge in offshore regulatory (such as BVI, Cayman etc.) will be advantage\u00a0\nCustomer oriented with professional client services manner\u00a0\nProficiency in MS Office applications\nExcellent communication skills with fluency in written and spoken English and Chinese (including Mandarin)", "employment_types": ["Full Time", "Contract"], "selling_points": ["Day-to-day  customer  due  diligence  checking", "University Degree holder in Accounting", "Relevant work experience in financial services"], "locations": ["Kowloon Bay"], "categories": ["Banking / Finance", "Analyst", "Financial Services", "Professional Services", "Legal & Compliance"], "post_time": "2022-01-17T01:32:41Z", "salary": {"currency": null, "max": null, "min": null, "period": null, "term": null}, "salary_visible": false, "title_keywords": ["assistant", "aml compliance"], "responsibilities": ["ad hoc duties", "due diligence", "control", "aml", "cdd", "policies", "review", "compliance", "implementation", "procedures", "monitoring", "regulatory requirements", "customer due diligence", "daily operations", "maintain", "provide advice", "provide guidance", "conduct research"], "requirements": {"degrees": ["degree holder"], "majors": ["finance", "business", "law"], "languages": ["english", "chinese", "mandarin"], "language_level": ["fluency", "excellent"], "hard_skills": ["cdd", "ms office", "kyc"], "soft_skills": ["communication skills", "good team player"], "languages_combined": [{"language": "english", "language_level": ["fluency", "excellent"]}, {"language": "chinese", "language_level": ["fluency", "excellent"]}, {"language": "mandarin", "language_level": ["fluency", "excellent"]}]}, "experience_required": {"duration": ["1 - 2 years"], "field": ["compliance"]}}, {"job_id": "100003009054236", "location_code": "hk", "company": "SinoPac Securities (Asia) Limited", "job_title": "Vice President, Institutional Sales", "description": "HGC Investment Management\n\nHGC is an asset management arm of a major immigration related investment group with a large pool of HWN clients. HGC\u2019s AUM is in excess of US 1 billion dollars. It has established EAM relationship with private banks and financial institutions in Hong Kong and Singapore to offer clients both discretional and advisory investment services. We offer full range of financial products plus a full spectrum of alternative products covering insurance, immigration, PE investments, Pre-IPOs and properties. Headquartered in Beijing and with offices in HK, Shanghai and Singapore. HGC Hong Kong is licensed by the Securities and Futures Commission in Hong Kong in Type 1, 4 & 9 activities.\n\nFamily Office Partner & Executives\n\nWe welcome financial professionals with insurance and investment advisory background to join us as a partner to help develop our wealth management business. We operate attractive profit sharing arrangement for our business partners. Successful candidates will allow access to group company HNW client base to explore new business potentials.\n\nRequirements\n\n\nBachelor degree in Finance, Accounting or relevant discipline\nKnowledge in investment consultancy, financial product sales or insurance agency\nExtensive experience in handling and maintaining client relationship\nExcellent interpersonal and communication skills\n\nInterested parties please send your full resume, with contact telephone number by clicking APPLY NOW quoting the post applied. All information received will be kept in strict confidence and only for employment-related purpose.\n", "employment_types": ["Full Time", "Permanent"], "selling_points": ["5-days work", "Bachelor\u2019s degree", "Hedge funds & other trading house"], "locations": ["Causeway Bay"], "categories": ["Banking / Finance", "Investment", "Financial Services", "Wealth Management"], "post_time": "2022-01-17T08:52:50Z", "salary": {"currency": null, "max": null, "min": null, "period": "monthly", "term": null}, "salary_visible": false, "title_keywords": ["vice president", "sales"], "responsibilities": ["management", "maintaining", "develop", "communication", "client base", "insurance", "asset management"], "requirements": {"degrees": ["degree", "bachelor"], "majors": ["finance", "accounting"], "languages": [], "language_level": [], "hard_skills": ["plus", "pe"], "soft_skills": ["communication skills", "extensive", "interpersonal"], "languages_combined": []}, "experience_required": {"duration": [], "field": []}}, {"job_id": "100003009049131", "location_code": "hk", "company": "HGC Investment Management (HK) Limited", "job_title": "Wealth Management Partner & Executives", "description": "Our client is a fast-expanding fintech and securities brokerage platform. We are looking for a Business Development Manager to drive the business expansion.\n\nResponsibilities\n\nLead and build the sales team to achieve target for fintech products\nIdentify and reach out to institutional client leads in brokerage industry\nDefine target market segments, locate and reach target market\nManage the entire Sales Cycle from product introduction to contract negotiation\nEstablish and maintain valuable business relationships\nKeep track of client feedback and recommend product improvements\nRequirements\n\n3-8 years\u2019 working experience, team management exposure is an advantage\nStrong business connections with financial institutions\nIn-depth understanding of financial systems and client needs\nFamiliar with business directions and specific business operation processes\nExcellent negotiation and communication skills\u00a0\nGood written and verbal Chinese (both Cantonese & Mandarin) and English", "employment_types": ["Full Time", "Part Time", "Freelance"], "selling_points": ["Wealth management and investment advisory", "Knowledgeable in financial products", "Attention to clients' investment needs"], "locations": ["Central"], "categories": ["Banking / Finance", "Private Banking", "Financial Services"], "post_time": "2022-01-17T07:26:29Z", "salary": {"currency": null, "max": null, "min": null, "period": "monthly", "term": null}, "salary_visible": false, "title_keywords": ["wealth management"], "responsibilities": ["brokerage", "maintain", "sales team"], "requirements": {"degrees": [], "majors": [], "languages": ["cantonese", "english", "chinese", "mandarin"], "language_level": ["good"], "hard_skills": [], "soft_skills": ["communication skills", "negotiation"], "languages_combined": [{"language": "cantonese", "language_level": ["good"]}, {"language": "english", "language_level": ["good"]}, {"language": "chinese", "language_level": ["good"]}, {"language": "mandarin", "language_level": ["good"]}]}, "experience_required": {"duration": ["3-8 years"], "field": ["management", "team"]}}, {"job_id": "100003009054759", "location_code": "hk", "company": "Public Finance Limited", "job_title": "Assistant Manager(s) (Branch Operations)", "description": "Duties\n\nProcess, check, validate and maintain client data and related administrative and fundamental accounting activities to ensure full compliance with rules and regulations.\n\nChecking and validating bank records\nProcess cash in and cash out transactions\nPerform new client account setup\nMaintain client account records and data\nPerform settlement administrative duties including data input, report printing, filing\nCommunicate with internal parties and external parties\nEnsure full compliance in accordance with rules and regulations\nRaise any irregularities or concerns regarding clients and compliance immediately\nOther ad-hoc projects as assigned\nAny other duties as instructed as required\n\nSkills\n\nExperience with back-office system iBoss or similar back office supporting system\nNumerate proficient or some accounting experience or similar\nProficient in MS Office and Chinese word processing\nExperience in the financial industry is an advantage\nFamiliar with regulatory and compliance requirements\nGood command in written and spoken English, Chinese and Mandarin\n\nCompetencies\n\nHigh level of professionalism and positive attitude\nGood verbal, communication and interpersonal skills\nObservant and has attention to detail\nMotivated, organized and efficient\nCapable of adapting to a fast-paced environment\nMust be a team player and maintain confidentiality\nRetirees and part-timers welcome to apply\u00a0\n\nCandidate with less experience will be considered as Office Assistant\n", "employment_types": ["Full Time", "Permanent"], "selling_points": [], "locations": ["Not Specified"], "categories": ["Banking / Finance", "Financial Services", "Sales, CS & Business Devpt", "Customer Service - Manager", "Direct Sales"], "post_time": "2022-01-17T10:57:06Z", "salary": {"currency": null, "max": null, "min": null, "period": "monthly", "term": null}, "salary_visible": false, "title_keywords": ["operations", "assistant"], "responsibilities": ["regulations", "any other duties", "irregularities", "data", "compliance", "external parties", "checking", "transactions", "data input", "back office", "communication", "maintain", "administrative duties", "communicate with internal parties", "ad-hoc projects", "setup", "report"], "requirements": {"degrees": [], "majors": [], "languages": ["english", "chinese", "mandarin"], "language_level": ["good command", "proficient"], "hard_skills": ["chinese word processing", "ms office"], "soft_skills": ["efficient", "organized", "capable", "fast-paced environment", "positive attitude", "communication and interpersonal skills", "motivated", "attention to detail", "team player"], "languages_combined": [{"language": "english", "language_level": ["good command"]}, {"language": "chinese", "language_level": ["good command", "proficient"]}, {"language": "mandarin", "language_level": ["good command"]}]}, "experience_required": {"duration": [], "field": ["accounting experience", "financial industry"]}}, {"job_id": "100003009048191", "location_code": "hk", "company": "Vistra (Hong Kong) Limited", "job_title": "Associate, Client Acceptance (KYC / CDD)", "description": "Key Responsibilities:\u00a0\n\nHandle daily on-boarding and periodic file reviews of client due diligence (\u201cCDD\u201d) matters in various onshore and offshore jurisdictions\nConduct research from public information system to collect and verify due diligence information\nManage and mentor a team of junior staff (both in HK & Foshan), provide guidance and assistance on handling complicated cases and daily operations of the Client Acceptance Team\nReview due diligence information supplied by client and conduct client risk assessments\nCommunicate closely with business on CDD requirements and attend to client enquiries\nIdentify and escalate CDD issues to Business and Group Compliance where necessary\nMaintain and update the Group\u2019s Customer Due Diligence Information System\nProvide advice on the development and implementation of compliance policies, procedures and monitoring programs on AML related activities, compliance manual and core control documents that meet regulatory requirements\nImplement and maintain Group\u2019s Compliance Policies & Procedures\nHandle any ad hoc duties as assigned\nKey Requirements:\n\nDegree\u00a0holder\u00a0in Business Law, Law, Finance or related discipline\n1 - 2 years of relevant compliance experience in handling KYC / CDD functions for corporate clients / accounts\u00a0\nA good team player with good communications skill\u00a0\nKnowledge in offshore regulatory (such as BVI, Cayman etc.) will be advantage\u00a0\nCustomer oriented with professional client services manner\u00a0\nProficiency in MS Office applications\nExcellent communication skills with fluency in written and spoken English and Chinese (including Mandarin)", "employment_types": ["Full Time", "Permanent"], "selling_points": ["Handle KYC / CDD function for corporate clients", "Exposure to offshore jurisdictions regulations", "Good communications and interpersonal skills"], "locations": ["Causeway Bay"], "categories": ["Banking / Finance", "Financial Services", "Professional Services", "Legal & Compliance"], "post_time": "2022-01-14T05:49:18Z", "salary": {"currency": null, "max": null, "min": null, "period": "monthly", "term": null}, "salary_visible": false, "title_keywords": ["associate"], "responsibilities": ["ad hoc duties", "due diligence", "control", "aml", "cdd", "policies", "review", "compliance", "implementation", "procedures", "monitoring", "regulatory requirements", "customer due diligence", "daily operations", "maintain", "provide advice", "provide guidance", "conduct research"], "requirements": {"degrees": ["degree holder"], "majors": ["finance", "business", "law"], "languages": ["english", "chinese", "mandarin"], "language_level": ["fluency", "excellent"], "hard_skills": ["cdd", "ms office", "kyc"], "soft_skills": ["communication skills", "good team player"], "languages_combined": [{"language": "english", "language_level": ["fluency", "excellent"]}, {"language": "chinese", "language_level": ["fluency", "excellent"]}, {"language": "mandarin", "language_level": ["fluency", "excellent"]}]}, "experience_required": {"duration": ["1 - 2 years"], "field": ["compliance"]}}, {"job_id": "100003009053006", "location_code": "hk", "company": "Talentquest HR Limited", "job_title": "Business Development Manager, Fintech", "description": "Our client is a fast-expanding fintech and securities brokerage platform. We are looking for a Business Development Manager to drive the business expansion.\n\nResponsibilities\n\nLead and build the sales team to achieve target for fintech products\nIdentify and reach out to institutional client leads in brokerage industry\nDefine target market segments, locate and reach target market\nManage the entire Sales Cycle from product introduction to contract negotiation\nEstablish and maintain valuable business relationships\nKeep track of client feedback and recommend product improvements\nRequirements\n\n3-8 years\u2019 working experience, team management exposure is an advantage\nStrong business connections with financial institutions\nIn-depth understanding of financial systems and client needs\nFamiliar with business directions and specific business operation processes\nExcellent negotiation and communication skills\u00a0\nGood written and verbal Chinese (both Cantonese & Mandarin) and English", "employment_types": ["Full Time", "Permanent"], "selling_points": ["Fast-growing fintech platform", "Passionate in driving new business growth", "Securities Trading, Settlement, ESOP systems"], "locations": ["Admiralty"], "categories": ["Banking / Finance", "Financial Services", "Sales, CS & Business Devpt", "Business Development", "Sales - Sales Management"], "post_time": "2022-01-17T04:59:41Z", "salary": {"currency": null, "max": null, "min": null, "period": "monthly", "term": null}, "salary_visible": false, "title_keywords": ["business development manager"], "responsibilities": ["brokerage", "maintain", "sales team"], "requirements": {"degrees": [], "majors": [], "languages": ["cantonese", "english", "chinese", "mandarin"], "language_level": ["good"], "hard_skills": [], "soft_skills": ["communication skills", "negotiation"], "languages_combined": [{"language": "cantonese", "language_level": ["good"]}, {"language": "english", "language_level": ["good"]}, {"language": "chinese", "language_level": ["good"]}, {"language": "mandarin", "language_level": ["good"]}]}, "experience_required": {"duration": ["3-8 years"], "field": ["management", "team"]}}, {"job_id": "100003009054889", "location_code": "hk", "company": "Magpie Securities Limited", "job_title": "Client Data Maintenance Officer / Office Assistant", "description": "Duties\n\nProcess, check, validate and maintain client data and related administrative and fundamental accounting activities to ensure full compliance with rules and regulations.\n\nChecking and validating bank records\nProcess cash in and cash out transactions\nPerform new client account setup\nMaintain client account records and data\nPerform settlement administrative duties including data input, report printing, filing\nCommunicate with internal parties and external parties\nEnsure full compliance in accordance with rules and regulations\nRaise any irregularities or concerns regarding clients and compliance immediately\nOther ad-hoc projects as assigned\nAny other duties as instructed as required\n\nSkills\n\nExperience with back-office system iBoss or similar back office supporting system\nNumerate proficient or some accounting experience or similar\nProficient in MS Office and Chinese word processing\nExperience in the financial industry is an advantage\nFamiliar with regulatory and compliance requirements\nGood command in written and spoken English, Chinese and Mandarin\n\nCompetencies\n\nHigh level of professionalism and positive attitude\nGood verbal, communication and interpersonal skills\nObservant and has attention to detail\nMotivated, organized and efficient\nCapable of adapting to a fast-paced environment\nMust be a team player and maintain confidentiality\nRetirees and part-timers welcome to apply\u00a0\n\nCandidate with less experience will be considered as Office Assistant\n", "employment_types": ["Full Time", "Part Time"], "selling_points": ["Client Data Maintenance", "Office Assistant", "Securities settlement"], "locations": ["Causeway Bay"], "categories": ["Banking / Finance", "Financial Services", "Others", "Order Processing & Operation / Settlement"], "post_time": "2022-01-17T12:52:42Z", "salary": {"currency": null, "max": null, "min": null, "period": "monthly", "term": null}, "salary_visible": false, "title_keywords": ["office assistant", "maintenance officer"], "responsibilities": ["regulations", "any other duties", "irregularities", "data", "compliance", "external parties", "checking", "transactions", "data input", "back office", "communication", "maintain", "administrative duties", "communicate with internal parties", "ad-hoc projects", "setup", "report"], "requirements": {"degrees": [], "majors": [], "languages": ["english", "chinese", "mandarin"], "language_level": ["good command", "proficient"], "hard_skills": ["chinese word processing", "ms office"], "soft_skills": ["efficient", "organized", "capable", "fast-paced environment", "positive attitude", "communication and interpersonal skills", "motivated", "attention to detail", "team player"], "languages_combined": [{"language": "english", "language_level": ["good command"]}, {"language": "chinese", "language_level": ["good command", "proficient"]}, {"language": "mandarin", "language_level": ["good command"]}]}, "experience_required": {"duration": [], "field": ["accounting experience", "financial industry"]}}, {"job_id": "100003009054887", "location_code": "hk", "company": "Manulife (International) Limited", "job_title": "*Urgent* Financial Planning Manager \u7406\u8ca1\u7b56\u5283\u7d93\u7406", "description": "\u5de5\u4f5c\u6027\u8cea\n\n\n\u63a8\u5ee3\u3001\u92b7\u552e\u5168\u9762\u7684\u4fdd\u969c\u3001\u7406\u8ca1\u53ca\u9000\u4f11\u7b56\u5283\u7522\u54c1\n\u6574\u5408\u5f37\u7a4d\u91d1\u5e33\u6236\n\u5411\u4f01\u696d\u5ba2\u6236\u63a8\u5ee3\u53ca\u92b7\u552e\u6709\u95dc\u50f1\u54e1\u798f\u5229\u7522\u54c1\n\u5411\u5ba2\u6236\u63d0\u4f9b\u5c08\u696d\u53ca\u5168\u9762\u7684\u8ca1\u52d9\u7b56\u5283\n\u8ca0\u8cac\u62db\u8058\u3001\u7ba1\u7406\u53ca\u8a13\u7df4\n\n\u798f\u5229\u53ca\u5f85\u9047\n\n\n\u5b8c\u5584\u85aa\u91d1\u798f\u5229\u5236\u5ea6\u00a0\uff08\u5305\u62ec\u8c50\u539a\u4f63\u91d1\u3001\u6bcf\u6708\u734e\u91d1\u3001\u5e74\u5c3e\u82b1\u7d05\uff09\n\u6d77\u5916\u6703\u8b70\u53ca\u65c5\u904a\u734e\u8cde\n\u63d0\u4f9b\u5168\u65b9\u4f4d\u8077\u524d\u53ca\u5728\u8077\u5c08\u696d\u57f9\u8a13\uff0c\u63d0\u5347\u92b7\u552e\u6280\u5de7\u3001\u767c\u6398\u5ba2\u6e90\u65b9\u6cd5\u53ca\u5c0d\u5e02\u5834\u7522\u54c1\u8a8d\u77e5\n\u8a2d\u6709\u516c\u5e73\u3001\u5feb\u6377\u6649\u5347\u5236\u5ea6\uff0c\u5efa\u7acb\u5c6c\u65bc\u81ea\u5df1\u7684\u5718\u968a\n\n\u8981\u6c42\n\n\nDSE\u6700\u5c11\u4e94\u79d1\u5408\u683c\u00a0(\u5305\u62ec\u00a0\u4e2d\u6587\u53ca\u6578\u5b78\u5408\u683c\u00a0\u6216\u00a0\u82f1\u6587\u53ca\u6578\u5b78\u5408\u683c\u00a0)\n\u5de5\u4f5c\u7d93\u9a57\u4e0d\u62d8 \uff08\u5177\u6709\u92b7\u552e\u6216\u5f9e\u4e8b\u91d1\u878d\u884c\u696d\u7684\u5de5\u4f5c\u7d93\u9a57\u512a\u5148\u8003\u616e\uff09\n\u6027\u683c\u4e3b\u52d5\u3001\u4e0a\u9032\u3001\u7a4d\u6975\u3001\u958b\u6717\u3001\u6562\u65bc\u6311\u6230\u00a0\u3001\u559c\u6b61\u5b78\u7fd2\n\u6b61\u8fce\u61c9\u5c46\u7562\u696d\u751f\u548cIANG\u52a0\u5165\u00a0\n\u6709\u610f\u8005\u8acb\u806f\u7d61\u6211\u5011\n\n\u806f\u7d61\u4eba\uff1a\u00a0\u9673\u5c0f\u59d0\n\u96fb\u8a71\uff1a\u00a09164 7808\n\n\n\u6709\u95dc\u62db\u8058\u7d93\u7406\n\n\u9673\u5c0f\u59d0\u5f9e\u4e8b\u91d1\u878d\u696d\u754c\u591a\u5e74\uff0c\u5177\u8c50\u5bcc\u9280\u884c\u670d\u52d9\u7d93\u9a57\uff0c\u5ba2\u6236\u4ee5\u5927\u578b\u4f01\u696d\u70ba\u4e3b\u3002\u73fe\u6642\u5e36\u9818\u5c0d\u7406\u8ca1\u7b56\u5283\u884c\u696d\u5145\u6eff\u71b1\u8aa0\u3001\u5e79\u52c1\u7684\u5925\u4f34\u6210\u70ba\u767e\u842c\u5713\u684c(MDRT)\u00a0\u5718\u968a\uff0c\u5e0c\u671b\u4ee5\u751f\u547d\u5f71\u97ff\u751f\u547d\uff0c\u8b93\u5c0d\u7406\u8ca1\u7b56\u5283\u884c\u696d\u6709\u7406\u60f3\u7684\u4eba\u767c\u63ee\u6700\u597d\u7684\u81ea\u5df1\u3002\n\nNow is Your Future! Join Us!\u00a0", "employment_types": ["Full Time", "Part Time", "Permanent", "Contract", "Internship"], "selling_points": [], "locations": ["Ngau Tau Kok"], "categories": ["Banking / Finance", "Financial Services", "Sales, CS & Business Devpt", "Business Development", "Management", "General Management"], "post_time": "2022-01-17T12:53:46Z", "salary": {"currency": "HKD", "max": 54999, "min": 20000, "period": "monthly", "term": null}, "salary_visible": true, "title_keywords": ["\u7406\u8ca1\u7b56\u5283\u7d93\u7406", "manager"], "responsibilities": [], "requirements": {"degrees": [], "majors": [], "languages": [], "language_level": [], "hard_skills": [], "soft_skills": [], "languages_combined": []}, "experience_required": {"duration": [], "field": []}}, {"job_id": "100003009052572", "location_code": "hk", "company": "Be Myjob Company Limited", "job_title": "Associate - Director, ESOP Sales & Support", "description": "Key Accountabilities\n\nBuild and maintenance good relationship with ESOP VIP clients;\nResponse ESOP VIP clients in professional manner and on timely basis;\nKeep track on instruction and progress update with ESOP VIP clients;\nCoordinate daily tasks or ad-hoc tasks closely with relevant departments;\nProvide support to the team and carry out other ad-hoc tasks as assigned.\n\nSkills & Experience\n\nDegree holder in Business, Finance or related disciplines;Candidate with SFC type 1 License is preferred;\nSolid experience in ESOP product & customer servicing are an advantage;\nIndependent, responsible and detail-minded with positive working attitude;\nGood command of written and spoken English & Chinese (including Putonghua);\nProficient in MS Office application.", "employment_types": ["Full Time"], "selling_points": ["Employee Stock Option Plan", "Sales & Support", "SFC RA 1"], "locations": ["Wan Chai"], "categories": ["Banking / Finance", "Financial Services", "Equities / Capital Markets", "Fund Management"], "post_time": "2022-01-17T03:26:50Z", "salary": {"currency": null, "max": null, "min": null, "period": "monthly", "term": null}, "salary_visible": false, "title_keywords": ["associate", "director", "sales"], "responsibilities": ["provide support", "maintenance", "ad-hoc tasks", "professional manner", "good relationship", "coordinate"], "requirements": {"degrees": ["degree holder"], "majors": ["related disciplines", "finance", "business"], "languages": ["putonghua", "english", "chinese"], "language_level": ["good command"], "hard_skills": ["maintenance", "ms office"], "soft_skills": ["detail-minded", "independent", "responsible", "timely", "positive working attitude"], "languages_combined": [{"language": "putonghua", "language_level": ["good command"]}, {"language": "english", "language_level": ["good command"]}, {"language": "chinese", "language_level": ["good command"]}]}, "experience_required": {"duration": [], "field": []}}, {"job_id": "100003009053591", "location_code": "hk", "company": "Principal Trust Company (Asia) Limited", "job_title": "Officer, Pension Operations", "description": "Principal Hong Kong is one of the major service providers of total retirement solutions in Hong Kong.\u00a0We are one of the winners received \"The 2021 MPF Award\" by MPF Ratings. Pension Operations plays a critical role to contribute the success of our business, join us if you are striving in an exciting operational environment or want to be a pension operation expert!\n\n\nThe Officer will participate in end-to-end pension operations process. You will handle daily administration of retirement schemes including but not limited to member enrollments, contributions, terminations, and group changes, in accordance with internal approved procedures, policies and local ordinance and regulations.\u00a0\n\nOther responsibilities include:\n\nProcess data and perform quality checking\nProvide customer service to clients and/or respond clients' verbal and written enquiries\nMaintain accurate records and thorough documentation\nAssist in any ad-hoc assignments or special projects\n\nEssential Skills, Experience and Competencies\n\nWe are looking for detail-minded candidates with strong time management skill. Competent in communicating across a wide variety of clients and deliver excellent customer service skills. Passionate about operational process with continuous improvement mindset will be a key to success.\n\nOther key skills required for the role:\n\nGraduates in business, finance or other related disciplines\n1 year of experience in Operations role\nExperience or sound knowledgeable in MPF and/or ORSO schemes administration is highly preferred\nA self-starter and good team player\nAble to meet tight timeline\nStrong PC applications especially Microsoft Excel and Word\nGood command of spoken and written English and Chinese\nFresh graduates who want to develop your career in Pension industry are welcome to apply/ candidate with less experience will be considered as Assistant Officer\n\nWhat We Offer\n\nPrincipal offers employees a competitive package and a comprehensive range of benefits to help meeting your needs now and in the future, including:\n\n5-Day Work Week\nYear-end Payment\nDiscretionary Bonus\nBirthday Leave\nMedical Plan\nLife Insurance\nPension Scheme\nEmployee Stock Purchase Plan\nAnd Growth Opportunities!", "employment_types": ["Full Time", "Permanent"], "selling_points": ["Participate in entire pension operations process", "Experience in MPF/ORSO is highly preferred", "Fresh graduates are welcome to apply"], "locations": ["Kwun Tong"], "categories": ["Banking / Finance", "Financial Services", "Insurance", "Others", "Order Processing & Operation / Settlement"], "post_time": "2022-01-17T07:12:35Z", "salary": {"currency": null, "max": null, "min": null, "period": "monthly", "term": null}, "salary_visible": false, "title_keywords": ["officer", "operations"], "responsibilities": ["provide customer service", "quality checking", "management", "data", "ad-hoc assignments", "maintain", "customer service", "documentation"], "requirements": {"degrees": [], "majors": [], "languages": ["english", "chinese"], "language_level": ["good command"], "hard_skills": ["microsoft excel", "word", "pc applications"], "soft_skills": ["good team player"], "languages_combined": [{"language": "english", "language_level": ["good command"]}, {"language": "chinese", "language_level": ["good command"]}]}, "experience_required": {"duration": ["1 year"], "field": ["mpf", "administration"]}}, {"job_id": "100003009052379", "location_code": "hk", "company": "Manulife (International) Limited", "job_title": "Customer Relationship Officer (\u9867\u5ba2\u95dc\u4fc2\u4e3b\u4efb)", "description": "\u5de5\u4f5c\u5167\u5bb9:\n\n\u8ca0\u8cac\u8207\u8655\u7406\u5ba2\u6236\u7684\u67e5\u8a62\n\u5354\u52a9\u71df\u92b7\u5718\u968a\u9054\u5230\u92b7\u552e\u76ee\u6a19\n\u5354\u52a9\u92b7\u552e\u904e\u7a0b\u884c\u653f\u8207\u8ddf\u9032\u4e8b\u5b9c\n\u5b9a\u6642\u6e96\u5099\u5ba2\u6236\u5831\u544a\u53ca\u696d\u7e3e\u5831\u544a\n\u8655\u7406\u6587\u66f8\u53ca\u884c\u653f\u5de5\u4f5c\n\n\u5165\u8077\u8981\u6c42:\n\n\u5b78\u58eb\u6216\u4ee5\u4e0a\u5b78\u6b77\n\u6b61\u8fce\u61c9\u5c46\u7562\u696d\u751f/IANG\n\u826f\u597d\u7684\u4e2d\u6587\u3001\u82f1\u6587\n\u5177\u6709\u826f\u597d\u7684\u6e9d\u901a,\u8cac\u4efb\u611f\u53ca\u826f\u597d\u5718\u968a\u5408\u4f5c\u7cbe\u795e\n\u5373\u6642\u4e0a\u73ed\u7372\u512a\u5148\u8003\u616e\n\n\u5f85\u9047:\n\n5\u5929\u5de5\u4f5c\u9031\n\u5b8c\u5584\u7684\u798f\u5229\u4fdd\u969c\n\u5e74\u7d42\u82b1\u7d05", "employment_types": ["Full Time"], "selling_points": ["5 day work per week", "Customer Services", "Fresh graduates are welcome"], "locations": ["Ngau Tau Kok"], "categories": ["Banking / Finance", "Financial Services", "Hospitality / F & B", "Tourism / Travel Agency", "Sales, CS & Business Devpt", "Direct Sales"], "post_time": "2022-01-17T02:53:48Z", "salary": {"currency": null, "max": null, "min": null, "period": "monthly", "term": null}, "salary_visible": false, "title_keywords": ["officer"], "responsibilities": [], "requirements": {"degrees": [], "majors": [], "languages": [], "language_level": [], "hard_skills": [], "soft_skills": [], "languages_combined": []}, "experience_required": {"duration": [], "field": []}}, {"job_id": "100003009052398", "location_code": "hk", "company": "", "job_title": "Graduate Trainee/Internship Program (15K or above)", "description": "Our Financial Trainee program is designed to 2021 graduates, or any newly joined to job market candidates, to become a professional financial specialist. We\u00a0believe in providing high-quality training of financial services that fosters continuous professional development to high net worth individuals and proven to significantly enhance the client\u2019s portfolio.\n\nJOB DESCRIPTION:\n\nExperience valued communication training from the industry\u2019s leading performers.\nPractice on asset management, project finance, research and analysis skills\u00a0\u00a0\nComplete project and task to illustrate understanding the value of asset and risk management.\n\nContinuous Training:\n\nIn addition to the training at the start of your career, there will be continuous on the job training\nAttend monthly to biweekly company sponsored seminars where you will learn more about wealth management, risk management, and many more finance related topics\n\n\n\nREQUIREMENTS:\n\nFinal\u00a0year\u00a0students/ Fresh graduates\u00a0\u00a0\u00a0\u00a0\nExcellent interpersonal, communications and presentation skills\u00a0\n\n", "employment_types": ["Full Time", "Part Time", "Internship"], "selling_points": [], "locations": ["Wan Chai"], "categories": ["Banking / Finance", "Financial Services", "Professional Services", "Business Consultancy", "Property / Real Estate", "Property Consultancy"], "post_time": "2022-01-17T02:57:09Z", "salary": {"currency": "HKD", "max": 34999, "min": 14000, "period": "monthly", "term": null}, "salary_visible": true, "title_keywords": ["graduate trainee", "internship"], "responsibilities": ["communication", "analysis", "management", "asset management"], "requirements": {"degrees": [], "majors": [], "languages": [], "language_level": [], "hard_skills": [], "soft_skills": ["presentation skills", "interpersonal"], "languages_combined": []}, "experience_required": {"duration": [], "field": []}}, {"job_id": "100003009052439", "location_code": "hk", "company": "PeopleSearch Ltd", "job_title": "Global Markets Operations Analyst", "description": "Our client, an European bank, is seeking a Global market operation analyst, focusing on handling global market daily operation.\n\nResponsibilities:\n\n\nPerform day-to-day settlement operations to ensure timely settlement and the firm\u2019s compliant with regulatory requirements and ratio. To support funding liquidity and daily positions for the branch\nResolve any Front-office to Back-office/Nostro breaks\nPerform day-to-day core operational support functions to Front Office including trade validation of FX/MM/Bonds/OTC Derivatives/Loans\nPrepare MIS/KPIs for senior management reporting\n\n\nRequirements:\n\nUniversity degree in relevant subject would be an advantage\nRequires to rotate and work on Hong Kong holidays and China business weekends\nMinimum 3-5 years of experience in Global Markets operations\nExperience in SWIFT, RTGS, CLS and other settlement related systems is an advantage\nStrong analytical skills and ability to learn quickly new knowledge such as systems and policies, with good adaptability to constantly changing environment\nFluent in English and Chinese\u00a0\n\nInterested applicants please send your full resume (in Word format) together with present and expected salary to Raymond Lam", "employment_types": ["Full Time", "Permanent", "Temporary"], "selling_points": ["Global market exposure", "Attractive package and benefits", "Excellent employee development and career growth"], "locations": ["Central & Western Area"], "categories": ["Banking / Finance", "Financial Services", "Dealing & Trading"], "post_time": "2022-01-17T03:02:14Z", "salary": {"currency": null, "max": null, "min": null, "period": "monthly", "term": null}, "salary_visible": false, "title_keywords": ["operations analyst"], "responsibilities": ["reporting", "operational support", "operations", "regulatory requirements", "kpis", "senior management", "timely settlement"], "requirements": {"degrees": ["university degree"], "majors": [], "languages": ["english", "chinese"], "language_level": ["fluent"], "hard_skills": ["swift", "word", "analytical skills"], "soft_skills": ["adaptability", "analytical skills"], "languages_combined": [{"language": "english", "language_level": ["fluent"]}, {"language": "chinese", "language_level": ["fluent"]}]}, "experience_required": {"duration": ["minimum 3-5 years"], "field": ["related"]}}, {"job_id": "100003009054054", "location_code": "hk", "company": "Carrier Hong Kong Limited", "job_title": "Financial Analyst (Ref : CHK/FA)", "description": "Job Responsibilities\n\nTo prepare monthly forecast package and assist in the preparation of annual budget such as order booking, sales, margin and working capital\nTo prepare monthly assets management review package including variance analysis on working capital\nTo prepare reports for regular business review with management including variance analysis on P&L, cash flow and working capital\nTo monitor capital expenditure forecasting, spending and variance analysis\nTo preparation of key business metrics, such as labor productivity analysis, warranty spending, sales and margin performance, etc.\nTo partner with business units to keep track of performance and set up business targets\nTo support any ad hoc business review with top management\n\nRequirements\n\nBachelor degree in Finance or Accounting\n2-3 experience in financial analysis\nStrong skills in data consolidation, Excel, PowerPoint required. Experience in SAP & HFM is desirable\nGood interpersonal and communication skills\nSelf-motivated, multi-tasking, attention to details, proactive and fast learner\nFluent English and Mandarin is pre-requisite for this position\u00a0\nAttractive compensation and benefits packages will be offered to the right candidate. Interested parties, please click \"Apply Now\" and send your application together with a full resume stating your present and expected salary and date of availability to us; Or\nBy mail: Human Resources Department, Carrier Hong Kong Limited, Unit 901, 9/F, Habourside HQ, 8 Lam Chak Street, Kowloon Bay, Kowloon.\n\nPersonal data provided in your application will be kept in the strictest confidence. It will only be used for employment-related purposes by any entity within our Group. Applicants not notified within 1 month will be considered as unsuccessful. Unsuccessful application may be kept for another 3 months for new openings or consideration by another entity within our Group before properly shredded.", "employment_types": ["Full Time", "Permanent"], "selling_points": ["Financial Planning & Analysis", "2-3 Years FP&A Experience", "Degree in Finance or Accounting"], "locations": ["Kowloon Bay"], "categories": ["Banking / Finance", "Financial Services"], "post_time": "2022-01-17T08:47:24Z", "salary": {"currency": null, "max": null, "min": null, "period": "monthly", "term": null}, "salary_visible": false, "title_keywords": ["financial analyst"], "responsibilities": ["management", "ad hoc", "analysis", "budget", "review", "monitor", "p&l", "variance analysis", "cash flow", "booking", "forecast", "prepare reports", "forecasting", "management review"], "requirements": {"degrees": ["degree", "bachelor"], "majors": ["finance", "accounting"], "languages": ["english", "mandarin"], "language_level": ["fluent"], "hard_skills": ["financial analysis", "excel", "sap", "powerpoint"], "soft_skills": ["communication skills", "self-motivated", "multi-tasking", "attention to details", "proactive", "fast learner", "interpersonal"], "languages_combined": [{"language": "english", "language_level": ["fluent"]}, {"language": "mandarin", "language_level": ["fluent"]}]}, "experience_required": {"duration": [], "field": ["financial"]}}, {"job_id": "100003009052653", "location_code": "hk", "company": "ICBC International Holdings Limited", "job_title": "Accounting Clerk", "description": "Job Responsibilities:\n\nResponsible for firm's expenses claim process;\nAssist to drive process improvement on approval of daily accounting entries and provide guidance on expenses analysis for management approval;\nEstablish appropriate operating expenses approval procedure which in line with compliance;\nAssist to Improve the effectiveness of internal control systems and accounting information systems;\nMaintain effective communication with other departments and external parties;\nDevelop team spirit and advising daily accounting operations.\n\nJob Requirements:\n\nBachelor degree in accounting or related discipline;\nMinimum 2 years of relevant experience in a leading financial institutions;\nProficient in Word and Excel;\nGood problem solving and negotiating skills;\nGood administrative skills;\nFluent in Putonghua and English;\nGood interpersonal skills;\nGood verbal and written skills.", "employment_types": ["Full Time"], "selling_points": ["Leading Chinese Investment Bank", "Investment Bank", "Accounts Payable Focused"], "locations": ["Not Specified"], "categories": ["Banking / Finance", "Financial Services", "Others"], "post_time": "2022-01-17T03:38:47Z", "salary": {"currency": "HKD", "max": 34999, "min": 25000, "period": "monthly", "term": null}, "salary_visible": true, "title_keywords": ["accounting clerk"], "responsibilities": ["management", "analysis", "expenses", "compliance", "systems", "external parties", "develop", "communication", "daily accounting operations", "maintain", "daily accounting", "provide guidance", "internal control"], "requirements": {"degrees": ["degree", "bachelor"], "majors": ["accounting"], "languages": ["putonghua", "english"], "language_level": ["fluent"], "hard_skills": ["problem solving", "excel", "word"], "soft_skills": ["problem solving", "interpersonal skills"], "languages_combined": [{"language": "putonghua", "language_level": ["fluent"]}, {"language": "english", "language_level": ["fluent"]}]}, "experience_required": {"duration": ["minimum 2 years"], "field": ["financial institutions", "relevant experience"]}}, {"job_id": "100003009053042", "location_code": "hk", "company": "Chubb Life Insurance Company Ltd.", "job_title": "\u4fdd\u96aa\u7406\u8ca1\u9867\u554f Financial & Insurance Consultant", "description": "- \u81f4\u529b\u7dad\u7e6b\u4e26\u62d3\u5c55\u5ba2\u6236\u95dc\u4fc2\uff0c\u4ee5\u5c08\u696d\u70ba\u57fa\u790e\u00a0\n\n\n- \u63d0\u4f9b\u9069\u5207\u4fdd\u969c\u65b9\u6848\uff0c\u8ddf\u9032\u6838\u4fdd\u53ca\u7d22\u50f9\uff0c\u4ee5\u81f3\u6b7b\u4ea1\u7406\u8ce0\u7684\u6d41\u7a0b \u00a0\n\n- \u4fdd\u55ae\u552e\u5f8c\u670d\u52d9\u00a0\n\n\nOffer\n\n- \u6bcf\u6708\u6d25\u8cbc\n\n- \u5718\u968a\u65c5\u884c\u734e\u52f5\n\n-\u00a0\u696d\u7e3e\u734e\u52f5\n\n- \u6d77\u5916\u6703\u8b70\n\n- \u826f\u597d\u6649\u5347\u6a5f\u6703\n\n\n\nRequirements / Qualifications\n\n- \u6301\u6709\u9999\u6e2f\u6c38\u4e45\u8eab\u4efd\u8a3c\n\n- \u9999\u6e2f\u4e2d\u5b78\u6587\u6191\u8003\u8a66/\u9999\u6e2f\u4e2d\u5b78\u6703\u8003\u4e94\u79d1\u6210\u7e3e\u5408\u683c\uff0c\u5fc5\u9808\u5305\u62ec\u4e2d\u570b\u8a9e\u6587/\u82f1\u570b\u8a9e\u6587\u53ca\u6578\u5b78\n\n- \u6b61\u8fce\u6240\u6709\u8077\u696d\u80cc\u666f\u4eba\u58eb\n\n\u6709\u610f\u61c9\u5fb5\u8005\uff0c\u8acb\u7d93\u7531\u201cApply Now\u201d\u63d0\u4ea4\u7533\u8acb\u3002\n(Interested Parties please click \u2018Apply Now\u2019 to process the application.)\n\n\u6216\u8acb\u65bc\u5de5\u4f5c\u6642\u9593\u5167Whatsapp\u806f\u7d61\u00a0\u00a097454667 Ms. Yeung\u67e5\u8a62\u8a73\u60c5\u3002\n(Or Whatsapp Ms. Yeung 97454667 on working hours)\n\n\u6240\u6709\u6536\u96c6\u7684\u500b\u4eba\u8cc7\u6599\u53ea\u6703\u88ab\u7528\u4f5c\u62db\u52df\u4e4b\u7528\u53ca\u5c07\u6703\u6839\u64da\u6211\u5011\u7684\u8cc7\u6599\u79c1\u7a69\u539f\u5247\u8655\u7406\uff0c\u4f60\u53ef\u5411\u6211\u5011\u7d22\u53d6\u6211\u5011\u7684\u8cc7\u6599\u79c1\u7a69\u539f\u5247\uff0c\u6211\u5011\u5728\u6536\u5230\u8981\u6c42\u5f8c\uff0c\u6703\u96a8\u5373\u63d0\u4f9b\u4e00\u4efd\u6709\u95dc\u539f\u5247\u7684\u8907\u672c\u3002\u5b89\u9054\u4eba\u58fd\u4fdd\u7559\u66f4\u6539\u5f85\u9047\u7684\u689d\u6b3e\u53ca\u7d30\u5247\u3002", "employment_types": ["Full Time"], "selling_points": ["\u5f48\u6027\u4e0a\u73ed\u6642\u9593", "\u8c50\u539a\u6536\u5165", "\u5728\u8b58\u57f9\u8a13"], "locations": ["Causeway Bay"], "categories": ["Banking / Finance", "Financial Services", "Insurance", "Insurance Agent / Broker", "Risk Management"], "post_time": "2022-01-17T05:20:11Z", "salary": {"currency": null, "max": null, "min": null, "period": "monthly", "term": null}, "salary_visible": false, "title_keywords": ["consultant"], "responsibilities": [], "requirements": {"degrees": [], "majors": [], "languages": [], "language_level": [], "hard_skills": [], "soft_skills": [], "languages_combined": []}, "experience_required": {"duration": [], "field": []}}, {"job_id": "100003009054760", "location_code": "hk", "company": "BOCI-Prudential Trustee Limited", "job_title": "Senior Administrator, Unit Trust", "description": "Responsibilities:\n\nHandle daily unit trust order, including subscription, redemption, switching, transfer, dividend and reinvestment\nLiaise with Fund Houses or Distributors (including Overseas and Mainland China) for routine operation issues\nHandle payment settlement with clients or Finance, including autopay instruction with banks\nPrint and dispatch contract notes, advice, statements and reports to unit holders, distributors or fund houses\nAssist the team supervisor to set up new fund groups for new business\nGeneral clerical support to the team\nHandle ad hoc assignment as required\n\nRequirements:\n\nDegree holder in Business Administration, Finance,\u00a0Economics, Banking\u00a0or related disciplines\nAt least 1 year working experience specialist in Fund Transfer Agent, Investor Service and Fund Administration is preferred\nTeam player with excellent interpersonal and presentation skills\nGood at problem-solving, customer focused and communication skills\nAble to work independently and under pressure\nProficient in PC applications including Excel, Word, PowerPoint and Chinese Word Processing\nGood command of both written and spoken English, Chinese and Mandarin\nCandidate with\u00a0more experience will be considered as Assistant Supervisor\n\nWe offer attractive remuneration package & benefits to the right candidates. Interested candidates, please send your application letter & resume with current & expected salary\u00a0by mail to Human Resources Department, 12/F., Citicorp Centre, 18 Whitfield Road, Causeway Bay, Hong Kong.\u00a0Or by direct application, please visit our career page at\u00a0http://www.bocpt.com.\n\nWe are an equal opportunities employer and is committed to equality, ethics, inclusivity, diversity and transparency. Information provided will be treated in strict confidence and only be used for recruitment related purposes. Applicants who are not contacted within 6 weeks may consider their application unsuccessful. Applications will also be considered for other suitable positions available in our Group. Unsuccessful applications will be kept in our file for a period of one year\u00a0and which will be destroyed after the said period of retention.", "employment_types": ["Full Time", "Permanent"], "selling_points": ["Handle daily unit trust order, payment settlement", "Liaise with fund houses / distributors", "Assist in set up new fund groups for new business"], "locations": ["Tin Hau"], "categories": ["Banking / Finance", "Financial Services", "Dealing & Trading", "Order Processing & Operation / Settlement"], "post_time": "2022-01-17T10:57:40Z", "salary": {"currency": null, "max": null, "min": null, "period": "monthly", "term": null}, "salary_visible": false, "title_keywords": ["administrator"], "responsibilities": ["ad hoc assignment", "clerical support", "payment", "reports", "liaise with", "autopay"], "requirements": {"degrees": ["degree holder"], "majors": ["related disciplines", "finance", "economics", "business administration"], "languages": ["english", "chinese", "mandarin"], "language_level": ["good command", "proficient"], "hard_skills": ["excel", "chinese word processing", "problem-solving", "word", "powerpoint", "pc applications"], "soft_skills": ["communication skills", "work independently", "under pressure", "focused", "problem-solving", "presentation skills", "team player", "interpersonal"], "languages_combined": [{"language": "english", "language_level": ["good command"]}, {"language": "chinese", "language_level": ["good command", "proficient"]}, {"language": "mandarin", "language_level": ["good command"]}]}, "experience_required": {"duration": ["at least 1 year"], "field": ["administration"]}}, {"job_id": "100003009054374", "location_code": "hk", "company": "Bright Smart Securities International (H.K.) Limited", "job_title": "Research Analyst", "description": "Responsibilities:\n\n\nPrepare and edit daily report or Pre-IPO research report;\nAssist in answering queries regarding investment services;\nStay abreast of market trends and news through different channels;\nAnalyze company fundamental, financial data, generate investment ideas with proven reasons;\nHandle ad hoc assignments as required.\nRequirements & Qualification:\n\nDegree holder in Economics, Finance or other related disciplines;\n1-2 years of\u00a0relevant experiences preferably with solid research experience in securities firm/investment company;\nExcellent analytical, report writing and presentation skills;\nStrong interpersonal and communication skills\nQuick Learner with an ability to work under pressure;\nProficient in MS Word, Excel and PowerPoint;\nExcellent command of spoken and written Chinese;\nCandidate with more experience will be considered as Senior Research Analyst.\n\nWe Offer:\n\nCompetitive remuneration package\n5 Days Work & Bank Holidays\nAttendance Bonus\nMeal Allowance\nDiscretionary Bonus\nMedical Insurance\n\nWe provide attractive remuneration package and fringe benefits for the right candidate. Interested parties please send detailed resume with current and expected salaries to\u00a0Human Resources Department by clicking \"Apply Now\" or fax to: 2530 2218.\n\nAll information collected will be used for recruitment purpose only, only shortlisted candidates will be notified.\n\nWelcome to visit our website: http://www.bsgroup.com.hk/ for more information.", "employment_types": ["Full Time", "Permanent"], "selling_points": [], "locations": ["Central"], "categories": ["Banking / Finance", "Analyst", "Financial Services", "Others"], "post_time": "2022-01-17T09:18:38Z", "salary": {"currency": null, "max": null, "min": null, "period": "monthly", "term": null}, "salary_visible": false, "title_keywords": ["research analyst"], "responsibilities": ["ideas", "data", "ad hoc assignments", "daily report", "report"], "requirements": {"degrees": ["degree holder"], "majors": ["related disciplines", "finance", "economics"], "languages": ["chinese"], "language_level": ["excellent"], "hard_skills": ["excel", "powerpoint", "ms word"], "soft_skills": ["communication skills", "quick learner", "presentation skills", "interpersonal", "work under pressure"], "languages_combined": [{"language": "chinese", "language_level": ["excellent"]}]}, "experience_required": {"duration": ["1-2 years"], "field": ["research", "securities firm", "investment"]}}, {"job_id": "100003009050874", "location_code": "hk", "company": "Manpower Services (Hong Kong) Limited", "job_title": "Credit & Trade Finance Specialist (25-40K)", "description": "Responsibilities:\n\nProcessing import LC / amendments issuances and import collections and the related acceptances and payments\nProcessing Back to back, Front to back, Standby LC/amendments & Trade-related Bank Guarantee and Shipping Guarantee issuance/redemption and the related acceptances and payments\nProcessing export LC/amendments advising, confirmation, transfer and export negotiations/collections and the related acceptance and payments\nHandling Import and Export collection bills under DA/DP\nHandling of import and export loans and discounting loans, roll-over, payments and past due loans\nHandling of funded and unfunded participations in system and payments\nPerform KYC validation and Anti-money Laundering Checks on trade finance transactions;\nInput trade finance transactions into related systems and generate entries and customer advices;\nInput payment and other SWIFT messages into related systems\nSend emails/faxes to customers, sorting of documents, matching of SWIFT messages, photocopy of documents and filing duties;\nScanning of documents to outsourcing center for checking\nSending out export documents to LC issuing banks / negotiating banks\nAttend to Customer queries on trade finance activities covered\nEscalate to team leaders, team head or Head, Trade Finance Support Services for any exception, problem, error and abnormal transaction identified during processing.\nAll other job duties as and when assigned by team leaders, team head or Head, Trade Finance Support Services.\u00a0\u00a0\u00a0\u00a0\u00a0\u00a0\u00a0\u00a0\u00a0\n\nJob Requirements\n\n3 years relevant experience in Corporate / Commodities Trade Finance BO services\nGood attitude and interpersonal skills.\nFluent written and spoken English\nSpoken Mandarin & Cantonese, Written Chinese an advantage\nKnowledge in trade finance product is key. UCP 600, International trade and the\u00a0Incoterms 2020 rules, URC 522, ISBP, ISP, URDG & URR 725\nFamiliar with Microsoft Windows (Excel, Word, PowerPoint)\n\nInterested parties please send your full resume with expected salary to yan.chan@manpowergrc.hk\u00a0or by clicking \"Apply Now\".", "employment_types": ["Contract"], "selling_points": ["Corporate / Commodities Trade Finance BO services", "LC Issuance", "3 years relevant experience"], "locations": ["Aberdeen"], "categories": ["Banking / Finance", "Corporate Banking", "Credit Analysis / Approval", "Financial Services"], "post_time": "2022-01-14T11:36:22Z", "salary": {"currency": null, "max": null, "min": null, "period": "monthly", "term": null}, "salary_visible": false, "title_keywords": ["specialist"], "responsibilities": ["scanning", "shipping", "systems", "support services", "checking", "transactions", "payment", "payments", "kyc", "customer queries"], "requirements": {"degrees": [], "majors": [], "languages": ["cantonese", "english", "chinese", "mandarin"], "language_level": ["advantage", "fluent"], "hard_skills": ["excel", "word", "powerpoint"], "soft_skills": ["interpersonal skills"], "languages_combined": [{"language": "cantonese", "language_level": []}, {"language": "english", "language_level": ["fluent"]}, {"language": "chinese", "language_level": ["advantage"]}, {"language": "mandarin", "language_level": []}]}, "experience_required": {"duration": ["3 years"], "field": ["finance", "relevant experience"]}}, {"job_id": "100003009051929", "location_code": "hk", "company": "Octopus Holdings Limited", "job_title": "Compliance Analyst, Financial Crime Compliance (1 year contract) (Ref: OCL/RMC/2021-218-219)", "description": "Job Responsibilities:\nDemonstrate commitment to regulatory compliance and high ethical standards\nPerform quality assurance review on risk and compliance related tasks\nEffectively discharge the responsibility of being the 2nd line of defense\nPerform AML function on a continuous basis, including the detection and reporting of suspicious transactions and activities\nEnsure the alerts generated from the system are fully and properly investigated\nIdentify and investigate the patterns, trends and abnormalities on transaction cases and customer data so as to meet the AML requirements\nConduct investigation and file the Suspicious Transaction Report (STR) appropriately on a timely basis\nRequirements:\nUniversity Degree holder preferably in Risk Management, Engineering, Computer Science or related disciplines\nRelevant work experience in payment service industry, consulting firms, or financial institutions is a plus\nProficiency in Excel (hands on experience on MS Excel functions e.g. Pivot tables, VLOOKUP etc. is an advantage) and other data analytics software\nSelf-starter with integrity\nAttentive to details with strong analytical skills especially on data filtering & data processing\nGood analytical and communication skills\nProactive with can-do attitude\nGood command of written and spoken English and Chinese\nPrefer immediately available or in short-notice period candidate", "employment_types": ["Contract"], "selling_points": ["Perform quality assurance review on risk", "University Degree holder", "Relevant work experience in payment service"], "locations": ["Kowloon Bay"], "categories": ["Banking / Finance", "Analyst", "Financial Services", "Others"], "post_time": "2022-01-17T01:32:42Z", "salary": {"currency": null, "max": null, "min": null, "period": "monthly", "term": null}, "salary_visible": false, "title_keywords": ["compliance analyst"], "responsibilities": ["reporting", "aml", "review", "compliance", "quality", "transactions", "investigation", "customer data", "report"], "requirements": {"degrees": ["university degree"], "majors": ["related disciplines", "risk management", "engineering", "computer science"], "languages": ["english", "chinese"], "language_level": ["good command"], "hard_skills": ["excel", "plus", "data analytics", "analytical skills", "ms excel", "vlookup", "processing"], "soft_skills": ["communication skills", "attentive to details", "can-do attitude", "integrity", "analytical skills", "hands on", "proactive"], "languages_combined": [{"language": "english", "language_level": ["good command"]}, {"language": "chinese", "language_level": ["good command"]}]}, "experience_required": {"duration": [], "field": ["consulting firms", "financial institutions", "service industry"]}}, {"job_id": "100003009054746", "location_code": "hk", "company": "Public Finance Limited", "job_title": "Clerks (Various Departments)", "description": "Responsibilities\nProvide administrative support\nCompile various kinds of reports\nPerform general clerical duties\nRequirements\nSecondary education\n1 year administrative / clerical working experience\nGood communication and interpersonal skills\nSelf-motivated, able to work independently\nKnowledge of MS Word / MS Excel\nBenefits\nDouble Pay\nDiscretionary Bonus\nInsurance Benefits\nStudy subsidy\nApplication Method:\nBy Whatsapp : 9309 2925By E-mail via \"Apply Now\"\nPersonal data collected will be treated in the strictest confidence in accordance with our\u00a0Personal Information Collection Statement\u00a0and\u00a0Privacy Policy\u00a0and will be handled by authorized personnel for recruitment-related purposes only. All applications will be kept for a maximum period of one year as may be considered for other suitable positions within Public Finance Ltd. and its associated companies. For details, please visit the Company\u2019s website\u00a0http://www.publicfinance.com.hk", "employment_types": ["Full Time", "Permanent"], "selling_points": [], "locations": ["Not Specified"], "categories": ["Admin & HR", "Clerical / Admin Staff", "Others", "Banking / Finance", "Financial Services"], "post_time": "2022-01-17T10:52:54Z", "salary": {"currency": null, "max": null, "min": null, "period": "monthly", "term": null}, "salary_visible": false, "title_keywords": [], "responsibilities": ["provide administrative support", "reports"], "requirements": {"degrees": ["secondary education"], "majors": [], "languages": [], "language_level": [], "hard_skills": ["ms excel", "ms word"], "soft_skills": ["self-motivated", "communication and interpersonal skills", "work independently"], "languages_combined": []}, "experience_required": {"duration": ["1 year"], "field": ["administrative", "clerical"]}}, {"job_id": "100003009049270", "location_code": "hk", "company": "Shanghai Commercial Bank Ltd", "job_title": "Associate, i-Banking Centre (Account Opening Support)", "description": "Responsibilities:\n\nResponsible for processing online account opening request and the customer\u2019s internet banking application\nFollow up with branch staff on online account opening issues\nProvide administrative support e.g. documents filing and record keeping\nHandle enquiries from internal staff\nTake up ad hoc projects as assigned\n\nRequirements:\n\nPost-secondary education or above, preferably with at least 1 year's relevant experience in account opening\nAbility to work independently and under pressure\nCustomer-focused with good communication and interpersonal skills; fluency in written and spoken English and Chinese, preferably with proficiency in Putonghua\nGood PC knowledge, including MS Word, Excel and Chinese word processing\n\nAttractive remuneration package will be offered to the right candidates. Interested parties please click\u00a0\"Apply Now\"\u00a0to submit your full resume with current and expected salary to the\u00a0Human Resources Division.\n\nPlease visit us at\u00a0www.shacombank.com.hk\u00a0for more information about our Bank.\n\nAll personal data collected will be used for recruitment related purposes strictly in accordance with the Bank's personal data policies, a copy of which will be provided immediately upon request by contacting our Personal Data Compliance Officer at the above email address.\u00a0Applicants who are not contacted within two months may consider their applications unsuccessful and the personal data collected will be destroyed within 12 months of receipt.", "employment_types": ["Full Time", "Permanent"], "selling_points": ["Handle enquiries from internal staff", "Responsible for processing online account opening", "Follow up with branch staff"], "locations": ["Not Specified"], "categories": ["Banking / Finance", "Financial Services", "Others"], "post_time": "2022-01-15T03:50:16Z", "salary": {"currency": null, "max": null, "min": null, "period": "monthly", "term": null}, "salary_visible": false, "title_keywords": ["associate"], "responsibilities": ["documents filing", "account opening", "handle enquiries", "ad hoc projects", "banking", "provide administrative support"], "requirements": {"degrees": ["secondary education"], "majors": [], "languages": ["putonghua", "english", "chinese"], "language_level": ["fluency", "proficiency", "good"], "hard_skills": ["excel", "chinese word processing", "account opening", "pc knowledge", "ms word"], "soft_skills": ["work independently", "customer-focused", "under pressure", "communication and interpersonal skills"], "languages_combined": [{"language": "putonghua", "language_level": ["proficiency", "fluency"]}, {"language": "english", "language_level": ["proficiency", "fluency"]}, {"language": "chinese", "language_level": ["proficiency", "fluency", "good"]}]}, "experience_required": {"duration": ["at least 1 year"], "field": ["relevant experience", "education"]}}, {"job_id": "100003009054733", "location_code": "hk", "company": "AXA China Region Insurance Company Limited", "job_title": "MANAGEMENT ASSOCIATE/ FINANCIAL MANAGER", "description": "\u00a0KNOW YOU CAN!!!\n\nWe are looking to partner up with success driven, strong and willing to conqueror challenges. If you are THE 1 and want to come out of your comfort zone and have growth\u00a0 JOIN US!!! We Will Welcome You With all our HEART!!!\u00a0\n\n\nJob Description\nPersonal GROWTH, understanding oneself better and others.\u00a0\nLearning from lots of experienced MANAGERS who have excel in this industry.\u00a0\nWorking together with the team to learn ways of making opportunities (cross- selling)Wealth management, Financial Planning, Fund investments, Retirement planning, Non-life commercial insurance etc.\u00a0\nThrough extensive training and experience building\u00a0your own BRAND and TEAM.\u00a0\u00a0\n\nRequirements\n\n\nBachelor\u2019s degree or above or Fresh graduates (will be considered)\u00a0\nInterpersonal skills, self-motivated, open-minded, eager to learn, crave for success, responsible\n\nWe Offer\n\nOverseas trip incentives ( Rookies convention, Top Producers Convention etc)\u00a0\nSpecial Training ( both 1 on 1 and group trainings), comprehensive trainings to make you competitive in the market.\u00a0\nGet to learn from\u00a0experienced professional mentors.\u00a0\nShowing ways where to find opportunities and handling the client objections.\nTrain to be MDRT!! (million dollar round table)\n\nBenefits and packages\n\n\n5 Days working\u00a0\nfrom HK$25K above+ 4 Quarterly Bonus +1 Year End Bonus\nFREE Medical insurance\u00a0\nFlexible working hours\u00a0\nTrainings to prepare you to be THE FUTURE LEADER (CAREER DEVELOPMENT)\n\n\n", "employment_types": ["Full Time"], "selling_points": [], "locations": ["Kwun Tong"], "categories": ["Banking / Finance", "Financial Services", "Admin & HR", "Recruitment / Executive Search", "Asset Management"], "post_time": "2022-01-17T10:48:50Z", "salary": {"currency": null, "max": null, "min": null, "period": "monthly", "term": null}, "salary_visible": false, "title_keywords": ["management associate", "financial manager"], "responsibilities": ["management", "insurance", "planning"], "requirements": {"degrees": ["degree or above", "bachelor"], "majors": [], "languages": [], "language_level": [], "hard_skills": [], "soft_skills": ["self-motivated", "responsible", "open-minded", "eager to learn", "interpersonal skills"], "languages_combined": []}, "experience_required": {"duration": [], "field": []}}, {"job_id": "100003009052103", "location_code": "hk", "company": "Talent Recruitment Company", "job_title": "Asset Management Consultant/Trainee", "description": "Some careers\u00a0grow faster than others.\u00a0If you are seeking a platform where\u00a0you can become a young entrepreneur, where growth and opportunities are unlimited, join us.\u00a0\n\nWe serve clients with comprehensive wealth management services to enable them to manage their finances and protect and build their financial futures.\u00a0\n\nNow we are currently seeking a high calibre professional to join our team as an asset management consultant.\n\nPrincipal Responsibilities\n\nUnderstand clients' current and long-term needs and advise them on products and services to meet their financial goals\nMonitor clients' investment portfolio constantly\u00a0\nConduct regular review to update clients on their portfolio performance\nBuild\u00a0long-term relationship with clients and expand network\n\nRequirements\n\nFresh graduates will also be considered\nMature, self-motivated, hardworking and willing to learn\nEnergetic and outgoing\nGood interpersonal and communication skills\nAllow to work in Hong Kong is a must\n\nIncentives\n\nAttractive commission and bonus\nWelcome Fresh graduate & Mainland China graduates (IANG)\nFast-track promotion to managerial position\nOverseas trips & conventions plus excellent career path\nExcellent and comprehensive in-house training programs\nProfessional training to become a Millionaire", "employment_types": ["Full Time", "Permanent"], "selling_points": ["Salary with commission", "Education and Development Opportunities", "Professional Career Progression"], "locations": ["Central & Western Area"], "categories": ["Banking / Finance", "Financial Services"], "post_time": "2022-01-17T02:09:12Z", "salary": {"currency": "HKD", "max": 29999, "min": 20000, "period": "monthly", "term": null}, "salary_visible": true, "title_keywords": ["consultant", "trainee", "asset management"], "responsibilities": ["regular review", "monitor"], "requirements": {"degrees": ["fresh graduate"], "majors": [], "languages": [], "language_level": [], "hard_skills": ["plus"], "soft_skills": ["outgoing", "communication skills", "self-motivated", "willing to learn", "mature", "comprehensive", "energetic", "interpersonal", "hardworking"], "languages_combined": []}, "experience_required": {"duration": [], "field": []}}, {"job_id": "100003009051130", "location_code": "hk", "company": "JAN Financial Press Limited", "job_title": "Accounts Clerk/ Senior Accounts Clerk - Billing (5 days work)", "description": "Responsibilities:\n- Perform general accounting functions such as data entry, document checking and filing,\u00a0prepare voucher \u00a0 \u00a0 \u00a0 \u00a0\n- Perform daily system input, prepare invoices and statements\n- Assist in month end closing\n- Ad hoc project\n\nRequirements:\n- Form 5 / HKDSE / Diploma with LCCI Intermediate level or above\n- 1 year relevant working experience\n- Proficiency in MS Office (Word, Excel and Chinese word processing)\n- Strong sense of the responsibilities, detail-minded and willing to learn\n- Fresh graduated is welcome\n- Immediately available or short notice is preferred.\n\nBenefits\n- 5 days works\n- MPF\n- Medical benefits\n- Bank holiday\n- On-the-job training is provided\n- One minute to Central MTR Station\n\nWe offer attractive package to the right candidate.\u00a0Interested parties please submit your FULL RESUME with AVAILABILITY, CURRENT and EXPECTED SALARY by clicking\u00a0APPLY NOW.\n\nAll information of candidates will be treated as strictly confidential and used for recruitment purposes only.\u00a0", "employment_types": ["Full Time", "Permanent"], "selling_points": ["General accounting duties", "Form 5 / DSE with LCCI 2nd level", "Fresh graduated is welcomed"], "locations": ["Central"], "categories": ["Accounting", "Accounting Clerk / Supervisor", "Banking / Finance", "Financial Services"], "post_time": "2022-01-15T03:05:52Z", "salary": {"currency": null, "max": null, "min": null, "period": "monthly", "term": null}, "salary_visible": false, "title_keywords": ["accounts clerk", "senior accounts clerk"], "responsibilities": ["month end closing", "ad hoc", "invoices", "data entry", "checking", "system input"], "requirements": {"degrees": ["diploma", "form 5", "hkdse"], "majors": [], "languages": ["chinese"], "language_level": ["proficiency"], "hard_skills": ["excel", "chinese word processing", "word", "ms office"], "soft_skills": ["detail-minded", "willing to learn"], "languages_combined": [{"language": "chinese", "language_level": ["proficiency"]}]}, "experience_required": {"duration": ["1 year"], "field": ["relevant working experience"]}}, {"job_id": "100003009054799", "location_code": "hk", "company": "BOCI-Prudential Trustee Limited", "job_title": "Manager, Fund Administration", "description": "Responsibilities:\n\nAssist the Senior Manager to run the team smoothly and operational metrics as required by management.\nDevelop the internal control procedures and workflow on daily tasks.\nEnsure the compliance with the applicable laws and regulations in relation to restricted investments.\nMonitor daily funding position of all managed funds to avoid overdraft.\nCheck and authorize the settlement instructions and pre-advice in sub-custodian system and ensure that they are completed before cut-off time.\nEnsure all prices and foreign exchange rates are updated into the system promptly and correctly.\nReview the reconciliation on bank accounts and custodian reports to ensure there is no discrepancies.\nLiaise with Fund Manager and Custodian on operation issues.\nProvide guidance to staff for improving productivity\n\nRequirements:\n\nUniversity graduate in Business Administration or Accounting\nAt least 6 years\u2019 experience in trustee company or custodian in fund administration or settlement areas of which at least 3 years at the supervisory level\nFamiliar to settlement practice in fixed income securities, equities, and FX transactions\nKnowledgeable in nominee services and corporate action events.\u00a0 A thorough understanding of Trustee company\u2019s service\nIn-depth knowledge in PORTIA and different settlement systems\nGood understanding of MPF & ORSO regulations\nStrong communication skills in both written and spoken English & Chinese\nStrong initiative with good problem solving skills\nProactively respond to changes in market and regulations\n\nWe offer attractive remuneration package & benefits to the right candidates. Interested candidates, please send your application letter & resume with current & expected salary\u00a0by mail to Human Resources Department, 12/F., Citicorp Centre, 18 Whitfield Road, Causeway Bay, Hong Kong.\u00a0Or by direct application, please visit our career page at\u00a0http://www.bocpt.com.\n\nWe are an equal opportunities employer and is committed to equality, ethics, inclusivity, diversity and transparency.\u00a0 Information provided will be treated in strict confidence and only be used for recruitment related purposes. Applicants who are not contacted within 6 weeks may consider their application unsuccessful. Applications will also be considered for other suitable positions available in our Group. Unsuccessful applications will be kept in our file for a period of one year\u00a0and which will be destroyed after the said period of retention.", "employment_types": ["Full Time", "Permanent"], "selling_points": ["Min 6yrs\u2019 exp in Trustee Co./custodian in fund adm", "University graduates in Business Admin/Accounting", "Immediate Available is highly preferred"], "locations": ["Tin Hau"], "categories": ["Banking / Finance", "Financial Services", "Fund Management", "Order Processing & Operation / Settlement"], "post_time": "2022-01-17T11:08:53Z", "salary": {"currency": null, "max": null, "min": null, "period": "monthly", "term": null}, "salary_visible": false, "title_keywords": ["manager"], "responsibilities": ["regulations", "management", "compliance", "procedures", "monitor", "review", "develop", "reports", "liaise with", "provide guidance", "internal control"], "requirements": {"degrees": ["university graduate"], "majors": ["accounting", "business administration"], "languages": ["english", "chinese"], "language_level": [], "hard_skills": ["problem solving skills"], "soft_skills": ["communication skills", "problem solving skills", "initiative", "thorough"], "languages_combined": [{"language": "english", "language_level": []}, {"language": "chinese", "language_level": []}]}, "experience_required": {"duration": ["at least 6 years", "at least 3 years"], "field": ["supervisory level", "administration"]}}, {"job_id": "100003009054490", "location_code": "hk", "company": "King Fung & Co.", "job_title": "AIA Wealth Management Trainee (Local/Overseas/IANG Fresh Graduate Program)", "description": "Job Description:\u00a0\n\u00a0- Assess clients\u2019 financial situations by conducting financial needs analysis\n\u00a0-\u00a0Analyse\u00a0and provide total package of financial services planning\u00a0\n\u00a0- Provide comprehensive wealth management services to clients from Hong Kong and China market, including:\u00a0 \u00a0 \u00a0 \u00a0 \u00a0 \u00a0 \u00a0 \u00a0 \u00a0\u00a0\n\u00a0 \u00a0 \u00a0 \u00a0 \u00a01. Risk Management\n\u00a0 \u00a0 \u00a0 \u00a0 \u00a02. Retirement Planning\n\u00a0 \u00a0 \u00a0 \u00a0 \u00a03. Asset Allocation\n\u00a0 \u00a0 \u00a0 \u00a0 \u00a04. Estate Planning\n\u00a0- Build up close business relationship with clients and review their financial portfolios\n\u00a0- Build up and manage financial planning team\n\nWe look for:\u00a0\n\u00a0- Degree holder in all discipline (Fresh graduates will also be considered)\n\u00a0- Mature, self-motivated, hardworking and willing to learn\n\u00a0- Energetic, passionate and outgoing\n\u00a0- Good interpersonal and communication skills\n\u00a0- Fluent in Cantonese or Mandarin, and English\n\u00a0- Experience in banking industry will be an advantage\n\u00a0- Experience in aviation/tourism and hospitality/retail/beauty/fitness industry are welcomed\n\n\nWe Offer:\u00a0\n\u00a0-\u00a0Expected salary per year: HKD 550,000 or above\n\u00a0- Professional training and mentor program (Pre-job and on-job training on how to be MDRT qualifier)\n- Excellent career path to management level\n- Monthly Allowance + Attractive commission package + year-end bonus + comprehensive fringe benefits\n- Overseas trips and conventions\n- IIQE Paper 1 & 3 Licensing Training\n\nHong Kong ID Card Holders and IANG visa\u00a0Only\u00a0\nInterested parties please send full CV by clicking \u201cApply Now\u201d button.\u00a0\n\u00a0All information provided by applicants will be treated in strict confidence and used for recruitment purpose only.\n\n\u00a0\u2018CL-PRO\u2019 embraces the core values of Professional, Productive & Proactive.\u00a0\nWe are a group of young, energetic and ambitious talents who are committed to provide professional & tailor-made wealth management services to individuals, more than 50% of our talents with master\u2019s degree or above qualification. Most important, we have created a legend of 4 generations of TOT* in 2018.\u00a0\n\nApart from providing a comprehensive training in the field of medical, investment & law for CL-PRO teammates, we further encourage our teammates to better equip themselves with professional qualifications, such as CFA, CFP, FRM.\u00a0\n\nIn addition, CL-PRO\u2019 equally stress the importance of community\u2019s contribution. We regularly\u00a0organise\u00a0different team building activities, especially devoted ourselves\u00a0to support different social services at the community level.\u00a0\n*TOT = Top the Table Member, 6*times of MDRT requirement", "employment_types": ["Full Time", "Contract", "Internship"], "selling_points": ["Basic salary+ commission + bonus ($15000 - 50000)", "financial service; wealth management services", "Excellent career path to management level"], "locations": ["Central & Western Area"], "categories": ["Banking / Finance", "Financial Services", "Sales, CS & Business Devpt", "Sales - Sales Management", "Others", "Student / Fresh Graduate / No Experience"], "post_time": "2022-01-17T09:45:56Z", "salary": {"currency": null, "max": null, "min": null, "period": "monthly", "term": null}, "salary_visible": false, "title_keywords": ["wealth management", "trainee"], "responsibilities": ["management", "analysis", "review", "banking", "communication", "analyse", "planning"], "requirements": {"degrees": ["degree holder"], "majors": [], "languages": ["cantonese", "english", "mandarin"], "language_level": ["fluent"], "hard_skills": ["analysis"], "soft_skills": ["passionate", "outgoing", "self-motivated", "communication skills", "willing to learn", "mature", "comprehensive", "energetic", "interpersonal", "hardworking"], "languages_combined": [{"language": "cantonese", "language_level": ["fluent"]}, {"language": "english", "language_level": ["fluent"]}, {"language": "mandarin", "language_level": ["fluent"]}]}, "experience_required": {"duration": [], "field": ["banking industry", "tourism", "beauty", "retail"]}}, {"job_id": "100003009051635", "location_code": "hk", "company": "AIA International Limited", "job_title": "Wealth Management and Protection Manager (Local/Overseas/IANG Executive Development Program)", "description": "We are looking for:\n\nDegree holder\u00a0in all discipline\nEnergetic and outgoing\nMature, self\u00ad-motivated, hardworking and willing to learn\n1-2 years working experience is an advantage\nExperience\u00a0in banking industry or background in mainland will be an advantage\nOverseas Hong Kong Students are also welcome\nFluent in Cantonese, English and Mandarin is an advantage\u00a0\n\nResponsibilities:\n\nIdentifying needs of clients and providing\u00a0professional financial advice\nManagement of wealth assets of clients through investment vehicles\nUpdating financial news to your clients\nProviding\u00a0financial analyst, investment, saving, retirement, MPF\u00a0and\u00a0risk management\u00a0services\u00a0(Capital Investment Immigration Consultancy, Asset Management, Bonds & Mutual Funds Investment, Securities & Futures Dealing, Risk Management, Premium Financing)\nHigh End and Wealth Management for\u00a0HNW\u00a0and\u00a0PRC\u00a0Clients\nCorporate Solution Planning\u00a0for Corporate Clients\nProvide quality\u00a0after-sales services\u00a0to maintain good customer relationship\n\n\u00a0We\u00a0offer:\n\nOver 200 hours\u00a0well-structured and comprehensive mentoring program\nMonthly income from\u00a0HK$60,000 +\u00a0remuneration & fringe benefits\nOne year fast track program to managerial level\nSpecial holiday package\u00a0(2 company trips per year)\nOverseas learning experience\n\u201cWork Hard, Play Hard\u201dworking environment & lots of fun\nOpportunity to explore PRC and CIES business\n\nJob Description:\n\n1 \u00a0Professional Investment plannings for clients or companies\n\nWealth Management & Portfolio Advices\nInvestment Planning\nRetirement Planning\nPRC Business & CIES (Capital Investment Entrant Scheme) Planning\nCorporate Solutions Provision\n\n2 \u00a0Management level\n\nPlanning Strategies for Constructing Team\nLearn Leading, Recruiting & Managing Skills\nProvide marketing strategies skills\n\n3 \u00a0Self Continuous Improvement\n\nAchieve Professional Destinations (MDRT, COT, TOT, CFPCM,ChFC, RFP,RFC,etc.)\nAcquire Up-to-Date Financial Knowledge and News\nDevelop Better Interpersonal and Communication Skills\n\n4 \u00a0Development Path and Work Benefit\n\nA structured career path and solid training in all aspects of management\nYou will work very closely with a senior manager who will guide, train and mentor you\nManagement trainee programme offers excellent training and a fast track career into management\nSponsored overseas travelling for achieving yearly targets\n\nPlease click \"\u00a0APPLY NOW\u00a0'' if you are interested in our program.\u00a0\nWe always welcome talent.\u00a0", "employment_types": ["Full Time", "Permanent"], "selling_points": ["Monthly income from HK$60,000 +", "Special holiday package", "Overseas learning experience"], "locations": ["Quarry Bay"], "categories": ["Banking / Finance", "Financial Services", "Professional Services", "Business Analysis / Data Analysis", "Sales, CS & Business Devpt", "Business Development"], "post_time": "2022-01-16T16:03:43Z", "salary": {"currency": "HKD", "max": 89999, "min": 55000, "period": "monthly", "term": null}, "salary_visible": true, "title_keywords": ["executive", "wealth management and protection manager"], "responsibilities": ["management", "mpf", "quality", "planning", "maintain", "banking", "asset management"], "requirements": {"degrees": ["degree holder"], "majors": [], "languages": ["cantonese", "english", "mandarin"], "language_level": ["advantage", "fluent"], "hard_skills": [], "soft_skills": ["outgoing", "willing to learn", "mature", "energetic", "hardworking"], "languages_combined": [{"language": "cantonese", "language_level": ["fluent", "advantage"]}, {"language": "english", "language_level": ["fluent", "advantage"]}, {"language": "mandarin", "language_level": ["fluent", "advantage"]}]}, "experience_required": {"duration": ["1-2 years"], "field": ["banking industry"]}}, {"job_id": "100003009051760", "location_code": "hk", "company": "CMBC Capital Holdings Limited", "job_title": "Senior Manager \u2013  Risk Management", "description": "Job responsibilities:\n\n\nResponsible for risk monitoring, analysis and management reports for investments in secondary market.\nResponsible for the credit risk management functions in direct investments, loans, margin financing and investment banking businesses.\nPerform risk analysis, post-deal risk monitoring and portfolio analysis.\n\nJob requirements:\n\n\nDegree holder in Finance / Risk Management or related disciplines, CFA / FRM is a plus;\nAt least 6 years relevant experience preferably in sizeable Chinese securities firm or investment bank;\nResourceful, good team player; multi-task and work well under pressure;\nStrong commitment and high ethical standards;\nGood command of both written and spoken English and Chinese, proficiency\u00a0in Putonghua is preferred.", "employment_types": ["Full Time", "Permanent"], "selling_points": ["Responsible for the risk management functions", "Minimum 6 years of relevant experience", "Prepare ad hoc/ regular risk reports for managemnt"], "locations": ["Not Specified"], "categories": ["Banking / Finance", "Investment", "Financial Services", "Equities / Capital Markets"], "post_time": "2022-01-17T00:52:56Z", "salary": {"currency": null, "max": null, "min": null, "period": "monthly", "term": null}, "salary_visible": false, "title_keywords": ["senior manager"], "responsibilities": ["management", "analysis", "risk monitoring", "management reports", "risk analysis", "banking"], "requirements": {"degrees": ["degree holder"], "majors": ["related disciplines", "finance", "risk management"], "languages": ["putonghua", "english", "chinese"], "language_level": ["proficiency", "good command"], "hard_skills": ["cfa", "plus", "frm"], "soft_skills": ["good team player", "multi-task", "under pressure", "resourceful", "ethical"], "languages_combined": [{"language": "putonghua", "language_level": ["proficiency", "good command"]}, {"language": "english", "language_level": ["good command"]}, {"language": "chinese", "language_level": ["good command"]}]}, "experience_required": {"duration": ["at least 6 years"], "field": ["securities firm", "relevant experience", "investment bank"]}}, {"job_id": "100003009053123", "location_code": "hk", "company": "St. James's Place (Hong Kong) Limited", "job_title": "Compliance Officer and Regulatory Coordinator", "description": "Main Purpose of Job:\n\nProvide support to the Hong Kong Compliance team for compliance advisory and monitoring activities.\u00a0 Work closely with the Business to ensure that all members of staff, appointed representatives and those associated with the company are fully conversant with and adhere to all rules and regulations.\n\nProvide administrative support to the senior members of the Regulatory Division, comprising Risk, Compliance and legal, to ensure they liaise with both the Partnership and external parties in a timely and professional manner.\n\nKey Responsibilities of the Job:\n\nProvide support with all licensing-related matters with the SFC, IA and MPFA, including licensing applications, CPD/CPT tracking, and license renewal for individuals and our corporate entities.\u00a0\nAssist the licensing function and its associated risk to the business and escalate licensing risks to management in a timely fashion.\nGather related data for the completion of Compliance monitoring review and projects.\nCoordinate the distribution of compliance training materials and support with training to the Partnership and Business to ensure they are abreast of latest regulatory developments.\nProvide support to the Partnership and Business units regarding compliance best practices.\nProvide general support to the Compliance team as require.\nWork in partnership with the senior managers within the Regulatory Division to achieve the key strategic objectives. Anticipate the management team\u2019s requirements, understand the business pressures and unique challenges, and prioritize effectively for best use of their time.\nWork on a variety of projects and special assignments as necessary. Able to take initiative, use good judgment, understand deadlines, and carry multiple projects through to completion.\nUpdate and prepare reports related to the Regulatory Division as required.\n\nRequirements of the Job:\u00a0\n\nJob Knowledge:\n\n2 years\u2019 experience in financial industry.\nRelevant SFC and/or IA regulatory experience and/or product knowledge is an advantage.\n\nBusiness Expertise:\n\nAn understanding of the compliance and AML requirements of the Regulators relevant to the distribution activities in Hong Kong.\n\nProblem Solving:\n\nAbility to exercise sound judgement and initiative in making recommendations to resolve issues.\nTake a strategic approach to problem solving.\n\nNature and Scope of Impact:\n\nThe role contributes to the ability to exercise sound judgment and initiative in making recommendations to resolve compliance issues.\nProactive in approach and effective communication with all levels of the business.", "employment_types": ["Full Time"], "selling_points": ["MNC Working Environment", "Flexible Working", "Great Career Path"], "locations": ["Central"], "categories": ["Banking / Finance", "Investment", "Financial Services", "Wealth Management"], "post_time": "2022-01-17T05:57:59Z", "salary": {"currency": null, "max": null, "min": null, "period": "monthly", "term": null}, "salary_visible": false, "title_keywords": ["coordinator", "compliance officer"], "responsibilities": ["management team", "provide support", "management", "data", "compliance", "monitoring", "review", "coordinate", "prepare reports", "general support", "multiple projects", "tracking"], "requirements": {"degrees": [], "majors": [], "languages": [], "language_level": [], "hard_skills": ["problem solving", "aml"], "soft_skills": ["problem solving", "communication", "proactive", "initiative"], "languages_combined": []}, "experience_required": {"duration": ["2 years"], "field": ["financial industry"]}}, {"job_id": "100003009052050", "location_code": "hk", "company": "Hong Kong Interbank Clearing Ltd", "job_title": "Senior Manager (Human Resources)", "description": "Major Responsibilities\n\nResponsible for managing the full spectrum of human resources functions and overseeing the coordination and implementation of various human resources programs/initiatives covering compensation and benefits, talent acquisition, performance management, manpower planning and employee relations, etc.\nAssist in formulating and reviewing the Company\u2019s human resources policies and procedures, and monitoring their enforcement to ensure compliance with the related legislation and statutory requirements\nAnalyze market survey trends on human resources and compensation and benefits practices; and prepare total reward proposals to evaluate the effectiveness of existing compensation and benefits programmes with reference to market survey results\nManage staff recruitment to acquire talents and ensure the workforce is equipped with required skill sets for achieving the Company\u2019s business objectives\nCompile annual operating budget and other staff cost projections\nPlan and execute various employee development and training programmes, and handle employee relations matters\nRequirements\n\nUniversity education preferably majoring in human resources management, business studies or related disciplines\nAt least 10 years of relevant experience preferably gained from financial institutions with at least 5 years at managerial level\nWell versed in Hong Kong Employment Ordinance and related statutory requirements\nExcellent written and spoken English and Chinese, proficiency in Putonghua is an advantage\nCommitted, proactive, strong analytical, problem solving and leadership skills\nGood planning and organizing abilities with sound logical and numeric sense\nCandidates with more experience may be considered for a more senior position\nHow to Apply\nInterested parties please send your curriculum vitae stating your current and expected salaries, and the contact phone number to the Human Resources Division, Unit B, 25/F, MG Tower, 133 Hoi Bun Road, Kwun Tong, Kowloon\u00a0\u00a0by clicking the \"Apply Now\" button below.\nAll applications and personal information collected will be treated in strict confidence and only be used for the purpose of recruitment and selection.\u00a0 The information collected will be accessed by our authorized personnel only.\u00a0 Those applicants not contacted by the Human Resources Division within two months from their application date should consider their applications filed for future reference which will be retained for one year for possible future job matching, and will be destroyed after the expiry of one year.", "employment_types": ["Full Time", "Permanent"], "selling_points": [], "locations": ["Ngau Tau Kok"], "categories": ["Admin & HR", "Others", "Banking / Finance", "Financial Services", "HR Director / Manager"], "post_time": "2022-01-17T01:57:14Z", "salary": {"currency": null, "max": null, "min": null, "period": null, "term": null}, "salary_visible": false, "title_keywords": ["senior manager", "human resources"], "responsibilities": ["management", "policies", "monitoring", "procedures", "implementation", "ensure compliance", "statutory requirements", "coordination", "human resources functions", "planning"], "requirements": {"degrees": [], "majors": [], "languages": [], "language_level": [], "hard_skills": [], "soft_skills": [], "languages_combined": []}, "experience_required": {"duration": [], "field": []}}, {"job_id": "100003009052998", "location_code": "hk", "company": "Charison Co.", "job_title": "Relationship Manager (Wealth Management Centre) (Fresh Graduates are Welcome)", "description": "Responsibilities:\n\nStation at Wealth Management Centre\nPromote full range of wealth management product and services to high-net-worth customers in Wealth Management Centre\nDevelop and maintain customer relationships within the high-net-worth segment\n\u00a0Understand customers\u2019 wealth management needs and formulate appropriate solutions to meet the needs based on the customers\u2019 circumstances and risk appetite\n\u00a0Maintain good rapport with existing customers to explore new business opportunities in Hong Kong and China\nExpand new customers base in Wealth Management Centre\n\nRequirements:\n\nDegree holder would be an advantage\nStrong portfolio of HNW customers would be an advantage\nProficient in both spoken and written English and Chinese, fluency in Mandarin is preferable\nCandidates with IANG VISA/Spouse Visa would be an advantage\nCandidates with less experience will be considered as Assistant Relationship Manager\n\nWe offer:\n\nAttractive Remuneration Package\nWork-life Balance\nEnrichment of your Career Professionalism\nBright Career Future\nFriendly and Energetic Working Environment\nTraining and Development\n\nIf you aspire to an exciting and rewarding career, join us by clicking the button \u201cApply Now\u201d.", "employment_types": ["Full Time", "Part Time", "Permanent", "Contract"], "selling_points": ["Tertiary Education ; Degree Holder", "Wealth Management; Finance; Banking", "Flexible Working Hours"], "locations": ["Not Specified"], "categories": ["Banking / Finance", "Financial Services", "Sales, CS & Business Devpt", "Business Development", "Insurance", "Insurance Agent / Broker"], "post_time": "2022-01-17T04:55:17Z", "salary": {"currency": null, "max": null, "min": null, "period": "monthly", "term": null}, "salary_visible": false, "title_keywords": ["wealth management", "relationship manager"], "responsibilities": ["management", "maintain", "explore new business opportunities", "develop"], "requirements": {"degrees": ["degree holder"], "majors": [], "languages": ["english", "chinese", "mandarin"], "language_level": ["fluency", "proficient"], "hard_skills": [], "soft_skills": [], "languages_combined": [{"language": "english", "language_level": ["proficient"]}, {"language": "chinese", "language_level": ["proficient"]}, {"language": "mandarin", "language_level": ["fluency", "proficient"]}]}, "experience_required": {"duration": [], "field": []}}, {"job_id": "100003009051085", "location_code": "hk", "company": "Tampa Stone Co.", "job_title": "Business Development Manager  (30K above) (Part Time/ Full Time)", "description": "Job Description\n\nThis is a Golden opportunity to experience the Asset and Risk Management Industry. We believe in providing a high quality training of financial services that fosters continuous professional development to high new worth individuals and proven to significantly enhance client\u2019s portfolio.\n\nCandidates who are looking for an opportunity where provide professional training support to experience the business environment and career development are welcome to join our program:\n\nJob Duties:\n\nFollow up with potential clients\nManage and update clients\u00a0database\nIdentifying and developing client business relationships\nDevelop and maintain a strong working relationship with clients\nColdcall to constantly identify and initiate potential key accounts\nOrganize and participate in sales visits with potential and existing clients\nAny other administrative duties as assigned by immediate supervisor \u00a0\n\nRequirements:\n\nPassion to learn and become one of the successful leaders in the industry\nDegree Holder or above in any disciplines, Degree in Finance, Economics, Financial Engineering would be an advantage.\nProficiency in both written and spoken English and Cantonese, proficiency in Mandarin would be an advantage.\nFresh graduates with good interpersonal skills and great eagerness to learn and explore in order to become one of the successful leaders in the industry are welcome.\n\nDO NOT GIVE YOURSELF ANY LIMITATION, PASSION IS ALWAYS YOUR WINNING KEY.\n\nOur offer:\n\nPleasure working environment and warm spirit and atmosphere (incentive trips and oversea conferences)\nProfessional training program with successful leaders in the finance industry\u00a0\n5-day work week with flexible hours\nExcellent opportunities to corporate with different finance firms in the industry\nSFC, CFA, CPA, CFP, CIWM examinations resources and support with individual sponsorship provided, we feel like and we encourage our employees to gain these professional certification.\nPerformance bonus\u00a0\nMedical scheme & study allowance", "employment_types": ["Full Time"], "selling_points": [], "locations": ["Wan Chai Area"], "categories": ["Banking / Finance", "Financial Services", "Management", "General Management", "Others", "Student / Fresh Graduate / No Experience"], "post_time": "2022-01-15T01:59:26Z", "salary": {"currency": null, "max": null, "min": null, "period": "monthly", "term": null}, "salary_visible": false, "title_keywords": ["business development manager"], "responsibilities": ["management", "quality", "developing", "develop", "maintain", "administrative duties", "database", "career development"], "requirements": {"degrees": ["degree", "degree holder"], "majors": ["finance", "economics", "any disciplines", "engineering"], "languages": ["cantonese", "english", "mandarin"], "language_level": ["advantage", "proficiency"], "hard_skills": ["cfa", "scheme", "cpa"], "soft_skills": ["flexible", "interpersonal skills"], "languages_combined": [{"language": "cantonese", "language_level": ["advantage"]}, {"language": "english", "language_level": ["advantage"]}, {"language": "mandarin", "language_level": ["proficiency", "advantage"]}]}, "experience_required": {"duration": [], "field": []}}, {"job_id": "100003009052896", "location_code": "hk", "company": "Hong Kong Client Service International Limited", "job_title": "Sales Manager / Assistant Sales Manager (Full time / Part time)", "description": "Qualification :\n- Bachelor's degree or above\n- At least 5 years of solid sales experience in software company, familiar with banking customer in HK area, especially with local large scale bank (candidate with less experience will be considered for the post of assistant Sales Manager).\n- Familiar with IT project especially in the bank field (It is a must)\n- Full time / Part time\n- Good command of both spoken and written English, Mandarin and Cantonese\n\nResponsibility :\n- Establish, develop and maintain effective business relationships with potential and existing customers.\n- Collect the market information for formulating relevant strategies to gain market share\n-\u00a0Propose and promote company IT solutions and services to existing and potential customers\n\nInterested candidates, kindly send your detailed resume including:\n1) Expected salary/commission\n2) Current and last drawn salaries\n3) Reason for leaving current and past employments", "employment_types": ["Full Time", "Part Time"], "selling_points": ["Sales Manager / Assistant Sales Manager", "Central Area", "Familiar with IT project especially in the bank"], "locations": ["Central"], "categories": ["Banking / Finance", "Financial Services", "Information Technology (IT)", "IT Project Management / Team Lead", "Sales, CS & Business Devpt", "Direct Sales"], "post_time": "2022-01-17T04:28:06Z", "salary": {"currency": null, "max": null, "min": null, "period": "monthly", "term": null}, "salary_visible": false, "title_keywords": ["assistant sales manager", "sales manager"], "responsibilities": ["market information", "software", "develop", "maintain", "banking"], "requirements": {"degrees": ["degree or above", "bachelor"], "majors": [], "languages": ["cantonese", "english", "mandarin"], "language_level": ["good command"], "hard_skills": [], "soft_skills": [], "languages_combined": [{"language": "cantonese", "language_level": ["good command"]}, {"language": "english", "language_level": ["good command"]}, {"language": "mandarin", "language_level": ["good command"]}]}, "experience_required": {"duration": ["at least 5 years"], "field": ["banking"]}}, {"job_id": "100003009049184", "location_code": "hk", "company": "Hong Kong Interbank Clearing Ltd", "job_title": "Manager (Finance)", "description": "Responsibilities\n\nPrepare and review financial statements, management accounting reports, operating budget, statutory reports, business and financial analyses etc.\nPerform analyses on the company\u2019s operating performance against budget estimates\nReview financial analyses to be provided to external auditors in the annual financial audit and assist the external auditors in the operations audit\nReview cash positions and assist in liquidity management of the company\nManage the whole set of general ledger and accounts payable and receivable functions\nOversee the enhancement of the computerized systems for accounting and management data and manage user acceptance tests of new projects to ensure proper changes to the billing and accounting systems\nInitiate improvement of relevant accounting and tax planning processes\nManage relationships with bankers, auditors and internal/external stakeholders\nSupervise the finance team in general accounting operations\nPerform ad-hoc duties as assigned by superiors\nRequirements\n\nUniversity degree in accounting with HKICPA or equivalent professional qualification\nOver 8 years\u2019 accounting experience preferably in financial institutions or sizable organizations\nExcellent command of spoken and written English and Chinese\nGood knowledge of computerized accounting systems and PC applications\nStrong logical thinking, sound analytical skills and able to present ideas in an organized manner\nGood supervisory skill, self-motivated, independent and able to work under pressure\nCandidates with less experience may be considered for the position of Deputy Manager (Finance)\nHow to Apply\nInterested parties please send your curriculum vitae stating your current and expected salaries, and the contact phone number to the Human Resources Division, Unit B, 25/F, MG Tower, 133 Hoi Bun Road, Kwun Tong, Kowloon\u00a0\u00a0by clicking the \"Apply Now\" button below.\nAll applications and personal information collected will be treated in strict confidence and only be used for the purpose of recruitment and selection.\u00a0 The information collected will be accessed by our authorized personnel only.\u00a0 Those applicants not contacted by the Human Resources Division within two months from their application date should consider their applications filed for future reference which will be retained for one year for possible future job matching, and will be destroyed after the expiry of one year.", "employment_types": ["Full Time", "Permanent"], "selling_points": [], "locations": ["Ngau Tau Kok"], "categories": ["Accounting", "Finance / Accounting Manager", "Banking / Finance", "Financial Services", "Others"], "post_time": "2022-01-14T08:14:00Z", "salary": {"currency": null, "max": null, "min": null, "period": null, "term": null}, "salary_visible": false, "title_keywords": ["manager"], "responsibilities": ["tax", "management", "data", "operations", "general ledger", "review", "budget", "audit", "financial statements", "systems", "planning", "reports", "ad-hoc duties", "supervise the finance team", "accounts payable", "external auditors"], "requirements": {"degrees": ["university degree"], "majors": ["accounting"], "languages": ["english", "chinese"], "language_level": ["excellent"], "hard_skills": ["accounting systems", "pc applications", "analytical skills", "hkicpa"], "soft_skills": ["organized", "self-motivated", "independent", "analytical skills", "work under pressure"], "languages_combined": [{"language": "english", "language_level": ["excellent"]}, {"language": "chinese", "language_level": ["excellent"]}]}, "experience_required": {"duration": ["8 years"], "field": ["finance", "accounting experience", "financial institutions"]}}, {"job_id": "100003009051506", "location_code": "hk", "company": "The Aurora", "job_title": "Management Trainee \uff08\u61c9\u5c46\u7562\u696d\u751f\u512a\u5148\uff0cSalary 20k-30k\uff09", "description": "We are young, energetic and enthusiastic team, which aim to learn new things for their personal and professional development. Here we create a working environment that enables everyone to grow.\n\nJob Responsibilities\uff1a\n\u2022Sales and marketing\n\u2022Staff Management\n\u2022Account Management\n\nEducation Level\uff1a\n\u2022HKCEE / DSE Pass\n\nEntry Requirements\uff1a\n\u2022 Good communication skills\u00a0\n\u2022 Interpersonal skills\n\u2022\u00a0Responsible\n\u2022\u00a0Punctuality\n\nCompany Benefits\uff1a\n\u2022\u00a05 days working\u00a0\n\u2022 Training\n\u2022\u00a0Travel rewards\n\u2022 Cash rewards\n\u2022\u00a0Continuing education opportunities\n\nIf you are interested, please click APPLY\n\n", "employment_types": ["Full Time", "Part Time", "Internship"], "selling_points": [], "locations": ["Wan Chai"], "categories": ["Banking / Finance", "Financial Services", "Marketing / Public Relations", "Management", "Management", "Management Trainee"], "post_time": "2022-01-16T06:13:55Z", "salary": {"currency": null, "max": null, "min": null, "period": "monthly", "term": null}, "salary_visible": false, "title_keywords": ["management trainee"], "responsibilities": ["management"], "requirements": {"degrees": [], "majors": [], "languages": [], "language_level": [], "hard_skills": [], "soft_skills": ["communication skills", "interpersonal skills", "responsible"], "languages_combined": []}, "experience_required": {"duration": [], "field": []}}, {"job_id": "100003009054235", "location_code": "hk", "company": "SinoPac Securities (Asia) Limited", "job_title": "Sales, Fixed Income Division", "description": "RESPONSIBILITIES\nProviding support to sales team and help execute trades\nExisting client network of fixed income trader/portfolio managers across the buy side segment\nPreparing presentations, pitches, proposals, client materials and the supporting analysis\nAbility to create, develop and execute upon regional sales strategies\n\n\u00a0REQUIREMENTS\n\nUniversity graduate or above\nGood knowledge of Fixed Income Products\nStrong client network in China/HK/Taiwan preferred\nProficiency in MS Office applications, including MS Word & Excel, VBA, PowerPoint and Chinese word processing\u00a0\u00a0\u00a0\u00a0\nBe proactive, aggressive and a team player with good integrity\nProficient in both written and spoken English and Mandarin\nA competitive remuneration package will be offered. Please send your detailed resume, including present and expected salary as well as availability date, to Human Resources Department, SinoPac Securities (Asia) Limited, 7/F., Lee Garden Three, 1 Sunning Road, Causeway Bay, Hong Kong or by clicking \u201cApply Now\u201d.\u00a0\n\n\n\nAll personal data collected will be used for recruitment purpose only and will be kept strictly confidential. Only short-listed candidates will be notified.", "employment_types": ["Full Time", "Permanent"], "selling_points": ["5-days work", "University graduate or above", "Good knowledge of Fixed Income Products"], "locations": ["Causeway Bay"], "categories": ["Banking / Finance", "Financial Services", "Others"], "post_time": "2022-01-17T08:52:50Z", "salary": {"currency": null, "max": null, "min": null, "period": "monthly", "term": null}, "salary_visible": false, "title_keywords": ["sales"], "responsibilities": ["providing support to sales team", "analysis", "presentations", "develop"], "requirements": {"degrees": ["university graduate or above"], "majors": [], "languages": ["english", "chinese", "mandarin"], "language_level": ["proficiency", "proficient"], "hard_skills": ["excel", "vba", "chinese word processing", "powerpoint", "ms office", "ms word"], "soft_skills": ["team player", "proactive", "integrity", "detailed"], "languages_combined": [{"language": "english", "language_level": ["proficient"]}, {"language": "chinese", "language_level": ["proficiency"]}, {"language": "mandarin", "language_level": ["proficient"]}]}, "experience_required": {"duration": [], "field": []}}, {"job_id": "100003009049143", "location_code": "hk", "company": "Shanghai Commercial Bank Ltd", "job_title": "Assistant Relationship Manager, Investment & Insurance Services", "description": "To support business growth, we are expanding our team of relationship managers in Retail Banking Business and are seeking high calibre professionals to fill the position.\n\nResponsibilities:\n\nProvide financial solutions to customers to achieve business targets on wealth management (investment & insurance)\nIdentify customer needs through financial analysis and portfolio review\nCultivate long-term relationship with customers and explore new business opportunities through marketing and cross-selling bank products and services\n\nRequirements:\n\nDegree holder in Business or related disciplines\nMinimum 2 years of sales experience in promoting the full range of wealth management products including both investment and insurance product\nQualified individual to carry out regulated activities in insurance and investment\nSelf-motivated, customer-centric and able to work under pressure\nExcellent interpersonal, relationship management and communication skills\nExcellent command of spoken and written English and Chinese, including Putonghua\nProficient in MS Office applications including Chinese word processing\n\nAttractive remuneration package will be offered to the right candidates. Interested parties please click \"Apply Now\" to submit your full resume with current and expected salary to the Human Resources Division.\n\nPlease visit us at www.shacombank.com.hk for more information about our Bank.\n\nAll personal data collected will be used for recruitment related purposes strictly in accordance with the Bank's personal data policies, a copy of which will be provided immediately upon request by contacting our Personal Data Compliance Officer. Applicants who are not contacted within two months may consider their applications unsuccessful and the personal data collected from the applicants will be retained for no longer than two years from the date of rejection during which the applicants may be considered for other suitable positions within the Bank.", "employment_types": ["Full Time", "Permanent"], "selling_points": ["Provide financial solutions to customers", "Identify customer needs through financial analysis", "Cultivate long-term relationship with customers"], "locations": ["Not Specified"], "categories": ["Banking / Finance", "Investment", "Retail Banking", "Financial Services"], "post_time": "2022-01-15T03:50:08Z", "salary": {"currency": null, "max": null, "min": null, "period": "monthly", "term": null}, "salary_visible": false, "title_keywords": ["assistant relationship manager"], "responsibilities": ["management", "explore new business opportunities", "review", "financial analysis", "insurance"], "requirements": {"degrees": ["degree holder"], "majors": ["related disciplines", "business"], "languages": ["putonghua", "english", "chinese"], "language_level": ["excellent", "proficient"], "hard_skills": ["chinese word processing", "ms office"], "soft_skills": ["communication skills", "self-motivated", "interpersonal", "work under pressure"], "languages_combined": [{"language": "putonghua", "language_level": ["excellent"]}, {"language": "english", "language_level": ["excellent"]}, {"language": "chinese", "language_level": ["excellent", "proficient"]}]}, "experience_required": {"duration": ["minimum 2 years"], "field": ["management", "insurance", "investment"]}}, {"job_id": "100003009053363", "location_code": "hk", "company": "Right Person Found Consultant Company", "job_title": "Management Trainee", "description": "Our client is a fast-growing and well structured company in Asia that rewards hard working and life balancing. We are seeking an energetic, young and motivated individual to join the 2021 summer trainee program.\u00a0\n\nIn this position, you will\u00a0\n- Receive training in different areas by levels\n- Practice new skills to provide administrative and analytical support\u00a0\n- Conduct analyses on global economy\u00a0\n- Meet up with corporate and individual Clients regularly\u00a0\n- Establish and maintain good relationship with clients\n- Fast track promotion to management level\u00a0\n\nSkills and Qualifications\u00a0\n- Degree holders or above, graduated from oversea and IANG are welcomed\u00a0\n- Strong desire to learn and develop yourself\u00a0\n- Open minded with positive attitude\u00a0\n\nBenefits\n- Medical insurance\u00a0\n- Flexible working hours\u00a0\n- Oversea Convention trips\n- On going professional trainings\u00a0\n- Young and Fun working atmosphere\u00a0", "employment_types": ["Full Time"], "selling_points": ["Young and Fun working atmosphere", "Fast track promotions to different levels", "Hard working and life balancing"], "locations": ["Quarry Bay"], "categories": ["Banking / Finance", "Investment", "Financial Services", "Management", "Management Trainee"], "post_time": "2022-01-17T06:51:22Z", "salary": {"currency": "HKD", "max": 44999, "min": 17000, "period": "monthly", "term": null}, "salary_visible": true, "title_keywords": ["management trainee"], "responsibilities": ["develop", "management", "maintain good relationship"], "requirements": {"degrees": ["degree"], "majors": [], "languages": [], "language_level": [], "hard_skills": [], "soft_skills": ["hard working", "positive attitude", "motivated individual", "open minded", "structured", "energetic"], "languages_combined": []}, "experience_required": {"duration": [], "field": []}}, {"job_id": "100003009050361", "location_code": "hk", "company": "First Shanghai Securities Limited", "job_title": "Research Analyst", "description": "Job Responsibilities:\n\nAssist Senior Research Analyst to assess internal business and affairs\nAssist Analyst with data research and analysis\nTravel to mainland China is requested\n\nJob Requirements:\n\nDegree holder or above in economics, finance or related disciplines\nPossess professional qualification (I.e. CPA, CFA) is preferred\nHolder of SFC RA4 License will be an advantage\nStrong analytical skills and presentation skills\nGood communication and interpersonal skills\nProficient in MS word, PowerPoint, Excel and Chinese words processing\nProficiency in both spoken and written in English and Chinese (including Mandarin)\nWith relevant working or intern experience is preferred\n\n\n\nWe offer attractive package including\u00a05 days work, Year-end bonus and medical insurance\u00a0to the right candidate. Please apply with full resume stating present & expected salary and date available to: The Human Resources Manager by\u00a0clicking APPLY NOW.\n\n(Personal data collected would be used for recruitment purpose only.)", "employment_types": ["Full Time", "Permanent"], "selling_points": [], "locations": ["Central & Western Area"], "categories": ["Banking / Finance", "Investment", "Financial Services"], "post_time": "2022-01-14T10:12:11Z", "salary": {"currency": null, "max": null, "min": null, "period": null, "term": null}, "salary_visible": false, "title_keywords": ["research analyst"], "responsibilities": ["analysis", "data"], "requirements": {"degrees": ["degree holder"], "majors": ["related disciplines", "finance", "economics"], "languages": ["english", "chinese", "mandarin"], "language_level": ["proficiency", "proficient"], "hard_skills": ["excel", "words", "cfa", "powerpoint", "analytical skills", "cpa", "processing", "ms word"], "soft_skills": ["presentation skills", "communication and interpersonal skills", "analytical skills"], "languages_combined": [{"language": "english", "language_level": ["proficiency"]}, {"language": "chinese", "language_level": ["proficiency", "proficient"]}, {"language": "mandarin", "language_level": ["proficiency"]}]}, "experience_required": {"duration": [], "field": []}}, {"job_id": "100003009046570", "location_code": "hk", "company": "BOCI", "job_title": "AVP, Client Support, Investment Services", "description": "The Role\n\nNon-sales client support role in our brokerage business.\n\nKey Accountabilities\n\nSupport our securities and derivatives brokerage services\nAssist and manage the daily operation of the brokerage team\nProvide customer services and execute trades (equities, derivatives, OTC, etc.)\nAssist in trading and dealing streamlining projects\n\nSkills & Experience\n\nDiploma or above in relevant disciplines\nStrong language skills including spoken Mandarin\nPractical knowledge in financial products\nAt least 3-5 years of experience in securities broker / bank\nSFC type 1 and 2 preferred\n\nOther Information\n\nNotes to applicants:\n1. Please apply in strict confidence with full resume, academic record, current and expected salaries.\n2. The personal data provided will be used for consideration of recruitment only. All personal data of unsuccessful candidate will be destroyed within 24 months.\n3. Candidates with Enhanced Competency Framework (ECF): please state on the CV.\n\nAbout BOCI\n\nAs a leading investment bank in China and Hong Kong region, the investment banking arm of Bank of China, BOC International Holdings Limited (\u201cBOCI\u201d), is now seeking highly motivated, creative and success-oriented professional who would like to pursue the career in our group.\u00a0", "employment_types": ["Full Time"], "selling_points": ["Client servicing role for our brokerage business", "3-5 years of financial client service experience", "SFC type 1 and 2 preferred"], "locations": ["Sheung Wan"], "categories": ["Banking / Finance", "Investment", "Financial Services", "Equities / Capital Markets"], "post_time": "2022-01-13T14:26:05Z", "salary": {"currency": null, "max": null, "min": null, "period": "monthly", "term": null}, "salary_visible": false, "title_keywords": [], "responsibilities": ["brokerage", "daily operation", "customer services", "recruitment", "banking", "personal data"], "requirements": {"degrees": ["diploma or above"], "majors": [], "languages": ["mandarin"], "language_level": [], "hard_skills": [], "soft_skills": ["motivated", "confidence", "creative"], "languages_combined": [{"language": "mandarin", "language_level": []}]}, "experience_required": {"duration": ["at least 3-5 years"], "field": ["securities"]}}, {"job_id": "100003009053231", "location_code": "hk", "company": "Recruit HK", "job_title": "Insurance Broker - Wealth Management Consultant", "description": "A golden opportunity to provide private client services to high net worth individuals. We believe our approach is paramount, and proven to be a necessity in each individual\u2019s portfolio.\n\nIf you are seeking a role where you become a complete young entrepreneur, where growth and opportunities are unlimited, this platform will fulfil your aspirations.\n\nOur vision is to develop people's talents and potentials throughout providing professional wealth management services to the clients.\n\u00a0 \u00a0 \u00a0 \u00a0 \u00a0 \u00a0 \u00a0 \u00a0 \u00a0 \u00a0 \u00a0 \u00a0 \u00a0 \u00a0 \u00a0 \u00a0 \u00a0 \u00a0 \u00a0 \u00a0 \u00a0 \u00a0 \u00a0 \u00a0 \u00a0 \u00a0 \u00a0 \u00a0 \u00a0 \u00a0 \u00a0 \u00a0 \u00a0 \u00a0 \u00a0 \u00a0 \u00a0 \u00a0 \u00a0 \u00a0 \u00a0 \u00a0 \u00a0 \u00a0 \u00a0 \u00a0 \u00a0 \u00a0 \u00a0 \u00a0 \u00a0 \u00a0 \u00a0 \u00a0 \u00a0 \u00a0 \u00a0 \u00a0 \u00a0 \u00a0 \u00a0 \u00a0 \u00a0 \u00a0 \u00a0 \u00a0 \u00a0\n\u00a0 \u00a0 \u00a0 \u00a0 \u00a0 \u00a0 \u00a0 \u00a0 \u00a0 \u00a0 \u00a0 \u00a0 \u00a0 \u00a0 \u00a0 \u00a0 \u00a0 \u00a0 \u00a0 \u00a0 \u00a0 \u00a0 \u00a0 \u00a0 \u00a0 \u00a0 \u00a0 \u00a0 \u00a0 \u00a0 \u00a0 \u00a0 \u00a0 \u00a0 \u00a0 \u00a0 \u00a0 \u00a0 \u00a0 \u00a0 \u00a0 \u00a0 \u00a0 \u00a0 \u00a0 \u00a0 \u00a0 \u00a0 \u00a0 \u00a0 \u00a0 \u00a0 \u00a0 \u00a0 \u00a0 \u00a0 \u00a0 \u00a0 \u00a0 \u00a0 \u00a0 \u00a0 \u00a0 \u00a0 \u00a0 \u00a0 \u00a0 \u00a0 \u00a0 \u00a0 \u00a0 \u00a0 \u00a0 \u00a0\n\nInsurance Broker - Wealth Management Consultant\n\nResponsibilities:\n\nProvide comprehensive financial and banking advice to clients on\u00a0risk-and wealth-management products, Insurance, MPF and employee-benefits products\nAnalyze and compare products of different service providers/ insurance companies\nConstant monitoring of investment portfolios\nDevelop and expand existing network through relationship management\n\nRequirements:\n\nFresh graduates/ IANG will also be considered\nMature, self-motivated, hardworking and willing to learn\nEnergetic and outgoing\nGood interpersonal and communication skills\nAlways serve in the best interest of clients\nAllow to work in Hong Kong is a must\n\nIncentive:\n\nAttractive commission and bonus with allowance package\nFast-track promotion to managerial position\nOverseas trips & conventions plus excellent career path\nExcellent and comprehensive in-house training programs\nProfessional training to become a\u00a0Millionaires\n\n\n\u8ca1\u5bcc\u7ba1\u7406\u90e8 - \u7368\u7acb\u7406\u8ca1\u9867\u554f\n\n\u8077\u52d9:\n\n\u70ba\u5ba2\u6236\u5728\u98a8\u96aa\u53ca\u8ca1\u5bcc\u7ba1\u7406\u7522\u54c1\u3001\u4fdd\u96aa\u3001\u5f37\u7a4d\u91d1\u3001\u50f1\u54e1\u798f\u5229\u7522\u54c1\u7b49\u7bc4\u7587\uff0c\u63d0\u4f9b\u4e00\u7ad9\u5f0f\u6295\u8cc7\u53ca\u7406\u8ca1\u7b56\u5283\u65b9\u6848\u3002\n\u91dd\u5c0d\u5e02\u9762\u4e0a\u4e0d\u540c\u7684\u91d1\u878d\u6a5f\u69cb/\u4fdd\u96aa\u516c\u53f8\u7684\u7522\u54c1\u4f5c\u5206\u6790\u6bd4\u8f03\u3002\n\u70ba\u5ba2\u4eba\u4e4b\u6295\u8cc7\u65b9\u6848\u4f5c\u6301\u7e8c\u76e3\u5bdf\u53ca\u8abf\u6574\n\u5275\u5efa\u4eba\u8108\u8cc7\u6e90\u4f5c\u696d\u52d9\u63a8\u5ee3\n\n\u5165\u8077\u8981\u6c42:\n\n\u5927\u5b78\u7562\u696d\u6216\u6709\u76f8\u95dc\u5de5\u4f5c\u7d93\u9a57\u70ba\u4f73 (IANG\u4ea6\u53ef)\n\u80fd\u7368\u7acb\u5de5\u4f5c\u3001\u81ea\u5f8b\u3001\u6709\u6c42\u77e5\u617e\n\u6b63\u9762\u5fc3\u614b\u3001\u5916\u5411\u3001\u52c7\u65bc\u63a5\u53d7\u6311\u6230\n\u64c5\u65bc\u6e9d\u901a\n\u80fd\u4ee5\u5ba2\u6236\u5229\u76ca\u70ba\u5148\u3001\u6709\u4f7f\u547d\u611f\n\u6301\u6709\u6548\u9999\u6e2f\u5de5\u4f5c\u6191\u8b49\n\n\u798f\u5229:\n\n\u5e95\u85aa + \u4f63\u91d1\u53ef\u9054HKD100,000\u4e00\u500b\u6708\n\u5feb\u901f\u6649\u5347\u6977\u68af\uff0c\u5230\u4e3b\u7ba1\u7d1a\u5225\u53ef\u5275\u7acb\u81ea\u5df1\u5718\u968a\n\u6bcf\u5e74\u6d77\u5916\u6703\u8b70\u3001\u9054\u6a19\u734e\u52f5\n\u5b8c\u5584\u4e4b\u65b0\u4eba\u57f9\u8a13\u3001\n\u65b0\u4eba\u798f\u5229\uff0c\u52a9\u65b0\u4eba\u6700\u5feb\u9054\u6210\u767e\u842c\u5e74\u85aa", "employment_types": ["Full Time", "Part Time", "Permanent"], "selling_points": ["Basic salary and commission package", "Insurance, MPF, Mutual fund, Bond, Mortgage", "IIQE Paper 1,2,3 and 5 & SFC 1,7 and 8"], "locations": ["Central & Western Area"], "categories": ["Banking / Finance", "Financial Services", "Insurance", "Insurance Agent / Broker", "Wealth Management"], "post_time": "2022-01-17T06:30:00Z", "salary": {"currency": null, "max": null, "min": null, "period": "monthly", "term": null}, "salary_visible": false, "title_keywords": ["wealth management consultant"], "responsibilities": [], "requirements": {"degrees": [], "majors": [], "languages": [], "language_level": [], "hard_skills": [], "soft_skills": [], "languages_combined": []}, "experience_required": {"duration": [], "field": []}}, {"job_id": "100003009052164", "location_code": "hk", "company": "CACEIS Hong Kong Trust Company Limited", "job_title": "Fund Accountant/ Senior Fund Accountant", "description": "Job Responsibilities:\nOperational duties\nTo calculate Net Asset Values and be responsible of the perimeter of NAV\u2019s cycle\nTo deliver on time\nTo ensure first level control of produced NAV\nTo respect the internal procedures for NAV\u2019s calculation and controls\nTo deal with cash, stocks and holdings reconciliations\nTo investigate on discrepancies and/or exceptions\nTo liaise with various departments of our local and European offices\nTo answer internal & external clients\u2019 request\nSupervisory duties if applicable\nTo work autonomously\nTo train the staff\nTo handle complex topics\nTo be in charge of projects\nTo liaise with management and communicate about operational issues\nTo take charge of any tasks the manager delegates\nTo encourage team spirit\nRequirement:\nDegree holder, with a major in accounting or finance, qualified accountant / professional qualifications\nSupervisory experience required for senior role\n\nTeam spirit combined with the ability to work autonomously and pro-actively\nExcellent communication skills and well organized\nFluency in English/ Mandarin. Knowledge in French/ Japanese/ Korean and other Asian/ foreign languages would be an advantage\nCandidate with less experience will be considered for a junior role.\nCompetitive remuneration package will be offered to the successful applicant. We offer an environment that encourages diversity and professional continuous development. Aspiring talents please send your resume via JobsDB. Personal data provided in job applications will be used strictly in accordance with\u00a0 our personal data policy, a copy of which is available upon request.\nFor more information about the Group, please visit www.caceis.com", "employment_types": ["Full Time", "Permanent"], "selling_points": [], "locations": ["Admiralty"], "categories": ["Accounting", "Accountant", "Banking / Finance", "Financial Services", "Fund Management"], "post_time": "2022-01-17T02:18:36Z", "salary": {"currency": null, "max": null, "min": null, "period": "monthly", "term": null}, "salary_visible": false, "title_keywords": ["accountant"], "responsibilities": ["control", "management", "procedures", "liaise with various departments", "reconciliations", "liaise with", "operational duties"], "requirements": {"degrees": ["degree holder"], "majors": ["finance", "accounting"], "languages": ["english", "french", "mandarin", "japanese", "korean"], "language_level": ["fluency", "advantage"], "hard_skills": ["professional qualifications"], "soft_skills": ["communication skills", "team spirit", "well organized"], "languages_combined": [{"language": "english", "language_level": ["fluency"]}, {"language": "french", "language_level": ["advantage"]}, {"language": "mandarin", "language_level": ["fluency"]}, {"language": "japanese", "language_level": ["advantage"]}, {"language": "korean", "language_level": ["advantage"]}]}, "experience_required": {"duration": [], "field": ["supervisory experience"]}}, {"job_id": "100003009054530", "location_code": "hk", "company": "Hong Leong Bank Berhad", "job_title": "Assistant Manager, Financial Control", "description": "Responsibilities:\n\nPrepare timely and accurate HKMA Returns, and other banking regulatory returns as required for submission on time, including liquidity positions returns and daily monitoring, and other statutory reporting submissions;\nEnsure compliance with internal standards, controls and policies;\nResponsible for local financial reporting, Head Office reporting and financial disclosure of the bank per government regulations, accounting standards and the Bank\u2019s policies;\nPrepare management reports and presentation materials for senior management meeting;\nAssist in budget and forecast process, automation and process improvement projects\nAttend enquiries from the HKMA, internal and external auditors, Head Office and stakeholder;\nEngage in ad-hoc assignments.\n\nRequirements:\n\nDegree holder in Finance/ Accountancy/ Information System\nHKICPA or equivalent qualifications\nAt least 4 years of accounting/ audit experience with financial services industry\nStrong organizational skills including the ability to coordinate, prioritize and manage multiple activities to meet deadlines\nProactive self-starter, comfortable with working autonomously and have a strong sense of responsibility\nConversant with MS Office application. Knowledge of Excel VBA and MS SQL would be an advantage\nFluent in English and Chinese\n\nAll applications will be treated in strict confidence and used for recruitment purpose within Hong Leong Bank Berhad, Guoco Group Limited, or Hong Leong Group of which Guoco is a member (together, \u201cthe Group\u201d) only. A copy of our personal data policy is available on request.\n\nApplicants not hearing from us within 8 weeks may consider their applications unsuccessful. We may also consider their application for other or future vacancies within the Group. Personal data of unsuccessful applicants will be retained by the Group for a maximum period of one year.", "employment_types": ["Full Time", "Permanent"], "selling_points": [], "locations": ["Central"], "categories": ["Accounting", "Finance / Accounting Manager", "Banking / Finance", "Corporate Finance", "Financial Services"], "post_time": "2022-01-17T09:53:54Z", "salary": {"currency": null, "max": null, "min": null, "period": "monthly", "term": null}, "salary_visible": false, "title_keywords": ["assistant manager,"], "responsibilities": ["regulations", "reporting", "forecast process", "bank\u2019s policies", "policies", "ad-hoc assignments", "budget", "ensure compliance", "management reports", "financial reporting", "banking", "senior management", "daily monitoring", "external auditors"], "requirements": {"degrees": ["degree holder"], "majors": ["finance", "accountancy"], "languages": ["english", "chinese"], "language_level": ["fluent"], "hard_skills": ["excel", "vba", "information system", "hkicpa", "ms sql", "ms office"], "soft_skills": ["organizational skills", "confidence", "sense of responsibility", "prioritize", "meet deadlines", "proactive"], "languages_combined": [{"language": "english", "language_level": ["fluent"]}, {"language": "chinese", "language_level": ["fluent"]}]}, "experience_required": {"duration": ["at least 4 years"], "field": ["audit experience", "accounting", "financial services industry"]}}, {"job_id": "100003009046964", "location_code": "hk", "company": "China Construction Bank (Asia) Corporation Limited", "job_title": "Senior Relationship Manager, Corporate Banking II (Big 4 Candidates are welcomed)", "description": "Main Responsibilities :\n\nAssist in achieving the overall financial and business targets set by the Bank and maintaining the quality of lending\nLiaise with the Bank\u2019s other Divisions, CCBC domestic and overseas branches to achieve cross selling and risk control\nCommunicate with Risk Management /Operations /Legal and Compliance etc. for efficient internal approval while meeting the respective compliance requirements\nAssist in managing a substantial loan portfolio of blue chips (mainly in areas entrusted to her / his team) to derive maximum profitability for the Bank while maintaining the quality of the lending\nTake initiative to recommend new products that suit the customer\u2019s needs and maintain high standard of service so as to continually expanding the customer base by means of attracting new and retaining existing clients\nKeep regular contacts with other financial institutions to collect the information of the existing customers of the Bank in covered areas for risk monitoring, identify banking opportunities and make recommendation to the Bank and/or CCBC relevant branches\nConduct regular KYC assessment on a timely basis and to ensure client onboarding activity is complied with the AML policy and procedures\nTimely report of the work progress\n\nRequirements :\n\nUniversity degree in business or related disciplines\nMinimum 5 years\u2019 relevant banking experience\nStrong marketing skills with an ability to sell banking services to a competitive market in a highly motivated and profitable manner\nNetwork of relationships with corporate customers and financial institutions\nSound credit analysis skills relating to corporate, sovereign and bank debt\nGood command of both English and Chinese, including Putonghua\nWilling to travel\n\nApplicants who are not contacted within 8 weeks may consider their applications unsuccessful and their personal data will be retained by the bank for a period up to two years.\n\nAll information provided by applicants will be used for recruitment purposes only and will be used strictly in accordance with the bank\u2019s personal data policies, a copy of which will be provided upon request.", "employment_types": ["Full Time"], "selling_points": [], "locations": ["Not Specified"], "categories": ["Banking / Finance", "Financial Services", "Equities / Capital Markets", "Others"], "post_time": "2022-01-14T01:53:23Z", "salary": {"currency": null, "max": null, "min": null, "period": "monthly", "term": null}, "salary_visible": false, "title_keywords": ["senior relationship manager"], "responsibilities": ["communicate with", "control", "management", "make recommendation", "aml", "maintaining", "operations", "kyc", "compliance", "quality", "procedures", "risk monitoring", "maintain", "banking", "liaise with", "report"], "requirements": {"degrees": ["university degree"], "majors": ["related disciplines", "business"], "languages": ["putonghua", "english", "chinese"], "language_level": ["good command"], "hard_skills": ["credit analysis", "marketing skills"], "soft_skills": ["motivated"], "languages_combined": [{"language": "putonghua", "language_level": ["good command"]}, {"language": "english", "language_level": ["good command"]}, {"language": "chinese", "language_level": ["good command"]}]}, "experience_required": {"duration": ["minimum 5 years"], "field": ["banking experience"]}}, {"job_id": "100003009047955", "location_code": "hk", "company": "NewPages Recruitment Company Limited", "job_title": "Retail Banking: General Banking Officer / Personal Banking Manager (basic + incentive)", "description": "We have serval clients seeking for experience candidate to join their banking team.\u00a0\n\nGeneral Banking Officer / Personal Banking Manager / Relationship Officer / Personal Banker\n\n\nResponsibilities:\n\nPromotes a wide range of financial services to prospect customers on both investment and insurance products\nProvide financial services and customer services to high net worth customers\u00a0\nAdvisory to clients for general banking services and wealth management products including account opening, credit card, personal loan and insurance\nMaintain good relationship with both existing and new clients\n\nRequirement:\n\nMinimum 1 year banking experience, prefer with sales experience\u00a0\nHolding IIQE 1,2,3 is must / HKSI 1,7,8 is preferred\nProficient in English, Mandarin and Cantonese", "employment_types": ["Full Time", "Permanent"], "selling_points": ["high incentive", "fast promotion", "bank benefit"], "locations": ["Not Specified"], "categories": ["Banking / Finance", "Retail Banking", "Financial Services", "Wealth Management"], "post_time": "2022-01-14T04:22:22Z", "salary": {"currency": "HKD", "max": 44999, "min": 20000, "period": "monthly", "term": null}, "salary_visible": true, "title_keywords": ["officer", "personal", "manager"], "responsibilities": ["management", "account opening", "customer services", "maintain good relationship", "banking", "insurance"], "requirements": {"degrees": [], "majors": [], "languages": ["cantonese", "english", "mandarin"], "language_level": ["proficient"], "hard_skills": ["iiqe", "hksi"], "soft_skills": [], "languages_combined": [{"language": "cantonese", "language_level": ["proficient"]}, {"language": "english", "language_level": ["proficient"]}, {"language": "mandarin", "language_level": ["proficient"]}]}, "experience_required": {"duration": ["minimum 1 year"], "field": ["banking experience"]}}, {"job_id": "100003009045846", "location_code": "hk", "company": "Robert Half", "job_title": "AM/Manager, PE/Hedge Fund [Open to Auditor]", "description": "Our client is an International leading Financial Service company, the principal activities included corporate finance, fund management, and asset management.\n\n\n\nHandle daily operations of private funds including NAV calculation, trade settlement, cash and position reconciliation, cash collateral, margin management and corporate action handling\nWork closely with third party service providers such as external auditors, tax consultants and compliance team\nResponsible for operational support and maintenance of securities settlements covering fixed income and equity instruments ensure all transactions are settled in a timely manner\nManage the trading accounts and operations of FX, bonds, stocks, fixed income, equities and derivatives\nMonitor daily equity settlement functions including clearing and custodian services\nPerform ad hoc duties as assigned\n\n\n\nRequirements:\n\nBachelor's Degree in Accounting, Finance or relevant discipline\nMinimum of 4 years' fund related experience and consider candidates came from Big 4\nKnowledge of Private Equity/Hedge Funds with direct working experience of fund accounting, Financial Industry Audit and/or fund administration will be beneficial\nMember of CPA is an added advantage\nHigh level of multi-tasking and time management skill are required\nA team-player with excellent working attitude; willing to take on multiple functions\nExcellent verbal and written communication skills\n\n\n\nApply Today\n\nTo apply online (Word attachment only), please click the 'Apply' button. Please note that only short-listed candidates will be contacted.", "employment_types": ["Full Time", "Permanent"], "selling_points": ["A leading financial service company", "Fringe benefit with decent bonus", "Good exposure with career progression"], "locations": ["Central & Western Area"], "categories": ["Accounting", "Accountant", "Finance / Accounting Manager", "Banking / Finance", "Financial Services"], "post_time": "2022-01-13T08:53:51Z", "salary": {"currency": null, "max": null, "min": null, "period": "monthly", "term": null}, "salary_visible": false, "title_keywords": ["manager"], "responsibilities": ["tax", "ad hoc duties", "management", "operational support", "administration", "maintenance", "operations", "compliance", "a timely manner", "monitor", "transactions", "audit", "communication", "daily operations", "asset management", "third party", "external auditors"], "requirements": {"degrees": ["degree", "bachelor"], "majors": ["finance", "accounting"], "languages": [], "language_level": [], "hard_skills": ["cpa", "word", "private equity", "maintenance"], "soft_skills": ["communication skills", "responsible", "team-player", "timely", "multi-tasking", "time management skill"], "languages_combined": []}, "experience_required": {"duration": ["minimum of 4 years"], "field": ["related", "financial industry", "big 4", "audit", "accounting", "administration"]}}, {"job_id": "100003009052604", "location_code": "hk", "company": "", "job_title": "Customer Service Manager", "description": "Discover New Possibilities at\u00a0FinStyle\u00a0Group\u00a0FinStyle\u00a0Family Office is an\u00a0integrated platform works under AXA that delivers bespoke solutions of wealth preservation,\u00a0investments and risk managements to clients of Hong Kong and the Greater China. We provide\u00a0comprehensive training and excellent career development opportunities to the passionate individuals that share the same vision with us.\n\u00a0\u00a0Want a dynamic career that can create a difference? Come and join us!\n\nCore responsibilities:\u00a0\n\nAble\u00a0to provide market insights, investment opportunities in the corresponding market\nProvide\u00a0professional financial service to every individual client for their purposes of wealth management, retirement plan and investment\nManage\u00a0relationships with individual clients and corporate accounts\n\n\nWe offer:\n\nClient\u00a0Base\u00a0\n\nQuarterly\u00a0Bonus and Year End Bonus\n\nInitial\u00a0training and On-Job training\n\nTransparent\u00a0Career Path to Management Level\n\nLife\u00a0and Medical Insurance\n\n\u00a0\nAbout\u00a0FinStyle\u00a0Family Office\n\nWith our 18 years working in the wealth management industry, we understand clients\u2018 demand differently.\u00a0FinStyle\u00a0provides\u00a0customised\u00a0and comprehensive solutions to clients of Hong Kong and the Greater China.\u00a0We work with world-class wealth management companies and other strategic partners to provide the best solution to our clients. We put ourselves into our clients\u2019 shoes to create a win-win situation.\u00a0\n\nInterested parties, please contact Mr Chiu at 63320979 before applying.\n\n\nInterested candidates, please contact us at 63320979 for company details before applying.", "employment_types": ["Full Time", "Permanent", "Contract"], "selling_points": ["Family office", "Wealth management", "Finance"], "locations": ["Tsim Sha Tsui"], "categories": ["Accounting", "Accountant", "Banking / Finance", "Financial Services", "Management", "Management Trainee"], "post_time": "2022-01-17T03:31:23Z", "salary": {"currency": "HKD", "max": 44999, "min": 25000, "period": "monthly", "term": null}, "salary_visible": true, "title_keywords": ["customer service manager"], "responsibilities": [], "requirements": {"degrees": [], "majors": [], "languages": [], "language_level": [], "hard_skills": [], "soft_skills": [], "languages_combined": []}, "experience_required": {"duration": [], "field": []}}, {"job_id": "100003009048139", "location_code": "hk", "company": "Michael Page", "job_title": "Head of Equities Compliance - European Investment Bank", "description": "Independent contributor role to be part of the global markets compliance team. This role will focus on providing compliance advisory to the business for their equity derivatives and structured products business.\n\nClient Details\n\nMy client is one of the largest European based corporate investment banks in the world. They have businesses in global markets, private wealth management, asset management, and corporate bank. They have a strong footprint in Asia for their global markets business including fixed income, prime brokerages, equities, and structured products.\n\nDescription\n\nreport directly to the Head of Financial Markets Compliance APAC\nindependent contributor role\nwork closely with other global markets compliance colleagues\nprovide compliance advisory to the business for equity derivatives and structured products\nmain point of contact with the SFC\nbe aware and maintain updated compliance matters for their global markets business\n\nProfile\n\nminimum 10+ years of global markets compliance experience\npreferably strong product knowledge in equity derivatives and structured products\nopen to candidates within the legal field and/or securities/brokerage firms\nmust be able to work independently\nmust be currently located in HK\nfluency in english is a must\n\nJob Offer\n\nsenior level head role\nwork alongside high calibre staff for compliance\ngreat work culture\nglobal presence\n\nTo apply online please click the 'Apply' button below. For a confidential discussion about this role please contact Monica Wong on +852 2848 9520.", "employment_types": ["Full Time", "Permanent"], "selling_points": ["Looking for equities derivatives candidates !", "Looking for structured products candidates !", "senior level compliance role !"], "locations": ["Not Specified"], "categories": ["Banking / Finance", "Financial Services", "Equities / Capital Markets", "Professional Services", "Legal & Compliance"], "post_time": "2022-01-14T05:16:03Z", "salary": {"currency": "HKD", "max": null, "min": 160000, "period": "monthly", "term": null}, "salary_visible": true, "title_keywords": [], "responsibilities": ["management", "brokerage", "compliance", "asset management", "maintain", "contact", "report"], "requirements": {"degrees": [], "majors": [], "languages": ["english"], "language_level": ["fluency"], "hard_skills": ["focus"], "soft_skills": ["focus", "structured", "independent", "work independently"], "languages_combined": [{"language": "english", "language_level": ["fluency"]}]}, "experience_required": {"duration": ["minimum 10+ years"], "field": ["compliance"]}}, {"job_id": "100003009054907", "location_code": "hk", "company": "Manulife (International) Limited", "job_title": "Financial Planning Manager / Officer", "description": "Job Highlights\n\nAttractive Commission\nFlexible Working Hour\nWelcome Fresh Graduate / IANG Holder\n\nJob Description\n\nResponsibilities\n\nIn charge of the sales plan, able to identify customer need, maximize and cross sell\nKnow the existing products feature and able to answer clients\u2019 enquiries\nHandle customer complaints and enquiries to improve customer satisfaction\nConduct any ad-hoc assignments / projects as required\n\nRequirements\n\nHKCEE / DSE or above\n1 year working experience is an advantage\nFluent Mandarin or English is an advantage\nQuick-learner and willing to work in client-facing environment\nGood interpersonal and communication skill\nHardworking, outgoing and self-motivated\nKnowledge of WhatsApp, Wechat, Facebook, Instagram etc.\nWelcome Fresh Graduate / IANG Holder\n\nCandidates with lower qualifications will be considered as Financial Planning Officer\n\nWe offer\n\nOn-job Professional Training\nAttractive Commission & Bonus\nFast Track of Promotion to Management Level\nMedical Scheme\nIncentive Bonus Plan & Free Overseas Travel\nLow-interest Mortgage Loans\n\nPersonal data collected will be used for recruitment purposes only, the recruitment offer is subject to the terms & conditions as stipulated in the agreement to be signed.", "employment_types": ["Full Time", "Part Time"], "selling_points": ["Attractive Commission", "Flexible Working Hour", "Welcome Fresh Graduate / IANG Holder"], "locations": ["Ngau Tau Kok"], "categories": ["Banking / Finance", "Financial Services", "Sales, CS & Business Devpt", "Business Development", "Customer Service - Supervisor / Officer"], "post_time": "2022-01-17T13:32:04Z", "salary": {"currency": "HKD", "max": 54999, "min": 20000, "period": "monthly", "term": null}, "salary_visible": true, "title_keywords": ["officer", "manager"], "responsibilities": ["ad-hoc assignments", "plan", "customer complaints"], "requirements": {"degrees": ["fresh graduate", "dse"], "majors": [], "languages": ["english", "mandarin"], "language_level": ["advantage", "fluent"], "hard_skills": ["facebook", "whatsapp", "wechat"], "soft_skills": ["outgoing", "self-motivated", "communication skill", "interpersonal", "hardworking", "client-facing"], "languages_combined": [{"language": "english", "language_level": ["advantage", "fluent"]}, {"language": "mandarin", "language_level": ["advantage", "fluent"]}]}, "experience_required": {"duration": ["1 year"], "field": []}}, {"job_id": "100003009051496", "location_code": "hk", "company": "Future Leader Recruitment Agency", "job_title": "Management Trainee (Finance 20k+)", "description": "In this position, you will\u00a0\n- Receive training in different areas by levels\n- Practice new skills to provide administrative and analytical support\n- Conduct analyses on global economy\n- Meet up with corporate and individual Clients regularly\n- Establish and maintain good relationship with clients\n- Fast track promotion to management level\n\nSkills and Qualifications\n- Degree holders or above, graduated from oversea and IANG are welcomed\n- Strong desire to learn and develop yourself\n- Open minded with positive attitude\n\nBenefits\n- Medical insurance\n- Flexible working hours\n- Oversea Convention trips\n- On going professional trainings\n- Young and Fun working atmosphere\nOur client is a fast-growing and well structured financial company in Asia that rewards hard working and life balancing. We are seeking an energetic, young and motivated individual to join the 2021 summer trainee program.\u00a0", "employment_types": ["Full Time", "Internship"], "selling_points": ["Young and Fun working atmosphere", "Hard working and life balancing", "Fast track promotions to different levels"], "locations": ["Quarry Bay"], "categories": ["Banking / Finance", "Investment", "Financial Services", "Management", "Management Trainee"], "post_time": "2022-01-16T05:17:58Z", "salary": {"currency": "HKD", "max": 24999, "min": 20000, "period": "monthly", "term": null}, "salary_visible": true, "title_keywords": ["management trainee"], "responsibilities": ["develop", "management", "maintain good relationship"], "requirements": {"degrees": ["degree"], "majors": [], "languages": [], "language_level": [], "hard_skills": [], "soft_skills": ["positive attitude", "open minded"], "languages_combined": []}, "experience_required": {"duration": [], "field": []}}, {"job_id": "100003009049233", "location_code": "hk", "company": "Shanghai Commercial Bank Ltd", "job_title": "Assistant Vice President / Manager, Securities Services", "description": "Responsibilities:\n\nAnalyze the stock market, find profitable investment opportunities, and provide market updates and insights to frontline staff and customers in making sound investment decisions.\nCultivate long-term relationship with customers for meeting their short-term and long-term\u00a0 financial goals.\nConduct market research to stay abreast with financial trends and ensure their plans are in line with current market conditions.\nCreate a strong business presence by developing strategies, managing marketing campaigns through various channels including mass media and other online platforms.\nPerform ad hoc tasks when necessary.\n\nRequirements:\n\nDegree holder in Business, Finance, Economics or related disciplines.\nMinimum 8 - 10 years related experience gained from financial institutions, candidates with securities market analysis\u2019 sharing experience on mass media / online platforms preferred.\nCompleted HKSI examinations and qualified to register for RA1 & 4.\nExcellent interpersonal, relationship management and communication skills with sound knowledge in securities market.\nExcellent command of spoken and written English and Chinese, including Putonghua.\n\nAttractive remuneration package will be offered to the right candidates. Interested parties please click\u00a0\"Apply Now\"\u00a0to submit your full resume with current and expected salary to the\u00a0Human Resources Division.\n\nPlease visit us at\u00a0www.shacombank.com.hk\u00a0for more information about our Bank.\n\nAll personal data collected will be used for recruitment related purposes strictly in accordance with the Bank's personal data policies, a copy of which will be provided immediately upon request by contacting our Personal Data Compliance Officer. Applicants who are not contacted within two months may consider their applications unsuccessful and the personal data collected from the applicants will be retained for no longer than two years from the date of rejection during which the applicants may be considered for other suitable positions within the Bank.", "employment_types": ["Full Time", "Permanent"], "selling_points": ["Cultivate long-term relationship with customers", "Create a strong business presence", "Analyze the stock market"], "locations": ["Kwai Hing"], "categories": ["Banking / Finance", "Financial Services", "Others"], "post_time": "2022-01-15T03:50:13Z", "salary": {"currency": null, "max": null, "min": null, "period": "monthly", "term": null}, "salary_visible": false, "title_keywords": ["manager", "assistant vice president"], "responsibilities": ["conduct market research", "ad hoc tasks", "developing", "marketing campaigns", "plans"], "requirements": {"degrees": ["degree holder"], "majors": ["related disciplines", "finance", "business", "economics"], "languages": ["putonghua", "english", "chinese"], "language_level": ["excellent"], "hard_skills": ["analysis", "hksi"], "soft_skills": ["communication skills", "interpersonal"], "languages_combined": [{"language": "putonghua", "language_level": ["excellent"]}, {"language": "english", "language_level": ["excellent"]}, {"language": "chinese", "language_level": ["excellent"]}]}, "experience_required": {"duration": ["minimum 8 - 10 years"], "field": ["related", "financial institutions", "media", "securities"]}}, {"job_id": "100003009050157", "location_code": "hk", "company": "China Construction Bank (Asia) Corporation Limited", "job_title": "AVP / Manager (Institutional Banking, Internal Control)", "description": "Responsibilities\n\nAssist the team head to maintain Internal Control standards, including the timely implementation of internal and external audit points together with any issues raised by external regulators\nAct as a customer due diligence (\u201cCDD\u201d) expert by performing checking and validating daily CDD application according to both internal and external regulations and policies\nRecommend appropriate financial crime compliance measures on respective relationship for fraud or Anti-Money Laundering (\u201cAML\u201d) prevention\nAssist in developing action plans aimed at ensuring that KYC services and processes meet the expectations of the Business in the context of rapid development\nHandle ad hoc project on AML CDD as assigned by Management\n\nRequirements\n\nDegree holder or above with major in Business Administration or related disciplines\n3 - 5 years\u2019 banking experience in CDD / AML / risk related functions\nSound banking operation and compliance knowledge\nDetails conscious with good analytical reasoning\nIndependent, committed, proactive and responsible\nGood demand of English; fluency in Putonghua is an advantage\u00a0\nAbility to work and thrive in a fast changing, results driven environment\nFamiliarize with Microsoft Office i.e. Word, Excel & PowerPoint\nApplicants who are not contacted within 8 weeks may consider their applications unsuccessful and their personal data will be retained by the bank for a period up to two years.\n\n\n\nAll information provided by applicants will be used for recruitment purposes only and will be used strictly in accordance with the bank's personal data policies, a copy of which will be provided upon request.\u00a0", "employment_types": ["Full Time", "Permanent"], "selling_points": ["Degree holder or above with major in Business Admi", "3 - 5 years\u2019 banking experience in CDD / AML", "Sound banking operation and compliance knowledge"], "locations": ["Central"], "categories": ["Banking / Finance", "Corporate Banking", "Financial Services"], "post_time": "2022-01-14T09:53:19Z", "salary": {"currency": null, "max": null, "min": null, "period": "monthly", "term": null}, "salary_visible": false, "title_keywords": ["manager"], "responsibilities": ["regulations", "management", "aml", "ad hoc", "cdd", "policies", "compliance", "implementation", "audit", "checking", "developing", "customer due diligence", "maintain", "kyc", "plans", "internal control"], "requirements": {"degrees": ["degree holder"], "majors": ["related disciplines", "business administration"], "languages": ["putonghua", "english"], "language_level": ["fluency", "advantage", "good"], "hard_skills": ["excel", "aml", "microsoft office", "cdd", "word", "powerpoint"], "soft_skills": ["independent", "responsible", "committed", "proactive", "driven"], "languages_combined": [{"language": "putonghua", "language_level": ["fluency", "advantage"]}, {"language": "english", "language_level": ["good"]}]}, "experience_required": {"duration": ["3 - 5 years"], "field": ["related", "banking experience"]}}, {"job_id": "100003009051611", "location_code": "hk", "company": "Infinity Cargo Express Limited", "job_title": "Cost Accountant", "description": "Job\u00a0Description:\n\n-\u00a0\u00a0\u00a0\u00a0\u00a0 Handle daily AP accounting transactions,\n\n-\u00a0\u00a0\u00a0\u00a0\u00a0 Responsible for weekly cash forecast\n\n-\u00a0\u00a0\u00a0\u00a0\u00a0 Responsible for monthly airfreight job closing and GP analysis\n\n-\u00a0\u00a0\u00a0\u00a0\u00a0 Check and review airline Tonnage and EQ adjustment report\n\n-\u00a0\u00a0\u00a0\u00a0\u00a0 Assist with annual audit.\n\n-\u00a0\u00a0\u00a0\u00a0\u00a0 Perform other Ad-hoc duties as assigned\n\nQualifications and Experience:\n\n-\u00a0 \u00a0Diploma in accountancy with experience in e-commerce platforms/Freight forwarding industry will be advantage\n\n- \u00a0\u00a0\u00a03- 5 years relevant working experiences\n\n-\u00a0\u00a0\u00a0 Proficiency in Excel (e.g. Pivot & Vlookup) and Word processing\n\n-\u00a0\u00a0\u00a0 Good command of English and conversational Putonghua\n\n-\u00a0\u00a0 \u00a0Immediate available is highly preferred\n\n\n\nBenefits\n\nYear-end Double pay, MPF, Group Medical, Bank Holidays, 12 days Annual Leave\nWork life balance\n\nWorking Location: Tsuen Wan\n\nInterested candidates, please contact us at 24060820 for company details.\n\nAll information provided by applicants will be treated in strict confidential and used only for the recruitment purpose", "employment_types": ["Full Time"], "selling_points": ["Double Pay, 12 days AL, Group Medical", "Experience in Freight forwarding is an advantage", "Immediate Available is preferred"], "locations": ["Tsuen Wan Area"], "categories": ["Accounting", "Accountant", "Accounting Clerk / Supervisor", "Banking / Finance", "Financial Services"], "post_time": "2022-01-16T14:32:23Z", "salary": {"currency": null, "max": null, "min": null, "period": "monthly", "term": null}, "salary_visible": false, "title_keywords": ["accountant"], "responsibilities": ["ap", "annual audit", "analysis", "review", "e-commerce platforms", "transactions", "forecast", "ad-hoc duties", "report"], "requirements": {"degrees": ["diploma"], "majors": ["e-commerce", "accountancy"], "languages": ["putonghua", "english"], "language_level": ["conversational", "good command"], "hard_skills": ["ap", "excel", "e-commerce", "analysis", "airline", "word processing", "vlookup"], "soft_skills": ["responsible", "ad-hoc duties"], "languages_combined": [{"language": "putonghua", "language_level": ["good command"]}, {"language": "english", "language_level": ["conversational", "good command"]}]}, "experience_required": {"duration": ["3- 5 years"], "field": ["e-commerce"]}}, {"job_id": "100003009041098", "location_code": "hk", "company": "Shanxi Securities International Financial Holdings Limited", "job_title": "Dealer / Senior Dealer", "description": "Responsibilities:\n\n\u2022 Verify and execute trade orders of securities and futures products for local and global markets\n\u2022 Manage orders from both internal and external customers\n\u2022 Monitor portfolio of client accounts and perform margin call\n\u2022 Provide customer services, handle customer enquiries and related support to clients\n\u2022 Formulate policies & procedures and control operation risk\n\u2022 Assist development of new products, functionalities and services\n\u2022 Work with team members to assure competence and on-going improvement of productivity\n\u2022 Assist in ad-hoc projects and carry out other duties and responsibilities as assigned by management\n\nRequirements:\n\n\u2022 Bachelor\u2019s degree or above in Economics, Finance or other relevant disciplines\n\u2022 Minimum 1-3 years of dealing experience\n\u2022 Holder of SFC license RA1 and RA2\n\u2022 Familiar with the trading systems SP Trader and Esunny is preferred\n\u2022 Willing to work on night shift/other shift and work on public holiday\n\u2022 Strong analytical, communications and interpersonal skills\n\u2022 Knowledgeable about the associated compliance processes and standard operating procedures\n\u2022 Good command in spoken and written English and Chinese (fluency in Putonghua)\n\u2022 Proficiency in computer applications such as Bloomberg, MS-Excel, Word and PowerPoint\n\u2022 Candidates with more experience will be considered as Senior Dealer\n\nWe offer competitive remuneration packages to the right candidate. Interested parties please submit your resume stating current and expected salaries to Human Resources Department (1). by post to Unit A, 29/F., Tower 1, Admiralty Centre, 18 Harcourt Road, Admiralty, Hong Kong; or (2). by using \"Apply Now\" button. All applications will be treated in strict confidence and personal data provided by job applications will be used for recruitment purposes only.", "employment_types": ["Full Time", "Permanent"], "selling_points": [], "locations": ["Admiralty"], "categories": ["Banking / Finance", "Financial Services", "Dealing & Trading", "Order Processing & Operation / Settlement"], "post_time": "2022-01-12T03:27:00Z", "salary": {"currency": null, "max": null, "min": null, "period": "monthly", "term": null}, "salary_visible": false, "title_keywords": ["dealer"], "responsibilities": ["internal and external customers", "control", "management", "handle customer enquiries", "other duties", "policies", "monitor", "procedures", "customer services", "ad-hoc projects"], "requirements": {"degrees": ["degree or above", "bachelor"], "majors": ["finance", "economics"], "languages": ["putonghua", "english", "chinese"], "language_level": ["fluency", "good command"], "hard_skills": ["bloomberg", "word", "powerpoint", "ms-excel", "sfc license"], "soft_skills": ["interpersonal skills"], "languages_combined": [{"language": "putonghua", "language_level": ["fluency", "good command"]}, {"language": "english", "language_level": ["fluency", "good command"]}, {"language": "chinese", "language_level": ["fluency", "good command"]}]}, "experience_required": {"duration": ["minimum 1-3 years"], "field": []}}, {"job_id": "100003009051086", "location_code": "hk", "company": "ORIX Asia Limited", "job_title": "Senior Associate, Marketing - Vehicle Finance", "description": "Job\n\nConduct related customer/ market research to support relationship managers to identifying potential clients.\nAppraising an applicant's credit history, financial records, and the value of any collateral offered, along with other factors that depend on the size and purpose of the loan.\nAct as the front-to-backend channel support on various ad hoc assignments.\n\nRequirements\n\nAssociate degree or above with major in Banking, Finance or related\nMin. 2 years banking experience with relevant experience in credit or customer services sector\nKnowledge in vehicle finance operation\nGood communication, interpersonal and analytical skills\nHigh integrity and initiative, meticulous, able to work independently\nGood command of English and Chinese (Putonghua is a plus)\nProficiency in MS Office application\n\n\n\nWe offer attractive remuneration and benefits, comprehensive career development opportunities and 5-day week to the qualified candidate.\n\nInterested parties please send detailed resume including current salary and expected salary to:\u00a0HR Dept, 25/F, Two Exchange Square, 8 Connaught Place, Central, HK\n\nAll personal information provided by applicants will be treated in strict confidence and used solely for recruitment purpose. All information of unsuccessful candidates will be destroyed within 12 months from the date of this advertisement.", "employment_types": ["Full Time", "Permanent"], "selling_points": [], "locations": ["Central"], "categories": ["Banking / Finance", "Financial Services"], "post_time": "2022-01-15T02:02:42Z", "salary": {"currency": null, "max": null, "min": null, "period": "monthly", "term": null}, "salary_visible": false, "title_keywords": ["senior associate"], "responsibilities": ["market research", "customer services", "communication", "ad hoc assignments", "banking"], "requirements": {"degrees": ["degree or above"], "majors": ["finance"], "languages": ["putonghua", "english", "chinese"], "language_level": ["good command"], "hard_skills": ["plus", "ms office", "analytical skills"], "soft_skills": ["meticulous", "work independently", "integrity", "analytical skills", "communication", "interpersonal", "initiative"], "languages_combined": [{"language": "putonghua", "language_level": ["good command"]}, {"language": "english", "language_level": ["good command"]}, {"language": "chinese", "language_level": ["good command"]}]}, "experience_required": {"duration": ["2 years"], "field": ["relevant experience", "banking experience", "customer services"]}}, {"job_id": "100003009047766", "location_code": "hk", "company": "Public Bank (Hong Kong) Limited", "job_title": "Customer Relations Officer (Complaint Handling)", "description": "Handle complaint case independently and conduct prompt and detailed investigation of the case\nEnsure investigations are handled in compliance with relevant procedures and regulatory requirements in a timely and appropriate manner\nPromote, develop and implement service improvement activities\nDevelop, design and deliver customer service training\u00a0\nDegree holder or above with minimum 3 years of banking experience in retail banking\nStrong knowledge of banking products and operations\u00a0\nExperience in handling complaints\u00a0\u00a0\nProficiency in spoken and written English and Chinese\nExcellent interpersonal and communication skills\n\nTo apply, interested parties please follow the application methods available in the Bank\u2019s career website https://www.publicbank.com.hk/en/aboutus/careeropportunities. You can send us your resume quoting our job reference number together with present & expected salary (a must) to the Human Resources Department by email or fax at 2815 3157 or by post to Human Resources Department, 12/F, Public Bank Centre, 120 Des Voeux Road Central, Hong Kong. You may also visit our career website for other career opportunities available within our Group.\n\nPersonal data collected will be used for recruitment purpose only and will be treated in accordance with the Bank\u2019s Personal Information Collection Statement, a copy of which has been available in the Bank\u2019s career website.", "employment_types": ["Full Time", "Permanent"], "selling_points": [], "locations": ["Not Specified"], "categories": ["Banking / Finance", "Financial Services", "Admin & HR", "Training & Development", "Sales, CS & Business Devpt", "Others"], "post_time": "2022-01-15T03:49:06Z", "salary": {"currency": null, "max": null, "min": null, "period": null, "term": null}, "salary_visible": false, "title_keywords": ["customer relations officer"], "responsibilities": ["regulatory requirements", "operations", "compliance", "procedures", "investigation", "develop", "design", "communication", "customer service", "banking"], "requirements": {"degrees": ["degree holder"], "majors": [], "languages": ["english", "chinese"], "language_level": ["proficiency"], "hard_skills": [], "soft_skills": ["communication skills", "independently", "prompt", "timely", "customer service", "interpersonal", "detailed"], "languages_combined": [{"language": "english", "language_level": ["proficiency"]}, {"language": "chinese", "language_level": ["proficiency"]}]}, "experience_required": {"duration": ["minimum 3 years"], "field": ["retail banking", "banking experience"]}}, {"job_id": "100003009050786", "location_code": "hk", "company": "Morgan McKinley", "job_title": "Junior Sales (Wealth Management)", "description": "Key Responsibilities\n\nAchieved mutual fund sales (gross/net/AUM, Asset-based Account) target required\nIdentify potential clients for investment sales opportunities from existing client base and/or new-to-company prospects based on own contacts as well as generated by marketing activities and other media\nSuccessfully establish an understanding of the nature and needs of potential clients on investment solutions, and provide professional after-sales service to respective clients\nAdhere the defined sales process framework as described by the company and keep up high level sales quality at all time\nProtect the Company's assets and complies with all regulatory, legal and ethical requirements\n\nKey Skills\n\nUniversity graduated or equivalent with working experience in financial industry, preferable at least 3 years mutual funds sales experience\nComplete licensing examination for Securities and Futures intermediaries Paper 1 and 4\nPassionate about financial market and investment world\nExcellent people skills\nRelationship building is the key part of the success in the role\nStrong verbal and written communication skill\nEntrepreneurial, Self\u2010motivated and work independently\n\nApplication\n\nIf this above description fits your experience and is something you would like to explore, please click 'Apply Now' to submit your resume to us.\n\nOur specialist consultant will get in touch with you soon, if we find your profile suitable for this position or any other vacancies we are recruiting for.\n\nAny questions, please feel free to contact Regan Lo at 3907 3944.", "employment_types": ["Full Time", "Permanent"], "selling_points": ["Wealth Management Sales", "Mutual Fund; Investment and Insurance (I&I)", "Global scale institution"], "locations": ["Not Specified"], "categories": ["Banking / Finance", "Investment", "Financial Services", "Wealth Management"], "post_time": "2022-01-14T11:22:11Z", "salary": {"currency": "HKD", "max": 34999, "min": 30000, "period": "monthly", "term": null}, "salary_visible": true, "title_keywords": ["wealth management", "sales", "junior"], "responsibilities": ["quality", "communication", "after-sales service", "client base", "contact"], "requirements": {"degrees": [], "majors": [], "languages": [], "language_level": [], "hard_skills": [], "soft_skills": ["work independently", "communication skill", "ethical", "passionate about"], "languages_combined": []}, "experience_required": {"duration": ["at least 3 years"], "field": ["financial industry"]}}, {"job_id": "100003009051274", "location_code": "hk", "company": "Keep With Faith Company", "job_title": "Management Trainee - Fresh Graduate", "description": "Job Descriptions\n\nProvide professional financial services to clients, including risk management, health protection and retirement planning.\nBuild and manage new sales team\nProvide sales and administrative support\nAchieve higher levels of business goals to enable your advancement.\nWork independently\u00a0\n\nBenefits\u00a0\n\nYoung and energetic working environment\nCareer advancement programme sponsorship\nIncentive, commission bonus, travel conventions\nClear career path and fast-track promotion\nMedical benefits and training allowances\n\nRequirements\n\nDegree holder or above\nProactive with positive mindset, excellent interpersonal & communication skill\nSolid Management skills is an absolute advantage\nWilling to learn and face challenges\nGood command of written and spoken English and Chinese", "employment_types": ["Full Time", "Permanent"], "selling_points": ["Clear career path with attractive bonus", "On-job fast start training programs", "Flexible working hours"], "locations": ["Not Specified"], "categories": ["Banking / Finance", "Financial Services", "Sales, CS & Business Devpt", "Business Development", "Management", "Management Trainee"], "post_time": "2022-01-15T07:02:54Z", "salary": {"currency": null, "max": null, "min": null, "period": "monthly", "term": null}, "salary_visible": false, "title_keywords": ["management trainee"], "responsibilities": ["management", "business goals", "administrative support", "sales team", "planning"], "requirements": {"degrees": [], "majors": [], "languages": [], "language_level": [], "hard_skills": [], "soft_skills": [], "languages_combined": []}, "experience_required": {"duration": [], "field": []}}, {"job_id": "100003009050031", "location_code": "hk", "company": "Hong Kong Finance Company Limited", "job_title": "Administration Officer", "description": "Responsibilities:\n\nSupport the team to conduct product due diligence\nAssist Team Head in handling system and regulatory projects such as FNA, GL requirements\nReview and implement sales and promotional programs on life insurance products e.g. marketing promotions, sales incentives, events & seminars, etc.\nWork closely with different parties in formulating and reviewing process effectiveness to enhance sales efficiency\nConduct market research\n\nRequirements:\n\nBachelor Degree in Insurance, Business Administration, or related discipline\n1-2 years of product development experience in bancassurance, banking or life insurance industry is preferred\nProduct and market knowledge of life insurance\nSelf-motivated, detail-minded and with a \"can-do\" manner\nGood command of both spoken and written English and Chinese\nProficient in MS Office applications\n\nAttractive remuneration package will be offered to the right candidates. Interested parties please click \"Apply Now\" to submit your full resume with current and expected salary to the Human Resources Division.\n\nPlease visit us at www.shacombank.com.hk for more information about our Bank.\n\nAll personal data collected will be used for recruitment related purposes strictly in accordance with the Bank's personal data policies, a copy of which will be provided immediately upon request by contacting our Personal Data Compliance Officer. Applicants who are not contacted within two months may consider their applications unsuccessful and the personal data collected from the applicants will be retained for no longer than two years from the date of rejection during which the applicants may be considered for other suitable positions within the Bank.", "employment_types": ["Full Time"], "selling_points": ["Handle loan administration operations", "Coordinate with outside professionals", "Handle any ad hoc projects"], "locations": ["Admiralty"], "categories": ["Admin & HR", "Clerical / Admin Staff", "Banking / Finance", "Loan", "Financial Services"], "post_time": "2022-01-14T09:40:09Z", "salary": {"currency": null, "max": null, "min": null, "period": "monthly", "term": null}, "salary_visible": false, "title_keywords": ["administration officer"], "responsibilities": ["sales incentives", "regulatory projects", "events & seminars", "product due diligence", "conduct market research", "review", "marketing promotions", "insurance", "support the team"], "requirements": {"degrees": ["degree", "bachelor"], "majors": ["insurance", "business administration"], "languages": ["english", "chinese"], "language_level": ["good command"], "hard_skills": ["ms office"], "soft_skills": ["detail-minded", "self-motivated", "can-do"], "languages_combined": [{"language": "english", "language_level": ["good command"]}, {"language": "chinese", "language_level": ["good command"]}]}, "experience_required": {"duration": ["1-2 years"], "field": ["product development", "insurance industry", "banking"]}}, {"job_id": "100003009049177", "location_code": "hk", "company": "Shanghai Commercial Bank Ltd", "job_title": "Relationship Officer, Securities Services", "description": "Responsibilities:\n\nProvide administration support to the Loans Processing Centre\nPerform daily operations on loans drawdown, documentation and repayment\nAssist in preparation of facility letters and related loans documents\nWork closely with business units to provide quality services to customers\nParticipate in any projects as assigned\n\nRequirements:\n\nDegree holder in Business Administration or related disciplines\nWell-organized with attention to details\nGood communication and interpersonal skills\nGood command of spoken and written English and Chinese\nProficient in MS Word, Excel and Chinese Word Processing\n\nAttractive remuneration package will be offered to the right candidates. Interested parties please click \"Apply Now\" to submit your full resume with current and expected salary to the Human Resources Division.\n\nPlease visit us at www.shacombank.com.hk for more information about our Bank.\n\nAll personal data collected will be used for recruitment related purposes strictly in accordance with the Bank's personal data policies, a copy of which will be provided immediately upon request by contacting our Personal Data Compliance Officer. Applicants who are not contacted within two months may consider their applications unsuccessful and the personal data collected from the applicants will be retained for no longer than two years from the date of rejection during which the applicants may be considered for other suitable positions within the Bank.", "employment_types": ["Full Time", "Permanent"], "selling_points": ["Execute securities trade orders in branch or Ctr", "Provide efficient & excellent service to customers", "Cross-selling and making referrals to sales team"], "locations": ["Not Specified"], "categories": ["Banking / Finance", "Investment", "Financial Services", "Dealing & Trading"], "post_time": "2022-01-15T03:50:10Z", "salary": {"currency": null, "max": null, "min": null, "period": "monthly", "term": null}, "salary_visible": false, "title_keywords": ["officer"], "responsibilities": ["documentation", "letters", "quality", "daily operations", "loans processing", "administration"], "requirements": {"degrees": ["degree holder"], "majors": ["related disciplines", "business administration"], "languages": ["english", "chinese"], "language_level": ["good command", "proficient"], "hard_skills": ["excel", "chinese word processing", "ms word"], "soft_skills": ["communication and interpersonal skills", "well-organized", "attention to details"], "languages_combined": [{"language": "english", "language_level": ["good command"]}, {"language": "chinese", "language_level": ["good command", "proficient"]}]}, "experience_required": {"duration": [], "field": []}}, {"job_id": "100003009044623", "location_code": "hk", "company": "AXA China Region Insurance Company Limited", "job_title": "MPF Services Officer \u5f37\u7a4d\u91d1\u5c08\u54e1", "description": "Responsibilities:\n\nHandle all loan transactions and coordinate with internal working partners to ensure smooth and timely processing\nAssist in conducting credit review, monitoring credit quality and reporting signs of deterioration\nPerform customer due diligence\nPrepare reports e.g. overdue, rescheduled and classified accounts for the management's review\nProvide administrative support to the department\nRequirements:\n\nDegree holder in Accounting, Finance or related disciplines\nMinimum 1 year's administrative/operations support experience, preferably in financial institutions\nSelf-motivated and attentive to details\nFluency in written and spoken English and Chinese, preferably with proficiency in Putonghua\nConversant with MS Word, Excel, Powerpoint and Chinese Word Processing\n\nAttractive remuneration package will be offered to the right candidates. Interested parties please click\u00a0\"Apply Now\"\u00a0to submit your full resume with current and expected salary to the\u00a0Human Resources Division.\n\nPlease visit us at\u00a0www.shacombank.com.hk\u00a0for more information about our Bank.\n\nAll personal data collected will be used for recruitment related purposes strictly in accordance with the Bank's personal data policies, a copy of which will be provided immediately upon request by contacting our Personal Data Compliance Officer. Applicants who are not contacted within two months may consider their applications unsuccessful and the personal data collected from the applicants will be retained for no longer than two years from the date of rejection during which the applicants may be considered for other suitable positions within the Bank.", "employment_types": ["Full Time", "Part Time", "Permanent", "Temporary", "Contract", "Internship", "Freelance"], "selling_points": ["Benefit, salary, insurance, financial, management,", "AXA, no experience, bank, banking, development", "incentive, sales, wealth management, consultant"], "locations": ["Tsim Sha Tsui"], "categories": ["Banking / Finance", "Financial Services", "Insurance", "Insurance Agent / Broker", "Sales, CS & Business Devpt", "Direct Sales"], "post_time": "2022-01-13T04:54:28Z", "salary": {"currency": "HKD", "max": 29999, "min": 17000, "period": "monthly", "term": null}, "salary_visible": true, "title_keywords": ["officer", "\u5f37\u7a4d\u91d1\u5c08\u54e1"], "responsibilities": ["reporting", "management", "monitoring", "quality", "review", "coordinate with", "transactions", "customer due diligence", "prepare reports", "provide administrative support"], "requirements": {"degrees": ["degree holder"], "majors": ["related disciplines", "finance", "accounting"], "languages": ["putonghua", "english", "chinese"], "language_level": ["fluency", "proficiency"], "hard_skills": ["excel", "chinese word processing", "powerpoint", "ms word"], "soft_skills": ["self-motivated", "attentive to details"], "languages_combined": [{"language": "putonghua", "language_level": ["proficiency", "fluency"]}, {"language": "english", "language_level": ["proficiency", "fluency"]}, {"language": "chinese", "language_level": ["proficiency", "fluency"]}]}, "experience_required": {"duration": ["minimum 1 year"], "field": ["financial institutions", "administrative"]}}, {"job_id": "100003009044868", "location_code": "hk", "company": "GOLDHORSE SECURITIES LIMITED", "job_title": "Junior / Senior Dealer \u2013 Night Shift", "description": "Responsible:\n\nHandle phone banking enquiries\nProvide administrative support in call centre\n\nRequirements:\n\nAt least 5 subjects passed in HKCEE/HKDSE, including Chinese and English Language and passed in IIQE Examination preferred\n1 year\u2019s customer service experience preferred\nCustomer-oriented with good communication skills, with proficiency in Putonghua would be an advantage\nPC knowledge, including MS Word, Excel and Chinese word processing\nShift duty required\nWorking location : Kwai Hing / Mongkok\n\nAttractive remuneration package will be offered to the right candidates. Interested parties please click \"Apply Now\" to submit your full resume with current and expected salary to the Human Resources Division.\n\nPlease visit us at www.shacombank.com.hk for more information about our Bank.\n\nAll personal data collected will be used for recruitment related purposes strictly in accordance with the Bank's personal data policies, a copy of which will be provided immediately upon request by contacting our Personal Data Compliance Officer. Applicants who are not contacted within two months may consider their applications unsuccessful and the personal data collected from the applicants will be retained for no longer than two years from the date of rejection during which the applicants may be considered for other suitable positions within the Bank.", "employment_types": ["Full Time", "Permanent"], "selling_points": [], "locations": ["Sheung Wan"], "categories": ["Banking / Finance", "Financial Services", "Dealing & Trading"], "post_time": "2022-01-13T06:30:25Z", "salary": {"currency": null, "max": null, "min": null, "period": "monthly", "term": null}, "salary_visible": false, "title_keywords": ["dealer", "junior"], "responsibilities": ["provide administrative support", "banking"], "requirements": {"degrees": ["hkdse"], "majors": [], "languages": ["putonghua", "english", "chinese"], "language_level": ["advantage", "proficiency", "good"], "hard_skills": ["excel", "iiqe", "chinese word processing", "pc knowledge", "ms word"], "soft_skills": ["communication skills", "customer-oriented", "customer service"], "languages_combined": [{"language": "putonghua", "language_level": ["proficiency", "advantage", "good"]}, {"language": "english", "language_level": []}, {"language": "chinese", "language_level": []}]}, "experience_required": {"duration": ["1 year"], "field": ["customer service"]}}, {"job_id": "100003009049343", "location_code": "hk", "company": "Shanghai Commercial Bank Ltd", "job_title": "Assistant Manager/Manager, Finance (Financial Accounting & Reporting)", "description": "Responsibilities:\u00a0\n\nAssist supervisors on daily operations of Bills Processing Centre\nPerform LC documents checking, Import and Export loans processing\nEnsure transactions are handled in accordance with the Bank's policies, procedures and guidelines\nHandle enquiries from customers and internal staff\nWork closely with business units to provide quality bills services to customers\n\nRequirements:\u00a0\n\nDegree holder in Business Administration or related disciplines\nMinimum 3 years of relevant experience in trade finance operations\nGood knowledge in trade financing and familiar with UCP600 and ISBP\nCertified Documentary Credit Specialist is preferred\nProactive, able to work independently and under pressure\nGood command of spoken and written English and Chinese, including Putonghua\u00a0\n\nAttractive remuneration package will be offered to the right candidates. Interested parties please click\u00a0\"Apply Now\"\u00a0to submit your full resume with current and expected salary to the\u00a0Human Resources Division.\n\nPlease visit us at\u00a0www.shacombank.com.hk\u00a0for more information about our Bank.\n\nAll personal data collected will be used for recruitment related purposes strictly in accordance with the Bank's personal data policies, a copy of which will be provided immediately upon request by contacting our Personal Data Compliance Officer. Applicants who are not contacted within two months may consider their applications unsuccessful and the personal data collected from the applicants will be retained for no longer than two years from the date of rejection during which the applicants may be considered for other suitable positions within the Bank.", "employment_types": ["Full Time", "Permanent"], "selling_points": ["Formulate changes in accounting policies", "Effective control on the operations", "Liaise with external auditors"], "locations": ["North Point"], "categories": ["Banking / Finance", "Financial Services", "Others"], "post_time": "2022-01-15T03:50:19Z", "salary": {"currency": null, "max": null, "min": null, "period": "monthly", "term": null}, "salary_visible": false, "title_keywords": ["assistant manager", "manager", "accounting"], "responsibilities": ["guidelines", "policies", "procedures", "checking", "transactions", "quality", "handle enquiries", "daily operations", "loans processing"], "requirements": {"degrees": ["degree holder"], "majors": ["related disciplines", "business administration"], "languages": ["putonghua", "english", "chinese"], "language_level": ["good command"], "hard_skills": [], "soft_skills": ["work independently", "proactive", "under pressure"], "languages_combined": [{"language": "putonghua", "language_level": ["good command"]}, {"language": "english", "language_level": ["good command"]}, {"language": "chinese", "language_level": ["good command"]}]}, "experience_required": {"duration": ["minimum 3 years"], "field": ["finance", "relevant experience"]}}, {"job_id": "100003009046929", "location_code": "hk", "company": "MIB Securities (Hong Kong) Limited", "job_title": "IT Infrastructure Specialist", "description": "Responsibilities:\n\nResponsible for performing daily settlement of all transactions initiated by Treasury Department, including Foreign Exchange, Money Market, Debt Market, SCB-Issued Certificate of Deposits, Funds Transfer, and FX margin account.\nProcess settlement payments and receipts, as well as perform daily summary reports\nEnsure all transaction full compliance of internal/external rules and regulations\nPerform user acceptance test (UAT) of New Treasury system\n\nRequirements:\n\nPost-secondary educated or above\nMinimum 3 years of relevant experience in banking industry\nWell-organized personality with attention to details\nGood command of spoken and written English and Chinese\nConversant with MS Word, Excel and Chinese Word processing\n\nAttractive remuneration package will be offered to the right candidates. Interested parties please click\u00a0\"Apply Now\"\u00a0to submit your full resume with current and expected salary to the\u00a0Human Resources Division.\n\nPlease visit us at\u00a0www.shacombank.com.hk\u00a0for more information about our Bank.\n\nAll personal data collected will be used for recruitment related purposes strictly in accordance with the Bank's personal data policies, a copy of which will be provided immediately upon request by contacting our Personal Data Compliance Officer. Applicants who are not contacted within two months may consider their applications unsuccessful and the personal data collected from the applicants will be retained for no longer than two years from the date of rejection during which the applicants may be considered for other suitable positions within the Bank.\u00a0", "employment_types": ["Full Time", "Permanent"], "selling_points": [], "locations": ["Causeway Bay"], "categories": ["Banking / Finance", "Financial Services", "Information Technology (IT)", "Network & System"], "post_time": "2022-01-14T01:46:21Z", "salary": {"currency": null, "max": null, "min": null, "period": "monthly", "term": null}, "salary_visible": false, "title_keywords": ["specialist"], "responsibilities": ["regulations", "receipts", "uat", "compliance", "transactions", "payments", "reports"], "requirements": {"degrees": [], "majors": [], "languages": ["english", "chinese"], "language_level": ["good command"], "hard_skills": ["excel", "chinese word processing", "ms word"], "soft_skills": ["well-organized", "attention to details"], "languages_combined": [{"language": "english", "language_level": ["good command"]}, {"language": "chinese", "language_level": ["good command"]}]}, "experience_required": {"duration": ["minimum 3 years"], "field": ["banking industry", "relevant experience"]}}, {"job_id": "100003009051547", "location_code": "hk", "company": "Shun Hip Corporate Consultancy Limited", "job_title": "Relationship Management Trainee (China Business Development)", "description": "Responsibilities:\n\nProvide end to end project management support on customer data platform implementation.\nAssist in project planning, tracking, resourcing and execution.\nCoordinate with the selected vendors, Business, IT, and related departments to provide support on the implementation of data platform.\nSupport analyzing data on business needs across different functions.\nAssist to manage data quality, data analytic tools, data governance, and data migration.\n\nRequirements:\n\nDegree in Computer Science/IT or related discipline.\nMinimum 2 years of related working experience, preferably in banking industry.\nKnowledge in Big Data Platform tools with experience in managing hybrid Cloud IaaS environments is an advantage\nProactive with good communication skills.\nGood command of spoken and written English and Chinese. Mandarin is an advantage.\n\nAttractive remuneration package will be offered to the right candidates. Interested parties please click\u00a0\"Apply Now\"\u00a0to submit your full resume with current and expected salary to the\u00a0Human Resources Division.\n\nPlease visit us at\u00a0www.shacombank.com.hk\u00a0for more information about our Bank.\n\nAll personal data collected will be used for recruitment related purposes strictly in accordance with the Bank's personal data policies, a copy of which will be provided immediately upon request by contacting our Personal Data Compliance Officer. Applicants who are not contacted within two months may consider their applications unsuccessful and the personal data collected from the applicants will be retained for no longer than two years from the date of rejection during which the applicants may be considered for other suitable positions within the Bank.", "employment_types": ["Full Time", "Permanent", "Temporary"], "selling_points": ["challenges, traveling", "Graduated from oversea university is an advantage", "China Development and Strategy"], "locations": ["Tsim Sha Tsui"], "categories": ["Accounting", "Accounting Clerk / Supervisor", "Banking / Finance", "Financial Services", "Engineering", "Engineering Project Management"], "post_time": "2022-01-16T10:07:06Z", "salary": {"currency": "HKD", "max": 24999, "min": 14000, "period": "monthly", "term": null}, "salary_visible": true, "title_keywords": ["management trainee"], "responsibilities": ["project planning", "provide support", "data", "coordinate with", "implementation", "quality", "project management", "customer data", "migration", "tracking"], "requirements": {"degrees": ["degree"], "majors": ["it", "computer science"], "languages": ["english", "chinese", "mandarin"], "language_level": ["advantage", "good command"], "hard_skills": [], "soft_skills": ["communication skills", "proactive"], "languages_combined": [{"language": "english", "language_level": ["good command"]}, {"language": "chinese", "language_level": ["good command"]}, {"language": "mandarin", "language_level": ["advantage"]}]}, "experience_required": {"duration": ["minimum 2 years"], "field": ["related", "banking industry"]}}, {"job_id": "100003009044002", "location_code": "hk", "company": "AT Global Services Limited", "job_title": "Operations and Customer Service Officer (Fresh Graduate / IANG welcome)", "description": "Responsibilities:\n\nExecute trading orders accurately and efficiently\nCultivate and deepen relationship with existing customers\nSolicit new business opportunities from branch referrals\nFacilitate daily dealing administrations and prepare related documents\nMonitor clients orders and margin level and conduct margin call and margin report\nSupport system testing and UAT\nHandle ad hoc duties as assigned\n\nRequirements:\n\nPost-secondary educated with at least 5 years work experience in related field\nQualified individual to carry out regulated activities (Type 1 and 2) under SFO\nStrong knowledge in Global Stocks, Futures, Options and Commodities, etc\nGood command of both spoken English and Chinese including Putonghua\nWilling to work on holiday (compensation leave will be offered)\nShift duty is required including public holiday (major shift from 6:45am to 4:00pm)\nWorking location: TST\n\nAttractive remuneration package will be offered to the right candidates. Interested parties please click \"Apply Now\" to submit your full resume with current and expected salary to the Human Resources Division.\n\nPlease visit us at www.shacombank.com.hk for more information about our Bank.\n\nAll personal data collected will be used for recruitment related purposes strictly in accordance with the Bank's personal data policies, a copy of which will be provided immediately upon request by contacting our Personal Data Compliance Officer. Applicants who are not contacted within two months may consider their applications unsuccessful and the personal data collected from the applicants will be retained for no longer than two years from the date of rejection during which the applicants may be considered for other suitable positions within the Bank.", "employment_types": ["Full Time", "Permanent"], "selling_points": ["Provide quality customer services to clients", "Conduct KYC (Know Your Client) review", "Handle enquiries from frontline"], "locations": ["Wan Chai"], "categories": ["Banking / Finance", "Financial Services", "Sales, CS & Business Devpt", "Customer Service - Supervisor / Officer", "Account Servicing"], "post_time": "2022-01-13T02:45:21Z", "salary": {"currency": null, "max": null, "min": null, "period": "monthly", "term": null}, "salary_visible": false, "title_keywords": ["operations", "customer service officer"], "responsibilities": ["ad hoc duties", "uat", "related documents", "business opportunities", "monitor", "testing", "report"], "requirements": {"degrees": [], "majors": [], "languages": ["putonghua", "english", "chinese"], "language_level": ["good command"], "hard_skills": ["sfo"], "soft_skills": [], "languages_combined": [{"language": "putonghua", "language_level": ["good command"]}, {"language": "english", "language_level": ["good command"]}, {"language": "chinese", "language_level": ["good command"]}]}, "experience_required": {"duration": ["at least 5 years"], "field": ["related"]}}, {"job_id": "100003009047662", "location_code": "hk", "company": "PEI Media (Hong Kong) Co., Limited", "job_title": "Graduate Research Associate", "description": "Responsibilities:\n\nSupport the implementation of system revamp and involve in the system building stage\n\nParticipate in each of the test phases e.g. getting user requirements, data migration process, validation of accounting treatments and accounting entries, and UAT test arrangement and workflow\nPerform reconciliation and checking on the accounting entries generated, interfaces and reports generated after the system go live\nEnsure the tasks and issues are in line with business action plans\nEscalate the issues and risks to the designated task force\nAct as a main contact point between vendor and Finance Division\nAssist to prepare documentation related to the project \u00a0\u00a0\nHandle clean up or ad-hoc request to the end of the project\nPerform BAU tasks as required\n\nRequirements:\n\nDegree holder with accounting professional qualifications\n\nMinimum 1 year of relevant experience, preferably in banking or accounting industry\nSolid technical background with understanding or hands-on experience in software development and web technologies\nGood written and verbal communication skills\nSolid organizational skills including attention to details and multi-tasking skills\n\nAttractive remuneration package will be offered to the right candidates. Interested parties please click \"Apply Now\" to submit your full resume with current and expected salary to the Human Resources Division.\n\nPlease visit us at www.shacombank.com.hk for more information about our Bank.\n\nAll personal data collected will be used for recruitment related purposes strictly in accordance with the Bank's personal data policies, a copy of which will be provided immediately upon request by contacting our Personal Data Compliance Officer. Applicants who are not contacted within two months may consider their applications unsuccessful and the personal data collected from the applicants will be retained for no longer than two years from the date of rejection during which the applicants may be considered for other suitable positions within the Bank.\u00a0", "employment_types": ["Full Time", "Permanent"], "selling_points": [], "locations": ["Central"], "categories": ["Banking / Finance", "Financial Services", "Professional Services", "Business Analysis / Data Analysis", "Marketing / Public Relations", "Marketing - Market Research"], "post_time": "2022-01-14T07:34:26Z", "salary": {"currency": null, "max": null, "min": null, "period": "monthly", "term": null}, "salary_visible": false, "title_keywords": ["research associate"], "responsibilities": ["ad-hoc", "revamp", "uat", "data", "implementation", "checking", "reports", "contact", "documentation", "plans", "migration"], "requirements": {"degrees": ["degree holder"], "majors": ["accounting"], "languages": [], "language_level": [], "hard_skills": ["web technologies", "professional qualifications"], "soft_skills": ["communication skills", "organizational skills", "hands-on", "attention to details", "multi-tasking skills"], "languages_combined": []}, "experience_required": {"duration": ["minimum 1 year"], "field": ["software development", "accounting", "relevant experience", "banking"]}}, {"job_id": "100003009049175", "location_code": "hk", "company": "Hong Kong Interbank Clearing Ltd", "job_title": "Officer (Administration)", "description": "Responsibilities:\n\nResponsible for performing daily settlement of all transactions initiated by Treasury and Investment Products Department, including Foreign Exchange, Money Market, securities, options, futures and other investment products in a timely and effective manner\nProcess settlement payments and receipts, and prepare summary reports\nEnsure all transactions are in full compliance with internal / external rules and regulations\nSupport User Acceptance Test (UAT) and participate in any projects as assigned\n\nRequirements:\n\nDegree holder in Business Administration or related disciplines\nWell-organized, self-motivated and attention to details\nGood command of written and spoken English and Chinese\nProficient in MS Word, Excel and Chinese Word processing\n\nAttractive remuneration package will be offered to the right candidates. Interested parties please click \"Apply Now\" to submit your full resume with current and expected salary to the Human Resources Division.\n\nPlease visit us at www.shacombank.com.hk for more information about our Bank.\n\nAll personal data collected will be used for recruitment related purposes strictly in accordance with the Bank's personal data policies, a copy of which will be provided immediately upon request by contacting our Personal Data Compliance Officer. Applicants who are not contacted within two months may consider their applications unsuccessful and the personal data collected from the applicants will be retained for no longer than two years from the date of rejection during which the applicants may be considered for other suitable positions within the Bank.", "employment_types": ["Full Time", "Permanent"], "selling_points": [], "locations": ["Ngau Tau Kok"], "categories": ["Admin & HR", "Clerical / Admin Staff", "Others", "Banking / Finance", "Financial Services"], "post_time": "2022-01-14T08:13:07Z", "salary": {"currency": null, "max": null, "min": null, "period": null, "term": null}, "salary_visible": false, "title_keywords": ["officer"], "responsibilities": ["regulations", "receipts", "uat", "compliance", "transactions", "payments", "reports"], "requirements": {"degrees": ["degree holder"], "majors": ["related disciplines", "business administration"], "languages": ["english", "chinese"], "language_level": ["good command", "proficient"], "hard_skills": ["excel", "chinese word processing", "ms word"], "soft_skills": ["self-motivated", "well-organized", "attention to details"], "languages_combined": [{"language": "english", "language_level": ["good command"]}, {"language": "chinese", "language_level": ["good command", "proficient"]}]}, "experience_required": {"duration": [], "field": []}}, {"job_id": "100003009047597", "location_code": "hk", "company": "Future Leader Recruitment Agency", "job_title": "Investment account manager (Fresh grad welcome 20k+)", "description": "Responsibilities:\n\nProvide credit card service to the existing merchants in accordance with the rules and regulations as stipulated by the Bank and Card Associations\nSolicit new merchant accounts, business opportunities and prepare proposals for management approval\nProvide cross-team support when necessary\n\nRequirements:\n\nDegree holder with 1 year of experience in banking or financial institutions, preferably with sales or customer service experience\nIndependent and self-driven to achieve target\nOutdoor work and handle merchants\u2019 enquiries in non-office hours will be required\nCustomer-focused with good communication and interpersonal skills; fluency in written and spoken English and Chinese, preferably with proficiency in Putonghua\nPC knowledge, including MS Word, Excel and Chinese word processing\n\nMore experienced candidate would be considered as Officer \u2013 Credit Card (Merchant Service)\n\nAttractive remuneration package will be offered to the right candidates. Interested parties please click\u00a0\"Apply Now\"\u00a0to submit your full resume with current and expected salary to the\u00a0Human Resources Division.\n\nPlease visit us at\u00a0www.shacombank.com.hk\u00a0for more information about our Bank.\n\nAll personal data collected will be used for recruitment related purposes strictly in accordance with the Bank's personal data policies, a copy of which will be provided immediately upon request by contacting our Personal Data Compliance Officer. Applicants who are not contacted within two months may consider their applications unsuccessful and the personal data collected from the applicants will be retained for no longer than two years from the date of rejection during which the applicants may be considered for other suitable positions within the Bank.", "employment_types": ["Full Time", "Internship"], "selling_points": ["Young and Fun working atmosphere", "Work life balance, office 1min from MTR", "Fast track promotions to management levels"], "locations": ["Quarry Bay"], "categories": ["Banking / Finance", "Investment", "Financial Services", "Management", "Management Trainee"], "post_time": "2022-01-14T03:32:30Z", "salary": {"currency": "HKD", "max": 24999, "min": 20000, "period": "monthly", "term": null}, "salary_visible": true, "title_keywords": ["account manager"], "responsibilities": ["regulations", "business opportunities", "management"], "requirements": {"degrees": ["degree holder"], "majors": [], "languages": ["putonghua", "english", "chinese"], "language_level": ["fluency", "proficiency"], "hard_skills": ["excel", "pc knowledge", "chinese word processing", "ms word"], "soft_skills": ["independent", "customer-focused", "communication and interpersonal skills", "customer service", "driven"], "languages_combined": [{"language": "putonghua", "language_level": ["proficiency", "fluency"]}, {"language": "english", "language_level": ["proficiency", "fluency"]}, {"language": "chinese", "language_level": ["proficiency", "fluency"]}]}, "experience_required": {"duration": ["1 year"], "field": ["financial institutions", "customer service", "banking"]}}, {"job_id": "100003009049529", "location_code": "hk", "company": "Mitsubishi HC Capital (Hong Kong) Limited", "job_title": "Senior / Customer Services Officer", "description": "Responsibilities:\n\nHandle account opening and provide sales support\nProvide counter services and quality customer service in branch\nCross-sell general banking products\n\nRequirements:\n\nDegree holder or above in any disciplines\nMinimum 1 year\u2019s experience in counter services preferred\nPasses in IIQE and HKSI licensing examinations\nCustomer and sales oriented with strong sense of responsibility\nGood communication and interpersonal skills; fluency in written and spoken English and Chinese, preferably with proficiency in Putonghua\nPC knowledge, including MS Word, Excel and Chinese word processing\nPotential working location : Central\n(Fresh graduates will be considered and training will be provided)\n\nAttractive remuneration package will be offered to the right candidates. Interested parties please click \"Apply Now\" to submit your full resume with current and expected salary to the Human Resources Division.\n\nPlease visit us at www.shacombank.com.hk for more information about our Bank.\n\nAll personal data collected will be used for recruitment related purposes strictly in accordance with the Bank's personal data policies, a copy of which will be provided immediately upon request by contacting our Personal Data Compliance Officer. Applicants who are not contacted within two months may consider their applications unsuccessful and the personal data collected from the applicants will be retained for no longer than two years from the date of rejection during which the applicants may be considered for other suitable positions within the Bank.", "employment_types": ["Full Time", "Permanent"], "selling_points": [], "locations": ["Mong Kok"], "categories": ["Banking / Finance", "Financial Services"], "post_time": "2022-01-15T03:50:30Z", "salary": {"currency": null, "max": null, "min": null, "period": "monthly", "term": null}, "salary_visible": false, "title_keywords": ["customer services officer"], "responsibilities": ["account opening", "customer service", "quality", "banking"], "requirements": {"degrees": ["degree holder"], "majors": ["any disciplines"], "languages": ["putonghua", "english", "chinese"], "language_level": ["fluency", "proficiency"], "hard_skills": ["excel", "iiqe", "chinese word processing", "hksi", "pc knowledge", "ms word"], "soft_skills": ["communication and interpersonal skills", "sense of responsibility"], "languages_combined": [{"language": "putonghua", "language_level": ["proficiency", "fluency"]}, {"language": "english", "language_level": ["proficiency", "fluency"]}, {"language": "chinese", "language_level": ["proficiency", "fluency"]}]}, "experience_required": {"duration": ["minimum 1 year"], "field": []}}, {"job_id": "100003009049161", "location_code": "hk", "company": "Shanghai Commercial Bank Ltd", "job_title": "Associate, Branch Operations (Safety Box)", "description": "Responsibilities\n\nPlay a key role in driving Bank's data analytics capability and providing business direction to support Bank's retail segment strategy.\nLead two sub-teams with focus on data analytics and segment management.\nWork closely with Technical and Product teams in developing and implementing analytics capabilities with the aim of understanding customer needs better and improve customer experience.\nIdentify business opportunities and execute product solutions to improve cross-selling, acquisition and retention of the target customer segment,\nProvide thought leadership in the design & implementation of Bank's digital transformation roadmap on customer needs re-discovery,\nRequirements\n\nDegree or above in Business, Analytics, Statistics or related disciplines\nAt least 8 years or above relevant experience in financial industry, with hands-on experience in developing product solutions is preferred\nExcellent presentation skills and is able to communicate at all levels\nGood command of both written and spoken English and Chinese. Knowledgeable on Mandarin is a plus.\n(Candidates with more experience will be considered as Vice President, Business Analytics and Segment Solutions)\n\nAttractive remuneration package will be offered to the right candidates. Interested parties please click \"Apply Now\" to submit your full resume with current and expected salary to the Human Resources Division.\n\nPlease visit us at www.shacombank.com.hk for more information about our Bank.\n\nAll personal data collected will be used for recruitment related purposes strictly in accordance with the Bank's personal data policies, a copy of which will be provided immediately upon request by contacting our Personal Data Compliance Officer. Applicants who are not contacted within two months may consider their applications unsuccessful and the personal data collected from the applicants will be retained for no longer than two years from the date of rejection during which the applicants may be considered for other suitable positions within the Bank.", "employment_types": ["Full Time", "Permanent"], "selling_points": ["Prepare reports for branch operations business", "Support branch in operations enquiries", "Perform counter service if required"], "locations": ["Tsuen Wan Area"], "categories": ["Banking / Finance", "Financial Services", "Others", "Order Processing & Operation / Settlement"], "post_time": "2022-01-15T03:50:09Z", "salary": {"currency": null, "max": null, "min": null, "period": "monthly", "term": null}, "salary_visible": false, "title_keywords": ["operations", "associate"], "responsibilities": ["management", "identify business opportunities", "data", "teams", "developing", "design", "implementation"], "requirements": {"degrees": ["degree or above"], "majors": ["related disciplines", "business", "statistics"], "languages": ["english", "chinese", "mandarin"], "language_level": ["good command"], "hard_skills": ["plus"], "soft_skills": ["hands-on", "presentation skills"], "languages_combined": [{"language": "english", "language_level": ["good command"]}, {"language": "chinese", "language_level": ["good command"]}, {"language": "mandarin", "language_level": []}]}, "experience_required": {"duration": ["at least 8 years"], "field": ["business", "financial industry", "relevant experience", "developing"]}}, {"job_id": "100003009049110", "location_code": "hk", "company": "Hong Kong Interbank Clearing Ltd", "job_title": "Assistant Officer (Clearing Operations)", "description": "Responsibilities:\n\nWork closely with branches/business units to solicit General Insurance business from potential clients\nHandle General Insurance business enquires including product features, terms and conditions from clients referred\nNegotiate terms and conditions with clients and prepare insurance quotations, and follow-up on renewal business\nProvide quality post-sales services to clients\nAssist in ad hoc marketing projects as assigned\n\nRequirements:\n\nPost-secondary education or above, with at least 5 subjects passed in HKCEE/HKDSE, including Chinese, English and Mathematics\nAt least 1 year of sales and marketing experience in General Insurance or Intermediary Company\nFresh graduate who are determined to develop his/her career in General Insurance will also be considered\nPassed in Paper I and II under Insurance Intermediaries Qualifying Examination (IIQE) preferred\nHolder of ANZIIF preferred\nBasic knowledge of General Insurance products\nSelf-motivated, sales driven and client focused\nGood people and problem-solving skills\n\nAttractive remuneration package will be offered to the right candidates. Interested parties please click \"Apply Now\" to submit your full resume with current and expected salary to the Human Resources Division.\n\nPlease visit us at www.shacombank.com.hk for more information about our Bank.\n\nAll personal data collected will be used for recruitment related purposes strictly in accordance with the Bank's personal data policies, a copy of which will be provided immediately upon request by contacting our Personal Data Compliance Officer. Applicants who are not contacted within two months may consider their applications unsuccessful and the personal data collected from the applicants will be retained for no longer than two years from the date of rejection during which the applicants may be considered for other suitable positions within the Bank.", "employment_types": ["Full Time", "Permanent"], "selling_points": [], "locations": ["Ngau Tau Kok"], "categories": ["Admin & HR", "Clerical / Admin Staff", "Others", "Banking / Finance", "Financial Services"], "post_time": "2022-01-14T08:08:14Z", "salary": {"currency": null, "max": null, "min": null, "period": null, "term": null}, "salary_visible": false, "title_keywords": ["assistant officer", "operations"], "responsibilities": ["ad hoc", "insurance", "quality", "marketing projects"], "requirements": {"degrees": ["hkdse", "secondary education", "fresh graduate"], "majors": ["mathematics", "insurance"], "languages": ["english", "chinese"], "language_level": [], "hard_skills": ["problem-solving skills", "iiqe", "basic"], "soft_skills": ["self-motivated", "determined", "focused", "problem-solving skills", "driven"], "languages_combined": [{"language": "english", "language_level": []}, {"language": "chinese", "language_level": []}]}, "experience_required": {"duration": ["at least 1 year"], "field": ["general insurance", "marketing"]}}, {"job_id": "100003009043527", "location_code": "hk", "company": "Randstad Hong Kong Limited", "job_title": "Finance Director | Investment Group (SFC Type 1, 2, 4, 6, 9)", "description": "Responsibilities:\n\nAssist Relationship Manager to provide total financial solutions to customers in the areas of personal / commercial lending\nCultivate long-term relationship with customers and explore new business opportunities through marketing and cross-selling bank products and services\nConduct credit analyses and prepare credit proposals\nWork closely with different teams to meet the established\u00a0business goals\nExecute any ad hoc duties as assigned\n\nRequirements:\n\nDegree holder in Business or related disciplines\nHolder of ECF on Credit Risk Management certification is preferred\nMinimum 1 year of experience in retail banking or general banking services\nExperience in secured and unsecured lending business and lending operations, including credit checking, loan portfolio administration and recommendation for new loans applications\nTeam player, self-motivated and able to work under pressure\nProficiency in both written and spoken English, Chinese and Putonghua\n\nAttractive remuneration package will be offered to the right candidates. Interested parties please click\u00a0\"Apply Now\"\u00a0to submit your full resume with current and expected salary to the\u00a0Human Resources Division.\n\nPlease visit us at\u00a0www.shacombank.com.hk\u00a0for more information about our Bank.\n\nAll personal data collected will be used for recruitment related purposes strictly in accordance with the Bank's personal data policies, a copy of which will be provided immediately upon request by contacting our Personal Data Compliance Officer. Applicants who are not contacted within two months may consider their applications unsuccessful and the personal data collected from the applicants will be retained for no longer than two years from the date of rejection during which the applicants may be considered for other suitable positions within the Bank.\u00a0", "employment_types": ["Full Time", "Permanent"], "selling_points": ["Leading SFC licensed financial services", "Supervise reporting team", "FRR, client money, financial control & reporting"], "locations": ["Not Specified"], "categories": ["Accounting", "Financial Controller", "Banking / Finance", "Financial Services", "Equities / Capital Markets"], "post_time": "2022-01-12T16:07:42Z", "salary": {"currency": "HKD", "max": 119999, "min": 90000, "period": "monthly", "term": null}, "salary_visible": true, "title_keywords": ["director"], "responsibilities": ["ad hoc duties", "business goals", "teams", "explore new business opportunities"], "requirements": {"degrees": ["degree holder"], "majors": ["related disciplines", "business"], "languages": ["putonghua", "english", "chinese"], "language_level": ["proficiency"], "hard_skills": [], "soft_skills": ["team player", "self-motivated", "work under pressure"], "languages_combined": [{"language": "putonghua", "language_level": ["proficiency"]}, {"language": "english", "language_level": ["proficiency"]}, {"language": "chinese", "language_level": ["proficiency"]}]}, "experience_required": {"duration": ["minimum 1 year"], "field": ["administration", "retail banking", "business", "banking services"]}}, {"job_id": "100003008385560", "location_code": "hk", "company": "Ashford Recruitment", "job_title": "Business Development Associate (Welcome Fresh Graduate )", "description": "Responsibilities:\n\nPerform audit assignments on various banking products and operations\nIdentify and assess key risk areas and propose solutions to mitigate potential risks\nAssist to prepare audit reports with findings and recommendations\nPerform follow-up for proper implementation of audit recommendations\nTake up ad hoc projects as assigned\nRequirements:\n\nDegree holder in Business, Accounting, Finance or related disciplines\nAt least 2 years of working experience, preferably in banking or financial services industry\nIndependent and initiative with analytical mind, audit and risk control mindset\nOrganized mind with good communication and problem-solving skills\nProficient in MS Office application, data analysis, etc\n\nAttractive remuneration package will be offered to the right candidates. Interested parties please click\u00a0\"Apply Now\"\u00a0to submit your full resume with current and expected salary to the\u00a0Human Resources Division.\n\nPlease visit us at\u00a0www.shacombank.com.hk\u00a0for more information about our Bank.\n\nAll personal data collected will be used for recruitment related purposes strictly in accordance with the Bank's personal data policies, a copy of which will be provided immediately upon request by contacting our Personal Data Compliance Officer. Applicants who are not contacted within two months may consider their applications unsuccessful and the personal data collected from the applicants will be retained for no longer than two years from the date of rejection during which the applicants may be considered for other suitable positions within the Bank.", "employment_types": ["Full Time"], "selling_points": ["For MT: 12 months  MT program", "on-job training in the financial sector", "Graduated from oversea university is an advantage"], "locations": ["Tsim Sha Tsui"], "categories": ["Banking / Finance", "Financial Services", "Insurance", "Others", "Others", "Student / Fresh Graduate / No Experience"], "post_time": "2022-01-14T06:40:42Z", "salary": {"currency": null, "max": null, "min": null, "period": "monthly", "term": null}, "salary_visible": false, "title_keywords": ["associate"], "responsibilities": ["operations", "implementation", "audit", "reports", "ad hoc projects", "banking"], "requirements": {"degrees": ["degree holder"], "majors": ["related disciplines", "finance", "business", "accounting"], "languages": [], "language_level": [], "hard_skills": ["problem-solving skills", "analysis", "ms office"], "soft_skills": ["organized", "independent", "communication", "analytical mind", "problem-solving skills", "initiative"], "languages_combined": []}, "experience_required": {"duration": ["at least 2 years"], "field": ["financial services industry", "banking"]}}, {"job_id": "100003009048372", "location_code": "hk", "company": "Fortune (HK) Securities Limited", "job_title": "Customer Service Officer \u5ba2\u6237\u670d\u52a1\u4e3b\u4efb", "description": "Responsibilities:\n\nAnalyze structured and unstructured data in order to understand customer behavior, particularly for the Small Medium Enterprise and Retail customer segments.\nOffer assistance on developing analytics reports and visualization dashboard for business monitoring and delivering insights.\nSupport data-led experiments to continually refine our customer-led value proposition.\nSupport data maintenance and data management of a new implemented customer data platform and increase our data quality and accuracy of the data sources.\n\nRequirements\n\nDegree holder in Computer Science, Data Science, Mathematics, Statistics, IT or relevant disciplines.\n3-5 years experiences in data science or machine learning.\nGood knowledge on database and statistical software (such as SAS, Python) is preferred.\nSelf-motivated, presentable and analytical.\nTeam player and strong communication skill.\nGood command of both spoken and written English and Chinese. Mandarin is an advantage.\n\nAttractive remuneration package will be offered to the right candidates. Interested parties please click\u00a0\"Apply Now\"\u00a0to submit your full resume with current and expected salary to the\u00a0Human Resources Division.\n\nPlease visit us at\u00a0www.shacombank.com.hk\u00a0for more information about our Bank.\n\nAll personal data collected will be used for recruitment related purposes strictly in accordance with the Bank's personal data policies, a copy of which will be provided immediately upon request by contacting our Personal Data Compliance Officer. Applicants who are not contacted within two months may consider their applications unsuccessful and the personal data collected from the applicants will be retained for no longer than two years from the date of rejection during which the applicants may be considered for other suitable positions within the Bank.", "employment_types": ["Full Time", "Permanent"], "selling_points": ["Write press releases to promote company products", "Perform KYC to comply with SFC for account opening", "Proficient in both spoken & written Eng. & Chinese"], "locations": ["Sheung Wan"], "categories": ["Banking / Finance", "Investment", "Financial Services", "Dealing & Trading"], "post_time": "2022-01-14T06:26:30Z", "salary": {"currency": null, "max": null, "min": null, "period": "monthly", "term": null}, "salary_visible": false, "title_keywords": ["customer service officer"], "responsibilities": ["management", "visualization", "maintenance", "data", "monitoring", "quality", "developing", "reports", "customer data"], "requirements": {"degrees": ["degree holder"], "majors": ["data science", "mathematics", "statistics", "it", "computer science"], "languages": ["english", "chinese", "mandarin"], "language_level": ["advantage", "good command"], "hard_skills": ["python", "sas"], "soft_skills": ["self-motivated", "communication skill", "presentable", "learning", "team player"], "languages_combined": [{"language": "english", "language_level": ["good command"]}, {"language": "chinese", "language_level": ["good command"]}, {"language": "mandarin", "language_level": ["advantage"]}]}, "experience_required": {"duration": ["3-5 years"], "field": []}}]