[{"job_id": "100003009045870", "location_code": "hk", "company": "Robert Half", "job_title": "PE Fund, Sr Asso (5+ mths bonus)", "description": "Our client is a listed company and established a global presence with a variety of businesses around the world.\u00a0 Reporting to Head and Creative Director, candidate will take the ownership and be the go-to person of the website and mobile app.\n\nKey Responsibilities:\u00a0\n\nRedesign the current the website and build a new app from scratch for new business direction and enhanced backend technology\nDeliver CRO, UX, and UI ideas and solutions\u00a0to optimize the results and performance\nDrive A/B tests to improve conversion funnels and user engagement\nEnsure the highest standard and keep improving the design based on new business requirements and changes\n\nKey Requirements:\n\n\nDegree holder in Multimedia Design, Arts, Visual Arts or any related disciplines\nMinimum 3 years\u2019 relevant working experience, preferably gained in\u00a0advertising / creative / branding agency with UX/UI focused experience\u00a0\nProficient in Adobe Creative Suite, Photoshop, Illustrator and InDesign\nHands-on experience in UX design software such as Adobe XD, InVision and UXPin. Knowledge and experience in After Effects and Premiere Pro a bonus\nGood command of both written and spoken English and Chinese\nStrong sense of responsibility, self-motivated, eager to learn and a good team player\nPortfolio is required for application\nCandidate with more experience will be considered as Senior UX/UI Designer\u00a0\n\nInterested parties please send your application with full career history, current & expected salary and portfolio by clicking Apply Now button. Applications will be treated in strict confidence. Personal data collected will be used for recruitment purposes only.", "employment_types": ["Full Time", "Permanent"], "selling_points": ["A leading Private Equity Fund house", "Fringe benefit with decent bonus", "Good exposure with career progression"], "locations": ["Central & Western Area"], "categories": ["Accounting", "Accountant", "Banking / Finance", "Fund Management"], "post_time": "2022-01-13T08:58:51Z", "salary": {"currency": null, "max": null, "min": null, "period": "monthly", "term": null}, "salary_visible": false, "title_keywords": [], "responsibilities": ["ui", "ideas", "website", "design"], "requirements": {"degrees": ["degree holder"], "majors": ["multimedia design", "related disciplines"], "languages": ["english", "chinese"], "language_level": ["good command"], "hard_skills": ["adobe xd", "indesign", "illustrator", "after effects", "multimedia", "premiere pro", "adobe creative suite", "photoshop"], "soft_skills": ["self-motivated", "good team player", "focused", "sense of responsibility", "eager to learn", "hands-on", "creative"], "languages_combined": [{"language": "english", "language_level": ["good command"]}, {"language": "chinese", "language_level": ["good command"]}]}, "experience_required": {"duration": ["minimum 3 years"], "field": ["designer", "advertising", "agency", "relevant working experience", "design"]}}, {"job_id": "100003009048712", "location_code": "hk", "company": "Rich Loyal Consultants Limited", "job_title": "Junior Investment Advisor (IANG/Fresh Graduate Welcomed)", "description": "5-days work\u00a0and attractive remuneration package (15K above with attractive bonuses)\nProfessional training program including mentorship support and leadership workhouse\nMedical scheme\u00a0& study allowance\nSponsorship for professional qualifications (CFP, CFA, RFP)\nIncentive Trips & Overseas Conferences\nExcellent career path and fast-track advancement opportunities\n\n\n\nResponsibilities:\u00a0\n\nProvide comprehensive financial and investment advice to clients\nIdentify and recommend the high profitable segments\u00a0\nMonitor and review investment portfolios\nMaintain a high-quality standard relationship with our existing clients\n\n\n\nRequirements:\n\nHong Kong citizens or work permit holders is a must\nUniversity graduate in any discipline (preferably in finance discipline)\nFresh graduate and IANG also will be considered\nCandidates with overseas study or work experience are welcomed\nSelf-motivated, Independent, excellent presentation skills with the ability to work effectively under pressure\nOutgoing and willing to work in a team-oriented atmosphere", "employment_types": ["Full Time", "Permanent"], "selling_points": ["Fresh graduate and IANG will be considered first", "5-day week, Flexible working hours, stable income", "Guaranteed bonus, Year-end bonus"], "locations": ["Quarry Bay"], "categories": ["Accounting", "Financial Analyst", "Banking / Finance", "Investment", "Fund Management"], "post_time": "2022-01-15T03:50:03Z", "salary": {"currency": "HKD", "max": 44999, "min": 30000, "period": "monthly", "term": null}, "salary_visible": true, "title_keywords": ["advisor", "junior"], "responsibilities": ["review", "quality", "monitor", "investment portfolios", "maintain"], "requirements": {"degrees": ["university graduate", "fresh graduate"], "majors": ["finance"], "languages": [], "language_level": [], "hard_skills": [], "soft_skills": ["work effectively", "outgoing", "self-motivated", "under pressure", "independent", "presentation skills"], "languages_combined": []}, "experience_required": {"duration": [], "field": []}}, {"job_id": "100003009040340", "location_code": "hk", "company": "Pathos Consultancy Limited", "job_title": "Fund Accounting Manager", "description": "The Company\nOur client is a sizable financial services company based in Hong Kong. They are currently looking for a Fund Accounting Manager to join the Fund Services team.\u00a0\n\nThe Role\n\n\nAssist to supervise a team in performing portfolio valuation NAV prices computation and other fund administration works daily\nCheck valuation reports and other fund administration works to ensure that they are correctly prepared\nMaintaining a high degree of accuracy and consistency in preparation of daily reporting and ensure that the pricing/valuation process are adhered to audit procedures and ensure service standards are met.\nDeal with issues and queries from clients in a professional and timely manner\nFollow and perform control as specified in the Procedure Manual and ensure comply with in all relevant work processes. Prompt escalation to Team Head or Department Head for any issues identified.\nStrong sense on risk awareness and supervise the team members to ensure they always comply with regulation and company\u2019s policy and procedures.\nParticipate in UAT for any new system enhancement prior to production\nParticipate in those tasks or projects as assigned by Department Head from time to time and take accountability.\u00a0\n\nYour Profile\n\n\nDegree holder in accountancy or Diploma in Business related discipline etc\nMinimum 8 years\u2019 experience in fund accounting and administration, with substantial\u00a0experience in regulated mutual funds / MPF / ORSO schemes operations\nGood command of spoken and written English and Chinese.\nBe flexible and an open-minded team player\nStrong adaptability to change\n\nApply Today\nTo apply online (Word attachment only), please click the 'Apply' button. Interested parties please apply with the most updated CV with expected salary and available date via JobsDB. Applicants who do not hear from us within 2 weeks may consider their applications unsuccessful.\n\nAbout Pathos\nWe are Pathos Consultancy Limited, a boutique recruitment firm based in Hong Kong strategically placing our candidates across all levels in permanent, temporary and contract roles.\u00a0 We specialize in IT and finance roles for banking, financial services and listed MNC sectors.", "employment_types": ["Full Time", "Permanent"], "selling_points": ["Financial Services", "Mutual Fund / Pension Fund", "Fund administration / Fund accounting"], "locations": ["Central"], "categories": ["Banking / Finance", "Financial Services", "Fund Management", "Asset Management"], "post_time": "2022-01-12T02:21:13Z", "salary": {"currency": null, "max": null, "min": null, "period": "monthly", "term": null}, "salary_visible": false, "title_keywords": ["accounting manager"], "responsibilities": ["reporting", "valuation", "control", "uat", "maintaining", "mpf", "operations", "procedures", "audit", "service standards", "reports", "administration"], "requirements": {"degrees": ["diploma", "degree", "degree holder"], "majors": ["business", "accountancy"], "languages": ["english", "chinese"], "language_level": ["good command"], "hard_skills": ["word"], "soft_skills": ["flexible", "accountability", "prompt", "open-minded", "timely", "adaptability", "team player"], "languages_combined": [{"language": "english", "language_level": ["good command"]}, {"language": "chinese", "language_level": ["good command"]}]}, "experience_required": {"duration": ["minimum 8 years"], "field": ["accounting", "mpf", "administration"]}}, {"job_id": "100003009035415", "location_code": "hk", "company": "China Tonghai Asset Management Limited", "job_title": "Fund Administrative Officer / Senior Fund Administrative Officer", "description": "Job Responsibilities: \u00a0\n\nResponsible for daily reconciliation of NAV, trade and positions of UCITS and hedge funds\nHandle FX, cash management and trade settlement of investment funds including Cayman and UCITS products\nHandling enquiries related to trade & settlement, corporate action\nEnsure timely delivery and upload of trade and position reports to custodians\nCalculation and reconciliation of fee payment to investment manager and distributors\nLiaise with internal parties for operations related reports\nHandle enquiries from auditors in preparing for financial statements of UCITS and Cayman funds\nHandling enquiries from clients in relations to operational related issues and in particularly the account opening of UCITS and Cayman products as well as FATCA and CRS reporting requirements\n\nJob Requirements:\n\nBachelor degree in Accounting, Finance or relevant discipline\nMinimum 2 \u2013 5 years of experience in fund administration or fund accounting and operation experiences\nGood knowledge in fund administration and accounting of UCITS and / or hedge Fund\nProficient in Microsoft Office, MS Excel. Good knowledge on Bloomberg usage would be an added advantage\nProficiency in both written and spoken in English, Cantonese and Mandarin\nGood communication skills and team player\nCandidates with more experience and qualifications will be considered as Senior Fund Administration Officer\nImmediate available is an advantage\u00a0\n\nWe offer attractive salary, benefits and 5-day workweek to the successful applicant.\u00a0 Please send your resume with\u00a0present\u00a0and\u00a0expected salary\u00a0to the Group Human Resources Manager. (Please quote the job reference number on the email subject line.)\u00a0\n\nPersonal Data collected will be used for recruitment purposes only.", "employment_types": ["Full Time", "Permanent"], "selling_points": ["5 days work week at Central", "Education allowance, medial, dental and insurance", "Asset Management"], "locations": ["Central"], "categories": ["Banking / Finance", "Fund Management", "Order Processing & Operation / Settlement", "Asset Management"], "post_time": "2022-01-10T07:04:29Z", "salary": {"currency": null, "max": null, "min": null, "period": "monthly", "term": null}, "salary_visible": false, "title_keywords": ["administrative officer"], "responsibilities": ["reporting", "management", "operations", "account opening", "financial statements", "handle enquiries", "payment", "reports", "liaise with", "internal parties"], "requirements": {"degrees": ["degree", "bachelor"], "majors": ["finance", "accounting"], "languages": ["cantonese", "english", "mandarin"], "language_level": ["proficiency"], "hard_skills": ["ms excel", "bloomberg", "microsoft office"], "soft_skills": ["communication skills", "team player"], "languages_combined": [{"language": "cantonese", "language_level": ["proficiency"]}, {"language": "english", "language_level": ["proficiency"]}, {"language": "mandarin", "language_level": ["proficiency"]}]}, "experience_required": {"duration": ["5 years"], "field": ["operation", "accounting", "administration"]}}, {"job_id": "100003009050137", "location_code": "hk", "company": "Don Nelson Recruitment Limited", "job_title": "Customer Service Executive - MPF Hotline (\u5e95\u85aa\u53ef\u905424K / \u4e94\u5929\u5de5\u4f5c / \u7121\u9700\u8f2a\u73ed / \u7121\u9700\u92b7\u552e)", "description": "\u8077\u8cac:\n\n\u8207\u5ba2\u6236\u4fdd\u6301\u826f\u597d\u95dc\u4fc2\uff0c\u89e3\u7b54\u5ba2\u6236\u67e5\u8a62\uff0c\u4e26\u63d0\u4f9b\u5f37\u7a4d\u91d1\u5efa\u8b70\u53ca\u670d\u52d9\u3002\n\u4e2d\u4e94\u6703\u8003/\u6587\u6191\u8a66\u5168\u79d1\u5408\u683c\u6216\u4ee5\u4e0a\u7a0b\u5ea6\n\u6301\u6709IIQE / HKSI \u6216\u5ba2\u6236\u670d\u52d9\u7d93\u9a57\u8005\uff0c\u5e95\u85aa\u53ef\u9ad8\u905426K\n\n\u5167\u5bb9:\n\n\u4e2d\u4e94\u6703\u8003/\u6587\u6191\u8a66 \u5168\u79d1\u5408\u683c\u6216\u4ee5\u4e0a\u7a0b\u5ea6\n\u6301\u6709IIQE / HKSI \u6216 \u5ba2\u6236\u670d\u52d9\u7d93\u9a57\u8005\uff0c\u5e95\u85aa\u53ef\u9ad8\u905426K\n\u5982\u6709\u8c50\u5bcc\u7d93\u9a57\u8005\uff0c\u5e95\u85aa\u53ef\u905426K\n5\u5929\u5de5\u4f5c (\u661f\u671f1-5\uff0c9:00am \u2013 6:00pm)\n\u826f\u597d\u6649\u5347\u6a5f\u6703\n\u7121\u9700\u8f2a\u73ed\u5de5\u4f5c\n\u6bcf\u5929\u5de5\u4f5c8\u5c0f\u6642\n\n\u54e1\u5de5\u798f\u5229:\n\n18-20 \u5929\u5e74\u5047 \u548c \u984d\u5916\u6709\u85aa\u5047\u671f (\u5a5a\u5047 , \u7522\u5047 , \u751f\u65e5\u5047)\n\n\u652f\u63f4\u54e1\u5de5\u8003\u53d6\u76f8\u95dc\u724c\u7167\n\n\u5168\u9762\u91ab\u7642\u4fdd\u96aa\uff0c\u5305\u62ec\u914d\u5076\u53ca\u5b50\u5973\n\n\u8c50\u539a\u5b63\u5ea6\u82b1\u7d05\uff0c\u96d9\u7ce7\u548c\u5e74\u7d42\u734e\u91d1\n\n\u4f4e\u606f\u54e1\u5de5\u7269\u696d\u6309\u63ed\u8cb8\u6b3e\n\n\u591a\u5143\u5316\u54e1\u5de5\u6d3b\u52d5\u53ca\u57f9\u8a13\u8ab2\u7a0b", "employment_types": ["Full Time"], "selling_points": ["\u5e95\u85aa\u9ad8\u905424,000", "\u4e94\u5929\u5de5\u4f5c / \u7121\u9700\u8f2a\u73ed", "\u826f\u597d\u6649\u5347\u6a5f\u6703"], "locations": ["Not Specified"], "categories": ["Banking / Finance", "Retail Banking", "Fund Management", "Sales, CS & Business Devpt", "Call Centre"], "post_time": "2022-01-15T03:50:51Z", "salary": {"currency": "HKD", "max": 29999, "min": 20000, "period": "monthly", "term": null}, "salary_visible": true, "title_keywords": ["customer service executive"], "responsibilities": [], "requirements": {"degrees": [], "majors": [], "languages": [], "language_level": [], "hard_skills": ["hksi"], "soft_skills": [], "languages_combined": []}, "experience_required": {"duration": [], "field": []}}, {"job_id": "100003009034388", "location_code": "hk", "company": "Caelus Asset Management Limited", "job_title": "Investment Associate / Analyst", "description": "Responsibility\n\u2022 Support the team to identify & evaluate potential investment opportunities\n\u2022 Produce investment materials to support business development effort\n\u2022 Market research, financial modelling, comparable company & deal analysis\n\u2022 Work alone with the execution team and ensure that deals are completed timely and effectively\n\nRequirement\n\u2022 Bachelor degree or above with 0-2 years of relevant experience, fresh graduate will also be considered\n\u2022 Detail-minded with strong capability to interpret financial statements and develop investment thesis\n\u2022 Outstanding Microsoft Office skills: PowerPoint, Excel, Word\n\u2022 Strong analytical and numerical skills\n\u2022 Good spoken Cantonese and English\n\nWe offer attractive remuneration and benefits to the right candidate.\n\nPlease send your full resume including your current and expected package by clicking \"APPLY NOW showing Expected Salary \"\n\nData collected will be used for recruitment purposes only. Personal data provided by job applicants will be used strictly in accordance with the Personal Data (Privacy) Ordinance. Only short-listed candidates will be invited for interview. The company will retain the applications for a maximum period of 6 months.\u00a0\n\n", "employment_types": ["Full Time"], "selling_points": [], "locations": ["Tsim Sha Tsui"], "categories": ["Banking / Finance", "Analyst", "Investment", "Fund Management"], "post_time": "2022-01-10T03:17:30Z", "salary": {"currency": null, "max": null, "min": null, "period": "monthly", "term": null}, "salary_visible": false, "title_keywords": ["analyst", "investment associate"], "responsibilities": ["evaluate", "analysis", "market research", "support the team"], "requirements": {"degrees": ["degree or above", "bachelor", "fresh graduate"], "majors": [], "languages": ["cantonese", "english"], "language_level": ["good"], "hard_skills": ["excel", "microsoft office", "word", "powerpoint", "numerical skills"], "soft_skills": ["detail-minded"], "languages_combined": [{"language": "cantonese", "language_level": ["good"]}, {"language": "english", "language_level": ["good"]}]}, "experience_required": {"duration": ["0-2 years"], "field": ["relevant experience"]}}, {"job_id": "100003009047528", "location_code": "hk", "company": "Cornerstone Global Partners", "job_title": "Corporate Communicitons VP/AVP (MPF Trustee, Up to 75k+bonus)", "description": "Our Client:\n\nA top Pension Trustee in HK\n\nRole Overview:\n\nEnhance Company\u2019s branding and image by PR events and strategy via multiple channels\nLead the team to create and execute PR campaigns, event and building rapport with members of the media.\nResponsible for corporate and marketing collaterals, press releases, CEO speeches, script of presentations, etc.\nIdentify industry award programmes to boost corporate image for maximizing business opportunity. Take charge of respective application to meet the goals.\nProvide support, including translation, to other departments on all kinds of communications materials such as correspondences and presentations, etc.\nUpdate corporate website and oversee the production of certain newsletters.\n\n\u00a0Ideal Profile:\n\nBachelor degree or above\n10+ years of practical experience in writing and editing for mass media, professional journals and publications\n5+ years of team management experience\nGood knowledge of pension and investment fund related areas would be an advantage\nGood networking with media\nCandidate with less experience will be considered as Assistant Vice President", "employment_types": ["Permanent"], "selling_points": ["Branding", "Pension, Investment Fund", "Media Connection"], "locations": ["Not Specified"], "categories": ["Banking / Finance", "Fund Management", "Marketing / Public Relations", "Marketing - Brand / Product Management", "Marketing - Marketing Communication"], "post_time": "2022-01-14T03:23:05Z", "salary": {"currency": "HKD", "max": 89999, "min": 45000, "period": "monthly", "term": null}, "salary_visible": true, "title_keywords": [], "responsibilities": ["provide support", "management", "marketing collaterals", "website", "presentations", "editing"], "requirements": {"degrees": ["degree or above", "bachelor"], "majors": [], "languages": [], "language_level": [], "hard_skills": ["translation", "presentations"], "soft_skills": ["responsible", "ideal"], "languages_combined": []}, "experience_required": {"duration": ["5+ years", "10+ years"], "field": ["management", "writing", "editing", "media", "team"]}}, {"job_id": "100003009041995", "location_code": "hk", "company": "Walters People (HK)", "job_title": "Portfolio Assistant/ Assistant Portfolio Manager (up to 40k)", "description": "Portfolio Assistant/ Assistant Portfolio Manager (<40k)\n- Career progression/ training\n- Investment Research/Fund experience\n- Portfolio management\n\nThis company is a reputable financial institution with strong presence around the world. They are looking for a candidate to support their investment research and assist in the portfolio management. This department has solid training program with stable working hours.\n\nJob duties\n\n- Responsible for investment research for the investment team\n- Collaborate with middle and back office team as well as external stakeholders to support investment team\n- Conduct investment performance analysis, reporting and reviewing regularly\n- Assist and handle the publication of fund factsheets, brochures for clients/ prospective clients\n- Enhance and review investment processes to ensure procedures are effective\n- Assist project manager on project execution tasks\n- Provide administrative support and support ad hoc projects\n\nJob Requirements:\n\u00b7 Bachelor degree in Business, Economics, Finance, or other related disciplines\n\u00b7 2 - 4 years' work experience in investment advisory, investment research, fund administration, or related fields\n\u00b7 Passionate about global financial markets and multi-asset classes (primarily in equity, fixed income, and money market instruments)\n\u00b7 Strong analytical capability and critical thinking skill\n\u00b7 Strong communication and interpersonal skills\n\u00b7 Good command of both English and Chinese\n\u00b7 CFA holder is preferred", "employment_types": ["Full Time", "Permanent"], "selling_points": ["Career progression/ training", "Investment Research/Fund experience", "Portfolio management"], "locations": ["Not Specified"], "categories": ["Accounting", "Accountant", "Banking / Finance", "Financial Services", "Fund Management"], "post_time": "2022-01-12T05:04:38Z", "salary": {"currency": "HKD", "max": 34999, "min": 30000, "period": "monthly", "term": null}, "salary_visible": true, "title_keywords": ["manager", "assistant"], "responsibilities": ["collaborate with", "reporting", "analysis", "review", "procedures", "back office", "ad hoc projects", "provide administrative support", "publication"], "requirements": {"degrees": ["degree", "bachelor"], "majors": ["finance", "economics", "related disciplines", "business"], "languages": ["english", "chinese"], "language_level": ["good command"], "hard_skills": ["cfa"], "soft_skills": ["communication and interpersonal skills", "passionate about"], "languages_combined": [{"language": "english", "language_level": ["good command"]}, {"language": "chinese", "language_level": ["good command"]}]}, "experience_required": {"duration": ["2 - 4 years"], "field": ["related", "research", "investment", "administration"]}}, {"job_id": "100003009040683", "location_code": "hk", "company": "Industrial and Commercial Bank of China Limited", "job_title": "Senior Officer to Manager, Business Support, Custody Services Department", "description": "Job Responsibilities\nReview and comment fund administration / custodian agreements, funds offering documents and clients\u2019 KYC and CDD documents\nCoordinate with fund managers and internal teams to finalize fund documents, fund administration /custodian agreements and related OM within prescribed timeframe\nPerform oversight on operation of trustee or fund administrator and delegated service generally, including performing regular review/control testing in relation to the trustee/fund administration business in accordance with internal policies and applicable regulations.\nClient onboarding management\nIdentify breaches, risks and other matters and provide advice to internal parties and/or clients on matters in fiduciary aspects for rectification/escalate report in timely manner\nReport trustee and fiduciary matters to Trustee director\nOther Compliance related issues\nJob Requirements\nUniversity graduate\u00a0in Law/Business/Economics/Compliance/CPA\nAt least 2 years of related working experience\nExperience in reviewing KYC documents preferred\nGood knowledge in private fund, custodian services or SFC authorized funds\nGood understanding of SFC authorized funds regulations and Cayman funds regulations", "employment_types": ["Permanent"], "selling_points": [], "locations": ["Central"], "categories": ["Banking / Finance", "Investment", "Fund Management", "Others"], "post_time": "2022-01-12T02:56:37Z", "salary": {"currency": null, "max": null, "min": null, "period": "monthly", "term": null}, "salary_visible": false, "title_keywords": ["senior officer", "manager"], "responsibilities": ["regulations", "control", "management", "cdd", "policies", "review", "coordinate with", "teams", "rectification", "testing", "regular review", "compliance", "provide advice", "kyc", "report", "internal parties", "administration"], "requirements": {"degrees": ["university graduate"], "majors": ["economics", "business", "law"], "languages": [], "language_level": [], "hard_skills": ["cpa", "sfc authorized funds regulations", "kyc"], "soft_skills": [], "languages_combined": []}, "experience_required": {"duration": ["at least 2 years"], "field": ["related"]}}, {"job_id": "100003009036172", "location_code": "hk", "company": "Amber Hill Holdings Limited", "job_title": "Fund Operation Manager", "description": "Amber Hill Group is an asset management institution based on financial science and technology. We aimed to provide intelligent and scientific asset management services for high-net-worth customers around the world and determined to become the world's well-known and integrated financial services group.\n\nWe are currently looking for talent to join our team as Fund Operation Manager.\n\nAs a Fund Operation Manager, you will:-\n\nChecking hedge fund valuations prepared by the external fund administrator\nAccurately prepare trade tickets and keep track of trade settlements\nProcess and review subscriptions, redemptions, and anti-money laundering application\nHandle month-end closing, vouchers, and office administration for the licensed corporation\nResponsible for routine operation and related secretarial work\nAssist accounts opening for client, brokerage, and banking services\nAssist in ad-hoc assignments and duties as required\nIt would be wonder if you are/have:-\n\nUniversity degree or above in Business Administration, Accounting, Finance, or related disciplines.\nMinimum of 5 years\u2019 working experience in fund operations and administration.\nGood interpersonal skills and presentation skills.\nFlexible and detailed minded.\nGood command of spoken and written English & Chinese, including Mandarin.\nImmediately available is highly preferred.\nYour application shall contain your resume stating your current & expected salary.\nYour application will go through severe screening & consideration; only qualified candidates will be contacted within two weeks after application.\nAll personal data collected will be strictly prohibited for recruitment purposes only; personal data of unsuccessful candidates will be destroyed within 12 months after the date of application.", "employment_types": ["Full Time", "Permanent"], "selling_points": ["Fund Operation, Hedged Fund, Fund valuation", "Fund accounting, subscriptions, redemption, AML", "Listed Company, Fintec, Grade A office"], "locations": ["Wan Chai"], "categories": ["Banking / Finance", "Fund Management", "Order Processing & Operation / Settlement", "Asset Management"], "post_time": "2022-01-10T09:33:18Z", "salary": {"currency": null, "max": null, "min": null, "period": "monthly", "term": null}, "salary_visible": false, "title_keywords": ["fund operation manager"], "responsibilities": ["administration", "office administration", "brokerage", "review", "ad-hoc assignments", "checking", "operations", "month-end closing", "recruitment", "banking", "personal data", "asset management"], "requirements": {"degrees": ["degree or above"], "majors": ["related disciplines", "finance", "accounting", "business administration"], "languages": ["english", "chinese", "mandarin"], "language_level": ["good command"], "hard_skills": ["go", "anti-money laundering"], "soft_skills": ["flexible", "determined", "responsible", "presentation skills", "interpersonal skills", "detailed"], "languages_combined": [{"language": "english", "language_level": ["good command"]}, {"language": "chinese", "language_level": ["good command"]}, {"language": "mandarin", "language_level": ["good command"]}]}, "experience_required": {"duration": ["minimum of 5 years"], "field": ["administration"]}}, {"job_id": "100003009050067", "location_code": "hk", "company": "Hong Kong Quality Assurance Agency", "job_title": "Project Manager (2-year contract)", "description": "Responsibilities:\n\nDeliver sustainability solutions in green finance, carbon management, sustainability strategy and reports\nProvide technical support on sales pitching, business meetings, seminars and proposal writing\nUndertake research, analysis and business visits to support development of new services\nConduct training and conformity assessment duties\n\nRequirements:\n\nDegree holder, preferably in environment, sustainability or business development\nKnowledge in green building assessment including BEAM Plus or LEED is preferred\nAt least 5 years work experience in related discipline\nGood data analysis and reporting skill\nGood command of spoken and written English and Chinese (Cantonese & Putonghua)\n\nRemuneration will be commensurate with qualification and working experience.\u00a0 Interested parties please forward your resume with photo, expected remuneration and personal particulars to the Human Resource Office, Hong Kong Quality Assurance Agency, 19th Floor, K Wah Centre, 191 Java Road, North Point, Hong Kong\u00a0OR\u00a0by fax to\u00a0 2202 9190\u00a0OR\u00a0 click Apply Now.\u00a0 Duplicate applications will not be considered.\u00a0\u00a0\n\nInformation supplied will be kept in strict confidence and only be used for recruitment related purpose.\u00a0 Applicants not invited for interview within 6 weeks may consider their applications unsuccessful. Application forms and curriculum vitae will be kept for a period of 3 months after completion of the selection process.", "employment_types": ["Full Time", "Contract"], "selling_points": ["Green Finance/Environmental/Sustainability field", "Minimum 5 years related working experience", "5-day work week, Medical & Life Insurance"], "locations": ["North Point"], "categories": ["Banking / Finance", "Fund Management", "Sales, CS & Business Devpt", "Business Development", "Sciences, Lab, R&D", "Environmental Science / Waste Management"], "post_time": "2022-01-14T09:43:12Z", "salary": {"currency": null, "max": null, "min": null, "period": "monthly", "term": null}, "salary_visible": false, "title_keywords": ["project manager"], "responsibilities": ["technical support", "carbon management", "analysis", "reports"], "requirements": {"degrees": ["degree holder"], "majors": ["business"], "languages": ["cantonese", "putonghua", "english", "chinese"], "language_level": ["good command"], "hard_skills": ["plus", "analysis"], "soft_skills": [], "languages_combined": [{"language": "cantonese", "language_level": ["good command"]}, {"language": "putonghua", "language_level": ["good command"]}, {"language": "english", "language_level": ["good command"]}, {"language": "chinese", "language_level": ["good command"]}]}, "experience_required": {"duration": ["at least 5 years"], "field": ["related"]}}, {"job_id": "100003009046488", "location_code": "hk", "company": "Randstad Hong Kong Limited", "job_title": "Asset Management - Sales Associate", "description": "about the company.\n\nMy client is an asset management firm in Hong Kong. Due to expansion, they are looking for a sales assistant to join their team.\n\nabout the team.\n\nJoin this firm with great team culture and supportive environment to stably develop your own career and expand market share for the asset management\n\nabout the job.\n\nAs a member of the team, you will cover all aspects in\n\nAssist Head of Asset Management for identifying business opportunities of mutual fund, private equity fund or other products for corporate or financial institutional clients\nProvide support on business plan and marketing seminars and activities to develop more business opportunities\nFollow and maintain relationship with clients and provide investors' feedback to fund managers\nExecute business development plan to expand fund resources\n\nskills & experiences required.\n\nYour previous experience as client services, sales or business development in banking or asset management and familiarity with fund products will help you succeed in this role. You will have 1+ years of experience in client services or ARM. Qualifying in HKSI LE exam/ License type 9 would be an advantage. Due to the targeted client segment, you will be proficient in Mandarin and English on a daily basis.\n\nIf you're interested in this role, click 'apply now' or for more information and a confidential discussion on this role or to find out more opportunities contact Anthony Chan at +852 2232 3425 or email anthony.chan@randstad.com.hk", "employment_types": ["Full Time", "Permanent"], "selling_points": ["Asset Management - Fund", "Sales Support", "Attractive salary package"], "locations": ["Not Specified"], "categories": ["Banking / Finance", "Investment", "Fund Management", "Asset Management"], "post_time": "2022-01-13T11:54:51Z", "salary": {"currency": "HKD", "max": 19999, "min": 17000, "period": "monthly", "term": null}, "salary_visible": true, "title_keywords": ["sales associate", "asset management"], "responsibilities": ["provide support", "business opportunities", "develop", "maintain", "contact", "plan", "banking", "business plan", "asset management"], "requirements": {"degrees": [], "majors": [], "languages": ["english", "mandarin"], "language_level": ["proficient"], "hard_skills": ["private equity", "hksi"], "soft_skills": ["supportive", "interested in"], "languages_combined": [{"language": "english", "language_level": ["proficient"]}, {"language": "mandarin", "language_level": ["proficient"]}]}, "experience_required": {"duration": ["1+ years"], "field": ["business development", "asset management", "banking"]}}, {"job_id": "100003009035611", "location_code": "hk", "company": "Kata Gj Palm Company", "job_title": "Assistant Relationship Manager", "description": "Our client is the leading financial advisory firm in Hong Kong with thousands of professional financial consultants in the Asia Pacific region. They focus on three core businesses: financial advisory, financial product manufacturing and FinTech. They are looking a Assistant Relationship Manager within their Wealth Management team.\n\nResponsibilities:\n\nSupporting Investment Representatives in financial and maintaining successful relationships with clients\nTo provide comprehensive financial strategies to clients including on financial planning, insurance and securities service\u00a0\nTo manage clients\u2019 financial portfolios periodically\nTo provide quality after-sales services to maintain relationship with clients Engage in team management and related activities Markets analysis and market event\nTo explore oversea property, asset management and risk management solution to individual and corporate clients\nQualifications:\n\nBachelor degree from University (Preferably in Finance, Business Management, Economics or related discipline)\nat least 1 years of relevant financial services experience\nDedicated team player with keen interest in financial industry\n\nJob Offer:\n\nWealth Management team\nSteep learning curve\nExcellent career development\nAttractive bonus package", "employment_types": ["Full Time", "Part Time", "Permanent", "Internship"], "selling_points": [], "locations": ["Admiralty"], "categories": ["Banking / Finance", "Fund Management", "Marketing / Public Relations", "Marketing - Market Research", "Asset Management"], "post_time": "2022-01-11T16:01:36Z", "salary": {"currency": "HKD", "max": 29999, "min": 20000, "period": "monthly", "term": null}, "salary_visible": true, "title_keywords": ["assistant relationship manager"], "responsibilities": ["management team", "management", "maintaining", "analysis", "quality", "maintain", "asset management", "career development", "insurance", "planning"], "requirements": {"degrees": ["degree", "bachelor"], "majors": ["finance", "business", "economics"], "languages": [], "language_level": [], "hard_skills": ["business management", "focus", "analysis"], "soft_skills": ["keen", "comprehensive", "team player", "learning", "focus"], "languages_combined": []}, "experience_required": {"duration": ["at least 1 years"], "field": ["financial services"]}}, {"job_id": "100003009038657", "location_code": "hk", "company": "Heyokha Brothers Limited", "job_title": "Portfolio Assistant", "description": "Help us execute strategies along with our Portfolio Manager and focus on quality and effective portfolio management.\n\nWe are looking for individual who has at least two years of full time working experience in portfolio or fund management business in financial institutions or family offices.\n\nHit the \"Apply\" button if you feel you share our passions:\n\nEnthusiasm for financial markets\nHigh interest in commodities supercyle and inflation hedges, market leaderships and technology excellence, as well as metaverse and virtual assets.\nGood knowledge in areas such as economics, finance, equity markets, or asset management.\nFluent in English with good writing skill\n\nDay to day tasks and responsibilities include:\n\n\n\nProvide enhancements to all portfolio management processes.\nGathering of industry information, developing relevant execution and digital settlement procedures, deploying advanced information and portfolio management systems as well as carrying out portfolio rebalancing driven by various investment strategies across all asset classes.\u00a0\nManage various ad hoc projects and provide support to sales, marketing and client service.\nPreparing presentation materials for client or prospect meetings, monitoring opening and termination of all investment related counterparty and client accounts, and ensuring the accuracy of portfolio valuations.\nMonitor all accounts for tracking cash and settlements for all funds, and to resolve all counterparty and client inquiries within required timeframe.\u00a0\nPrepare client reports and carry out regular client reviews.\nProducing fund and portfolio review reports within required timeframe, monitoring the adherence of client constraints and requests, arranging client meeting schedules and pre-distribution of documents, as well as providing research and answers for client enquiries.", "employment_types": ["Full Time"], "selling_points": [], "locations": ["Central"], "categories": ["Banking / Finance", "Fund Management"], "post_time": "2022-01-11T07:50:48Z", "salary": {"currency": null, "max": null, "min": null, "period": "monthly", "term": null}, "salary_visible": false, "title_keywords": ["assistant"], "responsibilities": ["client reports", "management", "investment strategies", "provide support", "tracking", "schedules", "systems", "procedures", "quality", "developing", "monitoring", "monitor", "review", "ad hoc projects", "reports", "asset management"], "requirements": {"degrees": [], "majors": [], "languages": ["english"], "language_level": ["good", "fluent"], "hard_skills": ["focus", "writing skill"], "soft_skills": ["advanced", "driven", "writing skill", "focus", "presentation"], "languages_combined": [{"language": "english", "language_level": ["fluent", "good"]}]}, "experience_required": {"duration": ["at least two years"], "field": ["management", "business", "financial institutions"]}}, {"job_id": "100003009039962", "location_code": "hk", "company": "MCP Asset Management Company Limited", "job_title": "SENIOR FUND ACCOUNTANT / FUND ACCOUNTANT", "description": "Core\u00a0 responsibilities\n\nReview of Net Asset Value for the funds\nHandle queries from service providers or regulatory bodies for the funds\nMonitor cash activity of the funds including cash transfer for investment needs, receipt of subscription proceeds, payment of redemptions and fund\u2019s operating expenses\nAssist in annual audit queries and review annual financial statements for the funds\nAssist in other clerical works and ad-hoc duties as required\n\n\n\nRequirements\n\nDegree holder preferably in Accounting, finance or related discipline with two years working\nGood written and verbal communication in English & Cantonese\nA team player with excellent attitude; willing to take on multiple functions\nProficient in MS office\nDetailed minded with good problem solving skill\nKnowledge of various financial instruments with direct working experience of Bloomberg terminal will be beneficial.\n\n\n\nWe offer a competitive salary and benefits to the right candidates\n\nInterested parties, please send your full resume with expected salary by clicking 'Apply Now'.\n\nPersonal data provided by job applicants will be used for recruitment purposes only and will be treated in strict confidential.", "employment_types": ["Full Time"], "selling_points": [], "locations": ["Causeway Bay"], "categories": ["Banking / Finance", "Investment", "Financial Services", "Fund Management"], "post_time": "2022-01-11T16:02:22Z", "salary": {"currency": null, "max": null, "min": null, "period": "monthly", "term": null}, "salary_visible": false, "title_keywords": ["accountant"], "responsibilities": ["annual audit", "expenses", "review", "monitor", "financial statements", "payment", "ad-hoc duties"], "requirements": {"degrees": ["degree holder"], "majors": ["finance", "accounting"], "languages": ["cantonese", "english"], "language_level": ["good"], "hard_skills": ["problem solving", "bloomberg", "ms office"], "soft_skills": ["communication", "team player", "problem solving skill", "detailed"], "languages_combined": [{"language": "cantonese", "language_level": ["good"]}, {"language": "english", "language_level": ["good"]}]}, "experience_required": {"duration": [], "field": ["financial"]}}, {"job_id": "100003009037553", "location_code": "hk", "company": "Robert Half", "job_title": "PE Fund, Sr Asso (5+ mths bonus)", "description": "Our client is a leading Asset Management, the principal activities included PE fund investment, Hedge Fund investment, insurance and corporate finance. To cope with their business expansion, they are looking for a caliber to join their team.\n\n\n\nHandle daily fund accounting including NAV calculation, cash and position reconciliation, cash collateral, distribution\u2026etc\nWork closely with third party service providers such as external auditors, tax consultants and compliance team\nAssist in new fund set up and wok with external and internal parties such as Risk, Investment, Finance, Sales\u2026etc\nMonitor and continuously improve the quality of services delivered by the services providers\nPerform ad hoc duties as assigned\n\n\n\nRequirements:\n\nBachelor's Degree in Accounting, Finance or relevant discipline\nMinimum of 4 years' fund related experience and consider candidates came from Fund Admin or Fund Operations\nKnowledge of Alternative Investment Fund with direct working experience of fund accounting,\nMember of CPA is an added advantage\nHigh level of multi-tasking and time management skill are required\nA team-player with excellent working attitude; willing to take on multiple functions\nExcellent verbal and written communication skills\n\n\nApply Today\n\nTo apply online (Word attachment only), please click the 'Apply' button. Please note that only short-listed candidates will be contacted.", "employment_types": ["Full Time", "Permanent"], "selling_points": ["A leading Private Equity Fund house", "Fringe benefit with decent bonus", "Good exposure with career progression"], "locations": ["Central & Western Area"], "categories": ["Accounting", "Accountant", "Banking / Finance", "Fund Management"], "post_time": "2022-01-11T03:06:28Z", "salary": {"currency": null, "max": null, "min": null, "period": "monthly", "term": null}, "salary_visible": false, "title_keywords": [], "responsibilities": ["tax", "ad hoc duties", "management", "operations", "compliance", "monitor", "quality", "communication", "asset management", "insurance", "third party", "internal parties", "external auditors"], "requirements": {"degrees": ["degree", "bachelor"], "majors": ["finance", "accounting"], "languages": [], "language_level": [], "hard_skills": ["cpa", "pe", "word"], "soft_skills": ["team-player", "communication skills", "multi-tasking", "time management skill"], "languages_combined": []}, "experience_required": {"duration": ["minimum of 4 years"], "field": ["related", "admin", "investment", "accounting"]}}, {"job_id": "100003009043952", "location_code": "hk", "company": "AIA International Limited", "job_title": "Wealth Management Manager", "description": "We seek to attract high-caliber\u00a0talent by offering a dynamic working environment, good career development opportunities and competitive compensation packages.\n\nJob Details:\nProvide professional financial advice and services to clients\nIdentify client financials needs and establish planning accordingly\nUpdate financial knowledge and news to your clients\nPrivate wealth management services to your clients\nWe are looking for:\n\nDegree holder in all discipline\nHong Kong ID Card holders and IANG VISA and Dependent VISA holders are welcomed\nFresh Graduates are welcomed. (1-2 years working experience is an advantage)\nEnergetic, mature, self-motivated, hardworking and willing to learn\nExperience in sales industry or background in mainland will be an advantage\nProficiency in both English and Chinese, fluency in Mandarins would be an advantage\nGood interpersonal and communication skills and strong teamwork spirit\nWe Offer:\n\nEligible applicants will be recommended to join the AIA Premier Academy training program to provide you with comprehensive wealth management theory and practice training, and strive to reach the first Million Dollar Round Table (MDRT) qualification\nOver 200 hours well-structured and comprehensive mentoring programs for professional advancement\nFast-track advancement opportunities, will be promoted to management positions within 12 months.\nGain accreditation from the internationally acclaimed Million Dollar Round Table association\nPromising career path to Associate Director/ Director of Wealth Management\nProfessional designations training e.g. CFP, AFP, RFP, RFC, FchFp\nBenefits:\n\nStandard income HK$500,000-HK$800,000 per annum\nMonthly Allowance from $10,000 to 50,000+, Attractive commission package + year-end bonus + comprehensive fringe benefits\nOverseas learning experience\nSpecial holiday package\u00a0\nAll information provided by applicants will be treated in strict confidence, and used for recruitment purpose only.", "employment_types": ["Full Time", "Permanent"], "selling_points": ["HK ID Card holders/ IANG or Dependent VISA", "Trainee/ Manager/ Senior Manager", "Flexible working hours/ high income"], "locations": ["Causeway Bay"], "categories": ["Banking / Finance", "Fund Management"], "post_time": "2022-01-13T02:34:53Z", "salary": {"currency": null, "max": null, "min": null, "period": "monthly", "term": null}, "salary_visible": false, "title_keywords": ["wealth management manager"], "responsibilities": ["communication", "management", "planning", "career development"], "requirements": {"degrees": ["degree holder"], "majors": [], "languages": ["english", "chinese"], "language_level": ["fluency", "advantage", "proficiency"], "hard_skills": ["id", "dynamic"], "soft_skills": ["communication skills", "self-motivated", "willing to learn", "mature", "dynamic", "teamwork spirit", "energetic", "interpersonal", "hardworking"], "languages_combined": [{"language": "english", "language_level": ["proficiency", "fluency", "advantage"]}, {"language": "chinese", "language_level": ["proficiency", "fluency", "advantage"]}]}, "experience_required": {"duration": ["1-2 years"], "field": []}}, {"job_id": "100003009039685", "location_code": "hk", "company": "Linnovate Partners Limited", "job_title": "Fund Accountant", "description": "The Role\nTo cope with our business growth, we are looking for Fund Accountants to join our Hong Kong team.\u00a0\u00a0The successful candidates will be responsible for the analysis and investment reporting for private equity and venture capital funds.\n\n\n\nResponsibilities\n\nProvide accounting services for clients including preparing and processing transactions and financial reports;\nProvide support to clients\u2019 investor inquires;\nPrepare fee calculations (managing fees, carried interest and waterfall) verifying that calculations are in accordance with LPA;\nPrepare investor capital and distribution notices;\nPrepare ad hoc requests regarding fund and investor specific reports as well as analysis;\nPrepare fund annual and quarterly financial reports;\nPrepare SPV accounting;\nUnderstand and assist clients with other reporting, such as FATCA, K1 etc.;\nAssist clients to address and resolve audit inquiries from external auditors during year-end audit;\nParticipate in pre-project stage discussion with the clients and to define more detailed services model for specific clients as required;\nPerform additional duties as assigned.\n\nRequirements\n\nBachelor\u2019s degree in Accounting or relevant disciplines;\n2-3 year experience preferably with CPA firms working environment;\nCandidate with private equity experience will be considered for senior position;\nStudent or associate member of CPA Australia, ACCA or equivalent qualification;\nBasic knowledge of different accounting standards (IFRS, GAAPs);\nExperience with RMB Fund accounting is a plus;\n\nOther Skills\n\nStrong organizational skills;\nAbility to communicate effectively;\nGood time management skills with ability to multi-task;\nFluency in both spoken and written English and Chinese (Mandarin);\nProficiency in Excel and other windows-based software;\nExperience with fund accounting software solutions (Investran and Altareturn) would be highly advantageous;\nExperience with Alternative investments management software (eFront) would be highly advantageous;\nKnowledge of Accounting software (Kingdee, SunSystems and Quickbook, etc.) is a plus.\n\nWe offer the right candidate attractive remuneration package and outstanding prospects for career advancement and development. The right candidate will progress career in a forward thinking and dynamic business with exciting growth plans. If you are qualified and interested, please send your full resume with current & expected salary and availability by clicking \"APPLY \".\n\nAll information collected will be treated as strictly confidential and used for recruitment purposes only. (Only shortlisted candidates will be notified)", "employment_types": ["Full Time", "Permanent"], "selling_points": ["Private Equity Fund Administration & Accounting", "RMB Fund", "CPA Australia, HKICPA, ACCA"], "locations": ["Kwun Tong"], "categories": ["Accounting", "Accountant", "Banking / Finance", "Financial Services", "Fund Management"], "post_time": "2022-01-11T10:30:25Z", "salary": {"currency": null, "max": null, "min": null, "period": "monthly", "term": null}, "salary_visible": false, "title_keywords": ["accountant"], "responsibilities": ["reporting", "financial reports", "provide support", "year-end", "ad hoc requests", "analysis", "additional duties", "audit", "transactions", "reports", "external auditors"], "requirements": {"degrees": ["degree", "bachelor"], "majors": ["accounting"], "languages": ["english", "chinese", "mandarin"], "language_level": ["fluency"], "hard_skills": ["excel", "acca", "ifrs", "basic", "plus", "accounting software", "cpa", "private equity"], "soft_skills": ["time management skills", "organizational skills", "multi-task"], "languages_combined": [{"language": "english", "language_level": ["fluency"]}, {"language": "chinese", "language_level": ["fluency"]}, {"language": "mandarin", "language_level": []}]}, "experience_required": {"duration": ["2-3 year"], "field": ["management", "accounting"]}}, {"job_id": "100003009043736", "location_code": "hk", "company": "KeeReal Consulting Limited", "job_title": "Finance Manager / Financial Controller (Private Equity & Venture Capital | Attractive Package)", "description": "Our client is a fast glowing private equity & venture capital company with regional offices. They are currently looking for a Finance Manager / Financial Controller (Private Equity & Venture Capital | Attractive Package) in the Hong Kong office to join their Finance dynamic team.\n\nResponsibilities:\nPrepare and review NAV, reconciliation on daily basis and monitor cash activity of the funds\nManage full set of fund accounting, reconciliation, and compliance duties\nPrepare and review internal and external reports for the funds' investors and other stakeholders\nResponsible for capital calls and review waterfall calculation\nPlan, implement and review the financial strategies of the corporation including budgeting, financing, taxation handling and compliance\nPrepare cash flow projection and forecasting for\u00a0 the corporation\nCoordinate SFC regulated activities for the licensed corporation and associated entities\nSupport management in key strategic initiatives and business improvement projects\nAny other ad hoc assignments assigned by the management team\nRequirements:\n\nDegree holder or above\u00a0in Accounting or Finance is required\nCPA qualified holder\nStrong understanding of regulations especially SFO\nAt least 5 years of experience in Fund Accounting\nStrong oral and written communication skills in English and Chinese", "employment_types": ["Full Time", "Permanent"], "selling_points": ["8 years of FI experience", "Attractive remuneration package", "Private Equity & Venture Capital"], "locations": ["Not Specified"], "categories": ["Accounting", "Financial Controller", "Banking / Finance", "Financial Services", "Fund Management"], "post_time": "2022-01-13T01:43:40Z", "salary": {"currency": null, "max": null, "min": null, "period": "monthly", "term": null}, "salary_visible": false, "title_keywords": ["finance manager", "financial controller"], "responsibilities": ["taxation", "management", "management team", "budgeting", "compliance", "review", "monitor", "coordinate", "cash flow", "reports", "ad hoc assignments", "plan", "forecasting"], "requirements": {"degrees": ["degree holder"], "majors": ["finance", "accounting"], "languages": ["english", "chinese"], "language_level": [], "hard_skills": ["cpa", "sfo"], "soft_skills": ["communication skills", "oral"], "languages_combined": [{"language": "english", "language_level": []}, {"language": "chinese", "language_level": []}]}, "experience_required": {"duration": ["at least 5 years"], "field": ["accounting"]}}, {"job_id": "100003009043985", "location_code": "hk", "company": "Avenue Family Office Limited", "job_title": "Graduate Trainee (For 2021 graduates) / Full-time Intern (For 2022 graduates)", "description": "Responsibilities\n\nPractice on asset management, project, research, operation and analysis skills\nWork with colleagues in different departments\nLiaise with professional counterparties and execute deals\nDeal with ad hoc tasks as assigned by supervisors\nRequirements\n\nDegree Holder graduated from\u00a0the world's Top 100 universities\u00a0\nPossess less than 1 year working experience, Fresh Graduates are welcomed\nDetermined to advance in asset and fund management\nExcellent in analytical and critical thinking\nStrong in communications skills (spoken & written) in both English & Chinese\nBe a good team player, proactive and highly motivated\nPositive and can-do attitude\nDetailed mind, committed and willing to work in a fast pace environment and excited to learn new things\nProficient in Microsoft Office applications\n\nAVENUE is an Equal Opportunity Employer. We respect and seek to empower each individual and support the diverse cultures, perspectives, skills and experiences within our workforce. Personal data provided by job applicants will be used strictly in accordance with the employer\u2019s personal data policies, a copy of which will be provided immediately upon request.\n", "employment_types": ["Full Time", "Permanent"], "selling_points": ["A young team with happy & relaxing working culture", "Fast learner and keen to develop career in Finance", "Comprehensive exposure to Fund, Bond, Equity, etc."], "locations": ["Central"], "categories": ["Banking / Finance", "Private Banking", "Fund Management", "Asset Management"], "post_time": "2022-01-13T02:40:59Z", "salary": {"currency": null, "max": null, "min": null, "period": "monthly", "term": null}, "salary_visible": false, "title_keywords": ["graduate trainee", "intern"], "responsibilities": ["liaise with", "analysis", "ad hoc tasks", "asset management"], "requirements": {"degrees": ["degree holder"], "majors": [], "languages": ["english", "chinese"], "language_level": [], "hard_skills": ["microsoft office"], "soft_skills": ["good team player", "determined", "can-do attitude", "committed", "diverse", "motivated", "proactive", "detailed mind", "positive"], "languages_combined": [{"language": "english", "language_level": []}, {"language": "chinese", "language_level": []}]}, "experience_required": {"duration": ["1 year"], "field": []}}, {"job_id": "100003009034629", "location_code": "hk", "company": "Links International", "job_title": "Fund Operations Associate - Welcome Fund Admin!", "description": "Responsibilities:\n\nPrepare daily and monthly reconciliation, NAV estimates\nPreparing monthly fund valuation, return attribution and investor reporting\nMonitor various fund operation issues including settlements, collateral, and cash management\nPerform trade bookings, trade matching, daily and P&L reconciliations, failed trade investigations\nLiaise with prime brokers and fund administrator on break resolutions\nPerform automation and process review to streamline and document workflow\nSupport the trading team and assist in back office tasks\nHandle ad-hoc projects assigned by management\n\nRequirements:\n\nUniversity degree in Accounting, Finance or other related disciplines\nMinimum of 1 year fund/ accounting related experience\nKnowledge of financial derivative products is an advantage\nExcellent communication skills in English and Mandarin, mature mindset and confident personality in order to interact with Trading teams and senior management to address business issues\nGood attention to details, able to adapt and work well under pressure\nProficiency in Excel and SQL are preferable\nA positive attitude, a sense of satisfaction from doing your best, and self-discipline are all essential", "employment_types": ["Full Time", "Permanent"], "selling_points": ["Guaranteed 13 months salary", "Work life balance", "All rounded and dynamic role"], "locations": ["Not Specified"], "categories": ["Accounting", "Accountant", "Banking / Finance", "Fund Management", "Asset Management"], "post_time": "2022-01-10T03:50:17Z", "salary": {"currency": null, "max": null, "min": null, "period": "monthly", "term": null}, "salary_visible": false, "title_keywords": ["admin", "fund operations associate"], "responsibilities": ["valuation", "reporting", "management", "prime brokers", "review", "monitor", "back office", "p&l", "reconciliations", "liaise with", "ad-hoc projects"], "requirements": {"degrees": ["university degree"], "majors": ["related disciplines", "finance", "accounting"], "languages": ["english", "mandarin"], "language_level": ["excellent"], "hard_skills": ["sql", "excel"], "soft_skills": ["confident", "communication skills", "under pressure", "mature", "positive attitude", "attention to details"], "languages_combined": [{"language": "english", "language_level": ["excellent"]}, {"language": "mandarin", "language_level": ["excellent"]}]}, "experience_required": {"duration": ["minimum of 1 year"], "field": ["related", "accounting"]}}, {"job_id": "100003009050298", "location_code": "hk", "company": "Vegasoul Capital Management (Asia) Limited", "job_title": "Quantitative Researcher - attractive salary!", "description": "We are looking for\u00a0candidates\u00a0(currently working in Hong Kong)\u00a0with a strong quantitative background in order to expand our research team. Candidates with degrees in scientific disciplines such as\u00a0computer science,\u00a0electronic engineering,\u00a0finance,\u00a0physics, mathematics, statistics or similar fields.\u00a0 Experience with global equities markets will be a definite advantage!\n\nAlthough prior experience in financial markets is not specifically required, experience with large databases and time series modeling, in particular high-frequency finance time series, will be considered a plus.\n\nDue to the technical nature of the job, all candidates are required to be proficient in programming, with emphasis on C#, C++ and Matlab.\n\nThe successful candidate, under the supervision of portfolio managers, will work on a 3-year apprenticeship model where he\\she learns how to develop trading strategies and manage a large institutional portfolio.\n\n\u00a03-shift rotation (including OVERNIGHT shift) is a requirement for this position.\n\nBasic salary packages will depend on background and experience while bonuses are linked to performances. Interested parties please send\u00a0full resume with current and expected salary\u00a0by clicking APPLY NOW or contact us by email (see Company details at top for email address)\n\nPersonal data will be used for recruitment purpose only.", "employment_types": ["Full Time", "Permanent"], "selling_points": [], "locations": ["Not Specified"], "categories": ["Banking / Finance", "Analyst", "Dealing & Trading", "Fund Management"], "post_time": "2022-01-14T10:04:17Z", "salary": {"currency": null, "max": null, "min": null, "period": "monthly", "term": null}, "salary_visible": false, "title_keywords": ["researcher"], "responsibilities": ["databases", "develop"], "requirements": {"degrees": [], "majors": [], "languages": [], "language_level": [], "hard_skills": ["plus", "basic", "c++", "programming", "databases", "matlab", "c#"], "soft_skills": [], "languages_combined": []}, "experience_required": {"duration": [], "field": ["finance", "financial markets"]}}, {"job_id": "100003009040010", "location_code": "hk", "company": "Hays", "job_title": "Assistant Manager/Finance Manager | Private Equity", "description": "HOT JOB: Fund House seeking an Assistant Manager to support their Finance team | ~$50K + Bonus\n\nYour new company\n\nThis multinational financial institution is currently hiring for an Assistant Manager/Finance Manager position. Its office in Hong Kong offers a word-class working environment with great exposure to the private equity and buy-side industry.\n\nYour new role\n\nYour responsibilities include:\n\n\nProvide support in preparing financial reports, tax and regulatory returns;\nAssist fund operation procedure, e.g. capital call, distribution, management fee, bank transactions and ad-hoc tasks (for responding to investors' requests)\nHandle full set of accounts, invoice payments, staff claims and bank reconciliations, etc.;\nLiaise with auditors to ensure smooth year end closing for group related entities;\nProvide general administration, company secretarial and compliance support;\nWork with Management for regular review and enhancement of accounting workflow\n\n\nWhat you'll need to succeed\n\n\nCPA or equivalent qualification\nExperience in handling PE/Venture Capital Fund\nExperience of working in SFC licensed corporations, FRR reporting is a plus\nBachelor's degree in Accounting or related field\nIndependent with strong analytical, communication, and computer skills (e.g. QuickBooks)\nProficiency in spoken and written English and Chinese\n\n\nWhat you'll get in return\n\n\nStrong exposure to the Buy-Side and Private Equity industry\nUnlimited Career Development Opportunities\nGood Work Life Balance\nAttractive Bonus\nFamily Like Culture\n\n\nWhat you need to do now\nIf you are interested in this position or other Accounting positions in the Financial Services industry, please send your Resume to Veronica.Lin@hays.com.hk\n\nAt Hays, we value diversity and are passionate about placing people in a role where they can flourish and succeed. We actively encourage people from diverse backgrounds to apply.", "employment_types": ["Full Time", "Permanent"], "selling_points": ["Exposure to the Buy-Side & Private Equity Industry", "Unlimited Career Development Opportunities", "Good Work Life Balance"], "locations": ["Not Specified"], "categories": ["Accounting", "Finance / Accounting Manager", "Banking / Finance", "Fund Management", "Asset Management"], "post_time": "2022-01-12T00:00:36Z", "salary": {"currency": "HKD", "max": 54999, "min": 45000, "period": "monthly", "term": null}, "salary_visible": true, "title_keywords": ["assistant manager", "finance manager"], "responsibilities": ["work with management", "transactions", "regular review", "communication", "liaise with", "administration", "full set of accounts", "compliance", "bank reconciliations", "finance team", "reporting", "provide support", "management", "invoice", "career development", "tax", "financial reports", "ad-hoc tasks", "payments"], "requirements": {"degrees": ["degree", "bachelor"], "majors": ["accounting"], "languages": ["english", "chinese"], "language_level": ["proficiency"], "hard_skills": ["plus", "quickbooks", "word", "cpa", "computer skills", "pe", "venture capital", "private equity", "frr"], "soft_skills": ["independent", "interested in", "communication", "diverse", "smooth", "passionate about"], "languages_combined": [{"language": "english", "language_level": ["proficiency"]}, {"language": "chinese", "language_level": ["proficiency"]}]}, "experience_required": {"duration": [], "field": ["venture capital"]}}, {"job_id": "100003009042202", "location_code": "hk", "company": "Manpower Services (Hong Kong) Limited", "job_title": "Onsite with HSBC- Fund Accountant (12 Month Contract, Up to 25K)", "description": "Title: Fund Accountant ( equivalent to GCB7)\nMax Salary : 20 -25K per month ( 1 year exp)\nDuration: 12 months\nLocation: 5/F Tower 1 HSBC Centre, 1 Sham Mong Road, Kowloon, Hong Kong\nDepartment : Securities Services GBMC\n\nPrincipal responsibilities :\n\nAssist in the day to day administration, valuation, custody, compliance and accounting of the assigned\nfund portfolios\nReview Net Asset Value reports and reconciliation prepared by servicing team and train the servicing\nteam in preparing such reports\nProvide support in preparing relevant reports to clients on a regular basis and ensure the operations are\nin compliance with relevant guidelines and governance\nEvaluate the fund operation procedures with the team to improve efficiency\nPerform operational and administrative works and assist in answering stakeholders enquiries\nEscalate and report any issues in accordance with internal incident management reporting requirements\nParticipate in ad-hoc projects as required\n\nRequirements :\n\nUniversity graduate majoring in accounting or finance related disciplines\nBasic understanding of accounting and experience in fund or banking industry is desired\nExcellent written and spoken English\nStrong team player, attention to details\nGood computer and interpersonal skills\n\nIf you are interested in this role, click \u201cApply Now\u201d, else, you may also directly send your updated resume and expected salary to Anson Li at anson.li@manpowergrc.hk.", "employment_types": ["Contract"], "selling_points": ["Uni graduate majoring in accounting or Commerce", "Experience in fund or banking industry is desired", "Working Location: HSBC Centre"], "locations": ["Kowloon City Area"], "categories": ["Accounting", "Accountant", "Banking / Finance", "Corporate Banking", "Fund Management"], "post_time": "2022-01-12T06:35:36Z", "salary": {"currency": null, "max": null, "min": null, "period": "monthly", "term": null}, "salary_visible": false, "title_keywords": ["accountant"], "responsibilities": ["valuation", "provide support", "relevant reports", "guidelines", "operations", "review", "compliance", "procedures", "evaluate", "reports", "management reporting", "report", "ad-hoc projects", "administration"], "requirements": {"degrees": ["university graduate"], "majors": ["related disciplines", "finance", "accounting"], "languages": ["english"], "language_level": ["excellent"], "hard_skills": ["basic"], "soft_skills": ["team player", "interested in", "interpersonal skills", "attention to details"], "languages_combined": [{"language": "english", "language_level": ["excellent"]}]}, "experience_required": {"duration": [], "field": ["banking industry", "accounting"]}}, {"job_id": "100003009042474", "location_code": "hk", "company": "Profile Search and Selection", "job_title": "COO  Multi-strategy Hedge Fund", "description": "Only candidates with multistrategy hedge fund experience need apply and those who are currently in a COO or Head of Operations position. Excellent renumeration for the right candidate.", "employment_types": ["Full Time", "Permanent"], "selling_points": ["Multi- strategy Hedge Fund", "Reporting to the founder", "Build up role"], "locations": ["Not Specified"], "categories": ["Banking / Finance", "Fund Management"], "post_time": "2022-01-12T07:38:36Z", "salary": {"currency": null, "max": null, "min": null, "period": "monthly", "term": null}, "salary_visible": false, "title_keywords": [], "responsibilities": ["operations"], "requirements": {"degrees": [], "majors": [], "languages": [], "language_level": [], "hard_skills": [], "soft_skills": [], "languages_combined": []}, "experience_required": {"duration": [], "field": []}}, {"job_id": "100003009039966", "location_code": "hk", "company": "\u81fa\u7063\u4e2d\u5c0f\u4f01\u696d\u9280\u884c\u80a1\u4efd\u6709\u9650\u516c\u53f8", "job_title": "\u570b\u969b\u806f\u8cb8\u53ca\u8de8\u5883\u878d\u8cc7\u696d\u52d9\u4eba\u54e1", "description": "\u5de5\u4f5c\u5167\u5bb9\uff1a\u8fa6\u7406\u570b\u969b\u806f\u8cb8\u8207\u8de8\u5883\u878d\u8cc7\u76f8\u95dc\u696d\u52d9\u3002\n\n\u8cc7\u683c\u689d\u4ef6\uff1a\n1.\u5b78\u6b77\uff1a\u570b\u5167\u5916\u5c08\u79d1\u4ee5\u4e0a\u5b78\u6821\u7562\u696d\u6216\u5177\u6709\u540c\u7b49\u5b78\u6b77\u3002\n\n2.\u5de5\u4f5c\u7d93\u6b77\uff1a\n(1)\u5177\u91d1\u878d\u6a5f\u69cb\u76f8\u95dc\u5de5\u4f5c\u7d93\u6b7710\u5e74\u4ee5\u4e0a\uff0c\u4e26\u65bc\u9999\u6e2f\u91d1\u878d\u6a5f\u69cb\u5de5\u4f5c\u7d93\u6b775\u5e74\u4ee5\u4e0a\u3002\n(2)\u5177\u9999\u6e2f\u5730\u5340\u6216\u5176\u4ed6\u6d77\u5916\u5730\u5340\u806f\u8cb8\u5e02\u5834\u696d\u52d9\u7c4c\u7d44\u7d93\u9a572\u5e74\u4ee5\u4e0a\u3002\n\n3.\u5176\u4ed6\u5c08\u9577\u8207\u5c08\u696d\u8b49\u7167\uff1a\n(1)\u5177\u4e2d\u3001\u82f1\u6587\u6e9d\u901a\u80fd\u529b\u3002\n(2)\u64d4\u4efb\u4e3b\u7ba1\u8077\uff0c\u61c9\u5177\u5099\u300c\u91d1\u878d\u63a7\u80a1\u516c\u53f8\u53ca\u9280\u884c\u696d\u5167\u90e8\u63a7\u5236\u53ca\u7a3d\u6838\u5236\u5ea6\u5be6\u65bd\u8fa6\u6cd5\u300d\u898f\u5b9a\u4e4b\u5167\u63a7\u76f8\u95dc\u7d93\u6b77\u3001\u8a13\u7df4\u6216\u8b49\u66f8\u3002\n\n\u4e0a\u73ed\u5730\u9ede\uff1a\u81fa\u7063(\u914d\u5408\u696d\u52d9\u9700\u8981\u9577\u671f\u6d3e\u99d0\u6d77\u5916\u55ae\u4f4d\u5de5\u4f5c)\n\n*\u6709\u610f\u8005\u8acb\u8a3b\u660e\u300c\u7504\u9078\u985e\u5225\u300d\uff0c\u4e26\u5c07\u4e2d\u3001\u82f1\u6587\u5c65\u6b77\u53ca\u76f8\u95dc\u8cc7\u6599\u4ee5\u96fb\u5b50\u90f5\u4ef6\u65b9\u5f0f\u5bc4\u81f3Apply Now\u3002\u672a\u4f9d\u898f\u5b9a\u65b9\u5f0f\u5831\u540d\u8005\uff0c\u8996\u70ba\u8cc7\u683c\u4e0d\u7b26\u3002\n\n", "employment_types": ["Full Time"], "selling_points": [], "locations": ["Overseas"], "categories": ["Banking / Finance", "Loan", "Financial Services", "Fund Management"], "post_time": "2022-01-11T16:02:24Z", "salary": {"currency": null, "max": null, "min": null, "period": "monthly", "term": null}, "salary_visible": false, "title_keywords": [], "responsibilities": [], "requirements": {"degrees": [], "majors": [], "languages": [], "language_level": [], "hard_skills": [], "soft_skills": [], "languages_combined": []}, "experience_required": {"duration": [], "field": []}}, {"job_id": "100003009038720", "location_code": "hk", "company": "Recruitment Intelligence Consultants Ltd", "job_title": "REGULATORY FUND REPORTING, AVP or above", "description": "Well established international Asset Management Firm\nExcellent Career Opportunity\nOur client is an international asset management firm with an unparalleled reputation across the Asia Pacific region. With the continued growth of the organization, the need has arisen to recruit a high calibre candidate to join them.\u00a0\u00a0\n\nResponsible for the coordination of the whole report production process for fund ranges in HK, SG and other locations in the region. Liaise with various internal and external parties, such as Compliance, Risk, Fund Accountant and Auditors and support the global project. \u00a0Coordination of report preparation process for the full HK fund range in collaboration with internal and external parties. \u00a0Oversight of whole report production process for HK and SG domiciled funds incl. Coordination with auditors, fund accountants and other service providers according to agreed timetable. Administration of report related information and answering ad-hoc requests from internal parties. Support of report preparation process in global office. Coordination of audit process.\u00a0\u00a0\n\nTo be considered, you should be a degree holder in with a minimum of 7 years of\u00a0experience in Audit Firms or Fund Accounting in AP region. Experience with an asset manager focusing on regulatory reporting and Fund administration is a plus. Sound \u00a0knowledge of MS Office products, especially MS Excel. Knowledge of asset management regulations and related requirements in terms of Regulatory Documents. Strong analytical skills with high level of accuracy and keen attention to detail. Fluent in English and Cantonese. Mandarin is a plus.\u00a0\n\nInterested applicants should send a detailed resume to Kelly Kam quoting reference jdb-4572\u00a0via email.\u00a0 Please click \u201cAPPLY NOW\u201d button below.\n\n(Applicants not contacted within 4 weeks should consider their application unsuccessful.)\n", "employment_types": ["Full Time", "Permanent"], "selling_points": [], "locations": ["Not Specified"], "categories": ["Banking / Finance", "Financial Services", "Fund Management", "Asset Management"], "post_time": "2022-01-11T07:58:37Z", "salary": {"currency": null, "max": null, "min": null, "period": "monthly", "term": null}, "salary_visible": false, "title_keywords": [], "responsibilities": ["administration", "ap", "reporting", "regulations", "production process", "internal and external parties", "compliance", "coordination with", "audit", "asset management", "coordination", "ad-hoc requests", "liaise with", "internal parties", "report"], "requirements": {"degrees": ["degree holder"], "majors": ["accounting"], "languages": ["cantonese", "english", "mandarin"], "language_level": ["fluent"], "hard_skills": ["ap", "plus", "analytical skills", "ms excel", "ms office"], "soft_skills": ["responsible", "keen", "analytical skills", "coordination", "attention to detail", "detailed"], "languages_combined": [{"language": "cantonese", "language_level": ["fluent"]}, {"language": "english", "language_level": ["fluent"]}, {"language": "mandarin", "language_level": []}]}, "experience_required": {"duration": ["minimum of 7 years"], "field": ["accounting", "audit", "administration"]}}, {"job_id": "100003009039965", "location_code": "hk", "company": "Taiwan Business Bank Co., Ltd", "job_title": "\u7d93\u71df\u9ad8\u6de8\u503c\u8ca1\u52d9\u7ba1\u7406\u696d\u52d9\u4eba\u54e1", "description": "\u5de5\u4f5c\u5167\u5bb9\uff1a\n1.\u719f\u6089\u5883\u5167\u5916\u57fa\u91d1\u3001\u6d77\u5916\u50b5\u3001\u6d77\u5916\u80a1\u7968\u3001\u7279\u5225\u80a1\u3001\u6307\u6578\u578b\u57fa\u91d1\u53ca\u884d\u751f\u6027\u91d1\u878d\u5546\u54c1\u7b49\u5546\u54c1\u7279\u6027\uff0c\u70ba\u9867\u5ba2\u9032\u884c\u5168\u65b9\u4f4d\u8ca1\u5bcc\u7ba1\u7406\u898f\u5283\u3002\n\n2.\u6eff\u8db3\u9ad8\u6de8\u503c\u8ca1\u5bcc\u7ba1\u7406\u5ba2\u6236\u5c0d\u570b\u969b\u91d1\u878d\u5e02\u5834\u7522\u54c1\u4e4b\u9700\u6c42\u8207\u5c08\u696d\u670d\u52d9\u3002\n\n3.\u70ba\u5ba2\u6236\u91cf\u8eab\u6253\u9020\u500b\u4eba\u6216\u5176\u5bb6\u65cf\u4e4b\u8cc7\u7522\u7ba1\u7406\u3002\n\n4.\u5354\u52a9\u6df1\u8015\u9ad8\u8cc7\u7522\u5ba2\u6236\uff0c\u589e\u52a0\u5ba2\u6236\u4e4b\u9ecf\u8457\u5ea6\u8207\u670d\u52d9\u4e4b\u5ee3\u5ea6\u548c\u6df1\u5ea6\u3002\n\n5.\u958b\u767c\u9ad8\u8cc7\u7522\u5ba2\u6236\u3002\n\n\u8cc7\u683c\u689d\u4ef6\uff1a\n1.\u5b78\u6b77\uff1a\n\u570b\u5167\u3001\u5916\u91d1\u878d\u3001\u7d93\u6fdf\u3001\u5546\u696d\u3001\u7ba1\u7406\u7814\u7a76\u6240\u7562\u696d\uff0c\u4e14\u5df2\u53d6\u5f97\u78a9\u58eb\u4ee5\u4e0a\u5b78\u4f4d\u8b49\u66f8\u3002\n\n2.\u5de5\u4f5c\u7d93\u6b77\uff1a\n\u5177\u91d1\u878d\u6a5f\u69cb\u76f8\u95dc\u5de5\u4f5c\u7d93\u6b7710\u5e74\u4ee5\u4e0a\uff0c\u4e26\u65bc\u9999\u6e2f\u91d1\u878d\u6a5f\u69cb\u5de5\u4f5c\u7d93\u6b775\u5e74\u4ee5\u4e0a\u3002\n\n3.\u5176\u4ed6\u5c08\u9577\u8207\u5c08\u696d\u8b49\u7167\uff1a\n(1)\u5177\u4e2d\u3001\u82f1\u6587\u6e9d\u901a\u80fd\u529b\u3002\n(2)\u82f1\u8a9e\u8a9e\u6587\u6e2c\u9a57\u6a19\u6e96\u61c9\u5177\u76f8\u7576\u65bc\u5168\u6c11\u82f1\u6aa2(GEPT)\u4e2d\u9ad8\u7d1a(\u542b)\u4ee5\u4e0a\u3002\n(3)\u64d4\u4efb\u4e3b\u7ba1\u8077\uff0c\u61c9\u5177\u5099\u300c\u91d1\u878d\u63a7\u80a1\u516c\u53f8\u53ca\u9280\u884c\u696d\u5167\u90e8\u63a7\u5236\u53ca\u7a3d\u6838\u5236\u5ea6\u5be6\u65bd\u8fa6\u6cd5\u300d\u898f\u5b9a\u4e4b\u5167\u63a7\u76f8\u95dc\u7d93\u6b77\u3001\u8a13\u7df4\u6216\u8b49\u66f8\u3002\n\n\u4e0a\u73ed\u5730\u9ede\uff1a\u81fa\u7063(\u914d\u5408\u696d\u52d9\u9700\u8981\u9577\u671f\u6d3e\u99d0\u6d77\u5916\u55ae\u4f4d\u5de5\u4f5c)\n\n*\u6709\u610f\u8005\u8acb\u8a3b\u660e\u300c\u7504\u9078\u985e\u5225\u300d\uff0c\u4e26\u5c07\u4e2d\u3001\u82f1\u6587\u5c65\u6b77\u53ca\u76f8\u95dc\u8cc7\u6599\u4ee5\u96fb\u5b50\u90f5\u4ef6\u65b9\u5f0f\u5bc4\u81f3Apply Now\u3002\u672a\u4f9d\u898f\u5b9a\u65b9\u5f0f\u5831\u540d\u8005\uff0c\u8996\u70ba\u8cc7\u683c\u4e0d\u7b26\u3002\n\n", "employment_types": ["Full Time"], "selling_points": [], "locations": ["Overseas"], "categories": ["Banking / Finance", "Loan", "Fund Management", "Wealth Management"], "post_time": "2022-01-11T16:02:24Z", "salary": {"currency": null, "max": null, "min": null, "period": "monthly", "term": null}, "salary_visible": false, "title_keywords": [], "responsibilities": [], "requirements": {"degrees": [], "majors": [], "languages": [], "language_level": [], "hard_skills": [], "soft_skills": [], "languages_combined": []}, "experience_required": {"duration": [], "field": []}}, {"job_id": "100003009042049", "location_code": "hk", "company": "Future Leader Recruitment Agency", "job_title": "Graduate Trainee Program (5 days work, 18-22K)", "description": "Comprehensive Trainee Program for graduates\nPromising career path\nCompetitive compensation and benefit package\n\n\nJob Description\n\nOur client is one of the major financial institution in Asia. They are young, energetic and innovative, that nurture many youngsters to be part of their management team. Now they offer highly professional trainee program to\u00a0caliber candidates:\n\nTraining program:\n\nStructured and comprehensive training to build the professional base on finance and investment market knowledge and strategies\nExtensive initial training covering\u00a0professional and comprehensive\u00a0soft skills consulting, negotiation, presentation and communication\u00a0 \u00a0\nWeekly mentor-ship training sessions hold\u00a0by experienced Managers of firm\u00a0\nRotation of job duties in order to acquire experience in management and leadership\n\nJob responsibilities:\n\nTrained to be able to provide investment advice for clients, especially high net worth asset clients, manage their account and improve their investment return\n\nAssist senior managers in presenting investment portfolio and market outlook to clients\n\nWork as a team to organize business development events, such as, investment seminars, marketing events and road shows regarding investment\n\nDevelop your own client servicing skills, and make use of your professional knowledge to maintain a good relationship with clients\n\nDevelop your interpersonal skills and management skills to be a part of the management team in the later stage of your career\n\nRequirements:\n\nUniversity graduate\u00a0in any discipline\nMainland China\u00a0Fresh graduates with IANG visa are welcome\nProficiency in Chinese and English\nProactive to learn\nExcellent interpersonal, communications and presentation skills\nAggressive, self-motivated, customer orientation\u00a0\u00a0\n\nInterested parties please\u00a0click\u00a0Apply Now\n\nPlease note: Short listed candidates will be notified within eight (8) weeks of the date of this advertisement. All personal data collected will be kept confidential and used for recruitment purposes only.\n\n\n\n", "employment_types": ["Full Time", "Permanent"], "selling_points": ["Comprehensive Trainee Program for graduates", "Promising career path to management in 2 years", "harmonious, energetic and professional environment"], "locations": ["Causeway Bay"], "categories": ["Banking / Finance", "Fund Management", "Marketing / Public Relations", "Marketing - Direct Marketing", "Management", "Management Trainee"], "post_time": "2022-01-12T05:42:05Z", "salary": {"currency": null, "max": null, "min": null, "period": "monthly", "term": null}, "salary_visible": false, "title_keywords": ["graduate trainee"], "responsibilities": ["management team", "management", "marketing events", "consulting", "develop", "communication", "good relationship", "maintain"], "requirements": {"degrees": ["university graduate"], "majors": [], "languages": ["english", "chinese"], "language_level": ["proficiency"], "hard_skills": [], "soft_skills": ["presentation skills", "proactive", "interpersonal", "self-motivated"], "languages_combined": [{"language": "english", "language_level": ["proficiency"]}, {"language": "chinese", "language_level": ["proficiency"]}]}, "experience_required": {"duration": [], "field": []}}, {"job_id": "100003009042203", "location_code": "hk", "company": "Manpower Services (Hong Kong) Limited", "job_title": "Onsite with HSBC- Senior Financial Services Specialist (12 Month Contract, Up to 18K)", "description": "Title : Senior Financial Services Specialist\nSalary: HKD16 to 18K monthly\nDuration: 1 year\nLocation: HSBC centre Kowloon\n\nResponsibilities:\n\nSupport the order processing, settlement, transfer, and maintenance tasks.\nProvide accurate and quality work to minimize reversal rate and complaint cases.\nHandle exceptions and problem cases under advice and supervision of manager.\nReport irregularities and issues to supervisor promptly and accurately.\nArrange payment settlement with client and counterparties.\nProvide quality services to internal and external clients in accordance with all group standards.\nFollow up independently with queries raised, escalating to line manager where appropriate.\nBack up other colleagues of the team in accordance with back up arrangements as advised by managers.\nProactively seek out opportunities to assist other team members.\nProactively learn other tasks in order to become familiar with the full operations flow.\nEnsure compliance with all relevant internal control documents and external regulatory requirements.\nEnsure Service Level Agreement on various tasks\nProactively initiate enhancement in job processes\n\n\nRequirements:\n\nExcellent understanding of Funds industry and possess adequate level of knowledge in its products\nKnowledge of Funds operations particularly from distribution side of business\nStrong analytical mind, numerical skills and attention to details\nEffective communication and interpersonal skill\nOpen minded, energetic, proactive, willing to learn and a good team player\nGood command of spoken and written English\nComputer competency including using Microsoft Excel and Word\n\nIf you are interested in this role, click \u201cApply Now\u201d, else, you may also directly send your updated resume and expected salary to Anson Li at anson.li@manpowergrc.hk.", "employment_types": ["Contract"], "selling_points": ["Excellent understanding of Funds industry", "Possess adequate level of knowledge in its product", "Working Location: HSBC Centre"], "locations": ["Kowloon City Area"], "categories": ["Banking / Finance", "Corporate Banking", "Financial Services", "Fund Management"], "post_time": "2022-01-12T06:35:41Z", "salary": {"currency": null, "max": null, "min": null, "period": "monthly", "term": null}, "salary_visible": false, "title_keywords": ["specialist"], "responsibilities": ["operations", "regulatory requirements", "quality", "maintenance tasks", "ensure compliance", "other tasks", "payment", "order processing", "internal control", "report irregularities"], "requirements": {"degrees": [], "majors": [], "languages": ["english"], "language_level": ["good command"], "hard_skills": ["numerical skills", "word", "microsoft excel"], "soft_skills": ["good team player", "proactive", "interested in", "willing to learn", "interpersonal skill", "communication", "analytical mind", "open minded", "attention to details", "energetic"], "languages_combined": [{"language": "english", "language_level": ["good command"]}]}, "experience_required": {"duration": [], "field": []}}, {"job_id": "100003009036815", "location_code": "hk", "company": "Noah International (Hong Kong) Limited", "job_title": "Risk Manager", "description": "Responsibilities:\u00a0\n\nSupport sales team and institution distributors to promote the funds\nReaching out to new and maintain existing relationship with clients\nParticipate in sale and marketing events through various activities\nSupport day-to-day queries from clients, fund administrators and prospective investors\nProduce regular marketing materials including presentation,\u00a0 newsletter and fund factsheets\nUpdate/Maintain company website with attention to relevant legal and regulatory requirements\nHandle fund subscription and redemption matters\nPerform other ad hoc assignments as required\n\n\u00a0\u00a0\u00a0Requirements:\u00a0\n\nUniversity\u00a0graduate\u00a0with Finance, Economics or Business-related disciplines;\nAbove 3 years relevant working experience in the industry\nExcellent command of written and spoken English and Chinese, Fluent Mandarin is a MUST\nProven ability to manage multiple tasks, priorities and workflows and meet deadlines\nProficient in MS office, particularly PPT and Excel\nIndependent personality with strong problem solving skills, able to work independently\n\nInterested parties please send with current and expected salary and date availability in MS WORD format.\n\nAll applications received will be treated in strict confidence and information collected is only be used for\u00a0employment-related purposes.\n\nFor more details, please visit our web site at www.pureheartcapital.com.", "employment_types": ["Full Time", "Permanent"], "selling_points": ["Min. of 2-3 years\u2019 experience in risk management", "Knowledge of fund management", "Professional Qualification (FRM/ CFA) is an adv"], "locations": ["Causeway Bay"], "categories": ["Banking / Finance", "Fund Management", "Risk Management", "Asset Management"], "post_time": "2022-01-10T15:11:08Z", "salary": {"currency": null, "max": null, "min": null, "period": "monthly", "term": null}, "salary_visible": false, "title_keywords": ["manager"], "responsibilities": ["marketing events", "regulatory requirements", "maintain", "sales team", "ad hoc assignments", "marketing materials", "company website"], "requirements": {"degrees": ["university graduate"], "majors": ["business", "finance", "related disciplines", "economics"], "languages": ["english", "chinese", "mandarin"], "language_level": ["excellent", "fluent"], "hard_skills": ["excel", "problem solving skills", "ms office"], "soft_skills": ["work independently", "independent", "multiple tasks", "problem solving skills", "meet deadlines"], "languages_combined": [{"language": "english", "language_level": ["excellent"]}, {"language": "chinese", "language_level": ["excellent"]}, {"language": "mandarin", "language_level": ["fluent", "excellent"]}]}, "experience_required": {"duration": ["3 years"], "field": ["relevant working experience"]}}, {"job_id": "100003009034474", "location_code": "hk", "company": "Pureheart Capital Asia Limited", "job_title": "Investor Relations Officer", "description": "In a world of disruption and increasingly complex business challenges, our professionals bring truth into focus with the Kroll Lens. Our sharp analytical skills, paired with the latest technology, allow us to give our clients clarity\u2014not just answers\u2014in all areas of business. We embrace diverse backgrounds and global perspectives, and we cultivate diversity by respecting, including, and valuing one another. As part of\u00a0One team, One Kroll, you\u2019ll contribute to a supportive and collaborative work environment that empowers you to excel.\n\nKroll\u2019s Compliance Consulting practice assists clients in setting up firms, obtaining their initial authorization or registration, and providing them with ongoing compliance advice to navigate the rapidly changing regulatory landscape.\n\nAt Kroll, your work will help deliver clarity to our clients\u2019 most complex governance, risk, and transparency challenges. Apply now to join\u00a0One team, One Kroll.\n\nRESPONSIBILITIES:\n\nManaging a portfolio of clients regulated by the SFC, SEC\u00a0and other global regulators\nPreparing compliance manuals and other related policies and procedures\u00a0\nSetting up the compliance infrastructure and assisting ongoing compliance monitoring\nUndertaking periodic compliance monitoring reviews at client premises\nWriting compliance monitoring reports\nManaging regulatory\u00a0filing and reporting schedules\nProviding ad hoc regulatory advice and creative solutions\nUpdating clients on regulatory change\nNetworking and relationship building with industry professionals and industry bodies\n\nREQUIREMENTS:\n\nProven experience in a compliance role, for example within an SFC regulated firm or a compliance consultancy practice\nDetailed understanding of SFC, SEC rules and regulations\nUnderstanding of the financial services industry i.e. asset management and broking sectors\nBroad understanding of the alternative asset management industry\nAbility to work on own initiative and as part of a team\nClient facing, solutions focused skills\nClear, logical thought processes, ability to make decisions and articulate these clearly\nStrong\u00a0English oral and written communication skills\nTime management skills and ability to work within deadlines\nSolution-driven and problem-solving attitude\nLegal or audit background would be useful\nCandidates with less experience will be considered as an Analyst\n\nIn order to be considered for a position, you must formally apply via careers.kroll.com.", "employment_types": ["Full Time", "Permanent"], "selling_points": [], "locations": ["Sheung Wan"], "categories": ["Banking / Finance", "Investment", "Financial Services", "Fund Management"], "post_time": "2022-01-10T03:28:09Z", "salary": {"currency": null, "max": null, "min": null, "period": "monthly", "term": null}, "salary_visible": false, "title_keywords": ["officer"], "responsibilities": ["reporting", "ad hoc", "schedules", "policies", "monitoring", "compliance", "procedures", "infrastructure", "reports"], "requirements": {"degrees": [], "majors": [], "languages": ["english"], "language_level": [], "hard_skills": ["make", "problem-solving"], "soft_skills": ["communication skills", "oral", "focused", "time management skills", "problem-solving", "driven", "clear", "articulate", "initiative", "detailed"], "languages_combined": [{"language": "english", "language_level": []}]}, "experience_required": {"duration": [], "field": ["compliance"]}}, {"job_id": "100003009036261", "location_code": "hk", "company": "D&P China (HK) Limited", "job_title": "Senior Associate, Compliance Consulting, Hong Kong", "description": "International Asset Management\nExcellent Exposure\u00a0\u00a0\nOur client is an international Asset Management with an unparalleled reputation across the Asia Pacific region. With the continued growth of the organization, the need has arisen to recruit high caliber to join them.\u00a0\u00a0\nResponsible for implementing and executing AP investment compliance program for the company's investment and trading related activities in AP and is part of a global team that works in close collaboration with other regions on policies, monitoring, training and resolving issues related to the firm's investment and trading related activities. \u00a0Portfolio compliance monitoring, including coding of investment restrictions, pre-trade and post-trade monitoring based on the portfolio/regulatory guidelines/restrictions. \u00a0Perform monitoring of the investment and trading related activities in AP as identified in the investment advisory compliance surveillance program. Areas may include, but not limited to best execution, fair allocation, insider dealing etc. Provide advice to the investment personnel on investment guidelines matter as well as on investment and trading related regulations, policies and procedures. Handle the requests and enquiries from internal and external parties. \u00a0Implement and maintain global and regional policies related to investment and trading activities for AP offices. \u00a0Disclosure of interests monitoring and reporting. Liaise with the compliance teams in other offices regularly and on ad-hoc investment compliance issues or projects. Participate in compliance department and/or company projects.\u00a0\u00a0\n\nTo be considered, you will be a degree holder with a minimum of 3 years of compliance experiences with knowledge of the investment management industry. Knowledge in regulatory investment restrictions for UCITS, SFC and MPF funds is a plus. Willingness to learn and work hard. Good communication skills. Diligent and attention to detail, with strong analytical skills. Ability to take initiative, work under pressure, and meet deadlines. Experience in a multi-cultural work environment.\u00a0\u00a0\n\nInterested applicants should send a detailed resume to Kelly Kam quoting reference jdb-4553 via email.\u00a0 Please click \u201cAPPLY NOW\u201d button below.\u00a0\u00a0\n\n(Applicants not contacted within 4 weeks should consider their application unsuccessful.)", "employment_types": ["Full Time", "Permanent"], "selling_points": ["Global work and exposure opportunities", "Amazing development, progression and culture", "SFC, SEC rules and regulations knowledge"], "locations": ["Admiralty"], "categories": ["Banking / Finance", "Fund Management", "Professional Services", "Business Consultancy", "Legal & Compliance"], "post_time": "2022-01-10T09:50:49Z", "salary": {"currency": null, "max": null, "min": null, "period": "monthly", "term": null}, "salary_visible": false, "title_keywords": ["senior associate"], "responsibilities": ["regulations", "ad-hoc", "internal and external parties", "coding", "communication", "maintain", "liaise with", "work under pressure", "ap", "compliance", "teams", "reporting", "management", "mpf", "monitoring", "procedures", "executing", "guidelines", "policies", "provide advice", "asset management"], "requirements": {"degrees": ["degree holder"], "majors": [], "languages": [], "language_level": [], "hard_skills": ["ap", "plus", "analytical skills"], "soft_skills": ["communication skills", "responsible", "diligent", "detailed", "analytical skills", "attention to detail", "meet deadlines", "initiative", "work under pressure"], "languages_combined": []}, "experience_required": {"duration": ["minimum of 3 years"], "field": ["management", "compliance", "investment"]}}, {"job_id": "100003009035132", "location_code": "hk", "company": "Recruitment Intelligence Consultants Ltd", "job_title": "INVESTMENT COMPLIANCE", "description": "Operations \u2013 Wealth Services\n\n\nHang Seng's Operations is a team of experienced banking operations professionals who strive for delivering time-to-market, efficient and world-class processing services to customers, corporations, financial institutions and internal units.\n\nWe are currently seeking a high caliber professional to join our department as\u00a0Investment Funds Operations Manager.\n\u00a0\n\nPrincipal responsibilities\n\nPlay the role of subject matter expert in supporting unit trust operations such as daily unit trust order, subscription and redemption settlement, dividend distribution, unit trust transfer and fee handling\nParticipate and support business, bank-wide and market initiatives/projects\nIdentify opportunities for process improvement and drive re-engineering initiatives to increase operational efficiency and effectiveness as well as client experience\nSet service standards, monitor actual performance and review service benchmarks of both onshore and offshore to ensure cost-effective service for business units and customers\nUnderstand the changing group/regulatory requirements and conduct assessment/ monitoring on operations to ensure in compliance with the standard\nManage the performance and development of subordinates\n\nRequirements\n\n\nUniversity degree in a related discipline or other relevant qualifications\nFulfillment of the competency requirements for carrying out relevant regulated activities as defined under the Securities and Futures Ordinance\nMinimum of 5 years\u2019 relevant experience in banking industry, with sound knowledge of investment products / systems and relevant regulations\nBe proactive, with good analytical and problem solving skills\nStrong self-motivation, attentiveness to details, with good communication, leadership and interpersonal skills\nSound knowledge of application software such as MS Excel\nProficiency in both English and Chinese, with fluency in Putonghua an advantage\nGreat sense of ownership and servicing mindset to ensure efficient and effective customer service processes\n\n\n\nIf you would like to explore other opportunities at Hang Seng Hong Kong, please visit\u00a0www.hangseng.com/careers/\u00a0for details.\n\nThe health and safety of our employees and candidates is very important to us. Due to the current situation related to the Novel Coronavirus (2019-nCoV), we\u2019re leveraging our digital capabilities to ensure we can continue to recruit top talent at the HSBC Group. \u00a0As your application progresses, you may be asked to use one of our digital tools to help you through your recruitment journey. \u00a0If so, one of our \u00a0Resourcing colleagues will explain how our video-interviewing technology will be used throughout the recruitment process and will be on hand to answer any questions you might have\n\nAll information provided by applicants will be used only for recruitment purposes and will be used strictly in accordance with the Bank's personal data policies, a copy of which may be obtained by the applicant upon request. Unless otherwise instructed in writing by the applicant concerned, applicants may be considered for other suitable positions within the Bank and its related companies. The personal data of unsuccessful job applicants may be retained for a maximum of two years from the date when the job application is rejected and such data may be retained for a longer period if there is a subsisting reason that obliges the Bank to do so, after which the personal data will be destroyed.", "employment_types": ["Full Time", "Permanent"], "selling_points": [], "locations": ["Not Specified"], "categories": ["Banking / Finance", "Fund Management", "Professional Services", "Legal & Compliance", "Asset Management"], "post_time": "2022-01-10T06:07:09Z", "salary": {"currency": null, "max": null, "min": null, "period": "monthly", "term": null}, "salary_visible": false, "title_keywords": [], "responsibilities": ["cost", "operations", "regulatory requirements", "review", "monitor", "subject matter expert", "monitoring", "compliance", "service standards", "re-engineering"], "requirements": {"degrees": ["university degree"], "majors": [], "languages": ["putonghua", "english", "chinese"], "language_level": ["fluency", "advantage", "proficiency"], "hard_skills": ["investment products", "securities and futures ordinance", "reason", "ms excel", "problem solving skills"], "soft_skills": ["efficient", "communication", "analytical and problem solving skills", "self-motivation", "interpersonal skills", "customer service", "novel", "proactive", "leadership"], "languages_combined": [{"language": "putonghua", "language_level": ["fluency", "advantage"]}, {"language": "english", "language_level": ["proficiency", "fluency", "advantage"]}, {"language": "chinese", "language_level": ["proficiency", "fluency", "advantage"]}]}, "experience_required": {"duration": ["minimum of 5 years"], "field": ["banking industry", "relevant experience", "investment"]}}, {"job_id": "100003009035684", "location_code": "hk", "company": "Hang Seng Bank Ltd", "job_title": "Investment Funds Operations Manager", "description": "MPF Financial Officer\u00a0\nBenefits and packages :\n4 Days working\u00a0\nMonthly salary start from HK$16,000 +\u00a0 Quarterly Bonus + Year End Bonus\nInitial training and On-Job training provided\nExcellent Career Path to Management Ladder\nLife and Medical Insurance\nClient Base provided\u00a0\nFlexible working hours\u00a0\nWork-Life Balance\nRequirements :\nFresh graduates is welcomed\n1 years working experience or above is preferred\nHKID card holder is a MUST\nFluent Cantonese and English\nMature, responsible, and strong desire for success\nJob\u00a0description:\u00a0\nProvide professional financial planning to individual clients for wealth management, medical and life insurance, retirement scheme, investment, etc.\nProvide benefits to corporate clients such as MPF, Group Medical, Business Insurance, etc\nBuild your own professional finance management team\u00a0\nInterested applicants please apply with full resume.\u00a0\nFinstyle\u00a0", "employment_types": ["Full Time", "Permanent"], "selling_points": [], "locations": ["Not Specified"], "categories": ["Banking / Finance", "Fund Management", "Others", "Order Processing & Operation / Settlement"], "post_time": "2022-01-10T08:10:08Z", "salary": {"currency": null, "max": null, "min": null, "period": "monthly", "term": null}, "salary_visible": false, "title_keywords": ["operations manager"], "responsibilities": [], "requirements": {"degrees": [], "majors": [], "languages": [], "language_level": [], "hard_skills": [], "soft_skills": [], "languages_combined": []}, "experience_required": {"duration": [], "field": []}}, {"job_id": "100003009045255", "location_code": "hk", "company": "AXA China Region Insurance Company Limited", "job_title": "MPF Financial Officer ( 4 Days & 16k )", "description": "Talent from banking who is looking for better rewards, advancement and new skill-sets on Product Management\n\nYour choice of jobs\n\nWe are a listed recruitment agency based in UK, I am specializing in Product Management hiring for banking & FI clients. They are resourceful and expanding companies including Retail Bank, SME segment, Corporate Bank and Private Bank.\n\nTo copy with their expansion needs and confidential search, I am covering different level of positions from Assistant Manager, Sr Mgr to Team Leader; Products coverage from Secured loan (Mortgage, Premium Financing) & Unsecured Loan, Credit Card, Deposit, Mortgage, Investment, FX for Retail, SME, Corporate segment.\n\nYour new company\n\n-I am copying with experienced hiring for clients from Retail Bank, SME, Corporate Bank and Private Bank thru accurate job matching in order to increase hit rate.\n\n-Regarding your interests and expectation, matching my numerous Hot Jobs on hand\n\nWhat you'll need to succeed\n\n-Has gained certain relevant Product Management skills from banking\n\n-Act fast but think thoroughly before committing to job change\n\n-Be open minded to explore your potential roles from my end, by sharing of your current profile and talk to me (We won't proceed job application unless gain your consent)\n\n-We are working together to get good job, TIPS about the application will be shared . At the same time. I am sourcing good candidate for clients, this is WIN-WIN relationship!\n\nWhat you'll get in return\n\n-Salary increase is a fundamental motivation of job changes, for more, I'll cater your interests and requirements (Let's communicate over the phone with my understanding about your experience)\n\nWhat you need to do now\n\nIf you're interested in new opportunity, click 'apply now' to forward an up-to-date copy of your CV, or call Ms LEE at +852 2230 7438 now by sharing your CV in advance.\n\nIf this job isn't quite right for you but you are looking for a new position, please contact me for a confidential discussion on your career.", "employment_types": ["Full Time", "Part Time", "Permanent", "Temporary", "Freelance"], "selling_points": ["Mpf officer", "Flexible working time", "4 days work Travel allowance"], "locations": ["Tsim Sha Tsui"], "categories": ["Banking / Finance", "Fund Management", "Sales, CS & Business Devpt", "Direct Sales", "Sales Administration"], "post_time": "2022-01-13T07:30:20Z", "salary": {"currency": "HKD", "max": 24999, "min": 17000, "period": "monthly", "term": null}, "salary_visible": true, "title_keywords": ["officer"], "responsibilities": ["management", "copying", "recruitment", "contact", "banking", "sme"], "requirements": {"degrees": [], "majors": [], "languages": [], "language_level": [], "hard_skills": ["sr"], "soft_skills": ["interested in", "accurate", "open minded", "resourceful"], "languages_combined": []}, "experience_required": {"duration": [], "field": []}}, {"job_id": "100003009041450", "location_code": "hk", "company": "Hays", "job_title": "Product Management/ Product Manager- Retail/ Corporate/ PB", "description": "Responsibilities:\n\nPrepare daily and monthly reconciliation, NAV estimates\nPreparing monthly fund valuation, return attribution and investor reporting\nMonitor various fund operation issues including settlements, collateral, and cash management\nPerform trade bookings, trade matching, daily and P&L reconciliations, failed trade investigations\nLiaise with prime brokers and fund administrator on break resolutions\nPerform automation and process review to streamline and document workflow\nSupport the trading team and assist in back office tasks\nHandle ad-hoc projects assigned by management\n\nRequirements:\n\nUniversity degree in Accounting, Finance or other related disciplines\nMinimum of 1 year fund/ accounting related experience\nKnowledge of financial derivative products is an advantage\nExcellent communication skills in English and Mandarin, mature mindset and confident personality in order to interact with Trading teams and senior management to address business issues\nGood attention to details, able to adapt and work well under pressure\nProficiency in Excel and SQL are preferable\nA positive attitude, a sense of satisfaction from doing your best, and self-discipline are all essential", "employment_types": ["Full Time", "Permanent"], "selling_points": ["Advance your career to next level", "Uplift your strategies and analytical skills", "Broaden management skills in competitive banks"], "locations": ["Not Specified"], "categories": ["Banking / Finance", "Investment", "Loan", "Fund Management"], "post_time": "2022-01-12T03:53:37Z", "salary": {"currency": null, "max": null, "min": null, "period": "monthly", "term": null}, "salary_visible": false, "title_keywords": ["product manager"], "responsibilities": ["valuation", "reporting", "management", "prime brokers", "review", "monitor", "back office", "p&l", "reconciliations", "liaise with", "ad-hoc projects"], "requirements": {"degrees": ["university degree"], "majors": ["related disciplines", "finance", "accounting"], "languages": ["english", "mandarin"], "language_level": ["excellent"], "hard_skills": ["sql", "excel"], "soft_skills": ["confident", "communication skills", "under pressure", "mature", "positive attitude", "attention to details"], "languages_combined": [{"language": "english", "language_level": ["excellent"]}, {"language": "mandarin", "language_level": ["excellent"]}]}, "experience_required": {"duration": ["minimum of 1 year"], "field": ["related", "accounting"]}}, {"job_id": "100003009033746", "location_code": "hk", "company": "Bank of Communications Hong Kong Branch", "job_title": "Section Head, Asset and Liability Management Compliance & Development", "description": "Career Level\nMiddle\nQualification\nDegree\nYears of Experience\n3 years\nJob Type\nFull Time\nJob Functions\nBanking / Finance, Fund Management, Professional Services, Legal & Compliance, Asset Management", "employment_types": ["Full Time"], "selling_points": [], "locations": ["Not Specified"], "categories": ["Accounting", "Others", "Banking / Finance", "Fund Management", "Professional Services", "Legal & Compliance"], "post_time": "2022-01-10T01:44:52Z", "salary": {"currency": null, "max": null, "min": null, "period": "monthly", "term": null}, "salary_visible": false, "title_keywords": ["section head"], "responsibilities": ["management", "compliance", "asset management", "banking"], "requirements": {"degrees": ["degree"], "majors": [], "languages": [], "language_level": [], "hard_skills": [], "soft_skills": [], "languages_combined": []}, "experience_required": {"duration": [], "field": []}}, {"job_id": "100003009036939", "location_code": "hk", "company": "JH Partners (Asia) Company Limited", "job_title": "Compliance Manager to Director ( Crypto Asset Manager )", "description": "Our Client\nA top Trustee in HK\n\n\nRole Overview\n\nPrepare for private trust establishment and transfer documentations\nEnsure accuracy of onboarding documents inclusive but not limited to trust deeds, letter of wishes\nPerform client annual review\nConduct due diligence/ KYC\nLiaise with internal and external stakeholders such as banks, lawyers, accountants, all partners a nd investment manager s or advisors regarding distribution, management and distributions of trust assets\n\nIdeal Profile\n\nBachelor degree or above\n3 years or above experience in handling private trust administration\nGood command of Chinese and English (Putonghua is preferred)\nProfessional qualifications such as TEP, CPA or ACIS preferable\u00a0", "employment_types": ["Full Time"], "selling_points": ["Crypto Asset Manager", "Compliance", "Remote work is allowed"], "locations": ["Central & Western Area"], "categories": ["Banking / Finance", "Fund Management", "Professional Services", "Legal & Compliance", "Asset Management"], "post_time": "2022-01-11T00:54:18Z", "salary": {"currency": null, "max": null, "min": null, "period": "monthly", "term": null}, "salary_visible": false, "title_keywords": ["manager", "director", "compliance manager"], "responsibilities": ["due diligence", "management", "review", "kyc", "liaise with", "administration"], "requirements": {"degrees": ["degree or above", "bachelor"], "majors": [], "languages": ["putonghua", "english", "chinese"], "language_level": ["good command"], "hard_skills": ["cpa", "professional qualifications", "documentations", "kyc"], "soft_skills": ["ideal"], "languages_combined": [{"language": "putonghua", "language_level": ["good command"]}, {"language": "english", "language_level": ["good command"]}, {"language": "chinese", "language_level": ["good command"]}]}, "experience_required": {"duration": ["3 years"], "field": ["administration"]}}, {"job_id": "100003009034608", "location_code": "hk", "company": "Cornerstone Global Partners", "job_title": "Private Trust Admin Manager / Senior Officer (KYC, Legal Documents, Top Trustee)", "description": "OnePlatform Asset Management\u00a0offers over 800 mutual funds managed by reputable fund houses and discretionary portfolio services to our customers. We are currently seeking a high-caliber professional to join our Asset Management business as an Investment Specialist/ Consultant to share the vision and venture our success.\n\nResponsibilities:\n\n\nPartner with the different sales channels, i.e. the Wealth Consultants/ Relationship Managers to share the investment market views and investment strategies\nStrategize the tactical plans and investment ideas to\u00a0provide investment advisory services. Prepare market commentaries, market update presentations to support channels partners to bring in new AUM to the business and achieve annual targets.\u00a0\nSupport sales channels on conducting the pre-case study, presentation,\u00a0and sales tactics on funds/portfolio products and carry out\u00a0joint-call activities proactively to boost the sales revenue\nDeliver regular reports and organize quarterly updates with different channels partners.\u00a0\nDevelop the sales capacity, sales coaching, training, and advisory support and ensure full compliance of both regulatory and internal requirements.\nDevelop strong relationships with channels and business partners; familiar with the respective rules and regulations, investment restraints and mandates, strategize and formulate solutions for the clients.\nParticipate in marketing communication pieces, promotion & campaign, training, and workshops\nPerform any ad-hoc tasks as assigned\n\nRequirements:\n\nBachelor\u2019s degree in Business, Finance, Economics or other related disciplines with professional qualifications such as CFA will be an advantage.\nMinimum 4 - 8 years relevant experience in banking or asset management company with strong knowledge of investment products and understanding of the distribution of funds.\nHolder of SFC Type 1.\nSelf-motivated\u00a0who takes responsibility and with a drive for execution\nOutstanding ability to build trust and long term relationships with internal and external stakeholders,\nExcellent communication skill and presentation skill, with strong influencing skill and analytical skill\nFulfillment of the competency requirements to carry out relevant regulated activities as defined under the Securities and Futures Ordinance\nExperience with financial software such as Morningstar or Bloomberg.\nProficient in written & spoken English and Chinese.\nProficient in MS Office applications\nMore experience will be considered as Senior Investment Consultant\n\nWe offer competitive remuneration including career prospects to the right candidate. Interested parties please send a detailed resume with availability, current and expected salaries to\u00a0Human Resources Department, OnePlatform Asset Management Limited, by clicking the Apply\u00a0button and uploading your CV and cover letter.\n\n(All applications will be treated in strict confidence and used for recruitment purposes within OnePlatform Asset Management Limited only. All applicants are kept on file 6 months from the date of the application.)", "employment_types": ["Permanent"], "selling_points": ["private trust transfer", "private trust establishment", "due diligence/ KYC"], "locations": ["Central & Western Area"], "categories": ["Banking / Finance", "Private Banking", "Fund Management", "Asset Management"], "post_time": "2022-01-10T03:47:48Z", "salary": {"currency": "HKD", "max": 44999, "min": 25000, "period": "monthly", "term": null}, "salary_visible": true, "title_keywords": ["senior officer", "admin", "manager"], "responsibilities": ["regulations", "market commentaries", "investment strategies", "ideas", "boost the sales", "ad-hoc tasks", "compliance", "presentations", "develop", "communication", "reports", "plans"], "requirements": {"degrees": ["degree", "bachelor"], "majors": ["related disciplines", "finance", "business", "economics"], "languages": ["english", "chinese"], "language_level": ["proficient"], "hard_skills": ["presentation skill", "analytical skill", "bloomberg", "professional qualifications", "cfa", "investment products", "securities and futures ordinance", "ms office"], "soft_skills": ["presentation skill", "self-motivated", "communication skill", "analytical skill"], "languages_combined": [{"language": "english", "language_level": ["proficient"]}, {"language": "chinese", "language_level": ["proficient"]}]}, "experience_required": {"duration": ["minimum 4 - 8 years"], "field": ["financial", "relevant experience", "investment", "banking", "asset management"]}}, {"job_id": "100003009030188", "location_code": "hk", "company": "OnePlatform Asset Management Limited", "job_title": "Investment Consultant (Manager, Business Development)", "description": "about the company.\nHong Kong-based single family office that is actively expanding its exposure to private markets. The company believe in a thematic, high-conviction approach to investing. Given an increasing allocation to private markets, they are looking to add highly capable investment professionals to the team.\nabout the team.\nThey believe that empowering the team members to (i) form their own ideas, and (ii) challenge those of others leads to superior decision-making. Team members are expected to be able to work independently, but investment discussions are collaborative. The company invest across all asset classes and geographies. This affords the team members the opportunity to develop a unique, broad skill set and perspective.\nabout the job.\nLead diligence and investment analysis for various fund and direct investments (venture, growth, and pre-IPO)\nPreparation of financial models and investment memorandums\nRepresent the firm in interactions with founders/management teams\nCursory review of term sheets and other deal documentation (with support from legal counsel)\nResearch for key investment themes\nskills & experiences required.\n3-8 years of experience in top tier bank or buyside firm (ideally private market investing)\nStrong technical ability (financial modelling, valuation, and preparation of investment memos)\nExcellent communication skills ie. the ability to synthesise complex information, and present it in a concise manner (written and verbal)\nDiligent, detail oriented, with an ability to prioritise\nSuccessful candidate will be rewarded with a competitive compensation package", "employment_types": ["Full Time", "Permanent"], "selling_points": ["Partner with the different sales channels", "Strategize the tactical plans and investment ideas", "Deliver regular reports"], "locations": ["Wan Chai"], "categories": ["Banking / Finance", "Investment", "Fund Management", "Asset Management"], "post_time": "2022-01-07T06:56:36Z", "salary": {"currency": null, "max": null, "min": null, "period": "monthly", "term": null}, "salary_visible": false, "title_keywords": ["manager", "investment consultant"], "responsibilities": ["management teams", "valuation", "ideas", "investment analysis", "financial models", "review", "develop", "communication", "documentation"], "requirements": {"degrees": [], "majors": [], "languages": [], "language_level": [], "hard_skills": ["documentation", "analysis"], "soft_skills": ["communication skills", "work independently", "capable", "detail oriented", "diligent", "collaborative", "unique", "prioritise", "superior"], "languages_combined": []}, "experience_required": {"duration": ["3-8 years"], "field": []}}, {"job_id": "100003009033134", "location_code": "hk", "company": "Randstad Hong Kong Limited", "job_title": "Investment  Associate / VP - Private Market", "description": "International asset management firm\nExcellent Exposure\nOur client is an international asset management firm with an international presence. To cope with their business expansion, they are seeking an outstanding candidate to join them.\nYou will lead the Trade Management function within Investment Operations, provide management expertise and best practice advice to the investment operations teams to support business as usual projects and deliverables. Develop and maintain enhanced procedures and controls within investment operations to ensure consistent high quality services and support to the front office, clients and other business units. Work with regional and country operations teams to promote best practices and standardization across the Asia region. Assist in providing leadership and training to build expertise and enhance Investment Operations capabilities. Participate or lead Investment Operations projects. Support post trade processing and resolving escalated trade settlement issues in a timely manner. Identify work flow, system improvements and work with the team on requirements needed for enhancement. Manage the relationship with custodian banks and internal/external counterparties such as brokers to monitor the quality of services and ensure market standard practices are in place.\nTo qualify for the position, you should be a Degree holder with a minimum of 6 years\u2019 experience across investment operations. Experience and knowledge of Middle Office/Investment Operations\u2019 policies and procedures, including but not limited to trade management oversight, trade support, corporate actions, pricing and valuations and fund operations. Experience with oversight of shared service operations and external providers such as fund administrators. Leadership experience building industry best practice within investment operations preferred. Good team player with strong written and verbal communication skills and the ability to build relationships across multiple levels of the organization.\nInterested applicants should send a detailed resume to Kelly Kam quoting reference jdb-4551\u00a0via email.\u00a0 Please click \u201cAPPLY NOW\u201d button below\n(Applicants not contacted within 4 weeks should consider their application unsuccessful.)", "employment_types": ["Full Time", "Permanent"], "selling_points": [], "locations": ["Not Specified"], "categories": ["Banking / Finance", "Fund Management"], "post_time": "2022-01-08T10:22:55Z", "salary": {"currency": null, "max": null, "min": null, "period": "monthly", "term": null}, "salary_visible": false, "title_keywords": ["associate"], "responsibilities": ["management", "settlement issues", "operations", "system improvements", "policies", "teams", "procedures", "quality", "develop", "a timely manner", "monitor", "communication", "maintain", "providing leadership", "asset management"], "requirements": {"degrees": ["degree holder"], "majors": [], "languages": [], "language_level": [], "hard_skills": ["processing"], "soft_skills": ["communication skills", "good team player", "timely", "leadership", "detailed"], "languages_combined": []}, "experience_required": {"duration": ["minimum of 6 years"], "field": ["management", "investment"]}}, {"job_id": "100003009035523", "location_code": "hk", "company": "Recruitment Intelligence Consultants Ltd", "job_title": "TRADE MANAGEMENT, INVESTMENT OPERATIONS - MANAGER / SENIOR MANAGER or above", "description": "Scope of Responsibilities:\n\n\nMeasure and Monitor risks in our managed portfolios, include but not limited to investment, liquidity and counterparty risks;\nMonitor risk limits and exposure limits to ensure that all supported products and mandates adhere to internal and regulatory investment risk guidelines;\nSupport and develop model valuation on various risk management projects;\nCoordinate operational risk management projects, including incidents review, key risk register and RSCA workshops preparation;\nReview and Update on risk management policies and procedures; Perform stress testing from market/liquidity risk aspects, with hands-on experience in latest risk management development;\nSupport ad hoc projects and prepare risk reporting for Risk Committee meeting;\nOn-job training will be provided.\n\n\u00a0Skills & Qualifications:\n\n\nBachelor Degree with major in Finance, Accounting, Risk Management or other related discipline\nMinimum of 2-3 years\u2019 risk management and controls experience in asset management or banking industry.\nHolder of other relevant Professional Qualification (e.g. CPA/ FRM/ CFA) will be an advantage\nKnowledge and experience in fund management and various financial product operations\nGood analytical and interpersonal skills\nExcellent verbal and written communication skills in Cantonese, Mandarin and English.\n\nWe offer:\n\nCompetitive\u00a0package + year-end bonus + comprehensive\u00a0insurance benefit\nFull range of professional training program\nBright\u00a0career path to every\u00a0successful candidate\nCompany sponsors selected professional qualification\n\nPlease attach a detailed resume together with your current salary, expected salary, notice period and contact information. Please note that only short-listed applicants will be notified. For more information, please visit our website: http://www.noahgroup.hk/\n\nAs an equal opportunity employer, Noah and its affiliates consider all qualified applicants will receive equal consideration for employment. We will contact you to pursue a conversation if your background and skills align with our firm\u2019s needs.", "employment_types": ["Full Time", "Permanent"], "selling_points": [], "locations": ["Not Specified"], "categories": ["Banking / Finance", "Financial Services", "Fund Management", "Asset Management"], "post_time": "2022-01-10T07:32:21Z", "salary": {"currency": null, "max": null, "min": null, "period": "monthly", "term": null}, "salary_visible": false, "title_keywords": ["senior manager", "operations", "manager"], "responsibilities": ["valuation", "management", "reporting", "guidelines", "policies", "operations", "review", "monitor", "procedures", "develop", "coordinate", "testing", "communication", "ad hoc projects", "banking", "asset management"], "requirements": {"degrees": ["degree", "bachelor"], "majors": ["finance", "accounting", "risk management"], "languages": ["cantonese", "english", "mandarin"], "language_level": ["excellent"], "hard_skills": ["workshops", "cpa", "frm", "cfa"], "soft_skills": ["communication skills", "hands-on", "interpersonal skills"], "languages_combined": [{"language": "cantonese", "language_level": ["excellent"]}, {"language": "english", "language_level": ["excellent"]}, {"language": "mandarin", "language_level": ["excellent"]}]}, "experience_required": {"duration": ["minimum of 2-3 years"], "field": ["risk management", "banking industry", "management", "financial", "development", "testing", "asset management"]}}, {"job_id": "100003009023016", "location_code": "hk", "company": "Bank Consortium Trust Co. Ltd.", "job_title": "Officer/ Assistant Officer \u2013 Fund Services (Fund Accounting & Valuation) (BCT-FS10)", "description": "Key Responsibilities:\n\n\nAssist to coach associates to perform portfolio valuation NAV prices computation and other fund administration works daily.\nPrepare and / or check valuation reports and other fund administration works to ensure that they are correctly prepared.\nMaintain a high degree of accuracy and consistency in preparation of daily reporting and ensure that the pricing/valuation process are adhered to audit procedures and ensure service standards are met.\nDeal with issues and queries from clients in a professional and timely manner.\nStrong sense on risk awareness and ensure that team members will comply with regulation and company\u2019s policy and procedures.\nFollow the procedures as specified in the Procedure Manual and ensure comply with in all relevant work processes.\u00a0 Prompt escalation to Team Head for any issues identified.\nParticipate in UAT for any new system enhancement prior to production.\nParticipate in those tasks or projects as assigned by Team Head from time to time and take accountability.\n\nRequirements:\n\n\nDegree holder in accountancy or Diploma in Business related discipline.\nFor candidates with academic background below degree, strong and relevant experience in fund administration industry must be demonstrated.\nMinimum 4 years\u2019 experience in fund accounting and administration, with substantial\u00a0experience in regulated mutual funds / MPF / ORSO schemes operations\nGood command of spoken and written English and Chinese.\nBe flexible and an open-minded team player\nStrong adaptability to change\nCandidate with less experience will be considered as Assisttant Officer\n\nRemuneration will be commensurate with qualification and experience. Please send your application with detailed resume indicating both present and expected salary and date of availability to the Human Resources Department, 18/F Cosco Tower, 183 Queen\u2019s Road Central, Hong Kong, or click 'Apply Now' or fax to 23143984.\n\n(Personal data collected will be used for recruitment purpose only and will be kept strictly confidential)", "employment_types": ["Full Time", "Permanent"], "selling_points": ["Degree holder in accountancy", "Minimum 4 years\u2019 experience in fund accounting", "Perform portfolio valuation NAV prices computation"], "locations": ["Central & Western Area"], "categories": ["Accounting", "Accountant", "Banking / Finance", "Fund Management"], "post_time": "2022-01-05T07:12:12Z", "salary": {"currency": null, "max": null, "min": null, "period": "monthly", "term": null}, "salary_visible": false, "title_keywords": ["assistant officer", "officer", "accounting"], "responsibilities": ["reporting", "valuation", "uat", "procedures", "audit", "service standards", "maintain", "reports", "administration"], "requirements": {"degrees": ["diploma", "degree", "degree holder"], "majors": ["business", "accountancy"], "languages": ["english", "chinese"], "language_level": ["good command"], "hard_skills": [], "soft_skills": ["flexible", "open-minded", "adaptability", "team player", "detailed"], "languages_combined": [{"language": "english", "language_level": ["good command"]}, {"language": "chinese", "language_level": ["good command"]}]}, "experience_required": {"duration": ["minimum 4 years"], "field": ["accounting", "relevant experience", "mpf", "administration"]}}, {"job_id": "100003009027793", "location_code": "hk", "company": "Waystone Governance (HK) Limited", "job_title": "Associate - Fund Governance", "description": "Are you looking for the next step in your career?\u00a0\u00a0Do you have a desire to work in a dynamic environment? Waystone has a fantastic opportunity our on Fund Governance Team for an Associate in our Hong Kong Operations.\n\nWe are seeking an individual with strong organisational and time management skills. The right individual will have excellent communication skills with the ability to work as part of a team and build relationships with key stakeholders.\n\n\u00a0If this sounds like you, we want to hear from you!\n\nThe successful candidate will work closely with and provide support to Directors, Associate Directors of the Fund Governance Team, to ensure client service delivery across global governance product lines, collaborate on various projects within the team and take on a portfolio of clients.\n\nWaystone is a place where talented people are empowered to steer their careers towards greatness. We dare employees to become the best at what they do in a field they love. When they rise to that challenge, great business happens.\n\nESSENTIAL DUTIES AND RESPONSIBILITIES\n\nService complex portfolio of Cayman domiciled hedge funds and companies and provide support to a team of associate directors and directors.\nIndependently manage client correspondence and deliverables such as document review and execution and quality control of provided service, including a 24 hour turn around on all communications and timely saving of relevant information to client management database.\nResponsible for data integrity, accuracy, and completeness in the client management database.\nProvide appropriate materials prepared to a high standard as defined by Waystone protocols, meeting all policy and procedure expectations and timelines.\nDraft documentation based on internal templates.\nArrange client phone calls.\nAssist with common client deliverables for other business units.\nManage the Document Execution Form (\u201cDEF\u201d) workflow for board resolutions, agreements and other transactional documentation prior to director execution.\nProvide excellent customer service and independently liaise in a professional manner with fund service providers.\nDisplay understanding of onboarding required and proactively begin process when relevant new engagement is assigned.\nIdentify and explore opportunities for cross-selling Waystone products.\nBuild to maintain a full portfolio of client relationships following successful completion of training.\nTake responsibility for regulatory and risk management projects on assigned portfolio, including but not limited to:\nCompleteness of performance and investor reporting\nCompleteness of board meeting minutes for the year\nFinancial Statement/Audit reviews and regulatory filing\nImplementation of new regulatory requirements\nFund status, regulatory and service provider information in client management database (weekly, monthly & quarterly projects).\nMonitor the accounts receivable for portfolio of clients, proactively follow up and escalate when necessary.\nProvide support to the Board Support Team on the provision of board meeting services to a portfolio of clients.\nMaintain professional interaction with internal and external clients in conversation and in emails. Ensure clients are phoned when communications are being prolonged by emails and ensure appropriate phone notes are made to the system.\nWhen out of office, provide notes to Manager the day before leaving and complete the out of office checklist regarding all outstanding DEFs, upcoming meetings and any other pending matters related to client portfolio or regulatory projects.\nEvaluate risk involved with each situation and prioritize time and risk levels appropriately.\nDemonstrate understanding of the operational risk associated with Governance clients, including a complete understanding of all Policies & Procedures.\nKeep abreast of all industry developments and regulatory changes and assist in projects related to operational risk and compliance as well as be able to communicate with clients on such as well\nFoster a positive environment through open communication and willingness to work efficiently and effectively with others.\nShare key learning and knowledge lessons at team meetings.\nEngage with Associate Directors, Directors and Business Unit Leaders to further knowledge and to define and grow a career path within Waystone.\nBe able/willing to take on additional duties as and when required. Assist colleagues when capacity permits and notify Manager with availability.\n\nREQUIREMENTS\n\n\n\nTo perform this job successfully, an individual must be able to perform each essential duty satisfactorily. The requirements listed below are representative of the knowledge, skill, and/or ability required. Reasonable accommodations may be made to enable individuals with disabilities to perform the essential functions.\n\nEducation:\n\nBachelors\u2019 degree or internationally recognized professional qualification.\nExperience:\n\nMinimum of 2 \u2013 4 years\u2019 investment fund client service experience.\nA strong working knowledge of fund structures, fund documentation and regulatory requirements is required.\nMust be able to work in a fast-paced environment, including reporting and providing support to various members of a large team and diverse client portfolio complex portfolio of Cayman domiciled hedge funds and companies\nLanguage skills \u2013 Fluency in Cantonese/Mandarin", "employment_types": ["Full Time"], "selling_points": [], "locations": ["Central"], "categories": ["Banking / Finance", "Fund Management", "Risk Management", "Asset Management"], "post_time": "2022-01-07T10:36:09Z", "salary": {"currency": null, "max": null, "min": null, "period": "monthly", "term": null}, "salary_visible": false, "title_keywords": ["associate"], "responsibilities": ["liaise", "reporting", "provide support", "management", "data", "review", "professional manner", "audit", "customer service", "maintain", "quality control", "database", "documentation", "financial statement", "phone calls"], "requirements": {"degrees": ["degree"], "majors": [], "languages": ["cantonese", "mandarin"], "language_level": ["fluency"], "hard_skills": ["documentation"], "soft_skills": ["fast-paced environment", "prioritize", "communication", "diverse", "learning", "willingness to work", "positive"], "languages_combined": [{"language": "cantonese", "language_level": ["fluency"]}, {"language": "mandarin", "language_level": ["fluency"]}]}, "experience_required": {"duration": ["4 years"], "field": ["investment"]}}, {"job_id": "100003009023099", "location_code": "hk", "company": "Bank Consortium Trust Co. Ltd.", "job_title": "Manager/ Assistant Manager \u2013 Fund Services (Fund Accounting & Valuation) (BCT-FS12)", "description": "Key Responsibilities:\n\n\nAssist to supervise a team in performing portfolio valuation NAV prices computation and other fund administration works daily\nCheck valuation reports and other fund administration works to ensure that they are correctly prepared\nMaintaining a high degree of accuracy and consistency in preparation of daily reporting and ensure that the pricing/valuation process are adhered to audit procedures and ensure service standards are met.\nDeal with issues and queries from clients in a professional and timely manner\nFollow and perform control as specified in the Procedure Manual and ensure comply with in all relevant work processes.\u00a0 Prompt escalation to Team Head or Department Head for any issues identified.\nStrong sense on risk awareness and supervise the team members to ensure they always comply with regulation and company\u2019s policy and procedures.\nParticipate in UAT for any new system enhancement prior to production\nParticipate in those tasks or projects as assigned by Department Head from time to time and take accountability.\n\nRequirements:\n\n\nDegree holder in accountancy or Diploma in Business related discipline etc. For candidates with academic background below degree, strong and relevant experience in fund administration industry must be demonstrated.\nMinimum 6 years\u2019 experience in fund accounting and administration, with substantial\u00a0experience in regulated mutual funds / MPF / ORSO schemes operations\nGood command of spoken and written English and Chinese.\nBe flexible and an open-minded team player\nStrong adaptability to change\nCandidate with less experience will be considered as Assistant Manager\n\nRemuneration will be commensurate with qualification and experience. Please send your application with detailed resume indicating both present and expected salary and date of availability to the Human Resources Department, 18/F Cosco Tower, 183 Queen\u2019s Road Central, Hong Kong, or click 'Apply Now' or fax to 23143984.\n\n(Personal data collected will be used for recruitment purpose only and will be kept strictly confidential)", "employment_types": ["Full Time", "Permanent"], "selling_points": ["Perform portfolio valuation NAV prices computation", "substantial experience in regulated mutual fundsS", "Maintaining a high degree of accuracy"], "locations": ["Central & Western Area"], "categories": ["Accounting", "Accountant", "Banking / Finance", "Fund Management"], "post_time": "2022-01-05T07:27:53Z", "salary": {"currency": null, "max": null, "min": null, "period": "monthly", "term": null}, "salary_visible": false, "title_keywords": ["assistant manager", "manager", "accounting"], "responsibilities": ["reporting", "valuation", "control", "uat", "maintaining", "procedures", "audit", "service standards", "reports", "administration"], "requirements": {"degrees": ["diploma", "degree", "degree holder"], "majors": ["business", "accountancy"], "languages": ["english", "chinese"], "language_level": ["good command"], "hard_skills": [], "soft_skills": ["flexible", "open-minded", "adaptability", "team player", "detailed"], "languages_combined": [{"language": "english", "language_level": ["good command"]}, {"language": "chinese", "language_level": ["good command"]}]}, "experience_required": {"duration": ["minimum 6 years"], "field": ["accounting", "relevant experience", "mpf", "administration"]}}, {"job_id": "100003009036582", "location_code": "hk", "company": "AXA China Region Insurance Company Limited", "job_title": "MPF Service Officer", "description": "MPF Service Officer/MPF Specialist\n\nAXA China Region Insurance Company Limited\n\nJob Highlights\n\n4 Days Office Work\n25-50K\nPerformance Bonus\nProvide MPF advise for customer\nLong term business development\n\nJob Description\nWe offer flexible working hour, fun , young and joyful environment!\nWe are a group of international team, including Cantonese, English. We are using a modern management system, no office politics and hierarchical, we treasure and listen every teammate, use our profession to provide MPF and retirement plan to our clients.\nProvide professional MPF service to individual clients for wealth management, retirement scheme, investment, etc.\nProvide benefits to corporate clients such as MPF, Investment, Group Medical, Business Insurance, etc\nBuild your own professional finance management team\nA pleasant work atmosphere on an international team\nAttractive Compensation\nBenefits\nMonthly Salary + Quarterly Bonus + Year End Bonus\nInitial training and On-Job training provided\nExcellent Career Path to Management Ladder\nLife and Medical Insurance\nClient Base provided\nFlexible working hours\nRequirements\nExperience in customer service or sales\nSales driven, self-motivated and customer-oriented\nMature personality with excellent inter-personal and communication skills\nHKID card holder is a MUST\nTeam spirit\nMature, responsible, and strong desire for success\n*** The best and transparent career path ***", "employment_types": ["Full Time", "Contract"], "selling_points": ["4 Days Office Work; 25-50K; Performance Bonus", "Provide MPF advise for customer", "Long term business development"], "locations": ["Not Specified"], "categories": ["Banking / Finance", "Fund Management", "Insurance", "Insurance Agent / Broker", "Others"], "post_time": "2022-01-10T11:10:39Z", "salary": {"currency": null, "max": null, "min": null, "period": "monthly", "term": null}, "salary_visible": false, "title_keywords": ["officer"], "responsibilities": [], "requirements": {"degrees": [], "majors": [], "languages": [], "language_level": [], "hard_skills": [], "soft_skills": [], "languages_combined": []}, "experience_required": {"duration": [], "field": []}}, {"job_id": "100003009027294", "location_code": "hk", "company": "Guosen Securities (HK) Financial Holdings Company, Limited", "job_title": "Vice President, ESOP (Employee Stock Ownership Plan)", "description": "Responsibilities:\n\nPrepare and update the policies and procedures of ESOP business to ensure the ESOP business is well coordinated and the daily operation is smooth\nEstablish the procedures and controls to manage the risks associated with the ESOP business\nManage all aspects of new client implementation\nAnalyze the client data of employee share plan and communicate with clients to confirm their requirements for ESOP\nPrepare relevant documents for ESOP business and daily operation\nAssist dealing and IT department in performing ESOP system testing and system rollout\nAssist in performing daily operation such as account opening, responding client enquires, reporting, recording keeping and system monitoring\nTo perform ad hoc projects as required\n\nRequirements:\n\nDegree holder in Business, Finance, Economics or related disciplines\nMinimum 3 years of working experience in ESOP business\nGood command of written and spoken English and Chinese, fluency in Putonghua\nExcellent communication, analytical and problem-solving skills\nGood interpersonal skills, self-motivated\n\n\nAttractive remuneration will be offered to the right candidate.\u00a0 Interested parties please email your full resume with present & expected salary and date of availability to hrm @guosen.com.hk or via \"Apply Now\".\n\nPersonal data collected would be used for recruitment purpose only.", "employment_types": ["Full Time", "Permanent"], "selling_points": ["Employee Stock Ownership Plan (ESOP)", "Stock options scheme", "employee share plan"], "locations": ["Admiralty"], "categories": ["Banking / Finance", "Corporate Banking", "Fund Management", "Asset Management"], "post_time": "2022-01-06T09:37:58Z", "salary": {"currency": null, "max": null, "min": null, "period": "monthly", "term": null}, "salary_visible": false, "title_keywords": ["vice president"], "responsibilities": ["communicate with", "reporting", "data", "policies", "account opening", "monitoring", "daily operation", "procedures", "implementation", "testing", "ad hoc projects", "plan"], "requirements": {"degrees": ["degree holder"], "majors": ["related disciplines", "finance", "business", "economics"], "languages": ["putonghua", "english", "chinese"], "language_level": ["fluency", "good command"], "hard_skills": ["problem-solving skills"], "soft_skills": ["communication", "problem-solving skills", "self-motivated", "interpersonal skills"], "languages_combined": [{"language": "putonghua", "language_level": ["fluency", "good command"]}, {"language": "english", "language_level": ["fluency", "good command"]}, {"language": "chinese", "language_level": ["fluency", "good command"]}]}, "experience_required": {"duration": ["minimum 3 years"], "field": ["business"]}}, {"job_id": "100003009029409", "location_code": "hk", "company": "Michael Page", "job_title": "PE Investment Associate - HK Family Office", "description": "This role is part of a high performing investment team. You will be needed to provide in-depth market research and due diligence of private market deals to assist the top management team with making sound investment decision.\n\nClient Details\n\nOur client is a HK family office with investments across private equity, private credit, real estate investment markets.\n\nDescription\n\nConduct market research and perform due diligence within private equity and credit sectors\nWork closely with the team to lead deal investment process from acquisition, execution and post-investment management\nPerform in-depth financial analysis on investment projects\nCommunicate key findings and recommendations to the investment committee.\nAssist in negotiation of terms of transaction and preparation of investment documentation\n\nProfile\n\nBachelor's degree or above in Finance, Mathematics, Statistics, Economics or related field from global top university.\nAround 3 - 8 years of working experience from IBD, Private Equity or Big 4 Transaction Services team\nExceptional analytical skills with a focus on private equity or private credit sector, especially in Asia region\nExcellent presentation and communication skills in Mandarin, Cantonese and English\n\nJob Offer\n\nCompetitive compensation\n\nTo apply online please click the 'Apply' button below. For a confidential discussion about this role please contact Chris Yang on +852 2848 4716", "employment_types": ["Full Time", "Permanent"], "selling_points": ["HK Family Office", "Private Equity and Private Credit Investments", "Fluent English is a must"], "locations": ["Central & Western Area"], "categories": ["Banking / Finance", "Investment", "Financial Services", "Fund Management"], "post_time": "2022-01-07T05:08:44Z", "salary": {"currency": null, "max": null, "min": null, "period": "monthly", "term": null}, "salary_visible": false, "title_keywords": ["investment associate"], "responsibilities": ["due diligence", "management team", "management", "conduct market research", "market research", "financial analysis", "communication", "contact", "documentation"], "requirements": {"degrees": ["degree or above", "bachelor"], "majors": ["finance", "economics", "statistics", "mathematics"], "languages": ["cantonese", "english", "mandarin"], "language_level": ["excellent"], "hard_skills": ["analytical skills", "financial analysis", "documentation", "focus", "private equity"], "soft_skills": ["communication skills", "negotiation", "analytical skills", "focus", "presentation"], "languages_combined": [{"language": "cantonese", "language_level": ["excellent"]}, {"language": "english", "language_level": ["excellent"]}, {"language": "mandarin", "language_level": ["excellent"]}]}, "experience_required": {"duration": ["3 - 8 years"], "field": ["big 4", "team"]}}, {"job_id": "100003009023020", "location_code": "hk", "company": "Bank Consortium Trust Co. Ltd.", "job_title": "Senior Associate \u2013 Fund Services (Settlement & Corporate Action)  (BCT-FS11)", "description": "Key Responsibilities:\n\n\nArrange settlement in global security markets\nFollow up with fund houses and custodians to resolve settlement and corporate action related issues\nSet up masters in Settlement system\nHandle daily compliance checklist\nConduct price feed with Equities and Bonds by collecting information from service providers and inputting correct prices data\nPrepare instructions for settlement, deposit and Forward Forex settlement\nObtain and collect information of corporate action from custodian agents and data quotation systems\nAssist in handling corporate action and funding arrangement\nPerform reconciliation to ensure securities and cash records are tie with Custodians\n\nRequirements:\n\n\nAssociate Degree or Degree Holder is preferred\nMinimum 2 years\u2019 relevant work experience in banking or financial services industry\nHands on experience in SWIFT with knowledge of global securities\nDetail-oriented with good interpersonal skills\nProficient in MS Excel\nGood command of written and spoken English and Chinese\n\nRemuneration will be commensurate with qualification and experience. Please send your application with detailed resume indicating both present and expected salary and date of availability to the Human Resources Department, 18/F Cosco Tower, 183 Queen\u2019s Road Central, Hong Kong, or click 'Apply Now' or fax to 23143984.\n\n(Personal data collected will be used for recruitment purpose only and will be kept strictly confidential)", "employment_types": ["Full Time", "Permanent"], "selling_points": ["Conduct price feed with Equities and Bonds", "Minimum 2 years\u2019 relevant experience", "Arrange settlement in global security markets"], "locations": ["Central & Western Area"], "categories": ["Accounting", "Accountant", "Banking / Finance", "Fund Management"], "post_time": "2022-01-05T07:12:14Z", "salary": {"currency": null, "max": null, "min": null, "period": "monthly", "term": null}, "salary_visible": false, "title_keywords": ["senior associate"], "responsibilities": ["quotation", "compliance", "systems", "data"], "requirements": {"degrees": ["associate degree", "degree holder"], "majors": [], "languages": ["english", "chinese"], "language_level": ["good command"], "hard_skills": ["swift", "ms excel"], "soft_skills": ["hands on", "interpersonal skills", "detailed", "detail-oriented"], "languages_combined": [{"language": "english", "language_level": ["good command"]}, {"language": "chinese", "language_level": ["good command"]}]}, "experience_required": {"duration": ["minimum 2 years"], "field": ["financial services industry", "securities", "banking"]}}, {"job_id": "100003009011206", "location_code": "hk", "company": "", "job_title": "Vice President / Executive Director", "description": "Job Description\n\nOpportunity to join a multi-strategy investment platform with a global mandate\nLooking for a driven and motivated individual to be part of a seasoned investment team\nLead investments in different asset classes, sectors and regions, with a focus on alternative assets\nResponsible for sourcing, analysis, due diligence, execution and monitoring investments\nLead strategic projects on market maps and other topics of interest\nSupervise, train and mentor junior team members\nDrive firmwide initiatives in support of shaping the long-term strategy and overall portfolio construction of the Firm\n\nRequirements\n\n6-10 years of relevant experience; prior primary fund investing experience is an asset\nDriven self-starter and independent thinker with high intellectual curiosity\nSolid communication skills with ability to build and maintain relationships with external parties\nTeam player with strong leadership capabilities / potentials; ability to work independently or to lead deal teams, reliable and responsible with high ethical and professional standards\nUndergraduate or postgraduate degree in Finance, Accounting, Economics, Business, Mathematics and Statistics or other relevant disciplines\nFluent in spoken and written English and Chinese\nInterested candidates, please contact us at 37933289 for company details before applying.", "employment_types": ["Full Time", "Permanent"], "selling_points": ["Multi-strategy investment firm with global mandate", "Alternatives-focused; mainly in fund investments", "VP/ED candidate with 6-10 years of experience"], "locations": ["Pok Fu Lam"], "categories": ["Banking / Finance", "Investment", "Fund Management", "Asset Management"], "post_time": "2022-01-05T20:31:55Z", "salary": {"currency": null, "max": null, "min": null, "period": "monthly", "term": null}, "salary_visible": false, "title_keywords": ["vice president", "executive director"], "responsibilities": ["due diligence", "analysis", "monitoring"], "requirements": {"degrees": ["degree"], "majors": ["mathematics", "finance", "economics", "statistics", "business", "accounting"], "languages": ["english", "chinese"], "language_level": ["fluent"], "hard_skills": [], "soft_skills": ["communication skills", "work independently", "independent", "responsible", "ethical", "team player", "reliable", "leadership", "driven"], "languages_combined": [{"language": "english", "language_level": ["fluent"]}, {"language": "chinese", "language_level": ["fluent"]}]}, "experience_required": {"duration": ["6-10 years"], "field": ["relevant experience"]}}, {"job_id": "100003009030163", "location_code": "hk", "company": "New Vision Asset Management Limited", "job_title": "Senior Operations Officer / Assistant Operations Manager", "description": "Our client is a leading Asset Management, the principal activities included PE fund investment, Hedge Fund investment, insurance and corporate finance. To cope with their business expansion, they are looking for a caliber to join their team.\n\n\n\nHandle daily fund accounting including NAV calculation, cash and position reconciliation, cash collateral, distribution\u2026etc\nWork closely with third party service providers such as external auditors, tax consultants and compliance team\nAssist in new fund set up and wok with external and internal parties such as Risk, Investment, Finance, Sales\u2026etc\nMonitor and continuously improve the quality of services delivered by the services providers\nPerform ad hoc duties as assigned\n\n\nRequirements:\n\nBachelor's Degree in Accounting, Finance or relevant discipline\nMinimum of 4 years' fund related experience and consider candidates came from Fund Admin or Fund Operations\nKnowledge of Alternative Investment Fund with direct working experience of fund accounting,\nMember of CPA is an added advantage\nHigh level of multi-tasking and time management skill are required\nA team-player with excellent working attitude; willing to take on multiple functions\nExcellent verbal and written communication skills\n\n\n\nApply Today\n\nTo apply online (Word attachment only), please click the 'Apply' button. Please note that only short-listed candidates will be contacted.", "employment_types": ["Full Time"], "selling_points": ["Experience in virtual asset industry", "Less experience will consider as Assistant Officer", "Immediate available is highly preferred"], "locations": ["Central"], "categories": ["Banking / Finance", "Fund Management", "Wealth Management"], "post_time": "2022-01-07T19:20:06Z", "salary": {"currency": null, "max": null, "min": null, "period": "monthly", "term": null}, "salary_visible": false, "title_keywords": ["officer", "senior operations", "assistant operations manager"], "responsibilities": ["tax", "ad hoc duties", "management", "operations", "compliance", "monitor", "quality", "communication", "asset management", "insurance", "third party", "internal parties", "external auditors"], "requirements": {"degrees": ["degree", "bachelor"], "majors": ["finance", "accounting"], "languages": [], "language_level": [], "hard_skills": ["cpa", "pe", "word"], "soft_skills": ["team-player", "communication skills", "multi-tasking", "time management skill"], "languages_combined": []}, "experience_required": {"duration": ["minimum of 4 years"], "field": ["related", "admin", "investment", "accounting"]}}, {"job_id": "100003009018927", "location_code": "hk", "company": "Gracious Eternity Consultant Company", "job_title": "Management Associate \u2013 Investment Sector (Fresh Grad are welcome)", "description": "Our client is a licensed adviser with Securities and Futures Commission (CE No. AFG549). They offer you high quality financial advice from a dedicated adviser and a robust financial plan that will change as you do. You also have a team of dedicated experts scouring the globe for the right products for you, monitoring any market development and making sure you stay on track to reach your goals.\n\nJob Responsibilities:\n\nWorks as part of the investment team, providing a range of financial services to designated clients\nSupports the overall investment team deal originators in the identification, analysis and presentation of investment opportunities\nPerform in-depth research on investment matrix, comprehensive financial analysis for global market\nReview the investment portfolios of clients regularly to determine whether life changes, economic changes, or financial performance indicate a need for plan reassessment\nConducts macro and micro market research for target markets on a daily basis, including monitoring local business and economic trends, logistics and goods movement fundamentals and local real estate market activity\nAble to work concurrently on multiple projects with a minimal supervision, solve problems, and produce accurate work through self-checks\n\nJob Requirements:\n\nDiploma / Bachelor degree holder in Finance, Risk Management, Business Administration or related discipline is preferred\nStrong analytical skills\nStrong communication skills\nSelf-motivated and hardworking with a strong sense of commitment and responsibility\nSelf-initiative, positive attitude and attentive to details\nFluent in both written and spoken English and Chinese\nFresh graduate are welcome\n\nWe offer:\n\nBasic salary 20k with attractive performance bonuses\nMedical insurance\u00a0\nFlexible working hours\u00a0\nOn going professional trainings\u00a0\nYoung and Fun working atmosphere\u00a0\n\nWe offer a competitive salary and benefits package and the professional advantages of a dynamic environment that supports your development and recognizes your achievements.\n\nInterested individuals please send your detailed resume and expected salary by clicking\u00a0\"Apply Now\". Only candidates who are authorized to work in Hong Kong will be considered.\n\nAll personal data provided will only be used for recruitment purpose only.", "employment_types": ["Full Time"], "selling_points": ["Great career path and personal growth", "Fresh graduate are welcome", "Professional Training Programme"], "locations": ["Quarry Bay"], "categories": ["Banking / Finance", "Fund Management", "Wealth Management"], "post_time": "2022-01-08T02:08:47Z", "salary": {"currency": null, "max": null, "min": null, "period": "monthly", "term": null}, "salary_visible": false, "title_keywords": ["management associate"], "responsibilities": ["analysis", "review", "investment portfolios", "market research", "monitoring", "financial analysis", "logistics", "plan", "multiple projects"], "requirements": {"degrees": ["diploma", "fresh graduate", "bachelor degree holder"], "majors": ["finance", "business administration", "risk management"], "languages": ["english", "chinese"], "language_level": ["fluent"], "hard_skills": ["analytical skills"], "soft_skills": ["communication skills", "self-motivated", "attentive to details", "analytical skills", "positive attitude", "self-initiative", "hardworking"], "languages_combined": [{"language": "english", "language_level": ["fluent"]}, {"language": "chinese", "language_level": ["fluent"]}]}, "experience_required": {"duration": [], "field": []}}, {"job_id": "100003009024602", "location_code": "hk", "company": "Walters People (HK)", "job_title": "Accounting & Operations Officer | PE Firm", "description": "One of the top 50 PE firms in Asia is hiring for an accounting and operaations officer/manager to cope with its expansion in Hong Kong. Their funds are worth about 2 billion US dollars.\n\n\n\n\nResponsibilities\n* Prepare quarterly reports and annual reports for venture capital funds under management (\"Funds\"), This will include valuation on portfolio companies of the Funds based on IFRS (fair values);\n* Collaborate with inter-office investment teams on financial information of portfolio companies;\n* Liaise with auditors on funds and tax advisors in respect of US K1 schedules and PFIC statements;\n* Performing compliance checking and filing in respect of FATCA, CRS, FAR and US ADV (annually);\n* Handle annual financial statements for Funds and annual audit of certain investment holding companies\n* Assist the fund operation procedure such as capital call, distribution, management fee, bank transactions and ad-hoc tasks (for responding to investors' requests especially during fundraising period) as assigned;\n\n\n\nRequirements:\n* Degree in accounting or related disciplines with preferably 2-3 year's relevant experience in accounting\n* Experience in portfolio valuation and VC/PE funds' operation will be a bonus\n* Student member in HKICPA or HKICPA qualified\n* Proficient in excel\n* Knowledge in accounting software, such as Quickbook and investment software, such as eFront, is a plus\n* Good communication skills, fluent in written English and Chinese and spoken English, Cantonese and Putonghua\n\n\n\n* more experienced fund candidates will be given assistant manager grade", "employment_types": ["Full Time", "Permanent"], "selling_points": ["", "", ""], "locations": ["Not Specified"], "categories": ["Accounting", "Accountant", "Banking / Finance", "Fund Management", "Others"], "post_time": "2022-01-06T01:54:28Z", "salary": {"currency": "HKD", "max": 34999, "min": 30000, "period": "monthly", "term": null}, "salary_visible": true, "title_keywords": ["operations officer", "accounting"], "responsibilities": ["collaborate with", "valuation", "management", "tax", "annual audit", "schedules", "ad-hoc tasks", "compliance", "teams", "checking", "financial statements", "transactions", "reports", "liaise with"], "requirements": {"degrees": ["degree"], "majors": ["related disciplines", "accounting"], "languages": ["cantonese", "putonghua", "english", "chinese"], "language_level": ["fluent", "good"], "hard_skills": ["excel", "plus", "vc", "accounting software", "pe", "hkicpa"], "soft_skills": ["communication skills"], "languages_combined": [{"language": "cantonese", "language_level": ["fluent", "good"]}, {"language": "putonghua", "language_level": ["fluent", "good"]}, {"language": "english", "language_level": ["fluent", "good"]}, {"language": "chinese", "language_level": ["fluent", "good"]}]}, "experience_required": {"duration": ["2-3 year"], "field": ["related", "operation", "accounting", "relevant experience"]}}, {"job_id": "100003009027795", "location_code": "hk", "company": "Waystone Governance (HK) Limited", "job_title": "Associate Director - Compliance Services", "description": "Are you looking for the next step in your career?\u00a0\u00a0Do you have a desire to work in a dynamic environment? Waystone has a fantastic opportunity our on Compliance Services Team for an Associate Director in our Hong Kong Operations.\n\nThe successful candidate will work serve as an AML Compliance Officer (\u201cAMLCO\u201d), Money Laundering Reporting Officer (\u201cMLRO\u201d) and/or Deputy MLRO (\u201cDMLRO\u201d) for a diverse portfolio of Cayman Islands funds. Fund clients will include hedge funds, funds of funds, private equity funds, private credit funds and real estate funds with a broad range of investment strategies, managed by investment advisors located primarily in the Asia-Pacific region.\n\nWaystone is a place where talented people are empowered to steer their careers towards greatness. We dare employees to become the best at what they do in a field they love. When they rise to that challenge, great business happens.\n\nESSENTIAL DUTIES AND RESPONSIBILITIES\n\nTake on appointments as AMLCO, MLRO and/or DMLRO for a diverse portfolio of Cayman Islands funds.\nOversee clients\u2019 AML compliance programs, to ensure that systems and controls are developed and maintained in line with Cayman Islands\u2019 Anti-Money Laundering Regulations and relevant legislation.\nOversee regular audits of clients\u2019 AML compliance programs.\nReport periodically to clients\u2019 boards of directors on the adequacy of the AML systems and controls, including key findings and recommendations.\nMonitor the Money Laundering Reporting functions for each client.\nCommunicate with clients to resolve any potential AML issues.\nAssist in the supervision and monitoring of each Waystone employee who acts in a supporting role to the AMLCO, MLRO and/or DMLRO (with respect to performance of those roles).\nDevelop and maintain detailed knowledge of Waystone operations and the regulatory implications thereof.\nTrack laws, regulations and best practices that might affect Waystone & Waystone client services.\nProvide expert advice and assist in transformation projects and in the implementation of best practices.\nCoordinate with Waystone's internal Compliance Department and manage project tasks as appropriate as directed by the Executive Director.\nCarry out duties with minimal oversight.\nDevelop, organize, and/or deliver consistent AML compliance related training.\nManage ad hoc projects in the Cayman Compliance Services function.\nMaintain a high standard in the performance of daily duties and escalate concerns to the Executive Director on a timely basis.\n\nREQUIREMENTS\n\n\nTo perform this job successfully, an individual must be able to perform each essential duty satisfactorily. The requirements listed below are representative of the knowledge, skill, and/or ability required. Reasonable accommodations may be made to enable individuals with disabilities to perform the essential functions.\n\nEducation:\n\nAn internationally recognized professional qualification.\nExperience:\n\nMinimum of 7-10 years of relevant experience in compliance, governance, risk, financial or consulting roles in the financial services sector.\nKnowledge of the Cayman Islands AML regulatory framework would be beneficial.\nExcellent interpersonal and communication skills, both written and verbal.\nProficient in English, Mandarin and Cantonese.\nStrong leadership and organizational skills.\nPrior Cayman Islands AML compliance experience would be an asset.", "employment_types": ["Full Time"], "selling_points": [], "locations": ["Central"], "categories": ["Banking / Finance", "Fund Management", "Risk Management", "Asset Management"], "post_time": "2022-01-07T10:37:20Z", "salary": {"currency": null, "max": null, "min": null, "period": "monthly", "term": null}, "salary_visible": false, "title_keywords": ["associate director"], "responsibilities": ["regulations", "reporting", "communicate with", "aml", "operations", "compliance", "systems", "monitor", "monitoring", "relevant legislation", "develop", "expert advice", "implementation", "maintain", "coordinate with", "ad hoc projects", "audits", "report"], "requirements": {"degrees": [], "majors": [], "languages": ["cantonese", "english", "mandarin"], "language_level": ["proficient"], "hard_skills": ["aml"], "soft_skills": ["communication skills", "leadership", "interpersonal", "organizational skills"], "languages_combined": [{"language": "cantonese", "language_level": ["proficient"]}, {"language": "english", "language_level": ["proficient"]}, {"language": "mandarin", "language_level": ["proficient"]}]}, "experience_required": {"duration": ["minimum of 7-10 years"], "field": ["consulting", "compliance", "financial services", "relevant experience", "financial"]}}, {"job_id": "100003009026135", "location_code": "hk", "company": "Page Personnel", "job_title": "Investment Operation Analyst - Private Investment Office", "description": "Our client is looking for a candidate with hedge fund operations background to support the investment and business operations in the team including but not limited to client portfolio system maintenance, client reporting and trade processing (trade reconciliation and settlement).\n\nClient Details\n\nOur client is a multifamily office with a focus on investment and services (Hedge fund, Fund of PE funds, Cayman funds) to their investors.\n\nDescription\n\nPerform trade reconciliation and settlement in a timely and accurate manner\nConduct regular portfolio data updates on internal system\nAssist portfolio manager in monitoring and managing daily portfolio asset allocations and risk exposures\nPrepare monthly portfolios reports/reviews for investors\nSupport the set up and maintenance of investment vehicles\nReview existing workflows periodically and provide recommendations on process enhancement\n\nProfile\n\nAt least 2-3 years experience in Hedge Fund operations/ fund services provider or relevant experience\nBachelor degree or above in related disciplines\nGood command of written and spoken in English and Mandarin\nDetail-oriented, ability to multi-task and meet deadlines\nOpen-minded, energetic and a good team player\nDriven with proactive learning attitude\n\nJob Offer\n\nYoung and energetic vibes\nModern multifamily office with investment innovative\nSteep learning curve\nExposure to multiple funds\nAttractive yearend bonus\n\nTo apply online please click the Apply button below. For a confidential discussion about this role please contact Mandy Wong on 3602 2411", "employment_types": ["Full Time", "Permanent"], "selling_points": ["Hedge Fund experience preferred", "Investment and Servicing focus", "Young and energetic culture"], "locations": ["Not Specified"], "categories": ["Banking / Finance", "Fund Management", "Order Processing & Operation / Settlement"], "post_time": "2022-01-06T07:24:31Z", "salary": {"currency": "HKD", "max": 34999, "min": 25000, "period": "monthly", "term": null}, "salary_visible": true, "title_keywords": ["analyst"], "responsibilities": ["reporting", "maintenance", "data", "operations", "monitoring", "review", "reports", "provide recommendations", "contact"], "requirements": {"degrees": ["degree or above", "bachelor"], "majors": ["related disciplines"], "languages": ["english", "mandarin"], "language_level": ["good command"], "hard_skills": ["focus", "processing", "pe", "maintenance"], "soft_skills": ["good team player", "proactive", "multi-task", "open-minded", "timely", "detail-oriented", "innovative", "energetic", "learning", "focus", "accurate", "meet deadlines", "driven"], "languages_combined": [{"language": "english", "language_level": ["good command"]}, {"language": "mandarin", "language_level": ["good command"]}]}, "experience_required": {"duration": ["at least 2-3 years"], "field": ["fund services", "relevant experience"]}}, {"job_id": "100003009019508", "location_code": "hk", "company": "Ever Fame (Hong Kong) Limited", "job_title": "Fund Management Assistant \u57fa\u91d1\u6295\u8cc7\u7d93\u7406/\u52a9\u7406", "description": "\u8077\u4f4d\u8077\u8cac\uff1a\n\n\u5b8c\u6210\u5ba2\u6236\u5c0d\u57fa\u91d1\u7684\u5206\u6790\u548c\u7814\u7a76\u5831\u544a\n\u8ddf\u8e64\u57fa\u91d1\u6295\u8cc7\u7684\u696d\u5167\u653f\u7b56\u53ca\u7522\u54c1\u52d5\u614b\uff0c\u5e7e\u6642\u8ddf\u9032\n\u5b8c\u6210\u6295\u8cc7\u53ef\u884c\u6027\u5206\u6790\uff0c\u64ec\u5b9a\u6295\u8cc7\u8a08\u5283\u65b9\u6848\n\u5354\u52a9\u516c\u53f8\u9818\u5c0e\u5be6\u65bd\u6295\u8cc7\u8a08\u5283\n\u8f14\u52a9\u5b8c\u6210\u6295\u8cc7\u9805\u76ee\u641c\u5c0b\u3001\u7be9\u9078\u548c\u5132\u5099\uff0c\u5e76\u5c0d\u6295\u8cc7\u76ee\u6a19\u9032\u884c\u521d\u6b65\u6e9d\n\n\u4efb\u8077\u8981\u6c42\uff1a\n\n\u7ba1\u7406\uff0c\u91d1\u878d\uff0c\u8ca1\u52d9\u7ba1\u7406\u76f8\u95dc\u5c08\u696d\u672c\u79d1\u53ca\u4ee5\u4e0a\u5b78\u6b77\uff0c\u6b61\u8fce\u60f3\u9032\u5165\u91d1\u878d\u884c\u696d\u4f46\u6c92\u6709\u884c\u696d\u80cc\u666f\u7684\u7cbe\u82f1\uff0c\u53ef\u4ee5\u4efb\u8077\u6295\u8cc7\u52a9\u7406\u53ca\u57f9\u8a13\u751f\u3002\n\u6709\u76f8\u95dc\u5de5\u4f5c\u7d93\u9a57\n\u6b61\u8fce\u61c9\u5c46\u7562\u696d\u751f\u548cIANG VISA \u6301\u6709\u8005\n\u826f\u597d\u7684\u6587\u5b57\u548c\u53e3\u982d\u8868\u9054\uff0c\u512a\u79c0\u7684\u6e9d\u901a\u80fd\u529b\uff0c\u8ac7\u5224\u80fd\u529b\u548c\u89aa\u548c\u529b\n\u8f03\u5f37\u7684\u7cfb\u7d71\u601d\u7dad\u80fd\u529b\u548c\u5224\u65b7\u529b\uff0c\u5177\u6709\u98a8\u96aa\u610f\u8b58\u548c\u98a8\u96aa\u63a7\u5236\u80fd\u529b", "employment_types": ["Full Time"], "selling_points": [], "locations": ["Wan Chai"], "categories": ["Banking / Finance", "Fund Management"], "post_time": "2022-01-04T07:48:15Z", "salary": {"currency": null, "max": null, "min": null, "period": "monthly", "term": null}, "salary_visible": false, "title_keywords": ["\u52a9\u7406", "assistant"], "responsibilities": [], "requirements": {"degrees": [], "majors": [], "languages": [], "language_level": [], "hard_skills": [], "soft_skills": [], "languages_combined": []}, "experience_required": {"duration": [], "field": []}}, {"job_id": "100003009025606", "location_code": "hk", "company": "Shanghai Pudong Development Bank Co., Ltd., Hong Kong Branch", "job_title": "Manager / Asst Manager, Client Servicing, Custody Team (Ref.:CV_FID_CBDM_202201)", "description": "Responsibilities:\n\n\u00a0Advise client for documentation and on-boarding requirements\n\u00a0Process account opening and mange a smooth client onboarding\n\u00a0Control, review and liaise with relevant parties independently on account documentations\n\u00a0Handle client inquiry in relation to cash movement, security settlement, Corporate actions, billing\n\u00a0Engage in projects in business development for new products, new services, system enhancement\n\nRequirements:\n\nUniversity graduate with at least\u00a05 years of experience in custody business\nFamiliar with QDII, QFII, stock connect, bond connect products\nGood knowledge of securities market\nStrong analytical skill, self-motivated and independent\nTeam player with good interpersonal and communication skills\nGood command of spoken and written Chinese and English, fluent Putonghua\nProficient in MS office applications including Power Points\n\nPlease quote the Reference No.: CV_FID_CBDM_202201 in your application.\n\nOur Bank offers attractive remuneration package to chosen candidates. Interested parties please apply with full resume stating expected salary and contact phone number via Apply Now.\n\nAll applications will be treated in the strictest confidence and personal data collected will be used for recruitment purpose only.", "employment_types": ["Full Time", "Permanent"], "selling_points": ["Develop professional knowledge in custody", "Excellent career path in growing platform", "Bonus, medical plan, staff canteen facility, etc."], "locations": ["Wan Chai"], "categories": ["Banking / Finance", "Fund Management", "Others"], "post_time": "2022-01-06T16:08:05Z", "salary": {"currency": null, "max": null, "min": null, "period": "monthly", "term": null}, "salary_visible": false, "title_keywords": ["asst manager", "manager"], "responsibilities": ["control", "account opening", "review", "liaise with", "documentation"], "requirements": {"degrees": ["university graduate"], "majors": ["business"], "languages": ["putonghua", "english", "chinese"], "language_level": ["good command", "fluent"], "hard_skills": ["qfii", "no", "analytical skill", "qdii", "ms office"], "soft_skills": ["communication skills", "analytical skill", "self-motivated", "independent", "team player", "interpersonal"], "languages_combined": [{"language": "putonghua", "language_level": ["fluent", "good command"]}, {"language": "english", "language_level": ["good command"]}, {"language": "chinese", "language_level": ["good command"]}]}, "experience_required": {"duration": ["at least 5 years"], "field": ["custody", "business"]}}, {"job_id": "100003009033345", "location_code": "hk", "company": "Antnergy Social Resources", "job_title": "Investment Consultant (Fresh Grad welcome) (18-30k+, 5 days)", "description": "The employer is\u00a0a licensed investment adviser with the Securities and Futures Commission (CE No. AFG549). They offer\u00a0you high quality financial advice from a dedicated adviser and a robust financial plan that will change as you do. You also have a team of dedicated experts scouring the globe for the right products for you, monitoring any market developments and making sure you stay on track to reach your goals.\n\nIn this position, you will:\n\nReceive training in various areas and monitor performance progress with management and key trainers\nUtilize your already gained Excel skills or learn new tricks to provide analytical and administrative support such as updating database, conducting analyses, and maintaining records\nMeet up with corporate and individual clients regularly, establish and maintain strong client relationship\nRespond quickly and effectively to client requests\u00a0relating to their financial needs\nLearn management viewpoints and company policies and practices affecting each phase of business\nSkills & Qualifications:\nRecognized degree in Business, Finance or related professional qualification\nStrong desire to learn more and develop yourself\nGreat problem solving skills and solution-oriented mindset\nConfident user skills in Microsoft Office applications, especially Excel\n\nBenefits:\n\nExciting, inspiring atmosphere\nHealth insurance\nProfessional development reimbursement\nComprehensive orientation program followed by ongoing support and training\nExcellent career prospects and opportunities to grow your expertise\u00a0and\u00a0take on new challenges and reinvent yourself\n\nOur\u00a0client will also accept graduates without the necessary experience as long as they have the right attitude.", "employment_types": ["Full Time", "Permanent", "Contract"], "selling_points": ["International colleagues, multiple cultures", "Fast Track promoting to management in 1-2 years", "15 days annual + public holiday,work life balance"], "locations": ["Causeway Bay"], "categories": ["Banking / Finance", "Fund Management", "Sales, CS & Business Devpt", "Customer Service - Supervisor / Officer", "Management", "Management Trainee"], "post_time": "2022-01-09T10:27:29Z", "salary": {"currency": null, "max": null, "min": null, "period": "monthly", "term": null}, "salary_visible": false, "title_keywords": ["investment consultant"], "responsibilities": ["management", "maintaining", "administrative support", "monitor performance", "policies", "monitoring", "quality", "develop", "maintain", "plan", "database"], "requirements": {"degrees": ["degree"], "majors": ["finance", "business"], "languages": [], "language_level": [], "hard_skills": ["excel", "no", "problem solving skills", "microsoft office"], "soft_skills": ["confident", "problem solving skills", "robust"], "languages_combined": []}, "experience_required": {"duration": [], "field": []}}, {"job_id": "100003009030190", "location_code": "hk", "company": "OnePlatform Asset Management Limited", "job_title": "Senior Officer, Investment Operations (Funds)", "description": "Due to our business expansion, we are looking for high calibre candidates to share our vision and venture our success.\n\n\n\nResponsibilities:\n\nSupport the daily dealing activities of mutual funds including subscription, redemption, dividend payment, share transfer and etc.\nAssist in reviewing the account opening, KYC/AML documents\nMonitor daily trade settlement of funds, daily matching report, corporate action and unsettled deals\nExecute day-end procedures, handle reconciliation and ensure data capture accuracy and completeness\nAdhere to the operating procedures and agreed services standard, and comply with internal guidelines and external regulatory requirements\nParticipate in UAT for system enhancement and other ad-hoc projects\nProvide support to the team whenever necessary\n\nRequirements:\n\nDegree holder in Business, Finance, Investment or related disciplines\nAt least 5 years in financial industries or with related working experience\nSelf-motivated, good communication and presentation skills\nA good team player\nGood command of both spoken and written English and Chinese\nProficient in MS Office applications\nWe offer competitive remuneration including career prospects to the right candidate. Interested parties please send detailed resume with availability, current and expected salaries to\u00a0Human Resources Department, OnePlatform Asset Management Limited, Trust Tower, 68 Johnston Road, Wan Chai, Hong Kong\u00a0or by clicking the\u00a0Apply Now\u00a0button and upload your CV and cover letter.\n(All applications will be treated in strict confidence and used for recruitment purpose within OnePlatform Asset Management Limited only. All applicants are kept on file 6 months from the date of the application.)", "employment_types": ["Full Time", "Permanent"], "selling_points": ["Support daily dealing activities of mutual funds", "Review the account opening, KYC/AML documents", "Monitor daily trade settlement of funds"], "locations": ["Wan Chai"], "categories": ["Banking / Finance", "Investment", "Financial Services", "Fund Management"], "post_time": "2022-01-07T06:56:37Z", "salary": {"currency": null, "max": null, "min": null, "period": "monthly", "term": null}, "salary_visible": false, "title_keywords": ["senior officer", "operations"], "responsibilities": ["provide support", "aml", "uat", "data", "guidelines", "account opening", "regulatory requirements", "monitor", "procedures", "payment", "kyc", "ad-hoc projects", "report"], "requirements": {"degrees": ["degree holder"], "majors": ["related disciplines", "finance", "business"], "languages": ["english", "chinese"], "language_level": ["good command"], "hard_skills": ["ms office"], "soft_skills": ["communication", "good team player", "self-motivated", "presentation skills"], "languages_combined": [{"language": "english", "language_level": ["good command"]}, {"language": "chinese", "language_level": ["good command"]}]}, "experience_required": {"duration": ["at least 5 years"], "field": ["related", "financial"]}}, {"job_id": "100003009023978", "location_code": "hk", "company": "Bosera Asset Management (International) Co., Limited", "job_title": "Operations Intern", "description": "Job descriptions:\n\nSupport for performing the daily operations work, such as cash & security holding reconciliation, preparing cash forecast reporting;\nMonitor the completeness of daily trade execution and matching performed by back office team;\nLiaise with fund administrators, custodians and prime brokers on a daily basis;\nParticipate in new fund launch;\nClose communication with internal departments, such as Legal & Compliance, Sales & Marketing etc;\nProvide support to senior management for new project implementation.\n\nRequirements:\n\nBachelor degree or above, major in finance, economics etc. preferred\nGood team spirit, strong sense of responsibility, and willing to learn\nAbility to pay attention to details and documents", "employment_types": ["Internship"], "selling_points": [], "locations": ["Central"], "categories": ["Banking / Finance", "Fund Management", "Asset Management"], "post_time": "2022-01-05T10:13:09Z", "salary": {"currency": null, "max": null, "min": null, "period": "monthly", "term": null}, "salary_visible": false, "title_keywords": ["operations", "intern"], "responsibilities": ["reporting", "provide support", "prime brokers", "compliance", "monitor", "back office", "implementation", "communication", "daily operations", "forecast", "liaise with", "senior management"], "requirements": {"degrees": ["degree or above", "bachelor"], "majors": ["finance", "economics"], "languages": [], "language_level": [], "hard_skills": [], "soft_skills": ["team spirit", "willing to learn", "attention to details", "sense of responsibility"], "languages_combined": []}, "experience_required": {"duration": [], "field": []}}, {"job_id": "100003009021693", "location_code": "hk", "company": "Osmium Consulting Group Limited", "job_title": "Operations Manager ( Hedge Fund )", "description": "Job Description:\n\nLiaise among different service providers, including but not limited to fund administrator, prime brokers, and other counter parties to resolve any day-to-day operational related matters.\nPerform trade settlements, NAV calculations, cash reconciliations, portfolio compositions and other day-to-day operations tasks.\u00a0\nLiaise among fund administrator, prime brokers, and auditors to perform fund audit and assist in preparing the financials for the asset management company.\nHelp prepare regular reports and filings to regulatory entities.\nHelp process investor subscriptions, redemptions, and KYC/DD procedures.\nHelp prepare investor presentation and monthly newsletter among other ad-hoc tasks.\n\n\u00a0Qualifications:\n\nIndependent, self-motivative, detail oriented, able to multi-task and set priority, with strong integrity and keen to finishing work with no delay\nEntrepreneur mind set and strong sense of ownership\n3-5 years\u2019 experience in buy side operations and ideally with hedge fund experience\nProficiency in English and Mandarin is highly preferred\nCollege degree in accounting / finance, and CPA would be a plus\n\nCompany Background\n\nWe are a Cayman Islands macro hedge fund running with a small team and strong investing capabilities and stable LP base of USD $100mn+ asset under management. We offer attractive compensation package with excellent opportunities for future career development.", "employment_types": ["Full Time", "Permanent"], "selling_points": ["Hedge Fund Operations Manager", "3-5 years of relevant experience", "Attractive Package"], "locations": ["Central & Western Area"], "categories": ["Banking / Finance", "Financial Services", "Fund Management", "Asset Management"], "post_time": "2022-01-05T04:25:54Z", "salary": {"currency": null, "max": null, "min": null, "period": "monthly", "term": null}, "salary_visible": false, "title_keywords": ["operations manager"], "responsibilities": ["liaise", "management", "prime brokers", "operations", "ad-hoc tasks", "day-to-day operations", "audit", "procedures", "reconciliations", "reports", "kyc", "asset management"], "requirements": {"degrees": ["degree"], "majors": ["finance", "accounting"], "languages": ["english", "mandarin"], "language_level": ["proficiency"], "hard_skills": ["small", "no", "plus", "macro", "cpa", "kyc"], "soft_skills": ["independent", "multi-task", "keen", "detail oriented", "integrity", "stable", "presentation"], "languages_combined": [{"language": "english", "language_level": ["proficiency"]}, {"language": "mandarin", "language_level": ["proficiency"]}]}, "experience_required": {"duration": ["3-5 years"], "field": []}}, {"job_id": "100003009021071", "location_code": "hk", "company": "Hang Tang International Capital Management Limited", "job_title": "Product Development Manger (Fund / FoF)", "description": "Responsibilities\n\nWork closely with investment team and sales team to develop and launch fund products and onboarding third party fund products\nConduct issuer and product due diligence for new/existing products\nMonitor the market trend and conduct product reviews regularly\nLiaise with lawyers, custodians and fund administrators in setting up new funds\nProvide support to ad hoc projects as assigned\n\nRequirements\n\nDegree holder with major in Business Administration or related disciplines\n3 years of experience in investment product development and/or fund due diligence and selection (Cayman private fund and other offshore fund structure)\nAbility to work independently\nExcellent presentation and negotiation skills\nGood knowledge of financial markets and products\nGood command of both verbal and written English and Chinese. Fluent in Mandarin a must", "employment_types": ["Full Time"], "selling_points": ["-", "-", "-"], "locations": ["Central"], "categories": ["Banking / Finance", "Fund Management", "Wealth Management", "Asset Management"], "post_time": "2022-01-05T02:59:57Z", "salary": {"currency": null, "max": null, "min": null, "period": "monthly", "term": null}, "salary_visible": false, "title_keywords": ["product development"], "responsibilities": ["provide support", "product due diligence", "monitor", "develop", "sales team", "ad hoc projects", "liaise with", "third party"], "requirements": {"degrees": ["degree holder"], "majors": ["related disciplines", "business administration"], "languages": ["english", "chinese", "mandarin"], "language_level": ["good command", "fluent"], "hard_skills": [], "soft_skills": ["work independently", "negotiation skills", "presentation"], "languages_combined": [{"language": "english", "language_level": ["good command"]}, {"language": "chinese", "language_level": ["good command"]}, {"language": "mandarin", "language_level": ["fluent"]}]}, "experience_required": {"duration": ["3 years"], "field": ["product development", "investment"]}}, {"job_id": "100003009023234", "location_code": "hk", "company": "Realord Asia Pacific Securities Limited", "job_title": "Research Analyst", "description": "Job Description\n\nConduct research and analysis of industries/stocks, especially IPO listed in HK\nAnalyze economic data and trends in China and Hong Kong using mathematical models and statistical techniques\nCompile daily stock commentary, research reports, publications, presentations, periodic reports and other materials to provide supportive information\nProvide research services to institutional, corporate and high net-worth clients\nUndertake investment research under supervision of the management\nParticipate in market activities including roadshows and investment forums\nHandle ad-hoc projects as assigned\n\nJob Requirements\n\nBachelor degree or above in Finance, Economics, Accounting or related disciplines\nHolder of SFC Type 4 licence and at least 2 years equity research experience with a focus in China and Hong Kong market\nOutstanding analytical skills with good grasp of statistics, and familiarity with global and regional economies\nStrong conceptual and critical thinking skills, able to identify and access key issues rather than simply filtering and reprocessing information\nSelf-motivated, responsible and able to work independently under pressure and tight deadlines\nExcellent interpersonal and communication skills\nFamiliar with MS Excel Marco, PowerPoint and experience in handling Bloomberg is an advantage\nExcellent command of written and spoken English and Chinese(including Mandarin)\n\n\n\nWe offer attractive remuneration and benefits to the right candidates. Interested parties, please send your application with full resume stating your CURRENT and EXPECTED salary\u00a0by email or click \"APPLY Now\".\n\nAll information collected will be kept in strictly confidential and will be used for recruitment purpose only.", "employment_types": ["Full Time"], "selling_points": ["Equity research", "At least 2 years of research experience", "IANG Holder is also welcome"], "locations": ["Central"], "categories": ["Banking / Finance", "Analyst", "Fund Management", "Others"], "post_time": "2022-01-05T07:51:47Z", "salary": {"currency": null, "max": null, "min": null, "period": "monthly", "term": null}, "salary_visible": false, "title_keywords": ["research analyst"], "responsibilities": ["management", "data", "analysis", "presentations", "reports", "ad-hoc projects", "conduct research"], "requirements": {"degrees": ["degree or above", "bachelor"], "majors": ["related disciplines", "finance", "economics", "accounting"], "languages": ["english", "mandarin"], "language_level": ["excellent"], "hard_skills": ["bloomberg", "powerpoint", "analytical skills", "marco", "ms excel", "focus"], "soft_skills": ["communication skills", "work independently", "self-motivated", "under pressure", "responsible", "analytical skills", "focus", "interpersonal"], "languages_combined": [{"language": "english", "language_level": ["excellent"]}, {"language": "mandarin", "language_level": ["excellent"]}]}, "experience_required": {"duration": ["at least 2 years"], "field": ["equity research"]}}, {"job_id": "100003009025821", "location_code": "hk", "company": "Bank of Communications Trustee Limited", "job_title": "Administrator, Custodian Administration", "description": "Responsibilities:\n\nReview and coordinate documentation in relation to corporate trust such as bond trustee, escrow agent and fund custodian related services (private fund or authorized fund)\nCommunicate with stakeholders for the follow up of documentation and administration matters on both new and existing cases\nPerform ad-hoc assignments as required\n\nRequirements:\n\nDiploma in corporate governance, Law or related disciplines\n1 year relevant experience in custodian administration\nProficient in both spoken and written English and Chinese, Putonghua a plus\nProficient in MS office application\nImmediately available is highly preferred\nFresh graduates are welcome\nPlease click \"Apply Now\" to submit your application.\nPersonal data collected will be used for recruitment purpose only.", "employment_types": ["Full Time", "Permanent"], "selling_points": ["Review and coordinate documentation in relation", "Diploma in corporate governance, Law", "1 year relevant experience in custodian adm"], "locations": ["Not Specified"], "categories": ["Banking / Finance", "Financial Services", "Fund Management", "Professional Services", "Legal & Compliance"], "post_time": "2022-01-06T06:33:44Z", "salary": {"currency": null, "max": null, "min": null, "period": "monthly", "term": null}, "salary_visible": false, "title_keywords": ["administrator"], "responsibilities": ["communicate with", "ad-hoc assignments", "review", "coordinate", "documentation", "administration"], "requirements": {"degrees": ["diploma"], "majors": ["related disciplines", "law"], "languages": ["putonghua", "english", "chinese"], "language_level": ["proficient"], "hard_skills": ["plus", "ms office"], "soft_skills": [], "languages_combined": [{"language": "putonghua", "language_level": ["proficient"]}, {"language": "english", "language_level": ["proficient"]}, {"language": "chinese", "language_level": ["proficient"]}]}, "experience_required": {"duration": ["1 year"], "field": ["relevant experience", "administration"]}}, {"job_id": "100003009023686", "location_code": "hk", "company": "Morgan McKinley", "job_title": "Credit Analyst, 3-6 years (Buy-side, Chinese Speaking)", "description": "My client is a Chinese Asset Management looking for a seasoned Credit Analyst for their Fixed Income Investment team.\n\nJob Responsibilities:\n\n-Conduct credit analysis research for both HY and IG USD Bonds portfolios.\n\n-Recommendations to portfolio managers in Bonds selections, returns improvements, asset allocations.\n\n-Perform due diligence and financial analysis on variety of companies\n\nJob Requirements:\n\n-Minimum 3 years working as Credit Analyst or Fixed income investment analyst\n\n-Familiar with Chinese USD Bonds\n\n-Fluent in Chinese and English", "employment_types": ["Full Time", "Permanent"], "selling_points": ["Asset Management", "Credit of Property", "3-6 years within Credit Analyst from buyside"], "locations": ["Not Specified"], "categories": ["Banking / Finance", "Analyst", "Investment", "Fund Management"], "post_time": "2022-01-05T09:29:32Z", "salary": {"currency": null, "max": null, "min": null, "period": "monthly", "term": null}, "salary_visible": false, "title_keywords": ["credit analyst"], "responsibilities": ["financial analysis", "due diligence", "analysis"], "requirements": {"degrees": [], "majors": [], "languages": ["english", "chinese"], "language_level": [], "hard_skills": [], "soft_skills": [], "languages_combined": [{"language": "english", "language_level": []}, {"language": "chinese", "language_level": []}]}, "experience_required": {"duration": [], "field": []}}, {"job_id": "100003009033092", "location_code": "hk", "company": "AXA China Region Insurance Company Limited", "job_title": "MPF Customer Service Officer (5 days work)", "description": "Career with a Difference\n\nWe offer flexible working hours, comprehensive training and excellent career development opportunities.\n\nWe deliver professional MPF services and retirement planning to our clients. Working in our young and joyful international team including native Cantonese and English speakers, we respect every teammate and have equal opportunities. Want a dynamic career with a difference? Come and join us!\n\n\u00a0Core responsibilities:\u00a0\n\nProvide professional MPF service to every individual client for their purposes of wealth management, retirement plan and investment\nProvide corporate benefits to company accounts like MPF schemes, Group Medical Plans and General Business Insurance\nManage relationships with individual clients and corporate accounts\nHandle incoming inquiries from scheme members\nEnjoy our benefits:\n\nClient Base provided\u00a0\nFlexible working hours\u00a0\nMonthly salary ranging from HK$16,000 to $25,000\nQuarterly Bonus and Year End Bonus\nInitial training and On-Job training provided\nTransparent Career Path to Management Level\nLife and Medical Insurance\nAs a MPF service officer, you should possess the following qualities:\n\nDegree or Diploma holders would be preferred\nFluent in Cantonese, English, and Mandarin as an advantage\nStrong interpersonal and communication skills with the ability to manage client relationships\nProactive, self-motivated, and customer-oriented\nResponsible team player with strong desire for success\nHKID card holder is a MUST\nFresh graduates would also be considered\n\nWe offer attractive benefits packages and excellent career development opportunities.\u00a0 Please mention your expected salary and the earliest availability in the resume.", "employment_types": ["Full Time"], "selling_points": ["Flexible working hours", "Year end bonus", "Transparent career path"], "locations": ["Tsim Sha Tsui"], "categories": ["Banking / Finance", "Retail Banking", "Fund Management", "Sales, CS & Business Devpt", "Customer Service - Supervisor / Officer"], "post_time": "2022-01-08T08:15:30Z", "salary": {"currency": "HKD", "max": 24999, "min": 17000, "period": "monthly", "term": null}, "salary_visible": true, "title_keywords": ["customer service officer"], "responsibilities": [], "requirements": {"degrees": [], "majors": [], "languages": [], "language_level": [], "hard_skills": [], "soft_skills": [], "languages_combined": []}, "experience_required": {"duration": [], "field": []}}, {"job_id": "100003009031784", "location_code": "hk", "company": "Newbit Fiduciary Services (Hong Kong) Limited", "job_title": "Head / Senior Manager of Fund Accounting", "description": "Newbit Fiduciary Services (Hong Kong) Limited is an independent fund administrator to provide fully integrated services, including fund launch support, central fund administration solution, transfer agency services and shadow NAV assistance.\n\nWith well consideration of data privacy and global standards of fund administration procedures, Newbit drives our business with high-end technology to meet our clients\u2019 needs and provides reports in both Chinese and English languages. Newbit becomes the first fund administrator to provide both web-based client portal and mobile APP platform.\n\nOur team are expanding, we are currently looking for a Head / Senior Manager of Fund Accounting.\n\nAs a Head / Senior Manager of Fund Accounting, you will:\n\nGuide and supervise junior staff to complete their work, including Net Asset Value calculations (\u201cNAV\u201d) and ad hoc reports.\nAct as major point of contact of your clients, capable of planning ahead timeline, identifying & anticipating issues and suggesting possible solutions\nCoordinate with client and Compliance Team to complete client onboarding and ongoing review.\nParticipate in fund operations related projects, such as system deployment and enhancement of policies & procedures\nTimely Report to senior management\n\n\u00a0It would be great if you are/have:\n\nBachelor Degree in Finance, Accounting or related disciplines\nQualified accountant, Member HKICPA or equivalent\nAt least 7 years\u2019 relevant experience (preferably in fund administrators, fund house or audit firm etc.)\nKnowledge of Paxus is preferred\nA good team player and able to work independently\nFluent in spoken and written Chinese and English\n\nYour application shall contain your resume stating your current & expected salary.\n\nYour application will go through severe screening & consideration; only qualified candidates will be contacted within two weeks after application.\n\nAll personal data collected will be strictly prohibited for recruitment purposes only; personal data of unsuccessful candidates will be destroyed within 12 months after the date of application.", "employment_types": ["Full Time", "Permanent"], "selling_points": ["Work life balance", "Excellent career path", "2mins next to MTR station"], "locations": ["Not Specified"], "categories": ["Banking / Finance", "Financial Services", "Fund Management"], "post_time": "2022-01-07T09:45:49Z", "salary": {"currency": null, "max": null, "min": null, "period": "monthly", "term": null}, "salary_visible": false, "title_keywords": ["senior manager", "accounting"], "responsibilities": ["data", "operations", "audit", "personal data", "senior management", "administration", "mobile app", "ad hoc", "compliance", "reports", "report", "review", "coordinate with", "procedures", "contact", "policies", "administration procedures", "recruitment", "planning"], "requirements": {"degrees": ["degree", "bachelor"], "majors": ["related disciplines", "finance", "accounting"], "languages": ["english", "chinese"], "language_level": ["fluent"], "hard_skills": ["web", "mobile", "deployment", "go", "hkicpa"], "soft_skills": ["good team player", "work independently", "independent", "capable", "timely"], "languages_combined": [{"language": "english", "language_level": ["fluent"]}, {"language": "chinese", "language_level": ["fluent"]}]}, "experience_required": {"duration": ["at least 7 years"], "field": ["relevant experience", "audit"]}}, {"job_id": "100003009024556", "location_code": "hk", "company": "OP Investment Management Ltd.", "job_title": "Capital Introduction Associate / Senior Associate", "description": "OPIM is now accepting applications for the position of Capital Introduction Associate / Senior Associate. This is a challenging but rewarding role in a fast-paced collaborative environment. Reporting directly to the CEO and the Head of IR, you will work with the front office team to promote strategies targeting institutional allocators, corporate allocators and distributors globally.\u00a0\n\nYour work experience in fund management and confident communication skills, a strong command of English, and affinity for helping allocators will be advantageous. You will be involving frequent client meetings/calls in which analysts assist in preparation, participation, and follow-up. Heavy in-person, phone, and e-mail interaction with hedge fund clients and allocators.\u00a0\n\nResponsibilities:\u00a0\n\nProspecting for new managers and allocators;\nConducting introductory calls, coordinating and hosting new prospective allocator meetings;\nAssisting in planning and execution of a range of client conferences and events, including overnight calls;\u00a0\nMaintaining existing allocator relationships;\nWork with the team to craft a consistent message of investment strategy;\nPreparing overview materials on individual hedge fund and investor firm;\nAssisting in preparing standard documents such as pitch books, investor reports, and due diligence documentation when required;\u00a0\nAnalyze data on the hedge fund industry and summarize key trends and themes by creating content that is distributed to allocators on a quarterly basis;\u00a0\nLiaising with media channels to issue press releases of new launches and critical events;\u00a0\nCoordinating with global databases and uploading fund performance;\u00a0\nUpdating internal Salesforce CRM for client and allocator data;\nNetworking and attending industry conferences; and\nCoordinating ad hoc investor requests.\nRequirements:\n\nBachelor\u2019s degree or above;\u00a0\nUp to 4 years of relevant experience (e.g, capital introduction, marketing, investor relations, allocator role, hedge fund sales);\u00a0\nSelf-starter with excellent attention to detail and exemplary problem-solving abilities;\nExceptional interpersonal skills;\u00a0\nEnergetic, efficient, and resourceful team player and individual contributor;\nDetail-oriented and able to multitask, meet deadlines, and adjust to changing priorities;\nDemonstrated comfort with presenting in front of both small and large groups;\nProficient computer skills including Microsoft Office suite, particularly Microsoft Excel and PowerPoint (high-level Excel and PowerPoint skills required, including experience with developing charts, pivot tables, and complex formulas);\nProject Management experience is preferred; and\nFluent in spoken English, Mandarin and Cantonese.\n\nPlease apply in confidence with full resume stating your recent and expected salary to the HR Manager Ms. Carmen Lau, 9/F, The Wellington, 198 Wellington Street, Central, Hong Kong (Data collect would be used for recruitment purpose only).\n\n\nApplicants who do not receive a substantive reply within two months may assume their applications unsuccessful.\u00a0\n\nwww.opim.com.hk\u00a0\n", "employment_types": ["Full Time", "Permanent"], "selling_points": ["Assisting in preparing reports and pitch books", "Analyze data on the hedge fund industry", "Liaising with media to issue press release"], "locations": ["Sheung Wan"], "categories": ["Banking / Finance", "Fund Management", "Asset Management"], "post_time": "2022-01-06T01:43:27Z", "salary": {"currency": null, "max": null, "min": null, "period": "monthly", "term": null}, "salary_visible": false, "title_keywords": ["senior associate", "associate"], "responsibilities": ["due diligence", "ad hoc", "maintaining", "data", "liaising with", "media channels", "conferences", "reports", "fund performance", "databases", "documentation", "analyze data", "planning"], "requirements": {"degrees": ["degree or above", "bachelor"], "majors": [], "languages": ["cantonese", "english", "mandarin"], "language_level": ["fluent"], "hard_skills": ["small", "excel", "problem-solving", "powerpoint", "microsoft excel", "microsoft office suite", "project management", "computer skills"], "soft_skills": ["efficient", "confidence", "resourceful", "problem-solving", "detail-oriented", "multitask", "project management", "interpersonal skills", "attention to detail", "team player", "energetic", "meet deadlines"], "languages_combined": [{"language": "cantonese", "language_level": ["fluent"]}, {"language": "english", "language_level": ["fluent"]}, {"language": "mandarin", "language_level": ["fluent"]}]}, "experience_required": {"duration": ["4 years"], "field": ["project management", "relevant experience", "developing"]}}, {"job_id": "100003009027258", "location_code": "hk", "company": "Zhongtai Financial International Limited", "job_title": "Asset Management - Product Manager \u8d44\u4ea7\u7ba1\u7406\u90e8 - \u56fa\u6536\u4ea7\u54c1\u7d93\u7406", "description": "Responsibilities:\n\nResearch and structure new product ideas. Familiar with product design procedures, prepare legal documents for fund launching;\nUnderstand the needs of Asset Management market, able to identify product opportunities in the market and matching to targeted customer;\nCoordinate with sales team in presenting on-the-shelf products to distribution channels & targeting customers;\nAssessing feasibility and profitability of various ad hoc investment proposals;\n\nRequirements:\nMinimum 1 years\u2019 experience in finance field, preferable in renowned Asset Management Company;\nExperience with offshore fund market will be an advantage;\nAble to work independently with good problem solving skill and analytical mindset;\nGood team player with excellent communication and interpersonal skills;\nGood command of spoken and written Mandarin and English is a MUST.", "employment_types": ["Full Time"], "selling_points": ["Familiar with product design procedures", "Minimum 1 years\u2019 experience in finance field", "Research and structure new product ideas"], "locations": ["Central"], "categories": ["Banking / Finance", "Treasury", "Fund Management", "Asset Management"], "post_time": "2022-01-06T09:30:07Z", "salary": {"currency": null, "max": null, "min": null, "period": "monthly", "term": null}, "salary_visible": false, "title_keywords": ["product manager", "asset management"], "responsibilities": ["ideas", "ad hoc", "coordinate with", "procedures", "product design", "sales team", "asset management"], "requirements": {"degrees": [], "majors": [], "languages": ["english", "mandarin"], "language_level": ["good command"], "hard_skills": ["problem solving"], "soft_skills": ["good team player", "work independently", "communication and interpersonal skills", "problem solving skill"], "languages_combined": [{"language": "english", "language_level": ["good command"]}, {"language": "mandarin", "language_level": ["good command"]}]}, "experience_required": {"duration": ["minimum 1 years"], "field": ["finance", "asset management"]}}, {"job_id": "100003009029884", "location_code": "hk", "company": "Global Associates", "job_title": "Compliance Officer", "description": "Compliance Officer\n\nOur client is a leading asset management company in Asia Pacific region.\n\nThe job:\n- Report to the Head of Compliance\n- Responsible for launching of new funds, both domestic and public or otherwise\n- Advise Sales, Trading, Operations Management on relevant regulatory and compliance issue\n- Assure the Company at all time is to comply with local laws and regulations\n- Advise management on new laws affecting the asset management business\n- Answer enquiries from regulators.\n\nThe requirements:\n- 5 years experience in compliance in an asset management environment\n- Knowledgeable on fund launch, risk management and post launch procedures and settlement\n- Holder of a good degree in business, preferably in laws\n- Excellent command of English and Chinese\n\nPlease send cv with MS Word format to Thomson Ng, email, thomson.ng @ globalassociates.com cc cv @ globalassociates.com", "employment_types": ["Full Time"], "selling_points": ["Experienced on new fund launch and registration", "Familiar with post launch procedures", "Advise staff members on new laws and regulations"], "locations": ["Central"], "categories": ["Banking / Finance", "Fund Management", "Risk Management", "Asset Management"], "post_time": "2022-01-07T06:22:31Z", "salary": {"currency": null, "max": null, "min": null, "period": "monthly", "term": null}, "salary_visible": false, "title_keywords": ["compliance officer"], "responsibilities": ["regulations", "management", "operations", "compliance", "asset management", "report"], "requirements": {"degrees": ["degree"], "majors": ["laws", "business"], "languages": ["english", "chinese"], "language_level": ["excellent"], "hard_skills": ["ms word"], "soft_skills": [], "languages_combined": [{"language": "english", "language_level": ["excellent"]}, {"language": "chinese", "language_level": ["excellent"]}]}, "experience_required": {"duration": ["5 years"], "field": ["compliance", "asset management"]}}, {"job_id": "100003009020214", "location_code": "hk", "company": "Links International", "job_title": "Fund Operations Associate - Hedge Fund", "description": "Responsibilities:\n\nPrepare daily and monthly reconciliation, NAV estimates\nPreparing monthly fund valuation, return attribution and investor reporting\nMonitor various fund operation issues including settlements, collateral, and cash management\nPerform trade bookings, trade matching, daily and P&L reconciliations, failed trade investigations\nLiaise with prime brokers and fund administrator on break resolutions\nPerform automation and process review to streamline and document workflow\nSupport the trading team and assist in back office tasks\nHandle ad-hoc projects assigned by management\n\nRequirements:\n\nUniversity degree in Accounting, Finance or other related disciplines\nMinimum of 1 year fund/ accounting related experience\nKnowledge of financial derivative products is an advantage\nExcellent communication skills in English and Mandarin, mature mindset and confident personality in order to interact with Trading teams and senior management to address business issues\nGood attention to details, able to adapt and work well under pressure\nProficiency in Excel and SQL are preferable\nA positive attitude, a sense of satisfaction from doing your best, and self-discipline are all essential", "employment_types": ["Full Time", "Permanent"], "selling_points": ["Guaranteed 13 months salary", "Work life balance", "All rounded and dynamic role"], "locations": ["Not Specified"], "categories": ["Accounting", "Accountant", "Banking / Finance", "Fund Management", "Asset Management"], "post_time": "2022-01-04T10:13:11Z", "salary": {"currency": null, "max": null, "min": null, "period": "monthly", "term": null}, "salary_visible": false, "title_keywords": ["fund operations associate"], "responsibilities": ["valuation", "reporting", "management", "prime brokers", "review", "monitor", "back office", "p&l", "reconciliations", "liaise with", "ad-hoc projects"], "requirements": {"degrees": ["university degree"], "majors": ["related disciplines", "finance", "accounting"], "languages": ["english", "mandarin"], "language_level": ["excellent"], "hard_skills": ["sql", "excel"], "soft_skills": ["confident", "communication skills", "under pressure", "mature", "positive attitude", "attention to details"], "languages_combined": [{"language": "english", "language_level": ["excellent"]}, {"language": "mandarin", "language_level": ["excellent"]}]}, "experience_required": {"duration": ["minimum of 1 year"], "field": ["related", "accounting"]}}, {"job_id": "100003009020369", "location_code": "hk", "company": "The Bank of East Asia, Limited", "job_title": "Fund Administrator", "description": "MPF Department (Job ID: 3345)\n\nResponsibilities:\n\nTo be a team member of MPF Department\nTo prepare portfolio valuations, interim/annual financial statements, and NAV calculation for MPF funds and APIFs\nTo maintain full accounting records and reconcile cash positions\nTo perform investment compliance monitoring and prepare regulatory returns for MPF funds and unit trusts\nTo handle daily enquiries\nRequirements:\n\nDiploma holder or above in Accounting, Finance or related disciplines, preferably a member of ACCA, HKICPA or equivalent\nMinimum 1 year of fund accounting experience in the banking and financial services industry\nProficiency in Microsoft Office software\nGood command of spoken and written English and Chinese\nAble to work under pressure\nKnowledge of portfolio valuation is an advantage\n* Fresh university graduates will also be considered\n\nInterested parties, please click \"Apply Now\" to submit your application.\n\nPersonal data collected will be used for recruitment purpose only.", "employment_types": ["Full Time", "Permanent"], "selling_points": ["Prepare portfolio valuations", "To be a team member of MPF Department", "1 year fund accounting experience"], "locations": ["Not Specified"], "categories": ["Accounting", "Accounting Clerk / Supervisor", "Banking / Finance", "Financial Services", "Fund Management"], "post_time": "2022-01-04T10:45:49Z", "salary": {"currency": null, "max": null, "min": null, "period": null, "term": null}, "salary_visible": false, "title_keywords": ["administrator"], "responsibilities": ["mpf", "compliance", "monitoring", "financial statements", "maintain"], "requirements": {"degrees": ["diploma holder"], "majors": ["related disciplines", "finance", "accounting"], "languages": ["english", "chinese"], "language_level": ["good command"], "hard_skills": ["microsoft office software", "acca", "hkicpa"], "soft_skills": ["work under pressure"], "languages_combined": [{"language": "english", "language_level": ["good command"]}, {"language": "chinese", "language_level": ["good command"]}]}, "experience_required": {"duration": ["minimum 1 year"], "field": ["accounting experience", "financial services industry", "banking"]}}, {"job_id": "100003009031238", "location_code": "hk", "company": "Nanyang Commercial Bank", "job_title": "Customer Relationship Manager, Wealth Management (Ref: NC8047-00-JDB)", "description": "Establish and strengthen the relationships with high net worth customers, identify and fulfil their investment needs by providing thorough financial analysis. Initiate and implement strategies to promote a full range of retail banking products through a proactive and professional approach in achieving the business sales targets of the bank.\n\nRequirements:\n\n\nDegree holder with at least 3 years sales experience in consumer banking field; or non-degree holder with at least 6 years consumer banking experience;\nPassed in LE 1, 7, 8 or equivalent, IIQE (Paper 1, 2, 3 & 5) and MPF Intermediaries Examination is a must; holder of CFP, ARWP or CRWP qualifications will be an advantage;\nCertified Banker is preferred;\nSound knowledge towards investment market and various banking products;\nSales and customer-oriented with good communication skills;\nProficient in both spoken and written English and Chinese, fluent in Putonghua is preferable.\n\nIf you are flexible enough and zeal for a harmonious and supportive working environment where enables you to grow and succeed professionally, please send a full resume indicating your public examination results (HKCEE and HKALE / HKDSE), your present and expected salary and quoting reference number attention to\u00a0Talent Acquisition Division, Nanyang Commercial Bank, 151 Des Voeux Road Central, Hong Kong or apply through email. For details, please visit\u00a0https://www.ncb.com.hk/ and select the page Recruit.\n\nWe are an Equal Opportunities Employer. Data collected would be used for recruitment purposes only. Applicants who do not hear from us within 8 weeks may consider their applications unsuccessful and their data will be destroyed within 12 months of receipt.", "employment_types": ["Full Time", "Permanent"], "selling_points": ["strengthen the relationships with customers", "Passed in LE ,IIQE ,MPF Intermediaries", "Degree holder with at least 3 years sales exp."], "locations": ["Not Specified"], "categories": ["Banking / Finance", "Investment", "Financial Services", "Fund Management"], "post_time": "2022-01-07T09:05:07Z", "salary": {"currency": null, "max": null, "min": null, "period": "monthly", "term": null}, "salary_visible": false, "title_keywords": ["wealth management", "relationship manager"], "responsibilities": ["mpf", "data", "financial analysis", "communication", "recruitment", "banking"], "requirements": {"degrees": ["hkdse", "degree holder"], "majors": [], "languages": ["putonghua", "english", "chinese"], "language_level": ["fluent", "proficient"], "hard_skills": ["financial analysis", "iiqe"], "soft_skills": ["flexible", "communication skills", "supportive", "harmonious", "customer-oriented", "thorough", "proactive"], "languages_combined": [{"language": "putonghua", "language_level": ["fluent", "proficient"]}, {"language": "english", "language_level": ["fluent", "proficient"]}, {"language": "chinese", "language_level": ["fluent", "proficient"]}]}, "experience_required": {"duration": ["at least 6 years", "at least 3 years"], "field": ["banking experience", "banking"]}}, {"job_id": "100003009030766", "location_code": "hk", "company": "Cornerstone Global Partners", "job_title": "Corporate Communicitons VP/AVP (FI-Trustee, Up to 75k+bonus)", "description": "Our Client:\n\nA top Pension Trustee in HK\n\nRole Overview:\n\nEnhance Company\u2019s branding and image by PR events and strategy via multiple channels\nLead the team to create and execute PR campaigns, event and building rapport with members of the media.\nResponsible for corporate and marketing collaterals, press releases, CEO speeches, script of presentations, etc.\nIdentify industry award programmes to boost corporate image for maximizing business opportunity. Take charge of respective application to meet the goals.\nProvide support, including translation, to other departments on all kinds of communications materials such as correspondences and presentations, etc.\nUpdate corporate website and oversee the production of certain newsletters.\n\n\u00a0Ideal Profile:\n\nBachelor degree or above\n10+ years of practical experience in writing and editing for mass media, professional journals and publications\n5+ years of team management experience\nGood knowledge of pension and investment fund related areas would be an advantage\nGood networking with media\nCandidate with less experience will be considered as Assistant Vice President", "employment_types": ["Permanent"], "selling_points": ["Branding", "Pension, Investment Fund", "Media Connection"], "locations": ["Not Specified"], "categories": ["Banking / Finance", "Fund Management", "Marketing / Public Relations", "Marketing - Brand / Product Management", "Marketing - Marketing Communication"], "post_time": "2022-01-07T08:17:38Z", "salary": {"currency": "HKD", "max": 89999, "min": 45000, "period": "monthly", "term": null}, "salary_visible": true, "title_keywords": [], "responsibilities": ["provide support", "management", "marketing collaterals", "website", "presentations", "editing"], "requirements": {"degrees": ["degree or above", "bachelor"], "majors": [], "languages": [], "language_level": [], "hard_skills": ["translation", "presentations"], "soft_skills": ["responsible", "ideal"], "languages_combined": []}, "experience_required": {"duration": ["5+ years", "10+ years"], "field": ["management", "writing", "editing", "media", "team"]}}, {"job_id": "100003009022660", "location_code": "hk", "company": "ConnectedGroup Limited", "job_title": "Senior Fund Accountant (6-month Contract)", "description": "Our client is one of the global leading financial institutions offering fund and private equity administration services and solutions. To cope with its increasing demands, we are currently assisting it to hire a candidate to support fund audit preparation of financial statements.\n\nThe CORE COMPETENCIES for the role is - hands-on in drafting accounts and independence.\n\nResponsibilities:\n\nDraft accounts and work with auditors to prepare year-end financial accounts\nPrepare a variety of fund reports for clients, e.g. Net Assets Values, distributions, reconciliation, and other fund accounting output, etc.\nSupport all aspects of ad-hoc reporting\n\n\nRequirements:\n\nBachelor's degree in accounting or relevant disciplines\nExperience with hedge fund and asset management\nIndependent and take ownership of assigned tasks\nGood communication skills\n\nFor those who are interested, please submit your latest profile (in WORD Format) to raman.hong@connectedgroup.com. Only qualified candidates will be contacted.\n\nFor more job opportunities, please visit our web-site: www.connectedgroup.com.", "employment_types": ["Full Time", "Contract"], "selling_points": ["Leading Financial Institution", "International Working Environment", "Energetic Team"], "locations": ["Not Specified"], "categories": ["Banking / Finance", "Financial Services", "Equities / Capital Markets", "Fund Management"], "post_time": "2022-01-05T06:07:24Z", "salary": {"currency": null, "max": null, "min": null, "period": "monthly", "term": null}, "salary_visible": false, "title_keywords": ["accountant"], "responsibilities": ["ad-hoc", "year-end", "reports", "reporting"], "requirements": {"degrees": ["degree", "bachelor"], "majors": ["accounting"], "languages": [], "language_level": [], "hard_skills": ["word", "web"], "soft_skills": ["communication skills", "independent"], "languages_combined": []}, "experience_required": {"duration": [], "field": ["asset management"]}}, {"job_id": "100003009018606", "location_code": "hk", "company": "AEM Asset Management Limited", "job_title": "Junior Associate, Client Services", "description": "Responsibilities\n\n\u00a0\u00a0\u00a0\u00a0\u00a0\u00a0\u00a0\u00a0 Products covered include equities, fixed income, investment/mutual funds,\u00a0 \u00a0 \u00a0 \u00a0 \u00a0 \u00a0 \u00a0 \u00a0 \u00a0 \u00a0 \u00a0private equity\n\u00a0\u00a0\u00a0\u00a0\u00a0\u00a0\u00a0\u00a0 Conduct research on various markets and products\n\u00a0 \u00a0 \u00a0 \u00a0 \u00a0Assist in establishing and maintaining strong business relationships with clients\n\u00a0\u00a0\u00a0\u00a0\u00a0\u00a0\u00a0\u00a0 Occasionally travel to other countries for site visits\n\u00a0\u00a0\u00a0\u00a0\u00a0\u00a0\u00a0\u00a0 Perform ad-hoc assignments\n\nRequirements\n\n\u00a0\u00a0\u00a0\u00a0\u00a0\u00a0\u00a0\u00a0 Good command of spoken and written English, Mandarin and Cantonese\n\u00a0\u00a0\u00a0\u00a0\u00a0\u00a0\u00a0\u00a0 Proficiency in MS Office and Chinese word processing\n\u00a0\u00a0\u00a0\u00a0\u00a0\u00a0\u00a0\u00a0 Team player with strong sense of responsibility and self-motivation\n\u00a0 \u00a0 \u00a0 \u00a0 \u00a0Good interpersonal and communication skills\n\u00a0 \u00a0 \u00a0 \u00a0 \u00a0Outgoing and energetic personality\n\u00a0 \u00a0 \u00a0 \u00a0 \u00a0Fresh graduates are also welcomed\n\nWe offer\n\n\u00a0\u00a0\u00a0\u00a0\u00a0\u00a0\u00a0\u00a0 5 Days\u2019 work\n\u00a0\u00a0\u00a0\u00a0\u00a0\u00a0\u00a0\u00a0 Performance bonus\n\u00a0 \u00a0 \u00a0 \u00a0 \u00a0Study and examination leaves\n\nPlease click \"Apply Now\" to submit your application.\nAll personal data collected will be used for recruitment purpose only.", "employment_types": ["Full Time", "Permanent"], "selling_points": [], "locations": ["Causeway Bay"], "categories": ["Accounting", "Financial Analyst", "Banking / Finance", "Fund Management", "Asset Management"], "post_time": "2022-01-04T04:03:32Z", "salary": {"currency": null, "max": null, "min": null, "period": "monthly", "term": null}, "salary_visible": false, "title_keywords": ["associate", "junior"], "responsibilities": ["ad-hoc assignments", "conduct research", "maintaining"], "requirements": {"degrees": [], "majors": [], "languages": ["cantonese", "english", "chinese", "mandarin"], "language_level": ["proficiency", "good command"], "hard_skills": ["chinese word processing", "ms office"], "soft_skills": ["outgoing", "communication skills", "sense of responsibility", "self-motivation", "team player", "energetic", "interpersonal"], "languages_combined": [{"language": "cantonese", "language_level": ["good command"]}, {"language": "english", "language_level": ["good command"]}, {"language": "chinese", "language_level": ["proficiency"]}, {"language": "mandarin", "language_level": ["good command"]}]}, "experience_required": {"duration": [], "field": []}}, {"job_id": "100003009022769", "location_code": "hk", "company": "Recruitment Intelligence Consultants Ltd", "job_title": "MANAGER RESEARCH DIRECTOR / ASSOCIATE DIRECTOR", "description": "International Asset Management\nExcellent Opportunity\nOur client is an international asset management firm, they are now seeking for a high calibre candidate to join them.\u00a0\u00a0\n\nAct as senior manager researcher to conduct in-depth fund and investment strategy due diligence and assessments that require meeting with portfolio managers, on the investment capabilities of investment managers. Operational and compliance aspects are not covered under this role. Regional responsibilities to the local and regional fund platforms and other relevant open or managed architecture investment platforms within Asia. Provide analysis and opinion required to perform due diligence and appointment of new investment managers. Manage on-going oversight of Asia-based investment managers on all investment platforms. Recommend fund terminations or manager changes to local business units and investment platform owners. Develop a center of expertise that adds value to the businesses through excellent fund research and investment manager analysis. Coordinate and maintain a consistent yet locally applicable approach and process with the manager research analysts in the global team.\u00a0\u00a0\n\nTo qualify for the position, you should be a Degree holder with a minimum of 8 years of investment manager, fund research, assessment and analysis experience. Good relationships within the investment management industry. Highly developed leadership, communication, writing, interpersonal, analytical and presentation skills. Must be a team player. Knowledge of wealth, retirement or investment-linked insurance scheme platforms preferred.\u00a0\u00a0\n\nInterested applicants should send a detailed resume to Kelly Kam quoting reference jdb-4559\u00a0via email.\u00a0 Please click \u201cAPPLY NOW\u201d button below.\u00a0\u00a0\n\n(Applicants not contacted within 4 weeks should consider their application unsuccessful.)", "employment_types": ["Full Time", "Permanent"], "selling_points": [], "locations": ["Not Specified"], "categories": ["Banking / Finance", "Financial Services", "Fund Management", "Asset Management"], "post_time": "2022-01-05T06:30:03Z", "salary": {"currency": null, "max": null, "min": null, "period": "monthly", "term": null}, "salary_visible": false, "title_keywords": ["associate director", "manager", "director"], "responsibilities": ["due diligence", "management", "analysis", "compliance", "develop", "coordinate", "communication", "maintain", "insurance", "architecture", "asset management"], "requirements": {"degrees": ["degree holder"], "majors": [], "languages": [], "language_level": [], "hard_skills": ["analysis", "scheme"], "soft_skills": ["communication", "presentation skills", "team player", "leadership", "interpersonal", "detailed"], "languages_combined": []}, "experience_required": {"duration": ["minimum of 8 years"], "field": ["research", "investment"]}}, {"job_id": "100003009024764", "location_code": "hk", "company": "Elite Jobs", "job_title": "(Entry Level) Management Associate [5 Days Work, Bank Holiday]", "description": "Key Roles and Responsibilities\u00a0:\n\nProviding quality services and financial solutions to customers\u00a0and satisfy their changing financial needs.\nPresent investment portfolio to our prestigious personal and corporate clients.\nManage the financial needs of a diverse range of customers from mass-market to high-net-worth segments.\nExplore business opportunities and strengthen customer relationships.\nQualifications and Skills:.\n\nUniversity fresh graduate, preferably in finance or business related discipline\nStrong client skills with ability to deliver needs based solutions\nProven organization skills and attention to details\nStrong self-motivation with good interpersonal and analytical skills.\nStrong communication with fluent Cantonese, Mandarin and English.\nCompetitive benefits package, including:\n\nFive-day work week\nPerformance bonus\n20 working days annual leave\nSuperior training and development program\nProgressive career advancement opportunities\n\nWe offer a competitive salary and benefits package and the professional advantages of a dynamic environment that supports your development and recognizes your achievements.\n\nInterested parties please click \"Apply Now\" to send\u00a0full resume with the date of availability and expected salary.\u00a0\n\nAll\u00a0information provided by applicants will be treated in strict confidence and used solely for recruitment purpose. All applicants\u2019 information will be destroyed after 12 months.", "employment_types": ["Full Time"], "selling_points": ["Five-day work week", "University degree in any discipline", "Attractive income, Sustainable career development"], "locations": ["Central & Western Area"], "categories": ["Banking / Finance", "Fund Management", "Marketing / Public Relations", "Management", "Others", "Student / Fresh Graduate / No Experience"], "post_time": "2022-01-06T02:26:23Z", "salary": {"currency": "HKD", "max": 24999, "min": 17000, "period": "monthly", "term": null}, "salary_visible": true, "title_keywords": ["management associate"], "responsibilities": ["communication", "business opportunities", "quality"], "requirements": {"degrees": ["fresh graduate"], "majors": ["finance", "business"], "languages": ["cantonese", "english", "mandarin"], "language_level": ["fluent"], "hard_skills": ["analytical skills"], "soft_skills": ["analytical skills", "communication", "diverse", "self-motivation", "attention to details", "organization skills", "interpersonal"], "languages_combined": [{"language": "cantonese", "language_level": ["fluent"]}, {"language": "english", "language_level": ["fluent"]}, {"language": "mandarin", "language_level": ["fluent"]}]}, "experience_required": {"duration": [], "field": []}}, {"job_id": "100003009020343", "location_code": "hk", "company": "The Bank of East Asia, Limited", "job_title": "MPF Settlement Assistant", "description": "Bank of East Asia (Trustees) Limited\u00a0\n\nMPF Settlement Assistant (Job ID 3234)\n\nResponsibilities\n\n\nTo perform daily settlement on global equities, fixed income securities and unit trust transactions\nTo prepare and monitor funding arrangement and cash positions\nTo process the information of corporate actions\nTo handle ad hoc tasks as requested\n\nRequirements\n\n\nDiploma holder or above preferably in Finance or related disciplines\nMinimum 1 year's settlement or fund operations experience in banking and financial industry\nProficiency in Microsoft Office software\nStrong communication and interpersonal skills\nKnowledge of MPF investment regulations and SFC Code is an advantage\nPlease apply online via the BEA Careers website at\u00a0https://careers.hkbea.com/psp/hcmprd/EMPLOYEE/HRMS/c/HRS_HRAM.HRS_APP_SCHJOB.GBL?Page=HRS_APP_JBPST&Action=UFOCUS=Applicant&SiteId=1&JobOpeningId=3234&PostingSeq=1 or by clicking the \"Apply Now\" button below. Kindly note that if you are a new user, you have to first create your User Profile before you can apply.\nPersonal data provided by job applicants will be used for recruitment purposes only and will be treated in accordance with the Bank's Personal Information Collection (Employees) Statement and Privacy Policy Statement. Applicants who are not invited for interviews within six weeks may consider their applications unsuccessful and the personal data collected will be destroyed after six months.", "employment_types": ["Full Time", "Permanent"], "selling_points": ["To be a member of Bank of East Asia (Trustees) Ltd", "To perform daily settlement", "University fresh graduates are welcome"], "locations": ["Not Specified"], "categories": ["Banking / Finance", "Fund Management", "Order Processing & Operation / Settlement"], "post_time": "2022-01-04T10:40:51Z", "salary": {"currency": null, "max": null, "min": null, "period": "monthly", "term": null}, "salary_visible": false, "title_keywords": ["assistant"], "responsibilities": ["ad hoc tasks", "monitor", "transactions"], "requirements": {"degrees": ["diploma holder"], "majors": ["related disciplines", "finance"], "languages": [], "language_level": [], "hard_skills": ["microsoft office software", "c", "code"], "soft_skills": ["communication and interpersonal skills"], "languages_combined": []}, "experience_required": {"duration": ["minimum 1 year"], "field": ["financial industry", "banking"]}}, {"job_id": "100003009017134", "location_code": "hk", "company": "Connexe Search Limited", "job_title": "Fund Operations Assistant Manager", "description": "About Our Client\n\nOur client is an international fund manager with strong presence in Asia. They are currently looking for a high caliber to join their Fund Operations team.\n\nJob Description\n\nReport to Head of Fund Operations\nResponsible for all aspects of fund administration and valuations for various types of funds\nPerform NAV valuation of the company\u2019s products\nHandle daily reconciliations, trade matching and settlement\nLiaise with external parties, such as tax advisors, auditors, custodians, prime brokers, fund administrators etc\nMonitor the accuracy of fund expense\nMonitor client portfolio and prepare client reporting\nLiaison with auditors for the audit of account\n\nRequirements\n\nUniversity degree in Accounting, Finance or a related discipline\nMember of ACCA, HKICPA or equivalent is preferable\nMinimum 5 years\u2019 relevant working experience in fund industry (Mutual Fund, Hedge Fund)\nBe independent, confident and self-motivated\nStrong verbal and written English skills is a must\u00a0\n\nAll information collected will be kept in strict confidence and will only be used for recruitment purpose. Only shortlisted candidates will be notified.", "employment_types": ["Full Time"], "selling_points": ["Fund Operations, Fund Accounting, Fund Admin", "5 - 7 years experience", "Hedge Fund, Mutual Fund"], "locations": ["Central"], "categories": ["Banking / Finance", "Fund Management", "Order Processing & Operation / Settlement", "Asset Management"], "post_time": "2022-01-03T10:45:13Z", "salary": {"currency": null, "max": null, "min": null, "period": "monthly", "term": null}, "salary_visible": false, "title_keywords": ["manager", "operations assistant"], "responsibilities": ["tax", "valuation", "reporting", "prime brokers", "operations", "external parties", "monitor", "audit", "reconciliations", "liaise with", "report", "administration"], "requirements": {"degrees": ["university degree"], "majors": ["finance", "accounting"], "languages": ["english"], "language_level": [], "hard_skills": ["acca", "hkicpa"], "soft_skills": ["confident", "self-motivated", "confidence", "independent"], "languages_combined": [{"language": "english", "language_level": []}]}, "experience_required": {"duration": ["minimum 5 years"], "field": ["relevant working experience"]}}, {"job_id": "100003009023509", "location_code": "hk", "company": "Infinity Asset Management Limited", "job_title": "Management Trainee - Digital Marketing Executive", "description": "Job Descriptions:\n\n1.\u00a0Assist in asset management business;\n\n2.\u00a0Work with the team to execute business development plans by preparing presentations ;\n\n3.\u00a0Assist in fund administration and daily operations;\n\n4.\u00a0Any ad hoc tasks relating to asset management.\n\n5.Formulating marketing strategy and execution plan;\n\n6.Advertising design on platforms including Facebook, Linkedin and Wechat etc;\n\n7.Develop and edit the publicity material (e.g. newsletter, leaflet and brochure);\n\nQualifications:\n\n1.\u00a0Bachelor's degree holder in Finance or Economic or Accounting or Business Administration\u00a0 \u00a0\u00a0\n\n2.\u00a0High level of Microsoft Office Proficiency, such as Word, Excel, PowerPoint\n\n3.\u00a0Strong written and oral communication skills in English, Cantonese, Putonghua\n\n4.\u00a01-2 years working experience preferred / fresh graduates would also be considered\n\nInterested parties please send your\u00a0RESUME with\u00a0AVAILABILITY & EXPECTED SALARY\u00a0to \"Apply Now\".\u00a0All applications received will be used strictly for hiring purposes only.\u00a0\n\n\n\nAbout\u00a0Infinity Asset Management Limited\n\nInfinity Asset Management is a Hong Kong based fast growing asset management company. Our company aims to develop external asset management and hedge fund business in Hong Kong. We provide opportunities to candidates with the ambition to obtain experience in the high-net-worth wealth management industry.", "employment_types": ["Full Time"], "selling_points": ["Asset Management", "Hedge Fund", "5 working days"], "locations": ["Wan Chai"], "categories": ["Banking / Finance", "Financial Services", "Fund Management", "Asset Management"], "post_time": "2022-01-05T08:59:20Z", "salary": {"currency": null, "max": null, "min": null, "period": "monthly", "term": null}, "salary_visible": false, "title_keywords": ["management trainee", "digital marketing executive"], "responsibilities": ["advertising", "leaflet", "ad hoc tasks", "presentations", "design", "develop", "communication", "daily operations", "asset management", "plan", "plans", "facebook", "administration"], "requirements": {"degrees": ["bachelor", "degree holder"], "majors": ["finance", "accounting", "business administration"], "languages": ["cantonese", "putonghua", "english"], "language_level": [], "hard_skills": ["excel", "microsoft office", "word", "presentations", "wechat", "powerpoint", "facebook"], "soft_skills": ["communication skills", "oral"], "languages_combined": [{"language": "cantonese", "language_level": []}, {"language": "putonghua", "language_level": []}, {"language": "english", "language_level": []}]}, "experience_required": {"duration": ["1-2 years"], "field": []}}, {"job_id": "100003009018945", "location_code": "hk", "company": "Robert Half", "job_title": "PE Fund, Sr Asso (5+ mths bonus)", "description": "Our client is a leading Asset Management, the principal activities included PE fund investment, Hedge Fund investment, insurance and corporate finance. To cope with their business expansion, they are looking for a caliber to join their team.\n\n\n\nHandle daily fund accounting including NAV calculation, cash and position reconciliation, cash collateral, distribution\u2026etc\nWork closely with third party service providers such as external auditors, tax consultants and compliance team\nAssist in new fund set up and wok with external and internal parties such as Risk, Investment, Finance, Sales\u2026etc\nMonitor and continuously improve the quality of services delivered by the services providers\nPerform ad hoc duties as assigned\n\n\n\nRequirements:\n\nBachelor's Degree in Accounting, Finance or relevant discipline\nMinimum of 4 years' fund related experience and consider candidates came from Fund Admin or Fund Operations\nKnowledge of Alternative Investment Fund with direct working experience of fund accounting,\nMember of CPA is an added advantage\nHigh level of multi-tasking and time management skill are required\nA team-player with excellent working attitude; willing to take on multiple functions\nExcellent verbal and written communication skills\n\nApply Today\n\nTo apply online (Word attachment only), please click the 'Apply' button. Please note that only short-listed candidates will be contacted.", "employment_types": ["Full Time", "Permanent"], "selling_points": ["A leading Private Equity Fund house", "Fringe benefit with decent bonus", "Good exposure with career progression"], "locations": ["Central & Western Area"], "categories": ["Accounting", "Accountant", "Banking / Finance", "Fund Management"], "post_time": "2022-01-04T06:13:10Z", "salary": {"currency": null, "max": null, "min": null, "period": "monthly", "term": null}, "salary_visible": false, "title_keywords": [], "responsibilities": ["tax", "ad hoc duties", "management", "operations", "compliance", "monitor", "quality", "communication", "asset management", "insurance", "third party", "internal parties", "external auditors"], "requirements": {"degrees": ["degree", "bachelor"], "majors": ["finance", "accounting"], "languages": [], "language_level": [], "hard_skills": ["cpa", "pe", "word"], "soft_skills": ["team-player", "communication skills", "multi-tasking", "time management skill"], "languages_combined": []}, "experience_required": {"duration": ["minimum of 4 years"], "field": ["related", "admin", "investment", "accounting"]}}, {"job_id": "100003009024565", "location_code": "hk", "company": "AIA International Limited", "job_title": "Wealth Management Manager", "description": "We seek to attract high-caliber\u00a0talent by offering a dynamic working environment, good career development opportunities and competitive compensation packages.\n\nJob Details:\nProvide professional financial advice and services to clients\nIdentify client financials needs and establish planning accordingly\nUpdate financial knowledge and news to your clients\nPrivate wealth management services to your clients\nWe are looking for:\n\nDegree holder in all discipline\nHong Kong ID Card holders and IANG VISA and Dependent VISA holders are welcomed\nFresh Graduates are welcomed. (1-2 years working experience is an advantage)\nEnergetic, mature, self-motivated, hardworking and willing to learn\nExperience in sales industry or background in mainland will be an advantage\nProficiency in both English and Chinese, fluency in Mandarins would be an advantage\nGood interpersonal and communication skills and strong teamwork spirit\nWe Offer:\n\nEligible applicants will be recommended to join the AIA Premier Academy training program to provide you with comprehensive wealth management theory and practice training, and strive to reach the first Million Dollar Round Table (MDRT) qualification\nOver 200 hours well-structured and comprehensive mentoring programs for professional advancement\nFast-track advancement opportunities, will be promoted to management positions within 12 months.\nGain accreditation from the internationally acclaimed Million Dollar Round Table association\nPromising career path to Associate Director/ Director of Wealth Management\nProfessional designations training e.g. CFP, AFP, RFP, RFC, FchFp\nBenefits:\n\nStandard income HK$500,000-HK$800,000 per annum\nMonthly Allowance from $10,000 to 50,000+, Attractive commission package + year-end bonus + comprehensive fringe benefits\nOverseas learning experience\nSpecial holiday package\u00a0\nAll information provided by applicants will be treated in strict confidence, and used for recruitment purpose only.", "employment_types": ["Full Time", "Permanent"], "selling_points": ["HK ID Card holders/ IANG or Dependent VISA", "Trainee/ Manager/ Senior Manager", "Flexible working hours/ high income"], "locations": ["Causeway Bay"], "categories": ["Banking / Finance", "Fund Management"], "post_time": "2022-01-06T01:45:03Z", "salary": {"currency": null, "max": null, "min": null, "period": "monthly", "term": null}, "salary_visible": false, "title_keywords": ["wealth management manager"], "responsibilities": ["communication", "management", "planning", "career development"], "requirements": {"degrees": ["degree holder"], "majors": [], "languages": ["english", "chinese"], "language_level": ["fluency", "advantage", "proficiency"], "hard_skills": ["id", "dynamic"], "soft_skills": ["communication skills", "self-motivated", "willing to learn", "mature", "dynamic", "teamwork spirit", "energetic", "interpersonal", "hardworking"], "languages_combined": [{"language": "english", "language_level": ["proficiency", "fluency", "advantage"]}, {"language": "chinese", "language_level": ["proficiency", "fluency", "advantage"]}]}, "experience_required": {"duration": ["1-2 years"], "field": []}}, {"job_id": "100003009019272", "location_code": "hk", "company": "TeamPlus Consulting Limited", "job_title": "Fixed Income Investment Manager/ Director", "description": "Key Responsibilities:\n\nManage investment portfolios, formulate investment strategies, implement and maintain strategic asset allocation, implement investment strategies and manage daily portfolio transactions\u00a0\nResponsible for tracking research on fixed-income assets/products, establishing and maintaining asset/product portfolios, taking the initiative to optimise high-quality assets\u00a0\nFollow up market changes to conduct market analysis and research, and at the same time carry out portfolio investment transactions and asset adjustments based on portfolio authorization and risk control guidelines\nAnalyze and report on the management portfolio to improve investment performance\n\nRequirements:\n\n3 years or above experience in investment institutions engaged in fixed income investment, research, and trading.\nPossess the professional analysis and understanding of the macro economy, financial market and FICC market with strong risk control ability.\nMaster's degree or above\nSolid understanding about middle and back office operations, risk controls and investment process of fund management companies a plus\nHave good overall quality, communication skills, ethical qualities, and a strong sense of work responsibility, strong team spirit with a can-do attitude\nProficiency in Mandarin and English\n\nInterest parties please send your full resume with expected salary and availability date\n\nAll information will be kept strictly confidential\u00a0", "employment_types": ["Full Time", "Permanent", "Contract"], "selling_points": ["PM role in a top PRC investment firm", "Current Rep with enough experience considered", "Min 3 years industry experience"], "locations": ["Central"], "categories": ["Banking / Finance", "Investment", "Fund Management", "Asset Management"], "post_time": "2022-01-04T07:10:38Z", "salary": {"currency": null, "max": null, "min": null, "period": "monthly", "term": null}, "salary_visible": false, "title_keywords": ["investment manager", "director"], "responsibilities": ["control", "investment strategies", "management", "maintaining", "guidelines", "investment portfolios", "quality", "transactions", "maintain", "market analysis", "report", "tracking"], "requirements": {"degrees": ["degree or above", "master"], "majors": [], "languages": ["english", "mandarin"], "language_level": ["proficiency"], "hard_skills": ["analysis", "macro", "plus"], "soft_skills": ["communication skills", "team spirit", "ethical", "can-do attitude"], "languages_combined": [{"language": "english", "language_level": ["proficiency"]}, {"language": "mandarin", "language_level": ["proficiency"]}]}, "experience_required": {"duration": ["3 years"], "field": ["research", "trading", "investment"]}}, {"job_id": "100003009021333", "location_code": "hk", "company": "Besway Asia Limited", "job_title": "(Senior) Fund Manager - Authorized Fund", "description": "My client, a HK listed financial group, is now looking for an outstanding talent:\n\n(Senior) Fund Manager - Authorized Fund\n\nResponsibilities:\n\n\nAct as the Key Investment Personnel\nManage authorized funds and investment products\nDevelop quantitative stock selection strategy and market timing strategy\nResearch and develop new investment ideas\nAd-hoc projects assigned by managements\n\nRequirements:\u00a0\n\nDegree or above in Finance or related disciplines\n5 years or above working experience in Public Fund operation\nFamiliar with SFC ordinances and regulatory requirements\nGood in English and Chinese\n\nPlease send your resume with current salary and expecting salary via \"APPLY NOW\".\u00a0", "employment_types": ["Full Time", "Permanent"], "selling_points": ["Authorized Fund", "Good benefit", "KIP"], "locations": ["Not Specified"], "categories": ["Banking / Finance", "Investment", "Fund Management", "Asset Management"], "post_time": "2022-01-05T03:39:36Z", "salary": {"currency": null, "max": null, "min": null, "period": "monthly", "term": null}, "salary_visible": false, "title_keywords": ["manager"], "responsibilities": ["ad-hoc projects", "ideas", "develop"], "requirements": {"degrees": ["degree or above"], "majors": ["related disciplines", "finance"], "languages": ["english", "chinese"], "language_level": ["good"], "hard_skills": [], "soft_skills": [], "languages_combined": [{"language": "english", "language_level": ["good"]}, {"language": "chinese", "language_level": ["good"]}]}, "experience_required": {"duration": ["5 years"], "field": ["operation"]}}, {"job_id": "100003009013614", "location_code": "hk", "company": "Ascent Fund Services (Hong Kong) Limited", "job_title": "Fund Administration / Client Services Manager / Assistant Manager", "description": "Principal Responsibilities\n\nAssist in the day-to-day administration and accounting of the assigned fund portfolios.\nReview fund accounting and transfer agency deliverables to ensure compliance with Fund governing documents prior to distribution to clients or investors.\nWork with internal service teams on client on-boarding and new funds set up.\nLiaison with the client\u2019s working team. Respond to client enquiries in a timely and accurate manner.\nSupport the client during year-end audit.\u00a0 Liaison with auditors to provide requested information and respond to queries.\n\nRequirements\n\nBachelor\u2019s Degree with major in Accounting, Finance, or related disciplines.\nMinimum 3 years prior experience in fund administration or accounting covering hedge funds or private equity funds\u00a0or digital assets.\nStrong analytical and problem-solving skills.\u00a0\nHigh level of attention to details, able to work independently.\nExcellent written and spoken English and Mandarin.", "employment_types": ["Full Time"], "selling_points": ["Fund Administration / Client Services", "Hedge Funds / PE Funds / VC Funds etc", "Traditional Asset / Digital Asset"], "locations": ["Admiralty"], "categories": ["Accounting", "Accountant", "Admin & HR", "Administration / Operation Manager", "Banking / Finance", "Fund Management"], "post_time": "2022-01-03T02:32:14Z", "salary": {"currency": null, "max": null, "min": null, "period": "monthly", "term": null}, "salary_visible": false, "title_keywords": ["assistant manager", "client services manager"], "responsibilities": ["year-end", "review", "teams", "audit", "ensure compliance", "administration"], "requirements": {"degrees": ["degree", "bachelor"], "majors": ["related disciplines", "finance", "accounting"], "languages": ["english", "mandarin"], "language_level": ["excellent"], "hard_skills": ["problem-solving skills", "private equity"], "soft_skills": ["problem-solving skills", "work independently", "attention to details"], "languages_combined": [{"language": "english", "language_level": ["excellent"]}, {"language": "mandarin", "language_level": ["excellent"]}]}, "experience_required": {"duration": ["minimum 3 years"], "field": ["digital", "accounting", "administration"]}}, {"job_id": "100003009023980", "location_code": "hk", "company": "Bosera Asset Management (International) Co., Limited", "job_title": "Product Intern", "description": "Job descriptions:\n\nDevelop and implement product strategies consistent with company vision\nProduce and review product requirements documents\nAssist product managers and coordinate internal teams, ensure products are launched correctly and on schedule\nCollect, organize, and analyze market data of mutual funds\n\nRequirements:\n\nBachelor degree or above, major in finance, economics etc. preferred\nGood team spirit, strong sense of responsibility, and willing to learn\nAbility to pay attention to details and documents", "employment_types": ["Internship"], "selling_points": [], "locations": ["Central"], "categories": ["Banking / Finance", "Fund Management", "Asset Management"], "post_time": "2022-01-05T10:13:33Z", "salary": {"currency": null, "max": null, "min": null, "period": "monthly", "term": null}, "salary_visible": false, "title_keywords": ["intern"], "responsibilities": ["review", "teams", "develop", "coordinate", "schedule", "market data"], "requirements": {"degrees": ["degree or above", "bachelor"], "majors": ["finance", "economics"], "languages": [], "language_level": [], "hard_skills": [], "soft_skills": ["team spirit", "willing to learn", "attention to details", "sense of responsibility"], "languages_combined": []}, "experience_required": {"duration": [], "field": []}}, {"job_id": "100003009022732", "location_code": "hk", "company": "Links International", "job_title": "KYC & CDD Officer", "description": "Responsibilities:\n\nPerform KYC and CDD on Corporate and Institutional clients\nLead recurring project such as AML periodic review and tax reporting (FATCA, CRS)\nReview and update the account opening procedures and client due diligence policy\nStreamline and automate existing operation workflow\nWork closely with Salesperson, Compliance, Internal Audit and other operation departments for client onboarding and ongoing monitoring issues\n\nRequirements:\n\nBachelor's degree or above, preferably major in BBA or related disciplines\nAt least 2 years relevant experience in client onboarding, KYC/CDD and AML from banking or financial institutions\nFluent in English, Cantonese and Mandarin\nMature, self-motivated & well-organized\nExcellent interpersonal & communication skills", "employment_types": ["Full Time", "Permanent"], "selling_points": ["Attractive year end bonus", "Work closely with management", "Fast-growing company"], "locations": ["Not Specified"], "categories": ["Banking / Finance", "Financial Services", "Fund Management", "Order Processing & Operation / Settlement"], "post_time": "2022-01-05T06:24:56Z", "salary": {"currency": null, "max": null, "min": null, "period": "monthly", "term": null}, "salary_visible": false, "title_keywords": ["officer"], "responsibilities": ["tax", "reporting", "due diligence", "aml", "internal audit", "cdd", "account opening", "review", "procedures", "compliance", "monitoring", "kyc"], "requirements": {"degrees": ["degree or above", "bachelor"], "majors": ["related disciplines", "bba"], "languages": ["cantonese", "english", "mandarin"], "language_level": ["fluent"], "hard_skills": ["cdd", "aml", "kyc"], "soft_skills": ["communication skills", "self-motivated", "well-organized", "mature", "interpersonal"], "languages_combined": [{"language": "cantonese", "language_level": ["fluent"]}, {"language": "english", "language_level": ["fluent"]}, {"language": "mandarin", "language_level": ["fluent"]}]}, "experience_required": {"duration": ["at least 2 years"], "field": ["financial institutions", "relevant experience", "banking"]}}, {"job_id": "100003009020911", "location_code": "hk", "company": "Recruitment Intelligence Consultants Ltd", "job_title": "RELATIONSHIP MANAGER", "description": "International Asset Management Firm\nExcellent Career Opportunity\nOur client is an international asset management firm an unparalleled reputation across the Asia Pacific region. With the continued growth of the organization, the need has arisen to recruit a high caliber candidate to join them.\n\n\nAchieve mutual fund sales, identify potential clients for investment sales opportunities from existing client base or new prospects based on own contacts as well as generated by marketing activities and other media. Build effective partnership relationship with insurance agents, to generate referral for investment sales. For the partnering with insurance agents, to participate client joint call and keeping partnering insurance agents for total relationship management to conclude investment sales and to provide ongoing investment market and product update, portfolio review and upselling opportunity. Successfully establish an understanding of the nature and needs of potential clients on investment solutions, and provide professional after-sales service to respective clients. Supports the achievement of sales and performance targets. Adhere the defined sales process framework as described by the company and keep up high level sales quality at all time.\nTo be considered, you will be a university graduate with a minimum of 3 years mutual funds sales experience in asset management or retail banking. Passionate about financial market and investment world. Excellent people skills. Strong verbal and written communication skill. Entrepreneurial, Self\u2010motivated and work independently.\u00a0\u00a0\nInterested applicants should send a detailed resume to Kelly Kam quoting reference jdb-4570\u00a0via email.\u00a0 Please click \u201cAPPLY NOW\u201d button below.\n(Applicants not contacted within 4 weeks should consider their application unsuccessful.)", "employment_types": ["Full Time", "Permanent"], "selling_points": [], "locations": ["Not Specified"], "categories": ["Banking / Finance", "Financial Services", "Fund Management", "Asset Management"], "post_time": "2022-01-05T02:31:52Z", "salary": {"currency": null, "max": null, "min": null, "period": "monthly", "term": null}, "salary_visible": false, "title_keywords": ["relationship manager"], "responsibilities": ["management", "review", "quality", "communication", "after-sales service", "client base", "banking", "insurance", "asset management"], "requirements": {"degrees": ["university graduate"], "majors": [], "languages": [], "language_level": [], "hard_skills": [], "soft_skills": ["work independently", "communication skill", "passionate about", "detailed"], "languages_combined": []}, "experience_required": {"duration": ["minimum of 3 years"], "field": ["retail banking", "asset management"]}}, {"job_id": "100003009021075", "location_code": "hk", "company": "Robert Walters (HK)", "job_title": "Assistant Digital Product Manager  - wealth management", "description": "Act as Assitant Digital Product Manager to enhance customer experience and expand business opportunities\n\nResponsibilities\n\n* Familiar with Wealth Management Digital Product, understand product benefits and unique selling proposition\n* Strong sense in product digitisation in cash equity, Unit Trust & FX and grow online channel share & plate form\n* Propose idea on new product , develop ideas to grow online channel share and conversion funnel across digital platforms\n* Drive Innovation Technology enhance customer journey & experience\n* Oversee budget, P&L, product launched time line, assets market acceptance\n\n\nRequirements\n\n* Degree holder in related discipline\n* 3+ years experience in corporate bank / wealth management industry\n* Strong sense digital market trend, aware of latest Fintech technology, proficient in UX research & design\n* Digital Product knowledge in Cash equity / Unit Trust / FX\n* Strong product & project management skills, fast react to customer react\n* Familiar with Agile environment", "employment_types": ["Full Time", "Contract"], "selling_points": ["strong sense in product digitization", "3+ in corporate bank / wealth management", "Propose idea on new product"], "locations": ["Not Specified"], "categories": ["Banking / Finance", "Equities / Capital Markets", "Fund Management", "Wealth Management"], "post_time": "2022-01-05T03:00:18Z", "salary": {"currency": null, "max": null, "min": null, "period": "monthly", "term": null}, "salary_visible": false, "title_keywords": ["product manager", "wealth management", "assistant"], "responsibilities": [], "requirements": {"degrees": [], "majors": [], "languages": [], "language_level": [], "hard_skills": [], "soft_skills": [], "languages_combined": []}, "experience_required": {"duration": [], "field": []}}, {"job_id": "100003009023021", "location_code": "hk", "company": "Bank Consortium Trust Co. Ltd.", "job_title": "Assistant Vice President \u2013 Fund Services (Fund Accounting & Valuation) (BCT-FS08)", "description": "Key Responsibilities:\n\n\nSupervise a team of accounting staff in performing daily NAV prices computation for MPF Schemes, APIFs and pension schemes.\nPlacement of unit trust orders, review cash funding, execute FX and arrange cash transfer with relevant Banks in a timely and accurate manner.\u00a0\nUnderstand MPF /ORSO Scheme Regulations and SFC Codes and Guidelines well to facilitate the monitoring of pre and post trade settlement compliance.\nEnsure all transaction and accounting records are recorded accurately and timely.\nMaintaining a high degree of accuracy and consistency in preparation of daily reporting and ensure that the pricing/valuation process are adhered to audit procedures and ensure service standards and regulations are met.\nEnsure all reporting, regulatory returns and client\u2019s reports are prepared and released within specified deadline and with no service slippage.\nWork closely with First Vice President to deal with issues and queries from clients in a professional and timely manner\nFollow and perform control as specified in the Procedure Manual and operational procedure and ensure staff are strictly in compliance with it in all relevant work processes to minimize any potential operational risks.\u00a0 Prompt escalation to First Vice President or Department Head for any issues identified.\nParticipate in ad hoc or any automation project to enhance operational efficiency in Fund Services as assigned by Department Head.\u00a0 Take initiative to provide user requirements, give recommendation and work closely with other stakeholders including IT team, Business Analyst and service vendor to ensure a smooth implementation to enhance operational efficiency and effectiveness.\nAct as expert users and drive the team members to perform user testing on system enhancement or projects\nProvide training and coaching to team members and establish effective communication channel within the team, across teams and with other departments.\n\nRequirements:\n\nDegree holder in Accountancy or Business related discipline, preferably in Finance or Accounting\nMinimum 8 years\u2019 experience in fund accounting and administration, with substantial\u00a0experience in unit trust / MPF / ORSO operations\nStrong fund administration industry knowledge must be demonstrated\nGood command of spoken and written English and Chinese.\n\nRemuneration will be commensurate with qualification and experience. Please send your application with detailed resume indicating both present and expected salary and date of availability to the Human Resources Department, 18/F Cosco Tower, 183 Queen\u2019s Road Central, Hong Kong, or click 'Apply Now' or fax to 23143984.\n\n(Personal data collected will be used for recruitment purpose only and will be kept strictly confidential)", "employment_types": ["Full Time", "Permanent"], "selling_points": ["Degree holder in Accountancy or Business related", "Minimum 8 years\u2019 experience in fund accounting", "Understand MPF /ORSO Scheme Regulations"], "locations": ["Central & Western Area"], "categories": ["Accounting", "Accountant", "Banking / Finance", "Fund Management"], "post_time": "2022-01-05T07:12:14Z", "salary": {"currency": null, "max": null, "min": null, "period": "monthly", "term": null}, "salary_visible": false, "title_keywords": ["accounting", "assistant vice president"], "responsibilities": ["regulations", "provide training", "audit", "communication", "service standards", "control", "ad hoc", "maintaining", "compliance", "teams", "implementation", "testing", "reports", "reporting", "valuation", "mpf", "monitoring", "review", "procedures", "guidelines"], "requirements": {"degrees": ["degree holder"], "majors": ["finance", "business", "accounting", "accountancy"], "languages": ["english", "chinese"], "language_level": ["good command"], "hard_skills": [], "soft_skills": ["detailed"], "languages_combined": [{"language": "english", "language_level": ["good command"]}, {"language": "chinese", "language_level": ["good command"]}]}, "experience_required": {"duration": ["minimum 8 years"], "field": ["accounting", "mpf", "administration"]}}, {"job_id": "100003009013737", "location_code": "hk", "company": "CHINA INDUSTRIAL SECURITIES INTERNATIONAL FINANCIAL GROUP LIMITED", "job_title": "Compliance-SFC Type 9", "description": "JobDescription\n\n1.Responsible for ongoing compliance monitoring \u3001compliance checkand compliance report preparation for management review on periodic basis\uff1b\n2.Liaise with asset management department on corporate integrity and regulatory compliance;\n3.Assist in fund establishment projects including fund documentation drafting and review, account opening, KYC verification and AML screening;\n4.Perform SFC licensing tasks such as individual licence application, notifications and returns submission;\n5.Maintain and update internal policies and procedural manuals to ensure compliance with latest regulatory requirements;\n6.Prepare responses to SFC\u2019s inquiries, notice or client\u2019s complaints.\n\n\n\nThe Successful Applicant:\n\n1.Bachelor degree or above in Law, Finance or a related discipline;\n2.3 years or above experience in FS compliance, preferably from fund industry;\n3.Experience with financial derivatives;\n4.Knowledge in SFO and SFC regulations would be an advantage;\n5.Strong analytical, problem-solving and communication skills;\n6.Good command of verbal and written both English and Chinese (Mandarin and Cantonese);\n7.Self-motivated with the ability to multitask in a fast-paced environment.", "employment_types": ["Full Time"], "selling_points": ["Securities", "Compliance", "Bachelor degree"], "locations": ["Sheung Wan"], "categories": ["Banking / Finance", "Financial Services", "Fund Management", "Professional Services", "Legal & Compliance"], "post_time": "2022-01-03T02:39:49Z", "salary": {"currency": null, "max": null, "min": null, "period": "monthly", "term": null}, "salary_visible": false, "title_keywords": [], "responsibilities": ["regulations", "documentation", "account opening", "policies", "monitoring", "compliance", "review", "regulatory requirements", "ensure compliance", "communication", "asset management", "maintain", "aml screening", "kyc", "liaise with", "management review", "report"], "requirements": {"degrees": ["degree or above", "bachelor"], "majors": ["finance", "law"], "languages": ["cantonese", "english", "chinese", "mandarin"], "language_level": ["good command"], "hard_skills": ["account opening", "problem-solving", "aml screening", "kyc", "documentation", "sfo"], "soft_skills": ["communication skills", "self-motivated", "responsible", "fast-paced environment", "problem-solving", "integrity", "ability to multitask"], "languages_combined": [{"language": "cantonese", "language_level": ["good command"]}, {"language": "english", "language_level": ["good command"]}, {"language": "chinese", "language_level": ["good command"]}, {"language": "mandarin", "language_level": ["good command"]}]}, "experience_required": {"duration": ["3 years"], "field": ["compliance", "financial"]}}, {"job_id": "100003009017797", "location_code": "hk", "company": "Links International", "job_title": "KYC & CDD Analyst - Asset Management", "description": "Responsibilities:\n\nPerform KYC/ CDD analysis of distributors, institutional investors and beneficial owners in accordance with regulations required by the policies and procedures\nMaintain Clients' KYC/ CDD data in relevant systems in accordance with Group policies and relevant local regulations\nCollaborate with relevant representatives of Sales, Client Account Management and Compliance\nAssist all stakeholders with the implementation of the new KYC/ CDD rules and policies\nProvide periodic KYC/CDD reporting to your management including for the APAC Regional Management\nCoordinate ad hoc client and sales communications in collaboration with relevant internal department\nActive contribution and participation in all Client Service projects\n\nRequirements:\n\nBachelor or Master Degree in Business Administration/ Finance\nMinimum 2 years of experience in client service/ sales support in the financial services industry in Asia-Pacific, with hands-on exposure to KYC/ CDD onboarding and periodic reviews\nUnderstanding of KYC/ CDD regulations\nWorking knowledge of fund distribution landscape, rules, regulations and legal structures in the Asia-Pacific countries/territories is a plus\nExcellent command of English & Mandarin, written and spoken", "employment_types": ["Full Time", "Permanent"], "selling_points": ["Attractive year end bonus", "Work closely with management", "Fast-growing company"], "locations": ["Not Specified"], "categories": ["Banking / Finance", "Financial Services", "Fund Management", "Order Processing & Operation / Settlement"], "post_time": "2022-01-04T02:02:03Z", "salary": {"currency": null, "max": null, "min": null, "period": "monthly", "term": null}, "salary_visible": false, "title_keywords": ["analyst", "asset management"], "responsibilities": ["regulations", "collaborate with", "management", "reporting", "ad hoc", "data", "cdd", "analysis", "policies", "procedures", "systems", "compliance", "implementation", "coordinate", "maintain", "kyc"], "requirements": {"degrees": ["bachelor", "master degree"], "majors": ["finance", "business administration"], "languages": ["english", "mandarin"], "language_level": ["excellent"], "hard_skills": ["cdd", "plus", "sales support", "kyc"], "soft_skills": ["hands-on"], "languages_combined": [{"language": "english", "language_level": ["excellent"]}, {"language": "mandarin", "language_level": ["excellent"]}]}, "experience_required": {"duration": ["minimum 2 years"], "field": ["financial services industry", "sales support"]}}, {"job_id": "100003009023369", "location_code": "hk", "company": "QHire Limited", "job_title": "Fund Lawyer, TOP TIER Chinese House", "description": "Hiring a Fund Lawyer for a TOP-TIER Chinese named financial institution based in HK.\n\u00a0 \u00a0 \u00a0 \u00a0 \u00a0 \u00a0\n\u00a0 \u00a0 \u00a0 \u00a0 \u00a0 \u00a0 \u00a0Job duties:\nAdvising and supporting management and business by offering active and competent support on all asset management work\nMonitoring and controlling legal risk\nLiaising with external service providers (e.g. law firms, administrators, custodians)\nAssisting in such projects as are assigned from time to time\n\u00a0 \u00a0 \u00a0 \u00a0 \u00a0 \u00a0Qualifications:\nBachelor degree in law\nHong Kong qualified lawyer of 4 to 6 years post-qualification experience gained from a top-tier law firm and/or sizable financial institution\nExcellent written and verbal communication skills in English, Mandarin, and Cantonese", "employment_types": ["Full Time"], "selling_points": ["Attractive salary", "Stable house", "Sizable pipeline"], "locations": ["Central"], "categories": ["Banking / Finance", "Fund Management", "Professional Services", "Legal & Compliance"], "post_time": "2022-01-05T08:29:00Z", "salary": {"currency": "HKD", "max": 119999, "min": 70000, "period": "monthly", "term": null}, "salary_visible": true, "title_keywords": [], "responsibilities": ["management", "monitoring", "liaising with", "communication", "asset management"], "requirements": {"degrees": ["degree", "bachelor"], "majors": ["law"], "languages": ["cantonese", "english", "chinese", "mandarin"], "language_level": ["excellent"], "hard_skills": [], "soft_skills": ["communication skills", "active", "competent"], "languages_combined": [{"language": "cantonese", "language_level": ["excellent"]}, {"language": "english", "language_level": ["excellent"]}, {"language": "chinese", "language_level": []}, {"language": "mandarin", "language_level": ["excellent"]}]}, "experience_required": {"duration": ["of 4 to 6 years"], "field": ["post-qualification", "financial"]}}, {"job_id": "100003009024235", "location_code": "hk", "company": "Links International", "job_title": "Account Opening Associate - KYC & CDD", "description": "Responsibilities:\n\nHandle account opening and corporate client onboarding processes, including data collection, KYC and record keeping\nProvide and promote quality client solutions by working closely with all business lines\nAssist the department head to establish and enforce service procedures, policies and standards\nParticipate in the coaching and training process of less experienced associates when necessary\n\nRequirements:\n\nBachelor Degree in Accounting, Finance, Investment Management, Economics or related disciplines\nExperience in KYC/ AML areas within Finance industry is strongly preferred\nFamiliar with SFC regulation on KYC and AML requirements\nExperience of providing service to all type of clients including Institutional, Corporate and Individual is highly preferred\nFluent in Mandarin and English is a must", "employment_types": ["Full Time", "Permanent"], "selling_points": ["Guaranteed 13 months salary", "Excellent medical & dental", "Work life balance"], "locations": ["Not Specified"], "categories": ["Banking / Finance", "Fund Management", "Order Processing & Operation / Settlement", "Asset Management"], "post_time": "2022-01-05T11:49:24Z", "salary": {"currency": "HKD", "max": 29999, "min": 20000, "period": "monthly", "term": null}, "salary_visible": true, "title_keywords": ["associate"], "responsibilities": ["account opening", "policies", "quality", "procedures", "data collection", "kyc"], "requirements": {"degrees": ["degree", "bachelor"], "majors": ["related disciplines", "finance", "accounting", "economics"], "languages": ["english", "mandarin"], "language_level": ["fluent"], "hard_skills": ["aml", "kyc"], "soft_skills": [], "languages_combined": [{"language": "english", "language_level": ["fluent"]}, {"language": "mandarin", "language_level": ["fluent"]}]}, "experience_required": {"duration": [], "field": ["finance industry"]}}, {"job_id": "100003009019850", "location_code": "hk", "company": "Zhongtai Financial International Limited", "job_title": "Asset Management - Trade Support", "description": "Responsibilities:\n\n\nTo undertake trading activities support across various asset classes including equities, fixed income and derivatives\nTo monitor funds' overall positions and support investment teams in terms of information flow, trade ideas and data requests\nTo perform risk management support\nTo monitor market activity and provide feedback to portfolio managers\nTo manage orders and trade flow in a logical and risk-controlled manner\nTo support the company in other relevant areas\n\nRequirements:\nOver 2 years solid experience in relevant fields, experience in well-known financial institution is highly preferable;\nGood communication skill with analytical mind;\nStrong Mandarin communication skills, proficient in both written and spoken Mandarin, English, Cantonese; \u00a0\nImmediate available is an advantage", "employment_types": ["Full Time"], "selling_points": ["Over 2 years relevant experience", "Manage orders and trade flow", "Equities \u3001fixed income\u3001 derivatives trade support"], "locations": ["Central"], "categories": ["Banking / Finance", "Dealing & Trading", "Fund Management", "Asset Management"], "post_time": "2022-01-04T09:24:43Z", "salary": {"currency": null, "max": null, "min": null, "period": "monthly", "term": null}, "salary_visible": false, "title_keywords": ["asset management"], "responsibilities": ["management", "ideas", "data", "teams", "monitor"], "requirements": {"degrees": [], "majors": [], "languages": ["cantonese", "english", "mandarin"], "language_level": ["proficient"], "hard_skills": [], "soft_skills": ["communication skills", "analytical mind", "communication skill"], "languages_combined": [{"language": "cantonese", "language_level": ["proficient"]}, {"language": "english", "language_level": ["proficient"]}, {"language": "mandarin", "language_level": ["proficient"]}]}, "experience_required": {"duration": ["2 years"], "field": ["financial"]}}, {"job_id": "100003009012342", "location_code": "hk", "company": "Apex Fund Services (HK) Limited", "job_title": "Private Equity Fund Administration \u2013 Supervisor", "description": "Job Description:\n\nThe successful applicant will be responsible for day-to-day operations of accounting and administration of private equity funds and will strive to be the one point contact to investment managers and funds\u2019 investors. To carry out these duties, the successful applicant will carry out and coordinate with and lead relevant support team reporting to Senior Account Manager to deliver timely and accurate fund administration services to our clients.\n\n\u00a0Responsibilities:\n\n\nPerform and coordinate with services center teams for Net Asset Value Calculation / Partner Capital Account allocation, distribution waterfall and processing of capital transactions\nReview and ensure accuracy of services deliverables e.g. NAV computation, Investor Reporting\nPerform and coordinate with services center teams for AML/KYC checks on fund investors, delivery of reporting and accounting solutions and FATCA/CRS filing\nReview and coordinate to perform in monitoring cash activity of fund client account and preparation of reconciliations on a regular basis\nReview and coordinate to perform accounting for fund investment transactions and reconcile Investment positions on regular basis\nMaintain robust understanding of fund administration requirement with respect to relevant client fund mandates\nAdhere to client service level agreements delivery, engage in process management with supporting and services center teams in delivering client services\nAcquire and mastery of system knowledge in relevant accounting, investor reporting and relevant services systems\nLiaise with auditors and coordinate for audit on financial statements\nAcquiring understanding and application of relevant organizational and performance controls, operational procedures\nCompiling and assisting Senior Account Managers in compiling ad hoc reports and operation metrics as required by management\nRequirements:\n\nUniversity degree in Accounting, Finance or a related discipline\nProfessional qualified accountant\nMinimum 4 years of work experience in fund administration with at least 2 years relevant exposure in private equity funds /closed ended fund\nGood communications, interpersonal and problem solving skills\nStrong verbal and written English skills, proficiency in Mandarin is a must\nFlexibility and ability to multi-task\nProficient in the use of Microsoft Excel and Microsoft Word\nKnowledge in eFront /PAXUS is an advantage\nCandidate with less working experience may be considered as Supervisor, Fund Administration\n\nTo be successful in this role it is envisaged you are a motivated and self-driven individual eager to contribute and grow with the organization.\n\nWe offer a modern and progressive work environment, and offer a path towards future career growth. Interested parties, please send your full resume with your expected salary and availability by clicking \"Apply Now\" below.\u00a0\n\n\u00a0Personal data provided by job applicants will be used for recruitment purpose only and will be treated in strictly confidential.", "employment_types": ["Full Time", "Permanent"], "selling_points": [], "locations": ["Central & Western Area"], "categories": ["Banking / Finance", "Investment", "Fund Management", "Asset Management"], "post_time": "2021-12-31T10:54:10Z", "salary": {"currency": null, "max": null, "min": null, "period": "monthly", "term": null}, "salary_visible": false, "title_keywords": ["supervisor"], "responsibilities": ["day-to-day operations", "audit", "transactions", "financial statements", "maintain", "liaise with", "administration", "ad hoc", "teams", "operational procedures", "reports", "kyc", "reporting", "management", "review", "coordinate with", "monitoring", "reconciliations", "contact", "fund investors", "aml", "systems", "coordinate"], "requirements": {"degrees": ["university degree"], "majors": ["finance", "accounting"], "languages": ["english", "mandarin"], "language_level": ["proficiency"], "hard_skills": ["problem solving skills", "microsoft word", "private equity", "microsoft excel"], "soft_skills": ["multi-task", "motivated", "problem solving skills", "interpersonal", "driven"], "languages_combined": [{"language": "english", "language_level": []}, {"language": "mandarin", "language_level": ["proficiency"]}]}, "experience_required": {"duration": ["minimum 4 years", "at least 2 years"], "field": ["administration"]}}, {"job_id": "100003009019627", "location_code": "hk", "company": "Cornerstone Global Partners", "job_title": "Korean - Chinese Translator (Native Korean is a must)", "description": "Responsibilities:\n\nIdentity opportunities for develop sales strategies to enhance client relationships to achieve sales targets.\nCommunicate with existing and potential clients on behalf of the company.\nCommunicate with internal stake holders(portfolio managers, credit officers, operations etc.), including HQ teams in China, on behalf of the clients.\nWorks with sales manager to ensure that all the client servicing requirements from the clients.\nArrange and participate in client meetings/calls, translate during the meetings/calls if required.\nAssist in producing RFPs / RFIs and marketing materials such as client presentations, pitch books, product profiles.\nWork with internal teams to client on-boarding.\n\n\u00a0Requirements:\n\nBachelor Degree or above in Finance, Banking, Economic, Business Administration or related disciplines.\n1-2 years\u2019 sales and marketing experience, preferably gained from financial industry.\nNew graduate with relevant internship experience will also be considered.\nKnowledge on financial market and product such as RQFII ,QFII, ETFs etc.\nLanguage skill requirements: Native Korean (both speaking and writing), fluent Mandarin Chinese.", "employment_types": ["Full Time"], "selling_points": ["Korean Translator", "Marketing materials", "Asset Management"], "locations": ["Central"], "categories": ["Banking / Finance", "Fund Management"], "post_time": "2022-01-04T08:10:31Z", "salary": {"currency": null, "max": null, "min": null, "period": "monthly", "term": null}, "salary_visible": false, "title_keywords": ["translator"], "responsibilities": ["communicate with", "operations", "teams", "presentations", "develop", "marketing materials"], "requirements": {"degrees": ["degree or above", "bachelor"], "majors": ["related disciplines", "finance", "business administration"], "languages": ["mandarin chinese", "korean"], "language_level": ["native", "fluent"], "hard_skills": ["qfii", "rqfii"], "soft_skills": [], "languages_combined": [{"language": "mandarin chinese", "language_level": ["fluent"]}, {"language": "korean", "language_level": ["native", "fluent"]}]}, "experience_required": {"duration": ["1-2 years"], "field": ["marketing", "financial industry"]}}, {"job_id": "100003009022885", "location_code": "hk", "company": "Aurex Group Limited", "job_title": "Legal Counsel (VP), Global Real Estate Investment Manager", "description": "Based in Hong Kong, global real estate deal flow and operations\nBroad real estate legal experience requires\nEnglish and Cantonese language essential\nWe are working with Hong Kong headquartered real estate investor, developer and operator. As they continue to grow, we are assisting in the search for a Legal Counsel to join their Hong Kong office and work closely with the Head of Legal.\n\nThis role will report to Head of Legal and partner extensively with the various Department Heads of Leasing, Project Development, Operations, Investment, Finance, HR and Facilities.\u00a0Considering the nature of the firm, we are looking for a legal professional with detailed real estate experience covering both investment deals and general operations.\n\nScope of role/responsibilities:\n\nDraft, review general corporate / M&A documents and agreements such as subscription agreements, sale and purchase agreements, shareholders' agreements, limited liability partnership agreements, asset purchase agreements, loan agreements, etc.\nDrafting commercial documents with minimal review (templates, policies and procedures to support trading activities)\nDraft legal opinions relating to complex legal compliance issues\nCoordinate with legal teams globally and other business stakeholder\nDesired Skills & Experience:\n\nQualified Lawyer essential (other jurisdictions UK/USA considered a plus) with 6-10 years of PQE\nReal Estate background\nAt least 5 years of relevant working experience gained in a reputed International law firm and\u00a0some experience in-house with a real estate firm\nProfessional proficiency English and Cantonese (spoken & written) required for working with global counterparts\n\nIf you believe this opportunity is right for you, please send your CV in English to Ben Watt by using the \"Apply Now\" button below.\n\nTo view similar opportunities or express interest in related positions, please visit our website www.aurexgroup.com and follow us on LinkedIn https://lnkd.in/fgAWEBa", "employment_types": ["Full Time"], "selling_points": ["Based in Hong Kong, global real estate deal flow", "Broad real estate legal experience required", "English and Cantonese language essential"], "locations": ["Central & Western Area"], "categories": ["Banking / Finance", "Financial Services", "Project Finance", "Fund Management"], "post_time": "2022-01-05T06:46:23Z", "salary": {"currency": null, "max": null, "min": null, "period": "monthly", "term": null}, "salary_visible": false, "title_keywords": ["legal counsel", "investment manager"], "responsibilities": ["operations", "hr", "review", "policies", "procedures", "compliance", "coordinate with", "teams", "website", "purchase", "report"], "requirements": {"degrees": [], "majors": [], "languages": ["cantonese", "english"], "language_level": ["proficiency"], "hard_skills": ["plus"], "soft_skills": ["detailed"], "languages_combined": [{"language": "cantonese", "language_level": ["proficiency"]}, {"language": "english", "language_level": ["proficiency"]}]}, "experience_required": {"duration": ["at least 5 years"], "field": ["relevant working experience", "investment", "legal"]}}]