[{"job_id": "100003009054791", "location_code": "hk", "company": "Public Finance Limited", "job_title": "Relief Branch Manager", "description": "Responsibilities:\nPerform relief/acting duties in branches and assist to manage the operations of the branches such as loan processing, credit approval, promotion of loan products etc.\nRequirements:\n5 years experience in banking / finance industry of which 3 years at supervisory level\nExperienced in preparing credit proposal or promoting banking / financial products e.g. personal loan, credit card, etc.\nResult-oriented, energetic, mature with good communication skills\nBenefits\nDouble Pay\nDiscretionary Bonus\nInsurance Benefits\nStudy subsidy\nApplication Method:\nBy E-mail via \"Apply Now\"\n\nPersonal data collected will be treated in the strictest confidence in accordance with our\u00a0Personal Information Collection Statement\u00a0and\u00a0Privacy Policy\u00a0and will be handled by authorized personnel for recruitment-related purposes only. All applications will be kept for a maximum period of one year as may be considered for other suitable positions within Public Finance Ltd. and its associated companies. For details, please visit the Company\u2019s website\u00a0http://www.publicfinance.com.hk", "employment_types": ["Full Time", "Permanent"], "selling_points": [], "locations": ["Not Specified"], "categories": ["Banking / Finance", "Credit Analysis / Approval", "Loan", "Financial Services"], "post_time": "2022-01-17T11:05:42Z", "salary": {"currency": null, "max": null, "min": null, "period": "monthly", "term": null}, "salary_visible": false, "title_keywords": ["manager"], "responsibilities": ["operations"], "requirements": {"degrees": [], "majors": [], "languages": [], "language_level": [], "hard_skills": [], "soft_skills": ["communication skills", "energetic", "result-oriented", "mature"], "languages_combined": []}, "experience_required": {"duration": ["5 years", "3 years"], "field": ["supervisory level", "finance industry", "banking"]}}, {"job_id": "100003009054734", "location_code": "hk", "company": "Public Finance Limited", "job_title": "\u71df\u696d\u4ee3\u8868 (\u79c1\u4eba\u8cb8\u6b3e)  Direct Sales Executive (Personal Loan)", "description": "\u8077\u8cac\n\n\u8ca0\u8cac\u5411\u5ba2\u6236\u63a8\u92b7\u79c1\u4eba\u8cb8\u6b3e\u670d\u52d9\n\n\u5165\u8077\u8981\u6c42\u00a0\n\n\u4e2d\u5b78\u7a0b\u5ea6\n\u826f\u597d\u92b7\u552e\u6280\u5de7\u3001\u7a4d\u6975\u9032\u53d6\n\u81ea\u4fe1\u3001\u7a4d\u6975\u3001\u6709\u8cac\u4efb\u611f\n\u7d93\u9a57\u4e0d\u62d8\uff0c\u4f46\u5177\u92b7\u552e\u7d93\u9a57\u8005\u512a\u5148\n\n\u798f\u5229\u00a0\n\n\u7372\u8058\u8005\u5c07\u76f4\u63a5\u53d7\u8058\u70ba\u672c\u516c\u53f8\u9577\u671f\u50f1\u54e1\uff0c\u4e26\u7531\u6240\u5c6c\u92b7\u552e\u968a\u4f0d\u4e3b\u4efb\u63d0\u4f9b\u9069\u7576\u6307\u5c0e\u548c\u652f\u63f4\u3002\n\n\u4eab\u6709\u798f\u5229\u5305\u62ec\u56fa\u5b9a\u5e95\u85aa\u3001\u512a\u539a\u4f63\u91d1\u3001\u91ab\u7642\u798f\u5229 (\u9023\u5bb6\u5c6c)\u3001\u9280\u884c\u5047\u671f\u3001\u52e4\u5de5\u6d25\u8cbc\u3001\u984d\u5916\u734e\u91d1\u7b49\u3002\u6bcf\u6708\u6536\u5165\u4e00\u822c\u53ef\u9054$30,000\u4ee5\u4e0a\u3002\n\n\u7533\u8acb\u65b9\u6cd5:\u00a0\n\n\u8acb\u81f4\u96fb29961877\u6216 Whatsapp 9309 2925\u67e5\u8a62\u53ca\u4f5c\u9762\u8a66\u5b89\u6392\uff0c\u6216\u5c07\u5c65\u6b77\u96fb\u90f5\u81f3Apply Now\u00a0\u7533\u8acb\u3002\n\n\u00a0Personal data collected will be treated in the strictest confidence in accordance with our\u00a0Personal Information Collection Statement\u00a0and\u00a0Privacy Policy\u00a0and will be handled by authorized personnel for recruitment-related purposes only. All applications will be kept for a maximum period of one year as may be considered for other suitable positions within Public Finance Ltd. and its associated companies. For details, please visit the Company\u2019s website\u00a0http://www.publicfinance.com.hk", "employment_types": ["Full Time", "Permanent"], "selling_points": [], "locations": ["Not Specified"], "categories": ["Banking / Finance", "Loan", "Sales, CS & Business Devpt", "Business Development", "Direct Sales"], "post_time": "2022-01-17T10:48:53Z", "salary": {"currency": null, "max": null, "min": null, "period": "monthly", "term": null}, "salary_visible": false, "title_keywords": ["\u71df\u696d\u4ee3\u8868", "direct sales executive", "personal"], "responsibilities": ["personal data", "recruitment", "website"], "requirements": {"degrees": [], "majors": [], "languages": [], "language_level": [], "hard_skills": ["whatsapp"], "soft_skills": ["confidence"], "languages_combined": []}, "experience_required": {"duration": [], "field": []}}, {"job_id": "100003009053103", "location_code": "hk", "company": "HY Credit Company Limited", "job_title": "Customer Service Representative / Customer Service Officer", "description": "Responsibilities:\n\nHandle customer enquiries and consumer loan applications.\nFollow up with existing customers on loan repayment and redemption.\nPromote loan products to new and existing customers.\nPerform administrative support to CS/Credit department (e.g. data input, document filing, scanning and reporting).\nPrepare Ad hoc reports as required\nMaintain good customer relationships to enhance business growth.\n\nRequirements:\n\nForm 5 graduate or above.\n1 - 2 years of CS or telemarketing experience, specialized in consumer loan/ mortgage/ finance business preferably.\nGood interpersonal and communication skills.\nPositive attitude and strong problem-solving skills.\nGood command of written and spoken English and Chinese.\nProficient in Microsoft Office applications, including Word, Excel, and Chinese Word Processing.\n\nCandidates with more experience shall be considered as Customer Service Officers.\n\nWe offer an attractive remuneration package including double pay and discretionary performance bonus. Interested parties, please submit your full resume with PRESENT and EXPECTED SALARY stated.\u00a0\n\nPersonal Data collected will be kept in strict confidence and will be used for recruitment purposes only.\u00a0 Applicants who are not invited for an interview within six weeks may consider their applications unsuccessful.\u00a0 All personal data from unsuccessful candidates will be destroyed after six months.\n\n\u00a0Company website: www.hyc.com.hk", "employment_types": ["Full Time", "Permanent"], "selling_points": ["Customer service, telemarketing experience", "Consumer loans, personal loans, mortgage loans", "Competitive Salary, Double Pay & Medical Insurance"], "locations": ["Wan Chai"], "categories": ["Banking / Finance", "Loan", "Mortgage", "Sales, CS & Business Devpt", "Tele-sales (Telemarketing)"], "post_time": "2022-01-17T05:51:40Z", "salary": {"currency": null, "max": null, "min": null, "period": "monthly", "term": null}, "salary_visible": false, "title_keywords": ["customer service officer", "customer service representative"], "responsibilities": ["scanning", "document filing", "reporting", "handle customer enquiries", "ad hoc", "administrative support", "data input", "maintain", "reports"], "requirements": {"degrees": ["form 5"], "majors": [], "languages": ["english", "chinese"], "language_level": ["good command", "proficient"], "hard_skills": ["excel", "chinese word processing", "microsoft office", "word", "problem-solving skills"], "soft_skills": ["communication skills", "positive attitude", "customer service", "problem-solving skills", "interpersonal"], "languages_combined": [{"language": "english", "language_level": ["good command"]}, {"language": "chinese", "language_level": ["good command", "proficient"]}]}, "experience_required": {"duration": ["1 - 2 years"], "field": ["consumer loan", "finance", "business", "customer service", "cs"]}}, {"job_id": "100003009054838", "location_code": "hk", "company": "Cathay United Bank Company, Limited", "job_title": "Credit Administration Manager, Operations", "description": "Responsibilities:\n\nPrepare and review facility and security documentation\n\nCheck and comment on loan documents\nFollow up precedent/subsequent loan conditions, financial covenants, etc.\nIdentify documentation and workflow deficiencies, report and follow-up\nParticipate and contribute to projects and conduct UAT\nPrepare, review and update SOP\n\nCandidates are expected to possess:\n\nBachelor\u2019s Degree\u00a0with minimum 8 years of experience in Credit Administration, with well qualified supervisory experience\nIn-depth knowledge of processing bilateral loans, syndicated loans, Lombard lending, etc., especially in areas of banking practice and legal aspects\nStrong management skills with positive attitude and team spirit\nStrong communication and organization skills\nProficiency in MS Office application like WORD and EXCEL\nExcellent command of written and spoken English and Chinese, including Mandarin\n\nWe offer attractive salary and comprehensive fringe benefits. Interested parties please e-mail your full resume with current and expected salary by clicking 'Apply Now'.\n\nPersonal information collected will be used for considering suitability for the post and strictly in accordance with our personal data policies.\u00a0 It is our policy to retain the personal data of unsuccessful applicants for future recruitment purposes for a period of maximum two years.\u00a0", "employment_types": ["Full Time", "Permanent"], "selling_points": ["University graduate", "At least 8 years of Credit Admin experience", "Well qualified supervisory experience"], "locations": ["Causeway Bay"], "categories": ["Banking / Finance", "Credit Analysis / Approval", "Loan", "Others"], "post_time": "2022-01-17T11:37:24Z", "salary": {"currency": null, "max": null, "min": null, "period": "monthly", "term": null}, "salary_visible": false, "title_keywords": ["administration manager", "operations"], "responsibilities": ["management", "uat", "review", "communication", "banking", "documentation", "report", "administration"], "requirements": {"degrees": ["degree", "bachelor"], "majors": [], "languages": ["english", "chinese", "mandarin"], "language_level": ["excellent"], "hard_skills": ["excel", "word", "banking practice", "documentation", "processing", "ms office"], "soft_skills": ["positive attitude", "team spirit", "organization skills", "communication"], "languages_combined": [{"language": "english", "language_level": ["excellent"]}, {"language": "chinese", "language_level": ["excellent"]}, {"language": "mandarin", "language_level": ["excellent"]}]}, "experience_required": {"duration": ["minimum 8 years"], "field": ["supervisory experience", "administration"]}}, {"job_id": "100003009054756", "location_code": "hk", "company": "Public Finance Limited", "job_title": "Senior Marketing Officer (Mortgage Loan Sales) ($20,000+ plus Commission)", "description": "Responsibilities\nTo achieve mortgage loan sales target\nTo establish good relationship with business partners such as solicitor firms, property agencies, referral intermediaries, etc\nRequirements\n3 years experience in mortgage loan sales\nHave developed a good people-network with brokers / Mortgage Referral Services Companies / Estate Agencies/Solicitor firms is an advantage\nApplications from the existing Estate Agencies are welcome\nWork in Central Office\n(Candidate who posses less experience may be considered as Marketing Officer)\nBenefits\nInsurance Benefits\nStudy subsidy\nApplication Method:\n\nBy Whatsapp : 9309 2925\nBy E-mail via \"Apply Now\"", "employment_types": ["Full Time", "Permanent"], "selling_points": [], "locations": ["Central"], "categories": ["Banking / Finance", "Loan", "Mortgage", "Sales, CS & Business Devpt", "Sales - Sales Management"], "post_time": "2022-01-17T10:55:46Z", "salary": {"currency": null, "max": null, "min": null, "period": "monthly", "term": null}, "salary_visible": false, "title_keywords": ["sales", "senior marketing officer"], "responsibilities": ["good relationship", "sales target"], "requirements": {"degrees": [], "majors": [], "languages": [], "language_level": [], "hard_skills": [], "soft_skills": [], "languages_combined": []}, "experience_required": {"duration": ["3 years"], "field": ["marketing"]}}, {"job_id": "100003009053756", "location_code": "hk", "company": "United Asia Finance Limited", "job_title": "Specialist, Phone Credit", "description": "Job Responsibilities:\n\nAssist teammate to handle customer enquiries and complaints\nSupport daily operations and promotional activities\nProvide support on credit assessment to supervisors according to lending policies\nCoach and train junior staff\n\nJob Requirements:\n\nF.5 HKCEE / F.6 HKDSE or above\nStrong customer services orientation\nDynamic, strong analytical skill, good interpersonal and communication skills\nGood command of spoken and written Chinese and English\nOn-the-job training will be provided\nExperience in loan assessment and approval\n\nWe offer attractive remuneration package which includes double pay and discretionary bonus. Interested parties please send your CV indicating your current salary, expected salary and availability to HR Department, by email via clicking \"Apply Now\".\n\n(Personal data collected will be treated in the strictest confidence and will be handled by authorized personnel for recruitment-related purposes only. Applicants who do not hear from us within 3 months may consider their application unsuccessful and their data will be destroyed within 24 months of receipt.)", "employment_types": ["Full Time", "Permanent"], "selling_points": ["Provide support on credit assessment", "Coach and train junior staff", "F.5 HKCEE / F.6 HKDSE or above"], "locations": ["Wan Chai"], "categories": ["Admin & HR", "Clerical / Admin Staff", "Banking / Finance", "Loan", "Sales, CS & Business Devpt", "Customer Service - Supervisor / Officer"], "post_time": "2022-01-17T07:32:24Z", "salary": {"currency": null, "max": null, "min": null, "period": "monthly", "term": null}, "salary_visible": false, "title_keywords": ["specialist"], "responsibilities": ["provide support", "policies", "daily operations", "promotional activities", "customer enquiries and complaints"], "requirements": {"degrees": ["hkdse"], "majors": [], "languages": ["english", "chinese"], "language_level": ["good command"], "hard_skills": ["analytical skill", "dynamic"], "soft_skills": ["communication skills", "analytical skill", "dynamic", "interpersonal"], "languages_combined": [{"language": "english", "language_level": ["good command"]}, {"language": "chinese", "language_level": ["good command"]}]}, "experience_required": {"duration": [], "field": []}}, {"job_id": "100003009053124", "location_code": "hk", "company": "Konew Financial Express Ltd", "job_title": "Sales Executive (Branch) \u92b7\u552e\u5c08\u54e1 (\u5206\u884c)", "description": "Main Duties & Responsibilities:\n\nPromote all type of loan services to new and existing clients\nPromote loan refinance service to existing clients\nHandle customer\u2019s enquiries in professional manner and follow up loan applications\nCooperate with Service Ambassador to maintain daily branch operation\nCollect market information for product positioning\nPerform outside work when necessary\nSupport and act towards the Konew Group\u2019s vision\nBranch locations: Tai Po / Sham Shui Po / Kowloon Bay / Kwun Tong / Shau Kei Wan\nDuty hours: Monday to Friday ( 0900 - 1900 )\n\u8ca0\u8cac\u63a8\u5ee3\u53ca\u92b7\u552e\u5404\u985e\u578b\u8cb8\u6b3e\u670d\u52d9\uff0c\u4e26\u7a4d\u6975\u62d3\u5c55\u65b0\u5ba2\u6236\n\u8207\u5ba2\u6236\u5efa\u7acb\u826f\u597d\u95dc\u4fc2\uff0c\u4fdd\u6301\u7dca\u5bc6\u6e9d\u901a\n\u63d0\u4f9b\u512a\u8cea\u5ba2\u6236\u67e5\u8a62\u670d\u52d9\uff0c\u8655\u7406\u53ca\u8ddf\u9032\u6709\u95dc\u8cb8\u6b3e\u7533\u8acb\n\u5728\u9700\u8981\u6642\u57f7\u884c\u5916\u51fa\u5de5\u4f5c\n\u8207\u670d\u52d9\u5927\u4f7f\u5408\u4f5c\uff0c\u7dad\u6301\u5206\u884c\u65e5\u5e38\u904b\u4f5c\n\u70ba\u7522\u54c1\u5b9a\u4f4d\u6536\u96c6\u5e02\u5834\u4fe1\u606f\n\u79c9\u627f\u5eb7\u696d\u96c6\u5718\u6838\u5fc3\u50f9\u503c\u89c0\u53ca\u670d\u52d9\u7406\u5ff5\n\u4e0a\u73ed\u5730\u9ede\uff1a\u5927\u57d4 / \u6df1\u6c34\u57d7 / \u4e5d\u9f8d\u7063 / \u89c0\u5858 / \u7b72\u7b95\u7063\n\u4e0a\u73ed\u6642\u9593\uff1a\u661f\u671f\u4e00\u81f3\u4e94 ( 0900 - 1900\uff09\n\n\n\nRequirements:\n\nSecondary education (HKCEE/HKDSE), or above\n2 years\u2019 working experience in sales or customer service is highly preferred\nProficiency in both English and Chinese\nProactive and commit to the job\nExcellent communication, interpersonal and selling skills\nComplete on-the-job training\nImmediate available is highly preferred\nCandidate with less experience will also be considered as Sales Support role.\u00a0\nHKCEE / HKDSE \u7a0b\u5ea6\u6216\u4ee5\u4e0a\n\u5169\u5e74\u6216\u4ee5\u4e0a\u92b7\u552e\u7d93\u9a57\uff0c\u5177\u7269\u696d\u8cb8\u6b3e\u92b7\u552e\u7d93\u9a57\u8005\u512a\u5148\u8003\u616e\n\u64cd\u6d41\u5229\u5ee3\u6771\u8a71\u53ca\u826f\u597d\u82f1\u8a9e\n\u7a4d\u6975\u4e3b\u52d5\u3001\u6709\u8cac\u4efb\u611f\n\u5177\u826f\u597d\u7684\u8868\u9054\u80fd\u529b\u3001\u8aaa\u8a71\u6280\u5de7\u3001\u92b7\u552e\u53ca\u9867\u5ba2\u670d\u52d9\u6280\u5de7\n\u5165\u8077\u5f8c\u516c\u53f8\u5c07\u63d0\u4f9b\u5b8c\u5584\u7684\u5728\u8077\u57f9\u8a13\n\u80fd\u5373\u6642\u4e0a\u73ed\u8005\u5c07\u512a\u5148\u8003\u616e\n\u5de5\u4f5c\u7d93\u9a57\u8f03\u6dfa\u8005\u6216\u6703\u88ab\u8003\u616e\u8058\u4efb\u70ba\u92b7\u552e\u52a9\u7406\n\nWe offer:\n\n5-day Work Week\nPublic Holiday\nDiscretionary Year-end Performance Bonus\nMedical Insurance\nAttendance Bonus\nBirthday Leave\nAnniversary Leave\nStudy Leave\nOn-the-job Training\n\nHow to apply:\n\nInterested parties, please send your resume stating your expected salary to Human Capital Department\u00a0by clicking \"APPLY NOW\".\n\n(We are an equal opportunity employer.\u00a0 Personal data collected will be used for recruitment purpose only.\u00a0 The unsuccessful applications will be destroyed after 6 months.)\u00a0\n\nCandidate with less experience will be considered as Branch Assistant\u00a0\nCandidate with less experience will be considered as Branch Assistant\u00a0", "employment_types": ["Full Time"], "selling_points": ["2 years' sales/customer services exp.", "5-day Work Week (Mon-Fri), 0900 - 1900", "Immediate available is highly preferred"], "locations": ["Others"], "categories": ["Banking / Finance", "Loan", "Mortgage", "Sales, CS & Business Devpt", "Direct Sales"], "post_time": "2022-01-17T05:58:10Z", "salary": {"currency": null, "max": null, "min": null, "period": "monthly", "term": null}, "salary_visible": false, "title_keywords": ["sales executive"], "responsibilities": ["maintain", "professional manner", "cooperate with", "market information"], "requirements": {"degrees": ["hkdse", "secondary education"], "majors": [], "languages": ["english", "chinese"], "language_level": ["proficiency"], "hard_skills": ["sales support"], "soft_skills": ["communication", "customer service", "proactive", "interpersonal"], "languages_combined": [{"language": "english", "language_level": ["proficiency"]}, {"language": "chinese", "language_level": ["proficiency"]}]}, "experience_required": {"duration": ["2 years"], "field": ["customer service", "sales support"]}}, {"job_id": "100003009052317", "location_code": "hk", "company": "Hudson Global Resources (Hong Kong) Limited", "job_title": "Loan/Credit card Sales / Telesales / Telemarketing \u9280\u884c\u96fb\u8a71\u92b7\u552e\u5c08\u54e1  (\u4e94\u5929\u5de5\u4f5c-Call Centre)", "description": "\u8077\u8cac:\n\n\u5728\u547c\u53eb\u4e2d\u5fc3\u70ba\u5ba2\u6236\u8655\u7406\u96fb\u8a71\u92b7\u552e\u670d\u52d9\n\u8655\u7406\u5ba2\u6236\u67e5\u8a62\u4e26\u92b7\u552e\u7684\u9280\u884c\u7522\u54c1\n\u63a8\u5ee3\u4fe1\u7528\u5361\u8cb8\u6b3e/\u79c1\u4eba\u8cb8\u6b3e\u7d66\u73fe\u6709\u5ba2\u6237\n\u5b8c\u6210\u500b\u4eba\u92b7\u552e\u76ee\u6a19\n\n\u8981\u6c42:\n\n\u4e2d\u4e94\u6216\u4ee5\u4e0a\uff0c\u6709\u5ba2\u6236\u670d\u52d9\u6216\u547c\u53eb\u4e2d\u5fc3\u5de5\u4f5c\u7d93\u9a57\n\u4ee5\u5ba2\u6236\u70ba\u4e2d\u5fc3\uff0c\u5177\u6709\u826f\u597d\u7684\u6e9d\u901a\u6280\u5de7\n\u81ea\u6211\u6fc0\u52f5\u548c\u71b1\u60c5\u7684\u500b\u6027\n\u7cbe\u901a\u7cb5\u8a9e\u3001\u82f1\u8a9e\u53ca\u666e\u901a\u8a71\u6d41\u5229\n\n\n\u798f\u5229:\n\n\u6301\u7e8c\u7684\u57f9\u8a13\n\u57fa\u672c\u5de5\u8cc7\u52a0\u9ad8\u7e3e\u6548\u734e\u91d1\n\u4e94\u5929\u5de5\u4f5c\n\n\nResponsibilities:\n\nHandle inbound calls and outbound tele-sales service to our customers at Call Center\nSupport pro-sales, pre-sales activities, counter service and other customer service duties\nKey Stakeholders: Product Team, Fulfilment Team, Operation Team, Branches and CCC\n\nRequirements:\n\n\u00a0Form 5 or above\nAt least 1 years\u2019 customer service or call center experience\nGood command in Cantonese, English and Mandarin\nCustomer-oriented and Excellent communication skill\nSelf-motivated and Enthusiastic personality\n\nBenefits:\n\nOn-going training\nBase pay and high commission\n5 days work", "employment_types": ["Full Time"], "selling_points": ["\u9280\u884c\u5de5,\u9280\u884c\u798f\u5229", "\u5e95\u85aa\u9023\u4f63\u91d1 20k-50k", "\u6301\u7e8c\u6709\u57f9\u8a13"], "locations": ["Kwun Tong"], "categories": ["Banking / Finance", "Loan"], "post_time": "2022-01-17T02:45:11Z", "salary": {"currency": "HKD", "max": 44999, "min": 17000, "period": "monthly", "term": null}, "salary_visible": true, "title_keywords": ["telesales", "telemarketing", "sales"], "responsibilities": ["sales activities", "customer service duties"], "requirements": {"degrees": ["form 5 or above"], "majors": [], "languages": ["cantonese", "english", "mandarin"], "language_level": ["good command"], "hard_skills": [], "soft_skills": ["self-motivated", "communication skill", "customer-oriented", "customer service", "enthusiastic"], "languages_combined": [{"language": "cantonese", "language_level": ["good command"]}, {"language": "english", "language_level": ["good command"]}, {"language": "mandarin", "language_level": ["good command"]}]}, "experience_required": {"duration": ["at least 1 years"], "field": ["customer service", "call center"]}}, {"job_id": "100003009053188", "location_code": "hk", "company": "Konew Financial Express Limited \u5eb7\u696d\u4fe1\u8cb8\u5feb\u905e", "job_title": "Officer, Credit Approval", "description": "Main Duties & Responsibilities:\n\nConduct credit approvals on all applications including property loans, personal loans and SME loans in accordance with authority\nAssist to ensure that credit activities are conducted in accordance with requirements as stipulated in the credit policies\nEnsure appropriate infrastructure, resources and systems are in place for credit risk management\nCollaborate with Sales Department for the criteria of credit approval\nReview and prepare various reports of credit risk management\n\nRequirements:\n\nBachelor Degree in Risk Management, Mathematics, Economics or related discipline\nAt least 1\u00a0year relevant working experience\nExcellent analytical, communication and interpersonal skills\nIndependent, proactive, detail-oriented and able to work under pressure\nCandidates with more experience will be considered as\u00a0Senior Officer\n\nWe offer:\n\nDiscretionary bonus\nMedical insurance\nDental insurance\nHardship allowance\nCompetitive annual leave days\nBirthday leave\nAnniversary leave\nStudy leave\nMarriage leave\nCompassionate leave\n\nHow to apply:\n\nInterested parties, please send your resume stating your expected salary to Human Capital Department\u00a0by clicking \"APPLY NOW\".\n\n(We are an equal opportunity employer.\u00a0 Personal data collected will be used for recruitment purpose only.\u00a0 The unsuccessful applications will be destroyed after 6 months.)\u00a0", "employment_types": ["Full Time", "Permanent"], "selling_points": ["Conduct credit approvals on all loan applications", "Collaborate for the criteria of credit approval", "5 days work, birthday leave, anniversary leave"], "locations": ["Central"], "categories": ["Banking / Finance", "Credit Analysis / Approval", "Loan", "Mortgage"], "post_time": "2022-01-17T06:22:00Z", "salary": {"currency": null, "max": null, "min": null, "period": "monthly", "term": null}, "salary_visible": false, "title_keywords": ["officer"], "responsibilities": ["collaborate with", "management", "policies", "infrastructure", "systems", "review", "reports", "sme"], "requirements": {"degrees": ["degree", "bachelor"], "majors": ["risk management", "economics", "mathematics"], "languages": [], "language_level": [], "hard_skills": [], "soft_skills": ["independent", "detail-oriented", "communication and interpersonal skills", "proactive", "work under pressure"], "languages_combined": []}, "experience_required": {"duration": ["at least 1 year"], "field": ["relevant working experience"]}}, {"job_id": "100003009053641", "location_code": "hk", "company": "United Asia Finance Limited", "job_title": "Associate / Assistant, Electronic Credit", "description": "Job Responsibilities\nProvide customer service and handle consumer loan online application\nPerform general clerical duties\nJob Requirements:\nF.5 HKCEE / F.6 HKDSE or above, customer-service oriented\nAt least 1 year working experience in customer service, preferable in personal loan business\nGood interpersonal skill, willing to learn and mature\nFluent in written and spoken English and Chinese\nOn-the-job training will be provided\nFresh graduates will also be considered\nWe offer attractive remuneration package which includes double pay and discretionary bonus. Interested parties please send your CV indicating your current salary, expected salary and availability to HR Department, by email via clicking \"Apply Now\".\n\n(Personal data collected will be treated in the strictest confidence and will be handled by authorized personnel for recruitment-related purposes only. Applicants who do not hear from us within 3 months may consider their application unsuccessful and their data will be destroyed within 24 months of receipt.)", "employment_types": ["Full Time", "Permanent"], "selling_points": ["Double pay and discretionary bonus", "Perform general clerical duties", "F.5 HKCEE / F.6 HKDSE or above"], "locations": ["Wan Chai"], "categories": ["Admin & HR", "Clerical / Admin Staff", "Banking / Finance", "Loan", "Sales, CS & Business Devpt", "Customer Service - Supervisor / Officer"], "post_time": "2022-01-17T07:16:33Z", "salary": {"currency": null, "max": null, "min": null, "period": "monthly", "term": null}, "salary_visible": false, "title_keywords": ["associate", "assistant"], "responsibilities": ["provide customer service"], "requirements": {"degrees": ["hkdse"], "majors": [], "languages": ["english", "chinese"], "language_level": ["fluent"], "hard_skills": [], "soft_skills": ["customer service", "willing to learn", "mature", "interpersonal skill"], "languages_combined": [{"language": "english", "language_level": ["fluent"]}, {"language": "chinese", "language_level": ["fluent"]}]}, "experience_required": {"duration": ["at least 1 year"], "field": ["loan business", "customer service"]}}, {"job_id": "100003009052894", "location_code": "hk", "company": "United Overseas Bank Limited", "job_title": "Contract Assistant Vice President, Wholesale Loan Operations (1-year)", "description": "Job Responsibilities\n\n-\u00a0\u00a0\u00a0\u00a0\u00a0\u00a0\u00a0\u00a0\u00a0 Process daily loan operation covering bilateral and syndication loan\n\n-\u00a0\u00a0\u00a0\u00a0\u00a0\u00a0\u00a0\u00a0\u00a0 Act as payment bank role and handle syndicated loan payments\n\n-\u00a0\u00a0\u00a0\u00a0\u00a0\u00a0\u00a0\u00a0\u00a0 Maintain proper loan archival records\n\n-\u00a0\u00a0\u00a0\u00a0\u00a0\u00a0\u00a0\u00a0\u00a0 Prepare all loan administration related instructions.\n\n-\u00a0\u00a0\u00a0\u00a0\u00a0\u00a0\u00a0\u00a0\u00a0 Prepare internal and external reports\n\n-\u00a0\u00a0\u00a0\u00a0\u00a0\u00a0\u00a0\u00a0\u00a0 Provide enquiry feedback to internal and external customers\n\nJob Requirements\n\n-\u00a0\u00a0\u00a0\u00a0\u00a0\u00a0\u00a0\u00a0\u00a0 University graduate in Business disciplines\n\n-\u00a0\u00a0\u00a0\u00a0\u00a0\u00a0\u00a0\u00a0\u00a0 At least 5 years\u2019 experience in corporate banking loan operations\n\n-\u00a0\u00a0\u00a0\u00a0\u00a0\u00a0\u00a0\u00a0\u00a0 Good knowledge of banking practices, operations and procedures\n\n-\u00a0\u00a0\u00a0\u00a0\u00a0\u00a0\u00a0\u00a0\u00a0 Strong team player and ability to foster teamwork\n\n-\u00a0\u00a0\u00a0\u00a0\u00a0\u00a0\u00a0\u00a0\u00a0 Proficient in MS Office suite of applications\n\n-\u00a0\u00a0\u00a0\u00a0\u00a0\u00a0\u00a0\u00a0\u00a0 Excellent communication and interpersonal skills", "employment_types": ["Full Time", "Contract"], "selling_points": ["Loan Operations", "Wholesale Banking Focus", "Comprehensive Renumerations & Convenient Location"], "locations": ["Causeway Bay"], "categories": ["Banking / Finance", "Loan", "Order Processing & Operation / Settlement"], "post_time": "2022-01-17T04:27:25Z", "salary": {"currency": null, "max": null, "min": null, "period": "monthly", "term": null}, "salary_visible": false, "title_keywords": ["operations", "assistant vice president"], "responsibilities": ["internal and external customers", "payment", "maintain", "payments", "reports", "administration"], "requirements": {"degrees": ["university graduate"], "majors": ["business"], "languages": [], "language_level": [], "hard_skills": ["ms office"], "soft_skills": ["team player", "teamwork", "communication and interpersonal skills"], "languages_combined": []}, "experience_required": {"duration": ["at least 5 years"], "field": ["banking"]}}, {"job_id": "100003009054803", "location_code": "hk", "company": "Public Finance Limited", "job_title": "Direct Sales Supervisor (Personal Loan)", "description": "Responsibilities\nTo be responsible for achieving sales target of the team\nTo source and provide training to Direct Sales Executives\nRequirements\nMinimum 2 years relevant experience at supervisory level in the financial industry\nBasic salary plus high commission\nApplication Method:\nBy E-mail via \"Apply Now\"\nWhatsapp : 9309 2925\nPersonal data collected will be treated in the strictest confidence in accordance with our\u00a0Personal Information Collection Statement\u00a0and\u00a0Privacy Policy\u00a0and will be handled by authorized personnel for recruitment-related purposes only. All applications will be kept for a maximum period of one year as may be considered for other suitable positions within Public Finance Ltd. and its associated companies. For details, please visit the Company\u2019s website\u00a0http://www.publicfinance.com.hk", "employment_types": ["Full Time", "Permanent"], "selling_points": [], "locations": ["Not Specified"], "categories": ["Banking / Finance", "Loan", "Sales, CS & Business Devpt", "Others", "Direct Sales"], "post_time": "2022-01-17T11:09:55Z", "salary": {"currency": null, "max": null, "min": null, "period": "monthly", "term": null}, "salary_visible": false, "title_keywords": ["personal", "sales supervisor"], "responsibilities": ["provide training", "sales target"], "requirements": {"degrees": [], "majors": [], "languages": [], "language_level": [], "hard_skills": ["whatsapp", "plus", "basic"], "soft_skills": ["confidence"], "languages_combined": []}, "experience_required": {"duration": ["minimum 2 years"], "field": ["supervisory level", "financial industry", "relevant experience"]}}, {"job_id": "100003009053877", "location_code": "hk", "company": "JAC Recruitment Hong Kong Co., Limited", "job_title": "Product Manager (VP - Team Head) - ESG (Environmental, Social & Governance) - Corporate Banking", "description": "Our client is a fast growing foreign bank. They are looking for someone to join as a Product Manager (VP - Team Head) - ESG (Environmental, Social & Governance) - Corporate Banking.\u00a0\n\nKey Responsibilities\n\n\n- To help RMs to structure and joint pitch SLL and green loans.\u00a0\n\n- Ideally, being able to help the bank's Greater China's region to set up ESG product manual, writeups for various ESG presentations.\u00a0\n\n-\u00a0Promote Corporate Banking products e.g.\u00a0Syndicated-Loan, Club Loan, Bilateral Loan, and Structured Finance\n\n-\u00a0Knowledge in banking facilities and credit proposal\n\n\n\n\nRequirements\n\n- Around 4-12 years (Manager - Team Head) experience in Corporate Banking,\u00a0specializing in ESG.\u00a0\n\n-\u00a0Degree holder in Business Administration or related disciplines;\n\n-\u00a0Fluent in English, Cantonese and Mandarin\n\n\n*We offer*\n\n\"Interested candidates, please send an updated CV to kelvin.lam @jac-recruitment.com and CC jac.hk @jac-recruitment.com\"\n\nPersonal data collected will be used for employment-related purpose only. We regret to inform that only shortlisted candidates will be notified.", "employment_types": ["Full Time"], "selling_points": ["A fast growing Foreign Bank", "ESG (Environmental, Social & Governance)", "Syndicated-Loan, Club Loan, Bilateral Loan"], "locations": ["Central & Western Area"], "categories": ["Banking / Finance", "Corporate Banking", "Credit Analysis / Approval", "Loan"], "post_time": "2022-01-17T07:40:32Z", "salary": {"currency": null, "max": null, "min": null, "period": "monthly", "term": null}, "salary_visible": false, "title_keywords": ["product manager"], "responsibilities": ["presentations", "banking"], "requirements": {"degrees": ["degree holder"], "majors": ["related disciplines", "business administration"], "languages": ["cantonese", "english", "mandarin"], "language_level": ["fluent"], "hard_skills": [], "soft_skills": [], "languages_combined": [{"language": "cantonese", "language_level": ["fluent"]}, {"language": "english", "language_level": ["fluent"]}, {"language": "mandarin", "language_level": ["fluent"]}]}, "experience_required": {"duration": ["4-12 years"], "field": ["banking", "team"]}}, {"job_id": "100003009054807", "location_code": "hk", "company": "Public Finance Limited", "job_title": "Telemarketing Executives (Personal Loan)", "description": "Responsibilities\nTo make warm calls for selling the company\u2019s financial products\nRequirements\nSecondary education\nGood telesales experience in banking and finance industry is preferred\nGood communication skills, sales-oriented\nWork in Central Office\nBenefits\nInsurance Benefits\nStudy subsidy\nIncentive Scheme\nApplication Method:\nBy E-mail via \"Apply now\"\u00a0or\nWhatsapp : 9309 2925\nPersonal data collected will be treated in the strictest confidence in accordance with our\u00a0Personal Information Collection Statement\u00a0and\u00a0Privacy Policy\u00a0and will be handled by authorized personnel for recruitment-related purposes only. All applications will be kept for a maximum period of one year as may be considered for other suitable positions within Public Finance Ltd. and its associated companies. For details, please visit the Company\u2019s website\u00a0http://www.publicfinance.com.hk", "employment_types": ["Full Time", "Permanent"], "selling_points": [], "locations": ["Central"], "categories": ["Banking / Finance", "Loan", "Financial Services", "Sales, CS & Business Devpt", "Tele-sales (Telemarketing)"], "post_time": "2022-01-17T11:12:26Z", "salary": {"currency": null, "max": null, "min": null, "period": "monthly", "term": null}, "salary_visible": false, "title_keywords": ["personal", "telemarketing"], "responsibilities": [], "requirements": {"degrees": ["secondary education"], "majors": [], "languages": [], "language_level": [], "hard_skills": [], "soft_skills": ["communication skills"], "languages_combined": []}, "experience_required": {"duration": [], "field": ["finance industry", "telesales", "banking"]}}, {"job_id": "100003009049467", "location_code": "hk", "company": "Hang Seng Bank Ltd", "job_title": "Assistant Personal Loan Products Manager", "description": "Personal Banking Products\n\nHang Seng's Unsecured Loans business offers a full spectrum of cards and personal loan products and services to customers.\n\nWe have over 20 card products, including generic credit cards, co-branded credit cards, affinity cards and commercial cards, and are one of the leading credit card issuers in the market. We are dedicated to offering customers superior credit card services and loyalty schemes, with an aim of enabling customers to get the most out of their day-to-day spending.\n\nOur Unsecured Personal Loan services offer installment loans, revolving loans, and overdraft facilities to meet the financial needs of customers at all levels.\n\nWe are currently seeking high caliber professionals to join our department as Assistant Personal Loan Products Manager.\u00a0\n\nPrincipal responsibilities\n\nResponsible for the planning and execution of Personal Lending\u2019s\u2019 acquisition and portfolio management initiatives in all channels to achieve business target within the budget\nResponsible for the performance of unsecured personal lending products and participate in product development and system enhancement projects to enhance product features, improve customer journey and comply with regulatory requirements\nPerform market and portfolio analysis for formulating business strategies\nLiaise with different sales channels and operations to develop efficient and effective sales and operating workflows\nWork with different channels including telesales and digital banking to drive business from new customers and boost cross selling opportunities from existing customer base\nMonitor the performance of sales channels and evaluate programs results\nRequirements\nUniversity degree in a related discipline or other relevant qualification\nMinimum 2 years of retail banking experience, exposure in personal loan products would be an advantage\nStrong product development and project management skills\nStrong team orientation, with good communication and interpersonal skills\nProficiency in both English and Chinese\nGreat sense of ownership and servicing mindset to ensure efficient and effective customer service processes\n\nIf you would like to explore other opportunities at Hang Seng Hong Kong, please visit www.hangseng.com/careers/ for details.\n\nThe health and safety of our employees and candidates is very important to us. Due to the current situation related to the Novel Coronavirus (2019-nCoV), we\u2019re leveraging our digital capabilities to ensure we can continue to recruit top talent at the HSBC Group. As your application progresses, you may be asked to use one of our digital tools to help you through your recruitment journey. If so, one of our Resourcing colleagues will explain how our video-interviewing technology will be used throughout the recruitment process and will be on hand to answer any questions you might have.\n\nAll information provided by applicants will be used only for recruitment purposes and will be used strictly in accordance with the Bank's personal data policies, a copy of which may be obtained by the applicant upon request. Unless otherwise instructed in writing by the applicant concerned, applicants may be considered for other suitable positions within the Bank and its related companies. The personal data of unsuccessful job applicants may be retained for a maximum of two years from the date when the job application is rejected and such data may be retained for a longer period if there is a subsisting reason that obliges the Bank to do so, after which the personal data will be destroyed.", "employment_types": ["Full Time", "Permanent"], "selling_points": [], "locations": ["Not Specified"], "categories": ["Banking / Finance", "Loan", "Financial Services", "Others"], "post_time": "2022-01-17T02:27:13Z", "salary": {"currency": null, "max": null, "min": null, "period": "monthly", "term": null}, "salary_visible": false, "title_keywords": ["personal", "manager", "assistant"], "responsibilities": ["management", "regulatory requirements", "analysis", "budget", "operations", "develop", "evaluate", "monitor the performance", "banking", "liaise with", "enhancement projects", "planning"], "requirements": {"degrees": ["university degree"], "majors": [], "languages": ["english", "chinese"], "language_level": ["proficiency"], "hard_skills": ["project management", "loan products", "reason"], "soft_skills": ["efficient", "project management skills", "communication and interpersonal skills", "customer service", "novel"], "languages_combined": [{"language": "english", "language_level": ["proficiency"]}, {"language": "chinese", "language_level": ["proficiency"]}]}, "experience_required": {"duration": ["minimum 2 years"], "field": ["retail banking"]}}, {"job_id": "100003009052473", "location_code": "hk", "company": "Hong Kong Huafa Investment Holdings Limited", "job_title": "Treasury/ Finance Manager \u8cc7\u91d1\u7ba1\u7406\u7d93\u7406", "description": "Hong Kong Huafa Investment Holdings Ltd. is a key platform for Huafa Group to reach out to the overseas market. Representing Huafa Group, Hong Kong Huafa is responsible for overseas investments, cross-border lending and listings of core assets. To meet the demands of growing business, we are now seeking a high-caliber finance professional to join our Treasury Team, this position will support all treasury operation activities for the Hong Kong Huafa and subsidiaries of Huafa Group.\n\nJob Duties\n\nDevelop and maintain networks and collaborative partnerships with financial institutions\nExplore and identify potential business opportunities, including but not limited to, corporate lending, structured transactions, syndications, treasury, trade financing and other financial products\nPrepare and review documentation in relation to bank accounts management and financing activities\nManage cash flow and budgeting with accurate forecasting\nPerform ad hoc duties as assigned\nRequirements\n\nBachelor degree or above in Business Administration, Finance, Accounting or a related discipline\nAt least 3 years' experience in corporate lending\nProficient in both spoken and written English and Chinese, Putonghua is preferred\nAbility to work independently and be able to work under pressure, with good communication, interpersonal and analytical skills\nCandidate with more experience will be considered as Manager/ Senior Manager\n\u5de5\u4f5c\u8077\u8cac\n\n\u8207\u91d1\u878d\u6a5f\u69cb\u7dad\u6301\u826f\u597d\u7684\u5408\u4f5c\u95dc\u4fc2\n\u63a2\u7d22\u4f01\u696d\u8cb8\u6b3e\u3001\u7d50\u69cb\u6027\u4ea4\u6613\u3001\u8cc7\u91d1\u7ba1\u7406\u3001\u8cbf\u6613\u878d\u8cc7\u3001\u5176\u4ed6\u91d1\u878d\u7522\u54c1\u7b49\u7684\u5546\u696d\u6a5f\u6703\n\u6e96\u5099\u53ca\u8986\u6838\u9280\u884c\u53ca\u878d\u8cc7\u6d3b\u52d5\u76f8\u95dc\u6587\u4ef6\n\u5354\u52a9\u73fe\u91d1\u6d41\u91cf\u9810\u6e2c\u53ca\u8ca1\u52d9\u9810\u7b97\u7684\u7ba1\u7406\n\u5b8c\u6210\u4e0a\u53f8\u4ea4\u8fa6\u7684\u5176\u4ed6\u5de5\u4f5c\u53ca\u9805\u76ee\n\u4efb\u8077\u8981\u6c42\n\n\u5927\u5b78\u672c\u79d1\u6216\u4ee5\u4e0a\u5b78\u6b77\uff0c\u4fee\u8b80\u5de5\u5546\u7ba1\u7406\u3001\u91d1\u878d\u3001\u6703\u8a08\u6216\u76f8\u95dc\u5c08\u696d\u7562\u696d\n\u81f3\u5c113\u5e74\u7684\u516c\u53f8\u8cb8\u6b3e\u76f8\u95dc\u5de5\u4f5c\u7d93\u9a57\n\u7cbe\u901a\u4e2d\u82f1\u6587\u53e3\u8a9e\u548c\u66f8\u5beb\uff0c\u719f\u6089\u666e\u901a\u8a71\u8005\u5c07\u7372\u512a\u5148\u8003\u616e\n\u5177\u826f\u597d\u7684\u5206\u6790\u80fd\u529b\u3001\u7368\u7acb\u5de5\u4f5c\u80fd\u529b\u3001\u4eba\u969b\u6e9d\u901a\u80fd\u529b\uff0c\u80fd\u7368\u7acb\u5de5\u4f5c\uff0c\u4e26\u627f\u53d7\u58d3\u529b\n\u5177\u8f03\u9ad8\u8cc7\u6b77\u7684\u7533\u8acb\u4eba\u53ef\u7372\u8003\u616e\u8058\u7528\u70ba\u7d93\u7406\uff0f\u9ad8\u7d1a\u7d93\u7406\n\nWe offer attractive remuneration package to the right candidates, including year-end double pay, discretionary bonus, allowances, group medical insurance, annual health check, and etc. Interested parties please apply directly by clicking \"Apply Now\".", "employment_types": ["Full Time", "Permanent"], "selling_points": ["Candidates with strong treasury exposure preferred", "At least 3 years' experience in corporate lending", "Nurturing professional in treasury team"], "locations": ["Central"], "categories": ["Accounting", "Finance / Accounting Manager", "Banking / Finance", "Loan", "Treasury"], "post_time": "2022-01-17T03:07:22Z", "salary": {"currency": null, "max": null, "min": null, "period": "monthly", "term": null}, "salary_visible": false, "title_keywords": ["finance manager"], "responsibilities": ["ad hoc duties", "management", "budgeting", "business opportunities", "review", "transactions", "develop", "cash flow", "maintain", "documentation", "forecasting"], "requirements": {"degrees": ["degree or above", "bachelor"], "majors": ["finance", "accounting", "business administration"], "languages": ["putonghua", "english", "chinese"], "language_level": ["proficient"], "hard_skills": ["analytical skills"], "soft_skills": ["work independently", "analytical skills", "communication", "interpersonal", "work under pressure"], "languages_combined": [{"language": "putonghua", "language_level": ["proficient"]}, {"language": "english", "language_level": ["proficient"]}, {"language": "chinese", "language_level": ["proficient"]}]}, "experience_required": {"duration": ["at least 3 years"], "field": []}}, {"job_id": "100003009050031", "location_code": "hk", "company": "Hong Kong Finance Company Limited", "job_title": "Administration Officer", "description": "Responsibilities:\n\nHandle loan administration operations i.e. loan drawdown / filing\nCoordinate with outside professionals to follow up the progress of the Loan and Legal documents\nCoordinate with other teams for internal system checking, data input etc.\nHandle any ad hoc projects and tasks whenever necessary\n\nRequirements:\n\nDiploma holder or above\nRelevant working experience in banks or financial institutions is preferred\nGood command of in English and Chinese;\nWell organized, detailed minded, self-motivated, independent and able to work under pressure\nGood interpersonal and communication skills\nProficient in MS office", "employment_types": ["Full Time"], "selling_points": ["Handle loan administration operations", "Coordinate with outside professionals", "Handle any ad hoc projects"], "locations": ["Admiralty"], "categories": ["Admin & HR", "Clerical / Admin Staff", "Banking / Finance", "Loan", "Financial Services"], "post_time": "2022-01-14T09:40:09Z", "salary": {"currency": null, "max": null, "min": null, "period": "monthly", "term": null}, "salary_visible": false, "title_keywords": ["administration officer"], "responsibilities": ["operations", "teams", "coordinate with", "checking", "data input", "ad hoc projects", "administration"], "requirements": {"degrees": ["diploma holder"], "majors": [], "languages": ["english", "chinese"], "language_level": ["good command"], "hard_skills": ["ms office"], "soft_skills": ["communication skills", "self-motivated", "independent", "well organized", "detailed", "interpersonal", "work under pressure"], "languages_combined": [{"language": "english", "language_level": ["good command"]}, {"language": "chinese", "language_level": ["good command"]}]}, "experience_required": {"duration": [], "field": ["financial institutions", "relevant working experience"]}}, {"job_id": "100003009054764", "location_code": "hk", "company": "Fillture Group Limited", "job_title": "General Manager - FinTech", "description": "A FinTech group is looking for General Manager to join their team. This role will be\u00a0develop action plan for consumer business to improve productivity, make recommendations on modification of procedures and application of technology to enhance operational efficiency and minimize operational risk.\n\nResponsibilities:\n\nFormulate the business plan, corporate strategies and policies according to the group annual objectives, monitoring their implementation and timely report to CEO.\nMonitor the achievement status of KPI\u2019s closely, analyze and make suggestions to different departments and subordinates to improve performance.\nReport the business performance to CEO regularly, adjust business strategies in a timely manner according to the actual operating situation.\nParticipate in thematic meetings in order to discuss the operation matters and development of various projects.\nReview and approve for the staffing plan, performance evaluation and make recommendations based on the result of appraisal.\nEssential to promote and establish a good communication and working atmosphere.\nKeep updated in industry news and local policies, organize various departments to conduct market research and new product development.\nRequirements:\n\nBachelor degree or above, majoring in Business Administration, Finance, Economics, or the relevant\n10 years or above working experience in Finance companies or banks; preferably the relevant experience in running mortgage and unsecured personal loan business\n\u00a0At least 5 years role as senior executive position of Finance companies or banks\nFamiliar with the financial market crossing Mainland and Hong Kong, good connections with target clients, strong financial business development capability\nCompetence in FinTech is necessary; Sales-oriented with strong marketing skills\nExcellent team management capability and cross-cultural communication and coordination capability\nGood computer skills and experienced in MS Office applications\nFluent in written and spoken English & Mandarin\nActive and Open-minded; Process work in a timely, punctual manner\n\nApply for this job:\n\nInterested candidate please CLICK apply button to apply online or send your resume in MS word format to Fillture Group Limited\n\nFor more information, please contact\u00a0Danvis Lau\u00a0+852 2814 9388.\n\nPlease note that only shortlisted candidate will be notified. All information will be treated in strict confidence and solely used for recruitment purposes.", "employment_types": ["Full Time", "Permanent"], "selling_points": ["FinTech Company", "Experienced in consumer loans", "Attractive Salary Package and Benefits"], "locations": ["Central & Western Area"], "categories": ["Banking / Finance", "Loan", "Financial Services", "Management", "General Management"], "post_time": "2022-01-17T10:58:45Z", "salary": {"currency": null, "max": null, "min": null, "period": "monthly", "term": null}, "salary_visible": false, "title_keywords": ["general manager"], "responsibilities": ["make recommendations", "policies", "conduct market research", "monitoring", "monitor", "implementation", "a timely manner", "review", "communication", "plan", "evaluation", "business plan", "report"], "requirements": {"degrees": ["degree or above", "bachelor"], "majors": ["finance", "economics", "business administration"], "languages": ["english", "mandarin"], "language_level": ["fluent"], "hard_skills": ["ms word", "marketing skills", "computer skills", "ms office"], "soft_skills": ["confidence", "open-minded", "timely", "communication", "coordination", "active"], "languages_combined": [{"language": "english", "language_level": ["fluent"]}, {"language": "mandarin", "language_level": ["fluent"]}]}, "experience_required": {"duration": ["10 years"], "field": ["loan business", "finance", "relevant experience"]}}, {"job_id": "100003009047370", "location_code": "hk", "company": "Ego Finance Limited", "job_title": "\u8cb8\u6b3e\u4e3b\u4efb / \u52a9\u7406\u8cb8\u6b3e\u4e3b\u4efb / \u8cb8\u6b3e\u6587\u54e1 \u2013 \u6309\u63ed\u90e8", "description": "\u8077\u8cac :\n\n\u63a5\u898b\u5ba2\u4eba\u53ca\u89e3\u7b54\u5ba2\u6236\u4e00\u822c\u8aee\u8a62\n\u8655\u7406\u8cb8\u6b3e\u7533\u8acb\n\u8655\u7406\u65e5\u5e38\u96fb\u8166\u53ca\u6587\u66f8\u5de5\u4f5c\n\u96fb\u8a71\u63a8\u5ee3\n\u8981\u6c42 :\n\n\u6b61\u8fce\u61c9\u5c46\u7562\u696d\u751f\n\u4e2d\u4e94\u7a0b\u5ea6\u3001\u5177\u67092\u5e74\u6216\u4ee5\u4e0a\u91d1\u878d/\u6309\u63ed\u8cb8\u6b3e\u76f8\u95dc\u7d93\u9a57\u6703\u88ab\u4f5c\u512a\u5148\u8003\u616e\n(\u5c11\u65bc2\u5e74\u76f8\u95dc\u7d93\u9a57\u53ef\u8003\u616e\u70ba\u8cb8\u6b3e\u6587\u54e1)\n\u8aa0\u5be6\u3001\u5c0d\u5de5\u4f5c\u71b1\u8aa0\u3001\u6709\u8cac\u4efb\u611f\n\u6d41\u5229\u7cb5\u8a9e\u3001\u6709\u826f\u597d\u6e9d\u901a\u53ca\u8868\u9054\u80fd\u529b (\u6709\u96fb\u8a71\u92b7\u552e\u7d93\u9a57\u66f4\u4f73)\n\u57fa\u672c\u96fb\u8166\u77e5\u8b58 (\u5305\u62ec\u4e2d\u6587\u8f38\u5165\u6cd5 <\u5009\u9821/\u901f\u6210>\u3001MS Word\u548cMS Excel)\n\u5f85\u9047 :\n\n\u7af6\u722d\u529b\u85aa\u916c\n\u5e74\u7d42\u82b1\u7d05\n\u9280\u884c\u5047\u671f\n\u6709\u85aa\u5e74\u504710\u81f316\u5929\n\u9577\u77ed\u9031\n\u91ab\u7642\u6d25\u8cbc\u53ca\u4f4f\u9662\u4fdd\u96aa\n\u751f\u65e5\u5047\n\u5a5a\u5047\n\u6069\u6064\u5047\n\u5165\u8077\u5c08\u4eba\u57f9\u8a13\n\u826f\u597d\u6649\u5347\u6a5f\u6703\n\u9032\u4fee\u6d25\u8cbc\uff0c\u8207\u6642\u589e\u503c\n\u5de5\u4f5c\u6642\u9593\uff1a\n\n\u661f\u671f\u4e00\u81f3\u4e94 : \u4e0a\u53489\u6642\u81f3\u4e0b\u53486\u6642 (\u5305\u542b1\u5c0f\u664210\u5206\u9418\u5348\u81b3\u6642\u9593)\n\u661f\u671f\u516d\u00a0 \u00a0 \u00a0 \u00a0 \u00a0: \u4e0a\u53489\u6642\u81f3\u4e0b\u53481\u6642 (\u9031\u516d\u9577\u77ed\u9031)\n\u6709\u610f\u61c9\u5fb5\u8005\u8acb\u9644\u4e0a\u95a3\u4e0b\u4e4b\u8a73\u7d30\u7684\u5c65\u6b77\u8868\u3001\u53ef\u5230\u8077\u65e5\u671f\u548c\u8981\u6c42\u5f85\u9047\u4f5c\u70ba\u8a55\u5be9\u4e4b\u7528\u3002 \uff0a\uff0a\u6240\u6709\u500b\u4eba\u8cc7\u6599\u53ea\u6703\u7528\u4f5c\u62db\u8058\u7528\u9014\uff0a\uff0a\n", "employment_types": ["Full Time"], "selling_points": [], "locations": ["Mong Kok"], "categories": ["Banking / Finance", "Loan", "Mortgage", "Others"], "post_time": "2022-01-14T02:55:58Z", "salary": {"currency": null, "max": null, "min": null, "period": "monthly", "term": null}, "salary_visible": false, "title_keywords": [], "responsibilities": [], "requirements": {"degrees": [], "majors": [], "languages": [], "language_level": [], "hard_skills": ["excel"], "soft_skills": [], "languages_combined": []}, "experience_required": {"duration": [], "field": []}}, {"job_id": "100003009051050", "location_code": "hk", "company": "The Wharf Group", "job_title": "Treasury Operation Officer", "description": "Responsibilities :\n\nResponsible for coordinating with banks on daily funding arrangement, payment settlement for various transactions, loan administration and related documentation, deposit placement, inter-company transfer transactions, and preparation of treasury reports.\u00a0 \u00a0\u00a0\n\n\nRequirements :\nDegree holders in related disciplines with 5 years\u2019 relevant experience preferably acquired from large corporations or banks.\u00a0 Possessing good communication, interpersonal, analytical and problem-solving skills; self-motivated, well organized, detail-minded, proficient in English and Chinese and having advanced knowledge of Microsoft Word and Excel.\u00a0\nCandidates with less experience may be considered as Assistant Treasury Operation Officer.\n\n\nWe work 5 days per week.\n\n\nInterested parties, please click \"APPLY NOW\" and attach with your application letter and full resume.\n\n\nFor further information of the Wharf Group, please visit our website: www.wharfholdings.com", "employment_types": ["Full Time", "Permanent"], "selling_points": [], "locations": ["Tsim Sha Tsui"], "categories": ["Banking / Finance", "Loan", "Treasury", "Fund Management"], "post_time": "2022-01-15T19:11:47Z", "salary": {"currency": null, "max": null, "min": null, "period": null, "term": null}, "salary_visible": false, "title_keywords": ["operation officer"], "responsibilities": ["related documentation", "transactions", "payment", "reports", "administration"], "requirements": {"degrees": ["degree"], "majors": ["related disciplines"], "languages": ["english", "chinese"], "language_level": ["proficient"], "hard_skills": ["problem-solving skills", "microsoft word", "excel"], "soft_skills": ["detail-minded", "self-motivated", "advanced", "well organized", "communication", "problem-solving skills", "interpersonal"], "languages_combined": [{"language": "english", "language_level": ["proficient"]}, {"language": "chinese", "language_level": ["proficient"]}]}, "experience_required": {"duration": ["5 years"], "field": ["related", "operation", "relevant experience"]}}, {"job_id": "100003009049839", "location_code": "hk", "company": "Wang On Financial Services Management Limited", "job_title": "Mortgage \u2013 Business Development Manager", "description": "Job Description\n\nTo handle mortgage referral applications and enquiries;\nIdentify sales opportunities and develop new business in mortgage\nTo solicit and generate revenue growth on mortgage loan business through various sales activities;\nTo establish and develop a good business relationship with referral parties including mortgage intermediaries, property agencies, mortgage brokers, banks and other sales channels;\nTo achieve individual targets on mortgage lending;\nTo evaluate potential credit risk to ensure loan proceedings in compliance with procedural and documentation requirements;\n\n\nRequirements\n\nAt least 5 years\u2019 experience gained from local money lender companies in mortgage loan development business;\nGood track record in mortgage sales, with extensive network with mortgage intermediaries/agents/banks/property agencies;\nWith a strong potential client network is an advantage;\nGood communication, presentation and interpersonal skills;\nProactive, motivated, good market sense and sales-oriented;\nGood command of both spoken and written English and Chinese;\nImmediate available is highly preferred\n\nWe offer competitive remuneration package, our benefits include:\n\nPerformance bonus\nEducation subsidy\nProfessional membership fee sponsorship\nLife & medical insurance\nMarriage Leave, Compassionate Leave, Examination Leave etc.\nPublic holidays\nStaff purchase discount\n\nInterested parties please send full resume with present and expected salary to Human Resources Department by clicking\u00a0Apply Now.\n\n(Information provided will be treated in strict confidence and will only be used for recruitment-related purposes.)", "employment_types": ["Full Time", "Permanent"], "selling_points": [], "locations": ["Sheung Wan"], "categories": ["Banking / Finance", "Loan", "Mortgage"], "post_time": "2022-01-14T09:18:43Z", "salary": {"currency": null, "max": null, "min": null, "period": "monthly", "term": null}, "salary_visible": false, "title_keywords": ["business development manager"], "responsibilities": ["sales activities", "develop new business", "compliance", "develop", "evaluate", "revenue growth", "documentation"], "requirements": {"degrees": [], "majors": [], "languages": ["english", "chinese"], "language_level": ["good command"], "hard_skills": [], "soft_skills": ["communication", "motivated", "interpersonal skills", "proactive", "extensive", "presentation"], "languages_combined": [{"language": "english", "language_level": ["good command"]}, {"language": "chinese", "language_level": ["good command"]}]}, "experience_required": {"duration": ["at least 5 years"], "field": ["development", "business"]}}, {"job_id": "100003009049886", "location_code": "hk", "company": "Waion Solutions Limited", "job_title": "Customer Service Officer - SME and Personal Loan Banking (Ref: 11892)", "description": "Summary:\nOur client is a large-scale MNC bank. They're currently hiring Assistant Officers, to support their administration and wealth management back office operations. We hope to gather talents here and offer the opportunity to generate remarkable results together.\n\nResponsibilities:\n\nProvide daily customer services backup and center operational support, load operations data entry\nProvide admin support to Small Enterprise (SME) and Personal Load Center\nHandle customer enquiries\nPerform KYC support duties, prepare and file reports\nEnsure compliance with regulatory requirements as well as internal compliance policies and guidelines\nAny ad-hoc projects as assigned\u00a0\n\nRequirements:\n\nDSE graduate / High Diploma or above\u00a0\nCandidates with prior experience in customer service preferred\nExperience in loan operation would be a great advantage\nIndependent, responsible\u00a0and self-motivated\nGood analytical and problem-solving skills\u00a0\nStrong PC skills and proficient in MS application, and Chinese Word Processing\nGood communication skills of both written and spoken English and Chinese\u00a0\nIf you have the desire for a challenging and rewarding career development, send us your resume quoting your present and expected salary\n\nby clicking\u00a0\"Apply Now\"\u00a0\n* Information collected will only be used for recruitment purpose *", "employment_types": ["Full Time", "Contract"], "selling_points": ["Banking Customer Service", "Handle customer inquiries", "5 days work week, Medical, Bank holidays"], "locations": ["Mong Kok"], "categories": ["Banking / Finance", "Loan", "Private Banking", "Retail Banking"], "post_time": "2022-01-14T09:32:58Z", "salary": {"currency": null, "max": null, "min": null, "period": "monthly", "term": null}, "salary_visible": false, "title_keywords": ["personal", "customer service officer"], "responsibilities": ["operational support", "handle customer enquiries", "data entry", "guidelines", "operations", "regulatory requirements", "compliance", "policies", "customer services", "ensure compliance", "admin support", "reports", "kyc", "sme", "ad-hoc projects"], "requirements": {"degrees": ["high diploma or above", "dse"], "majors": [], "languages": ["english", "chinese"], "language_level": ["good", "proficient"], "hard_skills": ["problem-solving skills", "pc skills", "chinese word processing", "ms application"], "soft_skills": ["communication skills", "self-motivated", "independent", "responsible", "customer service", "problem-solving skills"], "languages_combined": [{"language": "english", "language_level": ["good"]}, {"language": "chinese", "language_level": ["good", "proficient"]}]}, "experience_required": {"duration": [], "field": ["operation", "customer service"]}}, {"job_id": "100003009053971", "location_code": "hk", "company": "\u5fc5\u9ad8\u4eba\u4e8b\u9867\u554f\u6709\u9650\u516c\u53f8", "job_title": "Senior Officer \u2013 Remittance Department", "description": "Our client is a reputable Bank, now they are seeking a professional to join their Remittance Department.\n\n\n\nResponsibilities\n\nHandle remittance transactions in professional manner;\nConduct customer contact and handle customer enquires;\nPrepare daily and management reports;\nHandle system enhancement projects from time to time;\nComplete work tasks as assigned by management and team leader.\n\nRequirements:\n\nPost-secondary education;\nMinimum 6 years of relevant experience;\nFamiliar with regulatory requirements of cross border Renminbi settlement as well as SWIFT/Telex handling;\nHands-on experience in trade or settlement transaction is an advantage;\nGood interpersonal and communication skills with good time management;\nGood command of spoken English, Cantonese, and Putonghua;\nCandidates with more experiencse can be considered as Manager.\n\nInterested parties please forward your CV in word format with current and expected salaries to PICCO Bent Consultancy Limited.\n\n[All applications will be treated with strict confidential and will be used for recruitment purposes only]", "employment_types": ["Full Time"], "selling_points": ["Familiar with cross border Renminbi settlement", "Familiar with SWIFT/Telex handling", "Handle system enhancement projects"], "locations": ["Admiralty"], "categories": ["Banking / Finance", "Loan", "Order Processing & Operation / Settlement"], "post_time": "2022-01-17T07:52:55Z", "salary": {"currency": null, "max": null, "min": null, "period": "monthly", "term": null}, "salary_visible": false, "title_keywords": ["senior officer"], "responsibilities": ["management", "professional manner", "transactions", "management reports", "contact", "enhancement projects"], "requirements": {"degrees": ["secondary education"], "majors": [], "languages": ["cantonese", "putonghua", "english"], "language_level": ["good command"], "hard_skills": ["swift"], "soft_skills": ["communication skills", "hands-on", "time management", "interpersonal"], "languages_combined": [{"language": "cantonese", "language_level": ["good command"]}, {"language": "putonghua", "language_level": ["good command"]}, {"language": "english", "language_level": ["good command"]}]}, "experience_required": {"duration": ["minimum 6 years"], "field": ["relevant experience"]}}, {"job_id": "100003009051838", "location_code": "hk", "company": "The Great Eagle Group of Companies", "job_title": "Manager - Treasury", "description": "Responsibilities:\n\nResponsible for routine treasury and loan transactions execution and administration including loan documentation negotiation, treasury dealing, KYC and compliance monitoring and relevant treasury reporting\nAssist in fund raising in bank loan market and international debt capital market\nAssist in managing all treasury functions including corporate liquidity, forex hedging, cash flow forecast and risk management\nDrive process and system improvement to increase data integrity and security\nAssist in managing banking relationship\nHandle ad hoc works as assigned by management\n\nRequirements:\n\nDegree holder in Accounting, Finance or other related disciplines\nHolder of CPA or CFA is an advantage\nMinimum 10 years\u2019 experience with corporate treasury, in-depth knowledge of debt, forex, derivative and cash management \u00a0\nStrong analytical and problem solving skills\nGood communication, presentation and interpersonal skills\nResponsible, well-organized, detail-minded, independent and able to work under pressure\nGood team player, willing to learn and take up new tasks\nProficiency in MS Office Applications\nGood command of both spoken and written\u00a0English\u00a0and Chinese (including Putonghua)\n\nSalary and benefits will be commensurate with qualifications and experience.\u00a0 Interested parties, please send a full resume with present and expected salary, and date available to The Human Resources Department, 32/F., Great Eagle Centre, 23 Harbour Road, Wanchai, Hong Kong or e-mail to us.\u00a0\u00a0(Please quote the reference no. on the envelope and the covering letter.)\n\nTo know more about us, please visit our websites at http://www.greateagle.com.hk\n\nWe are an equal opportunity employer and welcome applications from all qualified candidates.\n\nPersonal data collected will be treated in strict confidence and used only for recruitment-related purpose. Applicants who have not heard from us within four weeks may consider their applications unsuccessful. All personal data will be destroyed after 12 months.", "employment_types": ["Full Time", "Permanent"], "selling_points": ["Manage all corporate treasury functions", "Fund raising, debt capital market", "Holder of CPA or CFA is an advantage"], "locations": ["Wan Chai"], "categories": ["Accounting", "Consulting", "Banking / Finance", "Loan", "Dealing & Trading"], "post_time": "2022-01-17T01:20:52Z", "salary": {"currency": null, "max": null, "min": null, "period": "monthly", "term": null}, "salary_visible": false, "title_keywords": ["manager"], "responsibilities": ["reporting", "management", "ad hoc", "data", "compliance", "monitoring", "banking", "transactions", "cash flow", "forecast", "kyc", "documentation", "administration"], "requirements": {"degrees": ["degree holder"], "majors": ["related disciplines", "finance", "accounting"], "languages": ["putonghua", "english", "chinese"], "language_level": ["good command"], "hard_skills": ["cfa", "cpa", "problem solving skills", "ms office"], "soft_skills": ["detail-minded", "good team player", "independent", "responsible", "well-organized", "willing to learn", "communication", "analytical and problem solving skills", "interpersonal skills", "presentation", "work under pressure"], "languages_combined": [{"language": "putonghua", "language_level": ["good command"]}, {"language": "english", "language_level": ["good command"]}, {"language": "chinese", "language_level": ["good command"]}]}, "experience_required": {"duration": ["minimum 10 years"], "field": ["management"]}}, {"job_id": "100003009048086", "location_code": "hk", "company": "Hong Kong Credit Corporation Limited", "job_title": "Officer, Lending", "description": "As a maker role to develop loan applications by evaluating applicant information and documentation\n\nResponsibilities:\u00a0\n\nEvaluate and verify the loan applications and documentation by confirming credit worthiness\nAnalyze and determine the feasibility of granting loans\nEnsure the accuracy of data input and documentary preparation\nEnsure fully comply with both internal and external regulatory compliance requirements\nConduct a final review of the file before closing\nProvide administrative and operational support on business\nPerform other duties as assigned\n\nRequirements:\n\nF5/DSE or above graduate\nPossess accurate and efficient data entry and reporting skills\nGood analytical skills and good in details\nGood communication skills with good command of written and spoken English and Cantonese.\u00a0 Mandarin an added advantage\nProficiency in MS windows applications\nWilling to take initiative in improving work process and service delivery\nWork exposure in credit approval of consumer loans an advantage\nWe offer competitive remuneration including career prospects to the right candidate. Interested parties please send detailed resume with availability, current and expected salaries to\u00a0Human Resources Department, Hong Kong Credit Corporation Limited, Trust Tower, 68 Johnston Road, Wan Chai, Hong Kong\u00a0or by clicking the\u00a0Apply Now\u00a0button and upload your CV and cover letter.\n(All applications will be treated in strict confidence and used for recruitment purpose within\u00a0Hong Kong Credit Corporation Limited only. All applicants are kept on file 6 months from the date of the application.)", "employment_types": ["Full Time", "Permanent"], "selling_points": ["Evaluate and verify the loan applications", "Analyze the feasibility of granting loans", "Ensure the accuracy of data input"], "locations": ["Wan Chai"], "categories": ["Banking / Finance", "Loan", "Mortgage", "Sales, CS & Business Devpt", "Account Servicing"], "post_time": "2022-01-14T04:45:24Z", "salary": {"currency": null, "max": null, "min": null, "period": "monthly", "term": null}, "salary_visible": false, "title_keywords": ["officer"], "responsibilities": ["perform other duties", "operational support", "compliance", "review", "data input", "evaluate", "documentation"], "requirements": {"degrees": ["dse"], "majors": [], "languages": ["cantonese", "english", "mandarin"], "language_level": ["advantage", "good command", "good"], "hard_skills": ["ms windows", "analytical skills"], "soft_skills": ["efficient", "communication skills", "analytical skills", "accurate", "initiative"], "languages_combined": [{"language": "cantonese", "language_level": ["good command", "good"]}, {"language": "english", "language_level": ["good command", "good"]}, {"language": "mandarin", "language_level": ["advantage"]}]}, "experience_required": {"duration": [], "field": []}}, {"job_id": "100003009047618", "location_code": "hk", "company": "Wealth Dimensions Consultancy Limited", "job_title": "Credit Card / Personal Loan - Telesales, Telemarketing Officer (Bank - Call Centre) \u9280\u884c\u96fb\u8a71\u92b7\u552e\u4e3b\u4efb", "description": "Our client is leading bank in Hong Kong, and now looking for the High Calibre candidates to join their position of\u00a0Credit Card Loan / Personal Loan - Telesales, Telemarketing Officer\n\nResponsibilities:\nPromote credit card loan / personal loan over the phone for existing customers\nAchieve assigned sales target\n\u63a8\u5ee3\u4fe1\u7528\u5361\u8cb8\u6b3e/\u79c1\u4eba\u8cb8\u6b3e\u7d66\u73fe\u6709\u5ba2\u6237\n\u5b8c\u6210\u500b\u4eba\u92b7\u552e\u76ee\u6a19\nRequirements:\u00a0\nHKDSE/HKCEE or above\u00a0\n1 year of experience in sales, telesales, telemarketing or customer service\n\u4e2d\u5b78\u6703\u8003\u6216\u6587\u6191\u8a66\n\u4e00\u5e74\u92b7\u552e\u6216\u5ba2\u6237\u670d\u52d9\u7d93\u9a57", "employment_types": ["Full Time", "Permanent"], "selling_points": ["\u5e95\u85aa\u9023\u4f63\u91d1\u6708\u5165 20K - 40K", "\u9280\u884c\u798f\u5229", "\u63a8\u5ee3\u4fe1\u7528\u5361\u8cb8\u6b3e/\u79c1\u4eba\u8cb8\u6b3e\u7d66\u73fe\u6709\u5ba2\u6237"], "locations": ["Not Specified"], "categories": ["Banking / Finance", "Loan", "Retail Banking", "Wealth Management"], "post_time": "2022-01-14T03:35:14Z", "salary": {"currency": null, "max": null, "min": null, "period": "monthly", "term": null}, "salary_visible": false, "title_keywords": ["officer", "personal", "telemarketing", "telesales"], "responsibilities": ["sales target"], "requirements": {"degrees": ["hkdse"], "majors": [], "languages": [], "language_level": [], "hard_skills": [], "soft_skills": ["customer service"], "languages_combined": []}, "experience_required": {"duration": ["1 year"], "field": ["customer service", "telesales"]}}, {"job_id": "100003009051084", "location_code": "hk", "company": "ORIX Asia Limited", "job_title": "Senior Associate, Business Operations \u2013 Customer Services", "description": "Job\n\nPerform operations support to the team including customer services, custody and mortgage loan related matters in accordance with Company policies and procedures\n\n\u00a0Requirements\n\nMatriculated or above with relevant training in banking or finance\nMin. 2 years working experience in banking & finance industry with relevant experience in customer services or loan operations\nGood communication and interpersonal skills\nHigh integrity and initiative, good team-player, meticulous and able to work independently\nGood command of English and Chinese\nProficiency in MS Office application\n\n\n\nWe offer attractive remuneration and benefits, comprehensive career development opportunities and 5-day week to the qualified candidate.\n\nInterested parties please send detailed resume including current salary and expected salary to:\u00a0HR Dept, 25/F, Two Exchange Square, 8 Connaught Place, Central, HK\n\nAll personal information provided by applicants will be treated in strict confidence and used solely for recruitment purpose. All information of unsuccessful candidates will be destroyed within 12 months from the date of this advertisement.", "employment_types": ["Full Time", "Permanent"], "selling_points": [], "locations": ["Central"], "categories": ["Banking / Finance", "Loan"], "post_time": "2022-01-15T01:58:57Z", "salary": {"currency": null, "max": null, "min": null, "period": "monthly", "term": null}, "salary_visible": false, "title_keywords": ["senior associate", "operations"], "responsibilities": ["operations", "policies", "procedures", "customer services", "communication", "banking"], "requirements": {"degrees": [], "majors": [], "languages": ["english", "chinese"], "language_level": ["good command"], "hard_skills": ["ms office"], "soft_skills": ["meticulous", "work independently", "team-player", "integrity", "communication and interpersonal skills", "initiative"], "languages_combined": [{"language": "english", "language_level": ["good command"]}, {"language": "chinese", "language_level": ["good command"]}]}, "experience_required": {"duration": ["2 years"], "field": ["relevant experience", "customer services", "finance industry", "banking"]}}, {"job_id": "100003009050265", "location_code": "hk", "company": "China Construction Bank (Asia) Corporation Limited", "job_title": "Branch Sales Executive, Small Enterprise and Personal Loan Centre", "description": "Job Description:\n\nProactively solicit loan sales of unsecured personal loan and mortgage loan to customers, cross sell banking products including insurance and investment business and achieve designated sales objectives\nManage sales activities and performance, reach centre\u2019s agreed goals\nDemonstrate high quality services, establish, retain and build up customer relationships for contributing business and customer referrals\nPropose a tailored loan planning for customers according to their needs, handle customer\u2019s enquiries/complaints, resolves issues and follow up with customer\u2019s loan application to drawdown\nConduct outbound calls and perform outdoor marketing activities i.e. site promotion\nEnsure Centre\u2019s work procedures are in compliance with Bank\u2019s policies and guidelines and comply with the regulatory requirements\n\nRequirements:\n\n\u00a0\u00a0\u00a0\u00a0\u00a0\u00a0\u00a0\u00a0 Higher Diploma / DSE graduate or above\n\u00a0\u00a0\u00a0\u00a0\u00a0\u00a0\u00a0\u00a0 Minimum one year of experience as a sales role in related industry\n\u00a0\u00a0\u00a0\u00a0\u00a0\u00a0\u00a0\u00a0 Knowledge of loan products\n\u00a0\u00a0\u00a0\u00a0\u00a0\u00a0\u00a0\u00a0 Qualifications in IIQE/HKSI areas are preferred\n\u00a0 \u00a0 \u00a0 \u00a0 \u00a0Strong team player, aggressive and self-motivated with positive attitude\n\u00a0 \u00a0 \u00a0 \u00a0 \u00a0Excellent interpersonal skills and customer oriented. Good communication skills\u00a0 \u00a0 \u00a0 \u00a0 \u00a0 \u00a0in English, Cantonese and Mandarin\n\nApplicants who are not contacted within 8 weeks may consider their applications unsuccessful and their personal data will be retained by the bank for a period up to two years.\n\nAll information provided by applicants will be used for recruitment purposes only and will be used strictly in accordance with the bank\u2019s personal data policies, a copy of which will be provided upon request.", "employment_types": ["Full Time", "Permanent"], "selling_points": ["solicit loan sales of UPL and mortgage", "Manage sales activities and performance", "Demonstrate high quality services"], "locations": ["Not Specified"], "categories": ["Banking / Finance", "Loan", "Mortgage", "Retail Banking"], "post_time": "2022-01-14T10:03:17Z", "salary": {"currency": null, "max": null, "min": null, "period": "monthly", "term": null}, "salary_visible": false, "title_keywords": ["personal", "sales executive"], "responsibilities": ["sales activities", "bank\u2019s policies", "guidelines", "regulatory requirements", "compliance", "quality", "procedures", "banking", "insurance", "planning"], "requirements": {"degrees": ["diploma", "dse"], "majors": [], "languages": ["cantonese", "english", "mandarin"], "language_level": ["good"], "hard_skills": ["loan products", "iiqe", "hksi"], "soft_skills": ["communication skills", "self-motivated", "positive attitude", "interpersonal skills", "team player"], "languages_combined": [{"language": "cantonese", "language_level": ["good"]}, {"language": "english", "language_level": ["good"]}, {"language": "mandarin", "language_level": ["good"]}]}, "experience_required": {"duration": ["minimum one year"], "field": ["related"]}}, {"job_id": "100003009047784", "location_code": "hk", "company": "Public Bank (Hong Kong) Limited", "job_title": "Credit Administration Clerk (Ref: JD-CAC)", "description": "Prepare and review loan documents for commercial banking facilities\nLiaise with marketing units to ensure proper and efficient operations of credit administration\u00a0work\nSecondary education with minimum 2 years of credit administration experience\nCandidate with conveyancing experience in legal firm will also be considered\nGood interpersonal and communication skills in both English and Chinese\nHands-on experience in MS Office applications\n\nTo apply, interested parties please follow the application methods available in the Bank\u2019s career website https://www.publicbank.com.hk/en/aboutus/careeropportunities. You can send us your resume quoting our job reference number together with present & expected salary (a must) to the Human Resources Department by email or fax at 2815 3157 or by post to Human Resources Department, 12/F, Public Bank Centre, 120 Des Voeux Road Central, Hong Kong. You may also visit our career website for other career opportunities available within our Group.\n\nPersonal data collected will be used for recruitment purpose only and will be treated in accordance with the Bank\u2019s Personal Information Collection Statement, a copy of which has been available in the Bank\u2019s career website.\u00a0", "employment_types": ["Full Time", "Permanent"], "selling_points": [], "locations": ["Not Specified"], "categories": ["Banking / Finance", "Loan", "Mortgage", "Others"], "post_time": "2022-01-15T03:49:09Z", "salary": {"currency": null, "max": null, "min": null, "period": null, "term": null}, "salary_visible": false, "title_keywords": ["clerk"], "responsibilities": ["operations", "review", "communication", "banking", "liaise with", "administration"], "requirements": {"degrees": ["secondary education"], "majors": [], "languages": ["english", "chinese"], "language_level": ["good"], "hard_skills": ["ms office"], "soft_skills": ["efficient", "communication skills", "hands-on", "interpersonal"], "languages_combined": [{"language": "english", "language_level": ["good"]}, {"language": "chinese", "language_level": ["good"]}]}, "experience_required": {"duration": ["minimum 2 years"], "field": ["administration", "legal", "education"]}}, {"job_id": "100003009049444", "location_code": "hk", "company": "OCBC Wing Hang Bank Limited", "job_title": "Senior Loan Processing Officer", "description": "Responsibilities\n\u200bPrepare all loan documents include offer letters, guarantee and charge forms etc. for corporate clients\nCheck the completeness and correctness of documents before loan disbursement and/or credit limits set-up\nLiaise with valuation / properties agents and follow up with the valuation reports\nHandle credit limit loading, loans disbursement, roll-over and settlement process\nHandle and supervise loans repayment & maintenance functions\nAssist in other ad hoc tasks as assigned\nRequirements\n\u200bDiploma or above\nMinimum 3 years\u2019 relevant experience in Banking industry\nFamiliar with credit administration or loans processing duties\nGood interpersonal and communication skills\nOutgoing, independent and self-motivated\n\nAttractive remuneration package will be offered to the right candidate. Please apply with full resume stating present & expected salary and contact phone number\u00a0to\u00a0The Human Resources Manager, 10/F, 161 Queen\u2019s Road Central, Hong Kong.\u00a0Please quote the reference.\n\nPersonal data collected will be used for recruitment purpose only. For more information, please visit our website:\u00a0http://www.ocbcwhhk.com.", "employment_types": ["Full Time", "Permanent"], "selling_points": ["Loan Processing", "Mortgage", "Back Office"], "locations": ["Shau Kei Wan"], "categories": ["Banking / Finance", "Loan", "Retail Banking", "Order Processing & Operation / Settlement"], "post_time": "2022-01-14T08:39:40Z", "salary": {"currency": null, "max": null, "min": null, "period": "monthly", "term": null}, "salary_visible": false, "title_keywords": ["officer"], "responsibilities": ["valuation", "maintenance", "settlement process", "letters", "ad hoc tasks", "reports", "liaise with"], "requirements": {"degrees": [], "majors": [], "languages": [], "language_level": [], "hard_skills": ["processing"], "soft_skills": ["outgoing", "communication skills", "self-motivated", "independent", "interpersonal"], "languages_combined": []}, "experience_required": {"duration": ["minimum 3 years"], "field": ["banking industry", "relevant experience"]}}, {"job_id": "100003009043677", "location_code": "hk", "company": "United Asia Finance Limited", "job_title": "\u5ba2\u6236\u670d\u52d9\u4ee3\u8868 (\u5206\u884c)", "description": "\u5de5\u4f5c\u8077\u8cac:\n\n\u8655\u7406\u8cb8\u6b3e\u7533\u8acb\u76f8\u95dc\u4e8b\u9805\n\u8ca0\u8cac\u5206\u884c\u7684\u4e00\u822c\u67e5\u8a62\u53ca\u5ba2\u6236\u670d\u52d9\u5de5\u4f5c\n\u8655\u7406\u5ba2\u6236\u9084\u6b3e\u624b\u7e8c\n\u63a8\u5ee3\u516c\u53f8\u7522\u54c1\n\u8655\u7406\u4e00\u822c\u6587\u8077\u5de5\u4f5c (\u5982\u6587\u4ef6\u5b58\u6a94\u53ca\u8cc7\u6599\u8f38\u5165)\n\n\u8077\u4f4d\u8981\u6c42:\n\n\u4e2d\u4e94\u7a0b\u5ea6\u6216\u4ee5\u4e0a\n\u5177\u512a\u8cea\u670d\u52d9\u614b\u5ea6\n\u826f\u597d\u5206\u6790\u529b, \u826f\u597d\u4eba\u969b\u95dc\u4fc2\u53ca\u6e9d\u901a\u6280\u5de7\n\u7a4d\u6975\u4e3b\u52d5, \u5177\u8cac\u4efb\u611f\u53ca\u9858\u610f\u5b78\u7fd2\n\u6d41\u5229\u5ee3\u6771\u8a71\uff0c\u57fa\u672c\u82f1\u8a9e\u53ca\u666e\u901a\u8a71\n\u64c1\u6709\u4e09\u5e74\u6216\u4ee5\u4e0a\u76f8\u95dc\u5de5\u4f5c\u7d93\u9a57\u8005\u53ef\u7372\u8003\u616e\u70ba\u5354\u7406\u8cb8\u6b3e\u5c08\u54e1\n\n\u6b61\u8fce\u61c9\u5c46\u7562\u696d\u751f\u52a0\u5165\n\n\n\u512a\u539a\u7684\u54e1\u5de5\u798f\u5229\u5305\u62ec:\n\n\u6709\u85aa\u5e74\u5047\u00a0\u00a0 \u00a0\u00a0\u00a0\n\u5a5a\u5047\u00a0\u00a0\u00a0\n\u9280\u884c\u5047\u671f\u00a0 \u00a0\n\u96d9\u7ce7\n\u54e1\u5de5\u6d3b\u52d5\n\u914c\u60c5\u6027\u82b1\u7d05\n\u826f\u597d\u6649\u5347\u6a5f\u6703\n\u91ab\u7642\u53ca\u4eba\u58fd\u4fdd\u96aa\n\u5c08\u696d\u5728\u8077\u57f9\u8a13\n\n~ \u6b61\u8fce\u61c9\u5c46\u7562\u696d\u751f\u52a0\u5165~\n\n\u62db\u8058\u65e5\n\n\u65e5\u671f\uff1a\u65e5\u671f\uff1a2021\u5e7412\u670815, 16\u53ca 17\u65e5\n\n\u6642\u9593\uff1a\u4e0b\u53482\u6642\u81f35\u6642\n\n\u5730\u5740\uff1a\u7063\u4ed4\u544a\u58eb\u6253\u9053 138 \u865f\u806f\u5408\u9e7f\u5cf6\u5927\u5ec821\u6a13\n\n\u61c9\u5fb5\u8005\u8acb\u5e36\u5099\u500b\u4eba\u5c65\u6b77\u3001\u8fd1\u7167\u4e00\u5f35\u3001\u5de5\u4f5c\u53ca\u5b78\u6b77\u8a3c\u660e\u6587\u4ef6\u6b63\u672c\uff0c\u5373\u5834\u9762\u8a66\n\n(\u5982\u61c9\u5fb5\u8005\u672a\u80fd\u5728\u4e0a\u8ff0\u6642\u9593\u89aa\u81e8\u9762\u8a66\uff0c\u53ef\u5c07\u500b\u4eba\u5c65\u6b77\u96fb\u90f5\u81f3Apply Now\u7533\u8acb)\n\n(Personal data collected will be treated in the strictest confidence and will be handled by authorized personnel for recruitment-related purposes only. Applicants who do not hear from us within 3 months may consider their application unsuccessful and their data will be destroyed within 24 months of receipt.)", "employment_types": ["Full Time", "Permanent"], "selling_points": ["\u8655\u7406\u8cb8\u6b3e\u7533\u8acb\u76f8\u95dc\u4e8b\u9805, \u8ca0\u8cac\u5206\u884c\u7684\u4e00\u822c\u67e5\u8a62\u53ca\u5ba2\u6236\u670d\u52d9\u5de5\u4f5c", "\u4e2d\u4e94\u7a0b\u5ea6\u6216\u4ee5\u4e0a, \u64c1\u6709\u4e09\u5e74\u6216\u4ee5\u4e0a\u76f8\u95dc\u5de5\u4f5c\u7d93\u9a57\u8005\u53ef\u7372\u8003\u616e\u70ba\u5354\u7406\u8cb8\u6b3e\u5c08\u54e1", "\u6709\u85aa\u5e74\u5047, \u914c\u60c5\u6027\u82b1\u7d05, \u9280\u884c\u5047\u671f, \u96d9\u7ce7"], "locations": ["Not Specified"], "categories": ["Banking / Finance", "Loan", "Financial Services", "Sales, CS & Business Devpt", "Customer Service - Supervisor / Officer"], "post_time": "2022-01-13T01:27:15Z", "salary": {"currency": null, "max": null, "min": null, "period": "monthly", "term": null}, "salary_visible": false, "title_keywords": [], "responsibilities": ["personal data", "recruitment", "data"], "requirements": {"degrees": [], "majors": [], "languages": [], "language_level": [], "hard_skills": [], "soft_skills": ["confidence"], "languages_combined": []}, "experience_required": {"duration": [], "field": []}}, {"job_id": "100003009050761", "location_code": "hk", "company": "China Construction Bank (Asia) Corporation Limited", "job_title": "Assistant Manager, Credit Verification (Commercial & Retail Banking)", "description": "Responsibilities:\n\n\n\u2022\u00a0\u00a0\u00a0\u00a0\u00a0\u00a0\u00a0\u00a0\u00a0\u00a0 Prepare facility letters, loan documents and relevant correspondences such as instruction letter to solicitor firms;\n\n\u2022\u00a0\u00a0\u00a0\u00a0\u00a0\u00a0\u00a0\u00a0\u00a0\u00a0 Perform the checker role for reviewing the basic facility letters and/or loan documentations prepared by the marker if necessary;\n\n\u2022\u00a0\u00a0\u00a0\u00a0\u00a0\u00a0\u00a0\u00a0\u00a0\u00a0 Perform loan documentation review prior to the loan drawdown/ line validation;\n\n\u2022\u00a0\u00a0\u00a0\u00a0\u00a0\u00a0\u00a0\u00a0\u00a0\u00a0 Process the regular MIS reports;\n\n\u2022\u00a0\u00a0\u00a0\u00a0\u00a0\u00a0\u00a0\u00a0\u00a0\u00a0 Participate in UAT project;\n\n\u2022\u00a0\u00a0\u00a0\u00a0\u00a0\u00a0\u00a0\u00a0\u00a0\u00a0 Participate in monthly outstanding cases clean-up exercise and/or yearly files cleaning up project;\n\n\u2022\u00a0\u00a0\u00a0\u00a0\u00a0\u00a0\u00a0\u00a0\u00a0\u00a0 Assist supervisor in drafting and reviewing the operation manual;\n\n\u2022\u00a0\u00a0\u00a0\u00a0\u00a0\u00a0\u00a0\u00a0\u00a0\u00a0 Ordering and reviewing of valuation report;\n\n\u2022\u00a0\u00a0\u00a0\u00a0\u00a0\u00a0\u00a0\u00a0\u00a0\u00a0 Perform ad hoc duties as assigned;\n\n\u2022\u00a0\u00a0\u00a0\u00a0\u00a0\u00a0\u00a0\u00a0\u00a0\u00a0 Reply follow-up issues as requested by LPS;\n\n\u2022\u00a0\u00a0\u00a0\u00a0\u00a0\u00a0\u00a0\u00a0\u00a0\u00a0 Deliver loan documents and/or other relevant documents to various business units and/or other relevant parties\n\nRequirements:\n\n\n\nDegree holder, preferably in Business or related disciplines\nMinimum 4 years of loan documentation and credit execution experience\nStrong command of spoken and written English and Chinese (including Putonghua)", "employment_types": ["Full Time", "Permanent"], "selling_points": ["Prepare facility letters & loan documents", "Process the regular MIS reports", "Degree holder & 4 yrs exp in loan documentation"], "locations": ["Kowloon Bay"], "categories": ["Banking / Finance", "Loan", "Retail Banking", "Risk Management"], "post_time": "2022-01-14T11:17:43Z", "salary": {"currency": null, "max": null, "min": null, "period": "monthly", "term": null}, "salary_visible": false, "title_keywords": ["assistant manager,"], "responsibilities": ["ad hoc duties", "valuation", "uat", "review", "letters", "reports", "cleaning", "documentation", "report"], "requirements": {"degrees": ["degree holder"], "majors": ["related disciplines", "business"], "languages": ["putonghua", "english", "chinese"], "language_level": [], "hard_skills": ["documentation"], "soft_skills": [], "languages_combined": [{"language": "putonghua", "language_level": []}, {"language": "english", "language_level": []}, {"language": "chinese", "language_level": []}]}, "experience_required": {"duration": ["minimum 4 years"], "field": []}}, {"job_id": "100003009050674", "location_code": "hk", "company": "Dah Sing Financial Group", "job_title": "OK Finance - Customer Services Representative", "description": "Reporting to the Branch Manager, you will be responsible for providing quality customer services to the customers.\n\nResponsibilities\nGreet and welcome walk-in & phone-in customers according to the established service standard\nHandle customer enquiries and requests, and always seek advice from supervisor for proper handling of customer complaint as and when necessary\nPerform loan processing and administrative duties\nAssist in payment transaction such as disbursing loan proceeds and handle repayment over the counter\nTo meet the challenge, you should have the following qualifications and attributes:\nSecondary education\nExperience in Consumer Finance/banking industry is preferable\nGood interpersonal and communication skills\nGood knowledge of MS Office\nWith initiative, pleasant personality and willing to learn\nGood command of written and spoken English and Chinese\nPlease note that only shortlisted candidates will be notified.", "employment_types": ["Full Time", "Permanent"], "selling_points": ["Responsible for providing quality customer service", "Secondary education", "Experience in Consumer Finance/banking industry"], "locations": ["Not Specified"], "categories": ["Banking / Finance", "Loan", "Others", "Sales, CS & Business Devpt", "Customer Service - Supervisor / Officer"], "post_time": "2022-01-14T11:09:56Z", "salary": {"currency": null, "max": null, "min": null, "period": "monthly", "term": null}, "salary_visible": false, "title_keywords": ["customer services representative"], "responsibilities": ["reporting", "handle customer enquiries", "service standard", "quality", "customer services", "communication", "payment", "administrative duties", "banking"], "requirements": {"degrees": ["secondary education"], "majors": [], "languages": ["english", "chinese"], "language_level": ["good command"], "hard_skills": ["processing", "ms office"], "soft_skills": ["communication skills", "responsible", "willing to learn", "pleasant", "interpersonal", "initiative"], "languages_combined": [{"language": "english", "language_level": ["good command"]}, {"language": "chinese", "language_level": ["good command"]}]}, "experience_required": {"duration": [], "field": ["finance", "banking industry"]}}, {"job_id": "100003009050462", "location_code": "hk", "company": "Giant Mind (China) Limited", "job_title": "Business Manager of Finance Company", "description": "Following the entire money lending process from application to closing, including managing loan application documents and corresponding administrative duties.\u00a0\nInquire about various types of loan repayments and maintain data, monitor customer repayment records, provide customer service for loan inquiries, take appropriate actions early, and proactively manage mortgage loan portfolios to reduce delinquencies and bad debts.\nCommunicate and collaborate with stakeholders, including board members, senior management and department managers.\nCreate business\nNegotiating with intermediaries on behalf of the company\nFind real estate companies to cooperate\nRequirements\uff1a\nHaving experience in banking, funds, insurance, money lending, etc. is preferred and familiar with financial business and money lending circles.\nA business degree, certificate or licence in finance or a related discipline.\nRelevant work experience in the money lending industry, including personal loan and/or mortgage loan management.\nStrong business sense with financial analysis and problem solving skills.\nFamiliar with relevant laws, rules, regulations and corporate governance practices.\nGood communication and interpersonal skills\nFluent written and spoken English and Chinese\nWe provide successful candidates with excellent career opportunities and competitive compensation packages, including, medical benefit plans and performance bonuses. Interested applicants please submit your CV to us with available dates, current and expected salary.\nThe annual salary is equal to the fixed salary + performance bonuses (depending on experience), and the salary is negotiable.", "employment_types": ["Full Time", "Permanent"], "selling_points": ["5.5 working days", "Financial professional network", "Familiar with real estate and finance"], "locations": ["Central"], "categories": ["Banking / Finance", "Loan"], "post_time": "2022-01-14T10:28:13Z", "salary": {"currency": null, "max": null, "min": null, "period": "monthly", "term": null}, "salary_visible": false, "title_keywords": ["manager"], "responsibilities": ["provide customer service", "collaborate with", "management", "regulations", "monitor", "application documents", "financial analysis", "communication", "administrative duties", "maintain data", "banking", "senior management", "insurance"], "requirements": {"degrees": ["certificate", "degree"], "majors": ["finance", "business"], "languages": ["english", "chinese"], "language_level": ["fluent"], "hard_skills": ["financial analysis", "problem solving skills"], "soft_skills": ["problem solving skills", "customer service", "communication and interpersonal skills", "business sense"], "languages_combined": [{"language": "english", "language_level": ["fluent"]}, {"language": "chinese", "language_level": ["fluent"]}]}, "experience_required": {"duration": [], "field": ["management", "insurance", "banking"]}}, {"job_id": "100003009049401", "location_code": "hk", "company": "Shanghai Commercial Bank Ltd", "job_title": "Associate, Loans Processing", "description": "Responsibilities:\n\nProvide administration support to the Loans Processing Centre\nPerform daily operations on loans drawdown, documentation and repayment\nAssist in preparation of facility letters and related loans documents\nWork closely with business units to provide quality services to customers\nParticipate in any projects as assigned\n\nRequirements:\n\nDegree holder in Business Administration or related disciplines\nWell-organized with attention to details\nGood communication and interpersonal skills\nGood command of spoken and written English and Chinese\nProficient in MS Word, Excel and Chinese Word Processing\n\nAttractive remuneration package will be offered to the right candidates. Interested parties please click \"Apply Now\" to submit your full resume with current and expected salary to the Human Resources Division.\n\nPlease visit us at www.shacombank.com.hk for more information about our Bank.\n\nAll personal data collected will be used for recruitment related purposes strictly in accordance with the Bank's personal data policies, a copy of which will be provided immediately upon request by contacting our Personal Data Compliance Officer. Applicants who are not contacted within two months may consider their applications unsuccessful and the personal data collected from the applicants will be retained for no longer than two years from the date of rejection during which the applicants may be considered for other suitable positions within the Bank.", "employment_types": ["Full Time", "Permanent"], "selling_points": ["Perform the operations tasks of loans", "Prepare loan documents and reports", "Handle enquiries from internal staff"], "locations": ["Kwai Hing"], "categories": ["Banking / Finance", "Loan", "Others", "Order Processing & Operation / Settlement"], "post_time": "2022-01-15T03:50:22Z", "salary": {"currency": null, "max": null, "min": null, "period": "monthly", "term": null}, "salary_visible": false, "title_keywords": ["associate"], "responsibilities": ["documentation", "letters", "quality", "daily operations", "loans processing", "administration"], "requirements": {"degrees": ["degree holder"], "majors": ["related disciplines", "business administration"], "languages": ["english", "chinese"], "language_level": ["good command", "proficient"], "hard_skills": ["excel", "chinese word processing", "ms word"], "soft_skills": ["communication and interpersonal skills", "well-organized", "attention to details"], "languages_combined": [{"language": "english", "language_level": ["good command"]}, {"language": "chinese", "language_level": ["good command", "proficient"]}]}, "experience_required": {"duration": [], "field": []}}, {"job_id": "100003009046088", "location_code": "hk", "company": "Manpower Services (Hong Kong) Limited", "job_title": "On-Site with Hang Seng Bank - Card Authorization & Portfolio Services Officer(Contractor, Up to 18K)", "description": "Title: CCC CAPS Officer (Card Authorization & Portfolio Services Officer)\nContract Duration: asap - 31 Dec 22\nSalary: HK$16-18k + OT allowance\nWorking Hours: Mon-Fri, 9-6pm\n\nCard Authorization & Portfolio Services Officer\nCustomer Contact Centre\n\nHang Seng's Customer Contact Centre has been ranked one of the best phone banking service providers for consecutive years. Our team strives to provide professional services for a wide range of banking products to address customers' different services and financial needs.\n\nWe are currently seeking high caliber professionals to join our department as Card Authorization & Portfolio Services Officer\n\nPrincipal responsibilities\n\u2022 Process card related applications\n\u2022 Ensure provision of efficient card loan service to customers\n\u2022 Provide good phone service to customers\n\u2022 Ensure the performance of card loan services meets the service pledge\n\u2022 Initiate process improvement areas for enhancing operation efficiency\n\u2022 Provide administrative support in ad-hoc duties as assigned\n\nRequirements\n\u2022 Diploma in a related discipline or other relevant professional qualifications\n\u2022 Minimum 1 years\u2019 experience in customer service experience, with exposure to unsecured leading products and call centre business preferred\n\u2022 Strong attentiveness to details, with ability to work independently and under pressure\n\u2022 Good communication, interpersonal and analytical skills\n\u2022 Proficiency in both English and Chinese, with fluency in Putonghua an advantage\n\u2022 Good knowledge of computer applications such as MS Excel and Access\n\u2022 Great sense of ownership and servicing mindset to ensure efficient and effective customer service processes\n\nIf you are interested in this role, click \u201cApply Now\u201d, else, you may also directly send your updated resume and expected salary to Anson Li at anson.li@manpowergrc.hk.", "employment_types": ["Contract"], "selling_points": ["Diploma in a related discipline", "1 years\u2019 experience in customer service experience", "Exposure to unsecured loan & call centre business"], "locations": ["Kowloon Bay"], "categories": ["Banking / Finance", "Loan", "Sales, CS & Business Devpt", "Call Centre", "Customer Service - Supervisor / Officer"], "post_time": "2022-01-13T09:35:54Z", "salary": {"currency": null, "max": null, "min": null, "period": "monthly", "term": null}, "salary_visible": false, "title_keywords": [], "responsibilities": ["provide administrative support", "ad-hoc duties"], "requirements": {"degrees": ["diploma"], "majors": [], "languages": ["putonghua", "english", "chinese"], "language_level": ["fluency", "advantage", "proficiency"], "hard_skills": ["ms excel", "analytical skills", "professional qualifications"], "soft_skills": ["efficient", "work independently", "under pressure", "interested in", "analytical skills", "communication", "customer service", "interpersonal"], "languages_combined": [{"language": "putonghua", "language_level": ["fluency", "advantage"]}, {"language": "english", "language_level": ["proficiency", "advantage"]}, {"language": "chinese", "language_level": ["proficiency", "advantage"]}]}, "experience_required": {"duration": ["minimum 1 years"], "field": ["business", "customer service"]}}, {"job_id": "100003009047344", "location_code": "hk", "company": "Asia One Credit Limited", "job_title": "Credit Officer", "description": "Responsibilities\n\nHandle daily loan operation from application, credit assessment to disbursement\nHandle portfolio management e.g. repayment monitoring, due diligence, refinancing, regularly reporting\nHandle general inquiries and maintain a good relationship with customers and business partners\nAssist in system maintenance and operational manual update\nRegularly review credit policies, procedures & market updates\nRequirements:\n\nBachelor degree holder in Accounting, Finance, Economic or related discipline\nMinimum of 3-year experiences in load operation and credit analysis\nAble to analyze complex financial data and willing to learn\nDetail-minded, able to work independently and good team player\nGood command of both spoken and written English, Chinese and Mandarin\nImmediate available is highly preferred.\n\nWe offer competitive remuneration package with comprehensive fringe benefits to the right candidates:\n\n- Birthday Leave / Marriage Leave / Paternity Leave / Examination Leave\n- Staff Care Programme\n- Career Development Programme\n\n\n\nContact us\n\nQualified candidate, please email your full resume with academic credentials, working experience, expected salary and availability by clicking the \"apply now\" button as below.\n", "employment_types": ["Full Time", "Permanent"], "selling_points": ["3-yrs exp in commercial/ financial institution/b", "Able to analyze complex financial info", "5-days work, discretionary bonus, birthday leave"], "locations": ["Cheung Sha Wan"], "categories": ["Banking / Finance", "Credit Analysis / Approval", "Loan", "Financial Services"], "post_time": "2022-01-14T02:51:56Z", "salary": {"currency": null, "max": null, "min": null, "period": "monthly", "term": null}, "salary_visible": false, "title_keywords": ["officer"], "responsibilities": ["due diligence", "management", "reporting", "maintenance", "policies", "monitoring", "review", "procedures", "good relationship", "maintain"], "requirements": {"degrees": ["bachelor degree holder"], "majors": ["finance", "accounting"], "languages": ["english", "chinese", "mandarin"], "language_level": ["good command"], "hard_skills": ["credit analysis"], "soft_skills": ["detail-minded", "good team player", "work independently", "willing to learn"], "languages_combined": [{"language": "english", "language_level": ["good command"]}, {"language": "chinese", "language_level": ["good command"]}, {"language": "mandarin", "language_level": ["good command"]}]}, "experience_required": {"duration": ["minimum of 3-year"], "field": ["operation"]}}, {"job_id": "100003009045881", "location_code": "hk", "company": "Eternity Consultants (HK) Ltd", "job_title": "Customer Services (\u5206\u884c\u5ba2\u6236\u670d\u52d9\u4ee3\u8868)", "description": "\u5de5\u4f5c\u8077\u8cac\n\n\u8655\u7406\u8cb8\u6b3e\u7533\u8acb\u76f8\u95dc\u4e8b\u9805\n\u8ca0\u8cac\u5206\u884c\u7684\u4e00\u822c\u67e5\u8a62\u53ca\u5ba2\u6236\u670d\u52d9\u5de5\u4f5c\n\u8655\u7406\u8cc7\u6599\u8f38\u5165\u53ca\u5176\u4ed6\u6587\u8077\u5de5\u4f5c\n\n\u8077\u4f4d\u8981\u6c42\u00a0\n\n\u4e2d\u4e94\u7a0b\u5ea6\u6216\u4ee5\u4e0a\n\u5177\u91d1\u878d\u6a5f\u69cb\u6216\u76f8\u95dc\u5ba2\u6236\u670d\u52d9\u7d93\u9a57\u8005\u5c07\u7372\u512a\u5148\u8003\u616e\n\u5177\u826f\u597d\u6e9d\u901a\u6280\u5de7\uff0c\u80fd\u64cd\u6d41\u5229\u5ee3\u6771\u8a71\uff0c\u57fa\u672c\u82f1\u8a9e\u53ca\u666e\u901a\u8a71\n\u5177\u57fa\u672c\u96fb\u8166\u6587\u66f8\u6280\u5de7\u5305\u62ec Microsoft Word, Excel \u53ca\u4e2d\u6587\u8f38\u5165\u6cd5\uff08\u5009\u9821 / \u901f\u6210\uff09\n\u54e1\u5de5\u798f\u5229\u5305\u62ec\uff1a\u6709\u85aa\u5e74\u504712\u65e5\u8d77\u3001\u8d85\u6642\u5de5\u4f5c\u6d25\u8cbc\u3001\u4ea4\u901a\u6d25\u8cbc\u3001\u914c\u60c5\u82b1\u7d05\u3001\u9031\u5e74\u54e1\u5de5\u6d3b\u52d5\u3001\u826f\u597d\u6649\u5347\u6a5f\u6703\u3001\u5c08\u696d\u5728\u8077\u57f9\u8a13\u3001\u91ab\u7642\u4fdd\u96aa\u3001\u7b49\u7b49\n\n\u00a0\n\u5730\u5340:\u00a0\u00a0\u00a0\u00a0\u00a0\u00a0 \u5143\u6717 / \u5929\u6c34\u570d / \u6cb9\u5c16\u65fa / \u9577\u6c99\u7063 / \u8475\u82b3 / \u8343\u7063 / \u5317\u89d2 / \u9285\u947c\u7063\n\n\n\n\u8acb\u63d0\u4f9b\u500b\u4eba\u5c65\u6b77\u53ca\u4eba\u5de5\u8981\u6c42 email \u5f80:\u00a0 jobs@hketernity. com\n\n(\u6240\u6709\u500b\u4eba\u8cc7\u6599\u53ea\u4f5c\u62db\u8058\u7528\u9014)\n\n\u66f4\u591a\u4e0d\u540c\u7684\u5de5\u4f5c:\u00a0www.hketernity.com", "employment_types": ["Full Time", "Permanent"], "selling_points": ["\u8ca0\u8cac\u5206\u884c\u7684\u4e00\u822c\u67e5\u8a62\u53ca\u5ba2\u6236\u670d\u52d9\u5de5\u4f5c. \u8cc7\u6599\u8f38\u5165\u53ca\u5176\u4ed6\u6587\u8077\u5de5\u4f5c.", "\u8655\u7406\u8cb8\u6b3e\u7533\u8acb", "\u826f\u597d\u6e9d\u901a\u6280\u5de7."], "locations": ["Not Specified"], "categories": ["Banking / Finance", "Loan", "Sales, CS & Business Devpt", "Customer Service - Supervisor / Officer", "Account Servicing"], "post_time": "2022-01-13T09:00:42Z", "salary": {"currency": null, "max": null, "min": null, "period": "monthly", "term": null}, "salary_visible": false, "title_keywords": [], "responsibilities": [], "requirements": {"degrees": [], "majors": [], "languages": [], "language_level": [], "hard_skills": ["excel", "microsoft word"], "soft_skills": [], "languages_combined": []}, "experience_required": {"duration": [], "field": []}}, {"job_id": "100003009049715", "location_code": "hk", "company": "Bangkok Bank Public Co Ltd", "job_title": "Chief of Loan Processing (Ref: BP-14/180/240-DB)", "description": "We are now seeking a high caliber candidate to join our Hong Kong Branch.\n\nResponsibilities:\n\nOversee the overall operations of\u00a0Loan Processing\nAuthorize customer's loan drawdown (including disbursement) and repayment and relevant fee collection transactions\nHandle enquires on loan processing from\u00a0Relationship Managers and loan customers\nAssist in liaising with external auditors and other external parties\u00a0during examination\nProvide coaching / supervision / on-the-job training to subordinates\nHandle ad-hoc tasks assigned by Senior Management as and when required\n\nRequirements:\n\nDegree holder\nMinimum 8 years of loan processing experience,\u00a0preferably with exposure in syndication loans\nPossess strong leadership, presentation and communication skills\nAble to work under pressure and meet\u00a0tight schedules\nProficient in\u00a0both spoken and written English and Chinese (Cantonese & Putonghua)\n\nWe offer excellent career prospects to the right candidate. Salary will be commensurate with qualifications and experience. Interested parties please apply with\u00a0full resume, stating current / expected salary and availability to The Human Resources Manager, Bangkok Bank Public Co. Ltd., Bangkok Bank Building, 28 Des Voeux Road Central, Hong Kong.\n\nPersonal data provided by job applicants will be used solely for considering suitability for the post and strictly in accordance with our personal data policies which are available on request.\n\n(Only shortlisted candidates will be contacted.)", "employment_types": ["Full Time"], "selling_points": [], "locations": ["Central"], "categories": ["Banking / Finance", "Corporate Banking", "Loan"], "post_time": "2022-01-14T09:08:57Z", "salary": {"currency": null, "max": null, "min": null, "period": "monthly", "term": null}, "salary_visible": false, "title_keywords": [], "responsibilities": ["operations", "ad-hoc tasks", "external parties", "liaising with", "transactions", "senior management", "external auditors"], "requirements": {"degrees": ["degree holder"], "majors": [], "languages": ["cantonese", "putonghua", "english", "chinese"], "language_level": ["proficient"], "hard_skills": ["processing"], "soft_skills": ["communication skills", "work under pressure", "leadership", "presentation", "meet tight schedules"], "languages_combined": [{"language": "cantonese", "language_level": []}, {"language": "putonghua", "language_level": []}, {"language": "english", "language_level": ["proficient"]}, {"language": "chinese", "language_level": ["proficient"]}]}, "experience_required": {"duration": ["minimum 8 years"], "field": []}}, {"job_id": "100003009046096", "location_code": "hk", "company": "Zero Finance Hong Kong Limited", "job_title": "Senior Credit Officer / Assistant Manager - Mortgage Loan", "description": "In this role, you will perform:\n\nResponsible for proactively follow up with related parties\nExecute properties appraisal on the new mortgage loans and refinance applications\nMaintain close relationship with agency and solicitors\u2019 firms\nEnsure the correctness of loan contracts before corporate approval\nImplement business plan to achieve sales targets\n\nTo be successful in this role, you should meet the following requirements:\u00a0\n\nTertiary education or above, finance or other business related disciplines are preferred\nPreferably 5 years relevant experience in Money Lending Industry\nGood command of spoken & written English, Cantonese and Mandarin\nStrong adaptability and flexibility\nProficient in MS Word, MS Excel and Chinese Word Processing\nLess experience will be considered as Senior Officer\n\nCompany Website: https://www.zerofinance.hk/zh/\u00a0\n\nAttractive remuneration package will be offered to the right candidate. Please apply with full resume stating present and expected salary to us by\u00a0clicking \u201cAPPLY NOW\u201d.\n\n(Personal data collected will be used for recruitment purpose only.)", "employment_types": ["Full Time", "Permanent"], "selling_points": ["Mortgage loans operation", "Credit administration", "5 days work, bank holidays"], "locations": ["Sheung Wan"], "categories": ["Banking / Finance", "Credit Analysis / Approval", "Loan", "Mortgage"], "post_time": "2022-01-13T09:36:31Z", "salary": {"currency": null, "max": null, "min": null, "period": "monthly", "term": null}, "salary_visible": false, "title_keywords": ["officer", "assistant manager"], "responsibilities": ["contracts", "maintain", "recruitment", "business plan", "personal data", "company website"], "requirements": {"degrees": [], "majors": [], "languages": ["cantonese", "english", "chinese", "mandarin"], "language_level": ["good command", "proficient"], "hard_skills": ["ms excel", "chinese word processing", "ms word"], "soft_skills": ["adaptability", "responsible"], "languages_combined": [{"language": "cantonese", "language_level": ["good command"]}, {"language": "english", "language_level": ["good command"]}, {"language": "chinese", "language_level": ["proficient"]}, {"language": "mandarin", "language_level": ["good command"]}]}, "experience_required": {"duration": ["5 years"], "field": ["relevant experience"]}}, {"job_id": "100003009048915", "location_code": "hk", "company": "China Minsheng Banking Corporation Limited", "job_title": "Product Manager / Assistant Manager, Corporate Banking (Loan Syndication and Distribution)", "description": "Responsibilities:\n\nResponsible for distribution of syndicated loan transactions,\u00a0preparation of pitchbooks and information memorandum.\nWork closely with relationship managers to originate and execute syndicated loan and structured loan transactions.\nManage and review the loan pricing with\u00a0syndication strategy\u00a0in markets for corporate clients.\nPromote syndicated loan opportunities to corporate clients and be able to bring in new loan investors.\n\nRequirements:\n\nBachelor\u2019s\u00a0degree\u00a0or above, preferably majors in BBA or related disciplines.\nAt least 3 years' relevant experience in loan distribution.\nGood knowledge of PRC laws and related regulations with exposure of Mainland China's financial markets.\nDetailed-minded, strong analytical and\u00a0credit analysis and risk management skills.\nAble to work independently and under pressure with team spirit.\nProficient in\u00a0both\u00a0written and spoken English and Chinese, Fluent in Mandarin is a must.\nCandidate with more experience will be considered as Manager.", "employment_types": ["Full Time"], "selling_points": ["Promote syndicated loan opportunities", "Preparation of pitch books", "Originate and execute syndicated loan"], "locations": ["Central"], "categories": ["Banking / Finance", "Loan"], "post_time": "2022-01-14T07:41:27Z", "salary": {"currency": null, "max": null, "min": null, "period": "monthly", "term": null}, "salary_visible": false, "title_keywords": ["assistant manager,", "product manager"], "responsibilities": ["review", "transactions"], "requirements": {"degrees": ["degree or above", "bachelor"], "majors": ["related disciplines", "bba"], "languages": ["english", "chinese", "mandarin"], "language_level": ["fluent", "proficient"], "hard_skills": ["credit analysis"], "soft_skills": ["work independently", "team spirit", "under pressure", "detailed"], "languages_combined": [{"language": "english", "language_level": ["proficient"]}, {"language": "chinese", "language_level": ["proficient"]}, {"language": "mandarin", "language_level": ["fluent", "proficient"]}]}, "experience_required": {"duration": ["at least 3 years"], "field": ["relevant experience"]}}, {"job_id": "100003009049394", "location_code": "hk", "company": "Ambition", "job_title": "Assistant Manager, Unsecured Loan Product", "description": "\nAssistant Manager, Unsecured Loan Product\n\nOur client is a leading banking group with diversified businesses in Retail, Corporate and Private banking. With their continuous growth, an excellent opportunity has arisen for a high-calibre product management professional to join their retail banking business.\nReporting to the Team Lead, you will assist in developing and enhancing unsecured loan product. You will assist to formulate and launch unsecured loan product marketing strategies. You will be responsible for liaising with internal and external parties for new product initiatives, executing marketing campaigns to support the business growth. You will also need to prepare training for sales channels on product and campaign details.\n\nTo qualify, individuals must possess:\n\nBachelor degree or above in related discipline\nMinimum 2 years' experience in personal loan and / or card loan, product development, product management gained from Banks, Credit Card and/or other Financial Institutions\nStrong analytical, interpersonal and communication skills\nStrong communications skills in English and Chinese\n\n\n\nContact Petty LAM on (852) 3103 4363 or via email petty.lam@ambition.com.hk, APPLY NOW by clicking the button below quoting reference number PL 252068 www.ambition.com.hk\nData provided is for recruitment purposes only\n\nIf this job isn't quite right for you, but you know someone who would be great at this role, why not take advantage of our referral scheme? We offer HKD1000 in Apple gift cards for every referred candidate who we place in a role. Terms & Conditions Apply. https://www.ambition.com.hk/refer-a-friend", "employment_types": ["Full Time", "Permanent"], "selling_points": ["Sizeable retail bank", "Open to loan product experience", "Attractive salary and bonuses"], "locations": ["Not Specified"], "categories": ["Banking / Finance", "Loan", "Retail Banking", "Financial Services"], "post_time": "2022-01-14T08:33:01Z", "salary": {"currency": null, "max": null, "min": null, "period": "monthly", "term": null}, "salary_visible": false, "title_keywords": ["assistant manager,"], "responsibilities": ["reporting", "management", "marketing strategies", "data", "internal and external parties", "developing", "liaising with", "communication", "executing", "contact", "marketing campaigns", "banking", "recruitment"], "requirements": {"degrees": ["degree or above", "bachelor"], "majors": [], "languages": ["english", "chinese"], "language_level": [], "hard_skills": ["pl", "scheme"], "soft_skills": ["communication skills", "interpersonal", "responsible"], "languages_combined": [{"language": "english", "language_level": []}, {"language": "chinese", "language_level": []}]}, "experience_required": {"duration": ["minimum 2 years"], "field": ["product management", "product development", "credit card", "financial institutions"]}}, {"job_id": "100003009053875", "location_code": "hk", "company": "JAC Recruitment Hong Kong Co., Limited", "job_title": "Non-Bank Financial Institution RM (Budget HKD 40-55k) - Well-known foreign bank", "description": "Our client, a foreign bank, is looking for a\u00a0Non-Bank Financial Institution Relationship Manager\u00a0 for their\u00a0financial institutions Department.\u00a0\n\nJob Description\n\nManage and grow some non-bank financial institutions (Asset management company, insurance company and securities firm.) focusing on clients with Chinese & International background and APAC region.\nProvide professional financial solutions and conduct client due diligence, credit analysis and prepare credit proposals\n\nRequirements:\n\nDegree holder in Business Administration or related disciplines;\nAround 3-7\u00a0 years relevant experience in financial institutions (NBFI / BFI) coverage.\u00a0\nProficient in both spoken and written English and Cantonese.\u00a0\nFluency in Cantonese, Mandarin & English.\u00a0\n\n\"Interested candidates, please send an updated CV to\u00a0kelvin.lam @jac-recruitment.com\u00a0and CC\u00a0jac.hk @jac-recruitment.com", "employment_types": ["Full Time"], "selling_points": ["Well-known foreign Non-Bank Financial Institutions", "Credit Analysis", "3-7  years relevant experience in FI"], "locations": ["Central & Western Area"], "categories": ["Banking / Finance", "Corporate Banking", "Credit Analysis / Approval", "Loan"], "post_time": "2022-01-17T07:40:31Z", "salary": {"currency": null, "max": null, "min": null, "period": "monthly", "term": null}, "salary_visible": false, "title_keywords": [], "responsibilities": ["due diligence", "analysis", "insurance", "asset management"], "requirements": {"degrees": ["degree holder"], "majors": ["related disciplines", "business administration"], "languages": ["cantonese", "english", "mandarin"], "language_level": ["fluency", "proficient"], "hard_skills": [], "soft_skills": [], "languages_combined": [{"language": "cantonese", "language_level": ["fluency", "proficient"]}, {"language": "english", "language_level": ["fluency", "proficient"]}, {"language": "mandarin", "language_level": ["fluency"]}]}, "experience_required": {"duration": [], "field": ["financial institutions", "relevant experience"]}}, {"job_id": "100003009049570", "location_code": "hk", "company": "Conners Consulting Limited", "job_title": "Senior Manager \u2013 Loan Department (Banking) Many Post", "description": "Our client, a well-known bank in Hong Kong, is looking for a high caliber to join the group.\n\nSenior Manager \u2013 Loan Administration\n\nResponsibilities\n\n\nLead team to handle overall loan administration functions to both retail and wholesale banking customers\nEnhance the working guidelines to fulfil the bank\u2019s compliance requirement\n\nRequirements\n\nUniversity degree or above\nAt least 10 years\u2019 experience in loan operation\n\nSenior Manager \u2013 Loan Documentation 1\n\nResponsibilities\n\nEnhance working guideline and policy to fulfil the bank\u2019s compliance requirement.\nReview and provide comments on facility and security documentation prepared by legal counsel\u00a0 \u00a0\u00a0\n\nRequirements\n\nUniversity degree or above\nAt least 10 years\u2019 experience in loan documentation\u00a0\n\nSenior Manager \u2013 Loan Documentation 2\n\nResponsibilities\n\nLead team to handle daily MIS / regulatory reporting and monitoring tasks\nHandle contingency credit control and monitoring / regular reporting\n\nRequirements\n\nUniversity degree or above\nAt least 10 years\u2019 experience on credit process / monitoring of banking industry\u00a0\n\nTo apply, please send your detailed resume or contact Ms Tsui at 3955 1358 for a confidential discussion.\u00a0\nOnly shortlisted candidates will be notified.\u00a0\nApplicants who are not contacted within two weeks may consider their applications unsuccessful.\u00a0\nAll data collected will be used for recruitment purpose only & will be used strictly confidential.\u00a0\n\nConners Consulting Limited\n2005 Kai Tak Commercial Building 317 Des Voeux Road Central Hong Kong\u00a0\nTel: (852) 3996 8090\u00a0\u00a0\u00a0\u00a0\u00a0\u00a0 Website: www.connersconsulting.com", "employment_types": ["Full Time", "Permanent"], "selling_points": ["Senior Manager", "Loan Department", "Attractive Annual Packager"], "locations": ["Central & Western Area"], "categories": ["Banking / Finance", "Loan", "Others", "Order Processing & Operation / Settlement"], "post_time": "2022-01-15T03:50:32Z", "salary": {"currency": null, "max": null, "min": null, "period": "monthly", "term": null}, "salary_visible": false, "title_keywords": ["senior manager"], "responsibilities": ["guidelines", "compliance", "banking", "administration"], "requirements": {"degrees": ["degree or above"], "majors": [], "languages": [], "language_level": [], "hard_skills": ["documentation"], "soft_skills": ["detailed"], "languages_combined": []}, "experience_required": {"duration": ["at least 10 years"], "field": ["banking industry", "operation"]}}, {"job_id": "100003009053456", "location_code": "hk", "company": "Hang Seng Bank Ltd", "job_title": "Proposition Manager", "description": "Wholesale Banking COO Office\n\nHang Seng's Wholesale Banking business provides a broad spectrum of financing solutions to large corporations and financial institutions. As a strategic financial partner to corporate customers, Hang Seng offers a comprehensive range of products and services including bilateral and syndication loans, project financing, property development financing, property investment loans, working capital financing, trade financing, cash management and treasury products. Our experienced and knowledgeable professionals understand the specific requirements of our customers and are committed to providing tailor-made financial packages in their best interests.\n\nWe are currently seeking a high caliber professional to join our department as\u00a0Proposition Manager.\n\n\nPrincipal responsibilities\n\nPerform analysis and provide key insights on portfolio management in managing Wholesale lending assets to optimize balance sheet capacity with focusing on capital efficiency and reward;\nAssist in the execution of lending related initiatives which support business strategies and achieve financial goal;\nOversee the regulatory compliance related to credit and lending and responsible for related regulatory returns;\nDrive and coordinate the IT enhancement, digital lending and data management projects;\nEnsure the timely and quality deliverables to meet the expectation of our key stakeholders\n\nRequirements\n\nUniversity degree in a related discipline or other relevant qualifications;\u00a0\nMinimum of 5 years' experience in banking industry, preferably with experience in lending proposition, business development / business management;\u00a0\nSound knowledge in portfolio management, Bank\u2019s governance framework and regulatory requirements on corporate customers;\u00a0\nStrong attentiveness to detail, resilient and ability to work responsibly in a dynamic environment;\u00a0\nCreative, curious and with sound analytical and problem solving skills;\u00a0\nAbility to manage multiple stakeholders and manage conflicts, high connectivity, capable to drive change and transformation effectively;\u00a0\nProficiency in both spoken and written English and Chinese;\u00a0\nGreat sense of ownership and servicing mindset to ensure efficient and effective customer service processes\nIf you would like to explore other opportunities at Hang Seng Hong Kong, please visit www.hangseng.com/careers/ for details.\nThe health and safety of our employees and candidates is very important to us. Due to the current situation related to the Novel Coronavirus (2019-nCoV), we\u2019re leveraging our digital capabilities to ensure we can continue to recruit top talent at the HSBC Group. As your application progresses, you may be asked to use one of our digital tools to help you through your recruitment journey. If so, one of our Resourcing colleagues will explain how our video-interviewing technology will be used throughout the recruitment process and will be on hand to answer any questions you might have.\nAll information provided by applicants will be used only for recruitment purposes and will be used strictly in accordance with the Bank's personal data policies, a copy of which may be obtained by the applicant upon request. Unless otherwise instructed in writing by the applicant concerned, applicants may be considered for other suitable positions within the Bank and its related companies. The personal data of unsuccessful job applicants may be retained for a maximum of two years from the date when the job application is rejected and such data may be retained for a longer period if there is a subsisting reason that obliges the Bank to do so, after which the personal data will be destroyed.", "employment_types": ["Full Time", "Permanent"], "selling_points": [], "locations": ["Not Specified"], "categories": ["Banking / Finance", "Corporate Banking", "Loan", "Sales, CS & Business Devpt", "Business Development"], "post_time": "2022-01-17T07:00:19Z", "salary": {"currency": null, "max": null, "min": null, "period": "monthly", "term": null}, "salary_visible": false, "title_keywords": ["manager"], "responsibilities": ["management", "data", "analysis", "compliance", "quality", "coordinate", "balance sheet"], "requirements": {"degrees": ["university degree"], "majors": [], "languages": ["english", "chinese"], "language_level": ["proficiency"], "hard_skills": ["business management", "problem solving skills", "dynamic", "reason"], "soft_skills": ["efficient", "dynamic environment", "capable", "analytical and problem solving skills", "customer service", "novel", "creative"], "languages_combined": [{"language": "english", "language_level": ["proficiency"]}, {"language": "chinese", "language_level": ["proficiency"]}]}, "experience_required": {"duration": ["minimum of 5 years"], "field": ["business", "banking industry", "management", "business development"]}}, {"job_id": "100003009044044", "location_code": "hk", "company": "Sun Hung Kai Credit Limited", "job_title": "Direct Sales - Mortgage Business", "description": "Responsibilities\n\nPlan and implement mortgage product marketing strategies\nAchieve individual and team targets on mortgage lending\nCultivate and maintain business relationships with customers\nDrive mortgage business and generate revenue from network through various sales activities\nPersonal sales and marketing duties to achieve target on mortgage loan business\nReview mortgage loan applications and monitor overdraft accounts\nHandle incoming customer enquiries\n\n\u00a0Requirements\n\nDegree holder or above\nMinimum 3 to 5 years of relevant experience in finance, banking or property industry with a focus in mortgage loan business\nStrong potential client network\nStrong communications and leadership skills\nAggressive, proactive with an outgoing personality\nProficient in Microsoft Office and Chinese word processing\nGood command of spoken and written Chinese, Putonghua & English\n\n\u00a0We offer a competitive remuneration package to the right candidate.\u00a0\n\nPlease send your resume with present and expected salaries to Human Resources Department at by email.\n\nPlease visit\u00a0www.shkcredit.com.hk for more information about us.\u00a0\n\n\n\nDisclaimer / Policy Statements\n\nWe are an Equal Opportunity Employer and welcome applications from all qualified candidates. We evaluate qualified applicants without regards to gender, race, colour, nationality, religion, sexual orientation or disability and other status protected by law. We respect and seek to empower each individual and support diverse cultures, perspectives, skills and experience within our workforce to foster an inclusive work environment.\n\nAll applications will be treated in the strictest confidence. Personal data provided will be used for recruitment purposes only.", "employment_types": ["Full Time", "Permanent"], "selling_points": ["First Mortgage Loan and Second Mortgage Loan", "Mortgage loan business", "Mortgage lending"], "locations": ["Wan Chai"], "categories": ["Banking / Finance", "Loan", "Mortgage"], "post_time": "2022-01-13T02:54:03Z", "salary": {"currency": null, "max": null, "min": null, "period": "monthly", "term": null}, "salary_visible": false, "title_keywords": ["sales"], "responsibilities": ["sales activities", "marketing strategies", "customer enquiries", "review", "monitor", "maintain", "plan"], "requirements": {"degrees": ["degree holder"], "majors": [], "languages": ["putonghua", "english", "chinese"], "language_level": ["good command", "proficient"], "hard_skills": ["focus", "chinese word processing", "microsoft office"], "soft_skills": ["outgoing personality", "focus", "leadership skills", "proactive"], "languages_combined": [{"language": "putonghua", "language_level": ["good command"]}, {"language": "english", "language_level": ["good command"]}, {"language": "chinese", "language_level": ["good command", "proficient"]}]}, "experience_required": {"duration": ["minimum 3 to 5 years"], "field": ["loan business", "finance", "relevant experience", "banking"]}}, {"job_id": "100003009045949", "location_code": "hk", "company": "PrimeCredit Ltd", "job_title": "Customer Service Representative (Part-time) (Sunday Working)", "description": "Responsibilities:\n\nGreet & welcome all walk in customers in branch\nPerform administrative duties e.g. photocopying & filing\nAssist in branch operation\nHandle customers\u2019 enquiries & requests\n\nRequirements:\n\nForm 5 / DSE graduate or above\nFluent in written and spoken English is must\nKnowledge of Tagalog or Bahasa is an advantage\nSunday work is a must\nGood interpersonal & communication skills\nUndergraduate / Fresh graduate will be also considered\n\nThis is a very rewarding and exciting opportunity. We offer an attractive remuneration to the successful candidates. Please forward your resume with present and expected salary by clicking \u201cAPPLY NOW\u201d or complete the online application form at https://www.primecredit.com/career/en/jobs.\n\nTo know more about PrimeCredit, please visit our websites https://www.primecredit.com/career/en/.\n\nAll applications will be treated in strict confidence and only be used for recruitment related purpose.", "employment_types": ["Part Time"], "selling_points": ["Provide excellent customer service", "Part time sunday work", "Knowledge of Tagalog or Bahasa is an advantage"], "locations": ["Shatin Area"], "categories": ["Admin & HR", "Clerical / Admin Staff", "Banking / Finance", "Loan", "Sales, CS & Business Devpt", "Customer Service - Supervisor / Officer"], "post_time": "2022-01-13T09:12:01Z", "salary": {"currency": null, "max": null, "min": null, "period": "hourly", "term": null}, "salary_visible": false, "title_keywords": ["customer service representative"], "responsibilities": ["administrative duties"], "requirements": {"degrees": ["fresh graduate", "form 5", "dse"], "majors": [], "languages": ["english", "tagalog"], "language_level": ["advantage", "fluent"], "hard_skills": [], "soft_skills": ["communication skills", "interpersonal"], "languages_combined": [{"language": "english", "language_level": ["fluent"]}, {"language": "tagalog", "language_level": ["advantage"]}]}, "experience_required": {"duration": [], "field": []}}, {"job_id": "100003009047717", "location_code": "hk", "company": "Public Bank (Hong Kong) Limited", "job_title": "Assistant Manager - Special Projects Unit (Credit Department) (Ref: JD-AMSPU)", "description": "Assist in implementing credit risk management systems\nPrepare/ Review reports related to credit risk management for identification/ evaluation of potential risks\nAssist in development of electronic systems to enhance the Bank's loan delivery process\nAssist in managing credit-related projects\nUniversity Degree with minimum 6 years of banking experience, of which minimum 3 years in credit risk management function\nKnowledgeable in credit risk modeling and banking products\nStrong credit sense and conversant with financial analysis\nProficiency in data analysis using MS Excel\nWith Enhanced Competency Framework (ECF) qualification is preferable\n\nTo apply, interested parties please follow the application methods available in the Bank\u2019s career website https://www.publicbank.com.hk/en/aboutus/careeropportunities. You can send us your resume quoting our job reference number together with present & expected salary (a must) to the Human Resources Department by email or fax at 2815 3157 or by post to Human Resources Department, 12/F, Public Bank Centre, 120 Des Voeux Road Central, Hong Kong. You may also visit our career website for other career opportunities available within our Group.\n\nPersonal data collected will be used for recruitment purpose only and will be treated in accordance with the Bank\u2019s Personal Information Collection Statement, a copy of which has been available in the Bank\u2019s career website.", "employment_types": ["Full Time", "Permanent"], "selling_points": [], "locations": ["Not Specified"], "categories": ["Banking / Finance", "Credit Analysis / Approval", "Loan", "Mortgage"], "post_time": "2022-01-15T03:48:58Z", "salary": {"currency": null, "max": null, "min": null, "period": null, "term": null}, "salary_visible": false, "title_keywords": ["assistant manager"], "responsibilities": ["management", "review", "systems", "banking", "financial analysis", "data analysis", "reports", "evaluation"], "requirements": {"degrees": ["university degree"], "majors": ["risk management"], "languages": [], "language_level": [], "hard_skills": ["financial analysis", "analysis", "ms excel"], "soft_skills": [], "languages_combined": []}, "experience_required": {"duration": ["minimum 6 years", "minimum 3 years"], "field": ["credit risk", "management", "banking experience"]}}, {"job_id": "100003009050271", "location_code": "hk", "company": "China Construction Bank (Asia) Corporation Limited", "job_title": "Unsecured Personal Loans Professional (Ref: CB/MF)", "description": "Main Responsibilities\nSupport preparation and implementation for product programs to deliver business target and objectives\nPropose pricing strategy based on program nature, business objectives, targets and predicted behaviour\nWork with different sale channels and internal departments to ensure smooth execution of programs\nAssist in tracking and analysing data and results of programs\nMonitor marketing trend and conduct competitive analyse\nEnsure all programs and projects are adhered to banking practice, compliance and regulatory requirement\nActively work with project team & related departments to support and deliver the New Generation projects related to secured and unsecured loans\nRequirements\nUniversity degree with minimum 4 years marketing experience, preferably in credit card / loan / consumer banking\nAggressive, result-oriented, good communication and interpersonal skills\nSelf-motivated, enthusiastic and able to work independently\nSensitive to market changes and strong business acumen with excellent project management skills\nProficient in spoken and written English, Cantonese and Mandarin\nApplicants who are not contacted within 8 weeks may consider their applications unsuccessful and their personal data will be retained by the bank for a period up to two years.\n\nAll information provided by applicants will be used for recruitment purposes only and will be used strictly in accordance with the bank\u2019s personal data policies, a copy of which will be provided upon request.", "employment_types": ["Full Time"], "selling_points": ["Credit Card & Pesonal loans Product", "unsecured lending", "product development"], "locations": ["Not Specified"], "categories": ["Banking / Finance", "Loan"], "post_time": "2022-01-14T10:03:20Z", "salary": {"currency": null, "max": null, "min": null, "period": "monthly", "term": null}, "salary_visible": false, "title_keywords": ["personal"], "responsibilities": ["data", "compliance", "monitor", "implementation", "banking", "marketing trend", "analyse", "tracking"], "requirements": {"degrees": ["university degree"], "majors": ["marketing"], "languages": ["cantonese", "english", "mandarin"], "language_level": ["proficient"], "hard_skills": ["project management", "acumen"], "soft_skills": ["work independently", "self-motivated", "project management skills", "sensitive to", "communication and interpersonal skills", "enthusiastic", "business acumen", "result-oriented"], "languages_combined": [{"language": "cantonese", "language_level": ["proficient"]}, {"language": "english", "language_level": ["proficient"]}, {"language": "mandarin", "language_level": ["proficient"]}]}, "experience_required": {"duration": ["minimum 4 years"], "field": ["credit card", "marketing", "banking"]}}, {"job_id": "100003009045945", "location_code": "hk", "company": "PrimeCredit Ltd", "job_title": "Customer Service Executive, Card Centre (With Monthly Incentive + 4-Month Plus Discretionary Bonus)", "description": "Responsibilities\n\n\nHandle customer inquiries, request and complaints\nHandle customer requests on dispute transaction, re-issue of statement, sales slip or other information retrieval\nMaintain and update customer information upon request\nAssist Marketing department in telemarketing of credit card product\n\nRequirements\n\n\nForm 5 / DSE graduate or above\n2-3 years\u2019 relevant working experience in consumer finance / retail banking industry, preferable in credit card products\nShift duty is required\nDynamic, strong analytical skill, good interpersonal and communication skills\nFluent in spoken and written English and Chinese\nProficient in MS Office applications including Excel, PowerPoint and Chinese / English word processing\n\nThis is a very rewarding and exciting opportunity. We offer an attractive remuneration to the successful candidates. Please forward your resume with present and expected salary by clicking \u201cAPPLY NOW\u201d or complete the online application form at\u00a0https://www.primecredit.com/career/en/jobs.\n\nTo know more about PrimeCredit, please visit our websites\u00a0https://www.primecredit.com/career/en/.\n\nAll applications will be treated in strict confidence and only be used for recruitment related purpose.", "employment_types": ["Full Time", "Permanent"], "selling_points": ["Handle customer inquiries about credit card", "Maintain and update customer information", "2-3 years\u2019 relevant working experience"], "locations": ["Wan Chai"], "categories": ["Banking / Finance", "Loan", "Sales, CS & Business Devpt", "Call Centre", "Customer Service - Supervisor / Officer"], "post_time": "2022-01-13T09:12:00Z", "salary": {"currency": null, "max": null, "min": null, "period": "monthly", "term": null}, "salary_visible": false, "title_keywords": ["customer service executive"], "responsibilities": ["maintain", "customer inquiries", "customer requests"], "requirements": {"degrees": ["form 5", "dse"], "majors": [], "languages": ["english", "chinese"], "language_level": ["proficient", "fluent"], "hard_skills": ["excel", "analytical skill", "word processing", "powerpoint", "dynamic", "ms office"], "soft_skills": ["communication skills", "analytical skill", "dynamic", "interpersonal"], "languages_combined": [{"language": "english", "language_level": ["proficient", "fluent"]}, {"language": "chinese", "language_level": ["proficient", "fluent"]}]}, "experience_required": {"duration": ["2-3 years"], "field": ["credit card", "finance", "retail banking", "relevant working experience"]}}, {"job_id": "100003009039966", "location_code": "hk", "company": "\u81fa\u7063\u4e2d\u5c0f\u4f01\u696d\u9280\u884c\u80a1\u4efd\u6709\u9650\u516c\u53f8", "job_title": "\u570b\u969b\u806f\u8cb8\u53ca\u8de8\u5883\u878d\u8cc7\u696d\u52d9\u4eba\u54e1", "description": "\u5de5\u4f5c\u5167\u5bb9\uff1a\u8fa6\u7406\u570b\u969b\u806f\u8cb8\u8207\u8de8\u5883\u878d\u8cc7\u76f8\u95dc\u696d\u52d9\u3002\n\n\u8cc7\u683c\u689d\u4ef6\uff1a\n1.\u5b78\u6b77\uff1a\u570b\u5167\u5916\u5c08\u79d1\u4ee5\u4e0a\u5b78\u6821\u7562\u696d\u6216\u5177\u6709\u540c\u7b49\u5b78\u6b77\u3002\n\n2.\u5de5\u4f5c\u7d93\u6b77\uff1a\n(1)\u5177\u91d1\u878d\u6a5f\u69cb\u76f8\u95dc\u5de5\u4f5c\u7d93\u6b7710\u5e74\u4ee5\u4e0a\uff0c\u4e26\u65bc\u9999\u6e2f\u91d1\u878d\u6a5f\u69cb\u5de5\u4f5c\u7d93\u6b775\u5e74\u4ee5\u4e0a\u3002\n(2)\u5177\u9999\u6e2f\u5730\u5340\u6216\u5176\u4ed6\u6d77\u5916\u5730\u5340\u806f\u8cb8\u5e02\u5834\u696d\u52d9\u7c4c\u7d44\u7d93\u9a572\u5e74\u4ee5\u4e0a\u3002\n\n3.\u5176\u4ed6\u5c08\u9577\u8207\u5c08\u696d\u8b49\u7167\uff1a\n(1)\u5177\u4e2d\u3001\u82f1\u6587\u6e9d\u901a\u80fd\u529b\u3002\n(2)\u64d4\u4efb\u4e3b\u7ba1\u8077\uff0c\u61c9\u5177\u5099\u300c\u91d1\u878d\u63a7\u80a1\u516c\u53f8\u53ca\u9280\u884c\u696d\u5167\u90e8\u63a7\u5236\u53ca\u7a3d\u6838\u5236\u5ea6\u5be6\u65bd\u8fa6\u6cd5\u300d\u898f\u5b9a\u4e4b\u5167\u63a7\u76f8\u95dc\u7d93\u6b77\u3001\u8a13\u7df4\u6216\u8b49\u66f8\u3002\n\n\u4e0a\u73ed\u5730\u9ede\uff1a\u81fa\u7063(\u914d\u5408\u696d\u52d9\u9700\u8981\u9577\u671f\u6d3e\u99d0\u6d77\u5916\u55ae\u4f4d\u5de5\u4f5c)\n\n*\u6709\u610f\u8005\u8acb\u8a3b\u660e\u300c\u7504\u9078\u985e\u5225\u300d\uff0c\u4e26\u5c07\u4e2d\u3001\u82f1\u6587\u5c65\u6b77\u53ca\u76f8\u95dc\u8cc7\u6599\u4ee5\u96fb\u5b50\u90f5\u4ef6\u65b9\u5f0f\u5bc4\u81f3Apply Now\u3002\u672a\u4f9d\u898f\u5b9a\u65b9\u5f0f\u5831\u540d\u8005\uff0c\u8996\u70ba\u8cc7\u683c\u4e0d\u7b26\u3002\n\n", "employment_types": ["Full Time"], "selling_points": [], "locations": ["Overseas"], "categories": ["Banking / Finance", "Loan", "Financial Services", "Fund Management"], "post_time": "2022-01-11T16:02:24Z", "salary": {"currency": null, "max": null, "min": null, "period": "monthly", "term": null}, "salary_visible": false, "title_keywords": [], "responsibilities": [], "requirements": {"degrees": [], "majors": [], "languages": [], "language_level": [], "hard_skills": [], "soft_skills": [], "languages_combined": []}, "experience_required": {"duration": [], "field": []}}, {"job_id": "100003009049954", "location_code": "hk", "company": "Giant Mind (China) Limited", "job_title": "Compliance Manager", "description": "Job Responsibilities:\n\nEnsuring company financial documents comply with legal standards\u00a0\nEnsure the salesman signs the documents in compliance\nEnsure the salesman comply with the company approval guidelines\nEnsure compliance with anti-money laundering guidelines\nConduct process for monitoring and tracking of remedial actions derived from Compliance Monitoring activity under regulatory or internal requirement.\nMaintain and review company\u2019s policies, procedures and practices to ensure compliance with all applicable laws and regulations\u00a0\nPrepare and respond to inquiries and audits from regulatory authorities\n\nRequirements\n\n\nHolding a degree or professional qualification in Legal, Business, Finance, Accounting or related disciplines\nMinimum 3 years compliance experience\nWorking knowledge of securities laws and regulations in Hong Kong, with a good understanding of financial business compliance tasks\nA good team player, mature, responsible, detail minded, with the ability to handle multiple tasks independently under pressure\nHigh proficiency in PC skills and MS office applications (MS Excel, Word & PowerPoint)\nGood communication and organization skills\nGood command in written and spoken English, Cantonese and Chinese\nSalary negotiable", "employment_types": ["Full Time", "Permanent"], "selling_points": ["5.5 working days", "corporate finance industry preferred", "Company Ordinances and regulatory matters"], "locations": ["Central"], "categories": ["Banking / Finance", "Loan"], "post_time": "2022-01-14T09:29:49Z", "salary": {"currency": null, "max": null, "min": null, "period": "monthly", "term": null}, "salary_visible": false, "title_keywords": ["compliance manager"], "responsibilities": ["regulations", "guidelines", "policies", "monitoring", "compliance", "review", "procedures", "ensure compliance", "maintain", "audits", "tracking"], "requirements": {"degrees": ["degree"], "majors": ["related disciplines", "finance", "business", "accounting"], "languages": ["cantonese", "english", "chinese"], "language_level": ["good command"], "hard_skills": ["word", "powerpoint", "securities laws", "ms excel", "pc skills", "ms office"], "soft_skills": ["good team player", "independently", "under pressure", "responsible", "mature", "handle multiple tasks", "communication", "organization skills"], "languages_combined": [{"language": "cantonese", "language_level": ["good command"]}, {"language": "english", "language_level": ["good command"]}, {"language": "chinese", "language_level": ["good command"]}]}, "experience_required": {"duration": ["minimum 3 years"], "field": ["compliance"]}}, {"job_id": "100003009045948", "location_code": "hk", "company": "PrimeCredit Ltd", "job_title": "Loan Business Executive", "description": "Responsibilities\n\nExplore neighborhood sales opportunities and establish local sales network to solicit personal loans & credit card business via direct selling to meet individual sales target\nTake part in sales and promotion programs to acquire business opportunities and ensure satisfactory after-sales services\nHandle and follow up customer\u2019s enquiries on company products and services\nMaintain and develop relationship with potential customers\n\nRequirements\n\nForm 5 / DSE graduate or above\nMinimum 1 year of direct sales experience in retail banking or consumer finance business, preferable in personal loan business\nSound knowledge of consumer finance products, including personal loan and credit card\nGood command in both spoken and written English & Chinese\n\nThis is a very rewarding and exciting opportunity. We offer an attractive remuneration to the successful candidates. Please forward your resume with present and expected salary by clicking \u201cAPPLY NOW\u201d or complete the online application form at https://www.primecredit.com/career/en/jobs.\n\nTo know more about PrimeCredit, please visit our websites https://www.primecredit.com/career/en/.\n\nAll applications will be treated in strict confidence and only be used for recruitment related purpose.", "employment_types": ["Full Time", "Permanent"], "selling_points": ["Explore neighborhood sales opportunities", "Take part in sales and promotion programs", "Minimum 1 year of direct sales experience"], "locations": ["Wan Chai"], "categories": ["Banking / Finance", "Loan", "Sales, CS & Business Devpt", "Others", "Direct Sales"], "post_time": "2022-01-13T09:12:01Z", "salary": {"currency": null, "max": null, "min": null, "period": "monthly", "term": null}, "salary_visible": false, "title_keywords": ["business executive"], "responsibilities": ["sales target", "maintain", "business opportunities", "develop"], "requirements": {"degrees": ["form 5", "dse"], "majors": [], "languages": ["english", "chinese"], "language_level": ["good command"], "hard_skills": [], "soft_skills": [], "languages_combined": [{"language": "english", "language_level": ["good command"]}, {"language": "chinese", "language_level": ["good command"]}]}, "experience_required": {"duration": ["minimum 1 year"], "field": ["loan business", "finance", "retail banking", "business"]}}, {"job_id": "100003009050689", "location_code": "hk", "company": "Bank of Communications (Hong Kong) Limited", "job_title": "Mortgage Sales Manager", "description": "To achieve mortgage sales targets by establishing good relationship with business partners such as property agencies\nDegree holder or above, with minimum 3 years\u2019 experience in generating mortgage lending business in banking industries\nPasses in MPF, Insurance and Securities Intermediaries Examinations (Qualified under SFO for handling Regulated Activities Type 1 & 4)\nCandidates with less experience will be considered as Deputy Mortgage Sales Manager\n\u00a0\n\nWe offer attractive remuneration package to the right candidates. Please send your full resume with expected salary to\u00a0The Human Resources Manager, Bank of Communications Co., Ltd., 10/F, Bank of\u00a0Communications\u00a0Tower,\u00a0231-235 Gloucester Road, Wan Chai,\u00a0Hong Kong, or fax to\u00a02838 9209, or e-mail to : APPLY NOW.", "employment_types": ["Full Time"], "selling_points": ["Degree holder or above", "minimum 3 years\u2019 experience in generating mortgage", "Passes in MPF, Insurance Examinations"], "locations": ["Wan Chai"], "categories": ["Banking / Finance", "Loan", "Mortgage", "Others"], "post_time": "2022-01-14T11:10:47Z", "salary": {"currency": null, "max": null, "min": null, "period": "monthly", "term": null}, "salary_visible": false, "title_keywords": ["sales manager"], "responsibilities": ["good relationship", "insurance", "mpf", "banking"], "requirements": {"degrees": ["degree holder"], "majors": ["business"], "languages": [], "language_level": [], "hard_skills": ["sfo"], "soft_skills": [], "languages_combined": []}, "experience_required": {"duration": ["minimum 3 years"], "field": ["business", "banking"]}}, {"job_id": "100003009049387", "location_code": "hk", "company": "Shanghai Commercial Bank Ltd", "job_title": "Trade Finance Officer", "description": "Responsibilities:\u00a0\n\nAssist supervisors on daily operations of Bills Processing Centre\nPerform LC documents checking, Import and Export loans processing\nEnsure transactions are handled in accordance with the Bank's policies, procedures and guidelines\nHandle enquiries from customers and internal staff\nWork closely with business units to provide quality bills services to customers\n\nRequirements:\u00a0\n\nDegree holder in Business Administration or related disciplines\nMinimum 3 years of relevant experience in trade finance operations\nGood knowledge in trade financing and familiar with UCP600 and ISBP\nCertified Documentary Credit Specialist is preferred\nProactive, able to work independently and under pressure\nGood command of spoken and written English and Chinese, including Putonghua\u00a0\n\nAttractive remuneration package will be offered to the right candidates. Interested parties please click\u00a0\"Apply Now\"\u00a0to submit your full resume with current and expected salary to the\u00a0Human Resources Division.\n\nPlease visit us at\u00a0www.shacombank.com.hk\u00a0for more information about our Bank.\n\nAll personal data collected will be used for recruitment related purposes strictly in accordance with the Bank's personal data policies, a copy of which will be provided immediately upon request by contacting our Personal Data Compliance Officer. Applicants who are not contacted within two months may consider their applications unsuccessful and the personal data collected from the applicants will be retained for no longer than two years from the date of rejection during which the applicants may be considered for other suitable positions within the Bank.", "employment_types": ["Full Time", "Permanent"], "selling_points": ["Perform LC documents checking", "Assist supervisors on daily operations", "Handle enquiries from customers and internal staff"], "locations": ["Kwai Hing"], "categories": ["Banking / Finance", "Loan", "Others", "Order Processing & Operation / Settlement"], "post_time": "2022-01-15T03:50:22Z", "salary": {"currency": null, "max": null, "min": null, "period": "monthly", "term": null}, "salary_visible": false, "title_keywords": ["finance officer"], "responsibilities": ["guidelines", "policies", "procedures", "checking", "transactions", "quality", "handle enquiries", "daily operations", "loans processing"], "requirements": {"degrees": ["degree holder"], "majors": ["related disciplines", "business administration"], "languages": ["putonghua", "english", "chinese"], "language_level": ["good command"], "hard_skills": [], "soft_skills": ["work independently", "proactive", "under pressure"], "languages_combined": [{"language": "putonghua", "language_level": ["good command"]}, {"language": "english", "language_level": ["good command"]}, {"language": "chinese", "language_level": ["good command"]}]}, "experience_required": {"duration": ["minimum 3 years"], "field": ["finance", "relevant experience"]}}, {"job_id": "100003009039965", "location_code": "hk", "company": "Taiwan Business Bank Co., Ltd", "job_title": "\u7d93\u71df\u9ad8\u6de8\u503c\u8ca1\u52d9\u7ba1\u7406\u696d\u52d9\u4eba\u54e1", "description": "\u5de5\u4f5c\u5167\u5bb9\uff1a\n1.\u719f\u6089\u5883\u5167\u5916\u57fa\u91d1\u3001\u6d77\u5916\u50b5\u3001\u6d77\u5916\u80a1\u7968\u3001\u7279\u5225\u80a1\u3001\u6307\u6578\u578b\u57fa\u91d1\u53ca\u884d\u751f\u6027\u91d1\u878d\u5546\u54c1\u7b49\u5546\u54c1\u7279\u6027\uff0c\u70ba\u9867\u5ba2\u9032\u884c\u5168\u65b9\u4f4d\u8ca1\u5bcc\u7ba1\u7406\u898f\u5283\u3002\n\n2.\u6eff\u8db3\u9ad8\u6de8\u503c\u8ca1\u5bcc\u7ba1\u7406\u5ba2\u6236\u5c0d\u570b\u969b\u91d1\u878d\u5e02\u5834\u7522\u54c1\u4e4b\u9700\u6c42\u8207\u5c08\u696d\u670d\u52d9\u3002\n\n3.\u70ba\u5ba2\u6236\u91cf\u8eab\u6253\u9020\u500b\u4eba\u6216\u5176\u5bb6\u65cf\u4e4b\u8cc7\u7522\u7ba1\u7406\u3002\n\n4.\u5354\u52a9\u6df1\u8015\u9ad8\u8cc7\u7522\u5ba2\u6236\uff0c\u589e\u52a0\u5ba2\u6236\u4e4b\u9ecf\u8457\u5ea6\u8207\u670d\u52d9\u4e4b\u5ee3\u5ea6\u548c\u6df1\u5ea6\u3002\n\n5.\u958b\u767c\u9ad8\u8cc7\u7522\u5ba2\u6236\u3002\n\n\u8cc7\u683c\u689d\u4ef6\uff1a\n1.\u5b78\u6b77\uff1a\n\u570b\u5167\u3001\u5916\u91d1\u878d\u3001\u7d93\u6fdf\u3001\u5546\u696d\u3001\u7ba1\u7406\u7814\u7a76\u6240\u7562\u696d\uff0c\u4e14\u5df2\u53d6\u5f97\u78a9\u58eb\u4ee5\u4e0a\u5b78\u4f4d\u8b49\u66f8\u3002\n\n2.\u5de5\u4f5c\u7d93\u6b77\uff1a\n\u5177\u91d1\u878d\u6a5f\u69cb\u76f8\u95dc\u5de5\u4f5c\u7d93\u6b7710\u5e74\u4ee5\u4e0a\uff0c\u4e26\u65bc\u9999\u6e2f\u91d1\u878d\u6a5f\u69cb\u5de5\u4f5c\u7d93\u6b775\u5e74\u4ee5\u4e0a\u3002\n\n3.\u5176\u4ed6\u5c08\u9577\u8207\u5c08\u696d\u8b49\u7167\uff1a\n(1)\u5177\u4e2d\u3001\u82f1\u6587\u6e9d\u901a\u80fd\u529b\u3002\n(2)\u82f1\u8a9e\u8a9e\u6587\u6e2c\u9a57\u6a19\u6e96\u61c9\u5177\u76f8\u7576\u65bc\u5168\u6c11\u82f1\u6aa2(GEPT)\u4e2d\u9ad8\u7d1a(\u542b)\u4ee5\u4e0a\u3002\n(3)\u64d4\u4efb\u4e3b\u7ba1\u8077\uff0c\u61c9\u5177\u5099\u300c\u91d1\u878d\u63a7\u80a1\u516c\u53f8\u53ca\u9280\u884c\u696d\u5167\u90e8\u63a7\u5236\u53ca\u7a3d\u6838\u5236\u5ea6\u5be6\u65bd\u8fa6\u6cd5\u300d\u898f\u5b9a\u4e4b\u5167\u63a7\u76f8\u95dc\u7d93\u6b77\u3001\u8a13\u7df4\u6216\u8b49\u66f8\u3002\n\n\u4e0a\u73ed\u5730\u9ede\uff1a\u81fa\u7063(\u914d\u5408\u696d\u52d9\u9700\u8981\u9577\u671f\u6d3e\u99d0\u6d77\u5916\u55ae\u4f4d\u5de5\u4f5c)\n\n*\u6709\u610f\u8005\u8acb\u8a3b\u660e\u300c\u7504\u9078\u985e\u5225\u300d\uff0c\u4e26\u5c07\u4e2d\u3001\u82f1\u6587\u5c65\u6b77\u53ca\u76f8\u95dc\u8cc7\u6599\u4ee5\u96fb\u5b50\u90f5\u4ef6\u65b9\u5f0f\u5bc4\u81f3Apply Now\u3002\u672a\u4f9d\u898f\u5b9a\u65b9\u5f0f\u5831\u540d\u8005\uff0c\u8996\u70ba\u8cc7\u683c\u4e0d\u7b26\u3002\n\n", "employment_types": ["Full Time"], "selling_points": [], "locations": ["Overseas"], "categories": ["Banking / Finance", "Loan", "Fund Management", "Wealth Management"], "post_time": "2022-01-11T16:02:24Z", "salary": {"currency": null, "max": null, "min": null, "period": "monthly", "term": null}, "salary_visible": false, "title_keywords": [], "responsibilities": [], "requirements": {"degrees": [], "majors": [], "languages": [], "language_level": [], "hard_skills": [], "soft_skills": [], "languages_combined": []}, "experience_required": {"duration": [], "field": []}}, {"job_id": "100003009035347", "location_code": "hk", "company": "Bravo Personnel Consultancy Limited", "job_title": "Mortgage Loan / Settlement Officer ($20K-25K)", "description": "Job requirements:\nDegree holder in in Finance, Business Administration or equivalent\nA minimum of 1 year experience in mortgage loan or settlement operations\nExperience in loan origination, loan recovery and reverse mortgage operations would be an advantage\nGood command of spoken and written English and Chinese\nGood communication skills and team players\n12 months contract (renewable)\nInterested parties, please contact Ms LEE at 2881 6923 during office hours or email your CV by clicking \"Apply Now\"\u00a0or fax your resume to 2576 8026. All the personal data collected will be used for recruitment purpose only.\u00a0\u00a0", "employment_types": ["Full Time", "Permanent"], "selling_points": [], "locations": ["Not Specified"], "categories": ["Banking / Finance", "Loan", "Mortgage", "Order Processing & Operation / Settlement"], "post_time": "2022-01-10T10:17:18Z", "salary": {"currency": null, "max": null, "min": null, "period": "monthly", "term": null}, "salary_visible": false, "title_keywords": ["officer"], "responsibilities": ["communication", "operations", "administration"], "requirements": {"degrees": ["degree holder"], "majors": ["finance", "business administration"], "languages": ["english", "chinese"], "language_level": ["good command"], "hard_skills": [], "soft_skills": ["communication skills"], "languages_combined": [{"language": "english", "language_level": ["good command"]}, {"language": "chinese", "language_level": ["good command"]}]}, "experience_required": {"duration": ["minimum of 1 year"], "field": ["settlement operations"]}}, {"job_id": "100003009039088", "location_code": "hk", "company": "The Bank of East Asia, Limited", "job_title": "Senior Clerk (Loan Services)", "description": "Senior Clerk (Loan Services) (Job ID: 3371)\n\nResponsibilities\nTo be a team member of Lending Operations Department (work location: Mongkok)\nTo perform loan operations activities including but not limited to the followings:\nData input and checking on loan processing\nDay-end balancing\nImpairment loan handling\nPrepare and review payments by Chats, SWIFT and Cashier Order etc.\nTo take up ad-hoc tasks as assigned\nRequirements\nUniversity graduates with previous banking experience preferred\nPreferably with 1-2 years\u2019 of working experience in banking sector\nA good team player with strong interpersonal and communication skills\nGood knowledge of MS Office\nGood command of both spoken and written English and Chinese, Putonghua proficiency will be an advantage\nPlease apply online via the BEA Careers website at https://careers.hkbea.com/psp/hcmprd/EMPLOYEE/HRMS/c/HRS_HRAM.HRS_APP_SCHJOB.GBL?Page=HRS_APP_JBPST&Action=UFOCUS=Applicant&SiteId=1&JobOpeningId=3331&PostingSeq=1 or by clicking the \"Apply Now\" button below. Kindly note that if you are a new user, you have to first create your User Profile before you can apply.\n\nPersonal data provided by job applicants will be used for recruitment purposes only and will be treated in accordance with the Bank's Personal Information Collection (Employees) Statement and Privacy Policy Statement. Applicants who are not invited for interviews within six weeks may consider their applications unsuccessful and the personal data collected will be destroyed after six months.", "employment_types": ["Full Time", "Permanent"], "selling_points": ["Data input and checking on loan processing", "Day-end balancing & impairment loan handling", "University graduate with 1-2 yrs' exp. preferred"], "locations": ["Mong Kok"], "categories": ["Banking / Finance", "Loan", "Financial Services", "Order Processing & Operation / Settlement"], "post_time": "2022-01-11T08:42:12Z", "salary": {"currency": null, "max": null, "min": null, "period": null, "term": null}, "salary_visible": false, "title_keywords": ["senior clerk"], "responsibilities": [], "requirements": {"degrees": [], "majors": [], "languages": [], "language_level": [], "hard_skills": [], "soft_skills": [], "languages_combined": []}, "experience_required": {"duration": [], "field": []}}, {"job_id": "100003009049139", "location_code": "hk", "company": "Shanghai Commercial Bank Ltd", "job_title": "Assistant Relationship Manager, Commercial & Retail Lending", "description": "Responsibilities:\n\nProvide total financial solutions to customers in the areas of personal/corporate lending and trade financing\nConduct credit analyses and prepare credit proposals\nCultivate long-term relationship with customers and explore new business opportunities through marketing and cross-selling bank products and services\n\nRequirements:\n\nDegree holder with 5 years of relevant experience and a qualified Technical Representative\nExperience in personal/corporate lending business and trade finance\nStrong credit analysis and risk management skills\nExcellent relationship management, communication and interpersonal skills\nSelf-motivated, customer-centric and able to work under pressure\nExcellent command of spoken and written English and Chinese, including Putonghua\nProficient in MS Office applications including Chinese word processing\n\nAttractive remuneration package will be offered to the right candidates. Interested parties please click \"Apply Now\" to submit your full resume with current and expected salary to the Human Resources Division.\n\nPlease visit us at www.shacombank.com.hk for more information about our Bank.\n\nAll personal data collected will be used for recruitment related purposes strictly in accordance with the Bank's personal data policies, a copy of which will be provided immediately upon request by contacting our Personal Data Compliance Officer. Applicants who are not contacted within two months may consider their applications unsuccessful and the personal data collected from the applicants will be retained for no longer than two years from the date of rejection during which the applicants may be considered for other suitable positions within the Bank.", "employment_types": ["Full Time", "Permanent"], "selling_points": ["Provide total financial solutions to customers", "Conduct credit analyses & prepare credit proposals", "Cultivate long-term relationship with customers"], "locations": ["Not Specified"], "categories": ["Banking / Finance", "Corporate Banking", "Loan", "Others"], "post_time": "2022-01-15T03:50:07Z", "salary": {"currency": null, "max": null, "min": null, "period": "monthly", "term": null}, "salary_visible": false, "title_keywords": ["assistant relationship manager"], "responsibilities": ["explore new business opportunities"], "requirements": {"degrees": ["degree holder"], "majors": [], "languages": ["putonghua", "english", "chinese"], "language_level": ["excellent", "proficient"], "hard_skills": ["credit analysis", "chinese word processing", "ms office"], "soft_skills": ["self-motivated", "communication and interpersonal skills", "work under pressure"], "languages_combined": [{"language": "putonghua", "language_level": ["excellent"]}, {"language": "english", "language_level": ["excellent"]}, {"language": "chinese", "language_level": ["excellent", "proficient"]}]}, "experience_required": {"duration": ["5 years"], "field": ["finance", "business", "relevant experience"]}}, {"job_id": "100003009044819", "location_code": "hk", "company": "The Bank of Nova Scotia", "job_title": "Officer, Trade Finance Operations APAC, Hong Kong", "description": "Job Accountabilities:\n\nContributes to the overall success of the Trade Finance operations in the region, ensuring specific individual goals, plans, initiatives are executed / delivered in support of the team\u2019s business strategies and objectives.\u00a0 Ensures all activities conducted are in compliance with governing regulations, internal policies and procedures.\nAcquire and maintain a knowledge and understanding of Trade Finance Products in Hong Kong and other branches.\nEnsure the processing of import / export bills and related documents are accurate and within agreed service-level agreement. Processing of negotiation, discounting, Letter of Credit (L/C) financing and settlement.\nProvide prompt and courteous consultation to customers by answering questions and promoting the sale of Bank services.\nDocumentation in accordance to local jurisdiction record retention policy.\nAdhere to established Bank regulations and procedures with respect to assigned responsibilities and report unusual occurrences or fraudulent activity to the direct manager.\u00a0\nAssist during days with high volume, and holiday coverage for the other team members.\u00a0\nMaintain the confidentiality of the Bank and its\u2019 customer information.\nAssist with the training and development of junior staff in the department by providing guidance and direction in problem situations.\nSkills, Qualifications and Requirement:\u00a0\n\nMinimum 1-2 years experience in bills processing\nFresh graduate is also considered\nPossess relevant experiences with good knowledge of the operation of Letter of Credits both in the areas of import and export bills activities is an advantage.\nCapability to work independently in a high pressure environment.\nMust be flexible in a constantly changing environment (procedural and automated system changes).\nCan demonstrate initiative and aptitude for change.\nGood organizational skills, customer services and ability to multi task.\nMay be required to\u00a0report duty on rotational basis during Hong Kong public holiday to support the other Asia branches.\n\nInterested parties please send\u00a0your\u00a0full resume with present and expected salary, in strict confidence by clicking \"Apply Now\"\n\n\n(Data collected would be used for recruitment purpose only)", "employment_types": ["Full Time", "Permanent"], "selling_points": [], "locations": ["Central"], "categories": ["Banking / Finance", "Loan", "Others", "Order Processing & Operation / Settlement"], "post_time": "2022-01-13T06:25:41Z", "salary": {"currency": null, "max": null, "min": null, "period": "monthly", "term": null}, "salary_visible": false, "title_keywords": ["officer", "operations"], "responsibilities": ["regulations", "guidance", "related documents", "policies", "compliance", "procedures", "customer services", "finance operations", "maintain", "documentation", "plans", "system changes", "report"], "requirements": {"degrees": ["fresh graduate"], "majors": [], "languages": [], "language_level": [], "hard_skills": ["documentation", "c", "processing", "import and export"], "soft_skills": ["flexible", "organizational skills", "courteous", "work independently", "negotiation", "prompt", "accurate", "initiative"], "languages_combined": []}, "experience_required": {"duration": ["minimum 1-2 years"], "field": ["operation"]}}, {"job_id": "100003009036621", "location_code": "hk", "company": "Welab Bank Limited", "job_title": "Loan Telesales (Virtual Bank)", "description": "WeLab is a leading fintech company in Asia, \u00a0which operates one of first licensed digital banks in Asia \u2013 WeLab Bank, as well as multiple leading online financial services businesses including WeLend and WeLab Bank in Hong Kong, WeLab Digital (\u6211\u6765\u6570\u79d1), Taoxinji (\u6dd8\u65b0\u673a), Wallet Gugu (\u94b1\u5939\u8c37\u8c37) and Tianmian Tech (\u5929\u5195\u79d1\u6280) in Mainland China and Maucash in Indonesia. WeLab aims to bring joy to everyone\u2019s financial journey. We strive to improve people\u2019s lives by reinventing financial services through game-changing technology. We put our people first, whether it\u2019s our customers or our employees.\nAs the only homegrown Hong Kong fintech to receive a virtual banking license, we aim to reinvent and redefine the banking experience by building a bank we love.\nWe are an energetic and passionate team that can deliver and execute. We are looking for other intellectually curious, open-minded and smart-working individuals who are just as passionate as we are about making financial services enjoyable. Now you have the opportunity to join us on our journey to achieve our vision and be part of building a better financial future for everyone.\nAbout you:\nYou're a go-getter with mad juggling skills (or multiple hats) who can thrive in a fast-paced, agile environment\nYou have a strong thirst for knowledge and are driven to find solutions that don't exist yet\nYou are comfortable with ambiguity and extremely resourceful (in your past life you could've been a detective)\nYou always find a way to get things done without sacrificing the quality of your work, integrity and values. No task is off limits for you.\nYou are humble and prioritize the success of the team over your own with an eagerness to help those around you\nYou don't shy away from challenges and have the ability to bounce back from setbacks\nWhat you\u2019ll do and what success looks like in this role\nTo provide a one stop solution of personal loan to customer in a professional manner, including KYC, close deal etc\nTo handle customer enquiries and promote company services\nTo conduct warm call to existing bank customer (call list will be provided) and no cold call is required\nWhat is required and what we\u2019re looking for\nFrom 5 or above\nMinimum 1-year relevant experience in telemarketing\nProactive, good telephone manner and customer-oriented\nFluent in spoken Cantonese, basic in English and Mandarin\nKnowledge of basic computer skills and input methods in Chinese and English\nWork shifts is required on weekends and public holidays\nWeLab perks:\nCompetitive salary\nLearning and development stipend, because we value lifelong learning and believe the best way to invest in our employees is to encourage them to continue to learn\nWork hard and laugh lots (chicken wings and french toast, etc.) with a high-performing, fun and diverse team\nHappiness Dollars for spending on anything that makes you happy\nCoffee stipend\nConveniently located office surrounded by diverse and delicious lunch options\nLively office with gaming consoles and a ping pong table\nFun extracurricular activities with your colleagues like hiking, yoga, badminton, wine tasting, dragon boat racing, rock climbing, etc.\nEmployee referral bonuses\nAwards & recognition:\nFinancial Times (FT) 2020 Asia-Pacific High-Growth Companies \u2013 #2 ranked company\n2020 CNBC Disruptor 50 List \u2013 #11, only company included from Hong Kong and just one of five from Asia\nWe offer competitive salary package to the successful candidate.\u00a0 If you are interested in joining this exciting team, please apply with resume via the \"Apply\" button.\nAll information provided by applicants will be used for recruitment purposes only. Information of unsuccessful applicants will be destroyed within 24 months of receipt.", "employment_types": ["Full Time", "Permanent"], "selling_points": ["Provide a one stop solution of personal loan", "Handle customer enquiries", "No cold call is required"], "locations": ["Quarry Bay"], "categories": ["Banking / Finance", "Loan", "Order Processing & Operation / Settlement", "Sales, CS & Business Devpt", "Tele-sales (Telemarketing)"], "post_time": "2022-01-10T11:24:54Z", "salary": {"currency": null, "max": null, "min": null, "period": "monthly", "term": null}, "salary_visible": false, "title_keywords": ["telesales"], "responsibilities": ["handle customer enquiries", "quality", "professional manner", "banking", "kyc"], "requirements": {"degrees": [], "majors": [], "languages": ["cantonese", "english", "french", "mandarin", "chinese"], "language_level": ["basic", "fluent"], "hard_skills": ["no", "joy", "agile", "basic", "fun", "computer skills", "kyc", "go", "mad"], "soft_skills": ["passionate", "proactive", "agile", "resourceful", "open-minded", "integrity", "prioritize", "diverse", "customer-oriented", "learning", "energetic", "telephone manner", "driven"], "languages_combined": [{"language": "cantonese", "language_level": ["fluent"]}, {"language": "english", "language_level": ["basic"]}, {"language": "french", "language_level": []}, {"language": "mandarin", "language_level": ["basic"]}, {"language": "chinese", "language_level": ["basic"]}]}, "experience_required": {"duration": ["minimum 1-year"], "field": ["relevant experience", "banking experience", "banking"]}}, {"job_id": "100003009034313", "location_code": "hk", "company": "Promise (Hong Kong) Co., Limited", "job_title": "CS Representative \u5206\u884c\u5ba2\u6236\u670d\u52d9\u4ee3\u8868 (Ref: CSR-SAL)", "description": "\u5de5\u4f5c\u8077\u8cac\n\n\u8655\u7406\u8cb8\u6b3e\u7533\u8acb\u76f8\u95dc\u4e8b\u9805\n\u8ca0\u8cac\u5206\u884c\u7684\u4e00\u822c\u67e5\u8a62\u53ca\u5ba2\u6236\u670d\u52d9\u5de5\u4f5c\n\u8655\u7406\u8cc7\u6599\u8f38\u5165\u53ca\u5176\u4ed6\u6587\u8077\u5de5\u4f5c\n\u8077\u4f4d\u8981\u6c42\u00a0\n\u4e2d\u4e94\u7a0b\u5ea6\u6216\u4ee5\u4e0a\n\u5177\u91d1\u878d\u6a5f\u69cb\u6216\u76f8\u95dc\u5ba2\u6236\u670d\u52d9\u7d93\u9a57\u8005\u5c07\u7372\u512a\u5148\u8003\u616e\n\u5177\u826f\u597d\u6e9d\u901a\u6280\u5de7\uff0c\u80fd\u64cd\u6d41\u5229\u5ee3\u6771\u8a71\uff0c\u57fa\u672c\u82f1\u8a9e\u53ca\u666e\u901a\u8a71\n\u5177\u57fa\u672c\u96fb\u8166\u6587\u66f8\u6280\u5de7\u5305\u62ec Microsoft Word, Excel \u53ca\u4e2d\u6587\u8f38\u5165\u6cd5\uff08\u5009\u9821 / \u901f\u6210\uff09\n\u54e1\u5de5\u798f\u5229\u5305\u62ec\uff1a\u6709\u85aa\u5e74\u504712\u65e5\u8d77\u3001\u8d85\u6642\u5de5\u4f5c\u6d25\u8cbc\u3001\u4ea4\u901a\u6d25\u8cbc\u3001\u914c\u60c5\u82b1\u7d05\u3001\u9031\u5e74\u54e1\u5de5\u6d3b\u52d5\u3001\u826f\u597d\u6649\u5347\u6a5f\u6703\u3001\u5c08\u696d\u5728\u8077\u57f9\u8a13\u3001\u91ab\u7642\u4fdd\u96aa\u3001\u7b49\u7b49\n\n[\u53ef\u53c3\u95b1\u516c\u53f8\u7db2\u9801\u4e86\u89e3\u66f4\u591a\uff1ahttps://www.promise.com.hk/careers\u00a0]\n\n\u6709\u8208\u8da3\u4eba\u58eb\u8acb\u5c07\u500b\u4eba\u5c65\u6b77\u53ca\u8981\u6c42\u5f85\u9047(\u8acb\u8a3b\u660e\u7533\u8acb\u7de8\u865f)\u5bc4\u5f80\u9999\u6e2f\u7063\u4ed4\u544a\u58eb\u6253\u905372\u865f\u516d\u570b\u4e2d\u5fc314\u6a13-\u90a6\u6c11\u65e5\u672c\u8ca1\u52d9(\u9999\u6e2f)\u6709\u9650\u516c\u53f8(\u8acb\u8a3b\u660e\u4eba\u529b\u8cc7\u6e90\u90e8\u6536)\u6216\u6309\"Apply Now\"\u7533\u8acb\u6709\u95dc\u8077\u4f4d\u3002\n\n\u90a6\u6c11\u65e5\u672c\u8ca1\u52d9(\u9999\u6e2f)\u6709\u9650\u516c\u53f8\u70ba\u5e73\u7b49\u6a5f\u6703\u50f1\u4e3b\uff0c\u6b61\u8fce\u6240\u6709\u5408\u8cc7\u683c\u4eba\u58eb\u7533\u8acb\u5404\u9805\u8077\u4f4d\u3002\n\n\u7533\u8acb\u4eba\u6240\u63d0\u4f9b\u7684\u8cc7\u6599\u7d55\u5c0d\u4fdd\u5bc6\uff0c\u4e26\u53ea\u4f5c\u62db\u8058\u6709\u95dc\u7684\u7528\u9014\u3002", "employment_types": ["Full Time", "Permanent"], "selling_points": ["\u8655\u7406\u8cb8\u6b3e\u7533\u8acb\u76f8\u95dc\u4e8b\u9805\uff0c\u8ca0\u8cac\u5206\u884c\u7684\u4e00\u822c\u67e5\u8a62\u53ca\u8ca0\u8cac\u5206\u884c\u7684\u4e00\u822c\u67e5\u8a62/\u5ba2\u6236\u670d\u52d9\u5de5\u4f5c", "\u4e2d\u4e94\u7a0b\u5ea6\u6216\u4ee5\u4e0a\u53ca\u5177\u76f8\u95dc\u5ba2\u6236\u670d\u52d9\u7d93\u9a57\u8005\u512a\u5148\u8003\u616e", "\u826f\u597d\u5f85\u9047\u53ca\u5b8c\u5584\u798f\u5229\uff0c\u5305\u62ec\u91ab\u7642\u53ca\u4eba\u58fd\u4fdd\u96aa\u3001\u8d85\u6642\u53ca\u9031\u672b\u51fa\u52e4\u6d25\u8cbc\u7b49"], "locations": ["Not Specified"], "categories": ["Banking / Finance", "Loan", "Financial Services", "Sales, CS & Business Devpt", "Customer Service - Supervisor / Officer"], "post_time": "2022-01-10T03:08:58Z", "salary": {"currency": null, "max": null, "min": null, "period": "monthly", "term": null}, "salary_visible": false, "title_keywords": ["representative"], "responsibilities": [], "requirements": {"degrees": [], "majors": [], "languages": [], "language_level": [], "hard_skills": ["excel", "microsoft word"], "soft_skills": [], "languages_combined": []}, "experience_required": {"duration": [], "field": []}}, {"job_id": "100003009035434", "location_code": "hk", "company": "JAC Recruitment Hong Kong Co., Limited", "job_title": "Loan Admin \u2013 Senior Officer / Assistant Manager", "description": "Duties & Responsibilities\n\nPerform Syndication Agency function and loan administration as an officer;\nProcessing of bilateral loans and syndicated loans;\nProcess customer due diligent (KYC);\nReview the draft of structured & syndicated loan documentation, and to ensure all terms and conditions as well as security arrangements are properly structured according to the bank\u2019s policy.\nTo work closely with other departments for loan draw down and other operation activities;\nLiaise with legal counsels and marketing units to ensure proper and efficient operations of credit administration work;\nMonitor & follow up documentation deficiency and outstanding loan documents;\nMaintain the documentation tracking and filing system;\nEnsure the collateral, securities documents, conditions precedent, financial covenants and insurance documents are complied with loan agreements;\nCorrespondence to all enquiries, requirements and ad hot events from loans related parties;\nHandle Trade Finance operation jobs if required.\n\n\u00a0Education & Experience:\n\nPost-secondary or above\n3 years\u2019 experience in syndicated loan operation, or related job preferably\nKnowledge of loan documentation, procedures and relevant requirement\nWilling to work both syndicated loan and Trade Finance operations\nGood command of written and spoken English.\nGood command of written and spoken Korean is preferable.\nGood knowledge of MS Office\n\n\n\nAttractive remuneration packages\u00a0along with annual discretionary bonus and generous employee benefits\u00a0to the right candidates\n\n\"Interested candidates, please send an updated CV to\u00a0kevin.ng @jac-recruitment.com\u00a0and CC\u00a0jac.hk @jac-recruitment.com\"\n\nPersonal data collected will be used for employment-related purpose only. We regret to inform that only shortlisted candidates will be notified.\u00a0", "employment_types": ["Full Time"], "selling_points": ["Reputable Korean Bank based in Hong Kong", "Attractive Benefits and remuneration for Qualified", "Exciting Opportunity!"], "locations": ["Central & Western Area"], "categories": ["Banking / Finance", "Loan"], "post_time": "2022-01-10T07:09:17Z", "salary": {"currency": null, "max": null, "min": null, "period": "monthly", "term": null}, "salary_visible": false, "title_keywords": ["senior officer", "admin", "assistant manager"], "responsibilities": ["tracking", "documentation", "syndicated loan documentation", "operations", "review", "monitor", "procedures", "work closely with other departments", "finance operations", "maintain", "kyc", "liaise with", "insurance", "administration"], "requirements": {"degrees": [], "majors": [], "languages": ["english", "korean"], "language_level": ["good command"], "hard_skills": ["documentation", "processing", "ms office", "kyc"], "soft_skills": ["efficient", "structured", "diligent"], "languages_combined": [{"language": "english", "language_level": ["good command"]}, {"language": "korean", "language_level": ["good command"]}]}, "experience_required": {"duration": ["3 years"], "field": ["related", "operation", "education"]}}, {"job_id": "100003009031780", "location_code": "hk", "company": "Hong Kong Finance Company Limited", "job_title": "Mortgage Sales Manager", "description": "Promote SME and Mortgage loan services to new and existing customers\nPromote loan refinance service to existing customers\nHandle customer's enquiries in professional manner and follow up loan applications\nAchieve individual and team targets on SME and mortgage lending\n\nRequirements:\n\nDegree holder or above\nMinimum 3 years of relevant experience in finance, banking or property industry with a focus in SME and Mortgage loan business\nProficiency in both English and Chinese\nProactive and commit to the job\nExcellent communication, interpersonal and selling skills\nImmediate available is highly preferred", "employment_types": ["Full Time"], "selling_points": ["Promote SME and Mortgage loan services", "Promote loan refinance service to customer", "Able to work independently"], "locations": ["Admiralty"], "categories": ["Banking / Finance", "Loan", "Mortgage", "Financial Services"], "post_time": "2022-01-10T03:30:59Z", "salary": {"currency": null, "max": null, "min": null, "period": "monthly", "term": null}, "salary_visible": false, "title_keywords": ["sales manager"], "responsibilities": ["sme", "professional manner", "communication", "banking"], "requirements": {"degrees": ["degree holder"], "majors": [], "languages": ["english", "chinese"], "language_level": ["proficiency"], "hard_skills": ["focus"], "soft_skills": ["communication", "focus", "proactive", "interpersonal"], "languages_combined": [{"language": "english", "language_level": ["proficiency"]}, {"language": "chinese", "language_level": ["proficiency"]}]}, "experience_required": {"duration": ["minimum 3 years"], "field": ["loan business", "finance", "relevant experience", "banking"]}}, {"job_id": "100003009046045", "location_code": "hk", "company": "Conners Consulting Limited", "job_title": "VP (Project Manager) - Deposits and Remittance Operation (Multinational Bank)", "description": "Our client is well-known multinational bank and now looking for high calibre to join their group.\n\nResponsibilities\n\nManage process improvement and system projects to streamline work flows and procedures\nSupport daily deposits and remittance function of the bank in compliance with statutory requirements\nWork closely with business, marketing, control and risk units for new product development and conduct system UAT\nLiaise with regulators, auditors and compliance staff on latest regulatory, control and compliance requirements\n\nRequirements\n\nUniversity degree holder\nSound knowledge of bank operations with at least 7 years in bank operations and project management experience\nStrong knowledge of all aspects of local and overseas remittance and deposits operations and practices\nEnergetic personality with strong people management and communications skills\n\nTo apply, please send your detailed resume or contact Ms Liu at 3996 8091 for a confidential discussion.\n\nOnly shortlisted candidates will be notified.\n\nApplicants who are not contacted within two weeks may consider their applications unsuccessful.\n\nAll data collected will be used for recruitment purpose only & will be used strictly confidential.\n\nConners Consulting Limited 2005 Kai Tak Commercial Building 317 Des Voeux Road Central Hong Kong.\n\nTel: (852) 3996 8090", "employment_types": ["Full Time", "Permanent"], "selling_points": ["Operations / Deposits / Remittance", "Multinational Bank", "Attractive remuneration and bonus scheme"], "locations": ["Central & Western Area"], "categories": ["Banking / Finance", "Loan", "Retail Banking"], "post_time": "2022-01-13T09:33:48Z", "salary": {"currency": null, "max": null, "min": null, "period": "monthly", "term": null}, "salary_visible": false, "title_keywords": ["project manager"], "responsibilities": ["control", "uat", "compliance", "procedures", "statutory requirements", "liaise with"], "requirements": {"degrees": ["university degree"], "majors": [], "languages": [], "language_level": [], "hard_skills": ["project management"], "soft_skills": ["project management", "energetic", "detailed"], "languages_combined": []}, "experience_required": {"duration": ["at least 7 years"], "field": ["project management"]}}, {"job_id": "100003009034953", "location_code": "hk", "company": "Delken Group Limited", "job_title": "Assistant Manager / Senior Associate - Mortgage loans (Operations)", "description": "Our client is a Financial Institution, they are currently seeking for an Assistant Manager (Operations)\u00a0 to join their team.\n\n\nResponsibilities\n\n\nTo perform loan origination, eligibility assessment, documentation, administration and customer service duties;\nTo monitor the performance of the appointed servicers and agents;\nTo prepare management statistics and reports;\nTo identify rooms and propose recommendation for process re-engineering and risk control;\nTo provide support for ad-hoc tasks and projects\n\nResponsibilities:\n\n\nDegree holder in Finance, Business Administration or equivalent;\nA minimum of 5 years\u2019 solid experience in mortgage loans operations;\nHighly responsible, attentive to details with high degree of accuracy and with strong analytical skills;\nA good team player with positive thinking, self motivated, proactive working attitude, eager to learn and to take up new responsibilities;\nGood command of spoken English and Chinese, proficiency in Putonghua will be an asset; and\nStrong PC skills in MS Excel and MS Access.\n*Candidate(s) with less experience will be considered as Senior Associate / Associate.\nInterested candidates, please send your resume (MS Word document) including employment history, present and expected salary to us.\n\n\nFor more jobs, please visit our website:\u00a0www.delken.com.hk.\u00a0\n\n(All personal data submitted will be treated in strict confidential and used for recruitment purposes only.)\u00a0", "employment_types": ["Full Time", "Contract"], "selling_points": ["Solid exp in mortgage loans operations", "Loan origination, Assessment, Docs, Admin & CS", "5-days, 15AL, Med, Immediate Available preferable"], "locations": ["Kwun Tong"], "categories": ["Banking / Finance", "Loan", "Mortgage", "Order Processing & Operation / Settlement"], "post_time": "2022-01-10T04:51:12Z", "salary": {"currency": null, "max": null, "min": null, "period": "monthly", "term": null}, "salary_visible": false, "title_keywords": ["assistant manager", "operations", "senior associate"], "responsibilities": ["management", "control", "provide support", "re-engineering", "operations", "ad-hoc tasks", "reports", "monitor the performance", "documentation", "customer service duties", "administration"], "requirements": {"degrees": ["degree", "degree holder"], "majors": ["finance", "business administration"], "languages": ["putonghua", "english", "chinese"], "language_level": ["proficiency", "good command"], "hard_skills": ["documentation", "ms excel", "pc skills", "analytical skills"], "soft_skills": ["good team player", "attentive to details", "responsible", "positive thinking", "analytical skills", "self motivated", "eager to learn", "customer service", "proactive"], "languages_combined": [{"language": "putonghua", "language_level": ["proficiency", "good command"]}, {"language": "english", "language_level": ["proficiency", "good command"]}, {"language": "chinese", "language_level": ["proficiency", "good command"]}]}, "experience_required": {"duration": ["minimum of 5 years"], "field": []}}, {"job_id": "100003009039124", "location_code": "hk", "company": "PrimeCredit Ltd", "job_title": "Compliance Officer (Legal & Compliance)", "description": "Responsibilities\n\nAssist to review and approve the marketing materials and provide recommendation to various departments\nAssist to establish compliance monitoring program on the Company\u2019s various activities, products and workflows to ensure compliance with internal policies, applicable laws and regulations\nPrepare and review policies and procedures to address the relevant legislation and regulation changes\nPrepare the monthly compliance and operational risk reports\nAssist to conduct on-site compliance / operational risk checking on local branches and other departments\nAssist in other ad-hoc projects as assigned\n\nRequirements\n\nUniversity degree holder in Finance, Business Administration, Law or related disciplines\n1-2 years of compliance or relevant experience gained from financial institution\nKnowledge of compliance and regulatory requirements in banking / consumer finance industry is an advantage\nProficient in MS Office Applications and Chinese word processing\nProficient in both spoken and written English and Chinese\nUniversity fresh graduate of legal studies will also be considered\n\nThis is a very rewarding and exciting opportunity. We offer an attractive remuneration to the successful candidates. Please forward your resume with present and expected salary by clicking \u201cAPPLY NOW\u201d or complete the online application form at\u00a0https://www.primecredit.com/career/en/jobs.\n\nTo know more about PrimeCredit, please visit our websites\u00a0https://www.primecredit.com/career/en/.\n\nAll applications will be treated in strict confidence and only be used for recruitment related purpose.", "employment_types": ["Full Time", "Permanent"], "selling_points": ["Assist to review & approve the marketing materials", "Assist to establish compliance monitoring program", "1-2 years of compliance or relevant experience"], "locations": ["Wan Chai"], "categories": ["Banking / Finance", "Loan", "Others", "Professional Services", "Legal & Compliance"], "post_time": "2022-01-11T08:46:15Z", "salary": {"currency": null, "max": null, "min": null, "period": "monthly", "term": null}, "salary_visible": false, "title_keywords": ["compliance officer"], "responsibilities": ["regulations", "policies", "compliance", "monitoring", "review", "procedures", "ensure compliance", "provide recommendation", "relevant legislation", "checking", "reports", "marketing materials", "ad-hoc projects"], "requirements": {"degrees": ["university degree", "fresh graduate"], "majors": ["related disciplines", "finance", "business administration", "law"], "languages": ["english", "chinese"], "language_level": ["proficient"], "hard_skills": ["chinese word processing", "ms office"], "soft_skills": [], "languages_combined": [{"language": "english", "language_level": ["proficient"]}, {"language": "chinese", "language_level": ["proficient"]}]}, "experience_required": {"duration": ["1-2 years"], "field": ["compliance", "relevant experience", "financial"]}}, {"job_id": "100003009039123", "location_code": "hk", "company": "PrimeCredit Ltd", "job_title": "Senior Credit Card Officer", "description": "Responsibilities\n\nSupport team for strategic plan of marketing campaigns to grow credit card business and enhance brand building\nExecute marketing promotion and campaigns (end to end) for card usage to drive new card sales and portfolio growth\nLiaise with merchants to provide special merchant privileges or joint promotion for card spending programs\nAssist to develop customer segmentation program to push card usage and improve activity ratio\nCo-ordinate with internal and external parties on programs execution and post marketing evaluation\nPrepare and review reports related to credit card usage programs\n\nRequirements\n\nUniversity degree holder in Business Administration, Management, Economic or related disciplines\nAt least 2 years\u2019 working experience in marketing, sales and administration, preferably in banking and finance industry\nProficient in MS Office Applications including Excel, PowerPoint and Chinese / English word processing\nProficient in spoken and written English and Chinese\nCandidate with less experience will be considered as Credit Card Officer\n\nThis is a very rewarding and exciting opportunity. We offer an attractive remuneration to the successful candidates. Please forward your resume with present and expected salary by clicking \u201cAPPLY NOW\u201d or complete the online application form at\u00a0https://www.primecredit.com/career/en/jobs.\n\nTo know more about PrimeCredit, please visit our websites\u00a0https://www.primecredit.com/career/en/.\n\nAll applications will be treated in strict confidence and only be used for recruitment related purpose.", "employment_types": ["Full Time", "Permanent"], "selling_points": ["Support team for strategic plan of MKT campaigns", "Execute MKT promotion and campaigns (end to end)", "At least 2 years\u2019 working exp. in MKT & sales"], "locations": ["Wan Chai"], "categories": ["Banking / Finance", "Loan", "Marketing / Public Relations", "Marketing - Brand / Product Management", "Marketing - General / Support"], "post_time": "2022-01-11T08:46:15Z", "salary": {"currency": null, "max": null, "min": null, "period": "monthly", "term": null}, "salary_visible": false, "title_keywords": ["officer"], "responsibilities": ["evaluation", "co-ordinate with", "internal and external parties", "review", "develop", "reports", "marketing campaigns", "plan", "liaise with"], "requirements": {"degrees": ["university degree"], "majors": ["related disciplines", "business administration"], "languages": ["english", "chinese"], "language_level": ["proficient"], "hard_skills": ["excel", "word processing", "powerpoint", "ms office"], "soft_skills": [], "languages_combined": [{"language": "english", "language_level": ["proficient", "proficient"]}, {"language": "chinese", "language_level": ["proficient", "proficient"]}]}, "experience_required": {"duration": ["at least 2 years"], "field": ["finance industry", "credit card", "marketing", "banking", "administration"]}}, {"job_id": "100003009035643", "location_code": "hk", "company": "Victor Chiu Tsang & Partners", "job_title": "Mortgage Account Manager (Direct Sales) (Full-time and Part-time)", "description": "First Mortgage Loan and Second Mortgage Loan on all kind of properties, carparks and building mortgage etc\nMortgage loan business\nMortgage lending\nResponsibilities\n\nTo plan and execute mortgage and/or secured product marketing plans\nTo solicit mortgage business and accomplish targets on mortgage lending\nTo establish and develop the relationship with referral parties such as property agencies, mortgage brokers and solicitors\nOriginating, cultivating and maintain business relationships with customers\nDriving mortgage business and generate revenue from existing network through various sales activities\nPersonal sales and marketing duties to achieve target on mortgage loan business\nReview mortgage loan applications and monitor overdraft accounts\nResponsibly handling incoming customer enquiries\nRequirements\n\nDegree holder or above\nMinimum 3 to 5 years of relevant experience in in mortgage loan business\nEstablished existing and potential client network\nStrong communications and leadership skills\nAggressive, proactive with an outgoing personality\nProficient in Microsoft Office and Chinese word processing\nGood command of spoken and written Chinese, Putonghua & English\nWe offer a competitive remuneration package to the right candidate.\n\nPlease send your resume with present and expected salaries to Human Resources Department at by clicking \"Apply Now\".\n\n", "employment_types": ["Full Time", "Part Time", "Permanent"], "selling_points": ["Full Time, Permanent", "5 Days", "Tsim Sha Tsui"], "locations": ["Tsim Sha Tsui"], "categories": ["Banking / Finance", "Loan", "Mortgage", "Others"], "post_time": "2022-01-10T08:10:31Z", "salary": {"currency": null, "max": null, "min": null, "period": "monthly", "term": null}, "salary_visible": false, "title_keywords": ["account manager", "sales"], "responsibilities": ["sales activities", "marketing plans", "customer enquiries", "review", "monitor", "develop", "maintain", "plan"], "requirements": {"degrees": ["degree holder"], "majors": [], "languages": ["putonghua", "english", "chinese"], "language_level": ["good command", "proficient"], "hard_skills": ["chinese word processing", "microsoft office"], "soft_skills": ["outgoing personality", "leadership skills", "proactive"], "languages_combined": [{"language": "putonghua", "language_level": ["good command"]}, {"language": "english", "language_level": ["good command"]}, {"language": "chinese", "language_level": ["good command", "proficient"]}]}, "experience_required": {"duration": ["minimum 3 to 5 years"], "field": ["loan business", "relevant experience"]}}, {"job_id": "100003009034401", "location_code": "hk", "company": "Livi Bank Limited", "job_title": "Senior Manager / Manager, Loan Product", "description": "Responsibilities:\n\n\nNew product development for loan product in both retail and SME segment\nDevelop and execute plans, strategy and tactics which align with the overall bank strategy\nRunning the loan business to deliver business objective and P&L target\nOversee strategic loan product roadmap and drive the team to deliver and launch different loan products according to the scheduled timeline\nCoordinate with internal and external partners and manage varies projects to accomplish business goal\nDevelop plan and execute client value proposition, segmentation, pricing and channel management to deliver the P&L target\nDeliver the best customer experience through innovative idea in product design, process improvement and customer centric product features\u00a0 \u00a0\nMake sure all product setup, operation process and product programs comply to all internal and regulatory requirement\n\nRequirements:\n\n\nBachelor Degree Holder or equivalent\n8-10 years relevant experience in product management and development\nExcellent command of both spoken and written English and Chinese, including Putonghua\n\nWe offer competitive salary package to the successful candidate.\u00a0 If you are interested in joining this exciting team, please send your full resume including your\u00a0CURRENT\u00a0and\u00a0EXPECTED\u00a0salary for our consideration.\u00a0", "employment_types": ["Full Time", "Permanent"], "selling_points": ["Virtual Bank / Digital bank", "Loan Product", "Excellent Career Development Opportunity"], "locations": ["Quarry Bay"], "categories": ["Banking / Finance", "Loan", "Retail Banking", "Others"], "post_time": "2022-01-10T03:18:58Z", "salary": {"currency": null, "max": null, "min": null, "period": "monthly", "term": null}, "salary_visible": false, "title_keywords": ["senior manager", "manager"], "responsibilities": ["management", "coordinate with", "p&l", "develop", "product design", "plan", "sme", "plans", "setup"], "requirements": {"degrees": ["bachelor degree holder"], "majors": [], "languages": ["putonghua", "english", "chinese"], "language_level": ["excellent"], "hard_skills": [], "soft_skills": [], "languages_combined": [{"language": "putonghua", "language_level": ["excellent"]}, {"language": "english", "language_level": ["excellent"]}, {"language": "chinese", "language_level": ["excellent"]}]}, "experience_required": {"duration": ["8-10 years"], "field": ["product management", "development", "relevant experience"]}}, {"job_id": "100003009042327", "location_code": "hk", "company": "Hays", "job_title": "Team Head of E-Commerce Partnership", "description": "To join a leading international bank with exposure from HK market and GBA on merchant partnership\n\nYour new company\nMy client is a well known international bank expanding her HK business\n\nYour new role\n\nFormulate acquisition strategy on merchant acquisition and partnership development in HK and GBA\nBuild up sustainable business model to drive revenue, value propositions and marketing campaigns\nIdentify and source potential partners from all walks: retail merchant, hospitality, e-commerce, F&B, insurance, lifestyle\nFoster operation teams to ensure execution of campaigns and events in order to deliver timely marketing initiatives\nStrictly comply with company policies and regulations ensuring risk control\n\n\nWhat you'll need to succeed\n\n\nWelcome Banking & FI background, ideally with Fin-Tech, e-payment experience\nBusiness development or partnership experience is a must\nSeasonal product marketing caliber with co-brand, external partnership\nWith Greater China or GBA exposure is an advantage to succeed\n\n\nWhat you need to do now\nIf you're interested in this role, click 'apply now' to forward an up-to-date copy of your CV, or call Miss LEE at 2230 7438 now.\nIf this job isn't quite right for you but you are looking for a new position, please contact us for a confidential discussion on your career.", "employment_types": ["Full Time", "Permanent"], "selling_points": ["Exposure in GBA", "Work autonomy as decision maker", "Level up your career"], "locations": ["Not Specified"], "categories": ["Banking / Finance", "Loan"], "post_time": "2022-01-12T07:03:38Z", "salary": {"currency": null, "max": null, "min": null, "period": "monthly", "term": null}, "salary_visible": false, "title_keywords": [], "responsibilities": ["regulations", "control", "policies", "teams", "payment", "contact", "marketing campaigns", "banking", "insurance"], "requirements": {"degrees": [], "majors": [], "languages": [], "language_level": [], "hard_skills": ["e-commerce"], "soft_skills": ["timely", "interested in"], "languages_combined": []}, "experience_required": {"duration": [], "field": ["tech", "business development", "banking"]}}, {"job_id": "100003009026632", "location_code": "hk", "company": "Centaline Finance Limited", "job_title": "Mortgage Sales Manager", "description": "\u00a0Responsibilities\n\n* Team strategic execution;\n\n* Implement marketing activities to achieve business targets;\n\n* Achieve sales target assigned;\n\n* Support acquisition of mortgage loan or related products from enquiry to drawdown;\n\n* Build and maintain customer relationship, customer prospecting as well as marketing calls through personalized service\n\nRequirements\n\n* Eagerness to develop in financial field;\n\n* Sales and/or marketing experiences in mortgage or personal loan, experience in financial institution is preferable;\n\n* Sales oriented with good interpersonal skills;\n\n* Existing sales, marketer and C.S. are welcomed\n\nWe offer Basic salary plus high commission to potential talent.\u00a0 Join us and be a part of our exciting growth\n\nInterested parties, please send your FULL RESUME (in MS Word format) with availability, current and expected salary by email to Centaline Finance Limited.\u00a0", "employment_types": ["Full Time", "Permanent"], "selling_points": ["Basic Salary plus high commission", "Mortgage or Personal Loan", "Sales / Marketer / Customer Services"], "locations": ["Yau Ma Tei"], "categories": ["Banking / Finance", "Loan", "Mortgage", "Sales, CS & Business Devpt", "Direct Sales"], "post_time": "2022-01-06T08:25:50Z", "salary": {"currency": null, "max": null, "min": null, "period": "monthly", "term": null}, "salary_visible": false, "title_keywords": ["sales manager"], "responsibilities": ["sales target", "maintain"], "requirements": {"degrees": [], "majors": [], "languages": [], "language_level": [], "hard_skills": ["c"], "soft_skills": ["interpersonal skills"], "languages_combined": []}, "experience_required": {"duration": [], "field": ["marketing", "financial"]}}, {"job_id": "100003009030255", "location_code": "hk", "company": "NewPages Recruitment Company Limited", "job_title": "Loan Sales / Telesales \u8cb8\u6b3e\u5c08\u54e1 (\u9280\u884c\u5de5\uff0c\u4e94\u5929\u5de5\u4f5c) [\u9ad8\u4f63\u91d1, \u5e73\u5747\u6708\u51653\u842c] (Outbound Call)", "description": "\u4e3b\u8981\u8077\u8cac:\n\n\u9032\u884c\u92b7\u552e\u6d3b\u52d5\uff0c\u4e26\u4ee5\u5c08\u696d\u7684\u65b9\u5f0f\u5411\u5ba2\u6236\u63a8\u85a6\u5408\u9069\u7684\u4e00\u822c\u9280\u884c\u89e3\u6c7a\u65b9\u6848\n\n\u8655\u7406\u5ba2\u6236\u67e5\u8a62\u4e26\u92b7\u552e\u7684\u9280\u884c\u7522\u54c1\n\n\u70ba\u5be6\u73fe\u5718\u968a\u7684\u670d\u52d9\u548c\u92b7\u552e\u76ee\u6a19\u505a\u51fa\u8ca2\u737b\n\n\u78ba\u4fdd\u92b7\u552e\u6d41\u7a0b\u7b26\u5408\u9280\u884c\u7684\u653f\u7b56\u548c\u6240\u6709\u9069\u7528\u7684\u76e3\u7ba1\u6307\u5357\n\n* \u7533\u8acb\u4eba\u6301\u6709 \u4fdd\u96aa\u4e2d\u4ecb\u4eba\u724c\u7167\u6216\u6301\u6709\u8b49\u5238\u53ca\u671f\u8ca8\u5f9e\u696d\u54e1\u8cc7\u683c\u724c\u7167 \u512a\u5148\u8003\u616e\u00a0", "employment_types": ["Full Time", "Permanent"], "selling_points": ["\u9280\u884c\u5de5, \u8cb8\u6b3e\u90e8", "\u4e94\u5929\u5de5\u4f5c, \u9ad8\u4f63\u91d1", "\u9280\u884c\u5047\u671f, \u9577\u5de5, \u6709\u91ab\u7642\u798f\u5229"], "locations": ["Ngau Tau Kok"], "categories": ["Banking / Finance", "Loan", "Retail Banking", "Sales, CS & Business Devpt", "Tele-sales (Telemarketing)"], "post_time": "2022-01-07T19:20:10Z", "salary": {"currency": null, "max": null, "min": null, "period": "monthly", "term": null}, "salary_visible": false, "title_keywords": ["telesales", "sales"], "responsibilities": [], "requirements": {"degrees": [], "majors": [], "languages": [], "language_level": [], "hard_skills": [], "soft_skills": [], "languages_combined": []}, "experience_required": {"duration": [], "field": []}}, {"job_id": "100003009030945", "location_code": "hk", "company": "Hong Kong Finance Company Limited", "job_title": "Administration Officer", "description": "Responsibilities:\n\nHandle loan administration operations i.e. loan drawdown / filing\nCoordinate with outside professionals to follow up the progress of the Loan and Legal documents\nCoordinate with other teams for internal system checking, data input etc.\nHandle any ad hoc projects and tasks whenever necessary\n\nRequirements:\n\nDiploma holder or above\nRelevant working experience in banks or financial institutions is preferred\nGood command of in English and Chinese;\nWell organized, detailed minded, self-motivated, independent and able to work under pressure\nGood interpersonal and communication skills\nProficient in MS office", "employment_types": ["Full Time"], "selling_points": ["Handle loan administration operations", "Coordinate with outside professionals", "Handle any ad hoc projects"], "locations": ["Admiralty"], "categories": ["Admin & HR", "Clerical / Admin Staff", "Banking / Finance", "Loan", "Financial Services"], "post_time": "2022-01-07T08:42:03Z", "salary": {"currency": null, "max": null, "min": null, "period": "monthly", "term": null}, "salary_visible": false, "title_keywords": ["administration officer"], "responsibilities": ["operations", "teams", "coordinate with", "checking", "data input", "ad hoc projects", "administration"], "requirements": {"degrees": ["diploma holder"], "majors": [], "languages": ["english", "chinese"], "language_level": ["good command"], "hard_skills": ["ms office"], "soft_skills": ["communication skills", "self-motivated", "independent", "well organized", "detailed", "interpersonal", "work under pressure"], "languages_combined": [{"language": "english", "language_level": ["good command"]}, {"language": "chinese", "language_level": ["good command"]}]}, "experience_required": {"duration": [], "field": ["financial institutions", "relevant working experience"]}}, {"job_id": "100003009030070", "location_code": "hk", "company": "The Bank of East Asia, Limited", "job_title": "Marketing Manager (Card & Consumer Loan)", "description": "Responsibilities\n\nTo be a team\u00a0member of Retail Lending \u2013 Card and Consumer Loan Section\nTo manage cards and consumer loan\u00a0products\nTo design and implement on product strategy, pricing digitalization\nTo work closely with internal departments and external insurance company to ensure smooth implementation\nTo process optimization and customer engagement as well as expenses management\n\nRequirements\n\nUniversity graduate;\nPreferable over 5 years experience in banking sector cover the following:\nCreative and business oriented with excellent strategical mindset;\nStrong leadership, project management and financial analytical skills;\nStrong communication and interpersonal skills;\nGood command of both spoken and written English and Chinese.\n\nPlease apply online via the BEA Careers website at https://careers.hkbea.com/psp/hcmprd/EMPLOYEE/HRMS/c/HRS_HRAM.HRS_APP_SCHJOB.GBL?Page=HRS_APP_JBPST&Action=U&FOCUS=Applicant&SiteId=1&JobOpeningId=3236&PostingSeq=1 or by clicking the Apply Now button. Kindly note that if you are a new user, you have to first create your User Profile before you can apply.\n\nPersonal data provided by job applicants will be used for recruitment purposes only and will be treated in accordance with the Bank's Personal Data Policy, which is available upon request. Applicants who are not invited for interviews within six weeks may consider their applications unsuccessful and the personal data collected will be destroyed after six months.\n\n\n\n", "employment_types": ["Full Time", "Permanent"], "selling_points": ["Marketing Manager", "Card & Consumer Loan", "Marketing programs for acquisition"], "locations": ["Kwun Tong"], "categories": ["Banking / Finance", "Loan"], "post_time": "2022-01-07T19:20:04Z", "salary": {"currency": null, "max": null, "min": null, "period": null, "term": null}, "salary_visible": false, "title_keywords": ["marketing manager"], "responsibilities": ["management", "expenses", "implementation", "design", "insurance"], "requirements": {"degrees": ["university graduate"], "majors": [], "languages": ["english", "chinese"], "language_level": ["good command"], "hard_skills": ["project management", "c", "financial analytical skills"], "soft_skills": ["analytical skills", "project management", "communication and interpersonal skills", "creative", "leadership"], "languages_combined": [{"language": "english", "language_level": ["good command"]}, {"language": "chinese", "language_level": ["good command"]}]}, "experience_required": {"duration": ["5 years"], "field": ["banking sector"]}}, {"job_id": "100003009036698", "location_code": "hk", "company": "China Construction Bank (Asia) Corporation Limited", "job_title": "Contract KYC Officer (Transaction Banking business)", "description": "Job Descriptions:\n\nWork with sales team to understand deal pipeline and ensure KYC is in place prior to deal closing/ announcing\nWork with new and existing clients/ appropriate party(ies) directly to advise requirements for KYC completion\nCheck KYC and account opening documentation from clients, and arrange account opening\nPerform KYC, CDD renewals\u00a0\nEnsure client details and CSMs to ensure KYC for upcoming deals are fully approved prior to deal closing date\nEnsure compliance with bank's risk and KYC policy as it relates to the KYC process\nDepending on the AML risk and other risk profiles, liaise with Legal and Compliance for due diligence review and exception approvals\nRun client background checks for negative information\nSet up client details on bank systems\nWork with relationship managers regionally to obtain client information where appropriate\nPrepare daily, weekly and monthly pipeline reports for the Management team, which includes details of all KYC completed\nWork on a high profile KYC remediation project\nCheck against database upon receipt the alerts on sanction names and liaise with compliance\nAssist on transaction supporting duties e.g. documentation safekeeping, billing, etc.\nAssist on departmental projects including involvement in new system rollout or/ and UAT\u00a0\u00a0\n\nRequirements:\n\nBachelor degree or above in business related discipline\nPossess 2 years experience in client on-boarding or relevant exposure with understanding of related banking practice, corporate policies and compliance requirements\nPrevious Corporate Trust and Loan Agency experience is a definite advantage\nAttention to details with high accuracy in work; strive for process improvement\nGood time management skills and ability to prioritise and work to tight timeframes\nCooperative, proactive with high sense of responsibility and teamwork\nAble to work under pressure and in a volatile environment\n\nTo apply, please send the detailed resume to the designated email address.\n\nApplicants who are not contacted within 8 weeks may consider their applications unsuccessful and their personal data will be retained by the bank for a period up to two years.\n\nAll information provided by applicants will be used for recruitment purposes only and will be used strictly in accordance with the bank\u2019s personal data policies, a copy of which will be provided upon request.", "employment_types": ["Full Time", "Temporary", "Contract"], "selling_points": ["First line of defense", "KYC, CDD and clients on-boarding", "Liaise with legal & compliance"], "locations": ["Central"], "categories": ["Banking / Finance", "Loan", "Corporate Finance", "Risk Management"], "post_time": "2022-01-10T12:46:11Z", "salary": {"currency": null, "max": null, "min": null, "period": "monthly", "term": null}, "salary_visible": false, "title_keywords": ["officer"], "responsibilities": ["due diligence", "management team", "aml", "uat", "account opening", "cdd", "compliance", "review", "systems", "client information", "ensure compliance", "background checks", "liaise with", "sales team", "reports", "database", "kyc", "documentation"], "requirements": {"degrees": ["degree or above", "bachelor"], "majors": ["business"], "languages": [], "language_level": [], "hard_skills": ["banking practice"], "soft_skills": ["time management skills", "cooperative", "prioritise", "detailed", "attention to details", "proactive", "high sense of responsibility and teamwork", "work under pressure"], "languages_combined": []}, "experience_required": {"duration": ["2 years"], "field": ["related", "agency", "compliance", "banking"]}}, {"job_id": "100003009032521", "location_code": "hk", "company": "Hays", "job_title": "Officer/Senior Officer, Credit Admin, Great Work Life Balance", "description": "Our client is an leading Internet Broker in HK, with SFC Type 1, 2, 4, 5, 9 License.\n\nJob Description\n\nCollaborate with senior leadership to understand the organizations goals and strategy related to staffing, recruiting, Compensation & Benefits and retention.\u00a0\nWork directly with business stakeholders and provide HRBP service including recruitment, employee relations, talent review, remuneration review, performance management, talent development etc.\nBe one of the driver on change and transformation initiatives,such as HRIS implementation project, etc.\nIdentify and implement employee engagement opportunities and activities to build and sustain a positive and productive workforce\nImplement and review HR policies and procedures to support the Company\u2019s needs\n\nJob Requirements\n\nBachelor\u2019s degree in HR, Business Management or related disciplines\n6+ years\u2019\u00a0solid experience in Human Resources management and HRIS\nFamiliar with Hong Kong Employment ordinance\nResponsible, agile, adaptive to changes and resilient\nGood command of both spoken and written English and Chinese, including Mandarin\nProficiency in MS Office applications, particularly Excel", "employment_types": ["Full Time", "Permanent"], "selling_points": ["Regional Corporate Bank", "Officer/Senior Officer, Loan Operation", "3 years experience in loan operation"], "locations": ["Not Specified"], "categories": ["Banking / Finance", "Corporate Banking", "Loan", "Others"], "post_time": "2022-01-07T11:23:46Z", "salary": {"currency": null, "max": null, "min": null, "period": "monthly", "term": null}, "salary_visible": false, "title_keywords": ["officer", "senior officer", "admin"], "responsibilities": ["collaborate with", "management", "policies", "hr", "review", "procedures", "implementation", "recruitment"], "requirements": {"degrees": ["degree", "bachelor"], "majors": ["related disciplines", "business"], "languages": ["english", "chinese", "mandarin"], "language_level": ["good command"], "hard_skills": ["business management", "excel", "hong kong employment ordinance", "agile", "ms office"], "soft_skills": ["agile", "responsible"], "languages_combined": [{"language": "english", "language_level": ["good command"]}, {"language": "chinese", "language_level": ["good command"]}, {"language": "mandarin", "language_level": ["good command"]}]}, "experience_required": {"duration": ["6+ years"], "field": ["management", "human resources"]}}, {"job_id": "100003009032375", "location_code": "hk", "company": "Welend Limited", "job_title": "Credit Approval Manager", "description": "Our client, one of the AI-driven pharmaceutical R&D companies located at Science Park is recruiting a high-caliber candidate joining their HK office. A job description is as follows: -\u00a0\n\n\nDegree holder in any disciplines\u00a0\nMinimum a few years of secretarial / PA working experience (fresh graduate maybe considered)\nGood command of spoken & written English and Chinese (Cantonese & Mandarin)\u00a0\nGood interpersonal & communication skill\u00a0\nHands on experience in MS office and google\u00a0\nConfident in serving senior management executives and expatriates\u00a0\nImmediate available or short notice for interview and work\u00a0\u00a0\n\nPersonal data provided by job applicants will be used strictly in accordance with the employer's personal data policies and for recruitment purposes only.", "employment_types": ["Full Time", "Permanent"], "selling_points": ["Process credit applications", "Review and approve credit applications", "Minimum 5 year related experience"], "locations": ["Quarry Bay"], "categories": ["Banking / Finance", "Credit Analysis / Approval", "Loan", "Sales, CS & Business Devpt", "Others"], "post_time": "2022-01-07T10:57:14Z", "salary": {"currency": null, "max": null, "min": null, "period": "monthly", "term": null}, "salary_visible": false, "title_keywords": ["manager"], "responsibilities": ["policies", "communication", "recruitment", "personal data", "senior management"], "requirements": {"degrees": ["fresh graduate", "degree holder"], "majors": ["any disciplines"], "languages": ["cantonese", "english", "chinese", "mandarin"], "language_level": ["good command"], "hard_skills": ["r&d", "ms office", "ai"], "soft_skills": ["confident", "communication skill", "driven", "hands on", "interpersonal"], "languages_combined": [{"language": "cantonese", "language_level": ["good command"]}, {"language": "english", "language_level": ["good command"]}, {"language": "chinese", "language_level": ["good command"]}, {"language": "mandarin", "language_level": ["good command"]}]}, "experience_required": {"duration": [], "field": ["secretarial"]}}, {"job_id": "100003009026950", "location_code": "hk", "company": "Funki Finance", "job_title": "Loan Officer", "description": "Responsibilities:\n\nResponsible for the overall daily operation;\nPreparation of Credit Reports/Credit Recommendations/Credit Documentation;\nMaintain good relationship with customers, vendors and business partners;\nHandle emails, live chats, inbound and outbound calls of customers and vendors enquiries in a proactive and positive manner;\nEvaluate problems / issues raised by customers or vendors and provide solution effectively to build customer loyalty;\nHandle enquiries / complaints of customers;\nParticipate in projects on new process/service development, automation of new process and system enhancement / UAT to improve operational efficiency.\n\n\u00a0Requirements:\n\nDiploma/ Associate degree holder or above;\nMinimum 1 year of retail banking / phone banking / financial industry / customer service experience;\nCredit/Finance experience is highly preferred;\nGo-getter with mad juggling skills (or multiple hats) who can thrive in a fast-paced, agile environment;\nGood at English, Cantonese and Mandarin;\nKnowledge in Credit Reports/Credit Recommendations/Credit Documentation;\nGood communication and interpersonal skill.\n\nWe offer attractive remuneration package, career advancement opportunities and generous fringe benefits to the right candidate.\u00a0 Please apply with your\u00a0full resume, salary expectation and contact phone number(s)\u00a0by clicking \"Apply Now\".\n\nData collected will be used for recruitment purpose only.", "employment_types": ["Full Time", "Permanent"], "selling_points": ["Preparation of Credit Reports", "Maintain good relationship with customers, vendors", "Minimum 1 year of experience"], "locations": ["Sheung Wan"], "categories": ["Banking / Finance", "Loan", "Financial Services", "Sales, CS & Business Devpt", "Customer Service - Supervisor / Officer"], "post_time": "2022-01-06T08:55:46Z", "salary": {"currency": null, "max": null, "min": null, "period": "monthly", "term": null}, "salary_visible": false, "title_keywords": ["officer"], "responsibilities": ["uat", "daily operation", "maintain good relationship", "evaluate", "handle enquiries", "reports", "documentation"], "requirements": {"degrees": ["associate degree", "diploma"], "majors": [], "languages": ["cantonese", "english", "mandarin"], "language_level": ["good"], "hard_skills": ["documentation", "go", "agile", "mad"], "soft_skills": ["communication", "customer service", "agile", "interpersonal skill"], "languages_combined": [{"language": "cantonese", "language_level": ["good"]}, {"language": "english", "language_level": ["good"]}, {"language": "mandarin", "language_level": ["good"]}]}, "experience_required": {"duration": ["minimum 1 year"], "field": ["finance", "retail banking", "financial industry", "customer service", "banking"]}}, {"job_id": "100003009033776", "location_code": "hk", "company": "Konew Financial Express Ltd", "job_title": "Accountant", "description": "Main Duties & Responsibilities:\u00a0 \u00a0 \u00a0 \u00a0\n\nCompile various accounting and financial reports\nEnsure accurate and timely of the reconciliation and reports\nPrepare and monitor the budget & forecast\nEnsure accuracy and timely accounting records in the FlexSystem\nMaintain updated charts of Accounts & Analysis Code in FlexSystem\nReview and enhance accounting system, accounting policies and internal control\nLiaise with external auditors and professionals\nHandle accounting duties of Directors\u2019 investment in various countries\nFinal check the figures on the Redemption Report to ensure accuracy\nPerform daily routine accounting functions when required\nKeep proper and organized filing for easy retrieval and in confidential manner\nWorking on different projects, including but not limited to research and study of accounting treatment\nHandle ad hoc tasks as assigned from time to time\n\nRequirements:\n\n\nBachelor's degree or above in Finance, Accounting or related disciplines, preferably with CPA qualification\nMinimum 3 years relevant working experience, with experience in commercial field is an advantage\u00a0\nCan work well with different parties, both internal and external\nAble to handle multi-tasks and meet tight deadlines\nIndependent, proactive and attentive to details\nMature, able to work under pressure with strong sense of confidentially & analytical mind\nGood interpersonal and communication skills\nImmediately available is preferred\n\nWe offer:\n\nDiscretionary bonus\nMedical insurance\nDental insurance\nHardship allowance\nCompetitive annual leave days\nBirthday leave\nAnniversary leave\nStudy leave\nMarriage leave\nCompassionate leave\n\nHow to apply:\n\nInterested parties, please send your resume stating your expected salary\u00a0to\u00a0Human Capital Department\u00a0by clicking\u00a0\"APPLY NOW\".\n\n(We are an equal opportunity employer.\u00a0 Personal data collected will be used for recruitment purpose only.\u00a0 The unsuccessful applications will be destroyed after 6 months.)", "employment_types": ["Full Time"], "selling_points": ["Minimum 3 years relevant working experience", "Compile various accounting and financial reports", "Liaise with external auditors and professionals"], "locations": ["Central"], "categories": ["Accounting", "Accountant", "Banking / Finance", "Loan"], "post_time": "2022-01-10T01:46:56Z", "salary": {"currency": null, "max": null, "min": null, "period": "monthly", "term": null}, "salary_visible": false, "title_keywords": ["accountant"], "responsibilities": ["financial reports", "analysis", "budget", "monitor", "review", "ad hoc tasks", "external auditors", "accounting policies", "maintain", "reports", "forecast", "liaise with", "report", "accounting duties", "internal control"], "requirements": {"degrees": ["degree or above", "bachelor"], "majors": ["related disciplines", "finance", "accounting"], "languages": [], "language_level": [], "hard_skills": ["cpa"], "soft_skills": ["communication skills", "meet tight deadlines", "independent", "attentive to details", "multi-tasks", "mature", "analytical mind", "proactive", "interpersonal", "work under pressure"], "languages_combined": []}, "experience_required": {"duration": ["minimum 3 years"], "field": ["commercial", "relevant working experience"]}}, {"job_id": "100003009025197", "location_code": "hk", "company": "World Force Trading Limited", "job_title": "Loan Service Officer", "description": "Responsibilities:\n\nReport to the Branch Manager, you will be responsible for clean lending acquisition activities.\nStation at Personal Loan Service Corner of selected branch.\nTake proactive role to solicit sales from counter sales referral, sales promotion booth and out-reach marketing activities.\nWork to follow up on approval and drawdown to ensure customer satisfaction .\n\n\n\n", "employment_types": ["Full Time"], "selling_points": ["- 3 years of experience in Personal Loan Lending", "- Prefer in bank or Finance company", "- Attractive salary and bonus"], "locations": ["Tsim Sha Tsui"], "categories": ["Banking / Finance", "Loan"], "post_time": "2022-01-06T03:58:03Z", "salary": {"currency": null, "max": null, "min": null, "period": "monthly", "term": null}, "salary_visible": false, "title_keywords": ["officer"], "responsibilities": ["report"], "requirements": {"degrees": [], "majors": [], "languages": [], "language_level": [], "hard_skills": ["clean"], "soft_skills": ["proactive", "responsible"], "languages_combined": []}, "experience_required": {"duration": [], "field": []}}, {"job_id": "100003009026266", "location_code": "hk", "company": "China CITIC Bank International Limited", "job_title": "Officer (Loan Document - Retail Banking & Mortgage)", "description": "Job Purpose\n\nPerform maker role to prepare and administer standard loan documentation in compliance with Credit Policy and regulatory requirement\n\nKey Responsibilities\nPrepare facility letter, instruction letter and security documentation\nFollow up outstanding documentation items on timely basis\nAdminister registration / release of charge documents in HK Companies Registry\nHandle ad-hoc projects and other duties as assigned\nRequirements\nDegree holder / Post-secondary or equivalent\nMinimum 2 years of loan documentation experience\nBasic knowledge on Companies Ordinance and legal requirements for perfection of loan documentation\nGood knowledge and concept in retail banking products\nProficient in MS Office\nGood command of both written and spoken English and Chinese\nFor more details about career opportunities with the Bank, please visit our website http://www.cncbinternational.com/careers/en/index.jsp.\u00a0 Please apply with full resume stating current and expected salaries.\nPersonal data collected will be used for recruitment related purposes only. Applicants not invited for interview within 6 weeks may consider their applications unsuccessful. However, applicants may be considered for other suitable positions within the Group for a period of not more than 2 years. Personal data will be destroyed at any time after 3 months.\nChina CITIC Bank International is committed to being an equal opportunities employer and intends to provide a work environment free of unlawful discrimination or harassment.\u00a0 All employment decisions will be made in a non-discriminatory manner.\nJob highlight\nPrepare facility letter and security document\nFollow up outstanding documentation items\nKnowledge on Companies Ordinance/legal requirement", "employment_types": ["Full Time", "Permanent"], "selling_points": ["Check facility letter and security document", "Follow up outstanding documentation items", "Knowledge on Companies Ordinance"], "locations": ["Quarry Bay"], "categories": ["Banking / Finance", "Loan", "Mortgage", "Retail Banking"], "post_time": "2022-01-06T07:48:37Z", "salary": {"currency": null, "max": null, "min": null, "period": "monthly", "term": null}, "salary_visible": false, "title_keywords": ["officer"], "responsibilities": ["documentation", "ad-hoc projects", "other duties"], "requirements": {"degrees": ["degree holder"], "majors": [], "languages": ["english", "chinese"], "language_level": ["good command"], "hard_skills": ["documentation", "companies ordinance", "basic", "ms office"], "soft_skills": ["committed"], "languages_combined": [{"language": "english", "language_level": ["good command"]}, {"language": "chinese", "language_level": ["good command"]}]}, "experience_required": {"duration": ["minimum 2 years"], "field": []}}, {"job_id": "100003009020977", "location_code": "hk", "company": "Bangkok Bank Public Co Ltd", "job_title": "Credit Administration Assistant (Ref: CAS-09/175/240-DB)", "description": "We are now seeking a high caliber candidate to join our Hong Kong Branch.\n\nResponsibilities:\n\nPrepare and order miscellaneous reports, including but not limited to Credit Monitoring Report (CMOS), company search, land search, bankruptcy search and CCRA basic reports, etc.\nPrepare minutes and conclusion for Loan Committee Meetings\nMaintain credit file check list\nExamine monthly invoices of credit services agency and CCRA\nProvide general administrative and clerical support to the Department\nHandle ad-hoc assignments as and when required\n\nRequirements:\n\nUniversity graduate\nHands-on experience in handling loan documentation is preferable\nTeam player with positive attitude and good problem-solving skills\u00a0\nProficiency in MS Office\nFluent spoken and written English, Chinese (Cantonese & Putonghua)\n\nWe offer excellent career prospects to the right candidate. Salary will be commensurate with qualifications and experience. Interested parties please apply with\u00a0full resume, stating current / expected salary and availability to the The Human Resources Manager, Bangkok Bank Public Co. Ltd., Bangkok Bank Building, 28 Des Voeux Road Central,\u00a0Hong Kong.\u00a0\u00a0\u00a0\u00a0\n\nPersonal data provided by job applicants will be used solely\u00a0for considering suitability for the post and strictly in accordance with our personal data policies which are available on request.\n\n(Only shortlisted candidates will be contacted.)", "employment_types": ["Full Time"], "selling_points": [], "locations": ["Central"], "categories": ["Banking / Finance", "Corporate Banking", "Loan", "Others"], "post_time": "2022-01-07T08:34:37Z", "salary": {"currency": null, "max": null, "min": null, "period": "monthly", "term": null}, "salary_visible": false, "title_keywords": ["administration assistant"], "responsibilities": ["invoices", "ad-hoc assignments", "monitoring", "maintain", "reports", "administrative and clerical support", "report", "company search"], "requirements": {"degrees": ["university graduate"], "majors": [], "languages": ["cantonese", "putonghua", "english", "chinese"], "language_level": ["fluent"], "hard_skills": ["documentation", "problem-solving skills", "ms office"], "soft_skills": ["positive attitude", "problem-solving skills", "hands-on", "team player"], "languages_combined": [{"language": "cantonese", "language_level": ["fluent"]}, {"language": "putonghua", "language_level": ["fluent"]}, {"language": "english", "language_level": ["fluent"]}, {"language": "chinese", "language_level": ["fluent"]}]}, "experience_required": {"duration": [], "field": []}}, {"job_id": "100003009027547", "location_code": "hk", "company": "PrimeCredit Ltd", "job_title": "Senior Marketing Officer, Digital Channel", "description": "Responsibilities\n\nAct as administrator of media multi-platforms, including websites and apps to maintain its user-friendliness, functionality, attractiveness and security\nMonitor and analyze websites and apps\u2019 performance (e.g. traffic, behavior, conversions path, etc.) by Google Analytics and Firebase in order to provide optimization recommendation\nAssist in websites and apps development, revamp and maintenance\nAnalyze the website/apps layouts, structure, map, URL structure, HTML coding, navigation systems, SEO/ASO, etc. to improve the search rankings and enhance the visibility\nPerform Tealium Tag, Google Tag Manager (GTM) and Media Tag management\nAct as the checker to push the website and apps contents in production to ensure the functionality and efficiency of website and apps infrastructure\nImplement A/B testing to improve UX/UI and conversion rate\nAssist in Customer Data Platform development and testing\n\nRequirements\n\nUniversity degree holder or above in Marketing, Business, Information System or related disciplines\nAt least 3 years\u2019 working experience in marketing or digital projects with working knowledge of website management tools and WordPress, preferable in consumer finance / retail banking industry\nGood knowledge of web analytics, Google Analytics, SEO, Google Tag Manager is a must\nProficient in HTML/CSS, HTTP, XML; knowledge of SQL, JavaScript and Tealium Tag are preferable\nGood team player with strong digital project management, analytical and problem solving skills\nProficient in MS Office Applications including Chinese word processing\nProficient in both spoken and written English and Chinese\n\nThis is a very rewarding and exciting opportunity. We offer an attractive remuneration to the successful candidates. Please forward your resume with present and expected salary by clicking \u201cAPPLY NOW\u201d or complete the online application form at\u00a0https://www.primecredit.com/career/en/jobs.\n\nTo know more about PrimeCredit, please visit our websites\u00a0https://www.primecredit.com/career/en/.\n\nAll applications will be treated in strict confidence and only be used for recruitment related purpose.", "employment_types": ["Full Time", "Permanent"], "selling_points": ["Act as administrator of media multi-platforms", "Monitor and analyze websites and apps\u2019 performance", "At least 3 years of experience in Marketing"], "locations": ["Wan Chai"], "categories": ["Banking / Finance", "Loan", "Marketing / Public Relations", "Marketing - General / Support", "Digital Marketing"], "post_time": "2022-01-06T10:20:44Z", "salary": {"currency": null, "max": null, "min": null, "period": "monthly", "term": null}, "salary_visible": false, "title_keywords": ["senior marketing officer"], "responsibilities": ["management", "revamp", "seo", "maintenance", "systems", "monitor", "website", "coding", "infrastructure", "testing", "customer data", "maintain", "contents", "ui"], "requirements": {"degrees": ["university degree"], "majors": ["business", "related disciplines", "marketing"], "languages": ["english", "chinese"], "language_level": ["proficient"], "hard_skills": ["google analytics", "seo", "chinese word processing", "information system", "html", "sql", "project management", "wordpress", "javascript", "web analytics", "css", "problem solving skills", "ms office"], "soft_skills": ["web analytics", "project management", "good team player", "analytical and problem solving skills"], "languages_combined": [{"language": "english", "language_level": ["proficient"]}, {"language": "chinese", "language_level": ["proficient"]}]}, "experience_required": {"duration": ["at least 3 years"], "field": ["management", "finance", "retail banking", "marketing", "digital"]}}, {"job_id": "100003009007172", "location_code": "hk", "company": "The Bank of East Asia, Limited", "job_title": "Assistant Planning & Process Manager (Risk & Control and General Administration)", "description": "Assistant Planning & Process Manager (Risk & Control and General Administration)\u00a0(Job ID: 3332)\n\nResponsibilities\nTo be a team member of Risk & Control and General Administration Team of Lending Operations Department\nTo provide support risk and control and general administration functions of the department\nTo take up ad-hoc tasks as assigned\nRequirements\nUniversity graduate, preferably major in business, finance; OR\nPreferably with over 3 years of experience in banking sector with job knowledge in retail & corporate lending operations;\nPossess strong risk awareness and have a good understanding of banking policies and practices as well as regulatory rules and guidelines;\nAble to work under high pressure and complete the assigned tasks within the schedules;\nIndependent, self-motivated, detail-oriented and with a logical and analytical sense of mind;\nA good team player with strong interpersonal and communication skills;\nThorough MS Office knowledge;\nGood command of both spoken and written English and Chinese, Putonghua proficiency is an advantage.\n\n(Candidate with less experience will be considered for the position of Senior Planning & Process Officer)\nPlease apply online via the BEA Careers website at https://careers.hkbea.com/psp/hcmprd/EMPLOYEE/HRMS/c/HRS_HRAM.HRS_APP_SCHJOB.GBL?Page=HRS_APP_JBPST&Action=UFOCUS=Applicant&SiteId=1&JobOpeningId=3332&PostingSeq=1 or by clicking the \"Apply Now\" button below. Kindly note that if you are a new user, you have to first create your User Profile before you can apply.\n\nPersonal data provided by job applicants will be used for recruitment purposes only and will be treated in accordance with the Bank's Personal Information Collection (Employees) Statement and Privacy Policy Statement. Applicants who are not invited for interviews within six weeks may consider their applications unsuccessful and the personal data collected will be destroyed after six months.", "employment_types": ["Full Time", "Permanent"], "selling_points": ["Support risk & control functions in lending ops", "Provide general administration support", "University graduate with 3 yrs' exp. preferred"], "locations": ["Kwun Tong"], "categories": ["Banking / Finance", "Loan", "Financial Services", "Order Processing & Operation / Settlement"], "post_time": "2022-01-04T16:20:04Z", "salary": {"currency": null, "max": null, "min": null, "period": null, "term": null}, "salary_visible": false, "title_keywords": ["manager", "assistant"], "responsibilities": ["control", "provide support", "operations", "ad-hoc tasks", "administration"], "requirements": {"degrees": ["university graduate"], "majors": ["finance", "business"], "languages": ["putonghua", "english", "chinese"], "language_level": ["advantage", "proficiency", "good command"], "hard_skills": ["c", "ms office"], "soft_skills": ["communication skills", "good team player", "self-motivated", "independent", "detail-oriented", "work under high pressure", "thorough", "interpersonal"], "languages_combined": [{"language": "putonghua", "language_level": ["proficiency", "advantage", "good command"]}, {"language": "english", "language_level": ["advantage", "good command"]}, {"language": "chinese", "language_level": ["advantage", "good command"]}]}, "experience_required": {"duration": ["3 years"], "field": ["retail", "banking sector", "planning"]}}, {"job_id": "100003009032194", "location_code": "hk", "company": "Gravitas Recruitment Group", "job_title": "AVP - China Large Corp, Relationship Manager", "description": "Our client is a rapid growing international bank with a strong reputation and presence worldwide with a wide range pf banking product. In their Corporate Banking Division, they have strong client networks in Greater China regions with a heavy target in SOE and POE corporate customers. Currently they are actively hiring for a high caliber to join their team in Corporate Banking to achieve a higher international banking exposure and outstand your achievement.\n\nJob Responsibilities:\n\nManage existing portfolio of China 1st tier SOE large corporates\nProactively participate in the marketing corporate financial services\nPrepare credit analysis for new & existing clients\nPrepare comprehensive credit applications to obtain credit approval\nComply with risk and AML requirements in accordance with regulatory standards and bank policy\nPerform periodic review for the key accounts to report and control the risks\n\nJob Requirement:\n\nBachelor's degree or above in related discipline\n3-5 experience in Corporate Banking\nExperience in Audit is preferred\nSolid credit analysis and application proposal writing skills in English\nCustomer-oriented with passion to cultivate business relationship\nProficiency in spoken and written Chinese, Mandarin and English\n\nInterested parties please click Apply Now to submit your CV to us. For any enquiries and immediate response, please feel free to send you CV or contact Abby Chu at A.chu@gravitasgroup.com or by phone +852 3896 2507 / +852 6046 8678.", "employment_types": ["Full Time", "Permanent"], "selling_points": ["rapid-growing bank with extensive market share", "Top tier China large Corp SOE clients", "No sales target, deal participation exposure"], "locations": ["Not Specified"], "categories": ["Banking / Finance", "Corporate Banking", "Loan"], "post_time": "2022-01-07T10:26:46Z", "salary": {"currency": "HKD", "max": 54999, "min": 30000, "period": "monthly", "term": null}, "salary_visible": true, "title_keywords": ["relationship manager"], "responsibilities": ["control", "aml", "analysis", "review", "report"], "requirements": {"degrees": ["degree or above", "bachelor"], "majors": [], "languages": ["english", "chinese", "mandarin"], "language_level": ["proficiency"], "hard_skills": ["credit analysis", "writing skills"], "soft_skills": ["customer-oriented", "writing skills"], "languages_combined": [{"language": "english", "language_level": ["proficiency"]}, {"language": "chinese", "language_level": ["proficiency"]}, {"language": "mandarin", "language_level": ["proficiency"]}]}, "experience_required": {"duration": [], "field": ["audit", "banking"]}}, {"job_id": "100003009018665", "location_code": "hk", "company": "The Great Eagle Group of Companies", "job_title": "Manager - Treasury", "description": "Responsibilities:\n\nResponsible for routine treasury and loan transactions execution and administration including loan documentation negotiation, treasury dealing, KYC and compliance monitoring and relevant treasury reporting\nAssist in fund raising in bank loan market and international debt capital market\nAssist in managing all treasury functions including corporate liquidity, forex hedging, cash flow forecast and risk management\nDrive process and system improvement to increase data integrity and security\nAssist in managing banking relationship\nHandle ad hoc works as assigned by management\n\nRequirements:\n\nDegree holder in Accounting, Finance or other related disciplines\nHolder of CPA or CFA is an advantage\nMinimum 10 years\u2019 experience with corporate treasury, in-depth knowledge of debt, forex, derivative and cash management \u00a0\nStrong analytical and problem solving skills\nGood communication, presentation and interpersonal skills\nResponsible, well-organized, detail-minded, independent and able to work under pressure\nGood team player, willing to learn and take up new tasks\nProficiency in MS Office Applications\nGood command of both spoken and written\u00a0English\u00a0and Chinese (including Putonghua)\n\nSalary and benefits will be commensurate with qualifications and experience.\u00a0 Interested parties, please send a full resume with present and expected salary, and date available to The Human Resources Department, 32/F., Great Eagle Centre, 23 Harbour Road, Wanchai, Hong Kong or e-mail to us.\u00a0\u00a0(Please quote the reference no. on the envelope and the covering letter.)\n\nTo know more about us, please visit our websites at http://www.greateagle.com.hk\n\nWe are an equal opportunity employer and welcome applications from all qualified candidates.\n\nPersonal data collected will be treated in strict confidence and used only for recruitment-related purpose. Applicants who have not heard from us within four weeks may consider their applications unsuccessful. All personal data will be destroyed after 12 months.", "employment_types": ["Full Time", "Permanent"], "selling_points": ["Manage all corporate treasury functions", "Fund raising, debt capital market", "Holder of CPA or CFA is an advantage"], "locations": ["Wan Chai"], "categories": ["Accounting", "Consulting", "Banking / Finance", "Loan", "Dealing & Trading"], "post_time": "2022-01-04T04:15:45Z", "salary": {"currency": null, "max": null, "min": null, "period": "monthly", "term": null}, "salary_visible": false, "title_keywords": ["manager"], "responsibilities": ["reporting", "management", "ad hoc", "data", "compliance", "monitoring", "banking", "transactions", "cash flow", "forecast", "kyc", "documentation", "administration"], "requirements": {"degrees": ["degree holder"], "majors": ["related disciplines", "finance", "accounting"], "languages": ["putonghua", "english", "chinese"], "language_level": ["good command"], "hard_skills": ["cfa", "cpa", "problem solving skills", "ms office"], "soft_skills": ["detail-minded", "good team player", "independent", "responsible", "well-organized", "willing to learn", "communication", "analytical and problem solving skills", "interpersonal skills", "presentation", "work under pressure"], "languages_combined": [{"language": "putonghua", "language_level": ["good command"]}, {"language": "english", "language_level": ["good command"]}, {"language": "chinese", "language_level": ["good command"]}]}, "experience_required": {"duration": ["minimum 10 years"], "field": ["management"]}}, {"job_id": "100003009019449", "location_code": "hk", "company": "PrimeCredit Ltd", "job_title": "Clerk (Contract) \u2013 Credit Card Centre", "description": "Responsibilities\n\nProvide general clerical support to Credit Card Centre, e.g. data entry, filing, returned mail handling etc.\nPrepare MIS reports for Customer Support Section\n\nRequirements\n\nForm 5 / DSE graduate or above\n1 - 2 years clerical working experience is preferable\nProficient in MS Office Applications, e.g. Word & Excel\nGood command of both written & spoken Cantonese and English\nFresh graduate will also be considered\n\nThis is a very rewarding and exciting opportunity. We offer an attractive remuneration to the successful candidates. Please forward your resume with present and expected salary by clicking \u201cAPPLY NOW\u201d or complete the online application form at https://www.primecredit.com/career/en/jobs.\n\nTo know more about PrimeCredit, please visit our websites https://www.primecredit.com/career/en/.\n\nAll applications will be treated in strict confidence and only be used for recruitment related purpose.", "employment_types": ["Full Time", "Contract"], "selling_points": ["Provide clerical support to Credit Card Centre", "Prepare MIS reports for Customer Support Section", "1 - 2 years clerical working exp. is preferable"], "locations": ["Wan Chai"], "categories": ["Admin & HR", "Clerical / Admin Staff", "Others", "Banking / Finance", "Loan"], "post_time": "2022-01-04T07:43:20Z", "salary": {"currency": null, "max": null, "min": null, "period": "monthly", "term": null}, "salary_visible": false, "title_keywords": ["clerk"], "responsibilities": ["reports", "clerical support", "data entry"], "requirements": {"degrees": ["fresh graduate", "form 5", "dse"], "majors": [], "languages": ["cantonese", "english"], "language_level": ["good command"], "hard_skills": ["excel", "word", "ms office"], "soft_skills": [], "languages_combined": [{"language": "cantonese", "language_level": ["good command"]}, {"language": "english", "language_level": ["good command"]}]}, "experience_required": {"duration": ["1 - 2 years"], "field": ["clerical"]}}, {"job_id": "100003009016379", "location_code": "hk", "company": "Taishin International Bank Co Ltd", "job_title": "AVP/ VP - Credit", "description": "Responsibilities:\u00a0\n\nInterview new loan applicants and collect and analyze financial and related data in order to determine the general credit worthiness of the prospect and the merits of the specific loan request and validate the reasons put forward for requiring the credit facilities.\nEvaluate, assess and scrutinize securities pledged for credit facilities by reference to the legal effect of the documentation and sale-ability of the collateral.\nConduct independent credit review to evaluate and assess the credit-worthiness of a particular customer\nWork closely with loan department to structure customer loan package\nReview and scrutinize existing accounts to anticipate and spot potential problems and to take remedial actions\nMonitor security value and keep to an agreed level by liaising with customers and management.\nRequirements:\n\nUniversity degree in Business Management, Banking, Finance or a related discipline or other relevant qualifications\n5-10 years' experience in private banking, credit risk management is preferable,\nAbility to work under pressure, with strong self-motivation\nStrong communication, interpersonal and analytical skills\nProficiency in both English and Chinese, fluency in Putonghua an advantage\nInterested parties please send your FULL RESUME with present & expected salary to\n\n\n\u00a0Manager, Human Resource\nTaishin International Bank, Hong Kong Branch\n6/F, Tower 5, The Gateway,\n15 Canton Road, Tsimshatsui.\n\nData from employment applications will be kept confidential and used only for the purpose of selection. Applications not being contacted within 2 months may consider their applications unsuccessful. Our Bank will retain the applications for a maximum of one year for future suitable openings.", "employment_types": ["Full Time", "Permanent"], "selling_points": ["Interview new loan applicants", "Evaluate, assess and scrutinize securities", "5-10 years' experience"], "locations": ["Yau Tsim Mong Area"], "categories": ["Banking / Finance", "Loan", "Financial Services"], "post_time": "2022-01-03T08:58:08Z", "salary": {"currency": null, "max": null, "min": null, "period": "monthly", "term": null}, "salary_visible": false, "title_keywords": [], "responsibilities": ["management", "data", "review", "monitor", "liaising with", "evaluate", "documentation"], "requirements": {"degrees": ["university degree"], "majors": ["finance", "business"], "languages": ["putonghua", "english", "chinese"], "language_level": ["fluency", "advantage", "proficiency"], "hard_skills": ["business management", "analytical skills"], "soft_skills": ["analytical skills", "communication", "self-motivation", "interpersonal", "work under pressure"], "languages_combined": [{"language": "putonghua", "language_level": ["fluency"]}, {"language": "english", "language_level": ["proficiency", "fluency", "advantage"]}, {"language": "chinese", "language_level": ["proficiency", "fluency", "advantage"]}]}, "experience_required": {"duration": ["5-10 years"], "field": ["management", "credit risk", "banking"]}}, {"job_id": "100003009020819", "location_code": "hk", "company": "PeopleSearch Ltd", "job_title": "Vice President, Liquidity Risk", "description": "Our client, a reputable international bank in Asia is currently looking for a VP to join their growing Risk Management team. Incumbents will be rewarded with a stable work environment with excellent career progression opportunities.\n\nKEY RESPONSIBILITIES\n\nReview the Bank\u2019s Liquidity Risk and Interest rate risk and implement the related policies and provide risk advisory to the management\nParticipate in Basel III and other related regulatory project\nLiaise with other departments of the Bank for daily and ad-hoc issues about interest rate risk and liquidity risk\nImplement stress test with regular review\n\nREQUIREMENTS\n\nDegree holder in Business, Accounting, Finance, Economics or related disciplines\nMinimum 6 years of relevant experience in the banking industry\nRelevant experience in liquidity risk management, or liquidity and interest rate risk regulatory reporting or asset liability management will be preferred\nProfessional qualifications, like CPA or CFA will be an advantage\nGood knowledge about Basel II/III will be a plus\nGood communication and presentation skills\nStrong computer skills including MS Excel, PowerPoint and Word\nFluent in Cantonese, English and Mandarin\n\nInterested applicants please send your full resume (in Word format) together with present and expected salary to Raymond Lam\n\nTel: (852) 2521-5118 ext.810", "employment_types": ["Full Time", "Permanent"], "selling_points": ["Excellent Career Path with Stability", "Liquidity Management Role", "Min 6 years of Experience in Risk Management"], "locations": ["Central & Western Area"], "categories": ["Banking / Finance", "Corporate Banking", "Loan", "Financial Services"], "post_time": "2022-01-05T02:09:46Z", "salary": {"currency": null, "max": null, "min": null, "period": "monthly", "term": null}, "salary_visible": false, "title_keywords": ["vice president"], "responsibilities": ["ad-hoc", "management", "policies", "review", "regular review", "liaise with"], "requirements": {"degrees": ["degree holder"], "majors": ["finance", "economics", "related disciplines", "business", "accounting"], "languages": ["cantonese", "english", "mandarin"], "language_level": ["fluent"], "hard_skills": ["plus", "professional qualifications", "cfa", "word", "powerpoint", "cpa", "ms excel", "computer skills"], "soft_skills": ["communication", "presentation skills"], "languages_combined": [{"language": "cantonese", "language_level": ["fluent"]}, {"language": "english", "language_level": ["fluent"]}, {"language": "mandarin", "language_level": ["fluent"]}]}, "experience_required": {"duration": ["minimum 6 years"], "field": ["banking industry", "management", "relevant experience", "risk management"]}}, {"job_id": "100003009017809", "location_code": "hk", "company": "Cornerstone Global Partners", "job_title": "Tele Sales (Bank, Perm, Up to 30k Comm/Mth) Welcome Retail Sales", "description": "Our Client\n\nA well-established bank in HK\n\nRole Overview\n\nConduct outbound telemarketing activities to cross-sell Credit Card or Personal Loan products to customers to achieve business goals and objectives\nAchieve sales targets, objectives and to meet service standard\nPresent strong commitment in delivering quality customer service\n\n\u00a0Ideal Profile\n\nSecondary education or above with relevant experience in sales and customer services\nAbility to work under pressure and achieve sales target", "employment_types": ["Full Time", "Permanent"], "selling_points": ["Commission 10-30k per month", "Retail Banking", "1 year sales experience"], "locations": ["Not Specified"], "categories": ["Banking / Finance", "Loan", "Sales, CS & Business Devpt", "Retail Sales", "Tele-sales (Telemarketing)"], "post_time": "2022-01-04T02:05:26Z", "salary": {"currency": null, "max": null, "min": null, "period": "monthly", "term": null}, "salary_visible": false, "title_keywords": ["retail sales", "sales"], "responsibilities": ["business goals", "service standard", "sales target", "quality", "customer services", "customer service", "work under pressure"], "requirements": {"degrees": ["secondary education"], "majors": [], "languages": [], "language_level": [], "hard_skills": ["loan products"], "soft_skills": ["work under pressure", "customer service", "ideal"], "languages_combined": []}, "experience_required": {"duration": [], "field": ["relevant experience", "customer services", "education"]}}, {"job_id": "100003009024049", "location_code": "hk", "company": "Morgan McKinley", "job_title": "Corporate Banking Relationship Manager (AVP/VP/SVP)", "description": "Key Responsibilities:\n\nDevelop and manage a corporate client portfolio by providing financial solutions and cross-selling suitable products/services\nSolicit new-to-bank clients to expand the bank's clients portfolio\nTo develop and maintain relationships with corporate customers and financial institutions\nProvide quality and value-added services to clients for cultivating a long-term business relationship\nPrepare comprehensive credit proposals and reviews for assessing customers' credit worthiness and react to market changes from time to time\n\nKey Skills:\n\nUniversity graduate in Finance, Economics, or related discipline, with HKICPA/ACCA or equivalent professional qualifications an advantage\nMinimum 5 years' solid experience in corporate/commercial banking; experienced candidates will be considered as VP or above\nGood credit analysis, report writing and communication skills\nSelf-motivated, independent and able to work under pressure\nProficient in both written and spoken English and Chinese including Putonghua\n\nApplication\n\nIf this above description fits your experience and is something you would like to explore, please click 'Apply Now' to submit your resume to us.\n\nOur specialist consultant will get in touch with you soon, if we find your profile suitable for this position or any other vacancies we are recruiting for.\n\nAny questions, please feel free to contact Regan Lo at 3907 3944.", "employment_types": ["Full Time", "Permanent"], "selling_points": ["AVP to SVP level Relationship Manager", "Large Coporate; Mid-Cap; SME clients", "Large Regional Bank"], "locations": ["Not Specified"], "categories": ["Banking / Finance", "Corporate Banking", "Loan", "Financial Services"], "post_time": "2022-01-05T10:29:22Z", "salary": {"currency": "HKD", "max": 69999, "min": 45000, "period": "monthly", "term": null}, "salary_visible": true, "title_keywords": ["relationship manager"], "responsibilities": ["maintain relationships", "work under pressure", "analysis", "quality", "develop", "communication", "contact", "banking", "report"], "requirements": {"degrees": ["university graduate"], "majors": ["finance", "economics"], "languages": ["putonghua", "english", "chinese"], "language_level": ["proficient"], "hard_skills": ["acca", "professional qualifications", "react", "credit analysis", "hkicpa"], "soft_skills": ["communication skills", "self-motivated", "independent", "comprehensive", "work under pressure"], "languages_combined": [{"language": "putonghua", "language_level": []}, {"language": "english", "language_level": ["proficient"]}, {"language": "chinese", "language_level": ["proficient"]}]}, "experience_required": {"duration": ["minimum 5 years"], "field": ["commercial", "banking"]}}, {"job_id": "100003009014993", "location_code": "hk", "company": "Connexe Search Limited", "job_title": "Assistant Relationship Manager, Large Corp/ Structured Finance (30k)", "description": "Our client is a well-regarded regional bank. They are currently looking for Assistant Relationship Manager to join their teams in Corporate Banking.\n\n(Written test required)\n\nJob Duties:\u00a0\n\nAssist Relationship Manager in managing a portfolio of corporate clients\nPrepare credit proposals, regular credit review\nCultivate long-term relationship with customers and explore new business opportunities through marketing and cross-selling bank products\nHandle account opening, KYC / AML related duties\n\nRequirement:\u00a0\u00a0\n\nUniversity degree in Finance, Accounting, Business or relevant discipline\n2+ years of ARM & credit analysis experience in corporate banking\nExcellent writing skills in both English and Chinese\nProficient Mandarin is a must\n\nPlease click Apply Now or email your full resume in MS Word format\u00a0quoting the job reference N211258 in the subject field. Your interest will be treated in strict confidence. Only shortlisted candidates will be notified.", "employment_types": ["Full Time", "Permanent"], "selling_points": ["Credit analyst/ Junior Relationship Manager", "Large corporate, syndication loan", "stable platform, no sales targets"], "locations": ["Central & Western Area"], "categories": ["Banking / Finance", "Corporate Banking", "Credit Analysis / Approval", "Loan"], "post_time": "2022-01-03T04:49:51Z", "salary": {"currency": null, "max": null, "min": null, "period": "monthly", "term": null}, "salary_visible": false, "title_keywords": ["assistant relationship manager"], "responsibilities": ["aml", "explore new business opportunities", "account opening", "review", "kyc"], "requirements": {"degrees": ["university degree"], "majors": ["business", "finance", "accounting"], "languages": ["english", "chinese", "mandarin"], "language_level": ["excellent", "proficient"], "hard_skills": ["credit analysis", "writing skills", "ms word"], "soft_skills": ["confidence", "writing skills"], "languages_combined": [{"language": "english", "language_level": ["excellent"]}, {"language": "chinese", "language_level": ["excellent"]}, {"language": "mandarin", "language_level": ["proficient"]}]}, "experience_required": {"duration": ["2+ years"], "field": ["banking"]}}, {"job_id": "100003009015621", "location_code": "hk", "company": "Ambition", "job_title": "Senior Officer, Deposit product", "description": "\nOur client is a well-established banking group with a stable and diversified business portfolio. They are now seeking a high-calibre marketing candidate to join Deposit product team.\n\n\nReporting to Team Head, you will be an active participant in the end-to-end process of product development and feature enhancement of Deposit product, formulating and executing acquisition and retention marketing campaign to facilitate business growth in the business, responsible for liaising with internal and external parties to ensure on-time delivery. You will also monitor sales channel and analyse campaign performances.\nTo qualify, individuals must possess:\n\nBachelor degree or above in related discipline\n1 - 2 years' experience in Marketing / Product gained from retail banking\nCandidates from other Financial Services firms will also be considered\nMotivated individual with a positive attitude and strong business acumen\nStrong communications skills in English and Chinese\n\n\nContact Petty LAM on (852) 3103 4363 or via email petty.lam@ambition.com.hk, APPLY NOW by clicking the button below quoting reference number PL 252068 www.ambition.com.hk\nData provided is for recruitment purposes only\n\nIf this job isn't quite right for you, but you know someone who would be great at this role, why not take advantage of our referral scheme? We offer HKD1000 in Apple gift cards for every referred candidate who we place in a role. Terms & Conditions Apply. https://www.ambition.com.hk/refer-a-friend", "employment_types": ["Full Time", "Permanent"], "selling_points": ["Stable and friendly work environment", "Retail banking product management", "Attractive package and benefits"], "locations": ["Not Specified"], "categories": ["Banking / Finance", "Loan", "Mortgage", "Retail Banking"], "post_time": "2022-01-03T07:10:59Z", "salary": {"currency": null, "max": null, "min": null, "period": "monthly", "term": null}, "salary_visible": false, "title_keywords": ["senior officer"], "responsibilities": ["reporting", "data", "internal and external parties", "monitor", "liaising with", "executing", "contact", "recruitment", "banking", "analyse"], "requirements": {"degrees": ["degree or above", "bachelor"], "majors": [], "languages": ["english", "chinese"], "language_level": [], "hard_skills": ["pl", "scheme", "acumen"], "soft_skills": ["responsible", "positive attitude", "motivated individual", "business acumen", "stable", "active"], "languages_combined": [{"language": "english", "language_level": []}, {"language": "chinese", "language_level": []}]}, "experience_required": {"duration": ["1 - 2 years"], "field": ["retail banking", "marketing"]}}, {"job_id": "100003009009721", "location_code": "hk", "company": "Ego Finance Limited", "job_title": "Loan Clerk / Assistant Loan Officer / Loan Officer - Personal Loan Department", "description": "Responsibilities :\n\nProcessing & checking loan application\nResponsible for credit evaluation and loan approval\nHandling computer operation daily and paperwork\n\nRequirements :\n\nForm 5 graduation, have stable working history with 2 years or above relevant experience\n(Less than 2 years of relevant experience will be considered as Loan Clerk)\nHonest, responsible, mature and can work independently\nGood communication skills and response skills, proactive, and sincere service attitude\nBasic PC knowledge (including Chinese word processing input, MS Word, MS Excel)\n\nAn attractive remuneration package including :\n\nCompetitive salary\nDiscretionary Bonus\nBank holiday\nAnnual Leave 10-16 days\nAlternative Saturday-Off\nMedical and hospital insurance\nBirthday Leave\nMarriage Leave\nFuneral Leave\nCareer Progression\nChance to build-up your career path\nValue added training allowance\n\nWorking Hours :\n\nMonday to Friday:\u00a09:00 am to 6:00 pm (including 1 hour & 10 minutes lunch time)\nSaturday\u00a0 \u00a0 \u00a0 \u00a0 \u00a0 \u00a0 \u00a0 \u00a0: 9:00 am to 1:00 pm\u00a0(Alternative Saturday-Off)\n\nInterested parties please send your application including your full details resume, availability and expected salary for our consideration.\n\n\uff0a\uff0aAll personal data collected will be used for recruitment purpose only\uff0a\uff0a", "employment_types": ["Full Time"], "selling_points": [], "locations": ["Mong Kok"], "categories": ["Banking / Finance", "Loan", "Others"], "post_time": "2021-12-31T01:57:11Z", "salary": {"currency": null, "max": null, "min": null, "period": "monthly", "term": null}, "salary_visible": false, "title_keywords": ["officer", "personal", "clerk", "assistant"], "responsibilities": ["checking", "evaluation"], "requirements": {"degrees": ["form 5"], "majors": ["history"], "languages": ["chinese"], "language_level": ["basic"], "hard_skills": ["chinese word processing", "basic", "ms excel", "pc knowledge", "ms word"], "soft_skills": ["communication skills", "work independently", "responsible", "sincere", "mature", "honest", "stable", "proactive"], "languages_combined": [{"language": "chinese", "language_level": ["basic"]}]}, "experience_required": {"duration": ["2 years"], "field": ["relevant experience"]}}, {"job_id": "100003009019977", "location_code": "hk", "company": "Ambition", "job_title": "Relationship Manager - Corporate Banking", "description": "Job Responsibilities:\n\nManaging corporate client portfolio as well as conduct regular credit reviews to maintain quality loan portfolios;\nExplore new business opportunities and actively participate in the marketing and selling of the Bank's corporate financial services in the areas of corporate lending, trade financing, structured transactions, syndication, treasury and other financial services\nPerform credit analysis and prepare thorough credit proposal write-up for loans, trade finance and other banking facilities applications;\nAssist the team to achieve budgeted revenue and other campaign targets, covering a portfolio of corporate/cross border clients;\nHandle customer enquiries, account opening and related services;\nHandle ad hoc tasks and projects as assigned by the Department Head.\n\nJob Requirements:\n\nDegree holder in Business, Finance or related disciplines\nAt least 3 years relevant experiences in the designated business segment, preferably with exposure to public institutions\nGood knowledge of the corporate banking and treasury products and services\nFamiliar with the general banking operations and its legal and regulatory requirements\nCustomer-focused, with excellent communication and interpersonal skills\nGood command of written and spoken English and Chinese, fluency in Putonghua is a must\n\nContact Winnie Cheung on (852) 3103 4369/ winnie.cheung@ambition.com.hk quoting reference number BBBH253670 or APPLY NOW here\nhttp://www.ambition.com.hk\nData provided is for recruitment purposes only\n\nIf this job isn't quite right for you, but you know someone who would be great at this role, why not take advantage of our referral scheme? We offer HKD1000 in Apple gift cards for every referred candidate who we place in a role. Terms & Conditions Apply. https://www.ambition.com.hk/refer-a-friend", "employment_types": ["Full Time", "Permanent"], "selling_points": ["Assist in preparing sales performance report", "Assist in preparing sales performance report", "Cultivate long-term relationship with customers"], "locations": ["Not Specified"], "categories": ["Banking / Finance", "Corporate Banking", "Loan", "Financial Services"], "post_time": "2022-01-04T09:37:17Z", "salary": {"currency": null, "max": null, "min": null, "period": "monthly", "term": null}, "salary_visible": false, "title_keywords": ["relationship manager"], "responsibilities": ["handle customer enquiries", "explore new business opportunities", "maintain quality", "analysis", "account opening", "ad hoc tasks", "transactions", "banking"], "requirements": {"degrees": ["degree holder"], "majors": ["related disciplines", "finance", "business"], "languages": ["putonghua", "english", "chinese"], "language_level": ["fluency", "good command"], "hard_skills": ["scheme"], "soft_skills": ["communication and interpersonal skills", "customer-focused"], "languages_combined": [{"language": "putonghua", "language_level": ["fluency", "good command"]}, {"language": "english", "language_level": ["fluency", "good command"]}, {"language": "chinese", "language_level": ["fluency", "good command"]}]}, "experience_required": {"duration": ["at least 3 years"], "field": ["business"]}}, {"job_id": "100003009015518", "location_code": "hk", "company": "Hang Seng Bank Ltd", "job_title": "Credit Services Associate (Global Banking Agency Services)", "description": "Operations - Credit Services\u00a0\n\nHang Seng's Operations is a team of experienced banking operations professionals who strive for delivering time-to-market, efficient and world-class processing services to customers, corporations, financial institutions and internal units.\n\nCredit Services supports the processing and credit monitoring of a full range of lending products, including mortgages, overdraft, trade and business loans for Commercial Banking and Global Banking Customers.\u00a0\n\nWe are currently seeking a high caliber professional to join our department as\u00a0Credit Services Associate.\n\n\n\nPrincipal responsibilities\n\nHandle and review bilateral and / or syndicated loan documentation\nProvide support on loan agency services and operational matters related to loans processing according to operational procedures and service standards to maintain quality assurance of services provider\u00a0\nEnsure proper execution of credit documents and fulfillment of loan conditions before drawdown\u00a0\nLiaise with internal and external departments to ensure loan documents are in compliance with the Bank\u2019s policies, guidelines and regulatory requirements\nSupport the implementation of projects and business initiatives\nCompile reports for management review\u00a0\n\nRequirements\n\nUniversity degree in Business Management, Banking, Finance or a related discipline\nMinimum of 4 years' relevant banking experience, with loan agency experience will be an advantage.\u00a0\nGood communication, interpersonal and analytical skills\nProficiency in both English and Chinese\nGreat sense of ownership and servicing mindset to ensure efficient and effective customer service processes\n\nIf you would like to explore other opportunities at Hang Seng Hong Kong, please visit\u00a0www.hangseng.com/careers/\u00a0for details.\n\nThe health and safety of our employees and candidates is very important to us. Due to the current situation related to the Novel Coronavirus (2019-nCoV), we\u2019re leveraging our digital capabilities to ensure we can continue to recruit top talent at the HSBC Group. \u00a0As your application progresses, you may be asked to use one of our digital tools to help you through your recruitment journey. \u00a0If so, one of our Resourcing colleagues will explain how our video-interviewing technology will be used throughout the recruitment process and will be on hand to answer any questions you might have.\n\nAll information provided by applicants will be used only for recruitment purposes and will be used strictly in accordance with the Bank's personal data policies, a copy of which may be obtained by the applicant upon request. Unless otherwise instructed in writing by the applicant concerned, applicants may be considered for other suitable positions within the Bank and its related companies. The personal data of unsuccessful job applicants may be retained for a maximum of two years from the date when the job application is rejected and such data may be retained for a longer period if there is a subsisting reason that obliges the Bank to do so, after which the personal data will be destroyed.", "employment_types": ["Full Time", "Permanent"], "selling_points": [], "locations": ["Not Specified"], "categories": ["Banking / Finance", "Loan", "Others", "Order Processing & Operation / Settlement"], "post_time": "2022-01-03T06:54:55Z", "salary": {"currency": null, "max": null, "min": null, "period": "monthly", "term": null}, "salary_visible": false, "title_keywords": ["associate"], "responsibilities": ["business initiatives", "regulatory requirements", "fulfillment", "operational procedures and service standards", "liaise with", "loan agency services", "management review", "syndicated loan documentation", "maintain quality", "compliance", "handle and review bilateral", "implementation of projects", "provide support", "operational matters", "compile reports", "credit documents", "bank\u2019s policies", "guidelines", "loans processing"], "requirements": {"degrees": ["university degree"], "majors": ["finance", "business"], "languages": ["english", "chinese"], "language_level": ["proficiency"], "hard_skills": ["business management", "reason", "analytical skills"], "soft_skills": ["efficient", "analytical skills", "communication", "customer service", "novel", "interpersonal"], "languages_combined": [{"language": "english", "language_level": ["proficiency"]}, {"language": "chinese", "language_level": ["proficiency"]}]}, "experience_required": {"duration": ["minimum of 4 years"], "field": ["agency", "banking experience"]}}, {"job_id": "100003009011313", "location_code": "hk", "company": "Zero Finance Hong Kong Limited", "job_title": "Senior Credit Officer / Assistant Manager - Mortgage Loan", "description": "In this role, you will perform:\n\nResponsible for proactively follow up with related parties\nExecute properties appraisal on the new mortgage loans and refinance applications\nMaintain close relationship with agency and solicitors\u2019 firms\nEnsure the correctness of loan contracts before corporate approval\nImplement business plan to achieve sales targets\n\nTo be successful in this role, you should meet the following requirements:\u00a0\n\nTertiary education or above, finance or other business related disciplines are preferred\nPreferably 5 years relevant experience in Money Lending Industry\nGood command of spoken & written English, Cantonese and Mandarin\nStrong adaptability and flexibility\nProficient in MS Word, MS Excel and Chinese Word Processing\nLess experience will be considered as Senior Officer\n\nCompany Website: https://www.zerofinance.hk/zh/\u00a0\n\nAttractive remuneration package will be offered to the right candidate. Please apply with full resume stating present and expected salary to us by\u00a0clicking \u201cAPPLY NOW\u201d.\n\n(Personal data collected will be used for recruitment purpose only.)", "employment_types": ["Full Time", "Permanent"], "selling_points": ["Mortgage loans operation", "Credit administration", "5 days work, bank holidays"], "locations": ["Sheung Wan"], "categories": ["Banking / Finance", "Credit Analysis / Approval", "Loan", "Mortgage"], "post_time": "2021-12-31T06:55:26Z", "salary": {"currency": null, "max": null, "min": null, "period": "monthly", "term": null}, "salary_visible": false, "title_keywords": ["officer", "assistant manager"], "responsibilities": ["contracts", "maintain", "recruitment", "business plan", "personal data", "company website"], "requirements": {"degrees": [], "majors": [], "languages": ["cantonese", "english", "chinese", "mandarin"], "language_level": ["good command", "proficient"], "hard_skills": ["ms excel", "chinese word processing", "ms word"], "soft_skills": ["adaptability", "responsible"], "languages_combined": [{"language": "cantonese", "language_level": ["good command"]}, {"language": "english", "language_level": ["good command"]}, {"language": "chinese", "language_level": ["proficient"]}, {"language": "mandarin", "language_level": ["good command"]}]}, "experience_required": {"duration": ["5 years"], "field": ["relevant experience"]}}, {"job_id": "100003009011796", "location_code": "hk", "company": "China Construction Bank (Asia) Corporation Limited", "job_title": "Customer Service Officer, SE & PL Centre (1-year contract)", "description": "Main Responsibilities:\n\nAssist Centre Manager, Relationship Manager and Sales Executive for handling daily operations in a timely manner\nDeliver a high standard of customer service to our clients\nConsole all the operation and sales reports to Center Managers for business monitoring\nHandle customer\u2019s enquiries / complaints and resolve issues\nProvide administrative support for the Center\nComply with the regulatory requirements as well as the internal compliance policies and guidelines\n\n\u00a0Requirements:\n\nHigher Diploma / DSE graduate or above\nMinimum 1 year of experience in sales administrative\nDetail-minded and service oriented\nProactive with good communications and interpersonal skills\nGood command of English, Cantonese & Mandarin\nProficient in MS Word, Excel, PowerPoint and Chinese Word Processing\n\nApplicants who are not contacted within 8 weeks may consider their applications unsuccessful and their personal data will be retained by the bank for a period up to two years.\n\nAll information provided by applicants will be used for recruitment purposes only and will be used strictly in accordance with the bank\u2019s personal data policies, a copy of which will be provided upon request.", "employment_types": ["Full Time", "Contract"], "selling_points": ["Handle daily operations", "Deliver a high standard of customer service", "Console all the operation and sales reports"], "locations": ["Not Specified"], "categories": ["Admin & HR", "Clerical / Admin Staff", "Banking / Finance", "Loan", "Mortgage"], "post_time": "2021-12-31T08:18:43Z", "salary": {"currency": null, "max": null, "min": null, "period": "monthly", "term": null}, "salary_visible": false, "title_keywords": ["customer service officer"], "responsibilities": ["sales reports", "guidelines", "regulatory requirements", "policies", "monitoring", "a timely manner", "compliance", "daily operations", "customer service", "provide administrative support"], "requirements": {"degrees": ["diploma", "dse"], "majors": [], "languages": ["cantonese", "english", "chinese", "mandarin"], "language_level": ["good command", "proficient"], "hard_skills": ["excel", "chinese word processing", "powerpoint", "ms word"], "soft_skills": ["detail-minded", "proactive", "interpersonal skills"], "languages_combined": [{"language": "cantonese", "language_level": ["good command"]}, {"language": "english", "language_level": ["good command"]}, {"language": "chinese", "language_level": ["proficient"]}, {"language": "mandarin", "language_level": ["good command"]}]}, "experience_required": {"duration": ["minimum 1 year"], "field": ["administrative"]}}, {"job_id": "100003009009719", "location_code": "hk", "company": "Ego Finance Limited", "job_title": "Assistant Manager of Mortgage Department", "description": "Responsibilities:\n\nBe responsible for management of mortgage Loan department and leading a team to meet monthly target\nProvide on-the-job training to team members on regular basis\nEvaluate risk and implement marketing strategies in relation to company\nPrepare business and risk reports for monthly management meeting\nAssist in reviewing and improving the existing system and operation\nSupervise telemarketing day to day work\n\nRequirements:\n\nForm 5 or above\nAt least 3 years experience of mortgage loan and management position\nBe familiar with loan application process and approval of loan applications\nTelemarketing experience is preferable\n\nAn attractive remuneration package including:\n\nCompetitive salary\nDiscretionary Bonus\nBank holiday\nAnnual Leave 12-16 days\nAlternative Saturday-Off\nMedical and hospital insurance\nBirthday Leave\nMarriage Leave\nFuneral Leave\nCareer Progression\nChance to build-up your career path\nValue added training allowance\n\nWorking Hours:\n\nMonday to Friday\u00a0\u00a0\u00a0 :\u00a09:00 am to 6:00 pm (including 1 hour & 10 minutes lunch time)\nSaturday\u00a0 \u00a0 \u00a0 \u00a0 \u00a0 \u00a0 \u00a0 \u00a0 \u00a0 \u00a0: 9:00 am to 1:00 pm (Alternative Saturday-Off)\n\nInterested parties please send your application\u00a0including your full details resume, availability and expected salary for our consideration.\n\n\uff0a\uff0aAll personal data collected will be used for recruitment purpose only\uff0a\uff0a", "employment_types": ["Full Time"], "selling_points": [], "locations": ["Mong Kok"], "categories": ["Banking / Finance", "Credit Analysis / Approval", "Loan", "Mortgage"], "post_time": "2021-12-31T01:56:52Z", "salary": {"currency": null, "max": null, "min": null, "period": "monthly", "term": null}, "salary_visible": false, "title_keywords": ["assistant manager"], "responsibilities": ["evaluate", "management", "marketing strategies", "reports"], "requirements": {"degrees": ["form 5 or above"], "majors": [], "languages": [], "language_level": [], "hard_skills": [], "soft_skills": [], "languages_combined": []}, "experience_required": {"duration": ["at least 3 years"], "field": ["management position"]}}]