[{"job_id": "100003009054756", "location_code": "hk", "company": "Public Finance Limited", "job_title": "Senior Marketing Officer (Mortgage Loan Sales) ($20,000+ plus Commission)", "description": "Responsibilities\nTo achieve mortgage loan sales target\nTo establish good relationship with business partners such as solicitor firms, property agencies, referral intermediaries, etc\nRequirements\n3 years experience in mortgage loan sales\nHave developed a good people-network with brokers / Mortgage Referral Services Companies / Estate Agencies/Solicitor firms is an advantage\nApplications from the existing Estate Agencies are welcome\nWork in Central Office\n(Candidate who posses less experience may be considered as Marketing Officer)\nBenefits\nInsurance Benefits\nStudy subsidy\nApplication Method:\n\nBy Whatsapp : 9309 2925\nBy E-mail via \"Apply Now\"", "employment_types": ["Full Time", "Permanent"], "selling_points": [], "locations": ["Central"], "categories": ["Banking / Finance", "Loan", "Mortgage", "Sales, CS & Business Devpt", "Sales - Sales Management"], "post_time": "2022-01-17T10:55:46Z", "salary": {"currency": null, "max": null, "min": null, "period": "monthly", "term": null}, "salary_visible": false, "title_keywords": ["sales", "senior marketing officer"], "responsibilities": ["good relationship", "sales target"], "requirements": {"degrees": [], "majors": [], "languages": [], "language_level": [], "hard_skills": [], "soft_skills": [], "languages_combined": []}, "experience_required": {"duration": ["3 years"], "field": ["marketing"]}}, {"job_id": "100003009053124", "location_code": "hk", "company": "Konew Financial Express Ltd", "job_title": "Sales Executive (Branch) \u92b7\u552e\u5c08\u54e1 (\u5206\u884c)", "description": "Main Duties & Responsibilities:\n\nPromote all type of loan services to new and existing clients\nPromote loan refinance service to existing clients\nHandle customer\u2019s enquiries in professional manner and follow up loan applications\nCooperate with Service Ambassador to maintain daily branch operation\nCollect market information for product positioning\nPerform outside work when necessary\nSupport and act towards the Konew Group\u2019s vision\nBranch locations: Tai Po / Sham Shui Po / Kowloon Bay / Kwun Tong / Shau Kei Wan\nDuty hours: Monday to Friday ( 0900 - 1900 )\n\u8ca0\u8cac\u63a8\u5ee3\u53ca\u92b7\u552e\u5404\u985e\u578b\u8cb8\u6b3e\u670d\u52d9\uff0c\u4e26\u7a4d\u6975\u62d3\u5c55\u65b0\u5ba2\u6236\n\u8207\u5ba2\u6236\u5efa\u7acb\u826f\u597d\u95dc\u4fc2\uff0c\u4fdd\u6301\u7dca\u5bc6\u6e9d\u901a\n\u63d0\u4f9b\u512a\u8cea\u5ba2\u6236\u67e5\u8a62\u670d\u52d9\uff0c\u8655\u7406\u53ca\u8ddf\u9032\u6709\u95dc\u8cb8\u6b3e\u7533\u8acb\n\u5728\u9700\u8981\u6642\u57f7\u884c\u5916\u51fa\u5de5\u4f5c\n\u8207\u670d\u52d9\u5927\u4f7f\u5408\u4f5c\uff0c\u7dad\u6301\u5206\u884c\u65e5\u5e38\u904b\u4f5c\n\u70ba\u7522\u54c1\u5b9a\u4f4d\u6536\u96c6\u5e02\u5834\u4fe1\u606f\n\u79c9\u627f\u5eb7\u696d\u96c6\u5718\u6838\u5fc3\u50f9\u503c\u89c0\u53ca\u670d\u52d9\u7406\u5ff5\n\u4e0a\u73ed\u5730\u9ede\uff1a\u5927\u57d4 / \u6df1\u6c34\u57d7 / \u4e5d\u9f8d\u7063 / \u89c0\u5858 / \u7b72\u7b95\u7063\n\u4e0a\u73ed\u6642\u9593\uff1a\u661f\u671f\u4e00\u81f3\u4e94 ( 0900 - 1900\uff09\n\n\n\nRequirements:\n\nSecondary education (HKCEE/HKDSE), or above\n2 years\u2019 working experience in sales or customer service is highly preferred\nProficiency in both English and Chinese\nProactive and commit to the job\nExcellent communication, interpersonal and selling skills\nComplete on-the-job training\nImmediate available is highly preferred\nCandidate with less experience will also be considered as Sales Support role.\u00a0\nHKCEE / HKDSE \u7a0b\u5ea6\u6216\u4ee5\u4e0a\n\u5169\u5e74\u6216\u4ee5\u4e0a\u92b7\u552e\u7d93\u9a57\uff0c\u5177\u7269\u696d\u8cb8\u6b3e\u92b7\u552e\u7d93\u9a57\u8005\u512a\u5148\u8003\u616e\n\u64cd\u6d41\u5229\u5ee3\u6771\u8a71\u53ca\u826f\u597d\u82f1\u8a9e\n\u7a4d\u6975\u4e3b\u52d5\u3001\u6709\u8cac\u4efb\u611f\n\u5177\u826f\u597d\u7684\u8868\u9054\u80fd\u529b\u3001\u8aaa\u8a71\u6280\u5de7\u3001\u92b7\u552e\u53ca\u9867\u5ba2\u670d\u52d9\u6280\u5de7\n\u5165\u8077\u5f8c\u516c\u53f8\u5c07\u63d0\u4f9b\u5b8c\u5584\u7684\u5728\u8077\u57f9\u8a13\n\u80fd\u5373\u6642\u4e0a\u73ed\u8005\u5c07\u512a\u5148\u8003\u616e\n\u5de5\u4f5c\u7d93\u9a57\u8f03\u6dfa\u8005\u6216\u6703\u88ab\u8003\u616e\u8058\u4efb\u70ba\u92b7\u552e\u52a9\u7406\n\nWe offer:\n\n5-day Work Week\nPublic Holiday\nDiscretionary Year-end Performance Bonus\nMedical Insurance\nAttendance Bonus\nBirthday Leave\nAnniversary Leave\nStudy Leave\nOn-the-job Training\n\nHow to apply:\n\nInterested parties, please send your resume stating your expected salary to Human Capital Department\u00a0by clicking \"APPLY NOW\".\n\n(We are an equal opportunity employer.\u00a0 Personal data collected will be used for recruitment purpose only.\u00a0 The unsuccessful applications will be destroyed after 6 months.)\u00a0\n\nCandidate with less experience will be considered as Branch Assistant\u00a0\nCandidate with less experience will be considered as Branch Assistant\u00a0", "employment_types": ["Full Time"], "selling_points": ["2 years' sales/customer services exp.", "5-day Work Week (Mon-Fri), 0900 - 1900", "Immediate available is highly preferred"], "locations": ["Others"], "categories": ["Banking / Finance", "Loan", "Mortgage", "Sales, CS & Business Devpt", "Direct Sales"], "post_time": "2022-01-17T05:58:10Z", "salary": {"currency": null, "max": null, "min": null, "period": "monthly", "term": null}, "salary_visible": false, "title_keywords": ["sales executive"], "responsibilities": ["maintain", "professional manner", "cooperate with", "market information"], "requirements": {"degrees": ["hkdse", "secondary education"], "majors": [], "languages": ["english", "chinese"], "language_level": ["proficiency"], "hard_skills": ["sales support"], "soft_skills": ["communication", "customer service", "proactive", "interpersonal"], "languages_combined": [{"language": "english", "language_level": ["proficiency"]}, {"language": "chinese", "language_level": ["proficiency"]}]}, "experience_required": {"duration": ["2 years"], "field": ["customer service", "sales support"]}}, {"job_id": "100003009053103", "location_code": "hk", "company": "HY Credit Company Limited", "job_title": "Customer Service Representative / Customer Service Officer", "description": "Responsibilities:\n\nHandle customer enquiries and consumer loan applications.\nFollow up with existing customers on loan repayment and redemption.\nPromote loan products to new and existing customers.\nPerform administrative support to CS/Credit department (e.g. data input, document filing, scanning and reporting).\nPrepare Ad hoc reports as required\nMaintain good customer relationships to enhance business growth.\n\nRequirements:\n\nForm 5 graduate or above.\n1 - 2 years of CS or telemarketing experience, specialized in consumer loan/ mortgage/ finance business preferably.\nGood interpersonal and communication skills.\nPositive attitude and strong problem-solving skills.\nGood command of written and spoken English and Chinese.\nProficient in Microsoft Office applications, including Word, Excel, and Chinese Word Processing.\n\nCandidates with more experience shall be considered as Customer Service Officers.\n\nWe offer an attractive remuneration package including double pay and discretionary performance bonus. Interested parties, please submit your full resume with PRESENT and EXPECTED SALARY stated.\u00a0\n\nPersonal Data collected will be kept in strict confidence and will be used for recruitment purposes only.\u00a0 Applicants who are not invited for an interview within six weeks may consider their applications unsuccessful.\u00a0 All personal data from unsuccessful candidates will be destroyed after six months.\n\n\u00a0Company website: www.hyc.com.hk", "employment_types": ["Full Time", "Permanent"], "selling_points": ["Customer service, telemarketing experience", "Consumer loans, personal loans, mortgage loans", "Competitive Salary, Double Pay & Medical Insurance"], "locations": ["Wan Chai"], "categories": ["Banking / Finance", "Loan", "Mortgage", "Sales, CS & Business Devpt", "Tele-sales (Telemarketing)"], "post_time": "2022-01-17T05:51:40Z", "salary": {"currency": null, "max": null, "min": null, "period": "monthly", "term": null}, "salary_visible": false, "title_keywords": ["customer service officer", "customer service representative"], "responsibilities": ["scanning", "document filing", "reporting", "handle customer enquiries", "ad hoc", "administrative support", "data input", "maintain", "reports"], "requirements": {"degrees": ["form 5"], "majors": [], "languages": ["english", "chinese"], "language_level": ["good command", "proficient"], "hard_skills": ["excel", "chinese word processing", "microsoft office", "word", "problem-solving skills"], "soft_skills": ["communication skills", "positive attitude", "customer service", "problem-solving skills", "interpersonal"], "languages_combined": [{"language": "english", "language_level": ["good command"]}, {"language": "chinese", "language_level": ["good command", "proficient"]}]}, "experience_required": {"duration": ["1 - 2 years"], "field": ["consumer loan", "finance", "business", "customer service", "cs"]}}, {"job_id": "100003009049839", "location_code": "hk", "company": "Wang On Financial Services Management Limited", "job_title": "Mortgage \u2013 Business Development Manager", "description": "Job Description\n\nTo handle mortgage referral applications and enquiries;\nIdentify sales opportunities and develop new business in mortgage\nTo solicit and generate revenue growth on mortgage loan business through various sales activities;\nTo establish and develop a good business relationship with referral parties including mortgage intermediaries, property agencies, mortgage brokers, banks and other sales channels;\nTo achieve individual targets on mortgage lending;\nTo evaluate potential credit risk to ensure loan proceedings in compliance with procedural and documentation requirements;\n\n\nRequirements\n\nAt least 5 years\u2019 experience gained from local money lender companies in mortgage loan development business;\nGood track record in mortgage sales, with extensive network with mortgage intermediaries/agents/banks/property agencies;\nWith a strong potential client network is an advantage;\nGood communication, presentation and interpersonal skills;\nProactive, motivated, good market sense and sales-oriented;\nGood command of both spoken and written English and Chinese;\nImmediate available is highly preferred\n\nWe offer competitive remuneration package, our benefits include:\n\nPerformance bonus\nEducation subsidy\nProfessional membership fee sponsorship\nLife & medical insurance\nMarriage Leave, Compassionate Leave, Examination Leave etc.\nPublic holidays\nStaff purchase discount\n\nInterested parties please send full resume with present and expected salary to Human Resources Department by clicking\u00a0Apply Now.\n\n(Information provided will be treated in strict confidence and will only be used for recruitment-related purposes.)", "employment_types": ["Full Time", "Permanent"], "selling_points": [], "locations": ["Sheung Wan"], "categories": ["Banking / Finance", "Loan", "Mortgage"], "post_time": "2022-01-14T09:18:43Z", "salary": {"currency": null, "max": null, "min": null, "period": "monthly", "term": null}, "salary_visible": false, "title_keywords": ["business development manager"], "responsibilities": ["sales activities", "develop new business", "compliance", "develop", "evaluate", "revenue growth", "documentation"], "requirements": {"degrees": [], "majors": [], "languages": ["english", "chinese"], "language_level": ["good command"], "hard_skills": [], "soft_skills": ["communication", "motivated", "interpersonal skills", "proactive", "extensive", "presentation"], "languages_combined": [{"language": "english", "language_level": ["good command"]}, {"language": "chinese", "language_level": ["good command"]}]}, "experience_required": {"duration": ["at least 5 years"], "field": ["development", "business"]}}, {"job_id": "100003009049847", "location_code": "hk", "company": "Wang On Financial Services Management Limited", "job_title": "Business Development General Manager  - Mortgage Loan", "description": "Job Description\n\nThe General Manager will support revenue growth by working with the secured Loan team on specific strategies to grow the loan finance business. You will play a key role in business development and expand on agencies/ resellers/ direct clients, with the vision and able to give strategic advice and expand markets.\n\nResponsibilities:\n\n\nSolicitation and expansion of mortgage loan finance business for the Company;\nActively competes in the market to increase sales growth;\nResponse for the profit & loss of the mortgage department through better risk management throughout the whole mortgage operation process;\nDevelopment business relationship with agencies, consultants, legal firms, surveyors, etc.;\nExpand existing client relationships and build up different new clientele;\nDrive the Secured Loan Team to develop new business opportunities to achieve business objectives;\nResponsible for day-to-day client liaisons to understand the client\u2019s latest financial needs and credit standings;\nProvide consultation and analysis on clients\u2019 financial and business needs. Design tailor-made financial solution to clients;\nStructure the loan finance facilities and maintain a high quality of loan portfolio to exercise prudent credit assessment;\nManage daily business operations of the secured Loan Team in accordance with the Company's credit policies and guidelines;\nProvide direction on problem loan handling, loan recovery and loan restructuring process of the delinquent accounts;\nCollaborate with business partners including solicitors\u2019 firm, property agents, collection agents and internal departments and perform regular quality assurance checks on borrower, business partners and credit processes to assure execution in accordance with prevailing policy and control standards;\nTo prepare regular or ad hoc management reports regarding the lending portfolio and credit compliance\n\n\nRequirements:\n\n\nBachelor\u2019s degree in finance, accounting, business management or equivalent;\nAt least 15 years\u2019 solid experience in mortgage loan lending operation with at least 8 years in Money Lending Industrial;\nGood knowledge in real estate industry;\nGood people management skills, with solid experience in developing talents and achieving results through the team;\nGood business connections with proven track record of success in growing a portfolio and in acquiring new businesses;\nSound credit and business experience in secured lending business and relevant clients / industrial network;\nExcellent communication and interpersonal skills;\nDetail-oriented and strong in risk management;\nSelf-motived, detail-minded, independent and service centric;\nProficient in both English and Chinese, written and verbal, including Putonghua\n\nWe offer competitive remuneration package, our benefits include:\n\nPerformance bonus\nEducation subsidy\nProfessional membership fee sponsorship\nLife & medical insurance\nMarriage Leave, Compassionate Leave, Examination Leave etc.\nPublic holidays\nStaff purchase discount\n\nInterested parties please send full resume with present and expected salary to Human Resources Department by clicking\u00a0Apply Now.\n\n(Information provided will be treated in strict confidence and will only be used for recruitment-related purposes.)", "employment_types": ["Full Time", "Permanent"], "selling_points": [], "locations": ["Sheung Wan"], "categories": ["Banking / Finance", "Loan", "Mortgage"], "post_time": "2022-01-14T09:19:02Z", "salary": {"currency": null, "max": null, "min": null, "period": "monthly", "term": null}, "salary_visible": false, "title_keywords": ["general manager"], "responsibilities": ["collaborate with", "management", "develop new business", "control", "ad hoc", "provide direction", "guidelines", "operations", "analysis", "policies", "quality", "compliance", "design", "management reports", "maintain", "revenue growth"], "requirements": {"degrees": ["degree", "bachelor"], "majors": ["business", "finance", "accounting"], "languages": ["putonghua", "english", "chinese"], "language_level": ["proficient"], "hard_skills": ["business management"], "soft_skills": ["detail-minded", "communication and interpersonal skills", "independent", "detail-oriented"], "languages_combined": [{"language": "putonghua", "language_level": []}, {"language": "english", "language_level": ["proficient"]}, {"language": "chinese", "language_level": ["proficient"]}]}, "experience_required": {"duration": ["at least 8 years", "at least 15 years"], "field": ["developing", "people management", "business", "operation", "team"]}}, {"job_id": "100003009053188", "location_code": "hk", "company": "Konew Financial Express Limited \u5eb7\u696d\u4fe1\u8cb8\u5feb\u905e", "job_title": "Officer, Credit Approval", "description": "Main Duties & Responsibilities:\n\nConduct credit approvals on all applications including property loans, personal loans and SME loans in accordance with authority\nAssist to ensure that credit activities are conducted in accordance with requirements as stipulated in the credit policies\nEnsure appropriate infrastructure, resources and systems are in place for credit risk management\nCollaborate with Sales Department for the criteria of credit approval\nReview and prepare various reports of credit risk management\n\nRequirements:\n\nBachelor Degree in Risk Management, Mathematics, Economics or related discipline\nAt least 1\u00a0year relevant working experience\nExcellent analytical, communication and interpersonal skills\nIndependent, proactive, detail-oriented and able to work under pressure\nCandidates with more experience will be considered as\u00a0Senior Officer\n\nWe offer:\n\nDiscretionary bonus\nMedical insurance\nDental insurance\nHardship allowance\nCompetitive annual leave days\nBirthday leave\nAnniversary leave\nStudy leave\nMarriage leave\nCompassionate leave\n\nHow to apply:\n\nInterested parties, please send your resume stating your expected salary to Human Capital Department\u00a0by clicking \"APPLY NOW\".\n\n(We are an equal opportunity employer.\u00a0 Personal data collected will be used for recruitment purpose only.\u00a0 The unsuccessful applications will be destroyed after 6 months.)\u00a0", "employment_types": ["Full Time", "Permanent"], "selling_points": ["Conduct credit approvals on all loan applications", "Collaborate for the criteria of credit approval", "5 days work, birthday leave, anniversary leave"], "locations": ["Central"], "categories": ["Banking / Finance", "Credit Analysis / Approval", "Loan", "Mortgage"], "post_time": "2022-01-17T06:22:00Z", "salary": {"currency": null, "max": null, "min": null, "period": "monthly", "term": null}, "salary_visible": false, "title_keywords": ["officer"], "responsibilities": ["collaborate with", "management", "policies", "infrastructure", "systems", "review", "reports", "sme"], "requirements": {"degrees": ["degree", "bachelor"], "majors": ["risk management", "economics", "mathematics"], "languages": [], "language_level": [], "hard_skills": [], "soft_skills": ["independent", "detail-oriented", "communication and interpersonal skills", "proactive", "work under pressure"], "languages_combined": []}, "experience_required": {"duration": ["at least 1 year"], "field": ["relevant working experience"]}}, {"job_id": "100003009045344", "location_code": "hk", "company": "PC Securities Financial Group Limited", "job_title": "Mortgage Sales Manager", "description": "Job description\nGenerate\u00a0revenue growth on mortgage loan business through various sales activities\nEstablish\u00a0and develop a good business relationship with referral parties including mortgage intermediaries, property agencies, mortgage brokers, banks and other sales channels\nOversee\u00a0the end to end mortgage process and ensure a smooth application cycle\nProvide\u00a0quality customer services to clients on all mortgage-related matters\n\nRequirements\n\n\nAt\u00a0\u00a0least 3 years\u2019 experience in mortgage loan development business gained from local money lender companies\nGood\u00a0track record in mortgage sales, with extensive network with agents/banks/property agencies\nWith a\u00a0strong potential client network is an advantage\nGood\u00a0communication, presentation and interpersonal skills\nMotivated,\u00a0good market sense and sales-oriented\nGood\u00a0command of both spoken and written English and Chinese, including Mandarin\nAttractive salary and fringe benefits package will be provided to the right candidate. Please send a full resume with contact number and expected salary by clicking 'Apply Now'.\nData collected will be kept confidential and will be used for recruitment purposes only.", "employment_types": ["Full Time", "Permanent"], "selling_points": ["Focus on mortgage loan business development", "Stable financial firm across APAC", "Good commission scheme"], "locations": ["Causeway Bay"], "categories": ["Banking / Finance", "Loan", "Mortgage", "Sales, CS & Business Devpt", "Business Development"], "post_time": "2022-01-13T07:39:30Z", "salary": {"currency": null, "max": null, "min": null, "period": "monthly", "term": null}, "salary_visible": false, "title_keywords": ["sales manager"], "responsibilities": ["sales activities", "quality", "customer services", "develop", "revenue growth"], "requirements": {"degrees": [], "majors": [], "languages": ["english", "chinese", "mandarin"], "language_level": ["good command"], "hard_skills": [], "soft_skills": ["communication", "motivated", "interpersonal skills", "extensive", "presentation"], "languages_combined": [{"language": "english", "language_level": ["good command"]}, {"language": "chinese", "language_level": ["good command"]}, {"language": "mandarin", "language_level": ["good command"]}]}, "experience_required": {"duration": ["least 3 years"], "field": ["development", "business"]}}, {"job_id": "100003009044044", "location_code": "hk", "company": "Sun Hung Kai Credit Limited", "job_title": "Direct Sales - Mortgage Business", "description": "Responsibilities\n\nPlan and implement mortgage product marketing strategies\nAchieve individual and team targets on mortgage lending\nCultivate and maintain business relationships with customers\nDrive mortgage business and generate revenue from network through various sales activities\nPersonal sales and marketing duties to achieve target on mortgage loan business\nReview mortgage loan applications and monitor overdraft accounts\nHandle incoming customer enquiries\n\n\u00a0Requirements\n\nDegree holder or above\nMinimum 3 to 5 years of relevant experience in finance, banking or property industry with a focus in mortgage loan business\nStrong potential client network\nStrong communications and leadership skills\nAggressive, proactive with an outgoing personality\nProficient in Microsoft Office and Chinese word processing\nGood command of spoken and written Chinese, Putonghua & English\n\n\u00a0We offer a competitive remuneration package to the right candidate.\u00a0\n\nPlease send your resume with present and expected salaries to Human Resources Department at by email.\n\nPlease visit\u00a0www.shkcredit.com.hk for more information about us.\u00a0\n\n\n\nDisclaimer / Policy Statements\n\nWe are an Equal Opportunity Employer and welcome applications from all qualified candidates. We evaluate qualified applicants without regards to gender, race, colour, nationality, religion, sexual orientation or disability and other status protected by law. We respect and seek to empower each individual and support diverse cultures, perspectives, skills and experience within our workforce to foster an inclusive work environment.\n\nAll applications will be treated in the strictest confidence. Personal data provided will be used for recruitment purposes only.", "employment_types": ["Full Time", "Permanent"], "selling_points": ["First Mortgage Loan and Second Mortgage Loan", "Mortgage loan business", "Mortgage lending"], "locations": ["Wan Chai"], "categories": ["Banking / Finance", "Loan", "Mortgage"], "post_time": "2022-01-13T02:54:03Z", "salary": {"currency": null, "max": null, "min": null, "period": "monthly", "term": null}, "salary_visible": false, "title_keywords": ["sales"], "responsibilities": ["sales activities", "marketing strategies", "customer enquiries", "review", "monitor", "maintain", "plan"], "requirements": {"degrees": ["degree holder"], "majors": [], "languages": ["putonghua", "english", "chinese"], "language_level": ["good command", "proficient"], "hard_skills": ["focus", "chinese word processing", "microsoft office"], "soft_skills": ["outgoing personality", "focus", "leadership skills", "proactive"], "languages_combined": [{"language": "putonghua", "language_level": ["good command"]}, {"language": "english", "language_level": ["good command"]}, {"language": "chinese", "language_level": ["good command", "proficient"]}]}, "experience_required": {"duration": ["minimum 3 to 5 years"], "field": ["loan business", "finance", "relevant experience", "banking"]}}, {"job_id": "100003009050265", "location_code": "hk", "company": "China Construction Bank (Asia) Corporation Limited", "job_title": "Branch Sales Executive, Small Enterprise and Personal Loan Centre", "description": "Job Description:\n\nProactively solicit loan sales of unsecured personal loan and mortgage loan to customers, cross sell banking products including insurance and investment business and achieve designated sales objectives\nManage sales activities and performance, reach centre\u2019s agreed goals\nDemonstrate high quality services, establish, retain and build up customer relationships for contributing business and customer referrals\nPropose a tailored loan planning for customers according to their needs, handle customer\u2019s enquiries/complaints, resolves issues and follow up with customer\u2019s loan application to drawdown\nConduct outbound calls and perform outdoor marketing activities i.e. site promotion\nEnsure Centre\u2019s work procedures are in compliance with Bank\u2019s policies and guidelines and comply with the regulatory requirements\n\nRequirements:\n\n\u00a0\u00a0\u00a0\u00a0\u00a0\u00a0\u00a0\u00a0 Higher Diploma / DSE graduate or above\n\u00a0\u00a0\u00a0\u00a0\u00a0\u00a0\u00a0\u00a0 Minimum one year of experience as a sales role in related industry\n\u00a0\u00a0\u00a0\u00a0\u00a0\u00a0\u00a0\u00a0 Knowledge of loan products\n\u00a0\u00a0\u00a0\u00a0\u00a0\u00a0\u00a0\u00a0 Qualifications in IIQE/HKSI areas are preferred\n\u00a0 \u00a0 \u00a0 \u00a0 \u00a0Strong team player, aggressive and self-motivated with positive attitude\n\u00a0 \u00a0 \u00a0 \u00a0 \u00a0Excellent interpersonal skills and customer oriented. Good communication skills\u00a0 \u00a0 \u00a0 \u00a0 \u00a0 \u00a0in English, Cantonese and Mandarin\n\nApplicants who are not contacted within 8 weeks may consider their applications unsuccessful and their personal data will be retained by the bank for a period up to two years.\n\nAll information provided by applicants will be used for recruitment purposes only and will be used strictly in accordance with the bank\u2019s personal data policies, a copy of which will be provided upon request.", "employment_types": ["Full Time", "Permanent"], "selling_points": ["solicit loan sales of UPL and mortgage", "Manage sales activities and performance", "Demonstrate high quality services"], "locations": ["Not Specified"], "categories": ["Banking / Finance", "Loan", "Mortgage", "Retail Banking"], "post_time": "2022-01-14T10:03:17Z", "salary": {"currency": null, "max": null, "min": null, "period": "monthly", "term": null}, "salary_visible": false, "title_keywords": ["personal", "sales executive"], "responsibilities": ["sales activities", "bank\u2019s policies", "guidelines", "regulatory requirements", "compliance", "quality", "procedures", "banking", "insurance", "planning"], "requirements": {"degrees": ["diploma", "dse"], "majors": [], "languages": ["cantonese", "english", "mandarin"], "language_level": ["good"], "hard_skills": ["loan products", "iiqe", "hksi"], "soft_skills": ["communication skills", "self-motivated", "positive attitude", "interpersonal skills", "team player"], "languages_combined": [{"language": "cantonese", "language_level": ["good"]}, {"language": "english", "language_level": ["good"]}, {"language": "mandarin", "language_level": ["good"]}]}, "experience_required": {"duration": ["minimum one year"], "field": ["related"]}}, {"job_id": "100003009048086", "location_code": "hk", "company": "Hong Kong Credit Corporation Limited", "job_title": "Officer, Lending", "description": "As a maker role to develop loan applications by evaluating applicant information and documentation\n\nResponsibilities:\u00a0\n\nEvaluate and verify the loan applications and documentation by confirming credit worthiness\nAnalyze and determine the feasibility of granting loans\nEnsure the accuracy of data input and documentary preparation\nEnsure fully comply with both internal and external regulatory compliance requirements\nConduct a final review of the file before closing\nProvide administrative and operational support on business\nPerform other duties as assigned\n\nRequirements:\n\nF5/DSE or above graduate\nPossess accurate and efficient data entry and reporting skills\nGood analytical skills and good in details\nGood communication skills with good command of written and spoken English and Cantonese.\u00a0 Mandarin an added advantage\nProficiency in MS windows applications\nWilling to take initiative in improving work process and service delivery\nWork exposure in credit approval of consumer loans an advantage\nWe offer competitive remuneration including career prospects to the right candidate. Interested parties please send detailed resume with availability, current and expected salaries to\u00a0Human Resources Department, Hong Kong Credit Corporation Limited, Trust Tower, 68 Johnston Road, Wan Chai, Hong Kong\u00a0or by clicking the\u00a0Apply Now\u00a0button and upload your CV and cover letter.\n(All applications will be treated in strict confidence and used for recruitment purpose within\u00a0Hong Kong Credit Corporation Limited only. All applicants are kept on file 6 months from the date of the application.)", "employment_types": ["Full Time", "Permanent"], "selling_points": ["Evaluate and verify the loan applications", "Analyze the feasibility of granting loans", "Ensure the accuracy of data input"], "locations": ["Wan Chai"], "categories": ["Banking / Finance", "Loan", "Mortgage", "Sales, CS & Business Devpt", "Account Servicing"], "post_time": "2022-01-14T04:45:24Z", "salary": {"currency": null, "max": null, "min": null, "period": "monthly", "term": null}, "salary_visible": false, "title_keywords": ["officer"], "responsibilities": ["perform other duties", "operational support", "compliance", "review", "data input", "evaluate", "documentation"], "requirements": {"degrees": ["dse"], "majors": [], "languages": ["cantonese", "english", "mandarin"], "language_level": ["advantage", "good command", "good"], "hard_skills": ["ms windows", "analytical skills"], "soft_skills": ["efficient", "communication skills", "analytical skills", "accurate", "initiative"], "languages_combined": [{"language": "cantonese", "language_level": ["good command", "good"]}, {"language": "english", "language_level": ["good command", "good"]}, {"language": "mandarin", "language_level": ["advantage"]}]}, "experience_required": {"duration": [], "field": []}}, {"job_id": "100003009050689", "location_code": "hk", "company": "Bank of Communications (Hong Kong) Limited", "job_title": "Mortgage Sales Manager", "description": "To achieve mortgage sales targets by establishing good relationship with business partners such as property agencies\nDegree holder or above, with minimum 3 years\u2019 experience in generating mortgage lending business in banking industries\nPasses in MPF, Insurance and Securities Intermediaries Examinations (Qualified under SFO for handling Regulated Activities Type 1 & 4)\nCandidates with less experience will be considered as Deputy Mortgage Sales Manager\n\u00a0\n\nWe offer attractive remuneration package to the right candidates. Please send your full resume with expected salary to\u00a0The Human Resources Manager, Bank of Communications Co., Ltd., 10/F, Bank of\u00a0Communications\u00a0Tower,\u00a0231-235 Gloucester Road, Wan Chai,\u00a0Hong Kong, or fax to\u00a02838 9209, or e-mail to : APPLY NOW.", "employment_types": ["Full Time"], "selling_points": ["Degree holder or above", "minimum 3 years\u2019 experience in generating mortgage", "Passes in MPF, Insurance Examinations"], "locations": ["Wan Chai"], "categories": ["Banking / Finance", "Loan", "Mortgage", "Others"], "post_time": "2022-01-14T11:10:47Z", "salary": {"currency": null, "max": null, "min": null, "period": "monthly", "term": null}, "salary_visible": false, "title_keywords": ["sales manager"], "responsibilities": ["good relationship", "insurance", "mpf", "banking"], "requirements": {"degrees": ["degree holder"], "majors": ["business"], "languages": [], "language_level": [], "hard_skills": ["sfo"], "soft_skills": [], "languages_combined": []}, "experience_required": {"duration": ["minimum 3 years"], "field": ["business", "banking"]}}, {"job_id": "100003009046096", "location_code": "hk", "company": "Zero Finance Hong Kong Limited", "job_title": "Senior Credit Officer / Assistant Manager - Mortgage Loan", "description": "In this role, you will perform:\n\nResponsible for proactively follow up with related parties\nExecute properties appraisal on the new mortgage loans and refinance applications\nMaintain close relationship with agency and solicitors\u2019 firms\nEnsure the correctness of loan contracts before corporate approval\nImplement business plan to achieve sales targets\n\nTo be successful in this role, you should meet the following requirements:\u00a0\n\nTertiary education or above, finance or other business related disciplines are preferred\nPreferably 5 years relevant experience in Money Lending Industry\nGood command of spoken & written English, Cantonese and Mandarin\nStrong adaptability and flexibility\nProficient in MS Word, MS Excel and Chinese Word Processing\nLess experience will be considered as Senior Officer\n\nCompany Website: https://www.zerofinance.hk/zh/\u00a0\n\nAttractive remuneration package will be offered to the right candidate. Please apply with full resume stating present and expected salary to us by\u00a0clicking \u201cAPPLY NOW\u201d.\n\n(Personal data collected will be used for recruitment purpose only.)", "employment_types": ["Full Time", "Permanent"], "selling_points": ["Mortgage loans operation", "Credit administration", "5 days work, bank holidays"], "locations": ["Sheung Wan"], "categories": ["Banking / Finance", "Credit Analysis / Approval", "Loan", "Mortgage"], "post_time": "2022-01-13T09:36:31Z", "salary": {"currency": null, "max": null, "min": null, "period": "monthly", "term": null}, "salary_visible": false, "title_keywords": ["officer", "assistant manager"], "responsibilities": ["contracts", "maintain", "recruitment", "business plan", "personal data", "company website"], "requirements": {"degrees": [], "majors": [], "languages": ["cantonese", "english", "chinese", "mandarin"], "language_level": ["good command", "proficient"], "hard_skills": ["ms excel", "chinese word processing", "ms word"], "soft_skills": ["adaptability", "responsible"], "languages_combined": [{"language": "cantonese", "language_level": ["good command"]}, {"language": "english", "language_level": ["good command"]}, {"language": "chinese", "language_level": ["proficient"]}, {"language": "mandarin", "language_level": ["good command"]}]}, "experience_required": {"duration": ["5 years"], "field": ["relevant experience"]}}, {"job_id": "100003009047784", "location_code": "hk", "company": "Public Bank (Hong Kong) Limited", "job_title": "Credit Administration Clerk (Ref: JD-CAC)", "description": "Prepare and review loan documents for commercial banking facilities\nLiaise with marketing units to ensure proper and efficient operations of credit administration\u00a0work\nSecondary education with minimum 2 years of credit administration experience\nCandidate with conveyancing experience in legal firm will also be considered\nGood interpersonal and communication skills in both English and Chinese\nHands-on experience in MS Office applications\n\nTo apply, interested parties please follow the application methods available in the Bank\u2019s career website https://www.publicbank.com.hk/en/aboutus/careeropportunities. You can send us your resume quoting our job reference number together with present & expected salary (a must) to the Human Resources Department by email or fax at 2815 3157 or by post to Human Resources Department, 12/F, Public Bank Centre, 120 Des Voeux Road Central, Hong Kong. You may also visit our career website for other career opportunities available within our Group.\n\nPersonal data collected will be used for recruitment purpose only and will be treated in accordance with the Bank\u2019s Personal Information Collection Statement, a copy of which has been available in the Bank\u2019s career website.\u00a0", "employment_types": ["Full Time", "Permanent"], "selling_points": [], "locations": ["Not Specified"], "categories": ["Banking / Finance", "Loan", "Mortgage", "Others"], "post_time": "2022-01-15T03:49:09Z", "salary": {"currency": null, "max": null, "min": null, "period": null, "term": null}, "salary_visible": false, "title_keywords": ["clerk"], "responsibilities": ["operations", "review", "communication", "banking", "liaise with", "administration"], "requirements": {"degrees": ["secondary education"], "majors": [], "languages": ["english", "chinese"], "language_level": ["good"], "hard_skills": ["ms office"], "soft_skills": ["efficient", "communication skills", "hands-on", "interpersonal"], "languages_combined": [{"language": "english", "language_level": ["good"]}, {"language": "chinese", "language_level": ["good"]}]}, "experience_required": {"duration": ["minimum 2 years"], "field": ["administration", "legal", "education"]}}, {"job_id": "100003009047315", "location_code": "hk", "company": "The Hong Kong Mortgage Corporation Limited", "job_title": "Senior Manager (Customer Engagement)", "description": "Responsibilities:\nTo assist the promotion of HKMC products including \u2018HKMC Retire 3\u2019 and take care of customer accounts;\nTo support the formulation and implementation of sales strategies and monitor business performance;\nTo support business acquisition activities and manage the end-to-end sales cycle in accordance with prevailing policies and procedures;\nTo keep abreast of market trends and changes to the regulatory environment of retirement products; and\nThis is a contract position for 3 years and subject to renewal.\nRequirements:\nDegree holder or above, preferably in Business Administration, Marketing, Finance or related discipline;\nA minimum of 8 years\u2019 solid experience in customer engagement or sales management.\u00a0 Experience in sales roles in banking or insurance sectors is preferred;\nIn-depth knowledge of mortgage/secured loan/insurance products with analytical mind and business acumen.\u00a0 Recognised professional insurance qualification is an advantage;\nCustomer-centric and result oriented;\nExcellent presentation, problem-solving and interpersonal skills;\nProficient in MS Excel, Word and PowerPoint; and\nGood command in written and spoken English and Chinese (including Putonghua).\nCandidates with lesser experience may be considered for the post of Manager (Customer Engagement).\n\n\n\nInterested parties please send your full resume stating current and expected salary by \u00a027 January 2022.\n\nPlease visit http://www.hkmc.com.hk/eng/careers/job_openings.html for other application methods.\n\nPlease ensure that all information provided to the HKMC Group is accurate, complete and updated. Data provided which is inaccurate or incomplete may influence the process and outcome of the recruitment exercise. Please read the HKMC Group Personal Information Collection Statement for Job Applicants at the HKMC website before completing the application form. Personal data collected will be used for recruitment purposes only. Candidates not invited for interview within 8 weeks may consider their application unsuccessful.\n\n\n", "employment_types": ["Full Time"], "selling_points": [], "locations": ["Kwun Tong"], "categories": ["Banking / Finance", "Mortgage", "Sales, CS & Business Devpt", "Sales - Sales Management", "Wealth Management"], "post_time": "2022-01-14T06:25:18Z", "salary": {"currency": null, "max": null, "min": null, "period": "monthly", "term": null}, "salary_visible": false, "title_keywords": ["senior manager"], "responsibilities": ["policies", "monitor", "implementation", "procedures"], "requirements": {"degrees": ["degree holder"], "majors": ["finance", "marketing", "business administration"], "languages": ["putonghua", "english", "chinese"], "language_level": ["good command"], "hard_skills": ["problem-solving", "word", "powerpoint", "ms excel", "acumen"], "soft_skills": ["problem-solving", "result oriented", "analytical mind", "interpersonal skills", "business acumen", "presentation"], "languages_combined": [{"language": "putonghua", "language_level": ["good command"]}, {"language": "english", "language_level": ["good command"]}, {"language": "chinese", "language_level": ["good command"]}]}, "experience_required": {"duration": ["minimum of 8 years"], "field": ["management", "insurance", "banking"]}}, {"job_id": "100003009043504", "location_code": "hk", "company": "International Underwriting Limited", "job_title": "Loan officer, first lien property mortgages", "description": "The health and safety of our employees and candidates is very important to us. Due to the current situation related to the Novel Coronavirus (2019-nCoV), we\u2019re leveraging our digital capabilities to ensure we can continue to recruit top talent at HSBC. \u00a0As your application progresses, you may be asked to use one of our digital tools to help you through your recruitment journey.\u00a0\u00a0If so, one of our Resourcing colleagues will explain how our video-interviewing technology will be used throughout the recruitment process and will be on hand to answer any questions you might have.\n\nSome careers have more impact than others.\n\nIf you\u2019re looking for a career where you can make a real impression, join HSBC and discover how valued you\u2019ll be. Whether you want a career that could take you to the top, or simply take you in an exciting new direction, HSBC offers opportunities, support and rewards that will take you further.\n\nSales, Distribution and Business Development plays a vital role in understanding and meeting customer needs by offering the right solutions through the right channels to the right customer segments.\u00a0 The team is responsible for implementing distribution strategy, driving the delivery of market leading personal banking customer experiences and thereby maximising customer satisfaction.\n\nWe are currently seeking a high calibre professional to join our team as a Senior Mortgage Specialist II.\n\nPrincipal Responsibilities\n\nLead a team of mortgage specialists to deliver geographic market growth, share and penetration\nStay on top of market intelligence and changes and make feedback to management to ensure the competitiveness of our products and services\nTo establish good rapport and relationship with customers, assisting customers on selecting mortgage and general insurance products\nOffer professional property financing advice, recommendation and services to customers referred by various business sources to acquire and secure mortgage application\nTo act as mentor for junior mortgage specialists by providing coaching and support to them\n\nRequirements\n\nUniversity degree with prior mortgage related working experiences at a financial institution or at a brokerage firm with general insurance license\nExtensive Knowledge in Mortgage products with proven experience, preferably with team leading exposure\nIndependent contributor with collaborative approach who work well with staff from frontline and internal department\nOutgoing and positive with strong relationship building and agency networking\nGood command of Cantonese and English. Mandarin is advantageous\nCandidates with less mortgage experience will be considered for a Senior Mortgage Specialist I role\n\nYou\u2019ll achieve more when you join HSBC.\u00a0\nhttp://www.hsbc.com/careers\n\nHSBC is committed to building a culture where all employees are valued, respected and opinions count. We take pride in providing a workplace that fosters continuous professional development, flexible working and opportunities to grow within an inclusive and diverse environment. Personal data held by the Bank relating to employment applications will be used in accordance with our Privacy Statement, which is available on our website.\n\nIssued by The Hongkong and Shanghai Banking Corporation Limited.", "employment_types": ["Full Time", "Permanent"], "selling_points": [], "locations": ["Sheung Wan"], "categories": ["Banking / Finance", "Mortgage"], "post_time": "2022-01-12T15:52:50Z", "salary": {"currency": null, "max": null, "min": null, "period": "monthly", "term": null}, "salary_visible": false, "title_keywords": ["officer"], "responsibilities": ["lead a team", "management", "insurance"], "requirements": {"degrees": ["university degree"], "majors": ["insurance"], "languages": ["cantonese", "english", "mandarin"], "language_level": ["good command"], "hard_skills": [], "soft_skills": ["outgoing", "flexible", "independent", "collaborative", "committed", "diverse", "extensive", "positive"], "languages_combined": [{"language": "cantonese", "language_level": ["good command"]}, {"language": "english", "language_level": ["good command"]}, {"language": "mandarin", "language_level": []}]}, "experience_required": {"duration": [], "field": ["general insurance", "financial", "related", "brokerage", "team"]}}, {"job_id": "100003009044834", "location_code": "hk", "company": "HSBC Group", "job_title": "Senior Mortgage Specialist II - Wealth & Personal Banking", "description": "Job Responsibilities\n\nPerform credit risk assessment and approval function for retail lending products with focus on mortgage loans\nRecommend credit policy guidelines / workflow simplification to achieve operational efficiency\nEnsure the compliance of regulatory requirement as well as credit policy guidelines in credit assessment\nWork with business departments and front line sales staff in solving issues arising from mortgage loan applications and able to put up with workable recommendation / solutions Support user acceptance test on Loan Application Processing System\nParticipate in ad hoc projects as required\nJob Requirements\n\nUniversity graduate with major in Business Administration, Finance or related disciplines\nAt least 5 years of solid experience in assessing and under-writing mortgage loan applications covering residential and commercial properties in a bank or mortgage under-writing agency\nFamiliar with the end to end mortgage loan application process, mortgage loan under-writing / process platform\nThorough knowledge, understanding and application of mortgage loan credit policy and regulatory requirements\nGood product knowledge and risk exposure in retail banking\nAble to deal with front line sales staff in resolving issues arising from the loan applications and providing workable solutions\nA team player but able to work independently with minimal supervision\nGood communication and interpersonal skills\nProficiency in PC software operations such as MS Office\nGood command in both spoken & written English and Chinese\nInterested\u00a0parties,\u00a0please\u00a0click\u00a0\"Apply\u00a0Now\"\u00a0for\u00a0application.\nPersonal\u00a0data\u00a0collected\u00a0will\u00a0be\u00a0used\u00a0for\u00a0recruitment\u00a0purpose\u00a0only.", "employment_types": ["Full Time"], "selling_points": ["Excellent Career Progression", "Excellent Opportunity for Seasoned professionals", "Sales opportunity"], "locations": ["Central"], "categories": ["Banking / Finance", "Loan", "Mortgage"], "post_time": "2022-01-13T06:26:43Z", "salary": {"currency": null, "max": null, "min": null, "period": "monthly", "term": null}, "salary_visible": false, "title_keywords": ["senior mortgage specialist", "personal"], "responsibilities": ["guidelines", "ad hoc projects", "compliance of regulatory"], "requirements": {"degrees": ["university graduate"], "majors": ["related disciplines", "finance", "business administration"], "languages": ["english", "chinese"], "language_level": ["good command"], "hard_skills": ["pc", "ms office"], "soft_skills": ["team player", "communication and interpersonal skills", "thorough", "work independently"], "languages_combined": [{"language": "english", "language_level": ["good command"]}, {"language": "chinese", "language_level": ["good command"]}]}, "experience_required": {"duration": ["at least 5 years"], "field": ["agency", "commercial", "writing"]}}, {"job_id": "100003009042885", "location_code": "hk", "company": "Industrial and Commercial Bank of China (Asia) Limited", "job_title": "Deputy Manager to Senior Manager, Mortgage Credit (Ref: CAD-MC-752)", "description": "Our company is setting up a new licensed money lender unit focusing on first lien residential mortgages in Hong Kong. We are looking for an experienced loan officer to independently manage loan applications. Our ideal candidate should:\n\n\nAt least 5 years+ experience in independently managing mortgage applications\nFamiliar with loan application and management process for money lenders\nLiaise with stakeholders including registered intermediaries, solicitors and internal colleagues\nVery familiar with Hong Kong residential mortgage process\nIndependently assess case and present to risk officer and ultimately to directors for approval\nFluent in English and Chinese\u00a0\nEducational background in accounting and bookkeeping a plus\nWe are an equal opportunity employer and offer flexible hours and benefits including health insurance. We are located in the Central and Western District. Some part-time work-from-home arrangements may be available.", "employment_types": ["Full Time", "Permanent"], "selling_points": [], "locations": ["Kwun Tong"], "categories": ["Banking / Finance", "Credit Analysis / Approval", "Mortgage", "Retail Banking"], "post_time": "2022-01-12T09:07:15Z", "salary": {"currency": null, "max": null, "min": null, "period": null, "term": null}, "salary_visible": false, "title_keywords": ["senior manager", "deputy manager"], "responsibilities": ["liaise with", "management"], "requirements": {"degrees": [], "majors": [], "languages": ["english", "chinese"], "language_level": ["fluent"], "hard_skills": ["plus"], "soft_skills": ["independently", "ideal"], "languages_combined": [{"language": "english", "language_level": ["fluent"]}, {"language": "chinese", "language_level": ["fluent"]}]}, "experience_required": {"duration": [], "field": []}}, {"job_id": "100003009043301", "location_code": "hk", "company": "Conners Consulting Limited", "job_title": "Mortgage Sales  (Listed Bank Group)", "description": "Our client, a well-known bank in Hong Kong, is looking for a high caliber to join the group.\n\nResponsibilities\n\nProvide professional mortgage advice and product support to sophisticated high net worth\u00a0customers\nManage loan applications from customers to finance property purchases\u00a0\nSupport agency sales channels with product and process expertise\nTo participate in product development and enhancement of lending products\nPrepare presentations and marketing materials\nAssisting in preparation of administration reports\nWork as a team and assist in implementing marketing activities to meet team goals\n\nRequirements\n\nSecondary education or above. Degree holder is preferred.\nMinimum 2 years mortgage sales & service experience\nGood knowledge of mortgage products.\nGood command written and spoken English and Chinese (including Putonghua)\n\nTo apply, please send your detailed resume or contact Mr Choi 2851 7761 for a confidential discussion.\n\nOnly shortlisted candidates will be notified.\n\nAll data collected will be used for recruitment purpose only & will be used strictly confidential.\n\n\nConners Consulting Limited\n\n2005 Kai Tak Commercial Building 317 Des Voeux Road Central Hong Kong\n\nTel: (852) 3996 8090\u00a0\u00a0\u00a0\u00a0\u00a0\u00a0 Website: www.connersconsulting.com", "employment_types": ["Full Time", "Permanent"], "selling_points": ["Mortgage Sales", "Finance Company", "Attractive Package, Urgent, 5 days work"], "locations": ["Sheung Wan"], "categories": ["Banking / Finance", "Mortgage", "Property / Real Estate", "Property Consultancy", "Property Management"], "post_time": "2022-01-12T10:35:36Z", "salary": {"currency": null, "max": null, "min": null, "period": "monthly", "term": null}, "salary_visible": false, "title_keywords": ["sales"], "responsibilities": ["marketing materials", "reports", "presentations", "administration"], "requirements": {"degrees": ["secondary education", "degree holder"], "majors": [], "languages": ["putonghua", "english", "chinese"], "language_level": ["good command"], "hard_skills": [], "soft_skills": ["detailed"], "languages_combined": [{"language": "putonghua", "language_level": ["good command"]}, {"language": "english", "language_level": ["good command"]}, {"language": "chinese", "language_level": ["good command"]}]}, "experience_required": {"duration": ["minimum 2 years"], "field": []}}, {"job_id": "100003009047322", "location_code": "hk", "company": "The Hong Kong Mortgage Corporation Limited", "job_title": "Senior Manager (Channel Development)", "description": "Responsibilities:\nTo expand existing distribution channels and devise effective B2B business collaboration platforms with channel partners for HKMC products including \u2018HKMC Retire 3\u2019;\nTo collaborate and monitor business activities of channel partners and their intermediaries to improve business performance;\nTo devise and implement an effective operational framework and workflows to work with channel partners;\nTo develop training plans for channel partners;\nTo keep abreast of market trends and changes to the regulatory environment of retirement products; and\nThis is a contract position for 3 years and subject to renewal.\nRequirements:\nDegree holder or above, preferably in Business Administration, Marketing, Finance or related discipline;\nA minimum of 8 years\u2019 solid experience in channel management, preferably in the financial sector; \u00a0\nIn-depth knowledge of financial products with analytical mind and business acumen;\nStrong project management, presentation and problem-solving skills;\nDetail-minded and able to work independently;\nProficient in MS Excel, Word and PowerPoint; and\nExcellent written and spoken English and Chinese (including Putonghua).\nCandidates with lesser experience may be considered for the post of Manager (Channel Development).\n\n\n\nInterested parties please send your full resume stating current and expected salary by\u00a027 January 2022.\n\nPlease visit http://www.hkmc.com.hk/eng/careers/job_openings.html for other application methods.\n\nPlease ensure that all information provided to the HKMC Group is accurate, complete and updated. Data provided which is inaccurate or incomplete may influence the process and outcome of the recruitment exercise. Please read the HKMC Group Personal Information Collection Statement for Job Applicants at the HKMC website before completing the application form. Personal data collected will be used for recruitment purposes only. Candidates not invited for interview within 8 weeks may consider their application unsuccessful.\n\n\n", "employment_types": ["Full Time"], "selling_points": [], "locations": ["Kwun Tong"], "categories": ["Banking / Finance", "Mortgage", "Sales, CS & Business Devpt", "Channel / Distribution", "Wealth Management"], "post_time": "2022-01-14T06:24:00Z", "salary": {"currency": null, "max": null, "min": null, "period": "monthly", "term": null}, "salary_visible": false, "title_keywords": ["senior manager"], "responsibilities": ["collaborate", "monitor", "develop", "plans", "business activities"], "requirements": {"degrees": ["degree holder"], "majors": ["finance", "marketing", "business administration"], "languages": ["putonghua", "english", "chinese"], "language_level": ["excellent"], "hard_skills": ["word", "powerpoint", "project management", "ms excel", "problem-solving skills", "acumen"], "soft_skills": ["detail-minded", "work independently", "project management", "analytical mind", "business acumen", "problem-solving skills", "presentation"], "languages_combined": [{"language": "putonghua", "language_level": ["excellent"]}, {"language": "english", "language_level": ["excellent"]}, {"language": "chinese", "language_level": ["excellent"]}]}, "experience_required": {"duration": ["minimum of 8 years"], "field": ["development", "financial", "channel management"]}}, {"job_id": "100003009047370", "location_code": "hk", "company": "Ego Finance Limited", "job_title": "\u8cb8\u6b3e\u4e3b\u4efb / \u52a9\u7406\u8cb8\u6b3e\u4e3b\u4efb / \u8cb8\u6b3e\u6587\u54e1 \u2013 \u6309\u63ed\u90e8", "description": "\u8077\u8cac :\n\n\u63a5\u898b\u5ba2\u4eba\u53ca\u89e3\u7b54\u5ba2\u6236\u4e00\u822c\u8aee\u8a62\n\u8655\u7406\u8cb8\u6b3e\u7533\u8acb\n\u8655\u7406\u65e5\u5e38\u96fb\u8166\u53ca\u6587\u66f8\u5de5\u4f5c\n\u96fb\u8a71\u63a8\u5ee3\n\u8981\u6c42 :\n\n\u6b61\u8fce\u61c9\u5c46\u7562\u696d\u751f\n\u4e2d\u4e94\u7a0b\u5ea6\u3001\u5177\u67092\u5e74\u6216\u4ee5\u4e0a\u91d1\u878d/\u6309\u63ed\u8cb8\u6b3e\u76f8\u95dc\u7d93\u9a57\u6703\u88ab\u4f5c\u512a\u5148\u8003\u616e\n(\u5c11\u65bc2\u5e74\u76f8\u95dc\u7d93\u9a57\u53ef\u8003\u616e\u70ba\u8cb8\u6b3e\u6587\u54e1)\n\u8aa0\u5be6\u3001\u5c0d\u5de5\u4f5c\u71b1\u8aa0\u3001\u6709\u8cac\u4efb\u611f\n\u6d41\u5229\u7cb5\u8a9e\u3001\u6709\u826f\u597d\u6e9d\u901a\u53ca\u8868\u9054\u80fd\u529b (\u6709\u96fb\u8a71\u92b7\u552e\u7d93\u9a57\u66f4\u4f73)\n\u57fa\u672c\u96fb\u8166\u77e5\u8b58 (\u5305\u62ec\u4e2d\u6587\u8f38\u5165\u6cd5 <\u5009\u9821/\u901f\u6210>\u3001MS Word\u548cMS Excel)\n\u5f85\u9047 :\n\n\u7af6\u722d\u529b\u85aa\u916c\n\u5e74\u7d42\u82b1\u7d05\n\u9280\u884c\u5047\u671f\n\u6709\u85aa\u5e74\u504710\u81f316\u5929\n\u9577\u77ed\u9031\n\u91ab\u7642\u6d25\u8cbc\u53ca\u4f4f\u9662\u4fdd\u96aa\n\u751f\u65e5\u5047\n\u5a5a\u5047\n\u6069\u6064\u5047\n\u5165\u8077\u5c08\u4eba\u57f9\u8a13\n\u826f\u597d\u6649\u5347\u6a5f\u6703\n\u9032\u4fee\u6d25\u8cbc\uff0c\u8207\u6642\u589e\u503c\n\u5de5\u4f5c\u6642\u9593\uff1a\n\n\u661f\u671f\u4e00\u81f3\u4e94 : \u4e0a\u53489\u6642\u81f3\u4e0b\u53486\u6642 (\u5305\u542b1\u5c0f\u664210\u5206\u9418\u5348\u81b3\u6642\u9593)\n\u661f\u671f\u516d\u00a0 \u00a0 \u00a0 \u00a0 \u00a0: \u4e0a\u53489\u6642\u81f3\u4e0b\u53481\u6642 (\u9031\u516d\u9577\u77ed\u9031)\n\u6709\u610f\u61c9\u5fb5\u8005\u8acb\u9644\u4e0a\u95a3\u4e0b\u4e4b\u8a73\u7d30\u7684\u5c65\u6b77\u8868\u3001\u53ef\u5230\u8077\u65e5\u671f\u548c\u8981\u6c42\u5f85\u9047\u4f5c\u70ba\u8a55\u5be9\u4e4b\u7528\u3002 \uff0a\uff0a\u6240\u6709\u500b\u4eba\u8cc7\u6599\u53ea\u6703\u7528\u4f5c\u62db\u8058\u7528\u9014\uff0a\uff0a\n", "employment_types": ["Full Time"], "selling_points": [], "locations": ["Mong Kok"], "categories": ["Banking / Finance", "Loan", "Mortgage", "Others"], "post_time": "2022-01-14T02:55:58Z", "salary": {"currency": null, "max": null, "min": null, "period": "monthly", "term": null}, "salary_visible": false, "title_keywords": [], "responsibilities": [], "requirements": {"degrees": [], "majors": [], "languages": [], "language_level": [], "hard_skills": ["excel"], "soft_skills": [], "languages_combined": []}, "experience_required": {"duration": [], "field": []}}, {"job_id": "100003009047729", "location_code": "hk", "company": "Public Bank (Hong Kong) Limited", "job_title": "Senior / Customer Service Officer (Ref: JD-CSO)", "description": "Promote and cross-sell retail banking products through proactive business solicitation and relationship building with customers\nProvide quality and value-added services to the customers\nAssist in daily branch operations and perform annual review on loan accounts\nMaintain awareness of operational risks and adhere to relevant policies and guidelines\nSecondary education or above with minimum 3 years of relevant experience\nQualification of HKSI, IIQE and MPF preferred\nCandidates with less experience are also welcomed\nWith Enhanced Competency Framework (ECF) qualification is preferable\n\nTo apply, interested parties please follow the application methods available in the Bank\u2019s career website https://www.publicbank.com.hk/en/aboutus/careeropportunities. You can send us your resume quoting our job reference number together with present & expected salary (a must) to the Human Resources Department by email or fax at 2815 3157 or by post to Human Resources Department, 12/F, Public Bank Centre, 120 Des Voeux Road Central, Hong Kong. You may also visit our career website for other career opportunities available within our Group.\n\nPersonal data collected will be used for recruitment purpose only and will be treated in accordance with the Bank\u2019s Personal Information Collection Statement, a copy of which has been available in the Bank\u2019s career website.\n\n", "employment_types": ["Full Time", "Permanent"], "selling_points": [], "locations": ["Not Specified"], "categories": ["Banking / Finance", "Loan", "Mortgage", "Retail Banking"], "post_time": "2022-01-15T03:49:01Z", "salary": {"currency": null, "max": null, "min": null, "period": null, "term": null}, "salary_visible": false, "title_keywords": ["customer service officer"], "responsibilities": ["mpf", "guidelines", "operations", "policies", "review", "quality", "maintain", "banking"], "requirements": {"degrees": ["secondary education"], "majors": [], "languages": [], "language_level": [], "hard_skills": ["iiqe", "hksi"], "soft_skills": ["proactive"], "languages_combined": []}, "experience_required": {"duration": ["minimum 3 years"], "field": ["relevant experience", "education"]}}, {"job_id": "100003009042359", "location_code": "hk", "company": "Hays", "job_title": "Mortgage Specialist/ Direct Mortgage Sales, 35k, Retail Bank", "description": "Sales Talents who seek to achieve attractive reward in Mortgage and to develop their career in banks\n\nYour new company\nA leading retail bank with strong client portfolio and competitive mortgage products in the market has gained reputation and customer satisfaction by its business expansion in recent years. To further strengthen its talent force, she is now looking for high calibre Mortgage Specialist - Consumer Banking to join their team with rewarding package and achieve career growth.\n\nYour new role\n\nRewarding and competitive package gained (Up to basic 35k + Quarterly + Year-end bonus 4-6mth)\n\n\nTo play an instrumental role in their Direct Mortgage Sales Team\nTo cross sell general insurance services to clients\nTo handle mortgage plan and application in meeting the assigned business targets\n\nWhat you'll need to succeed\nDirect selling experience in Mortgage is a must\nBanking background is a must\nPasses in IIQE licenses\n\nWhat you'll get in return\nRewarding and competitive package gained (Up to basic 30k + Quarterly + Year-end bonus)\nWorking opportunity within an ambitious and innovative leading bank\nCompetitive career development opportunity provided\n\nWhat you need to do now\nIf you're interested in this role, click 'apply now' to forward an up-to-date copy of your CV, or call us now.\nIf this job isn't quite right for you but you are looking for a new position, please contact Miss LEE at 22307438 for a confidential discussion on your career.", "employment_types": ["Full Time", "Permanent"], "selling_points": ["Attractive commission scheme", "Up to 30k basic + Quarterly + Year-end bonus", "Fringe Banking Benefits"], "locations": ["Not Specified"], "categories": ["Banking / Finance", "Loan", "Mortgage"], "post_time": "2022-01-12T07:10:39Z", "salary": {"currency": null, "max": null, "min": null, "period": "monthly", "term": null}, "salary_visible": false, "title_keywords": ["specialist", "sales"], "responsibilities": ["year-end", "develop", "sales team", "contact", "plan", "banking", "career development", "insurance"], "requirements": {"degrees": [], "majors": [], "languages": [], "language_level": [], "hard_skills": ["iiqe", "basic"], "soft_skills": ["interested in", "innovative", "instrumental"], "languages_combined": []}, "experience_required": {"duration": [], "field": []}}, {"job_id": "100003009034953", "location_code": "hk", "company": "Delken Group Limited", "job_title": "Assistant Manager / Senior Associate - Mortgage loans (Operations)", "description": "Our client is a Financial Institution, they are currently seeking for an Assistant Manager (Operations)\u00a0 to join their team.\n\n\nResponsibilities\n\n\nTo perform loan origination, eligibility assessment, documentation, administration and customer service duties;\nTo monitor the performance of the appointed servicers and agents;\nTo prepare management statistics and reports;\nTo identify rooms and propose recommendation for process re-engineering and risk control;\nTo provide support for ad-hoc tasks and projects\n\nResponsibilities:\n\n\nDegree holder in Finance, Business Administration or equivalent;\nA minimum of 5 years\u2019 solid experience in mortgage loans operations;\nHighly responsible, attentive to details with high degree of accuracy and with strong analytical skills;\nA good team player with positive thinking, self motivated, proactive working attitude, eager to learn and to take up new responsibilities;\nGood command of spoken English and Chinese, proficiency in Putonghua will be an asset; and\nStrong PC skills in MS Excel and MS Access.\n*Candidate(s) with less experience will be considered as Senior Associate / Associate.\nInterested candidates, please send your resume (MS Word document) including employment history, present and expected salary to us.\n\n\nFor more jobs, please visit our website:\u00a0www.delken.com.hk.\u00a0\n\n(All personal data submitted will be treated in strict confidential and used for recruitment purposes only.)\u00a0", "employment_types": ["Full Time", "Contract"], "selling_points": ["Solid exp in mortgage loans operations", "Loan origination, Assessment, Docs, Admin & CS", "5-days, 15AL, Med, Immediate Available preferable"], "locations": ["Kwun Tong"], "categories": ["Banking / Finance", "Loan", "Mortgage", "Order Processing & Operation / Settlement"], "post_time": "2022-01-10T04:51:12Z", "salary": {"currency": null, "max": null, "min": null, "period": "monthly", "term": null}, "salary_visible": false, "title_keywords": ["assistant manager", "operations", "senior associate"], "responsibilities": ["management", "control", "provide support", "re-engineering", "operations", "ad-hoc tasks", "reports", "monitor the performance", "documentation", "customer service duties", "administration"], "requirements": {"degrees": ["degree", "degree holder"], "majors": ["finance", "business administration"], "languages": ["putonghua", "english", "chinese"], "language_level": ["proficiency", "good command"], "hard_skills": ["documentation", "ms excel", "pc skills", "analytical skills"], "soft_skills": ["good team player", "attentive to details", "responsible", "positive thinking", "analytical skills", "self motivated", "eager to learn", "customer service", "proactive"], "languages_combined": [{"language": "putonghua", "language_level": ["proficiency", "good command"]}, {"language": "english", "language_level": ["proficiency", "good command"]}, {"language": "chinese", "language_level": ["proficiency", "good command"]}]}, "experience_required": {"duration": ["minimum of 5 years"], "field": []}}, {"job_id": "100003009047717", "location_code": "hk", "company": "Public Bank (Hong Kong) Limited", "job_title": "Assistant Manager - Special Projects Unit (Credit Department) (Ref: JD-AMSPU)", "description": "Assist in implementing credit risk management systems\nPrepare/ Review reports related to credit risk management for identification/ evaluation of potential risks\nAssist in development of electronic systems to enhance the Bank's loan delivery process\nAssist in managing credit-related projects\nUniversity Degree with minimum 6 years of banking experience, of which minimum 3 years in credit risk management function\nKnowledgeable in credit risk modeling and banking products\nStrong credit sense and conversant with financial analysis\nProficiency in data analysis using MS Excel\nWith Enhanced Competency Framework (ECF) qualification is preferable\n\nTo apply, interested parties please follow the application methods available in the Bank\u2019s career website https://www.publicbank.com.hk/en/aboutus/careeropportunities. You can send us your resume quoting our job reference number together with present & expected salary (a must) to the Human Resources Department by email or fax at 2815 3157 or by post to Human Resources Department, 12/F, Public Bank Centre, 120 Des Voeux Road Central, Hong Kong. You may also visit our career website for other career opportunities available within our Group.\n\nPersonal data collected will be used for recruitment purpose only and will be treated in accordance with the Bank\u2019s Personal Information Collection Statement, a copy of which has been available in the Bank\u2019s career website.", "employment_types": ["Full Time", "Permanent"], "selling_points": [], "locations": ["Not Specified"], "categories": ["Banking / Finance", "Credit Analysis / Approval", "Loan", "Mortgage"], "post_time": "2022-01-15T03:48:58Z", "salary": {"currency": null, "max": null, "min": null, "period": null, "term": null}, "salary_visible": false, "title_keywords": ["assistant manager"], "responsibilities": ["management", "review", "systems", "banking", "financial analysis", "data analysis", "reports", "evaluation"], "requirements": {"degrees": ["university degree"], "majors": ["risk management"], "languages": [], "language_level": [], "hard_skills": ["financial analysis", "analysis", "ms excel"], "soft_skills": [], "languages_combined": []}, "experience_required": {"duration": ["minimum 6 years", "minimum 3 years"], "field": ["credit risk", "management", "banking experience"]}}, {"job_id": "100003009035643", "location_code": "hk", "company": "Victor Chiu Tsang & Partners", "job_title": "Mortgage Account Manager (Direct Sales) (Full-time and Part-time)", "description": "First Mortgage Loan and Second Mortgage Loan on all kind of properties, carparks and building mortgage etc\nMortgage loan business\nMortgage lending\nResponsibilities\n\nTo plan and execute mortgage and/or secured product marketing plans\nTo solicit mortgage business and accomplish targets on mortgage lending\nTo establish and develop the relationship with referral parties such as property agencies, mortgage brokers and solicitors\nOriginating, cultivating and maintain business relationships with customers\nDriving mortgage business and generate revenue from existing network through various sales activities\nPersonal sales and marketing duties to achieve target on mortgage loan business\nReview mortgage loan applications and monitor overdraft accounts\nResponsibly handling incoming customer enquiries\nRequirements\n\nDegree holder or above\nMinimum 3 to 5 years of relevant experience in in mortgage loan business\nEstablished existing and potential client network\nStrong communications and leadership skills\nAggressive, proactive with an outgoing personality\nProficient in Microsoft Office and Chinese word processing\nGood command of spoken and written Chinese, Putonghua & English\nWe offer a competitive remuneration package to the right candidate.\n\nPlease send your resume with present and expected salaries to Human Resources Department at by clicking \"Apply Now\".\n\n", "employment_types": ["Full Time", "Part Time", "Permanent"], "selling_points": ["Full Time, Permanent", "5 Days", "Tsim Sha Tsui"], "locations": ["Tsim Sha Tsui"], "categories": ["Banking / Finance", "Loan", "Mortgage", "Others"], "post_time": "2022-01-10T08:10:31Z", "salary": {"currency": null, "max": null, "min": null, "period": "monthly", "term": null}, "salary_visible": false, "title_keywords": ["account manager", "sales"], "responsibilities": ["sales activities", "marketing plans", "customer enquiries", "review", "monitor", "develop", "maintain", "plan"], "requirements": {"degrees": ["degree holder"], "majors": [], "languages": ["putonghua", "english", "chinese"], "language_level": ["good command", "proficient"], "hard_skills": ["chinese word processing", "microsoft office"], "soft_skills": ["outgoing personality", "leadership skills", "proactive"], "languages_combined": [{"language": "putonghua", "language_level": ["good command"]}, {"language": "english", "language_level": ["good command"]}, {"language": "chinese", "language_level": ["good command", "proficient"]}]}, "experience_required": {"duration": ["minimum 3 to 5 years"], "field": ["loan business", "relevant experience"]}}, {"job_id": "100003009035347", "location_code": "hk", "company": "Bravo Personnel Consultancy Limited", "job_title": "Mortgage Loan / Settlement Officer ($20K-25K)", "description": "Job requirements:\nDegree holder in in Finance, Business Administration or equivalent\nA minimum of 1 year experience in mortgage loan or settlement operations\nExperience in loan origination, loan recovery and reverse mortgage operations would be an advantage\nGood command of spoken and written English and Chinese\nGood communication skills and team players\n12 months contract (renewable)\nInterested parties, please contact Ms LEE at 2881 6923 during office hours or email your CV by clicking \"Apply Now\"\u00a0or fax your resume to 2576 8026. All the personal data collected will be used for recruitment purpose only.\u00a0\u00a0", "employment_types": ["Full Time", "Permanent"], "selling_points": [], "locations": ["Not Specified"], "categories": ["Banking / Finance", "Loan", "Mortgage", "Order Processing & Operation / Settlement"], "post_time": "2022-01-10T10:17:18Z", "salary": {"currency": null, "max": null, "min": null, "period": "monthly", "term": null}, "salary_visible": false, "title_keywords": ["officer"], "responsibilities": ["communication", "operations", "administration"], "requirements": {"degrees": ["degree holder"], "majors": ["finance", "business administration"], "languages": ["english", "chinese"], "language_level": ["good command"], "hard_skills": [], "soft_skills": ["communication skills"], "languages_combined": [{"language": "english", "language_level": ["good command"]}, {"language": "chinese", "language_level": ["good command"]}]}, "experience_required": {"duration": ["minimum of 1 year"], "field": ["settlement operations"]}}, {"job_id": "100003009033677", "location_code": "hk", "company": "Bank of Communications (Hong Kong) Limited", "job_title": "Mortgage Sales Manager", "description": "To achieve mortgage sales targets by establishing good relationship with business partners such as property agencies\nDegree holder or above, with minimum 3 years\u2019 experience in generating mortgage lending business in banking industries\nPasses in MPF, Insurance and Securities Intermediaries Examinations (Qualified under SFO for handling Regulated Activities Type 1 & 4)\nCandidates with less experience will be considered as Deputy Mortgage Sales Manager\n\u00a0\n\nWe offer attractive remuneration package to the right candidates. Please send your full resume with expected salary to\u00a0The Human Resources Manager, Bank of Communications Co., Ltd., 10/F, Bank of\u00a0Communications\u00a0Tower,\u00a0231-235 Gloucester Road, Wan Chai,\u00a0Hong Kong, or fax to\u00a02838 9209, or e-mail to : APPLY NOW.", "employment_types": ["Full Time"], "selling_points": ["Degree holder or above", "minimum 3 years\u2019 experience in generating mortgage", "Passes in MPF, Insurance Examinations"], "locations": ["Wan Chai"], "categories": ["Banking / Finance", "Loan", "Mortgage", "Others"], "post_time": "2022-01-10T01:34:18Z", "salary": {"currency": null, "max": null, "min": null, "period": "monthly", "term": null}, "salary_visible": false, "title_keywords": ["sales manager"], "responsibilities": ["good relationship", "insurance", "mpf", "banking"], "requirements": {"degrees": ["degree holder"], "majors": ["business"], "languages": [], "language_level": [], "hard_skills": ["sfo"], "soft_skills": [], "languages_combined": []}, "experience_required": {"duration": ["minimum 3 years"], "field": ["business", "banking"]}}, {"job_id": "100003009047719", "location_code": "hk", "company": "Public Bank (Hong Kong) Limited", "job_title": "Senior Credit Analyst (Ref: JD-SCA)", "description": "Perform credit evaluation and risk assessment on commercial and retail credit proposals and periodic reviews\nIdentify and assess credit risks and potential problems, and make recommendations for appropriate lending authority\u2019s consideration and approval\nEnsure efficient turnaround of credit processing\nDegree holder with minimum 5 years of solid experience in commercial credit\u00a0and risk management functions in banking industry\nExcellent interpersonal and communication skills in both English and Chinese\nCandidate with less experience will be considered as Credit Analyst\nWith Enhanced Competency Framework (ECF) qualification is preferable\n\nTo apply, interested parties please follow the application methods available in the Bank\u2019s career website https://www.publicbank.com.hk/en/aboutus/careeropportunities. You can send us your resume quoting our job reference number together with present & expected salary (a must) to the Human Resources Department by email or fax at 2815 3157 or by post to Human Resources Department, 12/F, Public Bank Centre, 120 Des Voeux Road Central, Hong Kong. You may also visit our career website for other career opportunities available within our Group.\n\nPersonal data collected will be used for recruitment purpose only and will be treated in accordance with the Bank\u2019s Personal Information Collection Statement, a copy of which has been available in the Bank\u2019s career website.", "employment_types": ["Full Time", "Permanent"], "selling_points": [], "locations": ["Not Specified"], "categories": ["Banking / Finance", "Credit Analysis / Approval", "Loan", "Mortgage"], "post_time": "2022-01-15T03:48:59Z", "salary": {"currency": null, "max": null, "min": null, "period": null, "term": null}, "salary_visible": false, "title_keywords": ["credit analyst"], "responsibilities": ["make recommendations", "management", "evaluation", "communication", "banking"], "requirements": {"degrees": ["degree holder"], "majors": ["risk management"], "languages": ["english", "chinese"], "language_level": ["excellent"], "hard_skills": ["make", "credit processing"], "soft_skills": ["make recommendations", "communication skills", "interpersonal", "efficient"], "languages_combined": [{"language": "english", "language_level": ["excellent"]}, {"language": "chinese", "language_level": ["excellent"]}]}, "experience_required": {"duration": ["minimum 5 years"], "field": ["commercial", "banking industry", "risk management"]}}, {"job_id": "100003009047763", "location_code": "hk", "company": "Public Bank (Hong Kong) Limited", "job_title": "Loans Operations Clerk (Ref: JD-LOC)", "description": "Handle enquiries from branches and customers in matters related to loans operations\nProcess loans transactions accurately and maintain a smooth workflow with branches and related units\nResponsible for property fire insurance & property collateral system maintenance\nHandle loan drawdown, repayment, arrange the disbursement of loan proceeds to customers or solicitor, monitor the renewal of fire insurance policies, input credit limit and perform general clerical duties\nSecondary education or above with 1 year experience in banking operations\nGood typing, PC skills and basic knowledge relating to loan products & operations are required\nFresh graduate will also be considered\n\nTo apply, interested parties please follow the application methods available in the Bank\u2019s career website https://www.publicbank.com.hk/en/aboutus/careeropportunities. You can send us your resume quoting our job reference number together with present & expected salary (a must) to the Human Resources Department by email or fax at 2815 3157 or by post to Human Resources Department, 12/F, Public Bank Centre, 120 Des Voeux Road Central, Hong Kong. You may also visit our career website for other career opportunities available within our Group.\n\nPersonal data collected will be used for recruitment purpose only and will be treated in accordance with the Bank\u2019s Personal Information Collection Statement, a copy of which has been available in the Bank\u2019s career website.", "employment_types": ["Full Time", "Permanent"], "selling_points": [], "locations": ["Not Specified"], "categories": ["Banking / Finance", "Loan", "Mortgage", "Others"], "post_time": "2022-01-15T03:49:05Z", "salary": {"currency": null, "max": null, "min": null, "period": null, "term": null}, "salary_visible": false, "title_keywords": ["operations clerk"], "responsibilities": ["maintenance", "operations", "policies", "monitor", "transactions", "handle enquiries", "maintain", "banking", "insurance"], "requirements": {"degrees": ["secondary education", "fresh graduate"], "majors": [], "languages": [], "language_level": [], "hard_skills": ["loan products", "basic", "maintenance", "typing", "pc skills"], "soft_skills": ["responsible", "smooth"], "languages_combined": []}, "experience_required": {"duration": ["1 year"], "field": ["banking", "education"]}}, {"job_id": "100003009031780", "location_code": "hk", "company": "Hong Kong Finance Company Limited", "job_title": "Mortgage Sales Manager", "description": "Promote SME and Mortgage loan services to new and existing customers\nPromote loan refinance service to existing customers\nHandle customer's enquiries in professional manner and follow up loan applications\nAchieve individual and team targets on SME and mortgage lending\n\nRequirements:\n\nDegree holder or above\nMinimum 3 years of relevant experience in finance, banking or property industry with a focus in SME and Mortgage loan business\nProficiency in both English and Chinese\nProactive and commit to the job\nExcellent communication, interpersonal and selling skills\nImmediate available is highly preferred", "employment_types": ["Full Time"], "selling_points": ["Promote SME and Mortgage loan services", "Promote loan refinance service to customer", "Able to work independently"], "locations": ["Admiralty"], "categories": ["Banking / Finance", "Loan", "Mortgage", "Financial Services"], "post_time": "2022-01-10T03:30:59Z", "salary": {"currency": null, "max": null, "min": null, "period": "monthly", "term": null}, "salary_visible": false, "title_keywords": ["sales manager"], "responsibilities": ["sme", "professional manner", "communication", "banking"], "requirements": {"degrees": ["degree holder"], "majors": [], "languages": ["english", "chinese"], "language_level": ["proficiency"], "hard_skills": ["focus"], "soft_skills": ["communication", "focus", "proactive", "interpersonal"], "languages_combined": [{"language": "english", "language_level": ["proficiency"]}, {"language": "chinese", "language_level": ["proficiency"]}]}, "experience_required": {"duration": ["minimum 3 years"], "field": ["loan business", "finance", "relevant experience", "banking"]}}, {"job_id": "100003009034373", "location_code": "hk", "company": "ORIENTAL HUMAN RESOURCES LIMITED", "job_title": "Credit Administration Clerk", "description": "Secondary school graduate or above\nAt least 2 years clerical experience, have experience in credit administration will be an advantage\nHands-on experience in MS Office and Chinese word processing\nStrong interpersonal and communication skills\nWell-organized, proactive and strong sense of responsibility\n\nApplication Method\n\nWe offer competitive salary, discretionary bonus, 5-day work week, public holidays and fringe benefits. Interested parties, please send full resume with expected salary to\u00a0ORIENTAL HUMAN RESOURCES LIMITED\u00a0by clicking \"Apply now\" ;\u00a0or\u00a0fax to 3600 1900\u00a0( Please quote reference on the application letter )\n\n\nPersonal Information Collection Statement\n\nPersonal data collected will be treated in accordance with our Personal Data Policy and handled in strict confidence by authorized personnel for recruitment related purpose only.\n\non.cc", "employment_types": ["Full Time"], "selling_points": [], "locations": ["North Point"], "categories": ["Admin & HR", "Clerical / Admin Staff", "Banking / Finance", "Mortgage", "Order Processing & Operation / Settlement"], "post_time": "2022-01-10T03:15:53Z", "salary": {"currency": null, "max": null, "min": null, "period": "monthly", "term": null}, "salary_visible": false, "title_keywords": ["clerk"], "responsibilities": ["communication", "administration"], "requirements": {"degrees": [], "majors": [], "languages": ["chinese"], "language_level": [], "hard_skills": ["chinese word processing", "ms office"], "soft_skills": ["communication skills", "sense of responsibility", "well-organized", "hands-on", "proactive", "interpersonal"], "languages_combined": [{"language": "chinese", "language_level": []}]}, "experience_required": {"duration": ["at least 2 years"], "field": ["clerical", "administration"]}}, {"job_id": "100003009043136", "location_code": "hk", "company": "Chasseur Pro Executive Consultant Limited", "job_title": "General Banking Officer / Personal Banking Manager / Assistant Relationship Manager (17K-25K)", "description": "General Banking Manager / Personal Banking Officer / Assistant Relationship Manager (HKD $17,000 - HKD $25,000)General Banking Officer / GBO / Personal Banking Officer / Assistant Relationship Manager (17K-25K)\n\nResponsibilities:\n\nCross-sell other banking products and make referrals to relevant staff\nIdentify potential customers in order to sell integrated financial services packages and other general banking products, such as mortgages, credit cards, and other non-life insurance consumer banking products\nTo acquire new customers through sales and marketing activities\nMaintain good relationship with both existing and new clients\n\nRequirements:\u00a0\n\nMinimum 1 year's relevant experience in banking or finance industry\nIIQE Paper 1,2,3 is required\nPro-active, mature, independent, customer-focused, and pleasant\nProficient in both spoken and written English and Chinese, knowledge of Putonghua will be an advantage\n\nFor interested parties, please send your CV to\u00a0Sam\u00a0or call us at\u00a03188 9055\u00a0for further information", "employment_types": ["Full Time"], "selling_points": ["\u2022Salary up to 25K", "\u2022No need to sell investment", "\u2022Good promotion opportunities to Junior RM"], "locations": ["Not Specified"], "categories": ["Banking / Finance", "Loan", "Mortgage", "Retail Banking"], "post_time": "2022-01-12T09:54:09Z", "salary": {"currency": "HKD", "max": 24999, "min": 17000, "period": "monthly", "term": null}, "salary_visible": true, "title_keywords": ["officer", "personal", "manager", "assistant relationship manager"], "responsibilities": ["maintain good relationship", "insurance", "banking"], "requirements": {"degrees": [], "majors": [], "languages": ["putonghua", "english", "chinese"], "language_level": ["advantage", "proficient"], "hard_skills": ["iiqe paper"], "soft_skills": ["customer-focused", "independent", "mature", "pleasant", "pro-active"], "languages_combined": [{"language": "putonghua", "language_level": ["advantage", "proficient"]}, {"language": "english", "language_level": ["advantage", "proficient"]}, {"language": "chinese", "language_level": ["advantage", "proficient"]}]}, "experience_required": {"duration": ["minimum 1 year"], "field": ["relevant experience", "finance industry", "banking"]}}, {"job_id": "100003009037419", "location_code": "hk", "company": "Talent Axis Management Consulting Group Limited", "job_title": "AVP / VP, Secured Lending Products (Bank)", "description": "Our client, a well-established Bank in Hong Kong, is looking for a high-calibre candidate to join their Group:\n\nResponsibilities:\n\nDeliver key performance indicators of the secured lending business and perform portfolio management.\nDevelop short and long term product and marketing strategies and campaigns for mortgage loans, investment product pledged facilities and premium financing.\nOversee new product ideas and channel strategies to improve market awareness and market share.\nDevelop pricing strategies, monitor profitability of products and carry out appropriate actions.\nDerive channel strategies and monitor sales channels to achieve business targets.\nDirect planning, implementing and monitoring of marketing campaign performance and competitiveness\nAnalyze customer/product MIS and market information to understand customer behavior, market trend and our gaps for continuous improvement.\nDrive process improvement and system enhancement projects so as to improve product features, efficiency and customer experience.\u00a0\nWork closely with business stakeholders to enhance credit policy and operation workflow.\nControl and manage marketing budget and ensure effectiveness of initiatives and campaigns.\nPrepare relevant business proposals and reports for presentation to senior management.\nProvide guidance and coaching to subordinates as required.\u00a0\n\nRequirements:\n\nPreferably a Degree holder or equivalent\nMinimum of 7 years of solid experience in product development / management for retail banking products, mortgage, deposit, loans, cards\nGood product development and project management skills and is result-oriented\nGood leadership and presentation skills\nProficient in MS Office\nGood command of written and spoken English and Chinese (including Putonghua).\n\nInterested candidates please forward your resume (in MS Word format)\u00a0together with current and expected salary details\u00a0by clicking the Apply Now button.", "employment_types": ["Full Time"], "selling_points": ["Bachelor degree holder", "7 years\u2019 relevant experience", "Secured Lending"], "locations": ["Not Specified"], "categories": ["Banking / Finance", "Mortgage", "Retail Banking", "Order Processing & Operation / Settlement"], "post_time": "2022-01-11T02:46:00Z", "salary": {"currency": null, "max": null, "min": null, "period": "monthly", "term": null}, "salary_visible": false, "title_keywords": [], "responsibilities": ["management", "market information", "marketing strategies", "ideas", "control", "monitoring", "monitor", "budget", "develop", "senior management", "reports", "enhancement projects", "provide guidance", "planning"], "requirements": {"degrees": ["degree holder"], "majors": [], "languages": ["putonghua", "english", "chinese"], "language_level": ["good command"], "hard_skills": ["project management", "ms office"], "soft_skills": ["project management skills", "presentation skills", "leadership", "result-oriented"], "languages_combined": [{"language": "putonghua", "language_level": ["good command"]}, {"language": "english", "language_level": ["good command"]}, {"language": "chinese", "language_level": ["good command"]}]}, "experience_required": {"duration": ["minimum of 7 years"], "field": ["product development", "retail banking", "management"]}}, {"job_id": "100003009027135", "location_code": "hk", "company": "Roots \u4e0a\u6703", "job_title": "Marketing Officer (Fresh graduates are welcome!)", "description": "Key Responsibilities\nPropose digital marketing strategies, facilitate social media content, and manage different social media platform to generate awareness and engagement\nParticipate in projects / assignments on development, improvement and enhancement of work process\nHandle customers\u2019 inquiries in professional and timely manner to build customer loyalty\nCollate and maintain records and forms\nParticipate in ad hoc project as assigned\nRequirements\n\nDiploma or Degree holder, preferably in Marketing/Business or related discipline\nGood command of spoken and written English and Chinese\nStrong computer skills in MS Office and Chinese word processing\nTeam player with strong interpersonal and communication skills\nAbility to multi-task and manage assigned projects\nCustomer oriented, cheerful and outgoing personality\nKnowledge and experience in adobe photoshop, illustrator, premiere pro is a plus\nInterested parties please send your full resume with expected salary and date of availability by clicking \"Apply Now\".", "employment_types": ["Full Time", "Permanent"], "selling_points": ["Manage and in charge of social media platform", "Startup company; provide learning opportunities", "5 days work; bank holiday; discretionary bonus"], "locations": ["Wan Chai"], "categories": ["Banking / Finance", "Mortgage", "Sales, CS & Business Devpt", "Business Development", "Marketing / Public Relations", "Digital Marketing"], "post_time": "2022-01-10T05:59:21Z", "salary": {"currency": "HKD", "max": 16999, "min": 14000, "period": "monthly", "term": null}, "salary_visible": true, "title_keywords": ["marketing officer"], "responsibilities": ["social media", "ad hoc", "digital marketing strategies", "maintain", "social media content"], "requirements": {"degrees": ["diploma", "degree holder"], "majors": ["business", "marketing"], "languages": ["english", "chinese"], "language_level": ["good command"], "hard_skills": ["plus", "chinese word processing", "adobe photoshop", "illustrator", "computer skills", "premiere pro", "ms office"], "soft_skills": ["outgoing personality", "communication skills", "cheerful", "multi-task", "team player", "interpersonal"], "languages_combined": [{"language": "english", "language_level": ["good command"]}, {"language": "chinese", "language_level": ["good command"]}]}, "experience_required": {"duration": [], "field": []}}, {"job_id": "100003009028227", "location_code": "hk", "company": "Speedy Finance Limited", "job_title": "Sales Manager (Mortgage Loan)", "description": "Responsibilities:\n\n- To solicit mortgage loan businesses which include 1st mortgage, 2nd mortgage and mortgage refinancing to achieve individual targets\n\n- To Develop and maintain relationship with real estate agencies, solicitors and broker firms\n\n- To interview mortgage applicants and provide professional recommendations which suites the needs of each individual applicant\n\n- To ensure the terms and conditions and the related mortgage loan documents are well explained to the applicants\n\n- To provide quality after sale customer services once agreements have been signed\n\nRequirements:\n\n- Form 5 or above\n\n- Highly customer-focused and sales results-oriented\n\n- Strong network with related business partners\n\n- Good knowledge of mortgage products and related credit policies\n\n- Proven marketing experience and records preferable\n\n- Basic Salary + Commission", "employment_types": ["Full Time", "Permanent"], "selling_points": [], "locations": ["Central"], "categories": ["Banking / Finance", "Loan", "Mortgage", "Sales, CS & Business Devpt", "Sales - Sales Management"], "post_time": "2022-01-07T01:49:45Z", "salary": {"currency": null, "max": null, "min": null, "period": "monthly", "term": null}, "salary_visible": false, "title_keywords": ["sales manager"], "responsibilities": ["maintain", "quality", "customer services", "develop"], "requirements": {"degrees": ["form 5 or above"], "majors": [], "languages": [], "language_level": [], "hard_skills": ["basic"], "soft_skills": ["customer-focused"], "languages_combined": []}, "experience_required": {"duration": [], "field": ["marketing"]}}, {"job_id": "100003009026632", "location_code": "hk", "company": "Centaline Finance Limited", "job_title": "Mortgage Sales Manager", "description": "\u00a0Responsibilities\n\n* Team strategic execution;\n\n* Implement marketing activities to achieve business targets;\n\n* Achieve sales target assigned;\n\n* Support acquisition of mortgage loan or related products from enquiry to drawdown;\n\n* Build and maintain customer relationship, customer prospecting as well as marketing calls through personalized service\n\nRequirements\n\n* Eagerness to develop in financial field;\n\n* Sales and/or marketing experiences in mortgage or personal loan, experience in financial institution is preferable;\n\n* Sales oriented with good interpersonal skills;\n\n* Existing sales, marketer and C.S. are welcomed\n\nWe offer Basic salary plus high commission to potential talent.\u00a0 Join us and be a part of our exciting growth\n\nInterested parties, please send your FULL RESUME (in MS Word format) with availability, current and expected salary by email to Centaline Finance Limited.\u00a0", "employment_types": ["Full Time", "Permanent"], "selling_points": ["Basic Salary plus high commission", "Mortgage or Personal Loan", "Sales / Marketer / Customer Services"], "locations": ["Yau Ma Tei"], "categories": ["Banking / Finance", "Loan", "Mortgage", "Sales, CS & Business Devpt", "Direct Sales"], "post_time": "2022-01-06T08:25:50Z", "salary": {"currency": null, "max": null, "min": null, "period": "monthly", "term": null}, "salary_visible": false, "title_keywords": ["sales manager"], "responsibilities": ["sales target", "maintain"], "requirements": {"degrees": [], "majors": [], "languages": [], "language_level": [], "hard_skills": ["c"], "soft_skills": ["interpersonal skills"], "languages_combined": []}, "experience_required": {"duration": [], "field": ["marketing", "financial"]}}, {"job_id": "100003009025286", "location_code": "hk", "company": "Kowloon Development Company Ltd", "job_title": "ASSISTANT MANAGER (MORTGAGE LOAN)", "description": "Responsibilities:\n\n\nLead a small team to achieve the company\u2019s targets\nEvaluate and ensure the loan application procedures in compliance with Company & statutory requirements/policies.\nManage and monitor loan applications progress, credit review and loan documents\nHandle customer\u2019s enquiries and follow up with customer\u2019s loan application to drawdown\nMonitor overdraft accounts, ensure credit quality and follow up overdue payment\nConsolidate reports for management review regularly\nAssist in any ad hoc duties as assigned by Management\n\nRequirements:\n\n\nDegree holder or above\nMinimum 5 years\u2019 solid experience in mortgage loan operation and debt recovery gained in financial institutions/property developer\nStrong problem-solving, interpersonal and communication skills\nMeticulous, proactive, independent and able to work under pressure\nGood command of both spoken and written English and Chinese (Cantonese & Mandarin)\n\nWe offer an attractive remuneration package and excellent career prospects to the right candidate. Interested parties are invited to send their applications with a cover letter quoting job reference number and\u00a0full resumes stating career history, qualifications, availability, current and expected salary, and contact telephone number by fax to 2394 1424 or by clicking \"APPLY NOW\".\u00a0 More information on the Company is available at www.kdc.com.hk.\n\n\nApplicants not invited for interview within two months may consider their applications unsuccessful. All personal data provided will be kept in strict confidence and only for employment purposes.", "employment_types": ["Full Time", "Permanent"], "selling_points": ["5-day work", "Double Pay and Discretionary Bonus", "Mortgage Loan"], "locations": ["Mong Kok"], "categories": ["Banking / Finance", "Loan", "Mortgage", "Sales, CS & Business Devpt", "Sales - Sales Management"], "post_time": "2022-01-06T04:00:37Z", "salary": {"currency": null, "max": null, "min": null, "period": null, "term": null}, "salary_visible": false, "title_keywords": ["assistant manager"], "responsibilities": ["ad hoc duties", "management", "policies", "lead a small team", "compliance", "procedures", "monitor", "review", "quality", "evaluate", "statutory requirements", "payment", "reports", "management review"], "requirements": {"degrees": ["degree holder"], "majors": [], "languages": ["cantonese", "english", "chinese", "mandarin"], "language_level": ["good command"], "hard_skills": ["problem-solving"], "soft_skills": ["communication skills", "meticulous", "independent", "problem-solving", "proactive", "interpersonal", "work under pressure"], "languages_combined": [{"language": "cantonese", "language_level": ["good command"]}, {"language": "english", "language_level": ["good command"]}, {"language": "chinese", "language_level": ["good command"]}, {"language": "mandarin", "language_level": ["good command"]}]}, "experience_required": {"duration": ["minimum 5 years"], "field": ["developer", "financial institutions", "operation"]}}, {"job_id": "100003009038728", "location_code": "hk", "company": "China Construction Bank (Asia) Corporation Limited", "job_title": "Relationship Manager (Liability) \u2013 Commercial Banking (Ref. no.: NBRM/CMB/JDB)", "description": "Job Descriptions:\n\n\n\nManage a portfolio of non-borrowing clients in Commercial Banking Division\nHandle general enquiries and resolve issues\nComply with the established policies and procedures to ensure the safety and security of bank\u2019s and customer\u2019s asset\nComply and adhere to bank\u2019s AML Compliance procedures, including but not limited to customer due diligence and ongoing transaction monitoring.\n\nJob Requirements:\n\nDegree holder in Business, Economics or related disciplines is preferred\nMinimum 1 year of banking experience as a front-line role in related industry\n\nSales-driven, result-oriented and be able to work under pressure\nQualifications in IIQE/HKSI related areas are preferred\n\nProficiency in the financial services/products offered to middle market companies\nGood communication skills in both English and Chinese (Cantonese & Putonghua)\nProficient in PC applications, including Microsoft Word and Excel\n\nTo apply, please send your detailed resume\u00a0stating present and expected salary\u00a0to one of the following channels:-\n\nBy Email\nBy Fax: 3718 2910\n\nApplicants who are not contacted within 8 weeks may consider their applications unsuccessful and their personal data will be retained by the bank for a period up to two years.\n\nAll information provided by applicants will be used for recruitment purposes only and will be used strictly in accordance with the bank's personal data policies, a copy of which will be provided upon request.", "employment_types": ["Full Time", "Permanent"], "selling_points": ["Non Borrowing RM", "Handle general enquiries and resolve issues", "Bachelor Degree or 1 year of experience"], "locations": ["Kowloon Bay"], "categories": ["Banking / Finance", "Corporate Banking", "Mortgage", "Financial Services"], "post_time": "2022-01-11T07:41:24Z", "salary": {"currency": null, "max": null, "min": null, "period": "monthly", "term": null}, "salary_visible": false, "title_keywords": ["relationship manager"], "responsibilities": ["aml", "policies", "compliance", "procedures", "monitoring", "customer due diligence", "banking"], "requirements": {"degrees": ["degree holder"], "majors": ["related disciplines", "economics", "business"], "languages": ["cantonese", "putonghua", "english", "chinese"], "language_level": ["good"], "hard_skills": ["excel", "iiqe", "microsoft word", "hksi", "pc applications"], "soft_skills": ["communication skills", "work under pressure", "driven", "result-oriented", "detailed"], "languages_combined": [{"language": "cantonese", "language_level": ["good"]}, {"language": "putonghua", "language_level": ["good"]}, {"language": "english", "language_level": ["good"]}, {"language": "chinese", "language_level": ["good"]}]}, "experience_required": {"duration": ["minimum 1 year"], "field": ["related", "banking experience"]}}, {"job_id": "100003009033823", "location_code": "hk", "company": "Konew Financial Express Ltd", "job_title": "\u5ba2\u6236\u670d\u52d9\u4ee3\u8868 (\u5206\u884c)", "description": "\u5de5\u4f5c\u5167\u5bb9\uff1a\n\u4e3b\u52d5\u63a8\u5ee3\u6700\u65b0\u8cb8\u6b3e\u670d\u52d9\u53ca\u7522\u54c1\u7d66\u5ba2\u6236\n\u63d0\u4f9b\u512a\u8cea\u5ba2\u6236\u67e5\u8a62\u670d\u52d9\uff0c\u5305\u62ec\u6709\u95dc\u8cb8\u6b3e\u7533\u8acb\u72c0\u6cc1\u3001\u5be9\u6279\u7d50\u679c\u7b49\n\u5982\u5ba2\u4eba\u6709\u8208\u8da3\u7533\u8acb\u8cb8\u6b3e\uff0c\u53ef\u5b89\u6392\u5ba2\u4eba\u65bc\u7db2\u4e0a\u8fa6\u7406\u8cb8\u6b3e\u624b\u7e8c \u6216 \u5b89\u6392\u71b1\u7dda\u540c\u4e8b\u8ddf\u9032\n\u5efa\u7acb\u548c\u4fdd\u6301\u826f\u597d\u7684\u5ba2\u6236\u95dc\u4fc2\uff0c\u6642\u523b\u70ba\u5ba2\u4eba\u63d0\u4f9b\u5c08\u696d\u610f\u898b\n\u4e0a\u73ed\u5730\u9ede\uff1a\u4e5d\u9f8d\u7063 / \u89c0\u5858 / \u7b72\u7b95\u7063\n\u4e0a\u73ed\u6642\u9593\uff1a\u661f\u671f\u4e00\u81f3\u4e94 ( 0900 - 1945\uff09\n\u8077\u4f4d\u8981\u6c42\uff1a\n\nHKCEE / HKDSE \u7a0b\u5ea6\u6216\u4ee5\u4e0a\n\u64cd\u6d41\u5229\u5ee3\u6771\u8a71\u53ca\u826f\u597d\u82f1\u8a9e\n\u7a4d\u6975\u4e3b\u52d5\u3001\u6709\u8cac\u4efb\u611f\u3001\u5177\u826f\u597d\u7684\u8868\u9054\u80fd\u529b\u3001\u8aaa\u8a71\u6280\u5de7\u3001\u92b7\u552e\u53ca\u9867\u5ba2\u670d\u52d9\u6280\u5de7\n\u5169\u5e74\u6216\u4ee5\u4e0a\u92b7\u552e\u7d93\u9a57\uff0c\u5177\u7269\u696d\u8cb8\u6b3e\u92b7\u552e\u7d93\u9a57\u8005\u512a\u5148\u8003\u616e\n\u80fd\u5373\u6642\u4e0a\u73ed\u8005\u5c07\u512a\u5148\u8003\u616e\n\u5165\u8077\u5f8c\u516c\u53f8\u5c07\u63d0\u4f9b\u5b8c\u5584\u7684\u5728\u8077\u57f9\u8a13\n\u54e1\u5de5\u798f\u5229\uff1a\n\n\u4e94\u5929\u5de5\u4f5c\uff0c\u9280\u884c\u5047\u671f\n\u6709\u85aa\u75c5\u5047\n\u5168\u9762\u7684\u5728\u8077\u57f9\u8a13\n\u5e74\u7d42\u82b1\u7d05\n\u5b8c\u5584\u7684\u91ab\u7642\u4fdd\u96aa\n\u7259\u79d1\u4fdd\u5065\n\u52e4\u5de5\u734e\u91d1\n\u6709\u85aa\u5e74\u5047\n\u6bcf\u5e74\u751f\u65e5\u5047\n\u5165\u8077\u5468\u5e74\u5047\n\u8003\u8a66\u5047\n\u516c\u53f8\u734e\u52f5\u5047\u671f", "employment_types": ["Full Time", "Permanent"], "selling_points": ["\u4e3b\u52d5\u63a8\u5ee3\u6700\u65b0\u8cb8\u6b3e\u670d\u52d9\u53ca\u7522\u54c1\u7d66\u5ba2\u6236", "\u63d0\u4f9b\u512a\u8cea\u5ba2\u6236\u67e5\u8a62\u670d\u52d9", "\u4e94\u5929\u5de5\u4f5c\uff0c\u9280\u884c\u5047\u671f"], "locations": ["Others"], "categories": ["Banking / Finance", "Loan", "Mortgage", "Sales, CS & Business Devpt", "Customer Service - Supervisor / Officer"], "post_time": "2022-01-10T01:51:06Z", "salary": {"currency": null, "max": null, "min": null, "period": "monthly", "term": null}, "salary_visible": false, "title_keywords": [], "responsibilities": [], "requirements": {"degrees": ["hkdse"], "majors": [], "languages": [], "language_level": [], "hard_skills": [], "soft_skills": [], "languages_combined": []}, "experience_required": {"duration": [], "field": []}}, {"job_id": "100003009030072", "location_code": "hk", "company": "The Bank of East Asia, Limited", "job_title": "Marketing Manager (Secured Lending)", "description": "Retail Lending Department (Job ID: 3110)\n\n\n\nResponsibilities\n\nTo drive the business result and support business growth\nTo liaise with internal stakeholders and concerned business partners, including Call centre, Agency, etc.\nTo provide first-class customer service which meet the standards/requirements/guidelines prescribed by all concerned regulators as well as the Bank\nTo recommend products and services to meet the needs, risk profiles and affordability of customers whom will be provided with clear and accurate information and kept informed throughout and after the sales process\nTo plan marketing programs and new initiatives to achieve the Mortgage Loan business target\nTo develop the campaign logistics and work closely with internal departments to ensure effective and efficient implementation of planned initiatives\nTo prepare briefing notes to inform concerned Branches or colleagues for details of promotional offers, new initiatives, etc.\nTo monitor the result of promotional programmes and prepare programme result reports and post-program evaluation\nTo handle the marketing expense and ensure it worked within the budget\nTo ensure standardized practice in disclosing products and services information, features, risks, fees and charges to customers throughout and after the sales process\n\n\u00a0Requirements\n\nUniversity graduate, preferably major in Marketing, Business, Finance or related disciplines OR Form 5 or above, with 5 subjects at Grade E or above in HKCEE including English, Chinese and Mathematics, AND\nA minimum of 6 years\u2019 banking experience.\u00a0 Experience in Mortgage Product / marketing is preferred;\nProficient in project management, advertising production and direct marketing with strong communication skills;\nExperienced in management of external direct sales or telesales agents would be a plus;\nPossess effective interpersonal and presentation skills;\nIndependent, self-motivated and a team player;\nAnalytical with strong business acumen and problem-solving skills;\nProficiency in both spoken and written English and Chinese;\nProficiency in computer skills", "employment_types": ["Full Time", "Permanent"], "selling_points": ["To be a team member of Retail Lending Department", "Unsecured Lending and Mortgage Specialist", "Product Marketing"], "locations": ["Kwun Tong"], "categories": ["Banking / Finance", "Loan", "Mortgage", "Retail Banking"], "post_time": "2022-01-07T19:20:05Z", "salary": {"currency": null, "max": null, "min": null, "period": null, "term": null}, "salary_visible": false, "title_keywords": ["marketing manager"], "responsibilities": ["guidelines", "budget", "monitor", "implementation", "develop", "customer service", "logistics", "reports", "plan", "evaluation", "liaise with"], "requirements": {"degrees": ["university graduate", "form 5 or above"], "majors": ["mathematics", "finance", "related disciplines", "business", "marketing"], "languages": ["english", "chinese"], "language_level": ["proficiency"], "hard_skills": ["plus", "project management", "computer skills", "problem-solving skills", "acumen"], "soft_skills": ["communication skills", "self-motivated", "independent", "project management", "presentation skills", "business acumen", "problem-solving skills", "team player", "interpersonal"], "languages_combined": [{"language": "english", "language_level": ["proficiency"]}, {"language": "chinese", "language_level": ["proficiency"]}]}, "experience_required": {"duration": ["minimum of 6 years"], "field": ["marketing", "banking experience"]}}, {"job_id": "100003009030883", "location_code": "hk", "company": "Dah Sing Financial Group", "job_title": "Assistant Financial Services Manager / General Banking Officer", "description": "\n\nJob Purpose:\nTo provide proactive service to walk-in customers and conduct selling and cross-selling of banking products to satisfy customers\u2019 needs\nMain Responsibilities:\nMeet and exceed sales target assigned\nResponsible for full range of general banking products such as CASA, Cleaning Lending, Mortgage, Insurance and Credit Card.\nActively acquire new customers through proactive sales effort\nWork to understand customers\u2019 banking needs for selling and cross-selling products\nMake sales referrals to branch colleagues or other departments as appropriate\nParticipate in localized or off-site promotional activities\nWork with product specialists where appropriate to provide services to customers\nConduct operational procedures in a compliant manner by following the Bank\u2019s policy and procedures\nIncumbent Requirements:\nUniversity degree with 1-2 years or secondary education with 3-4 years experience in branch frontline customer service\nIIQE paper 1, 2 & 3\nGood command of written and spoken English and Chinese\nPlease note that only shortlisted candidates will be notified.", "employment_types": ["Full Time"], "selling_points": ["To provide proactive service to walk-in customers", "Make sales referrals to branch colleagues", "University degree with 1-2 years experience"], "locations": ["Not Specified"], "categories": ["Banking / Finance", "Mortgage", "Financial Services", "Sales, CS & Business Devpt", "Customer Service - Manager"], "post_time": "2022-01-07T08:31:48Z", "salary": {"currency": null, "max": null, "min": null, "period": "monthly", "term": null}, "salary_visible": false, "title_keywords": ["officer", "manager", "assistant"], "responsibilities": ["sales target", "procedures", "banking", "operational procedures", "promotional activities", "cleaning", "insurance"], "requirements": {"degrees": ["university degree", "secondary education"], "majors": [], "languages": ["english", "chinese"], "language_level": ["good command"], "hard_skills": ["iiqe paper"], "soft_skills": ["customer service"], "languages_combined": [{"language": "english", "language_level": ["good command"]}, {"language": "chinese", "language_level": ["good command"]}]}, "experience_required": {"duration": ["1-2 years", "3-4 years"], "field": ["customer service", "education"]}}, {"job_id": "100003009021058", "location_code": "hk", "company": "OCBC Wing Hang Credit Limited", "job_title": "Relationship Manager \u2013 Mortgage Loan", "description": "Responsibilities\nSolicit and generate significant mortgage loan business to achieve the assigned sales target and loan growth with customer service excellence\nBuild and deepen existing client relationships\nProvide professional advice and services to customer and follow through the mortgage application cycle\nMake sales calls to potential customers and provide total product solution to customers\nActively participate in roadshows, property fairs and sales launch at developers' sites according to business direction\nEstablish and develop relations with referral parties including mortgage intermediaries, property agencies, solicitor firms and housing developers etc\nControl potential credit risk and ensure loan proceedings in compliance with procedural and documentation requirements\nHandle client enquiries or complaints if any\nRequirements\nDegree holder or equivalent\nMinimum 4 years' experience in mortgage loan sales\nCommitted and self-motivated with positive attitude and can work independently\nExcellent selling technique and customer service skills\nA good team player and be able to work under pressure\nProficient in both written and spoken English and Chinese\n\n\n\nAttractive remuneration package will be offered to the right candidate. Please apply with full resume stating present & expected salary and contact phone number to\u00a0The Human Resources Manager, 10/F, 161 Queen\u2019s Road Central, Hong Kong. Please quote the reference.\n\nPersonal data collected will be used for recruitment purpose only. For more information, please visit our website:\u00a0http://www.ocbcwhhk.com.", "employment_types": ["Full Time", "Permanent"], "selling_points": ["Solicit and generate mortgage loan business", "Build and deepen existing client relationships", "Provide professional advice and services"], "locations": ["Wan Chai"], "categories": ["Banking / Finance", "Loan", "Mortgage", "Sales, CS & Business Devpt", "Sales - Real Estate"], "post_time": "2022-01-05T02:58:51Z", "salary": {"currency": null, "max": null, "min": null, "period": "monthly", "term": null}, "salary_visible": false, "title_keywords": ["relationship manager"], "responsibilities": ["control", "sales target", "compliance", "develop", "customer service", "documentation"], "requirements": {"degrees": ["degree holder"], "majors": [], "languages": ["english", "chinese"], "language_level": ["proficient"], "hard_skills": [], "soft_skills": ["customer service skills", "self-motivated", "work independently", "good team player", "positive attitude", "committed", "work under pressure"], "languages_combined": [{"language": "english", "language_level": ["proficient"]}, {"language": "chinese", "language_level": ["proficient"]}]}, "experience_required": {"duration": ["minimum 4 years"], "field": []}}, {"job_id": "100003009030194", "location_code": "hk", "company": "Hong Kong Credit Corporation Limited", "job_title": "Manager, Lending", "description": "Responsibilities:\u00a0\n\nExercise due diligence on mortgage loan and approve credit applications within credit guidelines and delegated authority\nFormulate and recommend credit policy / guidelines / operation workflow\nEnsure the compliance of regulatory requirements as well as credit policy guidelines in credit assessment\nPrepare credit risk analysis and MIS reports to the management\nManage mortgage portfolio proactively to reduce delinquency by taking proactive remedial actions at early stage\nLiaise with business department and mortgage sales in solving issues arising from the application\nOversee the credit operations function\nParticipate in loan system development and conducting comprehensive project & UAT Plan\nHandle ad hoc project as assigned by management\n\n\u00a0Requirements:\n\nBachelor\u2019s degree in business administration, Finance and Accounting or related disciplines\nAt least 5 years\u2019 relevant working experience in mortgage lending\nGood experience and knowledge in credit approval, operations, regulations policies and practices in mortgage lending\nStrong understanding in property market and industry dynamics of Hong Kong\nWilling to take initiative in improving approval process and service delivery\nDetailed-oriented, good analytical, interpersonal and communication skills\nGood command of spoken and written English and Chinese\nProficiency in MS applications including Word, Excel, PowerPoint\nWe offer competitive remuneration including career prospects to the right candidate. Interested parties please send detailed resume with availability, current and expected salaries to\u00a0Human Resources Department, Hong Kong Credit Corporation Limited, Trust Tower, 68 Johnston Road, Wan Chai, Hong Kong\u00a0or by clicking the\u00a0Apply Now\u00a0button and upload your CV and cover letter.\n(All applications will be treated in strict confidence and used for recruitment purpose within\u00a0Hong Kong Credit Corporation Limited only. All applicants are kept on file 6 months from the date of the application.)", "employment_types": ["Full Time", "Permanent"], "selling_points": ["Exercise due diligence on mortgage loan", "Formulate and recommend credit policy", "Ensure the compliance of regulatory requirements"], "locations": ["Wan Chai"], "categories": ["Banking / Finance", "Mortgage", "Sales, CS & Business Devpt", "Account Servicing"], "post_time": "2022-01-07T06:57:03Z", "salary": {"currency": null, "max": null, "min": null, "period": "monthly", "term": null}, "salary_visible": false, "title_keywords": ["manager"], "responsibilities": ["due diligence", "management", "ad hoc", "uat", "guidelines", "operations", "compliance of regulatory", "reports", "risk analysis", "plan", "liaise with"], "requirements": {"degrees": ["degree", "bachelor"], "majors": ["related disciplines", "finance", "accounting", "business administration"], "languages": ["english", "chinese"], "language_level": ["good command"], "hard_skills": ["excel", "ms applications", "word", "powerpoint"], "soft_skills": ["communication skills", "interpersonal", "initiative", "detailed"], "languages_combined": [{"language": "english", "language_level": ["good command"]}, {"language": "chinese", "language_level": ["good command"]}]}, "experience_required": {"duration": ["at least 5 years"], "field": ["relevant working experience"]}}, {"job_id": "100003009032511", "location_code": "hk", "company": "\u5fc5\u9ad8\u4eba\u4e8b\u9867\u554f\u6709\u9650\u516c\u53f8", "job_title": "Credit Loan Officer (Personal loan/ Mortgage loan/ Consumer loan - Multiple roles)", "description": "Our clients are global bank corporations who are looking for loan officers, we are working for multiple roles, if you would like to advance your career and join in a promising company, please apply for the following:\n\nJob responsibilities:\n\n\n\u200bHandle loan application processing, including loan drawdown & disbursement\nCommunicate with customer on loan offering and any other outstanding issues\nProvide administrative support and assist in all operational matters\nAnalyze credit proposals of auto and equipment financing and Mortgage loan\nConduct annual reviews on existing customers' portfolios\nPrepare credit analysis report for management\u2019s approval\nHandle customer enquiries\nPerform ad hoc task as assigned\nJob requirements:\n\nHigher Diploma or above\nMinimum 2 years\u2019 relevant experience in financial industry\nAble to work under pressure and independently\nGood interpersonal and communication skills\nGood PC skills, fast and accurate typing\nProficient in writing and speaking in Cantonese, English and Mandarin\nInterested parties please forward your CV in word format with current and expected salaries to\u00a0PICCO Bent Consultancy Limited.\u00a0\n[All applications will be treated with strict confidential and will be used for recruitment purposes only]\n", "employment_types": ["Full Time"], "selling_points": ["Money lender; loan; personal loan; bank; sales", "mortgage; customer service; clients; drawdown;", "lending; credit analysis; credit proposal; finance"], "locations": ["Central"], "categories": ["Banking / Finance", "Credit Analysis / Approval", "Loan", "Mortgage"], "post_time": "2022-01-07T11:22:33Z", "salary": {"currency": null, "max": null, "min": null, "period": "monthly", "term": null}, "salary_visible": false, "title_keywords": ["officer", "personal"], "responsibilities": ["communicate with", "management", "handle customer enquiries", "ad hoc", "analysis report", "provide administrative support", "operational matters"], "requirements": {"degrees": ["higher diploma or above"], "majors": [], "languages": ["cantonese", "english", "mandarin"], "language_level": ["proficient"], "hard_skills": ["pc skills", "typing"], "soft_skills": ["communication skills", "independently", "accurate", "interpersonal", "work under pressure"], "languages_combined": [{"language": "cantonese", "language_level": ["proficient"]}, {"language": "english", "language_level": ["proficient"]}, {"language": "mandarin", "language_level": ["proficient"]}]}, "experience_required": {"duration": ["minimum 2 years"], "field": ["financial industry", "relevant experience"]}}, {"job_id": "100003009019855", "location_code": "hk", "company": "OCBC Wing Hang Credit Limited", "job_title": "Operation Associate", "description": "Responsibilities\n\u200bHandle loan application processing, including loan drawdown & disbursement\nCommunicate with customer on loan offering and any other outstanding issues\nHandle customer enquiries\nProvide administrative support and assist in all operational matters\nPerform ad hoc task as assigned\nRequirements\n\u200bHigher Diploma or above\nMinimum 2 years\u2019 relevant experience in financial industry\nAble to work under pressure and independently\nGood interpersonal and communication skills\nGood PC skills, fast and accurate typing\n\n\n\nAttractive remuneration package will be offered to the right candidate. Please apply with full resume stating present & expected salary and contact phone number to\u00a0The Human Resources Manager, 10/F, 161 Queen\u2019s Road Central, Hong Kong.\u00a0Please quote the reference.\n\nPersonal data collected will be used for recruitment purpose only. For more information, please visit our website:\u00a0http://www.ocbcwhhk.com.", "employment_types": ["Full Time", "Permanent"], "selling_points": ["\u200bHandle loan application processing", "Communicate with customer", "Provide administrative support"], "locations": ["Wan Chai"], "categories": ["Banking / Finance", "Loan", "Mortgage", "Order Processing & Operation / Settlement"], "post_time": "2022-01-04T09:25:35Z", "salary": {"currency": null, "max": null, "min": null, "period": "monthly", "term": null}, "salary_visible": false, "title_keywords": ["associate"], "responsibilities": ["communicate with", "ad hoc", "handle customer enquiries", "provide administrative support", "operational matters"], "requirements": {"degrees": ["diploma or above"], "majors": [], "languages": [], "language_level": [], "hard_skills": ["pc skills", "typing"], "soft_skills": ["communication skills", "independently", "accurate", "interpersonal", "work under pressure"], "languages_combined": []}, "experience_required": {"duration": ["minimum 2 years"], "field": ["financial industry", "relevant experience"]}}, {"job_id": "100003009021318", "location_code": "hk", "company": "Pan Asian Mortgage Company Limited", "job_title": "Credit Administration Officer", "description": "Responsibilities:\n\nl\u00a0\u00a0 Provide credit support in loan documentation\nl\u00a0\u00a0 Handle daily loan processing\nl\u00a0\u00a0 Maintain the documentation tracking and filing system\nl\u00a0\u00a0 Conduct searches for mortgage applications\nl\u00a0\u00a0 Perform ad-hoc duties as and when required\n\nRequirements:\n\nl\u00a0\u00a0 Form 5 / DSE graduates or above\nl\u00a0\u00a0 Hands-on experience in handling loans documentation is an advantage\nl\u00a0\u00a0 Self-starter with willingness to work in a dynamic and changing environment\nl\u00a0\u00a0 Good command of both written and spoken English and Chinese\nl\u00a0\u00a0 Immediately available is an advantage\n\nWe offer attractive compensation package with a potentially fast-track promotion to the right candidates.\u00a0\u00a0Interested parties, please send us your full resume, current pay level and expected compensation by email.\u00a0 Applicants who don't receive a reply within 6 weeks may consider their applications unsuccessful. All submitted data will only be used for recruitment purposes only.\u00a0\u00a0", "employment_types": ["Full Time", "Permanent"], "selling_points": ["Form 5 / DSE graduates", "5 Days Work", "Medical Allowances"], "locations": ["Wan Chai"], "categories": ["Banking / Finance", "Mortgage"], "post_time": "2022-01-05T03:37:13Z", "salary": {"currency": null, "max": null, "min": null, "period": "monthly", "term": null}, "salary_visible": false, "title_keywords": ["administration officer"], "responsibilities": ["documentation", "maintain", "ad-hoc duties", "tracking"], "requirements": {"degrees": ["form 5", "dse"], "majors": [], "languages": ["english", "chinese"], "language_level": ["good command"], "hard_skills": ["documentation", "dynamic"], "soft_skills": ["hands-on", "dynamic", "willingness to work"], "languages_combined": [{"language": "english", "language_level": ["good command"]}, {"language": "chinese", "language_level": ["good command"]}]}, "experience_required": {"duration": [], "field": []}}, {"job_id": "100003009032457", "location_code": "hk", "company": "Allegis Global Solutions (Hong Kong) Limited", "job_title": "Junior Analyst, Credit Operation (Virtual Bank, contract, to perm)", "description": "The role is based on-site with our client, a reputable global bank with a strong presence in Asia Pacific. They are looking for a Credit Operations Analyst to be responsible to support the Team Manager to run the daily credit related operations activities and support to meet business needs and future growth.\n\n\n\nResponsibilities\n\nSupport day-to-day credit operations including document review process, TU related activities, Card transaction reconciliations and dispute\nProvide efficient and effective operation support related to the responsible area by ensuring accuracy and integrity\nDeliver quality services and support to internal and external customers\nEnsure good controls to responsible area\nTimely escalate to team leader in case of any irregularity is identified\u00a0\n\nQualifications\n\nUniversity or above\nWelcome fresh graduates\u00a0\nRelevant experience in banking / credit card / unsecured loans business is preferred but not mandatory\nGood communication skills, good in spoken English and Chinese\u00a0\nProficient on Microsoft Office Suite\nMay need to work extra hours during weekday and weekend subject to business needs (with good OT pay)", "employment_types": ["Full Time", "Contract"], "selling_points": ["Virtual Bank, Fintech", "Potential to extend contract, to perm", "Great career development opportunity"], "locations": ["Quarry Bay"], "categories": ["Banking / Finance", "Mortgage", "Order Processing & Operation / Settlement", "Others", "Student / Fresh Graduate / No Experience"], "post_time": "2022-01-07T11:09:56Z", "salary": {"currency": null, "max": null, "min": null, "period": "monthly", "term": null}, "salary_visible": false, "title_keywords": ["analyst", "junior"], "responsibilities": ["internal and external customers", "operations", "review", "quality", "communication", "reconciliations", "banking", "support the team"], "requirements": {"degrees": [], "majors": [], "languages": ["english", "chinese"], "language_level": ["good"], "hard_skills": ["microsoft office suite", "operation support"], "soft_skills": ["efficient", "communication skills", "responsible", "timely", "integrity"], "languages_combined": [{"language": "english", "language_level": ["good"]}, {"language": "chinese", "language_level": ["good"]}]}, "experience_required": {"duration": [], "field": ["credit card", "business", "relevant experience", "banking"]}}, {"job_id": "100003009015889", "location_code": "hk", "company": "Sun Hung Kai Credit Limited", "job_title": "Mortgage Account Manager (Direct Sales)", "description": "Responsibilities\n\nPlan and implement mortgage product marketing strategies\nAchieve individual and team targets on mortgage lending\nCultivate and maintain business relationships with customers\nDrive mortgage business and generate revenue from network through various sales activities\nPersonal sales and marketing duties to achieve target on mortgage loan business\nReview mortgage loan applications and monitor overdraft accounts\nHandle incoming customer enquiries\n\n\u00a0Requirements\n\nDegree holder or above\nMinimum 3 to 5 years of relevant experience in finance, banking or property industry with a focus in mortgage loan business\nStrong potential client network\nStrong communications and leadership skills\nAggressive, proactive with an outgoing personality\nProficient in Microsoft Office and Chinese word processing\nGood command of spoken and written Chinese, Putonghua & English\n\n\u00a0We offer a competitive remuneration package to the right candidate.\u00a0\n\nPlease send your resume with present and expected salaries to Human Resources Department at by email.\n\nPlease visit\u00a0www.shkcredit.com.hk for more information about us.\u00a0", "employment_types": ["Full Time", "Permanent"], "selling_points": ["First Mortgage Loan and Second Mortgage Loan", "Mortgage loan business", "Mortgage lending"], "locations": ["Wan Chai"], "categories": ["Banking / Finance", "Loan", "Mortgage"], "post_time": "2022-01-03T07:51:11Z", "salary": {"currency": null, "max": null, "min": null, "period": "monthly", "term": null}, "salary_visible": false, "title_keywords": ["account manager", "sales"], "responsibilities": ["sales activities", "marketing strategies", "customer enquiries", "review", "monitor", "maintain", "plan"], "requirements": {"degrees": ["degree holder"], "majors": [], "languages": ["putonghua", "english", "chinese"], "language_level": ["good command", "proficient"], "hard_skills": ["focus", "chinese word processing", "microsoft office"], "soft_skills": ["outgoing personality", "focus", "leadership skills", "proactive"], "languages_combined": [{"language": "putonghua", "language_level": ["good command"]}, {"language": "english", "language_level": ["good command"]}, {"language": "chinese", "language_level": ["good command", "proficient"]}]}, "experience_required": {"duration": ["minimum 3 to 5 years"], "field": ["loan business", "finance", "relevant experience", "banking"]}}, {"job_id": "100003009028221", "location_code": "hk", "company": "Speedy Finance Limited", "job_title": "Finance Manager", "description": "Responsibilities:\u00a0\u00a0\u00a0\u00a0\u00a0\u00a0\u00a0\u00a0\u00a0\u00a0\u00a0\u00a0\n\n-\u00a0\u00a0\u00a0\u00a0\u00a0\u00a0\u00a0\u00a0\u00a0 Responsible for daily accounting, treasury & finance functions of the group of companies.\n\n-\u00a0\u00a0\u00a0\u00a0\u00a0\u00a0\u00a0\u00a0\u00a0 Responsible for human resources management tasks of the group of companies.\n\n-\u00a0\u00a0\u00a0\u00a0\u00a0\u00a0\u00a0\u00a0\u00a0 Responsible for company secretary tasks of the group of companies.\n\n-\u00a0\u00a0\u00a0\u00a0\u00a0\u00a0\u00a0\u00a0\u00a0 Responsible for maintaining full set of ledgers of the group of companies.\n\n-\u00a0\u00a0\u00a0\u00a0\u00a0\u00a0\u00a0\u00a0\u00a0 Develop cash flow projections.\n\n-\u00a0\u00a0\u00a0\u00a0\u00a0\u00a0\u00a0\u00a0\u00a0 Prepare monthly management reports and financial analysis for group companies\n\n-\u00a0\u00a0\u00a0\u00a0\u00a0\u00a0\u00a0\u00a0\u00a0 Prepare annual budget and periodic forecast.\n\n-\u00a0\u00a0\u00a0\u00a0\u00a0\u00a0\u00a0\u00a0\u00a0 Liaise with external auditors and bank relationship managers\n\n-\u00a0\u00a0\u00a0\u00a0\u00a0\u00a0\u00a0\u00a0\u00a0 Handle tax filings and other taxation issues.\n\n-\u00a0\u00a0\u00a0\u00a0\u00a0\u00a0\u00a0\u00a0\u00a0 Participate in ad-hoc projects.\u00a0\u00a0\n\nRequirements:\n\n-\u00a0\u00a0\u00a0\u00a0\u00a0\u00a0\u00a0\u00a0\u00a0\u00a0\u00a0 Qualified accountant with minimum 3 years\u2019 supervisory/managerial experience\n\n-\u00a0\u00a0\u00a0\u00a0\u00a0\u00a0\u00a0\u00a0\u00a0\u00a0\u00a0 Good command of English, Mandarin and Cantonese;\n\n-\u00a0\u00a0\u00a0\u00a0\u00a0\u00a0\u00a0\u00a0\u00a0\u00a0\u00a0 Proficiency in Microsoft Office Suite and MYOB\n\n-\u00a0\u00a0\u00a0\u00a0\u00a0\u00a0\u00a0\u00a0\u00a0\u00a0\u00a0 Knowledge in company secretarial field\n\n-\u00a0\u00a0\u00a0\u00a0\u00a0\u00a0\u00a0\u00a0\u00a0\u00a0\u00a0 Self-motivated and able to work independently\n\n-\u00a0\u00a0\u00a0\u00a0\u00a0\u00a0\u00a0\u00a0\u00a0\u00a0\u00a0 Immediately available is preferred", "employment_types": ["Full Time"], "selling_points": [], "locations": ["Central"], "categories": ["Accounting", "Accountant", "Finance / Accounting Manager", "Banking / Finance", "Mortgage"], "post_time": "2022-01-07T01:49:05Z", "salary": {"currency": null, "max": null, "min": null, "period": "monthly", "term": null}, "salary_visible": false, "title_keywords": ["finance manager"], "responsibilities": ["tax", "taxation", "management", "maintaining", "budget", "develop", "financial analysis", "cash flow", "management reports", "forecast", "liaise with", "daily accounting", "ad-hoc projects", "external auditors"], "requirements": {"degrees": [], "majors": [], "languages": ["cantonese", "english", "mandarin"], "language_level": ["good command"], "hard_skills": ["microsoft office suite", "myob"], "soft_skills": ["self-motivated", "work independently"], "languages_combined": [{"language": "cantonese", "language_level": ["good command"]}, {"language": "english", "language_level": ["good command"]}, {"language": "mandarin", "language_level": ["good command"]}]}, "experience_required": {"duration": ["minimum 3 years"], "field": ["managerial", "supervisory"]}}, {"job_id": "100003009025415", "location_code": "hk", "company": "Hong Kong Kind Nice Limited", "job_title": "Marketing & Operation Manager", "description": "Responsibilities:\n\nDevelop & implement strategies to ensure expectations from both the senior management and guests are met;\nDevelop and manage relationships with different business units;\nLead, define, develop and implement the operation strategic;\nMaximize the profitability of the portfolio;\nEvaluate the effectiveness and propose new ideas to strengthen the performance of operation;\nSupervise whole business team to ensure strategic and project delivery under schedule.\n\nRequirements:\n\nMinimum 5-8 years of relevant experience in operation and project management;\nExcellent leadership skills with a strong entrepreneurial spirit, self-motivated and constantly looking for new challenges;\nAttention to detail, open minded, adaptable and collaborative;\nBe innovative, positive and macroscopic in thinking;\nExtensive knowledge of marketing strategies, channels, and branding will be preferred.\nRelated experience in mortgage is advantage.\n\n\n\nBenefits:\n\nCompetitive salary package\nVarious caring leave types\nGreat learning and career development platform\nExcellent working environment\n\n\nInterested parties please send your CV (English and Chinese) with current and expected package, as well as date of availability to us for selection by clicking \u201cApply Now\u201d. All information collected would be used for recruitment purpose only. Application process may take 2 to 3 weeks; candidates would not be considered, should there be no contact within 6 weeks.", "employment_types": ["Full Time", "Permanent"], "selling_points": ["5-yr experience in operation & project management", "Detailed, open-minded, adaptable and collaborative", "Strong entrepreneurial spirit, self-motivated"], "locations": ["Kowloon Bay"], "categories": ["Banking / Finance", "Mortgage", "Private Banking", "Project Finance"], "post_time": "2022-01-06T05:40:53Z", "salary": {"currency": null, "max": null, "min": null, "period": "monthly", "term": null}, "salary_visible": false, "title_keywords": ["operation manager"], "responsibilities": ["ideas", "develop", "evaluate", "schedule", "senior management"], "requirements": {"degrees": [], "majors": [], "languages": [], "language_level": [], "hard_skills": ["project management"], "soft_skills": ["self-motivated", "adaptable", "leadership skills", "collaborative", "project management", "open minded", "attention to detail", "innovative", "extensive", "positive"], "languages_combined": []}, "experience_required": {"duration": ["minimum 5-8 years"], "field": ["related", "project management", "operation", "relevant experience"]}}, {"job_id": "100003009019384", "location_code": "hk", "company": "Hang Seng Bank Ltd", "job_title": "Mortgage Relationship Manager", "description": "Personal Banking Products\u00a0\u2013 Mortgage Relationship Management\n\nAs one of the Hong Kong's leading mortgage banks, we help smooth the path to home ownership for customers by offering innovative, timely and comprehensive mortgage products and services that allow homebuyers at all levels to fulfill their home-buying dreams.\u00a0\u00a0Our services are delivered through a comprehensive range of service channels, including branches, mobile direct sales, e-channels and customer hotlines.\n\nShould you join our Secured Loans business, you will work closely with our professional, innovative and committed staff to develop and enhance secured loan products to meet the changing needs of customers in a dynamic market environment and to deliver premium services to our customers.\n\nWe are currently seeking a high caliber professional to join our department as\u00a0Mortgage Relationship Manager.\n\nPrincipal responsibilities\n\nGrow the Bank's mortgage lending business by acquiring referrals from property agencies / solicitors' firms and participarting in on-site sales projects\nHandle mortgage applicaiton documents independtly and submit for credit assessment based on the Bank's mortgage guidelines and policies\nDevelop and maintain close relationship with property agencies and solicitors' firms\n\n\n\nRequirements\n\nUniversity degree in a related dicipline OR other relevant qualifications preferred\nMinimum of two years' experience in mortgage lending business with good contacts at property agencies / developers and solicitors' firms\nStrong service and sales orientation, with good communication and interpersonal skills\nAble to work under pressure and willingness to work on Sundays and public holidays\nProficiency in both English and Chinese; knowledge of Putonghua an advantage\nCustomer centric mindset and ability to manage complex interactions effectively\nShown strong situation awarenss, strong desire to learn and able to work in Agile environment\nHigh level of customer centricity mindset with dedication to deliver exceptional quality services for customers\n\nIf you would like to explore other opportunities at Hang Seng Hong Kong, please visit\u00a0www.hangseng.com/careers/\u00a0for details.\n\n\nThe health and safety of our employees and candidates is very important to us. Due to the current situation related to the Novel Coronavirus (2019-nCoV), we\u2019re leveraging our digital capabilities to ensure we can continue to recruit top talent at the HSBC Group.\u00a0 As your application progresses, you may be asked to use one of our digital tools to help you through your recruitment journey.\u00a0 If so, one of our\u00a0 Resourcing colleagues will explain how our video-interviewing technology will be used throughout the recruitment process and will be on hand to answer any questions you might have.\nAll information provided by applicants will be used only for recruitment purposes and will be used strictly in accordance with the Bank's personal data policies, a copy of which may be obtained by the applicant upon request. Unless otherwise instructed in writing by the applicant concerned, applicants may be considered for other suitable positions within the Bank and its related companies. The personal data of unsuccessful job applicants may be retained for a maximum of two years from the date when the job application is rejected and such data may be retained for a longer period if there is a subsisting reason that obliges the Bank to do so, after which the personal data will be destroyed.", "employment_types": ["Full Time", "Permanent"], "selling_points": [], "locations": ["Not Specified"], "categories": ["Banking / Finance", "Mortgage", "Retail Banking", "Financial Services"], "post_time": "2022-01-04T07:31:44Z", "salary": {"currency": null, "max": null, "min": null, "period": "monthly", "term": null}, "salary_visible": false, "title_keywords": ["relationship manager"], "responsibilities": ["guidelines", "policies", "maintain", "develop"], "requirements": {"degrees": ["university degree"], "majors": [], "languages": ["putonghua", "english", "chinese"], "language_level": ["advantage", "proficiency"], "hard_skills": ["agile", "reason"], "soft_skills": ["agile", "communication and interpersonal skills", "willingness to work", "novel", "work under pressure"], "languages_combined": [{"language": "putonghua", "language_level": ["advantage"]}, {"language": "english", "language_level": ["proficiency"]}, {"language": "chinese", "language_level": ["proficiency"]}]}, "experience_required": {"duration": ["minimum of two years"], "field": ["business"]}}, {"job_id": "100003009014945", "location_code": "hk", "company": "Manpower Services (Hong Kong) Limited", "job_title": "mortgage credit approval, top bank (Up to 50K, URGENT)", "description": "Job Responsibilities\n\nReview and handle day-to-day mortgage credit applications and provide approval services following both internal/extrenal regulatory requirements.\nAccess mortgage\u00a0credit applications to prevent from fraud attack and report any suspicious applications/activity to manager.\nParticipate in improvment projets to improve approval efficiency.\nProvide support on credit approval applications to supervisors\u00a0 according to their instructions.\n\nJob Requirements\n\nAt least 2 years experiences in banking/finance industry or related.\nExperience in any kinds of approval (Mortgage/Personal loan/Credit Card/Security loan approval,etc.) is a must.\nGreat communication skills, able to work under pressure, great team player.\nFluent in written and spoken English is preferred.\nBasic PC skills.\n\nInterested parties please send your cv and expected salary to maurice.chim@manpowergrc.hk.", "employment_types": ["Permanent"], "selling_points": ["Experience in approval is a must", "Mortgage/personal loan/credit card/security loan", "Attractive Package"], "locations": ["Kwun Tong"], "categories": ["Banking / Finance", "Credit Analysis / Approval", "Loan", "Mortgage"], "post_time": "2022-01-03T04:36:11Z", "salary": {"currency": null, "max": null, "min": null, "period": "monthly", "term": null}, "salary_visible": false, "title_keywords": [], "responsibilities": ["regulatory requirements", "provide support", "review", "report"], "requirements": {"degrees": [], "majors": [], "languages": ["english"], "language_level": ["fluent"], "hard_skills": ["pc skills", "basic"], "soft_skills": ["communication skills", "team player", "work under pressure"], "languages_combined": [{"language": "english", "language_level": ["fluent"]}]}, "experience_required": {"duration": ["at least 2 years"], "field": ["related", "credit card", "banking", "security", "finance industry"]}}, {"job_id": "100003009015964", "location_code": "hk", "company": "Fubon Bank (Hong Kong) Limited", "job_title": "Sales Manager / Assistant Sales Manager, Mortgage Lending", "description": "Responsibilities:\n\nTo solicit the mortgage loan business and achieve individual target\nTo establish and develop the relationship with Referral Parties including property agencies, mortgage brokers and solicitors\nTo provide end to end service to the mortgage customer\nTo cross-sell the required products, e.g. credit card, personal loan, insurance and investment, according to management directives and with appropriate license\nTo fulfill the compliance requirement and handle the customer and application according to the procedure\n\n\nRequirements:\n\nUniversity graduate or above\n3 year or above relevant experience\nMinimum of 5 years' bank mortgage sales or property agency experience with proven sales track records (Minimum of 2 year for Assistant Manager) for\u00a0Form 5 graduate\nStrong self-motivation, customer and sales orientation\nStrong network with related business partners\nUnderstand relevant policies and procedures of the Bank as well as regulatory requirements\nGood communication skills\nGood PC knowledge\nFluent in English and Mandarin\n\nPlease send your application with full resume indicating current and expected salary, and quoting the above reference no.\n\nFor other vacancies, please visit our website: http://www.fubonbank.com.hk/\n\n*All personal data provided by job applicants will be used for recruitment purposes only in accordance with the Bank\u2019s Personal Data Information Collection Statement, a copy of which is available on our website: http://www.fubonbank.com.hk/web/html/sh_careers_e.html", "employment_types": ["Permanent"], "selling_points": ["13 Month Pay", "Medical Benefits", "Insurance Benefits"], "locations": ["Central"], "categories": ["Banking / Finance", "Loan", "Mortgage", "Others"], "post_time": "2022-01-03T07:59:49Z", "salary": {"currency": null, "max": null, "min": null, "period": "monthly", "term": null}, "salary_visible": false, "title_keywords": ["assistant sales manager", "sales manager"], "responsibilities": ["compliance", "management", "insurance", "develop"], "requirements": {"degrees": ["university graduate or above", "form 5"], "majors": [], "languages": ["english", "mandarin"], "language_level": ["fluent"], "hard_skills": ["no", "html", "pc knowledge", "web"], "soft_skills": ["communication skills", "self-motivation"], "languages_combined": [{"language": "english", "language_level": ["fluent"]}, {"language": "mandarin", "language_level": ["fluent"]}]}, "experience_required": {"duration": ["3 year", "minimum of 2 year", "minimum of 5 years"], "field": ["agency", "relevant experience"]}}, {"job_id": "100003009015888", "location_code": "hk", "company": "Sun Hung Kai Credit Limited", "job_title": "Product Development \u2013 VP Level", "description": "Responsibilities\n\n\nSupport SHK Credit\u2019s growth initiatives, including product development and strategic partnership for mortgage business in Hong Kong\nFormulate strategies on product development, marketing and channel sales plans in achieving business targets\nManage product cycle from features, pricing, compliance, operations to customer journey to maximize business profits\nExplore new partnership opportunities, lead the team to create and execute business ideas\nLiaise with internal and eternal parties to prioritize the delivery of new products\nStay on top of current market dynamics and be aware of competitors\u2019 products and marketing campaigns to develop and enhance mortgage product and features to maintain competitiveness in the market\nConduct analysis on business performance and evaluate programs\u2019 effectiveness to ensure that initiatives are measurable and reportable\nMark sure all product setup, operation process and product programs comply to all internal and regulatory requirement\n\nRequirements\n\n\nMin 10+ years relevant product experience gained from mortgage business\nEntrepreneurial self-starter who can work in a fast-paced environment with minimal supervision\nExcellent communication skills with an ability to distil complex issues into structured frameworks and concrete action plans\nExcellent command of both spoken and written English and Chinese, including Mandarin\n\n\u00a0We offer a competitive remuneration package to the right candidate.\u00a0\n\nPlease send your resume with present and expected salaries to Human Resources Department at\u00a0.\n\nPlease visitwww.shkcredit.com.hk for more information about us.\u00a0\n\n\u00a0\nWe are an equal opportunity employer and welcome applications from all qualified candidates. All applications will be treated in the strictest confidence. Personal data provided will be used for recruitment purposes only. The job applicant will assume all or any risks arising out of or in connection with the job application transmission process prior to our actual receipt of the same including but not limited to accidental or unauthorized loss or disclosure of personal information, to which we will not be responsible in any way.\n\nUnder the Personal Data (Privacy) Ordinance, you may request access to, and / or correction of your personal data in relation to your application.\u00a0\n", "employment_types": ["Full Time", "Permanent"], "selling_points": ["Mortgage operations and administration", "Product Development", "Marketing"], "locations": ["Wan Chai"], "categories": ["Banking / Finance", "Mortgage", "Financial Services"], "post_time": "2022-01-03T07:51:11Z", "salary": {"currency": null, "max": null, "min": null, "period": "monthly", "term": null}, "salary_visible": false, "title_keywords": ["product development"], "responsibilities": ["ideas", "operations", "analysis", "compliance", "develop", "evaluate", "maintain", "sales plans", "marketing campaigns", "liaise with", "setup"], "requirements": {"degrees": [], "majors": [], "languages": ["english", "chinese", "mandarin"], "language_level": ["excellent"], "hard_skills": [], "soft_skills": ["fast-paced environment", "communication skills", "structured"], "languages_combined": [{"language": "english", "language_level": ["excellent"]}, {"language": "chinese", "language_level": ["excellent"]}, {"language": "mandarin", "language_level": ["excellent"]}]}, "experience_required": {"duration": ["min 10+ years"], "field": ["business"]}}, {"job_id": "100003009015905", "location_code": "hk", "company": "Hang Seng Bank Ltd", "job_title": "Mortgage Sales Trainee", "description": "Personal Banking Products \u2013 Mortgage Relationship Management\n\nAs one of the Hong Kong's leading mortgage banks, we help smooth the path to home ownership for customers by offering innovative, timely and comprehensive mortgage products and services that allow homebuyers at all levels to fulfill their home-buying dreams.\u00a0\u00a0Our services are delivered through a comprehensive range of service channels, including branches, mobile direct sales, e-channels and customer hotlines.\n\nShould you join our Secured Loans business, you will work closely with our professional, innovative and committed staff to develop and enhance secured loan products to meet the changing needs of customers in a dynamic market environment and to deliver premium services to our customers.\n\nWe are currently seeking a high caliber professional to join our department as\u00a0Mortgage Sales Trainee.\n\nPrincipal responsibilities\n\nConduct sales activities and acquire mortgage business through establishing business network with property agents and mortgage brokers\nGrow the Bank's market share and maximize related profits in Hong Kong\nMaintain awareness of operational risks and adhere to relevant policies and guidelines\n\n\nRequirements\n\nUniversity degree, with passes in the Insurance Intermediaries Qualifying Examinations an advantage\nStrong sales and service orientation, with outgoing personality and good communication skills\nProficiency in both English and Chinese; with proficiency in\u00a0Putonghua an advantage\nCustomer centric mindset and ability to manage complex interactions effectively\nShown strong situation awarenss, strong desire to learn and able to work in Agile environment\nHigh level of customer centricity mindset with dedication to deliver exceptional quality services for customers\n\nSuccessful\u00a0 candidates will undergo a one-year career development programme consisting of training and job attachment to build your professional knowledge of secured loans buisness, customer relationship management skills and selling techniques. After the programe, you will be placed to our Mortgage Sales team, responsible for promoting mortgage and secured loans products, as well as cross-selling other financial products and services to our customers.\u00a0\n\nIf you would like to explore other opportunities at Hang Seng Hong Kong, please visit www.hangseng.com/careers/ for details.\n\n\n\nThe health and safety of our employees and candidates is very important to us. Due to the current situation related to the Novel Coronavirus (2019-nCoV), we\u2019re leveraging our digital capabilities to ensure we can continue to recruit top talent at the HSBC Group. \u00a0As your application progresses, you may be asked to use one of our digital tools to help you through your recruitment journey.\u00a0 If so, one of our \u00a0Resourcing colleagues will explain how our video-interviewing technology will be used throughout the recruitment process and will be on hand to answer any questions you might have.\n\nAll information provided by applicants will be used only for recruitment purposes and will be used strictly in accordance with the Bank's personal data policies, a copy of which may be obtained by the applicant upon request. Unless otherwise instructed in writing by the applicant concerned, applicants may be considered for other suitable positions within the Bank and its related companies. The personal data of unsuccessful job applicants may be retained for a maximum of two years from the date when the job application is rejected and such data may be retained for a longer period if there is a subsisting reason that obliges the Bank to do so, after which the personal data will be destroyed.", "employment_types": ["Full Time", "Permanent"], "selling_points": [], "locations": ["Not Specified"], "categories": ["Banking / Finance", "Mortgage", "Retail Banking", "Information Technology (IT)", "Product Management / Business Analyst"], "post_time": "2022-01-03T07:53:22Z", "salary": {"currency": null, "max": null, "min": null, "period": "monthly", "term": null}, "salary_visible": false, "title_keywords": ["sales trainee"], "responsibilities": ["guidelines", "sales activities", "maintain", "policies"], "requirements": {"degrees": ["university degree"], "majors": ["insurance"], "languages": ["putonghua", "english", "chinese"], "language_level": ["advantage", "proficiency"], "hard_skills": ["agile", "reason"], "soft_skills": ["outgoing personality", "communication skills", "agile", "responsible", "novel"], "languages_combined": [{"language": "putonghua", "language_level": ["proficiency", "advantage"]}, {"language": "english", "language_level": ["proficiency"]}, {"language": "chinese", "language_level": ["proficiency"]}]}, "experience_required": {"duration": [], "field": []}}, {"job_id": "100003009013293", "location_code": "hk", "company": "KOS International Limited", "job_title": "Mortgage Specialist", "description": "Our client is one of the leading retail bank in Hong Kong. They are looking for several Mortgage Officers. This role mainly focuses on providing counter services and reporting directly to the Head of Lending Department.\n\nResponsibilities:\n\nIdentify customer needs and offers suitable lending products and services with financial planning solutions\nPerform credit review on loan portfolio\nHandle loans application and collect supporting documents. Perform credit analysis to facilitate loans approval process\nExplore new channels for lending business including property agencies, solicitor firms, accounting firms and professional bodies, etc.\nParticipate in marketing and promotion activities, events and projects\n\nRequirements:\n\n2 years of experience in lending business with good knowledge in credit management and credit risks\nHigher Diploma or Associate degree holder in Business Administration or a related discipline\nSales oriented mindset, self-motivated, team-player\nGood communications skills in both Chinese and English\nCandidate with more experience will be considered as Senior Mortgage Specialist\n\nClick \"Apply Now\" to apply for this position or call Carmen Ng at +852 3180 4923 for a confidential discussion. All information collected will be kept in strict confidence and will be used for recruitment purpose only.", "employment_types": ["Full Time", "Permanent"], "selling_points": ["On job training", "Attractive salary package", "New headcount"], "locations": ["Tsim Sha Tsui"], "categories": ["Banking / Finance", "Mortgage"], "post_time": "2022-01-03T01:59:53Z", "salary": {"currency": null, "max": null, "min": null, "period": "monthly", "term": null}, "salary_visible": false, "title_keywords": ["specialist"], "responsibilities": ["analysis", "review", "planning"], "requirements": {"degrees": ["associate degree", "diploma"], "majors": ["business administration"], "languages": ["english", "chinese"], "language_level": ["good"], "hard_skills": [], "soft_skills": ["team-player", "self-motivated", "confidence"], "languages_combined": [{"language": "english", "language_level": ["good"]}, {"language": "chinese", "language_level": ["good"]}]}, "experience_required": {"duration": ["2 years"], "field": ["management", "business"]}}, {"job_id": "100003009014707", "location_code": "hk", "company": "Pan Asian Mortgage Company Limited", "job_title": "Senior Officer  - Office Administrator", "description": "Job Responsibilities:\n\nPerform full spectrum of administrative duties in supporting the day to day office activities with internal and external parties;\nArranges meetings by scheduling appropriate meeting times, booking rooms, and planning refreshments\nManage reception area and look after visitors\nAssist in planning and arranging whole year Company / staff events\nMaintains accurate records for employee annual leave requests\nManages outgoing post on special deliveries\nCoordinate the repair and maintenance for office equipment;\nSupport finance team (when needed) to handle petty cash, bills payment, filing and scanning\nParticipate in other ad-hoc administrative duties / projects assigned by superior.\n\n\u00a0\u00a0Job Requirements:\n\n2 to 5 years of experience\nGood command of both spoken & written English and Chinese\nFamiliar with general office software applications like MS Excel, Word, PowerPoint & Chinese Word Processing;\nStrong coordination, communication and interpersonal skills\nFamiliar with\u00a0MS Word, Excel, PowerPoint & Chinese Word Processing\nProactive, confident and mature with strong interpersonal skills;\n\nWe offer attractive compensation package with a potentially fast-track promotion to the right candidates.\u00a0\u00a0Interested parties, please send us your full resume, current pay level and expected compensation by email.\u00a0 Applicants who don't receive a reply within 6 weeks may consider their applications unsuccessful. All submitted data will only be used for recruitment purposes only.\u00a0\u00a0\n", "employment_types": ["Full Time", "Permanent"], "selling_points": ["2+yrs exp", "5 days work", "Medical allowances"], "locations": ["Wan Chai"], "categories": ["Banking / Finance", "Mortgage"], "post_time": "2022-01-03T04:02:48Z", "salary": {"currency": null, "max": null, "min": null, "period": "monthly", "term": null}, "salary_visible": false, "title_keywords": ["senior officer", "administrator"], "responsibilities": ["scanning", "ad-hoc", "maintenance", "internal and external parties", "coordinate", "scheduling", "repair", "payment", "administrative duties", "booking", "finance team", "planning"], "requirements": {"degrees": [], "majors": [], "languages": ["english", "chinese"], "language_level": ["good command"], "hard_skills": ["excel", "chinese word processing", "word", "powerpoint", "ms excel", "office software", "ms word"], "soft_skills": ["confident", "mature", "communication and interpersonal skills", "interpersonal skills", "coordination", "proactive"], "languages_combined": [{"language": "english", "language_level": ["good command"]}, {"language": "chinese", "language_level": ["good command"]}]}, "experience_required": {"duration": ["2 to 5 years"], "field": []}}, {"job_id": "100003009009719", "location_code": "hk", "company": "Ego Finance Limited", "job_title": "Assistant Manager of Mortgage Department", "description": "Responsibilities:\n\nBe responsible for management of mortgage Loan department and leading a team to meet monthly target\nProvide on-the-job training to team members on regular basis\nEvaluate risk and implement marketing strategies in relation to company\nPrepare business and risk reports for monthly management meeting\nAssist in reviewing and improving the existing system and operation\nSupervise telemarketing day to day work\n\nRequirements:\n\nForm 5 or above\nAt least 3 years experience of mortgage loan and management position\nBe familiar with loan application process and approval of loan applications\nTelemarketing experience is preferable\n\nAn attractive remuneration package including:\n\nCompetitive salary\nDiscretionary Bonus\nBank holiday\nAnnual Leave 12-16 days\nAlternative Saturday-Off\nMedical and hospital insurance\nBirthday Leave\nMarriage Leave\nFuneral Leave\nCareer Progression\nChance to build-up your career path\nValue added training allowance\n\nWorking Hours:\n\nMonday to Friday\u00a0\u00a0\u00a0 :\u00a09:00 am to 6:00 pm (including 1 hour & 10 minutes lunch time)\nSaturday\u00a0 \u00a0 \u00a0 \u00a0 \u00a0 \u00a0 \u00a0 \u00a0 \u00a0 \u00a0: 9:00 am to 1:00 pm (Alternative Saturday-Off)\n\nInterested parties please send your application\u00a0including your full details resume, availability and expected salary for our consideration.\n\n\uff0a\uff0aAll personal data collected will be used for recruitment purpose only\uff0a\uff0a", "employment_types": ["Full Time"], "selling_points": [], "locations": ["Mong Kok"], "categories": ["Banking / Finance", "Credit Analysis / Approval", "Loan", "Mortgage"], "post_time": "2021-12-31T01:56:52Z", "salary": {"currency": null, "max": null, "min": null, "period": "monthly", "term": null}, "salary_visible": false, "title_keywords": ["assistant manager"], "responsibilities": ["evaluate", "management", "marketing strategies", "reports"], "requirements": {"degrees": ["form 5 or above"], "majors": [], "languages": [], "language_level": [], "hard_skills": [], "soft_skills": [], "languages_combined": []}, "experience_required": {"duration": ["at least 3 years"], "field": ["management position"]}}, {"job_id": "100003009015621", "location_code": "hk", "company": "Ambition", "job_title": "Senior Officer, Deposit product", "description": "\nOur client is a well-established banking group with a stable and diversified business portfolio. They are now seeking a high-calibre marketing candidate to join Deposit product team.\n\n\nReporting to Team Head, you will be an active participant in the end-to-end process of product development and feature enhancement of Deposit product, formulating and executing acquisition and retention marketing campaign to facilitate business growth in the business, responsible for liaising with internal and external parties to ensure on-time delivery. You will also monitor sales channel and analyse campaign performances.\nTo qualify, individuals must possess:\n\nBachelor degree or above in related discipline\n1 - 2 years' experience in Marketing / Product gained from retail banking\nCandidates from other Financial Services firms will also be considered\nMotivated individual with a positive attitude and strong business acumen\nStrong communications skills in English and Chinese\n\n\nContact Petty LAM on (852) 3103 4363 or via email petty.lam@ambition.com.hk, APPLY NOW by clicking the button below quoting reference number PL 252068 www.ambition.com.hk\nData provided is for recruitment purposes only\n\nIf this job isn't quite right for you, but you know someone who would be great at this role, why not take advantage of our referral scheme? We offer HKD1000 in Apple gift cards for every referred candidate who we place in a role. Terms & Conditions Apply. https://www.ambition.com.hk/refer-a-friend", "employment_types": ["Full Time", "Permanent"], "selling_points": ["Stable and friendly work environment", "Retail banking product management", "Attractive package and benefits"], "locations": ["Not Specified"], "categories": ["Banking / Finance", "Loan", "Mortgage", "Retail Banking"], "post_time": "2022-01-03T07:10:59Z", "salary": {"currency": null, "max": null, "min": null, "period": "monthly", "term": null}, "salary_visible": false, "title_keywords": ["senior officer"], "responsibilities": ["reporting", "data", "internal and external parties", "monitor", "liaising with", "executing", "contact", "recruitment", "banking", "analyse"], "requirements": {"degrees": ["degree or above", "bachelor"], "majors": [], "languages": ["english", "chinese"], "language_level": [], "hard_skills": ["pl", "scheme", "acumen"], "soft_skills": ["responsible", "positive attitude", "motivated individual", "business acumen", "stable", "active"], "languages_combined": [{"language": "english", "language_level": []}, {"language": "chinese", "language_level": []}]}, "experience_required": {"duration": ["1 - 2 years"], "field": ["retail banking", "marketing"]}}, {"job_id": "100003009009295", "location_code": "hk", "company": "SALT Consulting International Company Limited", "job_title": "Secured Loans (Mortgage) - Credit Approval Manager / Product Manager", "description": "Responsibilities:\n\nResponsible for account management and overdue repayment customers\nAnswering queries raised from customers about settling down overdue repayment\nRestructuring repayment schedule for customers in need\nOverseeing Operational Support Team in offering assistance to Mortgage Team\n\nRequirements:\n\nForm 5 or above\nAt least 3 years of experience in account management and debt restructuring experience\nGood communication and expression skills\nResponsible, mature and independent\nGood PC knowledge (including Chinese Word Processing Input, MS Word, MS Excel)\nEquipped with loan approval experience is preferable\n\nAn attractive remuneration package including:\n\nCompetitive salary\nDiscretionary Bonus\nBank holiday\nAnnual Leave 10-16 days\nAlternative Saturday-Off\nMedical and hospital insurance\nBirthday Leave\nMarriage Leave\nFuneral Leave\nCareer Progression\nChance to build-up your career path\nValue added training allowance\n\nWorking Hours:\n\nMonday to Friday:\u00a09:00 am to 6:00 pm (including 1 hour & 10 minutes lunch time)\nSaturday\u00a0 \u00a0 \u00a0 \u00a0 \u00a0 \u00a0 \u00a0 \u00a0: 9:00 am to 1:00 pm (Alternative Saturday-Off)\n\nInterested parties please send your application including your full details resume, availability and expected salary for our consideration.\n\n\uff0a\uff0aAll personal data collected will be used for recruitment purpose only\uff0a\uff0a", "employment_types": ["Full Time"], "selling_points": ["Credit approval in mortgage application", "Responsbile for Mortgage Product Development", "Conduct market research on Mortgage business"], "locations": ["Central"], "categories": ["Banking / Finance", "Mortgage"], "post_time": "2021-12-30T14:05:09Z", "salary": {"currency": null, "max": null, "min": null, "period": "monthly", "term": null}, "salary_visible": false, "title_keywords": ["manager", "product manager"], "responsibilities": ["management", "operational support", "schedule"], "requirements": {"degrees": ["form 5 or above"], "majors": [], "languages": ["chinese"], "language_level": ["good"], "hard_skills": ["pc knowledge", "ms excel", "chinese word processing", "ms word"], "soft_skills": ["communication", "independent", "responsible", "mature"], "languages_combined": [{"language": "chinese", "language_level": ["good"]}]}, "experience_required": {"duration": ["at least 3 years"], "field": ["account management"]}}, {"job_id": "100003009008566", "location_code": "hk", "company": "Mega Jobs Development Limited", "job_title": "Associate, Secured & SME Lending", "description": "Our Client is an international commercial bank in Hong Kong. It is now inviting high caliber professionals to join their Hong Kong Banking Company. \u00a0\n\n\n\nResponsibilities:\u00a0\n\nTo assist new product development, acquisition, utilization and management of Mortgage and Secured Lending products\nWork closely with related departments in implementing new product initiatives and marketing campaigns in a timely manner\nHelp to develop online and offline marketing communication materials, working closely with internal and external parties\nPrepare marketing proposal, product P&L, campaign evaluation and MIS analysis.\n\nTo follow up on the regulatory guidelines from HKMA or other regulatory bodies\nProvide update and training to sales channels and make sure the new measures are implemented timely as well as ensuring effective delivery of business targets\nReview and fine-tune product features and process streamlining to ensure product competitiveness and speedy turnaround\n\n\u00a0Requirements\n\nDegree holder\n\nAt least 2 years\u2019 relevant working experience, preferable in banking industry\nGood analytical and communication skills\nGood team player with a strong sense of ownership\nDetailed minded\nAble to work independently and under pressure\nGood command of both written and spoken English and Chinese (including Putonghua)\n\n\nCompetitive package will be offered to the right Candidates. If you are interested, please send your full resume with current and expected salary in word format to us by email. For more information on our services and other career opportunities, please visit our web site at www.megajobshr.com.\u00a0\n\nAll applications will be treated in strictly confidential and all personal data collected will be used for recruitment purpose only.", "employment_types": ["Full Time"], "selling_points": [], "locations": ["Not Specified"], "categories": ["Banking / Finance", "Mortgage"], "post_time": "2021-12-30T08:22:42Z", "salary": {"currency": null, "max": null, "min": null, "period": "monthly", "term": null}, "salary_visible": false, "title_keywords": ["associate"], "responsibilities": ["management", "guidelines", "analysis", "internal and external parties", "a timely manner", "review", "p&l", "develop", "communication", "marketing campaigns", "evaluation"], "requirements": {"degrees": ["degree holder"], "majors": [], "languages": ["putonghua", "english", "chinese"], "language_level": ["good command"], "hard_skills": ["word", "web"], "soft_skills": ["communication skills", "good team player", "work independently", "under pressure", "detailed"], "languages_combined": [{"language": "putonghua", "language_level": ["good command"]}, {"language": "english", "language_level": ["good command"]}, {"language": "chinese", "language_level": ["good command"]}]}, "experience_required": {"duration": ["at least 2 years"], "field": ["banking industry", "relevant working experience"]}}, {"job_id": "100003009002762", "location_code": "hk", "company": "Hang Seng Bank Ltd", "job_title": "Assistant Product Performance Manager", "description": "Responsibilities\u00a0\u00a0\n\nSolicit mortgage business opportunities to achieve individual targets.\nCross-sell other banking products to mortgage customers.\nProvide professional mortgage services to bank customers.\nRecommend solutions to mortgage applicants.\nExpand & maintain business network.\nBuild and maintain good client base and relationship.\n\u00a0\n\nRequirements\u00a0\n\nSecondary education or above. Degree holder is preferred.\nMinimum 3 years bank mortgage sales & service experience with proven sales track records.\nPossess IIQAS or other required qualifications under SFC.\nStrong network with related business partners.\nGood knowledge of mortgage products and related credit policies.\nGood command written and spoken English and Chinese (including Putonghua).\n\nFor more details about career opportunities with the Bank, please visit our website http://www.cncbinternational.com/careers/en/index.jsp. Please apply with full resume stating current and expected salaries.\n\nPersonal data collected will be used for recruitment related purposes only. Applicants not invited for interview within 6 weeks may consider their applications unsuccessful. However, applicants may be considered for other suitable positions within the Group for a period of not more than 2 years. Personal data will be destroyed at any time after 3 months.\n\nChina CITIC Bank International is committed to being an equal opportunities employer and intends to provide a work environment free of unlawful discrimination or harassment. All employment decisions will be made in a non-discriminatory manner.", "employment_types": ["Full Time", "Permanent"], "selling_points": [], "locations": ["Not Specified"], "categories": ["Banking / Finance", "Analyst", "Loan", "Mortgage"], "post_time": "2021-12-28T14:52:35Z", "salary": {"currency": null, "max": null, "min": null, "period": "monthly", "term": null}, "salary_visible": false, "title_keywords": ["manager", "assistant"], "responsibilities": ["client base", "business opportunities", "maintain", "banking"], "requirements": {"degrees": ["secondary education", "degree holder"], "majors": [], "languages": ["putonghua", "english", "chinese"], "language_level": ["good command"], "hard_skills": [], "soft_skills": ["committed"], "languages_combined": [{"language": "putonghua", "language_level": ["good command"]}, {"language": "english", "language_level": ["good command"]}, {"language": "chinese", "language_level": ["good command"]}]}, "experience_required": {"duration": ["minimum 3 years"], "field": []}}, {"job_id": "100003009006347", "location_code": "hk", "company": "China CITIC Bank International Limited", "job_title": "Business Development Manager, Mortgage Sales", "description": "Portfolio Management Department - Consumer Assets\n\nWe are currently seeking high caliber individual to join our department as Assistant Product Performance Manager.\n\n\n\nPrincipal Responsibilities\n\nConduct Consumer Assets portfolio and product profitability analysis and produce analytical insight from management information database and market data\nSupport the development of regular product performance management reporting with timely and insightful information on KPIs and business trends\nAssist in the establishment product profitability model and provide business case assumptions\nCollaborate with business and functional units to ensure the integrity of management information data and quality of reporting\n\nRequirements\nUniversity degree in a finance / accounting or related discipline\nMinimum of three years\u2019 experience in financial analysis, management reporting and business planning, preferably in credit card and consumer lending business\nStrong knowledge of PC application software such as MS Access, Excel, Datawatch Monarch\nGood communication, interpersonal, analytical and problem solving skills\nResilient, capable to work effectively and responsibly in a dynamic environment\nAbility to work independently and under pressure\nProficiency in both English and Chinese\nGreat sense of ownership and servicing mindset to ensure efficient and effective customer service processes\u00a0\nIf you would like to explore other opportunities at Hang Seng Hong Kong, please visit\u00a0www.hangseng.com/careers/\u00a0for details.\nThe health and safety of our employees and candidates is very important to us. Due to the current situation related to the Novel Coronavirus (2019-nCoV), we\u2019re leveraging our digital capabilities to ensure we can continue to recruit top talent at the HSBC Group. \u00a0As your application progresses, you may be asked to use one of our digital tools to help you through your recruitment journey.\u00a0 If so, one of our Resourcing colleagues will explain how our video-interviewing technology will be used throughout the recruitment process and will be on hand to answer any questions you might have.\u00a0\nAll information provided by applicants will be used only for recruitment purposes and will be used strictly in accordance with the Bank's personal data policies, a copy of which may be obtained by the applicant upon request. Unless otherwise instructed in writing by the applicant concerned, applicants may be considered for other suitable positions within the Bank and its related companies. The personal data of unsuccessful job applicants may be retained for a maximum of two years from the date when the job application is rejected and such data may be retained for a longer period if there is a subsisting reason that obliges the Bank to do so, after which the personal data will be destroyed.", "employment_types": ["Full Time"], "selling_points": ["Provide professional mortgage services to customer", "Cross-sell banking products to mortgage customers", "Build good client base and relationship"], "locations": ["Not Specified"], "categories": ["Banking / Finance", "Mortgage"], "post_time": "2021-12-29T08:16:48Z", "salary": {"currency": null, "max": null, "min": null, "period": "monthly", "term": null}, "salary_visible": false, "title_keywords": ["business development manager", "sales"], "responsibilities": ["collaborate with", "reporting", "management", "data", "analysis", "quality", "management reporting", "database", "kpis", "market data"], "requirements": {"degrees": ["university degree"], "majors": ["finance", "accounting"], "languages": ["english", "chinese"], "language_level": ["proficiency"], "hard_skills": ["excel", "reason", "financial analysis", "dynamic", "pc", "problem solving skills"], "soft_skills": ["work effectively", "efficient", "dynamic environment", "work independently", "under pressure", "capable", "communication", "analytical and problem solving skills", "customer service", "novel", "interpersonal"], "languages_combined": [{"language": "english", "language_level": ["proficiency"]}, {"language": "chinese", "language_level": ["proficiency"]}]}, "experience_required": {"duration": ["minimum of three years"], "field": ["management", "financial", "credit card", "business", "planning"]}}, {"job_id": "100003009006919", "location_code": "hk", "company": "China Construction Bank (Asia) Corporation Limited", "job_title": "Relationship Manager (Non-borrowing client) \u2013 Commercial Banking (Ref. no.: NBRM/CMB/JDB)", "description": "Job Descriptions:\n\n\n\nManage a portfolio of non-borrowing clients in Commercial Banking Division\nHandle general enquiries and resolve issues\nComply with the established policies and procedures to ensure the safety and security of bank\u2019s and customer\u2019s asset\nComply and adhere to bank\u2019s AML Compliance procedures, including but not limited to customer due diligence and ongoing transaction monitoring.\n\nJob Requirements:\n\nDegree holder in Business, Economics or related disciplines is preferred\nMinimum 3 years of banking experience as a front-line role in related industry\n\nSales-driven, result-oriented and be able to work under pressure\nQualifications in IIQE/HKSI related areas are preferred\n\nProficiency in the financial services/products offered to middle market companies\nGood communication skills in both English and Chinese (Cantonese & Putonghua)\nProficient in PC applications, including Microsoft Word and Excel\n\nTo apply, please send your detailed resume\u00a0stating present and expected salary\u00a0to one of the following channels:-\n\nBy Email\nBy Fax: 3718 2910\n\nApplicants who are not contacted within 8 weeks may consider their applications unsuccessful and their personal data will be retained by the bank for a period up to two years.\n\nAll information provided by applicants will be used for recruitment purposes only and will be used strictly in accordance with the bank's personal data policies, a copy of which will be provided upon request.", "employment_types": ["Full Time", "Permanent"], "selling_points": ["Non Borrowing RM", "Handle general enquiries and resolve issues", "Bachelor Degree or 3 years of experience"], "locations": ["Kowloon Bay"], "categories": ["Banking / Finance", "Corporate Banking", "Mortgage", "Financial Services"], "post_time": "2021-12-29T12:01:54Z", "salary": {"currency": null, "max": null, "min": null, "period": "monthly", "term": null}, "salary_visible": false, "title_keywords": ["relationship manager"], "responsibilities": ["aml", "policies", "compliance", "procedures", "monitoring", "customer due diligence", "banking"], "requirements": {"degrees": ["degree holder"], "majors": ["related disciplines", "economics", "business"], "languages": ["cantonese", "putonghua", "english", "chinese"], "language_level": ["good"], "hard_skills": ["excel", "iiqe", "microsoft word", "hksi", "pc applications"], "soft_skills": ["communication skills", "work under pressure", "driven", "result-oriented", "detailed"], "languages_combined": [{"language": "cantonese", "language_level": ["good"]}, {"language": "putonghua", "language_level": ["good"]}, {"language": "english", "language_level": ["good"]}, {"language": "chinese", "language_level": ["good"]}]}, "experience_required": {"duration": ["minimum 3 years"], "field": ["related", "banking experience"]}}, {"job_id": "100003008992755", "location_code": "hk", "company": "Public Finance Limited", "job_title": "Senior Marketing Officer (Mortgage Loan Sales) ($20,000+ plus Commission)", "description": "Responsibilities\nTo achieve mortgage loan sales target\nTo establish good relationship with business partners such as solicitor firms, property agencies, referral intermediaries, etc\nRequirements\n3 years experience in mortgage loan sales\nHave developed a good people-network with brokers / Mortgage Referral Services Companies / Estate Agencies/Solicitor firms is an advantage\nApplications from the existing Estate Agencies are welcome\nWork in Central Office\n(Candidate who posses less experience may be considered as Marketing Officer)\nBenefits\nInsurance Benefits\nStudy subsidy\nApplication Method:\n\nBy Whatsapp : 9309 2925\nBy E-mail via \"Apply Now\"", "employment_types": ["Full Time", "Permanent"], "selling_points": [], "locations": ["Central"], "categories": ["Banking / Finance", "Loan", "Mortgage", "Sales, CS & Business Devpt", "Sales - Sales Management"], "post_time": "2021-12-22T06:10:59Z", "salary": {"currency": null, "max": null, "min": null, "period": "monthly", "term": null}, "salary_visible": false, "title_keywords": ["sales", "senior marketing officer"], "responsibilities": ["good relationship", "sales target"], "requirements": {"degrees": [], "majors": [], "languages": [], "language_level": [], "hard_skills": [], "soft_skills": [], "languages_combined": []}, "experience_required": {"duration": ["3 years"], "field": ["marketing"]}}, {"job_id": "100003008992509", "location_code": "hk", "company": "Global International Credit Limited", "job_title": "Credit Manager - Mortgage Loan", "description": "Global International Credit Limited (Stock Code.1669) is one of the leading mortgage finance companies in Hong Kong. To cope with our fast expansion plan and build up a strong team in our\u00a0Central office located at World Wide House,\u00a0we invite high caliber professionals to join us and be a member of our successful team. If you are looking for a career, not just a job, here is a good opportunity for you.\n\nKey Responsibilities:\n\nExercise due diligence on individual mortgage loan and approve credit applications within delegated authority by taking into consideration in relating to credit risk, property valuation, legal risk and market risk.\nMake contribution to formulate credit strategies/policies to assist business growth and maximize profitability.\nManage mortgage portfolio proactively to reduce delinquency and bad debt by taking proactive remedial actions at early stage.\nProvide an independent assessment of credit proposals.\nSite Inspection when required.\n\nRequirements:\n\nDegree or above\nAt least 6 years experience in Mortgage loan approval.\nStrong communication and management skills\nProficient in written English and Chinese", "employment_types": ["Full Time", "Permanent"], "selling_points": ["Evaluate and process credit applications", "6 years above of credit assessment", "Excellent communication skills"], "locations": ["Central"], "categories": ["Banking / Finance", "Mortgage"], "post_time": "2021-12-22T05:07:22Z", "salary": {"currency": null, "max": null, "min": null, "period": "monthly", "term": null}, "salary_visible": false, "title_keywords": ["manager"], "responsibilities": ["due diligence", "valuation", "policies", "site inspection"], "requirements": {"degrees": ["degree or above"], "majors": [], "languages": ["english", "chinese"], "language_level": ["proficient"], "hard_skills": [], "soft_skills": ["communication"], "languages_combined": [{"language": "english", "language_level": ["proficient"]}, {"language": "chinese", "language_level": ["proficient"]}]}, "experience_required": {"duration": ["at least 6 years"], "field": []}}, {"job_id": "100003008994150", "location_code": "hk", "company": "Industrial and Commercial Bank of China (Asia) Limited", "job_title": "Senior Officer, Retail Loans Processing (Loans Administration Department)", "description": "Job Duties:\n\nAssignment of daily operation to operators;\nPerform checking & authorisation on Retail loans booking & disbursements, loan repayment & loan maintenance;\nPreparing & checking of the Settlement calculation related to property discharge;\nArrangement in Facility setting & maintainence with fee collection;\nArranging & checking of external reportings on loans sold to external parties;\nCo-ordinate with branch/ department staffs on customers requests.\n\nJob Requirements:\n\nPost-secondary or above.\nAt least 3 years of banking experience in loans processing, with 2 years supervisory level.\nFamiliar retail loans products such as mortgage and hire purchase loans.\nKnowledge of PC operations and good typewriting skill in Chinese and English.\nGood interpersonal communication skills.\nGood command of both written and spoken English and Chinese.\n\n\n\nInterested parties, please click \u201cApply Now\u201d for application.\n\n\nPersonal data collected will be used for recruitment purpose only.", "employment_types": ["Full Time"], "selling_points": [], "locations": ["Kwun Tong Area"], "categories": ["Banking / Finance", "Loan", "Mortgage", "Retail Banking"], "post_time": "2021-12-22T11:28:25Z", "salary": {"currency": null, "max": null, "min": null, "period": null, "term": null}, "salary_visible": false, "title_keywords": ["senior officer"], "responsibilities": ["maintenance", "co-ordinate with", "external parties", "daily operation", "checking", "booking", "disbursements"], "requirements": {"degrees": [], "majors": [], "languages": ["english", "chinese"], "language_level": ["good command", "good"], "hard_skills": ["processing", "typewriting", "pc operations"], "soft_skills": ["communication skills", "interpersonal"], "languages_combined": [{"language": "english", "language_level": ["good command", "good", "good"]}, {"language": "chinese", "language_level": ["good command", "good", "good"]}]}, "experience_required": {"duration": ["at least 3 years", "2 years"], "field": ["supervisory level", "banking experience"]}}, {"job_id": "100003008994148", "location_code": "hk", "company": "Industrial and Commercial Bank of China (Asia) Limited", "job_title": "Assistant Officer to Senior Officer, Retail Credit Administration (Loans Administration Department)", "description": "Job Duties:\n\nMonitor implementation of facilities by checking the necessary documents are in order, such as facility letters duly accepted, guarantees duly signed and accounts duly opened with us.\nCheck confirmation letters from solicitor firms to ensure that mortgages are executed in accordance with our instructions.\nMaintain close contact with other departments and solicitor firms to follow up details in documentation, progress of reassignment etc.\nMaintain customers\u2019 information, data, statements, correspondence etc. in proper order. Forwards security documents to vault for safe-keeping & maintains copies of such documents in credit files.\n\nJob Requirements:\n\nPost-secondary or above\nMinimum 1 year of working experience in credit administration\nKnowledge of PC operations and good typewriting skill in Chinese and English.\nGood interpersonal communication skills\nGood command of both written and spoken English and Chinese\u00a0\n\nInterested parties, please click \u201cApply Now\u201d for application.\n\n\n\u00a0Personal data collected will be used for recruitment purpose only.", "employment_types": ["Full Time", "Permanent"], "selling_points": [], "locations": ["Kwun Tong Area"], "categories": ["Banking / Finance", "Loan", "Mortgage", "Retail Banking"], "post_time": "2021-12-22T11:28:24Z", "salary": {"currency": null, "max": null, "min": null, "period": null, "term": null}, "salary_visible": false, "title_keywords": ["assistant officer", "senior officer"], "responsibilities": ["data", "letters", "checking", "monitor", "implementation", "maintain", "contact", "documentation"], "requirements": {"degrees": [], "majors": [], "languages": ["english", "chinese"], "language_level": ["good command", "good"], "hard_skills": ["pc operations", "typewriting"], "soft_skills": ["communication skills", "interpersonal"], "languages_combined": [{"language": "english", "language_level": ["good command", "good", "good"]}, {"language": "chinese", "language_level": ["good command", "good", "good"]}]}, "experience_required": {"duration": ["minimum 1 year"], "field": ["administration"]}}, {"job_id": "100003008996276", "location_code": "hk", "company": "Speedy Finance Limited", "job_title": "Finance Manager", "description": "Responsibilities:\u00a0\u00a0\u00a0\u00a0\u00a0\u00a0\u00a0\u00a0\u00a0\u00a0\u00a0\u00a0\n\n-\u00a0\u00a0\u00a0\u00a0\u00a0\u00a0\u00a0\u00a0\u00a0 Responsible for daily accounting, treasury & finance functions of the group of companies.\n\n-\u00a0\u00a0\u00a0\u00a0\u00a0\u00a0\u00a0\u00a0\u00a0 Responsible for human resources management tasks of the group of companies.\n\n-\u00a0\u00a0\u00a0\u00a0\u00a0\u00a0\u00a0\u00a0\u00a0 Responsible for company secretary tasks of the group of companies.\n\n-\u00a0\u00a0\u00a0\u00a0\u00a0\u00a0\u00a0\u00a0\u00a0 Responsible for maintaining full set of ledgers of the group of companies.\n\n-\u00a0\u00a0\u00a0\u00a0\u00a0\u00a0\u00a0\u00a0\u00a0 Develop cash flow projections.\n\n-\u00a0\u00a0\u00a0\u00a0\u00a0\u00a0\u00a0\u00a0\u00a0 Prepare monthly management reports and financial analysis for group companies\n\n-\u00a0\u00a0\u00a0\u00a0\u00a0\u00a0\u00a0\u00a0\u00a0 Prepare annual budget and periodic forecast.\n\n-\u00a0\u00a0\u00a0\u00a0\u00a0\u00a0\u00a0\u00a0\u00a0 Liaise with external auditors and bank relationship managers\n\n-\u00a0\u00a0\u00a0\u00a0\u00a0\u00a0\u00a0\u00a0\u00a0 Handle tax filings and other taxation issues.\n\n-\u00a0\u00a0\u00a0\u00a0\u00a0\u00a0\u00a0\u00a0\u00a0 Participate in ad-hoc projects.\u00a0\u00a0\n\nRequirements:\n\n-\u00a0\u00a0\u00a0\u00a0\u00a0\u00a0\u00a0\u00a0\u00a0\u00a0\u00a0 Qualified accountant with minimum 3 years\u2019 supervisory/managerial experience\n\n-\u00a0\u00a0\u00a0\u00a0\u00a0\u00a0\u00a0\u00a0\u00a0\u00a0\u00a0 Good command of English, Mandarin and Cantonese;\n\n-\u00a0\u00a0\u00a0\u00a0\u00a0\u00a0\u00a0\u00a0\u00a0\u00a0\u00a0 Proficiency in Microsoft Office Suite and MYOB\n\n-\u00a0\u00a0\u00a0\u00a0\u00a0\u00a0\u00a0\u00a0\u00a0\u00a0\u00a0 Knowledge in company secretarial field\n\n-\u00a0\u00a0\u00a0\u00a0\u00a0\u00a0\u00a0\u00a0\u00a0\u00a0\u00a0 Self-motivated and able to work independently\n\n-\u00a0\u00a0\u00a0\u00a0\u00a0\u00a0\u00a0\u00a0\u00a0\u00a0\u00a0 Immediately available is preferred", "employment_types": ["Full Time"], "selling_points": [], "locations": ["Central"], "categories": ["Accounting", "Accountant", "Finance / Accounting Manager", "Banking / Finance", "Mortgage"], "post_time": "2021-12-23T06:20:40Z", "salary": {"currency": null, "max": null, "min": null, "period": "monthly", "term": null}, "salary_visible": false, "title_keywords": ["finance manager"], "responsibilities": ["tax", "taxation", "management", "maintaining", "budget", "develop", "financial analysis", "cash flow", "management reports", "forecast", "liaise with", "daily accounting", "ad-hoc projects", "external auditors"], "requirements": {"degrees": [], "majors": [], "languages": ["cantonese", "english", "mandarin"], "language_level": ["good command"], "hard_skills": ["microsoft office suite", "myob"], "soft_skills": ["self-motivated", "work independently"], "languages_combined": [{"language": "cantonese", "language_level": ["good command"]}, {"language": "english", "language_level": ["good command"]}, {"language": "mandarin", "language_level": ["good command"]}]}, "experience_required": {"duration": ["minimum 3 years"], "field": ["managerial", "supervisory"]}}, {"job_id": "100003008995193", "location_code": "hk", "company": "Dah Sing Financial Group", "job_title": "Assistant Manager, Operations", "description": "Job Purpose:\nAssist on the daily account opening, client onboarding, and account review process run smoothly so as to minimize the AML risk of Private Banking\nAssist on assurance of Customer Due Diligence (\"CDD\") and customer data input quality\nPreparation of MIS report on Private Banking AML risk control\nMain Responsibilities:\nAssist the Operation Manager to work with front-line staffs in account opening and client onboarding process, including review documents, review CDD data and reports, conduct media search and follow up the process until complete\nAssist the Operation Manager to work with front-line sales in CDD reviews (regular review, review upon trigger events and review triggered by internal or external alert) and ensure timely completion\nReview database to ensure the quality of CDD and customer data input\nPerform account opening\nParticipate in system development projects such as UAT\nPrepare MIS report on Private Banking AML risk control\nPrepare the first draft on Sources of Wealth assessment\nPrepare training materials related to AML issues\nSupport other operations functions\nAd-hoc operation issues\nRequirements:\nDegree Holder of Business and Finance.\nAt least 2 years supporting experience in handling CDD, client onboarding and account review process as well as transaction monitoring in financial institution.\nAbility to multi-task and work under pressure\nGood analytical skill and self-motivated.\nGood command of written and spoken English and Chinese\nPlease note that only shortlisted candidates will be notified.", "employment_types": ["Full Time", "Permanent"], "selling_points": ["Assist on the daily account opening", "Degree Holder of Business and Finance", "At least 2 years supporting experience"], "locations": ["Not Specified"], "categories": ["Banking / Finance", "Mortgage", "Financial Services", "Wealth Management"], "post_time": "2021-12-23T03:07:05Z", "salary": {"currency": null, "max": null, "min": null, "period": "monthly", "term": null}, "salary_visible": false, "title_keywords": ["operations", "assistant manager,"], "responsibilities": ["ad-hoc", "control", "aml", "uat", "data", "account opening", "cdd", "review", "quality", "banking", "operations", "regular review", "reports", "database", "customer data", "report"], "requirements": {"degrees": ["degree holder"], "majors": ["finance", "business"], "languages": ["english", "chinese"], "language_level": ["good command"], "hard_skills": ["cdd", "analytical skill"], "soft_skills": ["analytical skill", "multi-task", "self-motivated", "work under pressure"], "languages_combined": [{"language": "english", "language_level": ["good command"]}, {"language": "chinese", "language_level": ["good command"]}]}, "experience_required": {"duration": ["at least 2 years"], "field": ["financial"]}}, {"job_id": "100003008987545", "location_code": "hk", "company": "", "job_title": "Head of Mortgage Business", "description": "Our Mortgage Loan business is expanding. We are looking for a Head of Mortgage Business, join us if you have strategic mindset, with strong network in industry and looking for new challenge.\n\nResponsibilities:\n\nFormulate and execute high quality business strategies to drive growth and achieve the company goals\nOversee all business development and operation matters of the business unit\nLead and motivate team to meet business targets\nManage all day-to-day operation matters\nResponsible for overall loan portfolio quality and employ safeguards to minimize impairment loss\nDevelop new business source from time to time\nMonitor market development and obtain market intelligence as to maintain market competitiveness\nConstant review on credit policies and credit processes according to the changing market environment\nStreamline operation processes to enhance overall operational efficiency and effectiveness\nEnsure compliance of Money Lending Ordinance in all operation workflow\n\nRequirements:\n\nDegree holder in Business Administration Or related disciplines \u00a0\nMinimum 10 years of experience in Mortgage/ Personal loan/ Money lending or finance-related business\nStrong leadership with practical experience of team work in achieving the business goal\u00a0\nPossess the ability of strategic planning and monitoring of mortgage loan business\nSales Oriented with proven track record in mortgage and loan sales and network\nWell versed in loan processing, procedures and relevant regulatory requirements\nStrong interpersonal, problem solving and communication and customer service skills\nGood command of English, Cantonese and Mandarin\nProficiency in computer skills including MS Excel\n\nCompetitive Salary will be offered to the right candidate.\u00a0\n\nOr\u00a0Interested parties, please contact Ms Chiu at 2316 8860.\u00a0", "employment_types": ["Full Time", "Permanent"], "selling_points": ["Lead team,strategic planning for mortgage business", "Sales Oriented with proven track record", "Streamline operation process & enhance efficiency"], "locations": ["Central & Western Area"], "categories": ["Banking / Finance", "Mortgage", "Sales, CS & Business Devpt", "Business Development", "Sales - Sales Management"], "post_time": "2021-12-20T06:59:05Z", "salary": {"currency": null, "max": null, "min": null, "period": "monthly", "term": null}, "salary_visible": false, "title_keywords": [], "responsibilities": ["develop new business", "policies", "review", "monitor", "quality", "ensure compliance", "maintain", "day-to-day operation"], "requirements": {"degrees": ["degree holder"], "majors": ["related disciplines", "business administration"], "languages": ["cantonese", "english", "mandarin"], "language_level": ["good command"], "hard_skills": ["problem solving", "goal", "ms excel", "computer skills", "processing"], "soft_skills": ["customer service skills", "problem solving", "communication", "leadership", "interpersonal"], "languages_combined": [{"language": "cantonese", "language_level": ["good command"]}, {"language": "english", "language_level": ["good command"]}, {"language": "mandarin", "language_level": ["good command"]}]}, "experience_required": {"duration": ["minimum 10 years"], "field": ["related", "finance", "business", "team"]}}, {"job_id": "100003008987219", "location_code": "hk", "company": "Bank of China (Hong Kong) Limited", "job_title": "Secured & Retail Lending Manager", "description": "Responsibilities:\nThis role is to support Mortgage and Secured Retail Lending businesses in business intelligence and finance related matters, ranging from management information production, portfolio analysis to budgeting and forecasting. Major responsibilities include:\nPerform market intelligence studies, integrate the findings to generate ideas on sales and marketing strategies\nSupport Mortgage and Secured Retail Lending businesses by planning and implementing marketing and sales promotion initiatives to achieve the business goals\nSupport and advise Mortgage and Secured Retail Lending businesses on its initiatives, providing financial advice, business and financial projections and ongoing result tracking\nMonitor and report the business progress and alert for proper action in a timely manner through ongoing keep track of KPI\nDesign and implement appropriate management information reports to meet business needs\nSupport innovative and transformational projects including but not limited to Open API, blockchain, digital banking, mobile banking etc. in forecasting and evaluation of benefits realization\nRequirements:\nDegree holder with major in Business Administration, Finance, Marketing or related discipline\nAt least 3-5 years of banking experience, preferably in marketing and product management\nIndependent, ability to work under pressure and sensitive to market changes with a proactive approach to drive business growth\nStrong knowledge and experience in using Microsoft Office Software i.e. Word, Excel and PowerPoint\nExcellent communication and presentation skills with good command in both written and spoken English and Chinese", "employment_types": ["Full Time"], "selling_points": ["Monitor and report the business progress", "Degree holder with major in Business Admin.", "At least 3-5 years of banking experience"], "locations": ["Central"], "categories": ["Banking / Finance", "Mortgage"], "post_time": "2021-12-20T05:08:49Z", "salary": {"currency": null, "max": null, "min": null, "period": "monthly", "term": null}, "salary_visible": false, "title_keywords": ["manager"], "responsibilities": ["management", "business goals", "ideas", "marketing strategies", "tracking", "budgeting", "analysis", "monitor", "a timely manner", "design", "reports", "banking", "report", "forecasting", "planning"], "requirements": {"degrees": [], "majors": [], "languages": [], "language_level": [], "hard_skills": [], "soft_skills": [], "languages_combined": []}, "experience_required": {"duration": [], "field": []}}]