[{"job_id": "100003009053269", "location_code": "hk", "company": "JQ Securities (Hong Kong) Limited", "job_title": "Settlement and Operations Officer", "description": "Key Responsibilities:\n\nReport to the team head, perform daily settlement operation (daily processing, corporate actions, physical certificates, stock and cash management, trade and stock reconciliation, IPO and placing, etc.) and monitor the operational activities in respect to the requirements of SFC, IRD, HKEx etc.\nHandle daily booking and ensure all trading processing are completed correctly and properly; Liaise and resolve settlement issues with clients and counterparties;\nPrepare the settlement payments, receipts and reports;\nHandle Market Rehearsal and system UAT when necessary;\nHandle data input and new account opening with settlement system;\nAssist in account opening, KYC documents for our asset management team;\nHandle other ad hoc duties.\n\nRequirements:\n\nDegree holder in any discipline;\nAround 1-3 years relevant experience;\nKnowledge of CCASS, (iAsia Online) iBoss systems is preferred;\nGood PC knowledge including Excel and MS Word;\nGood command of written and spoken English, Cantonese and Mandarin;\nSelf-motivated, detail oriented, reliable with good communication skills.\nWe offer Competitive Remuneration and Benefits package including\u00a0Double Pay, Performance Bonus, Group Medical & Dental\u00a0and Career Prospects to the right candidates.\n\n\nInterested parties please send your full resume with expected salary to us by clicking \"Apply Now\".\n\nPersonal data collected will be used for recruitment purpose only.\n\nFor details, please visit our official website:\u00a0http://www.jqshk.com/index_hk.html", "employment_types": ["Full Time", "Permanent"], "selling_points": ["Guaranteed 13 months\u2019 salary", "Five-day work week, Work life balance", "All rounded and dynamic role"], "locations": ["Wan Chai"], "categories": ["Banking / Finance", "Order Processing & Operation / Settlement"], "post_time": "2022-01-17T06:37:14Z", "salary": {"currency": "HKD", "max": 29999, "min": 20000, "period": "monthly", "term": null}, "salary_visible": true, "title_keywords": ["operations officer"], "responsibilities": ["liaise", "ad hoc duties", "management", "receipts", "uat", "account opening", "monitor", "data input", "asset management", "payments", "reports", "kyc", "handle daily booking", "resolve settlement issues", "report"], "requirements": {"degrees": ["degree holder"], "majors": [], "languages": ["cantonese", "english", "mandarin"], "language_level": ["good command"], "hard_skills": ["excel", "pc knowledge", "ccass", "ms word"], "soft_skills": ["communication skills", "detail oriented", "self-motivated", "reliable"], "languages_combined": [{"language": "cantonese", "language_level": ["good command"]}, {"language": "english", "language_level": ["good command"]}, {"language": "mandarin", "language_level": ["good command"]}]}, "experience_required": {"duration": ["1-3 years"], "field": ["relevant experience"]}}, {"job_id": "100003009053759", "location_code": "hk", "company": "Hang Seng Bank Ltd", "job_title": "Global Markets Operations Manager", "description": "Global Banking & Markets -\u00a0Global Markets Operations\n\n\nHang Seng's\u00a0Global Markets Operations is a team of experienced banking operations professionals who strive for delivering time-to-market, efficient and world-class processing services to customers, corporations, financial institutions and internal units. We are responsible for driving every part of the trade lifecycle post execution. We manage settlement activity, risk and control, while ensuring the delivery of regulatory compliance and seamless operational client services.\n\n\n\nWe are currently seeking a high caliber professional to join our department as\u00a0Global Markets Operations Manager.\n\n\u00a0Principal responsibilities\n\nHandle post-trade processing of Fixed Income products and perform life cycle management / settlement via BO systems;\nOversee daily operations to ensure compliance with internal and related regulatory requirements;\nProvide support on project / systems implementation, workflow design, and process re-engineering in supporting Global Markets Operations;\nWork closely with various stakeholders including business users, IT departments, legal and compliance to ensure effective operations\n\nRequirements\n\nUniversity degree in a related discipline OR other relevant qualifications;\nMinimum of five years' banking experience in products settlement preferably in GM products;\nAttentiveness to details and self-motivated with the ability to work independently and under pressure;\nResilient, capable to work responsibly in a dynamic environment;\nProficiency in both English and Chinese, fluency in Putonghua an advantage;\nGreat sense of ownership and servicing mindset to ensure efficient and effective customer service processes\n\nIf you would like to explore other opportunities at Hang Seng Hong Kong, please\u00a0visit\u00a0www.hangseng.com/careers/\u00a0for details.\n\nThe health and safety of our employees and candidates is very important to us. Due to the current situation related to the Novel Coronavirus (2019-nCoV), we\u2019re leveraging our digital capabilities to ensure we can continue to recruit top talent at the HSBC Group. \u00a0As your application progresses, you may be asked to use one of our digital tools to help you through your recruitment journey.\u00a0 If so, one of our Resourcing colleagues will explain how our video-interviewing technology will be used throughout the recruitment process and will be on hand to answer any questions you might have.\nAll information provided by applicants will be used only for recruitment purposes and will be used strictly in accordance with the Bank's personal data policies, a copy of which may be obtained by the applicant upon request. Unless otherwise instructed in writing by the applicant concerned, applicants may be considered for other suitable positions within the Bank and its related companies. The personal data of unsuccessful job applicants may be retained for a maximum of two years from the date when the job application is rejected and such data may be retained for a longer period if there is a subsisting reason that obliges the Bank to do so, after which the personal data will be destroyed.", "employment_types": ["Full Time", "Permanent"], "selling_points": [], "locations": ["Not Specified"], "categories": ["Banking / Finance", "Others", "Order Processing & Operation / Settlement"], "post_time": "2022-01-17T07:28:10Z", "salary": {"currency": null, "max": null, "min": null, "period": "monthly", "term": null}, "salary_visible": false, "title_keywords": ["operations manager"], "responsibilities": ["management", "provide support", "regulatory requirements", "operations", "systems", "compliance", "implementation", "design", "ensure compliance", "daily operations", "re-engineering"], "requirements": {"degrees": ["university degree"], "majors": [], "languages": ["putonghua", "english", "chinese"], "language_level": ["fluency", "advantage", "proficiency"], "hard_skills": ["gm", "dynamic", "reason"], "soft_skills": ["efficient", "self-motivated", "work independently", "under pressure", "capable", "dynamic environment", "customer service", "novel"], "languages_combined": [{"language": "putonghua", "language_level": ["fluency"]}, {"language": "english", "language_level": ["proficiency", "fluency", "advantage"]}, {"language": "chinese", "language_level": ["proficiency", "fluency", "advantage"]}]}, "experience_required": {"duration": ["minimum of five years"], "field": ["banking experience"]}}, {"job_id": "100003009049946", "location_code": "hk", "company": "Hang Seng Bank Ltd", "job_title": "Cards and Loans Operations Associate (Merchant & Accounting Settlement Team)", "description": "Digital Business Services - Cards and Loans Operations\n\nHang Seng's Operations is a team of experienced banking operations professionals who strive for delivering time-to-market, efficient and world-class processing services to customers, corporations, financial institutions and internal units.\n\nCards Operations, support the distribution of cards, account maintenance and merchant operations.\n\nShould you join our Operations unit, you will focus on delivering excellent services through teaming up with fellow colleagues, business partners and Group Services Centers. You will work closely with our branch staff, relationship managers, product owners and IT teams. You will be developed with skills and mindset for process ownership, quality and risk management, high performance coaching, adaptive operating model and effective cost management.\n\nWe are currently seeking multiple high caliber professionals to join our department as\u00a0Cards and Loans Operations Associate.\n\n\n\nPrincipal responsibilities\n\nWork with business and offshore teams to ensure performance levels continually meet or exceed agreed quality standards\u00a0\nMonitor different SLAs and ensure service standard is achieved\nAssist supervisor to perform daily operations and control; and management information reporting\nHandle internal and external customer\u2019s enquiries\nIs accountable for the effective use of controls to ensure operational risk within agreed limits\u00a0\nImplement/Support projects as a Subject Matter Expert for new product/service, process, improvement and migration projects as applicable to improve overall operational efficiency and effectiveness\nEscalate all issues with operational effectiveness in a timely and appropriate manner\nRequirements\nUniversity graduate in Accounting, Finance or related disciplines\nMinimum 3 years relevant experience in account reconciliation, account settlement, and/or payment.\nProficiency in both English and Chinese with proficiency skills in Microsoft Office\nAbility to deal with large volume of data with strong attention to details.\nA good team player with good interpersonal skills, great sense of ownership and servicing mindset to ensure efficient and effective customer service processes\nIf you would like to explore other opportunities at Hang Seng Hong Kong, please visit www.hangseng.com/careers/ for details.\nThe health and safety of our employees and candidates is very important to us. Due to the current situation related to the Novel Coronavirus (2019-nCoV), we\u2019re leveraging our digital capabilities to ensure we can continue to recruit top talent at the HSBC Group. As your application progresses, you may be asked to use one of our digital tools to help you through your recruitment journey. If so, one of our Resourcing colleagues will explain how our video-interviewing technology will be used throughout the recruitment process and will be on hand to answer any questions you might have.\nAll information provided by applicants will be used only for recruitment purposes and will be used strictly in accordance with the Bank's personal data policies, a copy of which may be obtained by the applicant upon request. Unless otherwise instructed in writing by the applicant concerned, applicants may be considered for other suitable positions within the Bank and its related companies. The personal data of unsuccessful job applicants may be retained for a maximum of two years from the date when the job application is rejected and such data may be retained for a longer period if there is a subsisting reason that obliges the Bank to do so, after which the personal data will be destroyed.", "employment_types": ["Full Time", "Permanent"], "selling_points": [], "locations": ["Not Specified"], "categories": ["Banking / Finance", "Others", "Order Processing & Operation / Settlement"], "post_time": "2022-01-17T02:25:00Z", "salary": {"currency": null, "max": null, "min": null, "period": "monthly", "term": null}, "salary_visible": false, "title_keywords": ["operations", "associate", "accounting"], "responsibilities": ["reporting", "control", "management", "support projects", "service standard", "quality", "monitor", "teams", "subject matter expert", "daily operations", "migration"], "requirements": {"degrees": ["university graduate"], "majors": ["related disciplines", "finance", "accounting"], "languages": ["english", "chinese"], "language_level": ["proficiency"], "hard_skills": ["reason", "microsoft office"], "soft_skills": ["efficient", "good team player", "customer service", "interpersonal skills", "attention to details", "novel"], "languages_combined": [{"language": "english", "language_level": ["proficiency"]}, {"language": "chinese", "language_level": ["proficiency"]}]}, "experience_required": {"duration": ["minimum 3 years"], "field": ["relevant experience"]}}, {"job_id": "100003009052652", "location_code": "hk", "company": "ICBC International Holdings Limited", "job_title": "Operations - Settlement - Assistant Manager", "description": "Requirements:\n\nPerform the daily operations of settlements;\nResponsible for futures/options and bonds settlement;\nCorporate action for equities and bonds market;\nEstimate funding requirement for equities, derivatives and bonds market;\nClient & exchange / broker trade and position reconciliation;\nClient money segregation;\nProvides quality support to both internal and external clients for ad hoc and regular queries;\nProject participation and implementation for new business/system enhancement;\nEnsure appropriate\u00a0controls are in place to comply with internal policy.\n\nQualifications:\n\nMinimum\u00a03 years of experience in Operations or Settlement;\nDegree in Business, Finance, Mathematics, Risk Management, Statistics or a related discipline;\nAttain professional qualification(s) in Investment Banking, Risk Management or other \u00a0relevant subject is preferred;\nSupervisory experience is advantageous.", "employment_types": ["Full Time", "Permanent"], "selling_points": ["Future settlement exp. is needed", "Exp. in corporate action is preferred", "Competitive salary package"], "locations": ["Central"], "categories": ["Banking / Finance", "Others", "Order Processing & Operation / Settlement"], "post_time": "2022-01-17T03:38:47Z", "salary": {"currency": null, "max": null, "min": null, "period": "monthly", "term": null}, "salary_visible": false, "title_keywords": ["operations", "assistant manager"], "responsibilities": ["management", "ad hoc", "operations", "quality", "implementation", "daily operations", "banking"], "requirements": {"degrees": ["degree"], "majors": ["risk management", "mathematics", "finance", "statistics", "business"], "languages": [], "language_level": [], "hard_skills": ["exchange"], "soft_skills": ["responsible"], "languages_combined": []}, "experience_required": {"duration": ["minimum 3 years"], "field": ["supervisory experience"]}}, {"job_id": "100003009054149", "location_code": "hk", "company": "China CITIC Bank International Limited", "job_title": "Officer/ Senior Officer, Customer Due Diligence (1-year Contract)", "description": "Job Purpose\n\nConduct customer due diligence for periodic review, trigger event review and Enhanced Due Diligence.\n\nKey Responsibilities\n\nEngage in Customer Due Diligence process for periodic review and trigger event review\nEnsure the completeness of CDD information and supporting documents for case review and approval\nHandle potential breach cases of Sanctions under the Bank\u2019s AML policies\nAct as the focal point for CDD information clarification among internal stakeholders\nComply with regulatory and the Bank\u2019s requirements for CDD review\nParticipate in CDD related process reviews for personal/corporate customers with an aim to comply with regulatory or policy changes, as well as to improve customer experience and service turnaround time\n\nRequirements\n\nUniversity degree in business or related discipline\nMinimum 1 year of customer service and banking experience\nKnowledge of retail/ corporate banking and Anti Money Laundering (AML) / Know Your Customer (KYC) regulatory requirements\nGood analytical mind and problem solving skills\nGood command of written and spoken English and Chinese\n\nFor more details about career opportunities with the Bank, please visit our website http://www.cncbinternational.com/careers/en/index.jsp.\u00a0 Please apply with full resume stating current and expected salaries.\n\nPersonal data collected will be used for recruitment related purposes only. Applicants not invited for interview within 6 weeks may consider their applications unsuccessful. However, applicants may be considered for other suitable positions within the Group for a period of not more than 2 years. Personal data will be destroyed at any time after 3 months.\n\nChina CITIC Bank International is committed to being an equal opportunities employer and intends to provide a work environment free of unlawful discrimination or harassment.\u00a0 All employment decisions will be made in a non-discriminatory manner.", "employment_types": ["Full Time", "Contract"], "selling_points": ["Retail & Corporate Banking Knowledge", "KYC and CDD experience", "Financial Crime Compliance Role"], "locations": ["Quarry Bay"], "categories": ["Banking / Finance", "Corporate Banking", "Retail Banking", "Order Processing & Operation / Settlement"], "post_time": "2022-01-17T08:33:58Z", "salary": {"currency": null, "max": null, "min": null, "period": "monthly", "term": null}, "salary_visible": false, "title_keywords": ["officer", "senior officer"], "responsibilities": ["aml", "policies", "cdd", "review", "clarification", "customer due diligence"], "requirements": {"degrees": ["university degree"], "majors": ["business"], "languages": ["english", "chinese"], "language_level": ["good command"], "hard_skills": ["aml", "know your customer", "anti money laundering", "kyc", "problem solving skills"], "soft_skills": ["analytical mind", "problem solving skills", "customer service", "committed"], "languages_combined": [{"language": "english", "language_level": ["good command"]}, {"language": "chinese", "language_level": ["good command"]}]}, "experience_required": {"duration": ["minimum 1 year"], "field": ["customer service", "banking experience"]}}, {"job_id": "100003009047099", "location_code": "hk", "company": "E Fund Management (Hong Kong) Co., Limited", "job_title": "Fund Settlement Associate, Operations", "description": "Duties and Responsibilities\n\nPerform trade matching & arrange trade settlement for funds & discretionary accounts;\nAssist in the trade matching system implementation (Omgeo CTM/ In house system);\nAssist in delay trade settlement aging report & follow up with trade settlement;\nPerform holding / cash reconciliations;\nPerform daily cash forecast;\nLiaise with internal departments for fee analysis & arrange payment;\nAssist in account opening/ closure with counterparties for funds launch/termination;\nProvide secretarial support to the team;\nPerform ad hoc tasks in professional & timely manner;\nRequire to work shift and holiday support.\nAssist in system development relating to trade matching and settlement.\nRequirements\nBachelor degree holder in Accounting, Finance or related disciplines;\n0-2 yearsof relevant working experience;\nProfessional education preferred (CFA or CPA);\nKnowledge of Bloomberg and Reuters;\nProficiency in VBA, Python preferred.\nLanguages Skills: Fluent in English, Cantonese and Mandarin;\nA strong team player;\nPrioritization and multi-tasking skills;\nSelf-motivatedand able to work independently;\nImmediately available will be an advantage;\nFresh graduates are welcome.\nCompensation and Benefits\u00a0\u00a0\n\nE Fund HK is a fast growing company with strong financial resources and parent company support. We offer competitive compensations and career growth opportunities. We also offer attractive benefit programsand continued education support.", "employment_types": ["Full Time"], "selling_points": ["Fund Settlement", "Trade Support", "Fund Operations"], "locations": ["Central"], "categories": ["Banking / Finance", "Order Processing & Operation / Settlement", "Asset Management"], "post_time": "2022-01-14T02:19:20Z", "salary": {"currency": null, "max": null, "min": null, "period": "monthly", "term": null}, "salary_visible": false, "title_keywords": ["operations", "associate"], "responsibilities": ["account opening", "analysis", "ad hoc tasks", "implementation", "reconciliations", "payment", "secretarial support", "forecast", "liaise with", "report"], "requirements": {"degrees": ["bachelor degree holder"], "majors": ["related disciplines", "finance", "accounting"], "languages": ["cantonese", "english", "mandarin"], "language_level": ["fluent"], "hard_skills": ["vba", "bloomberg", "cfa", "cpa", "python"], "soft_skills": ["multi-tasking skills", "team player", "work independently"], "languages_combined": [{"language": "cantonese", "language_level": ["fluent"]}, {"language": "english", "language_level": ["fluent"]}, {"language": "mandarin", "language_level": ["fluent"]}]}, "experience_required": {"duration": [], "field": ["relevant working experience"]}}, {"job_id": "100003009054889", "location_code": "hk", "company": "Magpie Securities Limited", "job_title": "Client Data Maintenance Officer / Office Assistant", "description": "Duties\n\nProcess, check, validate and maintain client data and related administrative and fundamental accounting activities to ensure full compliance with rules and regulations.\n\nChecking and validating bank records\nProcess cash in and cash out transactions\nPerform new client account setup\nMaintain client account records and data\nPerform settlement administrative duties including data input, report printing, filing\nCommunicate with internal parties and external parties\nEnsure full compliance in accordance with rules and regulations\nRaise any irregularities or concerns regarding clients and compliance immediately\nOther ad-hoc projects as assigned\nAny other duties as instructed as required\n\nSkills\n\nExperience with back-office system iBoss or similar back office supporting system\nNumerate proficient or some accounting experience or similar\nProficient in MS Office and Chinese word processing\nExperience in the financial industry is an advantage\nFamiliar with regulatory and compliance requirements\nGood command in written and spoken English, Chinese and Mandarin\n\nCompetencies\n\nHigh level of professionalism and positive attitude\nGood verbal, communication and interpersonal skills\nObservant and has attention to detail\nMotivated, organized and efficient\nCapable of adapting to a fast-paced environment\nMust be a team player and maintain confidentiality\nRetirees and part-timers welcome to apply\u00a0\n\nCandidate with less experience will be considered as Office Assistant\n", "employment_types": ["Full Time", "Part Time"], "selling_points": ["Client Data Maintenance", "Office Assistant", "Securities settlement"], "locations": ["Causeway Bay"], "categories": ["Banking / Finance", "Financial Services", "Others", "Order Processing & Operation / Settlement"], "post_time": "2022-01-17T12:52:42Z", "salary": {"currency": null, "max": null, "min": null, "period": "monthly", "term": null}, "salary_visible": false, "title_keywords": ["office assistant", "maintenance officer"], "responsibilities": ["regulations", "any other duties", "irregularities", "data", "compliance", "external parties", "checking", "transactions", "data input", "back office", "communication", "maintain", "administrative duties", "communicate with internal parties", "ad-hoc projects", "setup", "report"], "requirements": {"degrees": [], "majors": [], "languages": ["english", "chinese", "mandarin"], "language_level": ["good command", "proficient"], "hard_skills": ["chinese word processing", "ms office"], "soft_skills": ["efficient", "organized", "capable", "fast-paced environment", "positive attitude", "communication and interpersonal skills", "motivated", "attention to detail", "team player"], "languages_combined": [{"language": "english", "language_level": ["good command"]}, {"language": "chinese", "language_level": ["good command", "proficient"]}, {"language": "mandarin", "language_level": ["good command"]}]}, "experience_required": {"duration": [], "field": ["accounting experience", "financial industry"]}}, {"job_id": "100003009054799", "location_code": "hk", "company": "BOCI-Prudential Trustee Limited", "job_title": "Manager, Fund Administration", "description": "Responsibilities:\n\nAssist the Senior Manager to run the team smoothly and operational metrics as required by management.\nDevelop the internal control procedures and workflow on daily tasks.\nEnsure the compliance with the applicable laws and regulations in relation to restricted investments.\nMonitor daily funding position of all managed funds to avoid overdraft.\nCheck and authorize the settlement instructions and pre-advice in sub-custodian system and ensure that they are completed before cut-off time.\nEnsure all prices and foreign exchange rates are updated into the system promptly and correctly.\nReview the reconciliation on bank accounts and custodian reports to ensure there is no discrepancies.\nLiaise with Fund Manager and Custodian on operation issues.\nProvide guidance to staff for improving productivity\n\nRequirements:\n\nUniversity graduate in Business Administration or Accounting\nAt least 6 years\u2019 experience in trustee company or custodian in fund administration or settlement areas of which at least 3 years at the supervisory level\nFamiliar to settlement practice in fixed income securities, equities, and FX transactions\nKnowledgeable in nominee services and corporate action events.\u00a0 A thorough understanding of Trustee company\u2019s service\nIn-depth knowledge in PORTIA and different settlement systems\nGood understanding of MPF & ORSO regulations\nStrong communication skills in both written and spoken English & Chinese\nStrong initiative with good problem solving skills\nProactively respond to changes in market and regulations\n\nWe offer attractive remuneration package & benefits to the right candidates. Interested candidates, please send your application letter & resume with current & expected salary\u00a0by mail to Human Resources Department, 12/F., Citicorp Centre, 18 Whitfield Road, Causeway Bay, Hong Kong.\u00a0Or by direct application, please visit our career page at\u00a0http://www.bocpt.com.\n\nWe are an equal opportunities employer and is committed to equality, ethics, inclusivity, diversity and transparency.\u00a0 Information provided will be treated in strict confidence and only be used for recruitment related purposes. Applicants who are not contacted within 6 weeks may consider their application unsuccessful. Applications will also be considered for other suitable positions available in our Group. Unsuccessful applications will be kept in our file for a period of one year\u00a0and which will be destroyed after the said period of retention.", "employment_types": ["Full Time", "Permanent"], "selling_points": ["Min 6yrs\u2019 exp in Trustee Co./custodian in fund adm", "University graduates in Business Admin/Accounting", "Immediate Available is highly preferred"], "locations": ["Tin Hau"], "categories": ["Banking / Finance", "Financial Services", "Fund Management", "Order Processing & Operation / Settlement"], "post_time": "2022-01-17T11:08:53Z", "salary": {"currency": null, "max": null, "min": null, "period": "monthly", "term": null}, "salary_visible": false, "title_keywords": ["manager"], "responsibilities": ["regulations", "management", "compliance", "procedures", "monitor", "review", "develop", "reports", "liaise with", "provide guidance", "internal control"], "requirements": {"degrees": ["university graduate"], "majors": ["accounting", "business administration"], "languages": ["english", "chinese"], "language_level": [], "hard_skills": ["problem solving skills"], "soft_skills": ["communication skills", "problem solving skills", "initiative", "thorough"], "languages_combined": [{"language": "english", "language_level": []}, {"language": "chinese", "language_level": []}]}, "experience_required": {"duration": ["at least 6 years", "at least 3 years"], "field": ["supervisory level", "administration"]}}, {"job_id": "100003009054760", "location_code": "hk", "company": "BOCI-Prudential Trustee Limited", "job_title": "Senior Administrator, Unit Trust", "description": "Responsibilities:\n\nHandle daily unit trust order, including subscription, redemption, switching, transfer, dividend and reinvestment\nLiaise with Fund Houses or Distributors (including Overseas and Mainland China) for routine operation issues\nHandle payment settlement with clients or Finance, including autopay instruction with banks\nPrint and dispatch contract notes, advice, statements and reports to unit holders, distributors or fund houses\nAssist the team supervisor to set up new fund groups for new business\nGeneral clerical support to the team\nHandle ad hoc assignment as required\n\nRequirements:\n\nDegree holder in Business Administration, Finance,\u00a0Economics, Banking\u00a0or related disciplines\nAt least 1 year working experience specialist in Fund Transfer Agent, Investor Service and Fund Administration is preferred\nTeam player with excellent interpersonal and presentation skills\nGood at problem-solving, customer focused and communication skills\nAble to work independently and under pressure\nProficient in PC applications including Excel, Word, PowerPoint and Chinese Word Processing\nGood command of both written and spoken English, Chinese and Mandarin\nCandidate with\u00a0more experience will be considered as Assistant Supervisor\n\nWe offer attractive remuneration package & benefits to the right candidates. Interested candidates, please send your application letter & resume with current & expected salary\u00a0by mail to Human Resources Department, 12/F., Citicorp Centre, 18 Whitfield Road, Causeway Bay, Hong Kong.\u00a0Or by direct application, please visit our career page at\u00a0http://www.bocpt.com.\n\nWe are an equal opportunities employer and is committed to equality, ethics, inclusivity, diversity and transparency. Information provided will be treated in strict confidence and only be used for recruitment related purposes. Applicants who are not contacted within 6 weeks may consider their application unsuccessful. Applications will also be considered for other suitable positions available in our Group. Unsuccessful applications will be kept in our file for a period of one year\u00a0and which will be destroyed after the said period of retention.", "employment_types": ["Full Time", "Permanent"], "selling_points": ["Handle daily unit trust order, payment settlement", "Liaise with fund houses / distributors", "Assist in set up new fund groups for new business"], "locations": ["Tin Hau"], "categories": ["Banking / Finance", "Financial Services", "Dealing & Trading", "Order Processing & Operation / Settlement"], "post_time": "2022-01-17T10:57:40Z", "salary": {"currency": null, "max": null, "min": null, "period": "monthly", "term": null}, "salary_visible": false, "title_keywords": ["administrator"], "responsibilities": ["ad hoc assignment", "clerical support", "payment", "reports", "liaise with", "autopay"], "requirements": {"degrees": ["degree holder"], "majors": ["related disciplines", "finance", "economics", "business administration"], "languages": ["english", "chinese", "mandarin"], "language_level": ["good command", "proficient"], "hard_skills": ["excel", "chinese word processing", "problem-solving", "word", "powerpoint", "pc applications"], "soft_skills": ["communication skills", "work independently", "under pressure", "focused", "problem-solving", "presentation skills", "team player", "interpersonal"], "languages_combined": [{"language": "english", "language_level": ["good command"]}, {"language": "chinese", "language_level": ["good command", "proficient"]}, {"language": "mandarin", "language_level": ["good command"]}]}, "experience_required": {"duration": ["at least 1 year"], "field": ["administration"]}}, {"job_id": "100003009054602", "location_code": "hk", "company": "Darmax Limited", "job_title": "Payment Confirmation - Investment Bank", "description": "My client is an investment bank with a strong global footprint. They are currently looking to recruit a candidate with experience in banking operations for their payment confirmation team.\n\nResponsibilities\n\nProcess confirmations of and perform settlements and reconciliations for transactions across different entities\nHelp manage the entire trade cycle and ensure the transactions are processed within the set timeframe\nConduct investigations into any discrepancy\nParticipate in UAT testing when required\nRequired\n\n3+ years of experience in FXMM\nGood understanding of CLS processes\nStrong communication skills", "employment_types": ["Full Time", "Permanent"], "selling_points": ["Investment banking - operations", "Competitive package", "Multicultural environment"], "locations": ["Central & Western Area"], "categories": ["Banking / Finance", "Order Processing & Operation / Settlement"], "post_time": "2022-01-17T10:12:33Z", "salary": {"currency": null, "max": null, "min": null, "period": "monthly", "term": null}, "salary_visible": false, "title_keywords": [], "responsibilities": ["operations", "uat testing", "transactions", "communication", "reconciliations", "payment", "banking"], "requirements": {"degrees": [], "majors": [], "languages": [], "language_level": [], "hard_skills": [], "soft_skills": ["communication skills"], "languages_combined": []}, "experience_required": {"duration": ["3+ years"], "field": ["team", "banking"]}}, {"job_id": "100003009049791", "location_code": "hk", "company": "Phillip Securities Group", "job_title": "Graduate Trainee (Back Office)", "description": "Principal Hong Kong is one of the major service providers of total retirement solutions in Hong Kong.\u00a0We are one of the winners received \"The 2021 MPF Award\" by MPF Ratings. Pension Operations plays a critical role to contribute the success of our business, join us if you are striving in an exciting operational environment or want to be a pension operation expert!\n\n\nThe Officer will participate in end-to-end pension operations process. You will handle daily administration of retirement schemes including but not limited to member enrollments, contributions, terminations, and group changes, in accordance with internal approved procedures, policies and local ordinance and regulations.\u00a0\n\nOther responsibilities include:\n\nProcess data and perform quality checking\nProvide customer service to clients and/or respond clients' verbal and written enquiries\nMaintain accurate records and thorough documentation\nAssist in any ad-hoc assignments or special projects\n\nEssential Skills, Experience and Competencies\n\nWe are looking for detail-minded candidates with strong time management skill. Competent in communicating across a wide variety of clients and deliver excellent customer service skills. Passionate about operational process with continuous improvement mindset will be a key to success.\n\nOther key skills required for the role:\n\nGraduates in business, finance or other related disciplines\n1 year of experience in Operations role\nExperience or sound knowledgeable in MPF and/or ORSO schemes administration is highly preferred\nA self-starter and good team player\nAble to meet tight timeline\nStrong PC applications especially Microsoft Excel and Word\nGood command of spoken and written English and Chinese\nFresh graduates who want to develop your career in Pension industry are welcome to apply/ candidate with less experience will be considered as Assistant Officer\n\nWhat We Offer\n\nPrincipal offers employees a competitive package and a comprehensive range of benefits to help meeting your needs now and in the future, including:\n\n5-Day Work Week\nYear-end Payment\nDiscretionary Bonus\nBirthday Leave\nMedical Plan\nLife Insurance\nPension Scheme\nEmployee Stock Purchase Plan\nAnd Growth Opportunities!", "employment_types": ["Full Time", "Permanent"], "selling_points": ["trainee", "performance bonus", "fresh graduate"], "locations": ["Admiralty"], "categories": ["Accounting", "Audit", "Banking / Finance", "Order Processing & Operation / Settlement", "Others", "Student / Fresh Graduate / No Experience"], "post_time": "2022-01-15T03:50:36Z", "salary": {"currency": null, "max": null, "min": null, "period": "monthly", "term": null}, "salary_visible": false, "title_keywords": ["graduate trainee"], "responsibilities": ["provide customer service", "quality checking", "management", "data", "ad-hoc assignments", "maintain", "customer service", "documentation"], "requirements": {"degrees": [], "majors": [], "languages": ["english", "chinese"], "language_level": ["good command"], "hard_skills": ["microsoft excel", "word", "pc applications"], "soft_skills": ["good team player"], "languages_combined": [{"language": "english", "language_level": ["good command"]}, {"language": "chinese", "language_level": ["good command"]}]}, "experience_required": {"duration": ["1 year"], "field": ["mpf", "administration"]}}, {"job_id": "100003009053112", "location_code": "hk", "company": "Changjiang Securities International Financial Group Limited", "job_title": "Dealer", "description": "Job Responsibilities:\n\nVerify and execute trade orders of securities and futures products for global market in accurate and timely manner\nAssist to perform day-end processing for trade reconciliation and settlement\nProvide quality services in answering client\u2019s enquiries with trade related matters\nMonitor clients\u2019 risks and perform risk control\nSupport system testing and UAT\nTake up ad hoc assignments as required\nFresh graduates are also welcome\n\nRequirements:\n\n\nUniversity graduates preferably in Finance or Business related disciplines\n1 to 3 years relevant experience in financial institutions or brokerage firms\nHolder of SFC licenses RA1 and RA2\nFamiliar with the relevant rules of regulated bodies and exchanges in trading\nDetail minded, able to work effectively under pressure and be a team player\nStrong PC skills and online trading\nGood command of Putonghua, English and Cantonese\nWilling to work day/night shift and Hong Kong public holidays\nImmediate available is preferred\n\nWe offer 5-days work with good career prospect and remuneration package for the right candidate.\u00a0Salary will be commensurate with qualifications and experience.\u00a0Interested parties please apply with\u00a0full resume (both Chinese and English versions)\u00a0with\u00a0current and expected salary\u00a0by clicking 'Apply Now'.\n\nAll personal data will be used for recruitment purpose only and treated in strict confidence.", "employment_types": ["Full Time", "Permanent"], "selling_points": [], "locations": ["Sheung Wan"], "categories": ["Banking / Finance", "Dealing & Trading", "Equities / Capital Markets", "Order Processing & Operation / Settlement"], "post_time": "2022-01-17T05:53:25Z", "salary": {"currency": null, "max": null, "min": null, "period": "monthly", "term": null}, "salary_visible": false, "title_keywords": ["dealer"], "responsibilities": ["control", "uat", "monitor", "quality", "testing", "ad hoc assignments"], "requirements": {"degrees": [], "majors": [], "languages": ["cantonese", "putonghua", "english"], "language_level": ["good command"], "hard_skills": ["pc skills"], "soft_skills": ["work effectively", "team player", "under pressure"], "languages_combined": [{"language": "cantonese", "language_level": ["good command"]}, {"language": "putonghua", "language_level": ["good command"]}, {"language": "english", "language_level": ["good command"]}]}, "experience_required": {"duration": ["1 to 3 years"], "field": ["brokerage", "financial institutions", "relevant experience"]}}, {"job_id": "100003009052472", "location_code": "hk", "company": "Standard Chartered Bank (Hong Kong) Ltd", "job_title": "Client Delivery Specialist - (2100035957)", "description": "About Standard Chartered\u00a0\nWe are a leading international bank focused on helping people and companies prosper across Asia, Africa and the Middle East.\u00a0\n\nTo us, good performance is about much more than turning a profit.\u00a0 It's about showing how you embody our valued behaviours - do the right thing, better together and never settle - as well as our brand promise, Here for good.\n\nWe're committed to promoting equality in the workplace and creating an inclusive and flexible culture - one where everyone can realise their full potential and make a positive contribution to our organisation. This in turn helps us to provide better support to our broad client base.\nThe Role Responsibilities\n\nStrategy\n\nTargeted Improvements\n\nAct as a service partner, work together with RMs, Product Sales, Operations and other key internal stakeholders to solve client channel issues and identify opportunities to improve overall service for the clients\nEnsure uniform approach towards implementation of Global IMO Model and adherence to DOIs\nDeliver excellent service against agreed service standards, delivery standards, and minimal error rates as appropriate\n\nAutomation and Streamlining\n\nDrive continuous improvement of the operational efficiency and effectiveness of processes to increase the consistency of systems and processes\n\nBusiness\n\nProvide quality support and advice to Relationship Managers (RM\u2019s) within all lending units on all documentation related matters, including the origination of documentation for customers where required\nTo deliver excellent service and advice to our Corporate (Corporate & Institutional Banking) & Commercial Banking clients in all interactions for their channel activation pre-transactional enquiries/setup, trainings and other channel related issues\n\nGeneral\n\nPerform end-to-end orchestration across all processes and services managed by IMO\nEngage clients throughout process, ensuring seamless delivery and client experience\nOwn and drive execution of processes, working closely with stakeholders and the value chain to deliver excellent client service, getting clients to the point of ready-to-transact as quickly as possible, across both simple and complex cases.\nAdheres to first-time-right principles\nProvide insight and suggestions to improving processes, identifying opportunities to streamline and automate. Looks at ways to promote standard work and best practices.\nUndertake ad-hoc duties and when delegated by Line Manager and Country Head of IMO\n\nProcesses\n\nClient Due Diligence (CDD) and Regulatory Onboarding\n\nPerform all relevant onboarding processes\nCreation of CDD for New Clients & Review of CDD for Existing Clients and perform regulatory onboarding (e.g. FATCA, CRS) activities\nDrive GIC and network onboarding processes\nConduct checks on CDD as applicable\nRespond and clear queries from Checkers / Other Specialists / Business CRM on a timely manner\nWork in partnership with all relevant stakeholders effectively within the end-to-end CDD process\nWhere serving as a checker, perform checks on CDD output from Client Delivery Makers, ensuring they adhere to policies and standard work\nEscalate or enforce compliance requirements, and follow any other relevant internal controls and procedures as they relate to process, products, policies and regulations\n\nEnablement [Account Opening and Channels]\n\nPerform relevant account opening activities, working closely with the relevant onshore and Hub teams to deliver fast set-up of all relevant systems\nDeliver excellent service and advice to our Corporate (Corporate & Institutional Banking), Commercial Banking, and Business Banking (BB) clients in all interactions for their Straight2Bank channel activation pre-transactional enquiries/setup, training, and other channel related issues\nAccept and arrange processing of various channels (Straight2Bank) and related products and services setup requests for Corporate and Institutional Banking (CIB), Commercial Banking (CB) and Business Banking (BB) clients; including internal setups e.g. for Client Access, Transaction Banking (TB) implementation testing setups, various internal operations unit\u2019s setups relevant to channels activation\nConduct checks on activities, documentation, and output (by other specialists or makers) within the account opening and channels activation processes as applicable\nEscalate or enforce compliance requirements, and follow any other relevant internal controls and procedures as they relate to process, products, policies and regulations\n\nServicing [Static Data Maintenance, Offboarding]\n\nPerform relevant static data maintenance and offboarding activities including raising of SDM and offboarding requests in the system\n\nPeople and Talent\n\nProvide effective orientation /guidance to new joiners on the bank\u2019s policies/procedures/processes to ensure their successful assimilation into the team and the bank\nDevelop and implement a personal learning plan with team manager, to attain necessary competencies\nSuccessfully complete milestones as laid out in implemented personal learning plan\n\nRisk Management\n\nAwareness and understanding of the regulatory framework in which the Group operates, and the regulatory requirements and expectations relevant to the role remit\nComply with applicable Money Laundering Prevention Procedures and report any suspicious activity to the operational risk team and Line Manager\nEnsure a clear and uniform approach towards implementation of the global operating model for all IMO-related processes, and adherence to DOIs\nReport any deviation (if any) to appropriate authorities and obtain proper dispensations\nProactively manage risks and establish/monitor controls to improve the overall state of the risk management and operating framework\n\nGovernance\n\nEnsure strong due diligence on document safekeeping and data confidentiality\nEnsure correctness of documentation prior to any dispensation from the Bank\nEnsure compliance with the internal policies and credit policies, external policies, regulatory and statutory requirements\nUndertake periodic self-assessment on key controls to assess the proper functioning and adequacy of existing controls\nHighlight significant issues/errors to team leader\n\nRegulatory & Business Conduct\n\nDisplay exemplary conduct and live by the Group\u2019s Valued Behaviours and Code of Conduct.\nTake personal responsibility for embedding the highest standards of ethics, including regulatory and business conduct. This includes understanding and ensuring compliance with, in letter and spirit, all applicable laws, regulations, guidelines and the Group Code of Conduct.\nAchieve the outcomes set out in the Bank\u2019s Conduct Principles: Financial Crime Prevention;\u00a0The Right Environment.\nEffectively and collaboratively identify, escalate, mitigate and resolve risk, conduct and compliance matters.\n\nKey Stakeholders\n\nCountry IMO Head, Client Delivery Managers and other Specialists, Makers and Checkers\nControl Governance Managers and Specialists\nGBO Hub teams and In-country CET teams\nAccount Opening Teams\nFront Office (RMs, CMs, CCMs)\nLending Documentation Unit\nCommodities Transaction Management Unit\nBusiness CRM\nBusiness Operational Risk Manager\nTransaction Banking (Trade, Security Services, and Cash Management) Implementation Managers\nClient Documentation and Control\nCredit Documentation CoE\n\nOther Responsibilities\n\nEmbedding Here for good and the Group\u2019s brand and valued behaviours in the Integrated Middle Office team\nPerforming other responsibilities assigned under Group, Country, Business or Functional policies and procedures\nOur Ideal Candidate\nStrong ability to positively influence stakeholders across value chain to both orchestrate and execute on processes and deliver exceptional client service and experience\nAbility to positively engage and build rapport with clients\nStrong writing and presenting skills in English\nProblem solver; looks for solutions and finds ways to progress despite blockages\nStrong drive to deliver\nHas a clear understanding of the client needs being serviced\nAbility to work independently without direct supervision and able to cope with pressures from tight deadlines\nA team player with good interpersonal skills\nApply now to join the Bank for those with big career ambitions.\n", "employment_types": ["Full Time"], "selling_points": ["Strong ability to positively influence stakeholder", "Ability to positively engage", "Problem solver; looks for solutions"], "locations": ["Not Specified"], "categories": ["Banking / Finance", "Others", "Order Processing & Operation / Settlement"], "post_time": "2022-01-17T03:07:20Z", "salary": {"currency": null, "max": null, "min": null, "period": "monthly", "term": null}, "salary_visible": false, "title_keywords": ["specialist"], "responsibilities": ["client base"], "requirements": {"degrees": [], "majors": [], "languages": [], "language_level": [], "hard_skills": ["make"], "soft_skills": ["flexible", "focused", "committed", "organisation", "positive"], "languages_combined": []}, "experience_required": {"duration": [], "field": []}}, {"job_id": "100003009048019", "location_code": "hk", "company": "China Everbright Securities International Company Limited", "job_title": "Associate, Derivatives Operations (Settlement)", "description": "Ref: ASSO/OPD/140122DB/16\n\nResponsibilities\u00a0\u00a0\n\nPrepare and check internal vouchers, trade confirmations, settlement & payment instructions for listed derivatives (Futures, Options)\nHandle pre-matching of settlement instructions\nEnsure all trading processing (including Futures & Options settlement via DCASS terminal) are completed correctly and properly\nLiaise with internal and external counterparts (Exchanges, brokers etc.) on booking, position and settlement issues\nHandle inquiries from external and internal clients and take appropriate follow up actions\nConduct user acceptance test for system enhancement\nPerform ad-hoc duties as assigned by supervisor\u00a0\u00a0\u00a0\n\nRequirements\u00a0\u00a0\n\nHigher Diploma or above\n3 years or above settlement experience\u00a0in\u00a0financial industry\u00a0\nSolid experience in DCASS operations preferred\nSelf-disciplined and able to work independently\nGood command of both written and spoken English and Chinese.\u00a0 Fluency in Putonghua will be an advantage\nProficiency in MS Office and Chinese Word Processing\nCandidate with more experience will be considered as 'Senior Associate'\n\nWe offer a competitive remuneration package to the right candidate. If you are interested in the post, please send your resume together with your present and expected salaries by clicking \u201cApply Now\u201d.\u00a0\n\nFor more information about China Everbright Securities International Company Limited, please visit www.ebshk.com.\n\n\n\nWe are an equal opportunity employer and welcome applications from all qualified candidates. All applications will be treated in the strictest confidence. Personal data provided will be used for recruitment purposes only. The job applicant will assume all or any risks arising out of or in connection with the job application transmission process prior to our actual receipt of the same including but not limited to accidental or unauthorized loss or disclosure of personal information, to which we will not be responsible in any way.\n\nUnder the Personal Data (Privacy) Ordinance, you may request access to, and / or correction of your personal data in relation to your application. If you wish to do so, please email to us.", "employment_types": ["Full Time", "Permanent"], "selling_points": [], "locations": ["Causeway Bay"], "categories": ["Banking / Finance", "Equities / Capital Markets", "Order Processing & Operation / Settlement", "Wealth Management"], "post_time": "2022-01-14T04:32:00Z", "salary": {"currency": null, "max": null, "min": null, "period": "monthly", "term": null}, "salary_visible": false, "title_keywords": ["operations", "associate"], "responsibilities": ["payment", "booking", "ad-hoc duties", "liaise with", "settlement issues"], "requirements": {"degrees": ["higher diploma or above"], "majors": [], "languages": ["putonghua", "english", "chinese"], "language_level": ["fluency", "advantage", "proficiency", "good command"], "hard_skills": ["dcass", "chinese word processing", "ms office"], "soft_skills": ["work independently"], "languages_combined": [{"language": "putonghua", "language_level": ["fluency", "advantage"]}, {"language": "english", "language_level": ["good command"]}, {"language": "chinese", "language_level": ["proficiency", "good command"]}]}, "experience_required": {"duration": ["3 years"], "field": ["financial industry"]}}, {"job_id": "100003009052894", "location_code": "hk", "company": "United Overseas Bank Limited", "job_title": "Contract Assistant Vice President, Wholesale Loan Operations (1-year)", "description": "Job Responsibilities\n\n-\u00a0\u00a0\u00a0\u00a0\u00a0\u00a0\u00a0\u00a0\u00a0 Process daily loan operation covering bilateral and syndication loan\n\n-\u00a0\u00a0\u00a0\u00a0\u00a0\u00a0\u00a0\u00a0\u00a0 Act as payment bank role and handle syndicated loan payments\n\n-\u00a0\u00a0\u00a0\u00a0\u00a0\u00a0\u00a0\u00a0\u00a0 Maintain proper loan archival records\n\n-\u00a0\u00a0\u00a0\u00a0\u00a0\u00a0\u00a0\u00a0\u00a0 Prepare all loan administration related instructions.\n\n-\u00a0\u00a0\u00a0\u00a0\u00a0\u00a0\u00a0\u00a0\u00a0 Prepare internal and external reports\n\n-\u00a0\u00a0\u00a0\u00a0\u00a0\u00a0\u00a0\u00a0\u00a0 Provide enquiry feedback to internal and external customers\n\nJob Requirements\n\n-\u00a0\u00a0\u00a0\u00a0\u00a0\u00a0\u00a0\u00a0\u00a0 University graduate in Business disciplines\n\n-\u00a0\u00a0\u00a0\u00a0\u00a0\u00a0\u00a0\u00a0\u00a0 At least 5 years\u2019 experience in corporate banking loan operations\n\n-\u00a0\u00a0\u00a0\u00a0\u00a0\u00a0\u00a0\u00a0\u00a0 Good knowledge of banking practices, operations and procedures\n\n-\u00a0\u00a0\u00a0\u00a0\u00a0\u00a0\u00a0\u00a0\u00a0 Strong team player and ability to foster teamwork\n\n-\u00a0\u00a0\u00a0\u00a0\u00a0\u00a0\u00a0\u00a0\u00a0 Proficient in MS Office suite of applications\n\n-\u00a0\u00a0\u00a0\u00a0\u00a0\u00a0\u00a0\u00a0\u00a0 Excellent communication and interpersonal skills", "employment_types": ["Full Time", "Contract"], "selling_points": ["Loan Operations", "Wholesale Banking Focus", "Comprehensive Renumerations & Convenient Location"], "locations": ["Causeway Bay"], "categories": ["Banking / Finance", "Loan", "Order Processing & Operation / Settlement"], "post_time": "2022-01-17T04:27:25Z", "salary": {"currency": null, "max": null, "min": null, "period": "monthly", "term": null}, "salary_visible": false, "title_keywords": ["operations", "assistant vice president"], "responsibilities": ["internal and external customers", "payment", "maintain", "payments", "reports", "administration"], "requirements": {"degrees": ["university graduate"], "majors": ["business"], "languages": [], "language_level": [], "hard_skills": ["ms office"], "soft_skills": ["team player", "teamwork", "communication and interpersonal skills"], "languages_combined": []}, "experience_required": {"duration": ["at least 5 years"], "field": ["banking"]}}, {"job_id": "100003009053879", "location_code": "hk", "company": "Principal Investment & Retirement Services Limited", "job_title": "Supervisor, Fund Operations & Registration", "description": "Job Summary\n\nAs part of the Fund Administration and Operations team, the Supervisor, Fund Operations and Registration will administer the accounting opening and dealings in unit trusts and provide fund administration services to the investors of our Distributing partners. You will also liaise with external fund trustee and administrator of unit trusts and ensure a smooth operation in the Department\n\nEssential Skills, Experience and Competencies\n\nTo succeed in this role, you will need strong communication, organizational and problem-solving skills. You will be able to work independently and meet deadlines. Detailed-mind and relevant supervisory experience will be required to supervise and train new staffs.\n\nOther key skills required for the role:\n\nUniversity graduate or equivalent\nMinimum 3 - 4 years of relevant working experience with supervisory exposure\nExperience in transfer agency activities / unit trust administration/ Nominee service\nFluent in spoken and written English and Chinese (both Cantonese and Mandarin)\nRelevant experience in CDD or KYC is preferred\nKnowledge or experience in monitoring service provider on NAV calculation is preferred\nProficient in PC skills and MS Office applications, especially in excel\nTeam player with sound analytical, planning, and interpersonal skills\nAssist in Ad hoc project as instructed by management\n\nWhat We Offer\n\nPrincipal offers employees a competitive package and a comprehensive range of benefits to help meeting your needs now and in the future, including:\n\n5-Day Work Week\nYear-end Payment\nDiscretionary Bonus\nBirthday Leave\nMedical Plan\nLife Insurance\nPension Scheme\nEmployee Stock Purchase Plan\nAnd Growth Opportunities!", "employment_types": ["Full Time", "Permanent"], "selling_points": ["Fund operations and registration", "Transfer agency / unit trust / nominee services", "Attractive package: double pay, birthday leave"], "locations": ["Kwun Tong"], "categories": ["Banking / Finance", "Fund Management", "Order Processing & Operation / Settlement", "Asset Management"], "post_time": "2022-01-17T07:40:39Z", "salary": {"currency": null, "max": null, "min": null, "period": "monthly", "term": null}, "salary_visible": false, "title_keywords": ["operations", "supervisor"], "responsibilities": ["management", "ad hoc", "operations", "cdd", "monitoring", "communication", "planning", "kyc", "liaise with", "administration"], "requirements": {"degrees": ["university graduate"], "majors": [], "languages": ["cantonese", "english", "chinese", "mandarin"], "language_level": ["fluent"], "hard_skills": ["excel", "cdd", "kyc", "problem-solving skills", "pc skills", "ms office"], "soft_skills": ["work independently", "organizational", "communication", "team player", "interpersonal skills", "smooth", "problem-solving skills", "meet deadlines", "detailed"], "languages_combined": [{"language": "cantonese", "language_level": ["fluent"]}, {"language": "english", "language_level": ["fluent"]}, {"language": "chinese", "language_level": ["fluent"]}, {"language": "mandarin", "language_level": ["fluent"]}]}, "experience_required": {"duration": ["minimum 3 - 4 years"], "field": ["supervisory", "agency", "relevant working experience", "relevant experience", "supervisory experience", "administration"]}}, {"job_id": "100003009048851", "location_code": "hk", "company": "China Everbright Securities International Company Limited", "job_title": "Senior Analyst, OTC Products Operations (Settlement)", "description": "Ref: SA/OPD/140122DB/16\u00a0\n\nResponsibilities\n\nHandle daily settlement of\u00a0OTC Derivatives and Structured Products\nPrepare and check internal vouchers, trade confirmations and settlement & payment instructions\nLiaise with brokers and clients to perform pre-matching of settlement instructions\u00a0\nFollow up failed trade settlement cases with counterparties and clients\nPerform stock & cash reconciliation\nHandle enquiries and documents review requests from both internal and external parties\nParticipate in new projects and ad-hoc assignments including new products roll-out, system enhancement UAT, etc\n\nRequirements\n\nDegree holder in Economics, Banking and Finance, Business Administration or related disciplines preferred\n2 - 3 years' relevant experience in settlement, experience in OTC Derivatives & Structured Products preferred\nProficiency in MS Office applications and preferably Chinese Word Processing\nKnowledge in VBA macro, MS Access programming will be a strong advantage\nGood command of both written and spoken English and Chinese. Fluency in Putonghua preferred.\nCandidate with\u00a0more experience will be considered as 'Associate'\n\nWe offer a competitive remuneration package to the right candidate. If you are interested in the post, please send your resume together with your present and expected salaries by clicking \u201cApply Now\u201d.\u00a0\n\nFor more information about China Everbright Securities International Company Limited, please visit www.ebshk.com.\n\u00a0\n\n\nWe are an equal opportunity employer and welcome applications from all qualified candidates. All applications will be treated in the strictest confidence. Personal data provided will be used for recruitment purposes only. The job applicant will assume all or any risks arising out of or in connection with the job application transmission process prior to our actual receipt of the same including but not limited to accidental or unauthorized loss or disclosure of personal information, to which we will not be responsible in any way.\n\nUnder the Personal Data (Privacy) Ordinance, you may request access to, and / or correction of your personal data in relation to your application. If you wish to do so, please email to us.", "employment_types": ["Full Time", "Permanent"], "selling_points": [], "locations": ["Causeway Bay"], "categories": ["Banking / Finance", "Financial Services", "Equities / Capital Markets", "Order Processing & Operation / Settlement"], "post_time": "2022-01-14T07:27:14Z", "salary": {"currency": null, "max": null, "min": null, "period": "monthly", "term": null}, "salary_visible": false, "title_keywords": ["operations", "senior analyst"], "responsibilities": ["uat", "ad-hoc assignments", "review", "internal and external parties", "handle enquiries", "payment", "liaise with"], "requirements": {"degrees": ["degree holder"], "majors": ["related disciplines", "finance", "economics", "business administration"], "languages": ["putonghua", "english", "chinese"], "language_level": ["fluency", "proficiency", "good command"], "hard_skills": ["vba", "macro", "chinese word processing", "programming", "ms office"], "soft_skills": ["structured"], "languages_combined": [{"language": "putonghua", "language_level": ["fluency"]}, {"language": "english", "language_level": ["good command"]}, {"language": "chinese", "language_level": ["proficiency", "good command"]}]}, "experience_required": {"duration": ["2 - 3 years"], "field": ["relevant experience"]}}, {"job_id": "100003009052108", "location_code": "hk", "company": "Standard Chartered Bank (Hong Kong) Ltd", "job_title": "Manager, Trade Operations - (2100034294)", "description": "About Standard Chartered\u00a0\nWe are a leading international bank focused on helping people and companies prosper across Asia, Africa and the Middle East.\u00a0\n\nTo us, good performance is about much more than turning a profit.\u00a0 It's about showing how you embody our valued behaviours - do the right thing, better together and never settle - as well as our brand promise, Here for good.\n\nWe're committed to promoting equality in the workplace and creating an inclusive and flexible culture - one where everyone can realise their full potential and make a positive contribution to our organisation. This in turn helps us to provide better support to our broad client base.\nThe Role Responsibilities\nDelivering consistent and reliable Trade Finance transactions to Tier 1 Clients in line with their personalised service needs to Win through Service. Operating with a deep understanding of client business and the products they operate. Empowered decision makers taking ownership of transactions and enquires and leveraging Trade Product Operations, Trade Core Operations and Trade GBS Operations to ensure service standards are fulfilled.\nMeet Targets set on Query reduction, First Contact Resolution and Quick Kills.\nHandle escalated cases for tier 1 clients and ensure quick and satisfactory resolution\nEnsure meeting of Targets set on SLA adherence, TAT for Tier 1 clients.\nInstitute forums to discuss and resolve regular queries and find one-time solutions\nEnsure queries are resolved within agreed TAT for Tier 1 Clients\nProvide oversight for overdue queries and complaints\nArrange meetings with Tier 1 (ex-priority) clients at agreed frequency.\nEngage Product Operations Team for advisory for complex deals or based on requests from clients.\n\nProcess, Premium Service, Productivity and Budgetary Management\n\nManage Client Operation Team daily operations accordingly to the laid down procedure and standard of service and ensure operations complies with applicable:Ensure handling of Queries/Complaints as per the Documental Operating Instructions manual, customer\u2019s instructions and within the timeliness and accuracy standards specified.\nby Generic Product Program and Country Product Addendum\nMoney Laundering Prevention Procedures and report any suspicious activity to the Unit Money Laundering Prevention Officer and Line Manager\nSanctions policy & procedures\nGroup Policies / GDOI\nLegal & Compliance Policies\nEnsure all referrals are accurately checked and responded correctly with the SLA and in compliance with statutory regulatory and internal operational instructions.\nEnd to End Ownership of all Tier 1 (ex-priority) clients service queries/complaints until satisfactory resolution.\nEnsure prioritisation of Tier 1 (ex-priority) clients from a processing standpoint to achieve targeted TAT for all their transactions.\nMonitor and uplift Utilisation for Tier 1 (ex-priority) clients as per target set.\nMeet tier 1 clients to gain feedback and suggestions on service improvement.\nEngage Tier 1 clients on regular analysis of frequent queries and work with Product Operation Team on Disruptive Analysis for Tier 1 (ex-priority) clients to drive actions for reductions.\nMonitor Key Metrics Service Performance Scorecard around proactive query reduction, service quality increase and digitization index increase and initiate actions with tier 1 clients, stakeholders and product operations as required.\nManage the running cost of the team to meet or exceed the budgetary target.\nAssist Head of Trade Ops for collaboration with Technology on futuristic digital opportunities, pre-empt disruptive forces and commercialise innovative use of technologies\nAssist Head of Trade Ops to achieve the financial performance targets of front to back operations and to drive the respective country to prioritize investments into making client journey simpler, faster, better Challenge status quo in driving courageous conversations of doing business with Right Clients with a sustainable cost/ income ratio.\u00a0\n\nGovernance & Risk Management\n\nImmediate escalation of all queries/complaints received from regulators.\nEnsure Set Control standards are adhered to and met.\nContinuous update of service CDOI and dissemination of relevant information to team.\nProactive identification of risks and concerns including escalation to all relevant stakeholders\nMonitor complaints and completion of corrective action.\nSupport to effectively implement all operational, regulatory and financial control measures and monitoring plans for compliance and control standard as per the defined Enterprise Risk Management Framework.\nProactively communicate with the Business Unit Head and BRM on operational risk issues. Escalate significant events to Business Unit Head /BRM as appropriate. Support operations team pre/post audits and assurance reviews.\nProvide support on any regular and ad hoc tasks related to unit operational risk management assigned by BRM from time to time\nEmbed the Group\u2019s values and code of conduct. Develop a robust culture to ensure adherence with the highest standards of ethics, and compliance with relevant policies, processes and regulations among employees.\n\nBusiness Continuity Management:\n\nAssist Head of Trade Operations to ensure an adequate Business Continuity Management (\u201cBCM\u201d) plan is in place across the business, to facilitate continuity of critical business operations in the event of significant business interruption.\n\nPeople and Talent:\n\nTrain up team members to maximize the productivity of resources available and to ensure that they have the required level of expertise to answer customers\u2019 queries and apply the operational standard required by the Bank.\nMonitor morale and constantly motivate direct reports to ensure that optimum level of productivity and service standards are achieved.\nTo act as a sponsor for the team for all changes facing Trade Operations group to ensure that such changes are implemented successfully\nLead and support a change in mindset, building a culture of client centricity, agility, and accountability through standardised metrics and measurement, with the expectation that everyone in Operations are drivers and owners of client outcomes.\nReview team structure and capacity plans in accordance with change in business structure and demand.\n\nRegulatory & Business conduct:\n\nDisplay exemplary conduct and live by the Group\u2019s Values and Code of Conduct.\nTake personal responsibility for embedding the highest standards of ethics, including regulatory and business conduct, across Standard Chartered Bank. This includes understanding and ensuring compliance with, in letter and spirit, all applicable laws, regulations, guidelines and the Group Code of Conduct.\nAlways work towards achieving the outcomes set out in the Bank\u2019s conduct Principles: Fair Outcomes for Clients; Effective Financial Markets; Financial Crime Compliance; The Right Environment.\nEffectively and collaboratively identify, escalate, mitigate and resolve risk, conduct and compliance matters.\nEngage with local regulatory stakeholders and build trusted and valued relationships to drive outcomes that are satisfactory to the conduct of business in the country\nMonitor the effective communication and implementation of regulatory changes\n\nKey Relationships:\n\nInternal\nHead & team members of Trade Operations\nHead & managers of GBS\nTrade UORM\nGroup Trade Product and Client Operations\nLocal TB Product Management\nBusiness Technology\nFront Office & Middle Office\nOther Operations Functions\nOther Functions (HR, Finance, Legal & Compliance, Tax)\nAudit and investigations\nExternal\nCustomers\nVendors\nExternal consultants\nBank Audit / Accounting firms\nLocal and Regional Regulators\nOur Ideal Candidate\nEducation: University graduate or above\nExperience: 6 years Operations and Client Services working experience\n\nProfessional Skills\n\nSolid knowledge on various types of trade products and good understanding of process flow, regulations and issues faced by clients.\nStrong analytical, problem solving and operational skills.\nGood People interaction skills and ability to manage by Influence.\nExcellent understanding of service quality principles.\nGood management skill and able to coach the team to achieve agreed target.\n\nSoft Skills\n\nExcellent written and verbal communication skills Advanced skills on presentation & email writing.\nSound PC / MS Office skill.\nStrong organizational skills and well-developed business abilities.\nGood interpersonal skills and strong organizational skills.\nSelf-motivator, able to manage multiple tasks and work under pressure.\n\nOther Preference\n\nPassion in identifying and driving new operations improvement opportunities\nOther than above roles, job holders should follow other job duties and responsibilities assigned by line manage from time to time.\nApply now to join the Bank for those with big career ambitions.\n", "employment_types": ["Full Time"], "selling_points": ["Immediate escalation of all queries/complaints", "Education: University graduate or above", "Experience: 6 years Operations"], "locations": ["Not Specified"], "categories": ["Banking / Finance", "Others", "Order Processing & Operation / Settlement"], "post_time": "2022-01-17T02:06:42Z", "salary": {"currency": null, "max": null, "min": null, "period": "monthly", "term": null}, "salary_visible": false, "title_keywords": ["operations", "manager"], "responsibilities": ["regulations", "business continuity", "operations", "ensure adherence", "quality", "audit", "transactions", "communication", "service standards", "plan", "plans", "work under pressure", "control", "compliance", "monitor", "measurement", "implementation", "develop", "resolution", "client base", "reports", "report", "management", "cost", "provide support", "monitoring", "procedures", "ad hoc tasks", "review", "daily operations", "contact", "audits", "communicate with", "tax", "guidelines", "policies", "analysis", "hr", "arrange meetings"], "requirements": {"degrees": ["university graduate or above"], "majors": [], "languages": [], "language_level": [], "hard_skills": ["analysis", "problem solving", "sla", "make", "pc", "code", "processing", "ms office"], "soft_skills": ["organizational skills", "focused", "communication", "work under pressure", "multiple tasks", "robust", "problem solving", "committed", "interpersonal skills", "reliable", "presentation", "ideal", "communication skills", "passion in", "prioritize", "positive", "flexible", "advanced", "accountability", "deep", "innovative", "organisation", "proactive"], "languages_combined": []}, "experience_required": {"duration": ["6 years"], "field": []}}, {"job_id": "100003009053971", "location_code": "hk", "company": "\u5fc5\u9ad8\u4eba\u4e8b\u9867\u554f\u6709\u9650\u516c\u53f8", "job_title": "Senior Officer \u2013 Remittance Department", "description": "Our client is a reputable Bank, now they are seeking a professional to join their Remittance Department.\n\n\n\nResponsibilities\n\nHandle remittance transactions in professional manner;\nConduct customer contact and handle customer enquires;\nPrepare daily and management reports;\nHandle system enhancement projects from time to time;\nComplete work tasks as assigned by management and team leader.\n\nRequirements:\n\nPost-secondary education;\nMinimum 6 years of relevant experience;\nFamiliar with regulatory requirements of cross border Renminbi settlement as well as SWIFT/Telex handling;\nHands-on experience in trade or settlement transaction is an advantage;\nGood interpersonal and communication skills with good time management;\nGood command of spoken English, Cantonese, and Putonghua;\nCandidates with more experiencse can be considered as Manager.\n\nInterested parties please forward your CV in word format with current and expected salaries to PICCO Bent Consultancy Limited.\n\n[All applications will be treated with strict confidential and will be used for recruitment purposes only]", "employment_types": ["Full Time"], "selling_points": ["Familiar with cross border Renminbi settlement", "Familiar with SWIFT/Telex handling", "Handle system enhancement projects"], "locations": ["Admiralty"], "categories": ["Banking / Finance", "Loan", "Order Processing & Operation / Settlement"], "post_time": "2022-01-17T07:52:55Z", "salary": {"currency": null, "max": null, "min": null, "period": "monthly", "term": null}, "salary_visible": false, "title_keywords": ["senior officer"], "responsibilities": ["management", "professional manner", "transactions", "management reports", "contact", "enhancement projects"], "requirements": {"degrees": ["secondary education"], "majors": [], "languages": ["cantonese", "putonghua", "english"], "language_level": ["good command"], "hard_skills": ["swift"], "soft_skills": ["communication skills", "hands-on", "time management", "interpersonal"], "languages_combined": [{"language": "cantonese", "language_level": ["good command"]}, {"language": "putonghua", "language_level": ["good command"]}, {"language": "english", "language_level": ["good command"]}]}, "experience_required": {"duration": ["minimum 6 years"], "field": ["relevant experience"]}}, {"job_id": "100003009048422", "location_code": "hk", "company": "Hang Seng Bank Ltd", "job_title": "Cards and Loans Operations Associate (Customer Account Processing Team)", "description": "Cards and Loans Operations Department\n\nCards and Loans Operations supports the distribution of cards, credit cards and unsecured loan accounts maintenance and merchant acquiring operations\u00a0\n\nShould you join our Business Services, you will focus on delivering excellent services through teaming up with fellow colleagues, business partners and Group Services Centers. You will work closely with our branch staff, relationship managers, product owners and IT teams. You will be developed with skills and mindset for process ownership, quality and risk management, high performance coaching, adaptive operating model and effective cost management\u00a0\n\nWe are currently seeking a high caliber professional to join our department as\u00a0Cards and Loans Operations Associate.\n\n\nPrincipal responsibilities\n\nTo support card account maintenance related works including replacement, billing date change, auto repayment, account close, adding additional account, Octopus AAVS function, reprinting of statement and selecting valuable customer for anti-attrition etc.\nWork with business and offshore teams to ensure performance levels continually meet or exceed agreed quality standards\nSupport card account maintenance \u00a0 related to cards and loans operations\nPerform daily operations and control; and management information reporting\nHandle internal and external customer\u2019s enquiries\nIs accountable for the effective use of controls to ensure operational risk within agreed limits\u00a0\nImplement/Support projects as a Subject Matter Expert for new product/service, process improvement and migration projects as applicable to improve overall operational efficiency and effectiveness\nEscalate all issues with operational effectiveness in a timely and appropriate manner\n\nRequirements\nUniversity in related discipline OR other relevant qualifications\nMinimum of 2 years of experience in related fields\nStrong service and operation orientation, with good interpersonal and communication skills\nProficiency in both English and Chinese, with good knowledge of MS office applications\u00a0\nBe able to work under pressure and deliver results within tight schedule\u00a0\nGreat sense of ownership and servicing mindset to ensure efficient and effective customer service processes\n\n\n(Candidates with less experience will be considered for junior role.)\n\nIf you would like to explore other opportunities at Hang Seng Hong Kong, please visit www.hangseng.com/careers/ for details.\n\nThe health and safety of our employees and candidates is very important to us. Due to the current situation related to the Novel Coronavirus (2019-nCoV), we\u2019re leveraging our digital capabilities to ensure we can continue to recruit top talent at the HSBC Group. \u00a0As your application progresses, you may be asked to use one of our digital tools to help you through your recruitment journey. \u00a0If so, one of our Resourcing colleagues will explain how our video-interviewing technology will be used throughout the recruitment process and will be on hand to answer any questions you might have.\n\nAll information provided by applicants will be used only for recruitment purposes and will be used strictly in accordance with the Bank's personal data policies, a copy of which may be obtained by the applicant upon request. Unless otherwise instructed in writing by the applicant concerned, applicants may be considered for other suitable positions within the Bank and its related companies. The personal data of unsuccessful job applicants may be retained for a maximum of two years from the date when the job application is rejected and such data may be retained for a longer period if there is a subsisting reason that obliges the Bank to do so, after which the personal data will be destroyed.", "employment_types": ["Full Time", "Permanent"], "selling_points": [], "locations": ["Not Specified"], "categories": ["Banking / Finance", "Others", "Order Processing & Operation / Settlement"], "post_time": "2022-01-17T02:24:00Z", "salary": {"currency": null, "max": null, "min": null, "period": "monthly", "term": null}, "salary_visible": false, "title_keywords": ["operations", "associate"], "responsibilities": ["reporting", "control", "management", "support projects", "operations", "quality", "teams", "subject matter expert", "daily operations", "migration", "account maintenance"], "requirements": {"degrees": [], "majors": [], "languages": ["english", "chinese"], "language_level": ["proficiency", "good"], "hard_skills": ["reason", "ms office"], "soft_skills": ["efficient", "communication skills", "customer service", "novel", "interpersonal", "work under pressure"], "languages_combined": [{"language": "english", "language_level": ["proficiency", "good"]}, {"language": "chinese", "language_level": ["proficiency", "good"]}]}, "experience_required": {"duration": ["minimum of 2 years"], "field": ["related"]}}, {"job_id": "100003009052571", "location_code": "hk", "company": "Mitsui & Co (HK) Ltd", "job_title": "Senior Officer (Finance Team)", "description": "We are now inviting candidate of high calibre to join us in the following capacity in our Finance Team.\n\nJob Duties:\n\nResponsible for import & export transaction processing and checking\nMonitor and follow up irregular bills such as standby LC, LC add confirmation, etc.\nProvide professional advice to our internal business units relating the LC matters\nPerform and support other duties as assigned including RPA, SAP input, Filing, etc.\nMonthly Bank Reconciliation\nPerform other daily Finance jobs and ad hoc projects including audit confirmation, etc.\n\nRequirements\n\n\nAt least 3-5 years of working experience in handling commercial area, especially the trade finance operations\nGood knowledge in ICC rules and its operation\nPossess Bank Foreign Trade experience is preferable\nBasic knowledge and concepts of accounting is preferable\nSAP Knowledge is essential\nGood command of Microsoft Office Tools (e.g. Word, Excel)\nGood communication and interpersonal skills and able to work under pressure\nGood command of English and Mandarin\nInterested parties please apply with your full resume stating present and expected salary.\n\n\n\nAll information will be kept confidential and used for recruitment purpose only. Although we endeavour to respond to every applicant, this may not always be possible so if you receive no response within 60 days, please consider your application for this specific vacancy to be unsuccessful.\n\n", "employment_types": ["Full Time", "Permanent"], "selling_points": [], "locations": ["Admiralty"], "categories": ["Accounting", "Others", "Banking / Finance", "Others", "Order Processing & Operation / Settlement"], "post_time": "2022-01-17T03:26:35Z", "salary": {"currency": null, "max": null, "min": null, "period": "monthly", "term": null}, "salary_visible": false, "title_keywords": ["senior officer"], "responsibilities": ["other duties", "monitor", "bank reconciliation", "checking", "audit", "ad hoc projects", "transaction processing"], "requirements": {"degrees": [], "majors": [], "languages": ["english", "mandarin"], "language_level": ["good command"], "hard_skills": ["excel", "basic", "sap", "microsoft office", "word"], "soft_skills": ["communication and interpersonal skills", "work under pressure"], "languages_combined": [{"language": "english", "language_level": ["good command"]}, {"language": "mandarin", "language_level": ["good command"]}]}, "experience_required": {"duration": ["at least 3-5 years"], "field": ["finance", "commercial"]}}, {"job_id": "100003009047780", "location_code": "hk", "company": "China Everbright Securities International Company Limited", "job_title": "Senior / Analyst, Derivatives Operations (Settlement)", "description": "Ref: SA/OPD/140121DB/16\n\nResponsibilities\n\nSupport daily processing functions for Derivatives (e.g. stock options)\nPerform the duties of processing, control and monitoring the daily settlement and prepare regular reports\nLiaise with internal counterparts on transaction and settlement issues\nHandle Wealth Manager(s) requests and queries\nConduct user acceptance test for system enhancement / upgrades\nPerform ad-hoc duties as assigned by supervisor\u00a0\u00a0\u00a0\n\nRequirements\u00a0\u00a0\n\nDiploma or above\n2 years\u2019 relevant experience\u00a0in\u00a0financial industry\nSolid experience in CCASS / DCASS operations preferred\nSelf-disciplined and able to work independently\nGood command of both written and spoken English and Chinese.\u00a0 Fluency in Putonghua will be an advantage\nProficiency in MS Office and Chinese Word Processing\nCandidate with less experience will be considered as 'Analyst' and fresh graduates are\u00a0 welcome\n\nWe offer a competitive remuneration package to the right candidate. If you are interested in the post, please send your resume together with your present and expected salaries by clicking \u201cApply Now\u201d.\u00a0\n\nFor more information about China Everbright Securities International Company Limited, please visit www.ebshk.com.\n\u00a0\n\n\nWe are an equal opportunity employer and welcome applications from all qualified candidates. All applications will be treated in the strictest confidence. Personal data provided will be used for recruitment purposes only. The job applicant will assume all or any risks arising out of or in connection with the job application transmission process prior to our actual receipt of the same including but not limited to accidental or unauthorized loss or disclosure of personal information, to which we will not be responsible in any way.\n\nUnder the Personal Data (Privacy) Ordinance, you may request access to, and / or correction of your personal data in relation to your application. If you wish to do so, please email to us.", "employment_types": ["Full Time", "Permanent"], "selling_points": [], "locations": ["Causeway Bay"], "categories": ["Banking / Finance", "Equities / Capital Markets", "Others", "Order Processing & Operation / Settlement"], "post_time": "2022-01-14T04:30:46Z", "salary": {"currency": null, "max": null, "min": null, "period": "monthly", "term": null}, "salary_visible": false, "title_keywords": ["analyst", "operations"], "responsibilities": ["control", "upgrades", "monitoring", "reports", "ad-hoc duties", "liaise with", "settlement issues"], "requirements": {"degrees": ["diploma or above"], "majors": [], "languages": ["putonghua", "english", "chinese"], "language_level": ["fluency", "advantage", "proficiency", "good command"], "hard_skills": ["dcass", "chinese word processing", "ccass", "ms office"], "soft_skills": ["work independently"], "languages_combined": [{"language": "putonghua", "language_level": ["fluency", "advantage"]}, {"language": "english", "language_level": ["good command"]}, {"language": "chinese", "language_level": ["proficiency", "good command"]}]}, "experience_required": {"duration": ["2 years"], "field": ["financial industry", "relevant experience"]}}, {"job_id": "100003009050152", "location_code": "hk", "company": "Robert Walters (HK)", "job_title": "SVP, head of settlement, 1.2 mil", "description": "A well established banking group in Hong Kong is looking for a settlement head to manage retail investment products, payment operations and gneral banking products processing.\n\nResponsibilities\n\nService as department head to manage various operations teams to meet all operation and compliance requirements\nManage, oversee settlement functions covering investment products, payment/cash management operations and core banking products processing including loans, deposit, etc\nWork closely with senior managements to drive process streamlining initiatives as well as strategic projects\nDevelop procedure manuals and policy, including split office operations, BCP\nMaintain MIS and compilation of various reports; and manage budgeting\nHandle AML and all regulatory reporting\n\nRequirements\n\nBachelor degree or above\nAt least 15 years of relevant back office operations experience with proven people managing exposure\nSolid experience in branch operations, payment operations, retail investment settlement\nExposure in project management, especially in leading bank-wide projects;\nGood communication and leading skills;\nProject management skills; and AML handling knowledge;\nStrong self-motivation with ability to work under pressure; and\nFluent in English, Cantonese and Mandarin", "employment_types": ["Full Time", "Permanent"], "selling_points": ["investment product settlement", "payment operations", "loans and deposit processing"], "locations": ["Not Specified"], "categories": ["Banking / Finance", "Order Processing & Operation / Settlement"], "post_time": "2022-01-14T09:53:03Z", "salary": {"currency": "HKD", "max": 89999, "min": 70000, "period": "monthly", "term": null}, "salary_visible": true, "title_keywords": [], "responsibilities": ["reporting", "management", "aml", "operations", "budgeting", "compliance", "teams", "develop", "payment", "maintain", "reports", "banking"], "requirements": {"degrees": ["degree or above", "bachelor"], "majors": [], "languages": ["cantonese", "english", "mandarin"], "language_level": ["fluent"], "hard_skills": ["project management", "aml"], "soft_skills": ["project management skills", "communication", "project management", "self-motivation", "work under pressure"], "languages_combined": [{"language": "cantonese", "language_level": ["fluent"]}, {"language": "english", "language_level": ["fluent"]}, {"language": "mandarin", "language_level": ["fluent"]}]}, "experience_required": {"duration": ["at least 15 years"], "field": ["retail", "investment"]}}, {"job_id": "100003009049112", "location_code": "hk", "company": "Hong Kong Interbank Clearing Ltd", "job_title": "Specialist (Clearing Operations) (Two-Year Programme)", "description": "Major Responsibilities\nExposure to interbank clearing operations in Hong Kong to acquire expertise in interbank paper cheque clearing and other electronic clearing systems.\nInvolve in new system design and development and assist in new project implementation for interbank clearing and settlement initiatives in Hong Kong.\nParticipate in preparing clearing and settlement documentation, such as rules and procedures.\nPrepare user testing documentations and conduct user acceptance tests on new systems.\nParticipate in the clearing operation of paper cheque, e-Cheque and other electronic clearing items.\nInvolve in the operation and monitoring of the Faster Payment System.\nRequirements\nTertiary education with good academic achievement, majoring in banking, finance, business management, information technology or related disciplines will be an advantage.\nOne to two years working experience preferred.\u00a0\nTarget driven with excellent ethics to maintain business quality.\nConfident, self-motivated and resilient, with strong interpersonal and organization skills.\nExcellent command of both written and spoken English and Chinese; fluency in Putonghua is an advantage.\nRequired to work at alternative sites and perform shift duties as well as provide operation support under adverse weather situations.\u00a0\nOur Benefits and Career Path\nAttractive remuneration package\nMedical and dental insurance\nLife insurance\n2-year talent development program incorporating on-the-job training, external training and job rotations\nTo be an Assistant Manager after the two-year programme\n\n\nHow to Apply\nInterested parties please send your curriculum vitae stating your current and expected salaries, and the contact phone number to the Human Resources Division, Unit B, 25/F, MG Tower, 133 Hoi Bun Road, Kwun Tong, Kowloon\u00a0 by clicking the \"Apply Now\" button below.\nAll applications and personal information collected will be treated in strict confidence and only be used for the purpose of recruitment and selection.\u00a0 The information collected will be accessed by our authorized personnel only.\u00a0 Those applicants not contacted by the Human Resources Division within two months from their application date should consider their applications filed for future reference which will be retained for one year for possible future job matching, and will be destroyed after the expiry of one year.", "employment_types": ["Full Time", "Permanent"], "selling_points": [], "locations": ["Ngau Tau Kok"], "categories": ["Information Technology (IT)", "Testing / QA", "Banking / Finance", "Order Processing & Operation / Settlement", "Management", "Management Trainee"], "post_time": "2022-01-14T08:08:15Z", "salary": {"currency": null, "max": null, "min": null, "period": null, "term": null}, "salary_visible": false, "title_keywords": ["specialist", "operations"], "responsibilities": ["operations", "systems", "procedures", "implementation", "monitoring", "testing", "payment", "system design", "documentation"], "requirements": {"degrees": [], "majors": [], "languages": ["putonghua", "english", "chinese"], "language_level": ["fluency", "advantage", "excellent"], "hard_skills": ["business management", "operation support"], "soft_skills": ["confident", "self-motivated", "driven", "organization skills", "interpersonal"], "languages_combined": [{"language": "putonghua", "language_level": ["fluency", "advantage"]}, {"language": "english", "language_level": ["excellent"]}, {"language": "chinese", "language_level": ["excellent"]}]}, "experience_required": {"duration": ["one to two years"], "field": []}}, {"job_id": "100003009053434", "location_code": "hk", "company": "China Everbright Securities International Company Limited", "job_title": "Associate, Equities Operations (Settlement)", "description": "Ref: SA/OPD/170122DB/16\u00a0\n\nResponsibilities\n\nHandle daily settlement of Hong Kong shares &\u00a0Overseas Equities\u00a0\nHandle CCASS operations including physical stock deposit / withdrawal, SI / ISI, IPO and placement\nPrepare and check internal vouchers, trade confirmations and settlement\nLiaise and resolve settlement issues with clients and counterparties\nPerform daily stock reconciliation\nAssist to ensure the settlement process in compliance with both internal and external rules and regulations\nParticipate in ad-hoc projects, system enhancement UAT, etc\n\nRequirements\n\nDegree / Higher Diploma holder in Business, Economics, Finance or any related disciplines preferred\n3 - 5 years\u2019 relevant experience in financial services industry\nFamiliar with the operation of CCASS\nProficiency in MS Office and Chinese Word Processing\nGood command of both written and spoken English and Chinese. Fluency in Putonghua will be an advantage\nCandidate with less experience will be considered as 'Senior Analyst'\n\nWe offer a competitive remuneration package to the right candidate. If you are interested in the post, please send your resume together with your present and expected salaries by clicking \u201cApply Now\u201d.\u00a0\n\nFor more information about China Everbright Securities International Company Limited, please visit www.ebshk.com.\n\u00a0\u00a0\u00a0\u00a0\u00a0\n\nWe are an equal opportunity employer and welcome applications from all qualified candidates. All applications will be treated in the strictest confidence. Personal data provided will be used for recruitment purposes only. The job applicant will assume all or any risks arising out of or in connection with the job application transmission process prior to our actual receipt of the same including but not limited to accidental or unauthorized loss or disclosure of personal information, to which we will not be responsible in any way.\n\nUnder the Personal Data (Privacy) Ordinance, you may request access to, and / or correction of your personal data in relation to your application. If you wish to do so, please email to us.", "employment_types": ["Full Time", "Permanent"], "selling_points": [], "locations": ["Causeway Bay"], "categories": ["Banking / Finance", "Equities / Capital Markets", "Others", "Order Processing & Operation / Settlement"], "post_time": "2022-01-17T06:58:57Z", "salary": {"currency": null, "max": null, "min": null, "period": "monthly", "term": null}, "salary_visible": false, "title_keywords": ["operations", "associate"], "responsibilities": ["liaise", "regulations", "uat", "operations", "settlement process", "compliance", "ad-hoc projects", "resolve settlement issues"], "requirements": {"degrees": ["degree", "higher diploma holder"], "majors": ["finance", "economics", "related disciplines", "business"], "languages": ["putonghua", "english", "chinese"], "language_level": ["fluency", "advantage", "proficiency", "good command"], "hard_skills": ["chinese word processing", "ccass", "ms office"], "soft_skills": [], "languages_combined": [{"language": "putonghua", "language_level": ["fluency", "advantage"]}, {"language": "english", "language_level": ["good command"]}, {"language": "chinese", "language_level": ["proficiency", "good command"]}]}, "experience_required": {"duration": ["3 - 5 years"], "field": ["financial services industry", "relevant experience"]}}, {"job_id": "100003009053591", "location_code": "hk", "company": "Principal Trust Company (Asia) Limited", "job_title": "Officer, Pension Operations", "description": "Principal Hong Kong is one of the major service providers of total retirement solutions in Hong Kong.\u00a0We are one of the winners received \"The 2021 MPF Award\" by MPF Ratings. Pension Operations plays a critical role to contribute the success of our business, join us if you are striving in an exciting operational environment or want to be a pension operation expert!\n\n\nThe Officer will participate in end-to-end pension operations process. You will handle daily administration of retirement schemes including but not limited to member enrollments, contributions, terminations, and group changes, in accordance with internal approved procedures, policies and local ordinance and regulations.\u00a0\n\nOther responsibilities include:\n\nProcess data and perform quality checking\nProvide customer service to clients and/or respond clients' verbal and written enquiries\nMaintain accurate records and thorough documentation\nAssist in any ad-hoc assignments or special projects\n\nEssential Skills, Experience and Competencies\n\nWe are looking for detail-minded candidates with strong time management skill. Competent in communicating across a wide variety of clients and deliver excellent customer service skills. Passionate about operational process with continuous improvement mindset will be a key to success.\n\nOther key skills required for the role:\n\nGraduates in business, finance or other related disciplines\n1 year of experience in Operations role\nExperience or sound knowledgeable in MPF and/or ORSO schemes administration is highly preferred\nA self-starter and good team player\nAble to meet tight timeline\nStrong PC applications especially Microsoft Excel and Word\nGood command of spoken and written English and Chinese\nFresh graduates who want to develop your career in Pension industry are welcome to apply/ candidate with less experience will be considered as Assistant Officer\n\nWhat We Offer\n\nPrincipal offers employees a competitive package and a comprehensive range of benefits to help meeting your needs now and in the future, including:\n\n5-Day Work Week\nYear-end Payment\nDiscretionary Bonus\nBirthday Leave\nMedical Plan\nLife Insurance\nPension Scheme\nEmployee Stock Purchase Plan\nAnd Growth Opportunities!", "employment_types": ["Full Time", "Permanent"], "selling_points": ["Participate in entire pension operations process", "Experience in MPF/ORSO is highly preferred", "Fresh graduates are welcome to apply"], "locations": ["Kwun Tong"], "categories": ["Banking / Finance", "Financial Services", "Insurance", "Others", "Order Processing & Operation / Settlement"], "post_time": "2022-01-17T07:12:35Z", "salary": {"currency": null, "max": null, "min": null, "period": "monthly", "term": null}, "salary_visible": false, "title_keywords": ["officer", "operations"], "responsibilities": ["provide customer service", "quality checking", "management", "data", "ad-hoc assignments", "maintain", "customer service", "documentation"], "requirements": {"degrees": [], "majors": [], "languages": ["english", "chinese"], "language_level": ["good command"], "hard_skills": ["microsoft excel", "word", "pc applications"], "soft_skills": ["good team player"], "languages_combined": [{"language": "english", "language_level": ["good command"]}, {"language": "chinese", "language_level": ["good command"]}]}, "experience_required": {"duration": ["1 year"], "field": ["mpf", "administration"]}}, {"job_id": "100003009050287", "location_code": "hk", "company": "Nanyang Commercial Bank", "job_title": "Settlement Manager (Ref: S-00-JDB)", "description": "Supervise day-to-day settlement and operational support in the following areas: FX/ MM, Repo, NDF, OTC Option, ARR IRS, ARR Bonds etc. Liaise with counterparties and Front Office if there is trade booking discrepancy, confirmation mismatched, and settlement issues relating to Treasury transactions. Perform Collateral Management tasks, collaterals transfer, calculation of collateral interests, and arrangement settlement with CSA counterparties (Variation Margin & Initial Margin). Participate in system enhancement project, manage and resolve problems during different stages from project initiation to its implementation. Produce documentation on operating procedures and operating guideline Optimize workflow of the supervised business routine, so as to enhance operating efficiency and cost-effectiveness\n\nRequirements:\n\nDegree holder;\nMinimum 8 years of working experience in the settlement department;\nSolid experience of the operations and settlement of FX/MM, Repo, OTC Option, ARR IRS, ARR Bonds etc;\nFamiliar with settlement systems such as SWIFT, eMBT/eCMT, CMU and Euclid;\nStrong commitment, drive, willing to learn, and able to meet tight deadlines;\nGood command of both written and spoken English and Chinese.\n\nCandidate with more experience will be considered as Senior Settlement Manager.\n\nIf you are flexible enough and zeal for a harmonious and supportive working environment where enables you to grow and succeed professionally, please send a full resume indicating your public examination results (HKCEE and HKALE / HKDSE), your present and expected salary and quoting reference number attention to Talent Acquisition Division, Nanyang Commercial Bank, 151 Des Voeux Road Central, Hong Kong or apply through email. For details, please visit https://www.ncb.com.hk/ and select the page Recruit.\n\nWe are an Equal Opportunities Employer. Data collected would be used for recruitment purposes only. Applicants who do not hear from us within 8 weeks may consider their applications unsuccessful and their data will be destroyed within 12 months of receipt.", "employment_types": ["Full Time", "Permanent"], "selling_points": ["Supervise day-to-day settlement", "Liaise with counterparties and Front Office", "8 years of working experience"], "locations": ["Central & Western Area"], "categories": ["Banking / Finance", "Others", "Order Processing & Operation / Settlement"], "post_time": "2022-01-15T03:50:57Z", "salary": {"currency": null, "max": null, "min": null, "period": "monthly", "term": null}, "salary_visible": false, "title_keywords": ["settlement manager"], "responsibilities": ["management", "operational support", "documentation", "cost", "data", "operations", "systems", "procedures", "trade booking", "transactions", "implementation", "variation margin", "recruitment", "liaise with", "settlement issues"], "requirements": {"degrees": ["hkdse", "degree holder"], "majors": [], "languages": ["english", "chinese"], "language_level": ["good command"], "hard_skills": ["documentation", "swift", "euclid"], "soft_skills": ["flexible", "supportive", "meet tight deadlines", "harmonious", "willing to learn"], "languages_combined": [{"language": "english", "language_level": ["good command"]}, {"language": "chinese", "language_level": ["good command"]}]}, "experience_required": {"duration": ["minimum 8 years"], "field": []}}, {"job_id": "100003009050288", "location_code": "hk", "company": "Nanyang Commercial Bank", "job_title": "Settlement Manager \u2013 Securities (Ref: S-S-JDB)", "description": "Supervises the daily transaction processing of securities and funds to deliver a timely, smooth, reliable and efficient service to customer. Provides processing support on daily operation tasks such as trade matching, CCASS operations, corporate actions processing, IPO and placement, client fund transfers, borrowing and lending, data management and mutual funds processing. Manage the stock pledge processing of equities and derivatives in Hong Kong. Enforces segregation of duties and proper controls by verifying the transactions, amendments and data changes made by the operations team Streamlines existing processes and procedures continually Participate in system enhancement project, manage and resolve problems during different stages from project initiation to its implementation.\n\nRequirements:\n\nDegree holder or related;\nMinimum 8 years of working experience in the settlement and operations department;\nSolid experience of the operations and settlement of Equities, Fixed Income, mutual funds, derivatives;\nAbility to handle the full settlement cycle in CCASS is a must;\nGood understanding of the procedures for clearing, fees and commissions calculation, handling IPO, corporate actions, fund transfers and settlement instructions, mutual funds processing and the relevant SFC and HKEx rules and regulations;\nGood command of both written and spoken English and Chinese.\n\nCandidate with more experience will be considered as Senior Settlement Manager.\n\nIf you are flexible enough and zeal for a harmonious and supportive working environment where enables you to grow and succeed professionally, please send a full resume indicating your public examination results (HKCEE and HKALE / HKDSE), your present and expected salary and quoting reference number attention to Talent Acquisition Division, Nanyang Commercial Bank, 151 Des Voeux Road Central, Hong Kong or apply through email. For details, please visit https://www.ncb.com.hk/ and select the page Recruit.\n\nWe are an Equal Opportunities Employer. Data collected would be used for recruitment purposes only. Applicants who do not hear from us within 8 weeks may consider their applications unsuccessful and their data will be destroyed within 12 months of receipt.", "employment_types": ["Full Time", "Permanent"], "selling_points": ["Supervises the daily transaction of securities", ". Provides processing support on daily operation", "8 years of working experience"], "locations": ["Central & Western Area"], "categories": ["Banking / Finance", "Others", "Order Processing & Operation / Settlement"], "post_time": "2022-01-15T03:50:57Z", "salary": {"currency": null, "max": null, "min": null, "period": "monthly", "term": null}, "salary_visible": false, "title_keywords": ["settlement manager"], "responsibilities": ["regulations", "management", "data", "operations", "daily operation", "procedures", "transactions", "implementation", "commissions", "recruitment", "transaction processing"], "requirements": {"degrees": ["hkdse", "degree holder"], "majors": [], "languages": ["english", "chinese"], "language_level": ["good command"], "hard_skills": ["processing", "data management", "ccass"], "soft_skills": ["efficient", "flexible", "supportive", "harmonious", "timely", "smooth", "reliable"], "languages_combined": [{"language": "english", "language_level": ["good command"]}, {"language": "chinese", "language_level": ["good command"]}]}, "experience_required": {"duration": ["minimum 8 years"], "field": []}}, {"job_id": "100003009043734", "location_code": "hk", "company": "Connexe Search Limited", "job_title": "CDD Officer, Corporate Banking (25k)", "description": "Our client is a well-regarded regional bank. They are currently looking for CDD\u00a0Officer (Maker) in Operations Department.\n\n**Candidates with client-facing experience & immediate availability are preferred**\n\nJob Description:\n\nPerform periodic review, trigger review and CDD review for Relationship Management Application (RMA) in Corporate Banking\nUpdate e-KYC and AML system by collecting support documents and monitoring the review progress\nEnsure compliance with internal policies and regulatory requirements including KYC, CDD and AML\nHandle inquiries from front-line\u00a0staff and other internal parties\nPerform ad-hoc tasks as assigned\n\nJob Requirements:\n\nTertiary education or above is preferred\n1+ years\u2019 experience in account opening/ CDD in corporate banking\nSound knowledge of AML in Hong Kong\nGood PC and Chinese typing skills\nExcellent command of verbal and written English and Chinese, including Mandarin\n\n\nPlease email your full resume in MS Word format quoting the job reference N211266 in the subject field. Your interest will be treated in strict confidence. Only shortlisted candidates will be notified.", "employment_types": ["Full Time"], "selling_points": ["Account Opening/ CDD, Corporate Banking", "1+ years' experience", "Double pay & discretionary bonus"], "locations": ["Central"], "categories": ["Banking / Finance", "Corporate Banking", "Retail Banking", "Order Processing & Operation / Settlement"], "post_time": "2022-01-13T01:42:51Z", "salary": {"currency": null, "max": null, "min": null, "period": "monthly", "term": null}, "salary_visible": false, "title_keywords": ["officer"], "responsibilities": ["management", "aml", "cdd", "policies", "review", "monitoring", "banking", "regulatory requirements", "ensure compliance", "ad-hoc tasks", "kyc", "internal parties"], "requirements": {"degrees": [], "majors": [], "languages": ["english", "chinese", "mandarin"], "language_level": ["excellent", "good"], "hard_skills": ["aml", "account opening", "cdd", "typing", "pc", "ms word"], "soft_skills": ["confidence"], "languages_combined": [{"language": "english", "language_level": ["excellent"]}, {"language": "chinese", "language_level": ["excellent", "good"]}, {"language": "mandarin", "language_level": ["excellent"]}]}, "experience_required": {"duration": ["1+ years"], "field": ["banking"]}}, {"job_id": "100003009054781", "location_code": "hk", "company": "Public Finance Limited", "job_title": "Assistant Operations Officer (Business Operations and Administration Department)", "description": "Responsibilities\nAssist the department head to review and revise internal policies and procedures\nAssist in liaising with business units on operations issues\nCompile management reports\nAd hoc projects\nRequirements\nUniversity degree holder\nAt least 2 years working experience with good communication skills\nDetail minded and self motivated\nHands-on in Microsoft Office applications experience\nGood command of written and spoken English & Chinese\nCandidates with less experience will be considered as Operations Assistant\nBenefits\nDouble Pay\nDiscretionary Bonus\nInsurance Benefits\nStudy subsidy\n\nApplication Method:\nBy Whatsapp : 9309 2925\n\nBy E-mail via \"Apply now\"\nPersonal data collected will be treated in the strictest confidence in accordance with our\u00a0Personal Information Collection Statement\u00a0and\u00a0Privacy Policy\u00a0and will be handled by authorized personnel for recruitment-related purposes only. All applications will be kept for a maximum period of one year as may be considered for other suitable positions within Public Finance Ltd. and its associated companies. For details, please visit the Company\u2019s website\u00a0http://www.publicfinance.com.hk", "employment_types": ["Full Time", "Permanent"], "selling_points": [], "locations": ["Not Specified"], "categories": ["Admin & HR", "Clerical / Admin Staff", "Sales, CS & Business Devpt", "Business Development", "Banking / Finance", "Order Processing & Operation / Settlement"], "post_time": "2022-01-17T11:03:30Z", "salary": {"currency": null, "max": null, "min": null, "period": "monthly", "term": null}, "salary_visible": false, "title_keywords": ["operations", "operations officer", "assistant"], "responsibilities": ["policies", "operations", "review", "procedures", "liaising with", "management reports", "ad hoc projects"], "requirements": {"degrees": ["university degree"], "majors": [], "languages": ["english", "chinese"], "language_level": ["good command"], "hard_skills": ["microsoft office"], "soft_skills": ["self motivated", "communication skills", "hands-on"], "languages_combined": [{"language": "english", "language_level": ["good command"]}, {"language": "chinese", "language_level": ["good command"]}]}, "experience_required": {"duration": ["at least 2 years"], "field": []}}, {"job_id": "100003009047645", "location_code": "hk", "company": "China Everbright Securities International Company Limited", "job_title": "Senior Associate, Sales Administration (Wealth Management)", "description": "\u00a0Ref: SA/WM/140122DB/71\u00a0\n\nResponsibilities:\n\nAssist all daily administration and operation matters in the sales platform particular in Securities, Insurance and OTC Products\nMonitor daily sales / trades in compliance with internal procedures & guidelines and regulatory requirements\nCoordinate with Operations and Credit Departments on handling daily settlement and account opening to ensure smooth operations\nPerform regular compliance checking of clients, documents and trading activities\nHandle inquiries from Investment Consultants and external customers\nProvide professional service\u00a0or admin assistance to clients / potential clients and execute orders for clients, if necessary\n\nRequirements:\n\n\nForm 7 or above, University graduates\u00a0in Business Administration or related discipline preferred\nMinimum 3\u00a0years' relevant experience\u00a0in financial services industry\nHolder of\u00a0IA license and SFC licenses for Type 1 regulated activities are preferred\nGood communication skills with strong sense of responsibility, well-organized and able to work independently\nProficiency in MS Office and Chinese Word Processing\nGood command of both written and spoken English and Chinese, fluency in\u00a0Putonghua is preferred\nCandidate with\u00a0less experience will be considered as 'Associate'\n\nWe offer a competitive remuneration package to the right candidate. If you are interested in the post, please send your resume together with your present and expected salaries by clicking \u201cApply Now\u201d.\u00a0\n\nFor more information about China Everbright Securities International Company Limited, please visit www.ebshk.com.\n\nWe are an equal opportunity employer and welcome applications from all qualified candidates. All applications will be treated in the strictest confidence. Personal data provided will be used for recruitment purposes only. The job applicant will assume all or any risks arising out of or in connection with the job application transmission process prior to our actual receipt of the same including but not limited to accidental or unauthorized loss or disclosure of personal information, to which we will not be responsible in any way.\n\nUnder the Personal Data (Privacy) Ordinance, you may request access to, and / or correction of your personal data in relation to your application. If you wish to do so, please email to us.", "employment_types": ["Full Time", "Permanent"], "selling_points": [], "locations": ["Causeway Bay"], "categories": ["Banking / Finance", "Retail Banking", "Order Processing & Operation / Settlement", "Wealth Management"], "post_time": "2022-01-14T03:39:38Z", "salary": {"currency": null, "max": null, "min": null, "period": "monthly", "term": null}, "salary_visible": false, "title_keywords": ["senior associate", "wealth management", "sales"], "responsibilities": ["guidelines", "regulatory requirements", "operations", "compliance", "monitor", "procedures", "coordinate with", "account opening", "checking", "ensure smooth operations", "insurance", "administration"], "requirements": {"degrees": [], "majors": [], "languages": ["putonghua", "english", "chinese"], "language_level": ["fluency", "proficiency", "good command"], "hard_skills": ["chinese word processing", "ms office"], "soft_skills": ["communication skills", "work independently", "well-organized", "sense of responsibility"], "languages_combined": [{"language": "putonghua", "language_level": ["fluency", "good command"]}, {"language": "english", "language_level": ["good command"]}, {"language": "chinese", "language_level": ["proficiency", "good command"]}]}, "experience_required": {"duration": ["minimum 3 years"], "field": ["financial services industry", "relevant experience"]}}, {"job_id": "100003009046121", "location_code": "hk", "company": "Guotai Junan International Holdings Limited", "job_title": "Fund Operation Analyst, Asset Management", "description": "Job Description\n\nSupport daily operation duties for all asset types (equities, fixed income, Futures, Swap, derivatives..etc.)\u00a0 including trade capture, settlement, corporate action processing, payment processing, distribution processing, cash management and forecasting\nReconcile cash and trade activity between the Trustee/Prime broker/custodian and portfolio accounting system daily, including daily activity break clearing.\nReconciles weekly facility and monthly position data between the Trustee and portfolio accounting system, including follow-up with the Trustee.\nProcess operational activity accurately for each portfolio investment in the portfolio accounting system\nMaintain direct communication with various internal departments to coordinate trading, settlement, ensure accurate and timely reporting, and maintain compliance with the policy.\nWork professionally with team and coworkers.\nOther projects and duties as assigned.\n\nRequirement\n\nUniversity degree holder at least, Graduate in Finance / Accounting are preferable\n1-2 year + solid experience in operational experience either in a custodial, trustee,\u00a0 asset management\nProduct knowledge on bonds, derivatives, equities, and swap\nExperience in handling NAV calculation on private funds, hedge funds\nSelf-motivated, Detail-Oriented, patient and responsible\nAble to work under pressure and good at time management\nProficient in VBA will be an advantage\nGood command of both written and spoken in English and Chinese\nImmediately Available is highly preferred", "employment_types": ["Full Time", "Permanent"], "selling_points": ["Support daily operation duties for all asset types", "Process operational activity in accounting system", "Immediately Available is highly preferred"], "locations": ["Central & Western Area"], "categories": ["Banking / Finance", "Dealing & Trading", "Order Processing & Operation / Settlement", "Asset Management"], "post_time": "2022-01-13T09:39:55Z", "salary": {"currency": null, "max": null, "min": null, "period": "monthly", "term": null}, "salary_visible": false, "title_keywords": ["analyst", "asset management"], "responsibilities": ["reporting", "management", "data", "compliance", "daily operation", "communication", "coordinate", "payment", "maintain", "forecasting"], "requirements": {"degrees": ["university degree"], "majors": ["finance", "accounting"], "languages": ["english", "chinese"], "language_level": ["good command"], "hard_skills": ["vba"], "soft_skills": ["self-motivated", "responsible", "detail-oriented", "patient", "time management", "work under pressure"], "languages_combined": [{"language": "english", "language_level": ["good command"]}, {"language": "chinese", "language_level": ["good command"]}]}, "experience_required": {"duration": ["1-2 year"], "field": ["asset management"]}}, {"job_id": "100003009049830", "location_code": "hk", "company": "Chiyu Banking Corp Ltd", "job_title": "Business Support Officer (Settlement Operations)", "description": "Responsibilities:\n\nHandle daily settlement including but not limited to MM/Equities/Fixed Income/FX/Derivatives/Bonds/Gold exchanges\nPerform reconciliation functions with custodian, fund manager and internal books to ensure completeness and accuracy by reviewing data\nPrepare investment related schedules for group & statutory reporting and annual audit\nParticipate in project initiatives and UAT as assigned\n\n\nRequirements:\n\nDegree / Diploma holder with minimum 3 years\u2019 relevant experience in banking industry\nGood knowledge of CCASS, SWIFT, CHATS, RTGS and SWIFTNet systems\nSound knowledge in PC skills and computer application software such as Lotus Notes, MS Office\nCandidate with basic programming skill will be a plus\nGood command of both written and spoken English and Chinese\nWork on HK public holidays (by rotation) is required\n\n\n\nWe offer competitive packages and promising career opportunities to the right candidates. Please send your full resume with current salary, expected salary and the date of availability to The Human Resources Department, Chiyu Banking Corporation Ltd, 12/F, Chiyu Bank Building, No. 78 Des Voeux Road Central, Hong Kong or fax to 2986-3233 or by clicking Apply Now.\n\nInformation provided will be treated in strict confidence and only be used for recruitment purposes. All personal data of unsuccessful applicants will be destroyed after the recruitment exercise. A copy of Personal Information Collection Statement is available upon request.", "employment_types": ["Full Time", "Permanent"], "selling_points": [], "locations": ["Central"], "categories": ["Banking / Finance", "Order Processing & Operation / Settlement"], "post_time": "2022-01-14T09:18:01Z", "salary": {"currency": null, "max": null, "min": null, "period": "monthly", "term": null}, "salary_visible": false, "title_keywords": ["officer", "operations"], "responsibilities": ["reporting", "uat", "annual audit", "schedules", "data"], "requirements": {"degrees": ["diploma holder", "degree"], "majors": [], "languages": ["english", "chinese"], "language_level": ["good command"], "hard_skills": ["plus", "basic", "ccass", "programming", "swift", "pc skills", "ms office"], "soft_skills": [], "languages_combined": [{"language": "english", "language_level": ["good command"]}, {"language": "chinese", "language_level": ["good command"]}]}, "experience_required": {"duration": ["minimum 3 years"], "field": ["banking industry", "relevant experience"]}}, {"job_id": "100003009049393", "location_code": "hk", "company": "Shanghai Commercial Bank Ltd", "job_title": "Assistant, Bills Processing", "description": "Responsibilities:\n\nPerform the daily\u00a0import and export trade processing of the Bills Processing Centre\nConduct Anti-money laundering procedures according to the Bank\u2019s standards, procedures and guidelines\nHandle enquiries from customer and internal staff\nWork closely with business units to provide quality bills services to external customers\n\nRequirements:\n\nPost-secondary educated or above\nMinimum\u00a01 year of Bills operation experience preferred\nA team player and willing to work under pressure\nFluency in written and spoken English and Chinese, preferably with proficiency in Putonghua\nConversant with MS Word, Excel and Chinese Word processing\nFresh graduate will also be considered\n\nAttractive remuneration package will be offered to the right candidates. Interested parties please click \"Apply Now\" to submit your full resume with current and expected salary to the Human Resources Division.\n\nPlease visit us at www.shacombank.com.hk for more information about our Bank.\n\nAll personal data collected will be used for recruitment related purposes strictly in accordance with the Bank's personal data policies, a copy of which will be provided immediately upon request by contacting our Personal Data Compliance Officer. Applicants who are not contacted within two months may consider their applications unsuccessful and the personal data collected from the applicants will be retained for no longer than two years from the date of rejection during which the applicants may be considered for other suitable positions within the Bank.", "employment_types": ["Full Time", "Permanent"], "selling_points": ["Perform the daily import & export trade processing", "Conduct Anti-money laundering procedures", "Handle enquiries from customer and internal staff"], "locations": ["Kwai Hing"], "categories": ["Banking / Finance", "Corporate Finance", "Others", "Order Processing & Operation / Settlement"], "post_time": "2022-01-15T03:50:22Z", "salary": {"currency": null, "max": null, "min": null, "period": "monthly", "term": null}, "salary_visible": false, "title_keywords": ["assistant"], "responsibilities": ["guidelines", "handle enquiries", "procedures", "quality"], "requirements": {"degrees": ["fresh graduate"], "majors": [], "languages": ["putonghua", "english", "chinese"], "language_level": ["fluency", "proficiency"], "hard_skills": ["excel", "chinese word processing", "ms word"], "soft_skills": ["team player", "work under pressure"], "languages_combined": [{"language": "putonghua", "language_level": ["proficiency", "fluency"]}, {"language": "english", "language_level": ["proficiency", "fluency"]}, {"language": "chinese", "language_level": ["proficiency", "fluency"]}]}, "experience_required": {"duration": ["minimum 1 year"], "field": ["operation"]}}, {"job_id": "100003009046104", "location_code": "hk", "company": "\u4ee5\u592a\u8b49\u5238\u6709\u9650\u516c\u53f8", "job_title": "Settlement Manager", "description": "Responsibilities\n\nHandle daily equities settlement tasks\nPerform settlement functions including trade matching, customers fund deposit and withdrawal, SI, corporate actions, and other CCASS operations\nAssist in system modification and UAT testing\nLiaise with brokers, in-house departments to follow up any issues and enquiry\nHandle ad-hoc projects as assigned\n\nRequirements\n\nDegree holder with 3-5 years relevant experience in the settlement of HK, China Connect & Global equities market\nFamiliar with the operation of CCASS and Hundsun settlement system\u00a0\nKnowledge in local regulatory and compliance guidelines in related issues is preferable\u00a0\nGood communication and interpersonal skills\u00a0\nProficiency in spoken and written Mandarin , Cantonese and English\u00a0", "employment_types": ["Full Time", "Permanent"], "selling_points": ["CCASS & DCASS", "Hundsun & 2Go", "HK & China Connect Global Equities Market"], "locations": ["Wan Chai"], "categories": ["Banking / Finance", "Dealing & Trading", "Equities / Capital Markets", "Order Processing & Operation / Settlement"], "post_time": "2022-01-13T09:37:41Z", "salary": {"currency": null, "max": null, "min": null, "period": "monthly", "term": null}, "salary_visible": false, "title_keywords": ["settlement manager"], "responsibilities": ["operations", "uat testing", "system modification", "liaise with", "ad-hoc projects"], "requirements": {"degrees": ["degree holder"], "majors": [], "languages": ["cantonese", "english", "mandarin"], "language_level": ["proficiency"], "hard_skills": ["ccass"], "soft_skills": ["communication and interpersonal skills"], "languages_combined": [{"language": "cantonese", "language_level": ["proficiency"]}, {"language": "english", "language_level": ["proficiency"]}, {"language": "mandarin", "language_level": ["proficiency"]}]}, "experience_required": {"duration": ["3-5 years"], "field": ["relevant experience"]}}, {"job_id": "100003009046669", "location_code": "hk", "company": "Industrial and Commercial Bank of China (Asia) Limited", "job_title": "Assistant Manager - Deputy Manager, Treasury Operations (Settlement)", "description": "Job Responsibilities\n\nResponsible for processing settlement payments and receipts of treasury products\nProvide operations support in the daily treasury processing and settlement functions\nProvides support to IT projects in the department and conduct user acceptance tests for new procedures/systems\nPerform as a checker role in daily operation\nPerform ad-hoc duties as assigned\nJob Requirements\n\nUniversity graduate with minimum 3 years relevant experience in banking industry\nFamiliar with treasury product settlement and operational procedures\nFamiliar with Hong Kong Trade Repository Handling as well as collateral management\nKnowledge in RTGS (i.e. eMBT and eCMT) and Swift Alliance system\nCan operate Clearstream and \u00a0CMU clearing platform respectively\nGood communication with leadership skills and able to handle multi-tasking\nCapability on project handling (i.e. provide user requirement and UAT participation)\nExperience on Shift duty and working on holiday", "employment_types": ["Full Time", "Permanent"], "selling_points": [], "locations": ["Kwun Tong"], "categories": ["Banking / Finance", "Order Processing & Operation / Settlement"], "post_time": "2022-01-13T18:54:13Z", "salary": {"currency": null, "max": null, "min": null, "period": null, "term": null}, "salary_visible": false, "title_keywords": ["assistant manager", "deputy manager", "operations"], "responsibilities": ["receipts", "operations", "systems", "procedures", "daily operation", "payments", "ad-hoc duties"], "requirements": {"degrees": ["university graduate"], "majors": [], "languages": [], "language_level": [], "hard_skills": ["swift"], "soft_skills": ["communication", "leadership skills", "multi-tasking"], "languages_combined": []}, "experience_required": {"duration": ["minimum 3 years"], "field": ["banking industry", "relevant experience"]}}, {"job_id": "100003009044894", "location_code": "hk", "company": "Robert Walters (HK)", "job_title": "Settlement Analyst/ Associate", "description": "This is a new headcount from an expanding securities brokerage.\n\nResponsibilities:\n\nPerforming daily settlement of transactions, including cash equities, equity derivatives, structured Products, Japanese stock and funds transfer\nProcess settlement payments & receipts, G/L Batching as well as perform daily summary reports on a timely manner;\nCounterparts static data maintenance;\nEnsure all transactions complying with internal/external rules and regulations;\nSupport User Acceptance Test (UAT) as assigned;\nCoordinate with trading desk and relevant Counterparts in trade booking and reconciliation issue;\n\nRequirements:\n\nGraduated with an Bachelor/associate degree\nIdeally with 2-3 years of experience in financial institutions, fresh graduates are welcome\nGood command of spoken and written English and Chinese.", "employment_types": ["Full Time", "Permanent"], "selling_points": ["cash equities and derivatives settlement", "work life balance", "Asian securities brokerage"], "locations": ["Not Specified"], "categories": ["Banking / Finance", "Order Processing & Operation / Settlement"], "post_time": "2022-01-13T06:34:54Z", "salary": {"currency": "HKD", "max": 24999, "min": 20000, "period": "monthly", "term": null}, "salary_visible": true, "title_keywords": ["analyst", "associate"], "responsibilities": ["regulations", "receipts", "maintenance", "data", "uat", "a timely manner", "coordinate with", "transactions", "trade booking", "payments", "reports"], "requirements": {"degrees": ["associate degree", "bachelor"], "majors": [], "languages": ["english", "chinese"], "language_level": ["good command"], "hard_skills": [], "soft_skills": [], "languages_combined": [{"language": "english", "language_level": ["good command"]}, {"language": "chinese", "language_level": ["good command"]}]}, "experience_required": {"duration": ["2-3 years"], "field": ["financial institutions"]}}, {"job_id": "100003009048368", "location_code": "hk", "company": "DBS Bank Ltd", "job_title": "Analyst, Specialist, Operations, Loan Operations-Administration (Loan Redemption)", "description": "Business Function\n\nTechnology and Operations (T&O) enables and empowers the bank with an efficient, nimble and resilient infrastructure through a strategic focus on productivity, quality & control, technology, people capability and innovation. In T&O, we manage the majority of the Bank's operational processes and inspire to delight our business partners through our multiple banking delivery channels.\n\u00a0\n\nResponsibilities\n\nHandle and process to complete loan redemption requests, i.e. provide loan settlement amount and prepare redemption letters to solicitors for preparing release/discharge of mortgage/charge\nCollect redemption money, handle loan repayment, process discharge/release documents and cancellation of credit facility limit\nHandle and process to complete vehicle loan drawdown/maintenance/redemption requests, i.e. provide vehicle loan settlement amount, process the drawdown/maintenance /settlement in systems\nPerform the role of custodian to handle and safe-keep Vehicle Registration Documents (VRD) and other security/loan documents; update system where necessary\nHandle data input, contribution and maintenance for TransUnion (TU) reporting of loan transactions in accordance with the established processing/control procedures, Guidelines of the Sharing and Use of Consumer Credit Data\n\nRequirements\n\nDegree holder, or post-secondary education with relevant working experience\nGood knowledge and experience of loan operations especially in loan redemption\nAccuracy and thoroughness in work\nGood senses of risk control and management\nResult and customer service oriented\nPositive attitude, creative and innovative\nSelf-motivated with good analytical mind and problem-solving skills\nGood team player, supportive and flexible to take up departmental tasks\nGood PC knowledge and skills\n\nApply Now\n\nWe offer a competitive salary and benefits package and the professional advantages of a dynamic environment that supports your development and recognises your achievements.\n\nWe regret only shortlisted candidates will be notified.", "employment_types": ["Full Time"], "selling_points": ["Experience in loan redemption/ loan processing", "Experience in Vehicle Loan Processing preferable", "See job description."], "locations": ["Kwun Tong"], "categories": ["Banking / Finance", "Loan", "Order Processing & Operation / Settlement"], "post_time": "2022-01-14T06:26:20Z", "salary": {"currency": null, "max": null, "min": null, "period": "monthly", "term": null}, "salary_visible": false, "title_keywords": ["specialist", "analyst", "operations"], "responsibilities": ["reporting", "control", "maintenance", "data", "guidelines", "systems", "letters", "data input", "transactions", "procedures", "credit facility"], "requirements": {"degrees": ["secondary education", "degree holder"], "majors": [], "languages": [], "language_level": [], "hard_skills": ["problem-solving skills", "pc knowledge", "dynamic"], "soft_skills": ["flexible", "self-motivated", "good team player", "supportive", "dynamic environment", "customer service oriented", "innovative", "positive attitude", "analytical mind", "problem-solving skills", "creative"], "languages_combined": []}, "experience_required": {"duration": [], "field": ["redemption", "relevant working experience", "education"]}}, {"job_id": "100003009050519", "location_code": "hk", "company": "Manpower Services (Hong Kong) Limited", "job_title": "Operations Personnel (16-17K)", "description": "Our client, a leading global bank, is looking for a operation personnel to support operations of Mutual Funds.\n\nKey Responsibilities:\n\n\u2022 Ensure supporting services is sufficient with good quality delivery\n\u2022 Ensure lower operation error rate\n\u2022 Documentation follow-up and filing\n\u2022 Accounting & GSL entries posting\n\u2022 A/C reconcilement & investigation for discrepancies\n\u2022 Product Code setup & maintenance in system\n\u2022 System maintenance & Set Up\n\u2022 Handle billing / refund process on premium\n\u2022 Handle trade confirmations, allocations & dividend payment\n\u2022 Commission/Income account accrual & reconciliation\n\u2022 Liaise between branches & counterparties i.e. underwriters, Brokers, Fund Houses, RIO and other services providers\n\u2022 Answer phone inquiries from branches, other sales channels or counterparties\n\u2022 MIS reporting\n\u2022 Ensure all instructions are properly & timely executed without discrepancy\n\u2022 Follow-up and negotiate with counterparties or other internal depts\n\u2022 Prospectus/annual reports handling\n\u2022 Support system testing related to Insurance Products\n\u2022 Identify any irregular activities or potential risk and report to Investment Operations Manager\n\n\nRequirements:\n- With common senses for all operation controls\n- Knowledge of the Securities/Mutual Fund/Insurance operations/industry\n- Able to cope with the changing product offering and system enhancement\n-\u00a0Computer literacy (Word, Excel, PowerPoint, Access, etc\u2026)\n- Familiar with the processing systems such as Host system, TSO and DE, \u2026etc is preferred\n-\u00a0Good knowledge of English, clear communications\n- Accurate and fast input on figures\n- Attention to details\n\nInterested parties please send your full resume to yan.chan@manpowergrc.hk\u00a0or by clicking \"Apply Now\".", "employment_types": ["Contract"], "selling_points": ["Mutual Funds Operation", "Knowledge in operation control", "Banking industry"], "locations": ["Kwun Tong"], "categories": ["Admin & HR", "Clerical / Admin Staff", "Banking / Finance", "Fund Management", "Order Processing & Operation / Settlement"], "post_time": "2022-01-14T10:36:27Z", "salary": {"currency": null, "max": null, "min": null, "period": "monthly", "term": null}, "salary_visible": false, "title_keywords": ["operations"], "responsibilities": ["liaise", "reporting", "maintenance", "operations", "quality", "investigation", "testing", "payment", "reports", "accrual", "documentation", "insurance", "setup", "report"], "requirements": {"degrees": [], "majors": [], "languages": ["english"], "language_level": ["good"], "hard_skills": ["excel", "processing", "word", "powerpoint"], "soft_skills": ["clear", "computer literacy", "accurate", "attention to details"], "languages_combined": [{"language": "english", "language_level": ["good"]}]}, "experience_required": {"duration": [], "field": []}}, {"job_id": "100003009050642", "location_code": "hk", "company": "Dah Sing Financial Group", "job_title": "Senior Officer, Operations Support (Customer Due Diligence)", "description": "Reporting to the Assistant Manager, Operations Support, you will be responsible for monitoring and supervision to service of Account Opening.\nResponsibilities:\nProcess the account opening applications compliant with internal policies and local regulatory requirements;\nConduct KYC (Know Your Client) /CDD (Customer Due Diligence) / AML (Anti-Money Laundering) review on new client relationships;\nPerform maker role for account opening customer system data input;\nAssist with ad hoc projects as assigned;\nPerform back-up function to Operations Support teams.\nTo meet the challenge, you should have the following qualifications and attributes:\nMatriculated, Degree holder in Banking / Business Administration / Finance is preferred\nAt least 5 years banking experience. Experience in Branch operations is an advantage\nAble to work independently and under pressure\nGood PC knowledge\nGood communication and interpersonal skills\nSelf-motivated with analytical mind\nCandidates with less experiences may be considered as Officer, Operations Support.\nPlease note that only shortlisted candidates will be notified.", "employment_types": ["Full Time"], "selling_points": ["Assist with ad hoc projects as assigned", "Matriculated, Degree holder in Banking", "At least 5 years banking experience"], "locations": ["Not Specified"], "categories": ["Accounting", "Others", "Banking / Finance", "Corporate Banking", "Order Processing & Operation / Settlement"], "post_time": "2022-01-14T11:04:45Z", "salary": {"currency": null, "max": null, "min": null, "period": "monthly", "term": null}, "salary_visible": false, "title_keywords": ["senior officer", "operations"], "responsibilities": ["reporting", "aml", "policies", "operations", "monitoring", "account opening", "regulatory requirements", "cdd", "review", "system data", "customer due diligence", "teams", "banking", "ad hoc projects", "communication", "kyc", "administration"], "requirements": {"degrees": ["degree holder"], "majors": ["finance", "business administration"], "languages": [], "language_level": [], "hard_skills": ["aml", "cdd", "account opening", "customer due diligence", "anti-money laundering", "kyc", "pc knowledge"], "soft_skills": ["work independently", "self-motivated", "under pressure", "responsible", "communication and interpersonal skills", "analytical mind"], "languages_combined": []}, "experience_required": {"duration": ["at least 5 years"], "field": ["banking experience"]}}, {"job_id": "100003009050870", "location_code": "hk", "company": "Manpower Services (Hong Kong) Limited", "job_title": "Operations Personnel", "description": "Our client is looking for an operation personnel.\n\nResponsibilities:\n\nWork with front office and legal to review financing and equity derivatives documents including swap, accumulator, securities lending confirmation.\nMonitor cash and securities flows (from processing to settlement of trades) and work with front office and other middle to back functional support teams to ensure trading activities are properly booked and timely settled. Working with the client and trader to resolve all breaks in a timely manner and ensuring daily deliverables are met.\nManage end-to-end loan processing from loan application, loan drawdown, rollover and repayment in accordance with approved terms, procedures and regulatory requirements\nConduct collateral management which includes Credit Support Annex computations and transaction monitoring;\u00a0\nSupport in fixing, post-trade events, trade lifecycle, corporate event and other daily processing in relation to equities derivatives and equity linked financing.\u00a0\nEnsuring operational standards are adhered to and any exception processes are fully documented and approved.\u00a0\nProvide expertise advice to front office on trade booking such that all downstream reports are accurate.\u00a0\nSuggest and implement process improvements and utilize technology to improve efficiency in terms of reconciliations process and other operations workflow.\u00a0\nProvide management with information on unusual booking and settlement matters.\u00a0\nAnswer queries from internal and external counterparties and provide necessary supporting documents and reports.\nTo handle other duties assigned by the Team Lead &/or Head of Operations.\n\nRequirements:\n\nWith similar work experience in operations in banking industries\nGood Command of English\nDetailed oriented\n\nInterested parties please send your full resume with expected salary to yan.chan@manpowergrc.hk\u00a0or by clicking \"Apply Now\".", "employment_types": ["Contract"], "selling_points": ["Monitor cash and securities flows", "Loan processing", "Banking industry"], "locations": ["Yau Tsim Mong Area"], "categories": ["Banking / Finance", "Loan", "Order Processing & Operation / Settlement"], "post_time": "2022-01-14T11:36:07Z", "salary": {"currency": null, "max": null, "min": null, "period": "monthly", "term": null}, "salary_visible": false, "title_keywords": ["operations"], "responsibilities": ["management", "other duties", "regulatory requirements", "operations", "review", "a timely manner", "teams", "monitor", "procedures", "monitoring", "trade booking", "reconciliations", "reports", "booking"], "requirements": {"degrees": [], "majors": [], "languages": ["english"], "language_level": ["good command"], "hard_skills": [], "soft_skills": ["detailed oriented"], "languages_combined": [{"language": "english", "language_level": ["good command"]}]}, "experience_required": {"duration": [], "field": ["banking"]}}, {"job_id": "100003009049571", "location_code": "hk", "company": "Conners Consulting Limited", "job_title": "MPF Company (Multiple Perm Job / Fresh graduate)", "description": "Our client, a well-known MPF company in Hong Kong, is looking for a high caliber to join the group.\n\nSenior Client Service, Pension team\n\nProvide MPF scheme administration support, such as enrollment, contribution, switching and termination (align with all regulatory requirements)\nHandle customers' enquiries and provide possible solutions\u00a0\nPerform clerical duties including data input, scanning and filing\u00a0\u00a0\n\nRequirement:\n\nDiploma or above and at least 1 year working experience is preferred\nMPF knowledge\u00a0\n\nAssociate/Senior Associate \u2013 Fund Services (Fund Accounting & Valuation)\n\nPrepare reports, such as customer reports, internal and financial status.\nReconcile accounts with banks, plans, and people, and ensure that relevant records and entries are updated to the accounting system.\nPrepare accounting entries and expense schedules for plans and funds.\nPrepare an evaluation report to ensure that all transactions and pricing are correctly updated in the accounting system, and calculate the net value of each unit of funds. Handle customers' enquiries and provide possible solutions\n\nRequirement:\n\nForm 6 or above, LCC Higher and preferably university graduate\n1-2 years working experience is also preferable. Candidate with 3 years direct experience will be considered as Senior Associate.\nStrong in MS Excel and MS Word\u00a0\n\nBusiness Development Manager\n\nDevelop business with designated channel partners and prospects referred in establishing and operating their employee retirement scheme\nService selected clients for their pension schemes in compliance with the service standards\nHandle enquiries and complaints from channel partners and clients and acquire a good understanding of client\u2019s needs\nAssist in developing business strategy and implementing business plan and relevant business development activities\nSupport business development functions including project management and product promotion\nProvide support to customer service activities\u00a0\n\nRequirement:\n\nDegree holder\n4 years\u2019 relevant work experience in client services areas within financial institutions\nGood knowledge of MPF and ORSO is an advantage\u00a0\n\nOfficer, Call Center - Inbound\u00a0/ Outbound\n\nHandle MPF & ORSO enquiries through hotlines & emails\nProvide outbound service to promote company product & service\n\nRequirement:\n\nTertiary educated or above\n1-2 years working experience in call center / customer service environment / financial industry.\u00a0\u00a0\u00a0\n\nOthers Position\u00a0\n\nTo apply, please send your detailed resume or contact Ms Tsui at 3955 1358 for a confidential discussion.\nOnly shortlisted candidates will be notified.\u00a0\nApplicants who are not contacted within two weeks may consider their applications unsuccessful.\u00a0\nAll data collected will be used for recruitment purpose only & will be used strictly confidential.\u00a0\n\nConners Consulting Limited\u00a0\n2005 Kai Tak Commercial Building 317 Des Voeux Road Central Hong Kong\nTel: (852) 3996 8090\u00a0\u00a0\u00a0\u00a0\u00a0\u00a0 Website: www.connersconsulting.com", "employment_types": ["Full Time", "Permanent"], "selling_points": ["Fresh Graduates", "Many position", "Attractive Annual Packager & Career Development"], "locations": ["Central & Western Area"], "categories": ["Accounting", "Accounting Clerk / Supervisor", "Insurance", "Others", "Banking / Finance", "Order Processing & Operation / Settlement"], "post_time": "2022-01-15T03:50:33Z", "salary": {"currency": null, "max": null, "min": null, "period": "monthly", "term": null}, "salary_visible": false, "title_keywords": [], "responsibilities": ["consulting", "data", "schedules", "regulatory requirements", "website", "transactions", "service standards", "customer service", "evaluation", "plans", "administration", "scanning", "compliance", "handle enquiries and complaints", "developing", "develop", "reports", "business plan", "report", "valuation", "enrollment", "provide support", "mpf", "reconcile accounts", "contact", "data input", "project management", "recruitment", "prepare reports"], "requirements": {"degrees": ["university graduate", "diploma or above", "degree holder"], "majors": [], "languages": [], "language_level": [], "hard_skills": ["scheme", "project management", "ms excel", "lcc", "accounting system", "ms word"], "soft_skills": ["project management", "customer service", "detailed"], "languages_combined": []}, "experience_required": {"duration": ["3 years", "4 years", "at least 1 year", "1-2 years"], "field": ["financial institutions", "call center", "customer service", "financial industry"]}}, {"job_id": "100003009044819", "location_code": "hk", "company": "The Bank of Nova Scotia", "job_title": "Officer, Trade Finance Operations APAC, Hong Kong", "description": "Job Accountabilities:\n\nContributes to the overall success of the Trade Finance operations in the region, ensuring specific individual goals, plans, initiatives are executed / delivered in support of the team\u2019s business strategies and objectives.\u00a0 Ensures all activities conducted are in compliance with governing regulations, internal policies and procedures.\nAcquire and maintain a knowledge and understanding of Trade Finance Products in Hong Kong and other branches.\nEnsure the processing of import / export bills and related documents are accurate and within agreed service-level agreement. Processing of negotiation, discounting, Letter of Credit (L/C) financing and settlement.\nProvide prompt and courteous consultation to customers by answering questions and promoting the sale of Bank services.\nDocumentation in accordance to local jurisdiction record retention policy.\nAdhere to established Bank regulations and procedures with respect to assigned responsibilities and report unusual occurrences or fraudulent activity to the direct manager.\u00a0\nAssist during days with high volume, and holiday coverage for the other team members.\u00a0\nMaintain the confidentiality of the Bank and its\u2019 customer information.\nAssist with the training and development of junior staff in the department by providing guidance and direction in problem situations.\nSkills, Qualifications and Requirement:\u00a0\n\nMinimum 1-2 years experience in bills processing\nFresh graduate is also considered\nPossess relevant experiences with good knowledge of the operation of Letter of Credits both in the areas of import and export bills activities is an advantage.\nCapability to work independently in a high pressure environment.\nMust be flexible in a constantly changing environment (procedural and automated system changes).\nCan demonstrate initiative and aptitude for change.\nGood organizational skills, customer services and ability to multi task.\nMay be required to\u00a0report duty on rotational basis during Hong Kong public holiday to support the other Asia branches.\n\nInterested parties please send\u00a0your\u00a0full resume with present and expected salary, in strict confidence by clicking \"Apply Now\"\n\n\n(Data collected would be used for recruitment purpose only)", "employment_types": ["Full Time", "Permanent"], "selling_points": [], "locations": ["Central"], "categories": ["Banking / Finance", "Loan", "Others", "Order Processing & Operation / Settlement"], "post_time": "2022-01-13T06:25:41Z", "salary": {"currency": null, "max": null, "min": null, "period": "monthly", "term": null}, "salary_visible": false, "title_keywords": ["officer", "operations"], "responsibilities": ["regulations", "guidance", "related documents", "policies", "compliance", "procedures", "customer services", "finance operations", "maintain", "documentation", "plans", "system changes", "report"], "requirements": {"degrees": ["fresh graduate"], "majors": [], "languages": [], "language_level": [], "hard_skills": ["documentation", "c", "processing", "import and export"], "soft_skills": ["flexible", "organizational skills", "courteous", "work independently", "negotiation", "prompt", "accurate", "initiative"], "languages_combined": []}, "experience_required": {"duration": ["minimum 1-2 years"], "field": ["operation"]}}, {"job_id": "100003009050824", "location_code": "hk", "company": "Chubb Insurance Hong Kong Limited", "job_title": "Client Service Executive", "description": "Responsibilities:\n\nHandle policy administration tasks for Inward Business including new or renew policies issuance, endorsement issuance and related documentation\nHandle enquiries from other countries or territories or external parties for multinational insurance program\nWork closely with Global Client Executive\u2019s and Underwriters to deliver agreed client service standards\nCommunicate with brokers and other external parties\nWork closely with other Chubb offices and network partners, credit control and other departments to ensure resolution of accounting and processing problems\nAssist where required with ongoing projects that are identified throughout a given year for better improvement to the Global Services Department\nSupport Outward team when required from and implementation to follow up local policy and premium settlement\nIncidental work that may be required to be completed that may be outside the scope to day to day work requirements\n\nRequirements:\n\n\u00a0\n\nDiploma or above in related discipline\nAt least 1 year of working experience in policy administration within insurance industry is highly preferred\nConscientious, with strong attention to detail and sense of accuracy\nGood command in both spoken and written English and Cantonese\nHighly PC literate in Microsoft Word, Excel, etc.\nFresh graduate will also be considered\n\n\n\n\u00a0Please click \"Apply now\" to submit your application.\n\nPersonal data collected will be used for recruitment purpose only.", "employment_types": ["Full Time"], "selling_points": ["General Insurance", "Property & Casualty", "Welcome Fresh Graduate"], "locations": ["Quarry Bay"], "categories": ["Insurance", "Others", "Banking / Finance", "Order Processing & Operation / Settlement", "Sales, CS & Business Devpt", "Sales Administration"], "post_time": "2022-01-14T11:29:33Z", "salary": {"currency": null, "max": null, "min": null, "period": "monthly", "term": null}, "salary_visible": false, "title_keywords": ["service executive"], "responsibilities": ["communicate with", "control", "related documentation", "policies", "external parties", "implementation", "resolution", "handle enquiries", "service standards", "insurance", "administration"], "requirements": {"degrees": ["fresh graduate", "diploma or above"], "majors": [], "languages": ["cantonese", "english"], "language_level": ["good command"], "hard_skills": ["excel", "pc literate", "microsoft word"], "soft_skills": ["attention to detail", "conscientious"], "languages_combined": [{"language": "cantonese", "language_level": ["good command"]}, {"language": "english", "language_level": ["good command"]}]}, "experience_required": {"duration": ["at least 1 year"], "field": ["insurance industry", "policy administration"]}}, {"job_id": "100003009045023", "location_code": "hk", "company": "GF Holdings (Hong Kong) Corporation Ltd", "job_title": "Assistant, Operations (1 Year Contract)", "description": "Responsibilities\n\nTimely and accurately input data in internal system\nProvide operational support to the team\nAssist in ad hoc tasks as assigned by supervisor\nRequirement\n\nDiploma / Degree Holder\nGood command of spoken English, Chinese and Mandarin\nConversant with MS Word and Excel\nResponsible, self-motivated, independent & able to work under pressure\nWe offer attractive remuneration package and fringe benefits to the right candidate. Interested applicants please send detailed resume stating present & expected salaries and date of availability to Human Resources Department by clicking \"APPLY NOW\".\n\nFurther information about our group companies can be found at www.gfgroup.com.hk and www.gf.com.cn.\n\nAll applications will be treated in the strictest confidence and personal data collected will be used for recruitment purpose only.", "employment_types": ["Full Time"], "selling_points": ["Input data in internal system", "Provide operational support", "Diploma / Degree Holder"], "locations": ["Sheung Wan"], "categories": ["Banking / Finance", "Financial Services", "Others", "Order Processing & Operation / Settlement"], "post_time": "2022-01-13T06:55:43Z", "salary": {"currency": null, "max": null, "min": null, "period": "monthly", "term": null}, "salary_visible": false, "title_keywords": ["operations", "assistant"], "responsibilities": ["operational support", "ad hoc tasks", "data"], "requirements": {"degrees": ["diploma", "degree holder"], "majors": [], "languages": ["english", "chinese", "mandarin"], "language_level": ["good command"], "hard_skills": ["excel", "ms word"], "soft_skills": ["self-motivated", "independent", "responsible", "work under pressure"], "languages_combined": [{"language": "english", "language_level": ["good command"]}, {"language": "chinese", "language_level": ["good command"]}, {"language": "mandarin", "language_level": ["good command"]}]}, "experience_required": {"duration": [], "field": []}}, {"job_id": "100003009047387", "location_code": "hk", "company": "ProJob21.com Limited", "job_title": "Data Management & Business Operations VP, European Banking Group", "description": "Stable International Private Banking Platform\nOperations and Account Data Control\nPeople Management & Excellent Worklife Balance\n\nThe jobholder supervises a team to -\n\nOversight private banking business operations control; account services & documentation functions including new accounts opening, account maintenance/closure, static data maintenance to hold mail and physical materials arrangement\nEnsure quality corporate administrative support to front office private bankers and sales assistant\nEnsure timely deliverables to ensuring the fulfilment of regulatory and corporate governance by working closely with front office, operations and compliance/risk departments\nDevelop continuous review, streamline and improve daily operation steps as well as explore digitalization opportunity to increase efficiency and reduce turnaround time with reasonable internal controls and mitigation of operational risk\nPerform ad-hoc tasks and projects as needed, liaise tightly with project team and I.T. department on systems\u2019 new implementations and enhancements\n\n\nRequirements:\n\nDiploma holder or above with at least 8 years banking services, account documentation and operations control management experience acquired from International Private Bank / PWM Banking Groups\nProven capability in consulting senior management on banking operational support & control aspects\n4 years+ leadership and supervisory skills\nStrong banking compliance, control and regulatory knowledge\nRelevant corporate and office administrative management experiences\nGood command of written and spoken English and Chinese\n\n\n\nInterested candidates, please email your update resume (in MS WORD format) with current and expected salary to us soonest.\n\nAlso come visit ProJOB21 www.ProJob21.com to discover other exciting career opportunities!\n\nAll information received will be kept in strict confidence and used for employment-related purposes only.", "employment_types": ["Full Time"], "selling_points": [], "locations": ["Not Specified"], "categories": ["Banking / Finance", "Private Banking", "Retail Banking", "Order Processing & Operation / Settlement"], "post_time": "2022-01-14T02:57:32Z", "salary": {"currency": null, "max": null, "min": null, "period": "monthly", "term": null}, "salary_visible": false, "title_keywords": ["operations"], "responsibilities": ["liaise", "operational support", "consulting", "data", "operations", "quality", "senior management", "account maintenance", "control", "account documentation", "compliance", "develop", "banking", "management", "administrative support", "review", "documentation", "maintenance", "ad-hoc tasks", "systems", "daily operation"], "requirements": {"degrees": ["diploma holder"], "majors": [], "languages": ["english", "chinese"], "language_level": ["good command"], "hard_skills": ["documentation", "maintenance"], "soft_skills": ["stable", "leadership", "timely"], "languages_combined": [{"language": "english", "language_level": ["good command"]}, {"language": "chinese", "language_level": ["good command"]}]}, "experience_required": {"duration": ["at least 8 years"], "field": ["management", "administrative", "banking", "banking services"]}}, {"job_id": "100003009042985", "location_code": "hk", "company": "DBS Bank Ltd", "job_title": "Senior Associate/ Associate, Securities & Fiduciary Services Operations (Fund Administration)", "description": "Business Function\n\nTechnology and Operations (T&O) enables and empowers the bank with an efficient, nimble and resilient infrastructure through a strategic focus on productivity, quality & control, technology, people capability and innovation. In T&O, we manage the majority of the Bank's operational processes and inspire to delight our business partners through our multiple banking delivery channels.\n\u00a0\n\nResponsibilities\n\nPerform and / or check fund valuation, net asset value reconciliation, general ledger and transaction input\nLiaise with auditors on fund audit work\nEnsure stock, cash reconciliation, fees and expenses are properly accrued\nTo ensure subscription and redemption records are properly updated in the system\nHandle enquiries from fund managers and counter parties efficiently\nAdhere to the operating procedures and agreed services standard; comply with company and regulatory requirements\nParticipate in project initiatives, business development, and user acceptance test for system enhancements\n\nRequirements\n\nDegree holder in related disciplines\nMinimum 3 years of relevant working experience in banking operations and fund administration, and have 1 year of experience in people management is preferred\nStrong knowledge in finance, preferably with professional qualification in accounting and be able to prepare financial statement independently\nSound knowledge in financial product such as fixed income securities, derivatives, foreign exchange, interest rate products and swap\nExperience in HiPortfolio system would be an advantage\nExperience in handling private equity funds would be an advantage\nImmediate available is preferred\nThe incumbent with strong organization and people skills will join the management team to oversee daily production and overall management of the team\nThe incumbent with lesser people management will be given training and opportunity to develop the necessary skills for career development\nThe role is initially attached to one Fund Administration Team managing a portfolio of hedge funds and private equity funds.\u00a0 Good performers have the opportunity to rotate to the other teams to learn the other portfolios for development into well rounded professional in Fund Administration.\n\u00a0\n\nApply Now\n\nWe offer a competitive salary and benefits package and the professional advantages of a dynamic environment that supports your development and recognises your achievements.\n\nWe regret only shortlisted candidates will be notified.", "employment_types": ["Full Time"], "selling_points": ["Experience in Fund Admin/ Fund Accounting", "Knowledge in private equity funds preferable", "Checker experience is an advantage"], "locations": ["Kwun Tong"], "categories": ["Banking / Finance", "Fund Management", "Order Processing & Operation / Settlement"], "post_time": "2022-01-12T09:25:41Z", "salary": {"currency": null, "max": null, "min": null, "period": "monthly", "term": null}, "salary_visible": false, "title_keywords": ["senior associate", "associate", "operations"], "responsibilities": ["valuation", "general ledger", "regulatory requirements", "expenses", "procedures", "audit", "handle enquiries", "liaise with"], "requirements": {"degrees": ["degree holder"], "majors": ["related disciplines"], "languages": [], "language_level": [], "hard_skills": ["dynamic", "private equity", "exchange"], "soft_skills": ["dynamic environment", "independently"], "languages_combined": []}, "experience_required": {"duration": ["1 year", "minimum 3 years"], "field": ["administration", "people management", "relevant working experience", "banking"]}}, {"job_id": "100003009046316", "location_code": "hk", "company": "Pacific Focus Consultancy Limited", "job_title": "Operations Support", "description": "Our client is an international investment institution and they are looking for a high calibre candidate to join the trading team for daily Operational support (with exposure in client-facing).\n\n\n\nResponsibilities\n\nProvide complete support to the front office for the smooth running of the desk\nEnsure timely input of trades into trading systems\nResolve any trade queries received internally and externally, and ensure any trade discrepancies are resolved in a timely manner\nKeep trade records up to date.\nUpdate real-time manual / electronic whiteboards with market data\nProvide input on various projects for brokers and traders\nProvide trade details to brokers and traders on a daily basis\nGive live quotes to traders through the messaging systems\nMonitor markets and follow financial news and developments\nUnderstand the underlying products being traded and keep up to date with knowledge of new products / procedures\nLiaise with clients, (via telephone and face to face) to understand the business objectives of your clients as to provide a reliable and efficient broking service\nDevelop new business with existing clients and onboard new clients following the correct process with the Client Onboarding team\u00a0\n\nRequirements\n\nSound years of working experience (Working in the financial industry is an advantage)\nEffectively bilingual, fluent Mandarin is a must\nStrong interest in financial markets\nExcellent communications skills for interacting with people passionately\nAble to work independently in a fast-paced and highly intense environment is an advantage\nWorking in the aviation industry is an advantage", "employment_types": ["Full Time"], "selling_points": ["5-day work, attractive benefits", "Large scale international firm", "Great career exposure"], "locations": ["Wan Chai"], "categories": ["Banking / Finance", "Financial Services", "Dealing & Trading", "Order Processing & Operation / Settlement"], "post_time": "2022-01-13T10:25:38Z", "salary": {"currency": null, "max": null, "min": null, "period": "monthly", "term": null}, "salary_visible": false, "title_keywords": ["operations"], "responsibilities": ["liaise with clients", "develop new business", "systems", "monitor", "a timely manner", "procedures", "market data"], "requirements": {"degrees": [], "majors": [], "languages": ["mandarin"], "language_level": ["fluent"], "hard_skills": [], "soft_skills": ["work independently"], "languages_combined": [{"language": "mandarin", "language_level": ["fluent"]}]}, "experience_required": {"duration": [], "field": ["financial industry"]}}, {"job_id": "100003009049209", "location_code": "hk", "company": "Shanghai Commercial Bank Ltd", "job_title": "Assistant Vice President / Manager, Operation Efficiency", "description": "Responsibilities:\n\nSupport Team Lead to manage the project portfolio for the Operation Efficiency (OE) Workstream\nStreamline the end-to-end processes to deliver financial results\nCommunicate project progress, deliver recommendations and facilitate decisions with senior executives\nFacilitate continuous monitoring of projects after launch and evaluate the benefit realization achievement\nMeasure effectiveness of the improvement projects via the devised KPIs\nBesides delivering the operation efficiency projects in the OE Workstream, this role may also need to be involved in digital channel projects of the Customer Experiences Workstream to re-engineering the related back end processes\nAs a strong change advocate with \u2018customer focus\u2019 mind-set for process improvement\n\nRequirements:\n\nDegree holder with 8 years of experience in consulting / banking industry with at least 4 years of experiences in process analysis/process improvement/project management.\nSolid experience in managing projects of operation process improvement to enhance efficiency, service quality and customer experience.\nProven ability to build strong, cohesive partnerships and work effectively with the business, operations, technology and other key stakeholders.\nRecognized qualification in project management is desirable, with Six Sigma Black Belt is an advantage.\nGood knowledge of process improvement methodologies is preferred.\nOwnership mind-set, analytical and open-minded with strong communication, facilitation and interpersonal skills.\nGood command of both spoken and written English and Chinese. Mandarin is an advantage.\n\n(Candidate with less experience will be considered as Manager)\n\nAttractive remuneration package will be offered to the right candidates. Interested parties please click \"Apply Now\" to submit your full resume with current and expected salary to the Human Resources Division.\n\nPlease visit us at www.shacombank.com.hk for more information about our Bank.\n\nAll personal data collected will be used for recruitment related purposes strictly in accordance with the Bank's personal data policies, a copy of which will be provided immediately upon request by contacting our Personal Data Compliance Officer. Applicants who are not contacted within two months may consider their applications unsuccessful and the personal data collected from the applicants will be retained for no longer than two years from the date of rejection during which the applicants may be considered for other suitable positions within the Bank.", "employment_types": ["Full Time", "Permanent"], "selling_points": ["End-to-end processes to deliver financial results", "Facilitate continuous monitoring of projects", "Measure effectiveness of the improvement projects"], "locations": ["Kwun Tong"], "categories": ["Banking / Finance", "Analyst", "Others", "Order Processing & Operation / Settlement"], "post_time": "2022-01-15T03:50:11Z", "salary": {"currency": null, "max": null, "min": null, "period": "monthly", "term": null}, "salary_visible": false, "title_keywords": ["manager", "assistant vice president"], "responsibilities": ["project progress", "evaluate", "continuous monitoring", "kpis", "re-engineering"], "requirements": {"degrees": ["degree holder"], "majors": ["project management"], "languages": ["english", "chinese", "mandarin"], "language_level": ["advantage", "good command"], "hard_skills": ["six sigma", "project management", "analysis"], "soft_skills": ["work effectively", "open-minded", "cohesive", "communication", "project management", "interpersonal skills"], "languages_combined": [{"language": "english", "language_level": ["good command"]}, {"language": "chinese", "language_level": ["good command"]}, {"language": "mandarin", "language_level": ["advantage"]}]}, "experience_required": {"duration": ["at least 4 years", "8 years"], "field": ["banking industry", "project management", "operation", "consulting"]}}, {"job_id": "100003009040948", "location_code": "hk", "company": "Darmax Limited", "job_title": "Trade Support - Controls & Coordination Associate", "description": "Job Highlights\nTrade Support\nOperations\nMiddle Office\nJob Description\n\nHONG KONG based role (Full-time permanent position)\n\nOur client is a top-tier European Investment Bank that is continuing to expand their Operations in Asia, with Hong Kong as the APAC hub working closely with the global teams in London, New York and Paris - they have rebranded their positions to meet the business initiatives for the 1st quarter of 2022.\n\nAs such - they are seeking candidates from junior to mid level\u00a0Trade Support to support the growth towards building enhanced controls for the daily processes.\u00a0\n\nControl & Coordination team is responsible for trade repository reporting, AML/CTF message monitoring, local RTGS system, production and reporting of KPI/KRI, regional co-ordination and reporting, liquidity management, Nostro Projection and other transversal activities.\n\nKey Responsibilities for the position:\n- Trade Repository (TR) reconciliation, investigation, follow up and reporting for Hong Kong and Singapore.\n- Manage the liquidity management activities:\no Prepare and report the Nostro forecast balances to the various Treasury Front Offices\no Investigate any discrepancies and anomalies\n- Performing Nostro Projection for Hong Kong, Singapore and Tokyo.\n- Consolidate local and regional information for regional sites and Head Office.\n- Conduct and execute secondary level of processing and identify and resolve problems arising therein. - Invoicing (reconciliation, settlement and accounting)\n- AML/CTF message monitoring and processing in accordance with the Banks\u2019 procedures\n- Daily processing of statement integration in the relevant nostro reconciliation tools.\n- Coordinate the activities within CMO (IT issue, audit, special event).\n\nTransversal responsibilities:\n\n- Assist Line Manager to carry out common projects / global initiatives.\n- Assist in system enhancement and UAT testing.\n- Participation in the drafting and/or updating of operational procedures. - Manage operational risk with a duty to alert Management.\n\n\n\nTo obtain more details, please submit your application and more details will be disclosed in confidentiality.\u00a0\n\n%MCEPASTEBIN%", "employment_types": ["Full Time"], "selling_points": ["Controls", "Middle Office Trade Support", "Operations"], "locations": ["Admiralty"], "categories": ["Banking / Finance", "Order Processing & Operation / Settlement"], "post_time": "2022-01-12T03:15:34Z", "salary": {"currency": "HKD", "max": 34999, "min": 25000, "period": "monthly", "term": null}, "salary_visible": true, "title_keywords": ["associate"], "responsibilities": ["reporting", "control", "business initiatives", "aml", "management", "operations", "monitoring", "teams", "procedures", "investigation", "audit", "invoicing", "coordinate", "uat testing", "operational procedures", "coordination", "forecast", "report"], "requirements": {"degrees": [], "majors": [], "languages": [], "language_level": [], "hard_skills": ["integration", "processing", "aml"], "soft_skills": ["coordination", "responsible"], "languages_combined": []}, "experience_required": {"duration": [], "field": []}}, {"job_id": "100003009049752", "location_code": "hk", "company": "China Construction Bank (Asia) Corporation Limited", "job_title": "AVP/VP, AML Compliance Governance Professional", "description": "Main Responsibilities\n\n\u2022\u00a0Prepare AML reports and materials to head office and management, in both English and Chinese;\n\u2022 Assist to maintain the AML/CFT control and governance framework;\n\u2022 Liaise with internal and external auditors and regulators relating to AML audits/examinations or ad hoc projects;\n\u2022 Provide training on the Bank\u2019s AML/CFT policies, procedures and guidelines to heighten AML/CFT awareness;\n\u2022 Maintain and timely update Policies and Processes Manuals related to AML/CFT to be in line with corporate policies as well as the local regulatory requirements;\n\u2022 Provide advisory support and assistance to management and business on AML/CFT related queries and issues;\n\u2022 Review Policies and Processes Manuals updated by other business and non-business divisions or functions related to AML/CFT procedures;\n\u2022 Coordinate process changes as a result of regulatory/policy updates;\n\u2022 Handle Product ML risk assessment and review; and\n\u2022 Assist the Head of AML Compliance Governance to perform his/her duties and dealing with projects or tasks from to time being assigned.\n\nRequirements\n\n\u2022 Degree holder;\n\u2022 Minimum 4-8 years\u2019 experience in AML compliance, with CAMLP/ACAMS or relevant qualification would be an advantage;\n\u2022\u00a0Qualification in ECF is preferred;\n\u2022 Possess good knowledge of banking operations, products and services;\n\u2022 Self-motivated, independent with good communication and interpersonal skills;\n\u2022 Fluent written and spoken English, Cantonese and Mandarin;\n\u2022 Proficient in PC skills including MS Word and Excel; and\n\u2022 Attentive to details, compliance and control oriented, diligent and proactive.\n\n\nApplicants who are not contacted within 8 weeks may consider their applications unsuccessful and their personal data will be retained by the bank for a period up to two years.\n\nAll information provided by applicants will be used for recruitment purposes only and will be used strictly in accordance with the bank\u2019s personal data policies, a copy of which will be provided upon request.", "employment_types": ["Full Time"], "selling_points": ["Minimum 4-8 years of relevant work experience", "With CAMLP/ACAMS or relevant qualification", "Possess good knowledge of banking operations"], "locations": ["Not Specified"], "categories": ["Banking / Finance", "Order Processing & Operation / Settlement"], "post_time": "2022-01-14T09:11:31Z", "salary": {"currency": null, "max": null, "min": null, "period": "monthly", "term": null}, "salary_visible": false, "title_keywords": ["aml compliance"], "responsibilities": ["provide training", "management", "control", "aml", "guidelines", "policies", "regulatory requirements", "review", "procedures", "compliance", "audits", "coordinate", "maintain", "reports", "ad hoc projects", "liaise with", "external auditors"], "requirements": {"degrees": ["degree holder"], "majors": [], "languages": ["cantonese", "english", "mandarin"], "language_level": ["fluent"], "hard_skills": ["excel", "aml", "acams", "pc skills", "ms word"], "soft_skills": ["self-motivated", "independent", "attentive to details", "diligent", "communication and interpersonal skills", "proactive"], "languages_combined": [{"language": "cantonese", "language_level": ["fluent"]}, {"language": "english", "language_level": ["fluent"]}, {"language": "mandarin", "language_level": ["fluent"]}]}, "experience_required": {"duration": ["minimum 4-8 years"], "field": ["compliance"]}}, {"job_id": "100003009048326", "location_code": "hk", "company": "Links International", "job_title": "Responsible officer (Leading Securities ,1,4,6,9)", "description": "About the Client\n\nMy client is a Leading Securities with strong presence in Greater China. To cope with their new business in Hong Kong, they are currently looking for a Responsible Officer to join and grow with the company.\n\nResponsibilities:\n\nSet up a relevant license team and act as Responsible Officer with management responsibilities\nSupervise SFC regulated activities in Type 1, 4,6,9 of the company\nSupervise and manage daily operations to ensure full regulatory compliance\nProvide advice to BOD on strategic activities in compliance\nReview and update risk control, operational policies and procedures\n\nRequirements:\n\nBachelor degree or above\nAt least 5-8 years relevant experience in Securities& Asset Management.\nCurrent SFC RO license holder in any part or all of Type 1, 4, 6,9 regulated activities.\nFamiliar with structure set up, sales & marketing, product development\nSound knowledge of SFO, SFC codes & guidelines, regulations", "employment_types": ["Full Time", "Permanent"], "selling_points": ["Leading Securities", "Attractive Package with options", "Type 1,4,6,9"], "locations": ["Not Specified"], "categories": ["Banking / Finance", "Financial Services", "Order Processing & Operation / Settlement"], "post_time": "2022-01-14T06:16:04Z", "salary": {"currency": "HKD", "max": 119999, "min": 90000, "period": "monthly", "term": null}, "salary_visible": true, "title_keywords": ["responsible officer"], "responsibilities": ["management", "control", "policies", "review", "compliance", "procedures", "provide advice", "manage daily operations"], "requirements": {"degrees": ["degree or above", "bachelor"], "majors": [], "languages": [], "language_level": [], "hard_skills": ["sfo", "codes"], "soft_skills": [], "languages_combined": []}, "experience_required": {"duration": ["at least 5-8 years"], "field": ["securities", "relevant experience", "asset management"]}}, {"job_id": "100003009046772", "location_code": "hk", "company": "OCBC Wing Hang Bank Limited", "job_title": "Remittance Manager", "description": "Responsibilities:\n\u2022\u00a0\u00a0 \u00a0Direct supervise the day-to-day work of Remittance Operations\n\u2022\u00a0\u00a0 \u00a0Authenticate documents of Remittance Operations under Local/Foreign Signatory requirement\u00a0\n\u2022\u00a0\u00a0 \u00a0Scan Remittance transactions and report any suspicious items including Money-Laundering and Sanctioned / High Risk Countries activities to AML/CFT Compliance Officer by submitting STR form\n\u2022\u00a0\u00a0 \u00a0Conduct a monthly refresher briefing to all staff of the contents of training materials and the bank\u2019s policy relating to customer service and proper disposal of customer or bank information\n\u2022\u00a0\u00a0 \u00a0Authorize the Violation Detection transactions at AML System\n\u2022\u00a0\u00a0 \u00a0Assist the Department Head to act as the First Approver of all subordinates at E-leave System and perform the Administration tasks of Remittance Department\n\u2022\u00a0\u00a0 \u00a0Report/recommend to Department Head of any performance feedback/problems, improvement and modification of the Operational procedures\n\nRequirements:\n\u2022\u00a0\u00a0 \u00a0Post-secondary education or above\n\u2022\u00a0\u00a0 \u00a0At least 5 years\u2019 banking experience in remittance operations\n\u2022\u00a0\u00a0 \u00a0Courtesy, responsible, reliable\u00a0\n\u2022\u00a0\u00a0 \u00a0Good command of spoken English and Mandarin\n\u2022\u00a0\u00a0 \u00a0Good PC knowledge, including MS Word, Excel and Chinese word processing\n\u00a0\n\nAttractive remuneration package will be offered to the right candidate. Please apply with full resume stating present & expected salary and contact phone number to\u00a0The Human Resources Manager, 10/F, 161 Queen\u2019s Road Central, Hong Kong. Please quote the reference.\n\nPersonal data collected will be used for recruitment purpose only. For more information, please visit our website:\u00a0http://www.ocbcwhhk.com.", "employment_types": ["Full Time", "Permanent"], "selling_points": ["Post-secondary education or above", "At least 5 years\u2019 banking experience", "Direct supervise the day-to-day work of Remittance"], "locations": ["Sheung Wan"], "categories": ["Banking / Finance", "Retail Banking", "Financial Services", "Order Processing & Operation / Settlement"], "post_time": "2022-01-14T01:00:49Z", "salary": {"currency": null, "max": null, "min": null, "period": "monthly", "term": null}, "salary_visible": false, "title_keywords": ["manager"], "responsibilities": ["administration", "aml", "operations", "compliance", "transactions", "customer service", "operational procedures", "contents", "report"], "requirements": {"degrees": ["secondary education"], "majors": [], "languages": ["english", "chinese", "mandarin"], "language_level": ["good command", "good"], "hard_skills": ["excel", "pc knowledge", "chinese word processing", "ms word"], "soft_skills": ["reliable", "responsible"], "languages_combined": [{"language": "english", "language_level": ["good command", "good"]}, {"language": "chinese", "language_level": ["good"]}, {"language": "mandarin", "language_level": ["good command", "good"]}]}, "experience_required": {"duration": ["at least 5 years"], "field": ["banking experience"]}}, {"job_id": "100003009050747", "location_code": "hk", "company": "Dah Sing Financial Group", "job_title": "OK Finance - Branch Officer", "description": "Job Purpose:\n\n\nDirect and supervise the junior staff in performing the loan processing and administration including conduct loan interviews, data input into the system and loan disbursement.\nMain Responsibilities:\nAssist in day-to-day management of branch operation and ensure to deliver high quality service to customers.\nPerform credit analysis, evaluation and recommend loan approval according to the established credit guideline.\nCoach and train junior staff on delivering both quality service and sale support activity.\nIncumbent Requirements:\nForm 5 / Matriculated or above.\nAt least 3 years' experience in Finance/ Banking industry specialized in Consumer Finance business.\nFamiliar with branch operation & loan application processing\nGood interpersonal and communication skill.\nGood knowledge of MS office.\nGood command of written & spoken English and Chinese.\nCandidates with more experiences may be considered as Senior Branch Officer.\nPlease note that only shortlisted candidates will be notified.", "employment_types": ["Full Time", "Permanent"], "selling_points": ["Day-to-day management of branch operation", "Form 5 / Matriculated or above", "At least 3 years' experience in Finance/ Banking"], "locations": ["Not Specified"], "categories": ["Banking / Finance", "Credit Analysis / Approval", "Loan", "Order Processing & Operation / Settlement"], "post_time": "2022-01-14T11:15:46Z", "salary": {"currency": null, "max": null, "min": null, "period": "monthly", "term": null}, "salary_visible": false, "title_keywords": ["officer"], "responsibilities": ["day-to-day management", "analysis", "quality", "evaluation"], "requirements": {"degrees": ["form 5"], "majors": [], "languages": ["english", "chinese"], "language_level": ["good command"], "hard_skills": ["processing", "ms office"], "soft_skills": ["communication skill", "interpersonal"], "languages_combined": [{"language": "english", "language_level": ["good command"]}, {"language": "chinese", "language_level": ["good command"]}]}, "experience_required": {"duration": ["at least 3 years"], "field": ["finance", "business", "banking industry"]}}, {"job_id": "100003009049829", "location_code": "hk", "company": "Zebra Strategic Outsource Solution Ltd", "job_title": "Office Clerk (Banking)", "description": "Responsibilities:\n\nAssist administrative support to the department\nProvide banking support including documentation, enquiries etc.\nHandle system data entries and document fillings\nRegular reports update\nPerform other duties assigned by managers or Department Head from time to time\n\nRequirements:\n\nUniversity Graduate\n2 years' banking operations experience\nProficiency in MS Office applications\nGood communication skills in Cantonese, English and Mandarin", "employment_types": ["Full Time", "Contract"], "selling_points": [], "locations": ["Southern Area"], "categories": ["Admin & HR", "Clerical / Admin Staff", "Banking / Finance", "Others", "Order Processing & Operation / Settlement"], "post_time": "2022-01-14T09:17:42Z", "salary": {"currency": null, "max": null, "min": null, "period": "monthly", "term": null}, "salary_visible": false, "title_keywords": ["office clerk"], "responsibilities": ["perform other duties", "administrative support", "system data", "reports", "banking", "documentation"], "requirements": {"degrees": ["university graduate"], "majors": [], "languages": ["cantonese", "english", "mandarin"], "language_level": ["good"], "hard_skills": ["ms office"], "soft_skills": ["communication skills"], "languages_combined": [{"language": "cantonese", "language_level": ["good"]}, {"language": "english", "language_level": ["good"]}, {"language": "mandarin", "language_level": ["good"]}]}, "experience_required": {"duration": ["2 years"], "field": ["banking"]}}, {"job_id": "100003009044771", "location_code": "hk", "company": "Shandong Gold Financial Holdings Group (Hongkong) Co., Limited", "job_title": "AVP - Commodities Import & Export", "description": "The company sincerely recruits an Assistant Vice President - Commodities Import & Export as the following requirements:\n\n\nJob Description:\u00a0\n\nBusiness development and clients\u2019 relationship management in international trade for commodities, non-ferrous metals and precious metals, candidates with clients resource are highly preferred;\nWork closely with both external and internal parties to identify good sourcing and procurement opportunities;\nFollow up on import & export Customs clearing, insurance, physical delivery and settlement, logistics and warehousing procedures and documentation when necessary;\nMonitor trade to ensure all executions are in compliance with relevant legal and regulatory requirements;\nFollow up on clients\u2019 orders and payment settlement;\nBusiness travel may be required.\n\n\nRequirements:\u00a0\n\nMaster\u2019s Degree or above, preferably in International Trade, Finance, Business Management or relevant majors;\n8-10 years\u2019 experience in international trade for commodities, non-ferrous metals or precious metals;\nFamiliar with Letter of Credit operations and UCP rules;\nComprehensive knowledge in import and export documentation and shipping process and requirements;\nExcellent command of written and spoken English and Chinese. Fluent in Mandarin is an advantage.\nPersonal data collected will be used strictly for recruitment-related purposes only and in accordance with the relevant data protection law.", "employment_types": ["Full Time", "Permanent"], "selling_points": [], "locations": ["Central"], "categories": ["Banking / Finance", "Financial Services", "Transportation & Logistics", "Supply Chain", "Order Processing & Operation / Settlement"], "post_time": "2022-01-13T06:13:04Z", "salary": {"currency": null, "max": null, "min": null, "period": "monthly", "term": null}, "salary_visible": false, "title_keywords": [], "responsibilities": ["warehousing", "management", "regulatory requirements", "compliance", "procedures", "monitor", "payment", "logistics", "documentation", "insurance", "internal parties"], "requirements": {"degrees": ["degree or above", "master"], "majors": ["finance", "business"], "languages": ["english", "chinese", "mandarin"], "language_level": ["advantage", "excellent", "fluent"], "hard_skills": ["business management", "documentation", "import and export"], "soft_skills": ["comprehensive"], "languages_combined": [{"language": "english", "language_level": ["excellent"]}, {"language": "chinese", "language_level": ["excellent"]}, {"language": "mandarin", "language_level": ["fluent", "advantage"]}]}, "experience_required": {"duration": ["8-10 years"], "field": []}}, {"job_id": "100003009050827", "location_code": "hk", "company": "Bank of Communications Trustee Limited", "job_title": "Head of Private Trust Business", "description": "Responsibilities:\nFormulate the goals, objectives and business plan of the Private Trust business sector\nDesign and devise business plan effectively for promoting and securing trust services to high net worth private trust clients (both bank and non-bank channels)\nLead the team to ensure smooth delivery of trust administration and customer relationship work\nCollaborate and communicate with both internal and external stakeholders\nTrain and develop subordinates so that staff can perform up to the required standard and successors can be identified\nPerform ad-hoc assignments as required\nRequirements:\nDegree in Law, Accounting or business related disciplines, preferably with professional qualification such as HKCIS, CPA, TEP, ACCA\nMin 5 years of solid experience in private trust business with 3 years in managerial role preferred\nSound knowledge in trust set-up and routine administrative operation\nCapability to draw up effective marketing plan independently\nGood business acumen with innovative ideas\nMarketing experience in Mainland China market is an advantage\nFluency in both written and spoken English and Chinese, Putonghua is a must\nImmediately available is highly preferred\nPlease click \"Apply Now\" to submit your application.\nPersonal data collected will be used for recruitment purpose only.", "employment_types": ["Full Time", "Permanent"], "selling_points": ["Design and devise business plan effectively", "Degree in Law, Accounting", "Min 5 years of solid experience"], "locations": ["Not Specified"], "categories": ["Banking / Finance", "Financial Services", "Others", "Order Processing & Operation / Settlement"], "post_time": "2022-01-14T11:31:01Z", "salary": {"currency": null, "max": null, "min": null, "period": "monthly", "term": null}, "salary_visible": false, "title_keywords": [], "responsibilities": ["collaborate", "communicate with", "ad-hoc assignments", "design", "develop", "business plan", "administration"], "requirements": {"degrees": ["degree"], "majors": ["business", "related disciplines", "accounting", "law"], "languages": ["putonghua", "english", "chinese"], "language_level": ["fluency"], "hard_skills": ["cpa", "acca", "acumen"], "soft_skills": ["business acumen", "independently", "innovative"], "languages_combined": [{"language": "putonghua", "language_level": ["fluency"]}, {"language": "english", "language_level": ["fluency"]}, {"language": "chinese", "language_level": ["fluency"]}]}, "experience_required": {"duration": ["3 years", "min 5 years"], "field": ["managerial", "business", "marketing"]}}, {"job_id": "100003009048328", "location_code": "hk", "company": "Links International", "job_title": "Responsible officer (Leading Asset Management)", "description": "About the Client\n\nMy client is a Leading Securities with strong presence in Greater China. To cope with their new business in Hong Kong, they are currently looking for a Responsible Officer to join and grow with the company.\n\nResponsibilities:\n\nSet up a relevant license team and act as Responsible Officer with management responsibilities\nSupervise SFC regulated activities in Type 4,9 of the company\nSupervise and manage daily operations to ensure full regulatory compliance\nProvide advice to BOD on strategic activities in compliance\nReview and update risk control, operational policies and procedures\n\nRequirements:\n\nBachelor degree or above\nAt least 5-8 years relevant experience in Securities& Asset Management.\nCurrent SFC RO license holder in any part or all of Type 4, 9 regulated activities.\nFamiliar with structure set up, sales & marketing, product development\nSound knowledge of SFO, SFC codes & guidelines, regulations", "employment_types": ["Full Time", "Permanent"], "selling_points": ["Leading Asset Management", "Attractive Package with options", "Flexible Working Hours"], "locations": ["Not Specified"], "categories": ["Banking / Finance", "Financial Services", "Order Processing & Operation / Settlement"], "post_time": "2022-01-14T06:17:09Z", "salary": {"currency": "HKD", "max": 119999, "min": 70000, "period": "monthly", "term": null}, "salary_visible": true, "title_keywords": ["asset management", "responsible officer"], "responsibilities": ["management", "control", "policies", "review", "compliance", "procedures", "provide advice", "manage daily operations"], "requirements": {"degrees": ["degree or above", "bachelor"], "majors": [], "languages": [], "language_level": [], "hard_skills": ["sfo", "codes"], "soft_skills": [], "languages_combined": []}, "experience_required": {"duration": ["at least 5-8 years"], "field": ["securities", "relevant experience", "asset management"]}}, {"job_id": "100003009047735", "location_code": "hk", "company": "Public Bank (Hong Kong) Ltd", "job_title": "Officer \u2013 Digital Transformation (Digital Marketing) (Ref: JD-ODTM)", "description": "Perform daily operations for social media platforms, websites and digital marketing campaigns\nManage relevant analytics and optimize various digital campaigns to drive sales\nConduct market survey on digital products and services offered by other financial institutions\nSupport marketing projects and perform ad-hoc duties as assigned\nSupport the hotline related to internet banking, mobile banking and digital banking\nDegree holder with minimum 1 year relevant experience\nGood communication skills in both English and Chinese\nGood interpersonal and coordination skills\n\nTo apply, interested parties please follow the application methods available in the Bank\u2019s career website https://www.publicbank.com.hk/en/aboutus/careeropportunities. You can send us your resume quoting our job reference number together with present & expected salary (a must) to the Human Resources Department by email or fax at 2815 3157 or by post to Human Resources Department, 12/F, Public Bank Centre, 120 Des Voeux Road Central, Hong Kong. You may also visit our career website for other career opportunities available within our Group.\n\nPersonal data collected will be used for recruitment purpose only and will be treated in accordance with the Bank\u2019s Personal Information Collection Statement, a copy of which has been available in the Bank\u2019s career website.", "employment_types": ["Full Time", "Permanent"], "selling_points": [], "locations": ["Not Specified"], "categories": ["Banking / Finance", "Analyst", "Order Processing & Operation / Settlement", "Marketing / Public Relations", "Digital Marketing"], "post_time": "2022-01-15T03:49:02Z", "salary": {"currency": null, "max": null, "min": null, "period": null, "term": null}, "salary_visible": false, "title_keywords": ["officer", "digital marketing"], "responsibilities": ["digital marketing campaigns", "social media platforms", "marketing projects", "banking", "communication", "daily operations", "digital campaigns", "ad-hoc duties", "coordination", "drive sales"], "requirements": {"degrees": ["degree holder"], "majors": [], "languages": ["english", "chinese"], "language_level": ["good"], "hard_skills": ["mobile"], "soft_skills": ["communication skills", "coordination skills", "interpersonal", "ad-hoc duties"], "languages_combined": [{"language": "english", "language_level": ["good"]}, {"language": "chinese", "language_level": ["good"]}]}, "experience_required": {"duration": ["minimum 1 year"], "field": ["relevant experience"]}}, {"job_id": "100003009050806", "location_code": "hk", "company": "AMG Wealth Management Limited", "job_title": "Senior Officer / Officer \u2013 Business Support", "description": "Responsibilities:\n\nCooperate with team members to provide professional business support\nProvide sales and administrative support to advisers\nSupport documents preparation and generate proposals\n\u00a0Liaise with various departments and customers to ensure timely and quality responses to enquiries\nMaintain good business relationship with frontline advisers\nAbility to build rapport with colleagues and business partners\nAssist in any ad-hoc tasks or duties as required\n\n\u00a0Requirement:\n\n2 years or above working experience is required\nGood communication and interpersonal skills\nStrong team player with positive attitude\nGood spoken and written English & Chinese. Fluent in Mandarin\nCandidate with less experience will be considered as Officer\nHolder of IIQE paper 1, 3 and 5 is preferred\nHong Kong Diploma of Secondary Education Examination (Level 2 or above\u00a0in 5 subjects, including Chinese or English, and Mathematics) or Hong Kong Certificate of Education Examination (Grade E or above in 5 subjects, including Chinese or English* and Mathematics)\n\nLocation: Western District, Hong Kong (Sai Ying Pun MTR)\n\nInterested parties, please send full resume by clicking \"Apply Now\" or mail to Human Resource Department at 40/F, 118 Connaught Road West, HONG KONG.\n\nPersonal data collected will be used for recruitment purpose only.", "employment_types": ["Full Time", "Permanent"], "selling_points": ["Medical & Dental Insurance & Birthday Leave", "Comprehensive Training", "Promotion Opportunity"], "locations": ["Sai Ying Pun"], "categories": ["Insurance", "Insurance Agent / Broker", "Banking / Finance", "Order Processing & Operation / Settlement", "Wealth Management"], "post_time": "2022-01-14T11:26:36Z", "salary": {"currency": null, "max": null, "min": null, "period": "monthly", "term": null}, "salary_visible": false, "title_keywords": ["senior officer", "officer"], "responsibilities": ["administrative support", "ad-hoc tasks", "quality", "liaise with various departments", "maintain", "cooperate with"], "requirements": {"degrees": ["certificate", "diploma", "secondary education"], "majors": ["mathematics"], "languages": ["english", "chinese", "mandarin"], "language_level": ["fluent", "good"], "hard_skills": ["iiqe paper"], "soft_skills": ["positive attitude", "team player", "communication and interpersonal skills"], "languages_combined": [{"language": "english", "language_level": ["good"]}, {"language": "chinese", "language_level": ["good"]}, {"language": "mandarin", "language_level": ["fluent"]}]}, "experience_required": {"duration": ["2 years"], "field": []}}, {"job_id": "100003009049753", "location_code": "hk", "company": "China Construction Bank (Asia) Corporation Limited", "job_title": "Manager/ AVP, AML Compliance Governance Professional", "description": "Main Responsibilities\n\n- Responsible for AML related IT system project management, data retrieval and analysis;\n- Participate in various system enhancement initiatives including but not limited to KYC system, name screening system, transaction screening system and AML related machine leaning projects;\n- Key coordinator with IT units for AML Compliance;\n- Coordinate with stakeholders and follow up on AML related system issues; and\n- Handle system/data related ad-hoc tasks as assigned\n\nRequirements\n\n- Degree holder;\n- Minimum 2-5 years of relevant work experience in compliance related system development, data\u00a0 \u00a0 \u00a0 analysis, data mapping, ETL process, data modelling and data visualization output, with compliance experience preferred;\n- Experience in Artificial Intelligence/Machine Learning, SQL is preferred;\n- Qualification in ECF is preferred;\n- Possession of good knowledge on banking operations, products and services would be an advantage;\n- Excellent in problem solving, interpersonal, analytical and organizational skills;\n- Excellent team work spirit;\n- Good command of both spoken and written English and Chinese;\n- Proficient in PC skills; and\n- Attentive to details, compliance and control oriented, diligent and proactive\n\nApplicants who are not contacted within 8 weeks may consider their applications unsuccessful and their personal data will be retained by the bank for a period up to two years.\n\nAll information provided by applicants will be used for recruitment purposes only and will be used strictly in accordance with the bank\u2019s personal data policies, a copy of which will be provided upon request.", "employment_types": ["Full Time"], "selling_points": ["Minimum 2-5 years of relevant work experience", "Experience in Artificial Intelligence", "Proficient in PC skills"], "locations": ["Not Specified"], "categories": ["Banking / Finance", "Order Processing & Operation / Settlement"], "post_time": "2022-01-14T09:11:31Z", "salary": {"currency": null, "max": null, "min": null, "period": "monthly", "term": null}, "salary_visible": false, "title_keywords": ["manager", "aml compliance"], "responsibilities": ["aml", "data", "analysis", "compliance", "coordinate with stakeholders", "ad-hoc tasks", "project management", "kyc"], "requirements": {"degrees": ["degree holder"], "majors": [], "languages": ["english", "chinese"], "language_level": ["good command"], "hard_skills": ["analysis", "sql", "problem solving", "data visualization", "pc skills"], "soft_skills": ["organizational skills", "attentive to details", "diligent", "problem solving", "learning", "proactive", "interpersonal"], "languages_combined": [{"language": "english", "language_level": ["good command"]}, {"language": "chinese", "language_level": ["good command"]}]}, "experience_required": {"duration": ["minimum 2-5 years"], "field": ["related", "sql", "compliance", "system development"]}}, {"job_id": "100003009043798", "location_code": "hk", "company": "OCBC Wing Hang Bank Limited", "job_title": "Bank Officer, Retail Operations", "description": "Responsibilities\n\u200bHandle fixed deposit and retail account transactions\nSupport reconciliation of outward clearing and verification of inward clearing daily\nAct as a back-up teller to handle counter and cash transactions\nHandle SWIFT transaction in an accurate and timely manner\nHandle enquiries from various departments and overseas branches\nParticipate in the assigned UAT/BCP/project execution\nPerform other duties as delegated and assigned by the department head\nRequirements\nTertiary education with minimum 5 years of relevant experience in banking industry\nGood knowledge in retail banking products and services, including current savings, fixed deposit related transactions handling\nPossess knowledge of cash handling will be an advantage\nKnowledge in SWIFT application is a plus\nGood interpersonal, communication and analytical skills\nGood team player and able to work under pressure\nGood command of both written and spoken English and Chinese, proficiency in Mandarin will be an advantage\nGood PC skills in Microsoft Office Applications\n\nAttractive remuneration package will be offered to the right candidate. Please apply with full resume stating present & expected salary and contact phone number to\u00a0The Human Resources Manager, 10/F, 161 Queen\u2019s Road Central, Hong Kong.\u00a0Please quote the reference.\n\nPersonal data collected will be used for recruitment purpose only. For more information, please visit our website:\u00a0http://www.ocbcwhhk.com.", "employment_types": ["Full Time", "Permanent"], "selling_points": ["Remittance", "Fixed Deposit", "SWIFT application"], "locations": ["Sheung Wan"], "categories": ["Banking / Finance", "Retail Banking", "Others", "Order Processing & Operation / Settlement"], "post_time": "2022-01-13T01:59:54Z", "salary": {"currency": null, "max": null, "min": null, "period": "monthly", "term": null}, "salary_visible": false, "title_keywords": ["officer", "operations"], "responsibilities": ["perform other duties", "fixed deposit", "uat", "transactions", "handle enquiries"], "requirements": {"degrees": [], "majors": [], "languages": ["english", "chinese", "mandarin"], "language_level": ["advantage", "proficiency", "good command"], "hard_skills": ["plus", "microsoft office", "analytical skills", "swift", "pc skills"], "soft_skills": ["good team player", "analytical skills", "communication", "interpersonal", "work under pressure"], "languages_combined": [{"language": "english", "language_level": ["advantage", "good command"]}, {"language": "chinese", "language_level": ["advantage", "good command"]}, {"language": "mandarin", "language_level": ["proficiency", "advantage", "good command"]}]}, "experience_required": {"duration": ["minimum 5 years"], "field": ["banking industry", "relevant experience", "education"]}}, {"job_id": "100003009042457", "location_code": "hk", "company": "Bank of Communications Trustee Limited", "job_title": "Fund Administrator, Transfer Agency Team", "description": "Key Responsibilities:\n\nPerform settlement functions including investor subscription and redemption, dividend distribution\nPerform client account opening and conduct KYC (know your client) / AML (Anti-Money Laundering) checking\nPerform order processing and data input and product master update\nSupport the on-going in-house system enhancement and improvement\nPerform ad-hoc assignments as required\n\nJob Requirements:\n\nDiploma in business related disciplines with minimum 1 year\u2019s working experience in banking or financial services industry\u00a0 \u00a0\nGood understanding in bank / fund operations is preferable\nSelf-motivated, detail-oriented, ability to work independently and under pressure\nFresh graduate in business related disciplines may also be considered\nProficiency in PC skills including Microsoft Word, Excel and PowerPoint\nGood command of Chinese and English (Putonghua is preferred)\nImmediately available is highly preferred\n\n\n", "employment_types": ["Full Time", "Permanent"], "selling_points": ["Perform ad-hoc assignments as required", "Diploma in business related", "1 year\u2019s working experience"], "locations": ["Not Specified"], "categories": ["Banking / Finance", "Dealing & Trading", "Fund Management", "Order Processing & Operation / Settlement"], "post_time": "2022-01-12T07:37:31Z", "salary": {"currency": null, "max": null, "min": null, "period": "monthly", "term": null}, "salary_visible": false, "title_keywords": ["administrator"], "responsibilities": ["aml", "account opening", "ad-hoc assignments", "checking", "data input", "order processing", "kyc"], "requirements": {"degrees": ["diploma", "fresh graduate"], "majors": ["related disciplines", "business"], "languages": ["putonghua", "english", "chinese"], "language_level": ["good command"], "hard_skills": ["excel", "pc skills", "microsoft word", "powerpoint"], "soft_skills": ["self-motivated", "under pressure", "work independently", "detail-oriented"], "languages_combined": [{"language": "putonghua", "language_level": ["good command"]}, {"language": "english", "language_level": ["good command"]}, {"language": "chinese", "language_level": ["good command"]}]}, "experience_required": {"duration": ["minimum 1 year"], "field": ["related", "financial services industry", "business", "banking"]}}, {"job_id": "100003009043492", "location_code": "hk", "company": "DBS Bank Ltd", "job_title": "Analyst/ Senior Officer/ Officer, Custody Operations", "description": "Business Function\n\nTechnology and Operations (T&O) enables aand empowers the bank with an efficient, nimble and resilient infrastructure through a strategic focus on productivity, quality & control, technology, people capability and innovation. In T&O, we manage the majority of the Bank's operational processes and inspire to delight our business partners through our multiple banking delivery channels.\n\nResponsibilities\nExecute securities transactions in settlement, corporate action, account opening and billing efficiently and accurately\nHandle day-to-day settlement (scripless and phyiscal) on equities, fixed income and other types of instruments.\nProcess voluntary and involuntary corporate action\nProcess monthly fee billings and collections\nProcess dispatches of holding statements\nProcess custody account maintenance\nPerform static data maintenance and information update.\nProvide second level client services.\u00a0 Handle customer inquiries in an efficient manner\nParticipate in user acceptance test for system enhancements and project initiatives and business development e.g. customer implementation, business continuity management, review of operational procedures, policies and guidelines; specific and job-related training, etc.\nHandle regular and ad hoc tasks as designed by Team Manager and Department Head\n\u00a0\nRequirements\n1 to 2 years of relevant experience in securities operations.\u00a0 Fresh graduates with good potential and high caliber will be considered.\nThe role is initially attached to one custody function (settlement, corporate action, billing or account opening).\u00a0 Good performers have the opportunity to rotate to other functions on a fast track for development into well rounded professionals in custody operations.\nKnowledge of CCASS, SFC rules, SFO and HKICL is an advantage\nAccuracy and thoroughness in work\nResult- and customer-oriented\nGood Interpersonal, communication skills and problem-solving skills\nPositive attitude and self-motivated\nGood team player, supportive and flexible to take up team tasks\n\nApply Now\n\nWe offer a competitive salary and benefits package and the professional advantages of a dynamic environment that supports your development and recognises your achievements.\n\nWe regret only shortlisted candidates will be notified.", "employment_types": ["Full Time"], "selling_points": ["Experience in custody Operation is an advantage", "Fresh Graduate are also welcome", "See job description."], "locations": ["Admiralty"], "categories": ["Banking / Finance", "Corporate Banking", "Order Processing & Operation / Settlement"], "post_time": "2022-01-12T14:25:43Z", "salary": {"currency": null, "max": null, "min": null, "period": "monthly", "term": null}, "salary_visible": false, "title_keywords": ["analyst", "senior officer", "officer", "operations"], "responsibilities": ["business continuity", "management", "maintenance", "data", "customer inquiries", "account opening", "billings", "review", "policies", "implementation", "transactions", "guidelines", "ad hoc tasks", "operational procedures", "account maintenance"], "requirements": {"degrees": [], "majors": [], "languages": [], "language_level": [], "hard_skills": ["account opening", "sfc rules", "dynamic", "ccass", "problem-solving skills", "sfo"], "soft_skills": ["flexible", "communication skills", "self-motivated", "good team player", "supportive", "dynamic environment", "positive attitude", "customer-oriented", "problem-solving skills", "interpersonal"], "languages_combined": []}, "experience_required": {"duration": ["1 to 2 years"], "field": ["securities", "relevant experience"]}}, {"job_id": "100003009044267", "location_code": "hk", "company": "Asia Progress Executive Limited", "job_title": "Treasury Settlement Manager /Asst Manager- Global Markets", "description": "Our client is Corporate Bank\u00a0to cope with the rapid business expansion, they are now inviting high caliber candidates to join the team\n\nTreasury Settlement Manager /Asst Manager - Global Markets ( many posts)\u00a0\n\nResponsibilities:-\n\nExecute daily settlement of treasury products, such as fixed income, fund, structure deposit and other derivatives\nTo closely monitor daily treasury operations process and make sure that they are duly completed within timeline\nTo review and authorize the payment instructions\nHandle system enhancement projects from time to time\n\nRequirements:-\n\nUniversity graduates, preferably major in Banking, Economics, Finance or related disciplines\nAt least 6-8 years\u2019 experience in treasury settlement or related areas\nFamiliar with local and overseas settlement system/practices such as CCASS\nSound knowledge of eIPO, SWIFT, RTGS or other related systems\nGood understanding of trade repository reporting of HKMA (\"TR\") and collateral management\nFamiliar with SFO and related regulatory requirements\nGood understanding of Bank and Regulatory policies, procedures, practices and rules\nGood command of both spoken and written English and Chinese; Putonghua speaking is definite an asset\nCandidates with less experience can be considered as Assistant Manager\n\nPlease send full resume with\u00a0present & expected\u00a0salary to expedite sourcing\u00a0in\u00a0MS-WORD\u00a0format by clicking \u201cAPPLY NOW\u201d\nPlease quote our reference in your application\nPersonal data provided by job applicants will be used strictly in accordance with the employer\u2019s personal data policies, a copy of which will be provided upon request\nAll information provided will be used for recruitment purpose only", "employment_types": ["Full Time"], "selling_points": ["Deg Holder; Min 6-8 yrs in Treasury Settlement", "CCASS; eIPO; SWIFT; RTGS; HKMA TR; SFO;", "Bank Reg Policy; Treasury Prdts; Enhance Projects"], "locations": ["Central & Western Area"], "categories": ["Banking / Finance", "Treasury", "Order Processing & Operation / Settlement", "Wealth Management"], "post_time": "2022-01-13T03:36:11Z", "salary": {"currency": null, "max": null, "min": null, "period": "monthly", "term": null}, "salary_visible": false, "title_keywords": ["settlement manager", "asst manager"], "responsibilities": ["operations", "review", "monitor", "payment", "enhancement projects"], "requirements": {"degrees": [], "majors": [], "languages": ["putonghua", "english", "chinese"], "language_level": ["good command"], "hard_skills": ["ms-word", "hkma", "ccass", "swift", "sfo"], "soft_skills": [], "languages_combined": [{"language": "putonghua", "language_level": []}, {"language": "english", "language_level": ["good command"]}, {"language": "chinese", "language_level": ["good command"]}]}, "experience_required": {"duration": ["at least 6-8 years"], "field": ["related"]}}, {"job_id": "100003009038578", "location_code": "hk", "company": "China Merchants Bank Co., Ltd.", "job_title": "Assistant Officer to Officer, Treasury Settlement team of Operations Department", "description": "Job Description:\n\nPerform daily settlement operations of different Investment products (FX/MM, Bonds, Commodities, Structured, Derivatives) of local and global market.\nPerform deal confirmation and accounting entries processing\nFollow up with inter-bank counterparties, customers, brokers and clearing agents/platform for trade confirmation or other issues.\nProcess fund transfer of Nostro/Vostro accounts and SWIFT MT202 payment.\nPerform data input and maintenance functions in various banking system\nExecute day-end reconciliation processing\nParticipate in UAT for new products and systems\n\nRequirements:\n\nUniversity degree or above\nAt least\u00a05 years banking operation experience, experience in treasury settlement and knowledge on operations of Clearing System (CMU, Clearstream/Euroclear, CCASS, LCH)\u00a0are preferred\nWork knowledge on SWIFT system and/or payment system\nFamiliar with Microsoft Word, Excel & PowerPoint\nExcellent command of spoken English, Mandarin & Cantonese\nGood interpersonal and communication skills\nA good team player, detail-oriented with good organizational skills", "employment_types": ["Full Time", "Permanent"], "selling_points": [], "locations": ["Central"], "categories": ["Banking / Finance", "Order Processing & Operation / Settlement"], "post_time": "2022-01-11T07:25:26Z", "salary": {"currency": null, "max": null, "min": null, "period": "monthly", "term": null}, "salary_visible": false, "title_keywords": ["assistant officer", "officer", "operations"], "responsibilities": ["uat", "maintenance", "operations", "systems", "data input", "payment", "trade confirmation", "banking"], "requirements": {"degrees": ["degree or above"], "majors": [], "languages": ["cantonese", "english", "mandarin"], "language_level": ["excellent"], "hard_skills": ["excel", "microsoft word", "powerpoint", "ccass", "swift"], "soft_skills": ["communication skills", "good team player", "organizational skills", "detail-oriented", "interpersonal"], "languages_combined": [{"language": "cantonese", "language_level": ["excellent"]}, {"language": "english", "language_level": ["excellent"]}, {"language": "mandarin", "language_level": ["excellent"]}]}, "experience_required": {"duration": ["at least 5 years"], "field": ["operation", "banking"]}}, {"job_id": "100003009048009", "location_code": "hk", "company": "OnePlatform Wealth Management Limited", "job_title": "Senior Officer/ Officer, Distributor Care Centre", "description": "Due to our business expansion, we are looking for high calibre candidates to share our vision and venture our success.\n\n\nThis role will be under Service and Operations Department to provide support for handling business from consultancy, platform business and other distributors.\n\nResponsibilities:\n\nProvide counter services by vetting documents face to face.\nProcess new business submission including Know Your Client (KYC) compliance checks in accordance with regulatory requirements.\nPerform ongoing Customer Risk Assessment (CRA) for existing clients.\nReview client account activities on an ongoing basis.\nUpdate Operational Procedure Manual for related processes.\nHandle enquiries including new business follow-up and policy servicing from consultancy, platform business and other distributors.\nCommunicate with business partners to resolve issues occurred during the business submission and post sales processes.\nUpdate reports for reviewing the service quantity and quality provided.\nHandle back-office duties, e.g. fund switching, filing, policy checking.\nAssist in ad-hoc projects as assigned.\n\nRequirements:\n\nUniversity graduated with at least 2 years of relevant working experience, preferably gained in banking, insurance industry.\nProactive with positive working attitude.\nSelf-motivated, organized and a committed team player.\nA good team player and be able to work independently.\nFast learner and be able to cope with rapid changes.\nProficiency in PC skills and MS office applications.\nGood command of spoken and written Chinese & English, Mandarin is a plus.\nWe offer competitive remuneration including career prospects to the right candidate. Interested parties please send detailed resume with availability, current and expected salaries to\u00a0Human Resources Department, OnePlatform Wealth Management Limited, Trust Tower, 68 Johnston Road, Wan Chai, Hong Kong\u00a0or by clicking the\u00a0Apply Now\u00a0button and upload your CV and cover letter.\n\n(All applications will be treated in strict confidence and used for recruitment purpose within OnePlatform Wealth Management Limited only. All applicants are kept on file 6 months from the date of the application.)", "employment_types": ["Full Time", "Permanent"], "selling_points": ["Provide counter services by vetting documents", "Process Know Your Client (KYC) compliance checks", "Perform ongoing Customer Risk Assessment (CRA)"], "locations": ["Wan Chai"], "categories": ["Banking / Finance", "Financial Services", "Sales, CS & Business Devpt", "Customer Service - Supervisor / Officer", "Order Processing & Operation / Settlement"], "post_time": "2022-01-14T04:28:20Z", "salary": {"currency": null, "max": null, "min": null, "period": "monthly", "term": null}, "salary_visible": false, "title_keywords": ["senior officer", "officer"], "responsibilities": ["communicate with", "regulatory requirements", "review", "compliance", "quality", "checking", "handle enquiries", "reports", "kyc", "ad-hoc projects"], "requirements": {"degrees": [], "majors": [], "languages": ["english", "chinese", "mandarin"], "language_level": ["good command"], "hard_skills": ["plus", "pc skills", "ms office", "rapid"], "soft_skills": ["organized", "self-motivated", "good team player", "work independently", "positive working attitude", "committed", "team player", "proactive", "fast learner"], "languages_combined": [{"language": "english", "language_level": ["good command"]}, {"language": "chinese", "language_level": ["good command"]}, {"language": "mandarin", "language_level": ["good command"]}]}, "experience_required": {"duration": ["at least 2 years"], "field": ["insurance industry", "relevant working experience", "banking"]}}, {"job_id": "100003009049317", "location_code": "hk", "company": "Shanghai Commercial Bank Ltd", "job_title": "Associate, Syndication Loan", "description": "Responsibilities:\n\nHandle all loan transactions and coordinate with internal working partners to ensure smooth and timely processing\nAssist in conducting credit review, monitoring credit quality and reporting signs of deterioration\nPerform customer due diligence\nPrepare reports e.g. overdue, rescheduled and classified accounts for the management's review\nProvide administrative support to the department\nRequirements:\n\nDegree holder in Accounting, Finance or related disciplines\nMinimum 1 year's administrative/operations support experience, preferably in financial institutions\nSelf-motivated and attentive to details\nFluency in written and spoken English and Chinese, preferably with proficiency in Putonghua\nConversant with MS Word, Excel, Powerpoint and Chinese Word Processing\n\nAttractive remuneration package will be offered to the right candidates. Interested parties please click\u00a0\"Apply Now\"\u00a0to submit your full resume with current and expected salary to the\u00a0Human Resources Division.\n\nPlease visit us at\u00a0www.shacombank.com.hk\u00a0for more information about our Bank.\n\nAll personal data collected will be used for recruitment related purposes strictly in accordance with the Bank's personal data policies, a copy of which will be provided immediately upon request by contacting our Personal Data Compliance Officer. Applicants who are not contacted within two months may consider their applications unsuccessful and the personal data collected from the applicants will be retained for no longer than two years from the date of rejection during which the applicants may be considered for other suitable positions within the Bank.", "employment_types": ["Full Time", "Permanent"], "selling_points": ["Handle all loan transactions", "Conduct credit review & monitor credit quality", "Perform customer due diligence"], "locations": ["Central"], "categories": ["Banking / Finance", "Loan", "Others", "Order Processing & Operation / Settlement"], "post_time": "2022-01-15T03:50:17Z", "salary": {"currency": null, "max": null, "min": null, "period": "monthly", "term": null}, "salary_visible": false, "title_keywords": ["associate"], "responsibilities": ["reporting", "management", "monitoring", "quality", "review", "coordinate with", "transactions", "customer due diligence", "prepare reports", "provide administrative support"], "requirements": {"degrees": ["degree holder"], "majors": ["related disciplines", "finance", "accounting"], "languages": ["putonghua", "english", "chinese"], "language_level": ["fluency", "proficiency"], "hard_skills": ["excel", "chinese word processing", "powerpoint", "ms word"], "soft_skills": ["self-motivated", "attentive to details"], "languages_combined": [{"language": "putonghua", "language_level": ["proficiency", "fluency"]}, {"language": "english", "language_level": ["proficiency", "fluency"]}, {"language": "chinese", "language_level": ["proficiency", "fluency"]}]}, "experience_required": {"duration": ["minimum 1 year"], "field": ["financial institutions", "administrative"]}}, {"job_id": "100003009044277", "location_code": "hk", "company": "Asia Progress Executive Limited", "job_title": "KYC Officer /SOW \u2013 Private Banking", "description": "Our client is a Foreign Bank Private Banking .To cope with the rapid business expansion they are now inviting high caliber candidates to join the team\n\nKYC Officer / SOW \u2013 Private Banking\n\nResponsibilities\n\nResponsible for the Account Opening operations, including client documentations and SOW review.\nConduct checks for client documentation i.e. customer verification in accordance to regulatory requirement.\nConduct checks for client onboarding and client review i.e. client due diligence, source of wealth corroboration, structure plausibility, name screening and transaction review etc.\nLiaise and communicate with stakeholders e.g. Front Office, Client Data Management, Compliance, Business Management.\nAssist in system enhancement UAT, ad-hoc tasks & projects.\nmust exp in private banking for KYC role\u00a0\n\nRequirements\n\nUniversity Degree holder.\nMinimum 3 years solid experience in handling both documentation and KYC due diligence checks in Private Banking a must\u00a0\nWell-versed with HKMA's AML requirements & risk assessment.\nGood knowledge in various corporate structures especially for trust & foundation in different jurisdiction.\u00a0\nMature, self-starter with good interpersonal skill, can work independently & willing to work overtime when required.\nGood command of written & spoken English/Cantonese/Chinese.\nProficient in Microsoft Word/Excel.\nECF on AML/CFT (Core Level).\n\nPlease send full resume with\u00a0present & expected\u00a0salary to expedite sourcing\u00a0in\u00a0MS-WORD\u00a0format by clicking \u201cAPPLY NOW\u201d\n\nPlease quote our reference in your application\n\nPersonal data provided by job applicants will be used strictly in accordance with the employer\u2019s personal data policies, a copy of which will be provided upon request\n\nAll information provided will be used for recruitment purpose only", "employment_types": ["Full Time"], "selling_points": ["Client onboarding,CDD review Account Document", "Deg 3yrs KYC /SOW solid exp in Private Banking", "KYC Doc,KYC review CDD periodic review Account"], "locations": ["Central & Western Area"], "categories": ["Banking / Finance", "Private Banking", "Order Processing & Operation / Settlement", "Wealth Management"], "post_time": "2022-01-13T03:38:10Z", "salary": {"currency": null, "max": null, "min": null, "period": "monthly", "term": null}, "salary_visible": false, "title_keywords": ["officer", "private banking"], "responsibilities": ["liaise", "due diligence", "communicate with", "management", "uat", "data", "account opening", "operations", "review", "compliance", "ad-hoc tasks", "kyc", "banking", "documentation"], "requirements": {"degrees": ["university degree"], "majors": [], "languages": ["cantonese", "english", "chinese"], "language_level": ["good command"], "hard_skills": ["excel", "ms-word", "microsoft word", "aml", "hkma", "cft", "kyc", "documentation"], "soft_skills": ["work independently", "work overtime", "mature", "interpersonal skill"], "languages_combined": [{"language": "cantonese", "language_level": ["good command"]}, {"language": "english", "language_level": ["good command"]}, {"language": "chinese", "language_level": ["good command"]}]}, "experience_required": {"duration": ["minimum 3 years"], "field": ["banking"]}}, {"job_id": "100003009037407", "location_code": "hk", "company": "CHINA INDUSTRIAL SECURITIES INTERNATIONAL FINANCIAL GROUP LIMITED", "job_title": "Asset Management, Operations/ Fund Operations", "description": "Job Duties and Responsibilities\n\nSupport daily operational duties of the funds, discretionary accounts and investment products (equities, fixed income, repo, private equity. etc)\nReconcile the fund/accounts\u2019 cash management, trade booking, position reconciliation and corporate action support\nOversee the fund NAV process ensuring full reconciliation of the fund administrator\u2019s NAV calculation as part of an internal maker-checker review\nOversee and review the operational support to the client onboarding process as pertains to AML/KYC in conjunction with the transfer agency\nOversee unmatched trades for timely settlement and liaise with custodians to reconcile any trade matching issues\nMaintain reasonable fund expenses and improve the fund expense ratio across all funds\nOversee the funds\u2019 financial audit and in conjunction with the fund\u2019s auditors, tax consultant and fund administrator\nWork with external Advisor to ensure FATCA and CRS reporting\u2019s processes adhere to the respective regulatory guidelines.\nWork with the platform development to streamline the operational process of the firm\u2019s products and assist in preparing and executing test cases and new systems support\n\nRequirements\n\nUniversity degree holder in business administration, Accountancy, Finance or related discipline are preferable\nMinimum 1-2years of experience in relevant asset management /fund administrator experience\nProduct knowledge of the fund operations workflow\nExperience in handling NAV calculations\nAble to take initiative and good at time management\nProficiency in Chinese (including Mandarin) and English are required\nImmediate Available is highly preferred", "employment_types": ["Full Time"], "selling_points": ["Immediate Available is highly preferred", "Support daily operation duties for asse management", "Securities"], "locations": ["Sheung Wan"], "categories": ["Banking / Finance", "Fund Management", "Order Processing & Operation / Settlement", "Asset Management"], "post_time": "2022-01-11T02:43:24Z", "salary": {"currency": null, "max": null, "min": null, "period": "monthly", "term": null}, "salary_visible": false, "title_keywords": ["operations", "asset management"], "responsibilities": ["tax", "reporting", "management", "operational support", "aml", "guidelines", "review", "expenses", "trade booking", "audit", "systems", "maintain", "executing", "kyc", "liaise with", "operational duties", "timely settlement"], "requirements": {"degrees": ["university degree"], "majors": ["finance", "business administration", "accountancy"], "languages": ["english", "chinese", "mandarin"], "language_level": ["proficiency"], "hard_skills": [], "soft_skills": ["time management", "initiative"], "languages_combined": [{"language": "english", "language_level": ["proficiency"]}, {"language": "chinese", "language_level": ["proficiency"]}, {"language": "mandarin", "language_level": ["proficiency"]}]}, "experience_required": {"duration": [], "field": ["asset management"]}}, {"job_id": "100003009038917", "location_code": "hk", "company": "CMB International Capital Corporation Limited", "job_title": "Associate / Vice President, Operations (Middle Office)", "description": "Responsibilities:\n\nPerform daily trade processing on various products including equity, fixed income, structured products etc.\nLiaise with counterparties/external clients on trade matching/confirmations\nManage static data/closing prices in trade booking systems\nResolve trade breaks\nLiaise with Settlement Team/Business/clients to ensure successful trade settlement\nCoordinate with other internal stakeholders including Compliance, Legal & Finance on the status of trades and ensure the completion of tasks\nProvide senior management with updates on the status of trades\nSupport new products and business initiatives. Provide inputs to trade flow and booking model\nProvide user requirements and perform UAT for system enhancements/migration\nRequirements:\n\n4-5 years of solid banking experience in middle office or related role\nKnowledge of front to back process in investment bank/brokerage firms\nProven ability to work under the pressure of tight timelines\nExtremely strong problem solving skills to create workarounds to ensure successful settlement\nTeam player who can also take on responsibility for transactions front to back\nAbility to think ahead and anticipate issues in advance so they can be mitigated\nA good understanding of banking operations, clearing systems and payments\nExcellent organisational skills and communication skills in English and Chinese", "employment_types": ["Full Time", "Permanent"], "selling_points": ["Familiar with daily trade processing", "Knowledge of front to back process", "Internal stakeholder coordination"], "locations": ["Central"], "categories": ["Banking / Finance", "Credit Collection", "Order Processing & Operation / Settlement", "Risk Management"], "post_time": "2022-01-11T08:08:51Z", "salary": {"currency": null, "max": null, "min": null, "period": "monthly", "term": null}, "salary_visible": false, "title_keywords": ["vice president", "operations", "associate"], "responsibilities": ["business initiatives", "uat", "data", "systems", "coordinate with", "trade booking", "compliance", "booking", "liaise with", "senior management", "migration"], "requirements": {"degrees": [], "majors": [], "languages": ["english", "chinese"], "language_level": ["excellent"], "hard_skills": ["problem solving skills"], "soft_skills": ["communication skills", "problem solving skills", "team player", "organisational skills"], "languages_combined": [{"language": "english", "language_level": ["excellent"]}, {"language": "chinese", "language_level": ["excellent"]}]}, "experience_required": {"duration": ["4-5 years"], "field": ["related", "banking experience"]}}, {"job_id": "100003009035462", "location_code": "hk", "company": "Delta Asia Securities Limited", "job_title": "Settlement Manager (Ref.:STM_220110_JD983)", "description": "Responsibilities\n\n\nPerform daily settlement functions for Hong Kong & Overseas equity markets, Hong Kong & Overseas Futures markets, Stock Options, Bonds & Funds\nSupport on settlement functions including trade matching, customers fund deposit and withdrawal, SI, corporate actions, stock pledge processing, IPO and placement and other CCASS operations etc.\nHandle client account maintenance and ensure information is accurately and timely updated\nParticipate in system implementation projects in particular UAT and system migration\nEnsure operation procedures being in compliance with applicable regulatory requirements\n\nRequirements\n\n\nDiploma / Degree holder\n8+ years relevant experience in brokerage firm\nWith experience in system enhancement project is a plus\nProficient in MS Office and Chinese Word Processing\nResponsible, self-motivated, independent & able to work under pressure\nGood command of written and spoken English and Chinese\nImmediate available is highly preferred\n\nThe Candidate\u00a0with less experience\u00a0will be considered as Assistant Settlement Manager.\n\n\n\nApplication\n\nWe offer\u00a0competitive\u00a0remuneration and fringe benefits\u00a0including but not limited to the followings:\n\n15-20 days' Annual Leave\nCaring Leave (including birthday leave, graduation leave, wedding leave, volunteer leave, children \u00a0graduation leave, children wedding leave, etc.)\n\nInterested parties, please click \"APPLY NOW\". For more information or enquiry, please contact us at +852 9882 7957.\n\nAll information provided will be treated in strict confidence and only be used for recruitment purpose.\n\nWebsite: www.delta-asia.com", "employment_types": ["Full Time", "Permanent"], "selling_points": ["5-day work with competitive remuneration package", "15-20 days AL, birthday leave, wedding leave, etc.", "Immediately available is highly preferred"], "locations": ["Wan Chai"], "categories": ["Banking / Finance", "Financial Services", "Equities / Capital Markets", "Order Processing & Operation / Settlement"], "post_time": "2022-01-10T07:17:02Z", "salary": {"currency": null, "max": null, "min": null, "period": "monthly", "term": null}, "salary_visible": false, "title_keywords": ["settlement manager"], "responsibilities": ["uat", "operations", "regulatory requirements", "compliance", "procedures", "implementation", "migration", "account maintenance"], "requirements": {"degrees": ["diploma", "degree holder"], "majors": [], "languages": ["english", "chinese"], "language_level": ["good command", "proficient"], "hard_skills": ["plus", "chinese word processing", "ms office"], "soft_skills": ["self-motivated", "independent", "responsible", "work under pressure"], "languages_combined": [{"language": "english", "language_level": ["good command"]}, {"language": "chinese", "language_level": ["good command", "proficient"]}]}, "experience_required": {"duration": ["8+ years"], "field": ["brokerage", "relevant experience"]}}, {"job_id": "100003009049444", "location_code": "hk", "company": "OCBC Wing Hang Bank Limited", "job_title": "Senior Loan Processing Officer", "description": "Responsibilities\n\u200bPrepare all loan documents include offer letters, guarantee and charge forms etc. for corporate clients\nCheck the completeness and correctness of documents before loan disbursement and/or credit limits set-up\nLiaise with valuation / properties agents and follow up with the valuation reports\nHandle credit limit loading, loans disbursement, roll-over and settlement process\nHandle and supervise loans repayment & maintenance functions\nAssist in other ad hoc tasks as assigned\nRequirements\n\u200bDiploma or above\nMinimum 3 years\u2019 relevant experience in Banking industry\nFamiliar with credit administration or loans processing duties\nGood interpersonal and communication skills\nOutgoing, independent and self-motivated\n\nAttractive remuneration package will be offered to the right candidate. Please apply with full resume stating present & expected salary and contact phone number\u00a0to\u00a0The Human Resources Manager, 10/F, 161 Queen\u2019s Road Central, Hong Kong.\u00a0Please quote the reference.\n\nPersonal data collected will be used for recruitment purpose only. For more information, please visit our website:\u00a0http://www.ocbcwhhk.com.", "employment_types": ["Full Time", "Permanent"], "selling_points": ["Loan Processing", "Mortgage", "Back Office"], "locations": ["Shau Kei Wan"], "categories": ["Banking / Finance", "Loan", "Retail Banking", "Order Processing & Operation / Settlement"], "post_time": "2022-01-14T08:39:40Z", "salary": {"currency": null, "max": null, "min": null, "period": "monthly", "term": null}, "salary_visible": false, "title_keywords": ["officer"], "responsibilities": ["valuation", "maintenance", "settlement process", "letters", "ad hoc tasks", "reports", "liaise with"], "requirements": {"degrees": [], "majors": [], "languages": [], "language_level": [], "hard_skills": ["processing"], "soft_skills": ["outgoing", "communication skills", "self-motivated", "independent", "interpersonal"], "languages_combined": []}, "experience_required": {"duration": ["minimum 3 years"], "field": ["banking industry", "relevant experience"]}}, {"job_id": "100003009042459", "location_code": "hk", "company": "Bank of Communications Trustee Limited", "job_title": "Associate (Contract)", "description": "Responsibilities:\nParticipate in daily operations such as cash / trade settlement for various funds and custody accounts\nProvide support in fund accounting activities including but not limited to portfolio valuation, net asset value calculation\nPerform cash and position reconciliation between internal and external records\nCarry out various clerical support among the department\nMaintain data integrity and update in system\nAssist the team to perform other administrative work\nRequirements:\nFresh graduate in Finance, Accounting, Business Administration or related disciplines\nWorking experience in banking or financial services industry is preferable but not a must\nStrong desire to develop career in banking and financial industry\nProficient in both spoken and written English and Chinese, Putonghua a plus\nProficient in MS office application\n***Initial contract employment with possibility to change to permanent position**", "employment_types": ["Full Time", "Contract"], "selling_points": ["Maintain data integrity and update in system", "Fresh graduate in Finance, Accounting", "Working experience in banking or financial service"], "locations": ["Not Specified"], "categories": ["Accounting", "Accounting Clerk / Supervisor", "Banking / Finance", "Financial Services", "Order Processing & Operation / Settlement"], "post_time": "2022-01-12T07:37:32Z", "salary": {"currency": null, "max": null, "min": null, "period": "monthly", "term": null}, "salary_visible": false, "title_keywords": ["associate"], "responsibilities": ["valuation", "provide support", "administrative work", "clerical support", "daily operations", "maintain data"], "requirements": {"degrees": ["fresh graduate"], "majors": ["related disciplines", "finance", "accounting", "business administration"], "languages": ["putonghua", "english", "chinese"], "language_level": ["proficient"], "hard_skills": ["plus", "ms office"], "soft_skills": [], "languages_combined": [{"language": "putonghua", "language_level": ["proficient"]}, {"language": "english", "language_level": ["proficient"]}, {"language": "chinese", "language_level": ["proficient"]}]}, "experience_required": {"duration": [], "field": ["financial services industry", "banking"]}}, {"job_id": "100003009043313", "location_code": "hk", "company": "KEK Consultancy Company Limited", "job_title": "Senior Officer \u2013 Operations  (23K, Overseas Bank) \u2013 Ref. 1112", "description": "One of our clients (an overseas bank) is now looking for a high calibre candidate to fill the following positions:\n\n2 years or above related experience;\nExperience/ knowledge of KYC, AML regulations, Swift Alliance, RTGS payments, Nostro Reconciliation;\nHandle inward/ outward cheque clearing and remittance transactions;\nMonitor account openings and servicing transactions;\nGood command of English and Chinese (Cantonese & Mandarin).\n\nRemarks:\n\nMonthly salary: Basic up to HK$23K + discretionary bonus;\n5-day work;\nWorking location: Tsim Sha Tsui / Jordan;\nGood fringe benefits: Banking holidays, dental, medical (including spouse), 22-day annual leave, etc.\n\n\nIf the above position is not suitable for you, please also feel free to send your CV to us for our job matching.\n\nInterested parties please click \"APPLY NOW\"\u00a0or send to\u00a0OUR EMAIL\u00a0and attach your updated resume with expected salary in \"MS WORD\" format.\n\nPlease quote the\u00a0Job Ref. No.\u00a0and\u00a0Applied Post\u00a0on the subject of your application.\n\nInterest to know our candidates' and clients' comments about our service? Please click\u00a0HERE.\n\nCompany website:\u00a0www.kek.com.hk\n\nThe information provided will only be used for recruitment related purposes.", "employment_types": ["Full Time", "Permanent"], "selling_points": ["5-day work", "Medical (including spouse), 22 days AL", "KYC, RTGS payment, Nostro Reconciliation"], "locations": ["Tsim Sha Tsui"], "categories": ["Banking / Finance", "Corporate Banking", "Retail Banking", "Order Processing & Operation / Settlement"], "post_time": "2022-01-12T10:40:31Z", "salary": {"currency": null, "max": null, "min": null, "period": "monthly", "term": null}, "salary_visible": false, "title_keywords": ["senior officer", "operations"], "responsibilities": ["regulations", "aml", "monitor", "transactions", "payments", "kyc"], "requirements": {"degrees": [], "majors": [], "languages": ["cantonese", "english", "chinese", "mandarin"], "language_level": ["good command"], "hard_skills": ["swift", "basic", "aml", "kyc"], "soft_skills": [], "languages_combined": [{"language": "cantonese", "language_level": ["good command"]}, {"language": "english", "language_level": ["good command"]}, {"language": "chinese", "language_level": ["good command"]}, {"language": "mandarin", "language_level": ["good command"]}]}, "experience_required": {"duration": ["2 years"], "field": ["related"]}}, {"job_id": "100003009050795", "location_code": "hk", "company": "City Super Ltd", "job_title": "Assistant, General Accounting", "description": "Job Duties:\u00a0\u00a0\n\nHandle daily accounting duties (AR, AP or G/L) of the Group;\nAssist in month-end and year-end closing;\nAssist in annual statutory audit and tax filing;\nPrepare monthly management and statutory reports or schedules;\nPerform other ad hoc duties when required\nRequirements:\n\nDegree/Diploma holder in Finance, Accounting and other related disciplines\nGood command of both spoken and written English and Chinese.\nHigh proficiency in MS Office.\u00a0 Knowledge with SAP is a plus.\nStrong interpersonal and communication skills.\nFresh graduate will also be considered\nImmediate available is highly preferred\n\nWe offer competitive remuneration package and good prospects to the right candidates. Interested parties please apply with your full resume with expected salary.*Data collected will be kept confidential and used for recruitment purposes only.", "employment_types": ["Full Time"], "selling_points": ["Handle daily accounting duties (AR, AP or G/L)", "Assist in month-end and year-end closing", "Assist in annual statutory audit and tax filing"], "locations": ["Tsim Sha Tsui"], "categories": ["Banking / Finance", "Order Processing & Operation / Settlement"], "post_time": "2022-01-14T11:24:05Z", "salary": {"currency": null, "max": null, "min": null, "period": "monthly", "term": null}, "salary_visible": false, "title_keywords": ["accounting", "assistant"], "responsibilities": ["ap", "ad hoc duties", "month-end and year-end closing", "management", "ar", "schedules", "tax filing", "reports", "daily accounting", "annual statutory audit"], "requirements": {"degrees": ["diploma holder", "degree", "fresh graduate"], "majors": ["related disciplines", "finance", "accounting"], "languages": ["english", "chinese"], "language_level": ["good command"], "hard_skills": ["plus", "sap", "ms office"], "soft_skills": ["communication skills", "interpersonal"], "languages_combined": [{"language": "english", "language_level": ["good command"]}, {"language": "chinese", "language_level": ["good command"]}]}, "experience_required": {"duration": [], "field": []}}, {"job_id": "100003009040791", "location_code": "hk", "company": "Page Personnel", "job_title": "Investment Operations Analyst - Leading Bank", "description": "Our client is looking for an Investment Operations Analyst to join their growing business. The ideal candidate will have 1+ years of experience in operations/ accounting management within banking.\n\nClient Details\n\nOur client is one of Hong Kong's largest banks with more than 80 years of history. Its main services include private banking, retail banking, investment services and wealth management. The bank provides a massive network of more than 200 service outlets in Hong Kong and has established its network in most major cities in mainland China.\n\nDescription\n\nHandle investment operations processes include trade management and support\nMonitor life cycle management and settlement, and oversight treasury positions\nLiaise with custodian banks, auditors, and internal/external counterparties to monitor the quality of services\nEnsure the arrangements with relevant service providers are being appropriately applied\nAssist in new product enablement coordinate with middle office service providers and custodian banks\n\nProfile\n\nUniversity degree in Business Administration or other relevant qualifications\nPrevious experience of operations/ accounting management is highly preferred\nGood PC skills including MS Word and Excel\nVBA and Bloomberg knowledge is an advantage\nGood command of written and spoken English and Cantonese\n\nJob Offer\n\nWorking days and time: Mon - Fri, 0900 - 1800\nWork location: MongKok\nHigh exposure in investment operations\nExcellent training and potential growth\nOpportunities for career progression\n\nTo apply online please click the 'Apply' button below. For a confidential discussion about this role please contact Kira Tang on +852 2258 3538.", "employment_types": ["Full Time", "Temporary"], "selling_points": ["High exposure in investment operations", "Excellent training and potential growth", "Opportunities for career progression"], "locations": ["Not Specified"], "categories": ["Banking / Finance", "Investment", "Treasury", "Order Processing & Operation / Settlement"], "post_time": "2022-01-12T03:04:37Z", "salary": {"currency": null, "max": null, "min": null, "period": "monthly", "term": null}, "salary_visible": false, "title_keywords": ["operations analyst"], "responsibilities": ["management", "operations", "monitor", "quality", "coordinate with", "banking", "liaise with", "administration"], "requirements": {"degrees": ["university degree"], "majors": ["business administration"], "languages": ["cantonese", "english"], "language_level": ["good command"], "hard_skills": ["excel", "vba", "bloomberg", "pc skills", "ms word"], "soft_skills": ["ideal"], "languages_combined": [{"language": "cantonese", "language_level": ["good command"]}, {"language": "english", "language_level": ["good command"]}]}, "experience_required": {"duration": ["1+ years"], "field": ["management", "accounting", "banking"]}}, {"job_id": "100003009039450", "location_code": "hk", "company": "Guotai Junan International Holdings Limited", "job_title": "Assistant Operations Manager", "description": "Responsibilities:\n\nAssist in settlements of Fixed Income, OTC Derivative and Structured Products\nPerform daily trade booking and position reconciliation\nPrepare funding report to Treasury for settlement\nHandle instruction to Euroclear and cusotidan banks and status monitoring\nOutstanding settlements follow up\nHandle corporate action\nDeal with queries from clients and/or their Account Managers\nHandle ad-hoc tasks assigned by supervisor\n\nRequirements:\n\nDegree holder in Business, Economics, Finance or any related disciplines is required.\nRelevant experience in financial services industry is preferred.\nProficiency in MS Office, VBA (Macro) knowledge is a plus.\nHands on experience in Euroclear system operations\nIndependent, enthusiastic and able to work under pressure.\nFluent in Cantonese, English and Mandarin.\n\nWe offer an attractive remuneration package to the right candidate. Interested parties please forward your full resume with availability, expected salary and press \"Apply now\"\u00a0or simply send it to 27/F., Low Block, Grand Millennium Plaza, 181 Queen\u2019s Road, Central, Hong Kong.\n\n(Data collected will be kept strictly confidential and used for recruitment purpose only.)", "employment_types": ["Full Time", "Part Time", "Permanent"], "selling_points": ["Prepare funding report", "Outstanding settlements follow up", "Handle corporate action"], "locations": ["Central & Western Area"], "categories": ["Banking / Finance", "Financial Services", "Order Processing & Operation / Settlement", "Wealth Management"], "post_time": "2022-01-11T09:48:39Z", "salary": {"currency": null, "max": null, "min": null, "period": "monthly", "term": null}, "salary_visible": false, "title_keywords": ["assistant operations manager"], "responsibilities": ["monitoring", "daily trade booking", "ad-hoc tasks", "report"], "requirements": {"degrees": ["degree holder"], "majors": ["finance", "economics", "related disciplines", "business"], "languages": ["cantonese", "english", "mandarin"], "language_level": ["fluent"], "hard_skills": ["vba", "macro", "plus", "ms office"], "soft_skills": ["work under pressure", "hands on", "independent", "enthusiastic"], "languages_combined": [{"language": "cantonese", "language_level": ["fluent"]}, {"language": "english", "language_level": ["fluent"]}, {"language": "mandarin", "language_level": ["fluent"]}]}, "experience_required": {"duration": [], "field": ["financial services industry", "relevant experience"]}}, {"job_id": "100003009049595", "location_code": "hk", "company": "Chiyu Banking Corp Ltd", "job_title": "Branch Operation Manager", "description": "Responsibilities:\n\nMonitor branch daily operations\nEnsure efficient branch operations and all activities are in compliance with the regulatory requirments\nAssist Branch Manager in implementing the business plan in order to achieve the assigned targets\u00a0\nRequirements:\nDegree or above in Business or related disciplines\nMinimum 5 years of supervisory experience in branch operations\nQualifications of HKSI, IIQE & MPF\nGood interpersonal and communication skills\nFlexible and detail-minded\nStrong in problem solving, coordinating and organizing skills\nWe offer competitive packages and promising career opportunities to the right candidates. Please send your full resume with current salary, expected salary and the date of availability to The Human Resources Department, Chiyu Banking Corporation Ltd, 12/F, Chiyu Bank Building, No. 78 Des Voeux Road Central, Hong Kong or fax to 2986-3233 or by clicking Apply Now.\n\n\nInformation provided will be treated in strict confidence and only be used for recruitment purposes. All personal data of unsuccessful applicants will be destroyed after the recruitment exercise. \u00a0A copy of Personal Information Collection Statement is available upon request.", "employment_types": ["Full Time", "Permanent"], "selling_points": [], "locations": ["Not Specified"], "categories": ["Banking / Finance", "Retail Banking", "Others", "Order Processing & Operation / Settlement"], "post_time": "2022-01-14T08:55:03Z", "salary": {"currency": null, "max": null, "min": null, "period": "monthly", "term": null}, "salary_visible": false, "title_keywords": ["operation manager"], "responsibilities": ["operations", "compliance", "monitor", "daily operations", "business plan"], "requirements": {"degrees": ["degree or above"], "majors": ["related disciplines", "business"], "languages": [], "language_level": [], "hard_skills": ["problem solving", "iiqe", "hksi"], "soft_skills": ["flexible", "communication skills", "detail-minded", "problem solving", "interpersonal"], "languages_combined": []}, "experience_required": {"duration": ["minimum 5 years"], "field": ["supervisory experience"]}}, {"job_id": "100003009039893", "location_code": "hk", "company": "DBS Bank Ltd", "job_title": "Associate/Analyst, Custody Settlement", "description": "Business Function\n\nTechnology and Operations (T&O) enables aand empowers the bank with an efficient, nimble and resilient infrastructure through a strategic focus on productivity, quality & control, technology, people capability and innovation. In T&O, we manage the majority of the Bank's operational processes and inspire to delight our business partners through our multiple banking delivery channels.\n\nResponsibilties\u00a0\n\nMonitor and execute stock settlement instructions efficiently and accurately\nMonitor and process physical scrip deposit and withdrawal to provide efficient services to our customers and maintain the record in a timely and accurate manner.\nMonitor day-to-day settlement on equities, fixed income and other types of instruments.\nPerform check and control on processes including static data maintenance, customer position update and pricing information update, and handle reconciliation of General Ledger accounts, preparation of transaction and miscellaneous reports, etc\nFollow up with brokers and custodians to clean up any unmatched/ unsettled instructions\nSupport the process of monthly fee billings and collections.\nProvide second level client services.\u00a0\u00a0Handle customer inquiries and resolve / escalate problems in an efficient manner\nParticipate in project initiatives and UAT for system enhancements\n\nRequirements\n\n1\u00a0years of relevant working experience in securities settlement in the banking environment\nSolid knowledge in investment product and end to end settlement process.\nBe conversant with CCASS, SFC rules, SFO and HKICL\nBe familiar with the market trend and new product / system development of Hong Kong securities market\nAccuracy and thoroughness in work\nGood problem-solving skills and ability to handle difficult customers\nGood team player, supportive and flexible to take up team tasks\nGood communication skills and good command in English and Chinese (both spoken & written)\n\nApply Now\n\nWe offer a competitive salary and benefits package and the professional advantages of a dynamic environment that supports your development and recognises your achievements.\n\nWe regret only shortlisted candidates will be notified.", "employment_types": ["Full Time"], "selling_points": ["With securities settlement experience preferable", "Currently holding a checker role is an advantage", "See job description."], "locations": ["Kwun Tong"], "categories": ["Banking / Finance", "Corporate Banking", "Order Processing & Operation / Settlement"], "post_time": "2022-01-11T14:25:31Z", "salary": {"currency": null, "max": null, "min": null, "period": "monthly", "term": null}, "salary_visible": false, "title_keywords": ["analyst", "associate"], "responsibilities": ["control", "uat", "maintenance", "data", "customer inquiries", "general ledger", "billings", "monitor", "maintain", "reports"], "requirements": {"degrees": [], "majors": [], "languages": ["english", "chinese"], "language_level": ["good command", "good"], "hard_skills": ["sfc rules", "dynamic", "ccass", "problem-solving skills", "sfo"], "soft_skills": ["flexible", "communication skills", "supportive", "good team player", "dynamic environment", "problem-solving skills"], "languages_combined": [{"language": "english", "language_level": ["good command", "good"]}, {"language": "chinese", "language_level": ["good command", "good"]}]}, "experience_required": {"duration": ["1 years"], "field": ["securities", "relevant working experience", "banking"]}}, {"job_id": "100003009050453", "location_code": "hk", "company": "Industrial Bank of Korea", "job_title": "Remittance Clerk", "description": "We are one of the well-known Korean banks seeking for high calibre candidate to fill in the following position:\n\nQualifications:\n\n\nHKID holder\n\n\nAdvantages:\n\nCertification(s) related to the task\n\nRelated working experience\n\nFluent English, Chinese and/or Korean\u00a0speaker\n\n\nDocuments Required:\n\n[English] Resume (Including expected salary and possible date to work)\n\n[English] Self-introduction\n\nContact Us:\n\u00a0You may\u00a0contact us at 2293-5022\u00a0on or before 28 Jan 2022\u00a0for more company details. Personal data collected will be used for recruitment purpose only.", "employment_types": ["Full Time", "Permanent"], "selling_points": [], "locations": ["Admiralty"], "categories": ["Banking / Finance", "Corporate Banking", "Others", "Order Processing & Operation / Settlement"], "post_time": "2022-01-14T10:27:17Z", "salary": {"currency": null, "max": null, "min": null, "period": "monthly", "term": null}, "salary_visible": false, "title_keywords": ["clerk"], "responsibilities": ["personal data", "recruitment", "contact"], "requirements": {"degrees": [], "majors": [], "languages": ["english", "chinese", "korean"], "language_level": ["fluent"], "hard_skills": [], "soft_skills": [], "languages_combined": [{"language": "english", "language_level": ["fluent"]}, {"language": "chinese", "language_level": ["fluent"]}, {"language": "korean", "language_level": []}]}, "experience_required": {"duration": [], "field": ["related"]}}, {"job_id": "100003009042466", "location_code": "hk", "company": "Bank of Communications Trustee Limited", "job_title": "Contract Officer, Operations Department (Ref. OPS-O)", "description": "Responsibilities:\nProcess member enrolments, terminations, contributions in accordance with all regulatory requirements as well as company procedures and policies\nEnsure to follow up outstanding issues and handle customer\u2019s enquires on a timely and professional manner\nPerform other job related duties or assist in ad-hoc projects as required\nAssist in carrying out various functional testing for system enhancement purposes\nRequirements:\nDegree holder with minimum 4 years\u00a0of pension fund administration is highly preferred\nKnowledge in MPF and ORSO regulation is a must\nDetail-oriented and good team player\nGood interpersonal skills and good command of both written and spoken English and Chinese\nPC literate in Word, Excel, Powerpoint and Chinese word processing\nImmediately available is highly preferred\nPlease click \"Apply Now\" to submit your application.\nPersonal data collected will be used for recruitment purpose only.", "employment_types": ["Full Time", "Contract"], "selling_points": ["Process member enrolments, terminations", "Assist in carrying out various functional testing", "Degree holder w/ minimum 4 years of pension fund"], "locations": ["Not Specified"], "categories": ["Banking / Finance", "Private Banking", "Others", "Order Processing & Operation / Settlement"], "post_time": "2022-01-12T07:37:34Z", "salary": {"currency": null, "max": null, "min": null, "period": "monthly", "term": null}, "salary_visible": false, "title_keywords": ["operations", "contract officer"], "responsibilities": ["regulatory requirements", "policies", "procedures", "professional manner", "testing", "ad-hoc projects"], "requirements": {"degrees": ["degree holder"], "majors": [], "languages": ["english", "chinese"], "language_level": ["good command", "good"], "hard_skills": ["excel", "chinese word processing", "word", "powerpoint", "pc literate"], "soft_skills": ["good team player", "interpersonal skills", "detail-oriented"], "languages_combined": [{"language": "english", "language_level": ["good command", "good"]}, {"language": "chinese", "language_level": ["good command", "good"]}]}, "experience_required": {"duration": [], "field": []}}, {"job_id": "100003009035684", "location_code": "hk", "company": "Hang Seng Bank Ltd", "job_title": "Investment Funds Operations Manager", "description": "Operations \u2013 Wealth Services\n\n\nHang Seng's Operations is a team of experienced banking operations professionals who strive for delivering time-to-market, efficient and world-class processing services to customers, corporations, financial institutions and internal units.\n\nWe are currently seeking a high caliber professional to join our department as\u00a0Investment Funds Operations Manager.\n\u00a0\n\nPrincipal responsibilities\n\nPlay the role of subject matter expert in supporting unit trust operations such as daily unit trust order, subscription and redemption settlement, dividend distribution, unit trust transfer and fee handling\nParticipate and support business, bank-wide and market initiatives/projects\nIdentify opportunities for process improvement and drive re-engineering initiatives to increase operational efficiency and effectiveness as well as client experience\nSet service standards, monitor actual performance and review service benchmarks of both onshore and offshore to ensure cost-effective service for business units and customers\nUnderstand the changing group/regulatory requirements and conduct assessment/ monitoring on operations to ensure in compliance with the standard\nManage the performance and development of subordinates\n\nRequirements\n\n\nUniversity degree in a related discipline or other relevant qualifications\nFulfillment of the competency requirements for carrying out relevant regulated activities as defined under the Securities and Futures Ordinance\nMinimum of 5 years\u2019 relevant experience in banking industry, with sound knowledge of investment products / systems and relevant regulations\nBe proactive, with good analytical and problem solving skills\nStrong self-motivation, attentiveness to details, with good communication, leadership and interpersonal skills\nSound knowledge of application software such as MS Excel\nProficiency in both English and Chinese, with fluency in Putonghua an advantage\nGreat sense of ownership and servicing mindset to ensure efficient and effective customer service processes\n\n\n\nIf you would like to explore other opportunities at Hang Seng Hong Kong, please visit\u00a0www.hangseng.com/careers/\u00a0for details.\n\nThe health and safety of our employees and candidates is very important to us. Due to the current situation related to the Novel Coronavirus (2019-nCoV), we\u2019re leveraging our digital capabilities to ensure we can continue to recruit top talent at the HSBC Group. \u00a0As your application progresses, you may be asked to use one of our digital tools to help you through your recruitment journey. \u00a0If so, one of our \u00a0Resourcing colleagues will explain how our video-interviewing technology will be used throughout the recruitment process and will be on hand to answer any questions you might have\n\nAll information provided by applicants will be used only for recruitment purposes and will be used strictly in accordance with the Bank's personal data policies, a copy of which may be obtained by the applicant upon request. Unless otherwise instructed in writing by the applicant concerned, applicants may be considered for other suitable positions within the Bank and its related companies. The personal data of unsuccessful job applicants may be retained for a maximum of two years from the date when the job application is rejected and such data may be retained for a longer period if there is a subsisting reason that obliges the Bank to do so, after which the personal data will be destroyed.", "employment_types": ["Full Time", "Permanent"], "selling_points": [], "locations": ["Not Specified"], "categories": ["Banking / Finance", "Fund Management", "Others", "Order Processing & Operation / Settlement"], "post_time": "2022-01-10T08:10:08Z", "salary": {"currency": null, "max": null, "min": null, "period": "monthly", "term": null}, "salary_visible": false, "title_keywords": ["operations manager"], "responsibilities": ["cost", "operations", "regulatory requirements", "review", "monitor", "subject matter expert", "monitoring", "compliance", "service standards", "re-engineering"], "requirements": {"degrees": ["university degree"], "majors": [], "languages": ["putonghua", "english", "chinese"], "language_level": ["fluency", "advantage", "proficiency"], "hard_skills": ["investment products", "securities and futures ordinance", "reason", "ms excel", "problem solving skills"], "soft_skills": ["efficient", "communication", "analytical and problem solving skills", "self-motivation", "interpersonal skills", "customer service", "novel", "proactive", "leadership"], "languages_combined": [{"language": "putonghua", "language_level": ["fluency", "advantage"]}, {"language": "english", "language_level": ["proficiency", "fluency", "advantage"]}, {"language": "chinese", "language_level": ["proficiency", "fluency", "advantage"]}]}, "experience_required": {"duration": ["minimum of 5 years"], "field": ["banking industry", "relevant experience", "investment"]}}, {"job_id": "100003009046503", "location_code": "hk", "company": "Principal Trust Company (Asia) Limited", "job_title": "Manager, Pension Operations", "description": "As the Manager, Pension Operations, you\u2019ll lead a small team and supervise all day-to-day administration duties of group products and services, and customer services related activities for both internal and external customers.\n\nYou\u2019ll ensure accurate and proper pension administration on enrolment, contribution, termination, switching, record maintenance as well as others related administration; monitor the daily operation to comply with internal, external, and regulatory requirement/regulation; and ensure staff to provide good quality and timely production to meet the company service pledge.\n\nOther key responsibilities:\n\nStakeholder management\nHandle/answer and cooperate internal and external enquires by responding enquiry/request from different sources, manage the expectations from internal staff, customer, sales agent, brokers, auditors as well as regulator or governmental bodies\nStaff training and development\nPerform staff development activities including to encourage our staff to have a continuous improvement mindset, conduct training, provide direction of work and conduct regular performance review\nStreamline production and workflow review\nAssist to review, develop and update local administrative forms, letters and procedural manuals\nAct as a process owner to review responsible processes and determine how to streamline the business flow in order to enhance operational efficiency and drive down the company expense\nProject management\nAssist in the process of new product launch, regulatory changes, support company initiatives and perform the local government filing for pension product\nPerform other job-related duties or special projects as requested\nParticipate in departmental projects when required\nEssential Skills, Experience and Competencies\n\n\nTo succeed in this role, you\u2019ll need extensive and in-depth knowledge about pension business, products and related services; strong analytical, organizational and project management skills. Good people management and coaching skills will be essential to guide the team.\n\nOther key skills required for the role:\n\nUniversity graduate or equivalent\nAt least 15 years of relevant experience in MPF and/or ORSO schemes administration with 5 years at managerial level\nHave a continuous improvement mindset\nExcellent interpersonal skills, attentive to details, high degree of accuracy and ability to work in an environment characterized by high level of activities\nReliable and able to work independent\nStrong problem-solving skills\nFluent in spoken and written English and Chinese (both Cantonese and Mandarin)\nAble to use word processing and spreadsheet programs\nKnowledge on excel macro or visual base application (VBA excel) will be an advantage\n\nWhat We Offer\n\nPrincipal offers employees a competitive package and a comprehensive range of benefits to help meeting your needs now and in the future, including:\n\n5-Day Work Week\nYear-end Payment\nDiscretionary Bonus\nBirthday Leave\nMedical Plan\nLife Insurance\nPension Scheme\nEmployee Stock Purchase Plan\nAnd Growth Opportunities!", "employment_types": ["Full Time", "Permanent"], "selling_points": ["Team management", "Experience in MPF/ORSO is essential", "Competitive offer package and attractive benefits"], "locations": ["Kwun Tong"], "categories": ["Banking / Finance", "Order Processing & Operation / Settlement"], "post_time": "2022-01-13T12:19:23Z", "salary": {"currency": null, "max": null, "min": null, "period": null, "term": null}, "salary_visible": false, "title_keywords": ["operations", "manager"], "responsibilities": ["management", "provide direction", "review", "letters", "develop", "project management"], "requirements": {"degrees": ["university graduate", "degree"], "majors": [], "languages": ["cantonese", "english", "chinese", "mandarin"], "language_level": ["fluent"], "hard_skills": ["excel", "macro", "vba", "word processing", "problem-solving skills", "spreadsheet"], "soft_skills": ["independent", "attentive to details", "interpersonal skills", "problem-solving skills", "reliable"], "languages_combined": [{"language": "cantonese", "language_level": ["fluent"]}, {"language": "english", "language_level": ["fluent"]}, {"language": "chinese", "language_level": ["fluent"]}, {"language": "mandarin", "language_level": ["fluent"]}]}, "experience_required": {"duration": ["5 years", "at least 15 years"], "field": ["managerial", "relevant experience", "mpf", "administration"]}}, {"job_id": "100003009040161", "location_code": "hk", "company": "Livi Bank Limited", "job_title": "Graduate Trainee, Operations", "description": "If this is you, join us as our graduate trainee in Operations and start making an impact:\n\nResponsibilities\n\nCarry out name screening, periodic review and clear alert generated by in-house system\nPerform CDD, EDD and eKYC tasks including world check, FATCA, etc\nParticipate the project for eKYC solution for various platforms\nAssist in preparing report for management and HKMA\nSupport promotional operations in area of promotion campaign performance monitoring, promotional rewards fulfilment, budget tracking etc\nBe a key driver of customer experience\nEnsure all operational processes are complied with internal policies and regulatory requirements\nSupport ad hoc duties assigned by Department Head\nRequirement\n\nTertiary Education with an Associate Degree/Diploma or above\nProactive and willing to learn\nAdaptive and able to work in a fast-paced environment\nProficient in computer skills e.g. Microsoft PowerPoint, Microsoft Excel etc\nFluent in Cantonese, Mandarin, and English", "employment_types": ["Full Time", "Contract"], "selling_points": ["Exciting graduate opportunity", "Join Virtual Banking industry", "Grow your career"], "locations": ["Quarry Bay"], "categories": ["Banking / Finance", "Retail Banking", "Order Processing & Operation / Settlement", "Others", "Student / Fresh Graduate / No Experience"], "post_time": "2022-01-12T01:40:31Z", "salary": {"currency": null, "max": null, "min": null, "period": "monthly", "term": null}, "salary_visible": false, "title_keywords": ["operations", "graduate trainee"], "responsibilities": ["ad hoc duties", "management", "tracking", "cdd", "operations", "review", "monitoring", "budget", "policies", "regulatory requirements", "report"], "requirements": {"degrees": ["associate degree", "diploma or above"], "majors": [], "languages": ["cantonese", "english", "mandarin"], "language_level": ["fluent"], "hard_skills": ["microsoft excel", "computer skills", "microsoft powerpoint"], "soft_skills": ["fast-paced environment", "proactive", "willing to learn"], "languages_combined": [{"language": "cantonese", "language_level": ["fluent"]}, {"language": "english", "language_level": ["fluent"]}, {"language": "mandarin", "language_level": ["fluent"]}]}, "experience_required": {"duration": [], "field": []}}, {"job_id": "100003009049570", "location_code": "hk", "company": "Conners Consulting Limited", "job_title": "Senior Manager \u2013 Loan Department (Banking) Many Post", "description": "Our client, a well-known bank in Hong Kong, is looking for a high caliber to join the group.\n\nSenior Manager \u2013 Loan Administration\n\nResponsibilities\n\n\nLead team to handle overall loan administration functions to both retail and wholesale banking customers\nEnhance the working guidelines to fulfil the bank\u2019s compliance requirement\n\nRequirements\n\nUniversity degree or above\nAt least 10 years\u2019 experience in loan operation\n\nSenior Manager \u2013 Loan Documentation 1\n\nResponsibilities\n\nEnhance working guideline and policy to fulfil the bank\u2019s compliance requirement.\nReview and provide comments on facility and security documentation prepared by legal counsel\u00a0 \u00a0\u00a0\n\nRequirements\n\nUniversity degree or above\nAt least 10 years\u2019 experience in loan documentation\u00a0\n\nSenior Manager \u2013 Loan Documentation 2\n\nResponsibilities\n\nLead team to handle daily MIS / regulatory reporting and monitoring tasks\nHandle contingency credit control and monitoring / regular reporting\n\nRequirements\n\nUniversity degree or above\nAt least 10 years\u2019 experience on credit process / monitoring of banking industry\u00a0\n\nTo apply, please send your detailed resume or contact Ms Tsui at 3955 1358 for a confidential discussion.\u00a0\nOnly shortlisted candidates will be notified.\u00a0\nApplicants who are not contacted within two weeks may consider their applications unsuccessful.\u00a0\nAll data collected will be used for recruitment purpose only & will be used strictly confidential.\u00a0\n\nConners Consulting Limited\n2005 Kai Tak Commercial Building 317 Des Voeux Road Central Hong Kong\u00a0\nTel: (852) 3996 8090\u00a0\u00a0\u00a0\u00a0\u00a0\u00a0 Website: www.connersconsulting.com", "employment_types": ["Full Time", "Permanent"], "selling_points": ["Senior Manager", "Loan Department", "Attractive Annual Packager"], "locations": ["Central & Western Area"], "categories": ["Banking / Finance", "Loan", "Others", "Order Processing & Operation / Settlement"], "post_time": "2022-01-15T03:50:32Z", "salary": {"currency": null, "max": null, "min": null, "period": "monthly", "term": null}, "salary_visible": false, "title_keywords": ["senior manager"], "responsibilities": ["guidelines", "compliance", "banking", "administration"], "requirements": {"degrees": ["degree or above"], "majors": [], "languages": [], "language_level": [], "hard_skills": ["documentation"], "soft_skills": ["detailed"], "languages_combined": []}, "experience_required": {"duration": ["at least 10 years"], "field": ["banking industry", "operation"]}}, {"job_id": "100003009049922", "location_code": "hk", "company": "Nanyang Commercial Bank", "job_title": "Clerk (Ref: HC8010-00-JDB)", "description": "Provide the clerical and administration supports to various business units.\n\nRequirements:\u00a0\n\nHKCEE / HKDSE with at least 5 subjects at Grade E / Level 2 or above including Chinese, English and Mathematics;\nRelevant working experience and knowledge of accounting are preferable;\nAttentive to details with good communication and organization skills;\nEager to learn and able to work independently;\nConversant with Chinese word processing and MS Office Suite.\n\nIf you are flexible enough and zeal for a harmonious and supportive working environment where enables you to grow and succeed professionally, please send a full resume indicating your public examination results (HKCEE and HKALE / HKDSE), your present and expected salary and quoting reference number attention to\u00a0Talent Acquisition Division, Nanyang Commercial Bank, 151 Des Voeux Road Central, Hong Kong or apply through email. For details, please visit https://www.ncb.com.hk/and select the page Recruit.\n\nWe are an Equal Opportunities Employer. Data collected would be used for recruitment purposes only. Applicants who do not hear from us within 8 weeks may consider their applications unsuccessful and their data will be destroyed within 12 months of receipt.", "employment_types": ["Full Time", "Permanent"], "selling_points": ["Clerical duties", "Eager to learn and able to work independently", "5 subjects at Grade E / Level 2 in HKCEE / HKDSE"], "locations": ["Not Specified"], "categories": ["Admin & HR", "Clerical / Admin Staff", "Banking / Finance", "Corporate Banking", "Order Processing & Operation / Settlement"], "post_time": "2022-01-15T03:50:41Z", "salary": {"currency": null, "max": null, "min": null, "period": "monthly", "term": null}, "salary_visible": false, "title_keywords": ["clerk"], "responsibilities": ["communication", "recruitment", "data", "administration"], "requirements": {"degrees": ["hkdse"], "majors": ["mathematics"], "languages": ["english", "chinese"], "language_level": [], "hard_skills": ["chinese word processing", "ms office"], "soft_skills": ["flexible", "work independently", "supportive", "attentive to details", "harmonious", "communication", "eager to learn", "organization skills"], "languages_combined": [{"language": "english", "language_level": []}, {"language": "chinese", "language_level": []}]}, "experience_required": {"duration": [], "field": ["accounting", "relevant working experience"]}}, {"job_id": "100003009049336", "location_code": "hk", "company": "Standard Chartered Bank (Hong Kong) Ltd", "job_title": "Product Manager,Investment - (2100033515)", "description": "About Standard Chartered\u00a0\nWe are a leading international bank focused on helping people and companies prosper across Asia, Africa and the Middle East.\u00a0\n\nTo us, good performance is about much more than turning a profit.\u00a0 It's about showing how you embody our valued behaviours - do the right thing, better together and never settle - as well as our brand promise, Here for good.\n\nWe're committed to promoting equality in the workplace and creating an inclusive and flexible culture - one where everyone can realise their full potential and make a positive contribution to our organisation. This in turn helps us to provide better support to our broad client base.\nAbout Mox\nAs one of the biggest banks in market, we are rapidly expanding by growing a new virtual banking business in Hong Kong. We see ourselves as a fast growing start-up company where you will enjoy autonomy and teamwork at the same time, solving new and exciting problems in a nimble and agile way. Join us and be part of history making for future banking experience!\nThe Role Responsibilities\nCoordinate the new product approval process of all investment products and services and ensure compliance to the corresponding product program\nLead the establishment of operating procedures for all investment product and services under management\nLead the formulation of product due diligence, product risk rating, customer risk profiling and suitability assessment framework and related procedures\nLead the conduct of investment product due diligence and ongoing monitoring\nEstablish regulatory reporting procedures and ensure timely submission\nAssist in formulating and provide secretarial support to related wealth/investment Committee\nMonitor local and overseas regulations closely and ensure that operational processes have the appropriate controls in place to satisfy compliance and external regulatory/internal policy requirements.\nDevelop post trade monitoring control framework\nSupport the team in the development and management of investment product platforms\nAct as Subject Matter Experts to support Product Owner in the development of new investment products/services\u200b\u200b\u200b\u200b\u200b\u200b\u200b\nOur Ideal Candidate\nRelevant experience in a similar capacity\nAdept at managing and working with various stakeholders\nStrong understanding of investment products and the regulatory requirements\nHands on experience in investment product diligence work\nOpen to challenge status quo and keen to uplift the banking experience for customers\nStrong presentation and interpersonal skills, with a positive mindset\nGood written and oral communication skills in English and Chinese\nProficiency in PC applications such as Microsoft\nQualify as an SFC Responsible Officer (RO) and a HKMA Executive Officer (EO) to supervise\u00a0 Types 1 and 4 regulated activities within the bank and manage risks associated with the business\nApply now to join the Bank for those with big career ambitions.\n", "employment_types": ["Full Time"], "selling_points": ["Relevant experience in a similar capacity", "Adept at managing and working", "Strong understanding of investment products"], "locations": ["Not Specified"], "categories": ["Banking / Finance", "Others", "Order Processing & Operation / Settlement"], "post_time": "2022-01-14T08:29:45Z", "salary": {"currency": null, "max": null, "min": null, "period": "monthly", "term": null}, "salary_visible": false, "title_keywords": ["product manager"], "responsibilities": ["regulations", "reporting", "management", "control", "product due diligence", "regulatory requirements", "monitoring", "procedures", "monitor", "compliance", "ensure compliance", "coordinate", "develop", "communication", "client base", "secretarial support", "banking", "support the team"], "requirements": {"degrees": [], "majors": [], "languages": ["english", "chinese"], "language_level": ["good"], "hard_skills": ["agile", "hkma", "investment products", "pc applications", "make"], "soft_skills": ["flexible", "communication skills", "oral", "agile", "focused", "positive mindset", "responsible", "keen", "timely", "teamwork", "committed", "hands on", "interpersonal skills", "organisation", "adept", "presentation", "positive", "ideal"], "languages_combined": [{"language": "english", "language_level": ["good"]}, {"language": "chinese", "language_level": ["good"]}]}, "experience_required": {"duration": [], "field": ["relevant experience", "investment", "banking experience"]}}, {"job_id": "100003009034287", "location_code": "hk", "company": "Yuanta Securities (Hong Kong) Company Limited", "job_title": "Settlement Officer", "description": "Responsibilities:\n\nHandle daily settlement of OTC Derivative and Stock option;\nHandle daily Corp Action / Entitlement of OTC Derivative;\nHandle daily trade reconciliation and confirmation;\nPerform daily system data input and file upload;\nAssist in system modification and responsible for UAT testing;\nRespond to all duties related to settlement matters;\nHandle ad hoc projects as assigned;\nThere will also be opportunities to learn about the settlement of other markets and other products.\u00a0\n\nRequirements:\n\nRelevant experience in settlement operations is preferable;\nExperience in\u00a0OTC/ overseas markets\u00a0is preferable;\nGood command PC skills & proficiency in Ms Word, Excel and Chinese word processing;\nGood command of written and spoken English and Chinese, including in Mandarin;\nResponsible, self-motivated, independent & able to work under pressure;\nGood command in both written and spoken English and Chinese (Cantonese & Mandarin);\nImmediate available is preferable;\nCandidates with more experience will be considered as Senior Officer;\nFresh Graduate is welcome.", "employment_types": ["Full Time", "Permanent"], "selling_points": [], "locations": ["Admiralty"], "categories": ["Banking / Finance", "Financial Services", "Order Processing & Operation / Settlement"], "post_time": "2022-01-10T03:05:45Z", "salary": {"currency": null, "max": null, "min": null, "period": "monthly", "term": null}, "salary_visible": false, "title_keywords": ["officer"], "responsibilities": ["ad hoc projects", "system modification", "uat testing", "system data"], "requirements": {"degrees": ["fresh graduate"], "majors": [], "languages": ["cantonese", "english", "chinese", "mandarin"], "language_level": ["proficiency", "good command"], "hard_skills": ["excel", "pc skills", "chinese word processing", "ms word"], "soft_skills": ["self-motivated", "independent", "responsible", "work under pressure"], "languages_combined": [{"language": "cantonese", "language_level": ["good command"]}, {"language": "english", "language_level": ["good command", "good command"]}, {"language": "chinese", "language_level": ["proficiency", "good command", "good command", "good command"]}, {"language": "mandarin", "language_level": ["good command", "good command"]}]}, "experience_required": {"duration": [], "field": ["settlement operations", "relevant experience"]}}, {"job_id": "100003009043266", "location_code": "hk", "company": "Harbridge Partners Limited", "job_title": "Head of Private Trust", "description": "Title:\u00a0 \u00a0 \u00a0 \u00a0 \u00a0 \u00a0 \u00a0 \u00a0 \u00a0 \u00a0 \u00a0 \u00a0 \u00a0Head of Private Trust\n\nLocation:\u00a0\u00a0\u00a0\u00a0\u00a0 \u00a0\u00a0\u00a0\u00a0\u00a0\u00a0\u00a0\u00a0\u00a0\u00a0 Hong Kong\n\nBackground: \u00a0\u00a0\u00a0\u00a0\u00a0\u00a0\u00a0\u00a0\u00a0\n\nOur client is an established Asian banking and financial services group with strong Asia presence and growth plans and is looking to hire Head of Private Trust positions.\n\nResponsibilities:\n\nFormulate the goals, objectives and business plan of the Private Trust business sector\nDesign and devise business plan effectively for promoting and securing trust services to high net worth private trust clients (both bank and non-bank channels)\nLead the team to ensure smooth delivery of trust administration and customer relationship work\nCollaborate and communicate with both internal and external stakeholders\nTrain and develop subordinates so that staff can perform up to the required standard and successors can be identified\nPerform ad-hoc assignments as required\n\nRequirements:\n\nDegree in Law, Accounting or business related disciplines, preferably with professional qualification such as HKCIS, CPA, TEP, ACCA\nMin 5 years of solid experience in private trust business with 3 years in managerial role preferred\nSound knowledge in trust set-up and routine administrative operation\nCapability to draw up effective marketing plan independently\nGood business acumen with innovative ideas\nMarketing experience in Mainland China market is an advantage\nFluency in both written and spoken English and Chinese, Putonghua is a must\nImmediately available is highly preferred\n\nWork Benefits/ Work Environment:\n\nGreat Career progression.\nGreat Training and Career Path\nGreat\u00a0MPF Pension Scheme\nGood Work Life Balance\nGreat working hours\n\nHarbridge Partners Limited\nEmployment Agency Licence:\u00a0 65522", "employment_types": ["Full Time", "Permanent"], "selling_points": ["Private Trust,Head,HKCIS,CPA,TEP ACCA,Lead Team,HK", "Formulate the goals,Objectives&Business plan", "Trust administration,Customer relationship work"], "locations": ["Central & Western Area"], "categories": ["Banking / Finance", "Financial Services", "Dealing & Trading", "Order Processing & Operation / Settlement"], "post_time": "2022-01-12T23:26:18Z", "salary": {"currency": null, "max": null, "min": null, "period": "monthly", "term": null}, "salary_visible": false, "title_keywords": [], "responsibilities": ["collaborate", "communicate with", "ad-hoc assignments", "design", "develop", "business plan", "administration"], "requirements": {"degrees": ["degree"], "majors": ["business", "related disciplines", "accounting", "law"], "languages": ["putonghua", "english", "chinese"], "language_level": ["fluency"], "hard_skills": ["cpa", "acca", "acumen"], "soft_skills": ["business acumen", "independently", "innovative"], "languages_combined": [{"language": "putonghua", "language_level": ["fluency"]}, {"language": "english", "language_level": ["fluency"]}, {"language": "chinese", "language_level": ["fluency"]}]}, "experience_required": {"duration": ["3 years", "min 5 years"], "field": ["managerial", "business", "marketing"]}}, {"job_id": "100003009046508", "location_code": "hk", "company": "Page Personnel", "job_title": "Business Risk and Control Senior Associate - Top US Bank", "description": "Our client is one of the largest financial services firms in the United States. They are currently looking for a high calibre as business risk and control senior associate to join the APAC Regional Business Risk and Control team to handle risk and control self assessment in APAC. The candidate should have at least 5 years of working experience in risk management within FS industry.\n\nClient Details\n\nOur client is one of the largest US financial services firms in the world, headquartered in San Francisco and founded in 1852. They are now opening an exciting role for business risk and control Senior Associate to join the APAC Regional Business Risk and Control team to manage front line control responsibilities for Business Process Management and Risk and Control Self Assessment for APAC. They identify, assess and mitigate risks across financial crimes, regulatory and operational risk types as well as designing and implementing controls to ensure work effectiveness by managing risk across corporate investment group.\n\nDescription\n\nResponsible for completing RCSA for the legal entity in APAC for the business and work with different business stakeholders for risk and control processes\nHandle frontline line responsibilities for the Regional International Business Process Management (BPM), Integrated Process Risk and Control (IPRC) programs and the business process risk ranking effort for APAC\nImplement Risk and Control Self-Assessments (RCSA) framework, identify and document RCSA activities associated with business processes\nDeliver Line of Business (LoB) RSCA, remediate RCSA quality assurance, identify control gaps and improvement opportunities in IPRC exercise\nWork closely with different stakeholders including international compliance, international operational risk, independent risk management, frontline business groups and business process subject matter experts for the RSCA program\nProvide guidance and advice on developing, implementing and monitoring business processes to identify, assess and mitigate risk\nDesign and implement risk mitigation strategies and controls, risk monitoring and risk reporting processes\n\nProfile\n\nBachelor's degree with major in risk management, business administration or relevant discipline\nAt least 5 years of working experience in risk management/ compliance (including operational risk, compliance, financial crimes, legal, credit risk, market risk, IT system security, business process management) within corporate investment banking/ risk and advisory role\nExperience in RCSA is a must\nStrong knowledge in excel, VLOOKUP and PPT\nExcellent stakeholder management skills with the ability to work with geographically dispersed teams and to communicate with all levels of stakeholders\nStrong analytical skills and data management skills\nExcellent English communication skills and interpersonal skills\n\nJob Offer\n\nInternational and dynamic working environment\nRewarding and stimulating job tasks\nExposure to APAC regional business\nMedical benefits\nCompetitive packages\n\nTo apply online please click the 'Apply' button below. For a confidential discussion about this role please contact Esther Liu on +852 2258 3537", "employment_types": ["Full Time", "Permanent"], "selling_points": ["International and dynamic working environment", "Rewarding and stimulating job tasks", "Exposure to APAC regional business"], "locations": ["Not Specified"], "categories": ["Banking / Finance", "Corporate Banking", "Order Processing & Operation / Settlement", "Risk Management"], "post_time": "2022-01-13T12:33:55Z", "salary": {"currency": null, "max": null, "min": null, "period": "monthly", "term": null}, "salary_visible": false, "title_keywords": ["senior associate"], "responsibilities": ["data", "quality", "design", "communication", "business process", "designing", "administration", "control", "compliance", "teams", "developing", "banking", "reporting", "management", "monitoring", "risk monitoring", "provide guidance", "communicate with", "system security"], "requirements": {"degrees": ["degree", "bachelor"], "majors": ["risk management", "business administration"], "languages": ["english"], "language_level": ["excellent"], "hard_skills": ["excel", "data management", "analytical skills", "dynamic", "vlookup"], "soft_skills": ["communication skills", "independent", "responsible", "analytical skills", "dynamic", "interpersonal skills"], "languages_combined": [{"language": "english", "language_level": ["excellent"]}]}, "experience_required": {"duration": ["at least 5 years"], "field": ["risk management", "management", "legal", "compliance", "it", "business", "security", "investment", "banking", "market risk", "credit risk", "financial"]}}, {"job_id": "100003009045590", "location_code": "hk", "company": "Resource Solutions Consulting Hong Kong Limited", "job_title": "Trade Operations Support (12 months contract, renewable)", "description": "About Our Client\nOur client is a prestigious international bank with a long history of providing corporate banking solutions to businesses and to large local companies, financial institutions and multinationals. We look for talented, tenacious individuals who are hungry to progress and eager to grow their knowledge.\n\nThe Global Market Operations is a global team, incorporated in 4 main platforms, working very closely with Front Office (FO) (Sales and Trading), Back Office, IT, Finance, Risk, Valuations & Risk Control and Process teams.\n\nIts main missions are to support efficiently the Front Office over:\n\nTrade Support : Trade bookings, late trade booking, amendments and cancellation\nPost trade allocation for clients,\u00a0validation and monitoring on trade repository\nP&L: Profit and Loss trading calculation and analysis, handle query for booking issues and provide the necessary information\nReporting, Control & Cross services: Internal controls and reporting, Static and Market Data maintenance, Corporate Actions and Index Tracking monitoring\u00a0\nConfirmation: Confirmations of trades\nSettlement: Settlements of trade\nExecution and brokerage\nWork closely with Front Offices and Client Services on any new client on-boarding process, ad-hoc requests and handle queries\nProduct Scopes: mainly on List Products, CBs, Vanilla Options, Forwards, Equity Swaps, Dividend Swaps, P-notes, NDFs, Accumulator/Decumulator, ELN, Variance Swap, Volatility Swap, Dispersion Swap and custom basket certificate.\u00a0\n\n\nQualifications:\u00a0\u00a0\n- Preferred bachelor or Master degree on Economics, Mathematics or Finance\n- Strong Delta One and equity derivatives products knowledge include front to back workflows and product event management\n- Good level of English to work in an international environment\n- Good command in Excel, VBA, Access\n\n\nValues and Diversity\n\nDynamic working gives everyone at our client the opportunity to integrate professional and personal lives, if you have a need for flexibility then please discuss this with the hiring manager. They are an equal opportunity employer and are opposed to discrimination on any grounds. It is the policy of our client to ensure equal employment opportunity without discrimination or harassment on the basis of race, colour, creed, religion, national origin, alienage or citizenship status, age, sex, sexual orientation, gender identity or expression, marital or domestic/civil partnership status, disability, veteran status, genetic information, or any other basis protected by law.", "employment_types": ["Full Time", "Temporary", "Contract"], "selling_points": ["Focus on Delta One and equity derivatives products", "Join a dynamic and top tier bank", "Immediately available preferred"], "locations": ["Central"], "categories": ["Banking / Finance", "Equities / Capital Markets", "Order Processing & Operation / Settlement"], "post_time": "2022-01-13T08:08:47Z", "salary": {"currency": null, "max": null, "min": null, "period": "monthly", "term": null}, "salary_visible": false, "title_keywords": ["operations"], "responsibilities": ["reporting", "control", "management", "maintenance", "operations", "analysis", "monitoring", "teams", "back office", "trade booking", "p&l", "brokerage", "ad-hoc requests", "booking", "banking", "market data", "tracking"], "requirements": {"degrees": ["certificate", "bachelor", "master degree"], "majors": ["finance", "mathematics", "economics"], "languages": ["english"], "language_level": ["good"], "hard_skills": ["vba", "excel", "maintenance", "analysis", "dynamic", "bookings"], "soft_skills": ["dynamic", "tenacious"], "languages_combined": [{"language": "english", "language_level": ["good"]}]}, "experience_required": {"duration": [], "field": []}}, {"job_id": "100003009043513", "location_code": "hk", "company": "QBE General Insurance (Hong Kong) Limited", "job_title": "Temp Account Receivable Staff", "description": "This is a 6 months temporary contract in the Accounts Receivable functions for handling daily cheque procedure for QBE.\u00a0\n\nOne of the responsibility will be\u00a0to handle the physical cheque receipting.\n\nImmediate available is a must\u00a0", "employment_types": ["Temporary", "Contract"], "selling_points": ["temp role", "account receivable", "finance"], "locations": ["Quarry Bay"], "categories": ["Banking / Finance", "Order Processing & Operation / Settlement"], "post_time": "2022-01-12T14:59:48Z", "salary": {"currency": null, "max": null, "min": null, "period": "monthly", "term": null}, "salary_visible": false, "title_keywords": ["staff"], "responsibilities": ["accounts receivable"], "requirements": {"degrees": [], "majors": [], "languages": [], "language_level": [], "hard_skills": [], "soft_skills": [], "languages_combined": []}, "experience_required": {"duration": [], "field": []}}, {"job_id": "100003009047715", "location_code": "hk", "company": "Public Bank (Hong Kong) Limited", "job_title": "Teller / Relief Teller (Full-Time / Part-Time) (Ref: JD-CSR)", "description": "Our client is a reputable international Private Banking /Wealth Management To cope with the rapid business expansion, they are now inviting high caliber candidates to join the team\n\n\n\nClient Onboarding /KYC -\u00a0Wealth Management/Private Banking\u00a0\n\nWorking Location: Quarry Bay\n\nPosition Purpose\n\n\nClient On-Boarding team\u2019s objective is to be the sole interface for new clients for standard\u00a0sensitive accounts. The goal, for this team, is to ensure a global and consistent \u201cfirst service\u201d is\u00a0rendered to the clients.\u00a0\nThis team will be working around 3 main themes: Prioritization of on-boarding, Coordination of\u00a0the whole process (Risk, Legal and Systems) and production of the Legal documentation and\u00a0KYC (Collection, Completeness, Conformity and Analysis. The team is also in charge of the\u00a0regular review process for standard sensitive accounts\nThe team must work as \u201cone team\u201d to ensure a cutting edge on-boarding service to clients and\u00a0work closely with major functions as well as FO/Markets.\u00a0\nOverall, through a dedicated on-boarding team and a single point of contact, the team is\u00a0responsible for client satisfaction with respect to on-boarding.\nTo facilitate and provide a complete transversal on\u2013boarding service to WM APAC. Producing\u00a0client risk assessments, client profiles, and due diligence analyses.\u00a0\nProviding feedback and escalating issues to the appropriate support functions and\u00a0management.\n\nKey Responsibilities\u00a0\u00a0\n\nImplementation and Process\n\nWork closely with Front Office to facilitate the collection of KYC and other relevant documents in accordance with the prevailing account opening procedures and local regulations.\nTo ensure evidence of each customer\u2019s identity and other relevant documents are received in order before account opening.\u00a0\nReview and approve KYC for new client on-boarding for standard sensitive accounts (i.e. non high risk clients).\nPerform qualitative and quantitative check on New Account Documentation for all clients\u00a0\nConduct KYC/CDD review on existing clients through periodic review.\u00a0\nEnsure all client files are stored and maintained accordingly (electronically and in paper format).\u00a0\nSupport Front Office queries related to client on boarding and client due diligence process.\u00a0 \u00a0\nPrepare regular reports for Management review (account documentation irregularities, monthly statistics).\u00a0\n\u00a0Ensure timely processing of static data updating request.\n\nTeam Spirit\n\nWork within a team \u2013 with an adaptable flexible approach, coordinate with team members and\u00a0\u00a0Front Office to resolve complex cases and address issues in a timely manner.\u00a0\nBe open to change and support the vision of working in a fully transversal operation\u00a0\u00a0\n\n\nInformation Sharing\n\nAbility to share information and eventually train new team members.\nControl and Risk\n\nAbide with operational risk procedures and escalate incidents to Seniors where necessary\nContribute to the implementation and controls for daily processes and assist with the update of\u00a0procedures\u00a0\u00a0\nReport and escalate concerns/issues to Seniors when required\u00a0\n\n\u00a0Communication\u00a0\n\nLiaise regularly with the following internal groups to ensure a smooth on boarding process:\u00a0Compliance, Legal, FO teams, Client on-boarding and due diligence team in Singapore/Hong Kong or other support teams within WMHK/WMSG that have any involvement in the Client On-boarding process.\n\nComply with Group Permanent Control Activities\u00a0\n\n\n\n\u00a0Direct contribution to Group operational permanent control framework.\n\u00a0Contribute to the implementation of operational permanent control policies and\u00a0 \u00a0procedures in\u00a0day-to-day business activities, such as Control Plan\u00a0\n\nComply with regulatory requirements and internal guideline\u00a0\nContribute to the reporting of all incidents according to the Incident Management System\u00a0\nMinimizing operational failure, including but not exclusively, the risk of fraud, by helping to\u00a0devise, and by implementing, sufficient regular controls\n\nEnsuring appropriate escalation to management and/or Permanent Control (or Compliance as\u00a0 appropriate) as soon as an issue is identified\n\nQualifications\u00a0\n\nCompetencies (Technical / Behavioural)\n\nTeam player, independent, hardworking, eager to learn and attention to details\nClient-oriented and high adaptability to changing environment\nAble to work under pressure and deal with unclear requests as well as a high volume of requests\nStrong analytical and strong risk sense\n\nSpecific Qualifications Required\u00a0\n\n\nMinimum 3 years of relevant working experience in\u00a0Client Onboarding /KYC /Account Document in Private Banking/ or Wealthmanagement\u00a0\nBachelor\u2019s level degree or professional qualification\u00a0\nUnderstand the principles and be familiar with WM products and types of customers\nStrong understanding of account documentation, due diligence and local Anti-Money\u00a0 Laundering requirements\nFluent in English (spoken and written).\u00a0 Good command in Mandarin is a plus (for supporting\u00a0Taiwan/China Markets).\u00a0\nExcellent communication and interpersonal skills\nMust possess a strong fundamental and technical skills, awareness of operational risk\nExcellent PC skills, especially in Excel. Knowledge of ACCESS is an advantage.\n\nPlease send full resume with\u00a0present & expected\u00a0salary to expedite sourcing\u00a0in\u00a0MS-WORD\u00a0format by clicking \u201cAPPLY NOW\u201d\n\nPlease quote our reference in your application\n\nPersonal data provided by job applicants will be used strictly in accordance with the employer\u2019s personal data policies, a copy of which will be provided upon request\n\nAll information provided will be used for recruitment purpose only", "employment_types": ["Full Time", "Permanent"], "selling_points": [], "locations": ["Not Specified"], "categories": ["Banking / Finance", "Retail Banking", "Financial Services", "Order Processing & Operation / Settlement"], "post_time": "2022-01-15T03:48:58Z", "salary": {"currency": null, "max": null, "min": null, "period": null, "term": null}, "salary_visible": false, "title_keywords": [], "responsibilities": ["regulations", "liaise", "data", "regulatory requirements", "regular review", "communication", "regular reports for management", "plan", "personal data", "work under pressure", "due diligence", "control", "account documentation", "account opening", "cdd", "compliance", "teams", "implementation", "banking", "kyc", "escalate incidents", "business activities", "report", "reporting", "management", "review", "procedures", "coordinate with", "contact", "documentation", "irregularities", "policies", "analysis", "systems", "a timely manner", "recruitment", "coordination", "share information"], "requirements": {"degrees": ["degree", "bachelor"], "majors": [], "languages": ["english", "mandarin"], "language_level": ["good command", "fluent"], "hard_skills": ["pc skills", "plus", "excel", "ms-word", "account opening", "analysis", "cdd", "goal", "rapid", "kyc", "documentation", "processing"], "soft_skills": ["flexible", "team spirit", "independent", "responsible", "adaptable", "timely", "technical skills", "communication", "smooth", "eager to learn", "communication and interpersonal skills", "adaptability", "coordination", "sensitive", "attention to details", "team player", "hardworking", "work under pressure"], "languages_combined": [{"language": "english", "language_level": ["fluent"]}, {"language": "mandarin", "language_level": ["good command"]}]}, "experience_required": {"duration": ["minimum 3 years"], "field": ["relevant working experience", "banking"]}}, {"job_id": "100003009039028", "location_code": "hk", "company": "KBC Bank N. V.", "job_title": "Junior Officer, Remittance & Settlement", "description": "\u00a0\n\n\u201cWe\u201d are the largest Belgian bank with Asian activities in Singapore, Shanghai and Hong Kong.\u00a0 Each and every day our team in Asia strives to become the Preferred European Banking Partner of our domestic and European customers. To do so, we combine high professional standards and a pleasant working environment and we put our customers in the center point in everything we do. Also our internal customers!\n\nWe are looking for an enthusiastic and self-motivating talent to join our team as the Junior Officer of Remittance and Settlement Team. You can have the exposure in full remittance and settlement process in the international banking.\n\n\u00a0About the job\n\nAs the Junior Officer of Remittance and Settlement team, you process inward and outward remittance;\nYou handle and respond to inquiries / requests from inter-department, customers, on transaction processing and related matters;\nYou perform customer FX transactions, as well as participating in AML screening on incoming & outgoing swift payments;\nYou manage the daily operations through SWIFT/ RTGS system;\nYou manage the general administrative duties of your team and assist in ad hoc duties as assigned by superiors.\n\nAbout you\n\nTo join the KBC team, you need to be a good team player, with ability to communicate clearly and concisely. You are with good command of spoken and written English, Chinese & Mandarin, as well as great self-motivation and self-starting ability. You need to be familiar AML screening and SWIFT/ RTGS system. You should also attain tertiary qualification and have minimum 3 years\u2019 relevant experience. Finally, need to be eager to learn and continuously develop yourself to remain future proof in a swiftly changing environment. If you are having less experience, we may also considered you as Senior Clerk.\n\nWe offer an attractive remuneration package in line with your relevant experience and the importance of the position.\u00a0\u00a0\n\nIf you feel like this position is a fit with your skill-set and expectations, please apply with a cover letter and CV (indicating your salary expectation) by email via \"Apply Now\". For any questions with regards to the position you can give us a call on\u00a0 (852) 2879 3363.\n\n\nAll information received will be used for recruitment purpose only. Applicants not being invited to interview within 6 weeks may consider their applications unsuccessful. All information on unsuccessful candidates will be deleted from our files within 12 months.", "employment_types": ["Full Time", "Permanent"], "selling_points": ["3 years' relevant experience", "Exposure in international banking", "Perform inward & outward remittance"], "locations": ["Wan Chai"], "categories": ["Banking / Finance", "Corporate Banking", "Others", "Order Processing & Operation / Settlement"], "post_time": "2022-01-11T08:26:15Z", "salary": {"currency": null, "max": null, "min": null, "period": "monthly", "term": null}, "salary_visible": false, "title_keywords": ["officer", "junior"], "responsibilities": ["ad hoc duties", "settlement process", "banking", "transactions", "develop", "daily operations", "payments", "aml screening", "administrative duties", "transaction processing"], "requirements": {"degrees": [], "majors": [], "languages": ["english", "chinese", "mandarin"], "language_level": ["good command"], "hard_skills": ["swift", "processing", "aml screening"], "soft_skills": ["outgoing", "good team player", "pleasant", "eager to learn", "self-motivation", "enthusiastic"], "languages_combined": [{"language": "english", "language_level": ["good command"]}, {"language": "chinese", "language_level": ["good command"]}, {"language": "mandarin", "language_level": ["good command"]}]}, "experience_required": {"duration": ["minimum 3 years"], "field": ["relevant experience"]}}, {"job_id": "100003009039074", "location_code": "hk", "company": "Page Personnel", "job_title": "Settlement - Asian Corporate Bank", "description": "Our client is a well-established Korean corporate bank established in Hong Kong for more than 50 years. They are now looking for a Settlement Officer with at least 4 years of experience in settlement operation.\n\nClient Details\n\nOur client is a well-established Korean corporate bank established in Hong Kong for more than 50 years. They provide corporate banking and investment banking services such as off-shore loan arrangement and participation, trade finance, corporate finance advisory(M&A) and fund management.\n\nThey are now looking for a Settlement Officer with at least 4 years of experience in settlement operation. The candidate would be expected to perform daily operation of treasury settlement including confirmation, payment and accounting for FX, MM, Fixed Income, Derivatives. The company culture is relatively stable.\n\nDescription\n\nPerform daily operation duties of treasury settlement including confirmation, payment and accounting for FX, MM, Fixed Income, Derivatives and transactions\nHandle pre-settlement/settlement exception cases and post-settlement investigations to prevent trade-breaks\nParticipate in new product or system upgrade projects, including assist in workflow design or testing as required\nLiaise with treasury front office, finance/accounting, legal/compliance, IT and other related units when necessary\n\nProfile\n\nPost-secondary or above\n4+ years of experience in settlement operations\nExperience in SWIFT, CHATS, CMU, Euroclear/Clearstream and other international/domestic payment and settlement systems\nGood command of written and spoken English and Chinese\nAble to work independently under time pressure with report on time\nAttention to details and with good risk awareness\n\nJob Offer\n\nStable Culture\nStable Working Hours\nDiscretionary Year-end Bonus\nMedical Benefits covering Spouse and Kids\nAnnual Leave: 13 days up\n\nTo apply online please click the 'Apply' button below. For a confidential discussion about this role please contact Janet CHang on +852 3602 2459.", "employment_types": ["Full Time", "Permanent"], "selling_points": ["FX/MM/Fixed Income/Derivatives", "Stable Working Hours", "Immediately Available is preferrable"], "locations": ["Not Specified"], "categories": ["Banking / Finance", "Financial Services", "Order Processing & Operation / Settlement"], "post_time": "2022-01-11T08:36:26Z", "salary": {"currency": "HKD", "max": 29999, "min": 25000, "period": "monthly", "term": null}, "salary_visible": true, "title_keywords": [], "responsibilities": ["year-end", "management", "operations", "compliance", "daily operation", "systems", "transactions", "design", "testing", "payment", "banking", "liaise with", "report"], "requirements": {"degrees": [], "majors": [], "languages": ["english", "chinese", "korean"], "language_level": ["good command"], "hard_skills": ["swift"], "soft_skills": ["stable", "work independently", "attention to details"], "languages_combined": [{"language": "english", "language_level": ["good command"]}, {"language": "chinese", "language_level": ["good command"]}, {"language": "korean", "language_level": []}]}, "experience_required": {"duration": ["at least 4 years", "4+ years"], "field": ["settlement operations", "operation"]}}, {"job_id": "100003009044716", "location_code": "hk", "company": "UOB Kay Hian (Hong Kong) Limited", "job_title": "Assistant Manager \u2013 Client Due Diligence & Data Management", "description": "Responsibilities:\n\n\nPerform KYC and CDD on Corporate and Institutional clients\nLead recurring project such as AML periodic review and tax reporting (FATCA, CRS)\nReview and update the account opening procedures and client due diligence policy\nStreamline and automate existing operation workflow\nWork closely with Salesperson, Compliance, Internal Audit and other operation departments for client onboarding and ongoing monitoring issues\nRequirements:\n\n\nAt least 5 years relevant experience in Corporate and Institutional client onboarding, KYC/CDD and AML from banking or financial institutions\nCandidate with managerial experience will be considered with priority\nFamiliar with complex entity structure (trust, limited partnership) and tax reporting standard is a plus\nFluent in English, Cantonese and Mandarin\nMature, self-motivated & well-organized\nExcellent interpersonal & communication skills\n\nInterested candidates are invited to send a comprehensive resume stating current and expected salaries to\u00a0Head of Human Resources, UOB Kay Hian (Hong Kong) Limited, 6/F Harcourt House, 39 Gloucester Road, Hong Kong\u00a0or email by clicking the below \"Apply Now\" button", "employment_types": ["Full Time", "Permanent"], "selling_points": [], "locations": ["Wan Chai"], "categories": ["Banking / Finance", "Financial Services", "Others", "Order Processing & Operation / Settlement"], "post_time": "2022-01-13T05:40:43Z", "salary": {"currency": null, "max": null, "min": null, "period": "monthly", "term": null}, "salary_visible": false, "title_keywords": ["assistant manager"], "responsibilities": ["tax", "reporting", "due diligence", "aml", "internal audit", "cdd", "account opening", "review", "procedures", "compliance", "monitoring", "kyc"], "requirements": {"degrees": [], "majors": [], "languages": ["cantonese", "english", "mandarin"], "language_level": ["fluent"], "hard_skills": ["cdd", "plus", "aml", "kyc"], "soft_skills": ["communication skills", "self-motivated", "well-organized", "mature", "interpersonal"], "languages_combined": [{"language": "cantonese", "language_level": ["fluent"]}, {"language": "english", "language_level": ["fluent"]}, {"language": "mandarin", "language_level": ["fluent"]}]}, "experience_required": {"duration": ["at least 5 years"], "field": ["managerial", "financial institutions", "relevant experience", "banking"]}}, {"job_id": "100003009042403", "location_code": "hk", "company": "Bank of China (Hong Kong) Limited", "job_title": "Assistant Trade Services Manager", "description": "Job Duties & Responsibilities:\nReporting directly to the Deputy Head of Operations, the incumbent would ---\nManage the Operation Support & Control Group in monitoring the process performance of other operations groups in the Department\nPerform as operation planning function to identify processing risks. Support product development, transaction processing system and regulatory related projects\nManage the Telecommunication team to ensure timely delivery of all in/out messages\nEnsure communications made through systems are in compliance with policies and rules of the Bank in security control\nCo-ordinate compliance and system related project implementations such as processing risk control improvement projects and branch-wise transaction processing etc.\nCo-ordinate cross-group training for the team and processing groups\u2019 members to enhance and maintain their risks and regulatory awareness and skills competence\nReview transaction sanction screening results and release SWIFT messages withheld under false positive hits\nAudit confirmation coordination for all business units and ensure completeness of the audit confirmation before sending it to the external auditor\nPrepare respond to banks for KYC inquiries request, consolidate responses and feedbacks for industry surveys and questionnaires\nPerform regular customers check upon receipt request from law firms and government bodies with strong sense of customer data protection\nRequirements:\nGood academic qualifications with degree or a professional accounting qualification\nOver 12 years\u2019 of experience in banking operation with at least 3 years at Managerial level\nWell versed in AML compliance on customer accounts documentation\nKnowledgeable in trade, loans and remittance products, i.e. their features, associated risks, operation flow, relevant international governing rules and practice would be an advantage\nPlease apply with detailed resume stating latest and expected salary by email via \u201cApply now\u201d.\u00a0\nSMBC is an equal opportunity employer. We are committed to fostering a diversified and inclusive workplace and removing barriers to provide equal access to employment.\nApplication details will be used only for recruitment purposes, and will be destroyed after 1 year. Applicants not contacted after 6 weeks may consider their applications unsuccessful.", "employment_types": ["Full Time"], "selling_points": ["CDCS", "Trade Services", "Operation"], "locations": ["Others"], "categories": ["Banking / Finance", "Order Processing & Operation / Settlement"], "post_time": "2022-01-12T07:19:40Z", "salary": {"currency": null, "max": null, "min": null, "period": "monthly", "term": null}, "salary_visible": false, "title_keywords": ["manager", "assistant"], "responsibilities": ["reporting", "control", "operations", "policies", "monitoring", "systems", "compliance", "review", "audit", "kyc", "customer data", "maintain", "coordination", "transaction processing", "planning"], "requirements": {"degrees": ["degree"], "majors": ["accounting"], "languages": [], "language_level": [], "hard_skills": ["documentation", "aml"], "soft_skills": ["committed", "detailed"], "languages_combined": []}, "experience_required": {"duration": ["at least 3 years", "12 years"], "field": ["managerial", "operation", "banking"]}}, {"job_id": "100003009043171", "location_code": "hk", "company": "iFAST ePension Services Limited", "job_title": "Assistant Operations Manager, Pension", "description": "Dynamic Trade Support & Portfolio Support\nComprehensive & Competitive Benefits\nGlobal PWM & Asset Management platform\n\nRepresenting multiple Global Private Banks and Asset Management Groups in searching for potential talents to be part of their regional middle office & front office support team!\n\n\nJob Duties\n\nEnsure timely production of trade booking/reconciliation; continuous monitoring of corporate action/operations issues\nTackle front office traders / portfolio managers enquiries related to trade related aspects\nActive participation in continuous process/system enhancement to cater for innovation, new markets/products initiatives\n\nRequirements\n\nWell qualified graduate in Mathematics/Financial Engineering with 4 years+ middle office/trader support experience earned from International Banks and Financial Institutions.\nGood understanding of global investment products in particular with Equities Derivatives, Fixed Income and investment funds.\nIT savvy with good proficiency in Excel and VBA\nProactive personality with sound analytical and interpersonal skill with proven exposure in working for traders\nAdaptive to working in a highly multi-cultural and dynamic trading environment\n\n\n\nInterested candidates, please email your update resume (in MS WORD format) with current and expected salary to us soonest.\n\nAlso come visit ProJOB21 www.ProJob21.com to discover other exciting career opportunities!\n\nAll information received will be kept in strict confidence and used for employment-related purposes only.", "employment_types": ["Full Time", "Permanent"], "selling_points": ["3 years experience in pension industry", "Setup of departmental infrastructure and process", "21 days annual leave"], "locations": ["Tsim Sha Tsui"], "categories": ["Banking / Finance", "Others", "Insurance", "Others", "Order Processing & Operation / Settlement"], "post_time": "2022-01-12T10:00:15Z", "salary": {"currency": null, "max": null, "min": null, "period": "monthly", "term": null}, "salary_visible": false, "title_keywords": ["assistant operations manager"], "responsibilities": [], "requirements": {"degrees": [], "majors": [], "languages": [], "language_level": [], "hard_skills": [], "soft_skills": [], "languages_combined": []}, "experience_required": {"duration": [], "field": []}}, {"job_id": "100003009035415", "location_code": "hk", "company": "China Tonghai Asset Management Limited", "job_title": "Fund Administrative Officer / Senior Fund Administrative Officer", "description": "Position Overview & Purpose\n\n\nIt is responsible for account payable payments handling, bank reconciliation and other team supporting activities.\n\nJob Description\n\n\nAssist in daily accounting operations including preparation of cheque, TT remittance & accounting entries;\nPrepare daily payment vouchers and confirm payment details with vendors\nAssist in updating payment bank records;\nLiaise with various departments to reconcile transactions;\nAssist in month-end closing, reporting, bank reconciliation and year-end audit;\nPerform other ad hoc assignments as required\n\nRequirements:\n\n\nDiploma holder or above in Accounting with LCCI intermediate or above;\nMinimum 1-2 years\u2019 relevant working experience;\nGood command of English and Chinese;\nGood knowledge in MS Office;\nWilling to learn and able to work under a dynamic environment, with strong emphasis on teamwork.\n\nCandidates with more experience will be considered as Senior Accounting Clerk.", "employment_types": ["Full Time", "Permanent"], "selling_points": ["5 days work week at Central", "Education allowance, medial, dental and insurance", "Asset Management"], "locations": ["Central"], "categories": ["Banking / Finance", "Fund Management", "Order Processing & Operation / Settlement", "Asset Management"], "post_time": "2022-01-10T07:04:29Z", "salary": {"currency": null, "max": null, "min": null, "period": "monthly", "term": null}, "salary_visible": false, "title_keywords": ["administrative officer"], "responsibilities": ["reporting", "year-end", "daily accounting operations", "transactions", "liaise with various departments", "bank reconciliation", "audit", "payment", "month-end closing", "ad hoc assignments"], "requirements": {"degrees": ["diploma holder"], "majors": ["accounting"], "languages": ["english", "chinese"], "language_level": ["good command"], "hard_skills": ["dynamic", "ms office"], "soft_skills": ["dynamic environment", "teamwork", "willing to learn"], "languages_combined": [{"language": "english", "language_level": ["good command"]}, {"language": "chinese", "language_level": ["good command"]}]}, "experience_required": {"duration": ["minimum 1-2 years"], "field": ["accounting", "relevant working experience"]}}]