[{"job_id": "100003009052277", "location_code": "hk", "company": "Surrich International Company Limited", "job_title": "\u6295\u8d44\u52a9\u7406 Research Assistant", "description": "1\uff09\u534f\u52a9\u6295\u8d44\u7ecf\u7406\u505a\u597d\u6743\u76ca\u5e02\u573a\u548c\u503a\u5238\u5e02\u573a\u7684\u6295\u8d44\u7814\u7a76\uff0c\u534f\u52a9\u5236\u5b9a\u80a1\u7968\u3001\u503a\u5238\u7684\u6295\u8d44\u8ba1\u5212\u3001\u6295\u8d44\u7b56\u7565\u3002\n\nAssist investment managers in the investment research of equity market and bond market, including formulating investment plans and investment strategies for stocks and bonds.\n\n2\uff09\u8fdb\u884c\u884c\u4e1a\u548c\u516c\u53f8\u7684\u57fa\u672c\u9762\u7814\u7a76\uff0c\u6316\u6398\u6295\u8d44\u673a\u4f1a\uff1b\n\nFollow up, research and analyze the fundamentals of industries and companies, and explore investment opportunities;\n\n3\uff09\u534f\u52a9\u6295\u8d44\u7ecf\u7406\u8ddf\u8e2a\u6301\u4ed3\u4e2a\u80a1\uff0c\u5e76\u63d0\u51fa\u6295\u8d44\u5efa\u8bae\uff1b\n\nHelp investment managers keep track of individual stocks held and make investment recommendations independently;\n\n4\uff09\u4fdd\u6301\u4e0e\u5e02\u573a\u4e2d\u5176\u4ed6\u673a\u6784\u6295\u8d44\u8005\u3001\u4e0a\u5e02\u516c\u53f8\u3001\u7814\u7a76\u5458\u7684\u7d27\u5bc6\u8054\u7cfb\u548c\u6c9f\u901a\uff1b\n\nMaintain close contact and communication with other institutional investors, listed companies, and researchers in the market;\n\n5\uff09\u5b8c\u6210\u90e8\u95e8\u548c\u516c\u53f8\u4ea4\u529e\u7684\u5176\u4ed6\u4e8b\u9879\u3002\n\nOrganize the implementation and completion of other matters assigned by the department and the company.", "employment_types": ["Full Time"], "selling_points": ["\u91cd\u70b9\u9662\u6821\u91d1\u878d\u53ca\u76f8\u5173\u4e13\u4e1a\u7855\u58eb\u53ca\u4ee5\u4e0a\u5b66\u5386\uff1b", "\u5bf9\u8bc1\u5238\u6295\u8d44\u4e1a\u52a1\u53ca\u6295\u8d44\u7ba1\u7406\u5de5\u4f5c\u62b1\u6709\u70ed\u5ff1\uff0c\u5177\u6709\u826f\u597d\u7684\u7814\u7a76\u3001\u5206\u6790\u3001\u5224\u65ad\u80fd\u529b\uff1b", "\u5177\u6709\u656c\u4e1a\u7cbe\u795e\uff0c\u6709\u8f83\u5f3a\u7684\u6c9f\u901a\u4ea4\u6d41\u3001\u56e2\u961f\u534f\u4f5c\u7b49\u80fd\u529b\uff0c\u5177\u6709\u8f83\u5f3a\u7684\u518d\u5b66\u4e60\u80fd\u529b\u3002"], "locations": ["Wan Chai"], "categories": ["Banking / Finance", "Investment", "Equities / Capital Markets", "Others"], "post_time": "2022-01-17T02:40:07Z", "salary": {"currency": null, "max": null, "min": null, "period": "monthly", "term": null}, "salary_visible": false, "title_keywords": ["research assistant"], "responsibilities": ["investment strategies", "implementation", "communication", "maintain", "contact", "plans"], "requirements": {"degrees": [], "majors": [], "languages": [], "language_level": [], "hard_skills": ["make"], "soft_skills": ["communication", "independently"], "languages_combined": []}, "experience_required": {"duration": [], "field": []}}, {"job_id": "100003009053271", "location_code": "hk", "company": "IPG Wealth Management Limited", "job_title": "Admin and Accounts Clerk", "description": "Job description and responsibilities\n\n-\u00a0 Handle daily admin work\u00a0\n-\u00a0Assist in accounting entry & month-end closing\n\n\n\nJob requirements\n\n-\u00a0 LCC Intermediate\n-\u00a02-4 years relevant experience", "employment_types": ["Full Time"], "selling_points": ["Double pay at year end", "Comprehensive medical scheme", "Special performance bonus"], "locations": ["Tsim Sha Tsui"], "categories": ["Banking / Finance", "Others"], "post_time": "2022-01-17T06:38:40Z", "salary": {"currency": null, "max": null, "min": null, "period": "monthly", "term": null}, "salary_visible": false, "title_keywords": ["accounts clerk", "admin"], "responsibilities": ["month-end closing"], "requirements": {"degrees": [], "majors": [], "languages": [], "language_level": [], "hard_skills": ["lcc"], "soft_skills": [], "languages_combined": []}, "experience_required": {"duration": ["2-4 years"], "field": ["relevant experience"]}}, {"job_id": "100003009054371", "location_code": "hk", "company": "Bright Smart Securities International (H.K.) Limited", "job_title": "Sales Officer (Warm Call Team)", "description": "Responsibilities:\n\nMaintain and develop trustful relationship with existing and potential clients;\nHandle daily phone/online customer enquiries and complaints;\nProvide back-end support to the sales team on client's enquiries;\nUndate and maintain customer information on database;\nParticipate in warm call, ad-hoc projects as assigned.\n\n\u00a0Requirement\u00a0& Qualification:\n\nForm 5 or above (Passed in Chinese and Mathematics/ English and Mathematics) is a must;\nOne year of telesales experience, fresh graduates are also welcomed\u00a0;\nHardworking, responsible and good communication skills;\nGood customer services and telephone manners;\nGood command of spoken and written English and Chinese including Putonghua.\n\n\u00a0We Offer:\n\nCompetitive remuneration package\n5 Days Work & Bank Holidays\nAttendance Bonus\nMeal Allowance\nDiscretionary Bonus\nMedical Insurance\nOn the Job Training\n\nWe provide attractive remuneration package and fringe benefits for the right candidate.\n\nInterested parties please send detailed resume with current and expected salaries to\u00a0Human Resources Department by clicking\u00a0\"Apply Now\"\u00a0or\u00a0fax to: 2530 2218.\n\nAll information collected will be used for recruitment purpose only, only shortlisted candidates will be notified. Welcome to visit our website: http://www.bsgroup.com.hk/ for more information.", "employment_types": ["Full Time", "Permanent"], "selling_points": [], "locations": ["Central"], "categories": ["Banking / Finance", "Retail Banking", "Others"], "post_time": "2022-01-17T09:18:37Z", "salary": {"currency": null, "max": null, "min": null, "period": "monthly", "term": null}, "salary_visible": false, "title_keywords": ["sales officer"], "responsibilities": ["develop", "maintain", "sales team", "database", "ad-hoc projects", "customer enquiries and complaints"], "requirements": {"degrees": ["form 5 or above"], "majors": ["mathematics"], "languages": ["putonghua", "english", "chinese"], "language_level": ["good command"], "hard_skills": [], "soft_skills": ["communication skills", "hardworking", "responsible"], "languages_combined": [{"language": "putonghua", "language_level": ["good command"]}, {"language": "english", "language_level": ["good command"]}, {"language": "chinese", "language_level": ["good command"]}]}, "experience_required": {"duration": ["one year"], "field": ["telesales"]}}, {"job_id": "100003009052129", "location_code": "hk", "company": "TDCX Hong Kong", "job_title": "Phone Banking Officer (Customer Service/ 5-day/ new join bonus $12K) - Welcome Fresh Graduates", "description": "#BeMore\n\nDo you aspire a rewarding career that lets you do more and achieve more? Unleash your full potential at work with TDCX, an award-winning and fast-growing BPO company.\n\nWork with the world\u2019s most loved brands and be with awesome, diverse people. Be home, belong, and start your journey to #BeMore!\n\nTop reasons to work with TDCX.\n\n\n\nAttractive remuneration,\u00a0great perks,\u00a0and performance incentives\u00a0\nComprehensive medical, insurance,\u00a0or social security coverage\nPremium workspaces\nEngaging activities\u00a0and recognition programs\nStrong learning and development plans for your career growth\nPositive culture for you to\u00a0#BeMore\u00a0at work\nEasy to locate area with direct access to public transport\n\nBe coached and mentored by experts in your field\nJoin a global company with 25 years of experience and more than\u00a0310+ industry awards\n\n\u4e3b\u8981\u8077\u8cac\n\n\u63a5\u807d\u71b1\u7dda\u67e5\u8a62\uff0c\u89e3\u7b54\u5ba2\u4eba\u6709\u95dc\u9280\u884c\u670d\u52d9\u6216\u7522\u54c1\u7684\u67e5\u8a62\n\u8ddf\u9032\u5ba2\u4eba\u610f\u898b\u6216\u6295\u8a34\n\n\u5165\u8077\u8981\u6c42\n\n\n\u81f3\u5c11\u5177\u5099\u534a\u5e74\u6216\u4ee5\u4e0a\u5de5\u4f5c\u7d93\u9a57\n\u4ee5\u79ae\u5c0d\u5f85\uff0c\u5b88\u6642\u53ca\u6301\u8a8d\u771f\u5de5\u4f5c\u614b\u5ea6\n\n\u826f\u597d\u6e9d\u901a\u6280\u5de7\u53ca\u80fd\u65bc\u58d3\u529b\u4e0b\u5de5\u4f5c\n\u80fd\u64cd\u6d41\u5229\u5ee3\u6771\u8a71\uff0c\u82f1\u8a9e\u53ca\u666e\u901a\u8a71\u8005\u512a\u5148\u53d6\u9304\n\u6b61\u8fce\u61c9\u5c46\u7562\u696d\u751f\n\n\u5f85\u9047\n\n\u65b0\u4eba\u734e $12,000\n\u56fa\u5b9a\u5e95\u85aa\u00a0\n\u5b9a\u671f\u6d3b\u52d5\u53ca\u826f\u597d\u8868\u73fe\u734e\u8cde\n\u4e00\u9031\u4e94\u5929\u5de5\u4f5c, \u6bcf\u59298\u5c0f\u6642\u5de5\u4f5c\n\n\u6bcf\u9031\u5de5\u4f5c\u6642\u9593\u4e0d\u591a\u65bc40\u5c0f\u6642,\u00a0\u8f2a\u73ed\u5236\n\u91ab\u7642\u4fdd\u969c\u00a0\u00a0(\u5305\u62ec:\u00a0\u9580\u8a3a,\u00a0\u00a0\u4f4f\u9662\u53ca\u4eba\u58fd)\u00a0\n\u9280\u884c\u5047\u671f\n12\u5929\u6709\u85aa\u5e74\u5047\n\u5f37\u7a4d\u91d1\n\u5168\u9762\u53ca\u512a\u8cea\u5c08\u696d\u57f9\u8a13", "employment_types": ["Full Time", "Permanent"], "selling_points": ["5 days work, 12 days AL, better career path", "no cold-call, no selling, inbound call", "banking, call centre"], "locations": ["Shatin Area"], "categories": ["Banking / Finance", "Others", "Sales, CS & Business Devpt", "Call Centre", "Customer Service - Supervisor / Officer"], "post_time": "2022-01-17T02:11:23Z", "salary": {"currency": "HKD", "max": 16999, "min": 14000, "period": "monthly", "term": null}, "salary_visible": true, "title_keywords": ["officer", "customer service"], "responsibilities": ["plans", "insurance"], "requirements": {"degrees": [], "majors": [], "languages": [], "language_level": [], "hard_skills": [], "soft_skills": ["diverse", "comprehensive", "positive", "learning"], "languages_combined": []}, "experience_required": {"duration": ["25 years"], "field": []}}, {"job_id": "100003009053838", "location_code": "hk", "company": "Konew Financial Express Ltd", "job_title": "\u7269\u696d\u8abf\u67e5\u54e1", "description": "\u8077\u8cac\uff1a\n\u5354\u52a9\u516c\u53f8\u9032\u884c\u5ba2\u6236\u7684\u7269\u696d\u67e5\u8a2a\n\u7d00\u9304\u9280\u4e3b\u76e4\u7684\u60c5\u6cc1\u53ca\u6e05\u7406\u7576\u4e2d\u96dc\u7269\n\u76e3\u5bdf\u9280\u4e3b\u76e4\u7684\u7dad\u4fee\u53ca\u7ffb\u65b0\n\u57f7\u884c\u884c\u653f\u90e8\u6307\u6d3e\u7684\u8077\u52d9\n\n\u8981\u6c42\uff1a\n\n\nHKCEE / HKDSE\u7a0b\u5ea6\u6216\u4ee5\u4e0a\n\u61c2\u5e73\u677f\u96fb\u8166\u64cd\u4f5c\n\u826f\u597d\u5ee3\u6771\u8a71\u3001\u7c21\u55ae\u82f1\u6587\n\u4e00\u5e74\u6216\u4ee5\u4e0a\u5ba2\u6236\u670d\u52d9\u7d93\u9a57\n\u614b\u5ea6\u8aa0\u61c7\u89aa\u5207\uff0c\u52e4\u596e\u5b88\u6642\uff0c\u6709\u8cac\u4efb\u611f\n\u6301 1\u30012 \u865f\u724c\u512a\u5148\u8003\u616e\n\n\u5f85\u9047\uff1a\n\n\u661f\u671f\u4e00\u81f3\u4e94\uff0c\u671d\u4e5d\u665a\u516d\n\u52e4\u5de5\u596c\u91d1\n\u914c\u60c5\u6027\u82b1\u7d05\n\u6709\u85aa\u5e74\u5047\n\u751f\u65e5\u5047\n\u5165\u8077\u5468\u5e74\u5047\n\u734e\u52f5\u5047\u671f\n\u91ab\u7642\u4fdd\u96aa\u798f\u5229\u53ca\u7259\u79d1\u798f\n\n\u7533\u8acb\u65b9\u6cd5\uff1a\u6709\u8208\u8da3\u7533\u8acb\u7684\u4eba\u58eb\uff0c\u8acb\u6309 'Apply Now'\u3002\n\n<\u6240\u6536\u96c6\u7684\u500b\u4eba\u8cc7\u6599\u7d55\u5c0d\u4fdd\u5bc6\u53ca\u53ea\u4f5c\u62db\u8058\u7528\u9014>", "employment_types": ["Full Time"], "selling_points": ["\u5354\u52a9\u516c\u53f8\u9032\u884c\u7269\u696d\u67e5\u8a2a", "\u6301 1\u30012 \u865f\u724c\u512a\u5148\u8003\u616e", "\u826f\u597d\u5de5\u4f5c\u798f\u5229"], "locations": ["Central"], "categories": ["Transportation & Logistics", "Others", "Banking / Finance", "Others", "Property / Real Estate", "Others"], "post_time": "2022-01-17T07:36:09Z", "salary": {"currency": null, "max": null, "min": null, "period": "monthly", "term": null}, "salary_visible": false, "title_keywords": [], "responsibilities": [], "requirements": {"degrees": [], "majors": [], "languages": [], "language_level": [], "hard_skills": [], "soft_skills": [], "languages_combined": []}, "experience_required": {"duration": [], "field": []}}, {"job_id": "100003009045579", "location_code": "hk", "company": "HANSEL INTERNATIONAL Executive Search Limited", "job_title": "Customer Service Officer - Fintech Company (5-day Rotational Duties per Week)", "description": "Career Level\nSenior\nQualification\nDegree\nYears of Experience\n5 years\nJob Type\nFull Time, Permanent\nJob Functions\nAccounting, Financial Analyst, Banking / Finance, Analyst, Others", "employment_types": ["Full Time"], "selling_points": ["2+ years of CS experience in brokerage industry", "5 days rotational per week; 9am-6pm", "Holder of SFC Type 1 & 2"], "locations": ["Tin Hau"], "categories": ["Banking / Finance", "Financial Services", "Others", "Sales, CS & Business Devpt", "Customer Service - Supervisor / Officer"], "post_time": "2022-01-13T08:07:31Z", "salary": {"currency": null, "max": null, "min": null, "period": "monthly", "term": null}, "salary_visible": false, "title_keywords": ["customer service officer"], "responsibilities": ["banking"], "requirements": {"degrees": ["degree"], "majors": [], "languages": [], "language_level": [], "hard_skills": [], "soft_skills": [], "languages_combined": []}, "experience_required": {"duration": [], "field": []}}, {"job_id": "100003009052717", "location_code": "hk", "company": "Delken Group Limited", "job_title": "Secretary (5-day work)", "description": "Career Level\nMiddle\nQualification\nDegree\nYears of Experience\n3 years\nJob Type\nFull Time, Permanent\nJob Functions\nBanking / Finance, Analyst, Corporate Banking, Credit Analysis / Approval", "employment_types": ["Full Time", "Permanent"], "selling_points": ["5 years of rel exp in sizable organisations", "Work independently on Secretarial; /Admin support", "5-days work, good benefit"], "locations": ["Central"], "categories": ["Admin & HR", "Clerical / Admin Staff", "Secretary", "Banking / Finance", "Others"], "post_time": "2022-01-17T03:47:18Z", "salary": {"currency": null, "max": null, "min": null, "period": "monthly", "term": null}, "salary_visible": false, "title_keywords": ["secretary"], "responsibilities": ["analysis", "banking"], "requirements": {"degrees": ["degree"], "majors": [], "languages": [], "language_level": [], "hard_skills": ["credit analysis"], "soft_skills": [], "languages_combined": []}, "experience_required": {"duration": [], "field": []}}, {"job_id": "100003009049424", "location_code": "hk", "company": "Shanghai Commercial Bank Ltd", "job_title": "Assistant Manager / Manager, Compliance Review", "description": "Prepare and review loan documents for Commercial Facilities\nLiaise with legal counsels and marketing units to ensure proper and efficient operations of credit administration work\nReview loan operation procedures and streamlining workflow\nDegree holder or above in Finance or related disciplines\nMinimum 3 years\u2019 experience in loan documentation and credit administration\nExperience in commercial loans and syndicated loans will be an advantage\nIn-depth knowledge of loan documentation, procedures and relevant legal requirements\n\nCandidate with less experience will be considered as Deputy Manager, Documentation (Commercial)\n\n\u00a0\n\nThe above post requires proficiency in English, Cantonese and Putonghua.\n\nWe offer attractive remuneration package to the right candidates. Please send your full resume with expected salary to\u00a0The Human Resources Manager, Bank of Communications Co., Ltd., 10/F, Bank of\u00a0Communications\u00a0Tower,\u00a0231-235 Gloucester Road, Wan Chai,\u00a0Hong Kong, or fax to\u00a02838 9209, or e-mail to APPLY NOW.", "employment_types": ["Full Time", "Permanent"], "selling_points": ["Develop a risk-based compliance review program", "Conduct compliance reviews and on-site visits", "Prepare compliance review reports"], "locations": ["North Point"], "categories": ["Banking / Finance", "Analyst", "Others"], "post_time": "2022-01-15T03:50:26Z", "salary": {"currency": null, "max": null, "min": null, "period": "monthly", "term": null}, "salary_visible": false, "title_keywords": ["assistant manager", "manager"], "responsibilities": ["documentation", "operations", "review", "procedures", "liaise with", "administration"], "requirements": {"degrees": ["degree holder"], "majors": ["related disciplines", "finance"], "languages": ["cantonese", "putonghua", "english"], "language_level": ["proficiency"], "hard_skills": ["documentation"], "soft_skills": ["efficient"], "languages_combined": [{"language": "cantonese", "language_level": ["proficiency"]}, {"language": "putonghua", "language_level": ["proficiency"]}, {"language": "english", "language_level": ["proficiency"]}]}, "experience_required": {"duration": ["minimum 3 years"], "field": ["commercial", "administration"]}}, {"job_id": "100003009049170", "location_code": "hk", "company": "Shanghai Commercial Bank Ltd", "job_title": "Associate, Branch Opeations (Account Opening)", "description": "Provide one-stop services to line departments on manpower planning, talent acquisition, HR advisory and change management\nFormulate & implement HR policies & participate actively in various Human Resources events, functions and projects\nDegree holder or above in Human Resources Management or related disciplines\nMinimum 8 years\u2019 relevant experience in banking or financial sector, with supervisory or checker experience is preferred\nSelf-motivated, flexible, and strong in communication, analytical and project management skills\nProficient in written Chinese and English\n\nCandidate with less experience may be considered as Manager, Resources Planning\n\nThe above post requires proficiency in English, Cantonese and Putonghua.\n\nWe offer attractive remuneration package to the right candidates. Please send your full resume with expected salary to\u00a0The Human Resources Manager, Bank of Communications Co., Ltd., 10/F, Bank of\u00a0Communications\u00a0Tower,\u00a0231-235 Gloucester Road, Wan Chai,\u00a0Hong Kong, or fax to\u00a02838 9209, or e-mail to\u00a0APPLY NOW.", "employment_types": ["Full Time", "Permanent"], "selling_points": ["Support branch in operations enquiries", "Provide administrative support", "Perform AML termination of account"], "locations": ["Central"], "categories": ["Banking / Finance", "Retail Banking", "Others", "Order Processing & Operation / Settlement"], "post_time": "2022-01-15T03:50:09Z", "salary": {"currency": null, "max": null, "min": null, "period": "monthly", "term": null}, "salary_visible": false, "title_keywords": ["associate"], "responsibilities": ["management", "change management", "policies", "hr", "communication", "project management", "banking", "planning"], "requirements": {"degrees": ["degree holder"], "majors": ["related disciplines"], "languages": ["cantonese", "putonghua", "english", "chinese"], "language_level": ["proficiency", "proficient"], "hard_skills": ["project management"], "soft_skills": ["flexible", "project management skills", "self-motivated", "communication"], "languages_combined": [{"language": "cantonese", "language_level": ["proficiency"]}, {"language": "putonghua", "language_level": ["proficiency"]}, {"language": "english", "language_level": ["proficiency", "proficient"]}, {"language": "chinese", "language_level": ["proficient"]}]}, "experience_required": {"duration": ["minimum 8 years"], "field": ["supervisory", "financial", "relevant experience", "banking", "planning"]}}, {"job_id": "100003009052354", "location_code": "hk", "company": "Standard Chartered Bank (Hong Kong) Ltd", "job_title": "Analytics & Assurance Manager, CPBB BRM - (2100035407)", "description": "Career Level\nSenior\nQualification\nDegree\nYears of Experience\n5 years\nJob Type\nFull Time, Permanent\nJob Functions\nBanking / Finance, Treasury, Financial Services, Others", "employment_types": ["Full Time"], "selling_points": ["Degree holder or equivalent", "Solid working experience in Consumer", "Solid experience in Risk, Control"], "locations": ["Not Specified"], "categories": ["Banking / Finance", "Others", "Order Processing & Operation / Settlement", "Risk Management"], "post_time": "2022-01-17T02:50:30Z", "salary": {"currency": null, "max": null, "min": null, "period": "monthly", "term": null}, "salary_visible": false, "title_keywords": ["manager"], "responsibilities": ["banking"], "requirements": {"degrees": ["degree"], "majors": [], "languages": [], "language_level": [], "hard_skills": [], "soft_skills": [], "languages_combined": []}, "experience_required": {"duration": [], "field": []}}, {"job_id": "100003009049140", "location_code": "hk", "company": "Shanghai Commercial Bank Ltd", "job_title": "Relationship Officer, Commercial & Retail Lending", "description": "Responsibilities:\nExplore new business opportunities in areas of lending and trade financing\u00a0\u00a0\u00a0\u00a0\nConduct credit analyses and prepare credit proposals\nHandle account opening and provide sales support\nCross-sell general banking products\nAssist in bills / loans administration in Commercial Business\nProvide quality customer services\n\nRequirements:\n\nDegree holder in Banking & Finance or related disciplines\nMinimum 1 year of administrative experience is preferred\nFresh graduated in Business or related disciplines is also welcome\nFamiliar with current market environment in various industries\nSelf-motivated, target-driven and client-focused\nStrong negotiation, communication, interpersonal and analytical skills; fluency in written and spoken English and Chinese, preferably with proficiency in Putonghua\nProficient in MS Office applications including Chinese word processing\n\nAttractive remuneration package will be offered to the right candidates. Interested parties please click \"Apply Now\" to submit your full resume with current and expected salary to the Human Resources Division.\n\nPlease visit us at www.shacombank.com.hk for more information about our Bank.\n\nAll personal data collected will be used for recruitment related purposes strictly in accordance with the Bank's personal data policies, a copy of which will be provided immediately upon request by contacting our Personal Data Compliance Officer. Applicants who are not contacted within two months may consider their applications unsuccessful and the personal data collected from the applicants will be retained for no longer than two years from the date of rejection during which the applicants may be considered for other suitable positions within the Bank.", "employment_types": ["Full Time", "Permanent"], "selling_points": ["Explore new business in lending & trade finance", "Conduct credit analyses & prepare credit proposals", "Handle account opening and provide sales support"], "locations": ["Not Specified"], "categories": ["Banking / Finance", "Corporate Banking", "Loan", "Others"], "post_time": "2022-01-15T03:50:07Z", "salary": {"currency": null, "max": null, "min": null, "period": "monthly", "term": null}, "salary_visible": false, "title_keywords": ["officer"], "responsibilities": ["explore new business opportunities", "account opening", "quality", "customer services", "banking", "administration"], "requirements": {"degrees": ["degree holder"], "majors": ["related disciplines", "finance"], "languages": ["putonghua", "english", "chinese"], "language_level": ["fluency", "proficiency", "proficient"], "hard_skills": ["chinese word processing", "ms office", "analytical skills"], "soft_skills": ["self-motivated", "negotiation", "focused", "analytical skills", "communication", "interpersonal", "driven"], "languages_combined": [{"language": "putonghua", "language_level": ["proficiency", "fluency"]}, {"language": "english", "language_level": ["proficiency", "fluency"]}, {"language": "chinese", "language_level": ["proficiency", "fluency", "proficient"]}]}, "experience_required": {"duration": ["minimum 1 year"], "field": ["administrative"]}}, {"job_id": "100003009052571", "location_code": "hk", "company": "Mitsui & Co (HK) Ltd", "job_title": "Senior Officer (Finance Team)", "description": "We are now inviting candidate of high calibre to join us in the following capacity in our Finance Team.\n\nJob Duties:\n\nResponsible for import & export transaction processing and checking\nMonitor and follow up irregular bills such as standby LC, LC add confirmation, etc.\nProvide professional advice to our internal business units relating the LC matters\nPerform and support other duties as assigned including RPA, SAP input, Filing, etc.\nMonthly Bank Reconciliation\nPerform other daily Finance jobs and ad hoc projects including audit confirmation, etc.\n\nRequirements\n\n\nAt least 3-5 years of working experience in handling commercial area, especially the trade finance operations\nGood knowledge in ICC rules and its operation\nPossess Bank Foreign Trade experience is preferable\nBasic knowledge and concepts of accounting is preferable\nSAP Knowledge is essential\nGood command of Microsoft Office Tools (e.g. Word, Excel)\nGood communication and interpersonal skills and able to work under pressure\nGood command of English and Mandarin\nInterested parties please apply with your full resume stating present and expected salary.\n\n\n\nAll information will be kept confidential and used for recruitment purpose only. Although we endeavour to respond to every applicant, this may not always be possible so if you receive no response within 60 days, please consider your application for this specific vacancy to be unsuccessful.\n\n", "employment_types": ["Full Time", "Permanent"], "selling_points": [], "locations": ["Admiralty"], "categories": ["Accounting", "Others", "Banking / Finance", "Others", "Order Processing & Operation / Settlement"], "post_time": "2022-01-17T03:26:35Z", "salary": {"currency": null, "max": null, "min": null, "period": "monthly", "term": null}, "salary_visible": false, "title_keywords": ["senior officer"], "responsibilities": ["other duties", "monitor", "bank reconciliation", "checking", "audit", "ad hoc projects", "transaction processing"], "requirements": {"degrees": [], "majors": [], "languages": ["english", "mandarin"], "language_level": ["good command"], "hard_skills": ["excel", "basic", "sap", "microsoft office", "word"], "soft_skills": ["communication and interpersonal skills", "work under pressure"], "languages_combined": [{"language": "english", "language_level": ["good command"]}, {"language": "mandarin", "language_level": ["good command"]}]}, "experience_required": {"duration": ["at least 3-5 years"], "field": ["finance", "commercial"]}}, {"job_id": "100003009052075", "location_code": "hk", "company": "Standard Chartered Bank (Hong Kong) Ltd", "job_title": "Associate, Financing Solutions - (2100032450)", "description": "About Standard Chartered\u00a0\nWe are a leading international bank focused on helping people and companies prosper across Asia, Africa and the Middle East.\u00a0\n\nTo us, good performance is about much more than turning a profit.\u00a0 It's about showing how you embody our valued behaviours - do the right thing, better together and never settle - as well as our brand promise, Here for good.\n\nWe're committed to promoting equality in the workplace and creating an inclusive and flexible culture - one where everyone can realise their full potential and make a positive contribution to our organisation. This in turn helps us to provide better support to our broad client base.\nThe Role Responsibilities\n\nStrategy\n\nSupport and assist Regional Head of Financing Solutions and senior transactors in the team for executing the business strategy.\nAwareness and understanding of the Group\u2019s business strategy and model appropriate to the role\n\nBusiness\n\nTo support the origination of primary transactions by working closely with Senior Transactors, Relationship Managers and other product teams\nWith Senior Transactors\u2019 guidance to prepare pitchbooks, market research, pricing and return analysis, term sheet amendment and translation.\nExecution of financings:\ncollaboration with internal deal team members and external clients for the collection, consolidation and preliminary review of corporate documents and project information\npreparation of info memo, financial projections, offering circular, due diligence, invitation lists and underwriting application\ntranslation of necessary materials to ensure a smooth deal execution process\ncoordination and event management of bank meetings, site visits and road show\nfollow up potential lenders/investors and update the execution timetable\nhandling enquiries from potential lenders/investors\npreparation of banks status reporting during syndication stage\ncoordination of loan documentation with external & internal legal counsels and syndicate banks\ncoordination of internal approval and dispensation if appropriate\narrangement of signing ceremonies\nliaison with Loan & Agency and LDU for loan drawdown\nMaintenance of up-to-dated banks\u2019 contact list for the team\nMaintenance of transaction file in accordance with Syndications Product Programme and audit requirements\nTo assist the reporting preparation for the team including deal pipelines, operational risk monitoring, financial control monitoring, regulatory and industry association reports.\nTo report SCB-arranged transactions to financial presses for league table purposes\nTo prepare regular updates on generic syndication credentials / pitchbook and ad hoc presentation slides for senior management\nAwareness and understanding of the wider business, economic and market environment in which the Group operates\n\nPeople and Talent\n\nMaintain close contact with senior staff and learn from them. To support the origination of primary transactions by working closely with Senior Transactors, Relationship Managers and other product teams.\n\nOur Ideal Candidate\n\nManage Conduct\nRisk Management and Internal Controls\nManage People\nCompliance - Governance, Oversight and Control\nRisk Management \u2013 Market / Liquidity\nBusiness - Strategy and Model\nBusiness - Market Knowledge\nProduct - Securitisation\nProduct \u2013 Credit Derivatives\nProduct \u2013 Structured Derivatives and Swaps\nApply now to join the Bank for those with big career ambitions.\n", "employment_types": ["Full Time"], "selling_points": ["Support and assist Regional Head of Financing", "Support the origination of primary transactions", "Risk Management and Internal Controls"], "locations": ["Not Specified"], "categories": ["Banking / Finance", "Others", "Wealth Management"], "post_time": "2022-01-17T02:02:26Z", "salary": {"currency": null, "max": null, "min": null, "period": "monthly", "term": null}, "salary_visible": false, "title_keywords": ["associate"], "responsibilities": ["memo", "audit", "transactions", "maintain", "senior management", "due diligence", "control", "corporate documents", "ad hoc", "compliance", "teams", "reports", "report", "guidance", "management", "reporting", "review", "monitoring", "risk monitoring", "executing", "contact", "documentation", "maintenance", "analysis", "market research", "coordination"], "requirements": {"degrees": [], "majors": [], "languages": [], "language_level": [], "hard_skills": [], "soft_skills": ["structured"], "languages_combined": []}, "experience_required": {"duration": [], "field": []}}, {"job_id": "100003009051929", "location_code": "hk", "company": "Octopus Holdings Limited", "job_title": "Compliance Analyst, Financial Crime Compliance (1 year contract) (Ref: OCL/RMC/2021-218-219)", "description": "Job Responsibilities:\nDemonstrate commitment to regulatory compliance and high ethical standards\nPerform quality assurance review on risk and compliance related tasks\nEffectively discharge the responsibility of being the 2nd line of defense\nPerform AML function on a continuous basis, including the detection and reporting of suspicious transactions and activities\nEnsure the alerts generated from the system are fully and properly investigated\nIdentify and investigate the patterns, trends and abnormalities on transaction cases and customer data so as to meet the AML requirements\nConduct investigation and file the Suspicious Transaction Report (STR) appropriately on a timely basis\nRequirements:\nUniversity Degree holder preferably in Risk Management, Engineering, Computer Science or related disciplines\nRelevant work experience in payment service industry, consulting firms, or financial institutions is a plus\nProficiency in Excel (hands on experience on MS Excel functions e.g. Pivot tables, VLOOKUP etc. is an advantage) and other data analytics software\nSelf-starter with integrity\nAttentive to details with strong analytical skills especially on data filtering & data processing\nGood analytical and communication skills\nProactive with can-do attitude\nGood command of written and spoken English and Chinese\nPrefer immediately available or in short-notice period candidate", "employment_types": ["Contract"], "selling_points": ["Perform quality assurance review on risk", "University Degree holder", "Relevant work experience in payment service"], "locations": ["Kowloon Bay"], "categories": ["Banking / Finance", "Analyst", "Financial Services", "Others"], "post_time": "2022-01-17T01:32:42Z", "salary": {"currency": null, "max": null, "min": null, "period": "monthly", "term": null}, "salary_visible": false, "title_keywords": ["compliance analyst"], "responsibilities": ["reporting", "aml", "review", "compliance", "quality", "transactions", "investigation", "customer data", "report"], "requirements": {"degrees": ["university degree"], "majors": ["related disciplines", "risk management", "engineering", "computer science"], "languages": ["english", "chinese"], "language_level": ["good command"], "hard_skills": ["excel", "plus", "data analytics", "analytical skills", "ms excel", "vlookup", "processing"], "soft_skills": ["communication skills", "attentive to details", "can-do attitude", "integrity", "analytical skills", "hands on", "proactive"], "languages_combined": [{"language": "english", "language_level": ["good command"]}, {"language": "chinese", "language_level": ["good command"]}]}, "experience_required": {"duration": [], "field": ["consulting firms", "financial institutions", "service industry"]}}, {"job_id": "100003009054588", "location_code": "hk", "company": "Talent Axis Management Consulting Group Limited", "job_title": "Senior Securities Manager, Digital Banking Department", "description": "Our client, a well-established Bank in Hong Kong, is looking for a high-calibre candidate to join their Group:\n\nResponsibilities:\n\nExecute US market securities dealing orders\nHandle clients\u2019 phone enquires and provide feedback\nEnsure all dealing activities are complied with internal policy, guidelines and regulatory requirements\nAssist in the daily operations\nOvernight Shift is required\n\nRequirements:\n\nDegree holder\nMinimum 2 years\u2019 working experience in securities trading\nPasses in Hong Kong Securities & Investment Institute Licensing Examinations\nGood communication and interpersonal skills\n\nInterested candidates please forward your resume (in MS Word format)\u00a0together with current and expected salary details\u00a0by clicking the Apply Now button.", "employment_types": ["Full Time"], "selling_points": ["Bachelor degree holder", "2 years\u2019 relevant experience", "Securities Trading"], "locations": ["Not Specified"], "categories": ["Banking / Finance", "Others", "Information Technology (IT)", "Security"], "post_time": "2022-01-17T10:08:39Z", "salary": {"currency": null, "max": null, "min": null, "period": "monthly", "term": null}, "salary_visible": false, "title_keywords": ["manager"], "responsibilities": ["guidelines", "regulatory requirements", "daily operations"], "requirements": {"degrees": ["degree holder"], "majors": [], "languages": [], "language_level": [], "hard_skills": [], "soft_skills": ["communication and interpersonal skills"], "languages_combined": []}, "experience_required": {"duration": ["minimum 2 years"], "field": ["securities", "trading"]}}, {"job_id": "100003009049317", "location_code": "hk", "company": "Shanghai Commercial Bank Ltd", "job_title": "Associate, Syndication Loan", "description": "Responsibilities:\n\nHandle all loan transactions and coordinate with internal working partners to ensure smooth and timely processing\nAssist in conducting credit review, monitoring credit quality and reporting signs of deterioration\nPerform customer due diligence\nPrepare reports e.g. overdue, rescheduled and classified accounts for the management's review\nProvide administrative support to the department\nRequirements:\n\nDegree holder in Accounting, Finance or related disciplines\nMinimum 1 year's administrative/operations support experience, preferably in financial institutions\nSelf-motivated and attentive to details\nFluency in written and spoken English and Chinese, preferably with proficiency in Putonghua\nConversant with MS Word, Excel, Powerpoint and Chinese Word Processing\n\nAttractive remuneration package will be offered to the right candidates. Interested parties please click\u00a0\"Apply Now\"\u00a0to submit your full resume with current and expected salary to the\u00a0Human Resources Division.\n\nPlease visit us at\u00a0www.shacombank.com.hk\u00a0for more information about our Bank.\n\nAll personal data collected will be used for recruitment related purposes strictly in accordance with the Bank's personal data policies, a copy of which will be provided immediately upon request by contacting our Personal Data Compliance Officer. Applicants who are not contacted within two months may consider their applications unsuccessful and the personal data collected from the applicants will be retained for no longer than two years from the date of rejection during which the applicants may be considered for other suitable positions within the Bank.", "employment_types": ["Full Time", "Permanent"], "selling_points": ["Handle all loan transactions", "Conduct credit review & monitor credit quality", "Perform customer due diligence"], "locations": ["Central"], "categories": ["Banking / Finance", "Loan", "Others", "Order Processing & Operation / Settlement"], "post_time": "2022-01-15T03:50:17Z", "salary": {"currency": null, "max": null, "min": null, "period": "monthly", "term": null}, "salary_visible": false, "title_keywords": ["associate"], "responsibilities": ["reporting", "management", "monitoring", "quality", "review", "coordinate with", "transactions", "customer due diligence", "prepare reports", "provide administrative support"], "requirements": {"degrees": ["degree holder"], "majors": ["related disciplines", "finance", "accounting"], "languages": ["putonghua", "english", "chinese"], "language_level": ["fluency", "proficiency"], "hard_skills": ["excel", "chinese word processing", "powerpoint", "ms word"], "soft_skills": ["self-motivated", "attentive to details"], "languages_combined": [{"language": "putonghua", "language_level": ["proficiency", "fluency"]}, {"language": "english", "language_level": ["proficiency", "fluency"]}, {"language": "chinese", "language_level": ["proficiency", "fluency"]}]}, "experience_required": {"duration": ["minimum 1 year"], "field": ["financial institutions", "administrative"]}}, {"job_id": "100003009049982", "location_code": "hk", "company": "The Bank of East Asia, Limited", "job_title": "Risk Officer (Credit Assessment)", "description": "Risk Officer (Credit Assessment) (Job ID: 3294)\n\nResponsibilities\n\nTo be a team member of Credit Risk Management Department\nTo perform independent credit assessment and make recommendations according to credit guidelines and policies\nTo assist in the formulation and review of credit policies and guidelines\nTo support daily administration and ad hoc projects as required\n\nRequirements\n\nUniversity graduate in Risk Management, Finance, Business, Economics or related discipline\nKnowledge of financial analysis techniques and 1-2 years of working experience in the banking industry or financial institution will be an advantage\nGood communication, presentation, analytical and time management skills\nA good team player, responsible with positive working attitude\nGood command of both spoken and written English and Chinese\nProficient with Microsoft Office application including Word and Excel\n\nPlease apply online via the BEA Careers website at https://careers.hkbea.com/psp/hcmprd/EMPLOYEE/HRMS/c/HRS_HRAM.HRS_APP_SCHJOB.GBL?Page=HRS_APP_JBPST&Action=U&FOCUS=Applicant&SiteId=1&JobOpeningId=3294&PostingSeq=1 or by clicking the Apply Now button. Kindly note that if you are a new user, you have to first create your User Profile before you can apply.\n\nPersonal data provided by job applicants will be used for recruitment purposes only and will be treated in accordance with the Bank's Personal Data Policy, which is available upon request. Applicants who are not invited for interviews within six weeks may consider their applications unsuccessful and the personal data collected will be destroyed after six months.", "employment_types": ["Full Time", "Permanent"], "selling_points": ["Perform independent credit assessment", "Formulate & review credit policies and guidelines", "University graduates with 1-2 yrs' exp in banking"], "locations": ["Kwun Tong"], "categories": ["Banking / Finance", "Credit Analysis / Approval", "Financial Services", "Others"], "post_time": "2022-01-15T03:50:46Z", "salary": {"currency": null, "max": null, "min": null, "period": null, "term": null}, "salary_visible": false, "title_keywords": ["officer"], "responsibilities": ["make recommendations", "management", "guidelines", "policies", "review", "ad hoc projects", "administration"], "requirements": {"degrees": ["university graduate"], "majors": ["finance", "risk management", "business", "economics"], "languages": ["english", "chinese"], "language_level": ["good command"], "hard_skills": ["excel", "microsoft office", "word", "financial analysis", "c"], "soft_skills": ["good team player", "responsible", "time management skills", "communication", "positive working attitude", "presentation"], "languages_combined": [{"language": "english", "language_level": ["good command"]}, {"language": "chinese", "language_level": ["good command"]}]}, "experience_required": {"duration": ["1-2 years"], "field": ["banking industry", "financial"]}}, {"job_id": "100003009049161", "location_code": "hk", "company": "Shanghai Commercial Bank Ltd", "job_title": "Associate, Branch Operations (Safety Box)", "description": "Responsibilities:\n\nResponsible for handling fixed deposits, remittance and safety box works\nPrepare reports for branch operations business\nSupport branch in operations enquiries\nProvide administrative support e.g. documents filing and record keeping\nPerform counter service if required\nTake up ad hoc projects as assigned\n\nRequirements:\n\nPost-secondary educated or above\nMinimum 1 year of branch operations experience preferred\nGood communication and interpersonal skills; fluency in written and spoken English and Chinese, preferably with proficiency in Putonghua\nAbility to work independently and under pressure\nGood PC knowledge, including MS Word, Excel and Chinese word processing\nWork Location: Tsuen Wan\n\nAttractive remuneration package will be offered to the right candidates. Interested parties please click\u00a0\"Apply Now\"\u00a0to submit your full resume with current and expected salary to the\u00a0Human Resources Division.\n\nPlease visit us at\u00a0www.shacombank.com.hk\u00a0for more information about our Bank.\n\nAll personal data collected will be used for recruitment related purposes strictly in accordance with the Bank's personal data policies, a copy of which will be provided immediately upon request by contacting our Personal Data Compliance Officer. Applicants who are not contacted within two months may consider their applications unsuccessful and the personal data collected from the applicants will be retained for no longer than two years from the date of rejection during which the applicants may be considered for other suitable positions within the Bank.", "employment_types": ["Full Time", "Permanent"], "selling_points": ["Prepare reports for branch operations business", "Support branch in operations enquiries", "Perform counter service if required"], "locations": ["Tsuen Wan Area"], "categories": ["Banking / Finance", "Financial Services", "Others", "Order Processing & Operation / Settlement"], "post_time": "2022-01-15T03:50:09Z", "salary": {"currency": null, "max": null, "min": null, "period": "monthly", "term": null}, "salary_visible": false, "title_keywords": ["operations", "associate"], "responsibilities": ["documents filing", "operations", "ad hoc projects", "prepare reports", "provide administrative support"], "requirements": {"degrees": [], "majors": [], "languages": ["putonghua", "english", "chinese"], "language_level": ["fluency", "proficiency", "good"], "hard_skills": ["excel", "pc knowledge", "chinese word processing", "ms word"], "soft_skills": ["work independently", "communication and interpersonal skills", "under pressure"], "languages_combined": [{"language": "putonghua", "language_level": ["proficiency", "fluency"]}, {"language": "english", "language_level": ["proficiency", "fluency"]}, {"language": "chinese", "language_level": ["proficiency", "fluency", "good"]}]}, "experience_required": {"duration": ["minimum 1 year"], "field": []}}, {"job_id": "100003009041641", "location_code": "hk", "company": "Bank of China (Hong Kong) Limited", "job_title": "\u5ba2\u6236\u670d\u52d9\u4e3b\u4efb (Customer Service Officer)", "description": "\u5d17\u4f4d\u8077\u8cac\n\nDeliver quality customer services through counter transactions\n\u6253\u9020\u5206\u884c\u4e00\u7ad9\u5f0f\u5c08\u696d\u91d1\u878d\u7406\u8ca1\u670d\u52d9\nSupport back-end branch operations\n\u8655\u7406\u5ba2\u6236\u6bcf\u65e5\u6ac3\u53f0\u4ea4\u6613(\u5305\u62ec\u73fe\u91d1\u6536\u4ed8\u3001\u5165\u7968\u3001\u8f49\u5e33\u3001\u5b9a\u671f\u3001\u532f\u6b3e\u7b49\u7684\u5de5\u4f5c)\u3001\u5ba2\u6236\u67e5\u8a62\u53ca\u5167\u90e8\u6587\u66f8\u5de5\u4f5c\nCross-sell retail banking products\n\u92b7\u552e\u53ca\u8f49\u4ecb\u5de5\u4f5c\n\u5d17\u4f4d\u8981\u6c42\n\nSecondary School graduate or above\n\u4e2d\u5b78\u6587\u6191\u6216\u4ee5\u4e0a\u7a0b\u5ea6\nStrong sales and service orientation with outgoing personality and good communication skills\n\u5177\u826f\u597d\u7684\u6e9d\u901a\u6280\u5de7\u53ca\u5ba2\u6236\u670d\u52d9\u610f\u8b58\nProficiency in English and Cantonese as well as fluency in Putonghua\n\u5177\u826f\u597d\u7684\u4e2d\u3001\u82f1\u6587\u95b1\u8b80\u3001\u66f8\u5beb\u53ca\u666e\u901a\u8a71\u8868\u9054\u80fd\u529b", "employment_types": ["Full Time"], "selling_points": ["\u6253\u9020\u5206\u884c\u4e00\u7ad9\u5f0f\u5c08\u696d\u91d1\u878d\u7406\u8ca1\u670d\u52d9", "\u8655\u7406\u5ba2\u6236\u6bcf\u65e5\u6ac3\u53f0\u4ea4\u6613(\u5305\u62ec\u73fe\u91d1\u6536\u4ed8\u3001\u5165\u7968\u3001\u8f49\u5e33\u3001\u5b9a\u671f\u3001\u532f\u6b3e\u7b49\u7684\u5de5\u4f5c)", "\u4e2d\u5b78\u6587\u6191\u6216\u4ee5\u4e0a\u7a0b\u5ea6"], "locations": ["Not Specified"], "categories": ["Banking / Finance", "Financial Services", "Others", "Sales, CS & Business Devpt", "Customer Service - Supervisor / Officer"], "post_time": "2022-01-12T04:08:59Z", "salary": {"currency": null, "max": null, "min": null, "period": "monthly", "term": null}, "salary_visible": false, "title_keywords": ["\u5ba2\u6236\u670d\u52d9\u4e3b\u4efb", "customer service officer"], "responsibilities": ["operations", "quality", "transactions", "customer services", "communication", "banking"], "requirements": {"degrees": [], "majors": [], "languages": ["cantonese", "putonghua", "english"], "language_level": ["fluency", "proficiency"], "hard_skills": [], "soft_skills": ["outgoing personality", "communication skills"], "languages_combined": [{"language": "cantonese", "language_level": ["proficiency"]}, {"language": "putonghua", "language_level": ["fluency", "proficiency"]}, {"language": "english", "language_level": ["fluency", "proficiency"]}]}, "experience_required": {"duration": [], "field": []}}, {"job_id": "100003009049217", "location_code": "hk", "company": "Shanghai Commercial Bank Ltd", "job_title": "Data Analyst - Assistant Manager/ Officer / Associate", "description": "Responsibilities:\n\nAnalyze structured and unstructured data in order to understand customer behavior, particularly for the Small Medium Enterprise and Retail customer segments.\nOffer assistance on developing analytics reports and visualization dashboard for business monitoring and delivering insights.\nSupport data-led experiments to continually refine our customer-led value proposition.\nSupport data maintenance and data management of a new implemented customer data platform and increase our data quality and accuracy of the data sources.\n\nRequirements\n\nDegree holder in Computer Science, Data Science, Mathematics, Statistics, IT or relevant disciplines.\n3-5 years experiences in data science or machine learning.\nGood knowledge on database and statistical software (such as SAS, Python) is preferred.\nSelf-motivated, presentable and analytical.\nTeam player and strong communication skill.\nGood command of both spoken and written English and Chinese. Mandarin is an advantage.\n\nAttractive remuneration package will be offered to the right candidates. Interested parties please click\u00a0\"Apply Now\"\u00a0to submit your full resume with current and expected salary to the\u00a0Human Resources Division.\n\nPlease visit us at\u00a0www.shacombank.com.hk\u00a0for more information about our Bank.\n\nAll personal data collected will be used for recruitment related purposes strictly in accordance with the Bank's personal data policies, a copy of which will be provided immediately upon request by contacting our Personal Data Compliance Officer. Applicants who are not contacted within two months may consider their applications unsuccessful and the personal data collected from the applicants will be retained for no longer than two years from the date of rejection during which the applicants may be considered for other suitable positions within the Bank.", "employment_types": ["Full Time", "Permanent"], "selling_points": ["Offer assistance on developing analytics reports", "Support data maintenance and data management", "Analyze structured and unstructured data"], "locations": ["Kwai Hing"], "categories": ["Banking / Finance", "Analyst", "Financial Services", "Others"], "post_time": "2022-01-15T03:50:12Z", "salary": {"currency": null, "max": null, "min": null, "period": "monthly", "term": null}, "salary_visible": false, "title_keywords": ["assistant manager", "associate", "data analyst", "officer"], "responsibilities": ["management", "visualization", "maintenance", "data", "monitoring", "quality", "developing", "reports", "customer data"], "requirements": {"degrees": ["degree holder"], "majors": ["data science", "mathematics", "statistics", "it", "computer science"], "languages": ["english", "chinese", "mandarin"], "language_level": ["advantage", "good command"], "hard_skills": ["python", "sas"], "soft_skills": ["self-motivated", "communication skill", "presentable", "learning", "team player"], "languages_combined": [{"language": "english", "language_level": ["good command"]}, {"language": "chinese", "language_level": ["good command"]}, {"language": "mandarin", "language_level": ["advantage"]}]}, "experience_required": {"duration": ["3-5 years"], "field": []}}, {"job_id": "100003009050674", "location_code": "hk", "company": "Dah Sing Financial Group", "job_title": "OK Finance - Customer Services Representative", "description": "Reporting to the Branch Manager, you will be responsible for providing quality customer services to the customers.\n\nResponsibilities\nGreet and welcome walk-in & phone-in customers according to the established service standard\nHandle customer enquiries and requests, and always seek advice from supervisor for proper handling of customer complaint as and when necessary\nPerform loan processing and administrative duties\nAssist in payment transaction such as disbursing loan proceeds and handle repayment over the counter\nTo meet the challenge, you should have the following qualifications and attributes:\nSecondary education\nExperience in Consumer Finance/banking industry is preferable\nGood interpersonal and communication skills\nGood knowledge of MS Office\nWith initiative, pleasant personality and willing to learn\nGood command of written and spoken English and Chinese\nPlease note that only shortlisted candidates will be notified.", "employment_types": ["Full Time", "Permanent"], "selling_points": ["Responsible for providing quality customer service", "Secondary education", "Experience in Consumer Finance/banking industry"], "locations": ["Not Specified"], "categories": ["Banking / Finance", "Loan", "Others", "Sales, CS & Business Devpt", "Customer Service - Supervisor / Officer"], "post_time": "2022-01-14T11:09:56Z", "salary": {"currency": null, "max": null, "min": null, "period": "monthly", "term": null}, "salary_visible": false, "title_keywords": ["customer services representative"], "responsibilities": ["reporting", "handle customer enquiries", "service standard", "quality", "customer services", "communication", "payment", "administrative duties", "banking"], "requirements": {"degrees": ["secondary education"], "majors": [], "languages": ["english", "chinese"], "language_level": ["good command"], "hard_skills": ["processing", "ms office"], "soft_skills": ["communication skills", "responsible", "willing to learn", "pleasant", "interpersonal", "initiative"], "languages_combined": [{"language": "english", "language_level": ["good command"]}, {"language": "chinese", "language_level": ["good command"]}]}, "experience_required": {"duration": [], "field": ["finance", "banking industry"]}}, {"job_id": "100003009054235", "location_code": "hk", "company": "SinoPac Securities (Asia) Limited", "job_title": "Sales, Fixed Income Division", "description": "RESPONSIBILITIES\nProviding support to sales team and help execute trades\nExisting client network of fixed income trader/portfolio managers across the buy side segment\nPreparing presentations, pitches, proposals, client materials and the supporting analysis\nAbility to create, develop and execute upon regional sales strategies\n\n\u00a0REQUIREMENTS\n\nUniversity graduate or above\nGood knowledge of Fixed Income Products\nStrong client network in China/HK/Taiwan preferred\nProficiency in MS Office applications, including MS Word & Excel, VBA, PowerPoint and Chinese word processing\u00a0\u00a0\u00a0\u00a0\nBe proactive, aggressive and a team player with good integrity\nProficient in both written and spoken English and Mandarin\nA competitive remuneration package will be offered. Please send your detailed resume, including present and expected salary as well as availability date, to Human Resources Department, SinoPac Securities (Asia) Limited, 7/F., Lee Garden Three, 1 Sunning Road, Causeway Bay, Hong Kong or by clicking \u201cApply Now\u201d.\u00a0\n\n\n\nAll personal data collected will be used for recruitment purpose only and will be kept strictly confidential. Only short-listed candidates will be notified.", "employment_types": ["Full Time", "Permanent"], "selling_points": ["5-days work", "University graduate or above", "Good knowledge of Fixed Income Products"], "locations": ["Causeway Bay"], "categories": ["Banking / Finance", "Financial Services", "Others"], "post_time": "2022-01-17T08:52:50Z", "salary": {"currency": null, "max": null, "min": null, "period": "monthly", "term": null}, "salary_visible": false, "title_keywords": ["sales"], "responsibilities": ["providing support to sales team", "analysis", "presentations", "develop"], "requirements": {"degrees": ["university graduate or above"], "majors": [], "languages": ["english", "chinese", "mandarin"], "language_level": ["proficiency", "proficient"], "hard_skills": ["excel", "vba", "chinese word processing", "powerpoint", "ms office", "ms word"], "soft_skills": ["team player", "proactive", "integrity", "detailed"], "languages_combined": [{"language": "english", "language_level": ["proficient"]}, {"language": "chinese", "language_level": ["proficiency"]}, {"language": "mandarin", "language_level": ["proficient"]}]}, "experience_required": {"duration": [], "field": []}}, {"job_id": "100003009050168", "location_code": "hk", "company": "Nanyang Commercial Bank", "job_title": "Graduate Recruitment 2022", "description": "Job Scopes\n\nFintech\nCorporate Banking\nPersonal Banking\nRisk Management\n\nRequirement\n\nFresh graduate with Bachelor Degree (Second Class Honors or above) or Master Degree\nDetermined to be a great banker with strong passion to grow and excel\nProactive, responsible, excellent communication and analytical skills\n\nJob Highlight\n\nYou will be placed to designated department that best suit your personal strengths and career goal, which also enable you to gain valuable experience and equip with sound knowledge in particular business area.\n\nJob Descriptions\n\nFintech (Ref:FT-GP-NCB)\n\nParticipate in fintech projects from project initiation to post-implementation;\nAssist in conducting analysis and researches on latest technology and market practice;\nWork closely with internal stakeholders and external vendors on project planning and execution.\n\nRequirement: Major in Business Administration, e-Commerce, IT, Computer Science, MIS, Data Science or other related streams.\n\nCorporate Banking (Ref:CB-GP-NCB)\n\nTake care of the commercial accounts of corporate clients in Hong Kong and Southern China;\nUnderstand their financial needs and provide comprehensive financial strategies and trade finance solutions to help them achieving their long-term business goals;\nEvaluate their needs, analyze their borrowing capacity, develop customized credit proposals and review their commercial loans portfolio.\n\nRequirement: Major in Business Administration, Accounting, Economics, Finance or other related streams.\n\nPersonal Banking (Ref:PB-GP-NCB)\n\nProvide superior and professional customer services and develop long-term relationships with our retail banking customers;\nExplore and identify their financial needs, provide solutions and introduce retail banking, insurance products and services to fulfil such needs.\nSupport in monitoring various account transactions, verify relevant documents and procedures to ensure the branch business is operated strictly according to all the legal and compliance requirements.\n\nRequirement: Major in Business Administration, Accounting, Economics, Finance or other related streams.\n\nRisk Management (Ref:RM-GP-NCB)\n\nAssist in conducting risk analysis for evaluating and identifying credit portfolio risk and market risk of the Bank.\n\nRequirement: Major in Business Administration, Risk Management, Economics, Finance or other related streams.\n\n\n\nWe are delighted to invite you to create the new chapter with us. Act now and start the most meaningful and fulfilling career journey here!\n\nPlease submit your full resume via email, indicating your University academic and open examination results (including HKDSE) as well as your career preference in both the email subject column and resume.\n\nWe are an Equal Opportunity Employer. Data collected would be used for recruitment purposes only. Applicants who do not hear from us within 8 weeks may consider their applications unsuccessful and their data will be destroyed within 12 months of receipt.\u00a0", "employment_types": ["Full Time"], "selling_points": ["Graduate Recruitment", "A degree holder with a second honor or above", "high initiative team player"], "locations": ["Not Specified"], "categories": ["Banking / Finance", "Others", "Others", "Student / Fresh Graduate / No Experience"], "post_time": "2022-01-15T03:50:54Z", "salary": {"currency": null, "max": null, "min": null, "period": "monthly", "term": null}, "salary_visible": false, "title_keywords": [], "responsibilities": ["business goals", "data", "transactions", "administration", "compliance", "implementation", "develop", "customer services", "banking", "management", "review", "monitoring", "procedures", "provide solutions", "project planning", "analysis", "evaluate", "recruitment", "risk analysis", "insurance"], "requirements": {"degrees": ["degree", "bachelor", "master degree", "fresh graduate"], "majors": [], "languages": [], "language_level": [], "hard_skills": ["excel", "goal", "analytical skills"], "soft_skills": ["determined", "responsible", "analytical skills", "communication", "proactive"], "languages_combined": []}, "experience_required": {"duration": [], "field": ["business"]}}, {"job_id": "100003009049308", "location_code": "hk", "company": "Shanghai Commercial Bank Ltd", "job_title": "Associate, Credit Card Marketing", "description": "Responsibilities:\n\nAssist in developing and implementing marketing programs with the objectives defined.\nMonitor and review the program effectiveness and suggest rooms for improvement.\nWork with advertising agency and ensure the deliverables are up to the Bank\u2019s standard.\nKeep good working relationship with the co-branded card partners and ensure healthy growth of the card portfolios.\nCoordinate with internal department for launch of card promotion programs.\nParticipate the credit card off-site promotion that is occasionally required to work on weekend or public holiday.\nProvide administrative support to the team.\nCross support to the merchant services team if required.\n\nRequirements:\n\nDegree holder or above preferably in banking and finance or business administration.\nAt least 1 year\u2019s relevant experience in commercial field, sales and marketing, business administration, preferably have relevant banking industry experience.\nExperience in working with advertising agent and merchant partners.\nProficient in Cantonese and English.\nSolid communication and interpersonal skills.\nWork Location: Kwai Hing\n\nCandidates with more experience would be considered as Officer, Credit Card Marketing\n\nAttractive remuneration package will be offered to the right candidates. Interested parties please click\u00a0\"Apply Now\"\u00a0to submit your full resume with current and expected salary to the\u00a0Human Resources Division.\n\nPlease visit us at\u00a0www.shacombank.com.hk\u00a0for more information about our Bank.\n\nAll personal data collected will be used for recruitment related purposes strictly in accordance with the Bank's personal data policies, a copy of which will be provided immediately upon request by contacting our Personal Data Compliance Officer. Applicants who are not contacted within two months may consider their applications unsuccessful and the personal data collected from the applicants will be retained for no longer than two years from the date of rejection during which the applicants may be considered for other suitable positions within the Bank.", "employment_types": ["Full Time", "Permanent"], "selling_points": ["Monitor and review the program effectiveness", "Work with advertising agency", "Participate the credit card off-site promotion"], "locations": ["Kwai Hing"], "categories": ["Banking / Finance", "Financial Services", "Others"], "post_time": "2022-01-15T03:50:17Z", "salary": {"currency": null, "max": null, "min": null, "period": "monthly", "term": null}, "salary_visible": false, "title_keywords": ["associate"], "responsibilities": ["advertising", "review", "monitor", "developing", "coordinate with", "provide administrative support"], "requirements": {"degrees": ["degree holder"], "majors": ["finance", "business administration"], "languages": ["cantonese", "english"], "language_level": ["proficient"], "hard_skills": [], "soft_skills": ["communication and interpersonal skills"], "languages_combined": [{"language": "cantonese", "language_level": ["proficient"]}, {"language": "english", "language_level": ["proficient"]}]}, "experience_required": {"duration": ["at least 1 year"], "field": ["banking industry", "business administration", "advertising", "commercial", "marketing", "relevant experience"]}}, {"job_id": "100003009049227", "location_code": "hk", "company": "Shanghai Commercial Bank Ltd", "job_title": "Officer / Associate, Life Insurance (Bancassurance)", "description": "About Standard Chartered\u00a0\nWe are a leading international bank focused on helping people and companies prosper across Asia, Africa and the Middle East.\u00a0\n\nTo us, good performance is about much more than turning a profit.\u00a0 It's about showing how you embody our valued behaviours - do the right thing, better together and never settle - as well as our brand promise, Here for good.\n\nWe're committed to promoting equality in the workplace and creating an inclusive and flexible culture - one where everyone can realise their full potential and make a positive contribution to our organisation. This in turn helps us to provide better support to our broad client base.\n\n\nThe Role Responsibilities\nConducts all aspects of market research activities to support the commercial team.\nAnalyses deal economics through robust financial modelling.\nAssists the team in pricing a deal/transaction to enhance deal selection and ensure alignment to AF strategy.\nPerforms robust risk analysis and ensuring adherence to the relevant bank polices/processes and Aviation Finance underwriting standards.\nSupports the commercial team in related marketing activities, preparation of proposals etc.\nSupports the commercial team in the origination of new business in franchise markets.\nSupport the Aviation Finance team in collaborating with CCIB teams to identify and target transactions and pursue cross-sell opportunities in line with CCIB\u2019s business strategy.\nSupport the Aviation Finance team in organising and driving business success through improvement in client penetration and profitability in conjunction coverage partners.\n\nBusiness\n\nEffectively use SCB\u2019s industry expertise, knowledge and professional network for ideation, generating leads for new deals and assessment of opportunities\nClient interface at senior management levels and ensuring that the engagement, services and quality of work meets the highest industry standards\nStructuring of transactions including cross border deals, to best meet clients\u2019 needs covering solutions ranging from senior and/ or mezzanine debt/bonds and/ or operating and finance lease options, financing across different parts of the capital structure\nPrepare high quality pitching and marketing materials for client presentations.\nCollaborate with internal stakeholders including client coverage, other product teams in financial markets,\u00a0 transaction banking and risk.\nTo ensure that new and existing business is consistent with Group policies, meets applicable credit risk criteria, internal approval procedures and provides acceptable risk adjusted return for the Bank, all as defined in the Underwriting Standards, globally and locally, including reputational risk.\nSupport and oversee robust deal selection through transaction analysis and pricing, conflict resolution and risk management to ensure the business is consistent with the strategy and risk appetite of the Bank\n\nOur Ideal Candidate\n\n2-3\u00a0years of experience in banking industry/ financial institution\u00a0\nBachelor's Degree or above in related discipline\nExperienced in credit analysis, ideally in aviation\nEffective communication skills & ability towork under pressure\nHKMA License as requested\nMandarin speaking is a must with good command in English\n\nApply now to join the Bank for those with big career ambitions.\u00a0", "employment_types": ["Full Time", "Permanent"], "selling_points": ["Conduct product due diligence", "Handling system and regulatory projects", "Review and implement sales & promotional programs"], "locations": ["Tsim Sha Tsui"], "categories": ["Banking / Finance", "Others", "Insurance", "Others"], "post_time": "2022-01-15T03:50:13Z", "salary": {"currency": null, "max": null, "min": null, "period": "monthly", "term": null}, "salary_visible": false, "title_keywords": ["officer", "associate"], "responsibilities": ["collaborate with", "management", "policies", "analysis", "teams", "market research", "transactions", "quality", "presentations", "procedures", "resolution", "client base", "communication", "finance team", "risk analysis", "banking", "marketing materials", "senior management"], "requirements": {"degrees": ["degree or above", "bachelor"], "majors": [], "languages": ["english", "mandarin"], "language_level": ["good command"], "hard_skills": ["hkma", "analysis", "presentations", "make", "credit analysis"], "soft_skills": ["flexible", "communication skills", "under pressure", "focused", "robust", "committed", "organisation", "positive", "ideal"], "languages_combined": [{"language": "english", "language_level": ["good command"]}, {"language": "mandarin", "language_level": ["good command"]}]}, "experience_required": {"duration": ["2-3 years"], "field": ["banking industry", "financial"]}}, {"job_id": "100003009049264", "location_code": "hk", "company": "Shanghai Commercial Bank Ltd", "job_title": "Associate - Credit Card Operations", "description": "Responsibilities:\n\nProcess ATM / credit card / membership card applications including data input, documents mapping, filing and follow up with customers for outstanding documents\nDeliver timely and quality service to customers and handle phone enquiries from customers and branches\nProvide administrative support to the department where necessary\n\nRequirements:\n\nDiploma holder or above in Business or related disciplines\nMinimum 1 year of relevant experience\nDetail-oriented, with strong customer service and good telephone manner and communication skills\nGood command of both spoken and written English and Chinese, proficient in Putonghua is an advantage\nGood PC knowledge, including MS Word, Excel and Chinese word processing\nWorking location: Kwai Hing\n\nAttractive remuneration package will be offered to the right candidates. Interested parties please click \"Apply Now\" to submit your full resume with current and expected salary to the Human Resources Division.\n\nPlease visit us at www.shacombank.com.hk for more information about our Bank.\n\nAll personal data collected will be used for recruitment related purposes strictly in accordance with the Bank's personal data policies, a copy of which will be provided immediately upon request by contacting our Personal Data Compliance Officer. Applicants who are not contacted within two months may consider their applications unsuccessful and the personal data collected from the applicants will be retained for no longer than two years from the date of rejection during which the applicants may be considered for other suitable positions within the Bank.", "employment_types": ["Full Time", "Permanent"], "selling_points": ["Process ATM / credit card applications", "Handle phone enquiries from customers and branches", "Provide administrative support to the department"], "locations": ["Kwai Hing"], "categories": ["Banking / Finance", "Financial Services", "Others", "Order Processing & Operation / Settlement"], "post_time": "2022-01-15T03:50:16Z", "salary": {"currency": null, "max": null, "min": null, "period": "monthly", "term": null}, "salary_visible": false, "title_keywords": ["operations", "associate"], "responsibilities": ["provide administrative support", "quality", "data input"], "requirements": {"degrees": ["diploma holder"], "majors": ["related disciplines", "business"], "languages": ["putonghua", "english", "chinese"], "language_level": ["advantage", "good", "good command", "proficient"], "hard_skills": ["excel", "pc knowledge", "chinese word processing", "ms word"], "soft_skills": ["communication skills", "customer service", "telephone manner", "detail-oriented"], "languages_combined": [{"language": "putonghua", "language_level": ["proficient", "advantage", "good", "good command"]}, {"language": "english", "language_level": ["advantage", "good", "good command"]}, {"language": "chinese", "language_level": ["advantage", "good", "good", "good command"]}]}, "experience_required": {"duration": ["minimum 1 year"], "field": ["relevant experience"]}}, {"job_id": "100003009052230", "location_code": "hk", "company": "ORIENTAL HUMAN RESOURCES LIMITED", "job_title": "Senior Editor / Reporter - Local News /  Financial News", "description": "University or College graduate\n5 years or above experience in Press or Media industry\nStrong sense on local news / financial news\nGood command of Chinese and English\nKnowledge of Chinese word processing\n(Less experience or fresh graduates\u00a0will be considered as Junior Position)\n\n\n\nApplication Method\n\nWe offer free shuttle bus, free parking and fringe benefits including medical scheme, discretionary bonus and public holidays\u00a0to the right candidate. Interested parties, please send full resume with expected salary to ORIENTAL HUMAN RESOURCES LIMITED\u00a0by\u00a0clicking \"Apply now\" ;\u00a0or fax to 3600 1900 ( Please quote reference on the application letter )\n\n\nPersonal Information Collection Statement\n\nPersonal data collected will be treated in accordance with our Personal Data Policy and handled in strict confidence by authorized personnel for recruitment related purpose only.\u00a0 \u00a0 \u00a0\n\u00a0 \u00a0 \u00a0 \u00a0 \u00a0 \u00a0\n\n\u00a0 \u00a0 \u00a0 \u00a0 \u00a0 \u00a0 \u00a0 \u00a0 \u00a0 \u00a0 \u00a0 \u00a0 \u00a0 \u00a0 \u00a0 \u00a0 \u00a0 \u00a0 \u00a0 \u00a0 \u00a0 \u00a0 \u00a0 \u00a0 \u00a0 \u00a0 \u00a0\u00a0on.cc\n\n", "employment_types": ["Full Time"], "selling_points": [], "locations": ["Tai Po Area"], "categories": ["Media & Advertising", "Others", "Banking / Finance", "Others", "Editorial / Journalism"], "post_time": "2022-01-17T02:31:17Z", "salary": {"currency": null, "max": null, "min": null, "period": "monthly", "term": null}, "salary_visible": false, "title_keywords": ["reporter", "senior editor"], "responsibilities": [], "requirements": {"degrees": [], "majors": [], "languages": ["english", "chinese"], "language_level": ["good command"], "hard_skills": ["chinese word processing"], "soft_skills": [], "languages_combined": [{"language": "english", "language_level": ["good command"]}, {"language": "chinese", "language_level": ["good command"]}]}, "experience_required": {"duration": ["5 years"], "field": ["media"]}}, {"job_id": "100003009048799", "location_code": "hk", "company": "Bank of China (Hong Kong) Limited", "job_title": "Risk Manager/Senior Risk Manager(Integrated Risk Management Division)", "description": "Responsibilities:\n\nTo assist drafting the Group\u2019s integrated risk management report;\nTo assist drafting risk management policies;\nTo assist drafting the Group\u2019s risk management strategies and annual work plan;\nTo coordinate the consolidation of risk management information from various risk management units;\nTo coordinate implementing risk management projects;\nTo keep track of changes in macro economies, regulatory requirements and business development, analyze its impact on risk management, and propose risk management measures accordingly;\nTo assist assessing effectiveness of single type risk management and identifying management loopholes;\nTo assist establishing new types of risks, crossover risks, risks infection, risks aggregation management mechanism; coordinating crossover risks management; strengthening risks infection monitoring.\n\nRequirements:\n\nQualifications of degree or above, major in Economics, Finance, Accounting, Business & Administration or relevant professions;\nWorking experience of 5 years or above in bank with at least 2 years in risk management, such as credit risk, market risk, interest risk;\nExcellent analytical, problem solving, communication and language skills;\nFamiliar with MS Office software, such as MS Word, Excel and PowerPoint;\nExcellent Chinese and English.\n\nWe offer competitive remuneration package and comprehensive fringe benefits including medical and life insurance, and different types of allowances to the right candidate. Interested parties, please submit your application online. For details, please visit our website\u00a0http://www.bochk.com\n\n[via APPLY NOW]\u00a0\u00a0\n\nData collected would be used for recruitment purposes only. It might also be disclosed to our subsidiaries or Associated Companies to process the information for appointment. Applicants who do not hear from us within 8 weeks may consider their application unsuccessful and their data will be destroyed within 12 months of receipt.", "employment_types": ["Full Time"], "selling_points": ["Identifying management loopholes", "Assessing effectiveness of risk management", "5 years experience in relevant field"], "locations": ["Not Specified"], "categories": ["Banking / Finance", "Financial Services", "Others", "Risk Management"], "post_time": "2022-01-14T07:19:40Z", "salary": {"currency": null, "max": null, "min": null, "period": "monthly", "term": null}, "salary_visible": false, "title_keywords": ["manager"], "responsibilities": ["management", "policies", "regulatory requirements", "monitoring", "coordinate", "plan", "management report"], "requirements": {"degrees": ["degree or above"], "majors": ["business", "finance", "economics", "accounting"], "languages": ["english", "chinese"], "language_level": ["excellent"], "hard_skills": ["excel", "powerpoint", "problem solving", "ms office", "ms word"], "soft_skills": ["problem solving", "comprehensive", "communication"], "languages_combined": [{"language": "english", "language_level": ["excellent"]}, {"language": "chinese", "language_level": ["excellent"]}]}, "experience_required": {"duration": ["at least 2 years", "of 5 years"], "field": ["risk management", "market risk", "credit risk"]}}, {"job_id": "100003009047761", "location_code": "hk", "company": "Public Bank (Hong Kong) Ltd", "job_title": "Senior Remittance Clerk (Ref: JD-RSC)", "description": "Process Outward Remittance through OTT System for generating SWIFT/SWIFTNet messages and accounting entries\nProcess Inward Remittance through ITT System for generating payment advice and accounting entries.\nKnowledge in perform AML screening on incoming and outgoing swift payments\nPerform general administrative duties\nSecondary education with minimum 1 year relevant working experience\nGood interpersonal and communication skill in both English and Chinese\nProficient in PC applications, including MS Excel, typewriting\nCandidate with less experience would be considered as Remittance Clerk\n\nTo apply, interested parties please follow the application methods available in the Bank\u2019s career website\u00a0https://www.publicbank.com.hk/en/aboutus/careeropportunities. You can send us your resume quoting our job reference number together with present &\u00a0expected salary (a must)\u00a0to the Human Resources Department by email or fax at\u00a02815 3157\u00a0or by post to\u00a0Human Resources Department, 12/F, Public Bank Centre, 120 Des Voeux Road Central, Hong Kong. You may also visit our career website for other career opportunities available within our Group.\n\nPersonal data collected will be used for recruitment purpose only and will be treated in accordance with the Bank\u2019s Personal Information Collection Statement, a copy of which has been available in the Bank\u2019s career website.", "employment_types": ["Full Time", "Permanent"], "selling_points": [], "locations": ["Not Specified"], "categories": ["Banking / Finance", "Retail Banking", "Others", "Order Processing & Operation / Settlement"], "post_time": "2022-01-15T03:49:04Z", "salary": {"currency": null, "max": null, "min": null, "period": null, "term": null}, "salary_visible": false, "title_keywords": ["clerk"], "responsibilities": ["communication", "payment", "administrative duties", "incoming and outgoing swift payments", "aml screening"], "requirements": {"degrees": ["secondary education"], "majors": [], "languages": ["english", "chinese"], "language_level": ["good"], "hard_skills": ["typewriting", "pc applications", "ms excel", "incoming and outgoing swift payments", "aml screening", "swift"], "soft_skills": ["outgoing", "communication skill", "interpersonal"], "languages_combined": [{"language": "english", "language_level": ["good"]}, {"language": "chinese", "language_level": ["good"]}]}, "experience_required": {"duration": ["minimum 1 year"], "field": ["relevant working experience", "education"]}}, {"job_id": "100003009054301", "location_code": "hk", "company": "OCBC Wing Hang Bank Limited", "job_title": "2022 OCBC Wing Hang Graduate Talent Programme", "description": "2022 OCBC Wing Hang Graduate\u00a0Talent Programme\n\nDesigned for graduates with up to two years of working experience who aspire to carve a career in banking, you will get a head start with our OCBC Wing Hang Graduate\u00a0Talent Programme. We have carefully designed a 24-month structured programme with an opportunity to gain exposure from front to back office of the bank to help you build a strong banking foundation to achieve your career goals in the banking industry.\n\n\n\nBy joining the Graduate Talent Programme, you will:\n\nGet onboard our 24-month accelerated career programme\nAchieve a head-start through job rotations\nDevelop broad-based banking knowledge\nBe guided by career coach / mentor\nWork on business projects\nBuild your regional network with graduates and businesses across the OCBC Group\n\n\nHere in OCBC Wing Hang Bank, we value the growth of every individual. We are here to help you take on the future of banking with us. We say that there's no better investment than the one in your own skills and growth.\n\nJoin us to become the next Graduate Talent of the future!\n\nWe seek passionate go-getters with high levels of motivation and drive, those who are interested in an accelerated career in the banking industry.\n\nRequirements\n\nA Bachelor\u2019s Degree with second upper class or above in any discipline\nLess than 2 years of working experience\nOutstanding extracurricular/internship achievements\nHighly motivated and analytical\nStrong leadership and open to new challenges and problem-solving\nTeam player with strong interpersonal and communication skills\nOpen-minded and able to work with colleagues from diverse cultures\nKeen interest in the latest development of global economy, including the Greater-Bay-Area (GBA)\nExcellent written and spoken English and Chinese, with proficiency in Putonghua would be an advantage\nIndividuals holding IANG visa are welcomed\n\nFor the 2022 Graduate Talent Programme, we are hiring for the following divisions:\n\nRetail Banking Group\nWholesale Banking Group\nTreasury\nOCBC Wing Hang Credit\nInformation Technology\nCompliance\n\nApply Now\n\nPlease submit your application\u00a0by providing your full resume, expected GPA and stating your top 3 choices of divisions.\n\nApplication ends on 3 February 2022.\n\nSelection Process\n\nOnline Application\nVideo Assessment\nOnline Aptitude & Numerical Tests\nAssessment Centre\nFinal Panel Interview\n\nProgramme Commencement Date\n\nJuly 2022", "employment_types": ["Full Time", "Permanent"], "selling_points": ["24-month accelerated career programme", "Achieve a head-start through job rotations", "Less than 2 years of working experience"], "locations": ["Sheung Wan"], "categories": ["Banking / Finance", "Corporate Banking", "Retail Banking", "Others"], "post_time": "2022-01-17T09:05:35Z", "salary": {"currency": null, "max": null, "min": null, "period": "monthly", "term": null}, "salary_visible": false, "title_keywords": [], "responsibilities": ["business projects", "compliance", "back office", "develop", "communication", "banking"], "requirements": {"degrees": ["degree", "bachelor"], "majors": [], "languages": ["putonghua", "english", "chinese"], "language_level": ["advantage", "excellent", "proficiency"], "hard_skills": ["problem-solving", "no", "go"], "soft_skills": ["passionate", "communication skills", "open-minded", "problem-solving", "interested in", "keen", "diverse", "motivated", "team player", "structured", "leadership", "interpersonal"], "languages_combined": [{"language": "putonghua", "language_level": ["proficiency", "advantage", "excellent"]}, {"language": "english", "language_level": ["advantage", "excellent"]}, {"language": "chinese", "language_level": ["advantage", "excellent"]}]}, "experience_required": {"duration": ["2 years", "two years"], "field": ["banking"]}}, {"job_id": "100003009050267", "location_code": "hk", "company": "China Construction Bank (Asia) Corporation Limited", "job_title": "Sales Executive - Sky Center", "description": "Main Responsibilities:\n\n\n\n- Achieve sales targets by actively promoting general banking products & services to customers\n- Address customer financial needs and cross-sell consumer banking products via both phone and face to face meeting, e.g. deposit, loan, investment and insurance, etc.\n- Handle general enquiries/complaints and resolve issues\n- Comply with the established policies and procedures to ensure the safety and security of bank and customer asset\n- Comply and adhere to bank AML Compliance procedures, including but not limited to customer due diligence and ongoing transaction monitoring.\n\n\u00a0Requirements:\n\n- 5 subjects at Grade E / Level 2 or above in HKCEE / HKDSE, including Chinese, English and Mathematics. Possess IIQE and HKSI qualification is preferable\n- Minimum 1 year of sales related experience\n- Sales-driven, result-oriented and be able to work under pressure\n- With good telephone selling skills will be an advantage\n- Good spoken English, Cantonese and Putonghua\n- Excellent command of MS Word & Excel\n\n\nApplicants who are not contacted within 8 weeks may consider their applications unsuccessful and their personal data will be retained by the bank for a period up to two years.\n\nAll information provided by applicants will be used for recruitment purposes only and will be used strictly in accordance with the bank\u2019s personal data policies, a copy of which will be provided upon request.", "employment_types": ["Full Time"], "selling_points": ["Promote general banking products & services", "Cross-sell consumer bank products", "Handle general enquiries"], "locations": ["Not Specified"], "categories": ["Banking / Finance", "Retail Banking", "Others"], "post_time": "2022-01-14T10:03:18Z", "salary": {"currency": null, "max": null, "min": null, "period": "monthly", "term": null}, "salary_visible": false, "title_keywords": ["sales executive"], "responsibilities": ["aml", "policies", "compliance", "procedures", "monitoring", "customer due diligence", "banking", "insurance"], "requirements": {"degrees": ["hkdse"], "majors": ["mathematics"], "languages": ["cantonese", "putonghua", "english", "chinese"], "language_level": ["good"], "hard_skills": ["excel", "iiqe", "hksi", "ms word"], "soft_skills": ["result-oriented", "driven", "work under pressure"], "languages_combined": [{"language": "cantonese", "language_level": ["good"]}, {"language": "putonghua", "language_level": ["good"]}, {"language": "english", "language_level": ["good"]}, {"language": "chinese", "language_level": []}]}, "experience_required": {"duration": ["minimum 1 year"], "field": ["related"]}}, {"job_id": "100003009049403", "location_code": "hk", "company": "Shanghai Commercial Bank Ltd", "job_title": "Associate, Settlement & Securities Processing", "description": "Responsibilities:\n\nResponsible for performing daily settlement of all transactions initiated by Treasury and Investment Products Department, including Foreign Exchange, Money Market, securities, options, futures and other investment products in a timely and effective manner\nProcess settlement payments and receipts, and prepare summary reports\nEnsure all transactions are in full compliance with internal / external rules and regulations\nSupport User Acceptance Test (UAT) and participate in any projects as assigned\n\nRequirements:\n\nDegree holder in Business Administration or related disciplines\nWell-organized, self-motivated and attention to details\nGood command of written and spoken English and Chinese\nProficient in MS Word, Excel and Chinese Word processing\n\nAttractive remuneration package will be offered to the right candidates. Interested parties please click \"Apply Now\" to submit your full resume with current and expected salary to the Human Resources Division.\n\nPlease visit us at www.shacombank.com.hk for more information about our Bank.\n\nAll personal data collected will be used for recruitment related purposes strictly in accordance with the Bank's personal data policies, a copy of which will be provided immediately upon request by contacting our Personal Data Compliance Officer. Applicants who are not contacted within two months may consider their applications unsuccessful and the personal data collected from the applicants will be retained for no longer than two years from the date of rejection during which the applicants may be considered for other suitable positions within the Bank.", "employment_types": ["Full Time", "Contract"], "selling_points": ["Responsible for performing daily settlement", "Process settlement payments and receipts", "Support User Acceptance Test (UAT)"], "locations": ["Not Specified"], "categories": ["Banking / Finance", "Treasury", "Others", "Order Processing & Operation / Settlement"], "post_time": "2022-01-15T03:50:23Z", "salary": {"currency": null, "max": null, "min": null, "period": "monthly", "term": null}, "salary_visible": false, "title_keywords": ["associate"], "responsibilities": ["regulations", "receipts", "uat", "compliance", "transactions", "payments", "reports"], "requirements": {"degrees": ["degree holder"], "majors": ["related disciplines", "business administration"], "languages": ["english", "chinese"], "language_level": ["good command", "proficient"], "hard_skills": ["excel", "chinese word processing", "ms word"], "soft_skills": ["self-motivated", "well-organized", "attention to details"], "languages_combined": [{"language": "english", "language_level": ["good command"]}, {"language": "chinese", "language_level": ["good command", "proficient"]}]}, "experience_required": {"duration": [], "field": []}}, {"job_id": "100003009050899", "location_code": "hk", "company": "Bank of Communications Co., Ltd. Hong Kong Branch", "job_title": "Manager, Financial Crime Compliance (AML advisory / Transaction Monitoring)", "description": "Career Level\nSenior\nQualification\nDegree\nYears of Experience\n5 years\nJob Type\nFull Time, Permanent\nJob Functions\nBanking / Finance, Others, Professional Services, Legal & Compliance, Risk Management", "employment_types": ["Full Time", "Permanent"], "selling_points": [], "locations": ["Not Specified"], "categories": ["Banking / Finance", "Others", "Professional Services", "Legal & Compliance", "Risk Management"], "post_time": "2022-01-14T11:41:47Z", "salary": {"currency": null, "max": null, "min": null, "period": null, "term": null}, "salary_visible": false, "title_keywords": ["manager"], "responsibilities": ["management", "compliance", "banking"], "requirements": {"degrees": ["degree"], "majors": [], "languages": [], "language_level": [], "hard_skills": [], "soft_skills": [], "languages_combined": []}, "experience_required": {"duration": [], "field": []}}, {"job_id": "100003009042748", "location_code": "hk", "company": "Guosen Securities (HK) Financial Holdings Company, Limited", "job_title": "Assistant (Strategic Development)", "description": "Responsibilities:\n\nProvide general administration support to the department\nPrepare meeting minutes, reporting materials, and corporate-related documents in simplified Chinese mainly\nAssist in daily company secretarial duties and legal documents\nEnsure relevant statutory and regulatory matters of the Group, as well as issues of corporate governance\nDocument translation when needed\nUpdate and maintain a filing system\nAble to meet a tight deadline, flexible personality, and hardworking\nTo perform ad hoc projects as required\n\n\u00a0Requirements:\n\nDegree holder in Finance, Law, Business, Company secretarial, Journalism, Language, Translation or other related disciplines\n1 - 2 year\u2019s working experience preferred\nExperience in simplified Chinese writing and translation is preferred;\nFamiliar with the requirements of the Company Ordinance, and equivalent laws/ regulations in offshore jurisdictions are preferred\nSelf-motivated, detail-oriented, strong sense of responsibility and able to work under pressure\nGood communication and interpersonal skills\nGood command of written and spoken English and Chinese, fluency in Putonghua\nProficient in computer skills, e.g. Excel, MS Word, PowerPoint, Chinese Word Processing\nStrong sense of responsibility, Independent, initiative & excellent communication skill\n\n\u00a0Attractive remuneration will be offered to the right candidate.\u00a0 Interested parties please email your full resume with present & expected salary and date of availability to hrm @guosen.com.hk or via \"Apply Now\".\n\n\nPersonal data collected would be used for recruitment purpose only.", "employment_types": ["Full Time", "Permanent"], "selling_points": ["Attractive remuneration", "Prepare meeting minutes", "Experience in simplified Chinese writing"], "locations": ["Admiralty"], "categories": ["Admin & HR", "Secretary", "Banking / Finance", "Others", "Professional Services", "Company Secretary"], "post_time": "2022-01-12T08:39:40Z", "salary": {"currency": null, "max": null, "min": null, "period": "monthly", "term": null}, "salary_visible": false, "title_keywords": ["assistant"], "responsibilities": ["reporting", "related documents", "prepare meeting minutes", "maintain", "ad hoc projects", "administration"], "requirements": {"degrees": ["degree holder"], "majors": ["law", "finance", "journalism", "related disciplines", "business"], "languages": ["putonghua", "english", "chinese"], "language_level": ["fluency", "good command"], "hard_skills": ["excel", "chinese word processing", "powerpoint", "computer skills", "translation", "ms word"], "soft_skills": ["self-motivated", "independent", "sense of responsibility", "communication skill", "detail-oriented", "communication and interpersonal skills", "initiative", "work under pressure"], "languages_combined": [{"language": "putonghua", "language_level": ["fluency", "good command"]}, {"language": "english", "language_level": ["fluency", "good command"]}, {"language": "chinese", "language_level": ["fluency", "good command"]}]}, "experience_required": {"duration": ["1 - 2 year"], "field": ["writing"]}}, {"job_id": "100003009047893", "location_code": "hk", "company": "Wellesley Associates Limited", "job_title": "Card Usage & Partnership Manager \u2013 Banking", "description": "This is an excellent opportunity for segment portfolio and digital project management professional to join one of the leading bank with great exposure that could bring your career to the next level and offered a very competitive compensation.\n\nDuties:\n\nGenerate credit card growth and driving card usage by different marketing programs and activities\nIdentify potential online partners for collaboration and/ or wallet partner to drive digital penetration\nManage strategic marketing programs\n\nRequirements:\n\n6+ years of relevant working experience in the banking industry\nDemonstrate a strong vision in the future with a forward-thinking mindset\nExcellent analytical, interpersonal and\u00a0presentation skills\nExcellent interpersonal, communication, work organization skills\nStrong language proficiency, verbal and written English and Chinese (both Cantonese and Mandarin) are essential\n\nIf this job isn't quite right for you but you are opened for a new position within banking / wealth management side, please contact me / submit your profile for a confidential discussion on your career.", "employment_types": ["Full Time"], "selling_points": ["Join a team with great dynamics", "Strong management support from leadership", "Attractive total compensation package"], "locations": ["Not Specified"], "categories": ["Banking / Finance", "Others"], "post_time": "2022-01-14T04:09:29Z", "salary": {"currency": null, "max": null, "min": null, "period": "monthly", "term": null}, "salary_visible": false, "title_keywords": ["manager"], "responsibilities": [], "requirements": {"degrees": [], "majors": [], "languages": ["cantonese", "english", "chinese", "mandarin"], "language_level": ["proficiency"], "hard_skills": [], "soft_skills": ["communication", "presentation skills", "organization skills", "interpersonal"], "languages_combined": [{"language": "cantonese", "language_level": []}, {"language": "english", "language_level": ["proficiency"]}, {"language": "chinese", "language_level": ["proficiency"]}, {"language": "mandarin", "language_level": []}]}, "experience_required": {"duration": ["6+ years"], "field": ["banking industry", "relevant working experience"]}}, {"job_id": "100003009050929", "location_code": "hk", "company": "Bank of Communications Co., Ltd. Hong Kong Branch", "job_title": "Manager, Treasury Products (Business Control \u2013 Global Markets)", "description": "Career Level\nSenior\nQualification\nDegree\nYears of Experience\n5 years\nJob Type\nFull Time, Permanent\nJob Functions\nBanking / Finance, Treasury, Financial Services, Others", "employment_types": ["Full Time", "Permanent"], "selling_points": [], "locations": ["Not Specified"], "categories": ["Banking / Finance", "Treasury", "Financial Services", "Others"], "post_time": "2022-01-14T11:49:54Z", "salary": {"currency": null, "max": null, "min": null, "period": null, "term": null}, "salary_visible": false, "title_keywords": ["manager"], "responsibilities": ["banking"], "requirements": {"degrees": ["degree"], "majors": [], "languages": [], "language_level": [], "hard_skills": [], "soft_skills": [], "languages_combined": []}, "experience_required": {"duration": [], "field": []}}, {"job_id": "100003009049416", "location_code": "hk", "company": "Shanghai Commercial Bank Ltd", "job_title": "System Administrator (MS Windows, Desktop & Operation Supports)", "description": "Responsibilities:\n\nSupport IT administration, maintenance and implementation tasks on IT System Infrastructure, with focus on Windows end-point services.\nSupport IT Data Center Operations and IT Service Provisioning\nRequirements:\n\nDegree holder in Computer Science or related disciplines\nProficiency in administration on PC, Windows based system (physical and virtual), Linux/Unix shell script programming.\u00a0 Knowledge and experience in IBM Mainframe, job control tools is an advantage\nMinimum 3 years of relevant experience in IT infrastructure design, implementation and administration; IT operations supports and planning\nAble to work independently and under pressure\nGood communication and interpersonal skills\n\nAttractive remuneration package will be offered to the right candidates. Interested parties please click\u00a0\"Apply Now\"\u00a0to submit your full resume with current and expected salary to the\u00a0Human Resources Division.\n\nPlease visit us at\u00a0www.shacombank.com.hk\u00a0for more information about our Bank.\n\nAll personal data collected will be used for recruitment related purposes strictly in accordance with the Bank's personal data policies, a copy of which will be provided immediately upon request by contacting our Personal Data Compliance Officer. Applicants who are not contacted within two months may consider their applications unsuccessful and the personal data collected from the applicants will be retained for no longer than two years from the date of rejection during which the applicants may be considered for other suitable positions within the Bank.", "employment_types": ["Full Time", "Permanent"], "selling_points": ["Windows end-point services", "Support IT Data Center Operations", "Windows based system, Linux/Unix shell script"], "locations": ["Kwai Hing"], "categories": ["Banking / Finance", "Others", "Information Technology (IT)", "Network & System", "Others"], "post_time": "2022-01-15T03:50:25Z", "salary": {"currency": null, "max": null, "min": null, "period": "monthly", "term": null}, "salary_visible": false, "title_keywords": ["system administrator"], "responsibilities": ["it service", "maintenance", "data", "operations", "infrastructure", "implementation", "administration"], "requirements": {"degrees": ["degree holder"], "majors": ["related disciplines", "computer science"], "languages": [], "language_level": [], "hard_skills": ["unix shell", "pc", "linux", "programming"], "soft_skills": ["work independently", "communication and interpersonal skills", "under pressure"], "languages_combined": []}, "experience_required": {"duration": ["minimum 3 years"], "field": ["infrastructure", "design", "it", "relevant experience", "administration"]}}, {"job_id": "100003009047771", "location_code": "hk", "company": "Public Bank (Hong Kong) Limited", "job_title": "Senior / Technician (\u9ad8\u7d1a / \u7dad\u4fee\u6280\u8853\u54e1) (Ref: JD-TEC)", "description": "\u8ca0\u8cac\u7e3d\u884c\u53ca\u5206\u884c\u7dad\u4fee\u4fdd\u990a\u6c34\u96fb\u8a2d\u65bd\u548c\u5c4b\u5b87\u8a2d\u5099\n\u5354\u52a9\u90e8\u9580\u4e3b\u7ba1\u8ddf\u9032\u88dd\u4fee\u5de5\u7a0b\u53ca\u76f8\u95dc\u5de5\u4f5c\n\u9700\u8655\u740624\u5c0f\u6642\u7dca\u6025\u7dad\u4fee\u5de5\u7a0b\n\u5177\u6587\u4ef6\u5132\u5009\u7d93\u9a57\u70ba\u4f73\n\u4e2d\u5b78\u7a0b\u5ea6\u6216\u4ee5\u4e0a, \u61c2\u57fa\u672c\u96fb\u8166\u64cd\u4f5c\n\u80fd\u64cd\u6d41\u884c\u7cb5\u8a9e, \u7565\u61c2\u82f1\u8a9e\u53ca\u666e\u901a\u8a71\n\u9808\u6301\u6709\u6a5f\u96fb\u5de5\u7a0b\u7f72\u96fb\u5de5' A ' \u724c\u53ca\u5e73\u5b89\u54ad\n\u5177\u5169\u5e74\u6216\u4ee5\u4e0a\u6709\u95dc\u5de5\u4f5c\u7d93\u9a57, \u66fe\u5728\u9280\u884c\u4efb\u8077\u8005\u53ca\u63011\u30012\u985e\u8eca\u724c\u5c07\u512a\u5148\u8003\u616e\n\u7d93\u9a57\u8f03\u4f73\u8005\u53ef\u8003\u616e\u7372\u8058\u70ba\u9ad8\u7d1a\u6280\u8853\u54e1\n\nTo apply, interested parties please follow the application methods available in the Bank\u2019s career website https://www.publicbank.com.hk/en/aboutus/careeropportunities. You can send us your resume quoting our job reference number together with present & expected salary (a must) to the Human Resources Department by email or fax at 2815 3157 or by post to Human Resources Department, 12/F, Public Bank Centre, 120 Des Voeux Road Central, Hong Kong. You may also visit our career website for other career opportunities available within our Group.\n\nPersonal data collected will be used for recruitment purpose only and will be treated in accordance with the Bank\u2019s Personal Information Collection Statement, a copy of which has been available in the Bank\u2019s career website.\n\n\n", "employment_types": ["Full Time", "Permanent"], "selling_points": [], "locations": ["Not Specified"], "categories": ["Banking / Finance", "Others", "Others", "Technician", "Building & Construction", "Others"], "post_time": "2022-01-15T03:49:07Z", "salary": {"currency": null, "max": null, "min": null, "period": null, "term": null}, "salary_visible": false, "title_keywords": ["technician"], "responsibilities": [], "requirements": {"degrees": [], "majors": [], "languages": [], "language_level": [], "hard_skills": [], "soft_skills": [], "languages_combined": []}, "experience_required": {"duration": [], "field": []}}, {"job_id": "100003009043774", "location_code": "hk", "company": "Zurich Insurance (Hong Kong)", "job_title": "Customer Care Consultant (General Insurance)", "description": "Responsibilities:\nLead the IT procurement management process covering IT hardware, software, and service.\n\nStreamline and enhance procurement processes, policies, practices and systems.\n\nEvaluate procurement proposal to protect the corporate\u2019s best interest and to comply with internal policies.\n\nProvide advice and guidance in tendering and procurement process.\n\nMeasure vendors\u2019 performance regularly.\n\nMaintain the contract administration function effectively and provide contractual advices on contract matters to internal users.\n\nSupport/lead other business activities and ad hoc tasks as required.\n\nRequirements:\nDegree holder in business administration, IT or related discipline.\n\nMinimum 5 years\u2019 working experience in IT procurement, preferably in the banking or IT industry. Candidate with more experience will be considered as senior position.\n\nExtensive supervision experience of procurement team and strong leadership, stakeholder management, coaching and change management skills; able to negotiate and persuade others for positive results and communicate effectively across all functions and levels;\n\nGood presentation, communication and negotiation skills; proficiency in both written and spoken English and Chinese (including Putonghua).\n\nStrong organizational skills, able to work independently with limited supervision, self-motivated, diligent with mature personality;\n\nCapable of working under pressure to meet deadlines\n\nExperience in Procurement system, Oracle iProcurement system is preferred; proficiency in MS Office applications including Word, Excel, PowerPoint.\n\nWe offer competitive remuneration package and comprehensive fringe benefits including medical and life insurance, and different types of allowances to the right candidate. Interested parties, please submit your application online. For details, please visit our website http://www.bochk.com\n\nData collected would be used for recruitment purposes only. It might also be disclosed to our subsidiaries or Associated Companies to process the information for appointment. Applicants who do not hear from us within 8 weeks may consider their application unsuccessful and their data will be destroyed within 12 months of receipt.", "employment_types": ["Full Time", "Permanent"], "selling_points": ["Handle customer enquiries and complaints", "Provide quality service to customers", "IIQE Paper 1 and 2"], "locations": ["Quarry Bay"], "categories": ["Banking / Finance", "Others", "Sales, CS & Business Devpt", "Customer Service - Supervisor / Officer", "Insurance", "Others"], "post_time": "2022-01-13T01:55:06Z", "salary": {"currency": null, "max": null, "min": null, "period": "monthly", "term": null}, "salary_visible": false, "title_keywords": ["consultant"], "responsibilities": ["guidance", "management", "software", "procurement processes", "policies", "contract administration", "systems", "ad hoc tasks", "tendering", "evaluate", "hardware", "provide advice", "maintain", "business activities", "it procurement"], "requirements": {"degrees": ["degree holder"], "majors": ["it", "business administration"], "languages": ["putonghua", "english", "chinese"], "language_level": ["proficiency"], "hard_skills": ["excel", "oracle", "word", "powerpoint", "ms office"], "soft_skills": ["organizational skills", "work independently", "self-motivated", "under pressure", "capable", "diligent", "mature", "communication", "negotiation skills", "comprehensive", "leadership", "meet deadlines", "extensive", "presentation", "positive"], "languages_combined": [{"language": "putonghua", "language_level": []}, {"language": "english", "language_level": ["proficiency"]}, {"language": "chinese", "language_level": ["proficiency"]}]}, "experience_required": {"duration": ["minimum 5 years"], "field": ["management", "it", "banking", "procurement", "team"]}}, {"job_id": "100003009039837", "location_code": "hk", "company": "Hays", "job_title": "Senior Officer, Cash Management", "description": "Foreign Corporate Bank is looking for a Cash Management Officer. Amazing culture and Great Exposure\n\nYour new company\nA Foreign Corporate Bank is looking for a Cash Management Senior Officer\n\nYour new role\n\nProcess money transfer instruction from customer\nHandle customer enquiry and make quote to customer for deposit and foreign exchange\nTransaction input, filing\nCheque Clearings\n\n\nWhat you'll need to succeed\n\n3+ years of experience in remittance\nExperience in FlexCube preferable\nFluent in English and Mandarin\nSound knowledge in international payment system\nSWIFT knowledge\n\n\n\nWhat you need to do now\nIf you're interested in this role, click 'apply now' to forward an up-to-date copy of your CV, or reach out to Christopher Cheung via phone 2230 7916 or via email christopher.cheung@hays.com.hk now.\nIf this job isn't quite right for you but you are looking for a new position, please contact us for a confidential discussion on your career.", "employment_types": ["Full Time", "Permanent"], "selling_points": ["Foreign Corporate Bank", "Cash Management Senior Officer", "3+ years of experience"], "locations": ["Not Specified"], "categories": ["Banking / Finance", "Corporate Banking", "Others", "Order Processing & Operation / Settlement"], "post_time": "2022-01-11T11:52:28Z", "salary": {"currency": null, "max": null, "min": null, "period": "monthly", "term": null}, "salary_visible": false, "title_keywords": ["senior officer", "cash management"], "responsibilities": ["management", "payment", "contact"], "requirements": {"degrees": [], "majors": [], "languages": ["english", "mandarin"], "language_level": ["fluent"], "hard_skills": ["swift", "make", "exchange"], "soft_skills": ["interested in"], "languages_combined": [{"language": "english", "language_level": ["fluent"]}, {"language": "mandarin", "language_level": ["fluent"]}]}, "experience_required": {"duration": ["3+ years"], "field": []}}, {"job_id": "100003009049576", "location_code": "hk", "company": "China Construction Bank (Asia) Corporation Limited", "job_title": "Head of AML Compliance Department", "description": "Main Responsibilities\n\nManage the Anti-Money Laundering Compliance Department.\nDevelop and maintain AML/CFT compliance programs and control framework that are in compliance with local AML/CFT legislation; rules and regulations issued by the HKMA and relevant authorities as well as relevant guidelines from Head Office.\nEnsure day to day functions of AML Compliance are conducted effectively including, but not exclusively, AML/CFT governance; customer name screening; transactions screening and approval functions; AML/CFT advisory and client risk assessment; AML/CFT transaction monitoring function.\nOffer advice and recommendation to management in the area of AML/CFT compliance standard enhancement.\nProvide advice to business/management on AML/CFT issues.\nCommunicate with Head Office on AML/CFT matters.\nLiaise with internal and external auditors and regulators on AML/CFT matters.\nEnsure the division is in compliance with the regulatory requirements as well as the internal compliance policies and guidelines including but not limited to anti-money laundering and counter-financing of terrorism.\nTake up the regulatory role of an AML Compliance Officer and MLRO\n\nRequirements\n\nDegree holder in Law, Accounting or related disciplines\nMinimum 15 relevant years of experience in compliance field with at least 5 years management experience in a sizable bank/financial institution and/or regulatory bodies\nPossess good knowledge on banking operations, products and services\nSelf-motivated, independent with excellent communication and interpersonal skills\nGood command of both spoken English and Chinese\n\nApplicants who are not contacted within 8 weeks may consider their applications unsuccessful and their personal data will be retained by the bank for a period up to two years.\n\nAll information provided by applicants will be used for recruitment purposes only and will be used strictly in accordance with the bank\u2019s personal data policies, a copy of which will be provided upon request.", "employment_types": ["Full Time"], "selling_points": ["Minimum 15 relevant years of experience", "At least 5 years management experience", "Possess good knowledge of banking operations"], "locations": ["Not Specified"], "categories": ["Banking / Finance", "Others"], "post_time": "2022-01-14T08:54:12Z", "salary": {"currency": null, "max": null, "min": null, "period": "monthly", "term": null}, "salary_visible": false, "title_keywords": ["aml compliance"], "responsibilities": ["regulations", "communicate with", "control", "management", "aml", "guidelines", "regulatory requirements", "policies", "compliance", "monitoring", "transactions", "develop", "maintain", "provide advice", "liaise with", "external auditors"], "requirements": {"degrees": ["degree holder"], "majors": ["related disciplines", "accounting", "law"], "languages": ["english", "chinese"], "language_level": ["good command"], "hard_skills": [], "soft_skills": ["self-motivated", "communication and interpersonal skills", "independent"], "languages_combined": [{"language": "english", "language_level": ["good command"]}, {"language": "chinese", "language_level": ["good command"]}]}, "experience_required": {"duration": ["at least 5 years"], "field": ["management", "compliance", "financial"]}}, {"job_id": "100003009047780", "location_code": "hk", "company": "China Everbright Securities International Company Limited", "job_title": "Senior / Analyst, Derivatives Operations (Settlement)", "description": "Ref: SA/OPD/140121DB/16\n\nResponsibilities\n\nSupport daily processing functions for Derivatives (e.g. stock options)\nPerform the duties of processing, control and monitoring the daily settlement and prepare regular reports\nLiaise with internal counterparts on transaction and settlement issues\nHandle Wealth Manager(s) requests and queries\nConduct user acceptance test for system enhancement / upgrades\nPerform ad-hoc duties as assigned by supervisor\u00a0\u00a0\u00a0\n\nRequirements\u00a0\u00a0\n\nDiploma or above\n2 years\u2019 relevant experience\u00a0in\u00a0financial industry\nSolid experience in CCASS / DCASS operations preferred\nSelf-disciplined and able to work independently\nGood command of both written and spoken English and Chinese.\u00a0 Fluency in Putonghua will be an advantage\nProficiency in MS Office and Chinese Word Processing\nCandidate with less experience will be considered as 'Analyst' and fresh graduates are\u00a0 welcome\n\nWe offer a competitive remuneration package to the right candidate. If you are interested in the post, please send your resume together with your present and expected salaries by clicking \u201cApply Now\u201d.\u00a0\n\nFor more information about China Everbright Securities International Company Limited, please visit www.ebshk.com.\n\u00a0\n\n\nWe are an equal opportunity employer and welcome applications from all qualified candidates. All applications will be treated in the strictest confidence. Personal data provided will be used for recruitment purposes only. The job applicant will assume all or any risks arising out of or in connection with the job application transmission process prior to our actual receipt of the same including but not limited to accidental or unauthorized loss or disclosure of personal information, to which we will not be responsible in any way.\n\nUnder the Personal Data (Privacy) Ordinance, you may request access to, and / or correction of your personal data in relation to your application. If you wish to do so, please email to us.", "employment_types": ["Full Time", "Permanent"], "selling_points": [], "locations": ["Causeway Bay"], "categories": ["Banking / Finance", "Equities / Capital Markets", "Others", "Order Processing & Operation / Settlement"], "post_time": "2022-01-14T04:30:46Z", "salary": {"currency": null, "max": null, "min": null, "period": "monthly", "term": null}, "salary_visible": false, "title_keywords": ["analyst", "operations"], "responsibilities": ["control", "upgrades", "monitoring", "reports", "ad-hoc duties", "liaise with", "settlement issues"], "requirements": {"degrees": ["diploma or above"], "majors": [], "languages": ["putonghua", "english", "chinese"], "language_level": ["fluency", "advantage", "proficiency", "good command"], "hard_skills": ["dcass", "chinese word processing", "ccass", "ms office"], "soft_skills": ["work independently"], "languages_combined": [{"language": "putonghua", "language_level": ["fluency", "advantage"]}, {"language": "english", "language_level": ["good command"]}, {"language": "chinese", "language_level": ["proficiency", "good command"]}]}, "experience_required": {"duration": ["2 years"], "field": ["financial industry", "relevant experience"]}}, {"job_id": "100003009043769", "location_code": "hk", "company": "Chong Hing Bank Ltd", "job_title": "Senior Officer / Assistant Manager, Payment Services & Cash Management", "description": "Responsibilities:\nHandle general banking transactions including inward/outward remittance, FX, account transfer and G/L entries\nCheck and verify suspected hits in AML system\nAssist in preparing MIS reports\nHandle office administrative works for the department\nAd hoc tasks as assigned by superior\nRequirements:\nDiploma holder with at least 3 years\u2019 working experience in branch, back office or payment operations in banking industry\nBasic knowledge on SWIFT, CHATS and other international/domestic payment systems\nGreat sense of ownership and servicing mindset\nAttentive to details, able to work under pressure and irregular working hours\nConversant with MS Office and Chinese Word Processing\nProficiency in both spoken and written English and Chinese\nCandidate with more relevant experience will be considered as Assistant Manager", "employment_types": ["Full Time", "Permanent"], "selling_points": ["Assist in preparing MIS reports", "Ad hoc tasks as assigned by superior", "Diploma holder"], "locations": ["Not Specified"], "categories": ["Banking / Finance", "Others", "Order Processing & Operation / Settlement"], "post_time": "2022-01-13T01:53:49Z", "salary": {"currency": null, "max": null, "min": null, "period": "monthly", "term": null}, "salary_visible": false, "title_keywords": ["senior officer", "assistant manager,", "cash management"], "responsibilities": ["aml", "ad hoc tasks", "transactions", "reports", "banking"], "requirements": {"degrees": ["diploma holder"], "majors": [], "languages": ["english", "chinese"], "language_level": ["proficiency"], "hard_skills": ["swift", "chinese word processing", "basic", "ms office"], "soft_skills": ["attentive to details", "work under pressure"], "languages_combined": [{"language": "english", "language_level": ["proficiency"]}, {"language": "chinese", "language_level": ["proficiency"]}]}, "experience_required": {"duration": ["at least 3 years"], "field": ["banking industry", "relevant experience"]}}, {"job_id": "100003009046510", "location_code": "hk", "company": "Page Personnel", "job_title": "Transaction Monitoring Senior Officer - Top HK Bank!", "description": "Our client is a leading public bank in Hong Kong that provides tailor-made financing solutions and services to their customers. They are currently looking for a role of transaction monitoring senior officer to join the financial crime compliance department to conduct AML/ case investigations and transaction monitoring. The candidate should have 2-3 years of working experience in transaction monitoring within banking industry.\n\nClient Details\n\nOur client is one of Hong Kong's largest listed banks and they are now seeking a position of transaction monitoring senior officer to join the financial crime compliance department to investigate assigned cases including transaction monitoring, unusual activity reports and customer screening alerts. The department is responsible for investigating cases, checking suspicious activity and reporting to the authorities according to the agreed standard reporting requirements and guidance.\n\nDescription\n\nResponsible for conducting effective and timely investigations including transaction monitoring cases from FCC operations, unusual activity reports from various business units and customer screening alerts suggesting risk\nComplete level 2 case analysis and identify suspicious activity or possible violations of regulation in business transaction documented in CDD according to regulatory reporting requirements\nWrite high quality reports to identify risks and escalate investigations to the line of business or the authorities\nProvide telephone or email guidance to line of business or relevant stakeholders in accordance with reporting standards\nProvide timely and accurate management information as required\n\nProfile\n\nBachelor's Degree with major in Business Administration/ Finance or relevant discipline\n2-3 years of working experience in AML investigation, transaction monitoring within banking industry\nExperience in identifying risk activity, investigating customer activity and writing reports for escalation. Regulatory investigation experience is an advantage\nExcellent English spoken and written communication skills\nStrong interpersonal skills and strong organization skills\n\nJob Offer\n\nStimulating and challenging work\nDynamic working environment\nCompetitive remuneration and benefit packages\n\nTo apply online please click the 'Apply' button below. For a confidential discussion about this role please contact Esther Liu on +852 2258 3537", "employment_types": ["Full Time", "Permanent"], "selling_points": ["Stimulating and challenging work", "Dynamic working environment", "Competitive remuneration and benefit packages"], "locations": ["Not Specified"], "categories": ["Banking / Finance", "Corporate Banking", "Financial Services", "Others"], "post_time": "2022-01-13T12:37:55Z", "salary": {"currency": null, "max": null, "min": null, "period": "monthly", "term": null}, "salary_visible": false, "title_keywords": ["senior officer"], "responsibilities": ["reporting", "guidance", "management", "aml", "operations", "analysis", "compliance", "monitoring", "checking", "cdd", "quality", "investigation", "communication", "reports", "contact", "banking", "administration"], "requirements": {"degrees": ["degree", "bachelor"], "majors": ["finance", "business administration"], "languages": ["english"], "language_level": ["excellent"], "hard_skills": ["cdd", "analysis", "dynamic", "aml"], "soft_skills": ["communication skills", "responsible", "timely", "dynamic", "interpersonal skills", "organization skills", "accurate"], "languages_combined": [{"language": "english", "language_level": ["excellent"]}]}, "experience_required": {"duration": ["2-3 years"], "field": ["banking industry", "writing"]}}, {"job_id": "100003009049337", "location_code": "hk", "company": "Shanghai Commercial Bank Ltd", "job_title": "Assistant Vice President, Credit Review", "description": "Responsibilities:\n\nPrepare credit facility review with focus on property development, construction financing, and syndication to identify and assess potential problematic credit accounts\nConduct risk evaluation and make recommendation on credit facilities on large scale customers\nEnsure compliance with of bank policy and regulatory requirements\nAssist in formulating credit policies, guidelines and procedures of credit activities undertaken by the bank\nExperience in handling regulatory and external/internal audit onsite examination an advantage\nHandle ad-hoc credit tasks as assigned\nCollaborate with business units and assess various market information/event and internal & external early warning signal to detect potential problem accounts for close & early management\nTake immediate action to manage & mitigate account irregularity and credit risk\nRequirements:\n\nDegree holder in Business Administration, Finance, Risk Management or related disciplines\nHolder of ECF-CRM certification an advantage\nMinimum 8 5 years of experience of solid experience in commercial / corporate/ listed companies' credit analysis (in terms of credit risk aspects and financial viability) and credit risk management in banking industry, experience in supervisory role an advantage.\nStrong understanding of legal and regulatory requirements and banking practices on credit risk management\nSelf-motivated with good analytical skill and risk control knowledge\nGood command of written and spoken English and Chinese\n\nAttractive remuneration package will be offered to the right candidates. Interested parties please click \"Apply Now\" to submit your full resume with current and expected salary to the Human Resources Division.\n\nPlease visit us at www.shacombank.com.hk for more information about our Bank.\n\nAll personal data collected will be used for recruitment related purposes strictly in accordance with the Bank's personal data policies, a copy of which will be provided immediately upon request by contacting our Personal Data Compliance Officer. Applicants who are not contacted within two months may consider their applications unsuccessful and the personal data collected from the applicants will be retained for no longer than two years from the date of rejection during which the applicants may be considered for other suitable positions within the Bank.", "employment_types": ["Full Time", "Permanent"], "selling_points": ["Prepare credit facility review", "Conduct risk evaluation and make recommendation", "Formulate credit policies, guidelines & procedures"], "locations": ["North Point"], "categories": ["Banking / Finance", "Credit Analysis / Approval", "Others", "Risk Management"], "post_time": "2022-01-15T03:50:19Z", "salary": {"currency": null, "max": null, "min": null, "period": "monthly", "term": null}, "salary_visible": false, "title_keywords": ["assistant vice president"], "responsibilities": ["ad-hoc", "collaborate with", "management", "market information", "make recommendation", "internal audit", "guidelines", "regulatory requirements", "policies", "review", "procedures", "ensure compliance", "evaluation", "credit facility"], "requirements": {"degrees": ["degree holder"], "majors": ["related disciplines", "finance", "business administration", "risk management"], "languages": ["english", "chinese"], "language_level": ["good command"], "hard_skills": ["credit analysis", "analytical skill"], "soft_skills": ["self-motivated", "analytical skill"], "languages_combined": [{"language": "english", "language_level": ["good command"]}, {"language": "chinese", "language_level": ["good command"]}]}, "experience_required": {"duration": ["5 years"], "field": ["banking industry", "management", "supervisory", "commercial", "credit risk", "financial"]}}, {"job_id": "100003009050660", "location_code": "hk", "company": "Bank of Communications (Hong Kong) Limited", "job_title": "Customer Relationship Manager", "description": "Assist in various credit risk management functions for the team\nCarry out risk data collection and analysis for monitoring and regular reporting\nExplore the changes and risk drivers of the bank\u2019s credit portfolio with reference to prevailing macro environment and market conditions\nPrepare credit portfolio analysis reports and presentation materials for senior management/ management committee\nEnhance and maintain credit related systems and database\nDegree holder or above in Statistics, Mathematics, IT / Computing, Risk Management, Finance or related disciplines\nMinimum 1 year\u2019s relevant experience in the banking or financial sector, with exposure on working with database and internal rating system.\nSound knowledge of Excel, Access, VBA, data warehouse and statistical tools (e.g. SAS)\nStrong interpersonal and communications skills\nStrong analytical skill and numerical sense\nConversant with Chinese word processing\nFluency in Mandarin is a plus\n\nCandidates with more experience will be considered as Senior Analyst, Credit Policy & Quantitative Analysis\n\n\u00a0\n\nThe above post requires proficiency in English, Cantonese and Putonghua.\n\nWe offer attractive remuneration package to the right candidates. Please send your full resume with expected salary to\u00a0The Human Resources Manager, Bank of Communications Co., Ltd., 10/F, Bank of Communications Tower, 231-235 Gloucester Road, Wan Chai, Hong Kong, or fax to\u00a02838 9209, or e-mail to APPLY NOW.", "employment_types": ["Full Time"], "selling_points": [], "locations": ["Not Specified"], "categories": ["Banking / Finance", "Investment", "Others", "Wealth Management"], "post_time": "2022-01-14T11:08:12Z", "salary": {"currency": null, "max": null, "min": null, "period": null, "term": null}, "salary_visible": false, "title_keywords": ["relationship manager"], "responsibilities": ["reporting", "management", "data", "analysis", "monitoring", "portfolio analysis reports", "systems", "banking", "maintain", "data collection", "database", "senior management"], "requirements": {"degrees": ["degree holder"], "majors": ["mathematics", "risk management", "finance", "statistics", "related disciplines", "it"], "languages": ["cantonese", "english", "mandarin", "putonghua", "chinese"], "language_level": ["fluency", "proficiency"], "hard_skills": ["vba", "excel", "macro", "analytical skill", "chinese word processing", "plus", "sas", "data warehouse", "analysis"], "soft_skills": ["analytical skill", "interpersonal", "presentation"], "languages_combined": [{"language": "cantonese", "language_level": ["proficiency"]}, {"language": "english", "language_level": ["proficiency"]}, {"language": "mandarin", "language_level": ["fluency"]}, {"language": "putonghua", "language_level": ["proficiency"]}, {"language": "chinese", "language_level": []}]}, "experience_required": {"duration": ["minimum 1 year"], "field": ["database", "relevant experience", "financial", "banking"]}}, {"job_id": "100003009050925", "location_code": "hk", "company": "Bank of Communications Hong Kong Branch", "job_title": "Analyst, Credit Policy & Quantitative Analysis", "description": "Responsibilities\n\n\nAssist in financial statements review and analysis\nAssist in cash flow management\nAssist in annual audit and interim review\nAssist in budget preparation and monitoring\nAssist in filing tax returns\nAssist in internal control procedures\nAssist in system implementation and maintenance\nAssist in business support and acquisition from financial perspective\nAssist in other tasks as assigned\n\nRequirements\n\n\n\nDegree holder in Finance/Accounting or related disciplines\nAround 5 years\u2019 relevant experience, package will be commensurate with experience\nProactive, detail-minded, well-organized and result-oriented with excellent interpersonal skills, analytical mind and sense of responsibility\nFluent in English, Mandarin and Cantonese\n\n\n\nWe offer attractive remuneration package and fringe benefits to the suitable candidates. Interested parties, please submit your application to us.\u00a0\n\nYou are welcome to visit our website at\u00a0https://htm.sf-express.com/hk/tc/\u00a0for more information about us.\n\nCandidates who are not invited for an interview within 1-month may consider their applications unsuccessful.\n\nAll personal data provided by job applicants will be used only for recruitment purposes and will be treated strictly confidential. Unsuccessful applications will be retained for a maximum period of 24-month.", "employment_types": ["Full Time"], "selling_points": ["Degree holder or above in Statistics, Mathematics", "Strong interpersonal and communications skills", "1 year\u2019s relevant experience in the banking"], "locations": ["Not Specified"], "categories": ["Banking / Finance", "Analyst", "Financial Services", "Others"], "post_time": "2022-01-14T11:48:51Z", "salary": {"currency": null, "max": null, "min": null, "period": "monthly", "term": null}, "salary_visible": false, "title_keywords": ["analyst"], "responsibilities": ["tax", "management", "maintenance", "annual audit", "analysis", "review", "budget", "monitoring", "financial statements", "procedures", "implementation", "other tasks", "cash flow", "internal control"], "requirements": {"degrees": ["degree holder"], "majors": ["related disciplines", "finance", "accounting"], "languages": ["cantonese", "english", "mandarin"], "language_level": ["fluent"], "hard_skills": [], "soft_skills": ["detail-minded", "sense of responsibility", "well-organized", "analytical mind", "interpersonal skills", "proactive", "result-oriented"], "languages_combined": [{"language": "cantonese", "language_level": ["fluent"]}, {"language": "english", "language_level": ["fluent"]}, {"language": "mandarin", "language_level": ["fluent"]}]}, "experience_required": {"duration": ["5 years"], "field": ["relevant experience"]}}, {"job_id": "100003009050893", "location_code": "hk", "company": "S.F. Express (Hong Kong) Limited", "job_title": "Assistant Finance Manager (SF REIT Asset Management Limited)", "description": "Job Responsibilities:\n\nCaptured the market price from Bloomberg and Reuters to feed into the valuation systems\nAnalyse and execute the corporate action event (dividend, spin off, shares split etc)\nHandle the research and implementation of corporate actions for equities (e.g. increases and decreases of capital stocks, IPOs, M&A activities, dividend payments, stock splits, spin-offs, etc.)\nClosely work with Europe and North America offices regarding market data enquires\nTake charge of different projects to develop the team in Hong Kong\n\nRequirements:\n\nExperience in VBA/SQL will be an advantage\nKnowledge in treasury product's. and treasury system (such as Murex system) and financial statement analysis is an advantage\nFluent in English, Mandarin and Cantonese.\n1+ years relevant experience", "employment_types": ["Full Time"], "selling_points": ["Free shuttle bus coverage", "Attractive performance bonus", "Finance Functions"], "locations": ["Tsing Yi"], "categories": ["Accounting", "Finance / Accounting Manager", "Taxation", "Banking / Finance", "Others"], "post_time": "2022-01-14T11:40:37Z", "salary": {"currency": null, "max": null, "min": null, "period": "monthly", "term": null}, "salary_visible": false, "title_keywords": ["assistant finance manager", "asset management"], "responsibilities": ["valuation", "systems", "implementation", "develop", "payments", "market data", "analyse"], "requirements": {"degrees": [], "majors": [], "languages": ["cantonese", "english", "mandarin"], "language_level": ["fluent"], "hard_skills": ["sql", "vba", "analysis"], "soft_skills": [], "languages_combined": [{"language": "cantonese", "language_level": ["fluent"]}, {"language": "english", "language_level": ["fluent"]}, {"language": "mandarin", "language_level": ["fluent"]}]}, "experience_required": {"duration": ["1+ years"], "field": ["sql", "relevant experience"]}}, {"job_id": "100003009046468", "location_code": "hk", "company": "Randstad Hong Kong Limited", "job_title": "Market Data Analyst - 32k", "description": "Responsible for providing advisory support to Global Markets Department on compliance issues\nReview internal operational procedures to ensure compliance with local regulatory requirements and internal control guidelines\nFormulate and review trade document (eg ISDA, Loan Agreement and Product Term Sheet)\nProvide training to departmental staff where necessary\nDegree holder or above in Law, Accounting, Business Administration or related disciplines\nMinimum 5 years\u2019 relevant experience in banking sector / audit firms\nFamiliar with treasury operations and local regulatory requirements on investment products\n\u00a0\n\nThe above post requires proficiency in English, Cantonese and Putonghua.\n\nWe offer attractive remuneration package to the right candidates. Please send your full resume with expected salary to\u00a0The Human Resources Manager, Bank of Communications Co., Ltd., 10/F, Bank of\u00a0Communications\u00a0Tower,\u00a0231-235 Gloucester Road, Wan Chai,\u00a0Hong Kong, or fax to\u00a02838 9209, or e-mail to APPLY NOW.", "employment_types": ["Full Time", "Permanent"], "selling_points": ["Foreign Bank", "VBA/ SQL preferred", "1+ years experience"], "locations": ["Not Specified"], "categories": ["Banking / Finance", "Treasury", "Equities / Capital Markets", "Others"], "post_time": "2022-01-13T11:30:54Z", "salary": {"currency": "HKD", "max": 29999, "min": 20000, "period": "monthly", "term": null}, "salary_visible": true, "title_keywords": ["data analyst"], "responsibilities": ["provide training", "administration", "guidelines", "regulatory requirements", "operations", "review", "compliance", "audit", "ensure compliance", "operational procedures", "banking", "internal control"], "requirements": {"degrees": ["degree holder"], "majors": ["related disciplines", "accounting", "business administration", "law"], "languages": ["cantonese", "putonghua", "english"], "language_level": ["proficiency"], "hard_skills": ["investment products", "internal control"], "soft_skills": ["responsible"], "languages_combined": [{"language": "cantonese", "language_level": ["proficiency"]}, {"language": "putonghua", "language_level": ["proficiency"]}, {"language": "english", "language_level": ["proficiency"]}]}, "experience_required": {"duration": ["minimum 5 years"], "field": ["relevant experience", "audit", "banking sector"]}}, {"job_id": "100003009050930", "location_code": "hk", "company": "Bank of Communications Hong Kong Branch", "job_title": "Manager, Treasury Compliance (Business Control \u2013 Global Markets)", "description": "About Standard Chartered\u00a0\nWe are a leading international bank focused on helping people and companies prosper across Asia, Africa and the Middle East.\u00a0\n\nTo us, good performance is about much more than turning a profit.\u00a0 It's about showing how you embody our valued behaviours - do the right thing, better together and never settle - as well as our brand promise, Here for good.\n\nWe're committed to promoting equality in the workplace and creating an inclusive and flexible culture - one where everyone can realise their full potential and make a positive contribution to our organisation. This in turn helps us to provide better support to our broad client base.\n\nAbout Mox\nAs one of the biggest banks in market, we are rapidly expanding by growing a new virtual banking business in Hong Kong. We see ourselves as a fast growing start-up company where you will enjoy autonomy and teamwork at the same time, solving new and exciting problems in a nimble and agile way. Join us and be part of history making for future banking experience!\n\nThe Role Responsibilities\nManage the Customer Care Centre which is the most important customer touchpoint of Mox, which provides 24hr service via Audio, Video Call and Text Chat.\nSupport the launch of wealth management products, work closely with the Product and Customer Team to ensure seamless customer support in that space.\nEstablish the appropriate service level target, and key performance indicators.\u00a0 Lead the team to meet and excel the target.\nAdvocate customer voice, and focus on continuously improving the process and setting new standards to provide best in class service.\nMaintain staffing plans, schedules; identify and develop talents, create and maintain a healthy organization structure with proper delegation among the team managers.\nCreates and automate the MIs and reports; leverage on the data to make sound and quality decisions; execute the solutions and continuously review and improve.\nOur Ideal Candidate\nBachelor\u2019s degree or higher from an accredited university\n8+ years of experience in Contact Centre in any sizable retail bank or insurance company\nProven track record of managing teams of 30+\nKnowledge in wealth management, and with HKSI license a solid advantage\nBasic literacy in Mac OS and enterprise cloud communication tools\nBe open to diverse culture and new ways of working, people-oriented\nResponsive and stay attentive even after office hours\nApply now to join the Bank for those with big career ambitions.\n", "employment_types": ["Full Time"], "selling_points": ["Degree holder or above in Law, Accounting", "5 years\u2019 relevant experience in banking sector", "Provide training to departmental staff"], "locations": ["Not Specified"], "categories": ["Banking / Finance", "Financial Services", "Others"], "post_time": "2022-01-14T11:50:40Z", "salary": {"currency": null, "max": null, "min": null, "period": "monthly", "term": null}, "salary_visible": false, "title_keywords": ["manager"], "responsibilities": ["management", "data", "schedules", "communication tools", "review", "quality", "teams", "develop", "maintain", "client base", "reports", "contact", "banking", "plans", "audio", "insurance"], "requirements": {"degrees": ["degree", "bachelor"], "majors": [], "languages": [], "language_level": [], "hard_skills": ["excel", "mac os", "basic", "agile", "hksi", "make", "focus"], "soft_skills": ["flexible", "attentive", "agile", "focused", "teamwork", "communication", "committed", "diverse", "organisation", "people-oriented", "focus", "responsive", "positive", "ideal"], "languages_combined": []}, "experience_required": {"duration": ["8+ years"], "field": ["retail", "banking experience", "insurance"]}}]