[{"job_id": "100003009054845", "location_code": "hk", "company": "Cathay United Bank Company, Limited", "job_title": "Associate, Relationship Management - Private Wealth Management", "description": "Responsibilities:\u00a0\n\n\nAssist Relationship Managers in daily transactional duties including taking investment orders, remittance, account documentations and credit modifications\nSupport client relationship building and account maintenance to facilitate the business of Relationship Managers\nHandle administrative duties including KYC/AML and onboarding pre-checks\n\n\u00a0Ideal candidates are expected to possess:\u00a0\n\n\nBachelor\u2019s degree or above\nAt least 2 years\u2019 relevant work experience serving high net-worth clients\nPass in the HKSI Licensing Examination and qualified under SFO for handling Regulated Activities Type\u00a01\nKnowledge of private banking and treasury services, good understanding of banking operations and policies\nSelf-motivated, detail oriented, able to work independently with good organization skills\nExcellent communication skills with strong customer-focused mindset\nProficient in written and spoken English and Chinese, good command in Mandarin is preferred\nWe offer attractive remuneration package and comprehensive fringe benefits. Interested parties please e-mail your full resume with current and expected salary by clicking\u00a0\"Apply Now\".\u00a0\n\nPersonal information collected will be used for considering suitability for the post and strictly in accordance with our personal data policies.\u00a0 It is our policy to retain the personal data of unsuccessful applicants for future recruitment purposes for a period of maximum two years.", "employment_types": ["Full Time", "Permanent"], "selling_points": ["Bachelor\u2019s degree or above", "At least 2 years\u2019 relevant work experience", "Pass in the HKSI Licensing Examination"], "locations": ["Causeway Bay"], "categories": ["Banking / Finance", "Private Banking", "Wealth Management"], "post_time": "2022-01-17T11:41:52Z", "salary": {"currency": null, "max": null, "min": null, "period": "monthly", "term": null}, "salary_visible": false, "title_keywords": ["wealth management", "associate"], "responsibilities": ["aml", "kyc", "operations", "policies", "communication", "administrative duties", "banking", "account maintenance"], "requirements": {"degrees": ["degree or above", "bachelor"], "majors": [], "languages": ["english", "chinese", "mandarin"], "language_level": ["good command", "proficient"], "hard_skills": ["aml", "hksi", "maintenance", "sfo", "kyc", "documentations"], "soft_skills": ["communication skills", "self-motivated", "work independently", "detail oriented", "customer-focused mindset", "organization skills", "ideal"], "languages_combined": [{"language": "english", "language_level": ["good command", "proficient"]}, {"language": "chinese", "language_level": ["good command", "proficient"]}, {"language": "mandarin", "language_level": ["good command", "proficient"]}]}, "experience_required": {"duration": ["at least 2 years"], "field": []}}, {"job_id": "100003009054200", "location_code": "hk", "company": "First Commercial Bank, Ltd", "job_title": "Deposit / Remittance Clerk", "description": "\u4e00\u822c\u5b58\u6b3e\u6216\u532f\u514c\u90e8\u9580\u6587\u54e1\n\nMain Responsibilities:\n\nHandle\u00a0counter transactions and opening accounts etc\nPerform inward/outward remittance and document\nHandle other duties as assigned by supervisors\n\n\nRequirements:\n\nAssociate Diploma or equivalent\nGood command in written & spoken Mandarin is a must, fluent in English and Cantonese\nProficient in MS Office applications including Chinese word processing\nFresh graduates are also welcomed\n\n\nWe offer competitive salary & attractive fringe benefits package to the right candidates. Please send your full resume, expected salary to us.\n", "employment_types": ["Full Time", "Permanent"], "selling_points": ["general duties of deposit or remittance clerk", "5 days work week, double pay & bonus", "Fresh graduates are also welcome"], "locations": ["Tsim Sha Tsui"], "categories": ["Banking / Finance", "Corporate Banking", "Private Banking", "Retail Banking"], "post_time": "2022-01-17T08:47:27Z", "salary": {"currency": null, "max": null, "min": null, "period": "monthly", "term": null}, "salary_visible": false, "title_keywords": ["clerk"], "responsibilities": ["other duties", "transactions"], "requirements": {"degrees": ["diploma"], "majors": [], "languages": ["cantonese", "english", "chinese", "mandarin"], "language_level": ["proficient", "good command", "fluent"], "hard_skills": ["chinese word processing", "ms office"], "soft_skills": [], "languages_combined": [{"language": "cantonese", "language_level": ["good command", "fluent"]}, {"language": "english", "language_level": ["good command", "fluent"]}, {"language": "chinese", "language_level": ["proficient"]}, {"language": "mandarin", "language_level": ["good command", "fluent"]}]}, "experience_required": {"duration": [], "field": []}}, {"job_id": "100003009054848", "location_code": "hk", "company": "Cathay United Bank Company, Limited", "job_title": "Vice President, Relationship Management - Private Wealth Management", "description": "Responsibilities:\n\nAcquire new Ultra High Net Worth Individuals and solicit business opportunities through cross-selling, referral and personal business connections\n\u200bIdentify customers\u2019 needs and provide customized solutions on a comprehensive range of private banking, investment and wealth management products to customers\nProvide updated financial market information, professional advice and quality services to clients\nPromote long term client relationships and loyalty\nEnsure all selling activities are in compliance with the Bank\u2019s guidelines\n\n\u00a0Requirements:\n\nDegree holder in Finance, Economic, Business or relevant disciplines preferred\nAt least\u00a05 years\u2019 Relationship Manager or Investment Advisor experience in private banking or ultra high net worth clients sector, experience in Taiwanese market a definite advantage\nKnowledge of private banking and treasury services, good understanding of banking operations and policies\nPass in the HKSI Licensing Examination and qualified under SFO for handling Regulated Activities Type 1\nSelf-initiated and a strong team player\nGood communication and interpersonal skills\nFluent in Mandarin, Cantonese and English\n\nWe offer attractive remuneration package and comprehensive fringe benefits. Interested parties please e-mail your full resume with current and expected salary by clicking \"Apply Now\".\u00a0\n\nPersonal information collected will be used for considering suitability for the post and strictly in accordance with our personal data policies.\u00a0 It is our policy to retain the personal data of unsuccessful applicants for future recruitment purposes for a period of maximum two years.", "employment_types": ["Full Time", "Permanent"], "selling_points": ["Degree holder in Finance, Economic, Business", "At least 5 years\u2019 experience", "Private Banking"], "locations": ["Causeway Bay"], "categories": ["Banking / Finance", "Private Banking", "Wealth Management"], "post_time": "2022-01-17T11:43:01Z", "salary": {"currency": null, "max": null, "min": null, "period": "monthly", "term": null}, "salary_visible": false, "title_keywords": ["vice president", "wealth management"], "responsibilities": ["management", "market information", "guidelines", "business opportunities", "compliance", "quality", "banking"], "requirements": {"degrees": ["degree holder"], "majors": ["finance", "business"], "languages": ["cantonese", "english", "mandarin"], "language_level": ["fluent"], "hard_skills": ["sfo", "hksi"], "soft_skills": ["team player", "communication and interpersonal skills"], "languages_combined": [{"language": "cantonese", "language_level": ["fluent"]}, {"language": "english", "language_level": ["fluent"]}, {"language": "mandarin", "language_level": ["fluent"]}]}, "experience_required": {"duration": ["at least 5 years"], "field": ["investment", "banking"]}}, {"job_id": "100003009054837", "location_code": "hk", "company": "Cathay United Bank Company, Limited", "job_title": "AVP, Product & Investment Advisory - Private Wealth Management Business Management", "description": "Responsibilities:\n\nAnalyze the market trend and keep the clients updated with market information\nWork closely with relationship managers to maintain and facilitate the sales of investment products\nProvide professional recommendations of investment products;\nMonitor customers\u2019 investment portfolios and provide advices to achieve target returns;\nAlert client for any significant market movement and make suggestions on time;\nFacilitate trade dealing and prepare relevant documents;\nEnsure proper conduct and selling procedures are complied with rules and regulations\n\nIdeal candidates should possess:\n\nBachelor\u2019s degree or above in Business Studies, major in Finance or related discipline preferred;\nAt least 8 years\u2019 relevant work experience serving the high net-worth clients;\nExperience in dealing investment products, including equity, fixed income products, mutual funds and structured products;\nExperience in alternative investment, i.e. Private Equity Fund, will be highly appreciated;\nKnowledge of Banking Ordinance, Securities and Futures Ordinance and related Codes is preferred;\nRelevant Individual with SFC Type 1 license is a must;\nExcellent communication and interpersonal skills;\nSelf-motivated with strong customer service mindset;\nProficient in written and spoken English and Chinese (Mandarin & Cantonese)\n\nWe offer attractive remuneration package and comprehensive fringe benefits. Interested parties please e-mail your full resume with current and expected salary by clicking \"Apply Now\".\u00a0\n\nPersonal information collected will be used for considering suitability for the post and strictly in accordance with our personal data policies.\u00a0 It is our policy to retain the personal data of unsuccessful applicants for future recruitment purposes for a period of maximum two years.", "employment_types": ["Full Time", "Permanent"], "selling_points": ["Bachelor's degree holder", "At least 8 years\u2019 experience", "Private Banking / Private Wealth Management"], "locations": ["Causeway Bay"], "categories": ["Banking / Finance", "Private Banking", "Wealth Management"], "post_time": "2022-01-17T11:36:18Z", "salary": {"currency": null, "max": null, "min": null, "period": "monthly", "term": null}, "salary_visible": false, "title_keywords": ["wealth management"], "responsibilities": ["regulations", "provide advices", "market information", "investment portfolios", "monitor", "procedures", "communication", "maintain", "customer service", "banking"], "requirements": {"degrees": ["degree or above", "bachelor"], "majors": ["finance", "business"], "languages": ["cantonese", "english", "chinese", "mandarin"], "language_level": ["proficient"], "hard_skills": ["investment products", "securities and futures ordinance", "make", "private equity", "codes"], "soft_skills": ["self-motivated", "customer service", "communication and interpersonal skills", "structured", "ideal"], "languages_combined": [{"language": "cantonese", "language_level": ["proficient"]}, {"language": "english", "language_level": ["proficient"]}, {"language": "chinese", "language_level": ["proficient"]}, {"language": "mandarin", "language_level": ["proficient"]}]}, "experience_required": {"duration": ["at least 8 years"], "field": ["investment"]}}, {"job_id": "100003009049131", "location_code": "hk", "company": "HGC Investment Management (HK) Limited", "job_title": "Wealth Management Partner & Executives", "description": "HGC Investment Management\n\nHGC is an asset management arm of a major immigration related investment group with a large pool of HWN clients. HGC\u2019s AUM is in excess of US 1 billion dollars. It has established EAM relationship with private banks and financial institutions in Hong Kong and Singapore to offer clients both discretional and advisory investment services. We offer full range of financial products plus a full spectrum of alternative products covering insurance, immigration, PE investments, Pre-IPOs and properties. Headquartered in Beijing and with offices in HK, Shanghai and Singapore. HGC Hong Kong is licensed by the Securities and Futures Commission in Hong Kong in Type 1, 4 & 9 activities.\n\nFamily Office Partner & Executives\n\nWe welcome financial professionals with insurance and investment advisory background to join us as a partner to help develop our wealth management business. We operate attractive profit sharing arrangement for our business partners. Successful candidates will allow access to group company HNW client base to explore new business potentials.\n\nRequirements\n\n\nBachelor degree in Finance, Accounting or relevant discipline\nKnowledge in investment consultancy, financial product sales or insurance agency\nExtensive experience in handling and maintaining client relationship\nExcellent interpersonal and communication skills\n\nInterested parties please send your full resume, with contact telephone number by clicking APPLY NOW quoting the post applied. All information received will be kept in strict confidence and only for employment-related purpose.\n", "employment_types": ["Full Time", "Part Time", "Freelance"], "selling_points": ["Wealth management and investment advisory", "Knowledgeable in financial products", "Attention to clients' investment needs"], "locations": ["Central"], "categories": ["Banking / Finance", "Private Banking", "Financial Services"], "post_time": "2022-01-17T07:26:29Z", "salary": {"currency": null, "max": null, "min": null, "period": "monthly", "term": null}, "salary_visible": false, "title_keywords": ["wealth management"], "responsibilities": ["management", "maintaining", "develop", "communication", "client base", "insurance", "asset management"], "requirements": {"degrees": ["degree", "bachelor"], "majors": ["finance", "accounting"], "languages": [], "language_level": [], "hard_skills": ["plus", "pe"], "soft_skills": ["communication skills", "extensive", "interpersonal"], "languages_combined": []}, "experience_required": {"duration": [], "field": []}}, {"job_id": "100003009053206", "location_code": "hk", "company": "Asia Progress Executive Limited", "job_title": "Associate, Financial Crime Compliance (Private Banking)  - Compliance Department", "description": "Our client is a European Private Banking to cope with the rapid business\u00a0expansion, they are now inviting high caliber candidates to join the team\n\nAssociate ,Financial Crime Compliance ( Private Banking) - Compliance Department\u00a0\n\nResponsibilities:\n\nAssist the Head of Financial Crime to establish, review and update the AML related guidelines, policies and procedural manuals to ensure they are in line with Group and regulatory requirements;\nReview and investigate transactions triggered by monitoring systems or escalated by front office or other monitoring parties for potential financial crime risks; Report suspicious transactions and escalate for management oversight timely to ensure adequate follow up actions and ongoing monitoring;\nMonitor effective operation of AML tools and processes for transaction monitoring, client screening, payment screening and client risk assessment; Escalate issues for timely resolution and manage necessary remediation;\nConduct regular recalibration and tuning of parameters and drive enhancements for AML tools and systems;\nReview escalated alerts stopped on payment screening system and escalate transactions potentially related to money laundering and sanctions;\nReview alerts from ongoing client screening and manage the escalation of true hits for risk reclassification and monitoring follow up actions;\nTrigger follow up actions and KYC updates upon irregularities noted from transaction monitoring or client screening;\nAssist the Head of AML / Compliance in preparing internal AML training materials;\nPrepare materials for periodic AML governance meetings;\nPerform ad hoc tasks as assigned by Head of AML/Compliance from time to time;\nAssist in audits and inspections, and investigations where required\nInvolvement in special work projects as and when required\nAssist Head of Compliance, Hong Kong and the Compliance team in any other work matters;\nMust solid exp in transaction monitoring and manage AML tools and System\u00a0\n\nCompetencies:\n\nBasic bachelor degree; \u00a0\n5 \u2013 8 years of relevant experience in general compliance and financial crime compliance in private banking industry\u00a0\nMust solid exp in transaction monitoring and manage AML tools and System\u00a0\nA keen interest to learn and perform compliance matters;\nGood interactive, communication and writing skills;\nAble to provide alternative solutions to business;\nMotivated and innovative; able to handle issues and resolve challenges in collaboration with colleagues;\nTeam player\n\nPlease send full resume with\u00a0present & expected\u00a0salary to expedite sourcing\u00a0in\u00a0MS-WORD\u00a0format by clicking \u201cAPPLY NOW\u201d\nPlease quote our reference in your application\nPersonal data provided by job applicants will be used strictly in accordance with the employer\u2019s personal data policies, a copy of which will be provided upon request\nAll information provided will be used for recruitment purpose only", "employment_types": ["Full Time"], "selling_points": ["Deg 5yr Financial crime compliance privatebanking", "AMLtransaction monitoring&manage AML tools&System", "AML/KYC review/CDD periodic review, CDD advisory"], "locations": ["Central & Western Area"], "categories": ["Banking / Finance", "Private Banking", "Professional Services", "Legal & Compliance", "Wealth Management"], "post_time": "2022-01-17T06:26:38Z", "salary": {"currency": null, "max": null, "min": null, "period": "monthly", "term": null}, "salary_visible": false, "title_keywords": ["associate", "private banking"], "responsibilities": ["regulatory requirements", "transactions", "communication", "payment", "personal data", "compliance", "monitor", "resolution", "kyc", "banking", "report", "management", "review", "monitoring", "ad hoc tasks", "audits", "aml", "irregularities", "guidelines", "policies", "systems", "recruitment"], "requirements": {"degrees": ["degree", "bachelor"], "majors": [], "languages": [], "language_level": [], "hard_skills": ["ms-word", "basic", "aml", "writing skills", "rapid", "kyc"], "soft_skills": ["keen", "timely", "writing skills", "communication", "motivated", "team player", "innovative"], "languages_combined": []}, "experience_required": {"duration": ["8 years"], "field": ["banking industry", "compliance", "general compliance", "relevant experience", "financial"]}}, {"job_id": "100003009054844", "location_code": "hk", "company": "Cathay United Bank Company, Limited", "job_title": "Vice President, Business Control - Private Wealth Management Business Management", "description": "Responsibilities:\n\nReporting to the Head of Private Wealth Management, the candidate shall lead a small team to:\n\nAct as first line of defense, monitor daily activities of PWM frontline staff (RM, ARM, IC) are compliant to regulatory requirements and internal policies\u00a0\nDevelop quantitative risk control framework for risk identification, measurement, management and reporting\nCommunicate with frontline staff regularly on significant risk items/irregularities found in investment transactions, areas of improvement in securities dealing, and provide guidance on investment suitability check before executing investment transactions for customers\nMonitor customer account opening and on-boarding procedures\nParticipate in projects and initiatives, system transformation etc.\nProvide regular training to frontline staff on regulatory requirements and dealing in securities\nRegularly review and update internal policies and procedures, to be in line with latest regulations, technology and industry best practices\nWork closely with the second line of defense and different stakeholders on policy and procedure implementation\n\nIdeal candidates should possess:\n\nBachelor\u2019s degree or equivalent academic qualification\nAt least 8 years\u2019 relevant risk control and investment suitability monitoring experience in private banking / private wealth management\nStrong knowledge of regulatory requirements on investment suitability framework/cross-border activities/AML/CTF/FATCA/CRS\nSelf-motivated, independent with strong communication skills\nProficient in written and spoken Chinese (Mandarin and Cantonese) and English\n\nWe offer attractive remuneration package and comprehensive fringe benefits. Interested parties please e-mail your full resume with current and expected salary by clicking \"Apply Now\".\u00a0\n\nPersonal information collected will be used for considering suitability for the post and strictly in accordance with our personal data policies.\u00a0 It is our policy to retain the personal data of unsuccessful applicants for future recruitment purposes for a period of maximum two years.", "employment_types": ["Full Time", "Permanent"], "selling_points": ["Bachelor's degree holder", "At least 8 years\u2019 experience", "Private Banking / Private Wealth Management"], "locations": ["Causeway Bay"], "categories": ["Banking / Finance", "Private Banking", "Wealth Management"], "post_time": "2022-01-17T11:41:10Z", "salary": {"currency": null, "max": null, "min": null, "period": "monthly", "term": null}, "salary_visible": false, "title_keywords": ["vice president", "wealth management"], "responsibilities": ["regulations", "regulatory requirements", "transactions", "communication", "control", "account opening", "monitor", "measurement", "implementation", "develop", "banking", "reporting", "management", "review", "procedures", "monitoring", "executing", "provide guidance", "communicate with", "irregularities", "aml", "policies", "lead a small team"], "requirements": {"degrees": ["degree", "bachelor"], "majors": [], "languages": ["cantonese", "english", "chinese", "mandarin"], "language_level": ["proficient"], "hard_skills": ["small", "crs", "aml", "account opening", "fatca"], "soft_skills": ["communication skills", "self-motivated", "independent", "ideal"], "languages_combined": [{"language": "cantonese", "language_level": ["proficient"]}, {"language": "english", "language_level": ["proficient"]}, {"language": "chinese", "language_level": ["proficient"]}, {"language": "mandarin", "language_level": ["proficient"]}]}, "experience_required": {"duration": ["at least 8 years"], "field": ["management", "investment", "banking"]}}, {"job_id": "100003009050282", "location_code": "hk", "company": "China Construction Bank (Asia) Corporation Limited", "job_title": "VP/AVP, Relationship Manager - Private Banking", "description": "Main Responsibilities\n- Provide wealth management services to target market\n- Handle client relationships from perspective of providing tailored solutions\n- Acquire wide range of product knowledge and continuous updates\n- Keep abreast of updates on global investment market\n- Groom junior Relationship Managers to support the business\n\nRequirements\n- University degree\n- 5 years or above relevant experience in Private Banking\n- Possess HKSI and IIQE qualifications\n- Qualification in ECF is preferred\n- Possess CPWP certification or pass in relevant papers\n- Sales and customer oriented, with strong communication and interpersonal skills\n- Proficiency in both written and spoken English and Chinese; fluency in Putonghua is required\n- Candidate with more experience will be considered as Team Head\n", "employment_types": ["Full Time"], "selling_points": ["University degree", "5 years or above relevant exp in Private Banking", "Possess HKSI and IIQE qualifications"], "locations": ["Central"], "categories": ["Banking / Finance", "Private Banking"], "post_time": "2022-01-14T10:03:23Z", "salary": {"currency": null, "max": null, "min": null, "period": "monthly", "term": null}, "salary_visible": false, "title_keywords": ["relationship manager", "private banking"], "responsibilities": ["management"], "requirements": {"degrees": ["university degree"], "majors": [], "languages": ["putonghua", "english", "chinese"], "language_level": ["fluency", "proficiency"], "hard_skills": ["iiqe", "hksi"], "soft_skills": ["communication and interpersonal skills"], "languages_combined": [{"language": "putonghua", "language_level": ["fluency"]}, {"language": "english", "language_level": ["proficiency"]}, {"language": "chinese", "language_level": ["proficiency"]}]}, "experience_required": {"duration": ["5 years"], "field": ["relevant experience", "team", "banking"]}}, {"job_id": "100003009047327", "location_code": "hk", "company": "NewPages Recruitment Company Limited", "job_title": "Assistant Relationship Manager (Private Wealth Department) - Support role", "description": "We have serval clients seeking for experience candidate to join their banking team.\u00a0\n\nAssistant Relationship Manager\u00a0\n\n\nResponsibilities:\n\nAssist multiple production support functions to aid partners in fulfilling sales requirements\nMonitor controls based on regulatory and reporting requirements\nDelivery and administration of access media and sales tools and assist in the overflow of digital self-service media\nAid in the customer service process to ensure the quality of customer service\nManage the safekeeping and control of files during operation hours\n\nRequirement:\n\nDegree Holder\nMinimum 3 year banking experience, prefer with sales support experience in Private Banking/ Private Wealth Department\u00a0\nHolding HKSI 1,7,8 is preferred\nProficient in English, Mandarin and Cantonese", "employment_types": ["Full Time", "Permanent"], "selling_points": ["non sales role", "stable", "Private Banking"], "locations": ["Not Specified"], "categories": ["Banking / Finance", "Private Banking", "Retail Banking", "Wealth Management"], "post_time": "2022-01-14T02:50:06Z", "salary": {"currency": "HKD", "max": 34999, "min": 30000, "period": "monthly", "term": null}, "salary_visible": true, "title_keywords": ["assistant relationship manager"], "responsibilities": ["reporting", "control", "monitor", "quality", "customer service", "administration"], "requirements": {"degrees": ["degree holder"], "majors": [], "languages": ["cantonese", "english", "mandarin"], "language_level": ["proficient"], "hard_skills": ["sales support", "hksi"], "soft_skills": [], "languages_combined": [{"language": "cantonese", "language_level": ["proficient"]}, {"language": "english", "language_level": ["proficient"]}, {"language": "mandarin", "language_level": ["proficient"]}]}, "experience_required": {"duration": ["minimum 3 year"], "field": ["sales support", "banking experience", "banking"]}}, {"job_id": "100003009050279", "location_code": "hk", "company": "China Construction Bank (Asia) Corporation Limited", "job_title": "Manager, Platform Management (Private Banking)", "description": "PRINCIPAL ACCOUNTABILITIES\n\n\nImplement regulatory compliance to ensure the Division\u2019s conformity to all compliance rules, guidelines, policies and procedures in relation to client on-boarding process, selling process and transactional monitoring.\u00a0\u00a0\nHandle compliance reviews and audit reviews in the Division, including material submission, provision of response, and following up on rectifications of findings.\nEscalate any issues and risks to the management as appropriate in a timely manner.\nPrepare the write up of the Division\u2019s operational procedures and manuals, investment scripts in accordance to the bank\u2019s regulatory policies and compliance standard.\nResponsible for operational activities as well as to set and implement operational guidelines and policies to maintain excellent service standards.\n\nREQUIREMENTS:\n\nUniversity graduate in Accounting/Finance or related disciplines\nAt least 2 years\u2019 experience in risk management, relationship management or operations in banking industry\nGood communication and interpersonal skills\nConversant with operational procedures and regulatory requirements, able to devise and maintain the effective quality assurance mechanism\u00a0\nIndependent, self-motivating and able to work under pressure\nExcellent command of English & Chinese (including Mandarin & Cantonese)\n\nApplicants who are not contacted within 8 weeks may consider their applications unsuccessful and their personal data will be retained by the bank for a period up to two years.\n\nAll information provided by applicants will be used for recruitment purposes only and will be used strictly in accordance with the bank\u2019s personal data policies, a copy of which will be provided upon\u00a0request.", "employment_types": ["Full Time", "Permanent"], "selling_points": ["Private Banking", "Risk management, Relationship management", "Platform Management and operation"], "locations": ["Central"], "categories": ["Banking / Finance", "Private Banking"], "post_time": "2022-01-14T10:03:22Z", "salary": {"currency": null, "max": null, "min": null, "period": "monthly", "term": null}, "salary_visible": false, "title_keywords": ["manager", "private banking"], "responsibilities": ["operations", "regulatory requirements", "quality", "audit", "communication", "service standards", "maintain", "personal data", "work under pressure", "compliance", "operational procedures", "banking", "management", "monitoring", "procedures", "guidelines", "policies", "a timely manner", "recruitment"], "requirements": {"degrees": ["university graduate"], "majors": ["related disciplines", "finance", "accounting"], "languages": ["cantonese", "english", "chinese", "mandarin"], "language_level": ["excellent"], "hard_skills": [], "soft_skills": ["independent", "responsible", "timely", "communication and interpersonal skills", "work under pressure"], "languages_combined": [{"language": "cantonese", "language_level": ["excellent"]}, {"language": "english", "language_level": ["excellent"]}, {"language": "chinese", "language_level": ["excellent"]}, {"language": "mandarin", "language_level": ["excellent"]}]}, "experience_required": {"duration": ["at least 2 years"], "field": ["risk management", "management", "banking industry"]}}, {"job_id": "100003009054312", "location_code": "hk", "company": "Infinity Asset Management Limited", "job_title": "Relationship Manager / Independent Private Banker", "description": "Job Descriptions:\n\n1. Develop and\u00a0maintain good\u00a0relationships with high-net-worth clients\n2. Acquire new high-net-worth clients\n3. Manage your own AUM book and achieve sales target\n4. Provide portfolio management services to clients\n5. Update clients\u2019 investment objectives and risk appetite\n\nQualifications:\n\n1. Min 5 years\u2019 financial working experience, preferably in private banking, investment banking, premium banking, retail banking\n2. Strong client network and good interpersonal communication skills\n3. Solid knowledge of cross-asset classes investment instruments\n4. Familiar with PB / IAM / EAM business model\n5. Eligible to be SFC license Type 4 and 9 representatives preferred\n\nWe offer attractive remuneration package to successful candidates. \u00a0Please\u00a0apply directly to this job post with expected and current salary.\n\nAbout\u00a0Infinity Asset Management Limited\n\nInfinity Asset Management is a Hong Kong based fast growing asset management company. Our company aims to develop external asset management and hedge fund business in Hong Kong. We provide opportunities to candidates with the ambition to obtain experience in the high-net-worth wealth management industry.", "employment_types": ["Full Time"], "selling_points": ["Welcome retired banker", "Building your own team", "High paid-out ratio"], "locations": ["Admiralty"], "categories": ["Banking / Finance", "Private Banking", "Wealth Management", "Asset Management"], "post_time": "2022-01-17T09:06:39Z", "salary": {"currency": null, "max": null, "min": null, "period": "monthly", "term": null}, "salary_visible": false, "title_keywords": ["relationship manager"], "responsibilities": ["management", "sales target", "develop", "communication", "maintain", "banking"], "requirements": {"degrees": [], "majors": [], "languages": [], "language_level": [], "hard_skills": ["sfc license"], "soft_skills": ["communication skills", "interpersonal"], "languages_combined": []}, "experience_required": {"duration": ["min 5 years"], "field": ["investment", "retail banking", "banking", "financial"]}}, {"job_id": "100003009043146", "location_code": "hk", "company": "Chasseur Pro Executive Consultant Limited", "job_title": "Relationship Manager Assistant", "description": "Responsibilities:\nPromote full-range of retail banking products and services to achieve sales targets\nIdentify customers\u2019 needs and match their needs with appropriate products and services including account opening, credit card, mortgage, personal loan and insurance and MPF products.\nMaintain good relationship with both existing and new clients.\nRequirements:\nDegree holder or above, with minimum 3 years\u2019 experience in promoting retail banking products.\nPasses in Insurance, Securities and Futures Intermediaries Examinations are required. (Qualified under SFO for handling Regulated Activities Types 1 & 4).\nPass in the MPF Intermediaries Qualifying Examination (Optional)\nProfessional qualification of ARWP is an advantage.\nCandidates with less experience will be considered as Deputy Financial Services Manager.\nCandidates with more experience will be considered as Senior Investment & Product Manager (Private Banking)", "employment_types": ["Full Time"], "selling_points": ["With IIQE 1,2,3 & HKSI 1,7,8", "Over 2 years Retail Banking Experience", "Non Sales role"], "locations": ["Central"], "categories": ["Banking / Finance", "Investment", "Private Banking", "Wealth Management"], "post_time": "2022-01-12T09:56:06Z", "salary": {"currency": null, "max": null, "min": null, "period": "monthly", "term": null}, "salary_visible": false, "title_keywords": ["relationship manager", "assistant"], "responsibilities": ["mpf", "account opening", "maintain good relationship", "banking", "insurance"], "requirements": {"degrees": ["degree holder"], "majors": [], "languages": [], "language_level": [], "hard_skills": ["sfo"], "soft_skills": [], "languages_combined": []}, "experience_required": {"duration": ["minimum 3 years"], "field": ["retail banking", "financial services", "investment", "banking"]}}, {"job_id": "100003009050647", "location_code": "hk", "company": "Bank of Communications (Hong Kong) Limited", "job_title": "Investment & Product Manager (Private Banking)", "description": "Responsibilities\n\nSupport Relationship Managers (RMs) to provide excellent service to high net-worth clients so as to achieve client retention\nUnderstand client requirements and assist RMs in daily maintenance of account relationships\nInitiate account openings / closures / update instruction checklists and interface with client to ensure completion of documentation requirements\nHandle and follow up clients' enquiries, service requests and complaints in a timely and professional manner\nEnsure timely follow up on client calls / queries\nEnsure compliance with all regulatory requirements\nProvide administrative support to the team\n\nRequirement\n\nDegree holder in Business, Financial Services, Economics or related disciplines.\n2 years\u2019 working experience preferably in brokerage industry.\nHolder of SFC Representative License of Type 1 is an advantage.\nProactive, patient and responsible.\nGood interpersonal skills, detail-oriented and customer-oriented.\nGood command of spoken and written English and Chinese. Proficiency in Putonghua is a must.\nMature, independent and self-motivated, ability to work effectively under pressure and be a team player.\nWe offer attractive remuneration package and fringe benefits to the right candidate. Interested applicants please send detailed resume stating present & expected salaries and date of availability to Human Resources Department by clicking \"APPLY NOW\".\n\nFurther information about our group companies can be found at www.gfgroup.com.hk and www.gf.com.cn.\n\nAll applications will be treated in the strictest confidence and personal data collected will be used for recruitment purpose only.", "employment_types": ["Full Time"], "selling_points": [], "locations": ["Not Specified"], "categories": ["Banking / Finance", "Investment", "Private Banking", "Others"], "post_time": "2022-01-14T11:06:26Z", "salary": {"currency": null, "max": null, "min": null, "period": null, "term": null}, "salary_visible": false, "title_keywords": ["product manager", "private banking"], "responsibilities": ["maintenance", "regulatory requirements", "professional manner", "ensure compliance", "documentation", "provide administrative support"], "requirements": {"degrees": ["degree holder"], "majors": ["related disciplines", "economics", "business"], "languages": ["putonghua", "english", "chinese"], "language_level": ["proficiency", "good command"], "hard_skills": [], "soft_skills": ["work effectively", "self-motivated", "independent", "under pressure", "responsible", "mature", "detail-oriented", "customer-oriented", "interpersonal skills", "patient", "team player", "proactive"], "languages_combined": [{"language": "putonghua", "language_level": ["proficiency"]}, {"language": "english", "language_level": ["good command"]}, {"language": "chinese", "language_level": ["good command"]}]}, "experience_required": {"duration": ["2 years"], "field": ["brokerage"]}}, {"job_id": "100003009044235", "location_code": "hk", "company": "Asia Progress Executive Limited", "job_title": "Client Onboarding/KYC -  Wealth Management /Private banking", "description": "Job Type\nFull Time\nJob Functions\nBanking / Finance, Financial Services, Others", "employment_types": ["Full Time"], "selling_points": ["Client On boarding/CDD /KYC perodic review/Documen", "Deg 3yrs ClientOn boarding/KYC in Private Banking", "Familiar Wealthmanagement products/Private Bank"], "locations": ["Central & Western Area"], "categories": ["Banking / Finance", "Private Banking", "Order Processing & Operation / Settlement", "Wealth Management"], "post_time": "2022-01-13T03:29:34Z", "salary": {"currency": null, "max": null, "min": null, "period": "monthly", "term": null}, "salary_visible": false, "title_keywords": ["wealth management", "private banking"], "responsibilities": ["banking"], "requirements": {"degrees": [], "majors": [], "languages": [], "language_level": [], "hard_skills": [], "soft_skills": [], "languages_combined": []}, "experience_required": {"duration": [], "field": []}}, {"job_id": "100003009046177", "location_code": "hk", "company": "ConnectedGroup Limited", "job_title": "Head of Business Development, Family Office (Based in China)", "description": "A rare and unique opportunity to build and develop a robust client portfolio from scratch, comprising Ultra-High-Net-Worth individuals and Family Offices with interest to invest, has arisen. Our client is seeking an experienced Head of Business Development to join a growing team of Family Office Specialists. The successful candidate will be involved in all facets of the process, including business development, generating leads, event management, partnership development, and client servicing. The ideal individual will be highly driven, resourceful, and have a minimum of 7 to 10 years of experience managing relationships with UHNW individuals and/or Family Offices.\n\nResponsibilities:\n\nBuild and main relationships with UHNW and Family Office investors\nGenerate and qualify new leads and be resourceful in using multiple approaches to penetrate prospective accounts\nEngage specialists and partners to address clients' needs\nAttend conferences, events, and seminars for marketing opportunities\nConduct duty visits across Southern China\nMaintain a high level of client satisfaction by generating, managing and proactively advising for a Ultra-High-Net-Worth portfolio of clients\nFollow up on enquiries proactively\nDevelop and drive marketing plans as well as engagement plans\n\nRequirements:\n\nBachelor's degree holder in Business Administration, Finance or related disciplines\nA minimum of 7 to 10 years' of experience managing relationships with UHNW clients and/or Family Offices would be essential\nStrong business development and project management kills\nImpeccable interpersonal, communication, and presentation skills\nSound knowledge of financial industry and current market conditions\nInteractive skills in order to understand client needs and take action with the appropriate solutions\nProficiency in written and spoken Cantonese, English, and Mandarin\nHave a comprehensive understanding of the local regulatory requirements of the investment advisory business and apply this knowledge appropriately\nWilling to travel", "employment_types": ["Full Time", "Permanent"], "selling_points": ["", "", ""], "locations": ["Not Specified"], "categories": ["Banking / Finance", "Investment", "Private Banking", "Financial Services"], "post_time": "2022-01-13T09:50:51Z", "salary": {"currency": null, "max": null, "min": null, "period": "monthly", "term": null}, "salary_visible": false, "title_keywords": [], "responsibilities": ["marketing plans", "develop", "conferences", "maintain", "plans"], "requirements": {"degrees": ["bachelor", "degree holder"], "majors": ["related disciplines", "finance", "business administration"], "languages": ["cantonese", "english", "mandarin"], "language_level": ["proficiency"], "hard_skills": ["project management"], "soft_skills": ["communication", "project management", "presentation skills", "comprehensive", "interpersonal"], "languages_combined": [{"language": "cantonese", "language_level": ["proficiency"]}, {"language": "english", "language_level": ["proficiency"]}, {"language": "mandarin", "language_level": ["proficiency"]}]}, "experience_required": {"duration": ["minimum of 7 to 10 years"], "field": []}}, {"job_id": "100003009039916", "location_code": "hk", "company": "Links International", "job_title": "Relationship Manager - In-house Insurance Specialist", "description": "Relationship Manager\n\nThis is a new headcount in addition to our current Private Wealth team of 6-7pax\nWe are looking for candidate with entrepreneurial minded for expanding the insurance patch\nSolid insurance knowledge is required, and the ideal candidate would be our in-house insurance specialist\nWith other RM's referring clients to them (in related to insurance) and the revenue split with be 25%-25%\nOtherwise, the basic commission rate would be 50% of commission generated (once salary is earned)", "employment_types": ["Full Time", "Permanent"], "selling_points": ["Fast expanding wealth management firm", "New market with sufficient resources", "Work-life balance"], "locations": ["Tsim Sha Tsui"], "categories": ["Banking / Finance", "Private Banking", "Insurance", "Insurance Agent / Broker", "Wealth Management"], "post_time": "2022-01-11T15:13:31Z", "salary": {"currency": null, "max": null, "min": null, "period": "monthly", "term": null}, "salary_visible": false, "title_keywords": ["insurance specialist", "relationship manager"], "responsibilities": ["insurance"], "requirements": {"degrees": [], "majors": [], "languages": [], "language_level": [], "hard_skills": ["basic"], "soft_skills": ["ideal"], "languages_combined": []}, "experience_required": {"duration": [], "field": []}}, {"job_id": "100003009042466", "location_code": "hk", "company": "Bank of Communications Trustee Limited", "job_title": "Contract Officer, Operations Department (Ref. OPS-O)", "description": "Responsibilities:\nProcess member enrolments, terminations, contributions in accordance with all regulatory requirements as well as company procedures and policies\nEnsure to follow up outstanding issues and handle customer\u2019s enquires on a timely and professional manner\nPerform other job related duties or assist in ad-hoc projects as required\nAssist in carrying out various functional testing for system enhancement purposes\nRequirements:\nDegree holder with minimum 4 years\u00a0of pension fund administration is highly preferred\nKnowledge in MPF and ORSO regulation is a must\nDetail-oriented and good team player\nGood interpersonal skills and good command of both written and spoken English and Chinese\nPC literate in Word, Excel, Powerpoint and Chinese word processing\nImmediately available is highly preferred\nPlease click \"Apply Now\" to submit your application.\nPersonal data collected will be used for recruitment purpose only.", "employment_types": ["Full Time", "Contract"], "selling_points": ["Process member enrolments, terminations", "Assist in carrying out various functional testing", "Degree holder w/ minimum 4 years of pension fund"], "locations": ["Not Specified"], "categories": ["Banking / Finance", "Private Banking", "Others", "Order Processing & Operation / Settlement"], "post_time": "2022-01-12T07:37:34Z", "salary": {"currency": null, "max": null, "min": null, "period": "monthly", "term": null}, "salary_visible": false, "title_keywords": ["operations", "contract officer"], "responsibilities": ["regulatory requirements", "policies", "procedures", "professional manner", "testing", "ad-hoc projects"], "requirements": {"degrees": ["degree holder"], "majors": [], "languages": ["english", "chinese"], "language_level": ["good command", "good"], "hard_skills": ["excel", "chinese word processing", "word", "powerpoint", "pc literate"], "soft_skills": ["good team player", "interpersonal skills", "detail-oriented"], "languages_combined": [{"language": "english", "language_level": ["good command", "good"]}, {"language": "chinese", "language_level": ["good command", "good"]}]}, "experience_required": {"duration": [], "field": []}}, {"job_id": "100003009043985", "location_code": "hk", "company": "Avenue Family Office Limited", "job_title": "Graduate Trainee (For 2021 graduates) / Full-time Intern (For 2022 graduates)", "description": "Responsibilities\n\nPractice on asset management, project, research, operation and analysis skills\nWork with colleagues in different departments\nLiaise with professional counterparties and execute deals\nDeal with ad hoc tasks as assigned by supervisors\nRequirements\n\nDegree Holder graduated from\u00a0the world's Top 100 universities\u00a0\nPossess less than 1 year working experience, Fresh Graduates are welcomed\nDetermined to advance in asset and fund management\nExcellent in analytical and critical thinking\nStrong in communications skills (spoken & written) in both English & Chinese\nBe a good team player, proactive and highly motivated\nPositive and can-do attitude\nDetailed mind, committed and willing to work in a fast pace environment and excited to learn new things\nProficient in Microsoft Office applications\n\nAVENUE is an Equal Opportunity Employer. We respect and seek to empower each individual and support the diverse cultures, perspectives, skills and experiences within our workforce. Personal data provided by job applicants will be used strictly in accordance with the employer\u2019s personal data policies, a copy of which will be provided immediately upon request.\n", "employment_types": ["Full Time", "Permanent"], "selling_points": ["A young team with happy & relaxing working culture", "Fast learner and keen to develop career in Finance", "Comprehensive exposure to Fund, Bond, Equity, etc."], "locations": ["Central"], "categories": ["Banking / Finance", "Private Banking", "Fund Management", "Asset Management"], "post_time": "2022-01-13T02:40:59Z", "salary": {"currency": null, "max": null, "min": null, "period": "monthly", "term": null}, "salary_visible": false, "title_keywords": ["graduate trainee", "intern"], "responsibilities": ["liaise with", "analysis", "ad hoc tasks", "asset management"], "requirements": {"degrees": ["degree holder"], "majors": [], "languages": ["english", "chinese"], "language_level": [], "hard_skills": ["microsoft office"], "soft_skills": ["good team player", "determined", "can-do attitude", "committed", "diverse", "motivated", "proactive", "detailed mind", "positive"], "languages_combined": [{"language": "english", "language_level": []}, {"language": "chinese", "language_level": []}]}, "experience_required": {"duration": ["1 year"], "field": []}}, {"job_id": "100003009050553", "location_code": "hk", "company": "Page Personnel", "job_title": "PB Credit Risk Transformation Project Manager - Top HK Bank!", "description": "Our client is a leading public bank in Hong Kong and they are currently looking for a role of Private Banking Credit Risk Transformation Program Manager to join the Risk Transformation team to conduct end to end review and drive transformation initiatives for the management of private bank credit risk for Asia Pacific. The candidate should have rich working experience in Credit Risk/ risk transformation within banking industry.\n\nClient Details\n\nOur client is one of Hong Kong's largest listed banks and they are now seeking a position of Private Banking Credit Risk Transformation Program Manager to join the Risk Transformation team to conduct end to end review and drive transformation initiatives for the management of private bank credit risk for Asia Pacific. This role will be supporting the \"Risk 2025\" Programme ('R2025') and Financial Risk Enhancement Programme ('FREP'), a multi-year programme mobilised to fundamentally transform and modernize the bank's approach to managing financial risks, across the first and second lines of defence. As such it will focus on driving the change necessary within the BAU environment to deliver against the objectives of the R2025 and FREP Programme and constituent workstreams as they relate to Private Banking.\n\nDescription\n\nResponsible for driving the delivery of the transformation initiatives while maintaining alignment with Business-led change priorities as well as ensuring interlock with Global Risk programmes such as R2025 and FREP related to Credit Risk\nPartner with the PB Business to drive initiatives related to credit process streamlining and system for risk management. Proactively engage stakeholders and internal customers by understanding the needs and challenges and sharing vision, best practice, and potential solutions; and work collaboratively with Risk IT and Risk Transformation to define new solutions and processes to enhance credit risk management\nDrive change within PB Credit Risk geared towards strategic R2025/FREP Programme objectives. Work within PB Credit Risk and Transformation to deliver a holistic, forward looking & globally integrated Credit Risk Management capability\nIn collaboration with the Global and other Regional Credit Risk teams, design and deliver solutions on a number of Risk Management initiatives including (but not limited to):\nReview opportunities for automating existing PB reports.\n* Support discussions with the Business for infrastructure and data requirements to ensure Risk's requirements are incorporated.\n* To align ASP PB data requirements into the group data management programme (as applicable) and assess/leverage global solutions for data infrastructure, sourcing, and data integrity.\nIdentify streamlining opportunities in the policies and processes for PB Credit Risk including exploring innovative technologies, e.g. Chatbot\nReview current state of services performed by PB Credit Risk and consider opportunities for realignment\nAssess the site and Centre of Excellence ('CoE') delegation authorities and work with relevant stakeholders to review and enable the CoE structure for the future\n\nProfile\n\nBachelor's Degree with major in Business Administration, Risk, Finance, IT or relevant discipline\n10 year of working experience in credit risk or risk transformation in Private Banking or other relevant line of business including Commercial Banking or Global Banking. Experience in Asia Pacific region is preferred\nExperience in projects leading to process efficiency in the customer credit process and internal cost reduction\nStrong English communication skills both verbal and written\nExcellent interpersonal skills, able to manage stakeholders proactively with excellent negotiation and influencing skills\nStrong problem-solving skills and able to work independently under pressure\nStrong self-motivation with sense of ownership and accountability\n\nJob Offer\n\nStimulating and challenging work\nDynamic working environment\nHuge global exposure\n15 days AL\n\nTo apply online please click the 'Apply' button below. For a confidential discussion about this role please contact Esther Liu on +852 2258 3537", "employment_types": ["Full Time", "Permanent"], "selling_points": ["Stimulating and challenging work", "Dynamic working environment", "Huge global exposure"], "locations": ["Not Specified"], "categories": ["Banking / Finance", "Credit Analysis / Approval", "Private Banking", "Risk Management"], "post_time": "2022-01-14T10:43:03Z", "salary": {"currency": null, "max": null, "min": null, "period": "monthly", "term": null}, "salary_visible": false, "title_keywords": ["project manager"], "responsibilities": ["management", "cost", "maintaining", "data", "policies", "review", "teams", "infrastructure", "design", "communication", "reports", "contact", "banking", "administration"], "requirements": {"degrees": ["degree", "bachelor"], "majors": ["finance", "it", "business administration"], "languages": ["english"], "language_level": [], "hard_skills": ["problem-solving skills", "focus", "dynamic", "data management"], "soft_skills": ["communication skills", "work independently", "under pressure", "negotiation", "responsible", "accountability", "integrity", "self-motivation", "interpersonal skills", "dynamic", "problem-solving skills", "focus", "innovative"], "languages_combined": [{"language": "english", "language_level": []}]}, "experience_required": {"duration": ["10 year"], "field": ["banking industry", "commercial", "business", "banking", "credit risk"]}}, {"job_id": "100003009045001", "location_code": "hk", "company": "Hang Seng Bank Ltd", "job_title": "Assistant Business Implementation Manager", "description": "Private Banking and Trust Services - Private Banking Department\n\nWe are currently seeking a high caliber professional to join our department as\u00a0Assistant Business Implementation Manager.\n\n\nPrincipal responsibilities\n\nAssist in the coordination and monitoring of various business/ system implementation projects with front office, middle office, operations, technology and services etc.\nParticipate in the project tasks such as business requirement review, preparation and review of project documentation, workflow and procedure review, review and preparation of testing scope, test plan and test cases, participation in User Acceptance Test and assist in resolving relevant project issues\nWork collaboratively with related stakeholders to ensure successful project delivery\nDeliver training to business users when needed\nDevelop subject matter expertise in business areas/ functions in relation to the assigned projects and provide ongoing support to business users upon system implementation/ workflow implementation\nSupport the procedure manual update in regard to business / system implementation projects\nRequirements\nUniversity degree in a related discipline OR other relevant qualifications\nMinimum 5 years\u2019 relevant experience in banking and project management, with knowledge in private banking operations, wealth management products, system/ workflow implementation etc.\nGreat sense of ownership and servicing mindset\nGood analytical, problem solving, communication and project management skills\nAttentiveness to details, strong self-motivation and ability to work independently and under pressure\nProficiency in both spoken and written English and Chinese, with good knowledge of application software such as MS Excel and PowerPoint\u00a0\n\nIf you would like to explore other opportunities at Hang Seng Hong Kong, please visit\u00a0www.hangseng.com/careers/\u00a0for details.\n\nThe health and safety of our employees and candidates is very important to us. Due to the current situation related to the Novel Coronavirus (2019-nCoV), we\u2019re leveraging our digital capabilities to ensure we can continue to recruit top talent at the HSBC Group. \u00a0As your application progresses, you may be asked to use one of our digital tools to help you through your recruitment journey. \u00a0If so, one of our \u00a0Resourcing colleagues will explain how our video-interviewing technology will be used throughout the recruitment process and will be on hand to answer any questions you might have.\n\nAll information provided by applicants will be used only for recruitment purposes and will be used strictly in accordance with the Bank's personal data policies, a copy of which may be obtained by the applicant upon request. Unless otherwise instructed in writing by the applicant concerned, applicants may be considered for other suitable positions within the Bank and its related companies. The personal data of unsuccessful job applicants may be retained for a maximum of two years from the date when the job application is rejected and such data may be retained for a longer period if there is a subsisting reason that obliges the Bank to do so, after which the personal data will be destroyed.", "employment_types": ["Full Time", "Permanent"], "selling_points": [], "locations": ["Not Specified"], "categories": ["Banking / Finance", "Private Banking", "Financial Services", "Project Finance"], "post_time": "2022-01-13T06:51:48Z", "salary": {"currency": null, "max": null, "min": null, "period": "monthly", "term": null}, "salary_visible": false, "title_keywords": ["manager", "assistant"], "responsibilities": ["operations", "review", "monitoring", "implementation", "testing", "develop", "coordination", "plan", "project documentation"], "requirements": {"degrees": ["university degree"], "majors": [], "languages": ["english", "chinese"], "language_level": ["proficiency", "good"], "hard_skills": ["powerpoint", "reason", "problem solving", "project management", "ms excel"], "soft_skills": ["work independently", "under pressure", "project management skills", "problem solving", "project management", "communication", "self-motivation", "novel"], "languages_combined": [{"language": "english", "language_level": ["proficiency", "good"]}, {"language": "chinese", "language_level": ["proficiency", "good"]}]}, "experience_required": {"duration": ["minimum 5 years"], "field": ["project management", "management", "relevant experience", "banking"]}}, {"job_id": "100003009039324", "location_code": "hk", "company": "DBS Bank Ltd", "job_title": "Senior Associate, Operations, Sec Svcs-Clrnc/Setlmnt/Invstgn, Private Banking (Payment, Loans & TRE Admin)", "description": "Business Function\n\nGroup Technology and Operations (T&O) enables and empowers the bank with an efficient, nimble and resilient infrastructure through a strategic focus on productivity, quality & control, technology, people capability and innovation. In Group T&O, we manage the majority of the Bank's operational processes and inspire to delight our business partners through our multiple banking delivery channels.\n\nResponsibilities:\n\nCash Related Transaction processing\nRemittance Out and In\nFund Transfer\nIssuance of Cashier Order & Demand Draft\nCheque & Time Deposit\nHandle RM & CS\u2019 enquiries\nInsufficient fund and collateral check\nDay-end reconciliation on deal ticket & incomplete order verification\nSystem enhancement & development\nReport and escalate any issue and exceptions\nComplete transaction such as remittance & issuance of CO & DD by cut-off time\nEnsure TT Out and 3rd\u00a0Party Fund Transfer with sufficient funds and collateral\nEnsure no error detected with control of day-end reconciliation\nOther clerical administration\n\nRequirements:\n\nUniversity Degree Holder\nMinimum 7-year experience in banking cash related products with 4-year in leader level\u00a0\u00a0\nGood experience and knowledge in banking cash products and remittance\nAble to work independently, excellent interpersonal and communication skills\nDigital mindset would be advantage\nProficient in MS Office\nProficiency in spoken / writing skills in both English and Chinese\nCandidate with more experience may consider for a senior position\n\nApply Now\n\nWe offer a competitive salary and benefits package and the professional advantages of a dynamic environment that supports your development and recognises your achievements.\n\nWe regret only shortlisted candidates will be notified.", "employment_types": ["Full Time"], "selling_points": ["Pension Fund Scheme", "Medical Coverage for Family", "Career Development"], "locations": ["Kwun Tong"], "categories": ["Banking / Finance", "Corporate Banking", "Private Banking", "Retail Banking"], "post_time": "2022-01-11T09:25:45Z", "salary": {"currency": null, "max": null, "min": null, "period": "monthly", "term": null}, "salary_visible": false, "title_keywords": ["senior associate", "admin", "operations", "private banking"], "responsibilities": ["administration", "report", "control", "transaction processing"], "requirements": {"degrees": ["university degree"], "majors": [], "languages": ["english", "chinese"], "language_level": ["proficiency"], "hard_skills": ["dynamic", "writing skills", "ms office"], "soft_skills": ["communication skills", "work independently", "dynamic environment", "writing skills", "interpersonal"], "languages_combined": [{"language": "english", "language_level": ["proficiency"]}, {"language": "chinese", "language_level": ["proficiency"]}]}, "experience_required": {"duration": ["4-year", "minimum 7-year"], "field": ["related", "banking"]}}, {"job_id": "100003009045840", "location_code": "hk", "company": "Robert Half", "job_title": "AVP/VP - Regulatory Reporting, Leading Bank", "description": "Our client is a leading International bank with operations in both banking and treasury services. To cope with their business expansion, they are looking for a caliber to join their team.\n\n\n\nResponsible for the HKMA regulatory reporting process, and to ensure the compilation of banking returns and surveys are in compliance with the completion instructions and relevant guidelines as set out by the HKMA\nEnsure proper control checking and review procedures are in place so as to minimize errors in reporting\nAssist in the implementation of system enhancement projects relating to banking return reporting and other ad hoc tasks as required by the management from time to time\n\n\nRequirements:\n\nBachelor's Degree in Accounting, Finance or relevant discipline\nMinimum 3 years' experience in banking and financial accounting / regulatory reporting functions\nMember of CPA is an added advantage\nHigh level of multi-tasking and time management skill are required\nA team-player with excellent working attitude; willing to take on multiple functions\nExcellent verbal and written communication skills\n\n\n\nApply Today\n\nTo apply online (Word attachment only), please click the 'Apply' button. Please note that only short-listed candidates will be contacted.", "employment_types": ["Full Time", "Permanent"], "selling_points": ["A leading retail banking and corporate banking", "Fringe benefit with decent bonus", "Good exposure with career progression"], "locations": ["Central & Western Area"], "categories": ["Banking / Finance", "Corporate Banking", "Private Banking", "Retail Banking"], "post_time": "2022-01-13T08:52:51Z", "salary": {"currency": null, "max": null, "min": null, "period": "monthly", "term": null}, "salary_visible": false, "title_keywords": [], "responsibilities": ["reporting", "control", "management", "guidelines", "operations", "compliance", "review", "checking", "procedures", "implementation", "ad hoc tasks", "communication", "banking", "enhancement projects"], "requirements": {"degrees": ["degree", "bachelor"], "majors": ["finance", "accounting"], "languages": [], "language_level": [], "hard_skills": ["hkma", "cpa", "word", "hkma regulatory reporting"], "soft_skills": ["communication skills", "responsible", "team-player", "multi-tasking", "time management skill"], "languages_combined": []}, "experience_required": {"duration": ["minimum 3 years"], "field": ["accounting", "financial", "banking"]}}, {"job_id": "100003009039894", "location_code": "hk", "company": "DBS Bank Ltd", "job_title": "Specialist, Operations (Account onboarding supervisor)", "description": "Business Function\n\nTechnology and Operations (T&O) enables and empowers the bank with an efficient, nimble and resilient infrastructure through a strategic focus on productivity, quality & control, technology, people capability and innovation. In T&O, we manage the majority of the Bank's operational processes and inspire to delight our business partners through our multiple banking delivery channels.\n\u00a0\n\nResponsibilities\n\nTo assist in Wealth Management Account onboarding team (Bank side), which includes\n\nSupervisor role in client onboarding team to support daily processing including account opening and static data maintenance\nHandling new business request, work with COO Office to update Operation procedure and policy\nDeliver continuous process improvements, in view of the changing operating and regulatory environment.\nEngage in system enhancement and development project\nAssist in Audit, regulatory review, FATCA and CRS reporting, etc\n\nRequirements\n\nUniversity degree or equivalent\nAt least 5 year experience in a similar position in the private banking industry.\u00a0\nBroker firm experience is preferable\nStrong understanding of the banking operational processes such as account onboarding and client static data maintenance\nGood organizational, communication and strong inter-personal skills as candidate is required to manage various activities within the team, and to be able to communicate effectively with relationship manager, COO Office and technology team.\nAbility to develop and maintain productive relationships with key internal clients including business, operations and colleagues from the SG regional team\nGood knowledge and experience in International Tax Regulations (FATCA//CRS) documentation handling and reporting\nSolid experience and knowledge in system enhancement project\n\nApply Now\n\nWe offer a competitive salary and benefits package and the professional advantages of a dynamic environment that supports your development and recognises your achievements.\n\nWe regret only shortlisted candidates will be notified.", "employment_types": ["Full Time"], "selling_points": ["Knowledge in account onboarding", "Good understand in FATCA/CRS", "Checker/ supervisor experience is an advantage"], "locations": ["Kwun Tong"], "categories": ["Banking / Finance", "Private Banking", "Order Processing & Operation / Settlement"], "post_time": "2022-01-11T14:25:36Z", "salary": {"currency": null, "max": null, "min": null, "period": "monthly", "term": null}, "salary_visible": false, "title_keywords": ["specialist", "operations", "supervisor"], "responsibilities": ["reporting", "management", "maintenance", "data", "account opening", "review", "audit"], "requirements": {"degrees": ["university degree"], "majors": [], "languages": [], "language_level": [], "hard_skills": ["crs", "maintenance", "fatca", "dynamic", "documentation"], "soft_skills": ["productive", "dynamic environment", "organizational", "inter-personal skills", "communication"], "languages_combined": []}, "experience_required": {"duration": ["at least 5 year"], "field": ["banking industry"]}}, {"job_id": "100003009037430", "location_code": "hk", "company": "China Development Bank Hong Kong Branch", "job_title": "Corporate Finance Associates", "description": "Department: \u00a0Corporate Finance \u00a0Department \u516c\u53f8\u696d\u52d9\u90e8\u9580\n\n\nResponsibilities\n\n\nDevelop and maintain business relationships with bank and non-bank FIs customers.\nCo-operate with FIs to arrange short term and long term bi-lateral and syndication loan agreements between the branch and international and regional financial institutions, including but not limited to banks, government agencies, investment/development banks, etc.\nProcess and ensure KYC, credit processing/reviews, credit proposals and all other administrative tasks are managed properly within the prescribed timeframe.\nPerform counterparty\u2019s credit risk assessment, review existing accounts and recommend limits for new and existing FI clients.\nWork closely with head office, branches and internal departments to deliver comprehensive solutions to clients.\nCooperate with correspondent banking to develop new and maintain existing peer relations, with major Chinese and international bank.\nPromote and market banking and credit products to clients in financial institution sector including Foreign & PRC Banking clients.\n\n\nRequirements\n\n\nUniversity degree or above in Finance, Economics or Accounting.\nMinimum 2 years or above relevant experience in Financial Institutions.\nFamiliar with FI products.\nGood knowledge of financial analysis\u00a0 experience and interpersonal skills.\nGood credit analysis and report writing skills.\nProficiency in both spoken and written English and Chinese (Mandarin).\n\n\n\u5de5\u4f5c\u8077\u8cac:\n\n\n\u8ca0\u8cac\u7dad\u8b77\u8207\u9280\u884c\u8207\u975e\u9280\u884c\u91d1\u878d\u6a5f\u69cb\u5ba2\u6236\u7684\u95dc\u4fc2\u7dad\u8b77\n\u8207\u9999\u6e2f\u672c\u5730\u6216\u570b\u969b\u91d1\u878d\u6a5f\u69cb\u5408\u4f5c\uff0c\u958b\u5c55\u77ed\u671f\u6216\u4e2d\u9577\u671f\u96d9\u908a\u6216\u9280\u5718\u8cb8\u6b3e\u5408\u4f5c\n\u719f\u6089KYC\u6d41\u7a0b\u3001\u4fe1\u7528\u98a8\u96aa\u8a55\u4f30\u53ca\u6388\u4fe1\u7b49\u6d41\u7a0b\n\u5c0d\u4ea4\u6613\u5c0d\u624b\u7684\u4fe1\u7528\u98a8\u96aa\u9032\u884c\u8a55\u4f30\u3001\u91cd\u6aa2\u4e26\u63d0\u51fa\u76f8\u95dc\u98a8\u96aa\u63a7\u5236\u63aa\u65bd\n\u8207\u7e3d\u884c\u3001\u5176\u4ed6\u5206\u884c\u53ca\u5167\u90e8\u5176\u4ed6\u90e8\u9580\u5408\u4f5c\uff0c\u70ba\u5ba2\u6236\u63d0\u4f9b\u7d9c\u5408\u878d\u8cc7\u89e3\u6c7a\u65b9\u6848\n\u7dad\u6301\u548c\u7ba1\u7406\u4ee3\u7406\u884c\u95dc\u4fc2\n\u5c0d\u5ba2\u6236\u9032\u884c\u4fe1\u7528\u7522\u54c1\u884c\u92b7\n\n\n\u4efb\u8077\u8005\u8981\u6c42:\n\n\u5177\u5099\u5927\u5b78\u4ee5\u4e0a\u5b78\u6b77\uff0c\u91d1\u878d\u3001\u7d93\u6fdf\u6216\u6703\u8a08\u5c08\u696d\u512a\u5148\u8003\u616e\n\u81f3\u5c112\u5e74\u6216\u4ee5\u4e0a\u76f8\u95dc\u5de5\u4f5c\u7d93\u6b77\n\u719f\u6089\u91d1\u878d\u6a5f\u69cb\u696d\u52d9\u689d\u7dda\u7522\u54c1\n\u5177\u6709\u8f03\u597d\u7684\u8ca1\u52d9\u5206\u6790\u548c\u6e9d\u901a\u80fd\u529b\n\u5177\u6709\u8f03\u597d\u7684\u4fe1\u7528\u5206\u6790\u53ca\u5831\u544a\u64b0\u5beb\u80fd\u529b\n\u5177\u6709\u8f03\u597d\u82f1\u8a9e\u3001\u666e\u901a\u8a71\u53e3\u8a9e\u53ca\u6587\u5b57\u8868\u9054\u80fd\u529b", "employment_types": ["Full Time", "Permanent"], "selling_points": ["University degree", "Finance, Economics or Accounting", "Minimum 2 years or above relevant exp"], "locations": ["Central"], "categories": ["Banking / Finance", "Private Banking", "Corporate Finance", "Project Finance"], "post_time": "2022-01-11T04:15:38Z", "salary": {"currency": null, "max": null, "min": null, "period": "monthly", "term": null}, "salary_visible": false, "title_keywords": ["corporate finance"], "responsibilities": ["review", "banking", "develop", "co-operate with", "maintain", "kyc", "administrative tasks", "cooperate with"], "requirements": {"degrees": ["degree or above"], "majors": ["finance", "economics", "accounting"], "languages": ["english", "chinese", "mandarin"], "language_level": ["proficiency"], "hard_skills": ["financial analysis", "credit analysis", "writing skills"], "soft_skills": ["interpersonal skills", "writing skills"], "languages_combined": [{"language": "english", "language_level": ["proficiency"]}, {"language": "chinese", "language_level": ["proficiency"]}, {"language": "mandarin", "language_level": []}]}, "experience_required": {"duration": ["minimum 2 years"], "field": ["financial institutions", "relevant experience", "financial"]}}, {"job_id": "100003009032957", "location_code": "hk", "company": "Elite Jobs", "job_title": "Graduate Trainee Program (5 Days work week, Welcome Fresh Grad)", "description": "We are currently seeking a high caliber professional to join our department as\u00a0Graduate Trainee.\n\nThe Role and Responsibilities:\n\nOn-the-job training to established related asset management expertise.\nTo develop investment strategies to achieve client\u2019s financial objectives.\nPerform investment portfolios analysis, monitor the performance and make necessary recommendation on portfolio re-allocation.\nPreparing different scheme of investment proposal and portfolio review report.\nIdentify client objectives and offer appropriate financial consultancy.\n\nRequirements:\n\n\nBachelor degree holder or above in all disciplines\nGood communication, interpersonal\u00a0and problem solving skills\nArticulate and detail oriented, ability to multitask in a fast paced environment.\u00a0\nFluency in Cantonese, English and Mandarin\n\nJob Offer:\n\n\nPersonal development and growth opportunities.\nContinuous Learning Sponsorship, medical benefits.\n5 day work week.\nWe offer a competitive salary and benefits package and the professional advantages of a dynamic environment that supports your development and recognizes your achievements.\n\n\nInterested individuals please send your detailed resume and expected salary by clicking\u00a0\"Apply Now\". Only candidates who are authorized to work in Hong Kong will be considered.\n\nAll personal data provided will only be used for recruitment purpose only. Information of candidates not selected will be destroyed in 3 months.", "employment_types": ["Full Time"], "selling_points": ["5 day work week", "Personal development and growth opportunities", "Continuous Learning Sponsorship, medical benefits"], "locations": ["Central & Western Area"], "categories": ["Accounting", "Finance / Accounting Manager", "Banking / Finance", "Private Banking", "Others", "Student / Fresh Graduate / No Experience"], "post_time": "2022-01-08T04:12:29Z", "salary": {"currency": "HKD", "max": 19999, "min": 14000, "period": "monthly", "term": null}, "salary_visible": true, "title_keywords": ["graduate trainee"], "responsibilities": ["investment strategies", "analysis", "investment portfolios", "develop", "investment proposal", "monitor the performance", "portfolio review report", "asset management"], "requirements": {"degrees": ["bachelor degree holder"], "majors": [], "languages": ["cantonese", "english", "mandarin"], "language_level": ["fluency"], "hard_skills": ["problem solving skills"], "soft_skills": ["ability to multitask", "detail oriented", "communication", "articulate", "problem solving skills", "interpersonal"], "languages_combined": [{"language": "cantonese", "language_level": ["fluency"]}, {"language": "english", "language_level": ["fluency"]}, {"language": "mandarin", "language_level": ["fluency"]}]}, "experience_required": {"duration": [], "field": []}}, {"job_id": "100003009034608", "location_code": "hk", "company": "Cornerstone Global Partners", "job_title": "Private Trust Admin Manager / Senior Officer (KYC, Legal Documents, Top Trustee)", "description": "Our Client\nA top Trustee in HK\n\n\nRole Overview\n\nPrepare for private trust establishment and transfer documentations\nEnsure accuracy of onboarding documents inclusive but not limited to trust deeds, letter of wishes\nPerform client annual review\nConduct due diligence/ KYC\nLiaise with internal and external stakeholders such as banks, lawyers, accountants, all partners a nd investment manager s or advisors regarding distribution, management and distributions of trust assets\n\nIdeal Profile\n\nBachelor degree or above\n3 years or above experience in handling private trust administration\nGood command of Chinese and English (Putonghua is preferred)\nProfessional qualifications such as TEP, CPA or ACIS preferable\u00a0", "employment_types": ["Permanent"], "selling_points": ["private trust transfer", "private trust establishment", "due diligence/ KYC"], "locations": ["Central & Western Area"], "categories": ["Banking / Finance", "Private Banking", "Fund Management", "Asset Management"], "post_time": "2022-01-10T03:47:48Z", "salary": {"currency": "HKD", "max": 44999, "min": 25000, "period": "monthly", "term": null}, "salary_visible": true, "title_keywords": ["senior officer", "admin", "manager"], "responsibilities": ["due diligence", "management", "review", "kyc", "liaise with", "administration"], "requirements": {"degrees": ["degree or above", "bachelor"], "majors": [], "languages": ["putonghua", "english", "chinese"], "language_level": ["good command"], "hard_skills": ["cpa", "professional qualifications", "documentations", "kyc"], "soft_skills": ["ideal"], "languages_combined": [{"language": "putonghua", "language_level": ["good command"]}, {"language": "english", "language_level": ["good command"]}, {"language": "chinese", "language_level": ["good command"]}]}, "experience_required": {"duration": ["3 years"], "field": ["administration"]}}, {"job_id": "100003009025602", "location_code": "hk", "company": "Shanghai Pudong Development Bank Co., Ltd., Hong Kong Branch", "job_title": "Senior Relationship Manager, Private Banking, Local Market (Ref.: CV_PBC_SRM_202201)", "description": "Responsibilities:\n\n\nDevelop and manage a portfolio of private banking clients\nProvide investment portfolio analysis and advices to the clients according to their needs, desires and risk profile\nDefine target market, analyze client needs and suggest scope of product enhancement\nInitiate and implement marketing strategies to promote a full range of investment and insurance products through a proactive & professional approach in achieving the business sales targets of the bank\nManage the credit quality and monitor the exposure of customers\u2019 loan portfolios\nWork on ad hoc projects and tasks assigned by management\nRequirements:\n\nDegree holder or above with major in Business Administration, Economics, Finance, Marketing or related disciplines\nAt least 8 years of relevant experience in private banking, wealth management\u00a0and/or retail banking\u00a0premier sector\nQualified under SFO for carrying out Regulated Activities Type 1, 4 and qualified as Insurance Intermediary\nIndependent, ability to work under pressure to meet tight schedule and sensitive to market changes with a proactive approach to drive business growth\nProficient in MS Office applications and Chinese Word Processing\nGood command of both verbal and written English, Chinese and Mandarin\n\nPlease quote the Reference No.: CV_PBC_SRM_202201 in your application.\n\nOur Bank offers attractive remuneration package to chosen candidates. Interested parties please apply with full resume stating expected salary and contact phone number via\u00a0Apply Now.\n\nAll applications will be treated in the strictest confidence and personal data collected will be used for recruitment purpose only.", "employment_types": ["Full Time", "Permanent"], "selling_points": ["Develop and manage a portfolio of PB Clients", "8yrs+ of rel. exp in PB / PWM / Retail Banking", "Qualified under SFO & IA is preferred"], "locations": ["Wan Chai"], "categories": ["Banking / Finance", "Private Banking", "Others", "Wealth Management"], "post_time": "2022-01-06T16:08:04Z", "salary": {"currency": null, "max": null, "min": null, "period": "monthly", "term": null}, "salary_visible": false, "title_keywords": ["senior relationship manager", "private banking"], "responsibilities": ["management", "marketing strategies", "analysis", "quality", "monitor", "develop", "ad hoc projects", "banking", "insurance"], "requirements": {"degrees": ["degree holder"], "majors": ["business administration", "finance", "economics", "related disciplines", "marketing"], "languages": ["english", "chinese", "mandarin"], "language_level": ["good command", "proficient"], "hard_skills": ["no", "chinese word processing", "sfo", "ms office"], "soft_skills": ["sensitive to", "proactive", "independent", "work under pressure"], "languages_combined": [{"language": "english", "language_level": ["good command"]}, {"language": "chinese", "language_level": ["good command", "proficient"]}, {"language": "mandarin", "language_level": ["good command"]}]}, "experience_required": {"duration": ["at least 8 years"], "field": ["management", "retail banking", "relevant experience", "banking"]}}, {"job_id": "100003009032938", "location_code": "hk", "company": "Cheuk Hang Growth", "job_title": "Fund Management Intern / Assistant / Trainee", "description": "Job Description\n\nOur clients are leading financial institutions in Hong Kong. They are currently looking for who interest in Finance to join their investment team as:\n\nResponsibilities:\n\nTo provide tailor-made financial advices to clients\nTo monitor & analyze clients\u2019 investment portfolio\nTo maintain good relationship with clients\n\nRequirements:\n\nUniversity graduate in any discipline\u00a0\nWilling to work with others\nExcellent interpersonal, communications and presentation skills\nAggressive, self-motivated, passionate for better career development\n\n\n\nBenefits:\n\n5 days work\nOn job training\nTraining allowance\nMedical Insurance, competitive salary and attractive bonus\n\nHK residents will only be considered.\nPersonal data will be used for recruitment purpose only.", "employment_types": ["Full Time"], "selling_points": [], "locations": ["Central & Western Area"], "categories": ["Banking / Finance", "Private Banking", "Management", "Management Trainee", "Asset Management"], "post_time": "2022-01-08T03:29:49Z", "salary": {"currency": "HKD", "max": 24999, "min": 20000, "period": "monthly", "term": null}, "salary_visible": true, "title_keywords": ["trainee", "assistant", "intern"], "responsibilities": ["monitor", "maintain good relationship"], "requirements": {"degrees": ["university graduate"], "majors": [], "languages": [], "language_level": [], "hard_skills": [], "soft_skills": ["passionate", "presentation skills", "interpersonal", "self-motivated"], "languages_combined": []}, "experience_required": {"duration": [], "field": []}}, {"job_id": "100003009023519", "location_code": "hk", "company": "Infinity Asset Management Limited", "job_title": "Relationship Manager Assistant", "description": "Job Descriptions:\n\nAssist relationship manager / portfolio manager to open accounts in custodian banks\nConduct KYC and gather SOW information from clients for account openings\nExecute investment orders on behalf of clients\nUpdate and maintain client profiles\nAssist the sales team to prepare sales & marketing materials\nProvide support is the customer relationship management\nHandle phone calls & reply enquiries from clients\n\nQualifications:\n\nTertiary education or above\nMin 3 years of financial working experience, with at least 1 years\u2019 experience in private banking/investment banking/family office/EAM\nGood interpersonal & communication skills\nBasic knowledge of cross-asset classes investment instruments\nProficient in both written & spoken English & Chinese\nEligible to be SFC license Type 4 and 9 representatives preferred\nFamiliar with common Software, e.g. Word, Excel & PowerPoint etc.\n\nWe offer attractive remuneration package to successful candidates. \u00a0Please either send your CV with expected and current salary apply directly to this job post.\n\nAbout\u00a0Infinity Asset Management Limited\n\nInfinity Asset Management is a Hong Kong based fast growing asset management company. Our company aims to develop external asset management and hedge fund business in Hong Kong. We provide opportunities to candidates with the ambition to obtain experience in the high-net-worth wealth management industry.", "employment_types": ["Full Time"], "selling_points": ["-\tBasic salary + discretionary bonus", "-\tOn the job training", "-\tBrilliant Career Path"], "locations": ["Admiralty"], "categories": ["Banking / Finance", "Private Banking", "Wealth Management", "Asset Management"], "post_time": "2022-01-05T09:00:19Z", "salary": {"currency": null, "max": null, "min": null, "period": "monthly", "term": null}, "salary_visible": false, "title_keywords": ["relationship manager", "assistant"], "responsibilities": ["provide support", "management", "software", "prepare sales", "banking", "communication", "maintain", "assist the sales", "kyc", "marketing materials", "phone calls"], "requirements": {"degrees": [], "majors": [], "languages": ["english", "chinese"], "language_level": ["proficient"], "hard_skills": ["excel", "basic", "word", "powerpoint", "sfc license", "kyc"], "soft_skills": ["communication skills", "interpersonal"], "languages_combined": [{"language": "english", "language_level": ["proficient"]}, {"language": "chinese", "language_level": ["proficient"]}]}, "experience_required": {"duration": ["at least 1 years", "min 3 years"], "field": ["investment", "banking", "financial"]}}, {"job_id": "100003009020057", "location_code": "hk", "company": "Ping An Bank Company Ltd.", "job_title": "Relationship Manager - Private Wealth Management", "description": "Job Responsibilities:\n\nProvide banking services toward UHNW/HNW private wealth management customers\nProvide marketing and training support to group staff;\nProvide customers with one-stop financial services, such as financial asset allocation recommendations, lead investment banking services, family office service, offshore trust needs understanding and planning services.\nDeepen and establish long-term customer relationships by determining customer needs for financial services, including but not limited to providing investment, insurance and other banking products and services;\nPlan and provide relevant and appropriate financial products and services to meet the needs of existing and potential customers;\nCooperate with relevant departments and personnel inside and outside the group to initiate and implement the marketing strategy/plan of wealth management products/services;\nAchieve key performance indicators;\nSupport cross-border business activities in the PWM field;\nStrictly comply with compliance requirements, ensure that product information is prepared for internal parties and comply with regulatory requirements and rules;\nAssist in system development and improvement projects of financial products/services;\nIf necessary, instruct and train junior staff;\nCoordinate marketing and promotional activities inside and outside the branch when necessary.\n\nJob Requirements:\n\nHold a university degree or above in business, major in finance or business related; pass HKSI Paper 1, 7 and 8 and IIQE Paper 1 and 3;\nAt least 3 years of experience related to private banking/asset management sales, distribution sales experience will be an advantage;\nHave cross-border business experience, willingness and compliance awareness;\nPossess good teamwork spirit, interpersonal communication skills and understanding; able to be independent and able to complete work under pressure;\nPossess good analytical skills, and can have a comprehensive understanding of various wealth management products (including but not limited to stocks, public funds, private funds, fixed income products, structured products and insurance), as well as roadshows and training capabilities;\nHave the ability to establish, operate and maintain pipeline relationships with internal partners;\nFluent Chinese (Mandarin) English listening, speaking, reading and writing skills;\nProficient in MS Word, Excel and PowerPoint;\nCFA, CFP, FRM and other professional qualifications are preferred;", "employment_types": ["Full Time"], "selling_points": ["financial services", "customer relationships", "financial products"], "locations": ["Central"], "categories": ["Banking / Finance", "Private Banking"], "post_time": "2022-01-05T20:31:59Z", "salary": {"currency": null, "max": null, "min": null, "period": "monthly", "term": null}, "salary_visible": false, "title_keywords": ["wealth management", "relationship manager"], "responsibilities": ["management", "regulatory requirements", "compliance", "coordinate", "promotional activities", "plan", "banking", "internal parties", "insurance", "cooperate with", "business activities", "planning"], "requirements": {"degrees": ["degree or above"], "majors": ["finance", "business"], "languages": ["english", "chinese", "mandarin"], "language_level": ["fluent"], "hard_skills": ["excel", "professional qualifications", "cfa", "hksi paper", "writing skills", "analytical skills", "iiqe paper", "powerpoint", "frm", "ms word"], "soft_skills": ["communication skills", "independent", "writing skills", "analytical skills", "comprehensive", "teamwork spirit", "structured", "interpersonal", "work under pressure"], "languages_combined": [{"language": "english", "language_level": ["fluent"]}, {"language": "chinese", "language_level": ["fluent"]}, {"language": "mandarin", "language_level": ["fluent"]}]}, "experience_required": {"duration": ["at least 3 years"], "field": ["related", "compliance", "business", "banking", "asset management"]}}, {"job_id": "100003009016973", "location_code": "hk", "company": "One Heritage Capital Management Limited", "job_title": "Private Banking Relationship Manager / Account Executive", "description": "You will be responsible for identifying, originating and developing client relationships with high net worth individuals or families on an ongoing basis to achieve the business strategies stipulated by the company.\n\n\nJob Responsibility\nOriginate, develop and maintain client relationships within the high-net-worth segment\nUnderstand clients\u2019 wealth management needs and formulate appropriate solutions to meet the needs based on the clients\u2019 circumstances and risk appetite\nProvide banking services and execute transactions for clients on a timely and effective manner\nMonitor clients\u2019 portfolio and provide timely update to clients as appropriate\nPerform regular reviews with clients to re-assess client\u2019s risk profile, wealth management needs and other customer details\nProvide efficient and high quality professional services and ensure a consistent delivery of good service standards and proposition\nPerform tasks in accordance with regulatory and compliance requirements\nTo meet the challenge, you should have the following qualifications and attributes:\nDegree holder Minimum 3 years of relevant working experience in banking industry or investment business serving high net worth customers\nFamiliar with KYC and account documentation with knowledge of wealth management products Excellent selling, relationship building and interpersonal skills\nStrong self-initiative and able to work under pressure\nProfessional licensing qualifications on HKSI LE Papers 1, 7 & 8 and IIQE Papers 1-3 & 5 or equivalent\nGood command of both written and spoken English and Chinese (including Cantonese and Putonghua)\nThe candidate who with less experience will be considered as Account Executive\nWe offer competitive salary package and attractive career development opportunities. Interested parties please send your full resume with current & expected salary and date of availability to us via JobsDB.\nDisclaimer: The personal data is collected for recruitment and employment purposes only.", "employment_types": ["Full Time", "Permanent"], "selling_points": ["Provide Private banking service to high-net-worth", "Attractive salary package with high commission", "Wealth Management Products & Services"], "locations": ["Wan Chai"], "categories": ["Banking / Finance", "Private Banking", "Financial Services", "Asset Management"], "post_time": "2022-01-03T10:13:52Z", "salary": {"currency": null, "max": null, "min": null, "period": "monthly", "term": null}, "salary_visible": false, "title_keywords": ["account executive", "relationship manager", "private banking"], "responsibilities": ["management", "account documentation", "kyc", "compliance", "monitor", "developing", "transactions", "develop", "quality", "service standards", "maintain", "banking", "work under pressure"], "requirements": {"degrees": ["degree holder"], "majors": ["business"], "languages": ["cantonese", "putonghua", "english", "chinese"], "language_level": ["good command"], "hard_skills": ["documentation", "iiqe", "hksi", "kyc"], "soft_skills": ["efficient", "responsible", "timely", "interpersonal skills", "self-initiative", "work under pressure"], "languages_combined": [{"language": "cantonese", "language_level": ["good command"]}, {"language": "putonghua", "language_level": ["good command"]}, {"language": "english", "language_level": ["good command"]}, {"language": "chinese", "language_level": ["good command"]}]}, "experience_required": {"duration": ["minimum 3 years"], "field": ["investment", "banking industry", "business", "relevant working experience"]}}, {"job_id": "100003009037503", "location_code": "hk", "company": "Robert Half", "job_title": "AVP/VP - Regulatory Reporting, Leading Bank", "description": "Our client is a leading International bank with operations in both banking and treasury services. To cope with their business expansion, they are looking for a caliber to join their team.\n\n\n\nResponsible for the HKMA regulatory reporting process, and to ensure the compilation of banking returns and surveys are in compliance with the completion instructions and relevant guidelines as set out by the HKMA\nEnsure proper control checking and review procedures are in place so as to minimize errors in reporting\nAssist in the implementation of system enhancement projects relating to banking return reporting and other ad hoc tasks as required by the management from time to time\n\n\n\nRequirements:\n\nBachelor's Degree in Accounting, Finance or relevant discipline\nMinimum 3 years' experience in banking and financial accounting / regulatory reporting functions\nMember of CPA is an added advantage\nHigh level of multi-tasking and time management skill are required\nA team-player with excellent working attitude; willing to take on multiple functions\nExcellent verbal and written communication skills\n\n\nApply Today\n\nTo apply online (Word attachment only), please click the 'Apply' button. Please note that only short-listed candidates will be contacted.", "employment_types": ["Full Time", "Permanent"], "selling_points": ["A leading retail banking and corporate banking", "Fringe benefit with decent bonus", "Good exposure with career progression"], "locations": ["Central & Western Area"], "categories": ["Banking / Finance", "Corporate Banking", "Private Banking", "Retail Banking"], "post_time": "2022-01-11T02:58:22Z", "salary": {"currency": null, "max": null, "min": null, "period": "monthly", "term": null}, "salary_visible": false, "title_keywords": [], "responsibilities": ["reporting", "control", "management", "guidelines", "operations", "compliance", "review", "checking", "procedures", "implementation", "ad hoc tasks", "communication", "banking", "enhancement projects"], "requirements": {"degrees": ["degree", "bachelor"], "majors": ["finance", "accounting"], "languages": [], "language_level": [], "hard_skills": ["hkma", "cpa", "word", "hkma regulatory reporting"], "soft_skills": ["communication skills", "responsible", "team-player", "multi-tasking", "time management skill"], "languages_combined": []}, "experience_required": {"duration": ["minimum 3 years"], "field": ["accounting", "financial", "banking"]}}, {"job_id": "100003009025747", "location_code": "hk", "company": "DBS Bank Ltd", "job_title": "AVP/ Senior Associate, Specialist, Know Your Customer, Private Banking (Contract)", "description": "Business Function\n\nDBS\u2019 Private Banking offers a one-stop, full-service touch-point for total banking requirements and provides the highest level of personalised banking. We have a team of dedicated, experienced investment advisors who identify opportunities in the various asset classes and employ the best strategies and product vehicles to cater to each client\u2019s needs. Coupled with partnerships within the DBS network and with global institutions, we strive to build long-term relationships with our Private Banking clients in Asia by providing them with high quality, timely and extensive wealth management, investment and financial solutions.\n\nResponsibilities:\n\nAssist KYC/AML activities associated with new account opening, periodic CDD reviews, trigger event CDD reviews of existing accounts and name screening in full compliance with policy and regulatory requirements.\nPlan and deliver KYC/AML related projects and support technology initiatives that impact KYC/AML and associated processes.\nEnsure that KYC/AML procedures, processes and systems have robust controls and support a positive customer and employee journey.\nSupport FCSS review, internal audit and regulatory inspections.\nAct as deputy of KYC/AML Champion for HK WM, and be the primary interface with Front Office, WMO, Internal Audit, FCSS and other Risk & Control functions on KYC/AML matters\nCoach and develop junior KYC/AML staff.\n\nRequirements\n\nKYC/AML specialist in the Private Banking or Wealth Management\nMinimum of 5\u00a0years of experience in banking industry, at least 1 years in Private Banking or Wealth Management.\nStrong understanding in financial products, policies and procedures in private banking. Hands-on remediation project and process improvement experience.\nA team leader with excellent project management skill and interpersonal skill\nExcellent critical thinking and analysis skills, problem solving capacities\nSelf-motivated, independent, strong sense of ownership with ability to work in a team environment.\nGood command of English and Chinese\n\nApply Now\n\nWe offer a competitive salary and benefits package and the professional advantages of a dynamic environment that supports your development and recognises your achievements.\n\nWe regret only shortlisted candidates will be notified.", "employment_types": ["Full Time"], "selling_points": ["KYC, AML in Private Banking", "PB job exposure", "Maker & Checker role"], "locations": ["Central"], "categories": ["Banking / Finance", "Private Banking", "Professional Services", "Legal & Compliance", "Wealth Management"], "post_time": "2022-01-06T06:25:51Z", "salary": {"currency": null, "max": null, "min": null, "period": "monthly", "term": null}, "salary_visible": false, "title_keywords": ["specialist", "senior associate", "private banking"], "responsibilities": ["regulatory inspections", "control", "aml", "internal audit", "cdd", "account opening", "compliance", "regulatory requirements", "procedures", "systems", "review", "develop", "plan", "kyc"], "requirements": {"degrees": [], "majors": [], "languages": ["english", "chinese"], "language_level": ["good command"], "hard_skills": ["aml", "analysis", "problem solving", "project management", "dynamic", "kyc"], "soft_skills": ["self-motivated", "dynamic environment", "independent", "interpersonal skill", "problem solving", "hands-on", "project management skill"], "languages_combined": [{"language": "english", "language_level": ["good command"]}, {"language": "chinese", "language_level": ["good command"]}]}, "experience_required": {"duration": ["at least 1 years", "minimum of 5 years"], "field": ["banking industry", "management", "banking"]}}, {"job_id": "100003009025605", "location_code": "hk", "company": "Shanghai Pudong Development Bank Co., Ltd., Hong Kong Branch", "job_title": "AVP / VP, Private Banking (Ref.: CV_PBC_RM_202201)", "description": "Responsibilities:\n\n\nDevelop and manage a portfolio of private banking clients\nProvide investment portfolio analysis and advices to the clients according to their needs, desires and risk profile\nDefine target market, analyze client needs and suggest scope of product enhancement\nInitiate and implement marketing strategies to promote a full range of investment and insurance products through a proactive & professional approach in achieving the business sales targets of the bank\nManage the credit quality and monitor the exposure of customers\u2019 loan portfolios\nWork on ad hoc projects and tasks assigned by management\nRequirements:\n\nDegree holder or above with major in Business Administration, Economics, Finance, Marketing or related disciplines\nAt least 3-5 years of relevant experience in private banking, wealth management\u00a0and/or retail banking\u00a0premier sector\nQualified under SFO for carrying out Regulated Activities Type 1, 4 and qualified as Insurance Intermediary\nIndependent, ability to work under pressure to meet tight schedule and sensitive to market changes with a proactive approach to drive business growth\nProficient in MS Office applications and Chinese Word Processing\nGood command of both verbal and written English, Chinese and Mandarin, fluency in other dialects (e.g. Shanghai dialects) is a definite advantage\nPromising candidates with more experience\u00a0will be considered for senior positions\n\n\nPlease quote the Reference No.: CV_PBC_RM_202201 in your application.\n\nOur Bank offers attractive remuneration package to chosen candidates. Interested parties please apply with full resume stating expected salary and contact phone number via\u00a0Apply Now.\n\nAll applications will be treated in the strictest confidence and personal data collected will be used for recruitment purpose only.", "employment_types": ["Full Time", "Permanent"], "selling_points": ["Develop and manage a portfolio of PB Clients", "3yrs+ of rel. exp in PB / PWM / Retail Banking", "Qualified under SFO & IA is preferred"], "locations": ["Wan Chai"], "categories": ["Banking / Finance", "Private Banking", "Others", "Wealth Management"], "post_time": "2022-01-06T16:08:04Z", "salary": {"currency": null, "max": null, "min": null, "period": "monthly", "term": null}, "salary_visible": false, "title_keywords": ["private banking"], "responsibilities": ["management", "marketing strategies", "analysis", "quality", "monitor", "develop", "ad hoc projects", "banking", "insurance"], "requirements": {"degrees": ["degree holder"], "majors": ["business administration", "finance", "economics", "related disciplines", "marketing"], "languages": ["english", "chinese", "mandarin"], "language_level": ["fluency", "good command", "proficient"], "hard_skills": ["no", "chinese word processing", "sfo", "ms office"], "soft_skills": ["sensitive to", "proactive", "independent", "work under pressure"], "languages_combined": [{"language": "english", "language_level": ["fluency", "good command"]}, {"language": "chinese", "language_level": ["fluency", "good command", "proficient"]}, {"language": "mandarin", "language_level": ["fluency", "good command"]}]}, "experience_required": {"duration": ["at least 3-5 years"], "field": ["management", "retail banking", "relevant experience", "banking"]}}, {"job_id": "100003009032210", "location_code": "hk", "company": "Randstad Hong Kong Limited", "job_title": "CDD Compliance Manager, Private Banking", "description": "about the company.\n\nA regional private and corporate bank is looking for a Customer Due Diligence (CDD) Compliance Manager\nabout the team.\nYou will be joining a team of 40+ in Compliance Team\nabout the job.\n\nPerform day-to-day Customer Due Diligence (CDD) review and approval. Review client due diligence assessment to determine the nature and level of due diligence required\n\nDetect any reporting on suspicious activities\n\nProvide AML advisory to relevant internal parties\n\nSupport regulatory filing and ad hoc projects\n\nskills & experiences required.\nBachelor degree holder in Law, Finance, Accounting, Business or relevant disciplines\nMinimum of 5 years Customer Due Diligence (CDD)/AML experience (open to candidates in operation/compliance), preferably with Private Banking exposure\nFluent in spoken and written English and Chinese\nMature working attitude, self-motivated and a team player\n\nInterested parties please apply by clicking \"Apply Now\". Alternatively, for a confidential discussion please contact Joanne Lo on + 852 2232 3421 or email: joanne.lo@randstad.com.hk", "employment_types": ["Full Time", "Permanent"], "selling_points": [], "locations": ["Not Specified"], "categories": ["Banking / Finance", "Private Banking", "Financial Services", "Professional Services", "Legal & Compliance"], "post_time": "2022-01-07T10:28:56Z", "salary": {"currency": "HKD", "max": 54999, "min": 35000, "period": "monthly", "term": null}, "salary_visible": true, "title_keywords": ["compliance manager", "private banking"], "responsibilities": ["due diligence", "reporting", "aml", "cdd", "review", "compliance", "customer due diligence", "ad hoc projects", "banking", "internal parties"], "requirements": {"degrees": ["bachelor degree holder"], "majors": ["business", "finance", "accounting", "law"], "languages": ["english", "chinese"], "language_level": ["fluent"], "hard_skills": ["customer due diligence", "aml", "cdd"], "soft_skills": ["self-motivated", "team player", "mature"], "languages_combined": [{"language": "english", "language_level": ["fluent"]}, {"language": "chinese", "language_level": ["fluent"]}]}, "experience_required": {"duration": ["minimum of 5 years"], "field": ["compliance", "operation", "banking"]}}, {"job_id": "100003009025519", "location_code": "hk", "company": "Basel Capital Holdings Limited", "job_title": "Relationship Manager, Private Banking", "description": "Basel Capital is a multi-family office based in Hong Kong specialized in private real estate investments. We partner with ultra-high net worth families and provide holistic wealth management and investment advisory services.\nThis position is based in Central, Hong Kong and open due to the expansion of our group.\nFor more information, please refer to our website basecg.com and baselpe.com.\n\nResponsibilities:\n\nResponsible for a portfolio of Private Banking (EAM) and their wealthy clients to provide sophisticated advice on solutions;\nPromote full range of Private Banking (EAM) and family office services and achieve the Company\u2019s objectives as well as revenue targets;\nDevelop and maintain long-term client network through effective relationship management, with extensive focus on the clients' financial analysis, protection and investment objectives;\nEnsure the grow of the client base to significantly contribute to the aggregation of AUM;\nDaily telephone contact and meetings with sophisticated clients as well as negotiations with internal interfaces;\nDeliver top service to clients and ensure smooth administration;\nInitiate account openings / closures / update instruction checklists and interface with client to ensure completion of documentation requirements;\nMaintain a close working relationship with the EAM team and private banks to ensure the continued viability of client objectives and management of client assets\nEffectively coordinate with the Company\u2019s teams and strategic partners to develop appropriate strategies and solutions;\nHandle financial transactions and product enquiries as well as all categories of customer service matters;\nProvide guidance, coaching and support to junior members.\n\n\u00a0Requirements:\n\nA university degree, ideally in Banking, Finance, Business Administration or Economics.\nMinimum 5 years of experience as a Relationship Manager, Business Development or Investment Advisor in the EAM, Private Banking, HNWI or Asset Management business;\nSound knowledge of various types of private banking products;\nQualified to carry out Investment regulated activities (Types 4 and 9) under Securities and Futures Ordinance (SFO) is a must;\nStrong client skills combined with the ability to communicate efficiently at all levels are some of your strengths;\nA standout colleague with excellent organizational skills and a structured and efficient approach;\nAble to contribute and deliver high-end dedicated service in a dynamic work environment;\nProficiency in spoken and written English and Chinese, excellent in Putonghua is preferred.\n\nPlease send your full resume with current and expected salary and availability by clicking \u201cApply Now\u201d.\nAll information collected will be treated as strictly confidential and used for recruitment purposes only. (Only shortlisted candidates will be notified)", "employment_types": ["Full Time"], "selling_points": ["Responsible for a portfolio of HNWI clients (EAM)", "Develop and maintain long-term client network", "Ensure the grow of the client base and AUM"], "locations": ["Central"], "categories": ["Banking / Finance", "Private Banking", "Wealth Management"], "post_time": "2022-01-06T04:51:38Z", "salary": {"currency": null, "max": null, "min": null, "period": "monthly", "term": null}, "salary_visible": false, "title_keywords": ["relationship manager", "private banking"], "responsibilities": ["management", "coordinate with", "teams", "transactions", "develop", "financial analysis", "maintain", "client base", "contact", "customer service", "banking", "documentation", "provide guidance", "administration"], "requirements": {"degrees": ["university degree"], "majors": ["finance", "economics", "business administration"], "languages": ["putonghua", "english", "chinese"], "language_level": ["proficiency", "excellent"], "hard_skills": ["dynamic", "securities and futures ordinance", "sfo"], "soft_skills": ["efficient", "organizational skills", "dynamic", "structured"], "languages_combined": [{"language": "putonghua", "language_level": ["excellent", "proficiency"]}, {"language": "english", "language_level": ["excellent", "proficiency"]}, {"language": "chinese", "language_level": ["excellent", "proficiency"]}]}, "experience_required": {"duration": ["minimum 5 years"], "field": ["business development", "business", "investment", "banking", "asset management"]}}, {"job_id": "100003009025864", "location_code": "hk", "company": "Job-Box Personnel", "job_title": "Management Associate (Bank Holiday, 5 day works)", "description": "Key Roles and Responsibilities\u00a0:\n\nProviding quality services and financial solutions to customers and satisfy their changing financial needs.\nPresent investment portfolio to our prestigious personal and corporate clients\nManage the financial needs of a diverse range of customers from mass-market to high-net-worth segments.\nExplore business opportunities and strengthen customer relationships\n\n\n\nQualifications and Skills:\n\nUniversity fresh graduate, preferably in finance or business related discipline.\nStrong client skills with ability to deliver needs based solutions.\nProven organization skills and attention to details\nStrong self-motivation with good interpersonal and analytical skills.\nStrong communication with fluent Cantonese, Mandarin and English.\n\n\n\nCompetitive benefits package, including:\n\nFive-day work week.\nPerformance bonus.\n20 working days annual leave.\nSuperior training and development program.\nProgressive career advancement opportunities.\n\n\n\nWe offer a competitive salary and benefits package and the professional advantages of a dynamic environment that supports your development and recognizes your achievements.\n\nInterested individuals please send your detailed resume and expected salary by clicking\u00a0\"Apply Now\". Only candidates who are authorized to work in Hong Kong will be considered.", "employment_types": ["Full Time", "Part Time", "Permanent", "Contract", "Internship"], "selling_points": ["Superior training and development program.", "5day work, 20 days annual leave, Performance bonus", "Progressive career advancement opportunities."], "locations": ["Central & Western Area"], "categories": ["Banking / Finance", "Private Banking", "Sales, CS & Business Devpt", "Customer Service - Manager", "Marketing / Public Relations", "Management"], "post_time": "2022-01-06T06:38:29Z", "salary": {"currency": "HKD", "max": 24999, "min": 20000, "period": "monthly", "term": null}, "salary_visible": true, "title_keywords": ["management associate"], "responsibilities": ["communication", "business opportunities", "quality"], "requirements": {"degrees": ["fresh graduate"], "majors": ["finance", "business"], "languages": ["cantonese", "english", "mandarin"], "language_level": ["fluent"], "hard_skills": ["analytical skills"], "soft_skills": ["analytical skills", "communication", "diverse", "self-motivation", "attention to details", "organization skills", "interpersonal"], "languages_combined": [{"language": "cantonese", "language_level": ["fluent"]}, {"language": "english", "language_level": ["fluent"]}, {"language": "mandarin", "language_level": ["fluent"]}]}, "experience_required": {"duration": [], "field": []}}, {"job_id": "100003009025818", "location_code": "hk", "company": "Bank of Communications Trustee Limited", "job_title": "Assistant Manager - Private Trust Business Development", "description": "Responsibilities\nExplore and acquire new business by networking through broker/insurance agent/branch etc.\nPromote private trust products such as family/charitable/employee\u2019s share award trust to potential clients through different channels including intermediaries and referrals\nAddress client\u2019s need and provide professional advices so as to maximize business opportunities\nManage client relationship and answer enquiries\nMonitor Know-Your-Customer process and ensure risk management policy is followed\nCollaborate with trust administration team for new client\u2019s onboarding process\nPrepare presentation, marketing and promotional materials\nParticipate in ad hoc projects pertaining to marketing and coordination with Head Office\nPerform ad-hoc assignments as required\nRequirements\nDegree in Law, Accounting or business related disciplines, preferably with professional qualification such as HKCIS, CPA, TEP\n1 year relevant experience in private trust / banking and financial services sector\n2 years or above experience to serve listed companies such as experience in IR or financial PR firm are also welcome\nKnowledge of securities and relevant regulations in Hong Kong\nExcellent business acumen, communication and organization skills\nGood knowledge in PC skills (M Word, Excel and PowerPoint), Chinese typing an advantage\nProficient in both spoken and written English and Chinese (Putonghua a must)\nImmediately available is highly preferred\nCandidate with more experience will be considered for the senior position", "employment_types": ["Full Time", "Permanent"], "selling_points": ["Prepare presentation, marketing", "Degree in Law, Accounting or business", "1 year relevant experience"], "locations": ["Not Specified"], "categories": ["Banking / Finance", "Private Banking", "Financial Services", "Sales, CS & Business Devpt", "Business Development"], "post_time": "2022-01-06T06:33:43Z", "salary": {"currency": null, "max": null, "min": null, "period": "monthly", "term": null}, "salary_visible": false, "title_keywords": ["assistant manager"], "responsibilities": ["collaborate with", "management", "ad-hoc assignments", "business opportunities", "coordination with", "monitor", "promotional materials", "ad hoc projects", "insurance", "administration"], "requirements": {"degrees": ["degree"], "majors": ["business", "related disciplines", "accounting", "law"], "languages": ["putonghua", "english", "chinese"], "language_level": ["advantage", "proficient", "good"], "hard_skills": ["excel", "word", "powerpoint", "typing", "cpa", "pc skills", "acumen"], "soft_skills": ["business acumen", "organization skills", "communication"], "languages_combined": [{"language": "putonghua", "language_level": []}, {"language": "english", "language_level": ["proficient"]}, {"language": "chinese", "language_level": ["proficient", "advantage", "good"]}]}, "experience_required": {"duration": ["2 years", "1 year"], "field": ["pr", "financial services", "relevant experience", "banking", "financial"]}}, {"job_id": "100003009021251", "location_code": "hk", "company": "Haitong International Securities Group Limited", "job_title": "Assistant Relationship Manager \u2013 Private Wealth Management (Ref :JDB/PWM/ARM)", "description": "The Job\n\nAcquire and grow high net worth client base and special focus on the clients' personal financial analysis, protection and investment needs.\nFully understand the client\u2019s needs and objectives and provide financial solutions, i.e. investment products, to satisfy client's needs and objectives..\nUnderstand the level of risk associated with all products and services and ensure that this information and any other pertinent information is appropriately disclosed to the client.\nMaintain a close working relationship with Business Units to ensure the continued viability of client objectives and to ensure coordination of a client\u2019s overall strategies and needs.\nManage and monitor client accounts on an ongoing basis in order to understand changing investment needs and objectives and to coordinate portfolio solutions.\nAssist company to coordinate and execute business project.\nPerform daily operations and customer services.\n\nRequirements\n\nMinimum 3 years\u2019 experience in banking or securities firm.\nPossess qualifications under SFC for marketing investment products.\nFamiliar with investment banking products and good knowledge in corporate finance services.\nGood interpersonal, problem solving and communication skills.\nGood command of written and spoken English and Chinese (including Putonghua).\n\nWe provide attractive remuneration package and fringe benefits for the right candidate. Interested parties please send detailed resume with current and expected salaries to Human Resources Department i) by mail: 22/F, Li Po Chun Chambers, 189 Des Voeux Road Central, HK; ii) by fax: 2537 5431; iii) by getting application method through the Job Opportunities Section of our Corporate website: www.htisec.com; or iv) by using \"APPLY NOW\".\n\nPlease quote the reference in the application. If application is submitted in hard copy format, it should be placed in a sealed envelope marked \u201cConfidential\u201d. All applications will be treated in strict confidence and personal data provided by job applications will be used for recruitment purposes only. A copy of our Personal Information Collection Statement will be available upon request.", "employment_types": ["Full Time", "Permanent"], "selling_points": [], "locations": ["Central"], "categories": ["Banking / Finance", "Private Banking", "Financial Services", "Wealth Management"], "post_time": "2022-01-05T03:26:20Z", "salary": {"currency": null, "max": null, "min": null, "period": null, "term": null}, "salary_visible": false, "title_keywords": ["wealth management", "assistant relationship manager"], "responsibilities": ["monitor", "customer services", "financial analysis", "coordinate", "daily operations", "client base", "maintain", "coordination"], "requirements": {"degrees": [], "majors": [], "languages": ["putonghua", "english", "chinese"], "language_level": ["good command"], "hard_skills": ["problem solving", "investment products"], "soft_skills": ["problem solving", "communication skills", "interpersonal"], "languages_combined": [{"language": "putonghua", "language_level": ["good command"]}, {"language": "english", "language_level": ["good command"]}, {"language": "chinese", "language_level": ["good command"]}]}, "experience_required": {"duration": ["minimum 3 years"], "field": ["securities firm", "banking"]}}, {"job_id": "100003009023378", "location_code": "hk", "company": "Talent Axis Management Consulting Group Limited", "job_title": "VP / AVP, KYC, Private Banking", "description": "Our client, a well-established Bank in Hong Kong, is looking for a high-calibre candidate to join their Group:\n\nResponsibilities:\n\nPerform first checker function in account documentation review of new and existing accounts and identify and follow up required documents according to regulatory and bank requirement\nKeep abreast of prevailing regulatory environment and work with appropriate stakeholders relevant to customers to ensure compliance\nEnsure all relevant policies and regulatory bodies (HKMA), etc. are implemented and adhered to\nPerform the required KYC screening on clients by documenting and corroborating the information obtained on the client as required by the KYC Procedures\n\nRequirements:\n\nDegree holder in related disciplines of Business Administration, Finance, Economics etc.\nMinimum 5 years\u2019 working experience in conducting customer due diligence in banking and finance sector\nExcellent interpersonal and communication skills\nProficient in both English and Chinese; fluency in Putonghua an advantage\n\nInterested candidates please forward your resume (in MS Word format)\u00a0together with current and expected salary details\u00a0by clicking the Apply Now button.", "employment_types": ["Full Time"], "selling_points": ["Bachelor degree holder", "5 years\u2019 relevant experience", "KYC"], "locations": ["Not Specified"], "categories": ["Banking / Finance", "Private Banking", "Sales, CS & Business Devpt", "Customer Service - Manager", "Professional Services", "Legal & Compliance"], "post_time": "2022-01-05T08:30:46Z", "salary": {"currency": null, "max": null, "min": null, "period": "monthly", "term": null}, "salary_visible": false, "title_keywords": ["private banking"], "responsibilities": ["account documentation", "policies", "review", "procedures", "ensure compliance", "kyc"], "requirements": {"degrees": ["degree holder"], "majors": ["related disciplines", "finance", "economics", "business administration"], "languages": ["putonghua", "english", "chinese"], "language_level": ["fluency", "advantage", "proficient"], "hard_skills": ["customer due diligence"], "soft_skills": ["communication skills", "interpersonal"], "languages_combined": [{"language": "putonghua", "language_level": ["fluency", "advantage"]}, {"language": "english", "language_level": ["proficient"]}, {"language": "chinese", "language_level": ["proficient"]}]}, "experience_required": {"duration": ["minimum 5 years"], "field": ["finance", "banking"]}}, {"job_id": "100003009016062", "location_code": "hk", "company": "Bank of China (Hong Kong) Limited", "job_title": "Operation Manager (Middle Office), Private Banking", "description": "Responsibilities:\n\nProvide account opening support, account transactions, credit, loan and investment related transactional processing; covering all kinds of investment products including system input, order maintenance and risks monitoring, etc.\nAttending to general client queries.\u00a0 Liaise with internal and external parties to fulfill client requests and administrative follow-up.\nMonitor the status of credit exposure/excess of client portfolios to ensure that no unauthorized and/or excessive credit facility is granted to clients and all transactions are processed according to bank\u2019s credit policies.\nEnsure that account opening documents and credit documents are in order. Follow up on outstanding documents.\nRegularly review operating procedures and guidelines, and continue to optimize processes and system functionality to improve service quality and productivity.\nFully compliant with regulations and Group policies and guidelines, and be able to highlight, mitigate and protect the bank against credit, legal, documentation, reputational and other risks; to conduct business at all times in a compliance-conscious manner and alert to the potential risks of money laundering and other undesirable transactions/activity during and after client on-boarding process.\n\nRequirements:\n\nDegree or above with major in Finance or related discipline\nAt least 3 years solid working experience in banking/credit operations, preferable in private banking business\nInterpersonal skills \u2013 communicating effectively and provide value adding advice to others, influencing effectively\nAbility to analyze situations, prioritize and implement processes effectively\n\u00a0Familiarity with banking laws and practices to regulations prevailing in Hong Kong\nStrong character and ability to work under stress and withstand pressure", "employment_types": ["Full Time"], "selling_points": ["Provide account opening support", "Degree or above with major in Finance", "At least 3 years solid working experience"], "locations": ["Central"], "categories": ["Banking / Finance", "Private Banking", "Others", "Order Processing & Operation / Settlement"], "post_time": "2022-01-03T08:12:24Z", "salary": {"currency": null, "max": null, "min": null, "period": "monthly", "term": null}, "salary_visible": false, "title_keywords": ["private banking", "operation manager"], "responsibilities": ["regulations", "documentation", "maintenance", "credit documents", "account opening", "policies", "monitoring", "internal and external parties", "monitor", "transactions", "review", "procedures", "guidelines", "quality", "compliance", "system input", "liaise with", "credit facility"], "requirements": {"degrees": ["degree or above"], "majors": ["finance"], "languages": [], "language_level": [], "hard_skills": ["banking laws"], "soft_skills": ["ability to analyze", "interpersonal skills", "prioritize"], "languages_combined": []}, "experience_required": {"duration": ["at least 3 years"], "field": ["business", "banking"]}}, {"job_id": "100003009025334", "location_code": "hk", "company": "Asia Progress Executive Limited", "job_title": "Associate, Financial Crime Compliance - Compliance Department", "description": "Our client is a European Private Banking to cope with the rapid business\u00a0expansion, they are now inviting high caliber candidates to join the team\n\nAssociate ,Financial Crime Compliance - Compliance Department\u00a0\n\nResponsibilities:\n\nAssist the Head of Financial Crime to establish, review and update the AML related guidelines, policies and procedural manuals to ensure they are in line with Group and regulatory requirements;\nReview and investigate transactions triggered by monitoring systems or escalated by front office or other monitoring parties for potential financial crime risks; Report suspicious transactions and escalate for management oversight timely to ensure adequate follow up actions and ongoing monitoring;\nMonitor effective operation of AML tools and processes for transaction monitoring, client screening, payment screening and client risk assessment; Escalate issues for timely resolution and manage necessary remediation;\nConduct regular recalibration and tuning of parameters and drive enhancements for AML tools and systems;\nReview escalated alerts stopped on payment screening system and escalate transactions potentially related to money laundering and sanctions;\nReview alerts from ongoing client screening and manage the escalation of true hits for risk reclassification and monitoring follow up actions;\nTrigger follow up actions and KYC updates upon irregularities noted from transaction monitoring or client screening;\nAssist the Head of AML / Compliance in preparing internal AML training materials;\nPrepare materials for periodic AML governance meetings;\nPerform ad hoc tasks as assigned by Head of AML/Compliance from time to time;\nAssist in audits and inspections, and investigations where required\nInvolvement in special work projects as and when required\nAssist Head of Compliance, Hong Kong and the Compliance team in any other work matters;\nMust solid exp in transaction monitoring and manage AML tools and System\u00a0\n\nCompetencies:\n\nBasic bachelor degree; \u00a0\n5 \u2013 8 years of relevant experience in general compliance and financial crime compliance in private banking industry\u00a0\nMust solid exp in transaction monitoring and manage AML tools and System\u00a0\nA keen interest to learn and perform compliance matters;\nGood interactive, communication and writing skills;\nAble to provide alternative solutions to business;\nMotivated and innovative; able to handle issues and resolve challenges in collaboration with colleagues;\nTeam player\n\nPlease send full resume with\u00a0present & expected\u00a0salary to expedite sourcing\u00a0in\u00a0MS-WORD\u00a0format by clicking \u201cAPPLY NOW\u201d\nPlease quote our reference in your application\nPersonal data provided by job applicants will be used strictly in accordance with the employer\u2019s personal data policies, a copy of which will be provided upon request\nAll information provided will be used for recruitment purpose only", "employment_types": ["Full Time"], "selling_points": ["Deg 5yr Financial crime compliance privatebanking", "AMLtransaction monitoring&manage AML tools&System", "AML/KYC review/CDD periodic review, CDD advisory"], "locations": ["Central & Western Area"], "categories": ["Banking / Finance", "Private Banking", "Professional Services", "Legal & Compliance", "Wealth Management"], "post_time": "2022-01-06T05:30:40Z", "salary": {"currency": null, "max": null, "min": null, "period": "monthly", "term": null}, "salary_visible": false, "title_keywords": ["associate"], "responsibilities": ["regulatory requirements", "transactions", "communication", "payment", "personal data", "compliance", "monitor", "resolution", "kyc", "banking", "report", "management", "review", "monitoring", "ad hoc tasks", "audits", "aml", "irregularities", "guidelines", "policies", "systems", "recruitment"], "requirements": {"degrees": ["degree", "bachelor"], "majors": [], "languages": [], "language_level": [], "hard_skills": ["ms-word", "basic", "aml", "writing skills", "rapid", "kyc"], "soft_skills": ["keen", "timely", "writing skills", "communication", "motivated", "team player", "innovative"], "languages_combined": []}, "experience_required": {"duration": ["8 years"], "field": ["banking industry", "compliance", "general compliance", "relevant experience", "financial"]}}, {"job_id": "100003009019579", "location_code": "hk", "company": "Wellesley Associates Limited", "job_title": "Assistant Relationship Manager job for a Top tier Global Private Bank", "description": "My client is a prominent private bank with robust commercial activities and expansion especially in Asian region. With undoubted commitment in the business, they are currently looking to hire a senior professional to join their front line.\n\nDuties:\n\nProvide primary support to the relationship managers in their daily tasks, managing client relationship and deliver a wide range of private wealth management services to High Net Worth clients\nRespond to client enquiries, monitor transactions and activities in client accounts\nExecute a range of banking and investment transactions (e.g., equities, fixed income, FX, OTC derivative products, mutual funds, alternative investments, deposits and loans) for clients\u00a0\nEnsure full awareness of and adherence to the policy and procedures e.g. credit policy and operation procedures\nCollect and prepare account opening documentations, perform KYC and due diligence, and work with internal departments to process account opening\u00a0\n\n\u00a0Requirements:\n\n3+ years of working experience in private banking sector\nSolid experience in serving high net-worth clients\nStrong understanding of private banking products and services, good knowledge of investments, operational procedures and systems\u00a0\nExcellent interpersonal, communication, work organisation and client interfacing skills\nCustomer-oriented and able to thrive in a fast-paced environment\nPassed in the HKSI Licensing Examination Paper 1, 7 & 8 and /or License Person of Type 1 and 4 under HKMA / SFC\u00a0\nStrong language proficiency, verbal and written English and Chinese (both Cantonese and Mandarin) are essential\n\nWhat you will get in return are the exposure at the bank that could bring your career to the next level, an ideal working environment and a competitive remuneration package will be offered to the successful incumbent.\u00a0\n\nIf you're interested in this role,\u00a0call directly on +852 2847 9957. If this job isn't quite right for you but you are opened for a new position within banking / wealth management side, please contact me for a confidential discussion on your career.", "employment_types": ["Permanent"], "selling_points": ["Join a team with great dynamics", "Attractive total compensation package", "Strong support from management"], "locations": ["Central & Western Area"], "categories": ["Banking / Finance", "Private Banking"], "post_time": "2022-01-04T08:02:24Z", "salary": {"currency": null, "max": null, "min": null, "period": "monthly", "term": null}, "salary_visible": false, "title_keywords": ["assistant relationship manager"], "responsibilities": ["due diligence", "management", "account opening", "kyc", "monitor", "procedures", "transactions", "banking"], "requirements": {"degrees": [], "majors": [], "languages": ["cantonese", "english", "chinese", "mandarin"], "language_level": ["proficiency"], "hard_skills": ["hkma", "hksi"], "soft_skills": ["fast-paced environment", "interested in", "communication", "customer-oriented", "organisation", "interpersonal", "ideal"], "languages_combined": [{"language": "cantonese", "language_level": []}, {"language": "english", "language_level": ["proficiency"]}, {"language": "chinese", "language_level": ["proficiency"]}, {"language": "mandarin", "language_level": []}]}, "experience_required": {"duration": ["3+ years"], "field": ["banking sector"]}}, {"job_id": "100003009020894", "location_code": "hk", "company": "PeopleSearch Ltd", "job_title": "Assistant Relationship Manager", "description": "Our Client, a leading global bank is currently looking for an Assistant Relationship Manager to join their expanding team in Hong Kong. The ideal candidate should process 3+ years\u2019 experience in private banking industry. \u00a0A great opportunity to be a part of dynamic private bank team with global exposure. The right candidate will be offered with attractive compensation package.\n\nResponsibilities\u00a0\u00a0\u00a0\u00a0\u00a0\u00a0\u00a0\u00a0\u00a0\u00a0\u00a0\u00a0\u00a0\u00a0\u00a0\u00a0\u00a0\u00a0\u00a0\u00a0\u00a0\u00a0\u00a0\u00a0\u00a0\u00a0\u00a0\u00a0\u00a0\u00a0\u00a0\u00a0\u00a0\u00a0\u00a0\u00a0\u00a0\u00a0\u00a0\u00a0\u00a0\u00a0\u00a0\u00a0\u00a0\u00a0\u00a0\u00a0\u00a0\u00a0\u00a0\u00a0\u00a0\u00a0\u00a0\u00a0\u00a0\u00a0\u00a0\u00a0\u00a0\u00a0\u00a0\u00a0\u00a0\u00a0\u00a0\u00a0\u00a0\n\nSupport Relationship Managers in providing complete service to clients and contribute to customer retention\u00a0and growth\nServe as customers\u2019 key contact point in initiating customer instructions, monitoring fund payment, and preparing loans disbursement instructions\nPreparation of account opening documents, ensure appropriate document of KYC/AML from the client and ensure all aspect of client\u2019s records are complete and up to date\nEnhance and deepen relationship with clients and deliver customer-focused solutions\nPerform regular reviews with clients to ensure profile is match to clients\u2019 needs.\nPerform task in accordance with regulatory and compliance requirements\n\nRequirements\n\nDegree holder in Business, Finance or related disciplines\nMinimum 3 years of experience in private banking / investment banking / corporate banking industry with proven track record\nStrong understanding of investment products and services\nIndependent, detail oriented, self-motivated and a good team player\nCustomer-focused, with excellent communication and interpersonal skills\nGood command of written and spoken English and Chinese, preferably fluent in Mandarin\n\nInterested applicants please send your full resume (in Word format) together with present and expected salary to Ken Chow\n\nTel: (852) 6377-1283\n\n** For more job opportunities, please visit our website: www.pplesearch.com**", "employment_types": ["Full Time", "Permanent"], "selling_points": ["Degree holder in Business, Finance", "Minimum 3 years of experience in private banking", "Strong understanding of investment products"], "locations": ["Central & Western Area"], "categories": ["Banking / Finance", "Private Banking"], "post_time": "2022-01-05T02:24:35Z", "salary": {"currency": null, "max": null, "min": null, "period": "monthly", "term": null}, "salary_visible": false, "title_keywords": ["assistant relationship manager"], "responsibilities": ["aml", "account opening", "kyc", "monitoring", "compliance", "website", "communication", "payment", "contact", "banking"], "requirements": {"degrees": ["degree holder"], "majors": ["related disciplines", "finance", "business"], "languages": ["english", "chinese", "mandarin"], "language_level": ["good command", "fluent"], "hard_skills": ["aml", "account opening", "investment products", "word", "dynamic", "kyc"], "soft_skills": ["self-motivated", "good team player", "independent", "customer-focused", "detail oriented", "dynamic", "communication and interpersonal skills", "ideal"], "languages_combined": [{"language": "english", "language_level": ["fluent", "good command"]}, {"language": "chinese", "language_level": ["fluent", "good command"]}, {"language": "mandarin", "language_level": ["fluent", "good command"]}]}, "experience_required": {"duration": ["3+ years", "minimum 3 years"], "field": ["banking industry", "investment", "banking"]}}, {"job_id": "100003009020969", "location_code": "hk", "company": "Job-Box Personnel", "job_title": "Graduate Trainee Program (Entry Level, Fresh Grad Welcome, 5 days work)", "description": "The Role and Responsibilities:\n\nOn-the-job training to established related asset management expertise.\nPreparing investment portfolio and global market analysis.\nTo develop investment strategies to achieve client\u2019s short-term and long-term financial objectives.\nOn going manage client\u2019s portfolios according to client\u2019s financial goals.\nPreparing different scheme of investment proposal and portfolio review report.\nIdentify client objectives and offer appropriate financial consultancy.\n\nRequirements:\n\nBachelor degree holder or above in all disciplines\nInnovative and a good team player\nFluency in Cantonese, English and Mandarin\nGood communication and interpersonal skills\nArticulate and detail oriented, ability to multitask in a fast paced environment.\u00a0\n\nJob Offer:\n\nPersonal development and growth opportunities.\nContinuous Learning Sponsorship, medical benefits.\n5 day work week.\n\nWe offer a competitive salary and benefits package and the professional advantages of a dynamic environment that supports your development and recognizes your achievements.\n\nInterested individuals please send your detailed resume and expected salary by clicking\u00a0\"Apply Now\". Only candidates who are authorized to work in Hong Kong will be considered.\n\nAll personal data provided will only be used for recruitment purpose only. Information of candidates not selected will be destroyed in 3 months.", "employment_types": ["Full Time", "Contract", "Internship"], "selling_points": ["5 day work,17-20 annual leave, Performance bonus", "Continuous Learning Sponsorship, medical benefits", "Personal development and growth opportunities"], "locations": ["Others"], "categories": ["Banking / Finance", "Private Banking", "Management", "General Management", "Marketing / Public Relations", "Marketing - Direct Marketing"], "post_time": "2022-01-05T02:42:57Z", "salary": {"currency": "HKD", "max": 19999, "min": 14000, "period": "monthly", "term": null}, "salary_visible": true, "title_keywords": ["graduate trainee"], "responsibilities": ["investment strategies", "preparing investment portfolio", "global market analysis", "develop", "investment proposal", "portfolio review report", "manage client\u2019s portfolios", "asset management"], "requirements": {"degrees": ["bachelor degree holder"], "majors": [], "languages": ["cantonese", "english", "mandarin"], "language_level": ["fluency"], "hard_skills": [], "soft_skills": ["good team player", "detail oriented", "communication and interpersonal skills", "articulate", "ability to multitask", "innovative"], "languages_combined": [{"language": "cantonese", "language_level": ["fluency"]}, {"language": "english", "language_level": ["fluency"]}, {"language": "mandarin", "language_level": ["fluency"]}]}, "experience_required": {"duration": [], "field": []}}, {"job_id": "100003009025521", "location_code": "hk", "company": "Basel Capital Holdings Limited", "job_title": "Investment Analyst, Family Office", "description": "Basel Capital is a multi-family office based in Hong Kong specialized in private real estate investments. We partner with ultra-high net worth families and provide holistic wealth management and investment advisory services.\nThis position is based in Central, Hong Kong and open due to the expansion of our group.\nFor more information, please refer to our website basecg.com and baselpe.com.\n\nResponsibilities:\n\nProvide general public markets investment and portfolio management support to senior management\nCollect market information and identify investment opportunities on the financial market;\nAssist in portfolio management and investment research in U.S. real estate and property markets\nDevelop detailed financial models and prepare investment research reports;\nConduct research, due diligence, financial and industry analysis, investment memorandum preparation, and investment execution for private equity investments;\nPrepare meeting materials for internal meetings such as annual reviews, return projections and others;\nPerform regular and ad-hoc assigned responsibilities and duties that are related to managerial and operational requirements.\n\n\u00a0Requirements:\n\nAt least 2-3 years of experience in asset management, private equity or investment banking;\nBachelor degree holder in Finance, Economics, Accounting, Business, or related discipline\nQualified to carry out Investment regulated activities (Types 4 and 9) under Securities and Futures Ordinance (SFO) preferred;\nStrong analytical and presentation skills;\nSolid knowledge of financial modelling and project management;\nHands-on experience in research, presentation preparation and data mining;\nAble to work independently and under pressure;\nProficient in both written and spoken English, Mandarin and Cantonese.\n\nPlease send your full resume with current and expected salary and availability by clicking \u201cApply Now\u201d.\nAll information collected will be treated as strictly confidential and used for recruitment purposes only. (Only shortlisted candidates will be notified)", "employment_types": ["Full Time"], "selling_points": ["Real estate, private equity, public markets", "Open to IB, PB and buyside candidate", "Sector covers real estate, TMT and healthcare"], "locations": ["Central"], "categories": ["Banking / Finance", "Investment", "Private Banking", "Wealth Management"], "post_time": "2022-01-06T04:53:11Z", "salary": {"currency": null, "max": null, "min": null, "period": "monthly", "term": null}, "salary_visible": false, "title_keywords": ["analyst"], "responsibilities": ["ad-hoc", "due diligence", "management", "market information", "financial models", "analysis", "develop", "reports", "senior management", "conduct research"], "requirements": {"degrees": ["bachelor degree holder"], "majors": ["business", "finance", "economics", "accounting"], "languages": ["cantonese", "english", "mandarin"], "language_level": ["proficient"], "hard_skills": ["securities and futures ordinance", "project management", "data mining", "private equity", "sfo"], "soft_skills": ["work independently", "under pressure", "project management", "presentation skills", "hands-on", "presentation"], "languages_combined": [{"language": "cantonese", "language_level": ["proficient"]}, {"language": "english", "language_level": ["proficient"]}, {"language": "mandarin", "language_level": ["proficient"]}]}, "experience_required": {"duration": ["at least 2-3 years"], "field": ["research", "banking", "investment", "asset management"]}}, {"job_id": "100003009016087", "location_code": "hk", "company": "Bank of China (Hong Kong) Limited", "job_title": "Assist/Deputy Operation Manager (Middle Office), Private Banking", "description": "Responsibilities:\n\nProvide account opening support, account transactions, credit, loan and investment related transactional processing; covering all kinds of investment products including system input, order maintenance and risks monitoring, etc.\nAttending to general client queries.\u00a0 Liaise with internal and external parties to fulfill client requests and administrative follow-up\nMonitor the status of credit exposure/excess of client portfolios to ensure that no unauthorized and/or excessive credit facility is granted to clients and all transactions are processed according to bank\u2019s credit policies.\nEnsure that account opening documents and credit documents are in order. Follow up on outstanding documents.\nRegularly review operating procedures and guidelines, and continue to optimize processes and system functionality to improve service quality and productivity.\nFully compliant with regulations and Group policies and guidelines, and be able to highlight, mitigate and protect the bank against credit, legal, documentation, reputational and other risks; to conduct business at all times in a compliance-conscious manner and alert to the potential risks of money laundering and other undesirable transactions/activity during and after client on-boarding process.\nRequirements:\nDegree or above with major in Finance or related discipline\nAt least 1-2 years working experience in banking/credit operations, preferable in private banking business\nInterpersonal skills \u2013 communicating effectively and provide value adding advice to others, influencing effectively\nAbility to analyze situations, prioritize and implement processes effectively\nStrong character and ability to work under stress and withstand pressure", "employment_types": ["Full Time"], "selling_points": ["Provide account opening support,account transactio", "Degree or above with major in Finance", "At least 1-2 years working experience in banking"], "locations": ["Central"], "categories": ["Banking / Finance", "Credit Analysis / Approval", "Private Banking", "Sales, CS & Business Devpt", "Business Development"], "post_time": "2022-01-03T08:15:08Z", "salary": {"currency": null, "max": null, "min": null, "period": "monthly", "term": null}, "salary_visible": false, "title_keywords": ["private banking", "operation manager"], "responsibilities": ["regulations", "documentation", "maintenance", "credit documents", "account opening", "policies", "monitoring", "internal and external parties", "monitor", "transactions", "review", "procedures", "guidelines", "quality", "compliance", "system input", "liaise with", "credit facility"], "requirements": {"degrees": ["degree or above"], "majors": ["finance"], "languages": [], "language_level": [], "hard_skills": [], "soft_skills": ["ability to analyze", "interpersonal skills", "prioritize"], "languages_combined": []}, "experience_required": {"duration": ["at least 1-2 years"], "field": ["business", "banking"]}}, {"job_id": "100003009023939", "location_code": "hk", "company": "Cheuk Hang Growth", "job_title": "Fund Management Intern / Assistant / Trainee", "description": "Job Description\n\nOur clients are leading financial institutions in Hong Kong. They are currently looking for who interest in Finance to join their investment team as:\n\nResponsibilities:\n\nTo provide tailor-made financial advices to clients\nTo monitor & analyze clients\u2019 investment portfolio\nTo maintain good relationship with clients\n\nRequirements:\n\nUniversity graduate in any discipline\u00a0\nWilling to work with others\nExcellent interpersonal, communications and presentation skills\nAggressive, self-motivated, passionate for better career development\n\n\n\nBenefits:\n\n5 days work\nOn job training\nTraining allowance\nMedical Insurance, competitive salary and attractive bonus\n\nHK residents will only be considered.\nPersonal data will be used for recruitment purpose only.", "employment_types": ["Full Time"], "selling_points": [], "locations": ["Central & Western Area"], "categories": ["Banking / Finance", "Private Banking", "Management", "Management Trainee", "Asset Management"], "post_time": "2022-01-05T10:03:57Z", "salary": {"currency": "HKD", "max": 24999, "min": 20000, "period": "monthly", "term": null}, "salary_visible": true, "title_keywords": ["trainee", "assistant", "intern"], "responsibilities": ["monitor", "maintain good relationship"], "requirements": {"degrees": ["university graduate"], "majors": [], "languages": [], "language_level": [], "hard_skills": [], "soft_skills": ["passionate", "presentation skills", "interpersonal", "self-motivated"], "languages_combined": []}, "experience_required": {"duration": [], "field": []}}, {"job_id": "100003009019029", "location_code": "hk", "company": "DBS Bank Ltd", "job_title": "AVP/Senior Associate, Specialist, Platform and Projects, Private Banking", "description": "Business Function\n\nDBS? Private Banking offers a one-stop, full-service touch-point for total banking requirements and provides the highest level of personalised banking. We have a team of dedicated, experienced investment advisors who identify opportunities in the various asset classes and employ the best strategies and product vehicles to cater to each client?s needs. Coupled with partnerships within the DBS network and with global institutions, we strive to build long-term relationships with our Private Banking clients in Asia by providing them with high quality, timely and extensive wealth management, investment and financial solutions.\n\nResponsibilities\n\nProject Management\n\nPlan, manage and drive multiple project deliverables for the wealth management business\nTake the role of Platform Subject Matter Expert (SME) on Wealth Platform changes related to Credit stream\nWork directly with business segments across regions to ensure all targets and requirements are met\nGather requirements from users and stakeholders, and prepare business requirement documentations for platform changes\nManage internal (business, support, product managers & technology teams) and external (partners and vendors) stakeholders to ensure the delivery of the initiatives and enhancements\nSupport and influence continuous improvement of product/solution development\nOffer training to end users on platform enhancements and initiatives\nCoordinate and/or perform User Acceptance Testing (UAT) for platform change\n\nPlatform Support & Service Manager\n\nKey representative / coordinator for departments being serviced\nTrusted advisor for processes and system enhancements\nManage, handle and follow up on platform related enquiries\n\nRequirements\n\nBachelor?s Degree or above in Business-related major, or Computer Science\n6 years or above business analysis/project management experience\n6 years or above banking/wealth management expertise\nAvaloq experience is an advantage\nCredit risk related domain knowledge is an advantage\nFamiliar with Agile methodology and able to manage multiple complex projects concurrently\nProven ability and strong interpersonal skills to influence cross-functional teams\nAbility to work well with teams & stakeholders and manage multiple projects with competing priorities\n\nApply Now\n\nWe offer a competitive salary and benefits package and the professional advantages of a dynamic environment that supports your development and recognises your achievements.\n\nWe regret only shortlisted candidates will be notified.", "employment_types": ["Full Time"], "selling_points": ["6 years or above business analysis", "Banking/wealth management expertise", "Preferably candidates have credit risk knowledge"], "locations": ["Central"], "categories": ["Banking / Finance", "Private Banking", "Financial Services", "Information Technology (IT)", "IT Project Management / Team Lead"], "post_time": "2022-01-04T06:26:16Z", "salary": {"currency": null, "max": null, "min": null, "period": "monthly", "term": null}, "salary_visible": false, "title_keywords": ["specialist", "senior associate", "private banking"], "responsibilities": ["management", "uat", "project deliverables", "teams", "subject matter expert", "testing", "coordinate", "project management", "plan", "sme"], "requirements": {"degrees": ["degree or above"], "majors": ["business", "computer science"], "languages": [], "language_level": [], "hard_skills": ["project management", "analysis", "dynamic", "agile"], "soft_skills": ["project management", "dynamic environment", "interpersonal skills", "agile"], "languages_combined": []}, "experience_required": {"duration": ["6 years"], "field": ["business analysis", "project management"]}}, {"job_id": "100003009026059", "location_code": "hk", "company": "Bank of China (Hong Kong) Limited", "job_title": "Senior / Application Development Manager(Personal Banking)", "description": "Responsibilities\n\nLead, manage and implement IT personal banking projects, such as investment, debit card or self-service machines\nManage project processes, documentation, progress reporting, status meeting and escalation effectively\nWork closely with users, vendors and collaborate with cross-functional teams for system requirement analysis, effort estimation, design, development, implementation and testing\nMonitor and communicate project progress and issues with project teams Identify dependencies and potential risks across project, take measure to resolve issues and mitigate risk\nTroubleshoot problem and propose recommendation to resolve issue, and collaborate with developers and/or external parties to resolve technical issue\nLiaise and coordinate effectively with both internal and external parties\nReview, implement and execute system disaster recovery procedure\nProvide emergency support and perform system maintenance during non-office hours\n\u00a0\n\nRequirement\n\nUniversity degree in Computer Science, Information Technology or related disciplines\nAt least 5 years of experience in application development and system support\nHands-on experience in Java/C#, SQL or COBOL, JCL, CICS, VSAM, IBM MQ development\nSound knowledge of various technologies such as Oracle, WebSphere, ClearCase, shell scripts, IBM Mainframe MVS\nSelf-initiative an innovative with good analytical, problem-solving, communication and interpersonal skills\nCandidate with less relevant experience would be considered as Application Manager\nProficiency in both Chinese and English, Mandarin is an advantage\nExperience in design and implementation of new brand system is an advantage\n\nWe offer competitive remuneration package and comprehensive fringe benefits including medical and life insurance, and different types of allowances to the right candidate. Interested parties, please submit your application online. For details, please visit our website\u00a0http://www.bochk.com\n\nTo apply:\u00a0\n\nInterested candidates, please click APPLY NOW \u00a0to apply.\n\nData collected would be used for recruitment purposes only. It might also be disclosed to our subsidiaries or Associated Companies to process the information for appointment. Applicants who do not hear from us within 8 weeks may consider their application unsuccessful and their data will be destroyed within 12 months of receipt.", "employment_types": ["Full Time"], "selling_points": ["implement IT personal banking projects", "Monitor and communicate project progress", "At least 5 years of experience"], "locations": ["Shatin Area"], "categories": ["Banking / Finance", "Private Banking", "Information Technology (IT)", "IT Project Management / Team Lead", "IT Management"], "post_time": "2022-01-06T07:10:49Z", "salary": {"currency": null, "max": null, "min": null, "period": "monthly", "term": null}, "salary_visible": false, "title_keywords": [], "responsibilities": ["collaborate with", "liaise", "external parties", "internal and external parties", "design", "troubleshoot", "monitor", "implementation", "project progress", "testing", "teams", "banking", "reporting", "review", "documentation", "cross-functional teams", "maintenance", "analysis", "coordinate"], "requirements": {"degrees": ["university degree"], "majors": ["related disciplines", "computer science", "information technology"], "languages": ["english", "chinese", "mandarin"], "language_level": ["advantage", "proficiency"], "hard_skills": ["java", "oracle", "problem-solving", "cics", "sql", "jcl", "cobol", "c#"], "soft_skills": ["problem-solving", "hands-on", "communication and interpersonal skills", "self-initiative", "comprehensive", "innovative"], "languages_combined": [{"language": "english", "language_level": ["proficiency"]}, {"language": "chinese", "language_level": ["proficiency"]}, {"language": "mandarin", "language_level": ["advantage", "proficiency"]}]}, "experience_required": {"duration": ["at least 5 years"], "field": ["brand", "development", "system support", "design", "sql", "relevant experience", "application development"]}}, {"job_id": "100003009014397", "location_code": "hk", "company": "Page Personnel", "job_title": "US Investment Bank - Assistant Relationship Manager", "description": "Our client is looking for an Assistant Relationship Manager to join their business to deliver private wealth management services to their High-Net-Worth clients. The ideal candidate will have 2+ years of experience in client onboarding, account opening and trade execution for private clients.\n\nClient Details\n\nOur client is the private wealth management segment of a notable global investment bank, which operates in 40+ countries and has 60,000+ employees. They provide financial services to High-Net-Worth clients including investment advisory services and asset management services.\n\nDescription\n\nPerform client on-boarding and account maintenance\nCarry out reviews on account profiles, documentation and investment risk profiles\nExecute banking and investment transactions\nResponsible for client's asset transfer requests\nConduct pre-trade checks and make relevant disclosures to clients\n\nProfile\n\nUniversity degree in Business Management, Banking, Finance or a related discipline\nHKSI Paper 1, 7, 8 passed\nAt least 2 years of experience in assisting private bankers/ relationship managers\nAbility to work under pressure and have excellent communication skills\nGood command of both written and verbal in English and Chinese\n\nJob Offer\n\nWorking hours: 9:00 AM - 6:00 PM\nWorking days: Mon - Fri\nInternational working environment\nWork with the world's largest brands\nExcellent product exposure\n\nTo apply online please click the 'Apply' button below. For a confidential discussion about this role please contact Kira Tang on +852 2258 3538.", "employment_types": ["Full Time", "Permanent"], "selling_points": ["One of the largest Investment Banks", "Excellent product exposure", "International working environment"], "locations": ["Not Specified"], "categories": ["Banking / Finance", "Private Banking", "Retail Banking", "Wealth Management"], "post_time": "2022-01-03T03:21:55Z", "salary": {"currency": null, "max": null, "min": null, "period": "monthly", "term": null}, "salary_visible": false, "title_keywords": ["assistant relationship manager"], "responsibilities": ["management", "work under pressure", "account opening", "transactions", "communication", "contact", "banking", "documentation", "account maintenance", "asset management"], "requirements": {"degrees": ["university degree"], "majors": ["finance", "business"], "languages": ["english", "chinese"], "language_level": ["good command"], "hard_skills": ["business management", "maintenance", "account opening", "hksi paper", "make", "documentation"], "soft_skills": ["work under pressure", "communication skills", "responsible", "ideal"], "languages_combined": [{"language": "english", "language_level": ["good command"]}, {"language": "chinese", "language_level": ["good command"]}]}, "experience_required": {"duration": ["at least 2 years", "2+ years"], "field": []}}, {"job_id": "100003009020803", "location_code": "hk", "company": "Manulife (International) Limited", "job_title": "MPF Customer Service Officer", "description": "Responsibilities\n\nMaintain good relationship with existing or potential customers\nHandle customer enquiries in a professional manner\nCoach junior team member on customer service skills\nFollow up and liaise with relevant parties\u00a0\nRequirements\n\nExperience at customer services/ insurance/ medical industry with 2 years or above\nExcellent customer services skill experience; self-motivated and good team player\nBe proactive and able to work independently,Strong communication skills\u00a0\nGood command of written and spoken English/ Mandarin\u00a0\nDiploma or above in any discipline, Insurance Studies and Qualification of IIQE Paper 1, 2 & 3 will be an advantage", "employment_types": ["Full Time", "Permanent"], "selling_points": ["20k up Income", "Customer Service Experience will be an advantage", "Coach junior team member"], "locations": ["Ngau Tau Kok"], "categories": ["Accounting", "Finance / Accounting Manager", "Banking / Finance", "Private Banking", "Marketing / Public Relations", "Marketing - Brand / Product Management"], "post_time": "2022-01-05T02:06:23Z", "salary": {"currency": null, "max": null, "min": null, "period": "monthly", "term": null}, "salary_visible": false, "title_keywords": ["customer service officer"], "responsibilities": ["handle customer enquiries", "professional manner", "maintain good relationship", "customer service", "liaise with"], "requirements": {"degrees": ["diploma or above"], "majors": ["insurance"], "languages": ["english", "mandarin"], "language_level": ["good command"], "hard_skills": ["iiqe paper"], "soft_skills": ["communication skills", "good team player", "self-motivated", "customer services skill", "work independently", "proactive"], "languages_combined": [{"language": "english", "language_level": ["good command"]}, {"language": "mandarin", "language_level": ["good command"]}]}, "experience_required": {"duration": ["2 years"], "field": ["medical", "insurance", "customer services"]}}, {"job_id": "100003009015897", "location_code": "hk", "company": "Bank of China (Hong Kong) Limited", "job_title": "Client Services Manager, Private Banking", "description": "Responsibilities:\nProvide all-rounded support to Private Banking Relationship Manager\nReceive investment instructions from clients and transmit same for accurate and timely execution and at all times ensure high service quality\nAssist RM or Senior RM to open accounts for clients and to conduct KYC\nAssist RM or Senior RM to prepare credit applications for clients\nAttending to general client queries; liaise with internal and external parties to fulfill client requests and administrative follow-up\nPrepare ad-hoc and regular internal reports for senior management\nFully compliant with regulations and Group policies and guidelines, and to conduct business at all times in a compliance-conscious manner and alert to the potential risks of money laundering and other undesirable transactions/activity\nRequirements:\nDegree holder or above with major in Finance or related discipline\nAt least 6 years solid working experience in serving personal banking clients, of which at least 3 years in private banking\nFamiliar with investment products in private banking field\nInterpersonal skills \u2013 communicating effectively and provide value adding advice to others, influencing, supervising effectively\nAble to analyze situations, prioritize and implement processes effectively\nStrong character and able to work under stress\nGood command of both verbal and written English and Chinese", "employment_types": ["Full Time"], "selling_points": ["Assist RM/Senior RM to open accounts for clients", "Degree holder or above with major in Finance", "At least 6 years solid working experience"], "locations": ["Central"], "categories": ["Banking / Finance", "Private Banking"], "post_time": "2022-01-03T07:53:02Z", "salary": {"currency": null, "max": null, "min": null, "period": "monthly", "term": null}, "salary_visible": false, "title_keywords": ["client services manager", "private banking"], "responsibilities": ["ad-hoc", "regulations", "guidelines", "policies", "internal and external parties", "quality", "banking", "compliance", "transactions", "reports", "kyc", "liaise with", "senior management"], "requirements": {"degrees": ["degree holder"], "majors": ["finance"], "languages": ["english", "chinese"], "language_level": ["good command"], "hard_skills": ["investment products"], "soft_skills": ["interpersonal skills", "prioritize"], "languages_combined": [{"language": "english", "language_level": ["good command"]}, {"language": "chinese", "language_level": ["good command"]}]}, "experience_required": {"duration": ["at least 6 years", "at least 3 years"], "field": ["banking"]}}, {"job_id": "100003009027401", "location_code": "hk", "company": "V Home Property (Hong Kong) Limited", "job_title": "Relationship Executive / Relationship Manager", "description": "Our young and dynamic team is now looking for a\u00a0Relationship Executive / Relationship Manager\u00a0to join the Creative Team at its Hong Kong headquarters.\u00a0We are looking for a proactive and enthusiastic candidate with 0-2 years of experience in sales role, the role will suit a self-driven who can work effectively within a team and in a fast paced environment.\u00a0\n\nJob\u00a0Responsibilities:\n\nParticipate in property exhibitions and seminars organised by the company\nCoordinate property closings, overseeing signing of documents\u00a0\nMaintaining a consistent professional relationship with current and prospective clients\nFollow up all documents and agreements of Sales & Purchase\nWork as customer service answering customers' enquiries\u00a0\nRequirement:\n\n\nMust be available to work on Saturday, Sunday and Public Holidays' Seminar\nPassionate, Enthusiasm and \u201ccan-do\u201d attitude\nExcellent presentation, interpersonal and communication skills\nProactive, independent, self-motivated and able to work under pressure\nGood command of English, Cantonese and Mandarin\nImmediately availability is highly preferred\u00a0\nSales representative for overseas properties work exclusively in relation to properties outside Hong Kong and are not licensed to deal with any properties situated in Hong Kong.\n\nJob Offer:\u00a0\n\nAttractive\u00a0salary package and\u00a0HIGH\u00a0incentive commission (28-38k)\nPromising career progression\nCompany overseas outing\n\n\u00a0Interested parties please apply with resume indicating current & expected salary with date of availability.", "employment_types": ["Full Time", "Permanent"], "selling_points": ["Relationship, account executive, property", "High commission, company outing, challenging", "Young and dynamic with vision, 0-2 years working"], "locations": ["Central"], "categories": ["Banking / Finance", "Investment", "Private Banking", "Property / Real Estate", "Property Consultancy"], "post_time": "2022-01-06T09:53:41Z", "salary": {"currency": "HKD", "max": 34999, "min": 25000, "period": "monthly", "term": null}, "salary_visible": true, "title_keywords": ["executive", "relationship manager"], "responsibilities": ["coordinate", "purchase", "customer service", "maintaining"], "requirements": {"degrees": [], "majors": [], "languages": ["cantonese", "english", "mandarin"], "language_level": ["good command"], "hard_skills": [], "soft_skills": ["passionate", "communication skills", "self-motivated", "independent", "presentation", "can-do", "proactive", "interpersonal", "work under pressure"], "languages_combined": [{"language": "cantonese", "language_level": ["good command"]}, {"language": "english", "language_level": ["good command"]}, {"language": "mandarin", "language_level": ["good command"]}]}, "experience_required": {"duration": [], "field": []}}, {"job_id": "100003009022968", "location_code": "hk", "company": "Randstad Hong Kong Limited", "job_title": "Private Bank Compliance", "description": "about the company\n\nOur client is a leading Regional Bank in APAC. Well-known for their Private Banking and Corporate Banking business\n\nabout the job\n\nMonitor and advise Private Banking activities in compliance perspective\nConduct investment suitability assessments and review product due diligence\nProvide training to front line staff on investment suitability and increase risk awareness & compliance culture. Topics covering material amend/cancel/re-book check, upward post-trade amendment check, order taking process for investment products etc\nAssist in bank-wide compliance projects and initiatives for Private Banking business\n\nskills & experiences required\n\nUniversity Degree in Economics, Finance, Law or Accounting\nAt least 3 to 7 years of relevant experience. Private Banking experience would be an advantage, Retail Banking/Wealth Management experience would be considered\nExperience in performing investment suitability testing is a must\nUnderstand selling practice and good to have product due diligence experience\nWritten and spoken English and conversational Chinese\n\nTo apply online, please click on the link. Alternatively, for a confidential discussion please contact Joanne Lo on + 852 2232 3421 or email: joanne.lo@randstad.com.hk", "employment_types": ["Full Time", "Permanent"], "selling_points": [], "locations": ["Not Specified"], "categories": ["Banking / Finance", "Private Banking", "Professional Services", "Legal & Compliance", "Risk Management"], "post_time": "2022-01-05T07:00:19Z", "salary": {"currency": "HKD", "max": 54999, "min": 45000, "period": "monthly", "term": null}, "salary_visible": true, "title_keywords": [], "responsibilities": ["provide training", "management", "product due diligence", "review", "compliance", "monitor", "testing", "contact", "banking", "order taking"], "requirements": {"degrees": ["university degree"], "majors": ["finance", "economics", "accounting", "law"], "languages": ["english", "chinese"], "language_level": ["conversational"], "hard_skills": ["investment products"], "soft_skills": [], "languages_combined": [{"language": "english", "language_level": ["conversational"]}, {"language": "chinese", "language_level": []}]}, "experience_required": {"duration": ["at least 3 to 7 years"], "field": ["management", "banking experience", "retail banking", "testing", "relevant experience", "investment"]}}, {"job_id": "100003009024113", "location_code": "hk", "company": "China Construction Bank (Asia) Corporation Limited", "job_title": "Manager, Product Development (Structured Product)", "description": "Main Responsibilities\n- Develop new structured products to achieve the strategic objectives of Private Banking Division\n- Manage existing structured products to ensure the competitiveness in the market and identify opportunities for improvements\n- Liaise with internal and external product providers to get new products on shelf\n- Support the review of Terms and Conditions for Accounts and Related Services (For Individuals), Schedule of Services Fees and Safe Deposit Box rentals\n- Monitor investment product risks and perform on-going due diligence on products\n- Evaluate performance of products and perform detailed analysis & report for management's review\n- Conduct training on new products for branches and sales teams\nRequirements\n- University degree holders, preferably major in Finances, Investment or Economics\n- Preferably holder of CFA or other similar qualification\n- Licensed by SFC for regulated activities, Type 1 and Type 4\n- Minimum 3 years' relevant experience in structured product development and management with exposure to various investment products.\n- Strong knowledge in investment structured products and regulatory requirements\n- Strong analytical and project management skills, able to multitask and meet tight deadlines\n- Creative, independent, a self-starter to deliver quality results\n- Strong PC skills with high proficiency in Microsoft Office applications\n- Good interpersonal and communication skills in written and spoken English and Chinese, spoken Putonghua is a must", "employment_types": ["Full Time"], "selling_points": ["Degree holder, prefer major in Finances, Econ, etc", "Preferably holder of CFA, etc", "Licensed by SFC for regulated activities_Type1&4"], "locations": ["Not Specified"], "categories": ["Banking / Finance", "Private Banking"], "post_time": "2022-01-05T10:47:02Z", "salary": {"currency": null, "max": null, "min": null, "period": "monthly", "term": null}, "salary_visible": false, "title_keywords": ["product development", "manager"], "responsibilities": ["due diligence", "management", "analysis", "review", "monitor", "teams", "develop", "evaluate", "schedule", "banking", "liaise with", "report"], "requirements": {"degrees": ["university degree"], "majors": ["economics"], "languages": ["putonghua", "english", "chinese"], "language_level": ["good"], "hard_skills": ["microsoft office", "cfa", "investment products", "project management", "pc skills"], "soft_skills": ["communication skills", "meet tight deadlines", "independent", "creative", "project management skills", "multitask", "structured", "interpersonal"], "languages_combined": [{"language": "putonghua", "language_level": ["good"]}, {"language": "english", "language_level": ["good"]}, {"language": "chinese", "language_level": ["good"]}]}, "experience_required": {"duration": ["minimum 3 years"], "field": ["investment", "product development", "relevant experience", "management"]}}, {"job_id": "100003009028771", "location_code": "hk", "company": "Robert Half", "job_title": "AVP/VP - Financial Reporting, Leading Bank", "description": "Our client is a leading International bank with operations in both banking and treasury services.\n\n\n\nPerform financial reporting functions and handle monthly, quarterly and year-end reporting e.g. preparation of financial reports, interim and annual reports\nEffective control on the operations, structure and workflow of financial data and general ledger production of the Group\nFormulate changes in accounting policies and practices or the adoption of new accounting policies and the monitoring of their subsequent implementations\nAssist in enhancements to financial controls and reporting process including automation and UAT\nLiaise with external auditors for annual audit and tax matters\n\n\nRequirements:\n\nBachelor's Degree in Accounting, Finance or relevant discipline\nMinimum 3 years' experience in banking and financial accounting /financial reporting functions\nMember of CPA is an added advantage\nHigh level of multi-tasking and time management skill are required\nA team-player with excellent working attitude; willing to take on multiple functions\nExcellent verbal and written communication skills\n\n\nApply Today\n\nTo apply online (Word attachment only), please click the 'Apply' button. Please note that only short-listed candidates will be contacted.", "employment_types": ["Full Time", "Permanent"], "selling_points": ["A leading retail banking and corporate banking", "Fringe benefit with decent bonus", "Good exposure with career progression"], "locations": ["Central & Western Area"], "categories": ["Banking / Finance", "Corporate Banking", "Private Banking", "Retail Banking"], "post_time": "2022-01-07T03:07:38Z", "salary": {"currency": null, "max": null, "min": null, "period": "monthly", "term": null}, "salary_visible": false, "title_keywords": [], "responsibilities": ["data", "operations", "general ledger", "communication", "accounting policies", "liaise with", "tax matters", "control", "uat", "reports", "banking", "reporting", "management", "annual audit", "monitoring", "year-end", "financial reports", "financial reporting", "external auditors"], "requirements": {"degrees": ["degree", "bachelor"], "majors": ["finance", "accounting"], "languages": [], "language_level": [], "hard_skills": ["cpa", "word"], "soft_skills": ["team-player", "communication skills", "multi-tasking", "time management skill"], "languages_combined": []}, "experience_required": {"duration": ["minimum 3 years"], "field": ["accounting", "financial", "banking"]}}, {"job_id": "100003009031094", "location_code": "hk", "company": "Hang Seng Bank Ltd", "job_title": "Relationship Manager / Senior Relationship Manager", "description": "Private Banking Department - Private Banking and Trust Services\n\n\nWe are currently seeking a high caliber professional to join our department as\u00a0Relationship Manager / Senior\u00a0Relationship Manager.\n\n\nPrincipal responsibilities:\nDevelop and manage a portfolio of private banking customers\nProvide investment advice and deliver premium service to customers and execute their orders\nPerform investment portfolios analysis, monitor the performance and make necessary recommendation on portfolio re-allocation\nManage the credit quality and monitor the exposure of customers\u2019 loan portfolios\nWork with internal departments to solicit business referrals\nRequirements\nUniversity degree in a related discipline OR other relevant qualifications such as CFP or CFA\nPasses in the HKSI licensing examinations\nMinimum 6 years\u2019 banking experience, with good knowledge of investment products\nStrong sales orientation and ability to work under pressure\nAbility to communicate effectively, embrace change and overcome challenges\nAbility to be resilient in face of difficult situations\nStrong desire of self-improvement and learn from experiences\nGood communication, interpersonal, analytical and relationship management skills\nProficiency in both written English and Chinese. Fluency in Putonghua and other dialects an advantage\nHigh level of customer centricity mindset with dedication to deliver exceptional quality services for customers\n\nIf you would like to explore other opportunities at Hang Seng Hong Kong, please visit www.hangseng.com/careers/ for details.\n\nThe health and safety of our employees and candidates is very important to us. Due to the current situation related to the Novel Coronavirus (2019-nCoV), we\u2019re leveraging our digital capabilities to ensure we can continue to recruit top talent at the HSBC Group. As your application progresses, you may be asked to use one of our digital tools to help you through your recruitment journey. If so, one of our Resourcing colleagues will explain how our video-interviewing technology will be used throughout the recruitment process and will be on hand to answer any questions you might have.\n\nAll information provided by applicants will be used only for recruitment purposes and will be used strictly in accordance with the Bank's personal data policies, a copy of which may be obtained by the applicant upon request. Unless otherwise instructed in writing by the applicant concerned, applicants may be considered for other suitable positions within the Bank and its related companies. The personal data of unsuccessful job applicants may be retained for a maximum of two years from the date when the job application is rejected and such data may be retained for a longer period if there is a subsisting reason that obliges the Bank to do so, after which the personal data will be destroyed.", "employment_types": ["Full Time"], "selling_points": [], "locations": ["Not Specified"], "categories": ["Banking / Finance", "Private Banking", "Sales, CS & Business Devpt", "Direct Sales"], "post_time": "2022-01-07T08:57:48Z", "salary": {"currency": null, "max": null, "min": null, "period": "monthly", "term": null}, "salary_visible": false, "title_keywords": ["senior relationship manager", "relationship manager"], "responsibilities": ["analysis", "investment portfolios", "quality", "monitor", "develop", "monitor the performance", "banking"], "requirements": {"degrees": ["university degree"], "majors": [], "languages": ["putonghua", "english", "chinese"], "language_level": ["fluency", "advantage", "proficiency"], "hard_skills": ["cfa", "investment products", "hksi", "reason"], "soft_skills": ["communication", "novel", "interpersonal", "work under pressure"], "languages_combined": [{"language": "putonghua", "language_level": ["fluency", "advantage"]}, {"language": "english", "language_level": ["proficiency"]}, {"language": "chinese", "language_level": ["proficiency"]}]}, "experience_required": {"duration": ["minimum 6 years"], "field": ["investment", "banking experience"]}}, {"job_id": "100003009027228", "location_code": "hk", "company": "DBS Bank Ltd", "job_title": "AVP, Specialist, Business Audit (Corporate Banking/Grp Transaction Services)", "description": "Business Function\u00a0\n\nGroup Audit helps the Board and Executive Management meet the strategic and operational objectives of the DBS Group. We conduct independent checks to ensure that the Group\u2019s risk and control processes are adequate and effective. All our team members are highly sought-after professionals who work as trusted advisors to our clients, in all matters related to a company\u2019s internal controls.\u00a0\n\nResponsibilities\n\nUndertake audit engagements as assigned by the Regional Audit Specialist and/or ED/SVP/VP of the team according to audit plan.\nAdvise and apprise promptly the Regional Audit Specialist and/or ED/SVP/VP of the team of all major risk, control and regulatory issues arising during the audit.\nExecute and complete all audits in accordance with departmental and professional standards and supervise team members during assigned audit engagements.\nAssist where appropriate in the update and maintenance of the audit strategy and plan.\nUpdate, maintain or review audit risk matrices, including audit work papers for each audit engagement.\nEvaluate controls over fraud risk but not to detect and investigate fraud events which is the responsibility of the 1st and 2nd lines of defence respectively.\nTest and follow up outstanding audit issues for proper implementation during each audit engagement.\nMaintain key relationships with middle level management and stakeholders, raise potential risk and control issues to audit management.\nKeep abreast of professional development opportunities to enhance skills and competence.\nProvide audit team members with proper guidance, coaching and supervision.\nProvide consultancy advice to Business/Support Units on new or revised policies and procedures so as to build up Audit\u2019s identity as trusted advisor.\nAdherence to audit charter, audit methodology, Institute of Internal Auditors (IIA) standards and relevant code of ethics, and regulatory requirements.\n\nRequirements\n\nDegree holder\u00a0in related discipline\n6-8 years' experience with relevant business or auditing background in financial institutions, external audit firms or consulting firms.\nPrior experience in risk management and control functions, auditing and data analytics would be an advantage but not essential\nGood knowledge of commercial banking (including cash management and trade finance)\nGood understanding of latest digital and data management technologies such as blockchain, artificial intelligence, etc.\nGood reporting, presentation and communication skills, both orally and in writing\nAbility to work independently and collaborate with internal / external stakeholders to achieve desired outcomes\nBe open-minded, agile and adaptable to changes\n\nApply Now\n\nWe offer a competitive salary and benefits package and the professional advantages of a dynamic environment that supports your development and recognises your achievements.\n\nWe regret only shortlisted candidates will be notified.", "employment_types": ["Full Time"], "selling_points": ["Pension Fund Scheme", "Medical Coverage for Dependents", "Career Development"], "locations": ["Quarry Bay"], "categories": ["Accounting", "Audit", "Banking / Finance", "Corporate Banking", "Private Banking"], "post_time": "2022-01-06T09:25:51Z", "salary": {"currency": null, "max": null, "min": null, "period": "monthly", "term": null}, "salary_visible": false, "title_keywords": ["specialist"], "responsibilities": ["guidance", "control", "management", "maintenance", "policies", "regulatory requirements", "supervise team members", "review", "audit", "implementation", "procedures", "evaluate", "maintain", "plan", "audits"], "requirements": {"degrees": ["degree holder"], "majors": [], "languages": [], "language_level": [], "hard_skills": ["blockchain", "data management", "agile", "data analytics", "dynamic"], "soft_skills": ["communication skills", "work independently", "dynamic environment", "agile", "adaptable", "open-minded", "orally", "presentation"], "languages_combined": []}, "experience_required": {"duration": ["6-8 years"], "field": ["consulting firms", "risk management", "audit", "business", "financial institutions"]}}, {"job_id": "100003009016147", "location_code": "hk", "company": "Bank of China (Hong Kong) Limited", "job_title": "(Assistant) Product & Portfolio Manager, Private Banking", "description": "Responsibilities:\nAssist in the development of private banking product and process management including continuous monitoring and after sales services\nAssist in product, sales and service processes review.\nOrder execution to counterparties\nProduction of sales documents for bond trade\nComplete other tasks assigned by senior\nRequirements:\nUniversity or above (major: business administration or bank related subjects are better)\nAt least 1 year relevant work experience in financial markets\nFamiliar with various types of investment products, risk management knowledge and regulatory requirements\nGood communication, presentation and negotiation skills\nA strong command of spoken and written Chinese (including Chinese word processing)\nProficiency in MS Office and/or VBA and Chinese word processing", "employment_types": ["Full Time"], "selling_points": ["Order execution to counterparties", "Complete other tasks assigned by senior", "At least 1 year relevant work experience"], "locations": ["Central"], "categories": ["Banking / Finance", "Private Banking", "Others"], "post_time": "2022-01-03T08:25:12Z", "salary": {"currency": null, "max": null, "min": null, "period": "monthly", "term": null}, "salary_visible": false, "title_keywords": ["manager", "assistant", "private banking"], "responsibilities": ["management", "review", "other tasks", "continuous monitoring", "banking"], "requirements": {"degrees": [], "majors": [], "languages": ["chinese"], "language_level": ["proficiency"], "hard_skills": ["vba", "investment products", "chinese word processing", "ms office"], "soft_skills": ["communication", "negotiation skills", "presentation"], "languages_combined": [{"language": "chinese", "language_level": ["proficiency"]}]}, "experience_required": {"duration": ["at least 1 year"], "field": ["financial markets"]}}, {"job_id": "100003009020295", "location_code": "hk", "company": "Harbridge Partners Limited", "job_title": "Contract Legal Assistant", "description": "Title:\u00a0 \u00a0 \u00a0 \u00a0 \u00a0 \u00a0 \u00a0 \u00a0 \u00a0 \u00a0 \u00a0 \u00a0 Contract Legal Assistant\n\nLocation:\u00a0\u00a0\u00a0\u00a0\u00a0 \u00a0\u00a0\u00a0\u00a0\u00a0\u00a0\u00a0\u00a0\u00a0\u00a0 Hong Kong\n\nBackground: \u00a0\u00a0\u00a0\u00a0\u00a0\u00a0\u00a0\u00a0\u00a0\n\nOur client is an established Asian banking and financial services group, head quartered in Hong Kong, and is looking to hire Contract Legal Assistant positions.\n\nResponsibilities:\n\nProof- read, review, and modify drafts of legal document or transaction documents such as trust deeds, agreements, fee quotations in relation to corporate trust or fund business including but not limited to bond trustee, escrow agent and fund custodian related (private fund or authorized fund) services\nCommunicate with stakeholders for the follow up of documentation and administration matters on both new and existing cases\nPerform ad-hoc assignments as required\n\nRequirements:\n\nDiploma in Legal Studies, Law, or related disciplines\n1-year relevant experience in handling legal document\nProficient in both spoken and written English and Chinese, Putonghua a plus\nProficient in MS office application\nImmediately available is highly preferred\nFresh graduates are welcome\n\nWork Benefits/ Work Environment:\n\nGreat Career progression.\nGreat Training and Career Path\nGreat\u00a0MPF Pension Scheme\nGood Work Life Balance\nGreat working hours\n\nHarbridge Partners Limited\nEmployment Agency Licence:\u00a0 65522", "employment_types": ["Full Time", "Permanent"], "selling_points": ["Assistant,Legal Documents,Adhoc assignment,English", "Trust deeds,Agreements,Fee quotations,Contract", "Private Fund or Authorized Fund Services,Chinese"], "locations": ["Central & Western Area"], "categories": ["Banking / Finance", "Private Banking", "Professional Services", "Legal & Compliance", "Order Processing & Operation / Settlement"], "post_time": "2022-01-04T16:20:22Z", "salary": {"currency": null, "max": null, "min": null, "period": null, "term": null}, "salary_visible": false, "title_keywords": ["legal assistant"], "responsibilities": ["communicate with", "ad-hoc assignments", "review", "documentation", "administration"], "requirements": {"degrees": ["diploma"], "majors": ["related disciplines", "law"], "languages": ["putonghua", "english", "chinese"], "language_level": ["proficient"], "hard_skills": ["plus", "ms office"], "soft_skills": [], "languages_combined": [{"language": "putonghua", "language_level": ["proficient"]}, {"language": "english", "language_level": ["proficient"]}, {"language": "chinese", "language_level": ["proficient"]}]}, "experience_required": {"duration": ["1-year"], "field": ["relevant experience", "legal"]}}, {"job_id": "100003009025750", "location_code": "hk", "company": "DBS Bank Ltd", "job_title": "Vice President / Assistant Vice President \u2013 Wealth Management Operations", "description": "Business Function\n\nGroup Technology and Operations (T&O) enables and empowers the bank with an efficient, nimble and resilient infrastructure through a strategic focus on productivity, quality & control, technology, people capability and innovation. In Group T&O, we manage the majority of the Bank's operational processes and inspire to delight our business partners through our multiple banking delivery channels.\n\nResponsibilities:\n\nSupport Wealth Management of the Bank and oversee payment servicing, loan and deposit processing and relevant support functions/reporting under Wealth Management Operations\nLead and implement various business initiatives and projects in term of system and processing procedure by considering operation flows, markets, upcoming regulations, controls' requirements\nManage payment service including inward and outward remittance for wealth management customers.\u00a0 Ensure daily processing/reporting are properly processed within pre-defined cutoff time and timely escalation for irregular cases being detected, if any\nSupport deposit and loan processing covering drawdown, rollover and rate maintenance.\u00a0\nHandling of regulatory reports such as GSIB, HKMA annual return, Granular Data Reporting (GDR), Deposit Protection Scheme (DPS), FATCA and CRS.\nStrengthen the risk and control mind set within the team and promote the risk awareness culture\nLiaise with business partners on the user requirements. Participate and monitoring the UAT status to ensure achieving project timeline. Drive, provide constant updates about the progress of each project and present it accordingly\nIdentify areas of improvement and drive for changes to ease employee pain points and reduce manual processes\nWork with senior business stakeholders to review Wealth Operations related service concerns, system and outsourced related service level\nReview and update SOPs regularly in order to ensure compliance with internal and external guidelines/regulations.\nPeople management and development for the team to optimize operations efficiency and resources planning\n\nRequirements:\n\nUniversity degree in Finance with at least 8 years hands-on experience on payment where at least 5 years in managerial role. Banking and Brokerage business knowledge is preferable.\nGood knowledge and experience in International Tax Regulations documentation handling and reporting such as GSIB, HKMA, DPS, GDR, FATCA/CRS, etc.\nKnowledge and experience in both local and overseas payment service including CHATS, TT and SWIFT usage\nUnderstanding of loan and deposit products, families with SWIFT message standards and banking operations\nKnowledge on regulatory requirement for investment products settlement, understanding of accounting concept, payment systems, trade settlement & process re-engineering\nEffective interpersonal and communication skill with great team spirits to work with various key stakeholders\nExcellent attention to detail\nGood command of written and spoken English and Chinese. Proficiency in Putonghua an advantage\n\nApply Now\n\nWe offer a competitive salary and benefits package and the professional advantages of a dynamic environment that supports your development and recognises your achievements.\n\nWe regret only shortlisted candidates will be notified.", "employment_types": ["Full Time"], "selling_points": ["Experience in wealth management operations", "Knowledge in payment, loans", "With people management experience"], "locations": ["Others"], "categories": ["Banking / Finance", "Corporate Banking", "Private Banking", "Retail Banking"], "post_time": "2022-01-06T06:26:01Z", "salary": {"currency": null, "max": null, "min": null, "period": "monthly", "term": null}, "salary_visible": false, "title_keywords": ["vice president", "operations", "wealth management", "assistant vice president"], "responsibilities": ["regulations", "reporting", "management", "business initiatives", "control", "uat", "maintenance", "data", "guidelines", "operations", "monitoring", "review", "ensure compliance", "payment", "reports", "sops", "liaise with", "planning"], "requirements": {"degrees": ["university degree"], "majors": ["finance"], "languages": ["putonghua", "english", "chinese"], "language_level": ["advantage", "proficiency", "good command"], "hard_skills": ["crs", "hkma", "investment products", "fatca", "swift", "dynamic", "documentation"], "soft_skills": ["dynamic environment", "communication skill", "hands-on", "attention to detail", "interpersonal"], "languages_combined": [{"language": "putonghua", "language_level": ["proficiency", "advantage"]}, {"language": "english", "language_level": ["good command"]}, {"language": "chinese", "language_level": ["good command"]}]}, "experience_required": {"duration": ["at least 8 years", "at least 5 years"], "field": ["finance", "managerial"]}}, {"job_id": "100003009017389", "location_code": "hk", "company": "Links International", "job_title": "Compliance Manager - Wealth Management", "description": "About the Company:\n\nOur client is an international private bank, currently looking for an experienced Compliance Manager to join their expanding business in Hong Kong.\n\n\nJob Description:\n\nProvide full range of compliance advisory and support to both frontline and back office on day-to-day operations and issues such as licensing, update of operational manuals/procedures, new marketing/product initiatives;\nKeep abreast of regulatory changes and drive the appropriate corresponding changes in policies and procedures for the compliance purpose\nDevelop and perform regular compliance risk reviews including thematic compliance review,\nProvide compliance advice and support for Wealth Management business in Hong Kong\nHandle enquiries from regulators and external parties\n\nRequirement:\n\nBachelor holder in related discipline\nMore than 8 years of working experience in compliance\nFluent English and Mandarin\nExperience in all-rounded compliance duties", "employment_types": ["Full Time", "Permanent"], "selling_points": ["Fast expanding private bank", "All-rounded duties", "Stable working hours"], "locations": ["Tsim Sha Tsui"], "categories": ["Banking / Finance", "Private Banking", "Financial Services", "Wealth Management"], "post_time": "2022-01-03T16:28:03Z", "salary": {"currency": null, "max": null, "min": null, "period": "monthly", "term": null}, "salary_visible": false, "title_keywords": ["wealth management", "compliance manager"], "responsibilities": ["management", "policies", "compliance", "day-to-day operations", "back office", "procedures", "develop", "review", "handle enquiries", "external parties"], "requirements": {"degrees": ["bachelor"], "majors": [], "languages": ["english", "mandarin"], "language_level": ["fluent"], "hard_skills": [], "soft_skills": [], "languages_combined": [{"language": "english", "language_level": ["fluent"]}, {"language": "mandarin", "language_level": ["fluent"]}]}, "experience_required": {"duration": ["8 years"], "field": ["compliance"]}}, {"job_id": "100003009015356", "location_code": "hk", "company": "Page Personnel", "job_title": "Client Relationship Support - Trust Services & Private Banking", "description": "* Support the promotion of private trust products to potential clients through different channels including intermediaries and referrals\n* Manage client relationship and answer enquiries\n\nClient Details\n\nThe client is a large Hong Kong bank\n\nDescription\n\n* Support the promotion of private trust products to potential clients through different channels including intermediaries and referrals\n* Manage client relationship and answer enquiries\n* Prepare presentation, marketing and promotional materials\n* Monitor KYC process and ensure risk management policies are followed\n* Collaborate with trust administration team on new client's onboarding process\n* Participate in ad hoc projects pertaining to marketing\n* Perform ad-hoc assignments as required\n\nProfile\n\nJob requirements:\n* Degree in Law, Accounting or business related disciplines, preferably with professional qualification such as HKCIS, CPA and STEP.\n* Relevant experience in private trust / banking or financial services sector\n* Good communication, interpersonal and organizational skills\n* Proficient in both spoken and written English and Chinese Languages\n\nJob Offer\n\nExcellent remuneration package and opportunities for career growth", "employment_types": ["Full Time", "Temporary"], "selling_points": ["Dynamic working environment", "Opportunities for career progression", "Challenging project"], "locations": ["Not Specified"], "categories": ["Banking / Finance", "Private Banking"], "post_time": "2022-01-03T06:34:56Z", "salary": {"currency": null, "max": null, "min": null, "period": "monthly", "term": null}, "salary_visible": false, "title_keywords": ["private banking"], "responsibilities": ["collaborate with", "management", "policies", "ad-hoc assignments", "monitor", "promotional materials", "ad hoc projects", "kyc", "administration"], "requirements": {"degrees": ["degree"], "majors": ["business", "related disciplines", "accounting", "law"], "languages": ["english", "chinese"], "language_level": ["proficient"], "hard_skills": ["cpa"], "soft_skills": ["communication", "organizational skills", "interpersonal"], "languages_combined": [{"language": "english", "language_level": ["proficient"]}, {"language": "chinese", "language_level": ["proficient"]}]}, "experience_required": {"duration": [], "field": ["financial services", "relevant experience", "banking"]}}, {"job_id": "100003009012807", "location_code": "hk", "company": "Job-Box Personnel", "job_title": "Business Management Associate [5 Days Work, Bank Holiday]", "description": "Key Roles and Responsibilities\u00a0:\n\nProviding quality services and financial solutions to customers and satisfy their changing financial needs.\nPresent investment portfolio to our prestigious personal and corporate clients\nManage the financial needs of a diverse range of customers from mass-market to high-net-worth segments.\nExplore business opportunities and strengthen customer relationships\n\n\n\nQualifications and Skills:\n\nUniversity fresh graduate, preferably in finance or business related discipline.\nStrong client skills with ability to deliver needs based solutions.\nProven organization skills and attention to details\nStrong self-motivation with good interpersonal and analytical skills.\nStrong communication with fluent Cantonese, Mandarin and English.\n\n\n\nCompetitive benefits package, including:\n\nFive-day work week.\nPerformance bonus.\n20 working days annual leave.\nSuperior training and development program.\nProgressive career advancement opportunities.\n\n\n\nWe offer a competitive salary and benefits package and the professional advantages of a dynamic environment that supports your development and recognizes your achievements.\n\nInterested individuals please send your detailed resume and expected salary by clicking\u00a0\"Apply Now\". Only candidates who are authorized to work in Hong Kong will be considered.", "employment_types": ["Full Time", "Permanent", "Internship"], "selling_points": ["Superior training and development program.", "5day work, 20 days annual leave, Performance bonus", "Progressive career advancement opportunities."], "locations": ["Eastern Area"], "categories": ["Banking / Finance", "Private Banking", "Marketing / Public Relations", "Marketing - Direct Marketing", "Others", "Student / Fresh Graduate / No Experience"], "post_time": "2022-01-02T08:19:49Z", "salary": {"currency": "HKD", "max": 24999, "min": 17000, "period": "monthly", "term": null}, "salary_visible": true, "title_keywords": ["management associate"], "responsibilities": ["communication", "business opportunities", "quality"], "requirements": {"degrees": ["fresh graduate"], "majors": ["finance", "business"], "languages": ["cantonese", "english", "mandarin"], "language_level": ["fluent"], "hard_skills": ["analytical skills"], "soft_skills": ["analytical skills", "communication", "diverse", "self-motivation", "attention to details", "organization skills", "interpersonal"], "languages_combined": [{"language": "cantonese", "language_level": ["fluent"]}, {"language": "english", "language_level": ["fluent"]}, {"language": "mandarin", "language_level": ["fluent"]}]}, "experience_required": {"duration": [], "field": []}}, {"job_id": "100003009015489", "location_code": "hk", "company": "Asia Progress Executive Limited", "job_title": "Regulatory Compliance / Conduct Risk Contract \u2013 Private Banking (One Year Contract) $30K-40K", "description": "Our client is Foreign Private Banking To cope with the rapid business expansion they are now inviting high caliber candidates to join the team\n\nRegulatory Compliance / Conduct Risk Contract \u2013 Private Banking(One Year Contract)\u00a0\u00a0$30K-40K\u00a0\n\n\nResponsibilities:\n\nSupports the Head of Conduct Risk in discharging his/her duties\nAssists to review training materials and provide necessary regulatory support to trainers (e.g. 1st line of defense).\nAssists to manage the implementation of Compliance transformation projects in different compliance workstreams\nAssists to implement remedial actions resulted from regulatory exam or internal reviews.\nActs as coordinator to carry out gap analysis to ensure policies and procedures in alignment with Laws and Regulations & requirements.\nAssists to issue compliance alerts and newsletters on new /revised laws and regulations with implications for the Bank and communicate the latest development of regulatory landscape and enforcement news.\nHandles compliance related Head Office reporting.\nProvides support on appropriate training and education to staff on compliance matters.\nHandles ad hoc compliance duties\n\n\u00a0Requirement:\n\nDegree holder, preferably in business, finance, accounting or law discipline.\nWith 2-3 yrs compliance risk experience in banking industry\nGood knowledge of the HKMA guidelines.\nSelf-motivated and work independently.\nExcellent command in both written and spoken English and Chinese\n\n\n\nPlease send full resume with\u00a0present & expected\u00a0salary to expedite sourcing\u00a0in\u00a0MS-WORD\u00a0format by clicking \u201cAPPLY NOW\u201d\n\nPlease quote our reference in your application\n\nPersonal data provided by job applicants will be used strictly in accordance with the employer\u2019s personal data policies, a copy of which will be provided upon request\n\nAll information provided will be used for recruitment purpose only", "employment_types": ["Contract"], "selling_points": ["Degree holder 1yr compliance risk exp in banking", "private banking and wealth management", "Compliance risk management in banking"], "locations": ["Central & Western Area"], "categories": ["Banking / Finance", "Private Banking", "Professional Services", "Legal & Compliance", "Wealth Management"], "post_time": "2022-01-03T06:49:44Z", "salary": {"currency": null, "max": null, "min": null, "period": "monthly", "term": null}, "salary_visible": false, "title_keywords": ["private banking"], "responsibilities": ["regulations", "reporting", "ad hoc", "policies", "analysis", "compliance", "review", "implementation", "procedures"], "requirements": {"degrees": ["degree holder"], "majors": ["finance", "business", "accounting", "law"], "languages": ["english", "chinese"], "language_level": ["excellent"], "hard_skills": ["hkma", "ms-word"], "soft_skills": ["self-motivated", "work independently"], "languages_combined": [{"language": "english", "language_level": ["excellent"]}, {"language": "chinese", "language_level": ["excellent"]}]}, "experience_required": {"duration": [], "field": ["banking industry", "compliance"]}}, {"job_id": "100003009014991", "location_code": "hk", "company": "Connexe Search Limited", "job_title": "Compliance Manager, Private Wealth Management (60k)", "description": "Our client is a well-regarded regional bank. They are currently looking for Manager, Private Banking Compliance in Legal and Compliance Department.\n\n\n\nResponsibilities:\n\nReport to Compliance Unit Head and Department Head\nProvide compliance advisory, training and monitoring\u00a0to Private Banking business and staff\nReview Investment Product Due Diligence (PDD) performed by Product Teams in Private Banking\nUpdate and implement policies & procedures, compliance plan and manuals related to Private Banking business\nEnsure business in compliance to local regulatory requirements and internal policies & procedures\n\nRequirements:\n\nDegree or above\nGood communication skills and sound knowledge of Banking Ordinance, Securities & Futures Ordinance, selling process and PI requirements\n5+ years' experience in general compliance in private banking/ wealth management\nCAMS/ CPA is a plus\nProficient spoken and written English and Chinese (Cantonese & Mandarin)\u00a0\n\nPlease click Apply Now or email your full resume in MS Word format quoting the job reference N211413 in the subject field. Your interest will be treated in strict confidence. Only shortlisted candidates will be notified.", "employment_types": ["Full Time"], "selling_points": ["5+ years in private banking compliance", "compliance advisory & training, monitoring", "PDD review, investment products"], "locations": ["Central & Western Area"], "categories": ["Banking / Finance", "Private Banking", "Treasury", "Professional Services", "Legal & Compliance"], "post_time": "2022-01-03T04:49:28Z", "salary": {"currency": null, "max": null, "min": null, "period": "monthly", "term": null}, "salary_visible": false, "title_keywords": ["wealth management", "compliance manager"], "responsibilities": ["product due diligence", "policies", "regulatory requirements", "review", "monitoring", "compliance", "teams", "procedures", "plan", "banking", "report"], "requirements": {"degrees": ["degree or above"], "majors": [], "languages": ["cantonese", "english", "chinese", "mandarin"], "language_level": ["proficient"], "hard_skills": ["cpa", "plus", "ms word"], "soft_skills": ["communication skills", "confidence"], "languages_combined": [{"language": "cantonese", "language_level": ["proficient"]}, {"language": "english", "language_level": ["proficient"]}, {"language": "chinese", "language_level": ["proficient"]}, {"language": "mandarin", "language_level": ["proficient"]}]}, "experience_required": {"duration": ["5+ years"], "field": ["management", "general compliance", "banking"]}}, {"job_id": "100003009025746", "location_code": "hk", "company": "DBS Bank Ltd", "job_title": "Analyst/Senior Officer, Specialist, Collections", "description": "Business Function\u00a0\n\nRisk Management Group (RMG) is responsible for the development and maintenance of risk management and internal control frameworks. We provide independent review and challenge to business to ensure that appropriate balance is considered in risk/return decisions. In addition, RMG is responsible for the monitoring and reporting on key risk issues of the Bank. To manage risk effectively and deliver strong financial performance, we invest significantly in our people and infrastructure.\n\nResponsibilities\n\n\u2022\u00a0\u00a0\u00a0\u00a0\u00a0\u00a0\u00a0\u00a0\u00a0\u00a0\u00a0\u00a0 To perform phone dunning to delinquent customers\n\n\u2022\u00a0\u00a0\u00a0\u00a0\u00a0\u00a0\u00a0\u00a0\u00a0\u00a0\u00a0\u00a0 To understand customers\u2019 financial difficulties and negotiate with customers on repayment arrangement\n\n\u2022\u00a0\u00a0\u00a0\u00a0\u00a0\u00a0\u00a0\u00a0\u00a0\u00a0\u00a0\u00a0 To handle customer\u2019s enquiries and complaints\n\n\u2022\u00a0\u00a0\u00a0\u00a0\u00a0\u00a0\u00a0\u00a0\u00a0\u00a0\u00a0\u00a0 To comply with the Bank\u2019s and regulatory requirements on risk and control\n\nRequirement\n\n\u2022\u00a0\u00a0\u00a0\u00a0\u00a0\u00a0\u00a0\u00a0\u00a0\u00a0\u00a0\u00a0 University graduate or equivalent OR\u00a0\n\n\u2022\u00a0\u00a0\u00a0\u00a0\u00a0\u00a0\u00a0\u00a0\u00a0\u00a0\u00a0\u00a0 Secondary education plus 2 years or above experience on consumer banking\n\n\u2022\u00a0\u00a0\u00a0\u00a0\u00a0\u00a0\u00a0\u00a0\u00a0\u00a0\u00a0\u00a0 Minimum 2 year\u2019s collection experience in Consumer Credit Collection/ Customer Service\n\n\u2022\u00a0\u00a0\u00a0\u00a0\u00a0\u00a0\u00a0\u00a0\u00a0\u00a0\u00a0\u00a0 Basic knowledge in collection activities on consumer products\n\n\u2022\u00a0\u00a0\u00a0\u00a0\u00a0\u00a0\u00a0\u00a0\u00a0\u00a0\u00a0\u00a0 Good communication and negotiation skills\n\n\u2022\u00a0\u00a0\u00a0\u00a0\u00a0\u00a0\u00a0\u00a0\u00a0\u00a0\u00a0\u00a0 Able to handle and solve complaints\n\n\u2022\u00a0\u00a0\u00a0\u00a0\u00a0\u00a0\u00a0\u00a0\u00a0\u00a0\u00a0\u00a0 Good PC Knowledge: Excel, Word\n\n\u2022\u00a0\u00a0\u00a0\u00a0\u00a0\u00a0\u00a0\u00a0\u00a0\u00a0\u00a0\u00a0 Experience in Customer expectation management and conflict resolution\n\nFor less experience candidates, officer will be considered\n\nApply Now\n\nWe offer a competitive salary and benefits package and the professional advantages of a dynamic environment that supports your development and recognises your achievements.\n\nWe regret only shortlisted candidates will be notified.", "employment_types": ["Full Time"], "selling_points": ["Pension Fund Scheme", "Medical Coverage for Family", "Career Development"], "locations": ["Quarry Bay"], "categories": ["Banking / Finance", "Corporate Banking", "Private Banking", "Retail Banking"], "post_time": "2022-01-06T06:25:46Z", "salary": {"currency": null, "max": null, "min": null, "period": "monthly", "term": null}, "salary_visible": false, "title_keywords": ["specialist", "analyst", "senior officer"], "responsibilities": [], "requirements": {"degrees": [], "majors": [], "languages": [], "language_level": [], "hard_skills": [], "soft_skills": [], "languages_combined": []}, "experience_required": {"duration": [], "field": []}}, {"job_id": "100003009017385", "location_code": "hk", "company": "Links International", "job_title": "Senior Manager, Compliance - Asia Trust/ Private Wealth", "description": "About the Company:\nOur client is top-tier global corporate service firm with more than 85 offices worldwide. They are actively expanding Hong Kong office as their APAC headquarter in order to support the rapid growth of business.\n\nJob Description:\n\nAssist in carrying out the Compliance function of the Asia Trust business (regulated by the Monetary Authority of Singapore and the Company Registry in Hong Kong)\nKeep senior management of Asia Trust abreast of new regulatory developments in their business footprint\nMaintain constructive and effective relationships with and support key Asia Trust stakeholders\nSupport Asia Trust senior management on regulatory relationships with the applicable regulators\nPromote the culture and practice of adherence to compliance standards (including conducting business within regulatory and Group requirements)\nDevelop, implement and maintain Compliance policies and procedures, guidance documents and SOP\nImplement Group Compliance and other relevant Group functional policies across the Asia Trust business (as applicable)\nReview existing and develop new internal forms and Compliance processes\nConduct Client Due Diligence on new and existing trust structures, including providing advice and as point of escalation\nPerform client risk profiling to ensure up-to-date records of clients' risk ratings\nPromote and advise on periodic reviews of structures based on clients' risk profiles\nManage and address compliance escalations from Asia Trust stakeholders\nProvide Compliance support and guidance to the Business, including data protection, outsourcing arrangements, Business Continuity Management, technology risk management, etc.\nParticipate in Asia Trust related Board meetings and business/risk committee meetings (as required)\nGuide Asia Trust stakeholders on regulatory inspections, internal and external audits, in particular to address any audit points\nAssist with compilation of data and preparation of reports for submission to Group Compliance\nAssist with regulators' queries and requests for information\nDeliver compliance monitoring under a defined program to ensure that Asia Trust business is conducted in accordance with Group and local policies and procedures\nMaintain risk registers (e.g. PEP, Other High Risk Clients, etc.), and review transactions of clients of various risk ratings\nPrepare, file and monitor Suspicious Transaction Reports\nDeliver periodic Compliance training\nManage issues independently from end-to-end, updating Regional Compliance Director, SEA or delegate periodically\n\nRequirement:\n\nDegree holder related discipline\nMinimum 8 years working experience (preferably in private wealth industry for APAC)\nFluent English and Mandarin\nGood team player", "employment_types": ["Full Time", "Permanent"], "selling_points": ["Flexible and international working style", "Internal compliance position", "Career growth in a top-tier global service firm"], "locations": ["Causeway Bay"], "categories": ["Banking / Finance", "Private Banking", "Financial Services", "Wealth Management"], "post_time": "2022-01-03T16:18:03Z", "salary": {"currency": null, "max": null, "min": null, "period": "monthly", "term": null}, "salary_visible": false, "title_keywords": ["senior manager"], "responsibilities": ["business continuity", "data", "audit", "transactions", "maintain", "senior management", "due diligence", "compliance", "monitor", "develop", "reports", "guidance", "management", "review", "procedures", "internal and external audits", "monitoring", "regulatory inspections", "policies"], "requirements": {"degrees": ["degree holder"], "majors": [], "languages": ["english", "mandarin"], "language_level": ["fluent"], "hard_skills": [], "soft_skills": ["good team player"], "languages_combined": [{"language": "english", "language_level": ["fluent"]}, {"language": "mandarin", "language_level": ["fluent"]}]}, "experience_required": {"duration": ["minimum 8 years"], "field": []}}, {"job_id": "100003009016165", "location_code": "hk", "company": "Bank of China (Hong Kong) Limited", "job_title": "Credit Manager, Credit Management, Private Banking", "description": "Responsibilities:\nManage to assess and approve credit application from PB Relationship Manager team, from solution provider viewpoint\nProactive to advise continuous improvement in credit application and credit static data maintenance process, to automate the end-to-end process\nEngage in stress test and other ad hoc risk analysis against PB loan portfolio, and periodic risk reporting and portfolio management tasks\nSupport the team in driving credit related initiatives, via collaborate with other stakeholders like Product team, Legal & Compliance and Risk Division\nRequirement:\nDegree holder or above in Finance, Accounting, Business, Information Technology or related discipline\nMinimum 3 years of experiences in Banking, with at least 2 years in credit underwriting is preferable\nGood analytical and credit assessment skills, with sound knowledge in PB AML requirements and relevant rules\nGood communication and interpersonal skills\nGood command of written and spoken English and Chinese (including Putonghua)", "employment_types": ["Full Time"], "selling_points": ["Manage to assess and approve credit application", "Degree holder or above in Finance", "Minimum 3 years of experiences in Banking"], "locations": ["Central"], "categories": ["Banking / Finance", "Credit Analysis / Approval", "Private Banking", "Others"], "post_time": "2022-01-03T08:28:28Z", "salary": {"currency": null, "max": null, "min": null, "period": "monthly", "term": null}, "salary_visible": false, "title_keywords": ["manager", "private banking"], "responsibilities": ["collaborate with", "reporting", "management", "ad hoc", "maintenance", "data", "compliance", "risk analysis", "support the team"], "requirements": {"degrees": ["degree holder"], "majors": ["business", "finance", "accounting", "information technology"], "languages": ["putonghua", "english", "chinese"], "language_level": ["good command"], "hard_skills": ["aml"], "soft_skills": ["communication and interpersonal skills"], "languages_combined": [{"language": "putonghua", "language_level": ["good command"]}, {"language": "english", "language_level": ["good command"]}, {"language": "chinese", "language_level": ["good command"]}]}, "experience_required": {"duration": ["at least 2 years", "minimum 3 years"], "field": ["underwriting", "banking"]}}, {"job_id": "100003009015892", "location_code": "hk", "company": "BRS Limited", "job_title": "Manager, KYC - Private Banking", "description": "Our client, a Chinese bank in Hong Kong, is seeking high calibres to fill the above position.\n\nResponsibilities :\n\n\nConduct CDD/KYC due diligence review on existing client, new account opening and periodic review\nProvide assistance and guidance to relationship managers on KYC matters\nReview name screening result and follow up, if necessary\nEnsure existing policies and procedures are in compliance with regulatory bodies\nPerform ad-hoc tasks as assigned\n\nRequirements:\n\n\nDegree holder or above in accounting, legal, business or related discipline\nA minimum of 5 years\u2019 relevant experience in private banking\nFamiliar with HKMA and SFC's regulatory requirement & risk assessments\nExcellent communication and interpersonal skills\nGood command of written English and Chinese\n\nInterested parties please forward your CV in Word Format\u00a0with current and expected salary to Vicki Ho of BRS Limited\u00a0\n\n[All applications will be treated strictly confidential and will be used for recruitment purpose only]", "employment_types": ["Full Time", "Permanent"], "selling_points": ["5 years\u2019 relevant experience in Private Banking", "Conduct KYC/CDD review on existing and new clients", "Chinese Bank with strong presence in PRC"], "locations": ["Central"], "categories": ["Banking / Finance", "Private Banking", "Others", "Professional Services", "Legal & Compliance"], "post_time": "2022-01-03T07:51:37Z", "salary": {"currency": null, "max": null, "min": null, "period": "monthly", "term": null}, "salary_visible": false, "title_keywords": ["manager", "private banking"], "responsibilities": ["due diligence", "guidance", "cdd", "account opening", "review", "policies", "procedures", "compliance", "ad-hoc tasks", "kyc", "provide assistance"], "requirements": {"degrees": ["degree holder"], "majors": ["business", "accounting"], "languages": ["english", "chinese"], "language_level": ["good command"], "hard_skills": ["hkma"], "soft_skills": ["communication and interpersonal skills"], "languages_combined": [{"language": "english", "language_level": ["good command"]}, {"language": "chinese", "language_level": ["good command"]}]}, "experience_required": {"duration": ["minimum of 5 years"], "field": ["relevant experience", "banking"]}}, {"job_id": "100003009015610", "location_code": "hk", "company": "AGS Group Limited", "job_title": "Assistant Manager-Middle Office  ( PE, Private Banking, FI)", "description": "Our Client is a Private investment Firm for prestige Family. They are looking for a high caliber to join the teams.\n\nJob Responsibility\n\nAssistance for daily operations including all settlement-related processes for Equity, Fixed Income, FX, Funds & Direct Investments.\nHe/ She will involve in bank account opening and structure set up for different trades\nPreparation of different monitoring reports including cash projections for investments\nAssist in regulatory and reporting requirements\nRequirements:\n\nDegree in Accounting, Finance, or related disciplines\n3-5 years of solid experience in Middle Office or Back Office of leading Financial Institutions is a must\nLogical and highly resourceful with strong strategic thinking, organizing, analytical, and reporting skills\n\u00a0\u00a0A good team player with strong product knowledge would be an advantage\nExcellent spoken and written communication in English, Cantonese, and Mandarin\nMore experience candidate will consider as Assistant Manager\nInterested parties, pls kindly email to ann.chan @agsgroup.com.hk", "employment_types": ["Full Time"], "selling_points": ["Middle Office", "Investment or Private Banking", "Settlement"], "locations": ["Tsim Sha Tsui"], "categories": ["Banking / Finance", "Private Banking", "Order Processing & Operation / Settlement"], "post_time": "2022-01-03T07:10:03Z", "salary": {"currency": null, "max": null, "min": null, "period": "monthly", "term": null}, "salary_visible": false, "title_keywords": ["assistant manager", "private banking"], "responsibilities": ["account opening", "daily operations", "monitoring", "reports"], "requirements": {"degrees": ["degree"], "majors": ["related disciplines", "finance", "accounting"], "languages": ["cantonese", "english", "mandarin"], "language_level": ["excellent"], "hard_skills": [], "soft_skills": ["communication", "good team player", "strategic thinking", "resourceful"], "languages_combined": [{"language": "cantonese", "language_level": ["excellent"]}, {"language": "english", "language_level": ["excellent"]}, {"language": "mandarin", "language_level": ["excellent"]}]}, "experience_required": {"duration": ["3-5 years"], "field": ["financial institutions"]}}, {"job_id": "100003009016133", "location_code": "hk", "company": "Bank of China (Hong Kong) Limited", "job_title": "(Senior) Business Strategy Manager, Private Banking", "description": "Responsibilities\nMonitor project progress and provide timely progress and status reports to management\nAssist in setting up a new business platform \u00a0\nPrepare business review management reports for management\nAssist in developing and executing the strategies and plans\nCarry out ad hoc or other projects assigned by management as may be required\nRequirements\nDegree or above with at least 3 year relevant experience in banking industry\nStrong financial and business analytical skills\nExcellent communications and presentation skills with good command of English and Chinese in both spoken and written. Fluent in Putonghua.\nBe self-motivated, energetic, creative and enthusiastic for new challenges.\nProficient in MS Office application and Chinese input method", "employment_types": ["Full Time"], "selling_points": ["Monitor project progress & provide timely progress", "Degree or above with at least 3 year relevant exp.", "Medical and life insurance"], "locations": ["Central"], "categories": ["Banking / Finance", "Analyst", "Private Banking", "Professional Services", "Business Analysis / Data Analysis"], "post_time": "2022-01-03T08:22:29Z", "salary": {"currency": null, "max": null, "min": null, "period": null, "term": null}, "salary_visible": false, "title_keywords": ["manager", "private banking"], "responsibilities": ["management", "monitor project progress", "ad hoc", "review", "developing", "management reports", "reports", "executing", "plans"], "requirements": {"degrees": ["degree or above"], "majors": [], "languages": ["putonghua", "english", "chinese"], "language_level": ["proficient", "excellent", "good command", "fluent"], "hard_skills": ["chinese input", "ms office", "analytical skills"], "soft_skills": ["self-motivated", "creative", "analytical skills", "presentation skills", "enthusiastic", "energetic"], "languages_combined": [{"language": "putonghua", "language_level": ["fluent"]}, {"language": "english", "language_level": ["excellent", "good command"]}, {"language": "chinese", "language_level": ["proficient", "excellent", "good command"]}]}, "experience_required": {"duration": ["at least 3 year"], "field": ["banking industry", "relevant experience"]}}, {"job_id": "100003009028686", "location_code": "hk", "company": "Robert Half", "job_title": "AVP/VP - Regulatory Reporting, Leading Bank", "description": "Our client is a leading International bank with operations in both banking and treasury services. To cope with their business expansion, they are looking for a caliber to join their team.\n\n\n\nResponsible for the HKMA regulatory reporting process, and to ensure the compilation of banking returns and surveys are in compliance with the completion instructions and relevant guidelines as set out by the HKMA\nEnsure proper control checking and review procedures are in place so as to minimize errors in reporting\nAssist in the implementation of system enhancement projects relating to banking return reporting and other ad hoc tasks as required by the management from time to time\n\nRequirements:\n\nBachelor's Degree in Accounting, Finance or relevant discipline\nMinimum 3 years' experience in banking and financial accounting / regulatory reporting functions\nMember of CPA is an added advantage\nHigh level of multi-tasking and time management skill are required\nA team-player with excellent working attitude; willing to take on multiple functions\nExcellent verbal and written communication skills\n\n\n\nApply Today\n\nTo apply online (Word attachment only), please click the 'Apply' button. Please note that only short-listed candidates will be contacted.", "employment_types": ["Full Time", "Permanent"], "selling_points": ["A leading retail banking and corporate banking", "Fringe benefit with decent bonus", "Good exposure with career progression"], "locations": ["Central & Western Area"], "categories": ["Banking / Finance", "Corporate Banking", "Private Banking", "Retail Banking"], "post_time": "2022-01-07T02:52:42Z", "salary": {"currency": null, "max": null, "min": null, "period": "monthly", "term": null}, "salary_visible": false, "title_keywords": [], "responsibilities": ["reporting", "control", "management", "guidelines", "operations", "compliance", "review", "checking", "procedures", "implementation", "ad hoc tasks", "communication", "banking", "enhancement projects"], "requirements": {"degrees": ["degree", "bachelor"], "majors": ["finance", "accounting"], "languages": [], "language_level": [], "hard_skills": ["hkma", "cpa", "word", "hkma regulatory reporting"], "soft_skills": ["communication skills", "responsible", "team-player", "multi-tasking", "time management skill"], "languages_combined": []}, "experience_required": {"duration": ["minimum 3 years"], "field": ["accounting", "financial", "banking"]}}, {"job_id": "100003009022161", "location_code": "hk", "company": "Spidernet Recruitment Services", "job_title": "Credit Risk Vice President / Manager  (Private Bank)", "description": "Credit Risk Manager / Vice President (Private Bank)\n\nResponsibilities:\n\nReview and approve Lombard lending proposals within delegated authority to ensure that the bank\u2019s credit offering is in compliance with bank\u2019s policies, procedures, risk appetite and local regulatory requirements;\nProvide recommendations and highlight key risk issues to front office and credit approvers;\nReview and approve Credit Exception requests and Loan-to-Value ratio for Lombard Lending requests. Evaluate credit risk based on overall analysis of counterparty, collateral\u2019s risk dynamics, client\u2019s portfolio holdings;\nProvide training and guidance to Relationship Managers / Client Services Officers on credit policies and processes (including preparation of credit proposals);\nAssist the department head in managing the loan portfolio and collateral of designated business unit;\nPrepare periodic credit risk portfolio report and risk management committee meeting minutes;\nParticipate in credit policy / new product programme review and ad-hoc projects;\nCoach junior Credit Officers, Relationship Managers and Client Services Officers on credit assessment competency.\n\nRequirements:\n\nDegree holder in Finance, Business and related disciplines. Holder of The Enhanced Competency Framework on Credit Risk Management (ECF-CRM) is a plus;\nAt least 8-12 years of relevant\u00a0experience in Private Banking;\nGood understanding of business strategy, plans and objectives of financial institutions. Ability to provide appropriate support in development and implementation of such strategies and objectives by identifying and mitigating external threats and risks;\nStrong technical knowledge of credit approval process, systems and controls and credit risk management of financial institutions;\nStrong financial and credit analysis, collateral management (credit monitoring and control) skills;\nStrong knowledge of wealth management and private banking products (bonds, equities, structured notes, funds, etc.);\nSound working knowledge of Hong Kong Company & Banking Law, Credit Policies and Collateral Management policies;\nExcellent ability to communicate with stakeholders of all levels;\nExcellent initiative with ability to work independently;\nProficiency in English, Cantonese and Mandarin.\n\nAttractive remuneration and fringe benefits will be offered to the successful candidate.\n\nInterested candidates should apply with detailed resume, present and expected salaries by clicking the Apply Now button.\n\nAll information received will be treated in strict confidence and used for recruitment purpose only.\n\nOnly shortlisted candidates will be notified.\n\n\n", "employment_types": ["Full Time", "Permanent"], "selling_points": ["Degree, Fluent English and Mandarin", "8-12 yrs credit risk exp. in Private Bank", "exp in review & approve Lombard lending proposals"], "locations": ["Central"], "categories": ["Banking / Finance", "Credit Analysis / Approval", "Private Banking", "Risk Management"], "post_time": "2022-01-05T05:07:13Z", "salary": {"currency": null, "max": null, "min": null, "period": "monthly", "term": null}, "salary_visible": false, "title_keywords": ["vice president", "manager"], "responsibilities": ["provide training", "guidance", "management", "bank\u2019s policies", "regulatory requirements", "analysis", "compliance", "review", "procedures", "policies", "evaluate", "provide recommendations", "ad-hoc projects", "report"], "requirements": {"degrees": ["degree holder"], "majors": ["related disciplines", "finance", "business"], "languages": ["cantonese", "english", "mandarin"], "language_level": ["proficiency"], "hard_skills": ["credit analysis", "plus"], "soft_skills": ["work independently", "structured", "initiative"], "languages_combined": [{"language": "cantonese", "language_level": ["proficiency"]}, {"language": "english", "language_level": ["proficiency"]}, {"language": "mandarin", "language_level": ["proficiency"]}]}, "experience_required": {"duration": ["at least 8-12 years"], "field": ["relevant experience", "banking"]}}, {"job_id": "100003009027476", "location_code": "hk", "company": "IT Solutions Ltd.", "job_title": "Private Banking: IT Business Analyst - Major Bank", "description": "We are searching on behalf of a major bank for a number of high-calibre\u00a0IT\u00a0Business Analyst\u00a0to work with their Senior Project Manager to manage a large-scale Private Banking System Enhancement Project.\n\nResponsibilities:\n\nPerform vendor management and project management\nManage IT project implementation and testing\u00a0\nAct as the key interface between business users and technical developers\nStudy system documentation such as requirements specifications\nWrite Test Plans and Test Cases\nCoordinate users to conduct User Acceptance Test\n\nRequirements:\n\nDegree in IT or related discipline\n2+ Year working experience, preferably in Banking backgrounds\nExperience in coordinating users and user requirement analysis and User Acceptance Testing\nVendor management experience is definitely an advantage\u00a0\nGood communication and interpersonal skills\n\n**Candidates with more experience will be considered as Senior Business Analyst\n\nBenefits:\n\nAttractive remunerations will be offered to the successful candidate.\nExcellent opportunity to further develop your professional skills in a major banking environment.\n\nIf you are interested, please send your resume in MS Word format, specifying your availability, current and expected salaries to:\n\njobs @itsolutions.com.hk\n\nor\n\nPlease click the Apply Now button and attach your cv in MS Word Format, specifying your availability, current and expected salaries.\n\nPersonal data collected will be used for recruitment purposes only.\n\nIT Solutions Ltd.\nSuite 2102\n21/F Lucky Building\n39 Wellington Street\nCentral, Hong Kong\n\n(P.S. We do not process applications from overseas for this position)", "employment_types": ["Full Time"], "selling_points": ["Private Banking Sys Enhancement", "from end-to-end Project Cycle", "Develop Career in a Major Bank"], "locations": ["Central"], "categories": ["Banking / Finance", "Private Banking", "Information Technology (IT)", "IT Project Management / Team Lead", "Product Management / Business Analyst"], "post_time": "2022-01-06T10:05:29Z", "salary": {"currency": null, "max": null, "min": null, "period": "monthly", "term": null}, "salary_visible": false, "title_keywords": ["business analyst", "private banking"], "responsibilities": ["management", "system documentation", "testing", "coordinate", "project management", "specifications", "plans", "it project implementation"], "requirements": {"degrees": ["degree"], "majors": ["it"], "languages": [], "language_level": [], "hard_skills": ["analysis", "vendor"], "soft_skills": ["communication and interpersonal skills"], "languages_combined": []}, "experience_required": {"duration": ["2+ year"], "field": ["testing", "management", "business", "banking"]}}, {"job_id": "100003009014947", "location_code": "hk", "company": "Manpower Services (Hong Kong) Limited", "job_title": "On-Site with Hang Seng Bank - Client Relationship Support (6 Month Contract, Up to 35K)", "description": "Title Client Relationship Support, Trust Services, Private Banking\nContract Duration 6 months (to start on 1st Feb 2022)\nSalary Range HKD25,000 \u2013 35,000 / month\n\nResponsibilities:\n\u2022 Support the promotion of private trust products to potential clients through different channels including intermediaries and referrals\n\u2022 Manage client relationship and answer enquiries\n\u2022 Prepare presentation, marketing and promotional materials\n\u2022 Monitor KYC process and ensure risk management policies are followed\n\u2022 Collaborate with trust administration team on new client\u2019s onboarding process\n\u2022 Participate in ad hoc projects pertaining to marketing\n\u2022 Perform ad-hoc assignments as required\nJob requirements:\n\u2022 Degree in Law, Accounting or business related disciplines, preferably with professional qualification such as HKCIS, CPA and STEP.\n\u2022 Relevant experience in private trust / banking or financial services sector\n\u2022 Good communication, interpersonal and organizational skills\n\u2022 Proficient in both spoken and written English and Chinese Languages\n\nIf you are interested in this role, click \u201cApply Now\u201d, else, you may also directly send your updated resume and expected salary to Anson Li at anson.li@manpowergrc.hk.", "employment_types": ["Contract"], "selling_points": ["Preferably with HKCIS, CPA and STEP", "Relevant experience in private trust", "Working Location: Central"], "locations": ["Central"], "categories": ["Admin & HR", "Administration / Operation Manager", "Banking / Finance", "Corporate Banking", "Private Banking"], "post_time": "2022-01-03T04:36:21Z", "salary": {"currency": null, "max": null, "min": null, "period": "monthly", "term": null}, "salary_visible": false, "title_keywords": [], "responsibilities": ["collaborate with", "management", "policies", "ad-hoc assignments", "monitor", "promotional materials", "ad hoc projects", "kyc", "administration"], "requirements": {"degrees": ["degree"], "majors": ["business", "related disciplines", "accounting", "law"], "languages": ["english", "chinese"], "language_level": ["proficient"], "hard_skills": ["cpa"], "soft_skills": ["communication", "organizational skills", "interested in", "interpersonal"], "languages_combined": [{"language": "english", "language_level": ["proficient"]}, {"language": "chinese", "language_level": ["proficient"]}]}, "experience_required": {"duration": [], "field": ["financial services", "relevant experience", "banking"]}}, {"job_id": "100003009011523", "location_code": "hk", "company": "Asia Progress Executive Limited", "job_title": "Client Services Manager  - Local Business Support ( Private Banking/Wealth Management )", "description": "Our client is a reputable international Private Banking /Wealth Management To cope with the rapid business expansion, they are now inviting high caliber candidates to join the team.\n\n\nClient Services Manager\u00a0 - Local Business Support ( Private Banking/Wealth Management )\u00a0\n\nPosition Purpose\nThis position offer the opportunity to join our client service section in our operations platform to provide business support to the front office staff, ensure the completeness of the daily pre-operational control and contribute to operational permanent control framework. As this is a transversal role, the candidate is expected to cover BAU activities.\n\nResponsibilities\u00a0\n\n\n\nDirect Responsibilities\n\nTo be customer-focused and maintain a high quality service standard in liaison with RM/ MA / RPC (Regional Processing Centre) / ISPL\u00a0 and other stakeholders.\nHandle general inquiries from RM/MA, RPC & ISPL related to BAU issue.\nTo prepare and review daily reporting.\nTo handle daily operations in fund and securities transfer.\nTo monitor trade and prepare reporting for CIES account\nTo handle daily operations in corporate actions, IPO, placement & disclosure.\nTo provide support to the BAU team as assigned by section head/ department head.\n\n\nContributing Responsibilities\n\nTo assist section head to perform daily pre-operational control of RM/MA\u2019s & client\u2019s instructions and ensure the transactions are handled properly in accordance with the bank procedures/guidelines.\nTo coordinate with RPC/ISPL for timely execution of client\u2019s instructions.\nTo handle cash deposit/withdrawal, local and foreign cheque clearing, FPS & Autopay clearing and Loan & Deposit processing\nTo perform account administrative tasks.\nTo handle daily operations in securities transfer and physical scrip depository/withdrawal.\nTo perform pre-operational checking for all securities transaction instruction and follow up queries with RPC, ISPL, custodian, front office or counterparties if necessary.\nTo closely coordinate with RPC for Corporate Action news and ensure timely execution of front office instructions. Monitor and review RMs/Clients\u2019 election on Corporate actions and Event Summary to RPC for further processing.\nPerform pre-operation check on payment instructions received from FO.\nDeceased account handling.\nReport distribution to RM/MA\nPerform cheque book order\nPerform IVS inward cheque clearing\nPerform MRCS autopay clearing\nPerform FPS clearing\nLoan & Deposit Processing\nMaintain warehouse record and arrange shipment of daily transaction files to warehouse regularly\nTo prepare management reporting.\nTo participate in project and ad hoc assignments e.g. new system implementation, UAT, BCP and DR.\nDirect contribution to operational permanent control framework.\nContribute to the implementation of operational permanent control policies and procedures in day-to-day business activities, such as Control Plan.\nComply with regulatory requirements and internal guidelines.\nContribute to the reporting of all incidents according to the Incident Management.\n\nTechnical & Behavioral Competencies\n\nRelevant working experience in payment and securities operations, ideally have checker experience.\nGood knowledge in account operations and general banking operations\nEffective communications skills.\nGood written and spoken English.\nGood in MS Office applications (Excel, Word, PowerPoint\u2026etc).\nTake initiatives, responsible and motivated. Willing to work overtime if required.\nGood interpersonal skill, attentive to details and accuracy.\nCommitted to customers, diligent, adaptability to changing environment\n\nSpecific Qualifications (if required)\n\nDegree holder in Business Studies (e.g. Accountancy & Finance)\nwith at least 5 years relevant Private banking experience.\nExperience in middle & back office operations in a sizable financial institution is\u00a0preferred.\u00a0\n\nPlease send full resume with\u00a0present & expected\u00a0salary to expedite sourcing\u00a0in\u00a0MS-WORD\u00a0format by clicking \u201cAPPLY NOW\u201d\nPlease quote our reference in your application\nPersonal data provided by job applicants will be used strictly in accordance with the employer\u2019s personal data policies, a copy of which will be provided upon request\nAll information provided will be used for recruitment purpose only", "employment_types": ["Full Time"], "selling_points": ["Degree 5yrs Private Banking Operation, US mkts", "daily operations in fund and securities transfer.", "exp in US stock /US Markets,transfer payments"], "locations": ["Central & Western Area"], "categories": ["Banking / Finance", "Private Banking", "Equities / Capital Markets", "Order Processing & Operation / Settlement"], "post_time": "2022-01-03T06:35:49Z", "salary": {"currency": null, "max": null, "min": null, "period": "monthly", "term": null}, "salary_visible": false, "title_keywords": ["wealth management", "client services manager", "private banking"], "responsibilities": ["service standard", "operations", "regulatory requirements", "quality", "transactions", "payment", "maintain", "plan", "personal data", "control", "uat", "new system implementation", "monitor", "implementation", "banking", "autopay", "business activities", "report", "reporting", "management", "provide support", "review", "procedures", "coordinate with", "checking", "daily operations", "management reporting", "administrative tasks", "guidelines", "policies", "back office", "recruitment", "ad hoc assignments"], "requirements": {"degrees": ["degree holder"], "majors": ["business"], "languages": ["english"], "language_level": ["good"], "hard_skills": ["excel", "ms-word", "word", "powerpoint", "rapid", "system implementation", "processing", "ms office"], "soft_skills": ["work overtime", "customer-focused", "responsible", "attentive to details", "timely", "diligent", "interpersonal skill", "committed", "motivated", "adaptability"], "languages_combined": [{"language": "english", "language_level": ["good"]}]}, "experience_required": {"duration": ["at least 5 years"], "field": ["securities", "relevant working experience", "banking experience", "financial"]}}, {"job_id": "100003009015287", "location_code": "hk", "company": "DBS Bank Ltd", "job_title": "SVP, Private Partner Services, Private Banking", "description": "Business Function\n\nDBS\u2019 Private Banking offers a one-stop, full-service touch-point for total banking requirements and provides the highest level of personalised banking. We have a team of dedicated, experienced investment advisors who identify opportunities in the various asset classes and employ the best strategies and product vehicles to cater to each client\u2019s needs. Coupled with partnerships within the DBS network and with global institutions, we strive to build long-term relationships with our Private Banking clients in Asia by providing them with high quality, timely and extensive wealth management, investment and financial solutions.\n\nThe candidate\u00a0is expected to lead the Private Partner Services (PPS) and Admin and Infrastructure (A&I) teams to provide outstanding support to PB front office and the overall Greater China PB team respectively.\n\nResponsibilities\n\nEnsure smooth and effective daily operation of the functions reporting into the role:\nPPS - meet all SLAs with good quality via data driven resource planning, workflow management and staff coaching / productivity uplif\nA&I \u2013 maintain high standard in admin support, office premise maintenance & provision of work tools/systems for the overall PB team\nVickers Retail - execute all items set for tail management in adherence to the framework in place, including but not limited to GLAO, periodic client communication execution of client service request, and complaint handling. Attend regular Vickers Retail management update meetings.\nKeep abreast of the evolving business needs and update relevant processes, resources planning and staff skillset to ensure consistent delivery outstanding support under a changing environment\nOn-going review and identification areas for development in processes, staff development and collaboration with work counterparts to uplift contribution of the functions to the business\nCoach and develop a team of professional with a data-driven decision making mindset & ability, and groom transformational leadership\nContribute to the overall transformation of the WM COO office by developing and implementing transformation initiatives and culture\nEnsure close adherence to all compliance requirement in all areas that the team look after and enforce it with relevant work counterpart\n\nRequirements\n\nDegree holder preferably in Business, Finance, Accounting, Economics or related disciplines\nDegree holder with at least 12 years of work experience in the financial industry, with at least 6 years in management role.\nExperience in leading operation functions with proven track record in delivering measurable improvements\nExperience in conducting data analysis for planning and business decision making\nProven track record in driving culture change and delivering measurable improvements\nKnowledge in equity brokerage including Operations, Research, and frontline Equity and Futures Sales and licensed under SFC for Type 1 and Type 2 Regulated Activities an advantage\nGood interpersonal and communication skills\nSelf-motivated, enthusiastic, organized and ability to multi-task\nMeticulous with good analytical skills\nKnowledge of private banking products\nProficiency in MS Office Word, Excel and PowerPoint.\n\n\nApply Now\n\nWe offer a competitive salary and benefits package and the professional advantages of a dynamic environment that supports your development and recognises your achievements.\n\nWe regret only shortlisted candidates will be notified.", "employment_types": ["Full Time"], "selling_points": ["Strong in Project Management", "Preferably have Private Banking experience", "Work under PB COO team"], "locations": ["Central"], "categories": ["Banking / Finance", "Private Banking", "Wealth Management"], "post_time": "2022-01-03T06:25:56Z", "salary": {"currency": null, "max": null, "min": null, "period": "monthly", "term": null}, "salary_visible": false, "title_keywords": ["private banking"], "responsibilities": ["reporting", "management", "maintenance", "data", "systems", "daily operation", "quality", "review", "develop", "communication", "developing", "compliance", "maintain", "admin support", "planning"], "requirements": {"degrees": ["degree holder"], "majors": ["finance", "economics", "related disciplines", "business", "accounting"], "languages": [], "language_level": [], "hard_skills": ["excel", "analysis", "word", "powerpoint", "analytical skills", "dynamic", "ms office"], "soft_skills": ["communication skills", "self-motivated", "organized", "multi-task", "meticulous", "dynamic environment", "analytical skills", "enthusiastic", "interpersonal", "decision making"], "languages_combined": []}, "experience_required": {"duration": ["at least 6 years", "at least 12 years"], "field": ["management", "financial industry", "data analysis", "operation", "business", "planning"]}}, {"job_id": "100003009005594", "location_code": "hk", "company": "SALT Consulting International Company Limited", "job_title": "Relationship Manager Assistant (Personal Bank / Corporate Bank / Private Bank)", "description": "We are assisting our banking clients in recruiting Assistant Relationship Manager (ARM) in Personal Banking, Private Banking and Corporate Banking. The ARM will assist Relationship Managers in servicing their clients in terms of account opening, trade booking, loan application and processing, account maintenance and general inquiries.\n\nInterested candidates pls send your CV in MS Word format.", "employment_types": ["Full Time"], "selling_points": ["Account Opening", "Loan application and processing", "Account Maintenance"], "locations": ["Central & Western Area"], "categories": ["Banking / Finance", "Corporate Banking", "Private Banking", "Retail Banking"], "post_time": "2021-12-29T04:06:08Z", "salary": {"currency": null, "max": null, "min": null, "period": "monthly", "term": null}, "salary_visible": false, "title_keywords": ["personal", "relationship manager", "assistant"], "responsibilities": ["account opening", "account maintenance", "trade booking", "banking"], "requirements": {"degrees": [], "majors": [], "languages": [], "language_level": [], "hard_skills": ["account opening", "processing", "maintenance"], "soft_skills": [], "languages_combined": []}, "experience_required": {"duration": [], "field": []}}, {"job_id": "100003009019746", "location_code": "hk", "company": "Harbridge Partners Limited", "job_title": "Contract Officer, Operation Department", "description": "Our Client:\n\nOur client is a well-established fund service provider with PRC bank background. They are looking for a contract officer to join their operations department\n\nResponsibilities:\n\nProcess members\u2019 enrolments and terminations in accordance with all regulatory requirements, company procedures and policies \u00a0\nProvide help in carry out functional testing for system enhancement process\nHandling outstanding issues customer\u2019s enquiries on a timely and professional manner\nAssist in other ad hoc assignments as required\n\nRequirements:\u00a0\n\nDegree holder with at least 4 years of pension fund administration experience\nKnowledgeable in both MPF and ORSO regulation\nTeam player with good interpersonal skill\nHard working and pay attention to details\nExcellent command of written and spoken English and Chinese.\nProficient in Microsoft Office Application (Word, Excel, Powerpoint) and Chinese word processing\nPrefer to be immediately available\n\nInterested candidate can send their cv to:\n\ncv AT harbridgepartners DOT com\u00a0 \u00a0 \u00a0 \u00a0 \u00a0 \u00a0 \u00a0 \u00a0 and\nconsultants AT harbridgepartners DOT com\u00a0", "employment_types": ["Full Time"], "selling_points": ["Operation Department, PRC Bank", "fund service provider, MPF, ORSO", "pension fund administration, system enhancement"], "locations": ["Not Specified"], "categories": ["Banking / Finance", "Private Banking", "Others", "Order Processing & Operation / Settlement"], "post_time": "2022-01-04T08:36:01Z", "salary": {"currency": null, "max": null, "min": null, "period": null, "term": null}, "salary_visible": false, "title_keywords": ["contract officer"], "responsibilities": ["regulatory requirements", "policies", "procedures", "professional manner", "testing", "ad hoc assignments"], "requirements": {"degrees": ["degree holder"], "majors": [], "languages": ["english", "chinese"], "language_level": ["excellent", "proficient"], "hard_skills": ["excel", "chinese word processing", "microsoft office", "word", "powerpoint"], "soft_skills": ["hard working", "team player", "attention to details", "interpersonal skill"], "languages_combined": [{"language": "english", "language_level": ["excellent"]}, {"language": "chinese", "language_level": ["excellent", "proficient"]}]}, "experience_required": {"duration": ["at least 4 years"], "field": ["administration"]}}, {"job_id": "100003009012861", "location_code": "hk", "company": "China Everbright Bank Company Limited", "job_title": "Senior Manager, Investment Product Development", "description": "Job Responsibilities:\n\nDevelop business plans to drive investment products and services, including investment funds, bonds and structured products, to meet business targets.\nManage and work closely with internal and external business partners / product providers to provide quality products and services to the bank\u2019s customers.\nImplement and manage effective product management and launch from product due diligence, product provider selection to ongoing review.\nManage the product development life cycle to ensure the successful launch of the products, e.g. co-ordination, set-up of workflow and documentation, system requirement analysis, UAT, etc.\nActively monitor and manage investment products and keep track of market intelligence.\nTrack, report and review product performance and give recommendations for improvement.\nSupport front office on providing product training, client visits and product implementation/customization.\nAssist to develop the marketing collaterals and enhance the Branch's product branding.\nComplete ad hoc tasks or projects as assigned by Department Head.\n\nJob Requirements:\n\nDegree holder in Business, Management, Finance or Marketing related disciplines.\nMinimum 6 years of solid experience in investment product development and management preferably in retail and/or private banking fields.\nExperience in managing investment products and distributing through multi-channels.\nKnowledge in funds, bonds and structure products are essential.\nPossess qualifications under SFC for marketing investment products and pass in relevant papers of Insurance Intermediaries Qualifying Examination (IIQE) is a plus.\nFamiliar with regulatory requirements, system functions and operational process flows in launching of new products.\nStrong and proven marketing and communication skills.\nGood command of written and spoken English and Chinese (including Putonghua).\n\n\nInterested candidates please apply in full resume with earliest availability, contact number, current & expected salary to HR Department.\nPersonal data provided will be used for recruitment and related purposes, strictly in accordance with our Personal Data Policy for Applicants for Employment, a copy of which is available on request. Applicants who are not contacted within 6 weeks may consider your applications unsuccessful and the personal data collected will be destroyed after six months.", "employment_types": ["Full Time", "Permanent"], "selling_points": ["Formulate of business strategy", "Market intelligence & analysis", "Investment product due diligence"], "locations": ["Wan Chai"], "categories": ["Banking / Finance", "Private Banking", "Wealth Management"], "post_time": "2022-01-02T12:35:42Z", "salary": {"currency": null, "max": null, "min": null, "period": "monthly", "term": null}, "salary_visible": false, "title_keywords": ["senior manager", "product development"], "responsibilities": ["management", "uat", "product due diligence", "analysis", "review", "quality", "monitor", "business plans", "develop", "implementation", "marketing collaterals", "ad hoc tasks", "documentation", "report"], "requirements": {"degrees": ["degree holder"], "majors": ["related disciplines", "finance", "business", "marketing"], "languages": ["putonghua", "english", "chinese"], "language_level": ["good command"], "hard_skills": ["iiqe", "investment products", "plus"], "soft_skills": ["communication skills"], "languages_combined": [{"language": "putonghua", "language_level": ["good command"]}, {"language": "english", "language_level": ["good command"]}, {"language": "chinese", "language_level": ["good command"]}]}, "experience_required": {"duration": ["minimum 6 years"], "field": ["management", "investment", "banking", "product development", "retail"]}}, {"job_id": "100003009012604", "location_code": "hk", "company": "Cheuk Hang Growth", "job_title": "Fund Management Intern / Assistant / Trainee", "description": "Job Description\n\nOur clients are leading financial institutions in Hong Kong. They are currently looking for who interest in Finance to join their investment team as:\n\nResponsibilities:\n\nTo provide tailor-made financial advices to clients\nTo monitor & analyze clients\u2019 investment portfolio\nTo maintain good relationship with clients\n\nRequirements:\n\nUniversity graduate in any discipline\u00a0\nWilling to work with others\nExcellent interpersonal, communications and presentation skills\nAggressive, self-motivated, passionate for better career development\n\n\n\nBenefits:\n\n5 days work\nOn job training\nTraining allowance\nMedical Insurance, competitive salary and attractive bonus\n\nHK residents will only be considered.\nPersonal data will be used for recruitment purpose only.", "employment_types": ["Full Time"], "selling_points": [], "locations": ["Central & Western Area"], "categories": ["Banking / Finance", "Private Banking", "Management", "Management Trainee", "Asset Management"], "post_time": "2022-01-01T06:29:39Z", "salary": {"currency": "HKD", "max": 24999, "min": 20000, "period": "monthly", "term": null}, "salary_visible": true, "title_keywords": ["trainee", "assistant", "intern"], "responsibilities": ["monitor", "maintain good relationship"], "requirements": {"degrees": ["university graduate"], "majors": [], "languages": [], "language_level": [], "hard_skills": [], "soft_skills": ["passionate", "presentation skills", "interpersonal", "self-motivated"], "languages_combined": []}, "experience_required": {"duration": [], "field": []}}, {"job_id": "100003009020032", "location_code": "hk", "company": "Harbridge Partners Limited", "job_title": "Contract assistant Operations Manager/ Operation Manager of MPF", "description": "Our Client:\n\nOur client is a well-established fund service provider with PRC bank background. They are looking for a contract assistant operation manager to join their operations department\n\nResponsibilities:\n\nEnsure the daily operational tasks are delivered in quality and on time, as well as compliance with statutory deadlines where applicable\nProvide job training to staffs about the new operation flow and procedure\nEnsure all mandatory training (e.g. Sanctions and AML) are completed by staffs in accordance with Head Office and regulatory requirements\nConnect colleagues among and across teams\nDevelop operation flow and procedure after the onboard of eMPF\nHandle special projects and other restricted transactions as assigned by supervisors\nPerform ad-hoc assignments as required\n\nRequirements:\u00a0\n\n\u00a0Degree holder with at least 10 years of MPF administration experience\nExperience in Operation and management teams in MPF, Fund and Trust Operations\nTeam player with good interpersonal skill\nAble to multitask and work under pressure\nExcellent command of written and spoken English and Chinese, Putonghua will be a plus\nProficient in Microsoft Office Application (Word, Excel, Powerpoint)\nPrefer to be immediately available\n\nInterested candidate can send their cv to:\n\ncv AT harbridgepartners DOT com\u00a0 \u00a0 \u00a0 \u00a0 \u00a0 \u00a0 \u00a0 \u00a0 and\nconsultants AT harbridgepartners DOT com\u00a0", "employment_types": ["Contract"], "selling_points": ["Assistant Operation Manager, MPF", "MPF administration, Funds, Trust Operations", "Operational Experience, job training ,eMPF"], "locations": ["Not Specified"], "categories": ["Banking / Finance", "Private Banking", "Others", "Order Processing & Operation / Settlement"], "post_time": "2022-01-04T09:46:35Z", "salary": {"currency": null, "max": null, "min": null, "period": null, "term": null}, "salary_visible": false, "title_keywords": ["operation manager", "assistant operations manager"], "responsibilities": ["aml", "regulatory requirements", "operational tasks", "compliance", "quality", "teams", "transactions", "develop", "ad-hoc assignments"], "requirements": {"degrees": ["degree holder"], "majors": [], "languages": ["putonghua", "english", "chinese"], "language_level": ["excellent"], "hard_skills": ["excel", "plus", "microsoft office", "word", "powerpoint"], "soft_skills": ["multitask", "team player", "work under pressure", "interpersonal skill"], "languages_combined": [{"language": "putonghua", "language_level": ["excellent"]}, {"language": "english", "language_level": ["excellent"]}, {"language": "chinese", "language_level": ["excellent"]}]}, "experience_required": {"duration": ["at least 10 years"], "field": ["mpf administration", "management", "operation", "mpf"]}}, {"job_id": "100003009018940", "location_code": "hk", "company": "Robert Half", "job_title": "AVP/VP - Management Reporting, leading bank", "description": "Our client is a leading International bank with operations in both banking and treasury services. To cope with their business expansion, they are looking for a caliber to join their team.\n\n\n\nReport to Senior Manager and lead a team of 5\nManage the strategic financial planning, forecasting, and budgeting process\nEvaluate the profit and cost efficiencies, Provide financial analysis and support for business case development, product and mandate pricing\nPerform financial modelling and analysis to support strategic projects and ad-hoc initiatives\n\n\n\nRequirements:\n\nBachelor's Degree in Accounting, Finance or relevant discipline\nMinimum 3 years' experience in banking and financial accounting / regulatory reporting functions\nMember of CPA is an added advantage\nHigh level of multi-tasking and time management skill are required\nA team-player with excellent working attitude; willing to take on multiple functions\nExcellent verbal and written communication skills\n\n\n\nApply Today\n\nTo apply online (Word attachment only), please click the 'Apply' button. Please note that only short-listed candidates will be contacted.", "employment_types": ["Full Time", "Permanent"], "selling_points": ["A leading retail banking and corporate banking", "Fringe benefit with decent bonus", "Good exposure with career progression"], "locations": ["Central & Western Area"], "categories": ["Banking / Finance", "Corporate Banking", "Private Banking", "Retail Banking"], "post_time": "2022-01-04T06:11:10Z", "salary": {"currency": null, "max": null, "min": null, "period": "monthly", "term": null}, "salary_visible": false, "title_keywords": [], "responsibilities": ["ad-hoc", "reporting", "cost", "management", "operations", "budgeting", "analysis", "evaluate", "lead a team", "financial analysis", "communication", "banking", "report", "forecasting", "planning"], "requirements": {"degrees": ["degree", "bachelor"], "majors": ["finance", "accounting"], "languages": [], "language_level": [], "hard_skills": ["financial analysis", "cpa", "analysis", "word"], "soft_skills": ["team-player", "communication skills", "multi-tasking", "time management skill"], "languages_combined": []}, "experience_required": {"duration": ["minimum 3 years"], "field": ["accounting", "financial", "banking"]}}, {"job_id": "100003009008257", "location_code": "hk", "company": "Hang Seng Bank Ltd", "job_title": "Assistant Client Service Manager", "description": "Private Banking and Trust Services - \u00a0Private Banking Department\n\nWe are currently seeking a high caliber professional to join our department as\u00a0Assistant Client Service Manager.\n\u00a0\n\nPrincipal Responsibilities\n\nAssist the relationship managers in managing customers\u2019 assets and investment portfolios by monitoring asset allocation, product mix and risk exposure\nAssist in developing and maintaining customer relationship by making servicing calls and handling customers\u2019 enquiries\nHandle the daily administration of customer accounts including investment, loans, deposits and other banking transactions\n\u00a0\nRequirements\nUniversity degree in a related discipline OR other relevant qualifications\nPasses in the HKSI licensing examinations\nMinimum 3 years\u2019 experience in banking with knowledge of investment and insurance products; experience in dealing with high net-worth customers an advantage\nAbility to communicate effectively, embrace change and overcome challenges\nAbility to be resilient in face of difficult situations\nGood sales and service mindset, with strong communication and interpersonal skills\nGood knowledge of application software\nProficiency in both English and Chinese; fluency in Putonghua and other dialects an advantage\nHigh level of customer centricity mindset with dedication to deliver exceptional quality services for customers\n\nIf you would like to explore other opportunities at Hang Seng Hong Kong, please visit\u00a0www.hangseng.com/careers/\u00a0for details.\n\n\nThe health and safety of our employees and candidates is very important to us. Due to the current situation related to the Novel Coronavirus (2019-nCoV), we\u2019re leveraging our digital capabilities to ensure we can continue to recruit top talent at the HSBC Group.\u00a0 As your application progresses, you may be asked to use one of our digital tools to help you through your recruitment journey.\u00a0 If so, one of our\u00a0 Resourcing colleagues will explain how our video-interviewing technology will be used throughout the recruitment process and will be on hand to answer any questions you might have.\n\nAll information provided by applicants will be used only for recruitment purposes and will be used strictly in accordance with the Bank's personal data policies, a copy of which may be obtained by the applicant upon request. Unless otherwise instructed in writing by the applicant concerned, applicants may be considered for other suitable positions within the Bank and its related companies. The personal data of unsuccessful job applicants may be retained for a maximum of two years from the date when the job application is rejected and such data may be retained for a longer period if there is a subsisting reason that obliges the Bank to do so, after which the personal data will be destroyed.\n\n", "employment_types": ["Full Time", "Permanent"], "selling_points": [], "locations": ["Not Specified"], "categories": ["Banking / Finance", "Private Banking", "Financial Services", "Others"], "post_time": "2021-12-30T07:17:06Z", "salary": {"currency": null, "max": null, "min": null, "period": "monthly", "term": null}, "salary_visible": false, "title_keywords": ["manager", "assistant"], "responsibilities": ["maintaining", "monitoring", "investment portfolios", "developing", "transactions", "banking", "administration"], "requirements": {"degrees": ["university degree"], "majors": [], "languages": ["putonghua", "english", "chinese"], "language_level": ["fluency", "advantage", "proficiency"], "hard_skills": ["hksi", "reason"], "soft_skills": ["novel", "communication and interpersonal skills"], "languages_combined": [{"language": "putonghua", "language_level": ["fluency", "advantage"]}, {"language": "english", "language_level": ["proficiency"]}, {"language": "chinese", "language_level": ["proficiency"]}]}, "experience_required": {"duration": ["minimum 3 years"], "field": ["investment", "insurance products", "banking"]}}, {"job_id": "100003009016172", "location_code": "hk", "company": "Bank of China (Hong Kong) Limited", "job_title": "Business Compliance & Operational Risks Manager", "description": "\u00a0Responsibilities:\u00a0\nImplement the risk control mechanisms (e.g KRIs) and risk monitoring requirements on the private banking business\nReview policies & procedures, risk assessment materials submitted by various units and to analyze the compliance/operation risks in new businesses / products / systems\nConduct trade surveillance, daily report monitoring and other regular transaction and work flow monitoring to identify possible compliance/operational risks and provide recommendations to enhance control weaknesses\nPerform self-assessment, gap analysis against internal and/or regulatory requirements\nAdvise business units on operational risks and control matters, including coordinate business contingency plan\nReview operational risk incidents / customer complaints and monitor the implementation status of the action plans\nPerform regular and ad hoc monitoring on relevant business activities and prepare management reports on compliance and operation risk related review results\nHandle internal / external review or audit\n\u00a0Requirements:\u00a0\nDegree or above \u00a0\u00a0\nAt least 4 years banking experience, preferably Operational Risk Management, or relevant experience on private banking.\u00a0 With Compliance background is an advantage.\u00a0\nIndependent, excellent analytical, time management and interpersonal skills, with ability to prioritize tasks.\nProficient in written, spoken English and Chinese\nFamiliar with regulatory requirements of private banking\n\u00a0", "employment_types": ["Full Time"], "selling_points": ["Implement the risk control mechanisms", "Degree or above", "At least 4 years banking experience"], "locations": ["Central"], "categories": ["Banking / Finance", "Private Banking"], "post_time": "2022-01-03T08:30:15Z", "salary": {"currency": null, "max": null, "min": null, "period": "monthly", "term": null}, "salary_visible": false, "title_keywords": ["manager"], "responsibilities": ["regulatory requirements", "audit", "plan", "plans", "control", "ad hoc", "compliance", "monitor", "implementation", "banking", "business activities", "customer complaints", "review", "procedures", "monitoring", "risk monitoring", "provide recommendations", "policies", "analysis", "systems", "coordinate", "management reports", "daily report"], "requirements": {"degrees": ["degree or above"], "majors": [], "languages": ["english", "chinese"], "language_level": ["proficient"], "hard_skills": [], "soft_skills": ["time management", "independent", "prioritize", "interpersonal skills"], "languages_combined": [{"language": "english", "language_level": ["proficient"]}, {"language": "chinese", "language_level": ["proficient"]}]}, "experience_required": {"duration": ["at least 4 years"], "field": ["risk management", "relevant experience", "banking experience", "banking"]}}, {"job_id": "100003009018822", "location_code": "hk", "company": "Robert Half", "job_title": "AVP/VP - Regulatory Reporting, Leading Bank", "description": "Our client is a leading International bank with operations in both banking and treasury services. To cope with their business expansion, they are looking for a caliber to join their team.\n\n\n\nResponsible for the HKMA regulatory reporting process, and to ensure the compilation of banking returns and surveys are in compliance with the completion instructions and relevant guidelines as set out by the HKMA\nEnsure proper control checking and review procedures are in place so as to minimize errors in reporting\nAssist in the implementation of system enhancement projects relating to banking return reporting and other ad hoc tasks as required by the management from time to time\n\nRequirements:\n\n\n\nBachelor's Degree in Accounting, Finance or relevant discipline\nMinimum 3 years' experience in banking and financial accounting / regulatory reporting functions\nMember of CPA is an added advantage\nHigh level of multi-tasking and time management skill are required\nA team-player with excellent working attitude; willing to take on multiple functions\nExcellent verbal and written communication skills\n\nApply Today\n\nTo apply online (Word attachment only), please click the 'Apply' button. Please note that only short-listed candidates will be contacted.\n\n", "employment_types": ["Full Time", "Permanent"], "selling_points": ["A leading retail banking and corporate banking", "Fringe benefit with decent bonus", "Good exposure with career progression"], "locations": ["Central & Western Area"], "categories": ["Banking / Finance", "Corporate Banking", "Private Banking", "Retail Banking"], "post_time": "2022-01-04T05:08:05Z", "salary": {"currency": null, "max": null, "min": null, "period": "monthly", "term": null}, "salary_visible": false, "title_keywords": [], "responsibilities": ["reporting", "control", "management", "guidelines", "operations", "compliance", "review", "checking", "procedures", "implementation", "ad hoc tasks", "communication", "banking", "enhancement projects"], "requirements": {"degrees": ["degree", "bachelor"], "majors": ["finance", "accounting"], "languages": [], "language_level": [], "hard_skills": ["hkma", "cpa", "word", "hkma regulatory reporting"], "soft_skills": ["communication skills", "responsible", "team-player", "multi-tasking", "time management skill"], "languages_combined": []}, "experience_required": {"duration": ["minimum 3 years"], "field": ["accounting", "financial", "banking"]}}, {"job_id": "100003009012032", "location_code": "hk", "company": "Cathay United Bank Company, Limited", "job_title": "Manager, Business Control - Private Wealth Management Business Management", "description": "Responsibilities:\n\nDevelop quantitative risk control framework for risk identification, measurement, management and reporting\nAct as first\u00a0line of defense, monitor daily activities of PWM frontline staff (RM, ARM, IC) are compliant to regulatory requirements and internal policies.\u00a0 Product lineup includes bond/mutual fund/private equity fund/hedge fund/equities/structured products/FX products\nCommunicate with the frontline staff regularly on significant risk items/irregularities found in investment transactions, areas of improvement in securities dealing, and provide guidance on investment suitability check before executing investment transactions for customers\nProvide regular training to frontline staff on dealing in securities\nRegularly review and update internal policies and procedures, to be in line with latest regulations, technology and industry best practices\nWork closely with the second line of defense and different stakeholders on policy and procedure implementation.\nPerform ad hoc duties as assigned by Team Head\n\nIdeal candidates should possess:\n\nBachelor\u2019s degree or equivalent academic qualification\nAt least 5 years\u2019 relevant risk control and investment suitability monitoring experience in private banking / private wealth management\nStrong knowledge of regulatory requirements on investment suitability framework\nOrganized, multi-tasking, detail-oriented\nGood communication and interpersonal skills\nAdaptive, willing to take up challenges\nProficient in written and spoken English and Chinese (Mandarin & Cantonese)\n\nWe offer attractive remuneration package and comprehensive fringe benefits. Interested parties please e-mail your full resume with current and expected salary by clicking \"Apply Now\".\u00a0\n\nPersonal information collected will be used for considering suitability for the post and strictly in accordance with our personal data policies.\u00a0 It is our policy to retain the personal data of unsuccessful applicants for future recruitment purposes for a period of maximum two years.", "employment_types": ["Full Time", "Permanent"], "selling_points": ["Bachelor's degree holder", "At least 5 years\u2019 experience", "Private Banking / Private Wealth Management"], "locations": ["Causeway Bay"], "categories": ["Banking / Finance", "Private Banking", "Wealth Management"], "post_time": "2021-12-31T08:56:23Z", "salary": {"currency": null, "max": null, "min": null, "period": "monthly", "term": null}, "salary_visible": false, "title_keywords": ["wealth management", "manager"], "responsibilities": ["regulations", "regulatory requirements", "transactions", "communication", "ad hoc duties", "control", "measurement", "monitor", "implementation", "develop", "banking", "reporting", "management", "review", "procedures", "monitoring", "executing", "provide guidance", "communicate with", "irregularities", "policies"], "requirements": {"degrees": ["degree", "bachelor"], "majors": [], "languages": ["cantonese", "english", "chinese", "mandarin"], "language_level": ["proficient"], "hard_skills": ["private equity"], "soft_skills": ["organized", "detail-oriented", "multi-tasking", "communication and interpersonal skills", "structured", "ideal"], "languages_combined": [{"language": "cantonese", "language_level": ["proficient"]}, {"language": "english", "language_level": ["proficient"]}, {"language": "chinese", "language_level": ["proficient"]}, {"language": "mandarin", "language_level": ["proficient"]}]}, "experience_required": {"duration": ["at least 5 years"], "field": ["management", "investment", "banking"]}}, {"job_id": "100003009006637", "location_code": "hk", "company": "Huatai Financial Holdings (Hong Kong) Limited", "job_title": "Relationship Manager, Private Wealth Management", "description": "\u5c97\u4f4d\u804c\u8d23\uff1a\n\n\u4e3a\u9ad8\u51c0\u503c\u4e2a\u4eba\u53ca\u673a\u6784\u5ba2\u6237\u63d0\u4f9b\u8de8\u5e02\u573a\u3001\u8de8\u8d44\u4ea7\u7c7b\u522b\u7684\u5168\u7403\u8d44\u4ea7\u914d\u7f6e\u670d\u52a1\n\u505a\u597d\u5ba2\u6237\u5173\u7cfb\u7ba1\u7406\u53ca\u6295\u8d44\u8005\u6559\u80b2\u5de5\u4f5c\uff0c\u7ed3\u5408\u5ba2\u6237\u80cc\u666f\u4e0e\u98ce\u9669\u627f\u53d7\u80fd\u529b\uff0c\u4e3a\u5176\u63d0\u4f9b\u5168\u65b9\u4f4d\u7684\u8d22\u52a1\u89c4\u5212\u53ca\u8d22\u5bcc\u7ba1\u7406\u670d\u52a1\n\u901a\u8fc7\u516c\u53f8\u73b0\u6709\u6e20\u9053\u53ca\u81ea\u62d3\u6e20\u9053\u589e\u52a0\u9ad8\u51c0\u503c\u5ba2\u6237\uff0c\u63d0\u5347\u5ba2\u5747\u8d44\u4ea7\n\u79ef\u6781\u5f00\u53d1\u5e76\u7ef4\u62a4\u4e0d\u540c\u7c7b\u578b\u7684\u8d22\u5bcc\u7ba1\u7406\u5ba2\u6237\uff0c\u5305\u62ec\u9ad8\u51c0\u503c\u4e2a\u4eba\u5ba2\u6237\u548c\u4f01\u4e1a\u5ba2\u6237\n\u805a\u7126\u8d44\u4ea7\u914d\u7f6e\u4e1a\u52a1\u53ca\u91d1\u878d\u4ea7\u54c1\u9500\u552e\uff0c\u4e3a\u5ba2\u6237\u63d0\u4f9b\u4e2a\u6027\u5316\u7684\u6295\u8d44\u5efa\u8bae\u3001\u8d22\u5bcc\u5206\u6790\u548c\u89c4\u5212\uff0c\u505a\u597d\u5ba2\u6237\u98ce\u9669\u504f\u597d\u3001\u8d22\u52a1\u72b6\u51b5\u8bc4\u4f30\uff0c\u5411\u5ba2\u6237\u63a8\u8350\u5408\u9002\u7684\u4ea7\u54c1\n\n\u804c\u4f4d\u8981\u6c42\uff1a\n\n\u672c\u79d1\u6216\u4ee5\u4e0a\u5b66\u5386\uff0c\u7855\u58eb\u5b66\u5386\u4f18\u5148\n\u4e09\u5e74\u4ee5\u4e0a\u91d1\u878d\u673a\u6784\u79c1\u4eba\u8d22\u5bcc\u7ba1\u7406\u4ece\u4e1a\u7ecf\u9a8c\uff0c\u4e1a\u7ee9\u7a81\u51fa\u8005\u53ef\u4e0d\u53d7\u6b64\u9650\n\u5177\u6709\u8d85\u9ad8\u51c0\u503c\u5ba2\u6237\u5f00\u62d3\u3001\u670d\u52a1\u548c\u7ef4\u62a4\u53ca\u91d1\u878d\u4ea7\u54c1\u9500\u552e\u7ecf\u9a8c\n\u5177\u6709\u8f83\u5f3a\u6297\u538b\u80fd\u529b\uff0c\u80fd\u591f\u9002\u5e94\u957f\u671f\u51fa\u5dee\n\u53ef\u4ee5\u5feb\u901f\u7684\u5b66\u4e60\uff0c\u5177\u6709\u5f00\u62d3\u8fdb\u53d6\u548c\u56e2\u961f\u5408\u4f5c\u7684\u7cbe\u795e\n\u666e\u901a\u8bdd\u548c\u82f1\u8bed\u6d41\u5229\uff0c\u4f1a\u5e7f\u4e1c\u8bdd\u4f18\u5148", "employment_types": ["Full Time"], "selling_points": ["\u4e09\u5e74\u4ee5\u4e0a\u91d1\u878d\u673a\u6784\u79c1\u4eba\u8d22\u5bcc\u7ba1\u7406\u4ece\u4e1a\u7ecf\u9a8c\uff0c\u4e1a\u7ee9\u7a81\u51fa\u8005\u53ef\u4e0d\u53d7\u6b64\u9650", "\u5177\u6709\u8d85\u9ad8\u51c0\u503c\u5ba2\u6237\u5f00\u62d3\u3001\u670d\u52a1\u548c\u7ef4\u62a4\u53ca\u91d1\u878d\u4ea7\u54c1\u9500\u552e\u7ecf\u9a8c", "\u672c\u79d1\u6216\u4ee5\u4e0a\u5b66\u5386"], "locations": ["Central"], "categories": ["Banking / Finance", "Private Banking", "Others", "Wealth Management"], "post_time": "2021-12-29T09:40:03Z", "salary": {"currency": null, "max": null, "min": null, "period": "monthly", "term": null}, "salary_visible": false, "title_keywords": ["wealth management", "relationship manager"], "responsibilities": [], "requirements": {"degrees": [], "majors": [], "languages": [], "language_level": [], "hard_skills": [], "soft_skills": [], "languages_combined": []}, "experience_required": {"duration": [], "field": []}}, {"job_id": "100003009008491", "location_code": "hk", "company": "E.SUN Commercial Bank, Ltd.", "job_title": "Product Service Specialist", "description": "Job Descriptions\n\nPrepare investment suitability assessment report to sales team according to customer information.\nAssist sales team in dealing with sales process, including investment advisory and trading.\nContact customers and deal with account matters on be behalf of salesperson.\nWork with Investment Research and PM team to provide sales materials and investment proposal templates.\n\nRequirement\n\nBachelor Degree or above\nPassed HKSI Licensing Examination Papers 1\n2+ years of relevant experience in Wealth Management, with exposure in financial products marketing.\nStrong sense of accountability, co-operative, detail-minded and multi-tasked\nGood communication and interpersonal skills\nGood computer skills in MS Word and Excel.\nProficiency in both English and Chinese, with fluency in Putonghua is an advantage\n\n\n\nWe offer attractive remuneration package including five-day work week, double pay, medical insurance coverage, performance bonus, OT allowance, public holiday, excellent career development opportunities and others benefit package to the right candidate. Please visit our website at https://www.esunbank.com.tw/bank/corporate/overseas-branch/overseas-branch/hong-kong for more information.\n\nInterested parties please forward your resume (in both Chinese and English versions are preferred) with current and expected salary to Human Resources Department\u00a0by APPLY NOW.\n\nAll information received will be kept in strictly confidential and only for employment related purposes.", "employment_types": ["Full Time", "Permanent"], "selling_points": ["Prepare investment suitability assessment report", "One of the leading banks in Taiwan", "Young and Energetic Working Culture"], "locations": ["Tsim Sha Tsui"], "categories": ["Banking / Finance", "Corporate Banking", "Private Banking"], "post_time": "2021-12-30T08:11:10Z", "salary": {"currency": null, "max": null, "min": null, "period": "monthly", "term": null}, "salary_visible": false, "title_keywords": ["specialist"], "responsibilities": ["investment proposal", "sales team", "contact", "report"], "requirements": {"degrees": ["degree or above", "bachelor"], "majors": [], "languages": ["putonghua", "english", "chinese"], "language_level": ["fluency", "advantage", "proficiency"], "hard_skills": ["excel", "computer skills", "hksi", "ms word"], "soft_skills": ["detail-minded", "multi-tasked", "communication and interpersonal skills", "accountability"], "languages_combined": [{"language": "putonghua", "language_level": ["fluency", "advantage"]}, {"language": "english", "language_level": ["proficiency", "fluency", "advantage"]}, {"language": "chinese", "language_level": ["proficiency", "fluency", "advantage"]}]}, "experience_required": {"duration": ["2+ years"], "field": ["products marketing", "management", "relevant experience", "financial"]}}, {"job_id": "100003009006745", "location_code": "hk", "company": "Cheuk Hang Growth", "job_title": "Fund Management Intern / Assistant / Trainee", "description": "Job Description\n\nOur clients are leading financial institutions in Hong Kong. They are currently looking for who interest in Finance to join their investment team as:\n\nResponsibilities:\n\nTo provide tailor-made financial advices to clients\nTo monitor & analyze clients\u2019 investment portfolio\nTo maintain good relationship with clients\n\nRequirements:\n\nUniversity graduate in any discipline\u00a0\nWilling to work with others\nExcellent interpersonal, communications and presentation skills\nAggressive, self-motivated, passionate for better career development\n\n\n\nBenefits:\n\n5 days work\nOn job training\nTraining allowance\nMedical Insurance, competitive salary and attractive bonus\n\nHK residents will only be considered.\nPersonal data will be used for recruitment purpose only.", "employment_types": ["Full Time"], "selling_points": [], "locations": ["Central & Western Area"], "categories": ["Banking / Finance", "Private Banking", "Management", "Management Trainee", "Asset Management"], "post_time": "2021-12-29T10:11:51Z", "salary": {"currency": "HKD", "max": 24999, "min": 20000, "period": "monthly", "term": null}, "salary_visible": true, "title_keywords": ["trainee", "assistant", "intern"], "responsibilities": ["monitor", "maintain good relationship"], "requirements": {"degrees": ["university graduate"], "majors": [], "languages": [], "language_level": [], "hard_skills": [], "soft_skills": ["passionate", "presentation skills", "interpersonal", "self-motivated"], "languages_combined": []}, "experience_required": {"duration": [], "field": []}}, {"job_id": "100003009002170", "location_code": "hk", "company": "Randstad Hong Kong Limited", "job_title": "Relationship Manager , Private Banking, HNW", "description": "about the company.\n\nThis well-known global bank is looking for well-focused coverage manager to join their Wealth Management team to manage and grow their customer portfolio across APAC. With broad product capability and exiting pool of clientele, they are in a great position to epand and lead in the market\n\nabout the team.\n\nJoin this team with strong cultural dynamics and fast paced work flow. Business oriented culture makes it easier for you to talk business and solicit new revenue. Client meetings are expected from your KPI instead of internal meetings.\n\nabout the job.\n\nAs an influential member of the team, you will cover all aspects within private banking /wealth management space\n\nestablish and maintain client relationships by understanding their special needs, handling their inquiries and complaints in a timely manner\ndrive business goals and achieve sales revenue target\nbe an expert in the market and communicate with Product & Research team\n\nskills & experiences required.\n\nYour previous experience as a Wealth Management / Private banking and familiarity with Investment, Insurance, Equities, Bonds, Real estate products will help you succeed in this role. You will have 8+ years of experience in private banking. You will be a team player in achieving team targets and also detail minded in conducting in-depth financial and assessment within credit policy and parameters of the bank. Due to the targeted client segment, you will be required to speak Mandarin, Cantonese and English on a daily basis.\n\nIf you're interested in this role, click 'apply now' or for more information and a confidential discussion on this role or to find out more opportunities in Retail / Private Banking contact Morris Cheng at +852 2232 3436 or email morris.cheng@randstad.com.hk", "employment_types": ["Full Time", "Permanent"], "selling_points": [], "locations": ["Not Specified"], "categories": ["Banking / Finance", "Investment", "Private Banking", "Wealth Management"], "post_time": "2021-12-28T04:00:00Z", "salary": {"currency": "HKD", "max": 159999, "min": 70000, "period": "monthly", "term": null}, "salary_visible": true, "title_keywords": ["relationship manager", "private banking"], "responsibilities": ["communicate with", "management team", "management", "business goals", "a timely manner", "inquiries and complaints", "maintain", "contact", "banking", "insurance"], "requirements": {"degrees": [], "majors": [], "languages": ["cantonese", "english", "mandarin"], "language_level": [], "hard_skills": [], "soft_skills": ["focused", "timely", "interested in", "influential", "team player"], "languages_combined": [{"language": "cantonese", "language_level": []}, {"language": "english", "language_level": []}, {"language": "mandarin", "language_level": []}]}, "experience_required": {"duration": ["8+ years"], "field": ["management", "insurance", "investment", "banking"]}}, {"job_id": "100003009008791", "location_code": "hk", "company": "Robert Half", "job_title": "AVP/VP - Asset & Liability Management/ALCO", "description": "Assist in organizing, implementing and developing asset and liability data management framework. Monitor and prepare report for the Group's crucial information and data regarding assets and liabilities management on a timely, accurately and completely basis.\nAssist in building up an effective Group ALM platform from the perspectives of capital return, capital structure, compliance with regulatory requirements, risk resisting capability and business need\nHelp to set up target balance sheet (\"TBS\") management framework, develop annual TBS taking into consideration annual business strategy and financial budget requirements, provide pivotal suggestions to support the Group's assets and liabilities structural risk and return management\nAssist in accomplishing tasks assigned by ALCO and Interest Rate Committee\nPerform other jobs assigned by superiors\n\nRequirements:\n\n\n\nBachelor's Degree in Accounting, Finance or relevant discipline\nMinimum 3 years' experience in banking and financial accounting / regulatory reporting functions\nMember of CPA is an added advantage\nHigh level of multi-tasking and time management skill are required\nA team-player with excellent working attitude; willing to take on multiple functions\nExcellent verbal and written communication skills\n\nApply Today\n\nTo apply online (Word attachment only), please click the 'Apply' button. Please note that only short-listed candidates will be contacted.\n\n", "employment_types": ["Full Time", "Permanent"], "selling_points": ["A leading retail banking and corporate banking", "Fringe benefit with decent bonus", "Good exposure with career progression"], "locations": ["Not Specified"], "categories": ["Banking / Finance", "Corporate Banking", "Private Banking", "Retail Banking"], "post_time": "2021-12-30T09:12:16Z", "salary": {"currency": null, "max": null, "min": null, "period": "monthly", "term": null}, "salary_visible": false, "title_keywords": [], "responsibilities": ["reporting", "prepare report", "management", "data", "regulatory requirements", "compliance", "monitor", "developing", "budget", "develop", "communication", "banking", "balance sheet"], "requirements": {"degrees": ["degree", "bachelor"], "majors": ["finance", "accounting"], "languages": [], "language_level": [], "hard_skills": ["cpa", "data management", "word"], "soft_skills": ["communication skills", "team-player", "timely", "multi-tasking", "time management skill"], "languages_combined": []}, "experience_required": {"duration": ["minimum 3 years"], "field": ["accounting", "financial", "banking"]}}, {"job_id": "100003009008033", "location_code": "hk", "company": "DBS Bank Ltd", "job_title": "VP/AVP, Business Finance, Consumer/Private Banking", "description": "Business Function\n\nGroup Finance aims to deliver world-class standards in reporting, financial planning and finance processes. We provide insights and analyses that help the bank make sound business decisions \u2013 whether in the areas of product development or customer profitability. We also provide capital management, business planning, forecasting, and tax and accounting advisory services\n\nResponsibilities\n\nFinancial reporting and consolidation for Consumer Bank and Wealth Management businesses \u2013 product & segment level analysis in areas of revenue, margins, volumes, direct and allocated expenses, headcount.\nCoordinate with Regional BUC team and Group MIS team for monthly submission of flash, periodic forecast and annual budget.\nAnalyze product margins and profitability, business volumes, with external market benchmarking and intelligence\nWork with stakeholders throughout the organization to identify opportunities for leveraging company data to drive business solutions, provide strategic and data-driven insights to grow revenues and profitability\nFacilitate expense management by analyzing and monitoring with relevant support units on cost allocations and review department expenses accruals\nEnsure proper business revenue recognition, expense booking and other relevant accounting matters\nSupport new projects and initiatives as required\n\nRequirements:\n\nDegree in Finance, Accounting, Statistics or other closely related field with minimum 8 years professional work experience in Business planning and analysis, financial analysis, research and/or consulting\nStrong communication and interpersonal skills in stakeholders\u2019 management\nStrong data mining, database management and programming skills preferred\nExperience with visualization software (Qlikview, PowerBI or equivalent) preferred\nKnowledge of Hyperion and PSGL\nPrior exposure to budgeting processes, Funds Transfer Pricing and Investment and Treasury Products\nPrior experience with business and data management initiatives\nGood command of spoken and written in English and Chinese\nCandidates with less experience will be considered as AVP\n\nApply Now\n\nWe offer a competitive salary and benefits package and the professional advantages of a dynamic environment that supports your development and recognises your achievements.\n\nWe regret only shortlisted candidates will be notified.", "employment_types": ["Full Time"], "selling_points": ["Pension Fund Scheme", "Medical Coverage for Family", "Flexible Working Arrangement"], "locations": ["Quarry Bay"], "categories": ["Banking / Finance", "Corporate Banking", "Private Banking", "Retail Banking"], "post_time": "2021-12-30T06:27:02Z", "salary": {"currency": null, "max": null, "min": null, "period": "monthly", "term": null}, "salary_visible": false, "title_keywords": ["private banking"], "responsibilities": [], "requirements": {"degrees": [], "majors": [], "languages": [], "language_level": [], "hard_skills": [], "soft_skills": [], "languages_combined": []}, "experience_required": {"duration": [], "field": []}}, {"job_id": "100003009008063", "location_code": "hk", "company": "Midas Associates Limited", "job_title": "Manager, AML advisory / Transaction Monitoring", "description": "Our client, a reputable bank, is looking for high caliber candidate for the position.\n\n\u00a0Job Description\n\nProvide AML advisory to business stakeholders in daily operations (e.g. AML Risk Assessment or Sanction etc.)\nDevelop and monitor\u00a0AML operations\u00a0on Private Banking sector related issues\u00a0to ensure that the Bank\u2019s operation are in compliance with statutory, regulatory and internal requirements\nInvestigate the alert-triggered cases and prepare the Suspicious Transaction Reports\nProvide FCC related regulatory updates to management and business stakeholders from time to time\nImplement effective Financial Crime Prevention policies and procedures to manage the financial crime risks\nConduct AML Compliance review / system testing\nBachelor degree holder in preferably Law, Business or relevant discipline\nMinimum 5 years of relevant FCC/AML experience in Banking and Finance Industry\nGood command in written and spoken English and Chinese\nEquipped with CAMLP or AAMLP is highly recommended\n\nInterested parties, please send update resume with present and expect salary.\n\n", "employment_types": ["Permanent"], "selling_points": ["AML, Transaction Monitoring", "Private Banking", "Financial Crime Compliance"], "locations": ["Others"], "categories": ["Banking / Finance", "Private Banking", "Financial Services"], "post_time": "2021-12-30T06:34:15Z", "salary": {"currency": "HKD", "max": 54999, "min": 45000, "period": "monthly", "term": null}, "salary_visible": true, "title_keywords": ["manager"], "responsibilities": ["management", "aml", "operations", "policies", "compliance", "monitor", "procedures", "review", "develop", "testing", "daily operations", "reports", "banking"], "requirements": {"degrees": ["bachelor degree holder"], "majors": ["business", "law"], "languages": ["english", "chinese"], "language_level": ["good command"], "hard_skills": ["aml", "aamlp"], "soft_skills": [], "languages_combined": [{"language": "english", "language_level": ["good command"]}, {"language": "chinese", "language_level": ["good command"]}]}, "experience_required": {"duration": ["minimum 5 years"], "field": ["finance industry", "banking"]}}, {"job_id": "100003009000730", "location_code": "hk", "company": "Job-Box Personnel", "job_title": "Business Management Associate [5 Days Work, Bank Holiday]", "description": "Key Roles and Responsibilities\u00a0:\n\nProviding quality services and financial solutions to customers and satisfy their changing financial needs.\nPresent investment portfolio to our prestigious personal and corporate clients\nManage the financial needs of a diverse range of customers from mass-market to high-net-worth segments.\nExplore business opportunities and strengthen customer relationships\n\n\n\nQualifications and Skills:\n\nUniversity fresh graduate, preferably in finance or business related discipline.\nStrong client skills with ability to deliver needs based solutions.\nProven organization skills and attention to details\nStrong self-motivation with good interpersonal and analytical skills.\nStrong communication with fluent Cantonese, Mandarin and English.\n\n\n\nCompetitive benefits package, including:\n\nFive-day work week.\nPerformance bonus.\n20 working days annual leave.\nSuperior training and development program.\nProgressive career advancement opportunities.\n\n\n\nWe offer a competitive salary and benefits package and the professional advantages of a dynamic environment that supports your development and recognizes your achievements.\n\nInterested individuals please send your detailed resume and expected salary by clicking\u00a0\"Apply Now\". Only candidates who are authorized to work in Hong Kong will be considered.", "employment_types": ["Full Time", "Permanent", "Internship"], "selling_points": ["Superior training and development program.", "5day work, 20 days annual leave, Performance bonus", "Progressive career advancement opportunities."], "locations": ["Eastern Area"], "categories": ["Banking / Finance", "Private Banking", "Marketing / Public Relations", "Marketing - Direct Marketing", "Others", "Student / Fresh Graduate / No Experience"], "post_time": "2021-12-27T05:12:28Z", "salary": {"currency": "HKD", "max": 24999, "min": 17000, "period": "monthly", "term": null}, "salary_visible": true, "title_keywords": ["management associate"], "responsibilities": ["communication", "business opportunities", "quality"], "requirements": {"degrees": ["fresh graduate"], "majors": ["finance", "business"], "languages": ["cantonese", "english", "mandarin"], "language_level": ["fluent"], "hard_skills": ["analytical skills"], "soft_skills": ["analytical skills", "communication", "diverse", "self-motivation", "attention to details", "organization skills", "interpersonal"], "languages_combined": [{"language": "cantonese", "language_level": ["fluent"]}, {"language": "english", "language_level": ["fluent"]}, {"language": "mandarin", "language_level": ["fluent"]}]}, "experience_required": {"duration": [], "field": []}}, {"job_id": "100003009008563", "location_code": "hk", "company": "Hang Seng Bank Ltd", "job_title": "Relationship Manager / Senior Relationship Manager", "description": "Private Banking Department - Private Banking and Trust Services\nWe are currently seeking a high caliber professional to join our department as\u00a0Relationship Manager / Senior\u00a0Relationship Manager.\nPrincipal responsibilities:\nDevelop and manage a portfolio of private banking customers\nProvide investment advice and deliver premium service to customers and execute their orders\nPerform investment portfolios analysis, monitor the performance and make necessary recommendation on portfolio re-allocation\nManage the credit quality and monitor the exposure of customers\u2019 loan portfolios\nWork with internal departments to solicit business referrals\nRequirements\nUniversity degree in a related discipline OR other relevant qualifications such as CFP or CFA\nPasses in the HKSI licensing examinations\nMinimum 6 years\u2019 banking experience, with good knowledge of investment products\nStrong sales orientation and ability to work under pressure\nAbility to communicate effectively, embrace change and overcome challenges\nAbility to be resilient in face of difficult situations\nStrong desire of self-improvement and learn from experiences\nGood communication, interpersonal, analytical and relationship management skills\nProficiency in both written English and Chinese. Fluency in Putonghua and other dialects an advantage\nHigh level of customer centricity mindset with dedication to deliver exceptional quality services for customers\n\nIf you would like to explore other opportunities at Hang Seng Hong Kong, please visit www.hangseng.com/careers/ for details.\n\nThe health and safety of our employees and candidates is very important to us. Due to the current situation related to the Novel Coronavirus (2019-nCoV), we\u2019re leveraging our digital capabilities to ensure we can continue to recruit top talent at the HSBC Group. As your application progresses, you may be asked to use one of our digital tools to help you through your recruitment journey. If so, one of our Resourcing colleagues will explain how our video-interviewing technology will be used throughout the recruitment process and will be on hand to answer any questions you might have.\n\nAll information provided by applicants will be used only for recruitment purposes and will be used strictly in accordance with the Bank's personal data policies, a copy of which may be obtained by the applicant upon request. Unless otherwise instructed in writing by the applicant concerned, applicants may be considered for other suitable positions within the Bank and its related companies. The personal data of unsuccessful job applicants may be retained for a maximum of two years from the date when the job application is rejected and such data may be retained for a longer period if there is a subsisting reason that obliges the Bank to do so, after which the personal data will be destroyed.", "employment_types": ["Full Time"], "selling_points": [], "locations": ["Not Specified"], "categories": ["Banking / Finance", "Private Banking", "Sales, CS & Business Devpt", "Direct Sales"], "post_time": "2021-12-30T16:40:34Z", "salary": {"currency": null, "max": null, "min": null, "period": "monthly", "term": null}, "salary_visible": false, "title_keywords": ["senior relationship manager", "relationship manager"], "responsibilities": ["analysis", "investment portfolios", "quality", "monitor", "develop", "monitor the performance", "banking"], "requirements": {"degrees": ["university degree"], "majors": [], "languages": ["putonghua", "english", "chinese"], "language_level": ["fluency", "advantage", "proficiency"], "hard_skills": ["cfa", "investment products", "hksi", "reason"], "soft_skills": ["communication", "novel", "interpersonal", "work under pressure"], "languages_combined": [{"language": "putonghua", "language_level": ["fluency", "advantage"]}, {"language": "english", "language_level": ["proficiency"]}, {"language": "chinese", "language_level": ["proficiency"]}]}, "experience_required": {"duration": ["minimum 6 years"], "field": ["investment", "banking experience"]}}, {"job_id": "100003009008960", "location_code": "hk", "company": "AIA International Limited", "job_title": "Relationship Manager / Team Manager (Wealth Management)", "description": "For you, through our Financial Services Centre, offering personal advice and perspective to your clients and finally solicit new businesses ranging from\n1) Fund Investment to Asset Management Services,\n2) MPF, Retirement / Pension Scheme Services\n3) CIES Investment Entrants Services as well as Risk Planning Solutions.\n\nRequirements:\n1) Diploma or Degree Holder, experience at Banking field is preferred\n2) Good Clients' Network and Interpersonal Connections\n3) Self-Confident, Outgoing with Energetic Personalites\n4) Past 2 Years Annual Income must be over HKD180,000 a year\n\nWe are now offering UNIQUE Package for the above High Calibre Candidate including\n\nOngoing Professional Training\n\nSubsidy to be CFP Credential\n\nirresistible Annual Income\n\nHigh Guarantee Basic Income with Performance Bonus\n\nFast Track Promotion Program", "employment_types": ["Full Time", "Permanent"], "selling_points": ["Subsidy to be CFP Credential", "irresistible Annual Income", "High Guarantee Basic Income with Performance Bonus"], "locations": ["Kowloon Bay"], "categories": ["Banking / Finance", "Private Banking", "Sales, CS & Business Devpt", "Business Development", "Insurance", "Insurance Agent / Broker"], "post_time": "2021-12-30T09:42:32Z", "salary": {"currency": null, "max": null, "min": null, "period": "monthly", "term": null}, "salary_visible": false, "title_keywords": ["wealth management", "manager", "relationship manager"], "responsibilities": ["planning", "banking", "mpf", "asset management"], "requirements": {"degrees": ["diploma", "degree holder"], "majors": [], "languages": [], "language_level": [], "hard_skills": ["basic", "scheme"], "soft_skills": ["confident", "outgoing", "unique", "energetic", "interpersonal"], "languages_combined": []}, "experience_required": {"duration": [], "field": ["banking"]}}, {"job_id": "100003009008262", "location_code": "hk", "company": "Hang Seng Bank Ltd", "job_title": "Assistant Risk and Sales Quality Management Manager", "description": "Private Banking and Trust Services \u2013 Private Banking Department\n\nWe are seeking a high caliber to join our department as\u00a0Assistant Risk and Sales Quality Management Manager.\n\n\n\nPrincipal responsibilities\n\nEngage in risk and control activities on Financial Crime Risk Management (FCRM).\nReview FCRM policies/process and enhance control/local procedure to comply with group /regulatory requirement with consideration of customer experience and work effectiveness. \u00a0 \u00a0\nCollaborate with front line staff members and key stakeholders including risk stewards and operation team on carrying out risk and control activities.\nHandle front line enquiries and prepare MIs for control and reporting.\nAssist managers in FCRM related projects.\nRequirements\nUniversity Degree in a related discipline or other relevant qualifications\nMinimum 3 years' retail banking/ private banking experience, preferably with exposure to retail banking/ private banking business and knowledge of related regulatory requirements and guidelines\nStrong attentiveness to detail, compliance and control orientation\nGood communication and interpersonal skills, with sound knowledge of application software such as MS Excel\u00a0\nProficiency in both English and Chinese\u00a0\nGreat sense of ownership and servicing mindset to ensure efficient and effective customer service processes\n\nIf you would like to explore other opportunities at Hang Seng Hong Kong, please visit www.hangseng.com/careers/ for details.\n\nThe health and safety of our employees and candidates is very important to us. Due to the current situation related to the Novel Coronavirus (2019-nCoV), we\u2019re leveraging our digital capabilities to ensure we can continue to recruit top talent at the HSBC Group. As your application progresses, you may be asked to use one of our digital tools to help you through your recruitment journey. If so, one of our Resourcing colleagues will explain how our video-interviewing technology will be used throughout the recruitment process and will be on hand to answer any questions you might have.\n\nAll information provided by applicants will be used only for recruitment purposes and will be used strictly in accordance with the Bank's personal data policies, a copy of which may be obtained by the applicant upon request. Unless otherwise instructed in writing by the applicant concerned, applicants may be considered for other suitable positions within the Bank and its related companies. The personal data of unsuccessful job applicants may be retained for a maximum of two years from the date when the job application is rejected and such data may be retained for a longer period if there is a subsisting reason that obliges the Bank to do so, after which the personal data will be destroyed.", "employment_types": ["Full Time", "Permanent"], "selling_points": [], "locations": ["Not Specified"], "categories": ["Banking / Finance", "Private Banking", "Financial Services", "Risk Management"], "post_time": "2021-12-30T07:20:26Z", "salary": {"currency": null, "max": null, "min": null, "period": "monthly", "term": null}, "salary_visible": false, "title_keywords": ["sales", "manager", "assistant"], "responsibilities": ["collaborate with", "reporting", "control", "management", "policies", "review", "assist managers"], "requirements": {"degrees": ["university degree"], "majors": [], "languages": ["english", "chinese"], "language_level": ["proficiency"], "hard_skills": ["ms excel", "reason"], "soft_skills": ["efficient", "novel", "communication and interpersonal skills", "customer service"], "languages_combined": [{"language": "english", "language_level": ["proficiency"]}, {"language": "chinese", "language_level": ["proficiency"]}]}, "experience_required": {"duration": ["minimum 3 years"], "field": ["banking experience", "related", "retail banking", "business", "banking"]}}]