[{"job_id": "100003009054200", "location_code": "hk", "company": "First Commercial Bank, Ltd", "job_title": "Deposit / Remittance Clerk", "description": "\u4e00\u822c\u5b58\u6b3e\u6216\u532f\u514c\u90e8\u9580\u6587\u54e1\n\nMain Responsibilities:\n\nHandle\u00a0counter transactions and opening accounts etc\nPerform inward/outward remittance and document\nHandle other duties as assigned by supervisors\n\n\nRequirements:\n\nAssociate Diploma or equivalent\nGood command in written & spoken Mandarin is a must, fluent in English and Cantonese\nProficient in MS Office applications including Chinese word processing\nFresh graduates are also welcomed\n\n\nWe offer competitive salary & attractive fringe benefits package to the right candidates. Please send your full resume, expected salary to us.\n", "employment_types": ["Full Time", "Permanent"], "selling_points": ["general duties of deposit or remittance clerk", "5 days work week, double pay & bonus", "Fresh graduates are also welcome"], "locations": ["Tsim Sha Tsui"], "categories": ["Banking / Finance", "Corporate Banking", "Private Banking", "Retail Banking"], "post_time": "2022-01-17T08:47:27Z", "salary": {"currency": null, "max": null, "min": null, "period": "monthly", "term": null}, "salary_visible": false, "title_keywords": ["clerk"], "responsibilities": ["other duties", "transactions"], "requirements": {"degrees": ["diploma"], "majors": [], "languages": ["cantonese", "english", "chinese", "mandarin"], "language_level": ["proficient", "good command", "fluent"], "hard_skills": ["chinese word processing", "ms office"], "soft_skills": [], "languages_combined": [{"language": "cantonese", "language_level": ["good command", "fluent"]}, {"language": "english", "language_level": ["good command", "fluent"]}, {"language": "chinese", "language_level": ["proficient"]}, {"language": "mandarin", "language_level": ["good command", "fluent"]}]}, "experience_required": {"duration": [], "field": []}}, {"job_id": "100003009053338", "location_code": "hk", "company": "Hang Seng Bank Ltd", "job_title": "Customer Relationship Manager", "description": "Retail Distribution\n\nHang Seng's Retail Distribution focuses on personal wealth management and financial services. Our one-stop wealth management initiatives are designed for both our affluent and mass integrated account customers.\u00a0With more than\u00a0290\u00a0branches\u00a0and automated banking centres, including\u00a0around 60\u00a0Prestige\u00a0Banking Centres\u00a0for our high-end personal customers, we serve over half of the adult population in Hong Kong while offering an extensive range of products to our valued customers.\n\nWe are currently seeking a high caliber professional to join our team as\u00a0Customer Relationship Manager.\n\nPrincipal responsibilities\n\nProvide financial planning services to high-net-worth customers\nProvide personalised service for this segment of customers to build and maintain good relationships\nPromote investment, insurance and banking products for optimising new business opportunities\nManage operational risk and observe the relevant policies /guidelines and compliance requirements\u00a0\n\u00a0\n\nHang Seng Bank Relationship Manager Virtual Recruitment Talk\u00a0\n\nIf you are keen to find out more about the working culture and how we nurture our Relationship Managers for their success at Hang Seng Bank, please join our Virtual Recruitment Talk\u00a0to hear the candid sharing from our Branch Networks business leaders and also our RMs. You will also find out our progressive career ladder for RMs from entry-level RM Trainee to Signature and Executive RM.\n\nDate:\u00a026 January 2022 (Wed)\n\nTime: 6:00 - 7:00 PM\n\nLocation:\u00a0Virtual Session \u2013 Dial in details will be provided upon registration\n\nRegister your place before 26 Jan 2022 by clicking\u00a0https://hsbc.zoom.us/webinar/register/WN_KABEhwC-RJqmSR07NkIS2g\u00a0\u00a0\n\n\n\nRequirements\n\nUniversity level education is an advantage OR\nHKCEE / HKDSE (with at least passes in Chinese and Mathematics OR English and Mathematics at Grade E / Level 2 / \"Attained\" or above) plus relevant work experience\nPasses in the Insurance Intermediaries Qualifying Examinations / Hong Kong Securities Institute Licensing Examinations\u00a0\nFulfilment of the competency requirements to carry out relevant regulated activities as defined under the Securities and Futures Ordinance\nMinimum of two years' experience in selling investment, insurance and banking products\nStrong sales and customer orientation, with good communication and interpersonal skills\nStrong self-motivation and ability to work under pressure\nProficiency in both English and Chinese, with proficiency in Putonghua an advantage\nHigh level of customer centricity mindset and ability to manage complex interactions effectively\nShown strong situation awareness, strong desire to learn and able to work in Agile environment\nBe curious and with passion to think deeply and rationally\n\n(Candidates with less experience will be considered for the position of\u00a0Senior Customer Relationship Officer)\n\nIf you would like to explore other opportunities at Hang Seng Hong Kong, please visit www.hangseng.com/careers/ for details.\n\nThe health and safety of our employees and candidates is very important to us. Due to the current situation related to the Novel Coronavirus (2019-nCoV), we\u2019re leveraging our digital capabilities to ensure we can continue to recruit top talent at the HSBC Group.\u00a0 As your application progresses, you may be asked to use one of our digital tools to help you through your recruitment journey.\u00a0 If so, one of our\u00a0 Resourcing colleagues will explain how our video-interviewing technology will be used throughout the recruitment process and will be on hand to answer any questions you might have.\n\nAll information provided by applicants will be used only for recruitment purposes and will be used strictly in accordance with the Bank's personal data policies, a copy of which may be obtained by the applicant upon request. Unless otherwise instructed in writing by the applicant concerned, applicants may be considered for other suitable positions within the Bank and its related companies. The personal data of unsuccessful job applicants may be retained for a maximum of two years from the date when the job application is rejected and such data may be retained for a longer period if there is a subsisting reason that obliges the Bank to do so, after which the personal data will be destroyed.", "employment_types": ["Full Time", "Permanent"], "selling_points": [], "locations": ["Not Specified"], "categories": ["Banking / Finance", "Credit Analysis / Approval", "Retail Banking", "Credit Collection"], "post_time": "2022-01-17T06:48:17Z", "salary": {"currency": null, "max": null, "min": null, "period": "monthly", "term": null}, "salary_visible": false, "title_keywords": ["relationship manager"], "responsibilities": ["guidelines", "policies", "business opportunities", "compliance", "maintain", "recruitment", "banking", "insurance", "planning"], "requirements": {"degrees": ["hkdse"], "majors": ["mathematics"], "languages": ["putonghua", "english", "chinese"], "language_level": ["advantage", "proficiency"], "hard_skills": ["plus", "securities and futures ordinance", "agile", "reason"], "soft_skills": ["agile", "communication and interpersonal skills", "self-motivation", "novel", "work under pressure"], "languages_combined": [{"language": "putonghua", "language_level": ["proficiency", "advantage"]}, {"language": "english", "language_level": ["proficiency", "proficiency", "advantage"]}, {"language": "chinese", "language_level": ["proficiency", "proficiency", "advantage"]}]}, "experience_required": {"duration": ["minimum of two years"], "field": ["insurance", "investment", "banking"]}}, {"job_id": "100003009049156", "location_code": "hk", "company": "Shanghai Commercial Bank Ltd", "job_title": "Customer Service Officer (Account Opening)", "description": "Responsibilities:\n\nHandle account opening and provide sales support\nProvide counter services and quality customer service in branch\nCross-sell general banking products\n\nRequirements:\n\nDegree holder or above in any disciplines\nMinimum 1 year\u2019s experience in counter services preferred\nPasses in IIQE and HKSI licensing examinations\nCustomer and sales oriented with strong sense of responsibility\nGood communication and interpersonal skills; fluency in written and spoken English and Chinese, preferably with proficiency in Putonghua\nPC knowledge, including MS Word, Excel and Chinese word processing\nPotential working location : Central\n(Fresh graduates will be considered and training will be provided)\n\nAttractive remuneration package will be offered to the right candidates. Interested parties please click \"Apply Now\" to submit your full resume with current and expected salary to the Human Resources Division.\n\nPlease visit us at www.shacombank.com.hk for more information about our Bank.\n\nAll personal data collected will be used for recruitment related purposes strictly in accordance with the Bank's personal data policies, a copy of which will be provided immediately upon request by contacting our Personal Data Compliance Officer. Applicants who are not contacted within two months may consider their applications unsuccessful and the personal data collected from the applicants will be retained for no longer than two years from the date of rejection during which the applicants may be considered for other suitable positions within the Bank.", "employment_types": ["Full Time", "Permanent"], "selling_points": ["Provide counter services and customer services", "Handle account opening and provide sales support", "Cross-sell general banking products"], "locations": ["Central"], "categories": ["Banking / Finance", "Investment", "Retail Banking", "Financial Services"], "post_time": "2022-01-15T03:50:09Z", "salary": {"currency": null, "max": null, "min": null, "period": "monthly", "term": null}, "salary_visible": false, "title_keywords": ["customer service officer"], "responsibilities": ["account opening", "customer service", "quality", "banking"], "requirements": {"degrees": ["degree holder"], "majors": ["any disciplines"], "languages": ["putonghua", "english", "chinese"], "language_level": ["fluency", "proficiency"], "hard_skills": ["excel", "iiqe", "chinese word processing", "hksi", "pc knowledge", "ms word"], "soft_skills": ["communication and interpersonal skills", "sense of responsibility"], "languages_combined": [{"language": "putonghua", "language_level": ["proficiency", "fluency"]}, {"language": "english", "language_level": ["proficiency", "fluency"]}, {"language": "chinese", "language_level": ["proficiency", "fluency"]}]}, "experience_required": {"duration": ["minimum 1 year"], "field": []}}, {"job_id": "100003009054376", "location_code": "hk", "company": "Bright Smart Securities International (H.K.) Limited", "job_title": "Branch Officer", "description": "Responsibilities:\n\nHandle account opening, customer enquiries and complaints;\nAssist in branch office daily operations;\nExecute trade orders on a timely and accurate manner is a must;\nMonitor client\u2019s orders and margin level, conduct margin call when necessary;\nMaintain good relationship with customers, explore and develop new customers;\nParticipate in marketing activities, warm call, events and other ad-hoc projects as assigned.\n\n\u00a0Requirement\u00a0& Qualification:\n\nHKDSE / Form 5 (HKCEE) or above (Passed in Chinese and mathematics/ English and Mathematics) is a must;\nPass in HKSI Paper 1, 7, 8 or equivalent is a plus;\nAt least one year of relevant working experience, fresh graduates are also welcomed\u00a0;\nGood command of spoken and written English and Chinese including Putonghua;\nGood communication skills, customer-oriented, proactive, patient and responsible;\nImmediate available will be an advantage.\n\n\u00a0We Offer:\n\nCompetitive remuneration package\n5 Days Work & Bank Holidays\nAttendance Bonus\nMeal Allowance\nDiscretionary Bonus\nMedical Insurance\nOn the Job Training\n\nWe provide attractive remuneration package and fringe benefits for the right candidate.\n\nInterested parties please send detailed resume with current and expected salaries to\u00a0Human Resources Department by clicking\u00a0\"Apply Now\"\u00a0or\u00a0fax to: 2530 2218.\n\nAll information collected will be used for recruitment purpose only, only shortlisted candidates will be notified. Welcome to visit our website: http://www.bsgroup.com.hk/ for more information.", "employment_types": ["Full Time", "Permanent"], "selling_points": [], "locations": ["Central & Western Area"], "categories": ["Banking / Finance", "Retail Banking"], "post_time": "2022-01-17T09:18:38Z", "salary": {"currency": null, "max": null, "min": null, "period": "monthly", "term": null}, "salary_visible": false, "title_keywords": ["officer"], "responsibilities": ["account opening", "monitor", "maintain good relationship", "develop", "daily operations", "ad-hoc projects", "customer enquiries and complaints"], "requirements": {"degrees": ["form 5", "hkdse"], "majors": ["mathematics"], "languages": ["putonghua", "english", "chinese"], "language_level": ["good command"], "hard_skills": ["hksi paper", "plus"], "soft_skills": ["communication skills", "responsible", "customer-oriented", "patient", "proactive"], "languages_combined": [{"language": "putonghua", "language_level": ["good command"]}, {"language": "english", "language_level": ["good command"]}, {"language": "chinese", "language_level": ["good command"]}]}, "experience_required": {"duration": ["at least one year"], "field": ["relevant working experience"]}}, {"job_id": "100003009053354", "location_code": "hk", "company": "Hang Seng Bank Ltd", "job_title": "Executive Customer Relationship Manager", "description": "Retail Distribution\n\nHang Seng's Retail Distribution focuses on personal wealth management and financial services. Our one-stop wealth management initiatives are designed for both our affluent and mass integrated account customers. With more than 170 branches and automated banking centres, including over 50 Prestige Banking Centres for our high-end personal customers, we serve over half of the adult population, offering an extensive range of products.\n\nWe are currently seeking a high caliber professional to join our team as\u00a0Executive Customer Relationship Manager.\n\nPrincipal responsibilities\n\nProvide financial planning services to high-net-worth customers\nProvide personalised service for this segment of customers to build and maintain good relationships\nPromote investment, insurance and banking products for optimising new business opportunities\nAssist the team head in providing coaching to Relationship Managers\nManage operational risk and observe the relevant policies /guidelines and compliance requirements\n\nHang Seng Bank Relationship Manager Virtual Recruitment Talk\u00a0\n\nIf you are keen to find out more about the working culture and how we nurture our Relationship Managers for their success at Hang Seng Bank, please join our Virtual Recruitment Talk\u00a0to hear the candid sharing from our Branch Networks business leaders and also our RMs. You will also find out our progressive career ladder for RMs from entry-level RM Trainee to Signature and Executive RM.\n\nDate:\u00a026 January 2022 (Wed)\n\nTime: 6:00 - 7:00 PM\n\nLocation:\u00a0Virtual Session \u2013 Dial in details will be provided upon registration\n\nRegister your place before 26 Jan 2022 by clicking\u00a0https://hsbc.zoom.us/webinar/register/WN_KABEhwC-RJqmSR07NkIS2g\u00a0\u00a0\n\n\n\nRequirements\n\nUniversity degree in a related discipline OR professional qualifications such as CFA, CFP or CFMP is preferred\nPasses in the Insurance Intermediaries Qualifying Examinations / Hong Kong Securities Institute Licensing Examinations\nFulfilment of the competency requirements to carry out relevant regulated activities as defined under the Securities and Futures Ordinance\nMinimum of five years' experience in selling investment, insurance and banking products\nStrong sales and customer orientation, with good communication and interpersonal skills\nStrong self-motivation and ability to work under pressure\nProficiency in both English and Chinese, with proficiency in Putonghua an advantage\nHigh level of customer centricity mindset with dedication to deliver exceptional quality services for customers\nIf you would like to explore other opportunities at Hang Seng Hong Kong, please visit\u00a0www.hangseng.com/careers/\u00a0for details.\n\n\n\n\nThe health and safety of our employees and candidates is very important to us. Due to the current situation related to the Novel Coronavirus (2019-nCoV), we\u2019re leveraging our digital capabilities to ensure we can continue to recruit top talent at the HSBC Group.\u00a0 As your application progresses, you may be asked to use one of our digital tools to help you through your recruitment journey.\u00a0 If so, one of our\u00a0 Resourcing colleagues will explain how our video-interviewing technology will be used throughout the recruitment process and will be on hand to answer any questions you might have.\n\n\n\nAll information provided by applicants will be used only for recruitment purposes and will be used strictly in accordance with the Bank's personal data policies, a copy of which may be obtained by the applicant upon request. Unless otherwise instructed in writing by the applicant concerned, applicants may be considered for other suitable positions within the Bank and its related companies. The personal data of unsuccessful job applicants may be retained for a maximum of two years from the date when the job application is rejected and such data may be retained for a longer period if there is a subsisting reason that obliges the Bank to do so, after which the personal data will be destroyed.", "employment_types": ["Full Time", "Permanent"], "selling_points": [], "locations": ["Not Specified"], "categories": ["Banking / Finance", "Credit Analysis / Approval", "Retail Banking", "Credit Collection"], "post_time": "2022-01-17T06:49:50Z", "salary": {"currency": null, "max": null, "min": null, "period": "monthly", "term": null}, "salary_visible": false, "title_keywords": ["executive", "relationship manager"], "responsibilities": ["guidelines", "policies", "business opportunities", "compliance", "maintain", "recruitment", "banking", "insurance", "planning"], "requirements": {"degrees": ["university degree"], "majors": [], "languages": ["putonghua", "english", "chinese"], "language_level": ["advantage", "proficiency"], "hard_skills": ["cfa", "reason", "securities and futures ordinance", "professional qualifications"], "soft_skills": ["novel", "communication and interpersonal skills", "self-motivation", "work under pressure"], "languages_combined": [{"language": "putonghua", "language_level": ["proficiency", "advantage"]}, {"language": "english", "language_level": ["proficiency", "proficiency", "advantage"]}, {"language": "chinese", "language_level": ["proficiency", "proficiency", "advantage"]}]}, "experience_required": {"duration": ["minimum of five years"], "field": ["insurance", "investment", "banking"]}}, {"job_id": "100003009053690", "location_code": "hk", "company": "AXA China Region Insurance Company Limited", "job_title": "MPF Customer Service Officer (5 days work)", "description": "Career with a Difference\n\nWe offer flexible working hours, comprehensive training and excellent career development opportunities.\n\nWe deliver professional MPF services and retirement planning to our clients. Working in our young and joyful international team including native Cantonese and English speakers, we respect every teammate and have equal opportunities. Want a dynamic career with a difference? Come and join us!\n\n\u00a0Core responsibilities:\u00a0\n\nProvide professional MPF service to every individual client for their purposes of wealth management, retirement plan and investment\nProvide corporate benefits to company accounts like MPF schemes, Group Medical Plans and General Business Insurance\nManage relationships with individual clients and corporate accounts\nHandle incoming inquiries from scheme members\nEnjoy our benefits:\n\nClient Base provided\u00a0\nFlexible working hours\u00a0\nMonthly salary ranging from HK$16,000 to $25,000\nQuarterly Bonus and Year End Bonus\nInitial training and On-Job training provided\nTransparent Career Path to Management Level\nLife and Medical Insurance\nAs a MPF service officer, you should possess the following qualities:\n\nDegree or Diploma holders would be preferred\nFluent in Cantonese, English, and Mandarin as an advantage\nStrong interpersonal and communication skills with the ability to manage client relationships\nProactive, self-motivated, and customer-oriented\nResponsible team player with strong desire for success\nHKID card holder is a MUST\nFresh graduates would also be considered\n\nWe offer attractive benefits packages and excellent career development opportunities.\u00a0 Please mention your expected salary and the earliest availability in the resume.", "employment_types": ["Full Time"], "selling_points": ["Flexible working hours", "Year end bonus", "Transparent career path"], "locations": ["Tsim Sha Tsui"], "categories": ["Banking / Finance", "Retail Banking", "Fund Management", "Sales, CS & Business Devpt", "Customer Service - Supervisor / Officer"], "post_time": "2022-01-17T07:21:29Z", "salary": {"currency": "HKD", "max": 24999, "min": 17000, "period": "monthly", "term": null}, "salary_visible": true, "title_keywords": ["customer service officer"], "responsibilities": [], "requirements": {"degrees": [], "majors": [], "languages": [], "language_level": [], "hard_skills": [], "soft_skills": [], "languages_combined": []}, "experience_required": {"duration": [], "field": []}}, {"job_id": "100003009052147", "location_code": "hk", "company": "KPMG", "job_title": "Operation Officer (Customer Due Diligence Operations) (CS/Admin experience are welcomed)", "description": "KPMG\u2019s Customer Due Diligence Operations is operated under the Managed Services and provide operational excellence, subject matter expertise with leading edge tools and technology to deliver fast, efficient and high-quality outcomes to meet our clients\u2019 most critical business needs. We are now looking for high calibre individuals to join our team\n\n\nResponsibilities\n\nIdentify and verify KYC documents and customer statistic data\nProcess customer\u2019s application and engage directly with customers to obtain specific information\nSupport financial crime-based investigations\nAchieving individual targets and performance expectations and development\nManage caseload throughout end to end process in timely manner\nComply with relevant regulations and requirements for customer due diligence\nTimely escalation of issues (relating to on-boarding) to supervisor\n\nRequirements\n\nDiploma holder or above in any disciplines (Candidates with HKALE / HKDSE / HKCEE or equivalent secondary education background, and prior customer services experience would also be considered)\nCandidates with no relevant experience would also be considered. Training will be provided\nExperience of working in customer service capacity (e.g. call centre, airline, hospitality) or handling customer due diligence business processes is an advantage\nGood communication skills and good command on written and spoken Cantonese, Mandarin and English\nAbility to assimilate and apply detailed process instructions\nStrong analytical skills and problem solving, self-motivation and possess an enquiring mind\nStrong desire to deliver results with attention to accuracy and detail\nSelf-motivated, able to work independently and willing to accept challenges\nProficiency in Microsoft Office (PowerPoint, Word, Excel) or other related applications\nA good team player with the ability to deliver efficient working outcomes and overcome challenges even under pressure\nProactive and solutions driven, with the ability to thrive in a challenging environment\nA Five-day work week\nWe offer successful candidates an attractive remuneration package and the opportunity to work in a dynamic and exciting environment.\u00a0\n\nPersonal data collected will be used for recruitment purposes only.\u00a0\n\n\u00a9 2020 KPMG, a Hong Kong partnership and a member firm of the KPMG network of independent member firms affiliated with KPMG International Cooperative (\"KPMG International\"), a Swiss entity. All rights reserved.", "employment_types": ["Full Time"], "selling_points": ["Diploma holder or above in any discipline", "Experience of working in customer service capacity", "Proficiency in Microsoft Office"], "locations": ["Aberdeen"], "categories": ["Admin & HR", "Clerical / Admin Staff", "Banking / Finance", "Retail Banking", "Others"], "post_time": "2022-01-17T02:16:21Z", "salary": {"currency": null, "max": null, "min": null, "period": "monthly", "term": null}, "salary_visible": false, "title_keywords": ["operations", "operation officer", "admin"], "responsibilities": ["regulations", "customer due diligence", "data", "kyc"], "requirements": {"degrees": ["diploma holder", "hkdse", "secondary education"], "majors": ["any disciplines"], "languages": ["cantonese", "english", "mandarin"], "language_level": ["good command", "good"], "hard_skills": ["excel", "no", "microsoft office", "airline", "powerpoint", "analytical skills", "problem solving", "customer due diligence", "word"], "soft_skills": ["efficient", "communication skills", "self-motivated", "work independently", "good team player", "under pressure", "analytical skills", "problem solving", "customer service", "self-motivation", "proactive", "driven", "detailed"], "languages_combined": [{"language": "cantonese", "language_level": ["good command", "good"]}, {"language": "english", "language_level": ["good command", "good"]}, {"language": "mandarin", "language_level": ["good command", "good"]}]}, "experience_required": {"duration": [], "field": ["customer service", "relevant experience", "customer services", "education"]}}, {"job_id": "100003009054371", "location_code": "hk", "company": "Bright Smart Securities International (H.K.) Limited", "job_title": "Sales Officer (Warm Call Team)", "description": "About Standard Chartered\u00a0\nWe are a leading international bank focused on helping people and companies prosper across Asia, Africa and the Middle East.\u00a0\n\nTo us, good performance is about much more than turning a profit.\u00a0 It's about showing how you embody our valued behaviours - do the right thing, better together and never settle - as well as our brand promise, Here for good.\n\nWe're committed to promoting equality in the workplace and creating an inclusive and flexible culture - one where everyone can realise their full potential and make a positive contribution to our organisation. This in turn helps us to provide better support to our broad client base.\n\nAbout Mox\nAs one of the biggest banks in market, we are rapidly expanding by growing a new virtual banking business in Hong Kong. We see ourselves as a fast growing start-up company where you will enjoy autonomy and teamwork at the same time, solving new and exciting problems in a nimble and agile way. Join us and be part of history making for future banking experience!\n\nThe Role Responsibilities\nManage the Customer Care Centre which is the most important customer touchpoint of Mox, which provides 24hr service via Audio, Video Call and Text Chat.\nSupport the launch of wealth management products, work closely with the Product and Customer Team to ensure seamless customer support in that space.\nEstablish the appropriate service level target, and key performance indicators.\u00a0 Lead the team to meet and excel the target.\nAdvocate customer voice, and focus on continuously improving the process and setting new standards to provide best in class service.\nMaintain staffing plans, schedules; identify and develop talents, create and maintain a healthy organization structure with proper delegation among the team managers.\nCreates and automate the MIs and reports; leverage on the data to make sound and quality decisions; execute the solutions and continuously review and improve.\nOur Ideal Candidate\nBachelor\u2019s degree or higher from an accredited university\n8+ years of experience in Contact Centre in any sizable retail bank or insurance company\nProven track record of managing teams of 30+\nKnowledge in wealth management, and with HKSI license a solid advantage\nBasic literacy in Mac OS and enterprise cloud communication tools\nBe open to diverse culture and new ways of working, people-oriented\nResponsive and stay attentive even after office hours\nApply now to join the Bank for those with big career ambitions.\n", "employment_types": ["Full Time", "Permanent"], "selling_points": [], "locations": ["Central"], "categories": ["Banking / Finance", "Retail Banking", "Others"], "post_time": "2022-01-17T09:18:37Z", "salary": {"currency": null, "max": null, "min": null, "period": "monthly", "term": null}, "salary_visible": false, "title_keywords": ["sales officer"], "responsibilities": ["management", "data", "schedules", "communication tools", "review", "quality", "teams", "develop", "maintain", "client base", "reports", "contact", "banking", "plans", "audio", "insurance"], "requirements": {"degrees": ["degree", "bachelor"], "majors": [], "languages": [], "language_level": [], "hard_skills": ["excel", "mac os", "basic", "agile", "hksi", "make", "focus"], "soft_skills": ["flexible", "attentive", "agile", "focused", "teamwork", "communication", "committed", "diverse", "organisation", "people-oriented", "focus", "responsive", "positive", "ideal"], "languages_combined": []}, "experience_required": {"duration": ["8+ years"], "field": ["retail", "banking experience", "insurance"]}}, {"job_id": "100003009039573", "location_code": "hk", "company": "Brave Business Consultancy Co.", "job_title": "Assistant Relationship Manager/ Execution Manager - Private Wealth", "description": "About Standard Chartered\u00a0\nWe are a leading international bank focused on helping people and companies prosper across Asia, Africa and the Middle East.\u00a0\n\nTo us, good performance is about much more than turning a profit.\u00a0 It's about showing how you embody our valued behaviours - do the right thing, better together and never settle - as well as our brand promise, Here for good.\n\nWe're committed to promoting equality in the workplace and creating an inclusive and flexible culture - one where everyone can realise their full potential and make a positive contribution to our organisation. This in turn helps us to provide better support to our broad client base.\n\nAbout Mox\nAs one of the biggest banks in market, we are rapidly expanding by growing a new virtual banking business in Hong Kong. We see ourselves as a fast growing start-up company where you will enjoy autonomy and teamwork at the same time, solving new and exciting problems in a nimble and agile way. Join us and be part of history making for future banking experience!\n\nThe Role Responsibilities\n\nCoordinate the stream (ie a project) and apply the programme methodology and governance to ensure deliveries are made on time and within the budget allocated\nIdentify all the required activities to delivery and build the plan accordingly\nCarefully manage the plan as well as the risks and issues and translate the plan into tangible timelines and milestones; suggest solid mitigation options when required\nIdentify and monitor the key external dependencies that could affect the delivery\nAct as a first escalation point: Remove any blocker preventing the delivery; able to escalate in a timely way to senior management when required\nWork out an effective communication to report regularly to management and key stakeholders the progress on the project as well as potential issues/decisions needed\nProvide visibility to the project stream leads on the overall progress and their contribution to the overall deliverables\nApply a structured methodology to ensure the project deliverables.\u202fIt should cover the following:\nDesign the mode and facilitate the communications within the wider project team, as well as to senior stakeholders; identify and manage areas of potential resistance\nSuggest metrics and KPIs to measure and monitor the progress\nMaintain close interactions with the work stream leaders to keep abreast of the progress, make adjustment to the project plan if necessary\nSupport program level governance work when required\n\nOur Ideal Candidate\n\nUniversity graduate with at least 5 years solid experience in the banking industry, exposure of key positions in Operations Development, Business Process Management, Change Management and/or Management Consulting; with at least 3 years in a project management role or equivalent capacity\nProven track record in delivery of large projects in a sizable organization\nProject management certification (PMP, SCRUM, PRINCE etc) with focus on Agile methodology required\nExpertise in software development methodologies (SDLC, Waterfall, Agile) including being seasoned Jira and Confluence user is a must\nResults oriented, able to work in high pressure environment\nStrong sense of ownership for the project and demonstrate commitment to driving project objectives\nDemonstrated ability to work with different cultures, and with proven negotiation and leadership skills; strong coordination skills and capability to drive the contributors and stakeholders who have different priorities; ability to influence and facilitate executive level decisions\nAbility to identify project risks and to recommend mitigation actions\nPro-active and forward thinker: able to anticipate and to take action accordingly\nAble to be comfortable at the deepest level of details and to be able to articulate a clear summary to senior stakeholders when required (covering both technical and business aspects)\nThinks critically about project delivery, challenges the status quo to identify opportunities to enhance processes and services\nDemonstrate strong moral principles to do what is right for the customers, employees and partners; have the courage to speak the mind and not afraid to push boundaries\nApply now to join the Bank for those with big career ambitions.\n", "employment_types": ["Full Time"], "selling_points": ["Large Corporate Chinese Bank", "Good Career progression", "High attractive package for qualified candidate"], "locations": ["Tsim Sha Tsui"], "categories": ["Banking / Finance", "Retail Banking", "Sales, CS & Business Devpt", "Account Servicing", "Wealth Management"], "post_time": "2022-01-17T05:56:00Z", "salary": {"currency": null, "max": null, "min": null, "period": "monthly", "term": null}, "salary_visible": false, "title_keywords": ["manager", "assistant relationship manager"], "responsibilities": ["software", "consulting", "operations", "budget", "design", "communication", "maintain", "business process", "plan", "senior management", "monitor", "client base", "banking", "kpis", "report", "management", "change management", "project deliverables", "project plan", "coordinate", "project management", "coordination"], "requirements": {"degrees": ["university graduate"], "majors": ["business"], "languages": [], "language_level": [], "hard_skills": ["agile", "pmp", "make", "project management", "sdlc", "focus"], "soft_skills": ["agile", "focused", "coordination skills", "leadership skills", "communication", "articulate", "focus", "moral", "clear", "committed", "ideal", "negotiation", "pro-active", "positive", "flexible", "timely", "teamwork", "project management", "organisation", "structured"], "languages_combined": []}, "experience_required": {"duration": ["at least 5 years"], "field": ["banking industry", "management", "banking experience", "consulting", "development", "business"]}}, {"job_id": "100003009044924", "location_code": "hk", "company": "First Commercial Bank, Ltd", "job_title": "Deposit / Remittance Clerk", "description": "About Standard Chartered\u00a0\nWe are a leading international bank focused on helping people and companies prosper across Asia, Africa and the Middle East.\u00a0\n\nTo us, good performance is about much more than turning a profit.\u00a0 It's about showing how you embody our valued behaviours - do the right thing, better together and never settle - as well as our brand promise, Here for good.\n\nWe're committed to promoting equality in the workplace and creating an inclusive and flexible culture - one where everyone can realise their full potential and make a positive contribution to our organisation. This in turn helps us to provide better support to our broad client base.\n\nAbout Mox\n\n\nAs one of the biggest banks in market, we are rapidly expanding by growing a new virtual banking business in Hong Kong. We see ourselves as a fast growing start-up company where you will enjoy autonomy and teamwork at the same time, solving new and exciting problems in a nimble and agile way. Join us and be part of history making for future banking experience!\n\nThe Role Responsibilities\n\nWe are looking for an experienced office manager to be responsible for the office administrative work, facilities management, team events, and assist a few senior executives of the Bank in some of their daily office administration.\u00a0\nYou will:\n\nManage the workday schedule of a few senior executives, and their day-to-day admin work.\nManage the office space, including the facilities management and premises improvements, engaging the landlord and the property management team, office lease arrangement, and ad hoc issues in relations with the premises.\u00a0\nFacilitate the smooth running of the offices, optimize the office space, ensure the health and safety of the personnel, procure and arrange the office equipment, and manage the hardware inventory.\u00a0\nAssist the team on some team events e.g. celebrations, team gatherings and townhalls events\nWork on any ad hoc team related tasks as assigned at times.\nOur Ideal Candidate\nAt least 8 years of work experience, of which no less than 5 years of experience as office manager, or personal assistant.\nExperience in facilities management an advantage.\nEnglish is the primary language in this organization.\u00a0 You need to be able to communicate effectively with English verbally and in writing; experience in working with non-Chinese speaking executives will be an advantage.\nProficient in Mac OS, MS Office and other new office communication tools \u2013 O365 and Slack.\nHighly responsive, and comfortable to work with the corporate mobile device during and after office hours; able to handle the ad hoc situations and response positively and promptly; feel at ease to offer occasional help outside office hours.\nPleasant and self-motivated personality, positive mindset, able to work with diverse culture.\nDiscretion and integrity in handling confidential information.\nApply now to join the Bank for those with big career ambitions.\n", "employment_types": ["Full Time", "Permanent"], "selling_points": ["general duties of deposit or remittance clerk", "5 days work week, double pay & bonus", "Fresh graduates are also welcome"], "locations": ["Tsim Sha Tsui"], "categories": ["Banking / Finance", "Corporate Banking", "Private Banking", "Retail Banking"], "post_time": "2022-01-13T06:38:44Z", "salary": {"currency": null, "max": null, "min": null, "period": "monthly", "term": null}, "salary_visible": false, "title_keywords": ["clerk"], "responsibilities": ["management team", "management", "ad hoc", "administrative work", "office administration", "inventory", "hardware", "client base", "schedule", "banking", "communication tools"], "requirements": {"degrees": [], "majors": [], "languages": ["english", "chinese"], "language_level": ["advantage"], "hard_skills": ["o365", "no", "mac os", "ease", "agile", "hardware", "make", "facilities management", "mobile device", "ms office"], "soft_skills": ["flexible", "self-motivated", "agile", "focused", "responsible", "positive mindset", "teamwork", "integrity", "pleasant", "communication", "committed", "diverse", "organisation", "smooth", "responsive", "positive", "ideal"], "languages_combined": [{"language": "english", "language_level": []}, {"language": "chinese", "language_level": ["advantage"]}]}, "experience_required": {"duration": ["at least 8 years", "5 years"], "field": ["management", "banking experience"]}}, {"job_id": "100003009047887", "location_code": "hk", "company": "China CITIC Bank International Limited", "job_title": "Business Development Executive, Call Centre (\u696d\u52d9\u62d3\u5c55\u4e3b\u4efb, \u96fb\u8a71\u7406\u8ca1\u4e2d\u5fc3)", "description": "About Standard Chartered\u00a0\nWe are a leading international bank focused on helping people and companies prosper across Asia, Africa and the Middle East.\u00a0\n\nTo us, good performance is about much more than turning a profit.\u00a0 It's about showing how you embody our valued behaviours - do the right thing, better together and never settle - as well as our brand promise, Here for good.\n\nWe're committed to promoting equality in the workplace and creating an inclusive and flexible culture - one where everyone can realise their full potential and make a positive contribution to our organisation. This in turn helps us to provide better support to our broad client base.\n\n\nThe Role Responsibilities\nConducts all aspects of market research activities to support the commercial team.\nAnalyses deal economics through robust financial modelling.\nAssists the team in pricing a deal/transaction to enhance deal selection and ensure alignment to AF strategy.\nPerforms robust risk analysis and ensuring adherence to the relevant bank polices/processes and Aviation Finance underwriting standards.\nSupports the commercial team in related marketing activities, preparation of proposals etc.\nSupports the commercial team in the origination of new business in franchise markets.\nSupport the Aviation Finance team in collaborating with CCIB teams to identify and target transactions and pursue cross-sell opportunities in line with CCIB\u2019s business strategy.\nSupport the Aviation Finance team in organising and driving business success through improvement in client penetration and profitability in conjunction coverage partners.\n\nBusiness\n\nEffectively use SCB\u2019s industry expertise, knowledge and professional network for ideation, generating leads for new deals and assessment of opportunities\nClient interface at senior management levels and ensuring that the engagement, services and quality of work meets the highest industry standards\nStructuring of transactions including cross border deals, to best meet clients\u2019 needs covering solutions ranging from senior and/ or mezzanine debt/bonds and/ or operating and finance lease options, financing across different parts of the capital structure\nPrepare high quality pitching and marketing materials for client presentations.\nCollaborate with internal stakeholders including client coverage, other product teams in financial markets,\u00a0 transaction banking and risk.\nTo ensure that new and existing business is consistent with Group policies, meets applicable credit risk criteria, internal approval procedures and provides acceptable risk adjusted return for the Bank, all as defined in the Underwriting Standards, globally and locally, including reputational risk.\nSupport and oversee robust deal selection through transaction analysis and pricing, conflict resolution and risk management to ensure the business is consistent with the strategy and risk appetite of the Bank\n\nOur Ideal Candidate\n\n2-3\u00a0years of experience in banking industry/ financial institution\u00a0\nBachelor's Degree or above in related discipline\nExperienced in credit analysis, ideally in aviation\nEffective communication skills & ability towork under pressure\nHKMA License as requested\nMandarin speaking is a must with good command in English\n\nApply now to join the Bank for those with big career ambitions.\u00a0", "employment_types": ["Full Time", "Contract"], "selling_points": ["\u96fb\u8a71\u7406\u8ca1\u4e2d\u5fc3 Call Centre", "Direct Banking / Telemarketing", "Telesales / Loan sales"], "locations": ["Lai Chi Kok"], "categories": ["Banking / Finance", "Retail Banking", "Sales, CS & Business Devpt", "Business Development"], "post_time": "2022-01-14T04:08:41Z", "salary": {"currency": null, "max": null, "min": null, "period": "monthly", "term": null}, "salary_visible": false, "title_keywords": ["business development executive"], "responsibilities": ["collaborate with", "management", "policies", "analysis", "teams", "market research", "transactions", "quality", "presentations", "procedures", "resolution", "client base", "communication", "finance team", "risk analysis", "banking", "marketing materials", "senior management"], "requirements": {"degrees": ["degree or above", "bachelor"], "majors": [], "languages": ["english", "mandarin"], "language_level": ["good command"], "hard_skills": ["hkma", "analysis", "presentations", "make", "credit analysis"], "soft_skills": ["flexible", "communication skills", "under pressure", "focused", "robust", "committed", "organisation", "positive", "ideal"], "languages_combined": [{"language": "english", "language_level": ["good command"]}, {"language": "mandarin", "language_level": ["good command"]}]}, "experience_required": {"duration": ["2-3 years"], "field": ["banking industry", "financial"]}}, {"job_id": "100003009048682", "location_code": "hk", "company": "Hang Seng Bank Ltd", "job_title": "Senior General Banking Manager", "description": "About Standard Chartered\u00a0\nWe are a leading international bank focused on helping people and companies prosper across Asia, Africa and the Middle East.\u00a0\n\nTo us, good performance is about much more than turning a profit.\u00a0 It's about showing how you embody our valued behaviours - do the right thing, better together and never settle - as well as our brand promise, Here for good.\n\nWe're committed to promoting equality in the workplace and creating an inclusive and flexible culture - one where everyone can realise their full potential and make a positive contribution to our organisation. This in turn helps us to provide better support to our broad client base.\nThe Role Responsibilities\n\nSupport to formulate the country execution and priorities to deliver sustainable growth across Affluent Banking segment clients, ensuring that the Bank fulfils the potential and realises the significant revenue and operating profit growth opportunity from the clients.\n\nThe role is to support the acquisition and CVP of Priority Private segment via\n\nAcquisition of New-to-Bank (NTB) and Upgrade of Existing-To-Bank (ETB) clients to Priority Private segment via strategic programs and partnerships\nDesign early engagement roadmap to effectively engage clients to drive product take-up and wealth penetration\nPlanning and implementation of segment CVP in the areas of wealth and lifestyle privileges \u00a0\n\nBusiness Performance\n\nDrive acquisition and upgrade of Priority Private clients through segment strategy & CVP propositions, marketing plans, segment and product offers across different channels\nDrive key KPIs including New-To-Bank (NTB) clients, New-To-Segment (NTS) clients, Qualified ratio, Wealth and Professional Investors (PI) penetration\nExecute segment strategy, marketing planning, products offer and integrated distribution deliveries to elevate client experience\n\nPriority Private \u2013 Acquisition and CVP\n\nAcquire NTB and ETB clients where appropriate in line with agreed protocols\nSupport execution of sales and marketing programs and initiatives to acquire NTB and NTS clients\nSupport the enhancement of onboarding experience and journeys to boost the qualified ratio and drive product take-up and wealth penetration\nManage, design and develop ongoing bespoke privileges for Priority Private through strategic partnerships\nCollaborate with relevant stakeholders to provide unique product offers and banking experiences to Priority Private clients across different client journeys\n\nProduct Bundles and Pricing\n\nSupport the development of product bundles, pricing & promotions to attract new clients, grow product and PI penetration by collaboration with Product teams\n\nProcesses\n\nExecute Priority Private sign-up process, campaign design & implementation process\nFollow through deepening programme processes, e.g. Campaign Management, Leads management\nSupport the management of budget & KPI, and ensure it is accurately reported & forecasted throughout the year\nManage the contractual relationships with external partners to provide bespoke client privileges\n\nPeople\u00a0\n\nDrive an optimized working environment and lives with the Bank\u2019s Value Behaviours\n\nRisk Management\n\nEnsure relevant control measures are undertaken to minimize risk exposure\n\nGovernance\n\nEnsure relevant control measures are undertaken to fully complied with regulatory & business conduct\n\nRegulatory & Business Conduct\n\nLive by the Group\u2019s Values and Code of Conduct.\nTake personal responsibility for embedding the highest standards of ethics, including regulatory and business conduct, across Standard Chartered Bank. This includes understanding and ensuring compliance with, in letter and spirit, all applicable laws, regulations, guidelines and the Group Code of Conduct.\nAchieve the outcomes set out in the Bank\u2019s Conduct Principles\nEffectively and collaboratively identify, escalate, mitigate and resolve risk, conduct and compliance matters\n\nKey Stakeholders\n\nChannel: Distribution Network, Corporate Partnerships, Digital Banking. Voice & Virtual\nProducts: Wealth Management, Retail Products\nGroup: Group Segments & other Group teams\nOthers: Brand & Marketing, Retail Analytics, Sales Performance Management, Legal & Compliance, Client Journey, Operations, external partners & vendors (Aspire, GiveGift)\nApply now to join the Bank for those with big career ambitions.\n", "employment_types": ["Full Time", "Permanent"], "selling_points": [], "locations": ["Not Specified"], "categories": ["Banking / Finance", "Retail Banking", "Others"], "post_time": "2022-01-14T07:02:28Z", "salary": {"currency": null, "max": null, "min": null, "period": "monthly", "term": null}, "salary_visible": false, "title_keywords": ["manager"], "responsibilities": ["collaborate with", "regulations", "marketing plans", "operations", "budget", "design and develop", "design", "control", "sales performance", "compliance", "teams", "implementation", "client base", "banking", "kpis", "management", "campaign management", "guidelines", "planning"], "requirements": {"degrees": [], "majors": [], "languages": [], "language_level": [], "hard_skills": ["make", "code"], "soft_skills": ["flexible", "focused", "unique", "committed", "organisation", "positive"], "languages_combined": []}, "experience_required": {"duration": [], "field": ["banking experiences", "marketing", "planning"]}}, {"job_id": "100003009054174", "location_code": "hk", "company": "Hang Seng Bank Ltd", "job_title": "Assistant Insurance Sales Support Manager", "description": "About Standard Chartered\u00a0\nWe are a leading international bank focused on helping people and companies prosper across Asia, Africa and the Middle East.\u00a0\n\nTo us, good performance is about much more than turning a profit.\u00a0 It's about showing how you embody our valued behaviours - do the right thing, better together and never settle - as well as our brand promise, Here for good.\n\nWe're committed to promoting equality in the workplace and creating an inclusive and flexible culture - one where everyone can realise their full potential and make a positive contribution to our organisation. This in turn helps us to provide better support to our broad client base.\nAbout Mox\nAs one of the biggest banks in market, we are rapidly expanding by growing a new virtual banking business in Hong Kong. We see ourselves as a fast growing start-up company where you will enjoy autonomy and teamwork at the same time, solving new and exciting problems in a nimble and agile way. Join us and be part of history making for future banking experience!\nThe Role Responsibilities\nOur technology stack is predominantly React Native using TypeScript.\nWe use GraphQL as an abstraction layer to our micro-services\u00a0\nWe have an emphasis on software quality and writing maintainable code using TDD, DDD and Continuous Integration and Delivery.\u00a0\nCollaborate closely with product designers with a focus on feature design and prototyping.\u00a0\nBe involved in the user experience design process, from wire-frames and mock-ups through implementation and release.\u00a0\nWorking closely with the design team to create a reusable component library.\u00a0\nOur Ideal Candidate\nExperience building and maintaining mobile apps.\nFluent with TypeScript, JavaScript and experience building modern JavaScript component applications (ES20XX, Flexbox).\nDeep understanding of ReactJS or React Native.\nUnderstanding of GraphQL and why it is used.\nExposure to native languages like Kotlin or Swift is beneficial\nYou understand what makes a great mobile user experience and care deeply about providing that experience to our users\nA keen learner with an ambitious and results driven personality, who loves to share with other engineers.\nExperience collaborating on software projects with design and backend aspects.\nWork well as part of a team in a fast-paced environment.\nWork in an iterative approach, driven by customer feedback and data insights.\nExcellent communication and organisational skills.\nApply now to join the Bank for those with big career ambitions.\n", "employment_types": ["Full Time", "Permanent"], "selling_points": [], "locations": ["Not Specified"], "categories": ["Banking / Finance", "Retail Banking"], "post_time": "2022-01-17T08:40:24Z", "salary": {"currency": null, "max": null, "min": null, "period": "monthly", "term": null}, "salary_visible": false, "title_keywords": ["sales", "manager", "assistant"], "responsibilities": ["collaborate", "software", "maintaining", "data", "mock-ups", "quality", "user experience", "design", "implementation", "communication", "client base", "banking"], "requirements": {"degrees": [], "majors": [], "languages": [], "language_level": [], "hard_skills": ["agile", "swift", "make", "mobile", "typescript", "react native", "javascript", "kotlin", "integration", "code", "focus"], "soft_skills": ["flexible", "agile", "focused", "fast-paced environment", "keen", "teamwork", "deep", "communication", "committed", "organisational skills", "organisation", "focus", "driven", "positive", "ideal"], "languages_combined": []}, "experience_required": {"duration": [], "field": ["banking experience", "design"]}}, {"job_id": "100003009049170", "location_code": "hk", "company": "Shanghai Commercial Bank Ltd", "job_title": "Associate, Branch Opeations (Account Opening)", "description": "Responsibilities:\n\nCoordinate with Relationship Mangers, officers and customers in dealing with AML issues such as Annual Review & Trigger Event Review\nPerform AML termination of account and data cleansing\nSupport branch in operations enquiries\nProvide administrative support related to Branch Operations\nTake up ad hoc projects as assigned\n\nRequirements:\n\nPost-secondary education or above with at least 5 subjects passed in HKCEE/HKDSE, including Chinese and English Language\nMinimum 1 year of branch operations experience is required\nGood communication and interpersonal skills; fluency in written and spoken English and Chinese, preferably with proficiency in Putonghua\nAbility to work independently and under pressure\nAttention to details with sense in Anti-money Laundering\nGood PC knowledge, including MS Word, Excel and Chinese word processing\nWork location: Central\n\nAttractive remuneration package will be offered to the right candidates. Interested parties please click \"Apply Now\" to submit your full resume with current and expected salary to the Human Resources Division.\n\nPlease visit us at www.shacombank.com.hk for more information about our Bank.\n\nAll personal data collected will be used for recruitment related purposes strictly in accordance with the Bank's personal data policies, a copy of which will be provided immediately upon request by contacting our Personal Data Compliance Officer at the above email address. Applicants who are not contacted within two months may consider their applications unsuccessful and the personal data collected will be destroyed within 12 months of receipt.", "employment_types": ["Full Time", "Permanent"], "selling_points": ["Support branch in operations enquiries", "Provide administrative support", "Perform AML termination of account"], "locations": ["Central"], "categories": ["Banking / Finance", "Retail Banking", "Others", "Order Processing & Operation / Settlement"], "post_time": "2022-01-15T03:50:09Z", "salary": {"currency": null, "max": null, "min": null, "period": "monthly", "term": null}, "salary_visible": false, "title_keywords": ["associate"], "responsibilities": ["aml", "data", "cleansing", "operations", "review", "coordinate with", "ad hoc projects", "provide administrative support"], "requirements": {"degrees": ["hkdse", "secondary education"], "majors": [], "languages": ["putonghua", "english", "chinese"], "language_level": ["fluency", "proficiency", "good"], "hard_skills": ["excel", "chinese word processing", "anti-money laundering", "pc knowledge", "ms word"], "soft_skills": ["work independently", "communication and interpersonal skills", "under pressure", "attention to details"], "languages_combined": [{"language": "putonghua", "language_level": ["proficiency", "fluency"]}, {"language": "english", "language_level": ["proficiency", "fluency"]}, {"language": "chinese", "language_level": ["proficiency", "fluency", "good"]}]}, "experience_required": {"duration": ["minimum 1 year"], "field": []}}, {"job_id": "100003009038949", "location_code": "hk", "company": "Hang Seng Bank Ltd", "job_title": "Customer Service Officer, General Banking Section", "description": "Customer Contact Centre\nHang Seng's Customer Contact Centre has been ranked one of the best phone banking service providers for consecutive years. Our team strives to provide professional services for a wide range of banking products to address customers' different services and financial needs.\n\nWe are currently seeking high caliber professionals to join our\u00a0team as\u00a0Customer Service Officer, General Banking Section.\n\n\nPrincipal responsibilities:\u00a0\nDelivers professional customer service through answering investments & eBanking enquires by phone and email for personal customers to achieve committed phone performance pledges\nPromotes a wide range of financial services to prospect customers with focus on investment and insurance products.\nPerforms cross-team support in Customer Contact Centre to ensure the provision of premium phone banking services\nHandles customer complaints properly and performs necessary investigation\nManages and report suspicious fraud cases, major incidents and customer feedback to respective internal counterparts timely and properly\nEnsures all activities are in compliance with the requirement of the Bank and regulatory authorities\nRequirements\nDiploma or Degree Holder; Form Five or DSE Graduates\u00a0with relevant working experience will also be considered\nPasses in the Insurance Intermediaries Qualifying Examinations (IIQE)\u00a0Paper 1, 2 and 3 and Hong Kong Securities and Investment (HKSI) Paper 1, 7 and 8 a MUST\nMinimum 2 years\u2019 of relevant experience; with exposure to call center operations & knowledge of life insurance products are an advantage\nWilling to work shift hours\nStrong customer service orientation, with good communication and problem solving skills\nAbility to be resilient in face of difficult situations\nHigh level of customer centricity mindset with dedication to deliver exceptional quality services for customers\nProficiency in both English and Chinese, with fluency in Putonghua an advantage\nGood knowledge of application software\n(Candidates with less experience will be considered as\u00a0Customer Service Officer)\n\nIf you would like to explore other opportunities at Hang Seng Hong Kong, please visit www.hangseng.com/careers/ for details.\n\n\nThe health and safety of our employees and candidates is very important to us. Due to the current situation related to the Novel Coronavirus (2019-nCoV), we\u2019re leveraging our digital capabilities to ensure we can continue to recruit top talent at the HSBC Group. \u00a0As your application progresses, you may be asked to use one of our digital tools to help you through your recruitment journey.\u00a0 If so, one of our Resourcing colleagues will explain how our video-interviewing technology will be used throughout the recruitment process and will be on hand to answer any questions you might have.\u00a0\n\nAll information provided by applicants will be used only for recruitment purposes and will be used strictly in accordance with the Bank's personal data policies, a copy of which may be obtained by the applicant upon request. Unless otherwise instructed in writing by the applicant concerned, applicants may be considered for other suitable positions within the Bank and its related companies. The personal data of unsuccessful job applicants may be retained for a maximum of two years from the date when the job application is rejected and such data may be retained for a longer period if there is a subsisting reason that obliges the Bank to do so, after which the personal data will be destroyed.\n", "employment_types": ["Full Time", "Permanent"], "selling_points": [], "locations": ["Not Specified"], "categories": ["Banking / Finance", "Retail Banking"], "post_time": "2022-01-12T02:11:56Z", "salary": {"currency": null, "max": null, "min": null, "period": "monthly", "term": null}, "salary_visible": false, "title_keywords": ["customer service officer"], "responsibilities": ["customer complaints", "compliance", "investigation", "customer service", "contact", "banking", "insurance", "report"], "requirements": {"degrees": ["diploma", "dse", "degree holder"], "majors": [], "languages": ["putonghua", "english", "chinese"], "language_level": ["fluency", "advantage", "proficiency"], "hard_skills": ["iiqe", "problem solving skills", "hksi", "reason"], "soft_skills": ["communication", "novel", "problem solving skills", "customer service"], "languages_combined": [{"language": "putonghua", "language_level": ["fluency", "advantage"]}, {"language": "english", "language_level": ["proficiency", "fluency", "advantage"]}, {"language": "chinese", "language_level": ["proficiency", "fluency", "advantage"]}]}, "experience_required": {"duration": ["minimum 2 years"], "field": ["customer service", "relevant experience", "relevant working experience"]}}, {"job_id": "100003009053283", "location_code": "hk", "company": "WallStone Partners & Company Limited", "job_title": "Retail / Business Banking- Insurance Specialist(Welcome Insurance Agent)(25-50K)", "description": "Our clients are an international bank and they are seeking Mobile Insurance Specialist from all levels to join their banking teams.\u00a0\nResponsibilities:\nAchieve individual target for life insurance product and medical product\nMake Appointment with customer and outreach meeting to different branch location.\nLow Target and High Commission\nRequirements:\nAt least 2 years for Life insurance & Medical\nStrong knowledge for Insurance product& Medical\nIIQE 1, 2, 3 and HKSI 1, 7, 8\nDegree Holder or above\nFluent Chinese, English and Putonghua in Written and speaking\n*Interested parties, please click on below button \u201cApply Now\u201d. For a confidential discussion, please contact Vincent Lau at +852 2568 4777", "employment_types": ["Full Time", "Permanent"], "selling_points": ["Insurance Specialist", "Retail or Business banking", "1 year banking or wealth management experience"], "locations": ["Not Specified"], "categories": ["Banking / Finance", "Retail Banking"], "post_time": "2022-01-17T06:41:09Z", "salary": {"currency": null, "max": null, "min": null, "period": "monthly", "term": null}, "salary_visible": false, "title_keywords": [], "responsibilities": ["insurance"], "requirements": {"degrees": ["degree holder"], "majors": [], "languages": ["putonghua", "english", "chinese"], "language_level": ["fluent"], "hard_skills": ["iiqe", "hksi"], "soft_skills": [], "languages_combined": [{"language": "putonghua", "language_level": ["fluent"]}, {"language": "english", "language_level": ["fluent"]}, {"language": "chinese", "language_level": ["fluent"]}]}, "experience_required": {"duration": [], "field": []}}, {"job_id": "100003009054301", "location_code": "hk", "company": "OCBC Wing Hang Bank Limited", "job_title": "2022 OCBC Wing Hang Graduate Talent Programme", "description": "2022 OCBC Wing Hang Graduate\u00a0Talent Programme\n\nDesigned for graduates with up to two years of working experience who aspire to carve a career in banking, you will get a head start with our OCBC Wing Hang Graduate\u00a0Talent Programme. We have carefully designed a 24-month structured programme with an opportunity to gain exposure from front to back office of the bank to help you build a strong banking foundation to achieve your career goals in the banking industry.\n\n\n\nBy joining the Graduate Talent Programme, you will:\n\nGet onboard our 24-month accelerated career programme\nAchieve a head-start through job rotations\nDevelop broad-based banking knowledge\nBe guided by career coach / mentor\nWork on business projects\nBuild your regional network with graduates and businesses across the OCBC Group\n\n\nHere in OCBC Wing Hang Bank, we value the growth of every individual. We are here to help you take on the future of banking with us. We say that there's no better investment than the one in your own skills and growth.\n\nJoin us to become the next Graduate Talent of the future!\n\nWe seek passionate go-getters with high levels of motivation and drive, those who are interested in an accelerated career in the banking industry.\n\nRequirements\n\nA Bachelor\u2019s Degree with second upper class or above in any discipline\nLess than 2 years of working experience\nOutstanding extracurricular/internship achievements\nHighly motivated and analytical\nStrong leadership and open to new challenges and problem-solving\nTeam player with strong interpersonal and communication skills\nOpen-minded and able to work with colleagues from diverse cultures\nKeen interest in the latest development of global economy, including the Greater-Bay-Area (GBA)\nExcellent written and spoken English and Chinese, with proficiency in Putonghua would be an advantage\nIndividuals holding IANG visa are welcomed\n\nFor the 2022 Graduate Talent Programme, we are hiring for the following divisions:\n\nRetail Banking Group\nWholesale Banking Group\nTreasury\nOCBC Wing Hang Credit\nInformation Technology\nCompliance\n\nApply Now\n\nPlease submit your application\u00a0by providing your full resume, expected GPA and stating your top 3 choices of divisions.\n\nApplication ends on 3 February 2022.\n\nSelection Process\n\nOnline Application\nVideo Assessment\nOnline Aptitude & Numerical Tests\nAssessment Centre\nFinal Panel Interview\n\nProgramme Commencement Date\n\nJuly 2022", "employment_types": ["Full Time", "Permanent"], "selling_points": ["24-month accelerated career programme", "Achieve a head-start through job rotations", "Less than 2 years of working experience"], "locations": ["Sheung Wan"], "categories": ["Banking / Finance", "Corporate Banking", "Retail Banking", "Others"], "post_time": "2022-01-17T09:05:35Z", "salary": {"currency": null, "max": null, "min": null, "period": "monthly", "term": null}, "salary_visible": false, "title_keywords": [], "responsibilities": ["business projects", "compliance", "back office", "develop", "communication", "banking"], "requirements": {"degrees": ["degree", "bachelor"], "majors": [], "languages": ["putonghua", "english", "chinese"], "language_level": ["advantage", "excellent", "proficiency"], "hard_skills": ["problem-solving", "no", "go"], "soft_skills": ["passionate", "communication skills", "open-minded", "problem-solving", "interested in", "keen", "diverse", "motivated", "team player", "structured", "leadership", "interpersonal"], "languages_combined": [{"language": "putonghua", "language_level": ["proficiency", "advantage", "excellent"]}, {"language": "english", "language_level": ["advantage", "excellent"]}, {"language": "chinese", "language_level": ["advantage", "excellent"]}]}, "experience_required": {"duration": ["2 years", "two years"], "field": ["banking"]}}, {"job_id": "100003009050664", "location_code": "hk", "company": "Bank of Communications (Hong Kong) Limited", "job_title": "Financial Services Manager \u2013 Wealth and Personal Banking", "description": "Job Type\nFull Time\nJob Functions\nBanking / Finance, Loan, Mortgage, Others", "employment_types": ["Full Time"], "selling_points": ["Fast track to CRM position", "Excellent career progression", "Experience in branch frontline customer service"], "locations": ["Not Specified"], "categories": ["Banking / Finance", "Retail Banking", "Financial Services", "Wealth Management"], "post_time": "2022-01-14T11:09:16Z", "salary": {"currency": null, "max": null, "min": null, "period": null, "term": null}, "salary_visible": false, "title_keywords": ["personal", "manager"], "responsibilities": ["banking"], "requirements": {"degrees": [], "majors": [], "languages": [], "language_level": [], "hard_skills": [], "soft_skills": [], "languages_combined": []}, "experience_required": {"duration": [], "field": []}}, {"job_id": "100003009049920", "location_code": "hk", "company": "Nanyang Commercial Bank", "job_title": "Anti-Money Laundering Manager \u2013 Transaction Monitoring (Ref: KC8022-TM- JDB)", "description": "Investigate/ review suspicious transactions in accordance with relevant statutory and regulatory requirements.\nProvide timely advice to business units on AML/CFT related regulations and matters;\nProvide technical support to the Bank\u2019s transaction monitoring system such as handling of user enquiries, collaboration with Business Analyst and troubleshooting application incident;\nHandle AML-related inquiries from regulators and law enforcement agencies;\nParticipate in AML/CFT related ad-hoc projects as assigned.\n\u00a0Requirements:\n\nDegree holder in Finance, Law, Accounting, Business Administration, Information Technology or related disciplines;\nA minimum of 5 years of relevant experience in AML/CFT compliance, preferably in transaction monitoring from banks;\nSound knowledge in AML/CFT related regulations, guidelines and practices;\nExposure in SAS programming and project experience/ technical support in transaction monitoring system and regtech solution;\nIndependent, good team player, analytical mind with sound communication and interpersonal skills;\nProficient in both spoken and written English and Chinese, fluent in Putonghua is preferable;\nHolder of AAMLP or CAMS would be an advantage.\n\n(Candidate with less experience will be considered as Assistant Anti-Money Laundering Manager \u2013 Transaction Monitoring.)\n\nIf you are flexible enough and zeal for a harmonious and supportive working environment where enables you to grow and succeed professionally, please send a full resume indicating your public examination results (HKCEE and HKALE / HKDSE), your present and expected salary and quoting reference number attention to\u00a0Talent Acquisition Division, Nanyang Commercial Bank, 151 Des Voeux Road Central, Hong Kong or apply through email. For details, please visit https://www.ncb.com.hk/ and select the page Recruit.\n\nWe are an Equal Opportunities Employer. Data collected would be used for recruitment purposes only. Applicants who do not hear from us within 8 weeks may consider their applications unsuccessful and their data will be destroyed within 12 months of receipt.", "employment_types": ["Full Time", "Permanent"], "selling_points": ["Investigate/ review suspicious transactions", "Handle AML-related inquiries", "A minimum of 5 years of relevant experience"], "locations": ["Central & Western Area"], "categories": ["Banking / Finance", "Corporate Banking", "Retail Banking", "Professional Services", "Legal & Compliance"], "post_time": "2022-01-15T03:50:40Z", "salary": {"currency": null, "max": null, "min": null, "period": "monthly", "term": null}, "salary_visible": false, "title_keywords": ["manager"], "responsibilities": ["regulations", "aml", "data", "technical support", "regulatory requirements", "guidelines", "review", "monitoring", "troubleshooting", "transactions", "compliance", "communication", "recruitment", "ad-hoc projects", "administration"], "requirements": {"degrees": ["hkdse", "degree holder"], "majors": ["business administration", "law", "finance", "information technology", "related disciplines", "accounting"], "languages": ["putonghua", "english", "chinese"], "language_level": ["fluent", "proficient"], "hard_skills": ["aml", "sas", "cft", "programming", "aamlp", "anti-money laundering"], "soft_skills": ["flexible", "good team player", "supportive", "independent", "harmonious", "timely", "troubleshooting", "analytical mind", "communication and interpersonal skills"], "languages_combined": [{"language": "putonghua", "language_level": ["fluent", "proficient"]}, {"language": "english", "language_level": ["fluent", "proficient"]}, {"language": "chinese", "language_level": ["fluent", "proficient"]}]}, "experience_required": {"duration": ["minimum of 5 years"], "field": ["compliance", "relevant experience", "programming"]}}, {"job_id": "100003009050265", "location_code": "hk", "company": "China Construction Bank (Asia) Corporation Limited", "job_title": "Branch Sales Executive, Small Enterprise and Personal Loan Centre", "description": "Job Description:\n\nProactively solicit loan sales of unsecured personal loan and mortgage loan to customers, cross sell banking products including insurance and investment business and achieve designated sales objectives\nManage sales activities and performance, reach centre\u2019s agreed goals\nDemonstrate high quality services, establish, retain and build up customer relationships for contributing business and customer referrals\nPropose a tailored loan planning for customers according to their needs, handle customer\u2019s enquiries/complaints, resolves issues and follow up with customer\u2019s loan application to drawdown\nConduct outbound calls and perform outdoor marketing activities i.e. site promotion\nEnsure Centre\u2019s work procedures are in compliance with Bank\u2019s policies and guidelines and comply with the regulatory requirements\n\nRequirements:\n\n\u00a0\u00a0\u00a0\u00a0\u00a0\u00a0\u00a0\u00a0 Higher Diploma / DSE graduate or above\n\u00a0\u00a0\u00a0\u00a0\u00a0\u00a0\u00a0\u00a0 Minimum one year of experience as a sales role in related industry\n\u00a0\u00a0\u00a0\u00a0\u00a0\u00a0\u00a0\u00a0 Knowledge of loan products\n\u00a0\u00a0\u00a0\u00a0\u00a0\u00a0\u00a0\u00a0 Qualifications in IIQE/HKSI areas are preferred\n\u00a0 \u00a0 \u00a0 \u00a0 \u00a0Strong team player, aggressive and self-motivated with positive attitude\n\u00a0 \u00a0 \u00a0 \u00a0 \u00a0Excellent interpersonal skills and customer oriented. Good communication skills\u00a0 \u00a0 \u00a0 \u00a0 \u00a0 \u00a0in English, Cantonese and Mandarin\n\nApplicants who are not contacted within 8 weeks may consider their applications unsuccessful and their personal data will be retained by the bank for a period up to two years.\n\nAll information provided by applicants will be used for recruitment purposes only and will be used strictly in accordance with the bank\u2019s personal data policies, a copy of which will be provided upon request.", "employment_types": ["Full Time", "Permanent"], "selling_points": ["solicit loan sales of UPL and mortgage", "Manage sales activities and performance", "Demonstrate high quality services"], "locations": ["Not Specified"], "categories": ["Banking / Finance", "Loan", "Mortgage", "Retail Banking"], "post_time": "2022-01-14T10:03:17Z", "salary": {"currency": null, "max": null, "min": null, "period": "monthly", "term": null}, "salary_visible": false, "title_keywords": ["personal", "sales executive"], "responsibilities": ["sales activities", "bank\u2019s policies", "guidelines", "regulatory requirements", "compliance", "quality", "procedures", "banking", "insurance", "planning"], "requirements": {"degrees": ["diploma", "dse"], "majors": [], "languages": ["cantonese", "english", "mandarin"], "language_level": ["good"], "hard_skills": ["loan products", "iiqe", "hksi"], "soft_skills": ["communication skills", "self-motivated", "positive attitude", "interpersonal skills", "team player"], "languages_combined": [{"language": "cantonese", "language_level": ["good"]}, {"language": "english", "language_level": ["good"]}, {"language": "mandarin", "language_level": ["good"]}]}, "experience_required": {"duration": ["minimum one year"], "field": ["related"]}}, {"job_id": "100003009045508", "location_code": "hk", "company": "Hang Seng Bank Ltd", "job_title": "Safe Deposits Supervisor", "description": "Retail Distribution\u00a0\nHang Seng's Retail Distribution focuses on personal wealth management and financial services. Our one-stop wealth management initiatives are designed for both our affluent and mass integrated account customers. With more than 290 branches and automated banking centres, including around 60 Prestige Banking Centres for our high-end personal customers, we serve over half of the adult population in Hong Kong while offering an extensive range of products to our valued customers.\nWe are currently seeking a high caliber professional to join our branch network as\u00a0Safe Deposits Officer.\nPrincipal responsibilities\nManage the operation and security of safe deposit box efficiently\nEnsure customers\u2019 enquiries, requests and transactions are properly handled\nSupervise, coach and motivate subordinates to maintain a high service standard\nCross-sell banking products and make referrals on wealth management and financial products to sales staff so as providing full banking services to customers\nEnsure all control measures are in compliance with the Bank\u2019s guidelines and the code of conduct from regulatory bodies\nRequirements\nAssociate degree or Higher diploma or HKCEE / HKDSE holder,\u00a0less academically qualified candidates with relevant work experience will also be considered\nMinimum\u00a02 years relevant experience, preferably in the banking industry\nStrong self-motivation and ability to work independently\nProficiency in both English and Chinese\nHigh level of customer centricity mindset with dedication to deliver exceptional quality services for customers\n(Candidates with more experience would be considered for the position of Safe Deposits Officer.)\nIf you would like to explore other opportunities at Hang Seng Hong Kong, please visit\u00a0www.hangseng.com/careers/\u00a0for details.\nThe health and safety of our employees and candidates is very important to us. Due to the current situation related to the Novel Coronavirus (2019-nCoV), we\u2019re leveraging our digital capabilities to ensure we can continue to recruit top talent at the HSBC Group.\u00a0 As your application progresses, you may be asked to use one of our digital tools to help you through your recruitment journey.\u00a0 If so, one of our\u00a0 Resourcing colleagues will explain how our video-interviewing technology will be used throughout the recruitment process and will be on hand to answer any questions you might have.\nAll information provided by applicants will be used only for recruitment purposes and will be used strictly in accordance with the Bank's personal data policies, a copy of which may be obtained by the applicant upon request. Unless otherwise instructed in writing by the applicant concerned, applicants may be considered for other suitable positions within the Bank and its related companies. The personal data of unsuccessful job applicants may be retained for a maximum of two years from the date when the job application is rejected and such data may be retained for a longer period if there is a subsisting reason that obliges the Bank to do so, after which the personal data will be destroyed.", "employment_types": ["Full Time", "Permanent"], "selling_points": [], "locations": ["Not Specified"], "categories": ["Banking / Finance", "Retail Banking"], "post_time": "2022-01-14T02:10:16Z", "salary": {"currency": null, "max": null, "min": null, "period": "monthly", "term": null}, "salary_visible": false, "title_keywords": ["supervisor"], "responsibilities": ["management", "control", "service standard", "guidelines", "compliance", "transactions", "maintain", "banking"], "requirements": {"degrees": ["associate degree", "diploma", "hkdse"], "majors": [], "languages": ["english", "chinese"], "language_level": ["proficiency"], "hard_skills": ["safe", "reason"], "soft_skills": ["novel", "work independently", "self-motivation"], "languages_combined": [{"language": "english", "language_level": ["proficiency"]}, {"language": "chinese", "language_level": ["proficiency"]}]}, "experience_required": {"duration": ["minimum 2 years"], "field": ["banking industry", "relevant experience"]}}, {"job_id": "100003009050789", "location_code": "hk", "company": "China Construction Bank (Asia) Corporation Limited", "job_title": "Relationship Manager, Consumer Banking", "description": "Main Responsibilities\n- Explore and develop profitable business to achieve the growth\n- Provide professional banking product and services to build, maintain and deepen target customer relationships\n- Ensure the strictest compliance with all regulatory requirements and the Banks policies and procedures\nRequirements\n- Possess relevant frontline experience in financial services industry\n- Possess HKSI (Paper 1, 7, 8) and IIQE (Paper 1, 2, 3, 5) qualifications\n- Qualification in ECF is preferred\n- Outstanding communication and presentation skills\n- Strong ability to develop a network of target prospects\n- Demonstrate a strong drive to achieve sales, be self-motivated to face sales challenges and be able to work under pressure\n- Fast learner and mature with strong sales and customer orientation\n- Candidates with less experience will be considered for Assistant Relationship Manager", "employment_types": ["Full Time"], "selling_points": ["Possess relevant frontline experience", "Possess HKSI (Paper 1, 7, 8)", "IIQE (Paper 1, 2, 3, 5)"], "locations": ["Not Specified"], "categories": ["Banking / Finance", "Retail Banking"], "post_time": "2022-01-14T11:23:23Z", "salary": {"currency": null, "max": null, "min": null, "period": "monthly", "term": null}, "salary_visible": false, "title_keywords": ["relationship manager"], "responsibilities": ["regulatory requirements", "policies", "compliance", "procedures", "develop", "maintain", "banking"], "requirements": {"degrees": [], "majors": [], "languages": [], "language_level": [], "hard_skills": ["iiqe", "hksi"], "soft_skills": ["self-motivated", "mature", "communication", "presentation skills", "fast learner", "work under pressure"], "languages_combined": []}, "experience_required": {"duration": [], "field": ["financial services industry"]}}, {"job_id": "100003009050911", "location_code": "hk", "company": "China Construction Bank (Asia) Corporation Limited", "job_title": "Officer/AM, KYC Support Centre (1-year Contract)", "description": "Main Responsibilities\n- Support the business units in completing internal ML (Money-laundering)/TF (Terrorist Financing) risk assessment materials for KYC (Know Your Customer) review\n- Conduct negative news search and name screening of clients\n- Perform KYC routine review and non-routine review\n- Ensure all related procedure and documentation required to complete KYC review are properly executed in compliance with regulatory requirements and internal AML policies\n- Conduct procedure reviews on an on-going basis and ensure adherence to regulatory requirements and internal policies\n- Work closely with business units to provide effective KYC review support services\n- Liaise with related stakeholders on KYC review related matters\n- Manage and monitor the KYC review progress\n- Prepare and review management reports\n- Perform other ad hoc tasks as assigned by Team Head\nRequirements\n- Degree holder\n- Attentive to details, compliance and control oriented, diligent, proactive and able to work under pressure\n- Possession of good knowledge on banking operations, products and services. Self-motivated, independent with good communication and interpersonal skills\n- AML/CFT compliance knowledge is preferred\n- Familiar with the banking ordinance and rules, codes and guidelines issues by HKMA\n- Project management experience is preferred\n- People-oriented and a team player\n- Proficient in both spoken and written English and Chinese (including Mandarin)\n- Proficient in PC skills including MS Word and Excel\n- Pragmatic with strong drives for results\n\nApplicants who are not contacted within 8 weeks may consider their applications unsuccessful and their personal data will be retained by the bank for a period up to two years.\n\nAll information provided by applicants will be used for recruitment purposes only and will be used strictly in accordance with the bank\u2019s personal data policies, a copy of which will be provided upon request.", "employment_types": ["Full Time", "Contract"], "selling_points": ["KYC Support", "General compliance exposure", "Liaison with various business units"], "locations": ["Not Specified"], "categories": ["Banking / Finance", "Retail Banking", "Others", "Professional Services", "Legal & Compliance"], "post_time": "2022-01-14T11:45:26Z", "salary": {"currency": null, "max": null, "min": null, "period": "monthly", "term": null}, "salary_visible": false, "title_keywords": ["officer"], "responsibilities": ["aml", "regulatory requirements", "policies", "compliance", "review", "ensure adherence", "support services", "monitor", "ad hoc tasks", "liaise with", "management reports", "kyc", "documentation", "kyc review"], "requirements": {"degrees": ["degree holder"], "majors": [], "languages": ["english", "chinese", "mandarin"], "language_level": ["proficient"], "hard_skills": ["excel", "aml", "hkma", "ms word", "project management", "cft", "pc skills", "codes"], "soft_skills": ["self-motivated", "independent", "attentive to details", "diligent", "project management", "communication and interpersonal skills", "people-oriented", "team player", "proactive", "work under pressure"], "languages_combined": [{"language": "english", "language_level": ["proficient"]}, {"language": "chinese", "language_level": ["proficient"]}, {"language": "mandarin", "language_level": []}]}, "experience_required": {"duration": [], "field": ["project management"]}}, {"job_id": "100003009047759", "location_code": "hk", "company": "Public Bank (Hong Kong) Ltd", "job_title": "Senior Remittance Officer (Ref: JD-RSO)", "description": "Assist to support the team to ensure transactions are processed properly in a timely manner\nAct as a Checker for handling of SWIFT/SWIFTNet messages, Inward and Outward Remittancesetc.\nClose collaboration with Treasury to perform FX position control\nAdvise receipt of remittance to and obtain disposal instruction from Account Officer\nTrace problematic payment orders from Correspondent Banks as well as to follow up outstanding and irregular transactions\nSecondary education or above with at least 5 years of experience in related banking operations, of which at least 3 years at officer level\nKnowledge in perform AML screening on incoming and outgoing swift payments\nProficient in PC applications, including MS Excel, typewriting\nCandidate with less experience would be considered as Remittance Officer\n\nTo apply, interested parties please follow the application methods available in the Bank\u2019s career website\u00a0https://www.publicbank.com.hk/en/aboutus/careeropportunities. You can send us your resume quoting our job reference number together with present &\u00a0expected salary (a must)\u00a0to the Human Resources Department by email or fax at\u00a02815 3157\u00a0or by post to\u00a0Human Resources Department, 12/F, Public Bank Centre, 120 Des Voeux Road Central, Hong Kong. You may also visit our career website for other career opportunities available within our Group.\n\nPersonal data collected will be used for recruitment purpose only and will be treated in accordance with the Bank\u2019s Personal Information Collection Statement, a copy of which has been available in the Bank\u2019s career website.", "employment_types": ["Full Time", "Permanent"], "selling_points": [], "locations": ["Not Specified"], "categories": ["Banking / Finance", "Retail Banking", "Others", "Order Processing & Operation / Settlement"], "post_time": "2022-01-15T03:49:04Z", "salary": {"currency": null, "max": null, "min": null, "period": null, "term": null}, "salary_visible": false, "title_keywords": ["officer"], "responsibilities": ["obtain disposal instruction", "trace problematic payment orders", "operations", "a timely manner", "transactions", "fx position control", "incoming and outgoing swift payments", "aml screening", "banking", "support the team"], "requirements": {"degrees": ["secondary education"], "majors": [], "languages": [], "language_level": [], "hard_skills": ["typewriting", "pc applications", "ms excel", "incoming and outgoing swift payments", "aml screening", "swift"], "soft_skills": ["outgoing", "timely"], "languages_combined": []}, "experience_required": {"duration": ["at least 3 years", "at least 5 years"], "field": ["related", "banking", "education"]}}, {"job_id": "100003009050290", "location_code": "hk", "company": "Nanyang Commercial Bank", "job_title": "Relationship Manager \u2013 Cross Border Business (Ref: SC8020-CBB-JDB)", "description": "Explore cross-border business opportunities and facilitate customer acquisition for the segment of Mainland customers. Identify and fulfil customer needs by providing thorough financial analysis. Initiate and implement strategies to promote a full range of banking services in achieving the business sales targets of the bank.\n\nRequirements:\n\n\nDegree holder with at least 3 years sales experience in consumer banking field; experience in cross border business or segment business is preferential Experience in handling cross border business is preferred;\nPassed in LE 1, 7, 8 or equivalent, IIQE (Paper 1, 2, 3 & 5) and MPF Intermediaries Examination will be an advantage;\nSound knowledge towards investment market and various banking products;\nSales and customer-oriented with good communication skills;\nWith strong people network in Mainland;\nAbility to communicate with Chinese financial institution independently;\nOccasional business travel maybe required;\nProficient in both spoken and written English and Chinese, fluent in Putonghua is a must.\nIf you are flexible enough and zeal for a harmonious and supportive working environment where enables you to grow and succeed professionally, please send a full resume indicating your public examination results (HKCEE and HKALE / HKDSE), your present and expected salary and quoting reference number attention to\u00a0Talent Acquisition Division, Nanyang Commercial Bank, 151 Des Voeux Road Central, Hong Kong\u00a0or apply through email. For details, please visit\u00a0https://www.ncb.com.hk/\u00a0and select the page\u00a0Recruit.\n\n\nWe are an Equal Opportunities Employer. Data collected would be used for recruitment purposes only. Applicants who do not hear from us within 8 weeks may consider their applications unsuccessful and their data will be destroyed within 12 months of receipt.", "employment_types": ["Full Time", "Permanent"], "selling_points": ["Explore cross-border business opportunities", "Initiate and implement strategies", "At least 5 years relevant working experience"], "locations": ["Not Specified"], "categories": ["Banking / Finance", "Retail Banking", "Financial Services", "Wealth Management"], "post_time": "2022-01-15T03:50:57Z", "salary": {"currency": null, "max": null, "min": null, "period": "monthly", "term": null}, "salary_visible": false, "title_keywords": ["relationship manager"], "responsibilities": ["communicate with", "mpf", "data", "business opportunities", "financial analysis", "communication", "recruitment", "banking"], "requirements": {"degrees": ["hkdse", "degree holder"], "majors": [], "languages": ["putonghua", "english", "chinese"], "language_level": ["fluent", "proficient"], "hard_skills": ["financial analysis", "iiqe"], "soft_skills": ["flexible", "communication skills", "supportive", "independently", "harmonious", "customer-oriented", "thorough"], "languages_combined": [{"language": "putonghua", "language_level": ["fluent", "proficient"]}, {"language": "english", "language_level": ["fluent", "proficient"]}, {"language": "chinese", "language_level": ["fluent", "proficient"]}]}, "experience_required": {"duration": ["at least 3 years"], "field": ["business", "banking"]}}, {"job_id": "100003009049444", "location_code": "hk", "company": "OCBC Wing Hang Bank Limited", "job_title": "Senior Loan Processing Officer", "description": "Responsibilities\n\u200bPrepare all loan documents include offer letters, guarantee and charge forms etc. for corporate clients\nCheck the completeness and correctness of documents before loan disbursement and/or credit limits set-up\nLiaise with valuation / properties agents and follow up with the valuation reports\nHandle credit limit loading, loans disbursement, roll-over and settlement process\nHandle and supervise loans repayment & maintenance functions\nAssist in other ad hoc tasks as assigned\nRequirements\n\u200bDiploma or above\nMinimum 3 years\u2019 relevant experience in Banking industry\nFamiliar with credit administration or loans processing duties\nGood interpersonal and communication skills\nOutgoing, independent and self-motivated\n\nAttractive remuneration package will be offered to the right candidate. Please apply with full resume stating present & expected salary and contact phone number\u00a0to\u00a0The Human Resources Manager, 10/F, 161 Queen\u2019s Road Central, Hong Kong.\u00a0Please quote the reference.\n\nPersonal data collected will be used for recruitment purpose only. For more information, please visit our website:\u00a0http://www.ocbcwhhk.com.", "employment_types": ["Full Time", "Permanent"], "selling_points": ["Loan Processing", "Mortgage", "Back Office"], "locations": ["Shau Kei Wan"], "categories": ["Banking / Finance", "Loan", "Retail Banking", "Order Processing & Operation / Settlement"], "post_time": "2022-01-14T08:39:40Z", "salary": {"currency": null, "max": null, "min": null, "period": "monthly", "term": null}, "salary_visible": false, "title_keywords": ["officer"], "responsibilities": ["valuation", "maintenance", "settlement process", "letters", "ad hoc tasks", "reports", "liaise with"], "requirements": {"degrees": [], "majors": [], "languages": [], "language_level": [], "hard_skills": ["processing"], "soft_skills": ["outgoing", "communication skills", "self-motivated", "independent", "interpersonal"], "languages_combined": []}, "experience_required": {"duration": ["minimum 3 years"], "field": ["banking industry", "relevant experience"]}}, {"job_id": "100003009047776", "location_code": "hk", "company": "Public Bank (Hong Kong) Ltd", "job_title": "Assistant Manager - Remittance & Settlement", "description": "Ensure all payments/receipts are properly settled on a timely manner\nFamiliar with payment processing, settlement and clearing systems such as CMU, CLEARSTREAM, etc.\nAssist to supervise day-to-day work of remittance & settlement.\nCaution list checking at AML system for all payments/receipts.\nCheck and approve SWIFT/SWIFTNet messages, G/L batch, Inward and Outward Remittances.\nTrace problematic payment orders from Correspondent Banks as well as to follow up outstanding and irregular transactions.\nCheck and prepare daily reports, monthly reports and AML reports.\nCheck FX/MM settlement confirmation /contract/ SWIFT and SWIFTNet messages.\nPerform FX/MM Settlement, G/L batch/RTGS transactions verification and data maintenance.\nHandle enquires from other banks related to FX/MM transactions, Debts Securities, FRCD issue.\nPerform limit control on counter parties and FX position control on Treasury.\nSecondary education or above with at least 5 years relevant experience.\nTo apply, interested parties please follow the application methods available in the Bank\u2019s career website https://www.publicbank.com.hk/en/aboutus/careeropportunities. You can send us your resume quoting our job reference number together with present & expected salary (a must) to the Human Resources Department by email or fax at 2815 3157 or by post to Human Resources Department, 12/F, Public Bank Centre, 120 Des Voeux Road Central, Hong Kong. You may also visit our career website for other career opportunities available within our Group.\n\nPersonal data collected will be used for recruitment purpose only and will be treated in accordance with the Bank\u2019s Personal Information Collection Statement, a copy of which has been available in the Bank\u2019s career website.", "employment_types": ["Full Time", "Permanent"], "selling_points": [], "locations": ["Not Specified"], "categories": ["Banking / Finance", "Retail Banking", "Others", "Order Processing & Operation / Settlement"], "post_time": "2022-01-15T03:49:08Z", "salary": {"currency": null, "max": null, "min": null, "period": null, "term": null}, "salary_visible": false, "title_keywords": ["assistant manager"], "responsibilities": ["control", "aml", "receipts", "maintenance", "monthly reports", "data", "systems", "a timely manner", "checking", "transactions", "fx position control", "payment", "payments", "inward and outward remittances", "reports", "daily reports", "trace problematic payment orders"], "requirements": {"degrees": ["secondary education"], "majors": [], "languages": [], "language_level": [], "hard_skills": ["aml", "maintenance", "batch", "swift", "processing"], "soft_skills": ["timely"], "languages_combined": []}, "experience_required": {"duration": ["at least 5 years"], "field": ["relevant experience", "education"]}}, {"job_id": "100003009050164", "location_code": "hk", "company": "Nanyang Commercial Bank", "job_title": "Economist (Ref: LB8003-00-JDB)", "description": "Write research reports and give presentations on macroeconomics and financial markets, provide forecasts of economic and financial markets indicators, concisely\u00a0 answer media\u2019s questions on economic issues, compile and analyze industry intelligence.\n\nRequirements:\n\nMaster\u2019s degree or above in Economics;\nAt least 3 years of experience in economic research, preferably in the banking sector;\nExcellent analytical and presentation skills;\nA critical thinker willing to challenge mainstream views;\nGood command of English, Chinese and Mandarin.\n\n\u00a0(Candidate with more experience will be considered as Senior Economist)\n\nIf you are flexible enough and zeal for a harmonious and supportive working environment where enables you to grow and succeed professionally, please send a full resume indicating your public examination results (HKCEE and HKALE / HKDSE), your present and expected salary and quoting reference number attention to\u00a0Talent Acquisition Division, Nanyang Commercial Bank, 151 Des Voeux Road Central, Hong Kong or apply through email. For details, please visit https://www.ncb.com.hk/ and select the page Recruit.\n\nWe are an Equal Opportunities Employer. Data collected would be used for recruitment purposes only. Applicants who do not hear from us within 8 weeks may consider their applications unsuccessful and their data will be destroyed within 12 months of receipt.", "employment_types": ["Full Time", "Permanent"], "selling_points": ["Write research reports on macroeconomics", "Provide forecasts for economic & financial markets", "Master\u2019s degree with at least 3 years relevant exp"], "locations": ["Central & Western Area"], "categories": ["Banking / Finance", "Analyst", "Retail Banking", "Equities / Capital Markets"], "post_time": "2022-01-15T03:50:52Z", "salary": {"currency": null, "max": null, "min": null, "period": "monthly", "term": null}, "salary_visible": false, "title_keywords": ["economist"], "responsibilities": ["data", "presentations", "recruitment", "reports", "banking"], "requirements": {"degrees": ["degree or above", "hkdse", "master"], "majors": ["economics"], "languages": ["english", "chinese", "mandarin"], "language_level": ["good command"], "hard_skills": ["presentations"], "soft_skills": ["flexible", "supportive", "presentation skills", "harmonious"], "languages_combined": [{"language": "english", "language_level": ["good command"]}, {"language": "chinese", "language_level": ["good command"]}, {"language": "mandarin", "language_level": ["good command"]}]}, "experience_required": {"duration": ["at least 3 years"], "field": ["research", "banking sector"]}}, {"job_id": "100003009039407", "location_code": "hk", "company": "CMB Wing Lung Bank Limited", "job_title": "General Banking Officer", "description": "Responsibilities:\n\nDeliver quality services to customers\nStrengthen relationship with customers to identify customers' needs and recommend appropriate financial services to meet their need so as to achieve business target\nParticipate in different promotion events\n\nRequirements:\n\nFresh graduate degree holder preferably in business related discipline or equivalent,\u00a0or Minimum 1 year' working experience in customer service\nGood communication and interpersonal skills\nExcellent command of spoken and written English and Chinese; fluency in Putonghua an advantage", "employment_types": ["Full Time", "Permanent"], "selling_points": ["Retail banking", "Customer Services", "Promote Bank's services"], "locations": ["Not Specified"], "categories": ["Banking / Finance", "Retail Banking"], "post_time": "2022-01-11T09:41:13Z", "salary": {"currency": null, "max": null, "min": null, "period": "monthly", "term": null}, "salary_visible": false, "title_keywords": ["officer"], "responsibilities": ["quality", "customers' needs"], "requirements": {"degrees": ["fresh graduate", "degree holder"], "majors": ["business"], "languages": ["putonghua", "english", "chinese"], "language_level": ["fluency", "advantage", "excellent"], "hard_skills": [], "soft_skills": ["customer service", "communication and interpersonal skills"], "languages_combined": [{"language": "putonghua", "language_level": ["fluency", "advantage"]}, {"language": "english", "language_level": ["excellent"]}, {"language": "chinese", "language_level": ["excellent"]}]}, "experience_required": {"duration": ["minimum 1 year"], "field": ["related", "business", "customer service"]}}, {"job_id": "100003009046309", "location_code": "hk", "company": "China Taiping Life Insurance (Hong Kong) Company Limited", "job_title": "Officer / Senior Officer, Bancassurance", "description": "Responsibilities\n\u5de5\u4f5c\u8303\u56f4\uff1a\n\n\nAssist in developing insurance research and product performance analysis\nAssist in bank channel business exploration and promotion\nAssist in providing all levels of sales support; build up and maintain solid relationship with key stakeholders of bank partners\nResponsible for the preparation of different kinds of report for management review\u00a0\nAssist in any ad-hoc projects as assigned\n\u5904\u7406\u65e5\u5e38\u6587\u6863\u4ea4\u63a5\uff0c\u8d77\u8349\u516c\u6587\n\u534f\u52a9\u7edf\u8ba1\u6570\u636e\u3001\u5236\u4f5c\u5206\u6790\u62a5\u544a\n\u00a0\u534f\u52a9\u8ddf\u8fdb\u95ee\u9898\u4ef6\u540e\u7eed\u5de5\u4f5c\n\u534f\u52a9\u89e3\u7b54\u6e20\u9053\u65e5\u5e38\u67e5\u627e\n\u5904\u7406\u4e0a\u7ea7\u5206\u914d\u4e13\u9879\u5de5\u4f5c\n\nRequirements\n\u5165\u804c\u8981\u6c42\uff1a\n\n\nBachelor\u2019s degree or above\nRelevant experience in insurance industry will be an advantage\nGood in MS Office and Chinese Word processing\nExcellent communication skills in both English and Chinese (Cantonese and Mandarin), fluent Mandarin will be an advantage\n\u5927\u5b66\u6216\u4ee5\u4e0a\n\u6709\u5fd7\u4ece\u4e8b\u4fdd\u9669\u5de5\u4f5c\uff0c\u6709\u4fdd\u9669\u884c\u4e1a\u5de5\u4f5c\u7ecf\u9a8c\u8005\u4f18\u5148\u8003\u8651\n\u5177\u5907\u4e00\u5b9a\u7684\u516c\u6587\u5199\u4f5c\u80fd\u529b\uff0c\u5bcc\u6709\u6587\u5b57\u5904\u7406\u80fd\u529b (Word/Excel/Powerpoint)\n\u4f18\u826f\u8bed\u8a00\u80fd\u529b(\u80fd\u64cd\u6d41\u5229\u666e\u901a\u8bdd\u4f18\u5148)\n\n\u8bf7\u4ee5\u4e2d\u82f1\u53cc\u8bed\u7b80\u5386\u6295\u9012\n\nCandidate with less experience will be considered as Officer,\u00a0Bancassurance\n\n\nApplication\nInterested parties please send a detailed resume, stating current and expected salary to Human Resources Department.\n\nInformation supplied will be treated in strict confidence and used in accordance with the Personal Data (Privacy) Ordinance. Applicants not invited for interview within 6 weeks may consider their applications unsuccessful.", "employment_types": ["Full Time", "Permanent"], "selling_points": ["Insurance product performance analysis", "Bank channel business exploration and promotion", "Attractive remuneration package"], "locations": ["Causeway Bay"], "categories": ["Banking / Finance", "Private Banking", "Retail Banking", "Wealth Management"], "post_time": "2022-01-13T10:25:04Z", "salary": {"currency": null, "max": null, "min": null, "period": "monthly", "term": null}, "salary_visible": false, "title_keywords": ["officer", "senior officer"], "responsibilities": ["analysis", "developing", "maintain", "ad-hoc projects", "insurance", "management review", "report"], "requirements": {"degrees": ["degree or above", "bachelor"], "majors": [], "languages": ["cantonese", "english", "chinese", "mandarin"], "language_level": ["advantage", "fluent", "excellent", "good"], "hard_skills": ["excel", "chinese word processing", "word", "powerpoint", "ms office"], "soft_skills": ["communication skills"], "languages_combined": [{"language": "cantonese", "language_level": ["fluent", "excellent"]}, {"language": "english", "language_level": ["advantage", "fluent", "excellent"]}, {"language": "chinese", "language_level": ["advantage", "fluent", "excellent", "good"]}, {"language": "mandarin", "language_level": ["fluent", "excellent"]}]}, "experience_required": {"duration": [], "field": ["relevant experience", "insurance industry"]}}, {"job_id": "100003009048616", "location_code": "hk", "company": "Bank of China (Hong Kong) Limited", "job_title": "Customer Analytics & Data Science Manager  (MIS & Modeling)", "description": "Responsibilities:\nPerform customer segmentation and profile analysis through advanced statistical modeling / data mining / AI & ML technologies to provide insight for segment strategy and identify business opportunities\nDevelop and enhance propensity / predictive models to support CRM strategies related to change of customer behavior or specific event trigger, eg. customer acquisition, upgrade and retention\nCompile MIS reports and conduct analysis across customer, product and channel perspectives to identify potential customer and deliver actionable insights and recommendations to business units for developing portfolio and product strategy\nAssist business units in applying propensity / predictive model and customer segmentation model in marketing campaign to drive business performance, evaluate and enhance model effectiveness to improve campaign efficiency\nDevelop and enhance MIS report automation to help improve campaign efficiency\nRequirements:\nDegree or above with major in quantitative, numerical science or related discipline\n3+ years' experience relating to data analytics\nProficiency in SAS, Python, R or similar analytically oriented programming languages,\u00a0 experience in model development covering segmentation, acquisition, attrition, cross-selling and related applications\nExperience in Banking, Financial Services or FinTech industry preferred\nA mature self-starter with strong drive, motivation, committed with good business sense and strong understanding of the personal banking market\nExcellent interpersonal and communication skills with excellent written and spoken English and Chinese, knowledge of Mandarin would be a definite advantage\nLess experience will be considered as our Deputy/Assistant Customer Analytics & Data Science Manager", "employment_types": ["Full Time"], "selling_points": ["statistical modeling", "data mining", "AI & ML"], "locations": ["Central"], "categories": ["Banking / Finance", "Retail Banking"], "post_time": "2022-01-14T06:54:30Z", "salary": {"currency": null, "max": null, "min": null, "period": "monthly", "term": null}, "salary_visible": false, "title_keywords": ["manager"], "responsibilities": ["predictive models", "identify business opportunities", "analysis", "developing", "develop", "evaluate", "reports", "data mining", "report"], "requirements": {"degrees": ["degree or above"], "majors": ["science"], "languages": ["english", "chinese", "mandarin"], "language_level": ["advantage", "excellent"], "hard_skills": ["sas", "data analytics", "programming", "python", "r"], "soft_skills": ["communication skills", "business sense", "mature", "committed", "interpersonal"], "languages_combined": [{"language": "english", "language_level": ["advantage", "excellent"]}, {"language": "chinese", "language_level": ["advantage", "excellent"]}, {"language": "mandarin", "language_level": ["advantage", "excellent"]}]}, "experience_required": {"duration": ["3+ years"], "field": ["related", "development", "financial services", "programming", "banking"]}}, {"job_id": "100003009043313", "location_code": "hk", "company": "KEK Consultancy Company Limited", "job_title": "Senior Officer \u2013 Operations  (23K, Overseas Bank) \u2013 Ref. 1112", "description": "One of our clients (an overseas bank) is now looking for a high calibre candidate to fill the following positions:\n\n2 years or above related experience;\nExperience/ knowledge of KYC, AML regulations, Swift Alliance, RTGS payments, Nostro Reconciliation;\nHandle inward/ outward cheque clearing and remittance transactions;\nMonitor account openings and servicing transactions;\nGood command of English and Chinese (Cantonese & Mandarin).\n\nRemarks:\n\nMonthly salary: Basic up to HK$23K + discretionary bonus;\n5-day work;\nWorking location: Tsim Sha Tsui / Jordan;\nGood fringe benefits: Banking holidays, dental, medical (including spouse), 22-day annual leave, etc.\n\n\nIf the above position is not suitable for you, please also feel free to send your CV to us for our job matching.\n\nInterested parties please click \"APPLY NOW\"\u00a0or send to\u00a0OUR EMAIL\u00a0and attach your updated resume with expected salary in \"MS WORD\" format.\n\nPlease quote the\u00a0Job Ref. No.\u00a0and\u00a0Applied Post\u00a0on the subject of your application.\n\nInterest to know our candidates' and clients' comments about our service? Please click\u00a0HERE.\n\nCompany website:\u00a0www.kek.com.hk\n\nThe information provided will only be used for recruitment related purposes.", "employment_types": ["Full Time", "Permanent"], "selling_points": ["5-day work", "Medical (including spouse), 22 days AL", "KYC, RTGS payment, Nostro Reconciliation"], "locations": ["Tsim Sha Tsui"], "categories": ["Banking / Finance", "Corporate Banking", "Retail Banking", "Order Processing & Operation / Settlement"], "post_time": "2022-01-12T10:40:31Z", "salary": {"currency": null, "max": null, "min": null, "period": "monthly", "term": null}, "salary_visible": false, "title_keywords": ["senior officer", "operations"], "responsibilities": ["regulations", "aml", "monitor", "transactions", "payments", "kyc"], "requirements": {"degrees": [], "majors": [], "languages": ["cantonese", "english", "chinese", "mandarin"], "language_level": ["good command"], "hard_skills": ["swift", "basic", "aml", "kyc"], "soft_skills": [], "languages_combined": [{"language": "cantonese", "language_level": ["good command"]}, {"language": "english", "language_level": ["good command"]}, {"language": "chinese", "language_level": ["good command"]}, {"language": "mandarin", "language_level": ["good command"]}]}, "experience_required": {"duration": ["2 years"], "field": ["related"]}}, {"job_id": "100003009053252", "location_code": "hk", "company": "Dah Sing Financial Group", "job_title": "Assistant Manager, Segment & Transaction Capabilities", "description": "In this role, you will assist the Manager / Senior Manager to identify valuable partners and grow retail banking business by coordinating channels and bank\u2019s units, to formulate and launch effective marketing campaigns to deliver business targets.\nMain Responsibilities:\nExecute effective business development strategies and marketing plans to achieve bank\u2019s business objective\nAssist to design, plan and implement end-to-end sales and marketing campaigns for driving the acquisition and portfolio growth for YOU Banking segment and characters accounts\nAssist to acquire new customers, grow CASA balance and enhance product cross-selling and transaction capabilities in order to maximize the profitability of the segment\nWork closely with all internal departments to grain their support for smooth program launch and fulfilment\nAssess and incorporate latest regulatory and compliance requirement in execution\nProactively analyze competitors\u2019 business and marketing activities to understand market trend\nMonitor campaign response and prepare the program result tracking\nBudget and expenses management (including invoice settlement)\nAssist to conduct regular sales performance review\nTo meet the challenge, you should have the following qualifications an attributes:\nDegree holder or above in Business Administration, Marketing or related disciplines\n5 years of experience in retail banking business, exposure to branch operation, segment management and transactions capabilities such as ATM and FPS is preferable\nKnowledge in overall banking products, operation & process flow, marketing activities, segment management and management skill\nGood communication & interpersonal skill, analytical and track record of effective marketing campaigns is an advantage\nGood team player and detail oriented\nAble to work under pressure and tight schedule\nGood command of both written and spoken English and Chinese\nPlease note that only shortlisted candidates will be notified.", "employment_types": ["Full Time", "Permanent"], "selling_points": ["Identify valuable partners and grow business", "Formulate and launch marketing campaigns", "5 years of experience in retail banking"], "locations": ["Wan Chai"], "categories": ["Banking / Finance", "Retail Banking", "Others", "Marketing / Public Relations", "Marketing - Brand / Product Management"], "post_time": "2022-01-17T06:32:33Z", "salary": {"currency": null, "max": null, "min": null, "period": "monthly", "term": null}, "salary_visible": false, "title_keywords": ["assistant manager,"], "responsibilities": ["marketing plans", "budget", "design", "transactions", "communication", "plan", "administration", "work under pressure", "sales performance", "compliance", "monitor", "expenses", "schedule", "marketing campaigns", "banking", "management", "invoice", "review", "tracking"], "requirements": {"degrees": ["degree holder"], "majors": ["related disciplines", "marketing", "business administration"], "languages": ["english", "chinese"], "language_level": ["good command"], "hard_skills": [], "soft_skills": ["good team player", "detail oriented", "interpersonal skill", "communication", "smooth", "work under pressure"], "languages_combined": [{"language": "english", "language_level": ["good command"]}, {"language": "chinese", "language_level": ["good command"]}]}, "experience_required": {"duration": ["5 years"], "field": ["operation", "retail banking", "business", "management"]}}, {"job_id": "100003009038672", "location_code": "hk", "company": "Hang Seng Bank Ltd", "job_title": "Request for Information and Customer Due Diligence Officer", "description": "Customer Contact Centre\n\nHang Seng's Customer Contact Centre has been ranked one of the best phone banking service providers for consecutive years. Our team strives to provide professional services for a wide range of banking products to address customers' different services and financial needs.\n\nWe are currently seeking high caliber professionals to join our department as\u00a0Request for Information and Customer Due Diligence Officer.\n\u00a0\n\nPrincipal Responsibilities\n\nReview RFI and Customer Due Diligence (CDD) requests received and devise the best contact approach to engage customer for information collection\nConduct outbound calls to collect customer information and respective supporting documents for RFI requests and CDD projects\nWork on and manage RFI and CDD process from end-to-end and to assure that it meets the Group requirements as well as the compliance and regulatory standards\nFulfill the hotline service standards (SLA) and quality monitoring requirements\nParticipate in ad-hoc projects and assignments as instructed by the superiors\n\u00a0\nRequirements\nUniversity Degree / Diploma in related discipline with relevant experience and professional qualifications\nPasses in Hong Kong Securities and Investment (HKSI) Paper 1, 7 and 8 a MUST\u00a0\nMinimum 1 years' retail banking experience, preferably with exposure to retail banking business and knowledge of related regulatory requirements and guidelines as well as experience in conduct outbound customer calls\nStrong attentiveness to detail, compliance and control orientation\nStrong customer service orientation with good communication and interpersonal skills\nStrong PC skills, such as MS Excel and Word will be an advantage\nProficiency in both English and Chinese, and fluency in Putonghua an advantage\nGreat sense of ownership and servicing mindset to ensure efficient and effective customer service processes\n\nIf you would like to explore other opportunities at Hang Seng Hong Kong, please visit www.hangseng.com/careers/ for details.\nThe health and safety of our employees and candidates is very important to us. Due to the current situation related to the Novel Coronavirus (2019-nCoV), we\u2019re leveraging our digital capabilities to ensure we can continue to recruit top talent at the HSBC Group. \u00a0As your application progresses, you may be asked to use one of our digital tools to help you through your recruitment journey.\u00a0 If so, one of our Resourcing colleagues will explain how our video-interviewing technology will be used throughout the recruitment process and will be on hand to answer any questions you might have.\nAll information provided by applicants will be used only for recruitment purposes and will be used strictly in accordance with the Bank's personal data policies, a copy of which may be obtained by the applicant upon request. Unless otherwise instructed in writing by the applicant concerned, applicants may be considered for other suitable positions within the Bank and its related companies. The personal data of unsuccessful job applicants may be retained for a maximum of two years from the date when the job application is rejected and such data may be retained for a longer period if there is a subsisting reason that obliges the Bank to do so, after which the personal data will be destroyed.", "employment_types": ["Full Time", "Permanent"], "selling_points": [], "locations": ["Not Specified"], "categories": ["Banking / Finance", "Retail Banking"], "post_time": "2022-01-11T07:37:17Z", "salary": {"currency": null, "max": null, "min": null, "period": "monthly", "term": null}, "salary_visible": false, "title_keywords": ["officer"], "responsibilities": ["cdd", "review", "compliance", "quality", "monitoring", "customer due diligence", "service standards", "contact", "ad-hoc projects"], "requirements": {"degrees": ["university degree", "diploma"], "majors": [], "languages": ["putonghua", "english", "chinese"], "language_level": ["fluency", "advantage", "proficiency"], "hard_skills": ["hksi", "professional qualifications", "word", "reason", "ms excel", "pc skills"], "soft_skills": ["efficient", "novel", "customer service", "communication and interpersonal skills"], "languages_combined": [{"language": "putonghua", "language_level": ["advantage"]}, {"language": "english", "language_level": ["proficiency", "fluency"]}, {"language": "chinese", "language_level": ["proficiency", "fluency"]}]}, "experience_required": {"duration": ["minimum 1 years"], "field": ["related", "retail banking", "business", "relevant experience"]}}, {"job_id": "100003009050266", "location_code": "hk", "company": "China Construction Bank (Asia) Corporation Limited", "job_title": "Bank Hall Ambassador, Consumer Banking", "description": "Job Description:\n\n\n\nGreet and welcome all walk-in customers. To act as the first contact point of customers in a warm and caring manner to ensure their journey satisfactory\nTo understand customers' needs and re-direct customer traffic to ensure pleasant customer journey\nProvide guidance to customers on Branch self-serve devices\nPromote and cross-sell general banking products and e-banking platform and services\nPromote and drive the usage of e-Banking and digital channel\nHandle general enquiries / complaints and resolve issues; drive fast and accurate transaction processing to serve customers in accordance with standard procedures\n\nRequirements:\n\n\n5 subjects at Grade E / Level 2 or above in HKCEE/HKDSE, including Chinese, English and Mathematics\nMinimum 1 year relevant sales and customer service experience\nCustomer centric servicing mind set and excellent communication skills\nA proactive team player with good interpersonal skills\nGood command of Cantonese, Mandarin and English\n\n\u00a0Applicants who are not contacted within 8 weeks may consider their applications unsuccessful and their personal data will be retained by the bank for a period up to two years.\n\nAll information provided by applicants will be used for recruitment purposes only and will be used strictly in accordance with the bank\u2019s personal data policies, a copy of which will be provided upon request.", "employment_types": ["Full Time", "Permanent"], "selling_points": ["Customer Service in Consumer Branch", "Customer centric servicing", "Excellent communication skills"], "locations": ["Not Specified"], "categories": ["Banking / Finance", "Retail Banking", "Others"], "post_time": "2022-01-14T10:03:18Z", "salary": {"currency": null, "max": null, "min": null, "period": "monthly", "term": null}, "salary_visible": false, "title_keywords": [], "responsibilities": ["customers' needs", "procedures", "banking", "contact", "transaction processing", "provide guidance"], "requirements": {"degrees": ["hkdse"], "majors": ["mathematics"], "languages": ["cantonese", "english", "chinese", "mandarin"], "language_level": ["good command"], "hard_skills": [], "soft_skills": ["communication skills", "customer service", "interpersonal skills", "team player", "proactive"], "languages_combined": [{"language": "cantonese", "language_level": ["good command"]}, {"language": "english", "language_level": ["good command"]}, {"language": "chinese", "language_level": []}, {"language": "mandarin", "language_level": ["good command"]}]}, "experience_required": {"duration": ["minimum 1 year"], "field": ["customer service"]}}, {"job_id": "100003009049219", "location_code": "hk", "company": "Shanghai Commercial Bank Ltd", "job_title": "Assistant Vice President - Investment & Insurance Sales Management", "description": "Responsibilities:\n\nPerform as a product expert in wealth management to support cluster branches in achieving both investment and insurance targets\nUplift performance of Relationship Managers by providing marketing information, advices, personal coaching and demonstration at sales interviews\nWork closely with Branch Managers and assist Relationship Managers to review and monitor customers' portfolio and identify potential business opportunities\nConduct joint calls and close deals, if necessary\nCoach and monitor good business practice and uphold regulated sales compliance of sales force\nParticipate in regular product/ sales compliance meeting and conduct regular meeting/ coaching workshops with staff as and when appropriate\n\nRequirements\n\nDegree holder in Finance, Business, Economics or related disciplines; with CFP / CRWP preferred\nMinimum 8 years of retail banking sales experience with at least 3 years in investment/insurance specialist and/or branch sales management positions\nExperience in coaching front-line salespeople is necessary\nSolid product and market knowledge in both investment and insurance products\nStrong communication and interpersonal skills\nGood command of spoken and written English and Chinese\nQualified individual to carry out regulated activities in investment and insurance\n\nAttractive remuneration package will be offered to the right candidates. Interested parties please click \"Apply Now\" to submit your full resume with current and expected salary to the Human Resources Division.\n\nPlease visit us at www.shacombank.com.hk for more information about our Bank.\n\nAll personal data collected will be used for recruitment related purposes strictly in accordance with the Bank's personal data policies, a copy of which will be provided immediately upon request by contacting our Personal Data Compliance Officer. Applicants who are not contacted within two months may consider their applications unsuccessful and the personal data collected from the applicants will be retained for no longer than two years from the date of rejection during which the applicants may be considered for other suitable positions within the Bank.", "employment_types": ["Full Time", "Permanent"], "selling_points": ["Perform as a product expert in wealth management", "Uplift performance of Relationship Managers", "Assist RMs to review&monitor customers' portfolio"], "locations": ["Central"], "categories": ["Banking / Finance", "Investment", "Retail Banking", "Others"], "post_time": "2022-01-15T03:50:13Z", "salary": {"currency": null, "max": null, "min": null, "period": "monthly", "term": null}, "salary_visible": false, "title_keywords": ["sales", "assistant vice president"], "responsibilities": ["management", "business opportunities", "review", "monitor", "compliance", "insurance"], "requirements": {"degrees": ["degree holder"], "majors": ["related disciplines", "finance", "business", "economics"], "languages": ["english", "chinese"], "language_level": ["good command"], "hard_skills": [], "soft_skills": ["communication and interpersonal skills"], "languages_combined": [{"language": "english", "language_level": ["good command"]}, {"language": "chinese", "language_level": ["good command"]}]}, "experience_required": {"duration": ["at least 3 years", "minimum 8 years"], "field": ["retail banking", "insurance", "investment", "management"]}}, {"job_id": "100003009047767", "location_code": "hk", "company": "Public Bank (Hong Kong) Ltd", "job_title": "Clerk - Branch Administration (Ref: JD-SBAC)", "description": "Provide general administrative support and perform a variety of clerical duties\nPrepare regular reports for senior management\nProvide support to ad hoc projects when required\nSecondary education level with minimum 1 year of relevant experience in banking industry\nGood communication skills in both English and Chinese\nGood interpersonal and coordination skills\nAble to work independently and under pressure\nProficient in MS Office applications (MS Word, Excel and Outlook)\u00a0\u00a0\n\nTo apply, interested parties please follow the application methods available in the Bank\u2019s career website\u00a0https://www.publicbank.com.hk/en/aboutus/careeropportunities. You can send us your resume quoting our job reference number together with present &\u00a0expected salary (a must)\u00a0to the Human Resources Department by email or fax at\u00a02815 3157\u00a0or by post to\u00a0Human Resources Department, 12/F, Public Bank Centre, 120 Des Voeux Road Central, Hong Kong. You may also visit our career website for other career opportunities available within our Group.\n\nPersonal data collected will be used for recruitment purpose only and will be treated in accordance with the Bank\u2019s Personal Information Collection Statement, a copy of which has been available in the Bank\u2019s career website.", "employment_types": ["Full Time", "Permanent"], "selling_points": [], "locations": ["Not Specified"], "categories": ["Admin & HR", "Clerical / Admin Staff", "Banking / Finance", "Retail Banking", "Others"], "post_time": "2022-01-15T03:49:06Z", "salary": {"currency": null, "max": null, "min": null, "period": null, "term": null}, "salary_visible": false, "title_keywords": ["clerk"], "responsibilities": ["provide support", "general administrative support", "communication", "ad hoc projects", "reports", "coordination", "banking", "senior management"], "requirements": {"degrees": ["secondary education"], "majors": [], "languages": ["english", "chinese"], "language_level": ["good"], "hard_skills": ["ms word", "excel", "outlook", "ms office"], "soft_skills": ["communication skills", "work independently", "under pressure", "coordination skills", "interpersonal"], "languages_combined": [{"language": "english", "language_level": ["good"]}, {"language": "chinese", "language_level": ["good"]}]}, "experience_required": {"duration": ["minimum 1 year"], "field": ["banking industry", "relevant experience", "education"]}}, {"job_id": "100003009049886", "location_code": "hk", "company": "Waion Solutions Limited", "job_title": "Customer Service Officer - SME and Personal Loan Banking (Ref: 11892)", "description": "Summary:\nOur client is a large-scale MNC bank. They're currently hiring Assistant Officers, to support their administration and wealth management back office operations. We hope to gather talents here and offer the opportunity to generate remarkable results together.\n\nResponsibilities:\n\nProvide daily customer services backup and center operational support, load operations data entry\nProvide admin support to Small Enterprise (SME) and Personal Load Center\nHandle customer enquiries\nPerform KYC support duties, prepare and file reports\nEnsure compliance with regulatory requirements as well as internal compliance policies and guidelines\nAny ad-hoc projects as assigned\u00a0\n\nRequirements:\n\nDSE graduate / High Diploma or above\u00a0\nCandidates with prior experience in customer service preferred\nExperience in loan operation would be a great advantage\nIndependent, responsible\u00a0and self-motivated\nGood analytical and problem-solving skills\u00a0\nStrong PC skills and proficient in MS application, and Chinese Word Processing\nGood communication skills of both written and spoken English and Chinese\u00a0\nIf you have the desire for a challenging and rewarding career development, send us your resume quoting your present and expected salary\n\nby clicking\u00a0\"Apply Now\"\u00a0\n* Information collected will only be used for recruitment purpose *", "employment_types": ["Full Time", "Contract"], "selling_points": ["Banking Customer Service", "Handle customer inquiries", "5 days work week, Medical, Bank holidays"], "locations": ["Mong Kok"], "categories": ["Banking / Finance", "Loan", "Private Banking", "Retail Banking"], "post_time": "2022-01-14T09:32:58Z", "salary": {"currency": null, "max": null, "min": null, "period": "monthly", "term": null}, "salary_visible": false, "title_keywords": ["personal", "customer service officer"], "responsibilities": ["operational support", "handle customer enquiries", "data entry", "guidelines", "operations", "regulatory requirements", "compliance", "policies", "customer services", "ensure compliance", "admin support", "reports", "kyc", "sme", "ad-hoc projects"], "requirements": {"degrees": ["high diploma or above", "dse"], "majors": [], "languages": ["english", "chinese"], "language_level": ["good", "proficient"], "hard_skills": ["problem-solving skills", "pc skills", "chinese word processing", "ms application"], "soft_skills": ["communication skills", "self-motivated", "independent", "responsible", "customer service", "problem-solving skills"], "languages_combined": [{"language": "english", "language_level": ["good"]}, {"language": "chinese", "language_level": ["good", "proficient"]}]}, "experience_required": {"duration": [], "field": ["operation", "customer service"]}}, {"job_id": "100003009049832", "location_code": "hk", "company": "Zebra Strategic Outsource Solution Ltd", "job_title": "Operations Support Specialist (AML/KYC)", "description": "Responsibilities:\n\nPerform customer on-boarding, review for retail banking customers\nConduct customer CDD/KYC review, including Transaction Monitoring, Trigger Event Review, Periodic Review\nHandle AML assessment, such as name screening\nReview the integrity and authenticity document(s) submitted by customers\nConduct outreach call and follow up customers' inquiries\n\nRequirements:\n\n1-2 years relevant experience in banking industry or customer services\nKnowledge in CDD/KYC requirement, experience in transaction monitoring is preferable\nEnsure the tasks are done in a timely and correct manner\nGood command of both written and spoken in English and Chinese, fluent in Mandarin and Cantonese speaking\nStrong customer services mindset with problem solving skills\nGood team player, positive and energetic\n\nThis position will be under the employment of Zebra Strategic Outsource Solution Ltd.\nTo find out more about Zebra, visit us at\u00a0www.zebragroup.com\nAll personal data collected will be kept in strict confidence and would only be used for recruitment purpose.", "employment_types": ["Full Time", "Contract"], "selling_points": [], "locations": ["Southern Area"], "categories": ["Banking / Finance", "Retail Banking", "Others", "Order Processing & Operation / Settlement"], "post_time": "2022-01-14T09:18:08Z", "salary": {"currency": null, "max": null, "min": null, "period": "monthly", "term": null}, "salary_visible": false, "title_keywords": ["specialist", "operations"], "responsibilities": ["aml", "cdd", "monitoring", "review", "customers' inquiries", "banking", "kyc review"], "requirements": {"degrees": [], "majors": [], "languages": ["cantonese", "english", "chinese", "mandarin"], "language_level": ["good command", "fluent"], "hard_skills": ["cdd", "problem solving skills", "kyc"], "soft_skills": ["good team player", "confidence", "timely", "problem solving skills", "energetic", "positive"], "languages_combined": [{"language": "cantonese", "language_level": ["good command"]}, {"language": "english", "language_level": ["fluent", "good command"]}, {"language": "chinese", "language_level": ["fluent", "good command"]}, {"language": "mandarin", "language_level": ["good command"]}]}, "experience_required": {"duration": ["1-2 years"], "field": ["banking industry", "relevant experience", "customer services"]}}, {"job_id": "100003009053104", "location_code": "hk", "company": "OCBC Wing Hang Bank Limited", "job_title": "VP/AVP, Business Compliance, Corporate & Commercial Banking", "description": "Responsibilities\n\n\u200b- Coordinate internal and external audit examination and help to monitor the process on adopting the remediation measures as agreed\n- Actively monitor / drive various AML or compliance related projects and work closely with various stakeholders to ensure effective project implementation\n- Perform gap analysis and update policies and procedures for latest regulatory requirement\n- Provide advisory service to business units regarding AML / CFT / sanction compliance\n- Design and prepare regular compliance control or monitoring report\n- Formulate internal control measures and ensure they are properly followed\n\nRequirements\n\n\u200b- Bachelor degree in business or related disciplines, with Compliance related certifications (ECF-AML/CFT, ACAMS)\n- At least 10 years of relevant experience in Financial / Banking industries, with minimum 5 years specialized in compliance / audit / project management work is preferred\n- Strong knowledge of general banking operation\n- Well versed with banking and regulatory requirements\n- Self-motivated with strong initiative and attention to details\n- Able to handle multi-tasks independently and work under tight deadline\u00a0\u00a0\u00a0\u00a0\u00a0\u00a0\u00a0\u00a0\u00a0\u00a0\u00a0\u00a0\u00a0\u00a0\u00a0\u00a0\u00a0\u00a0\u00a0\u00a0\u00a0\n- Proficiency in both spoken and written English and Chinese\u00a0\u00a0\u00a0\n- A good team player with strong communication skills\n- Proficient in MS Office applications\n\n\n\nAttractive remuneration package will be offered to the right candidate. Please apply with full resume stating present & expected salary and contact phone number\u00a0to\u00a0The Human Resources Manager, 10/F, 161 Queen\u2019s Road Central, Hong Kong.\u00a0Please quote the reference.\n\nPersonal data collected will be used for recruitment purpose only. For more information, please visit our website:\u00a0http://www.ocbcwhhk.com.", "employment_types": ["Full Time", "Permanent"], "selling_points": ["Coordinate internal and external audit examination", "Actively monitor / drive various AML", "Perform gap analysis and update policies"], "locations": ["Sheung Wan"], "categories": ["Banking / Finance", "Corporate Banking", "Retail Banking", "Professional Services", "Legal & Compliance"], "post_time": "2022-01-17T05:51:49Z", "salary": {"currency": null, "max": null, "min": null, "period": "monthly", "term": null}, "salary_visible": false, "title_keywords": [], "responsibilities": ["control", "aml", "policies", "analysis", "compliance", "monitor", "audit", "implementation", "procedures", "coordinate", "design", "monitoring", "internal control", "report"], "requirements": {"degrees": ["degree", "bachelor"], "majors": ["related disciplines", "business"], "languages": ["english", "chinese"], "language_level": ["proficiency"], "hard_skills": ["aml", "project management", "cft", "acams", "ms office"], "soft_skills": ["communication skills", "self-motivated", "independently", "good team player", "multi-tasks", "project management", "attention to details", "initiative"], "languages_combined": [{"language": "english", "language_level": ["proficiency"]}, {"language": "chinese", "language_level": ["proficiency"]}]}, "experience_required": {"duration": ["at least 10 years", "minimum 5 years"], "field": ["compliance", "audit", "project management", "relevant experience", "banking", "financial"]}}, {"job_id": "100003009047543", "location_code": "hk", "company": "Wealth Dimensions Consultancy Limited", "job_title": "Relationship Manager Assistant  - Retail Banking", "description": "Our client\u00a0is leading bank in Hong Kong, and now looking for the High Calibre candidates to join their position of\u00a0Relationship Manager Assistant.\n\nResponsibilities :\n\nAssist the Senior Relationship Managers in making appointments with customers, handling customers\u2019 transaction instructions and post-sales follow-ups, providing clerical and back-end support\nAct as the assistant of Senior Relationship Managers by providing support in the aspects of customer relationship management, system operation, clerical and information preparation, transaction execution, filing and back-end support\nHandle the phone calls and reply the enquiries from customers on behalf of the Senior Relationship Managers\nVisit customers if needed to follow customers' transactions.\nAssist the Senior Relationship Managers in customer analysis, check the MIS reports and systems regularly\nHandle account opening, phone call and customer enquiries.\n\u00a0Requirements :\nTertiary education or above, with qualifications in IIQE & HKSI\nAt least 1 years\u2019 experience in retail banking industry\nFamiliar with banking products, operations, relevant policies and procedures\nFamiliar with investment, insurance, retail banking and financial service and relevant legal requirements\nSound communication and customer relationship management skills with positive attitude\nGood command of both verbal and written English and Chinese\nWe offer attractive remuneration package to successful candidates. Salaries will be commensurate with qualifications and experience.\nAll data collected will be used for recruitment purpose only & will be used strictly confidential", "employment_types": ["Full Time"], "selling_points": ["1+ years Working Experience in Retail Banking", "IIQE and HKSI Qualifications", "Supporting Role"], "locations": ["Not Specified"], "categories": ["Banking / Finance", "Retail Banking", "Others", "Wealth Management"], "post_time": "2022-01-14T03:25:23Z", "salary": {"currency": null, "max": null, "min": null, "period": "monthly", "term": null}, "salary_visible": false, "title_keywords": ["relationship manager", "assistant"], "responsibilities": ["management", "customer enquiries", "account opening", "analysis", "systems", "transactions", "reports", "providing support", "phone calls"], "requirements": {"degrees": [], "majors": [], "languages": ["english", "chinese"], "language_level": ["good command"], "hard_skills": ["iiqe", "hksi"], "soft_skills": ["communication", "positive attitude"], "languages_combined": [{"language": "english", "language_level": ["good command"]}, {"language": "chinese", "language_level": ["good command"]}]}, "experience_required": {"duration": ["at least 1 years"], "field": ["retail banking"]}}, {"job_id": "100003009050856", "location_code": "hk", "company": "China Construction Bank (Asia) Corporation Limited", "job_title": "AM, Customer ML Risk Assessment (1-year contract)", "description": "Main Responsibilities\n- Participate in CDD cases review (for corporate banking and/or retail banking ) for customer risk assessments with High risk factors which required AML Compliance concurrence.\n- Provide comments to front line to improve the KYC documents, and properly conduct risk scoring\n- Provide advices to the AML-related issues account opening and exceptional approval\n- Conduct EDD from internal database on the customers requesting concurrence\n- Handle risk assessment on reassessment or account opening cases\n- Assist to prepare AMLCC material\n- Ad-hoc project(s)/ task(s)\nRequirements\n- Degree holder or equivalent\n- Qualification in ECF is preferred\n- AML experience in financial institutions and/or regulatory bodies will be an advantage\n- Possession of good knowledge on banking operations, products and services will be an advantage\n- Self-motivated, independent with good communication and interpersonal skills\n- Good command of both spoken English and Chinese\n- Proficient in PC skills including MS Word and Excel\n- Attentive to details, compliance and control oriented, diligent and proactive\n\nCandidate will less experience will be considered for the post of Manager.\u00a0Please specify your current and expected package in your application for reference.\u00a0\n\nApplicants who are not contacted within 8 weeks may consider their applications unsuccessful and their personal data will be retained by the bank for a period up to two years.\n\nAll information provided by applicants will be used for recruitment purposes only and will be used strictly in accordance with the bank\u2019s personal data policies, a copy of which will be provided upon request.", "employment_types": ["Full Time", "Contract"], "selling_points": ["Banking Compliance exposure", "AML Compliance Governance", "Customer ML Risk Assessment"], "locations": ["Not Specified"], "categories": ["Banking / Finance", "Corporate Banking", "Retail Banking", "Professional Services", "Legal & Compliance"], "post_time": "2022-01-14T11:33:44Z", "salary": {"currency": null, "max": null, "min": null, "period": "monthly", "term": null}, "salary_visible": false, "title_keywords": [], "responsibilities": ["ad-hoc", "provide advices", "aml", "cdd", "kyc", "review", "compliance", "comments", "account opening", "database", "banking"], "requirements": {"degrees": ["degree holder"], "majors": [], "languages": ["english", "chinese"], "language_level": ["good command"], "hard_skills": ["excel", "pc skills", "aml", "ms word"], "soft_skills": ["self-motivated", "independent", "attentive to details", "diligent", "communication and interpersonal skills", "proactive"], "languages_combined": [{"language": "english", "language_level": ["good command"]}, {"language": "chinese", "language_level": ["good command"]}]}, "experience_required": {"duration": [], "field": ["financial institutions"]}}, {"job_id": "100003009049708", "location_code": "hk", "company": "Chiyu Banking Corp Ltd", "job_title": "Assistant Product Development Manager - Wealth Product", "description": "Responsibilities:\n\nMonitor and analyze the data and trend of products and services in order to enhance and optimize the product image and to maximize product profitability\nAnalyze and optimize the wealth management products workflow and system enhancement for improving customer experience and reducing operational risk\nIntegrate the market analysis and business forecast, generate ideas on product features development and recommend appropriate pricing strategy\nCoordinate with relevant departments/units to perform the products optimization\nConduct market competition analysis of insurance and investment products and prepare proposals for new products / product revamp\nReview and report business status, effectiveness of the marketing campaigns and business plans periodically\nParticipate in ad-hoc assignment as assigned\n\nRequirements:\n\nDegree or above in Business Administration or related disciplines\nMinimum 3 years of product management experience in Banking or Financial Industry\nQualifications of HKSI, IIQE & MPF\nStrong marketing sense and familiar with wealth products\nCreative, initiative with good communication skills\nProficient in MS Word, Excel and PowerPoint\nGood command of spoken and written English and Chinese (Cantonese & Mandarin)\n\n(Candidates with less experience will be considered as of Product Development Officer)\u00a0\n\n\nWe offer competitive packages and promising career opportunities to the right candidates. Please send your full resume with current salary, expected salary and the date of availability to\u00a0The Human Resources Department, Chiyu Banking Corporation Ltd, 12/F, Chiyu Bank Building, No. 78 Des Voeux Road Central, Hong Kong or fax to 2986-3233 or by clicking Apply Now.\n\n\nInformation provided will be treated in strict confidence and only be used for recruitment purposes. All personal data of unsuccessful applicants will be destroyed after the recruitment exercise. A copy of Personal Information Collection Statement is available upon request.", "employment_types": ["Full Time", "Permanent"], "selling_points": [], "locations": ["Central & Western Area"], "categories": ["Banking / Finance", "Investment", "Retail Banking", "Marketing / Public Relations", "Marketing - Brand / Product Management"], "post_time": "2022-01-14T09:07:52Z", "salary": {"currency": null, "max": null, "min": null, "period": "monthly", "term": null}, "salary_visible": false, "title_keywords": ["product development manager", "assistant"], "responsibilities": ["ad-hoc", "management", "revamp", "ideas", "data", "analysis", "review", "monitor", "coordinate with", "business plans", "market analysis", "forecast", "marketing campaigns", "insurance", "report"], "requirements": {"degrees": ["degree or above"], "majors": ["related disciplines", "business administration"], "languages": ["cantonese", "english", "chinese", "mandarin"], "language_level": ["good command"], "hard_skills": ["excel", "iiqe", "hksi", "powerpoint", "ms word"], "soft_skills": ["communication skills", "creative", "marketing sense", "initiative"], "languages_combined": [{"language": "cantonese", "language_level": ["good command"]}, {"language": "english", "language_level": ["good command"]}, {"language": "chinese", "language_level": ["good command"]}, {"language": "mandarin", "language_level": ["good command"]}]}, "experience_required": {"duration": ["minimum 3 years"], "field": ["product management", "product development", "financial industry", "banking"]}}, {"job_id": "100003009050331", "location_code": "hk", "company": "Nanyang Commercial Bank", "job_title": "Strategic Planning Manager - Segment Management (Ref: LD8041-SM-JDB)", "description": "Assist to formulate and implement personal customer segment strategies to achieve the business targets and improve customer experience. Design and monitor the implementation of segment business plans through initiatives / activities on acquisition, cross-selling, service upgrade, customer loyalty and retention, etc. Work with various internal and external stakeholders to meet customers\u2019 needs from a holistic perspective. Design appropriate sales tools to facilitate frontline to achieve the planned business targets and objectives. Collect and analyze data and feedbacks from time to time and make business recommendations for continuous improvement.\n\n\nRequirements:\n\nDegree or above with major in Business Administration, Marketing, Finance or related discipline;\nAt least 4 years working experience in banking industry; solid experience in customer management, marketing, or product management is preferred;\nFamiliar with banking products and operations / service enhancement is an advantage;\nA good team player with strong business acumen and analytical skills;\nExcellent communications and presentation skills;\nProficient in both spoken and written English and Chinese, fluent in Putonghua is preferable.\n\nIf you are flexible enough and zeal for a harmonious and supportive working environment where enables you to grow and succeed professionally, please send a full resume indicating your public examination results (HKCEE and HKALE / HKDSE), your present and expected salary and quoting reference number attention to Talent Acquisition Division, Nanyang Commercial Bank, 151 Des Voeux Road Central, Hong Kong or apply through email. For details, please visit https://www.ncb.com.hk/ and select the page Recruit.\n\nWe are an Equal Opportunities Employer. Data collected would be used for recruitment purposes only. Applicants who do not hear from us within 8 weeks may consider their applications unsuccessful and their data will be destroyed within 12 months of receipt.", "employment_types": ["Full Time", "Permanent"], "selling_points": ["Formulate personal customer segment strategies", "Design and monitor the implementation", "At least 4 years working experience"], "locations": ["Central"], "categories": ["Banking / Finance", "Retail Banking", "Others", "Marketing / Public Relations", "Marketing - Brand / Product Management"], "post_time": "2022-01-15T03:50:59Z", "salary": {"currency": null, "max": null, "min": null, "period": "monthly", "term": null}, "salary_visible": false, "title_keywords": ["manager"], "responsibilities": ["management", "data", "operations", "monitor", "implementation", "business plans", "design", "recruitment", "banking", "analyze data", "administration"], "requirements": {"degrees": ["degree or above", "hkdse"], "majors": ["finance", "marketing", "business administration"], "languages": ["putonghua", "english", "chinese"], "language_level": ["fluent", "proficient"], "hard_skills": ["make", "analytical skills", "acumen"], "soft_skills": ["flexible", "good team player", "supportive", "harmonious", "analytical skills", "presentation skills", "business acumen"], "languages_combined": [{"language": "putonghua", "language_level": ["fluent", "proficient"]}, {"language": "english", "language_level": ["fluent", "proficient"]}, {"language": "chinese", "language_level": ["fluent", "proficient"]}]}, "experience_required": {"duration": ["at least 4 years"], "field": ["banking industry", "management", "product management", "business", "marketing"]}}, {"job_id": "100003009039873", "location_code": "hk", "company": "Industrial and Commercial Bank of China (Asia) Limited", "job_title": "Transaction Processing Officer - Operations Management Department", "description": "Responsibilities:\n\nResponsible for handling daily operation of inward and outward clearing and returned items\nPerform CCASS operations\nRetrieve outward and inward clearing cheque copies for Branches and Business Centres\nPerform online banking transactions\nPerform ad-hoc duties as assigned by supervisors\nRequirements:\n\nDiploma or above\n2 years of relevant working experience in bank clearing or branch operation\nGood communication skills, independent and detail-minded\nProficient in MS Office such as Word and Excel\nGood command of spoken and written English and Chinese, including Putonghua", "employment_types": ["Permanent"], "selling_points": [], "locations": ["Kwun Tong"], "categories": ["Banking / Finance", "Retail Banking", "Order Processing & Operation / Settlement"], "post_time": "2022-01-11T13:07:59Z", "salary": {"currency": null, "max": null, "min": null, "period": null, "term": null}, "salary_visible": false, "title_keywords": ["officer", "operations"], "responsibilities": ["operations", "daily operation", "banking", "transactions", "ad-hoc duties"], "requirements": {"degrees": ["diploma or above"], "majors": [], "languages": ["putonghua", "english", "chinese"], "language_level": ["good command"], "hard_skills": ["excel", "word", "ms office"], "soft_skills": ["detail-minded", "communication skills", "independent"], "languages_combined": [{"language": "putonghua", "language_level": ["good command"]}, {"language": "english", "language_level": ["good command"]}, {"language": "chinese", "language_level": ["good command"]}]}, "experience_required": {"duration": ["2 years"], "field": ["operation", "relevant working experience"]}}, {"job_id": "100003009037280", "location_code": "hk", "company": "WallStone Partners & Company Limited", "job_title": "Banking--Counter Service Officer hiring", "description": "Our client, a well-known international bank\u00a0is currently inviting applications for Counter Services Officer.\n\nOffer : HKD$15-20,000 x 12 + Bonus\u00a0\u00a0\n\n\u00a0Responsibilities:\n\n\u00a0\u00a0\u00a0\u00a0\u00a0\u00a0\u00a0\u00a0 \u00a0\u00a0\u00a0\u00a0\u00a0\u00a0\u00a0\u00a0 Processed teller transactions accurately and timely\n\u00a0\u00a0\u00a0\u00a0\u00a0\u00a0\u00a0\u00a0 \u00a0\u00a0\u00a0\u00a0\u00a0\u00a0\u00a0\u00a0 Balance daily cash deposits and bank vault inventory with zero error rate\n\u00a0\u00a0\u00a0\u00a0\u00a0\u00a0\u00a0\u00a0 \u00a0\u00a0\u00a0\u00a0\u00a0\u00a0\u00a0\u00a0 Provide exceptional customer service with every transaction processed\n\u00a0\u00a0\u00a0\u00a0\u00a0\u00a0\u00a0\u00a0 \u00a0\u00a0\u00a0\u00a0\u00a0\u00a0\u00a0\u00a0 Educate clients on digital and self-service opportunities offered by the bank\n\u00a0\u00a0\u00a0\u00a0\u00a0\u00a0\u00a0\u00a0 \u00a0\u00a0\u00a0\u00a0\u00a0\u00a0\u00a0\u00a0 Prepare branch invoices and reports on daily and weekly basis\n\nRequirements:\n\n\u00a0\u00a0\u00a0\u00a0\u00a0\u00a0\u00a0\u00a0 \u00a0\u00a0\u00a0\u00a0\u00a0\u00a0\u00a0\u00a0 HKCEE\u00a0or above (Math + Eng or Math + Chi passed)\n\u00a0\u00a0\u00a0\u00a0\u00a0\u00a0\u00a0\u00a0 \u00a0\u00a0\u00a0\u00a0\u00a0\u00a0\u00a0\u00a0 At least one year or above work experience in customer service(any industry)\n\u00a0\u00a0\u00a0\u00a0\u00a0\u00a0\u00a0\u00a0 \u00a0\u00a0\u00a0\u00a0\u00a0\u00a0\u00a0\u00a0 Highly customer-focused and sales results-oriented\n\u00a0\u00a0\u00a0\u00a0\u00a0\u00a0\u00a0\u00a0 \u00a0\u00a0\u00a0\u00a0\u00a0\u00a0\u00a0\u00a0 Strong commitment and good communication skill\n\u00a0\u00a0\u00a0\u00a0\u00a0\u00a0\u00a0\u00a0 \u00a0\u00a0\u00a0\u00a0\u00a0\u00a0\u00a0\u00a0 Good command of spoken English and Cantonese; Putonghua is a plus\u00a0", "employment_types": ["Permanent"], "selling_points": ["Customer Service Role", "Basic + Bonus", "Good career path"], "locations": ["Not Specified"], "categories": ["Banking / Finance", "Retail Banking", "Sales, CS & Business Devpt", "Customer Service - Supervisor / Officer", "Wealth Management"], "post_time": "2022-01-11T02:18:17Z", "salary": {"currency": null, "max": null, "min": null, "period": "monthly", "term": null}, "salary_visible": false, "title_keywords": ["officer"], "responsibilities": ["invoices", "inventory", "transactions", "customer service", "reports"], "requirements": {"degrees": [], "majors": [], "languages": ["cantonese", "putonghua", "english"], "language_level": ["good command"], "hard_skills": ["plus", "math"], "soft_skills": ["communication skill", "customer-focused"], "languages_combined": [{"language": "cantonese", "language_level": ["good command"]}, {"language": "putonghua", "language_level": []}, {"language": "english", "language_level": ["good command"]}]}, "experience_required": {"duration": ["at least one year"], "field": []}}, {"job_id": "100003009037261", "location_code": "hk", "company": "PI Business Consulting Limited", "job_title": "Customer Service Officer (fluent in Mandarin)", "description": "Responsibilities:\n\nConduct outbound welcome calls to customer\u00a0\u00a0\n\nAccount Openings and current accounts upgrade\u00a0 through telephone calls (make warm call with call leads)\n\nProvide Customer Service\u00a0\n\nIt's a banking CS role\n\nRequirements:\n\nWith 1-year call center or CS experience\n\nFluent in Mandarin and Cantonese\n\n1 year contract, will consider for permanent role after 1 year if meet basic service\u00a0requirements", "employment_types": ["Contract"], "selling_points": ["warm outbound welcome call", "Banking Job", "good career development"], "locations": ["Central"], "categories": ["Banking / Finance", "Retail Banking"], "post_time": "2022-01-11T02:14:54Z", "salary": {"currency": null, "max": null, "min": null, "period": "monthly", "term": null}, "salary_visible": false, "title_keywords": ["customer service officer"], "responsibilities": ["provide customer service", "banking"], "requirements": {"degrees": [], "majors": [], "languages": ["cantonese", "mandarin"], "language_level": ["fluent"], "hard_skills": ["basic"], "soft_skills": [], "languages_combined": [{"language": "cantonese", "language_level": ["fluent"]}, {"language": "mandarin", "language_level": ["fluent"]}]}, "experience_required": {"duration": ["1-year"], "field": ["call center", "cs"]}}, {"job_id": "100003009049595", "location_code": "hk", "company": "Chiyu Banking Corp Ltd", "job_title": "Branch Operation Manager", "description": "Responsibilities:\n\nMonitor branch daily operations\nEnsure efficient branch operations and all activities are in compliance with the regulatory requirments\nAssist Branch Manager in implementing the business plan in order to achieve the assigned targets\u00a0\nRequirements:\nDegree or above in Business or related disciplines\nMinimum 5 years of supervisory experience in branch operations\nQualifications of HKSI, IIQE & MPF\nGood interpersonal and communication skills\nFlexible and detail-minded\nStrong in problem solving, coordinating and organizing skills\nWe offer competitive packages and promising career opportunities to the right candidates. Please send your full resume with current salary, expected salary and the date of availability to The Human Resources Department, Chiyu Banking Corporation Ltd, 12/F, Chiyu Bank Building, No. 78 Des Voeux Road Central, Hong Kong or fax to 2986-3233 or by clicking Apply Now.\n\n\nInformation provided will be treated in strict confidence and only be used for recruitment purposes. All personal data of unsuccessful applicants will be destroyed after the recruitment exercise. \u00a0A copy of Personal Information Collection Statement is available upon request.", "employment_types": ["Full Time", "Permanent"], "selling_points": [], "locations": ["Not Specified"], "categories": ["Banking / Finance", "Retail Banking", "Others", "Order Processing & Operation / Settlement"], "post_time": "2022-01-14T08:55:03Z", "salary": {"currency": null, "max": null, "min": null, "period": "monthly", "term": null}, "salary_visible": false, "title_keywords": ["operation manager"], "responsibilities": ["operations", "compliance", "monitor", "daily operations", "business plan"], "requirements": {"degrees": ["degree or above"], "majors": ["related disciplines", "business"], "languages": [], "language_level": [], "hard_skills": ["problem solving", "iiqe", "hksi"], "soft_skills": ["flexible", "communication skills", "detail-minded", "problem solving", "interpersonal"], "languages_combined": []}, "experience_required": {"duration": ["minimum 5 years"], "field": ["supervisory experience"]}}, {"job_id": "100003009048383", "location_code": "hk", "company": "HSBC Group", "job_title": "Outreach Insurance Specialist - Wealth and Personal Banking", "description": "The health and safety of our employees and candidates is very important to us. Due to the current situation related to the Novel Coronavirus (2019-nCoV), we\u2019re leveraging our digital capabilities to ensure we can continue to recruit top talent at HSBC.\u00a0\u00a0As your application progresses, you may be asked to use one of our digital tools to help you through your recruitment journey.\u00a0\u00a0If so, one of our\u00a0\u00a0Resourcing colleagues will explain how our video-interviewing technology will be used throughout the recruitment process and will be on hand to answer any questions you might have.\n\nSome careers grow faster than others.\n\nIf you\u2019re looking for a career that will give you plenty of opportunities to develop, join HSBC and your future will be rich with potential. Whether you want a career that could take you to the top, or simply take you in an exciting new direction, HSBC offers opportunities, support and rewards that will take you further.\n\nWealth and Personal Banking is our new global business combining Retail Banking and Wealth Management; and Global Private Banking, to become one of the world\u2019s largest global wealth managers with USD1.4 trillion in assets. Across Asia, where wealth pools are growing faster than in any other region, HSBC\u2019s wealth revenues grew 12% in 2019 (year-on-year) to USD5.7 billion.\u00a0\u00a0Our dedicated colleagues serve millions of customers worldwide across the entire spectrum of private wealth, ranging from personal banking individuals and families, through to business owners, investors and ultra-high-net-worth individuals.\u00a0\u00a0We provide products and services such as bank accounts, credit cards, personal loans and mortgages, as well as asset management, insurance, wealth management and private banking, that best suit our customers\u2019 needs.\n\nWe are currently seeking a high calibre professional to join our team as an\u00a0Outreach Insurance Specialist.\n\nPrincipal Responsibilities\n\nProvide specialist advice on appropriate insurance solutions to ensure the insurance or protection needs of Advance and Mass Market, Jade or Premier segment are well fulfilled\nHandle individual insurance portfolio to ensure the highest rate of customer satisfaction and persistency\nEstablish effective working relationships with other teams within the Branch and other relevant partners that impact client's experience of HSBC in order to deliver a consistent approach and application of outstanding service standard\nBuild and maintain a positive team culture, through ensuring quality business referrals and referral skills among team members, and contributing to product knowledge and skills sharing\nMaintain high level of compliance guidelines and procedures\nEnsure self and team activities follow relevant legal and regulatory requirements and meets HSBC standards and procedures\n\nRequirements\n\nTertiary or university level education, preferably in finance, business or a related field\nProven experience in life insurance, preferably in Bancassurance Extensive wealth management and insurance product knowledge and sales capabilities\nInsurance licenses required\nCertified Financial Planner or Certified Financial Marketing Professional accreditation or other relevant qualification an advantage\nGood level of verbal English and Cantonese, with Putonghua preferred\nExcellent communication, interpersonal and motivational skills\nSelf-motivated, excellent interpersonal skill\n\nYou'll achieve more when you join HSBC.\nwww.hsbc.com/careers\n\nHSBC is committed to building a culture where all employees are valued, respected and opinions count. We take pride in providing a workplace that fosters continuous professional development, flexible working and opportunities to grow within an inclusive and diverse environment. Personal data held by the Bank relating to employment applications will be used in accordance with our Privacy Statement, which is available on our website.\u00a0\n\nIssued by The Hongkong and Shanghai Banking Corporation Limited.", "employment_types": ["Full Time"], "selling_points": ["One of the world\u2019s leading international banks", "Business Development Exposure", "Dynamic working environment"], "locations": ["Kowloon City"], "categories": ["Banking / Finance", "Retail Banking"], "post_time": "2022-01-14T06:27:10Z", "salary": {"currency": null, "max": null, "min": null, "period": "monthly", "term": null}, "salary_visible": false, "title_keywords": ["insurance specialist", "personal"], "responsibilities": ["service standard", "guidelines", "regulatory requirements", "compliance", "teams", "quality", "procedures", "maintain", "working relationships", "insurance"], "requirements": {"degrees": [], "majors": [], "languages": ["cantonese", "putonghua", "english"], "language_level": ["good"], "hard_skills": ["planner"], "soft_skills": ["flexible", "self-motivated", "interpersonal skill", "communication", "committed", "diverse", "extensive", "interpersonal"], "languages_combined": [{"language": "cantonese", "language_level": ["good"]}, {"language": "putonghua", "language_level": ["good"]}, {"language": "english", "language_level": ["good"]}]}, "experience_required": {"duration": [], "field": ["management", "insurance"]}}, {"job_id": "100003009050358", "location_code": "hk", "company": "China Everbright Securities International Company Limited", "job_title": "Dealer/Senior Dealer, FX", "description": "Ref: D/EBSHKFX/140122DB/61\n\u00a0\n\n\nResponsibilities\n\n\nHandle the execution and operation functions on Forex\nProvide general assistance to clients over the phone or via the web\nSit on the Forex desk and support the client on-boarding process\nHandle account opening and prepare\u00a0various reports\nMaintain good relationship with existing clients\n\nRequirements\n\nSecondary school graduate or above\nMinimum 1 year's relevant experience\u00a0in foreign exchange\nHolder of SFC\u00a0license for\u00a0Type 3\u00a0regulated activity\u00a0preferred\nGood interpersonal skills and detail-oriented\nGood command of both written and spoken English and Chinese. Fluency in Putonghua an advantage\nShift duty may require\nCandidate with more experience will be considered as Senior\u00a0Dealer.\n\n\n\nWe offer a competitive remuneration package to the right candidate. If you are interested in the post, please send your resume together with\u00a0your present\u00a0and\u00a0expected salaries\u00a0by clicking\u00a0\u201cApply Now\u201d.\n\n\nFor more information about China Everbright Securities International Company Limited, please visit\u00a0www.ebshk.com.\n\nWe are an equal opportunity employer\u00a0and welcome applications from all qualified candidates. All applications will be treated in the strictest confidence. Personal data provided will be used for recruitment purposes only. The job applicant will assume all or any risks arising out of or in connection with the job application transmission process prior to our actual receipt of the same including but not limited to accidental or unauthorized loss or disclosure of personal information, to which we will not be responsible in any way.\n\u00a0\nUnder the Personal Data (Privacy) Ordinance, you may request access to, and / or correction of your personal data in relation to your application. If you wish to do so, please email to us.", "employment_types": ["Full Time", "Permanent"], "selling_points": [], "locations": ["Causeway Bay"], "categories": ["Banking / Finance", "Retail Banking", "Treasury", "Dealing & Trading"], "post_time": "2022-01-14T10:12:06Z", "salary": {"currency": null, "max": null, "min": null, "period": "monthly", "term": null}, "salary_visible": false, "title_keywords": ["dealer"], "responsibilities": ["account opening", "reports", "maintain good relationship"], "requirements": {"degrees": [], "majors": [], "languages": ["putonghua", "english", "chinese"], "language_level": ["fluency", "advantage", "good command"], "hard_skills": ["sfc license", "exchange"], "soft_skills": ["interpersonal skills", "detail-oriented"], "languages_combined": [{"language": "putonghua", "language_level": ["fluency", "advantage"]}, {"language": "english", "language_level": ["good command"]}, {"language": "chinese", "language_level": ["good command"]}]}, "experience_required": {"duration": ["minimum 1 year"], "field": ["relevant experience"]}}, {"job_id": "100003009035597", "location_code": "hk", "company": "Hua Nan Commercial Bank, Ltd.", "job_title": "DEPOSIT OFFICER /\u5b58\u6b3e\u5c08\u54e1", "description": "DEPOSIT OFFICER\u5b58\u6b3e\u5c08\u54e1\n\n\u61c9\u5fb5\u8005\u5177\u5c08\u4e0a\u6216\u5927\u5b78\u5546\u79d1\u5b78\u7cfb\u7562\u696d\u3001\u9280\u884c\u5be6\u52d9\u7d93\u9a57\u8005\u4f73\uff0c\u00a0\u656c\u696d\u8ca0\u8cac\u3001\u7d30\u5fc3\u3001\u5177\u5718\u968a\u7cbe\u795e\u53ca\u670d\u52d9\u71b1\u8aa0\n\n\u6709\u9280\u884c\u5047\u671f\u3001\u82b1\u7d05\u3001\u91ab\u7642\u4fdd\u96aa\u53ca\u81b3\u98df\u6d25\u8cbc\uff0c\u661f\u671f\u4e00\u81f3\u4e94: \u4e0a\u53488\u664250\u5206\u81f3\u4e0b\u53485\u6642\u534a\uff0c \u6bcf\u9031\u5de5\u4f5c5\u5929\uff0c \u6bcf\u5929\u5de5\u4f5c 8 \u5c0f\u6642", "employment_types": ["Full Time", "Permanent"], "selling_points": [], "locations": ["Wan Chai"], "categories": ["Banking / Finance", "Retail Banking", "Financial Services", "Others"], "post_time": "2022-01-10T07:49:40Z", "salary": {"currency": null, "max": null, "min": null, "period": "monthly", "term": null}, "salary_visible": false, "title_keywords": ["officer"], "responsibilities": [], "requirements": {"degrees": [], "majors": [], "languages": [], "language_level": [], "hard_skills": [], "soft_skills": [], "languages_combined": []}, "experience_required": {"duration": [], "field": []}}, {"job_id": "100003009045526", "location_code": "hk", "company": "Hang Seng Bank Ltd", "job_title": "Assistant Business Support Manager", "description": "Wealth and Personal Banking \u2013 Chief Administration Office\n\nHang Seng\u2019s Wealth and Personal Banking (WPB) Chief Administration Office is a team of experienced banking professionals who strives for delivering time-to-market and efficient support and monitoring to support business growth.\n\nChief Administration Office is dedicated to implement, monitor and track business performance, prepare management information and reporting of WPB businesses for top management and coordinate project implementation in accordance to the bank\u2019s strategies.\n\nWe are currently seeking a high caliber professional to join our department as\u00a0Assistant Business Support Manager.\n\u00a0\n\nPrincipal responsibilities\n\nCarry out Hong Kong Monetary Authority (HKMA), Securities and Futures Commission (SFC), and HK Insurance Authorities (HKIA) license administration activities for business units, activities include document checking, competence assessment, license registration, deregistration, change of particulars, etc.\nAct as a gatekeeper or primary point of contact roles for license administration works\nBe a subject matter expert in license administration field\nAssisting with the execution of business initiatives and activities in support of business aims\n\nRequirements\nUniversity graduates in related discipline\nMinimum of 1-year work experience preferably in the banking industry, with good knowledge of business management and operations management\nStrong self-motivation, excellent communication, negotiation and interpersonal skills\nGreat sense of ownership and servicing mindset to ensure efficient and effective customer service processes\nStrong problem solving and negotiation skills, plus ability to work under pressure\nProficiency in both English and Chinese, fluency in Putonghua an advantage\n\n\u00a0\nIf you would like to explore other opportunities at Hang Seng Hong Kong, please visit\u00a0www.hangseng.com/careers/\u00a0for details.\n\nThe health and safety of our employees and candidates is very important to us. Due to the current situation related to the Novel Coronavirus (2019-nCoV), we\u2019re leveraging our digital capabilities to ensure we can continue to recruit top talent at the HSBC Group. \u00a0As your application progresses, you may be asked to use one of our digital tools to help you through your recruitment journey. \u00a0If so, one of our \u00a0Resourcing colleagues will explain how our video-interviewing technology will be used throughout the recruitment process and will be on hand to answer any questions you might have.\n\nAll information provided by applicants will be used only for recruitment purposes and will be used strictly in accordance with the Bank's personal data policies, a copy of which may be obtained by the applicant upon request. Unless otherwise instructed in writing by the applicant concerned, applicants may be considered for other suitable positions within the Bank and its related companies. The personal data of unsuccessful job applicants may be retained for a maximum of two years from the date when the job application is rejected and such data may be retained for a longer period if there is a subsisting reason that obliges the Bank to do so, after which the personal data will be destroyed.", "employment_types": ["Full Time", "Permanent"], "selling_points": [], "locations": ["Not Specified"], "categories": ["Admin & HR", "Administration / Operation Manager", "Others", "Banking / Finance", "Retail Banking"], "post_time": "2022-01-13T08:00:58Z", "salary": {"currency": null, "max": null, "min": null, "period": "monthly", "term": null}, "salary_visible": false, "title_keywords": ["manager", "assistant"], "responsibilities": ["business initiatives", "subject matter expert", "checking", "contact", "insurance", "administration"], "requirements": {"degrees": [], "majors": [], "languages": ["putonghua", "english", "chinese"], "language_level": ["fluency", "advantage", "proficiency"], "hard_skills": ["business management", "plus", "problem solving", "reason"], "soft_skills": ["efficient", "negotiation", "communication", "problem solving", "negotiation skills", "self-motivation", "interpersonal skills", "customer service", "novel", "work under pressure"], "languages_combined": [{"language": "putonghua", "language_level": ["fluency"]}, {"language": "english", "language_level": ["proficiency", "fluency", "advantage"]}, {"language": "chinese", "language_level": ["proficiency", "fluency", "advantage"]}]}, "experience_required": {"duration": ["minimum of 1-year"], "field": ["banking industry", "management", "business", "operations management"]}}, {"job_id": "100003009040266", "location_code": "hk", "company": "CMB Wing Lung Bank Limited", "job_title": "Relationship Manager / Senior Relationship Manager", "description": "Job Description\n\nDevelop the Bank's high-net-worth client base and establish long term relationship with clients\nIntroduce comprehensive wealth management solutions to meet clients' needs\nDeliver high quality services to clients\nRequirements\n\nDegree holder preferably in business related discipline or equivalent\nMinimum 2 years' working experience of retail banking\nPasses in the Insurance Intermediaries Qualifying Examinations and Hong Kong Securities & Investment Institute Licensing Examinations\nProficient in both English and Chinese; fluency in Putonghua an advantage\nGood communication and interpersonal skills", "employment_types": ["Full Time", "Permanent"], "selling_points": ["Retail Banking", "Relationship Manager", "Serve high-net-worth clients"], "locations": ["Not Specified"], "categories": ["Banking / Finance", "Retail Banking"], "post_time": "2022-01-12T02:04:18Z", "salary": {"currency": null, "max": null, "min": null, "period": "monthly", "term": null}, "salary_visible": false, "title_keywords": ["senior relationship manager", "relationship manager"], "responsibilities": ["management", "client base", "quality", "develop"], "requirements": {"degrees": ["degree holder"], "majors": ["business"], "languages": ["putonghua", "english", "chinese"], "language_level": ["fluency", "advantage", "proficient"], "hard_skills": [], "soft_skills": ["communication and interpersonal skills"], "languages_combined": [{"language": "putonghua", "language_level": ["fluency", "advantage"]}, {"language": "english", "language_level": ["proficient"]}, {"language": "chinese", "language_level": ["proficient"]}]}, "experience_required": {"duration": ["minimum 2 years"], "field": ["retail banking"]}}, {"job_id": "100003009049452", "location_code": "hk", "company": "Citibank (Hong Kong) Limited", "job_title": "Commercial Bank - Digital Segment HK - Relationship Manager Vice President", "description": "Responsibilities:\n\n\nActively calls on clients to deepen relationships and proactively owns, responds to, uncovers and anticipates future needs, challenges or risks and expectations\nIntroduces solutions to clients in building and strengthening an effective portfolio;\nWorks with product specialists and subject matter experts to structure innovative and customized solutions that meet clients' individual needs\nWorks closely with Case Manager on the on-boarding and retention of clients, ensuring the appropriate \"Know Your Client\" (KYC) and other compliance deliverables are met;\nIdentifies cross-sell opportunities to deepen and increase share of wallet;\nMaximizes client experience by proactively sharing markets updates, trends and intelligence;\nDrives innovation in the solutions we provide clients and further developing our business where necessary and appropriate\nExecution of strategic initiatives launched centrally at all levels (Group, Bank, commercial market and EIB)\nNetworks with clients to identify avenues for new business opportunities;\nAdministrate the credit relationship of the client, coordinating and supervising the entire process, ensuring the proper application of policies and institutional processes\nEnsures compliance with regulatory requirements and Citi's policies / guidelines at all times\nAppropriately assess risk when business decisions are made, demonstrating particular consideration for the firm's reputation and safeguarding Citigroup, its clients and assets, by driving compliance with applicable laws, rules and regulations, adhering to Policy, applying sound ethical judgment regarding personal behavior, conduct and business practices, and escalating, managing and reporting control issues with transparency.\n\nQualifications:\n\n\n6-10 years of experience\nSound knowledge of banking and investment products and process as well as a track record of providing sound banking and financial advice and solutions to clients\nDemonstrates sound credit skills by being able to structure more complex deals, which can include capital market transactions\nDemonstrates advanced level of Early Warning Detection skills\nDemonstrates advanced credit skills; able to structure all type of credit deals\nAbility to work effectively in team setting\nAbility to coordinate multi-functional teams to provide an exceptional client experience.\nExcellent interpersonal, communication and influencing skills (e.g. negotiation, consultative skills, leadership)\nAbility to work under pressure while making sound decisions\nHighly focused, able to rapidly determine key priorities, clearly communicate the priorities\nA proactive approach in looking for ways in strengthening business relationship with clients, delivers a simple, secure and seamless client experience\nAggressive and hungry for creating new business opportunities with existing clients and able to demonstrate innovative approaches to meeting clients' needs.\nAbility to embrace new technology and understand the role digital plays in the experience we deliver for our clients\nAble to quickly adapt priorities based on the latest data insights\n\nEducation:\n\n\nBachelor's/University degree, Master's degree preferred\n\nInterested candidates, please click APPLY NOW \u00a0to apply.\n\n\nJob Family Group:\nCommercial and Business Sales\nJob Family:\nRelationship Management\nTime Type:\n\nCiti is an equal opportunity and affirmative action employer.\n\nQualified applicants will receive consideration without regard to their race, color, religion, sex, sexual orientation, gender identity, national origin, disability, or status as a protected veteran.\n\nCitigroup Inc. and its subsidiaries (\"Citi\") invite all qualified interested applicants to apply for career opportunities. If you are a person with a disability and need a reasonable accommodation to use our search tools and/or apply for a career opportunity review\u00a0Accessibility at Citi\u00a0.", "employment_types": ["Full Time"], "selling_points": ["Actively calls on clients to deepen relationships", "Introduces solutions to clients", "6-10 years of experience"], "locations": ["Not Specified"], "categories": ["Banking / Finance", "Retail Banking", "Others"], "post_time": "2022-01-14T08:40:57Z", "salary": {"currency": null, "max": null, "min": null, "period": "monthly", "term": null}, "salary_visible": false, "title_keywords": ["vice president", "relationship manager"], "responsibilities": ["compliance", "kyc"], "requirements": {"degrees": [], "majors": [], "languages": [], "language_level": [], "hard_skills": ["kyc"], "soft_skills": ["innovative"], "languages_combined": []}, "experience_required": {"duration": [], "field": []}}, {"job_id": "100003009046221", "location_code": "hk", "company": "OCBC Wing Hang Bank Limited", "job_title": "District Sales Manager", "description": "Responsibilities\n\nDevelop and implement sales management strategy for driving consumer business, monitor and review the implementation of sales plans to achieve the assigned district target\nSupport District Head to drive consumer banking business and uplift productivity of branch sales staff\nPlan and manage the sales staff headcount of the district\nCreate sales culture to ensure the sales quality aligns with the regulatory requirement\nHave strong sales discipline and provide support to the District Head in business growth\n\nRequirements\n\nDegree holder is preferred\nMinimum of 10 years banking experience in retail consumer business, management experience will be preferable\nSolid experience in branch sales management\nGood interpersonal and communication skills.\nSelf-motivated and be able to work under pressure and independently\nProficient in MS Office", "employment_types": ["Full Time", "Permanent"], "selling_points": ["Drive consumer banking business of a District", "Uplift branch sales productivity", "Solid branch sales management experience"], "locations": ["Sheung Wan"], "categories": ["Banking / Finance", "Retail Banking"], "post_time": "2022-01-13T10:00:40Z", "salary": {"currency": null, "max": null, "min": null, "period": "monthly", "term": null}, "salary_visible": false, "title_keywords": ["sales manager"], "responsibilities": ["provide support", "review", "monitor", "implementation", "quality", "develop", "sales plans", "plan", "banking", "sales management"], "requirements": {"degrees": ["degree holder"], "majors": [], "languages": [], "language_level": [], "hard_skills": ["ms office"], "soft_skills": ["communication skills", "self-motivated", "independently", "interpersonal", "work under pressure"], "languages_combined": []}, "experience_required": {"duration": ["minimum of 10 years"], "field": ["business", "management", "retail", "banking experience"]}}, {"job_id": "100003009048549", "location_code": "hk", "company": "OCBC Wing Hang Bank Limited", "job_title": "Manager / Assistant Manager, Digital Channels (Remote Channels and Digital Projects)", "description": "Responsibilities\n\nManage projects relating to website management, SMS/email blasting and digital applications\nManage and administer the content and analysis the traffic of the bank website.\nSupport ATM administration and related networks services.\nSupport on digital projects through the whole development cycle on business proposal preparation, vendor selection, user requirement formation, project testing and execution management\nManage stakeholders\u2019 expectations and cost management\nEnsure collaboration among different team of developers, vendors, partners and end users\nEnsure processes comply with regulatory requirements and compliance standards\nRequirements\n\nAt least 4 years of working experience in digital product/service development\nGood business acumen with solid knowledge of banking and financial products\nSolid experience in digital channel projects on digital application projects including project administration, requirements specification, testing and project launch management.\nExperience in managing website content administration and traffic analytic\nUnderstanding of regulatory guidelines and risk control from HKMA, HKAB in digital channels perspective\nKnowledge of latest Fintech, digital landscape and trends, innovative and details-oriented\nKnowledge on Webpages development, content management and traffic analytic skills\nKnowledge on ATM administration, networks services management and implementation skill\nProficiency in MS PowerPoint, Excel Marco\nEnsure the customer journey is seamless with customer centric design\nAssistance in digital projects invoice and contract processing\nAssistance in providing support on marketing activities (SMS/email blasting, website update, etc.) for digital channels\nCompile market and regulatory reports on research findings and recommendations\nAnalyze and benchmarking latest market data in banking and financial industry\nPerform ad hoc and departmental duties as assigned", "employment_types": ["Full Time", "Permanent"], "selling_points": ["University graduate", "Experienced in API, ATM applications", "Good project management in e-banking"], "locations": ["Shau Kei Wan"], "categories": ["Banking / Finance", "Retail Banking", "Information Technology (IT)", "Others"], "post_time": "2022-01-14T06:46:10Z", "salary": {"currency": null, "max": null, "min": null, "period": "monthly", "term": null}, "salary_visible": false, "title_keywords": ["manager", "assistant manager,"], "responsibilities": ["user requirement", "management", "cost", "regulatory requirements", "analysis", "compliance", "website", "testing", "manage projects", "administration"], "requirements": {"degrees": [], "majors": [], "languages": [], "language_level": [], "hard_skills": ["excel", "hkma", "analytic skills", "marco", "ms powerpoint", "processing", "acumen"], "soft_skills": ["business acumen", "innovative"], "languages_combined": []}, "experience_required": {"duration": ["at least 4 years"], "field": ["management", "development", "testing", "digital", "administration"]}}, {"job_id": "100003009050761", "location_code": "hk", "company": "China Construction Bank (Asia) Corporation Limited", "job_title": "Assistant Manager, Credit Verification (Commercial & Retail Banking)", "description": "Responsibilities:\n\n\n\u2022\u00a0\u00a0\u00a0\u00a0\u00a0\u00a0\u00a0\u00a0\u00a0\u00a0 Prepare facility letters, loan documents and relevant correspondences such as instruction letter to solicitor firms;\n\n\u2022\u00a0\u00a0\u00a0\u00a0\u00a0\u00a0\u00a0\u00a0\u00a0\u00a0 Perform the checker role for reviewing the basic facility letters and/or loan documentations prepared by the marker if necessary;\n\n\u2022\u00a0\u00a0\u00a0\u00a0\u00a0\u00a0\u00a0\u00a0\u00a0\u00a0 Perform loan documentation review prior to the loan drawdown/ line validation;\n\n\u2022\u00a0\u00a0\u00a0\u00a0\u00a0\u00a0\u00a0\u00a0\u00a0\u00a0 Process the regular MIS reports;\n\n\u2022\u00a0\u00a0\u00a0\u00a0\u00a0\u00a0\u00a0\u00a0\u00a0\u00a0 Participate in UAT project;\n\n\u2022\u00a0\u00a0\u00a0\u00a0\u00a0\u00a0\u00a0\u00a0\u00a0\u00a0 Participate in monthly outstanding cases clean-up exercise and/or yearly files cleaning up project;\n\n\u2022\u00a0\u00a0\u00a0\u00a0\u00a0\u00a0\u00a0\u00a0\u00a0\u00a0 Assist supervisor in drafting and reviewing the operation manual;\n\n\u2022\u00a0\u00a0\u00a0\u00a0\u00a0\u00a0\u00a0\u00a0\u00a0\u00a0 Ordering and reviewing of valuation report;\n\n\u2022\u00a0\u00a0\u00a0\u00a0\u00a0\u00a0\u00a0\u00a0\u00a0\u00a0 Perform ad hoc duties as assigned;\n\n\u2022\u00a0\u00a0\u00a0\u00a0\u00a0\u00a0\u00a0\u00a0\u00a0\u00a0 Reply follow-up issues as requested by LPS;\n\n\u2022\u00a0\u00a0\u00a0\u00a0\u00a0\u00a0\u00a0\u00a0\u00a0\u00a0 Deliver loan documents and/or other relevant documents to various business units and/or other relevant parties\n\nRequirements:\n\n\n\nDegree holder, preferably in Business or related disciplines\nMinimum 4 years of loan documentation and credit execution experience\nStrong command of spoken and written English and Chinese (including Putonghua)", "employment_types": ["Full Time", "Permanent"], "selling_points": ["Prepare facility letters & loan documents", "Process the regular MIS reports", "Degree holder & 4 yrs exp in loan documentation"], "locations": ["Kowloon Bay"], "categories": ["Banking / Finance", "Loan", "Retail Banking", "Risk Management"], "post_time": "2022-01-14T11:17:43Z", "salary": {"currency": null, "max": null, "min": null, "period": "monthly", "term": null}, "salary_visible": false, "title_keywords": ["assistant manager,"], "responsibilities": ["ad hoc duties", "valuation", "uat", "review", "letters", "reports", "cleaning", "documentation", "report"], "requirements": {"degrees": ["degree holder"], "majors": ["related disciplines", "business"], "languages": ["putonghua", "english", "chinese"], "language_level": [], "hard_skills": ["documentation"], "soft_skills": [], "languages_combined": [{"language": "putonghua", "language_level": []}, {"language": "english", "language_level": []}, {"language": "chinese", "language_level": []}]}, "experience_required": {"duration": ["minimum 4 years"], "field": []}}, {"job_id": "100003009049925", "location_code": "hk", "company": "Nanyang Commercial Bank", "job_title": "Compliance Manager (Ref: KC8025-00-JDB)", "description": "Develops, reviews and enforces the compliance programmes in accordance with the policies and guidelines of the bank and regulatory bodies. Collaborates with other business units to review compliance issues in order to address and meet regulatory or business changes. Conducts regular compliance reviews, handles HKMA enquiries, develops and conducts internal trainings on all compliance issues to enhance the compliance consciousness of all staff levels.\n\nRequirements:\u00a0\n\n\nDegree holder in Business Administration, Finance, Business Law or related disciplines;\n\nAt least 7 years banking experience in compliance, internal auditing or risk management;\n\nExposure in China financial institutions with relevant compliance experience is highly preferable;\n\nSubstantial knowledge in regulatory requirements relating to banking industry;\n\nAnalytical, proactive and independent with sound communication skills;\n\nProficient in both spoken and written English and Chinese, fluent in Putonghua is preferable.\n\nIf you are flexible enough and zeal for a harmonious and supportive working environment where enables you to grow and succeed professionally, please send a full resume indicating your public examination results (HKCEE and HKALE / HKDSE), your present and expected salary and quoting reference number attention to\u00a0Talent Acquisition Division, Nanyang Commercial Bank, 151 Des Voeux Road Central, Hong Kong or apply through email. For details, please visit https://www.ncb.com.hk/ and select the page Recruit.\n\nWe are an Equal Opportunities Employer. Data collected would be used for recruitment purposes only. Applicants who do not hear from us within 8 weeks may consider their applications unsuccessful and their data will be destroyed within 12 months of receipt.", "employment_types": ["Full Time", "Permanent"], "selling_points": ["Conducts regular compliance reviews", "Liaise with regulators, including HKMA, SFC and IA", "At least 7 years relevant banking experience"], "locations": ["Central"], "categories": ["Banking / Finance", "Retail Banking", "Professional Services", "Legal & Compliance"], "post_time": "2022-01-15T03:50:42Z", "salary": {"currency": null, "max": null, "min": null, "period": "monthly", "term": null}, "salary_visible": false, "title_keywords": ["compliance manager"], "responsibilities": ["management", "data", "guidelines", "policies", "regulatory requirements", "review", "compliance", "communication", "recruitment", "banking", "auditing", "administration"], "requirements": {"degrees": ["hkdse", "degree holder"], "majors": ["business administration", "law", "finance", "related disciplines", "business"], "languages": ["putonghua", "english", "chinese"], "language_level": ["fluent", "proficient"], "hard_skills": ["hkma"], "soft_skills": ["flexible", "communication skills", "supportive", "independent", "harmonious", "proactive"], "languages_combined": [{"language": "putonghua", "language_level": ["fluent", "proficient"]}, {"language": "english", "language_level": ["fluent", "proficient"]}, {"language": "chinese", "language_level": ["fluent", "proficient"]}]}, "experience_required": {"duration": ["at least 7 years"], "field": ["risk management", "financial institutions", "compliance", "banking experience"]}}, {"job_id": "100003009049579", "location_code": "hk", "company": "China Construction Bank (Asia) Corporation Limited", "job_title": "AVP / VP, Big Data Analytics & Machine Learning", "description": "Responsibilities:\n\n\nExplore the availability, access and transformation/ use of unstructured data (browsing data, voice, email, picture, videos) for analytics and customer contact purpose\nHands-on develop advanced analytics/ Machine Learning-based solutions to uplift effectiveness of analytics, modelling and customer contact riding on (i) supervised/ unsupervised Machine Learning techniques (ii) unstructured data e.g. digital footprint\nStudy and develop the business implementation of speech and text analytics\nIntegrate customer external and internal data, structured and unstructured\nDevelop close-loop learning path and ensure insights and learnings are carried out for continuous customer interactions\nAs the Subject Matter Expert, trainer and advocate to uplift the machine learning skillset and culture of existing analysts pool\n\nRequirements:\n\nBachelor\u2019s / Master's degree in Computer Science, Data and Information Management or a related discipline\nA data scientist with minimum 8 years of hands-on experience in developing and executing large scale analytics deliverables/ projects in the Financial Services Industry\nDeep experience in applying artificial intelligence and machine learning techniques/algorithms, infused with industry knowledge, to enhance business strategies\nStrong in transforming analytical concepts and developments into business strategies and applications for the uplift of business value\nAbility to build strong stakeholders\u2019 relationships through thorough understanding of business requirements and the ability to analyse issues to find effective solutions\nSolid experience in training analysts on machine learning techniques\nEffective presentation, communication and interpersonal skills\nGreat sense of ownership and servicing mindset to ensure efficient and effective customer service processes\nProficiency in English and Chinese (both Cantonese and Mandarin)\nCandidate with less experience will be considered for the AVP position\n\nPlease specify your current and expected package in your application for reference.\u00a0\n\nApplicants who are not contacted within 8 weeks may consider their applications unsuccessful and their personal data will be retained by the bank for a period up to two years.\n\nAll information provided by applicants will be used for recruitment purposes only and will be used strictly in accordance with the bank\u2019s personal data policies, a copy of which will be provided upon request.", "employment_types": ["Full Time", "Permanent"], "selling_points": ["Data Management", "Big Data", "Machine Learning"], "locations": ["Not Specified"], "categories": ["Banking / Finance", "Corporate Banking", "Retail Banking", "Professional Services", "Business Analysis / Data Analysis"], "post_time": "2022-01-14T08:54:13Z", "salary": {"currency": null, "max": null, "min": null, "period": "monthly", "term": null}, "salary_visible": false, "title_keywords": [], "responsibilities": ["data", "implementation", "subject matter expert", "develop", "contact"], "requirements": {"degrees": ["degree", "bachelor", "master"], "majors": ["computer science"], "languages": ["cantonese", "english", "chinese", "mandarin"], "language_level": ["proficiency"], "hard_skills": [], "soft_skills": ["efficient", "ability to analyse", "deep", "hands-on", "learning", "communication and interpersonal skills", "thorough", "customer service", "presentation"], "languages_combined": [{"language": "cantonese", "language_level": []}, {"language": "english", "language_level": ["proficiency"]}, {"language": "chinese", "language_level": ["proficiency"]}, {"language": "mandarin", "language_level": []}]}, "experience_required": {"duration": ["minimum 8 years"], "field": ["financial services industry", "business", "training", "developing"]}}, {"job_id": "100003009047162", "location_code": "hk", "company": "OCBC Wing Hang Bank Limited", "job_title": "Customer Care Manager", "description": "Responsibilities\n\nHandle the Customer Feedback Hotline\nResolve customer complaints in accordance to regulatory requirements and identify root cause(s) for rectification\nCommunicate with other parties for complaint handling\nCoordinate with relevant business partners to secure the service standard\nPrepare complaint investigation report and keep record properly\nIdentify service deficiency via complaint handling and suggest improvement\nPrepare complaint statistics and analyses for timely reporting to management\n\nRequirements\n\nUniversity degree or equivalent\nProficient in Microsoft word, Excel and Powerpoint\nMin. 5 years\u2019 experience in complaint handling in banking industry\nPleasant and self-motivated, good negotiation, communication and interpersonal skills\nGood understanding in banking products and services\nGood command of detection and analytical mind\nAble to work under pressure and independently\nGood command of both spoken and written English and Chinese, fluent in Putonghua is preferable", "employment_types": ["Full Time", "Permanent"], "selling_points": ["University graduate", "Experienced in handling complaints in banking", "Good customer services"], "locations": ["Shau Kei Wan"], "categories": ["Banking / Finance", "Retail Banking", "Sales, CS & Business Devpt", "Customer Service - Manager"], "post_time": "2022-01-14T02:30:01Z", "salary": {"currency": null, "max": null, "min": null, "period": "monthly", "term": null}, "salary_visible": false, "title_keywords": ["manager"], "responsibilities": ["communicate with", "reporting", "management", "service standard", "resolve customer complaints", "regulatory requirements", "rectification", "coordinate with", "investigation", "report"], "requirements": {"degrees": ["university degree"], "majors": [], "languages": ["putonghua", "english", "chinese"], "language_level": ["good command", "fluent"], "hard_skills": ["excel", "microsoft word", "powerpoint"], "soft_skills": ["self-motivated", "independently", "negotiation", "pleasant", "analytical mind", "communication and interpersonal skills", "work under pressure"], "languages_combined": [{"language": "putonghua", "language_level": ["fluent", "good command"]}, {"language": "english", "language_level": ["good command"]}, {"language": "chinese", "language_level": ["good command"]}]}, "experience_required": {"duration": ["5 years"], "field": ["banking industry"]}}, {"job_id": "100003009048662", "location_code": "hk", "company": "OCBC Wing Hang Bank Limited", "job_title": "Manager / Assistant Vice President, Digital Channels  \u2013 SME projects", "description": "Responsibilities\n\nAssist to plan and participate in digital channel development for Consumer and SME banking projects under digital business user team\nManage and execute digital projects on acquisition, SME cash and loan\nAssist to manage digital projects through the whole development cycle on business proposal preparation, vendor selection, user requirement formation, project testing, execution management and performance tracking\nWork very closely with product owners in digitizing the product sale channels\nAssist to manage project budget and channel revenue generation to meet business P&L\nAssist to manage stakeholders\u2019 expectations and cost management\nEnsure collaboration among different team of developers, vendors, partners and end users (both consumer and SME teams)\nEnsure processes comply with regulatory requirements and compliance standards\nEnhance the UX and flow to come up a seamless digital customer journey with customer centric design\nCompile market reports on research findings and recommendations\nAnalyze latest market data in banking and financial industry\nPerform ad hoc duties as assigned\nRequirements\n\nUniversity graduate in business administration, finance, computer science, e-Commerce or related discipline\nAt least 5 years of relevant working experience on digital channel development in banking/finance industry\nSolid project management experience in banking/finance industry\nGood business acumen with solid knowledge of banking and financial products including both consumer and SME banking\nDemonstrate strong analytical skill and business mindset\nStrong stakeholders, developer and partners management skill\nUnderstand of regulatory guidelines and risk control\nKeep abreast of latest market trend and technology\nExperience in managing sizable projects with tracked result\nStrong written and spoken in English and Chinese\nBe open-minded and self-motivated with good communication, interpersonal, problem solving skills and strong sense of responsibility, able to work under pressure", "employment_types": ["Full Time", "Permanent"], "selling_points": ["University graduate", "Exp in digital platforms for SME &consumer banking", "Good project management in e-banking"], "locations": ["Shau Kei Wan"], "categories": ["Banking / Finance", "Retail Banking", "Information Technology (IT)", "Others"], "post_time": "2022-01-14T06:58:59Z", "salary": {"currency": null, "max": null, "min": null, "period": "monthly", "term": null}, "salary_visible": false, "title_keywords": ["manager", "assistant vice president"], "responsibilities": ["ad hoc duties", "user requirement", "management", "cost", "regulatory requirements", "budget", "teams", "compliance", "p&l", "testing", "design", "reports", "plan", "banking", "sme", "market data", "tracking"], "requirements": {"degrees": ["university graduate"], "majors": ["finance", "business administration", "computer science", "e-commerce"], "languages": ["english", "chinese"], "language_level": [], "hard_skills": ["analytical skill", "e-commerce", "project management", "problem solving skills", "acumen"], "soft_skills": ["analytical skill", "self-motivated", "sense of responsibility", "open-minded", "communication", "project management", "business acumen", "problem solving skills", "interpersonal", "work under pressure"], "languages_combined": [{"language": "english", "language_level": []}, {"language": "chinese", "language_level": []}]}, "experience_required": {"duration": ["at least 5 years"], "field": ["development", "relevant working experience", "banking", "project management", "finance industry", "digital"]}}, {"job_id": "100003009049754", "location_code": "hk", "company": "China CITIC Bank International Limited", "job_title": "Senior Manager, Service Quality (Complaint Handling)", "description": "Job Purpose\nEnsure and sustain competitive customer service quality through effective complaint management and assist in the development of customer-oriented culture in the Bank\nKey Responsibilities\nManage, monitor and investigate general and sensitive complaints and/or feedback received from all channels including Service Quality Hotline to ensure the complaints are handled timely and appropriately.\nIdentify and suggest gaps and improvement priorities from valid or invalid complaints and escalate to respective departments for consideration and implementation of improvement action\nReview voices of customers besides complaints lodged in Complaint Management System to analyze customers\u2019 needs and dissatisfaction\nContribute idea to the annual review of the Complaint Handling Policy and Service Quality related procedures\nMonitor and raise suggestions for enhancement of the Complaint Management System\nAssist to support the day to day operation of the team\u00a0\u00a0\u00a0\u00a0\u00a0\u00a0\u00a0\nRequirements\nDegree holder or equivalent\nMinimum 8 years\u2019 working experience in complaint handling or quality management, preferably from the banking and finance industry\nGood knowledge of compliant handling procedures and relevant regulatory requirements\nHigh awareness of both quality and risk, especially compliance related risk\nGood knowledge in banking products, services and selling process\nTactful communication and good interpersonal skills\nGood command of written and spoken English and Chinese (Cantonese and Putonghua)\nFor more details about career opportunities with the Bank, please visit our website http://www.cncbinternational.com/careers/en/index.jsp.\u00a0 Please apply with full resume stating current and expected salaries.\nPersonal data collected will be used for recruitment related purposes only. Applicants not invited for interview within 6 weeks may consider their applications unsuccessful. However, applicants may be considered for other suitable positions within the Group for a period of not more than 2 years. Personal data will be destroyed at any time after 3 months.\nChina CITIC Bank International is committed to being an equal opportunities employer and intends to provide a work environment free of unlawful discrimination or harassment.\u00a0 All employment decisions will be made in a non-discriminatory manner.", "employment_types": ["Full Time", "Permanent"], "selling_points": ["Handle and monitor customer complaints", "Assist in driving service quality management", "Good knowledge of complaint handling procedures"], "locations": ["Quarry Bay"], "categories": ["Banking / Finance", "Retail Banking", "Sales, CS & Business Devpt", "Customer Service - Manager", "Professional Services", "Legal & Compliance"], "post_time": "2022-01-14T09:11:50Z", "salary": {"currency": null, "max": null, "min": null, "period": "monthly", "term": null}, "salary_visible": false, "title_keywords": ["senior manager"], "responsibilities": ["management", "review", "quality", "monitor", "implementation", "procedures"], "requirements": {"degrees": ["degree holder"], "majors": [], "languages": ["cantonese", "putonghua", "english", "chinese"], "language_level": ["good command"], "hard_skills": [], "soft_skills": ["communication", "committed", "tactful", "interpersonal skills"], "languages_combined": [{"language": "cantonese", "language_level": ["good command"]}, {"language": "putonghua", "language_level": ["good command"]}, {"language": "english", "language_level": ["good command"]}, {"language": "chinese", "language_level": ["good command"]}]}, "experience_required": {"duration": ["minimum 8 years"], "field": ["finance industry", "quality management", "banking"]}}, {"job_id": "100003009049589", "location_code": "hk", "company": "Chiyu Banking Corp Ltd", "job_title": "Branch Manager", "description": "Responsibilities:\nParticipate in developing scenario solutions related to Cash Management and Trade Finance products and various innovative projects\n\nWork closely with the internal parties and prepare promotional materials for brand building\n\nConduct market research on new products and competitors\n\nResponsible for project management for various integrated projects with different internal stakeholders within the department\n\nResponsible for preparing presentation materials and other reports etc.\n\nRequirements:\nDegree holder or above in BBA, Finance, Information Technology and related disciplines\n\nSolid experience in project management and Cash Management and Trade Finance products in Banking industry\n\nGood communication and interpersonal skills. Experience in customer handling will be an advantage\n\nInnovative, self-motivated and be a good team player\n\nAble to work independently and under pressure.\n\nGood command of both verbal and written English and Chinese. Fluent in Mandarin will be an advantage\n\nWe offer competitive remuneration package and comprehensive fringe benefits including medical and life insurance, and different types of allowances to the right candidate. Interested parties, please submit your application online. For details, please visit our website http://www.bochk.com\n\nData collected would be used for recruitment purposes only. It might also be disclosed to our subsidiaries or Associated Companies to process the information for appointment. Applicants who do not hear from us within 8 weeks may consider their application unsuccessful and their data will be destroyed within 12 months of receipt.", "employment_types": ["Full Time", "Permanent"], "selling_points": [], "locations": ["Not Specified"], "categories": ["Banking / Finance", "Investment", "Retail Banking", "Management", "General Management"], "post_time": "2022-01-14T08:54:38Z", "salary": {"currency": null, "max": null, "min": null, "period": "monthly", "term": null}, "salary_visible": false, "title_keywords": ["manager"], "responsibilities": ["management", "conduct market research", "developing", "project management", "promotional materials", "reports", "internal parties"], "requirements": {"degrees": ["degree holder"], "majors": ["finance", "bba", "related disciplines", "information technology"], "languages": ["english", "chinese", "mandarin"], "language_level": ["advantage", "good command", "fluent"], "hard_skills": ["project management"], "soft_skills": ["self-motivated", "good team player", "work independently", "under pressure", "project management", "communication and interpersonal skills", "comprehensive", "innovative"], "languages_combined": [{"language": "english", "language_level": ["good command"]}, {"language": "chinese", "language_level": ["good command"]}, {"language": "mandarin", "language_level": ["fluent", "advantage"]}]}, "experience_required": {"duration": [], "field": ["finance", "project management", "management", "banking industry"]}}, {"job_id": "100003009042826", "location_code": "hk", "company": "Industrial and Commercial Bank Of China (Asia) Limited", "job_title": "Investment Consultant, Retail Banking and Wealth Management Department", "description": "Job Responsibilities\nClose liaison with Branches to prepare the sales plans and sales activities\nReview tactical and strategic plans to boost the sales revenue in order to achieve year end assigned target within regulatory framework\nDevelop the sales capacity, sales coaching, training and sales advisory support\nManage the sales force with the aim to achieve sales target performance\nObtain a thorough understanding of the Hong Kong regulatory framework, in particular related investment / insurance ordinances and guidelines issued by the HKMA and SFC to ensure frontline compliance\nClosely monitor high net worth clients\u2019 portfolios to continue enhance customers\u2019 experience\nJob Requirement\nBachelor degree or above in Business, Finance, Economics or other related discipline; CFA, CFP, FRM holders are preferable\n4-8 years related working and field experience with solid knowledge on investment and insurance products\nExcellent communication skill and presentation skill, with strong influencing skill and analytical skill\nProficient in MS Office including Word, Excel and Powerpoint\nFluent in Cantonese, English and Mandarin\n\u00a0", "employment_types": ["Full Time"], "selling_points": [], "locations": ["Central"], "categories": ["Banking / Finance", "Retail Banking"], "post_time": "2022-01-12T08:56:48Z", "salary": {"currency": null, "max": null, "min": null, "period": "monthly", "term": null}, "salary_visible": false, "title_keywords": ["wealth management", "investment consultant"], "responsibilities": ["sales activities", "strategic plans", "boost the sales", "guidelines", "sales target", "review", "compliance", "monitor", "develop", "sales plans", "insurance"], "requirements": {"degrees": ["degree or above", "bachelor"], "majors": ["finance", "business", "economics"], "languages": ["cantonese", "english", "mandarin"], "language_level": ["fluent"], "hard_skills": ["presentation skill", "excel", "analytical skill", "cfa", "word", "powerpoint", "frm", "ms office"], "soft_skills": ["presentation skill", "analytical skill", "communication skill"], "languages_combined": [{"language": "cantonese", "language_level": ["fluent"]}, {"language": "english", "language_level": ["fluent"]}, {"language": "mandarin", "language_level": ["fluent"]}]}, "experience_required": {"duration": ["4-8 years"], "field": ["related", "investment", "insurance products"]}}, {"job_id": "100003009043135", "location_code": "hk", "company": "Chasseur Pro Executive Consultant Limited", "job_title": "Bancassurance / Financial Planning Manager / Insurance Specialist (HKD 20,000 - HKD 38,000)", "description": "Financial Planning Manager / Insurance Specialist / Bancassurance (HKD 20,000 - HKD 38,000)\n\nWORK in BRANCH (RETAIL BANK)\n\nJob Duty\n\nCollaborate\u00a0with Relationship Manager\u00a0in Branch to provide insurance planning services to customer\nMaintain good relationship\u00a0with existing customer\u00a0and develop potential\u00a0client base\nEngage appointments to cross-sell insurance products and close deals\nComply with\u00a0Banking\u00a0policies and procedures.\u00a0\n\nRequirement\u00a0\n\nAt least 2 years relevant experience\nExtensive knowledge on insurance products and services\nGood communication, interpersonal and selling skills\nPassed IIQE Paper 1, 2, 3 & 5\nFluent mandarin speaking is definitely an advantage", "employment_types": ["Full Time"], "selling_points": ["Up to 38K basic with High incentive", "Local in retail bank with customer base", "Bank provide support for finding business"], "locations": ["Not Specified"], "categories": ["Banking / Finance", "Retail Banking", "Financial Services", "Insurance", "Insurance Agent / Broker"], "post_time": "2022-01-12T09:53:39Z", "salary": {"currency": "HKD", "max": 44999, "min": 30000, "period": "monthly", "term": null}, "salary_visible": true, "title_keywords": ["insurance specialist", "manager"], "responsibilities": ["collaborate with", "policies", "procedures", "maintain good relationship", "develop", "communication", "client base", "banking", "insurance", "planning"], "requirements": {"degrees": [], "majors": [], "languages": ["mandarin"], "language_level": ["advantage", "fluent"], "hard_skills": ["iiqe paper"], "soft_skills": ["communication", "extensive", "interpersonal"], "languages_combined": [{"language": "mandarin", "language_level": ["advantage", "fluent"]}]}, "experience_required": {"duration": ["at least 2 years"], "field": ["relevant experience"]}}, {"job_id": "100003009045028", "location_code": "hk", "company": "Hang Seng Bank Ltd", "job_title": "Assistant Form Delivery and Assurance Manager", "description": "WPB\u00a0Chief Operating Office\n\nWe are currently seeking high caliber professionals to join our department as\u00a0Assistant Form Delivery and Assurance Manager.\n\n\n\nPrincipal responsibilities\n\nTo develop high-quality forms with professional layout and format by applying various desktop publishing application software\nTo be a SME on form development and production by adopting various desktop publishing application software\nTo provide mentorship on form\u2019s technical aspects in the team and to help solving problematic cases\nTo monitor the end-to-end replenishment process and to ensure sufficient & quality stocks are ordered for users across the bank\u00a0\nTo provide supports on vendor management and to propose solutions for driving improvement on quality assurance\nTo conduct the recharge mechanism effectively and to ensure accurate values to be posted\nTo suggest and to engage in any process streamline initiative or projects\nRequirements:\nUniversity graduate in any disciplines or other relevant qualifications\nMinimum 2 to 5 years solid banking experience in any disciplines\nGood communication and problem-solving skills\u00a0\nGood time management with the ability to prioritize tasks and be detail-cautious\u00a0\nGood Leadership to provide guidance to team-members\u00a0\nGood negotiation skills to liaise with demanding stakeholders\u00a0\nProficient in MS Excel/Word, and preferably Adobe Illustrator, Acrobat, AEM Form - Designer and JavaScript\n\n\nIf you would like to explore other opportunities at Hang Seng Hong Kong, please visit www.hangseng.com/careers/ for details.\n\nThe health and safety of our employees and candidates is very important to us. Due to the current situation related to the Novel Coronavirus (2019-nCoV), we\u2019re leveraging our digital capabilities to ensure we can continue to recruit top talent at the HSBC Group. As your application progresses, you may be asked to use one of our digital tools to help you through your recruitment journey. If so, one of our Resourcing colleagues will explain how our video-interviewing technology will be used throughout the recruitment process and will be on hand to answer any questions you might have.\n\nAll information provided by applicants will be used only for recruitment purposes and will be used strictly in accordance with the Bank's personal data policies, a copy of which may be obtained by the applicant upon request. Unless otherwise instructed in writing by the applicant concerned, applicants may be considered for other suitable positions within the Bank and its related companies. The personal data of unsuccessful job applicants may be retained for a maximum of two years from the date when the job application is rejected and such data may be retained for a longer period if there is a subsisting reason that obliges the Bank to do so, after which the personal data will be destroyed.", "employment_types": ["Full Time", "Permanent"], "selling_points": [], "locations": ["Not Specified"], "categories": ["Banking / Finance", "Retail Banking", "Others", "Wealth Management"], "post_time": "2022-01-13T06:56:17Z", "salary": {"currency": null, "max": null, "min": null, "period": "monthly", "term": null}, "salary_visible": false, "title_keywords": ["manager", "assistant"], "responsibilities": ["management", "software", "quality", "monitor", "replenishment", "develop", "sme", "desktop publishing"], "requirements": {"degrees": ["university graduate"], "majors": ["any disciplines"], "languages": [], "language_level": [], "hard_skills": ["acrobat", "word", "adobe illustrator", "reason", "ms excel", "javascript", "problem-solving skills"], "soft_skills": ["prioritize", "communication", "negotiation skills", "problem-solving skills", "novel", "time management", "leadership"], "languages_combined": []}, "experience_required": {"duration": ["minimum 2 to 5 years"], "field": ["banking experience"]}}, {"job_id": "100003009042718", "location_code": "hk", "company": "Hang Seng Bank Ltd", "job_title": "Fraud Management Manager", "description": "WPB COO Office\n\nWe are currently seeking a high caliber professional to join our department as\u00a0Fraud Management Manager.\n\n\n\nPrincipal responsibilities\n\nDesign and drive the implementation of effective fraud mitigation strategies for WPB\nAct as SME for cross line of businesses in providing fraud management advices\nSupporting management oversight and reporting in governance meetings\nProject management the local deployment of regional projects and fraud systems\nManage merchant fraud risk as an acquiring bank\nCollaborate with business teams, fraud analytics and fraud operations teams to ensure thorough consideration of fraud risk implications and mitigation in the delivery of banking products and services\nRequirements\nUniversity degree in Business Administration, Statistics, Risk Management or other relevant qualification\nSolid experience and knowledge in managing fraud risk gained in financial industry\u00a0\u00a0\nKnowledge in merchant fraud risk management would be an advantage\u00a0\nSound business acumen, able to make judgment with strong sense of ownership\nExcellent communication, interpersonal and organization skills\nProficiency in both English and Chinese\nGreat sense of ownership and servicing mind-set to ensure efficient and effective customer service delivery\n\nIf you would like to explore other opportunities at Hang Seng Hong Kong, please visit\u00a0www.hangseng.com/careers/\u00a0for details.\n\nThe health and safety of our employees and candidates is very important to us. Due to the current situation related to the Novel Coronavirus (2019-nCoV), we\u2019re leveraging our digital capabilities to ensure we can continue to recruit top talent at the HSBC Group.\u00a0 As your application progresses, you may be asked to use one of our digital tools to help you through your recruitment journey.\u00a0 If so, one of our\u00a0 Resourcing colleagues will explain how our video-interviewing technology will be used throughout the recruitment process and will be on hand to answer any questions you might have.\n\nAll information provided by applicants will be used only for recruitment purposes and will be used strictly in accordance with the Bank's personal data policies, a copy of which may be obtained by the applicant upon request. Unless otherwise instructed in writing by the applicant concerned, applicants may be considered for other suitable positions within the Bank and its related companies. The personal data of unsuccessful job applicants may be retained for a maximum of two years from the date when the job application is rejected and such data may be retained for a longer period if there is a subsisting reason that obliges the Bank to do so, after which the personal data will be destroyed.\n", "employment_types": ["Full Time", "Permanent"], "selling_points": [], "locations": ["Not Specified"], "categories": ["Banking / Finance", "Retail Banking", "Financial Services", "Risk Management"], "post_time": "2022-01-13T00:54:37Z", "salary": {"currency": null, "max": null, "min": null, "period": "monthly", "term": null}, "salary_visible": false, "title_keywords": ["manager"], "responsibilities": ["collaborate with", "reporting", "management", "operations", "systems", "teams", "implementation", "design", "project management", "banking", "sme"], "requirements": {"degrees": ["university degree"], "majors": ["risk management", "statistics", "business administration"], "languages": ["english", "chinese"], "language_level": ["proficiency"], "hard_skills": ["make", "reason", "acumen"], "soft_skills": ["efficient", "organization skills", "communication", "customer service", "business acumen", "novel", "interpersonal"], "languages_combined": [{"language": "english", "language_level": ["proficiency"]}, {"language": "chinese", "language_level": ["proficiency"]}]}, "experience_required": {"duration": [], "field": ["financial industry"]}}, {"job_id": "100003009043193", "location_code": "hk", "company": "Manulife (International) Limited", "job_title": "Financial Planning officer / Wealth Management Manager", "description": "\u201dWe are working hard to not only change ourselves, but to reshape our industry. Our Mission is to help people make their decisions easier and lives better.\u201d\n\u300c \u6211\u5011\u4e0d\u50c5\u5c0b\u6c42\u81ea\u5df1\u7684\u9769\u65b0\uff0c\u4ea6\u81f4\u529b\u65bc\u884c\u696d\u7684\u9769\u65b0\u3002\u6211\u5011\u7684\u4f7f\u547d\u662f\u5e6b\u52a9\u4eba\u5011\u8f15\u9b06\u4f5c\u51fa\u660e\u667a\u6289\u64c7\uff0c\u5be6\u73fe\u7cbe\u5f69\u4eba\u751f\u3002\u300d\n\nWe offer:\n- Provide good training to be a professional financial planner\n- Unlimited Income: Monthly allowance, High commission, Unique monthly bonus, Year-end bonus, Mortgage subsidy\n-\u00a0Fast-track Promotion Program to Management Level\n- Free oversea travel\n- Flexible working hours\n- Work life balance opportunity\n\nWe are looking for:\n- Associate degree / higher diploma holder or above\n-\u00a0Welcome fresh graduates\n- Self discipline candidates\n\nJob Descriptions:\nProfessional Financial Services Provision to Clients\n- Risk Management Planning\n- Wealth Management & Portfolio Advices\n- Retirement Planning\n- Investment Planning", "employment_types": ["Full Time", "Permanent"], "selling_points": ["\u201cManulife, manage life, man new life\u201d", "We take a leading role or even No.1 in the market", "Monthly income 18k-30k with generous commission"], "locations": ["Ngau Tau Kok"], "categories": ["Banking / Finance", "Retail Banking", "Insurance", "Insurance Agent / Broker", "Sales, CS & Business Devpt", "Direct Sales"], "post_time": "2022-01-12T10:11:04Z", "salary": {"currency": "HKD", "max": 44999, "min": 17000, "period": "monthly", "term": null}, "salary_visible": true, "title_keywords": ["officer", "wealth management manager"], "responsibilities": [], "requirements": {"degrees": [], "majors": [], "languages": [], "language_level": [], "hard_skills": ["make"], "soft_skills": [], "languages_combined": []}, "experience_required": {"duration": [], "field": []}}, {"job_id": "100003009044009", "location_code": "hk", "company": "PI Business Consulting Limited", "job_title": "Strategist (Project Manager)", "description": "\n\nRequirements:\n- Degree holder in Business Administration, Management or related disciplines;\n- At\u00a0least\u00a05 years\u00a0project management\u00a0experience in either one of the following areas:\u00a0corporate banking, auditing,\u00a0IT;\n-Knowledge in financial analysis\u00a0or auditing is definitely an advantage;\n- Good project management and organizational skills with strategic mindset;\n- Analytical, independent and possession of good communication skills;\n- Proficient in both spoken and written English and Chinese, fluent in Putonghua is preferable.\n- Immediate available is highly preferred.", "employment_types": ["Full Time"], "selling_points": ["Project Management", "Clear Mindset", "banking or auditing background"], "locations": ["Central"], "categories": ["Banking / Finance", "Retail Banking"], "post_time": "2022-01-13T02:46:04Z", "salary": {"currency": null, "max": null, "min": null, "period": "monthly", "term": null}, "salary_visible": false, "title_keywords": ["project manager"], "responsibilities": ["management", "financial analysis", "project management", "communication", "banking", "auditing", "administration"], "requirements": {"degrees": ["degree holder"], "majors": ["related disciplines", "business administration"], "languages": ["putonghua", "english", "chinese"], "language_level": ["fluent", "proficient"], "hard_skills": ["financial analysis", "project management"], "soft_skills": ["communication skills", "project management", "independent", "organizational skills"], "languages_combined": [{"language": "putonghua", "language_level": ["fluent", "proficient"]}, {"language": "english", "language_level": ["fluent", "proficient"]}, {"language": "chinese", "language_level": ["fluent", "proficient"]}]}, "experience_required": {"duration": ["at least 5 years"], "field": ["project management", "it", "banking"]}}, {"job_id": "100003009049575", "location_code": "hk", "company": "China Construction Bank (Asia) Corporation Limited", "job_title": "AVP/VP, Sanctions Compliance", "description": "Job Descriptions:\n\n\nParticipate in sanctions review projects and initiatives related to sanctions topics\n\nProvide advisory support and coordinate on sanctions-related issues\n\nReview and coordinate sanctions-related escalations (customer level and transaction level)\n\nFacilitate transactions in all business line by providing sanctions advisory support\n\nWork closely with relevant local compliance teams in establishment of appropriate sanctions controls, monitoring procedure and framework based on Head Office and regulatory requirements\n\n\u00a0Requirements:\n\nBachelor degree or above, major in law is preferred\n\nDepending on the seniority of the associate, at least 3 years work experience in sanctions-related advisory role\n\nQualification in ECF is preferred\n\nKnowledge of sanctions law is an advantage\n\nAble to work independently under fast-pace and pressure\n\nFamiliar with international sanction regimes and key development\n\nPossess good organizational, technical and coordination skill and detail minded\n\nAble to perform extensive research to validate required documents and information\n\nExcellent interpersonal and communication skills in both Chinese and English (verbal and written)\n\nPlease send your application with both current and expected salary for reference.\n\n\nApplicants who are not contacted within 8 weeks may consider their applications unsuccessful and their personal data will be retained by the bank for a period up to two years.\n\nAll information provided by applicants will be used for recruitment purposes only and will be used strictly in accordance with the bank\u2019s personal data policies, a copy of which will be provided upon request.", "employment_types": ["Full Time", "Permanent"], "selling_points": ["sanctions review", "review sanctions-related escalations", "at least 3 years relevant work experience"], "locations": ["Kowloon Bay"], "categories": ["Banking / Finance", "Retail Banking", "Others", "Professional Services", "Legal & Compliance"], "post_time": "2022-01-14T08:54:12Z", "salary": {"currency": null, "max": null, "min": null, "period": "monthly", "term": null}, "salary_visible": false, "title_keywords": [], "responsibilities": ["regulatory requirements", "compliance", "review", "teams", "transactions", "monitoring", "coordinate"], "requirements": {"degrees": ["degree or above", "bachelor"], "majors": ["law"], "languages": ["english", "chinese"], "language_level": ["excellent"], "hard_skills": [], "soft_skills": ["communication skills", "work independently", "coordination skill", "organizational", "extensive", "interpersonal"], "languages_combined": [{"language": "english", "language_level": ["excellent"]}, {"language": "chinese", "language_level": ["excellent"]}]}, "experience_required": {"duration": ["at least 3 years"], "field": ["related"]}}, {"job_id": "100003009036721", "location_code": "hk", "company": "China Construction Bank (Asia) Corporation Limited", "job_title": "Customer Service Officer (RM Assistant)", "description": "Job Descriptions:-\u00a0\n\nProvide sales and service support to Relationship Manager in serving consolidated banking customers\nEnsure that all service queries are resolved timely\nPerform banking transaction & response to account enquiries\nHandle general enquiries / complaints and resolve issues\nProvide good after-sales support and logistics as assigned\nDeliver superior quality service to customers and refer potential customers to Relationship Manager in the branch\nAssist in meeting overall branch sales and service target\n\nRequirements:\u00a0-\u00a0\n\nDegree holder\nPossess HKIA & HKSI qualifications\nMinimum 2 years of relevant sales and customer service experience in banking industry\nGood service orientation and attentive to details\nProactive with good communications and interpersonal skills\nGood command of English, Cantonese and Mandarin\n\nApplicants who are not contacted within 8 weeks may consider their applications unsuccessful and their personal data will be retained by the bank for a period up to two years.\n\nAll information provided by applicants will be used for recruitment purposes only and will be used strictly in accordance with the bank\u2019s personal data policies, a copy of which will be provided upon request.", "employment_types": ["Full Time", "Permanent"], "selling_points": ["Provide sales and service support to RM", "customer service", "banking sales and customer service experience"], "locations": ["Not Specified"], "categories": ["Banking / Finance", "Investment", "Retail Banking", "Others"], "post_time": "2022-01-10T13:08:27Z", "salary": {"currency": null, "max": null, "min": null, "period": "monthly", "term": null}, "salary_visible": false, "title_keywords": ["assistant", "customer service officer"], "responsibilities": ["quality", "logistics", "banking"], "requirements": {"degrees": ["degree holder"], "majors": [], "languages": ["cantonese", "english", "mandarin"], "language_level": ["good command"], "hard_skills": ["hksi"], "soft_skills": ["customer service", "interpersonal skills", "proactive", "attentive to details"], "languages_combined": [{"language": "cantonese", "language_level": ["good command"]}, {"language": "english", "language_level": ["good command"]}, {"language": "mandarin", "language_level": ["good command"]}]}, "experience_required": {"duration": ["minimum 2 years"], "field": ["banking industry", "customer service"]}}, {"job_id": "100003009039976", "location_code": "hk", "company": "OCBC Wing Hang Bank Limited", "job_title": "Wealth Management Trainee", "description": "Grasp the chance to start your career in the banking industry through participating in our Wealth Management Trainee Programme which offers you an exciting career development journey. Successful candidates will undergo a 24-months fast track career development programme consisting of training, job attachment and senior management mentorship to build your professional knowledge of different banking products, customer relationship management skills and selling techniques.\n\nAccountabilities\n\nDeliver quality service to customer and handle customers\u2019 enquiries on general banking products and services\nAcquire new customers and depositors to fulfilling the Key Performance Indictor as required\nIdentify potential customers in order to sell integrated financial services packages and other general banking products\nAssist Relationship Manager and Personal Banker on administrative duties, account opening and cross selling or ad hoc assignments\nManage the sales and service environment of a branch in effective manner\nMaintain and develop good customer relationship\nProvide back-up support to branch operations\nAdherence to the Bank\u2019s guidelines and policies\n\nRequirements\n\nFresh university graduates with passion in banking industry\nCustomer services or sales experience in any industry is preferred\nGood communication and interpersonal skills\nGood command of spoken & written English & Chinese\nFluent in Mandarin a definite advantage\nHolder of HKSI Paper 1, 7,8 and / or IIQE Paper 1, 2 & 3 are preferred but not a must", "employment_types": ["Full Time", "Permanent"], "selling_points": ["24-months fast track career development programme", "Maintain and develop good customer relationship", "Fresh university graduates"], "locations": ["Not Specified"], "categories": ["Banking / Finance", "Retail Banking", "Wealth Management"], "post_time": "2022-01-11T16:05:44Z", "salary": {"currency": null, "max": null, "min": null, "period": "monthly", "term": null}, "salary_visible": false, "title_keywords": ["wealth management", "trainee"], "responsibilities": ["management", "guidelines", "account opening", "operations", "policies", "quality", "banking", "develop", "customer services", "communication", "maintain", "administrative duties", "ad hoc assignments", "career development", "senior management"], "requirements": {"degrees": [], "majors": [], "languages": ["english", "chinese", "mandarin"], "language_level": ["advantage", "good command", "fluent"], "hard_skills": ["iiqe paper", "account opening", "hksi paper"], "soft_skills": ["communication and interpersonal skills", "passion in"], "languages_combined": [{"language": "english", "language_level": ["good command"]}, {"language": "chinese", "language_level": ["good command"]}, {"language": "mandarin", "language_level": ["fluent", "advantage"]}]}, "experience_required": {"duration": [], "field": ["customer services"]}}, {"job_id": "100003009050656", "location_code": "hk", "company": "Bank of Communications (Hong Kong) Limited", "job_title": "Deputy Chief Business Analyst (Retail Banking Business)", "description": "Career Level\nSenior\nQualification\nDegree\nYears of Experience\n5 years\nJob Type\nFull Time\nJob Functions\nBanking / Finance, Retail Banking, Others", "employment_types": ["Full Time"], "selling_points": [], "locations": ["Not Specified"], "categories": ["Banking / Finance", "Retail Banking", "Others"], "post_time": "2022-01-14T11:07:31Z", "salary": {"currency": null, "max": null, "min": null, "period": "monthly", "term": null}, "salary_visible": false, "title_keywords": ["deputy chief business analyst"], "responsibilities": ["banking"], "requirements": {"degrees": ["degree"], "majors": [], "languages": [], "language_level": [], "hard_skills": [], "soft_skills": [], "languages_combined": []}, "experience_required": {"duration": [], "field": []}}, {"job_id": "100003009033666", "location_code": "hk", "company": "Bank of Communications (Hong Kong) Limited", "job_title": "Financial Services Manager \u2013 Wealth and Personal Banking", "description": "Responsibilities:\nPromote full-range of retail banking products and services to achieve sales targets\nIdentify customers\u2019 needs and match their needs with appropriate products and services including account opening, credit card, mortgage, personal loan and insurance and MPF products.\nMaintain good relationship with both existing and new clients.\nRequirements:\nDegree holder or above, with minimum 3 years\u2019 experience in promoting retail banking products.\nPasses in Insurance, Securities and Futures Intermediaries Examinations are required. (Qualified under SFO for handling Regulated Activities Types 1 & 4).\nPass in the MPF Intermediaries Qualifying Examination (Optional)\nProfessional qualification of ARWP is an advantage.\nCandidates with less experience will be considered as Deputy Financial Services Manager.\nCandidates with more experience will be considered as Senior Investment & Product Manager (Private Banking)", "employment_types": ["Full Time"], "selling_points": ["Fast track to CRM position", "Excellent career progression", "Experience in branch frontline customer service"], "locations": ["Not Specified"], "categories": ["Banking / Finance", "Retail Banking", "Financial Services", "Wealth Management"], "post_time": "2022-01-10T01:33:19Z", "salary": {"currency": null, "max": null, "min": null, "period": null, "term": null}, "salary_visible": false, "title_keywords": ["personal", "manager"], "responsibilities": ["mpf", "account opening", "maintain good relationship", "banking", "insurance"], "requirements": {"degrees": ["degree holder"], "majors": [], "languages": [], "language_level": [], "hard_skills": ["sfo"], "soft_skills": [], "languages_combined": []}, "experience_required": {"duration": ["minimum 3 years"], "field": ["retail banking", "financial services", "investment", "banking"]}}, {"job_id": "100003009049578", "location_code": "hk", "company": "China Construction Bank (Asia) Corporation Limited", "job_title": "Manager /Assistant Vice President, Data Management", "description": "Responsibilities:\n\n\nFollow the guidelines of Data Governance model from Head Office to setup the Bank's own Data Governance framework, and act abide by it\nEnvision & shape the governance, scope, framework and implementation plan in relationship to data quality management\nCollaborate effectively with technology, operations/ process, business and other stakeholders to formulate and lead project team on data quality to define data quality governance structure, identify critical data elements, and define data quality dashboards/ KPIs for ongoing monitor and review\nPerform data quality profiling and analysis, identify issues where applicable\nFormulate remediation strategy/ approach; drive, coordinate and collaborate with stakeholders on remediation activities; orchestrate between different data quality initiatives\nDevelop MI reports to provide business insight or review business performance\nAutomate the generation of regular reports to minimize human intervention\nSetup an effective mechanism to do ETL for external data, ensure the readiness and accuracy of data\nFacilitate the usage of OLAP tools and coordinate its related enhancements\u00a0\n\nRequirements:\n\n\nBachelor / Master degree in Computer Science, Data and Information Management or a related discipline\nMinimum 3 years' banking experience in information and data management, leads and campaign management, MI reporting with respect to programming and database architecture\nProven experience in leading and driving data quality management initiatives with measurable achievements\nTrack record of experience in data governance projects in banking industry\nKnowledge of data structures, data systems and tools and related software and data management policies and practices in a complex organizational environment an added advantage\nHands on experience in programming language : SAS, VBA, SQL etc.\nExcellence command of MS Excel (e.g. advanced formulas)\nBusiness process analysis skills, including the ability to analyze and document the current processes and organizations that create and manage the client data\nExcellent project management skill is a must with the ability to get things done through others not directly under his or her supervision\nGood command of written and spoken English, Chinese and Putonghua\nCandidates with less experience will be considered for the Manager position while candidates with more experience will be considered for the Vice President position\n\nPlease specify your current and expected package in your application for reference.\u00a0\n\nApplicants who are not contacted within 8 weeks may consider their applications unsuccessful and their personal data will be retained by the bank for a period up to two years.\n\nAll information provided by applicants will be used for recruitment purposes only and will be used strictly in accordance with the bank\u2019s personal data policies, a copy of which will be provided upon request.", "employment_types": ["Full Time", "Permanent"], "selling_points": ["Data Management", "Data Governance model", "Envision & shape the governance"], "locations": ["Not Specified"], "categories": ["Banking / Finance", "Corporate Banking", "Retail Banking", "Professional Services", "Business Analysis / Data Analysis"], "post_time": "2022-01-14T08:54:13Z", "salary": {"currency": null, "max": null, "min": null, "period": "monthly", "term": null}, "salary_visible": false, "title_keywords": ["manager", "assistant vice president"], "responsibilities": ["collaborate", "collaborate with", "management", "data", "guidelines", "operations", "analysis", "review", "quality", "implementation", "monitor", "develop", "coordinate", "reports", "plan", "kpis", "setup"], "requirements": {"degrees": ["bachelor", "master degree"], "majors": ["computer science"], "languages": ["putonghua", "english", "chinese"], "language_level": ["good command"], "hard_skills": ["vba", "data management", "sas", "analysis", "sql", "project management", "ms excel", "programming"], "soft_skills": ["advanced", "organizational", "ability to analyze", "hands on", "project management skill"], "languages_combined": [{"language": "putonghua", "language_level": ["good command"]}, {"language": "english", "language_level": ["good command"]}, {"language": "chinese", "language_level": ["good command"]}]}, "experience_required": {"duration": ["minimum 3 years"], "field": ["banking industry", "management", "banking experience", "sql", "programming", "quality management", "database"]}}, {"job_id": "100003009039175", "location_code": "hk", "company": "Hang Seng Bank Ltd", "job_title": "Assistant Sales Management Manager", "description": "Customer Contact Centre\n\nHang Seng's Customer Contact Centre has been ranked one of the best phone banking service providers for consecutive years. Our team strives to provide professional services for a wide range of banking products to address customers' different services and financial needs.\n\nWe are currently seeking high caliber professionals to join our Sales\u00a0Management\u00a0Section as\u00a0Assistant Sales Management Manager.\n\n\nPrincipal responsibilities:\n\nImprove contact centre sales capabilities through smoothening the implementation of various new telesales products\nDevelop sales knowledge centre and identify areas of improvement on customer experience and sales quality\nElevate professionalism and consultative selling skills of sales team through in-depth review on the activities of the individual sales staff\nPrepare and support telesales sales training to ensure standardization on sales quality standard and uplift overall sales performance\nCoordinate on behalf of Sales Team with other functions on sales management related tasks\nAssist in sales administrative works, e.g. prepare performance report, implement staff motivation initiatives etc.\n\nRequirements\nUniversity degree or Diploma in business disciplines or related disciplines\nMinimum of three years' banking experience with good understanding of bank products and services, experience in telesales training and telesales quality management would be an advantage.\nBe proactive, vigilant and paying attentions to details\nGood analytical mind\nA team player with good communications skills\nProficiency in both English, Chinese and Putonghua\n\nIf you would like to explore other opportunities at Hang Seng Hong Kong, please visit\u00a0www.hangseng.com/careers/\u00a0for\u00a0details\n\nThe health and safety of our employees and candidates is very important to us. Due to the current situation related to the Novel Coronavirus (2019-nCoV), we\u2019re leveraging our digital capabilities to ensure we can continue to recruit top talent at the HSBC Group.\u00a0 As your application progresses, you may be asked to use one of our digital tools to help you through your recruitment journey.\u00a0 If so, one of our Resourcing colleagues will explain how our video-interviewing technology will be used throughout the recruitment process and will be on hand to answer any questions you might have.\n\nAll information provided by applicants will be used only for recruitment purposes and will be used strictly in accordance with the Bank's personal data policies, a copy of which may be obtained by the applicant upon request. Unless otherwise instructed in writing by the applicant concerned, applicants may be considered for other suitable positions within the Bank and its related companies. The personal data of unsuccessful job applicants may be retained for a maximum of two years from the date when the job application is rejected and such data may be retained for a longer period if there is a subsisting reason that obliges the Bank to do so, after which the personal data will be destroyed.\n", "employment_types": ["Full Time", "Permanent"], "selling_points": [], "locations": ["Not Specified"], "categories": ["Banking / Finance", "Retail Banking"], "post_time": "2022-01-12T02:12:26Z", "salary": {"currency": null, "max": null, "min": null, "period": "monthly", "term": null}, "salary_visible": false, "title_keywords": ["sales", "manager", "assistant"], "responsibilities": ["sales performance", "review", "quality", "implementation", "develop", "coordinate", "sales team", "contact", "sales management", "report"], "requirements": {"degrees": ["university degree", "diploma"], "majors": ["related disciplines", "business"], "languages": ["putonghua", "english", "chinese"], "language_level": ["proficiency"], "hard_skills": ["reason"], "soft_skills": ["analytical mind", "team player", "proactive", "novel"], "languages_combined": [{"language": "putonghua", "language_level": ["proficiency"]}, {"language": "english", "language_level": ["proficiency"]}, {"language": "chinese", "language_level": ["proficiency"]}]}, "experience_required": {"duration": ["minimum of three years"], "field": ["quality management", "telesales", "training", "banking experience"]}}, {"job_id": "100003009031790", "location_code": "hk", "company": "The Bank of East Asia, Limited", "job_title": "Branch - Customer Services Officer/ Customer Services Representative (Teller)", "description": "Branch Distribution & Services\u00a0Department\n\nBranch - Customer Services Officer/Teller\u00a0(Job ID:\u00a02089)\n\n\u00a0Responsibilities:\n\nTo provide counter services to customers\nTo handle daily financial transactions and customers' enquiries\n\nRequirements:\n\nHKCEE/HKDSE or above, with 5 subjects, including Chinese, English and Mathematics, at Level 2/Attained/Grade E or above\nStrong desire to develop career in banking industry\nStrong commitment and good communication skills\nCandidate without relevant working experience will also be considered\n\n(Candidate with less working experience may be considered for the position of Customer Services Representative)\n\n(Candidate can choose to work for 4 days from Monday to Friday with\u00a0fringe benefits)\n\nPlease apply online via the BEA Careers website at\u00a0https://careers.hkbea.com/psp/hcmprd/EMPLOYEE/HRMS/c/HRS_HRAM.HRS_APP_SCHJOB.GBL?Page=HRS_APP_JBPST&Action=UFOCUS=Applicant&SiteId=1&JobOpeningId=2089&PostingSeq=1\u00a0or by clicking the \"Apply Now\" button below. Kindly note that if you are a new user, you have to first create your User Profile before you can apply.\n\nPersonal data provided by job applicants will be used for recruitment purposes only and will be treated in accordance with the Bank's Personal Information Collection (Employees) Statement and Privacy Policy Statement. Applicants who are not invited for interviews within six weeks may consider their applications unsuccessful and the personal data collected will be destroyed after six months.", "employment_types": ["Full Time", "Permanent"], "selling_points": ["To provide counter services to customers", "HKCEE/HKDSE or above", "Proficient in both English and Chinese"], "locations": ["Not Specified"], "categories": ["Banking / Finance", "Investment", "Retail Banking", "Others"], "post_time": "2022-01-07T19:20:51Z", "salary": {"currency": null, "max": null, "min": null, "period": null, "term": null}, "salary_visible": false, "title_keywords": ["customer services representative", "customer services officer"], "responsibilities": ["transactions"], "requirements": {"degrees": ["hkdse"], "majors": ["mathematics"], "languages": ["english", "chinese"], "language_level": [], "hard_skills": [], "soft_skills": ["communication skills"], "languages_combined": [{"language": "english", "language_level": []}, {"language": "chinese", "language_level": []}]}, "experience_required": {"duration": [], "field": ["relevant working experience", "customer services"]}}, {"job_id": "100003009031736", "location_code": "hk", "company": "The Bank of East Asia, Limited", "job_title": "Branch - Personal Banking Officer", "description": "Branch Distribution & Services Department\u00a0\n\nBranch - General Banking Officer\u00a0(Job ID: 1705)\n\nResponsibilities\n\nTo build long-term relationships with customers\nTo identify customers' needs and match their needs with appropriate products and services\nTo acquire new customers through sales and marketing activities\nTo coordinate in-branch and off-site promotions\n\nRequirements\n\n\nUniversity graduates preferred, with a minimum of half a year's banking experience, preferably in retail banking and/or business-related field\nPass in the Hong Kong Securities Institute Licensing Examination or an Exempted / Qualified Securities Dealer (optional)\nPasses in\u00a0the MPF and Insurance Intermediaries Qualifying Examinations (optional)\nPro-active, mature, independent, customer-focused, and pleasant\nProficient in both spoken and written English and Chinese, knowledge of Putonghua will be an advantage\n\n(Candidates with customer services experience in other industries will also be considered)\n\nPlease apply online via the BEA Careers website at https://careers.hkbea.com/psp/hcmprd/EMPLOYEE/HRMS/c/HRS_HRAM.HRS_APP_SCHJOB.GBL?Page=HRS_APP_JBPST&Action=UFOCUS=Applicant&SiteId=1&JobOpeningId=1705&PostingSeq=1 or by clicking the \"Apply Now\" button below. Kindly note that if you are a new user, you have to first create your User Profile before you can apply.\n\nPersonal data provided by job applicants will be used for recruitment purposes only and will be treated in accordance with the Bank's Personal Information Collection (Employees) Statement and Privacy Policy Statement. Applicants who are not invited for interviews within six weeks may consider their applications unsuccessful and the personal data collected will be destroyed after six months.\n", "employment_types": ["Full Time", "Permanent"], "selling_points": ["To build long-term relationships with customers", "University graduates preferred,", "identify customers' needs and match their needs"], "locations": ["Not Specified"], "categories": ["Banking / Finance", "Retail Banking", "Financial Services", "Others"], "post_time": "2022-01-07T19:20:48Z", "salary": {"currency": null, "max": null, "min": null, "period": null, "term": null}, "salary_visible": false, "title_keywords": ["officer", "personal"], "responsibilities": ["coordinate", "customers' needs"], "requirements": {"degrees": [], "majors": [], "languages": ["putonghua", "english", "chinese"], "language_level": ["advantage", "proficient"], "hard_skills": ["c"], "soft_skills": ["customer-focused", "independent", "mature", "pleasant", "pro-active"], "languages_combined": [{"language": "putonghua", "language_level": ["advantage", "proficient"]}, {"language": "english", "language_level": ["advantage", "proficient"]}, {"language": "chinese", "language_level": ["advantage", "proficient"]}]}, "experience_required": {"duration": [], "field": ["banking experience", "related", "retail banking", "customer services", "business"]}}, {"job_id": "100003009049394", "location_code": "hk", "company": "Ambition", "job_title": "Assistant Manager, Unsecured Loan Product", "description": "\nAssistant Manager, Unsecured Loan Product\n\nOur client is a leading banking group with diversified businesses in Retail, Corporate and Private banking. With their continuous growth, an excellent opportunity has arisen for a high-calibre product management professional to join their retail banking business.\nReporting to the Team Lead, you will assist in developing and enhancing unsecured loan product. You will assist to formulate and launch unsecured loan product marketing strategies. You will be responsible for liaising with internal and external parties for new product initiatives, executing marketing campaigns to support the business growth. You will also need to prepare training for sales channels on product and campaign details.\n\nTo qualify, individuals must possess:\n\nBachelor degree or above in related discipline\nMinimum 2 years' experience in personal loan and / or card loan, product development, product management gained from Banks, Credit Card and/or other Financial Institutions\nStrong analytical, interpersonal and communication skills\nStrong communications skills in English and Chinese\n\n\n\nContact Petty LAM on (852) 3103 4363 or via email petty.lam@ambition.com.hk, APPLY NOW by clicking the button below quoting reference number PL 252068 www.ambition.com.hk\nData provided is for recruitment purposes only\n\nIf this job isn't quite right for you, but you know someone who would be great at this role, why not take advantage of our referral scheme? We offer HKD1000 in Apple gift cards for every referred candidate who we place in a role. Terms & Conditions Apply. https://www.ambition.com.hk/refer-a-friend", "employment_types": ["Full Time", "Permanent"], "selling_points": ["Sizeable retail bank", "Open to loan product experience", "Attractive salary and bonuses"], "locations": ["Not Specified"], "categories": ["Banking / Finance", "Loan", "Retail Banking", "Financial Services"], "post_time": "2022-01-14T08:33:01Z", "salary": {"currency": null, "max": null, "min": null, "period": "monthly", "term": null}, "salary_visible": false, "title_keywords": ["assistant manager,"], "responsibilities": ["reporting", "management", "marketing strategies", "data", "internal and external parties", "developing", "liaising with", "communication", "executing", "contact", "marketing campaigns", "banking", "recruitment"], "requirements": {"degrees": ["degree or above", "bachelor"], "majors": [], "languages": ["english", "chinese"], "language_level": [], "hard_skills": ["pl", "scheme"], "soft_skills": ["communication skills", "interpersonal", "responsible"], "languages_combined": [{"language": "english", "language_level": []}, {"language": "chinese", "language_level": []}]}, "experience_required": {"duration": ["minimum 2 years"], "field": ["product management", "product development", "credit card", "financial institutions"]}}, {"job_id": "100003009042210", "location_code": "hk", "company": "OCBC Wing Hang Bank Limited", "job_title": "Associate / Assistant Manager, Administration & Compliance", "description": "Responsibilities\n\nAssist Manager on executing compliance control and reviewing various compliance topics including AML, Operational Risk etc.\nConduct Data Quality Sampling check.\nAct as IT coordinator in solving IT problems and communicating with IT Department for various technical issues.\nAssist Manager to organize training/briefing session regarding regulatory requirements, Corporate policies & procedures.\nPerform all round administrative tasks.\nSystem control on users\u2019 access rights.\nRequirements\n\nUniversity degree Minimum 3 years of relevant work experience\nAble to work under pressure and independent with good communication skill\nFamiliar with the use of MS Office\nFluent in written and spoken Chinese and English", "employment_types": ["Full Time", "Permanent"], "selling_points": ["Support compliance control and review tasks", "Responsible for IT & Administrative work", "Minimum 3 years relevant work experience"], "locations": ["Shau Kei Wan"], "categories": ["Banking / Finance", "Retail Banking"], "post_time": "2022-01-12T06:38:14Z", "salary": {"currency": null, "max": null, "min": null, "period": "monthly", "term": null}, "salary_visible": false, "title_keywords": ["associate", "assistant manager,"], "responsibilities": ["control", "aml", "data", "regulatory requirements", "policies", "compliance", "quality", "procedures", "communicating with", "executing", "administrative tasks"], "requirements": {"degrees": ["university degree"], "majors": [], "languages": ["english", "chinese"], "language_level": ["fluent"], "hard_skills": ["ms office"], "soft_skills": ["communication skill", "independent", "work under pressure"], "languages_combined": [{"language": "english", "language_level": ["fluent"]}, {"language": "chinese", "language_level": ["fluent"]}]}, "experience_required": {"duration": ["minimum 3 years"], "field": []}}, {"job_id": "100003009040259", "location_code": "hk", "company": "iFAST Financial (HK) Limited", "job_title": "Junior Client Investment Specialist/ Relationship Manager", "description": "Responsibilities:\n\nOrganize and implement business strategies to achieve\u00a0business and sales targets;\nDevelop and maintain clients\u2019 relationship;\nHandle the enquiries of the walk-in clients, including account opening, cheque deposit, transfer case and usage of our website;\nParticipate in marketing events, seminar and workshop.\n\nRequirements:\n\nBachelor degree in any discipline;\nMinimum 1 year working experience. Working experience in finance industry will be an advantage;\nSales and customer-oriented;\nGood knowledge of investment products.\n\nOur offer:\u00a0\n\nCareer development prospect;\n21+ days Annual Leave;\nMedical, Dental, Life Insurance;\nPerformance bonus and Performance Shares;\nEducation and Sports Allowance.\n\nOur company is an equal opportunities employer and welcome application from all qualified candidates.\u00a0Information provided will be treated with strict confidential and be used for the purpose of selection only.\u00a0Applicants who are not invited for interview within 10 weeks may consider their applications unsuccessful. Personal data of unsuccessful applicant will be destroyed within 12 months.", "employment_types": ["Full Time", "Permanent"], "selling_points": ["Career development prospect", "21+ days Annual Leave", "Staff performance shares"], "locations": ["Central"], "categories": ["Banking / Finance", "Retail Banking", "Financial Services", "Sales, CS & Business Devpt", "Account Servicing"], "post_time": "2022-01-12T02:02:09Z", "salary": {"currency": null, "max": null, "min": null, "period": "monthly", "term": null}, "salary_visible": false, "title_keywords": ["specialist", "relationship manager", "junior"], "responsibilities": ["marketing events", "account opening", "workshop", "website", "develop", "maintain"], "requirements": {"degrees": ["degree", "bachelor"], "majors": [], "languages": [], "language_level": [], "hard_skills": ["investment products"], "soft_skills": ["customer-oriented"], "languages_combined": []}, "experience_required": {"duration": ["minimum 1 year"], "field": ["finance industry"]}}, {"job_id": "100003009043134", "location_code": "hk", "company": "Chasseur Pro Executive Consultant Limited", "job_title": "Call Center / Customer Service Phone Banking / Loan Sales / Loan Officer (HKD $13,000 - HKD $20,000)", "description": "Call Center / Customer Service Phone Banking / Loan Sales / Loan Officer (HKD $13,000 - HKD $20,000)\n\nResponsibility:\n\nHandle in-bound call\u00a0to provide banking services\nNo selling target but good service is a must\n\nSkills and experience required:\n\nHigher diploma/ associate degree or above\nGood communication and interpersonal skills\nCustomer selling experience would be beneficial\nWorking experience in Bank will be preferred\nFresh grad will also be considered\n\n*** Will need to work on shift ***\n\nLatest shift will be until 10pm with ALLOWANCE (extra pay)\n\nThis entry level position provides ample promotion opportunities to branch service, sales, back office and other banking positions.\n\nSenior Loan Sales\u00a0will consider\u00a0for General Banking Officer and\u00a0locationed in Branch of the local Bank\u00a0\n\n\u00a0For interested parties, please send your CV to\u00a0Candy\u00a0or call us at\u00a03188 9055\u00a0for further information", "employment_types": ["Full Time"], "selling_points": ["No selling target with up to 20K salary", "Bank experience is prefer", "Need work on shift but with attractive allowance"], "locations": ["Not Specified"], "categories": ["Banking / Finance", "Retail Banking", "Sales, CS & Business Devpt", "Customer Service - Supervisor / Officer", "Tele-sales (Telemarketing)"], "post_time": "2022-01-12T09:53:06Z", "salary": {"currency": "HKD", "max": 19999, "min": 11000, "period": "monthly", "term": null}, "salary_visible": true, "title_keywords": ["officer", "customer service", "sales"], "responsibilities": ["communication", "customer service", "back office", "banking"], "requirements": {"degrees": ["diploma", "degree or above"], "majors": [], "languages": [], "language_level": [], "hard_skills": ["no"], "soft_skills": ["customer service", "communication and interpersonal skills"], "languages_combined": []}, "experience_required": {"duration": [], "field": []}}, {"job_id": "100003009049691", "location_code": "hk", "company": "Chiyu Banking Corp Ltd", "job_title": "Product Development Manager (Segmentation)", "description": "Responsibilities:\nSupport on formulating customer strategies to drive customer growth and profitability\nAssist to implement and monitor the segment strategies through initiatives on acquisition, cross-selling, service upgrade, customer loyalty and retention.\nAssist to formulate and implement customer segment strategies to achieve the business targets, improve customer experience and explore customer financial needs.\nAssist to design and implement an integrated sales & service platform, end-to-end sales process for frontline including planning, sales discussion and activities effectively\nMonitor sales channels\u2019 performance on acquisition, mainly work with direct sales and Branch\nPerform client profitability analysis, identify gaps and propose action plans to improve lead conversion and revenue generation from deposit or investment of specific segment\u00a0\u00a0\u00a0\nOrganize activities and events to improve customer satisfaction\nManage marketing budget to optimize acquisition spending effectively\nPrepare regular MIS and management presentation\nRequirements:\nDegree Holder in Marketing or related discipline\nMinimum 4 years of working experience in banking industry, preferably relevant experience in customer segmentation or marketing\nGood Interpersonal, communication and analytical skills\nIndependent, attentive to details, customer-oriented, positive and proactive working attitude\nStrong planning, organization and time management skills\nStrong sense of responsibility and able to work under pressure\nGood command of written English and Chinese\nWe offer competitive packages and promising career opportunities to the right candidates. Please send your full resume with current salary, expected salary and the date of availability to\u00a0The Human Resources Department, Chiyu Banking Corporation Ltd, 12/F, Chiyu Bank Building, No. 78 Des Voeux Road Central, Hong Kong\u00a0or fax to\u00a02986-3233\u00a0or by clicking\u00a0Apply Now.\n\n\nInformation provided will be treated in strict confidence and only be used for recruitment purposes. All personal data of unsuccessful applicants will be destroyed after the recruitment exercise. A copy of Personal Information Collection Statement is available upon request.", "employment_types": ["Full Time", "Permanent"], "selling_points": [], "locations": ["Central"], "categories": ["Banking / Finance", "Analyst", "Retail Banking", "Financial Services"], "post_time": "2022-01-14T09:05:48Z", "salary": {"currency": null, "max": null, "min": null, "period": "monthly", "term": null}, "salary_visible": false, "title_keywords": ["product development manager"], "responsibilities": ["management", "analysis", "budget", "monitor", "design", "plans", "planning"], "requirements": {"degrees": ["degree holder"], "majors": ["marketing"], "languages": ["english", "chinese"], "language_level": ["good command"], "hard_skills": ["analytical skills"], "soft_skills": ["independent", "attentive to details", "sense of responsibility", "time management skills", "analytical skills", "communication", "customer-oriented", "proactive", "interpersonal", "positive", "work under pressure"], "languages_combined": [{"language": "english", "language_level": ["good command"]}, {"language": "chinese", "language_level": ["good command"]}]}, "experience_required": {"duration": ["minimum 4 years"], "field": ["banking industry", "marketing", "relevant experience"]}}, {"job_id": "100003009040029", "location_code": "hk", "company": "", "job_title": "Sales Manager / Business Development Manager (5-day work)", "description": "Maximize your team\u2019s success by influencing to build competency of relationship-building to get the best possible result\n\n\u2022Minimum 3 to 5 years\u2019 work experience in managerial or supervisory position\n\u2022Welcome you from hospitality, airline and retail sales industries with solid coaching and people management experiences\n\u2022Good language and communication skills in Cantonese, Mandarin and English\n\u2022A Hong Kong Resident\n\u2022Fresh Graduate or any of you with less experience will be considered as Assistant Manager /Officer\n\n\nTrained and Equipped with highest valuable qualities\n\u2022Devoted to the well-being of your clients and work partners\n\u2022Embrace feedback, learning and knowledge sharing\n\u2022Genuine, natural, honest\n\u2022Reliable, thoughtful, detailed\n\u2022Caring, seamless, straightforward\n\u2022Dauntless, persistent, passionate\n\n\nAny says to your Work, Family and personal life ?\n\u2022Choose your own life, work-life balance\n\u2022Connect with contributing and dynamic work partners\u00a0\u00a0\n\u2022Intensive financial planning training & follow-up programs provided by the company\n\u2022One-on-one coaching session conducted within the unit(s) /branch as opportunities to share ideas and career advancement\n\u2022Attractive remuneration package up to $30,000 + bonus, a competitive and unique bonus structures; management & performance bonus plus year end performance bonus\n\u2022Engage in a fast \u2013track career development programs for management\n\u2022Be the Leader, build your fun team, build your bright career\n\u2022Group life and group medical insurance including spouse\n\u2022Incentive trip and overseas conference\n\u2022Preferred mortgage rate\n\nTake Action now !!\n\nPlease contact Senior Team Head, Mr. Kimm Chan at 6683-6233 immediately. OR, by whatsapp.\n\nInterested candidates, please contact us at 66836233 for company details before applying.", "employment_types": ["Full Time", "Part Time", "Permanent", "Contract", "Freelance"], "selling_points": [], "locations": ["Not Specified"], "categories": ["Banking / Finance", "Retail Banking", "Sales, CS & Business Devpt", "Business Development", "Beauty Care / Health", "Beautician"], "post_time": "2022-01-12T00:52:06Z", "salary": {"currency": "HKD", "max": 54999, "min": 25000, "period": "monthly", "term": null}, "salary_visible": true, "title_keywords": ["business development manager", "sales manager"], "responsibilities": ["management", "ideas", "communication", "contact", "career development", "insurance", "planning"], "requirements": {"degrees": [], "majors": [], "languages": ["cantonese", "english", "mandarin"], "language_level": [], "hard_skills": ["plus", "fun", "airline", "whatsapp", "dynamic"], "soft_skills": ["passionate", "communication skills", "persistent", "unique", "learning", "dynamic", "honest", "detailed"], "languages_combined": [{"language": "cantonese", "language_level": []}, {"language": "english", "language_level": []}, {"language": "mandarin", "language_level": []}]}, "experience_required": {"duration": ["3 to 5 years"], "field": ["managerial", "supervisory", "retail", "people management"]}}, {"job_id": "100003009043062", "location_code": "hk", "company": "I Connect Company", "job_title": "Management trainee (wealth management centre)", "description": "Job Highlights:\n\n-\u00a0\u00a0\u00a0\u00a0\u00a0\u00a0\u00a0 Tertiary education; degree holder\n\n-\u00a0\u00a0\u00a0\u00a0\u00a0\u00a0\u00a0 Wealth management; finance; banking\n\nJob responsibility\n\n-\u00a0\u00a0\u00a0\u00a0\u00a0\u00a0\u00a0 Station at wealth management centre\n\n-\u00a0\u00a0\u00a0\u00a0\u00a0\u00a0\u00a0 Assist in daily operation\n\n-\u00a0\u00a0\u00a0\u00a0\u00a0\u00a0\u00a0 Expand new customer base in wealth management centre\n\n-\u00a0\u00a0\u00a0\u00a0\u00a0\u00a0\u00a0 Promote full range of wealth management products and services\n\n-\u00a0\u00a0\u00a0\u00a0\u00a0\u00a0\u00a0 Engage in a long-term relationship with high-net-worth clients\n\n-\u00a0\u00a0\u00a0\u00a0\u00a0\u00a0\u00a0 Understand the needs of the customers and customize wealth products tailor-made for their needs\n\n-\u00a0\u00a0\u00a0\u00a0\u00a0\u00a0\u00a0 Build up good relationship with potential clients and offer professional financial planning services\n\nRequirement\n\nUniversity degree in a related discipline\nFresh graduates are welcome\nProficient in both spoken and written English and Chinese, fluency in Mandarin is preferrable\nStrong self-motivation with ability to work under pressure\nAttentive to details and flexible with excellent interpersonal, communication and problem-solving skills", "employment_types": ["Full Time", "Permanent", "Internship"], "selling_points": ["Promote wealth management products and services", "Expand new customer base in wealth management ctr", "Relationship with high-net-worth clients"], "locations": ["Tseung Kwan O"], "categories": ["Banking / Finance", "Retail Banking", "Financial Services"], "post_time": "2022-01-12T09:41:31Z", "salary": {"currency": null, "max": null, "min": null, "period": "monthly", "term": null}, "salary_visible": false, "title_keywords": ["wealth management", "management trainee"], "responsibilities": ["good relationship", "management", "daily operation", "planning"], "requirements": {"degrees": ["university degree"], "majors": [], "languages": ["english", "chinese", "mandarin"], "language_level": ["fluency", "proficient"], "hard_skills": ["problem-solving skills"], "soft_skills": ["flexible", "attentive to details", "communication", "self-motivation", "problem-solving skills", "interpersonal", "work under pressure"], "languages_combined": [{"language": "english", "language_level": ["proficient"]}, {"language": "chinese", "language_level": ["proficient"]}, {"language": "mandarin", "language_level": ["fluency", "proficient"]}]}, "experience_required": {"duration": [], "field": []}}, {"job_id": "100003009046205", "location_code": "hk", "company": "OCBC Wing Hang Bank Limited", "job_title": "Operations Manager, Premier Banking Centre - Central", "description": "Responsibilities\n\nResponsible for the entire operational of Premier Banking Centre - Central\nEnsure operation activities and processes are under control, implement control measures in accordance with bank\u2019s procedures and policies\nProvide support to the HOPBC Central in developing Sales Plan to achieve assigned target\nPreparation of Sales Pipelines Management\nRequirements\n\nDegree holder is preferred Minimum of 5 years branch operations supervisory experience in retail banking branch\nDetailed-minded with good analytical mind\nGood supervisory and interpersonal skills\nProficient in MS Office including MS Excel", "employment_types": ["Full Time", "Permanent"], "selling_points": ["Supervisor operation team for Premier Banking", "Solid experience in branch operations", "Details minded with good PC skills"], "locations": ["Central"], "categories": ["Banking / Finance", "Retail Banking"], "post_time": "2022-01-13T09:56:51Z", "salary": {"currency": null, "max": null, "min": null, "period": "monthly", "term": null}, "salary_visible": false, "title_keywords": ["operations manager"], "responsibilities": ["control", "provide support", "management", "policies", "procedures", "developing", "plan", "banking"], "requirements": {"degrees": ["degree holder"], "majors": [], "languages": [], "language_level": [], "hard_skills": ["ms excel", "ms office"], "soft_skills": ["analytical mind", "interpersonal skills", "detailed"], "languages_combined": []}, "experience_required": {"duration": ["minimum of 5 years"], "field": ["retail banking", "supervisory experience"]}}, {"job_id": "100003009040161", "location_code": "hk", "company": "Livi Bank Limited", "job_title": "Graduate Trainee, Operations", "description": "If this is you, join us as our graduate trainee in Operations and start making an impact:\n\nResponsibilities\n\nCarry out name screening, periodic review and clear alert generated by in-house system\nPerform CDD, EDD and eKYC tasks including world check, FATCA, etc\nParticipate the project for eKYC solution for various platforms\nAssist in preparing report for management and HKMA\nSupport promotional operations in area of promotion campaign performance monitoring, promotional rewards fulfilment, budget tracking etc\nBe a key driver of customer experience\nEnsure all operational processes are complied with internal policies and regulatory requirements\nSupport ad hoc duties assigned by Department Head\nRequirement\n\nTertiary Education with an Associate Degree/Diploma or above\nProactive and willing to learn\nAdaptive and able to work in a fast-paced environment\nProficient in computer skills e.g. Microsoft PowerPoint, Microsoft Excel etc\nFluent in Cantonese, Mandarin, and English", "employment_types": ["Full Time", "Contract"], "selling_points": ["Exciting graduate opportunity", "Join Virtual Banking industry", "Grow your career"], "locations": ["Quarry Bay"], "categories": ["Banking / Finance", "Retail Banking", "Order Processing & Operation / Settlement", "Others", "Student / Fresh Graduate / No Experience"], "post_time": "2022-01-12T01:40:31Z", "salary": {"currency": null, "max": null, "min": null, "period": "monthly", "term": null}, "salary_visible": false, "title_keywords": ["operations", "graduate trainee"], "responsibilities": ["ad hoc duties", "management", "tracking", "cdd", "operations", "review", "monitoring", "budget", "policies", "regulatory requirements", "report"], "requirements": {"degrees": ["associate degree", "diploma or above"], "majors": [], "languages": ["cantonese", "english", "mandarin"], "language_level": ["fluent"], "hard_skills": ["microsoft excel", "computer skills", "microsoft powerpoint"], "soft_skills": ["fast-paced environment", "proactive", "willing to learn"], "languages_combined": [{"language": "cantonese", "language_level": ["fluent"]}, {"language": "english", "language_level": ["fluent"]}, {"language": "mandarin", "language_level": ["fluent"]}]}, "experience_required": {"duration": [], "field": []}}, {"job_id": "100003009040153", "location_code": "hk", "company": "OCBC Wing Hang Bank Limited", "job_title": "Manager \u2013 Trade Services", "description": "Responsibilities\n\u200bPerform double-checking of daily transaction of Trade Finance transaction and control reports\nCheck the transactions are complied with the terms & conditions of CP\nPerform mark-to-market valuation\nCommunicate with client and internal department in order to proceed operation of the transaction\nSupport and provide feedback to RMs and Bills Department\nRequirements\nBachelor degree in Business, Finance, Banking and other related disciplines\nMinimum 5 years' experience in Trade Finance\nPreferably experience in handling commodity documents in Trade Operations\nGood organization and communication skill\nProactive, able to work independently and under pressure\nGood written and spoken English, Chinese, including Mandarin\nProficient in MS Office including MS Word, Excel, PowerPoint and Chinese Word Processing\n\n\n\nAttractive remuneration package will be offered to the right candidate. Please apply with full resume stating present & expected salary and contact phone number to\u00a0The Human Resources Manager, 10/F, 161 Queen\u2019s Road Central, Hong Kong.\u00a0Please quote the reference.\n\nPersonal data collected will be used for recruitment purpose only. For more information, please visit our website:\u00a0http://www.ocbcwhhk.com.", "employment_types": ["Full Time", "Permanent"], "selling_points": ["Trade Services", "Bills related experience", "Banking industry"], "locations": ["Shau Kei Wan"], "categories": ["Banking / Finance", "Loan", "Retail Banking", "Order Processing & Operation / Settlement"], "post_time": "2022-01-12T01:38:54Z", "salary": {"currency": null, "max": null, "min": null, "period": "monthly", "term": null}, "salary_visible": false, "title_keywords": ["manager"], "responsibilities": ["valuation", "control", "communicate with client", "checking", "transactions", "reports"], "requirements": {"degrees": ["degree", "bachelor"], "majors": ["related disciplines", "finance", "business"], "languages": ["english", "chinese", "mandarin"], "language_level": ["proficient", "good"], "hard_skills": ["excel", "chinese word processing", "powerpoint", "ms office", "ms word"], "soft_skills": ["work independently", "communication skill", "under pressure", "proactive"], "languages_combined": [{"language": "english", "language_level": ["good"]}, {"language": "chinese", "language_level": ["proficient", "good"]}, {"language": "mandarin", "language_level": ["good"]}]}, "experience_required": {"duration": ["minimum 5 years"], "field": ["finance"]}}, {"job_id": "100003009031991", "location_code": "hk", "company": "Don Nelson Recruitment Limited", "job_title": "Back Office - Senior Officer, Loans & Credit Operations (Loan Processing)", "description": "Responsibilities\nPrepare all loan documents include offer letters, guarantee and charge forms etc\nPrepare general ledger and maintenance customer profile\nLoans application & KYC checking\nPrepare chats, monthly report & some credit admin duties\n\nRequirements\nMinimum 1 years\u2019 relevant experience in Banking industry\nFamiliar with credit administration or loans processing duties\nGood interpersonal and communication skills", "employment_types": ["Full Time", "Permanent"], "selling_points": ["Perform the operations tasks of loans", "Loan Processing", "Back office role"], "locations": ["Not Specified"], "categories": ["Banking / Finance", "Credit Analysis / Approval", "Loan", "Retail Banking"], "post_time": "2022-01-07T19:21:01Z", "salary": {"currency": null, "max": null, "min": null, "period": "monthly", "term": null}, "salary_visible": false, "title_keywords": ["senior officer", "operations"], "responsibilities": ["maintenance", "general ledger", "letters", "checking", "monthly report", "kyc"], "requirements": {"degrees": [], "majors": [], "languages": [], "language_level": [], "hard_skills": ["processing"], "soft_skills": ["communication skills", "interpersonal"], "languages_combined": []}, "experience_required": {"duration": ["minimum 1 years"], "field": ["banking industry", "relevant experience"]}}, {"job_id": "100003009038504", "location_code": "hk", "company": "Hang Seng Bank Ltd", "job_title": "Assistant Manager, Insurance Sales", "description": "Retail Distribution \u2013 Wealth Sales Distribution\n\nHang Seng's Retail Distribution focuses on personal wealth management and financial services. Our one-stop wealth management initiatives are designed for both our affluent and mass integrated account customers. With more than 290 branches and automated banking centres, including around 60 Prestige Banking Centres for our high-end personal customers, we serve over half of the adult population in Hong Kong while offering an extensive range of products to our valued customers.\n\nWe are currently seeking high caliber professionals to join our department as\u00a0Assistant Manager, Insurance Sales.\n\n\n\nPrincipal responsibilities\n\nAchieve the insurance sales targets by collaboration with the assigned Customer Relationship Managers/branches\nDrive tactical programs to develop a robust insurance culture on need based financial planning to affluent segments\nEnsure sales staff are capable to cross-sell various types of insurance products and able to deliver innovative products to our customers\nImplement the Group\u2019s/Bank\u2019s Compliance policy by managing compliance risk, ensuring adequate compliance resources are in place and training is provided, fostering a compliance culture and optimizing relation with regulators\n\nRequirements\n\nUniversity degree in a related discipline and preferably with relevant qualifications such as CFA, CFP or CFMP\n3 to 5 years\u2019 insurance sales experience\nGood communication, interpersonal and analytical skills\nStrong self-motivation and drive to succeed, with ability to work under pressure\nProficiency in both English, Cantonese and Putonghua\nCustomer centric mindset and ability to manage complex interactions effectively\nShown strong situation awareness, strong desire to learn and able to work in Agile environment\nAdvocate of openness, able to create a cohesive teamwork and inspire others\nHigh level of customer centricity mindset with dedication to deliver exceptional quality services for customers\u00a0\n\nFor candidates with less relevant working experience, we will consider them as Senior Insurance Sales.\n\nIf you would like to explore other opportunities at Hang Seng Hong Kong, please visit www.hangseng.com/careers/ for details.\n\nThe health and safety of our employees and candidates is very important to us. Due to the current situation related to the Novel Coronavirus (2019-nCoV), we\u2019re leveraging our digital capabilities to ensure we can continue to recruit top talent at the HSBC Group. \u00a0As your application progresses, you may be asked to use one of our digital tools to help you through your recruitment journey. \u00a0If so, one of our Resourcing colleagues will explain how our video-interviewing technology will be used throughout the recruitment process and will be on hand to answer any questions you might have.\n\nAll information provided by applicants will be used only for recruitment purposes and will be used strictly in accordance with the Bank's personal data policies, a copy of which may be obtained by the applicant upon request. Unless otherwise instructed in writing by the applicant concerned, applicants may be considered for other suitable positions within the Bank and its related companies. The personal data of unsuccessful job applicants may be retained for a maximum of two years from the date when the job application is rejected and such data may be retained for a longer period if there is a subsisting reason that obliges the Bank to do so, after which the personal data will be destroyed.", "employment_types": ["Full Time", "Permanent"], "selling_points": [], "locations": ["Not Specified"], "categories": ["Banking / Finance", "Retail Banking"], "post_time": "2022-01-11T07:09:11Z", "salary": {"currency": null, "max": null, "min": null, "period": "monthly", "term": null}, "salary_visible": false, "title_keywords": ["assistant manager,", "sales"], "responsibilities": ["compliance", "insurance", "planning", "develop"], "requirements": {"degrees": ["university degree"], "majors": [], "languages": ["cantonese", "putonghua", "english"], "language_level": ["proficiency"], "hard_skills": ["cfa", "reason", "agile", "analytical skills"], "soft_skills": ["agile", "teamwork", "cohesive", "analytical skills", "communication", "self-motivation", "novel", "interpersonal", "work under pressure"], "languages_combined": [{"language": "cantonese", "language_level": ["proficiency"]}, {"language": "putonghua", "language_level": ["proficiency"]}, {"language": "english", "language_level": ["proficiency"]}]}, "experience_required": {"duration": ["3 to 5 years"], "field": ["insurance", "relevant working experience"]}}, {"job_id": "100003009038876", "location_code": "hk", "company": "Hang Seng Bank Ltd", "job_title": "Sales Management Manager", "description": "Customer Contact Centre\n\nHang Seng's Customer Contact Centre has been ranked one of the best phone banking service providers for consecutive years. Our team strives to provide professional services for a wide range of banking products to address customers' different services and financial needs.\n\nWe are currently seeking high caliber professionals to join our team as\u00a0CCC Sales Management Manager\n\n\n\nPrincipal responsibilities\n\nLead the sales management and quality assurance function of Customer Contact Centre, be accountable for the business strategies and sales development as a core driver for the contact centre revenue source\nDrive and implement contact centre revenue generation initiatives. Make decision to prioritize business initiatives with right balance of business impact and team capacity\nCarry out process review, identify process improvement/ streamlining opportunities, derive improvement action plan and monitor process improvement progress\nEngage proactively with stakeholders of business and supporting teams, build effective partnership to drive business initiatives\nIdentify areas of improvement on contact centre operations and sales administrative area to ensure effective process and quality deliverables\nManage and grow team members through effective coaching, skill uplift and career development\n\nRequirements:\n\nUniversity degree\u00a0in Business\u00a0Administration or\u00a0other relevant qualifications\nMinimum\u00a0of five years' banking experience, preferably\u00a0with good\u00a0knowledge of sales management and contact centre operations\u00a0\nStrong self-motivation, with good analytical, communication, presentation, interpersonal and negotiation skills\nProficiency in both English and Chinese\nGood knowledge of MS Office (Word, Excel, PowerPoint)\n\nIf you would like to explore other opportunities at Hang Seng Hong Kong, please visit www.hangseng.com/careers/ for details.\n\nThe health and safety of our employees and candidates is very important to us. Due to the current situation related to the Novel Coronavirus (2019-nCoV), we're leveraging our digital capabilities to ensure we can continue to recruit top talent at the HSBC Group. As your application progresses, you may be asked to use one of our digital tools to help you through your recruitment journey. If so, one of our Resourcing colleagues will explain how our video-interviewing technology will be used throughout the recruitment process and will be on hand to answer any questions you might have.\n\nAll information provided by applicants will be used only for recruitment purposes and will be used strictly in accordance with the Bank's personal data policies, a copy of which may be obtained by the applicant upon request. Unless otherwise instructed in writing by the applicant concerned, applicants may be considered for other suitable positions within the Bank and its related companies. The personal data of unsuccessful job applicants may be retained for a maximum of two years from the date when the job application is rejected and such data may be retained for a longer period if there is a subsisting reason that obliges the Bank to do so, after which the personal data will be destroyed.", "employment_types": ["Full Time", "Permanent"], "selling_points": [], "locations": ["Not Specified"], "categories": ["Banking / Finance", "Retail Banking"], "post_time": "2022-01-12T02:10:42Z", "salary": {"currency": null, "max": null, "min": null, "period": "monthly", "term": null}, "salary_visible": false, "title_keywords": ["manager", "sales"], "responsibilities": ["business initiatives", "operations", "review", "quality", "monitor", "teams", "contact", "plan", "career development", "sales management"], "requirements": {"degrees": ["university degree"], "majors": ["business administration"], "languages": ["english", "chinese"], "language_level": ["proficiency"], "hard_skills": ["excel", "word", "powerpoint", "reason", "ms office"], "soft_skills": ["communication", "negotiation skills", "self-motivation", "novel", "interpersonal", "presentation"], "languages_combined": [{"language": "english", "language_level": ["proficiency"]}, {"language": "chinese", "language_level": ["proficiency"]}]}, "experience_required": {"duration": ["minimum of five years"], "field": ["management", "banking experience"]}}, {"job_id": "100003009040096", "location_code": "hk", "company": "Page Personnel", "job_title": "Product Manager Assistant (Fresh Graduates Welcome!)", "description": "Our client is looking for a Product Manager Assistant to join their growing team. The candidate should have a Degree in Business Administration or related disciplines, and internship experience within private or retail banks.\n\nClient Details\n\nOur client is one of the most reputable banks in Hong Kong, with 3000+ offices across the world. They are currently one of the leaders in the market and have built a great reputation across the globe. Their Hong Kong business provides retail banking, private banking, commercial banking and global banking services to their clients.\n\nDescription\n\nManaging Liabilities Products which cover deposits, banking services, payments and FX\nResponsible for implementation & on-going work of the industrial project\nConduct data analysis and graphical presentations for management reporting\nResearch on market information on deposits, banking services, payments and FX\nResponsible for monitoring competitors movement on deposits, banking services, payments and FX\n\nProfile\n\nDegree in BBA, Marketing, Public Relations or relevant disciplines (First and second honours required)\nIntern experience in retail banking or private banking\nKnowledge in deposits, banking services, payments and FX\nFluent in English and Chinese\nProficient in MS Office (Excel, Word, PPT)\n\nJob Offer\n\nWorking days and time: Mon - Fri, 0900 - 1800\nReputable Bank Group in Hong Kong\nExcellent product exposure\nInternational work culture\n\nTo apply online please click the 'Apply' button below. For a confidential discussion about this role please contact Kira Tang on +852 2258 3538.", "employment_types": ["Full Time", "Permanent"], "selling_points": ["Reputable Bank Group in Hong Kong", "Excellent product exposure", "International work culture"], "locations": ["Not Specified"], "categories": ["Banking / Finance", "Private Banking", "Retail Banking", "Financial Services"], "post_time": "2022-01-12T01:22:33Z", "salary": {"currency": null, "max": null, "min": null, "period": "monthly", "term": null}, "salary_visible": false, "title_keywords": ["assistant", "product manager"], "responsibilities": ["market information", "monitoring", "implementation", "presentations", "data analysis", "payments", "management reporting", "contact", "banking", "administration"], "requirements": {"degrees": ["degree"], "majors": ["related disciplines", "bba", "marketing", "business administration"], "languages": ["english", "chinese"], "language_level": ["fluent"], "hard_skills": ["excel", "analysis", "word", "presentations", "ms office"], "soft_skills": ["responsible"], "languages_combined": [{"language": "english", "language_level": ["fluent"]}, {"language": "chinese", "language_level": ["fluent"]}]}, "experience_required": {"duration": [], "field": ["business administration", "related", "retail banking", "banking", "retail"]}}, {"job_id": "100003009039693", "location_code": "hk", "company": "GF Holdings (Hong Kong) Corporation Ltd", "job_title": "Associate/ Vice President, Corporate Services (Securities Brokerage)", "description": "Responsibilities\n\nConduct market research to identify business opportunities\nEstablish good business relationship with clients\nArrange presentations on products and services\nSupport the team on day-to-day client activities and prepare required documentation\nParticipate in sales planning initiatives and design appropriate relationship plans to generate new businesses\nHandle corporate account opening documents.\nResponsible for daily operation for corporate clients.\nPrepare business reports for Senior Management.\nFormulate user acceptance test for IT project.\nUndertake ad hoc projects as assigned.\nRequirements\n\nMinimum of 3-6 years relevant working experience in brokerage firms, banks, or other financial institutions. (Less experience will be considered as Associate)\nCandidate with front-line experience will be an advantage.\nSelf-motivated with excellent communication and analytical skills and able to work independently\nGood command of written and spoken English and Chinese (proficient in Mandarin preferred).\nFamiliar with Microsoft Office.\nGood knowledge in Share Incentive Plan will be an advantage.\nWe offer attractive remuneration package and fringe benefits to the right candidate. Interested applicants please send detailed resume stating present & expected salaries and date of availability to Human Resources Department by clicking \"APPLY NOW\".\n\nFurther information about our group companies can be found at www.gfgroup.com.hk and www.gf.com.cn.\n\nAll applications will be treated in the strictest confidence and personal data collected will be used for recruitment purpose only.", "employment_types": ["Full Time"], "selling_points": ["3-6 years working experience in brokerage firms", "Less experience will be considered as Associate", "Front-line experience will be an advantage"], "locations": ["Sheung Wan"], "categories": ["Banking / Finance", "Retail Banking", "Financial Services", "Others"], "post_time": "2022-01-11T10:32:03Z", "salary": {"currency": null, "max": null, "min": null, "period": "monthly", "term": null}, "salary_visible": false, "title_keywords": ["vice president", "associate"], "responsibilities": ["identify business opportunities", "account opening", "conduct market research", "daily operation", "presentations", "design", "reports", "ad hoc projects", "documentation", "plans", "senior management", "support the team", "planning"], "requirements": {"degrees": [], "majors": [], "languages": ["english", "chinese", "mandarin"], "language_level": ["good command", "proficient"], "hard_skills": ["microsoft office", "analytical skills"], "soft_skills": ["communication", "self-motivated", "work independently", "analytical skills"], "languages_combined": [{"language": "english", "language_level": ["proficient", "good command"]}, {"language": "chinese", "language_level": ["proficient", "good command"]}, {"language": "mandarin", "language_level": ["good command"]}]}, "experience_required": {"duration": ["minimum of 3-6 years"], "field": ["brokerage", "financial institutions", "relevant working experience"]}}, {"job_id": "100003009036631", "location_code": "hk", "company": "OCBC Wing Hang Bank Limited", "job_title": "Secretary", "description": "Responsibilities:\n\n\n\nProvide secretarial and administration support to the Operations Division\nPrepare various monthly reports and analysis to the Management\nPrepare and maintain departmental operations records in an accurate and timely manner\nHandle ad-hoc duties as assigned\n\nRequirements:\n\n\n\nHigher Diploma or above in Secretary or Administration discipline is preferred\nAt least 5 years\u2019 relevant experience in secretarial or administrative roles in sizable companies\nProficient in MS Office including MS Word, Excel, PowerPoint and Chinese Word Processing\nExcellent interpersonal, coordination and organization skills\nProficiency in both written and spoken English, Chinese and Putonghua\n\nAttractive remuneration package will be offered to the right candidate.\u00a0 Please apply with full resume stating present & expected salary and contact phone number to The Human Resources Manager, 10/F, 161 Queen\u2019s Road Central, Hong Kong. Please quote the reference.\n\nPersonal data collected will be used for recruitment purpose only.\u00a0 For more information, please visit our website: http://www.ocbcwhhk.com.", "employment_types": ["Full Time", "Permanent"], "selling_points": ["Secretary", "Administrative Support", "Operations"], "locations": ["Shau Kei Wan"], "categories": ["Admin & HR", "Clerical / Admin Staff", "Secretary", "Banking / Finance", "Retail Banking"], "post_time": "2022-01-10T11:29:19Z", "salary": {"currency": null, "max": null, "min": null, "period": "monthly", "term": null}, "salary_visible": false, "title_keywords": ["secretary"], "responsibilities": ["management", "monthly reports", "operations", "analysis", "maintain", "ad-hoc duties", "administration"], "requirements": {"degrees": ["higher diploma or above"], "majors": [], "languages": ["putonghua", "english", "chinese"], "language_level": ["proficiency", "proficient"], "hard_skills": ["excel", "chinese word processing", "sizable companies", "powerpoint", "ms office", "ms word"], "soft_skills": ["organization skills", "interpersonal", "coordination"], "languages_combined": [{"language": "putonghua", "language_level": ["proficiency"]}, {"language": "english", "language_level": ["proficiency"]}, {"language": "chinese", "language_level": ["proficiency", "proficient"]}]}, "experience_required": {"duration": ["at least 5 years"], "field": ["secretarial", "administrative", "relevant experience"]}}, {"job_id": "100003009042953", "location_code": "hk", "company": "Chong Hing Bank Ltd", "job_title": "Vice President, Auto Finance Operations - Retail Lending Department", "description": "Responsibilities:\n\nSupervise the daily operations of Auto Loan to achieve key performance indicators.\nUndertake special assignments/ projects and implement on schedule.\nLiaise with Compliance Department to review and assess adequacy of relevant compliance controls including AML requirements.\nEnsure Insurance and License renewal are closely monitor and follow up within the require timeline.\nHandle auto loan paid in full process\nResponsible to update daily operations or procedure in accordance with the latest regulatory or policy in order to fully complied with the relevant guidelines.\n\nRequirements:\n\nUniversity graduate in any disciplines, preferably major in Marketing, Business, Finance, Economics or Accounting\nMinimum 6 years\u2019 solid experience in Personal Banking with knowledge on Auto Finance & SME Banking products\nGood interpersonal skills and communication skills\nGood leadership skills and problem solving skills\nSelf-motivated, independent and able to work under pressure\nProficient in both spoken and written English, Chinese and Putonghua\nFamiliar with MS Office Applications and Chinese Word Processing\n\nWe offer competitive remuneration package and promising career opportunities to the successful candidates. Interested parties, please send full resume with current & expected salary and the date of availability to\u00a0The HR Division by clicking \"Apply Now\" button below. Please quote reference on your application. Information provided will be treated in strict confidence and only be used for recruitment purposes. Personal data of unsuccessful applications will be destroyed 24 months after the completion of the recruitment and selection exercise.", "employment_types": ["Full Time", "Permanent"], "selling_points": ["Supervise the daily operations of Auto Loan", "University graduate in any disciplines", "Minimum 6 yrs solid experience in Personal Banking"], "locations": ["Central"], "categories": ["Banking / Finance", "Loan", "Retail Banking", "Professional Services", "Legal & Compliance"], "post_time": "2022-01-12T09:17:58Z", "salary": {"currency": null, "max": null, "min": null, "period": "monthly", "term": null}, "salary_visible": false, "title_keywords": ["vice president", "operations"], "responsibilities": ["aml", "guidelines", "review", "compliance", "monitor", "daily operations", "schedule", "liaise with", "insurance"], "requirements": {"degrees": ["university graduate"], "majors": ["finance", "economics", "business", "marketing", "any disciplines", "accounting"], "languages": ["putonghua", "english", "chinese"], "language_level": ["proficient"], "hard_skills": ["problem solving skills", "chinese word processing", "ms office"], "soft_skills": ["communication skills", "self-motivated", "independent", "leadership skills", "interpersonal skills", "problem solving skills", "work under pressure"], "languages_combined": [{"language": "putonghua", "language_level": ["proficient"]}, {"language": "english", "language_level": ["proficient"]}, {"language": "chinese", "language_level": ["proficient"]}]}, "experience_required": {"duration": ["minimum 6 years"], "field": ["finance", "banking"]}}, {"job_id": "100003009045864", "location_code": "hk", "company": "Robert Half", "job_title": "AVP/VP - Management Reporting, leading bank", "description": "Our client is a leading International bank with operations in both banking and treasury services. To cope with their business expansion, they are looking for a caliber to join their team.\n\n\n\nReport to Senior Manager and lead a team of 5\nManage the strategic financial planning, forecasting, and budgeting process\nEvaluate the profit and cost efficiencies, Provide financial analysis and support for business case development, product and mandate pricing\nPerform financial modelling and analysis to support strategic projects and ad-hoc initiatives\n\n\n\nRequirements:\n\nBachelor's Degree in Accounting, Finance or relevant discipline\nMinimum 3 years' experience in banking and financial accounting / regulatory reporting functions\nMember of CPA is an added advantage\nHigh level of multi-tasking and time management skill are required\nA team-player with excellent working attitude; willing to take on multiple functions\nExcellent verbal and written communication skills\n\n\n\nApply Today\n\nTo apply online (Word attachment only), please click the 'Apply' button. Please note that only short-listed candidates will be contacted.", "employment_types": ["Full Time", "Permanent"], "selling_points": ["A leading retail banking and corporate banking", "Fringe benefit with decent bonus", "Good exposure with career progression"], "locations": ["Central & Western Area"], "categories": ["Banking / Finance", "Corporate Banking", "Private Banking", "Retail Banking"], "post_time": "2022-01-13T08:57:51Z", "salary": {"currency": null, "max": null, "min": null, "period": "monthly", "term": null}, "salary_visible": false, "title_keywords": [], "responsibilities": ["ad-hoc", "reporting", "cost", "management", "operations", "budgeting", "analysis", "evaluate", "lead a team", "financial analysis", "communication", "banking", "report", "forecasting", "planning"], "requirements": {"degrees": ["degree", "bachelor"], "majors": ["finance", "accounting"], "languages": [], "language_level": [], "hard_skills": ["financial analysis", "cpa", "analysis", "word"], "soft_skills": ["team-player", "communication skills", "multi-tasking", "time management skill"], "languages_combined": []}, "experience_required": {"duration": ["minimum 3 years"], "field": ["accounting", "financial", "banking"]}}, {"job_id": "100003009045895", "location_code": "hk", "company": "Robert Half", "job_title": "AVP/VP - Financial Reporting, Leading Bank", "description": "Our client is a leading International bank with operations in both banking and treasury services.\n\n\n\nPerform financial reporting functions and handle monthly, quarterly and year-end reporting e.g. preparation of financial reports, interim and annual reports\nEffective control on the operations, structure and workflow of financial data and general ledger production of the Group\nFormulate changes in accounting policies and practices or the adoption of new accounting policies and the monitoring of their subsequent implementations\nAssist in enhancements to financial controls and reporting process including automation and UAT\nLiaise with external auditors for annual audit and tax matters\n\n\nRequirements:\n\nBachelor's Degree in Accounting, Finance or relevant discipline\nMinimum 3 years' experience in banking and financial accounting /financial reporting functions\nMember of CPA is an added advantage\nHigh level of multi-tasking and time management skill are required\nA team-player with excellent working attitude; willing to take on multiple functions\nExcellent verbal and written communication skills\n\n\nApply Today\n\nTo apply online (Word attachment only), please click the 'Apply' button. Please note that only short-listed candidates will be contacted.", "employment_types": ["Full Time", "Permanent"], "selling_points": ["A leading retail banking and corporate banking", "Fringe benefit with decent bonus", "Good exposure with career progression"], "locations": ["Central & Western Area"], "categories": ["Banking / Finance", "Corporate Banking", "Private Banking", "Retail Banking"], "post_time": "2022-01-13T09:02:57Z", "salary": {"currency": null, "max": null, "min": null, "period": "monthly", "term": null}, "salary_visible": false, "title_keywords": [], "responsibilities": ["data", "operations", "general ledger", "communication", "accounting policies", "liaise with", "tax matters", "control", "uat", "reports", "banking", "reporting", "management", "annual audit", "monitoring", "year-end", "financial reports", "financial reporting", "external auditors"], "requirements": {"degrees": ["degree", "bachelor"], "majors": ["finance", "accounting"], "languages": [], "language_level": [], "hard_skills": ["cpa", "word"], "soft_skills": ["team-player", "communication skills", "multi-tasking", "time management skill"], "languages_combined": []}, "experience_required": {"duration": ["minimum 3 years"], "field": ["accounting", "financial", "banking"]}}, {"job_id": "100003009046264", "location_code": "hk", "company": "Conners Consulting Limited", "job_title": "Senior Systems Analyst", "description": "Responsibilities\n\nTo develop, improve, promote & govern systems architecture for application development\nTo develop application teams\u2019 competencies to ensure fulfillment & adherence to system architecture requirements\nTo review vendors\u2019 proposed solutions & evaluate system interface & integration with existing applications\nTo interpret technical aspects in user requirements for enhancing system architecture\n\nRequirements\n\nUniversity graduate in Computer Science or related disciplines\n8+ years\u2019 experience in bank application systems development\nProven understanding of system architecture & related governance\nFamiliar with Web based development using Java/JSP, JMS and capable for OOAD will be an advantage\nExcellent communication skills in both written and spoken English and Chinese/Putonghua\nCandidates with less experience will be considered as System Analyst\n\nTo apply, please send your detailed resume or contact Ernest WU at 2851 7763 for a confidential discussion.\n\nOnly shortlisted candidates will be notified.\nApplicants who are not contacted within two weeks may consider their applications unsuccessful.\nAll data collected will be used for recruitment purpose only & will be used strictly confidential.\n\nConners Consulting Limited\n2005 Kai Tak Commercial Building 317 Des Voeux Road Central Hong Kong\nTel: (852) 3996 8090", "employment_types": ["Full Time", "Permanent"], "selling_points": ["Develop/Govern systems architecture of application", "Permanent post with full bank's benefits", "Less experience candidate will consider as SA"], "locations": ["Not Specified"], "categories": ["Banking / Finance", "Retail Banking", "Information Technology (IT)", "Application Specialist - Software", "IT Project Management / Team Lead"], "post_time": "2022-01-13T10:10:00Z", "salary": {"currency": null, "max": null, "min": null, "period": "monthly", "term": null}, "salary_visible": false, "title_keywords": ["analyst"], "responsibilities": ["fulfillment", "systems", "teams", "review", "develop", "evaluate", "application development", "architecture"], "requirements": {"degrees": ["university graduate"], "majors": ["related disciplines", "computer science"], "languages": ["putonghua", "english", "chinese"], "language_level": ["excellent"], "hard_skills": ["java", "web"], "soft_skills": ["communication skills", "capable", "detailed"], "languages_combined": [{"language": "putonghua", "language_level": ["excellent"]}, {"language": "english", "language_level": ["excellent"]}, {"language": "chinese", "language_level": ["excellent"]}]}, "experience_required": {"duration": ["8+ years"], "field": ["system analyst", "development", "application systems"]}}, {"job_id": "100003009039289", "location_code": "hk", "company": "Livi Bank Limited", "job_title": "Senior Manager / Manager, Interest Rate and Liquidity Risk (Virtual Bank)", "description": "Responsibilities:\n\n\nPerform day-to-day market / liquidity / interest rate risk management for the entire bank\nCreate and produce regular risk monitoring reports with a number of risk management measures\nWork with data engineers for automation of risk controls and reports\nDevelopment and modification of simple risk models or tools to perform necessary analysis\nReview on risk limits to ensure risk commensurate with business risk appetite\nReview product due diligence assessments to come up with a professional opinion on the relevant risks\n\nRequirements:\n\n\nUniversity degree in Finance, Risk Management, Banking, Financial Engineering or related fields\nAt least 6 years of relevant experience in risk management\nData analytic skills such as SQL preferred\nExcellent command of both spoken and written English and Chinese, including Putonghua\n\nWe offer competitive salary package to the successful candidate.\u202f If you are interested in joining this exciting team, please send your full resume including your\u202fCURRENT\u202fand\u202fEXPECTED\u202fsalary for our consideration.", "employment_types": ["Full Time", "Permanent"], "selling_points": ["Virtual Bank / Digital bank", "Risk Management", "Excellent Career Development Opportunity"], "locations": ["Quarry Bay"], "categories": ["Banking / Finance", "Retail Banking", "Others", "Risk Management"], "post_time": "2022-01-11T09:18:39Z", "salary": {"currency": null, "max": null, "min": null, "period": "monthly", "term": null}, "salary_visible": false, "title_keywords": ["senior manager", "manager"], "responsibilities": ["management", "data", "product due diligence", "analysis", "review", "risk monitoring", "reports"], "requirements": {"degrees": ["university degree"], "majors": ["finance", "engineering", "risk management"], "languages": ["putonghua", "english", "chinese"], "language_level": ["excellent"], "hard_skills": ["sql", "analytic skills"], "soft_skills": [], "languages_combined": [{"language": "putonghua", "language_level": ["excellent"]}, {"language": "english", "language_level": ["excellent"]}, {"language": "chinese", "language_level": ["excellent"]}]}, "experience_required": {"duration": ["at least 6 years"], "field": ["risk management", "relevant experience"]}}, {"job_id": "100003009038554", "location_code": "hk", "company": "China CITIC Bank International Limited", "job_title": "Assistant Vice President, Medium Enterprise", "description": "Job Purpose\n\nResponsible for building relationships with ME customers and exploring new sales opportunities\n\nKey Responsibilities\n\nExplore new business opportunities of commercial banking products through different business networks and channels to achieve designated business targets\nCross-sell retail banking product to ME customers\nManage account portfolio and maintain close relationship with customers for business retention and referrals\nPrepare credit proposals by negotiation of credit terms, pricing and collateral requirements in accordance with the bank\u2019s guidelines\nIdentify and minimize credit risk within the portfolio through regular credit reviews\nMonitor loan repayment of customers; follow up and collect overdue payment\nPerform annual review of high risk / unsuitable customers timely\n\nRequirements\n\nPreferably a Degree holder or equivalent in Business or related disciplines\nMinimum 5 years of credit and marketing experience in commercial banking environment with proven record in new customer cultivation\nPreferably possess / obtain Core or Professional level of qualification under the HKMA Enhanced Competency Framework (ECF) on Credit Risk Management (CRM)\nStrong analytical mind and proactive\nGood interpersonal and people management skills\nGood command of written and spoken English and Chinese (including Putonghua)", "employment_types": ["Full Time", "Permanent"], "selling_points": ["Explore new business opportunities", "Cross-sell retail banking product to ME customers", "Min. 5 years of relevant experience"], "locations": ["Quarry Bay"], "categories": ["Banking / Finance", "Credit Analysis / Approval", "Retail Banking"], "post_time": "2022-01-11T07:19:42Z", "salary": {"currency": null, "max": null, "min": null, "period": "monthly", "term": null}, "salary_visible": false, "title_keywords": ["assistant vice president"], "responsibilities": ["explore new business opportunities", "guidelines", "review", "monitor", "payment", "maintain", "banking"], "requirements": {"degrees": ["degree holder"], "majors": ["related disciplines", "business"], "languages": ["putonghua", "english", "chinese"], "language_level": ["good command"], "hard_skills": ["hkma"], "soft_skills": ["analytical mind", "proactive", "interpersonal"], "languages_combined": [{"language": "putonghua", "language_level": ["good command"]}, {"language": "english", "language_level": ["good command"]}, {"language": "chinese", "language_level": ["good command"]}]}, "experience_required": {"duration": ["minimum 5 years"], "field": ["commercial", "marketing", "banking"]}}]