[{"job_id": "100003009054805", "location_code": "hk", "company": "Public Finance Limited", "job_title": "Risk Officer, Risk Management", "description": "Responsibilities\nTo identify, measure, monitor and control all material risks on the Company's business activities\nTo prepare risk management reports and assist in conducting regular/ad-hoc risk assessments\nTo assist in formulating and reviewing risk management policies, procedures, risk tolerance limits and methodologies\nTo assist in performing stress testing analysis, scenario analysis, and other types of portfolio analysis\nTo coordinate/provide guidance and supports to business units on risk management related matters\nTo review the updates on regulatory developments and requirements by HKMA\nRequirements:\nBachelor degree holders of any disciplines\n2 years experience in risk management or working experience in banking and finance industry will be an advantage\nGood command in English and Chinese\nGood analytical, interpersonal and communication skills, self initiation and independent\nStrong PC skills especially in MS Word and Excel\nBenefits\nDouble Pay\nDiscretionary Bonus\nInsurance Benefits\nStudy subsidy\nApplication Method:\nBy Whatsapp : 9309 2925\nBy E-mail via \"Apply Now\"", "employment_types": ["Full Time"], "selling_points": [], "locations": ["Not Specified"], "categories": ["Banking / Finance", "Others", "Risk Management"], "post_time": "2022-01-17T11:11:10Z", "salary": {"currency": null, "max": null, "min": null, "period": "monthly", "term": null}, "salary_visible": false, "title_keywords": ["officer"], "responsibilities": ["ad-hoc", "control", "management", "policies", "analysis", "review", "monitor", "procedures", "testing", "coordinate", "management reports", "provide guidance", "business activities"], "requirements": {"degrees": ["degree", "bachelor"], "majors": ["any disciplines"], "languages": ["english", "chinese"], "language_level": ["good command"], "hard_skills": ["excel", "pc skills", "ms word"], "soft_skills": ["communication skills", "independent", "interpersonal"], "languages_combined": [{"language": "english", "language_level": ["good command"]}, {"language": "chinese", "language_level": ["good command"]}]}, "experience_required": {"duration": ["2 years"], "field": ["risk management", "finance industry", "banking"]}}, {"job_id": "100003009049492", "location_code": "hk", "company": "Shanghai Commercial Bank Ltd", "job_title": "Manager, Risk Analytics", "description": "The successful candidate will be responsible for various analytical support in risk management related tasks, including model development, maintenance and governance, assist in keeping abreast of risk management regulatory requirements, review and establish policies and procedures in relation to the Bank's risk profile to comply with the regulatory or internal requirements.\n\nResponsibilities:\n\nDevelop, maintain, and enhance models for various risk initiatives (e.g., ICAAP pillar 2 capital, SDST, IRRBB, etc.) and relevant risk analytics methodologies\nDesign, review, enhance, implement, and maintain stress testing methodologies and procedures according to regulatory or internal requirements\nCollaborate with various internal and external units and stakeholders to collect essential information / data for model development and implementing latest risk projects\nAssume new risk management related projects and initiatives as required\nPerform other jobs and ad-hoc projects as assigned by supervisor\nRequirements:\n\nDegree holder or above in Risk Management, Statistics, Quantitative Analysis or related disciplines\nMinimum 5 years of relevant experience in risk analytics / risk management and familiar with banking business and products, with prior experience in risk modeling\nSelf-motivated and detail-oriented with a strong analytical mindset\nGood team player, with high level of curiosity as well as independent problem-solving and multi-tasking ability\nGood computer skills particularly in Excel and VBA, and proficiency in SAS or SQL programming skills would be an advantage\nGood command of both written and spoken English and Chinese\n(Candidates with less experience will be considered for the position of Assistant Manager)\n\n\nAttractive remuneration package will be offered to the right candidates. Interested parties please click \"Apply Now\" to submit your full resume with current and expected salary to the Human Resources Division.\n\nPlease visit us at www.shacombank.com.hk for more information about our Bank.\n\nAll personal data collected will be used for recruitment related purposes strictly in accordance with the Bank's personal data policies, a copy of which will be provided immediately upon request by contacting our Personal Data Compliance Officer. Applicants who are not contacted within two months may consider their applications unsuccessful and the personal data collected from the applicants will be retained for no longer than two years from the date of rejection during which the applicants may be considered for other suitable positions within the Bank.", "employment_types": ["Full Time", "Permanent"], "selling_points": ["Model development, maintenance and governance", "keep abreast of risk mgt regulatory requirement", "Review and establish policies and procedures"], "locations": ["North Point"], "categories": ["Banking / Finance", "Analyst", "Others", "Risk Management"], "post_time": "2022-01-15T03:50:28Z", "salary": {"currency": null, "max": null, "min": null, "period": "monthly", "term": null}, "salary_visible": false, "title_keywords": ["manager"], "responsibilities": ["collaborate with", "data", "review", "procedures", "risk management related projects", "design", "testing", "develop", "maintain", "ad-hoc projects"], "requirements": {"degrees": ["degree holder"], "majors": ["related disciplines", "risk management", "statistics"], "languages": ["english", "chinese"], "language_level": ["good command"], "hard_skills": ["excel", "vba", "sas", "problem-solving", "analysis", "sql", "computer skills", "programming"], "soft_skills": ["good team player", "self-motivated", "independent", "problem-solving", "detail-oriented", "multi-tasking"], "languages_combined": [{"language": "english", "language_level": ["good command"]}, {"language": "chinese", "language_level": ["good command"]}]}, "experience_required": {"duration": ["minimum 5 years"], "field": ["risk management", "business", "relevant experience", "banking"]}}, {"job_id": "100003009050892", "location_code": "hk", "company": "Bank of Communications Co., Ltd. Hong Kong Branch", "job_title": "Risk Management Officer (Quantitative Analysis) \u2013 1 year contract", "description": "Career Level\nEntry Level\nQualification\nDegree\nJob Type\nFull Time, Contract\nJob Functions\nBanking / Finance, Credit Analysis / Approval, Others, Student / Fresh Graduate / No Experience, Risk Management", "employment_types": ["Full Time", "Contract"], "selling_points": [], "locations": ["Not Specified"], "categories": ["Banking / Finance", "Credit Analysis / Approval", "Others", "Student / Fresh Graduate / No Experience", "Risk Management"], "post_time": "2022-01-14T11:40:20Z", "salary": {"currency": null, "max": null, "min": null, "period": "monthly", "term": null}, "salary_visible": false, "title_keywords": ["risk management officer"], "responsibilities": ["analysis", "management", "banking"], "requirements": {"degrees": ["degree", "fresh graduate"], "majors": ["finance", "risk management"], "languages": [], "language_level": [], "hard_skills": ["credit analysis", "no"], "soft_skills": [], "languages_combined": []}, "experience_required": {"duration": [], "field": ["finance", "risk management", "banking"]}}, {"job_id": "100003009051831", "location_code": "hk", "company": "John Swire & Sons (HK) Limited", "job_title": "Risk Manager", "description": "A highly diversified, global corporation, the Swire group's businesses encompass property, aviation, beverages and food chain, as well as marine services and trading and industrial activities. Its core businesses are mainly focused on Asia, with its key operations in Hong Kong and the Chinese Mainland. The Swire group's businesses in Asia are held by the listed company, Swire Pacific Limited.\n\nJohn Swire & Sons (H.K.) Limited is the holding company of the publicly listed conglomerate, Swire Pacific Ltd. Our Group Risk Management Department invites applications for the following position:\n\nRisk Manager\n\nReporting to the Head of Group Risk Management, the Risk Manager will be responsible for the development and implementation of a broad range of risk management programmes across Swire Pacific Ltd. \u00a0Close interaction will be required with group companies operating across different industry sectors when implementing group initiatives and conducting project work.\u00a0\n\nThe Risk Manager will be based in Hong Kong working as part of a small team which coordinates the risk management and insurance functions for group companies. The geographic scope of this position will predominantly be Greater China.\u00a0\n\nResponsibilities:\n\nSupport the group enterprise risk management process, including overseeing the preparation of corporate risk registers\nIdentify, develop and implement effective group initiatives to reduce operational and hazard-based risk exposures\nManage an annual group programme of risk engineering surveys and related activities\nCo-ordinate a programme of Health & Safety (H&S) and Wellbeing initiatives, and manage group level H&S reporting and analysis\nMaintain head office business continuity plans and support business continuity management across all divisions\nRequirements:\nBachelor\u2019s degree or above with a major in engineering, H&S, business or risk management\nAt least 10 years\u2019 experience in engineering, H&S or risk management\nAble to travel overseas and Chinese Mainland when required\nCantonese speaker with excellent command of oral and written English\nA good standard of proficiency in Putonghua and written Chinese\nH&S or risk management\nGood communication and listening skills\nExcellent knowledge in Microsoft 365 applications such as Word, Excel, PowerPoint and Teams\nApplication:\n\n\nAt Swire, we are committed to creating an inclusive and supportive working environment for all our people regardless of their age, gender, gender identity, sexual orientation, relationship, family status, disability, race, ethnicity, nationality, religious or political beliefs. We believe in creating an environment where people feel comfortable at work and are able to realise their full potential.\n\nWe offer a competitive package to the right candidate. If you meet the qualifications and are interested in this position, you can send your application by clicking \"Apply Now\". We will contact all shortlisted candidates.\n\nThe Swire group is an equal opportunity employer. All applications received will be used exclusively for selection purposes and handled confidentially by authorised personnel only. Your application may also be considered for other suitable positions within the Swire group (please indicate clearly on your application if you would not like to be considered for other positions within the group.) Following data privacy ordinance, all unsuccessful applications will be destroyed after an appropriate time.", "employment_types": ["Full Time", "Permanent"], "selling_points": ["Enterprise Risk Management", "10+ years' experience in H&S or risk management", "Mature, self-starter and independent"], "locations": ["Admiralty"], "categories": ["Banking / Finance", "Risk Management"], "post_time": "2022-01-17T01:18:33Z", "salary": {"currency": null, "max": null, "min": null, "period": null, "term": null}, "salary_visible": false, "title_keywords": ["manager"], "responsibilities": ["reporting", "management", "business continuity", "analysis", "develop", "maintain", "plans"], "requirements": {"degrees": ["degree or above", "bachelor"], "majors": ["risk management", "business", "engineering"], "languages": ["cantonese", "putonghua", "english", "chinese"], "language_level": ["excellent", "proficiency", "good"], "hard_skills": ["excel", "word", "powerpoint"], "soft_skills": ["communication", "committed", "oral", "supportive"], "languages_combined": [{"language": "cantonese", "language_level": ["excellent"]}, {"language": "putonghua", "language_level": ["proficiency", "good"]}, {"language": "english", "language_level": ["excellent"]}, {"language": "chinese", "language_level": ["proficiency", "good"]}]}, "experience_required": {"duration": ["at least 10 years"], "field": ["risk management", "engineering"]}}, {"job_id": "100003009051928", "location_code": "hk", "company": "Octopus Holdings Limited", "job_title": "AML Compliance Specialist (1-year contract) REF: OCL/RMC/2021-210", "description": "Job Responsibilities\n\n\nPerform a checker role on customer due diligence and ongoing monitoring for Octopus wallet and merchant customers (tasks including on boarding, name screening,trigger event review, etc.)\nProvide supervision and guidance to junior staff so as to improve the quality of deliverables\nConduct regular high-risk review to existing customers (both individuals and merchants)and trigger event reviews (where necessary)\nGather relevant information and prepare regular reports for management review and for regulatory reporting\nContribute to the review, standardization and rollout of policies, procedures, processes and systems if necessary\nPerform ad-hoc tasks as assigned by the management and assist other team members where necessary\nRequirements\n\n\nDegree holder preferably in Risk Management, Engineering or Computer Science discipline\nAt least 3years of relevant experience in financial services industry with sound experience in AML Compliance\nKnowledgeable in Payment Systems and Stored Value Facilities Ordinance/Banking Ordinance and HKMA\u2019s AML Guideline is a plus\nProficient in MS PowerPoint,Word and Excel (hands-on experience in MS Excel functions e.g. Pivot tables, VLOOKUP etc. is an advantage)\nAttentive to details and multi-tasking\nQuick learner and proactive with can-do attitude\nAble to provide quality work under tight schedule and minimal supervision\nGood communication, interpersonal and problem-solving skills\nGood command of written and spoken English and Chinese\n\nWe offer successful candidate an attractive remuneration package and excellent career prospects. Interested parties please send your resume, present and expected salary, contact details and quoting the reference number by clicking \"Apply Now\"Visit our web site:\u00a0http://www.octopus.com.hk/\n\nThe personal data collected will be used for recruitment purposes only. If you are not contacted by us within six weeks, you may consider your application unsuccessful. Personal data with an unsuccessful applicant will be destroyed 12 months after rejection of the application. During this retention period, you have the right to request for correction or destruction of your personal data at any time. Any request for the correction or destruction of personal data should be addressed in writing to our Human Resources & Administration Department.\n\nOctopus is an equal opportunity employer and all employment decisions and Human Resources policies are administered; especially those relating to recruitment & selection, compensation & benefits, promotion & transfer, training & development and termination & redundancy; without discrimination on the basis of age, race, colour, religion, sex, national origin, marital status, pregnancy, physical and mental disability and family status but on genuine occupational qualification, job performance, employees\u2019 ability and internal/ external relativities.", "employment_types": ["Contract"], "selling_points": ["Provide supervision and guidance to junior staff", "Degree holder preferably in Risk Management", "At least 3 years of relevant experience"], "locations": ["Kowloon Bay"], "categories": ["Banking / Finance", "Financial Services", "Professional Services", "Legal & Compliance", "Risk Management"], "post_time": "2022-01-17T01:32:42Z", "salary": {"currency": null, "max": null, "min": null, "period": "monthly", "term": null}, "salary_visible": false, "title_keywords": ["specialist", "aml compliance"], "responsibilities": ["guidance", "reporting", "management", "policies", "ad-hoc tasks", "review", "monitoring", "quality", "provide supervision", "procedures", "systems", "customer due diligence", "regular reports for management"], "requirements": {"degrees": ["degree holder"], "majors": ["risk management", "engineering", "computer science"], "languages": ["english", "chinese"], "language_level": ["good command"], "hard_skills": ["excel", "plus", "aml", "hkma", "vlookup", "word", "ms excel", "problem-solving skills", "ms powerpoint"], "soft_skills": ["attentive to details", "can-do attitude", "quick learner", "communication", "multi-tasking", "hands-on", "problem-solving skills", "proactive", "interpersonal"], "languages_combined": [{"language": "english", "language_level": ["good command"]}, {"language": "chinese", "language_level": ["good command"]}]}, "experience_required": {"duration": [], "field": ["financial services industry", "compliance", "relevant experience"]}}, {"job_id": "100003009052670", "location_code": "hk", "company": "Hua Nan Commercial Bank, Ltd.", "job_title": "AML Officer (TM team in Compliance Department)", "description": "Jobs Descriptions\n\u2022\u00a0Conduct transaction monitoring and investigation\n\u2022\u00a0Prepare suspicious transaction reports\n\u2022\u00a0Liaise with business and operations on AML/CFT compliance issues\n\u2022 Deal with\u00a0 name screening and\u00a0 sanction related matters\n\u2022\u00a0Deal with\u00a0 \u00a0the\u00a0 \u00a0affairs\u00a0 \u00a0assigned\u00a0 \u00a0by the\u00a0 \u00a0supervisor\n\u2022\u00a0\u57f7\u884c\u4ea4\u6613\u76e3\u63a7\u53ca\u8abf\u67e5\n\u2022\u00a0\u6e96\u5099\u53ef\u7591\u4ea4\u6613\u5831\u544a\n\u2022\u00a0\u8207\u696d\u52d9\u53ca\u4f5c\u696d\u90e8\u9580\u806f\u7e6b\u95dc\u65bcAML/CFT\u4e4b\u5408\u898f\u4e8b\u5b9c\n\u2022 \u8655\u7406\u540d\u7a31\u6aa2\u6838\u53ca\u5236\u88c1\u6709\u95dc\u4e8b\u52d9\n\u2022\u00a0\u8655\u7406\u4e3b\u7ba1\u4ea4\u8fa6\u7684\u4e8b\u52d9\n\nRequirements\n\u2022\u00a0\u00a0Bachelor Degree holder in Finance, Risk Management, Law, Accounting, Business Administration or related disciplines\n\u2022\u00a0Fresh graduates\u00a0 \u00a0are\u00a0 \u00a0welcome,\u00a0 while\u00a0 \u00a0at least 1 year\u00a0 of banking industry experience\u00a0 will be preferable\n\u2022\u00a0Candidate with EXCEL functional skills will be preferable\n\u2022 Fair knowledge in anti-money laundering related regulations, guidelines and practices\n\u2022\u00a0Good interpersonal communication skills and active working attitude\n\u2022\u00a0Excellent analytical and writing skills\n\u2022\u00a0Great time management and ability to work under pressure\n\u2022\u00a0Proficient in both spoken and written English and Chinese (including Putonghua)\n\u2022\u00a0\u5927\u5b78\u7562\u696d\uff0c\u4e3b\u4fee\u8ca1\u52d9\u3001\u98a8\u7ba1\u3001\u6cd5\u5f8b\u3001\u6703\u8a08\u3001\u5546\u696d\u7ba1\u7406\u7b49\u5b78\u79d1\n\u2022\u00a0\u6b61\u8fce\u61c9\u5c46\u7562\u696d\u751f\uff0c\u60df\u81f3\u5c111\u5e74\u9280\u884c\u696d\u76f8\u95dc\u7d93\u9a57\u8005\u5c07\u512a\u5148\u8003\u616e\n\u2022\u00a0\u5177\u5099EXCEL\u51fd\u6578\u8655\u7406\u80fd\u529b\u8005\u512a\u5148\u8003\u616e\n\u2022\u00a0\u5c0d\u65bcAML\u898f\u7bc4\u3001\u6307\u5f15\u53ca\u5be6\u52d9\u5177\u5099\u5408\u7406\u6c34\u6e96\u7684\u77e5\u8b58\n\u2022\u00a0\u826f\u597d\u7684\u4eba\u969b\u6e9d\u901a\u6280\u5de7\u53ca\u7a4d\u6975\u7684\u5de5\u4f5c\u614b\u5ea6\n\u2022\u00a0\u512a\u79c0\u7684\u5206\u6790\u53ca\u64b0\u5beb\u6280\u5de7\n\u2022\u00a0\u826f\u597d\u6642\u9593\u7ba1\u7406\u80fd\u529b\u53ca\u6297\u58d3\u6027\n\u2022\u00a0\u4e2d\u82f1\u6587\uff08\u5305\u62ec\u666e\u901a\u8a71\uff09\u8b80\u5beb\u6d41\u5229", "employment_types": ["Full Time", "Permanent"], "selling_points": [], "locations": ["Wan Chai"], "categories": ["Banking / Finance", "Retail Banking", "Financial Services", "Risk Management"], "post_time": "2022-01-17T03:40:55Z", "salary": {"currency": null, "max": null, "min": null, "period": "monthly", "term": null}, "salary_visible": false, "title_keywords": ["officer"], "responsibilities": ["aml", "operations", "monitoring", "compliance", "investigation", "reports", "liaise with"], "requirements": {"degrees": ["bachelor degree holder"], "majors": ["risk management", "business administration", "law", "finance", "related disciplines", "accounting"], "languages": ["putonghua", "english", "chinese"], "language_level": ["proficient"], "hard_skills": ["excel", "anti-money laundering", "writing skills"], "soft_skills": ["communication skills", "active", "writing skills", "time management", "interpersonal", "work under pressure"], "languages_combined": [{"language": "putonghua", "language_level": []}, {"language": "english", "language_level": ["proficient"]}, {"language": "chinese", "language_level": ["proficient"]}]}, "experience_required": {"duration": ["at least 1 year"], "field": ["banking industry"]}}, {"job_id": "100003009054556", "location_code": "hk", "company": "Sky Wise Hong Kong Limited", "job_title": "Investment Analyst", "description": "Responsibilities\n\nAs a buy-side investment analyst, participating in full lifecycle of investment projects (i.e., cross-border M&A): from sourcing and screening opportunities, conducting research and analysis, performing due diligence, negotiating terms, closing deal and participating in post-investment management\nLearn independently and quickly grasp complicated knowledge of relevant industry, conduct market research, gather market intelligence, including but not limited to foreign regulation, compliance and taxation matters\nStudy and analyze an investment opportunity from comprehensive perspectives, include business model, profitability, value chain, competition, market trends and financial prospects.\nProficient at analyzing financial accounts, evaluating financial projections and valuation models\nLiaising with third-party professionals (e.g., lawyers, appraisers, accountants, tax advisors, industrial experts, M&A consultants, etc.) during the M&A process\nPreparing investment opportunities intros, financial analysis, market updates, investment memorandum and other presentation materials\n\nJob Requirements\n\nBachelor degree or above in Finance /Accounting/Business or related disciplines\nSkilled at examining and interpreting data from various sources, including but not limited to financials, sales report and market data; able to generate insight and recommendation for investment decision making\nStrong communication and presentation skills, especially on report writing and graphing (English and Mandarin)\nPrior experience in investment analysis or due diligence is preferred\nCertificate of WSET, knowledge of French GAAP and PCG would be an advantage\nCandidates with less experience will be considered as Junior Investment Analyst.\nImmediately available is preferred\n\nBenefits:\n\n\u00a0\u00a0\u00a0\u00a0\u00a0\u00a0\u00a0 Competitive salary package\n\u00a0\u00a0\u00a0\u00a0\u00a0\u00a0\u00a0 Various caring leave types\n\u00a0\u00a0\u00a0\u00a0\u00a0\u00a0\u00a0 Great learning and career development platform\n\u00a0\u00a0\u00a0\u00a0\u00a0\u00a0\u00a0 Excellent working environment\n\nInterested parties please send your CV with current and expected package, as well as date of availability to us for selection by clicking \u201cApply Now\u201d. All information collected would be used for recruitment purpose only. Application process may take 2 to 3 weeks; candidates would not be considered, should there be no contact within 6 weeks.\n\n\n\n", "employment_types": ["Full Time", "Permanent"], "selling_points": ["Buy-side investment analyst", "Full lifecycle of investment projects", "Strong analytical and presentation skills"], "locations": ["Kowloon Bay"], "categories": ["Banking / Finance", "Investment", "Professional Services", "Business Analysis / Data Analysis", "Risk Management"], "post_time": "2022-01-17T09:58:48Z", "salary": {"currency": null, "max": null, "min": null, "period": "monthly", "term": null}, "salary_visible": false, "title_keywords": ["analyst"], "responsibilities": ["tax", "due diligence", "management", "taxation", "valuation", "analysis", "conduct market research", "compliance", "liaising with", "financial analysis"], "requirements": {"degrees": ["certificate", "degree or above", "bachelor"], "majors": ["business", "finance", "related disciplines", "accounting"], "languages": ["english", "french", "mandarin"], "language_level": ["advantage"], "hard_skills": ["analysis"], "soft_skills": ["communication", "presentation skills", "decision making"], "languages_combined": [{"language": "english", "language_level": []}, {"language": "french", "language_level": ["advantage"]}, {"language": "mandarin", "language_level": []}]}, "experience_required": {"duration": [], "field": ["investment"]}}, {"job_id": "100003009052935", "location_code": "hk", "company": "Grand Alliance Asset Management Ltd", "job_title": "Graduate Trainee - Operations", "description": "We aim to nurture bright, young finance talents by helping them to lay the foundation for a rewarding and challenging career in the asset management industry.\u00a0\n\nResponsibilities\n\nAssist in handling legal & compliance (incl. KYC/AML/CTF/PI/CRS/FATCA/SOW) matters and client service duties\nAssist in company accounting, fund accounting, reconciliation, risk management and fund operations\u00a0\n\nRequirements\n\nBachelor\u2019s degree in Business Administration, Accounting, Finance, Law, English Literature, Statistics or related disciplines. We also welcome candidates from other disciplines\nCPA, completion of certain core HKICPA modules, FRM, a certificate in legal studies, HKSI\u2019s Paper 1 exam and/or other relevant professional qualification is a plus\nLess than 2 years\u2019 prior work experience in legal & compliance, client services, investor relations, operations support, financial accounting, audit, taxation, risk management and/or data management is preferred\nStrong written and verbal communication skills with excellent command of English\nDetail-minded and well-organized\nStrong communication and interpersonal skills\nKnowledge in IT or any of the programming languages is a plus\nA team player and a self-starter, with a strong sense of responsibility and the ability to work well under pressure\u00a0\n\nCompetitive compensation, culture of growth and career development. Located in Central (Hong Kong), annual leave, public holidays, MPF, group life insurance & medical benefits\u00a0\n\nPlease e-mail cover letter & CV with expected salary\u00a0by clicking APPLY NOW.\n", "employment_types": ["Full Time", "Permanent"], "selling_points": [], "locations": ["Central"], "categories": ["Accounting", "Finance / Accounting Manager", "Information Technology (IT)", "Application Specialist - Software", "Banking / Finance", "Risk Management"], "post_time": "2022-01-17T04:45:22Z", "salary": {"currency": null, "max": null, "min": null, "period": "monthly", "term": null}, "salary_visible": false, "title_keywords": ["operations", "graduate trainee"], "responsibilities": ["management", "aml", "operations", "compliance", "kyc"], "requirements": {"degrees": ["certificate", "degree", "bachelor"], "majors": ["business administration", "law", "finance", "statistics", "related disciplines", "accounting"], "languages": ["english"], "language_level": ["excellent"], "hard_skills": ["plus", "data management", "hksi", "cpa", "programming", "frm", "hkicpa"], "soft_skills": ["detail-minded", "communication skills", "under pressure", "sense of responsibility", "well-organized", "communication and interpersonal skills", "team player"], "languages_combined": [{"language": "english", "language_level": ["excellent"]}]}, "experience_required": {"duration": ["2 years"], "field": ["risk management", "management", "legal", "compliance", "audit", "accounting", "financial"]}}, {"job_id": "100003009046825", "location_code": "hk", "company": "CITIC Futures International Company Limited", "job_title": "Manager, Risk Management", "description": "\u8077\u4f4d\u63cf\u8ff0\n\n1\u3001\u8a2d\u8a08\u548c\u9a57\u8b49\u516c\u53f8\u8b49\u5238\u53ca\u671f\u8ca8\u696d\u52d9\u7684\u98a8\u96aa\u7ba1\u7406\u6a21\u578b\uff0c\u70ba\u516c\u53f8\u65b0\u696d\u52d9\u65b0\u7522\u54c1\u63d0\u4f9b\u98a8\u96aa\u8a55\u4f30\u610f\u898b\u548c\u91cf\u5316\u76e3\u63a7\u6307\u6a19\uff1b\n2\u3001\u5b8c\u6210\u5c0d\u5e02\u5834\u98a8\u96aa\u3001\u64cd\u4f5c\u98a8\u96aa\u3001\u4fe1\u7528\u98a8\u96aa\u53ca\u6d41\u52d5\u6027\u98a8\u96aa\u7684\u65e5\u5e38\u76e3\u63a7\uff0c\u4e26\u5411\u98a8\u96aa\u7ba1\u7406\u90e8\u7d93\u7406\u5831\u544a\u98a8\u96aa\u4e8b\u9805\uff0c\u5354\u52a9\u8655\u7f6e\u98a8\u96aa\u4e8b\u4ef6\uff1b\n3\u3001\u5354\u52a9\u98a8\u96aa\u7ba1\u7406\u90e8\u7d93\u7406\u5b8c\u5584\u516c\u53f8\u98a8\u96aa\u7ba1\u7406\u9ad4\u7cfb\uff0c\u4fee\u8a02\u5236\u5ea6\u6d41\u7a0b\uff1b\n4\u3001\u5354\u52a9\u98a8\u96aa\u7ba1\u7406\u90e8\u7d93\u7406\u8b58\u5225\u548c\u8a55\u4f30\u516c\u53f8\u5404\u696d\u52d9\u958b\u5c55\u904e\u7a0b\u4e2d\u7684\u5176\u4ed6\u98a8\u96aa\uff0c\u7de8\u5beb\u76f8\u95dc\u5831\u544a\uff1b\n5\u3001\u5b8c\u6210\u6307\u6d3e\u7684\u5176\u5b83\u98a8\u96aa\u7ba1\u7406\u7684\u76f8\u95dc\u5de5\u4f5c\n\n\u4efb\u8077\u8981\u6c42\n\n1\u3001\u5927\u5b78\u672c\u79d1\u4ee5\u4e0a\u5b78\u6b77\uff0c\u91d1\u878d\u3001\u7d71\u8a08\u3001\u8ca1\u52d9\u7b49\u76f8\u95dc\u5c08\u696d\uff0c\u6301\u6709CFA/FRM\u8b49\u66f8\u8005\u512a\u5148\uff1b\n2\u3001\u4e09\u5e74\u4ee5\u4e0a1\u865f\u724c\u696d\u52d9\u98a8\u96aa\u7ba1\u7406\u7d93\u9a57\uff0c\u719f\u6089\u8b49\u5238\u3001\u671f\u8ca8\u3001\u671f\u6b0a\u3001\u50b5\u5238\u3001\u57fa\u91d1\u53ca\u7d50\u69cb\u5316\u7522\u54c1\u7b49\u904b\u4f5c\uff0c\u4e26\u80fd\u5b8c\u6210\u98a8\u96aa\u7ba1\u7406\u65b9\u9762\u7684\u5b9a\u91cf\u5206\u6790\uff1b\n3\u3001\u826f\u597d\u7684\u82f1\u8a9e\u548c\u4e2d\u6587\u8868\u9054\u80fd\u529b\uff0c\u5ee3\u6771\u8a71\u6d41\u5229\u512a\u5148\uff1b\n4\u3001\u638c\u63e1\u57fa\u672c\u98a8\u96aa\u7ba1\u7406\u7406\u8ad6\u548c\u5de5\u5177\uff0c\u719f\u7df4\u4f7f\u7528\u8fa6\u516c\u8edf\u9ad4, \u6709\u7a0b\u5f0f\u8a2d\u8a08\u80fd\u529b\u512a\u5148\uff1b\n5\u3001\u5584\u65bc\u5b78\u7fd2\uff0c\u6709\u8f03\u5f37\u8cac\u4efb\u5fc3\uff0c\u908f\u8f2f\u601d\u7dad\u53ca\u8868\u9054\u80fd\u529b\u8f03\u5f37\u3002\n\n\u516c\u53f8\u5c07\u63d0\u4f9b\u5728\u540c\u884c\u4e2d\u5bcc\u6709\u7af6\u722d\u529b\u7684\u4eba\u529b\u8cc7\u6e90\u7d9c\u5408\u767c\u5c55\u652f\u6301\u3002\n\n\u6536\u96c6\u7684\u500b\u4eba\u8cc7\u6599\u5c07\u56b4\u683c\u4fdd\u5bc6\uff0c\u50c5\u7528\u65bc\u62db\u52df\u76ee\u7684\u3002\u6709\u95dc\u500b\u4eba\u8cc7\u8a0a\u6536\u96c6\u8072\u660e\uff0c\u8acb\u8a2a\u554f\u6211\u5011\u7684\u7db2\u7ad9http://www.citicsf.com.hk/disclaimer/\u3002", "employment_types": ["Full Time"], "selling_points": ["3 years relevant working experience", "Competitive package", "Comprehensive medical plan covering dependents"], "locations": ["Admiralty"], "categories": ["Banking / Finance", "Risk Management"], "post_time": "2022-01-14T01:22:10Z", "salary": {"currency": null, "max": null, "min": null, "period": "monthly", "term": null}, "salary_visible": false, "title_keywords": ["manager"], "responsibilities": [], "requirements": {"degrees": [], "majors": [], "languages": [], "language_level": [], "hard_skills": [], "soft_skills": [], "languages_combined": []}, "experience_required": {"duration": [], "field": []}}, {"job_id": "100003009047769", "location_code": "hk", "company": "Public Bank (Hong Kong) Ltd", "job_title": "Officer \u2013 Risk Management (Ref: JD-RMO)", "description": "Assist in review of risk management framework, policies and procedures\nConduct risk analysis and assessment to identify and monitor major risks of the Bank\nPerform ad hoc tasks and projects assigned by supervisor\nUniversity Degree in Finance, Economics, Risk Management, Mathematics or other related disciplines with minimum 1 year relevant working experience\nExperience in asset and liability management will be an advantage\nSelf-motivated with good interpersonal and communication skill in both English and Chinese\nProficient in PC applications, including MS Excel\nCFA / FRM Level I or above is preferable\n\nTo apply, interested parties please follow the application methods available in the Bank\u2019s career website\u00a0https://www.publicbank.com.hk/en/aboutus/careeropportunities. You can send us your resume quoting our job reference number together with present &\u00a0expected salary (a must)\u00a0to the Human Resources Department by email or fax at\u00a02815 3157\u00a0or by post to\u00a0Human Resources Department, 12/F, Public Bank Centre, 120 Des Voeux Road Central, Hong Kong. You may also visit our career website for other career opportunities available within our Group.\n\nPersonal data collected will be used for recruitment purpose only and will be treated in accordance with the Bank\u2019s Personal Information Collection Statement, a copy of which has been available in the Bank\u2019s career website.", "employment_types": ["Full Time", "Permanent"], "selling_points": [], "locations": ["Not Specified"], "categories": ["Banking / Finance", "Analyst", "Professional Services", "Business Analysis / Data Analysis", "Risk Management"], "post_time": "2022-01-15T03:49:06Z", "salary": {"currency": null, "max": null, "min": null, "period": null, "term": null}, "salary_visible": false, "title_keywords": ["officer"], "responsibilities": ["management", "policies", "review", "procedures", "monitor", "ad hoc tasks", "communication", "risk analysis"], "requirements": {"degrees": ["university degree"], "majors": ["mathematics", "risk management", "finance", "economics", "related disciplines"], "languages": ["english", "chinese"], "language_level": ["good"], "hard_skills": ["cfa", "analysis", "pc applications", "ms excel", "frm"], "soft_skills": ["self-motivated", "communication skill", "interpersonal"], "languages_combined": [{"language": "english", "language_level": ["good"]}, {"language": "chinese", "language_level": ["good"]}]}, "experience_required": {"duration": ["minimum 1 year"], "field": ["risk management", "management", "related", "finance", "relevant working experience"]}}, {"job_id": "100003009050611", "location_code": "hk", "company": "Safe Investment Company Limited", "job_title": "Risk Associate", "description": "Responsibilities\n\nOverseeing, coordinating and taking the lead role in providing compliance and market risk advice and support to the investment teams on various day to day matters;\nDeveloping and maintaining various programs to ensure adherence to investment mandate and risk control policies;\nEnsure achievement of all requirements for risk and compliance reporting and escalation of risks as required;\nEnsure adherence to risk management frameworks through effective implementation of a consistent enterprise risk and control management regime across the company;\nBuilding strong relationships with portfolio managers to have risk discussions and facilitate risk management framework implementation including:- promoting awareness of risk and risk management best practices, and as needed, working with and advising portfolio managers in developing effective mitigation steps and controls, analyzing and reporting firm level risk themes, risk levels and focus action items.\n\nRequirement\n\nMaster or above with good school/academic records;\nWorking experience in financial industry would be an advantage;\nA good team player with good communication and interpersonal skill;\nStrong analytical minds with solid execution skills;\nExcellent command of written and spoken English and Putonghua;\nPossess of programing skills of at least one of following: SQL, Python, R, C, C#;\nFresh graduate will also be considered.\n\nWe offer an attractive remuneration with excellent opportunities to the right candidate. Interested parties please apply with detailed resume. (All personal information received will be kept in strictly confidential and only for recruitment purpose only.)", "employment_types": ["Full Time"], "selling_points": [], "locations": ["Central"], "categories": ["Banking / Finance", "Investment", "Risk Management", "Asset Management"], "post_time": "2022-01-14T10:56:18Z", "salary": {"currency": null, "max": null, "min": null, "period": "monthly", "term": null}, "salary_visible": false, "title_keywords": ["associate"], "responsibilities": ["reporting", "control", "management", "maintaining", "policies", "ensure adherence", "compliance", "teams", "developing", "implementation"], "requirements": {"degrees": ["fresh graduate", "master"], "majors": [], "languages": ["putonghua", "english"], "language_level": ["excellent"], "hard_skills": ["sql", "c", "python", "r", "c#"], "soft_skills": ["communication", "good team player", "interpersonal skill"], "languages_combined": [{"language": "putonghua", "language_level": ["excellent"]}, {"language": "english", "language_level": ["excellent"]}]}, "experience_required": {"duration": [], "field": ["financial industry"]}}, {"job_id": "100003009053042", "location_code": "hk", "company": "Chubb Life Insurance Company Ltd.", "job_title": "\u4fdd\u96aa\u7406\u8ca1\u9867\u554f Financial & Insurance Consultant", "description": "- \u81f4\u529b\u7dad\u7e6b\u4e26\u62d3\u5c55\u5ba2\u6236\u95dc\u4fc2\uff0c\u4ee5\u5c08\u696d\u70ba\u57fa\u790e\u00a0\n\n\n- \u63d0\u4f9b\u9069\u5207\u4fdd\u969c\u65b9\u6848\uff0c\u8ddf\u9032\u6838\u4fdd\u53ca\u7d22\u50f9\uff0c\u4ee5\u81f3\u6b7b\u4ea1\u7406\u8ce0\u7684\u6d41\u7a0b \u00a0\n\n- \u4fdd\u55ae\u552e\u5f8c\u670d\u52d9\u00a0\n\n\nOffer\n\n- \u6bcf\u6708\u6d25\u8cbc\n\n- \u5718\u968a\u65c5\u884c\u734e\u52f5\n\n-\u00a0\u696d\u7e3e\u734e\u52f5\n\n- \u6d77\u5916\u6703\u8b70\n\n- \u826f\u597d\u6649\u5347\u6a5f\u6703\n\n\n\nRequirements / Qualifications\n\n- \u6301\u6709\u9999\u6e2f\u6c38\u4e45\u8eab\u4efd\u8a3c\n\n- \u9999\u6e2f\u4e2d\u5b78\u6587\u6191\u8003\u8a66/\u9999\u6e2f\u4e2d\u5b78\u6703\u8003\u4e94\u79d1\u6210\u7e3e\u5408\u683c\uff0c\u5fc5\u9808\u5305\u62ec\u4e2d\u570b\u8a9e\u6587/\u82f1\u570b\u8a9e\u6587\u53ca\u6578\u5b78\n\n- \u6b61\u8fce\u6240\u6709\u8077\u696d\u80cc\u666f\u4eba\u58eb\n\n\u6709\u610f\u61c9\u5fb5\u8005\uff0c\u8acb\u7d93\u7531\u201cApply Now\u201d\u63d0\u4ea4\u7533\u8acb\u3002\n(Interested Parties please click \u2018Apply Now\u2019 to process the application.)\n\n\u6216\u8acb\u65bc\u5de5\u4f5c\u6642\u9593\u5167Whatsapp\u806f\u7d61\u00a0\u00a097454667 Ms. Yeung\u67e5\u8a62\u8a73\u60c5\u3002\n(Or Whatsapp Ms. Yeung 97454667 on working hours)\n\n\u6240\u6709\u6536\u96c6\u7684\u500b\u4eba\u8cc7\u6599\u53ea\u6703\u88ab\u7528\u4f5c\u62db\u52df\u4e4b\u7528\u53ca\u5c07\u6703\u6839\u64da\u6211\u5011\u7684\u8cc7\u6599\u79c1\u7a69\u539f\u5247\u8655\u7406\uff0c\u4f60\u53ef\u5411\u6211\u5011\u7d22\u53d6\u6211\u5011\u7684\u8cc7\u6599\u79c1\u7a69\u539f\u5247\uff0c\u6211\u5011\u5728\u6536\u5230\u8981\u6c42\u5f8c\uff0c\u6703\u96a8\u5373\u63d0\u4f9b\u4e00\u4efd\u6709\u95dc\u539f\u5247\u7684\u8907\u672c\u3002\u5b89\u9054\u4eba\u58fd\u4fdd\u7559\u66f4\u6539\u5f85\u9047\u7684\u689d\u6b3e\u53ca\u7d30\u5247\u3002", "employment_types": ["Full Time"], "selling_points": ["\u5f48\u6027\u4e0a\u73ed\u6642\u9593", "\u8c50\u539a\u6536\u5165", "\u5728\u8b58\u57f9\u8a13"], "locations": ["Causeway Bay"], "categories": ["Banking / Finance", "Financial Services", "Insurance", "Insurance Agent / Broker", "Risk Management"], "post_time": "2022-01-17T05:20:11Z", "salary": {"currency": null, "max": null, "min": null, "period": "monthly", "term": null}, "salary_visible": false, "title_keywords": ["consultant"], "responsibilities": [], "requirements": {"degrees": [], "majors": [], "languages": [], "language_level": [], "hard_skills": [], "soft_skills": [], "languages_combined": []}, "experience_required": {"duration": [], "field": []}}, {"job_id": "100003009051088", "location_code": "hk", "company": "Hong Kong Job Consulting", "job_title": "(Senior) Risk Manager", "description": "A full Licensed Corporation, covering RA1, 2, 4, 5 & 9, is looking for a professional Risk Manager handling risk & control function.\n\nResponsibilities:\n\nHandle risk management related issues covering securities, futures and asset management\nMeasure and monitor risks portfolios, include but not limited to investment, liquidity and counterparty risks\nReview and update on risk management policies and procedures\nEnsure the internal control policies and business activities procedures are complied with the Hong Kong laws included SFC codes and guidelines\nHandle ad-hoc projects assigned by senior management\n\nRequirements:\n\nBachelor\u2019s degree or above in Risk Management, Risk Control or Finance relevant discipline\nProfessional qualification such as CPA, CFA and FRM\n5-7 years of related working experience in risk management in financial services industry\nKnowledge and experience in handling Margin Trading related is must\nHands-on experience in risk management development\nKnowledge in fund management and financial product operations in SFC regulated activities, candidate with experience in fund companies, asset management companies, securities companies are preferred\nExcellent communication skills at both spoken and written in English and Putonghua\nCandidate with less experience will be considered as Manager\n\n\u00a0 \u00a0 Interested parties please send your resume to \"APPLY NOW\u201d\n\n\u00a0***Personal data collected will be used for recruitment purposes only***", "employment_types": ["Full Time", "Permanent"], "selling_points": ["Risk & Control of a SFC Licensed Corporation", "Monitor Risk Portfolios,such as Counterparty Risks", "Experience in Handling Margin Trading related"], "locations": ["Not Specified"], "categories": ["Banking / Finance", "Others", "Risk Management", "Asset Management"], "post_time": "2022-01-15T02:04:16Z", "salary": {"currency": null, "max": null, "min": null, "period": "monthly", "term": null}, "salary_visible": false, "title_keywords": ["manager"], "responsibilities": ["management", "guidelines", "policies", "review", "monitor", "procedures", "senior management", "ad-hoc projects", "internal control", "business activities", "asset management"], "requirements": {"degrees": ["degree or above", "bachelor"], "majors": ["finance", "risk management"], "languages": ["putonghua", "english"], "language_level": ["excellent"], "hard_skills": ["cfa", "cpa", "frm"], "soft_skills": ["communication skills", "hands-on"], "languages_combined": [{"language": "putonghua", "language_level": ["excellent"]}, {"language": "english", "language_level": ["excellent"]}]}, "experience_required": {"duration": ["5-7 years"], "field": ["risk management", "management", "related", "development", "securities", "asset management", "financial services industry", "trading", "financial"]}}, {"job_id": "100003009050613", "location_code": "hk", "company": "Safe Investment Company Limited", "job_title": "Risk Associate / Analyst / Manager (Quantitative)", "description": "Responsibilities\n\n\n\nDevelop and enhance risk models that measure investment risk exposures, and provide compliance and risk management advice to the investment teams;\nInitiate or participate in data analytics and research projects to systematically track index rebalances, factor performance, corporate actions and other investment related topics;\nEnsure achievement of all requirements for risk and compliance reporting and escalation of risks as required;\nWork closely with colleagues from portfolio management, research, and IT and facilitate benchmark and risk management framework implementation.\n\nRequirement\n\n\nBachelor or above in quantitative fields with good school/academic records;\nWorking experience in financial industry and/or data analytics areas would be an advantage;\nPossess of programing skills of SQL, Python, R, C# would be preferred;\nExperience in using Bloomberg, FactSet and Capital IQ is an advantage;\nExperience in index/quantitative research/corporate actions is a plus;\nA good team player with good communication and interpersonal skill;\nStrong analytical minds with solid execution skills;\nExcellent command of written and spoken English and Mandarin;\nFresh graduate will also be considered.\n\nWe offer an attractive remuneration with excellent opportunities to the right candidate. Interested parties please apply with detailed resume. (All personal information received will be kept in strictly confidential and only for recruitment purpose only.)", "employment_types": ["Full Time"], "selling_points": [], "locations": ["Central"], "categories": ["Banking / Finance", "Investment", "Risk Management", "Asset Management"], "post_time": "2022-01-14T10:56:18Z", "salary": {"currency": null, "max": null, "min": null, "period": "monthly", "term": null}, "salary_visible": false, "title_keywords": ["analyst", "associate", "manager"], "responsibilities": ["reporting", "management", "data", "research projects", "compliance", "teams", "implementation", "develop"], "requirements": {"degrees": ["bachelor", "fresh graduate"], "majors": [], "languages": ["english", "mandarin"], "language_level": ["excellent"], "hard_skills": ["plus", "bloomberg", "data analytics", "sql", "python", "r", "c#"], "soft_skills": ["communication", "good team player", "interpersonal skill"], "languages_combined": [{"language": "english", "language_level": ["excellent"]}, {"language": "mandarin", "language_level": ["excellent"]}]}, "experience_required": {"duration": [], "field": ["research", "financial industry"]}}, {"job_id": "100003009052221", "location_code": "hk", "company": "Aon Services Hong Kong Limited \u6021\u5b89\u670d\u52d9\u9999\u6e2f\u6709\u9650\u516c\u53f8", "job_title": "Account Manager - Health Solutions", "description": "We\u2019re hiring!\n\nAon is currently recruiting an Account Manager - Health Solutions\u00a0to join our team in Hong Kong.\n\nAbout Aon\n\nHeadquartered in London, Aon Plc is a leading global professional services firm providing a broad range of risk, retirement and health solutions. Our 50,000 colleagues in 120 countries empower results for clients by using proprietary data and analytics to deliver insights that reduce volatility and improve performance.\n\nAt Aon, you\u2019ll be part of a team which will support and inspire you and provide the opportunities and resources to develop your skills. It\u2019s an environment which encourages you to achieve your best - together we\u2019ll empower results.\u00a0\n\nResponsibilities:\n\nThe incumbent will be responsible to assist the business line department in providing account management to the existing and potential clients. Duties include:\n\nManaging and providing high quality broking services to our existing clients\nAchieving business growth by penetration from current portfolio and by prospects\nLiaise with insurers and service providers to ensure smooth renewal and tackle related issues \u00a0\nPerform claims data analytics and result interpretation for renewal preparation\nMaintain the quality and timeliness of client deliverables, responsible for report development in clear and concise manner\nSupport various projects as assigned by Supervisor\n\nRequirements:\n\nUniversity graduate with minimum\u00a05 years of working experience in Employee Benefits in broker firm or insurance company(ies)\nHolder of FLMI or passed in IIQE Paper I, II, III & IV are preferred\nMature and be a self-starter\nGood organization skills and effective interpersonal skills\nGood analytics and negotiations skills\nGood command of written and spoken English and Chinese; knowledge of Mandarin will be an advantage\nGood command of computer skills including MS Office (Word, Excel, Powerpoint)\n\nHow to Apply\n\nYour opportunity to empower results could start right here. Make your mark and apply online today with a brief covering letter and your resume, sharing relevant achievements for this position.\n\nWe Offer You\n\nA competitive total rewards package, continuing education & training, and tremendous potential with a growing worldwide organization.\n\nOur Colleague Experience\n\nEvery day, our colleagues make a difference, work with the best, own their potential, and value one another. Together, we share this one purpose: to empower economic and human possibility around the world. This unifying goal is at the heart of our identity, and it lives in everything we do. To learn more about our colleague experience, visit Aon Colleague Experience.\n\nAon is an equal opportunities employer. We are committed to creating a winning and inclusive culture where everyone feels valued and has opportunities for growth and development.", "employment_types": ["Full Time", "Permanent"], "selling_points": [], "locations": ["Quarry Bay"], "categories": ["Insurance", "Claims Officer", "Insurance Agent / Broker", "Banking / Finance", "Risk Management"], "post_time": "2022-01-17T02:30:37Z", "salary": {"currency": null, "max": null, "min": null, "period": "monthly", "term": null}, "salary_visible": false, "title_keywords": ["account manager"], "responsibilities": ["management", "data", "quality", "maintain", "liaise with", "report"], "requirements": {"degrees": [], "majors": [], "languages": [], "language_level": [], "hard_skills": [], "soft_skills": [], "languages_combined": []}, "experience_required": {"duration": [], "field": []}}, {"job_id": "100003009049334", "location_code": "hk", "company": "Shanghai Commercial Bank Ltd", "job_title": "Manager / Assistant Manager, Credit Appraisal (Corporate / Commercial)", "description": "Responsibilities:\n\nAnalyse and review complex and sizeable loans in HK and the Mainland to ensure that they adhere to existing policy guidelines\nLiaise with lending units to resolve credit issues and expedite the process\nAssist in collecting market intelligence through various channels\nPrepare various MIS reports for the management\u2019s review\nEnsure credit facilities adhere to the Bank's internal credit policies/guidelines as well as external regulatory requirements\n\nRequirements:\n\nDegree holder in Finance, Risk Management or related disciplines. Professional qualifications, such as CFA, CPA, ECF-CRM, etc., are preferred.\nMinimum 5 years of experience in credit review and analysis in Corporate/Commercial accounts, preferably in banking industry\nSound knowledge of lending and hedging products\nGood understanding in credit risk management and regulatory compliance\nSelf-motivated and detail-minded with strong risk control senses and analytical skills\n(Candidates with less experience will be considered for the position of Assistant Manager)\n\n\nAttractive remuneration package will be offered to the right candidates. Interested parties please click \"Apply Now\" to submit your full resume with current and expected salary to the Human Resources Division.\n\nPlease visit us at www.shacombank.com.hk for more information about our Bank.\n\nAll personal data collected will be used for recruitment related purposes strictly in accordance with the Bank's personal data policies, a copy of which will be provided immediately upon request by contacting our Personal Data Compliance Officer. Applicants who are not contacted within two months may consider their applications unsuccessful and the personal data collected from the applicants will be retained for no longer than two years from the date of rejection during which the applicants may be considered for other suitable positions within the Bank.", "employment_types": ["Full Time", "Permanent"], "selling_points": ["Analyse and review complex and sizeable loans", "Liaise with lending units to resolve credit issues", "Assist in collecting market intelligence"], "locations": ["Central"], "categories": ["Banking / Finance", "Credit Analysis / Approval", "Others", "Risk Management"], "post_time": "2022-01-15T03:50:18Z", "salary": {"currency": null, "max": null, "min": null, "period": "monthly", "term": null}, "salary_visible": false, "title_keywords": ["manager", "assistant manager,"], "responsibilities": ["management", "guidelines", "credit issues", "policies", "review", "regulatory requirements", "reports", "liaise with", "analyse"], "requirements": {"degrees": ["degree holder"], "majors": ["related disciplines", "finance", "risk management"], "languages": [], "language_level": [], "hard_skills": ["professional qualifications", "cfa", "analysis", "analytical skills", "cpa"], "soft_skills": ["detail-minded", "self-motivated", "analytical skills"], "languages_combined": []}, "experience_required": {"duration": ["minimum 5 years"], "field": ["commercial", "banking industry"]}}, {"job_id": "100003009050026", "location_code": "hk", "company": "Genesis Block Limited", "job_title": "KYC/AML Specialist", "description": "Responsibilities\n\nHandle the end-to-end onboarding of new client accounts, collecting all relevant information and manage the client onboarding experience\nReview KYC (Know Your Client) documentation and perform customer due diligence (CDD) for new client accounts and periodic CDD review on existing client accounts\nProvide administrative support for the middle and back-office team\nMaintain and update database of all information and documents\nLiaise with internal teams to ensure a smooth onboarding experience\nOpportunities to know know your token (KYT, Crypto transaction monitoring)\n\nQualifications\n\nBachelor\u2019s degree\n1+ years experience in client onboarding, KYC/AML is preferred but fresh graduates are welcome\nExcellent written and verbal communication skills\nStrong analytical and problem-solving skills with excellent attention to detail\nFluency in written and spoken English; fluency in an Asian language is an advantage\nAbility to work independently in a fast-paced environment", "employment_types": ["Full Time", "Permanent"], "selling_points": ["Growing Digital Assets Brokerage firm", "Great exposure to blockchain and crypto industry", "Attractive package, Performance Driven bonus"], "locations": ["Wan Chai"], "categories": ["Banking / Finance", "Analyst", "Professional Services", "Legal & Compliance", "Risk Management"], "post_time": "2022-01-14T09:39:12Z", "salary": {"currency": "HKD", "max": 34999, "min": 20000, "period": "monthly", "term": null}, "salary_visible": true, "title_keywords": ["specialist"], "responsibilities": ["aml", "cdd", "review", "teams", "monitoring", "communication", "customer due diligence", "liaise with", "maintain", "database", "kyc", "documentation", "provide administrative support"], "requirements": {"degrees": ["degree", "bachelor"], "majors": [], "languages": ["english"], "language_level": ["fluency"], "hard_skills": ["crypto", "aml", "cdd", "customer due diligence", "kyc", "documentation", "problem-solving skills"], "soft_skills": ["communication skills", "work independently", "fast-paced environment", "attention to detail", "smooth", "problem-solving skills"], "languages_combined": [{"language": "english", "language_level": ["fluency"]}]}, "experience_required": {"duration": ["1+ years"], "field": []}}, {"job_id": "100003009052509", "location_code": "hk", "company": "Standard Chartered Bank (Hong Kong) Ltd", "job_title": "Associate, Financing Solutions - (2100032450)", "description": "About Standard Chartered\u00a0\nWe are a leading international bank focused on helping people and companies prosper across Asia, Africa and the Middle East.\u00a0\n\nTo us, good performance is about much more than turning a profit.\u00a0 It's about showing how you embody our valued behaviours - do the right thing, better together and never settle - as well as our brand promise, Here for good.\n\nWe're committed to promoting equality in the workplace and creating an inclusive and flexible culture - one where everyone can realise their full potential and make a positive contribution to our organisation. This in turn helps us to provide better support to our broad client base.\nAbout Mox\nAs one of the biggest banks in market, we are rapidly expanding by growing a new virtual banking business in Hong Kong. We see ourselves as a fast growing start-up company where you will enjoy autonomy and teamwork at the same time, solving new and exciting problems in a nimble and agile way. Join us and be part of history making for future banking experience!\nThe Role Responsibilities\nYou will lead a multidisciplinary team as part of a broader portfolio to design, develop and deliver one of our key product or service propositions. You are a digital native with a natural intuition for design and technology, coupled with a strategic mindset. You are comfortable working in a fast-paced environment with high degrees of ambiguity, get excited by solving complex problems and are happy to roll your sleeves up and get things done. This role is as a Product Owner for investment.\nProvide insights into product, technology and market trends, preempting imminent disruptions and identifying opportunities for acceleration\nDeliver the best in class customer experiences, with cutting edge risk management & regulatory technologies\nPioneer in identifying and integrating internal and external alternative data\nConsecutively make researches about retail products, new features, identify possible outbreaking updates or changes within the sector, inform the teams about the changes and possible usage scenarios in our services\nGather, track and manage user comments, bank needs, concept testing, analytics tools\nFacilitate the build and testing of operational processes, systems, and reporting capabilities\nEnsure the credit risk services running 24/7 with very high response within the shortest response time\nEnsure bi-weekly app releases are smooth to customers and all services are working as expected\nWorking closely with business analysis, UX teams and technology teams to plan the product features backlog, prioritize, evaluate and deliver the initiatives. Ensure all teams has an adequate amount of prior prepared tasks to work on\nDesign, monitor and report on product KPIs, measure effectiveness of features and sharing results and insights within the organization\nOur Ideal Candidate\nSolid experience in product ownership and platform as well as service delivery with a strong technical background\nFluent English and Cantonese\nIn-depth knowledge and hands-on experience with agile development methodologies\nKnowledge about the platform developing skills and APIs\nOutstanding communication, presentation, and leadership skills\nAbility to manage time and schedules to meet aggressive deadlines and influence through persuasive written and verbal communication\nExceptional interpersonal and communication skills\nSharp analytical and problem-solving skills\nAn ability to think strategically and creatively\nAttention to details\nApply now to join the Bank for those with big career ambitions.\n", "employment_types": ["Full Time"], "selling_points": ["To support the origination of primary transactions", "Senior Transactors\u2019 guidance to prepare pitchbooks", "Arrangement of signing ceremonies"], "locations": ["Not Specified"], "categories": ["Banking / Finance", "Others", "Risk Management"], "post_time": "2022-01-17T03:17:00Z", "salary": {"currency": null, "max": null, "min": null, "period": "monthly", "term": null}, "salary_visible": false, "title_keywords": ["associate"], "responsibilities": ["provide insights", "data", "schedules", "agile development", "design", "communication", "plan", "service delivery", "teams", "monitor", "developing", "develop", "testing", "client base", "banking", "kpis", "report", "reporting", "management", "analytics tools", "comments", "systems", "evaluate", "business analysis"], "requirements": {"degrees": [], "majors": [], "languages": ["cantonese", "english"], "language_level": ["fluent"], "hard_skills": ["analytics tools", "inform", "bi", "agile", "analysis", "make", "problem-solving skills"], "soft_skills": ["persuasive", "agile", "focused", "fast-paced environment", "leadership skills", "communication", "committed", "smooth", "interpersonal", "presentation", "ideal", "communication skills", "prioritize", "attention to details", "think strategically", "problem-solving skills", "positive", "flexible", "teamwork", "hands-on", "organisation"], "languages_combined": [{"language": "cantonese", "language_level": ["fluent"]}, {"language": "english", "language_level": ["fluent"]}]}, "experience_required": {"duration": [], "field": ["risk management", "development", "banking experience"]}}, {"job_id": "100003009051920", "location_code": "hk", "company": "Octopus Holdings Limited", "job_title": "Compliance Specialist, Financial Crime Compliance (1 year contract)", "description": "About Standard Chartered\u00a0\nWe are a leading international bank focused on helping people and companies prosper across Asia, Africa and the Middle East.\u00a0\n\nTo us, good performance is about much more than turning a profit.\u00a0 It's about showing how you embody our valued behaviours - do the right thing, better together and never settle - as well as our brand promise, Here for good.\n\nWe're committed to promoting equality in the workplace and creating an inclusive and flexible culture - one where everyone can realise their full potential and make a positive contribution to our organisation. This in turn helps us to provide better support to our broad client base.\n\nAbout Mox\n\n\nAs one of the biggest banks in market, we are rapidly expanding by growing a new virtual banking business in Hong Kong. We see ourselves as a fast growing start-up company where you will enjoy autonomy and teamwork at the same time, solving new and exciting problems in a nimble and agile way. Join us and be part of history making for future banking experience!\n\nThe Role Responsibilities\n\nWe are looking for an experienced office manager to be responsible for the office administrative work, facilities management, team events, and assist a few senior executives of the Bank in some of their daily office administration.\u00a0\nYou will:\n\nManage the workday schedule of a few senior executives, and their day-to-day admin work.\nManage the office space, including the facilities management and premises improvements, engaging the landlord and the property management team, office lease arrangement, and ad hoc issues in relations with the premises.\u00a0\nFacilitate the smooth running of the offices, optimize the office space, ensure the health and safety of the personnel, procure and arrange the office equipment, and manage the hardware inventory.\u00a0\nAssist the team on some team events e.g. celebrations, team gatherings and townhalls events\nWork on any ad hoc team related tasks as assigned at times.\nOur Ideal Candidate\nAt least 8 years of work experience, of which no less than 5 years of experience as office manager, or personal assistant.\nExperience in facilities management an advantage.\nEnglish is the primary language in this organization.\u00a0 You need to be able to communicate effectively with English verbally and in writing; experience in working with non-Chinese speaking executives will be an advantage.\nProficient in Mac OS, MS Office and other new office communication tools \u2013 O365 and Slack.\nHighly responsive, and comfortable to work with the corporate mobile device during and after office hours; able to handle the ad hoc situations and response positively and promptly; feel at ease to offer occasional help outside office hours.\nPleasant and self-motivated personality, positive mindset, able to work with diverse culture.\nDiscretion and integrity in handling confidential information.\nApply now to join the Bank for those with big career ambitions.\n", "employment_types": ["Full Time", "Contract"], "selling_points": ["Five-day work", "Degree holder preferably in Risk Management", "At least 3 year of AML compliance related"], "locations": ["Kowloon Bay"], "categories": ["Banking / Finance", "Others", "Risk Management"], "post_time": "2022-01-17T01:32:39Z", "salary": {"currency": null, "max": null, "min": null, "period": "monthly", "term": null}, "salary_visible": false, "title_keywords": ["specialist"], "responsibilities": ["management team", "management", "ad hoc", "administrative work", "office administration", "inventory", "hardware", "client base", "schedule", "banking", "communication tools"], "requirements": {"degrees": [], "majors": [], "languages": ["english", "chinese"], "language_level": ["advantage"], "hard_skills": ["o365", "no", "mac os", "ease", "agile", "hardware", "make", "facilities management", "mobile device", "ms office"], "soft_skills": ["flexible", "self-motivated", "agile", "focused", "responsible", "positive mindset", "teamwork", "integrity", "pleasant", "communication", "committed", "diverse", "organisation", "smooth", "responsive", "positive", "ideal"], "languages_combined": [{"language": "english", "language_level": []}, {"language": "chinese", "language_level": ["advantage"]}]}, "experience_required": {"duration": ["at least 8 years", "5 years"], "field": ["management", "banking experience"]}}, {"job_id": "100003009049556", "location_code": "hk", "company": "Bangkok Bank Public Co Ltd", "job_title": "Compliance Officer (Ref: CL-11/178/240-DB)", "description": "About Standard Chartered\u00a0\nWe are a leading international bank focused on helping people and companies prosper across Asia, Africa and the Middle East.\u00a0\n\nTo us, good performance is about much more than turning a profit.\u00a0 It's about showing how you embody our valued behaviours - do the right thing, better together and never settle - as well as our brand promise, Here for good.\n\nWe're committed to promoting equality in the workplace and creating an inclusive and flexible culture - one where everyone can realise their full potential and make a positive contribution to our organisation. This in turn helps us to provide better support to our broad client base.\n\n\nThe Role Responsibilities\nConducts all aspects of market research activities to support the commercial team.\nAnalyses deal economics through robust financial modelling.\nAssists the team in pricing a deal/transaction to enhance deal selection and ensure alignment to AF strategy.\nPerforms robust risk analysis and ensuring adherence to the relevant bank polices/processes and Aviation Finance underwriting standards.\nSupports the commercial team in related marketing activities, preparation of proposals etc.\nSupports the commercial team in the origination of new business in franchise markets.\nSupport the Aviation Finance team in collaborating with CCIB teams to identify and target transactions and pursue cross-sell opportunities in line with CCIB\u2019s business strategy.\nSupport the Aviation Finance team in organising and driving business success through improvement in client penetration and profitability in conjunction coverage partners.\n\nBusiness\n\nEffectively use SCB\u2019s industry expertise, knowledge and professional network for ideation, generating leads for new deals and assessment of opportunities\nClient interface at senior management levels and ensuring that the engagement, services and quality of work meets the highest industry standards\nStructuring of transactions including cross border deals, to best meet clients\u2019 needs covering solutions ranging from senior and/ or mezzanine debt/bonds and/ or operating and finance lease options, financing across different parts of the capital structure\nPrepare high quality pitching and marketing materials for client presentations.\nCollaborate with internal stakeholders including client coverage, other product teams in financial markets,\u00a0 transaction banking and risk.\nTo ensure that new and existing business is consistent with Group policies, meets applicable credit risk criteria, internal approval procedures and provides acceptable risk adjusted return for the Bank, all as defined in the Underwriting Standards, globally and locally, including reputational risk.\nSupport and oversee robust deal selection through transaction analysis and pricing, conflict resolution and risk management to ensure the business is consistent with the strategy and risk appetite of the Bank\n\nOur Ideal Candidate\n\n2-3\u00a0years of experience in banking industry/ financial institution\u00a0\nBachelor's Degree or above in related discipline\nExperienced in credit analysis, ideally in aviation\nEffective communication skills & ability towork under pressure\nHKMA License as requested\nMandarin speaking is a must with good command in English\n\nApply now to join the Bank for those with big career ambitions.\u00a0", "employment_types": ["Full Time"], "selling_points": [], "locations": ["Central"], "categories": ["Banking / Finance", "Corporate Banking", "Others", "Risk Management"], "post_time": "2022-01-14T08:53:46Z", "salary": {"currency": null, "max": null, "min": null, "period": "monthly", "term": null}, "salary_visible": false, "title_keywords": ["compliance officer"], "responsibilities": ["collaborate with", "management", "policies", "analysis", "teams", "market research", "transactions", "quality", "presentations", "procedures", "resolution", "client base", "communication", "finance team", "risk analysis", "banking", "marketing materials", "senior management"], "requirements": {"degrees": ["degree or above", "bachelor"], "majors": [], "languages": ["english", "mandarin"], "language_level": ["good command"], "hard_skills": ["hkma", "analysis", "presentations", "make", "credit analysis"], "soft_skills": ["flexible", "communication skills", "under pressure", "focused", "robust", "committed", "organisation", "positive", "ideal"], "languages_combined": [{"language": "english", "language_level": ["good command"]}, {"language": "mandarin", "language_level": ["good command"]}]}, "experience_required": {"duration": ["2-3 years"], "field": ["banking industry", "financial"]}}, {"job_id": "100003009047739", "location_code": "hk", "company": "Public Bank (Hong Kong) Ltd", "job_title": "Risk Clerk (6 months renewable contract) (Ref: JD-RC)", "description": "Assist in compilation of management reports and provide administrative support to the team for the enhancement of risk management framework, policies and procedures\nHigher Diploma or above\nMinimum 1 year relevant experience in banking / risk management / accounting / finance\nFluency in written and spoken English and Chinese\nProficient in PC and MS Office application\nFresh graduate will also be considered\n\nTo apply, interested parties please follow the application methods available in the Bank\u2019s career website https://www.publicbank.com.hk/en/aboutus/careeropportunities.\n\nYou can send us your resume quoting our job reference number together with present & expected salary (a must) to the Human Resources Department by email or fax at 2815 3157 or by post to Human Resources Department, 12/F, Public Bank Centre, 120 Des Voeux Road Central, Hong Kong. You may also visit our career website for other career opportunities available within our Group.\n\nPersonal data collected will be used for recruitment purpose only and will be treated in accordance with the Bank\u2019s Personal Information Collection Statement, a copy of which has been available in the Bank\u2019s career website.", "employment_types": ["Contract"], "selling_points": [], "locations": ["Central"], "categories": ["Banking / Finance", "Others", "Risk Management"], "post_time": "2022-01-15T03:49:04Z", "salary": {"currency": null, "max": null, "min": null, "period": null, "term": null}, "salary_visible": false, "title_keywords": ["clerk"], "responsibilities": ["management", "policies", "procedures", "management reports", "banking", "provide administrative support"], "requirements": {"degrees": ["higher diploma or above", "fresh graduate"], "majors": [], "languages": ["english", "chinese"], "language_level": ["fluency"], "hard_skills": ["pc", "management reports", "ms office"], "soft_skills": [], "languages_combined": [{"language": "english", "language_level": ["fluency"]}, {"language": "chinese", "language_level": ["fluency"]}]}, "experience_required": {"duration": ["minimum 1 year"], "field": ["risk management", "finance", "relevant experience", "banking", "accounting"]}}, {"job_id": "100003009049835", "location_code": "hk", "company": "Chiyu Banking Corp Ltd", "job_title": "Assistant Risk Manager (Market Risk)", "description": "Responsibilities:\n\nAssist in implementing enhanced risk management framework\nIdentifying, measuring and monitoring market risk of trading book and banking book\u2019s fixed income / interest rate / FX business\nMonitor bank\u2019s risk level to fulfill the requirements of relevant policies and limits in areas of Market Risk, and follow up the limit excess events\nReview market risk and relevant risk management policies and procedures\nInvolve in related system enhancement projects, provide users specification and requirements\nInvolve for projects and Basel III / regulatory related issue(s), particularly on the new market risk management requirements under Basel III (i.e. FRTB)\nParticipate the new product and new business initiatives\nCarry out any Market Risk and other related risk management duties as from time to time assigned by the Senior Management\n\nRequirements:\n\nDegree holder in Quantitative Finance, Risk Management, Financial Engineering or related disciplines\nProfessional qualification in CFA or FRM will be an advantage\nMinimum 3 years working experience in banks or financial institutions with most of the risk management areas such as market risk\nSound knowledge in statistical and financial analysis & regulatory requirements\nSelf-motivated and willing to work under pressure\nGood command of both written and spoken English and Chinese\nProficient Good command of MS Office and computer analytic applications such as SAS\u3001SQL and Macro\n\n(For those with less working experience will consider the role of Senior Officer/ Officer)\n\n\n\nWe offer competitive packages and promising career opportunities to the right candidates. Please send your full resume with current salary, expected salary and the date of availability to The Human Resources Department, Chiyu Banking Corporation Ltd, 12/F, Chiyu Bank Building, No. 78 Des Voeux Road Central, Hong Kong or fax to 2986-3233 or by clicking Apply Now.\n\nInformation provided will be treated in strict confidence and only be used for recruitment purposes. All personal data of unsuccessful applicants will be destroyed after the recruitment exercise. A copy of Personal Information Collection Statement is available upon request.", "employment_types": ["Full Time", "Permanent"], "selling_points": [], "locations": ["Central"], "categories": ["Banking / Finance", "Risk Management"], "post_time": "2022-01-14T09:18:21Z", "salary": {"currency": null, "max": null, "min": null, "period": "monthly", "term": null}, "salary_visible": false, "title_keywords": ["manager", "assistant"], "responsibilities": ["management", "business initiatives", "policies", "monitoring", "monitor", "review", "procedures", "banking", "enhancement projects", "senior management"], "requirements": {"degrees": ["degree holder"], "majors": ["related disciplines", "finance", "engineering", "risk management"], "languages": ["english", "chinese"], "language_level": ["good command"], "hard_skills": ["macro", "cfa", "financial analysis", "frm", "ms office"], "soft_skills": ["self-motivated", "work under pressure"], "languages_combined": [{"language": "english", "language_level": ["good command"]}, {"language": "chinese", "language_level": ["good command"]}]}, "experience_required": {"duration": ["minimum 3 years"], "field": ["risk management", "financial institutions", "market risk"]}}, {"job_id": "100003009048835", "location_code": "hk", "company": "Bank of China (Hong Kong) Limited", "job_title": "Risk Manager/Senior Risk Manager(Integrated Risk Management)", "description": "Responsibilities:\nTo assist drafting the Group\u2019s integrated risk management report;\n\nTo assist drafting risk management policies;\n\nTo assist drafting the Group\u2019s risk management strategies and annual work plan;\n\nTo coordinate the consolidation of risk management information from various risk management units;\n\nTo coordinate implementing risk management projects;\n\nTo keep track of changes in macro economies, regulatory requirements and business development, analyze its impact on risk management, and propose risk management measures accordingly.\n\nRequirements:\nQualifications of degree or above, major in Economics, Finance, Accounting, Business & Administration or relevant professions.\n\nWorking experience of 5 years or above in bank with at least 2 years in risk management, such as credit risk, market risk, interest risk.\n\nExcellent analytical, problem solving, communication and language skills.\n\nFamiliar with MS Office software, such as MS Word, Excel and PowerPoint.\n\nExcellent Chinese and English.\n\nWe offer competitive remuneration package and comprehensive fringe benefits including medical and life insurance, and different types of allowances to the right candidate. Interested parties, please submit your application online. For details, please visit our website http://www.bochk.com\n\n[via APPLY NOW]\u00a0\u00a0\n\nData collected would be used for recruitment purposes only. It might also be disclosed to our subsidiaries or Associated Companies to process the information for appointment. Applicants who do not hear from us within 8 weeks may consider their application unsuccessful and their data will be destroyed within 12 months of receipt.", "employment_types": ["Full Time"], "selling_points": ["Drafting risk management policies", "Coordinate the consolidation of risk management", "5 years experience in relevant field"], "locations": ["Not Specified"], "categories": ["Banking / Finance", "Financial Services", "Risk Management"], "post_time": "2022-01-14T07:23:16Z", "salary": {"currency": null, "max": null, "min": null, "period": "monthly", "term": null}, "salary_visible": false, "title_keywords": ["manager"], "responsibilities": ["management", "policies", "regulatory requirements", "coordinate", "plan", "management report"], "requirements": {"degrees": ["degree or above"], "majors": ["business", "finance", "economics", "accounting"], "languages": ["english", "chinese"], "language_level": ["excellent"], "hard_skills": ["excel", "powerpoint", "problem solving", "ms office", "ms word"], "soft_skills": ["problem solving", "comprehensive", "communication"], "languages_combined": [{"language": "english", "language_level": ["excellent"]}, {"language": "chinese", "language_level": ["excellent"]}]}, "experience_required": {"duration": ["at least 2 years", "of 5 years"], "field": ["risk management", "market risk", "credit risk"]}}, {"job_id": "100003009048437", "location_code": "hk", "company": "Hang Seng Bank Ltd", "job_title": "Assistant Client Services Manager (Client Onboarding)", "description": "Commercial Banking \u2013 Wholesale Client Services\n\nHang Seng\u2019s Commercial Banking business provides customized one-stop financial solutions to our corporate customers, from prime small and medium-sized businesses to publicly listed companies. \u00a0\n\nFor customers conducting business locally or around the world, we offer a comprehensive range of services including corporate lending, trade and receivables finance, structured loan, cash management, investment, treasury services, insurance and e-Banking services. \u00a0As a reliable financial partner, we attend to the specific business needs of our customers and provide efficient tailor-made banking solutions through our relationship managers and dedicated specialists.\n\nWe are currently seeking a high caliber professional to join our department as\u00a0Assistant Client Services Manager.\n\n\n\nPrincipal responsibilities\n\nEngage new and existing Commercial Banking (CMB) customers in the completion of account opening requests\u00a0\nIdentify CDD requirement gap by analyzing customer information to ensure collection of sufficient information and supporting documents required for the completion of the account opening\u00a0\nMake recommendations on all client on-boarding decisions according to the sufficiency in fulfilling CDD requirements and raise exception / variance approval requests with sufficient justifications\nParticipate in account opening related process reviews and make recommendation with an aim to improve customer experience and service turnaround time\n\nRequirements\n\nUniversity degree in Business Administration or related disciplines\nMinimum of 2 years of work experience in providing high standard of customer service preferred\nKnowledge in commercial banking and Know Your Customer (KYC) regulatory requirements on corporate customers\nExperience in handling CDD review for corporate customers preferred\nGood communication and interpersonal skills\nProficiency in both spoken and written English and Chinese\nHigh level of customer centricity mindset with dedication to deliver exceptional quality services for customers\n\n(Candidate\u00a0with less experience will be considered as Client Services Officer)\n\nIf you would like to explore other opportunities at Hang Seng Hong Kong, please visit\u00a0www.hangseng.com/careers/\u00a0for details.\n\nThe health and safety of our employees and candidates is very important to us. Due to the current situation related to the Novel Coronavirus (2019-nCoV), we\u2019re leveraging our digital capabilities to ensure we can continue to recruit top talent at the HSBC Group. \u00a0As your application progresses, you may be asked to use one of our digital tools to help you through your recruitment journey. \u00a0If so, one of our Resourcing colleagues will explain how our video-interviewing technology will be used throughout the recruitment process and will be on hand to answer any questions you might have.\n\nAll information provided by applicants will be used only for recruitment purposes and will be used strictly in accordance with the Bank's personal data policies, a copy of which may be obtained by the applicant upon request. Unless otherwise instructed in writing by the applicant concerned, applicants may be considered for other suitable positions within the Bank and its related companies. The personal data of unsuccessful job applicants may be retained for a maximum of two years from the date when the job application is rejected and such data may be retained for a longer period if there is a subsisting reason that obliges the Bank to do so, after which the personal data will be destroyed.", "employment_types": ["Full Time", "Permanent"], "selling_points": [], "locations": ["Not Specified"], "categories": ["Banking / Finance", "Corporate Banking", "Others", "Risk Management"], "post_time": "2022-01-14T06:35:04Z", "salary": {"currency": null, "max": null, "min": null, "period": "monthly", "term": null}, "salary_visible": false, "title_keywords": ["client services manager", "assistant"], "responsibilities": ["make recommendations", "make recommendation", "cdd", "account opening", "banking"], "requirements": {"degrees": ["university degree"], "majors": ["related disciplines", "business administration"], "languages": ["english", "chinese"], "language_level": ["proficiency"], "hard_skills": ["cdd", "kyc", "reason", "know your customer"], "soft_skills": ["novel", "customer service", "communication and interpersonal skills"], "languages_combined": [{"language": "english", "language_level": ["proficiency"]}, {"language": "chinese", "language_level": ["proficiency"]}]}, "experience_required": {"duration": ["minimum of 2 years"], "field": ["customer service"]}}, {"job_id": "100003009048735", "location_code": "hk", "company": "Hang Seng Bank Ltd", "job_title": "Assistant Manager, Control Office", "description": "Responsibilities\n\nPerform acquisition policy execution, credit process improvement as well as portfolio management strategy in credit card portfolio to optimize the portfolio performance\nPerform credit analysis for acquisition and portfolio actions\nAssist to formulate and enhance credit policy of credit card\nPrepare periodic reports to monitor the portfolio performance, acquisition quality, product campaign, collection management, etc\nConduct credit assurance for credit card\nPerform user acceptance tests on system enhancement or other processes\nSupport other risk functions to identify potential areas of improvement in credit policies, product offers, customer segments, credit procedures, and portfolio management\n\nRequirements\n\nUniversity degree holder or above in Business Administration, Finance, Risk Management, Statistics or other related disciplines\n1-3 years\u2019 relevant experience in Risk Analytics and Credit & Risk Management, preferably in consumer finance or consumer banking industry with sound knowledge in Credit Card\nFinancial Risk Manager (FRM) or any risk management related qualification is preferable\nProficient in SAS\nKnowledge of VBA is an advantage\nProficient in spoken and written English and Chinese\nCandidates with less experience will be considered as Credit Risk Analyst\n\nThis is a very rewarding and exciting opportunity. We offer an attractive remuneration to the successful candidates. Please forward your resume with present and expected salary by clicking \u201cAPPLY NOW\u201d or complete the online application form at\u00a0https://www.primecredit.com/career/en/jobs.\n\nTo know more about PrimeCredit, please visit our websites\u00a0https://www.primecredit.com/career/en/.\n\nAll applications will be treated in strict confidence and only be used for recruitment related purpose.", "employment_types": ["Full Time", "Permanent"], "selling_points": [], "locations": ["Not Specified"], "categories": ["Banking / Finance", "Corporate Banking", "Risk Management"], "post_time": "2022-01-14T08:35:17Z", "salary": {"currency": null, "max": null, "min": null, "period": "monthly", "term": null}, "salary_visible": false, "title_keywords": ["assistant manager,"], "responsibilities": ["management", "policies", "analysis", "quality", "monitor", "procedures", "reports"], "requirements": {"degrees": ["university degree"], "majors": ["risk management", "business administration", "finance", "statistics", "related disciplines"], "languages": ["english", "chinese"], "language_level": ["proficient"], "hard_skills": ["vba", "financial risk manager", "frm", "sas"], "soft_skills": [], "languages_combined": [{"language": "english", "language_level": ["proficient"]}, {"language": "chinese", "language_level": ["proficient"]}]}, "experience_required": {"duration": ["1-3 years"], "field": ["risk management", "banking industry", "credit card", "finance", "relevant experience", "credit risk"]}}, {"job_id": "100003008648770", "location_code": "hk", "company": "\u81fa\u7063\u4e2d\u5c0f\u4f01\u696d\u9280\u884c\u80a1\u4efd\u6709\u9650\u516c\u53f8", "job_title": "\u6d77\u5916\u64da\u9ede\u7c4c\u8a2d\u4eba\u54e1", "description": "about the company\n\n\n\n\n\nOur client is a well-established corporate bank.\n\nabout the team\n\n\nThe team is hands-on and expanding.\n\nabout the job\n\n\nYou will be:\n\n\nDesigning, developing and performing market risk management and monitoring\nIdentify, monitor, manage, and control the market risk of business and products\nMonitor key risk measures (e.g. Greeks and PV01) and risk metrics (e.g. VaR, ES and Stress Test) against limits mandates\nProvide analysis and commentaries on the key drivers affecting risk metrics / stress testing results\n\nabout the requirements\n\n\n\n\nBachelor's degree holder in risk management, finance, accounting, or business discipline\n3+ years of experience in market risk, product control or valuation in corporate banks\nFamiliar with financial products of fixed income, FX, and other related derivatives\nGood command in both Chinese and English languages\nTo apply online, please click on the link. Alternatively, for a confidential discussion please contact Cheryl Tsang on + 852 2232 3470 or email: cheryl.tsang@randstad.com.hk", "employment_types": ["Full Time"], "selling_points": [], "locations": ["Overseas"], "categories": ["Banking / Finance", "Project Finance", "Marketing / Public Relations", "Marketing - Brand / Product Management", "Risk Management"], "post_time": "2022-01-11T16:01:28Z", "salary": {"currency": null, "max": null, "min": null, "period": "monthly", "term": null}, "salary_visible": false, "title_keywords": [], "responsibilities": ["management", "control", "analysis", "monitoring", "monitor", "developing", "testing", "designing"], "requirements": {"degrees": ["bachelor", "degree holder"], "majors": ["finance", "risk management", "accounting", "business"], "languages": ["english", "chinese"], "language_level": ["good command"], "hard_skills": [], "soft_skills": [], "languages_combined": [{"language": "english", "language_level": ["good command"]}, {"language": "chinese", "language_level": ["good command"]}]}, "experience_required": {"duration": ["3+ years"], "field": ["market risk"]}}, {"job_id": "100003009046467", "location_code": "hk", "company": "Ignite Recruitment Hong Kong Limited", "job_title": "Compliance Manager (Team Head, VP - SVP), Regional Corporate & Investment Bank", "description": "Responsibilities:\n\n\nAct as department head to manage various teams to meet all operation and compliance requirements;\nManage centralization and transactional services for retail and corporate customers;\nSupport Chief Operating Officer to develop centralised operations for Head Office and Mainland;\nHandle time critical customer transactions (including time deposit, transfer, unit trust operations, payment services, complicated problem solving, customer instructions handling);\nDevelop departmental procedure manuals/guidelines and policy, including split office operations, BCP;\nMaintain MIS and compilation of various reports; and manage budgeting ;\nHandle AML and all regulatory reporting;\nManage Key strategic projects; and\nAd hoc tasks/projects as assigned\u00a0\n\nRequirements\n\n\nUniversity graduate in Business Administration or related disciplines;\nMinimum 15 years solid experience in retail banking or back-office operations with at least 6 - 8 years as department head level;\nSolid experience in branch operations, payment operations, retail investment settlement and account opening;\nExposure in project management, especially in leading bank-wide projects;\nGood communication and leading skills;\nProject management skills; and AML handling knowledge;\nStrong self-motivation with ability to work under pressure; and\nExcellent analytical and with good command of both spoken and written English and Chinese including Putonghua.\n\nWe offer competitive remuneration package and promising career opportunities to the successful candidates. Interested parties, please send full resume with current & expected salary and the date of availability to\u00a0The HR Division by clicking \"Apply Now\" button below. Please quote reference on your application. Information provided will be treated in strict confidence and only be used for recruitment purposes. Personal data of unsuccessful applications will be destroyed 24 months after the completion of the recruitment and selection exercise.", "employment_types": ["Full Time", "Permanent"], "selling_points": ["Expanding Regional Corporate & Investment Bank", "Strong Financial Performance with Attractive Bonus", "Excellent Work-Life Balance"], "locations": ["Central & Western Area"], "categories": ["Banking / Finance", "Corporate Banking", "Others", "Risk Management"], "post_time": "2022-01-13T11:29:59Z", "salary": {"currency": null, "max": null, "min": null, "period": "monthly", "term": null}, "salary_visible": false, "title_keywords": ["compliance manager"], "responsibilities": ["reporting", "aml", "guidelines", "operations", "budgeting", "compliance", "teams", "ad hoc tasks", "transactions", "develop", "payment", "maintain", "reports"], "requirements": {"degrees": ["university graduate"], "majors": ["related disciplines", "business administration"], "languages": ["putonghua", "english", "chinese"], "language_level": ["excellent", "good command"], "hard_skills": ["account opening", "project management", "aml"], "soft_skills": ["project management skills", "communication", "project management", "self-motivation", "work under pressure"], "languages_combined": [{"language": "putonghua", "language_level": ["excellent", "good command"]}, {"language": "english", "language_level": ["excellent", "good command"]}, {"language": "chinese", "language_level": ["excellent", "good command"]}]}, "experience_required": {"duration": ["at least 6 - 8 years", "minimum 15 years"], "field": ["retail banking", "retail", "investment"]}}, {"job_id": "100003009046327", "location_code": "hk", "company": "Randstad Hong Kong Limited", "job_title": "Market Risk Manager, Corporate and Investment Bank", "description": "Reporting to the Senior Manager (Group-wide Supervision (GWS)), the incumbent will assume the following:\n\nKey Responsibilities\n\nAssist in the prudential supervision of major insurance groups, with focus on conducting reviews and risk assessments as part of the GWS supervisory framework\u00a0\nParticipate in the preparations for supervisory colleges and crisis management group meetings\nLiaise and co-ordinate with local and overseas insurance regulators and other financial regulators on prudential supervision of life insurers, and in performing group-wide supervision of major insurance groups\nKeep abreast of developments in the insurance industry, financial and capital markets that may impact on major insurance groups operating in Asia\nOther duties as assigned by senior management to facilitate the administration of the statutory functions of IA\n\nRequirements\n\nA Bachelor\u2019s degree in actuarial science, accounting, finance or related disciplines\nA professional qualification such as qualified actuary, CPA or financial risk manager\nMinimum 5 years\u2019 relevant experience in financial services\nStrong analytical and financial analysis skills\nStrong command of written and spoken English\n\nRemuneration Package\n\nA competitive remuneration package commensurate with the successful candidate\u2019s experience and qualifications will be offered.\u00a0\n\nApplication\n\nReview of the applications will start as soon as possible and continue until 21 January 2022, or until the post is filled. Interested applicants may send a letter of application quoting the reference number, together with a full resume stating current and expected salaries by clicking \"Apply Now\".\n\n\nThe Insurance Authority is an equal opportunities employer. Applicants not invited for an interview within 2 months from the closing date may assume their applications unsuccessful. Applications may be considered for other suitable positions within IA. All applications will be handled in strict confidence and the information collected will only be used for recruitment purposes. All information on non-shortlisted applicants will be destroyed after 6 months from the close of applications.\u00a0", "employment_types": ["Full Time", "Permanent"], "selling_points": ["Well-established Corporate Bank", "Bank-wide coverage", "Sizeable team"], "locations": ["Not Specified"], "categories": ["Banking / Finance", "Corporate Banking", "Financial Services", "Risk Management"], "post_time": "2022-01-13T10:30:59Z", "salary": {"currency": "HKD", "max": 54999, "min": 30000, "period": "monthly", "term": null}, "salary_visible": true, "title_keywords": ["manager"], "responsibilities": ["liaise", "other duties", "co-ordinate with", "senior management", "insurance", "crisis management", "administration"], "requirements": {"degrees": ["degree", "bachelor"], "majors": ["related disciplines", "finance", "accounting", "actuarial science"], "languages": ["english"], "language_level": [], "hard_skills": ["financial analysis", "cpa", "financial risk manager"], "soft_skills": ["confidence"], "languages_combined": [{"language": "english", "language_level": []}]}, "experience_required": {"duration": ["minimum 5 years"], "field": ["financial services", "relevant experience"]}}, {"job_id": "100003009042976", "location_code": "hk", "company": "Chong Hing Bank Ltd", "job_title": "Senior Vice President, Head of Centralised Transaction Services", "description": "Our subsidiary company is looking for a high calibre to join with our Company.\n\nJob Description\n\nScreen investment projects, to prepare analysis at various stages and be responsible for the project\u2019s execution\nConduct industry research including valuations, macro trends and comparisons, risk analysis etc.\nFundamental company and industry research include speaking with management teams, industry, and in-house experts\nFormulate investment strategies for the blockchain investments\n\nRequirements\n\nBachelor\u2019s degree or above, preferably in Finance, STEM or related\n3-8 years working experience in PE and investment firms\nIn-depth knowledge and experience in investment, especially TMT and blockchain sectors\nPrevious experience in cryptos is a distinct advantage\nProven track record in managing investment portfolio with returns\nExcellent analytical skills, with strong attention to detail\n\nPlease submit your CV (Chinese and English) online, including your current basic and expected salary. Also, remark the type of your visa and its status in your CV if you need a work permit in Hong Kong.", "employment_types": ["Full Time", "Permanent"], "selling_points": ["Centralisation, and transactional services", "Key Strategic projects", "Departmental procedure manuals/guidelines"], "locations": ["Not Specified"], "categories": ["Banking / Finance", "Order Processing & Operation / Settlement", "Risk Management"], "post_time": "2022-01-12T09:22:25Z", "salary": {"currency": null, "max": null, "min": null, "period": null, "term": null}, "salary_visible": false, "title_keywords": ["vice president"], "responsibilities": ["management teams", "analysis", "investment strategies", "risk analysis"], "requirements": {"degrees": ["degree or above", "bachelor"], "majors": ["finance"], "languages": ["english", "chinese"], "language_level": ["basic"], "hard_skills": ["blockchain", "basic", "pe", "analytical skills"], "soft_skills": ["attention to detail", "analytical skills"], "languages_combined": [{"language": "english", "language_level": ["basic"]}, {"language": "chinese", "language_level": ["basic"]}]}, "experience_required": {"duration": ["3-8 years"], "field": ["investment"]}}, {"job_id": "100003009045916", "location_code": "hk", "company": "Resource Solutions Consulting Hong Kong Limited", "job_title": "Project Controller, Wealth Management, 6 months contract", "description": "Key responsibilities\n\nDevelop/enhance and implement the enterprise risk management framework, including but not limited to risk governance, risk taxonomy, three lines of defense model etc.\nArticulate Risk Appetite Statement (RAS); monitor and report the Bank\u2019s actual performance against Board approved RAS to senior management.\nOversee, manage and, where appropriate, escalate bank-wide risk-related and regulatory issues.\nLead the annual bank-wide risk management initiatives, including ICAAP, bank-wide stress testing, Recovery Planning.\nFormulate agenda and provide secretarial support to Board-level Risk Committee and executive-level Risk Management Committee.\n\nQualifications\n\nUniversity degree in a business related discipline\n8+ years of banking experience in enterprise risk management, risk governance, or related areas.\nBroad understanding of banking regulatory requirements and relevant industry practices.\nProven experience in handling regulator, auditor and senior stakeholders.\nAdaptive to change and capable of multi-tasking.\nGood interpersonal and project management skills.\nExcellent written and presentation skills.\n\nWe offer competitive package to the right candidates. Interested parties please send your resume with current and expected salary by clicking the\u00a0\u201cApply Now\u201d\u00a0button.\u00a0\u00a0\n\nAll information provided by applicants will be treated in strict confidence and handled confidentially for recruitment purposes only. Applicants who are not contacted within 8 weeks may consider their application unsuccessful and their data will be destroyed within 12 months.", "employment_types": ["Full Time", "Temporary", "Contract"], "selling_points": ["Transaction controls and monitoring role", "Traditional Chinese essential", "Risk controls background preferred"], "locations": ["Eastern Area"], "categories": ["Banking / Finance", "Private Banking", "Risk Management", "Wealth Management"], "post_time": "2022-01-13T09:07:08Z", "salary": {"currency": null, "max": null, "min": null, "period": "monthly", "term": null}, "salary_visible": false, "title_keywords": ["wealth management"], "responsibilities": ["management", "recovery planning", "regulatory requirements", "monitor", "develop", "testing", "project management", "secretarial support", "banking", "senior management", "report"], "requirements": {"degrees": ["university degree"], "majors": ["business"], "languages": [], "language_level": [], "hard_skills": ["project management"], "soft_skills": ["capable", "project management skills", "multi-tasking", "presentation skills", "articulate", "interpersonal"], "languages_combined": []}, "experience_required": {"duration": ["8+ years"], "field": ["related", "risk management", "banking experience"]}}, {"job_id": "100003009046672", "location_code": "hk", "company": "Insurance Authority", "job_title": "Manager (Long Term Business \u2013 Group-wide Supervision)", "description": "Our client is Foreign Private Banking To cope with the rapid business expansion they are now inviting high caliber candidates to join the team\n\nRegulatory Compliance / Conduct Risk Contract \u2013 Private Banking(One Year Contract)\n\n\nResponsibilities:\n\nSupports the Head of Conduct Risk in discharging his/her duties\nAssists to review training materials and provide necessary regulatory support to trainers (e.g. 1st line of defense).\nAssists to manage the implementation of Compliance transformation projects in different compliance workstreams\nAssists to implement remedial actions resulted from regulatory exam or internal reviews.\nActs as coordinator to carry out gap analysis to ensure policies and procedures in alignment with Laws and Regulations & requirements.\nAssists to issue compliance alerts and newsletters on new /revised laws and regulations with implications for the Bank and communicate the latest development of regulatory landscape and enforcement news.\nHandles compliance related Head Office reporting.\nProvides support on appropriate training and education to staff on compliance matters.\nHandles ad hoc compliance duties\n\n\u00a0Requirement:\n\nDegree holder, preferably in business, finance, accounting or law discipline.\nWith 1-2 yrs compliance risk experience in banking industry\nGood knowledge of the HKMA guidelines.\nSelf-motivated and work independently.\nExcellent command in both written and spoken English and Chinese\n\n\n\nPlease send full resume with\u00a0present & expected\u00a0salary to expedite sourcing\u00a0in\u00a0MS-WORD\u00a0format by clicking \u201cAPPLY NOW\u201d\n\nPlease quote our reference in your application\n\nPersonal data provided by job applicants will be used strictly in accordance with the employer\u2019s personal data policies, a copy of which will be provided upon request\n\nAll information provided will be used for recruitment purpose only", "employment_types": ["Full Time", "Permanent"], "selling_points": [], "locations": ["Southern Area"], "categories": ["Insurance", "Actuarial", "Public / Civil", "Others", "Banking / Finance", "Risk Management"], "post_time": "2022-01-13T18:54:14Z", "salary": {"currency": null, "max": null, "min": null, "period": "monthly", "term": null}, "salary_visible": false, "title_keywords": ["manager"], "responsibilities": ["regulations", "reporting", "ad hoc", "policies", "analysis", "compliance", "review", "implementation", "procedures"], "requirements": {"degrees": ["degree holder"], "majors": ["finance", "business", "accounting", "law"], "languages": ["english", "chinese"], "language_level": ["excellent"], "hard_skills": ["hkma", "ms-word"], "soft_skills": ["self-motivated", "work independently"], "languages_combined": [{"language": "english", "language_level": ["excellent"]}, {"language": "chinese", "language_level": ["excellent"]}]}, "experience_required": {"duration": [], "field": ["banking industry", "compliance"]}}, {"job_id": "100003009044065", "location_code": "hk", "company": "Prince Group Holdings Limited", "job_title": "Investment Manager (Digital Assets)", "description": "Key Responsibilities\n\nInvolve and support various risk management workflow re-engineering, revamp of credit risk MIS processes & controls and development of in-house MIS database and applications.\n\nEnhance MIS processes from time to time in order to formulate appropriate strategies to improve the asset quality of the Bank\u2019s loan portfolios.\n\nSupport on\u00a0systems development or enhancement projects including performing UAT testing related to credit risk management.\n\nProvide\u00a0ad-hoc analytics for management whenever necessary.\n\nConduct data analysis and prepare various reports to management reporting as well as HKMA Banking Returns. Ensure all\u00a0output\u00a0in regulatory reporting achieved in high accuracy.\n\u00a0\n\n\u00a0Requirements\n\nDegree holder in Baking & Finance, Statistics, Risk Management or related discipline\n5 years of relevant experience in statistics and credit risk analytics.\nExperience in risk data aggregation,\u00a0risk analytics, portfolio management,\u00a0regulatory reporting, data governance.\nSound knowledge on bank-wide credit portfolios including retail, corporate, financial institutions and counterparts.\nExperience in HKMA regulatory reporting is preferred.\nProficiency in SAS, MS Office and data mining skill set.\nExperienced in IT projects and system implementation related to data systems.\nSelf-motivated, independent, with good communication skills, able to communicate effectively at all levels.\nGood command of written and spoken English and Chinese (including Putonghua).\n\nFor more details about career opportunities with the Bank, please visit our website http://www.cncbinternational.com/careers/en/index.jsp. Please apply with full resume stating current and expected salaries via https://careers.cncbinternational.com.\n\nPersonal data collected will be used for recruitment related purposes only. Applicants not invited for interview within 6 weeks may consider their applications unsuccessful. However, applicants may be considered for other suitable positions within the Group for a period of not more than 2 years. Personal data will be destroyed at any time after 3 months.\n\nChina CITIC Bank International is committed to being an equal opportunities employer and intends to provide a work environment free of unlawful discrimination or harassment. All employment decisions will be made in a non-discriminatory manner.", "employment_types": ["Full Time", "Permanent"], "selling_points": ["TMT and blockchain sectors", "3-8 years of experience in PE and investment firms", "5-day work week, attractive salary package"], "locations": ["Central"], "categories": ["Banking / Finance", "Analyst", "Investment", "Risk Management"], "post_time": "2022-01-13T02:57:02Z", "salary": {"currency": null, "max": null, "min": null, "period": "monthly", "term": null}, "salary_visible": false, "title_keywords": ["investment manager"], "responsibilities": ["ad-hoc", "reporting", "management", "revamp", "systems", "quality", "uat testing", "data analysis", "reports", "management reporting", "database", "banking", "enhancement projects", "re-engineering"], "requirements": {"degrees": ["degree holder"], "majors": ["finance", "statistics", "risk management"], "languages": ["putonghua", "english", "chinese"], "language_level": ["good command"], "hard_skills": ["sas", "system implementation", "hkma regulatory reporting", "data mining", "ms office"], "soft_skills": ["communication skills", "self-motivated", "data mining skill", "independent", "committed"], "languages_combined": [{"language": "putonghua", "language_level": ["good command"]}, {"language": "english", "language_level": ["good command"]}, {"language": "chinese", "language_level": ["good command"]}]}, "experience_required": {"duration": ["5 years"], "field": ["statistics", "relevant experience", "management", "credit risk"]}}, {"job_id": "100003009038636", "location_code": "hk", "company": "Airstar Bank Limited", "job_title": "Senior Risk Governance Manager / Risk Governance Manager", "description": "Responsibilities\n\nAdvise on a full range of compliance function (SFC 1,4,9)to ensure full compliance with regulatory requirements include UCITS/HK authorized fund/Cayman fund\nReview and approve marketing communications, materials, disclaimer consistency with applicable regulatory standards and provide guidance to writers and others involved\nConduct process for monitoring and tracking of remedial actions derived from Compliance Monitoring activity under regulatory or internal requirement.\nMaintain and review company\u2019s policies, procedures and practices to ensure compliance with all applicable laws and regulations\u00a0\nPerform Gap Analysis upon regulatory changes\nPrepare and respond to inquiries and audits from regulatory authorities\nResponsible on pre-trade and post-trade monitoring across multi asset guideline restrictions on Bloomberg CMGR and VMGR.\nIn-depth and comprehensive knowledge of KYC and AML, in particular onboarding entities, present AML & KYC view of cases\nPerform ad-hoc assignments as required.\nBackup each other in the team.\n\nRequirements\n\nHolds a\u00a0degree or professional qualification in Legal, Business, Finance, Accounting or related disciplines\nMinimum 5 years compliance experience in asset management, preferably in SFC regulated institutions\nWorking knowledge of securities laws and regulations in Hong Kong, Cayman and Luxemburg with a good understanding of Asset management business compliance tasks\nFamiliar with Bloomberg, MS Office applications and Chinese word processing\nA good team player, mature, responsible, detail minded, with the ability to handle multiple tasks independently under pressure\nGood communication and organization skills\nGood command in written and spoken English, Cantonese and Chinese\n\nWe offer an attractive remuneration package to the right candidate. Interested parties please forward your full resume with availability, expected salary by pressing \"Apply now\" or send it to 27/F., Low Block, Grand Millennium Plaza, 181 Queen\u2019s Road, Central, Hong Kong.\n\n(Data collected will be kept strictly confidential and used for recruitment purpose only.)", "employment_types": ["Full Time", "Permanent"], "selling_points": [], "locations": ["Tsim Sha Tsui"], "categories": ["Banking / Finance", "Risk Management"], "post_time": "2022-01-11T07:33:51Z", "salary": {"currency": null, "max": null, "min": null, "period": "monthly", "term": null}, "salary_visible": false, "title_keywords": ["manager"], "responsibilities": ["regulations", "aml", "regulatory requirements", "policies", "review", "compliance", "monitoring", "procedures", "ensure compliance", "analysis", "ad-hoc assignments", "maintain", "kyc", "audits", "provide guidance", "tracking"], "requirements": {"degrees": ["degree"], "majors": ["related disciplines", "finance", "business", "accounting"], "languages": ["cantonese", "english", "chinese"], "language_level": ["good command"], "hard_skills": ["securities laws", "chinese word processing", "bloomberg", "ms office"], "soft_skills": ["good team player", "independently", "under pressure", "responsible", "mature", "handle multiple tasks", "communication", "organization skills"], "languages_combined": [{"language": "cantonese", "language_level": ["good command"]}, {"language": "english", "language_level": ["good command"]}, {"language": "chinese", "language_level": ["good command"]}]}, "experience_required": {"duration": ["minimum 5 years"], "field": ["compliance", "asset management"]}}, {"job_id": "100003009038520", "location_code": "hk", "company": "Asia Progress Executive Limited", "job_title": "Regulatory Compliance / Conduct Risk Contract \u2013 Private Banking (One Year Contract)", "description": "Responsibilities:\n\nFollow up latest regulatory requirements and provide advisory services on compliance related issues in order to ensure business units in compliance with regulatory requirements;\nPerform review on general compliance issues and monitor business compliance with relevant external regulatory requirements;\nAssist in the formulating and executing compliance assurance projects;\nIdentify any deficiencies in business activities & operations during assurance reviews; and make recommendations to business units in improving & reinforcing compliance standards accordingly;\nMonitor the implementation status of assurance review recommendations as agreed with units;\nCompile compliance review reports and manage the reporting /escalation of review result to management;\nCoordinate with Regulators and relevant internal stakeholders in handling Regulatory examination related requests;\nConduct compliance training when necessary; and\nPerform other ad hoc projects or assignments.\nRequirements:\nUniversity degree in Law, Business Administration, Finance or related discipline;\nMinimum of 5 years\u2019 solid experience in general regulatory compliance of which 4 years in investment and insurance compliance;\nSound knowledge of investment products such as securities, funds and bonds;\nConversant with banking rules and regulations including Banking Ordinance and Securities & Futures Ordinance;\nKeep abreast of HKMA circulars, industry news and market information;\nExcellent communication and interpersonal skills, able to work with stakeholders at different levels; and\nWell-versed in spoken and written English and Chinese, including Putonghua.\nWe offer competitive remuneration package and promising career opportunities to the successful candidates. Interested parties, please send full resume with current & expected salary and the date of availability to\u00a0The HR Division by clicking \"Apply Now\" button below. Please quote reference on your application. Information provided will be treated in strict confidence and only be used for recruitment purposes. Personal data of unsuccessful applications will be destroyed 24 months after the completion of the recruitment and selection exercise.", "employment_types": ["Contract"], "selling_points": ["Degree holder 1yr compliance risk exp in banking", "private banking and wealth management", "Compliance risk management in banking"], "locations": ["Central & Western Area"], "categories": ["Banking / Finance", "Private Banking", "Professional Services", "Legal & Compliance", "Risk Management"], "post_time": "2022-01-11T07:13:25Z", "salary": {"currency": null, "max": null, "min": null, "period": "monthly", "term": null}, "salary_visible": false, "title_keywords": ["private banking"], "responsibilities": ["make recommendations", "reporting", "management", "regulatory requirements", "operations", "review", "compliance", "monitor", "implementation", "coordinate with", "executing", "reports", "ad hoc projects", "business activities"], "requirements": {"degrees": ["university degree"], "majors": ["finance", "business administration", "law"], "languages": ["putonghua", "english", "chinese"], "language_level": [], "hard_skills": ["hkma", "investment products"], "soft_skills": ["communication and interpersonal skills"], "languages_combined": [{"language": "putonghua", "language_level": []}, {"language": "english", "language_level": []}, {"language": "chinese", "language_level": []}]}, "experience_required": {"duration": ["4 years", "minimum of 5 years"], "field": ["compliance", "investment", "insurance"]}}, {"job_id": "100003009038917", "location_code": "hk", "company": "CMB International Capital Corporation Limited", "job_title": "Associate / Vice President, Operations (Middle Office)", "description": "Career Level\nSenior\nQualification\nDegree\nYears of Experience\n8 years\nJob Type\nFull Time\nJob Functions\nAccounting, Others, Banking / Finance, Fund Management, Professional Services, Legal & Compliance", "employment_types": ["Full Time", "Permanent"], "selling_points": ["Familiar with daily trade processing", "Knowledge of front to back process", "Internal stakeholder coordination"], "locations": ["Central"], "categories": ["Banking / Finance", "Credit Collection", "Order Processing & Operation / Settlement", "Risk Management"], "post_time": "2022-01-11T08:08:51Z", "salary": {"currency": null, "max": null, "min": null, "period": "monthly", "term": null}, "salary_visible": false, "title_keywords": ["vice president", "operations", "associate"], "responsibilities": ["management", "compliance", "banking"], "requirements": {"degrees": ["degree"], "majors": [], "languages": [], "language_level": [], "hard_skills": [], "soft_skills": [], "languages_combined": []}, "experience_required": {"duration": [], "field": []}}, {"job_id": "100003009042816", "location_code": "hk", "company": "Dah Sing Financial Group", "job_title": "Senior Officer, Project Management and UAT Support", "description": "Career Level\nEntry Level\nQualification\nDegree\nJob Type\nFull Time, Contract\nJob Functions\nBanking / Finance, Others, Professional Services, Legal & Compliance, Risk Management", "employment_types": ["Full Time", "Permanent"], "selling_points": ["Supporting and coordinating project activities", "University degree in Business Administrative", "Minimum 4 years of relevant experience"], "locations": ["Not Specified"], "categories": ["Banking / Finance", "Others", "Information Technology (IT)", "IT Project Management / Team Lead", "Risk Management"], "post_time": "2022-01-12T08:55:00Z", "salary": {"currency": null, "max": null, "min": null, "period": "monthly", "term": null}, "salary_visible": false, "title_keywords": ["senior officer"], "responsibilities": ["management", "compliance", "banking"], "requirements": {"degrees": ["degree"], "majors": [], "languages": [], "language_level": [], "hard_skills": [], "soft_skills": [], "languages_combined": []}, "experience_required": {"duration": [], "field": []}}, {"job_id": "100003009037321", "location_code": "hk", "company": "China CITIC Bank International Limited", "job_title": "Assistant Vice President, Business Analyst", "description": "Responsibilities:\n\nTo review the procedures and controls of the Company to ensure the effectiveness and complied with internal compliance control and relevant legal and regulatory requirements\nCo-ordinate the internal and external audit processes, liaise with external auditors and relevant regulatory bodies in compliance with the changes in relevant legal, regulatory, Company policies, headquarters and audit requirements\nLead the internal audit assignments and regular review activities for supervisory review\nDevelop and plan for annual audit plan as well as to design and launch the audit programme\nCarry out independent audits to identify deficiencies in internal controls and risk management, and to make appropriate recommendations for improvement in control and operating efficiency\nIdentify and escalate areas of potential risk and/or quality improvement areas\nTo perform ad hoc projects as required\n\nRequirements:\n\nDegree holder in Accounting, Finance or other Business related disciplines\nQualified HKICPA, ACCA, CIA or equivalent qualified candidates is an advantage\nMinimum 3 years\u2019 experience in external/ internal auditing field, working experience in brokerage firms, financial institutions or listed company is preferable\nKnowledge and experience in audit methodology, risk assessment, internal controls and compliance\nProficiency in PC Skills, including MS Word, Excel, PowerPoint and Chinese word processing\nGood command of written and spoken English and Chinese, fluency in Putonghua\nExcellent communication, analytical and problem-solving skills\nIndependent, attention to details and able to work under pressure to meet tight deadlines\n\n\nAttractive remuneration will be offered to the right candidate.\u00a0 Interested parties please email your full resume with present & expected salary and date of availability to hrm @guosen.com.hk or via \"Apply Now\".\n\nPersonal data collected would be used for recruitment purpose only.\n\n", "employment_types": ["Full Time", "Permanent"], "selling_points": ["Creates maximum value", "Drive process efficiency", "Minimum 6 years of experience"], "locations": ["Quarry Bay"], "categories": ["Banking / Finance", "Analyst", "Information Technology (IT)", "Product Management / Business Analyst", "Risk Management"], "post_time": "2022-01-11T02:28:16Z", "salary": {"currency": null, "max": null, "min": null, "period": "monthly", "term": null}, "salary_visible": false, "title_keywords": ["business analyst", "assistant vice president"], "responsibilities": ["internal audit", "regulatory requirements", "quality", "audit", "design", "regular review", "plan", "liaise with", "control", "compliance", "develop", "management", "annual audit", "review", "procedures", "audits", "policies", "ad hoc projects", "external auditors"], "requirements": {"degrees": ["degree holder"], "majors": ["business", "finance", "related disciplines", "accounting"], "languages": ["putonghua", "english", "chinese"], "language_level": ["fluency", "proficiency", "good command"], "hard_skills": ["excel", "acca", "chinese word processing", "powerpoint", "hkicpa", "problem-solving skills", "pc skills", "ms word"], "soft_skills": ["meet tight deadlines", "independent", "communication", "attention to details", "problem-solving skills", "work under pressure"], "languages_combined": [{"language": "putonghua", "language_level": ["fluency", "good command"]}, {"language": "english", "language_level": ["fluency", "good command"]}, {"language": "chinese", "language_level": ["fluency", "proficiency", "good command"]}]}, "experience_required": {"duration": ["minimum 3 years"], "field": ["brokerage", "financial institutions", "compliance", "audit"]}}, {"job_id": "100003009033780", "location_code": "hk", "company": "Bank of Communications Co., Ltd. Hong Kong Branch", "job_title": "Officer, Financial Crime Compliance \u2013 1 year contract", "description": "Career Level\nEntry Level\nQualification\nDegree\nJob Type\nFull Time, Contract\nJob Functions\nBanking / Finance, Retail Banking, Risk Management, Management, Management Trainee", "employment_types": ["Full Time", "Contract"], "selling_points": [], "locations": ["Not Specified"], "categories": ["Banking / Finance", "Others", "Professional Services", "Legal & Compliance", "Risk Management"], "post_time": "2022-01-10T01:47:06Z", "salary": {"currency": null, "max": null, "min": null, "period": "monthly", "term": null}, "salary_visible": false, "title_keywords": ["officer"], "responsibilities": ["management", "banking"], "requirements": {"degrees": ["degree"], "majors": [], "languages": [], "language_level": [], "hard_skills": [], "soft_skills": [], "languages_combined": []}, "experience_required": {"duration": [], "field": []}}, {"job_id": "100003009041266", "location_code": "hk", "company": "Guosen Securities (HK) Financial Holdings Company, Limited", "job_title": "Internal Control Auditor", "description": "Job Purpose\n\nThe job holder is responsible for the handling of market risk, liquidity risk, interest rate risk, and model validation functions for the Bank and its overseas branches and subsidiaries.\n\nResponsibilities\n\nActively participate in the improvement of reporting including those for committee to communicate market, liquidity, interests risk to senior management effectively.\nProvide quantitative analysis on different historical data and trend in assessing the liquidity risk and interest rate risk behavior and appropriateness for the clients; able to make sound recommendation and judgement on credit risk, market risk, liquidity risk, interest rate risk and/or risk modeling and their impacts to RWA.\nWork closely with business on their daily activities and development of new products and business initiatives.\nLead the model validation process (market, liquidity and credit) including documentation.\nAssist the team head to drive HKMA various risk management projects to ensure regulatory compliance.\nParticipate in the implementation of enhanced risk management framework in specific risk areas to ensure risks are holistically measured.\nReview existing risk policies and documentations to ensure compliance with regulatory and market standard.\nCollaborate with other support functions in different risk matters.\nTake lead to drive efficiency through identifying areas of improvement to simplify work process.\n\nRequirements\n\nDegree holder in finance, risk management, engineering, quantitative finance or related disciplines.\nHolder of CTMP/ CSTMP will be an advantage.\n5 - 8 years of experience in risk management areas such as market risk, credit risk, collateral management.\nGood knowledge of HKFRS-9 Requirements and Basel Requirements.\nExperienced in fixed income, interest rate, FX, treasury and/or associated derivatives for investment banking, commercial banking and/or retail banking.\nProficiency in visual basic, SAS and other programming languages and databases will be a plus.\nGood command of both written and spoken English and Chinese (Cantonese and Putonghua).\nCandidate with more relevant experience will be considered as Vice President.\n\nFor more details about career opportunities with the Bank, please visit our website http://www.cncbinternational.com/careers/en/index.jsp; Please apply with full resume stating current and expected salaries.\n\nPersonal data collected will be used for recruitment related purposes only. Applicants not invited for interview within 6 weeks may consider their applications unsuccessful. However, applicants may be considered for other suitable positions within the Group for a period of not more than 2 years. Personal data will be destroyed at any time after 3 months.\n\nChina CITIC Bank International is committed to being an equal opportunities employer and intends to provide a work environment free of unlawful discrimination or harassment.\u00a0 All employment decisions will be made in a non-discriminatory manner.", "employment_types": ["Permanent"], "selling_points": ["align relevant legal and regulatory requirements", "Co-ordinate the internal &external audit process", "Develop and plan for annual audit plan"], "locations": ["Admiralty"], "categories": ["Accounting", "Audit", "Banking / Finance", "Others", "Risk Management"], "post_time": "2022-01-12T03:40:12Z", "salary": {"currency": null, "max": null, "min": null, "period": "monthly", "term": null}, "salary_visible": false, "title_keywords": [], "responsibilities": ["collaborate with", "reporting", "management", "business initiatives", "data", "policies", "analysis", "compliance", "review", "implementation", "ensure compliance", "documentation", "senior management"], "requirements": {"degrees": ["degree holder"], "majors": ["related disciplines", "finance", "engineering", "risk management"], "languages": ["cantonese", "putonghua", "english", "chinese"], "language_level": ["good command"], "hard_skills": ["plus", "sas", "visual basic", "databases", "programming"], "soft_skills": ["committed"], "languages_combined": [{"language": "cantonese", "language_level": ["good command"]}, {"language": "putonghua", "language_level": ["good command"]}, {"language": "english", "language_level": ["good command"]}, {"language": "chinese", "language_level": ["good command"]}]}, "experience_required": {"duration": ["5 - 8 years"], "field": ["risk management", "management", "relevant experience", "market risk", "credit risk"]}}, {"job_id": "100003009033803", "location_code": "hk", "company": "Bank of Communications Co., Ltd. Hong Kong Branch", "job_title": "Officer Trainee \u2013 6 months contract", "description": "Responsibilities\n\nEnsure that the company conducts its business in full compliance and regulations and standards that are relevant to its industry\nAssist the manager to implement and manage an effective compliance program\nAssess company operations to determine compliance risk\nPerform periodic reviews to assess the effectiveness and efficiency of internal controls across the company\n\nRequirements\n\n\n\nDegree holder with minimum 3 years' experience in compliance and risk management role\nDynamic, self-motivated with strong analytical and problem-solving skills\nPossess excellent communication and interpersonal skills\nGood command of written and spoken English and Cantonese", "employment_types": ["Full Time", "Contract"], "selling_points": [], "locations": ["Not Specified"], "categories": ["Banking / Finance", "Retail Banking", "Risk Management", "Management", "Management Trainee"], "post_time": "2022-01-10T01:49:15Z", "salary": {"currency": null, "max": null, "min": null, "period": "monthly", "term": null}, "salary_visible": false, "title_keywords": ["officer trainee"], "responsibilities": ["regulations", "operations", "compliance"], "requirements": {"degrees": ["degree holder"], "majors": ["risk management"], "languages": ["cantonese", "english"], "language_level": ["good command"], "hard_skills": ["problem-solving skills", "dynamic"], "soft_skills": ["problem-solving skills", "self-motivated", "dynamic", "communication and interpersonal skills"], "languages_combined": [{"language": "cantonese", "language_level": ["good command"]}, {"language": "english", "language_level": ["good command"]}]}, "experience_required": {"duration": ["minimum 3 years"], "field": ["risk management", "compliance"]}}, {"job_id": "100003009038248", "location_code": "hk", "company": "Chandler Macleod Group (HK) Limited", "job_title": "Compliance Officer (Insurance)", "description": "Job Purpose\n\nThe Job Holder will assist the Product Owners to identify the risks and where necessary, engage the specific Risk Owners, other relevant supporting units or subject matter experts.\n\n\n\nKey Responsibilities\n\nAssist the team to drive continuous enhancements and implementation of the Bank's New Product Governance Framework and risk management processes to meet regulatory requirements and to be the major player in supporting the new product initiatives.\nAs one of the flow-to-work members, participates in the sprint show & tell, sprint planning and problem solving sessions of each squad;\nAssist the Product Owners to identify the risks based on the user stories, and engage the respective Risk Owner(s) for example on credit, market, interest rate, liquidity, operational, fraud, technology, legal, compliance, strategic and reputation risks for detailed assessment and engage in discussions if applicable;\nAssist the Product Owners to identify the relevant supporting units or subject matter experts to ensure there are adequate staffing, technology and resources to launch the product or service;\nProvide hands-on training and problem solving on key risk topics to the Product Owners and the squads; and\nReview the new product approval documents with the Product Owners and the Business Analysts prior to their submission for approval and report to NPG on the issues and latest development in a timely manner.\n\nRequirements\n\nDegree holder in Finance, Business, Risk Management or related disciplines, e-banking, e-commerce is advantage.\n8 years\u2019 experience in retail banking and/or risk management. Experience in e-banking services, retail products, risk management and internal control is an advantage.\nSelf-motivated, independent, with good communication skills, able to communicate effectively at all levels.\nGood command of written and spoken English and Chinese (including Putonghua).\n\n\u00a0For more details about career opportunities with the Bank, please visit our website http://www.cncbinternational.com/careers/en/index.jsp. Please apply with full resume stating current and expected salaries via https://careers.cncbinternational.com.\n\nPersonal data collected will be used for recruitment related purposes only. Applicants not invited for interview within 6 weeks may consider their applications unsuccessful. However, applicants may be considered for other suitable positions within the Group for a period of not more than 2 years. Personal data will be destroyed at any time after 3 months.\n\nChina CITIC Bank International is committed to being an equal opportunities employer and intends to provide a work environment free of unlawful discrimination or harassment. All employment decisions will be made in a non-discriminatory manner.", "employment_types": ["Full Time", "Permanent"], "selling_points": ["Compliance & Risk Mgmt", "Insurance Company", "FI exp preferred"], "locations": ["Not Specified"], "categories": ["Banking / Finance", "Risk Management"], "post_time": "2022-01-11T06:19:24Z", "salary": {"currency": null, "max": null, "min": null, "period": "monthly", "term": null}, "salary_visible": false, "title_keywords": ["compliance officer"], "responsibilities": ["management", "regulatory requirements", "compliance", "review", "implementation", "a timely manner", "report", "planning"], "requirements": {"degrees": ["degree holder"], "majors": ["risk management", "e-commerce", "finance", "related disciplines", "business"], "languages": ["putonghua", "english", "chinese"], "language_level": ["good command"], "hard_skills": ["internal control", "e-commerce"], "soft_skills": ["communication skills", "self-motivated", "committed", "independent"], "languages_combined": [{"language": "putonghua", "language_level": ["good command"]}, {"language": "english", "language_level": ["good command"]}, {"language": "chinese", "language_level": ["good command"]}]}, "experience_required": {"duration": ["8 years"], "field": ["risk management", "retail banking", "retail", "banking services"]}}, {"job_id": "100003009037634", "location_code": "hk", "company": "China CITIC Bank International Limited", "job_title": "Assistant Vice President, New Product Governance", "description": "Job Scope\n\nAssist in financial analysis and M&A activities\nConduct investment research\nGather information and create company/ industry overview on potential investment targets\nDevelop and maintain market and company databases\nExamine and assess economic and market trends, market news\nGather information and create company/ industry overview on potential investment targets\n\n\nJob Requirements\n\nDegree holder in finance, Economics or related discipline\n1-2 years related working experience\nStrong financial modelling skills and with strong analytical mind\nExperience in Fintech , TMT industry is highly preferred\nProficiency in MS Word\nExcellent command in English and Chinese", "employment_types": ["Full Time", "Permanent"], "selling_points": ["8 years\u2019 experience in retail banking/ products", "e-Banking related experience is a plus", "Drive New Product Governance in Risk Management"], "locations": ["Quarry Bay"], "categories": ["Banking / Finance", "Retail Banking", "Others", "Risk Management"], "post_time": "2022-01-11T03:19:58Z", "salary": {"currency": null, "max": null, "min": null, "period": "monthly", "term": null}, "salary_visible": false, "title_keywords": ["assistant vice president"], "responsibilities": ["financial analysis", "maintain", "databases", "develop"], "requirements": {"degrees": ["degree holder"], "majors": ["finance", "economics"], "languages": ["english", "chinese"], "language_level": ["excellent"], "hard_skills": ["financial analysis", "databases", "ms word"], "soft_skills": ["analytical mind"], "languages_combined": [{"language": "english", "language_level": ["excellent"]}, {"language": "chinese", "language_level": ["excellent"]}]}, "experience_required": {"duration": ["1-2 years"], "field": ["related"]}}, {"job_id": "100003009038270", "location_code": "hk", "company": "Links International", "job_title": "Research Analyst ( M&A,TMT   )", "description": "Job Scope\n\nAssist in financial analysis and M&A activities\nConduct investment research\nGather information and create company/ industry overview on potential investment targets\nDevelop and maintain market and company databases\nExamine and assess economic and market trends, market news\nGather information and create company/ industry overview on potential investment targets\n\n\nJob Requirements\n\nDegree holder in finance, Economics or related discipline\n1-2 years related working experience\nStrong financial modelling skills and with strong analytical mind\nExperience in Fintech , TMT industry is highly preferred\nProficiency in MS Word\nExcellent command in English and Chinese", "employment_types": ["Full Time", "Permanent"], "selling_points": ["Attractive Package", "M&A focus", "TMT Fintech background welcome"], "locations": ["Central & Western Area"], "categories": ["Banking / Finance", "Financial Services", "Marketing / Public Relations", "Management", "Risk Management"], "post_time": "2022-01-11T06:24:25Z", "salary": {"currency": null, "max": null, "min": null, "period": "monthly", "term": null}, "salary_visible": false, "title_keywords": ["research analyst"], "responsibilities": ["financial analysis", "maintain", "databases", "develop"], "requirements": {"degrees": ["degree holder"], "majors": ["finance", "economics"], "languages": ["english", "chinese"], "language_level": ["excellent"], "hard_skills": ["financial analysis", "databases", "ms word"], "soft_skills": ["analytical mind"], "languages_combined": [{"language": "english", "language_level": ["excellent"]}, {"language": "chinese", "language_level": ["excellent"]}]}, "experience_required": {"duration": ["1-2 years"], "field": ["related"]}}, {"job_id": "100003009038276", "location_code": "hk", "company": "Links International", "job_title": "Research Analyst ( M&A,TMT   )", "description": "Our Client is one of the world's major financial institutions with strong presence in Hong Kong market operating to cover a range of service for diverse products, including, equity, securities, derivatives, etc.\n\nYou will be joining its Operation Department and working in a highly international and dynamic environment.\n\nResponsibilities:\n\nPerform daily surveillance alerts and reports generated in SMARTS system for equities and derivatives products\nInvestigate trading activities and suspicious behaviors, and take part in market surveillance projects\nReview trading activities that are complying with trading rules, clearing rules and other regulatory policies\nCommunicate and interact with stakeholders, participants, external vendors and internal business units on surveillance domain\n\nRequirements:\n\nBachelor's Degree in Finance, Business Administration, or related disciplines\nWorking experience in financial institutions, with strong understanding in securities and derivatives markets\nExperience in trade surveillance and reporting system, i.e. SMARTS\nExperience in front office, middle office, risk management role, etc. with strong understanding in trade processing & operation is a plus\nGood command of written and spoken English and Chinese (Cantonese and Mandarin)\n\nFor those who are interested, please submit your latest profile (in WORD Format) to raman.hong@connectedgroup.com. Only qualified candidates will be contacted.\n\nFor more job opportunities, please visit our web-site: www.connectedgroup.com.", "employment_types": ["Full Time", "Permanent"], "selling_points": ["Attractive Package", "M&A focus", "TMT Fintech background welcome"], "locations": ["Central & Western Area"], "categories": ["Banking / Finance", "Financial Services", "Marketing / Public Relations", "Management", "Risk Management"], "post_time": "2022-01-11T06:25:25Z", "salary": {"currency": null, "max": null, "min": null, "period": "monthly", "term": null}, "salary_visible": false, "title_keywords": ["research analyst"], "responsibilities": ["policies", "review", "reports"], "requirements": {"degrees": ["degree", "bachelor"], "majors": ["related disciplines", "finance", "business administration"], "languages": ["cantonese", "english", "chinese", "mandarin"], "language_level": ["good command"], "hard_skills": ["plus", "processing", "word", "web"], "soft_skills": [], "languages_combined": [{"language": "cantonese", "language_level": ["good command"]}, {"language": "english", "language_level": ["good command"]}, {"language": "chinese", "language_level": ["good command"]}, {"language": "mandarin", "language_level": ["good command"]}]}, "experience_required": {"duration": [], "field": ["risk management", "financial institutions", "securities"]}}, {"job_id": "100003009037587", "location_code": "hk", "company": "ConnectedGroup Limited", "job_title": "Associate, Trade Surveillance (12-month Contract)", "description": "Our clients are well-known and fast expanding banks and now looking for high calibre to join their group.\n\n\n\nResponsibilities\n\nPrepare comprehensive credit assessment for corporate and cross border clients\nApprove and review credit facilities following bank credit policies and authority\u00a0\nReview and formulate credit risk policy to cope with regulatory changes\u00a0\nMonitor limit and conduct investigation or exceptional approval for high risk accounts/clients\nEnsure all approval process and internal credit policies & procedures are aligned with regulatory requirements\nMonitor portfolio quality and submit regular MIS report for management review\n\nRequirements\n\nBachelor\u2019s degree in Accounting, Finance or related disciplines\nMinimum 3 years\u2019 credit analysis, approval or risk monitoring in banking industry\nProficiency in written and spoken English & Chinese\nGood PC skills in MS Word and Excel\n\nTo apply, please send your detailed resume to winnie[at]connersconsulting[dot]com or contact Winnie Lai at 3618 8348 for a confidential discussion.\n\nOnly shortlisted candidates will be notified.\n\nApplicants who are not contacted within two weeks may consider their applications unsuccessful.\n\nAll data collected will be used for recruitment purpose only & will be used strictly confidential.\n\nConners Consulting Limited\n\n2005 Kai Tak Commercial Building 317 Des Voeux Road Central Hong Kong\n\nTel: (852) 3996 8090\nWebsite:\u00a0www.connersconsulting.com", "employment_types": ["Full Time", "Contract"], "selling_points": ["Trade Operations Control", "Multi-national Environment", "Chance for Conversion to Perm"], "locations": ["Not Specified"], "categories": ["Banking / Finance", "Dealing & Trading", "Order Processing & Operation / Settlement", "Risk Management"], "post_time": "2022-01-11T03:13:24Z", "salary": {"currency": null, "max": null, "min": null, "period": "monthly", "term": null}, "salary_visible": false, "title_keywords": ["associate"], "responsibilities": ["policies", "regulatory requirements", "review", "monitor", "procedures", "investigation", "quality", "management review", "report"], "requirements": {"degrees": ["degree", "bachelor"], "majors": ["related disciplines", "finance", "accounting"], "languages": ["english", "chinese"], "language_level": ["proficiency"], "hard_skills": ["credit analysis", "excel", "pc skills", "ms word"], "soft_skills": ["detailed"], "languages_combined": [{"language": "english", "language_level": ["proficiency"]}, {"language": "chinese", "language_level": ["proficiency"]}]}, "experience_required": {"duration": [], "field": []}}, {"job_id": "100003009042692", "location_code": "hk", "company": "Conners Consulting Limited", "job_title": "Credit Analyst and Approver (multiple bank openings $40k - $90k)", "description": "Snapshot\n\nAn exciting opportunity to join a sizeable foreign bank as an Operations Team Lead, to be responsible for process monitoring of banking operations.\n\nCompany Profile\n\nOur client, a sizeable foreign bank is looking for an Operations Team Lead to join the team\n\nExciting new role for you\n\nResponsible for monitoring and managing daily banking operation flows\nIdentity and minimize relevant operational risk in product, processing and transaction\nSpearhead risk and compliance related projects\n\nRequirements\n\nDegree holder in Accounting, Finance, Risk Management or related discipline\nAt least 10 years of experience in banking operations\nExperience in team management is required\nGood command of English and Chinese\nSolid reporting skills by using MS Excel and PowerPoint\n\nRewards\n\nInternational platform with stable career growth and attractive renumeration package", "employment_types": ["Full Time"], "selling_points": ["Credit Approval / Credit Analyst", "Attractive package and bonus scheme", "Multiple bank openings"], "locations": ["Central & Western Area"], "categories": ["Banking / Finance", "Analyst", "Credit Analysis / Approval", "Risk Management"], "post_time": "2022-01-12T08:24:57Z", "salary": {"currency": null, "max": null, "min": null, "period": "monthly", "term": null}, "salary_visible": false, "title_keywords": ["credit analyst"], "responsibilities": ["reporting", "management", "operations", "monitoring", "compliance", "banking"], "requirements": {"degrees": ["degree holder"], "majors": ["finance", "accounting", "risk management"], "languages": ["english", "chinese"], "language_level": ["good command"], "hard_skills": ["ms excel", "processing", "powerpoint"], "soft_skills": ["stable", "responsible"], "languages_combined": [{"language": "english", "language_level": ["good command"]}, {"language": "chinese", "language_level": ["good command"]}]}, "experience_required": {"duration": ["at least 10 years"], "field": ["management", "team", "banking"]}}, {"job_id": "100003009042425", "location_code": "hk", "company": "PERSOLKELLY Hong Kong Limited", "job_title": "Banking Operations Team Lead (up to 60k p/m + bonus + benefits)", "description": "AIA Challenge Family\u300c\u79c9\u6301\u5c08\u696d\u71b1\u8aa0 \u696d\u754c\u9577\u52dd\u5c07\u8ecd\u300d\n\n\u300c\u7cbe\u82f1\u5718\u968a\uff0c\u57f7\u884c\u7d30\u7bc0\uff0c\u8ffd\u6c42\u5353\u8d8a\u300d\u662f\u6211\u5011\u53cb\u90a6\u9999\u6e2f\u71df\u696d\u5718\u968a CHALLENGE Family \uff08\u6311\u6230\u5bb6\u65cf\uff09 \u7684\u6838\u5fc3\u71df\u904b\u7406\u5ff5\u3002\n\n\u95dc\u65bc\u6211\u5011\u7684\u5718\u968a\uff1a\n\u53cb\u90a6\u9999\u6e2f\u5340\u57df\u57f7\u884c\u7e3d\u76e3\u4f59\u9054\u5f37\uff08Terence\uff09\u5275\u7acb\u300c\u6311\u6230\u5bb6\u65cf\u300d\uff08Challenge Family\uff09\uff0c\u5f9e\u4e00\u500b\u4eba\u958b\u59cb\uff0c\u767c\u5c55\u4e86\u5340\u57df\u5718\u968a\uff0c\u518d\u64f4\u5c55\u6210\u64c1\u670913\u540d\u5340\u57df\u7e3d\u76e3\u7684\u300c\u6311\u6230\u5bb6\u65cf\u300d\uff0c\u4ee535\u5e74\u7684\u6b72\u6708\uff0c\u6210\u5c31\u5e02\u5834\u4e0a\u7684\u9802\u5c16\u5730\u4f4d\u3002\u6301\u7e8c\u7684\u6210\u529f\uff0c\u9577\u52dd\u7684\u300c\u8ecd\u968a\u300d\uff0c\u532f\u805a\u4e86\u9054\u6210\u696d\u754c\u516c\u8a8d\u6700\u5d07\u9ad8\u7684\u570b\u969b\u69ae\u8b7d\u2014\u2014\u767e\u842c\u5713\u684c\u6703\uff08MDRT\uff09\u6703\u54e1\uff0c\u9020\u5c31\u4e86\u7a7a\u524d\u6210\u529f\u3002\u300c\u6311\u6230\u5bb6\u65cf\u300d\u7cbe\u82f1\u8f29\u51fa\uff0c\u4ee5MDRT\uff08\u767e\u842c\u5713\u684c\u6703\u54e1\uff09\u70ba\u6307\u6a19\uff0c\u773e\u6210\u54e1\u64c1\u6709\u9ad8\u5b78\u6b77\uff0c\u914d\u5408\u6700\u5c08\u696d\u7684\u670d\u52d9\uff0c\u6301\u7e8c\u50b3\u627f\u5bb6\u65cf\u7684\u512a\u826f\u50b3\u7d71\uff0c\u4e0d\u65b7\u5275\u9020\u66f4\u9ad8\u7684\u69ae\u8000\uff0c\u4ee4\u6bcf\u4f4d\u5bb6\u65cf\u6210\u54e1\uff0c\u5747\u4ee5\u8eab\u70ba\u300c\u6311\u6230\u5bb6\u65cf\u300d\u7684\u4e00\u4efd\u5b50\u5f15\u4ee5\u70ba\u50b2\u3002\n\u6545\u6b64\uff0c\u300c\u6311\u6230\u5bb6\u65cf\u300d\u65bc1994\u5e74\u9996\u5275\u53cb\u90a6\u9999\u6e2f\u5148\u6cb3\uff0c\u5728\u4ecd\u8655\u65bc\u767c\u5c55\u521d\u671f\u7684\u4fdd\u96aa\u5e02\u5834\u4e0a\u62db\u8058\u5927\u5b78\u751f\uff0c\u4ee4\u5718\u968a\u7684\u8cea\u7d20\u4e0d\u65b7\u63d0\u5347\uff0c\u8b93\u300c\u6311\u6230\u5bb6\u65cf\u300d\u81eaAIA\u65bc2006\u5e74\u6709MDRT\u7d00\u9304\u4ee5\u4f86\u4fdd\u6301\u9577\u52dd\u7d00\u9304\uff0c\u9577\u671f\u56ca\u62ec\u516c\u53f8\u5167\u7684\u00a0\u300c\u6700\u9ad8\u767e\u842c\u5713\u684c\u6703\u6703\u54e1\u6bd4\u4f8b\u3001\u6700\u591a\u767e\u842c\u5713\u684c\u6703\u6703\u54e1\u4eba\u6578\u7684\u5340\u57df\u5927\u734e\u300d\u3002\u53ca\u81f32018\u5e74\uff0c\u300c\u6311\u6230\u5bb6\u65cf\u300d\u64c1\u6709429\u4f4dMDRT\u300147\u4f4dCOT\uff08\u53733\u500dMDRT\uff09\u53ca25\u4f4dTOT\uff08\u53736\u500dMDRT\uff09\uff0c\u50b2\u8996\u540c\u5115\uff0c\u6210\u5c31\u696d\u754c\u50b3\u5947\u3002\n\n\u900f\u904e\u4ee5\u4e0b\u9023\u7d50\u77ad\u89e3\u6211\u5011\u5718\u968a\u66f4\u591a:\nhttps://www.linkedin.com/company/aia-international-limited-challenge-district-cl-cyn\n\nJob Descriptions:\u00a0\n\n1. Professional Financial Services to Clients\n\nWealth Management and Taxation Advices\u00a0\nInvestment Planning & Portfolio Advices\nRetirement and Estate Planning\nRisk Management Planning\nMainland China Visitors business& CIES (Capital Investment Entrant Scheme) Planning\n\n2. Team Management\n\nDevelop Team Building Strategies\nRecruit and Interview Prospective Candidates\nMotivate and Inspire Team Members\n\n3. Self Continuous Improvement\n\nAchieve Professional Certifications and Awards (MDRT, CFP, ChFC, RFP, etc.)\nStay Up-to-Date with Financial Knowledge and News\nDevelop Better Interpersonal and Communication Skills\nImprove Negotiation and Presentation Skills\n\nOur Benefits:\n\nProfessional training program (Pre-job and on-job training on how to be MDRT qualifier)\nOne year fast-track promotion program to Senior Manager /Assistant Unit Manager\nExcellent career path to management level\nMonthly allowance + Attractive commission package + year-end bonus + comprehensive assorted benefits\nOverseas trips and conventions\n\nOur Requirements:\n\nDegree holder in any discipline\nEntrepreneurial mindset and self-motivated\nEnergetic and outgoing\nGood interpersonal and communication skills\nFluent in Cantonese or Mandarin\nFresh graduates and Postgraduates are both welcome\n\n******\u00a0 Hong Kong Residents and IANG Visa Students are welcome.******\n\nAll personal data collected will be used for recruitment purpose only and will be treated in accordance with our Personal Data Policy, which is available immediately upon request. All applications will be destroyed after 12 months.", "employment_types": ["Full Time", "Permanent"], "selling_points": ["Foreign Banking Operations Team Lead", "Well versed in banking operations and compliance", "Stable career growth, up to 60k p/m"], "locations": ["Yau Tsim Mong Area"], "categories": ["Banking / Finance", "Corporate Banking", "Order Processing & Operation / Settlement", "Risk Management"], "post_time": "2022-01-12T07:28:25Z", "salary": {"currency": null, "max": null, "min": null, "period": "monthly", "term": null}, "salary_visible": false, "title_keywords": ["operations", "lead"], "responsibilities": ["taxation", "management", "develop", "communication", "planning"], "requirements": {"degrees": [], "majors": [], "languages": [], "language_level": [], "hard_skills": [], "soft_skills": [], "languages_combined": []}, "experience_required": {"duration": [], "field": []}}, {"job_id": "100003009041033", "location_code": "hk", "company": "AIA International Limited", "job_title": "AIA Wealth Management Manager / Graduate Trainee / Winter Internship (Welcome Undergraduate Student)", "description": "Job Purpose\n\nHandle debt recovery and minimize impairment loss for the designated accounts.\n\nResponsibilities\n\nAssist to formulate and perform daily execution of collection strategies.\nHandle debt recovery for the designated accounts through cash/ assets recovery, debt restructuring and security enforcement.\nSustain positive working relationship with key internal customers to enhance recoverability of problem loans.\nMaximize debt recovery for the designated accounts including cash/ assets recovery, debt restructuring, security enforcement, obtaining additional securities etc.\nLiaise with solicitors and collection agents on problem loans management.\nSupervise and execute the repossession and sale of collaterals.\nAchieve annual business targets, for instances, provision balance, impairment loss ratio, bad debt recoveries etc.\u00a0\u00a0\nSupport bank-wide new business initiatives by providing timely advice from risk management perspective.\nMonitor the output quality from team members to ensure their compliance with the regulatory requirements and provide timely coaching to team members.\n\nRequirements\n\nSecondary education or above. Bachelor degree holder in business or risk management is a plus.\nMinimum 10 years\u2019 relevant experience in bank, credit or related field in which 3 years\u2019 experience at supervisory level is highly preferred.\nProfessional Qualification of Certified Credit Risk Management Professional (Credit Portfolio Management) is preferred.\nKnowledge of litigation process in HKSAR and PRC with focus on collaterals repossession.\nGood knowledge of regulatory requirements such as relevant ordinances and supervisory guidelines and in-depth knowledge on banking and investment products.\nSolid experience in Corporate Banking collection is preferable.\nStrong analytical and credit assessment skills with excellent understanding of lending principles.\nSelf-motivated, independent and able to communicate effectively at all levels.\nGood command of written and spoken English and Chinese including Putonghua.", "employment_types": ["Full Time", "Part Time", "Permanent", "Internship", "Freelance"], "selling_points": ["Fresh graduates or IANG are Welcome", "Monthly allowance +Attractive commission", "Professional training to MDRT"], "locations": ["Causeway Bay"], "categories": ["Others", "Student / Fresh Graduate / No Experience", "Banking / Finance", "Risk Management", "Management", "Management Trainee"], "post_time": "2022-01-12T03:21:41Z", "salary": {"currency": null, "max": null, "min": null, "period": "monthly", "term": null}, "salary_visible": false, "title_keywords": ["wealth management manager", "graduate trainee", "internship"], "responsibilities": ["management", "business initiatives", "regulatory requirements", "compliance", "quality", "monitor", "liaise with"], "requirements": {"degrees": ["secondary education", "bachelor degree holder"], "majors": ["risk management", "business"], "languages": ["putonghua", "english", "chinese"], "language_level": ["good command"], "hard_skills": ["litigation process", "plus", "focus", "investment products"], "soft_skills": ["focus", "independent", "self-motivated"], "languages_combined": [{"language": "putonghua", "language_level": ["good command"]}, {"language": "english", "language_level": ["good command"]}, {"language": "chinese", "language_level": ["good command"]}]}, "experience_required": {"duration": ["3 years", "minimum 10 years"], "field": ["related", "supervisory level", "relevant experience", "banking"]}}, {"job_id": "100003009037738", "location_code": "hk", "company": "China CITIC Bank International Limited", "job_title": "Assistant Vice President, Risk Assets Management", "description": "Responsibilities:\n\nConduct daily report review and account monitoring and liaise with Account Executives (AE) to obtain relevant information for credit due diligence\nCommunicate effectively with sales team on the follow-up action on credit control related issues\nConduct and comment assessments on credit limit proposals and act as a maker to adjust the client approved limit in the trading system\nObtain the proper approval for those accounts in accordance with credit policies and procedures\nSet up or create templates for reporting\nCollect the statistical data on credit risk analysis\nPerform ad hoc assignments and handle special projects with credit related issues from time to time required by management\nCompile daily, weekly and monthly reports on time and perform clerical duty\n\nRequirement\n\nUniversity degree in Finance / Risk Management / other related disciplines (FRM or CFA preferred). Minimum 5-6 years relevant working experience is required if the candidate is not a degree holder\nMinimum 3 years experience in credit risk management, preferably in financial institutions\nGood knowledge in equity market and derivatives products\nPossess strong credit analytical skills\nStrong proficiency in VBA and Excel-Macro\nProficient in MS Office application and Chinese word processing\nGood communication skills and good telephone manner\nGood command of written and spoken English and Chinese with fluency in Mandarin; knowledge of Simplified Chinese a plus\nEfficient, self-motivated, independent and able to work under pressure\nMore experience will be offered as Senior Associate\nImmediate Available is highly preferred\n\nApplication:\n\nWe offer an attractive remuneration package including a performance bonus, medical insurance covering dependants, MPF, Life and AD&D insurance, annual leave, birthday leave, marriage leave and training subsidy, etc. to the right candidate.\u00a0\n\nIf you are interested in this opportunity, please send your application with a detailed resume including current and expected salary, latest bonus and availability by clicking \"Apply Now\". Applications without required information will NOT be considered.\n\n*Information provided by applicants will be treated in the strictest confidence and will be solely used for recruitment purposes.", "employment_types": ["Full Time", "Permanent"], "selling_points": ["Handle debt recovery", "10 years\u2019 collection experience in bank", "Solid experience on Corporate Banking collection"], "locations": ["Quarry Bay"], "categories": ["Banking / Finance", "Corporate Banking", "Credit Collection", "Risk Management"], "post_time": "2022-01-11T03:41:45Z", "salary": {"currency": null, "max": null, "min": null, "period": "monthly", "term": null}, "salary_visible": false, "title_keywords": ["assistant vice president"], "responsibilities": ["due diligence", "control", "reporting", "management", "data", "policies", "monitoring", "review", "procedures", "liaise with", "sales team", "risk analysis", "ad hoc assignments", "daily report", "weekly and monthly reports"], "requirements": {"degrees": ["university degree", "degree holder"], "majors": ["related disciplines", "finance", "risk management"], "languages": ["english", "chinese", "mandarin"], "language_level": ["fluency", "good command", "proficient"], "hard_skills": ["vba", "excel", "macro", "chinese word processing", "plus", "cfa", "credit analytical skills", "frm", "ms office"], "soft_skills": ["efficient", "communication skills", "self-motivated", "confidence", "independent", "interested in", "detailed", "analytical skills", "telephone manner", "work under pressure"], "languages_combined": [{"language": "english", "language_level": ["fluency", "good command"]}, {"language": "chinese", "language_level": ["fluency", "good command", "proficient"]}, {"language": "mandarin", "language_level": ["fluency", "good command"]}]}, "experience_required": {"duration": ["minimum 5-6 years", "minimum 3 years"], "field": ["financial institutions", "management", "relevant working experience", "credit risk"]}}, {"job_id": "100003009036216", "location_code": "hk", "company": "BOCOM International Holdings Company Limited", "job_title": "Associate/ Senior Associate, Credit Risk", "description": "\u5de5\u4f5c\u5167\u5bb9\uff1a\n1.\u5354\u52a9\u5168\u884c(\u542b\u6d77\u5916\u5206\u884c)\u53ca\u5b50\u516c\u53f8\u6d17\u9322\u9632\u5236\u6cd5\u4ee4\u9075\u5faa\u3002\n\n2.\u53cd\u6d17\u9322\u4f5c\u696d\u53ca\u76e3\u7763\u3001\u8a55\u4f30\u3001\u898f\u5283\u8207\u57f7\u884c\u3002\n\n3.\u8fa6\u7406\u6d17\u9322\u9632\u5236\u91cd\u8981\u5c08\u6848\u76f8\u95dc\u4e8b\u5b9c\u3002\n\n4.\u5168\u884c\u53cd\u6d17\u9322\u7cfb\u7d71\u4f7f\u7528\u3001\u7ba1\u7406\u3001\u7dad\u8b77\u53ca\u512a\u5316\u7b49\u76f8\u95dc\u4e8b\u5b9c\u3002\n\n\u8cc7\u683c\u689d\u4ef6\uff1a\n1.\u5b78\u6b77\uff1a\n\u570b\u5167\u3001\u5916\u7814\u7a76\u6240\u7562\u696d\uff0c\u4e14\u5df2\u53d6\u5f97\u78a9\u58eb\u4ee5\u4e0a\u5b78\u4f4d\u8b49\u66f8\u3002\n\n2.\u5de5\u4f5c\u7d93\u6b77\uff1a\n(1)\u5177\u91d1\u878d\u6a5f\u69cb\u76f8\u95dc\u5de5\u4f5c\u7d93\u6b7720\u5e74\u4ee5\u4e0a\uff0c\u4e26\u65bc\u9999\u6e2f\u91d1\u878d\u6a5f\u69cb\u5de5\u4f5c\u7d93\u6b775\u5e74\u4ee5\u4e0a\u3002\n\n(2)\u5177\u9280\u884c\u696d\u6d17\u9322\u9632\u5236\u696d\u52d9\u76f8\u95dc\u5de5\u4f5c\u7d93\u6b7710\u5e74\u4ee5\u4e0a\uff0c\u719f\u7a14\u81fa\u7063\u3001\u7f8e\u570b\u3001\u5927\u9678\u5730\u5340\u53ca\u9999\u6e2f\u7576\u5730\u9632\u5236\u6d17\u9322\u53ca\u6253\u64ca\u8cc7\u6050\u76f8\u95dc\u6cd5\u898f\u3002\n\n3.\u5176\u4ed6\u5c08\u9577\u8207\u5c08\u696d\u8b49\u7167\uff1a\n(1)\u5177\u4e2d\u3001\u82f1\u6587\u6e9d\u901a\u80fd\u529b\u3002\n\n(2)\u82f1\u8a9e\u8a9e\u6587\u6e2c\u9a57\u6a19\u6e96\u61c9\u5177\u76f8\u7576\u65bcIELTS\u570b\u969b\u82f1\u8a9e\u6e2c\u8a667\u5206\u4ee5\u4e0a\u3002\n\n(3)\u570b\u969b\u516c\u8a8d\u53cd\u6d17\u9322\u5e2b(CAMS)\u8cc7\u683c\u3002\n\n(4)\u64d4\u4efb\u4e3b\u7ba1\u8077\uff0c\u61c9\u5177\u5099\u300c\u91d1\u878d\u63a7\u80a1\u516c\u53f8\u53ca\u9280\u884c\u696d\u5167\u90e8\u63a7\u5236\u53ca\u7a3d\u6838\u5236\u5ea6\u5be6\u65bd\u8fa6\u6cd5\u300d\u898f\u5b9a\u4e4b\u5167\u63a7\u76f8\u95dc\u7d93\u6b77\u3001\u8a13\u7df4\u6216\u8b49\u66f8\u3002\"\n\n\u4e0a\u73ed\u5730\u9ede\uff1a\u81fa\u7063(\u914d\u5408\u696d\u52d9\u9700\u8981\u9577\u671f\u6d3e\u99d0\u6d77\u5916\u55ae\u4f4d\u5de5\u4f5c)\n\n*\u6709\u610f\u8005\u8acb\u8a3b\u660e\u300c\u7504\u9078\u985e\u5225\u300d\uff0c\u4e26\u5c07\u4e2d\u3001\u82f1\u6587\u5c65\u6b77\u53ca\u76f8\u95dc\u8cc7\u6599\u4ee5\u96fb\u5b50\u90f5\u4ef6\u65b9\u5f0f\u5bc4\u81f3Apply Now\u3002\u672a\u4f9d\u898f\u5b9a\u65b9\u5f0f\u5831\u540d\u8005\uff0c\u8996\u70ba\u8cc7\u683c\u4e0d\u7b26\u3002\n\n", "employment_types": ["Full Time", "Permanent"], "selling_points": ["Credit Risk", "Strong in Excel (VBA, Macro)", "Margin Financing"], "locations": ["Central"], "categories": ["Banking / Finance", "Credit Analysis / Approval", "Credit Collection", "Risk Management"], "post_time": "2022-01-10T09:40:28Z", "salary": {"currency": null, "max": null, "min": null, "period": "monthly", "term": null}, "salary_visible": false, "title_keywords": ["senior associate", "associate"], "responsibilities": [], "requirements": {"degrees": [], "majors": [], "languages": [], "language_level": [], "hard_skills": [], "soft_skills": [], "languages_combined": []}, "experience_required": {"duration": [], "field": []}}, {"job_id": "100003009035015", "location_code": "hk", "company": "WIT Talent Solutions Limited", "job_title": "Risk AVP - Corporate Banking", "description": "Company: \u00a0\u00a0\u00a0\u00a0\u00a0 \u00a0\u00a0\u00a0\u00a0\u00a0\u00a0\u00a0\u00a0\u00a0\u00a0\u00a0 An International Corporate Bank\u00a0\nPosition: \u00a0\u00a0\u00a0\u00a0\u00a0\u00a0\u00a0 \u00a0\u00a0\u00a0\u00a0\u00a0\u00a0\u00a0\u00a0\u00a0\u00a0\u00a0 Risk AVP\nLocation:\u00a0\u00a0\u00a0\u00a0\u00a0\u00a0\u00a0 \u00a0\u00a0\u00a0\u00a0\u00a0\u00a0\u00a0\u00a0\u00a0\u00a0\u00a0 Hong Kong\n\nFUNCTION:\u00a0\u00a0\u00a0\u00a0\u00a0\u00a0\u00a0\u00a0\u00a0\u00a0\n\nResponsible for monitoring the risk position and evaluate the performance of the branch\u2019s treasury operations to ensure compliance with Head Office limits and guidelines. Play a key role for the branch operational risk control.\n\n\nMAIN DUTIES AND RESPONSIBILITIES:\u00a0\n\nCredit Risk Management:\n\nUpdate the branch management and Credit Risk Meeting of any material considerations affecting the loan portfolio, loan policy and individual loan transactions.\nAdminister and monitor the loan portfolio including portfolio quality control.\nManage and direct the work of the officers in their respective responsibilities.\nResponsible for overall risk assessment of the department\u2019s area of responsibility, including overall portfolio risk.\nCarry out adhoc assignments requested by the branch management to support Business Promotion Department.\nUpdate Credit Risk Management Procedure Manual.\nPerform any other duties as assigned.\n\nTreasury Risk Management:\n\nPrepare periodical reports for Head Office and management on the risk position and performance of the Treasury Department in an accurate and timely manner.\nEnsure compliance with Head Office limits and guidelines by treasury staff in the course of the department operations.\nCheck the logic built into the systems involved and implement such changes to the systems, procedures and rules as the case may require.\nDevelop, review and enhance risk-related reports to provide better support to management.\nConduct regular review and update of job processes and procedures within the department to ensure fast and effective response to changing conditions, and compliance with internal and external regulations.\nSupervise the work of junior staff and train the staff to gain a better understanding of the work carried out so as to ensure accuracy in work output and to aid staff\u2019s development.\u00a0\n\nREQUIREMENTS:\n\nDegree holder\nAt least 4 years of experience in market/treasury risk management from commercial/wholesale/corporate banks\nStrong sense of responsibility, good communication and organizational skill\nFluent in Cantonese and English", "employment_types": ["Full Time", "Permanent"], "selling_points": [], "locations": ["Central"], "categories": ["Banking / Finance", "Corporate Banking", "Treasury", "Risk Management"], "post_time": "2022-01-10T05:14:54Z", "salary": {"currency": null, "max": null, "min": null, "period": "monthly", "term": null}, "salary_visible": false, "title_keywords": [], "responsibilities": ["regulations", "any other duties", "management", "guidelines", "operations", "systems", "monitor", "procedures", "transactions", "ensure compliance", "develop", "review", "regular review", "compliance", "reports", "quality control"], "requirements": {"degrees": ["degree holder"], "majors": [], "languages": ["cantonese", "english"], "language_level": ["fluent"], "hard_skills": [], "soft_skills": ["communication", "organizational skill", "sense of responsibility"], "languages_combined": [{"language": "cantonese", "language_level": ["fluent"]}, {"language": "english", "language_level": ["fluent"]}]}, "experience_required": {"duration": ["at least 4 years"], "field": ["risk management", "commercial"]}}, {"job_id": "100003009039843", "location_code": "hk", "company": "Page Personnel", "job_title": "Collection/ Credit Control, Associate-MNC Platform", "description": "Our client is an European insurance company set up for more than 100 years. They are now looking for candidate who is with at least 2 years Collection/Credit Control experience with corporate clients to join them. They also welcome candidate coming from non-insurance background.\n\nClient Details\n\nOur client is an European based insurance company. They have set up for more than 100 years, specialising in general insurance business with corporate clients globally. They operate as a very strong MNC business with global footprint covering more than 200 regions. Setting their Asian hub in Hong Kong for more than 20 years, they have been providing competitive insurance services and products to their corporate clients.\n\nTo support their business growth, they are looking for candidate with Collection or Credit Control experience to join them. Candidate would be expected to negotiate with external counterpart from different countries to manage their collection status. Therefore, they would like to look for candidate who is strong in interpersonal skills and could communicate clearly in both Chinese and English. The company culture is very stable and friendly. They emphasise the career development of their staff by providing ample internal mobility opportunities.\n\nDescription\n\nPerform daily collection activities to manage the debt collection status meeting the assigned target.\nFollow up collection issues with suppliers and provide updated report to clients.\nWork closely with internal risk team for collection management\nHandle all enquiries related to collection issues.\nLiaise and maintain positive relationship with policy holders and brokers.\n\nProfile\n\nBachelor degree holder.\nAt least 2 years Collection/Credit Control experience with corporate clients.\nSolid experience of negotiation or client facing from previous job experiences.\nCandidate with experience of negotiating with regional counterpart would be a plus.\nExcellent command in both English and Chinese.\nSociable and self-motivated teamplayer who is with excellent interpersonal skills.\n\nJob Offer\n\nMNC Platform\nWell-established Business\nAnnual Leave: 14 days Up\nMedical Benefits\nDental Benefits\nBody Check\nExcellent Training\nInternal Mobility/ International Mobility\n\nTo apply online please click the 'Apply' button below. For a confidential discussion about this role please contact Ellen Fung on +852 3602 2447.", "employment_types": ["Full Time", "Permanent"], "selling_points": ["MNC Insurance Platform", "Collection Experience", "Excellent Internal Mobility"], "locations": ["Not Specified"], "categories": ["Accounting", "Credit Control", "Banking / Finance", "Credit Collection", "Risk Management"], "post_time": "2022-01-11T11:57:28Z", "salary": {"currency": "HKD", "max": 34999, "min": 20000, "period": "monthly", "term": null}, "salary_visible": true, "title_keywords": ["associate"], "responsibilities": ["liaise", "control", "management", "debt collection", "maintain", "career development", "insurance", "report"], "requirements": {"degrees": ["bachelor degree holder"], "majors": [], "languages": ["english", "chinese"], "language_level": ["excellent"], "hard_skills": ["plus"], "soft_skills": ["self-motivated", "negotiation", "sociable", "interpersonal skills", "friendly", "stable", "mobility", "positive"], "languages_combined": [{"language": "english", "language_level": ["excellent"]}, {"language": "chinese", "language_level": ["excellent"]}]}, "experience_required": {"duration": ["at least 2 years"], "field": ["business"]}}, {"job_id": "100003009043310", "location_code": "hk", "company": "Hays", "job_title": "Manager, Business Conduct and Advisory", "description": "\nYour new company\nAn esteemed global financial services is successfully expanding their market share in Hong Kong. With the increase complexity of the insurance regulatory market and their growing business needs, they are looking for a Manager to ensure proper regulatory landscape to support the growth of their insurance business.\n\nYour new role\nWorking in a fast paced environment, you will design the process and control on end to end flow to meet the latest regulatory requirements. You will drive to improve compliance culture across the business, ensure new initiatives are implemented according to company and regulatory requirements. You will be captivated in technical and solutions-driven compliance culture.\n\nWhat you'll need to succeed\n\nIdeally from insurance or financial services sector especially from bancassurance\n5+ years experience with demonstrated knowledge in insurance knowledge and regulatory requirements\nAble to stand firm on your compliance perspective, but strike a balance for business needs\n\n\nWhat you'll get in return\nThis will be an opportunity where you can develop technical compliance experience in a business where compliance is fully supported.\n\nWhat you need to do now\nIf you are interested in the above opportunity, click \"apply now\" to forward your CV. If you are interested in Compliance / Risk / Audit opportunities within insurance, please contact Ada Cheung at ada.cheung@hays.com.hk [mailto:ada.cheung@hays.com.hk] or 2101 0088.", "employment_types": ["Full Time", "Permanent"], "selling_points": ["Esteemed Global Financial Services", "Competitive Compliance and Project Exposures", "Dynamic team culture"], "locations": ["Not Specified"], "categories": ["Insurance", "Others", "Professional Services", "Legal & Compliance", "Banking / Finance", "Risk Management"], "post_time": "2022-01-12T10:38:42Z", "salary": {"currency": null, "max": null, "min": null, "period": "monthly", "term": null}, "salary_visible": false, "title_keywords": ["manager"], "responsibilities": ["control", "regulatory requirements", "compliance", "audit", "design", "develop", "contact", "insurance"], "requirements": {"degrees": [], "majors": [], "languages": [], "language_level": [], "hard_skills": ["ada"], "soft_skills": ["interested in", "driven"], "languages_combined": []}, "experience_required": {"duration": ["5+ years"], "field": ["business", "compliance", "insurance"]}}, {"job_id": "100003009033645", "location_code": "hk", "company": "OCBC Wing Hang Bank Limited", "job_title": "Associate, Credit RWA Solutions", "description": "Responsibilities\nPerform the data reconciliation\nPrepare the Credit RWA and Credit Portfolio MIS reports for the submission to senior management\u00a0\nPrepare user requirements and conduct the user acceptance test\nConduct the Credit Risk Stress Test (includes Climate Risk Stress Test)\nLiaise with business units and other relevant parities on Credit RWA and stress test issues\nParticipate in Basel IRB related initiatives\nRequirements\n\u200bBachelor\u2019s degree or above with major in Risk Management, Finance, Business, Economics, and other relevant disciplines\nAround 2 years\u2019 relevant experiences, fresh graduate will also be considered.\u00a0\nProficient in MS Office, especially MS Excel\nSound knowledge of SQL and SAS\nKnowledge of Basel 3 Credit RWA regulations will be an advantage\nStrong communication and presentation skill\nAble to work independently and a good team player\n\nAttractive remuneration package will be offered to the right candidate. Please apply with full resume stating present & expected salary and contact phone number\u00a0to\u00a0The Human Resources Manager, 10/F, 161 Queen\u2019s Road Central, Hong Kong.\u00a0Please quote the reference.\n\nPersonal data collected will be used for recruitment purpose only. For more information, please visit our website:\u00a0http://www.ocbcwhhk.com.", "employment_types": ["Full Time", "Permanent"], "selling_points": ["Credit RWA", "Risk Management", "Data Analytics"], "locations": ["Sheung Wan"], "categories": ["Banking / Finance", "Credit Analysis / Approval", "Retail Banking", "Risk Management"], "post_time": "2022-01-10T01:27:57Z", "salary": {"currency": null, "max": null, "min": null, "period": "monthly", "term": null}, "salary_visible": false, "title_keywords": ["associate"], "responsibilities": ["liaise with", "senior management", "reports", "data"], "requirements": {"degrees": ["degree or above", "fresh graduate"], "majors": ["finance", "risk management", "business", "economics"], "languages": [], "language_level": [], "hard_skills": ["presentation skill", "sas", "sql", "ms excel", "ms office"], "soft_skills": ["communication", "good team player", "presentation skill", "work independently"], "languages_combined": []}, "experience_required": {"duration": ["2 years"], "field": []}}, {"job_id": "100003009036618", "location_code": "hk", "company": "Welab Bank Limited", "job_title": "Operational Risk Manager (Virtual Bank)", "description": "WeLab is a leading fintech company in Asia, \u00a0which operates one of first licensed digital banks in Asia \u2013 WeLab Bank, as well as multiple leading online financial services businesses including WeLend and WeLab Bank in Hong Kong, WeLab Digital (\u6211\u6765\u6570\u79d1), Taoxinji (\u6dd8\u65b0\u673a), Wallet Gugu (\u94b1\u5939\u8c37\u8c37) and Tianmian Tech (\u5929\u5195\u79d1\u6280)\u00a0in Mainland China and Maucash in Indonesia. WeLab aims to bring joy to everyone\u2019s financial journey. We strive to improve people\u2019s lives by reinventing financial services through game-changing technology. We put our people first, whether it\u2019s our customers or our employees.\n\nAs the only homegrown Hong Kong fintech to receive a virtual banking license, we aim to reinvent and redefine the banking experience by building a bank we love.\n\nWe are an energetic and passionate team that can deliver and execute. We are looking for other intellectually curious, open-minded and smart-working individuals who are just as passionate as we are about making financial services enjoyable. Now you have the opportunity to join us on our journey to achieve our vision and be part of building a better financial future for everyone.\n\nAbout you:\n\nYou're a go-getter with mad juggling skills (or multiple hats) who can thrive in a fast-paced, agile environment\nYou have a strong thirst for knowledge and are driven to find solutions that don't exist yet\nYou are comfortable with ambiguity and extremely resourceful (in your past life you could've been a detective)\nYou always find a way to get things done without sacrificing the quality of your work, integrity and values. No task is off limits for you.\nYou are humble and prioritize the success of the team over your own with an eagerness to help those around you\nYou don't shy away from challenges and have the ability to bounce back from setbacks\n\nWhat you\u2019ll do and what success looks like in this role\n\nAssist business units to apply operational risk management tools to help identifying, assessing, monitoring and controlling operational risk;\nConduct reviews to identify possible operational risks and provide recommendations to address the control weakness; monitor the implementation progress of the enhanced controls;\nConduct due diligence pertaining to new products/ services as well as insourced/ outsourced activities, give advice on operational risk management matters;\nWork closely with business/ support units to effectively manage operational risk in accordance with legal, regulatory and internal requirements;\nCo-ordinate the establishment and ensure self-assessment is being conducted within own unit on risk toolkits such as Key Risk Indicators;\nLead and manage team members to perform daily work;\nWork on ad hoc projects.\n\nWhat is required and what we\u2019re looking for\n\nDegree holder in Finance, Economics, Business Administration, Accounting or equivalent disciplines;\nHolder of relevant Professional Qualification (eg. HKIB) will be an advantage;\nMinimum 5 years experience in financial industry with 3 years experience in operational risk or fraud risk management in banking industry, preferably from retail banking environment\nControl conscious with strong sense in risk awareness;\nGood logical thinking and analytical skills;\nAble to work independently with minimum supervision and a good team player as well;\nCandidate with less experience will be considered as Manager;\nGood command of both written and spoken English and Chinese.\n\nWeLab perks:\n\nCompetitive salary\nLearning and development stipend, because we value lifelong learning and believe the best way to invest in our employees is to encourage them to continue to learn\nWork hard and laugh lots (chicken wings and french toast, etc.) with a high-performing, fun and diverse team\nHappiness Dollars for spending on anything that makes you happy\nCoffee stipend\nConveniently located office surrounded by diverse and delicious lunch options\nLively office with gaming consoles and a ping pong table\nFun extracurricular activities with your colleagues like hiking, yoga, badminton, wine tasting, dragon boat racing, rock climbing, etc.\nEmployee referral bonuses\n\nAwards & recognition:\n\nFinancial Times (FT) 2020 Asia-Pacific High-Growth Companies \u2013 #2 ranked company\n2020 CNBC Disruptor 50 List \u2013 #11, only company included from Hong Kong and just one of five from Asia\n\nWe offer competitive salary package to the successful candidate.\u00a0 If you are interested in joining this exciting team, please apply with resume via the \"Apply\" button.\n\nAll information provided by applicants will be used for recruitment purposes only. Information of unsuccessful applicants will be destroyed within 24 months of receipt.", "employment_types": ["Full Time", "Permanent"], "selling_points": ["Assist to apply operational risk management tools", "Conduct reviews to identify operational risks", "Conduct due diligence"], "locations": ["Quarry Bay"], "categories": ["Banking / Finance", "Financial Services", "Order Processing & Operation / Settlement", "Risk Management"], "post_time": "2022-01-10T11:24:53Z", "salary": {"currency": null, "max": null, "min": null, "period": "monthly", "term": null}, "salary_visible": false, "title_keywords": ["manager"], "responsibilities": ["due diligence", "management", "control", "monitoring", "quality", "monitor", "implementation", "provide recommendations", "ad hoc projects", "banking", "administration"], "requirements": {"degrees": ["degree holder"], "majors": ["finance", "economics", "business administration", "accounting"], "languages": ["english", "french", "chinese"], "language_level": ["good command"], "hard_skills": ["no", "joy", "agile", "fun", "analytical skills", "go", "mad"], "soft_skills": ["passionate", "work independently", "good team player", "agile", "resourceful", "open-minded", "integrity", "prioritize", "analytical skills", "diverse", "learning", "good logical thinking", "energetic", "driven"], "languages_combined": [{"language": "english", "language_level": ["good command"]}, {"language": "french", "language_level": []}, {"language": "chinese", "language_level": ["good command"]}]}, "experience_required": {"duration": ["3 years", "minimum 5 years"], "field": ["risk management", "banking industry", "banking experience", "retail banking", "financial industry", "banking"]}}, {"job_id": "100003009040541", "location_code": "hk", "company": "Nova Credit Limited", "job_title": "Senior Product Manager / Product Manager (Fintech)", "description": "We are looking for an experienced and passionate Senior Product Manager to join us.\n\nThe Team:\u00a0We leverage data/analytics/Fintech products to 1) provide solutions for financial institutions to help them meet the demands of today\u2019s ever-changing environment; 2) provide innovative products and services to consumers to help them better manage their credit.\n\nResponsibilities:\n\nDirectly contribute to the successful execution of the product development and go-to-market strategies of solutions that solve for the needs of our clients\nUnderstand retail banking and credit cycle\nConduct market, company and competitor research on new products\nPropose new business opportunities to form product proposition through being in touch with the industry and regulatory trends in credit industry, data/analytics businesses, Fintech development;\nWork with internal and external stakeholders to understand needs, define features, write product specifications;\nCreate product manual, training materials and commercial education to inspire clients;\nWork with marketing and sales team to increase products acceptance\n\nRequirements:\n\nBachelor degree or above\n5 or more years of experience in financial industry (banking or lending business background is advantageous)\nPassionate for creating customer-centric solutions\nA mature team player with strong presentation and communications skills\nSound Project Management mindset and skills\nProficient in Cantonese, English and Mandarin\nCandidates with demonstrated strong track record of leadership and experience will be considered for the Senior Product Manager position\n\n", "employment_types": ["Full Time", "Permanent"], "selling_points": [], "locations": ["Cheung Sha Wan"], "categories": ["Banking / Finance", "Credit Analysis / Approval", "Information Technology (IT)", "Product Management / Business Analyst", "Risk Management"], "post_time": "2022-01-12T02:45:09Z", "salary": {"currency": null, "max": null, "min": null, "period": "monthly", "term": null}, "salary_visible": false, "title_keywords": ["senior product manager", "product manager"], "responsibilities": ["data", "business opportunities", "specifications", "sales team", "banking"], "requirements": {"degrees": ["degree or above", "bachelor"], "majors": [], "languages": ["cantonese", "english", "mandarin"], "language_level": ["proficient"], "hard_skills": ["project management"], "soft_skills": ["passionate", "mature", "project management", "team player", "leadership", "presentation"], "languages_combined": [{"language": "cantonese", "language_level": ["proficient"]}, {"language": "english", "language_level": ["proficient"]}, {"language": "mandarin", "language_level": ["proficient"]}]}, "experience_required": {"duration": [], "field": ["business", "financial industry", "banking"]}}, {"job_id": "100003009037631", "location_code": "hk", "company": "China CITIC Bank International Limited", "job_title": "Manager, Credit Risk Methodologies and Analytics", "description": "Job Purpose\n\nAssist in regular credit impairment report to meet HKFRS-9 requirements and assess the movement of credit impairment to drive methodology enhancement.\n\n\n\nKey Responsibilities\n\nEnhance the methodology, risk parameters and systems for the impairment provision estimation under IFRS-9 requirements.\nMonitor\u00a0the credit risk RWA calculation and provide judgement on credit RWA as appropriate.\nContribute in new product discussion and implementation, advise on Return of Allocate Capital (ROAC) and initiate relevant system changes.\nManage\u00a0stress testing methodology to meet regulatory requirements.\nPerform data validation, prepare monitoring and variance analysis of credit impairment provision movement.\nPrepare ICAAP reporting and support risk analytics projects in respect to requests from regulatory bodies and management.\nAssist to liaise with regulators, auditors, external parties and credit rating agencies\u00a0to provide explanations and clarifications on the credit risk methodologies adopted by the Bank.\n\nRequirements\n\n\nDegree holder in Finance, Accounting, Statistics or related disciplines.\nAt least 4\u00a0years' of relevant experience in bank or related industry.\nFamiliar with Basel frameworks, credit risk approaches and HKMA capital banking rules.\nProficiency in credit risk quantitative modeling, expected loss computations, data & risk analysis and stress testing.\nProfessional qualification like Associate Credit Risk Management Professional (ACRP), CFA, FRM, ACCA, etc. is preferred.\nSelf-motivated, independent, with good communication skills, able to communicate effectively at all levels.\nGood command of written and spoken English and Chinese including Putonghua.\nCandidate with\u00a0more experience will be considered\u00a0for the role of\u00a0Senior Manager.\n\nFor more details about career opportunities with the Bank, please visit our website http://www.cncbinternational.com/careers/en/index.jsp. Please apply with full resume stating current and expected salaries via https://careers.cncbinternational.com.\n\nPersonal data collected will be used for recruitment related purposes only. Applicants not invited for interview within 6 weeks may consider their applications unsuccessful. However, applicants may be considered for other suitable positions within the Group for a period of not more than 2 years. Personal data will be destroyed at any time after 3 months.\n\nChina CITIC Bank International is committed to being an equal opportunities employer and intends to provide a work environment free of unlawful discrimination or harassment. All employment decisions will be made in a non-discriminatory manner.", "employment_types": ["Full Time", "Permanent"], "selling_points": ["4 years of work experience in credit risk models", "Knowledge of Basel & IFRS9", "Experience in SAS"], "locations": ["Tsim Sha Tsui"], "categories": ["Banking / Finance", "Credit Analysis / Approval", "Professional Services", "Business Analysis / Data Analysis", "Risk Management"], "post_time": "2022-01-11T03:19:57Z", "salary": {"currency": null, "max": null, "min": null, "period": "monthly", "term": null}, "salary_visible": false, "title_keywords": ["manager"], "responsibilities": ["reporting", "management", "data", "regulatory requirements", "systems", "monitor", "implementation", "monitoring", "testing", "external parties", "variance analysis", "liaise with", "system changes"], "requirements": {"degrees": ["degree holder"], "majors": ["related disciplines", "finance", "accounting", "statistics"], "languages": ["putonghua", "english", "chinese"], "language_level": ["good command"], "hard_skills": ["acca", "hkma", "cfa", "analysis", "frm"], "soft_skills": ["communication skills", "self-motivated", "committed", "independent"], "languages_combined": [{"language": "putonghua", "language_level": ["good command"]}, {"language": "english", "language_level": ["good command"]}, {"language": "chinese", "language_level": ["good command"]}]}, "experience_required": {"duration": ["at least 4 years"], "field": ["related", "relevant experience"]}}, {"job_id": "100003009030141", "location_code": "hk", "company": "The Bank of East Asia, Limited", "job_title": "Credit Management Manager", "description": "Responsibilities\nTo be a team member of the Retail Lending Department\nTo increase the Department\u2019s interest income by underwriting more high-yield loans\nTo process of application approval of credit card, consumer loan and mortgage loan for meeting the Service Level Agreement (SLA) and securing more loan business\nTo handle and investigate customer\u2019s complaint/request\nTo handle general enquires from Branches/Departments\nRequirements\nUniversity graduate; OR\nPreferable over 6 years experiences in banking sector cover the followings:\nMinimum 2 years in supervision of credit approval or related credit experience\nGood understanding in retail lending products and unsecured SME loans\nSound knowledge of financial analysis and MIS tools\nFamiliar with related regulatory guidelines and banking policies\nPossess strong credit sense and risk awareness\nA good team leader with good analytical and interpersonal skills\nIndependent and detailed-oriented and able to work under pressure\nGood command of both spoken and written English and Chinese, Putonghua proficiency is an advantage\nPlease apply online via the BEA Careers website at\u00a0https://careers.hkbea.com/psp/hcmprd/EMPLOYEE/HRMS/c/HRS_HRAM.HRS_APP_SCHJOB.GBL?Page=HRS_APP_JBPST&Action=U&FOCUS=Applicant&SiteId=1&JobOpeningId=3307&PostingSeq=1 or by clicking the Apply Now button. Kindly note that if you are a new user, you have to first create your User Profile before you can apply.\nPersonal data provided by job applicants will be used for recruitment purposes only and will be treated in accordance with the Bank's Personal Data Policy, which is available upon request. Applicants who are not invited for interviews within six weeks may consider their applications unsuccessful and the personal data collected will be destroyed after six months.", "employment_types": ["Full Time", "Permanent"], "selling_points": ["Handle & investigate customer\u2019s complaint/request", "University graduate", "Minimum 2 years in supervision of credit approval"], "locations": ["Not Specified"], "categories": ["Banking / Finance", "Credit Analysis / Approval", "Others", "Risk Management"], "post_time": "2022-01-07T19:20:06Z", "salary": {"currency": null, "max": null, "min": null, "period": "monthly", "term": null}, "salary_visible": false, "title_keywords": ["manager"], "responsibilities": [], "requirements": {"degrees": ["university graduate"], "majors": [], "languages": ["putonghua", "english", "chinese"], "language_level": ["advantage", "proficiency", "good command"], "hard_skills": ["financial analysis", "c"], "soft_skills": ["independent", "detailed", "interpersonal skills", "good team leader", "work under pressure"], "languages_combined": [{"language": "putonghua", "language_level": ["proficiency", "advantage", "good command"]}, {"language": "english", "language_level": ["advantage", "good command"]}, {"language": "chinese", "language_level": ["advantage", "good command"]}]}, "experience_required": {"duration": ["6 years", "minimum 2 years"], "field": ["related", "banking sector"]}}, {"job_id": "100003009028060", "location_code": "hk", "company": "Min Xin Holdings Limited", "job_title": "Risk Management Manager", "description": "Job Responsibilities:\n\nSetting the vision and strategy for the enterprise risk management & function working in conjunction with all other senior leadership across the Group\nDevelop and implement the risk management policies, procedures and manuals to ensure the risk policies and practices are in full compliance with the regulatory requirements\nCoordinate with business units to ensure the errors are rectified and effective controls are put in place to mitigate similar risks in future\nPerform risk analysis and enhancement in new business and investment plan\nReview the internal control self-assessment reports from business units and provide recommendations on control enhancement\nServing as\u00a0the Chief Risk Officer of the Min Xin Insurance\nAppoint as the key person under the Insurance Authority\nResponsible for compiling, assessing and reporting risk information to the top management and the Board\n\n\u00a0Job Requirements:\u00a0\n\nDegree holder in Actuarial, Risk Management, Finance or related disciplines with professional qualifications in CFA/FRM/PRM/SOA\nMinimum of 8 years\u2019 experience in risk management, including 6 years in supervisory level\nActuarial and risk management experience in general insurance firms highly preferred\nSolid knowledge of modern risk management theory, common practice and overall risk management system including insurance risk, market risk, credit risk management as well as operational risk management\nPrior sound credit risk management experiences in particular experience to handle challenging requests from regulators and auditors\nMature and able to work independently under pressure\nSelf-motivated with good analytical and people skills\nExcellent analytical skills with high integrity and good communication skills in both written and spoken English and Cantonese and Putonghua.\nProficiency in MS office and Chinese Word Processing\n\nWe offer attractive package including 5 day work and fringe benefit to the right candidate. Interested candidates please apply with full resume\u00a0(both in English and Chinese)\u00a0stating present & expected salary and date available by e-mail.\n\n(Personal data collected will be used for recruitment purpose only.)", "employment_types": ["Full Time", "Permanent"], "selling_points": [], "locations": ["Admiralty"], "categories": ["Insurance", "Actuarial", "Banking / Finance", "Risk Management"], "post_time": "2022-01-07T01:24:15Z", "salary": {"currency": null, "max": null, "min": null, "period": "monthly", "term": null}, "salary_visible": false, "title_keywords": ["risk management manager"], "responsibilities": ["reporting", "management", "control", "policies", "regulatory requirements", "compliance", "procedures", "coordinate with", "review", "develop", "reports", "risk analysis", "plan", "provide recommendations", "insurance", "internal control"], "requirements": {"degrees": ["degree holder"], "majors": ["finance", "risk management", "related disciplines"], "languages": ["cantonese", "putonghua", "english", "chinese"], "language_level": ["excellent", "proficiency", "good"], "hard_skills": ["chinese word processing", "professional qualifications", "cfa", "analytical skills", "frm", "ms office"], "soft_skills": ["communication skills", "work independently", "self-motivated", "under pressure", "integrity", "mature", "analytical skills"], "languages_combined": [{"language": "cantonese", "language_level": ["excellent", "good"]}, {"language": "putonghua", "language_level": ["excellent", "good"]}, {"language": "english", "language_level": ["excellent", "good"]}, {"language": "chinese", "language_level": ["proficiency"]}]}, "experience_required": {"duration": ["6 years", "minimum of 8 years"], "field": ["general insurance", "risk management", "management", "supervisory level", "credit risk"]}}, {"job_id": "100003009036624", "location_code": "hk", "company": "Welab Bank Limited", "job_title": "Liquidity & Market Risk Manager (Virtual Bank)", "description": "WeLab is a leading fintech company in Asia, \u00a0which operates one of first licensed digital banks in Asia \u2013 WeLab Bank, as well as multiple leading online financial services businesses including WeLend and WeLab Bank in Hong Kong, WeLab Digital (\u6211\u6765\u6570\u79d1), Taoxinji (\u6dd8\u65b0\u673a), Wallet Gugu (\u94b1\u5939\u8c37\u8c37) and Tianmian Tech (\u5929\u5195\u79d1\u6280)\u00a0in Mainland China and Maucash in Indonesia. WeLab aims to bring joy to everyone\u2019s financial journey. We strive to improve people\u2019s lives by reinventing financial services through game-changing technology. We put our people first, whether it\u2019s our customers or our employees.\nAs the only homegrown Hong Kong fintech to receive a virtual banking license, we aim to reinvent and redefine the banking experience by building a bank we love.\n\nWe are an energetic and passionate team that can deliver and execute. We are looking for other intellectually curious, open-minded and smart-working individuals who are just as passionate as we are about making financial services enjoyable. Now you have the opportunity to join us on our journey to achieve our vision and be part of building a better financial future for everyone.\n\nAbout you:\n\nYou're a go-getter with mad juggling skills (or multiple hats) who can thrive in a fast-paced, agile environment\nYou have a strong thirst for knowledge and are driven to find solutions that don't exist yet\nYou are comfortable with ambiguity and extremely resourceful (in your past life you could've been a detective)\nYou always find a way to get things done without sacrificing the quality of your work, integrity and values. No task is off limits for you.\nYou are humble and prioritize the success of the team over your own with an eagerness to help those around you\nYou don't shy away from challenges and have the ability to bounce back from setbacks\n\nWhat you\u2019ll do and what success looks like in this role\n\nSupport to establish and maintain liquidity risk and marketing risk management framework of limits and controls, policies & procedures and governance that will operate across the 3 lines of defense to enable effective management;\nMonitor and manage liquidity risk and conduct daily liquidity ratios management and projection;\nMonitor and manage market risk including FX, interest rate risk, IRRBB etc\nFamiliar with HKMA SPMs for liquidity risk and marketing risk management and stay up to date on regulatory requirements to ensure compliance with all statutory requirements and internal policy/guidelines;\nConduct regular regulatory and internal stress testing exercises that involve liquidity risk considerations;\nSupport to develop the risk management systems & infrastructure and enhancing risk governance for liquidity risk and market risk;\nSupport the preparation of risk updates to risk oversight committees;\nSupport ICAAP exercise relating to liquidity rand market risk\n\nWhat is required and what we\u2019re looking for\n\nBachelor\u2019s degree holder in a quantitative discipline such as Risk Management, Quantitative Finance etc. or equivalent professional qualifications in risk (e.g. FRM), treasury (e.g. AMCT/MCT) or finance;\nAt least 3 years of relevant experience\nQualified for Enhanced Competency Framework on Treasury Management (e.g. TMA full member) is an advantage;\nPossess a good risk management and treasury network and strong knowledge of best practice techniques in the industry covering Non-Traded Market Risks, FTP, ALM, liquidity and financial risk management.\nStrong technical skills, including a solid understanding of banking products (particularly in retail banking product behaviours);\nTeam player, result-oriented, self-driven with strong sense of ownership;\nExcellent excel skills;\nExcellent command in both spoken and written English and Cantonese.\nCandidate with less experience will be considered as Assistant Manager\n\nWeLab perks:\n\nCompetitive salary\nLearning and development stipend, because we value lifelong learning and believe the best way to invest in our employees is to encourage them to continue to learn\nWork hard and laugh lots (chicken wings and french toast, etc.) with a high-performing, fun and diverse team\nHappiness Dollars for spending on anything that makes you happy\nCoffee stipend\nConveniently located office surrounded by diverse and delicious lunch options\nLively office with gaming consoles and a ping pong table\nFun extracurricular activities with your colleagues like hiking, yoga, badminton, wine tasting, dragon boat racing, rock climbing, etc.\nEmployee referral bonuses\n\nAwards & recognition:\n\nFinancial Times (FT) 2020 Asia-Pacific High-Growth Companies \u2013 #2 ranked company\n2020 CNBC Disruptor 50 List \u2013 #11, only company included from Hong Kong and just one of five from Asia\nWe offer competitive salary package to the successful candidate.\u00a0 If you are interested in joining this exciting team, please apply with resume via the \"Apply\" button.\nAll information provided by applicants will be used for recruitment purposes only. Information of unsuccessful applicants will be destroyed within 24 months of receipt.", "employment_types": ["Full Time", "Permanent"], "selling_points": ["Manage liquidity & market risk", "Familiar with HKMA SPMs", "Support ICAAP exercise"], "locations": ["Quarry Bay"], "categories": ["Banking / Finance", "Financial Services", "Risk Management"], "post_time": "2022-01-10T11:24:54Z", "salary": {"currency": null, "max": null, "min": null, "period": "monthly", "term": null}, "salary_visible": false, "title_keywords": ["manager"], "responsibilities": ["management", "guidelines", "policies", "regulatory requirements", "systems", "quality", "procedures", "monitor", "ensure compliance", "testing", "statutory requirements", "develop", "maintain", "infrastructure", "banking"], "requirements": {"degrees": ["bachelor", "degree holder"], "majors": ["finance", "risk management"], "languages": ["cantonese", "english", "french"], "language_level": ["excellent"], "hard_skills": ["excel", "no", "joy", "agile", "fun", "professional qualifications", "hkma", "go", "frm", "mad"], "soft_skills": ["passionate", "result-oriented", "agile", "resourceful", "open-minded", "integrity", "prioritize", "diverse", "learning", "technical skills", "team player", "energetic", "driven"], "languages_combined": [{"language": "cantonese", "language_level": ["excellent"]}, {"language": "english", "language_level": ["excellent"]}, {"language": "french", "language_level": []}]}, "experience_required": {"duration": ["at least 3 years"], "field": ["relevant experience", "banking experience", "banking"]}}, {"job_id": "100003009033696", "location_code": "hk", "company": "Octopus Holdings Limited", "job_title": "AML Compliance Analyst (7-month contract)", "description": "Job Responsibilities: \u00a0\nPerform customer due diligence and on-going checking/review (e.g. name screening, company search,\nrisk\u00a0 assessment\u00a0 of\u00a0 customers,\u00a0 reviewing\u00a0 supporting\u00a0 documents\u00a0 of\u00a0 application\u00a0 for\u00a0 Octopus\u00a0 Wallet\naccount and merchant businesses, etc.) according to the established procedures and guidelines\nPerform quality check to ensure the compliance of due diligence, name screening and record keeping\nrequirements including the identification and verification of relevant customer due diligence information\nand documentation\nPrepare regular reports for management review\nDemonstrate commitment to regulatory compliance and high ethical standards \u00a0\nKeep abreast of the regulatory development \u00a0\nPerform ad-hoc tasks as assigned\nRequirements: \u00a0\nDegree holder in relevant disciplines\nMinimum 1 year relevant work experience, experience in financial services industry is a plus\nProficient\u00a0 in\u00a0 MS\u00a0 Word\u00a0 and\u00a0 MS\u00a0 Excel\u00a0 (hands-on\u00a0 experience\u00a0 in\u00a0 MS\u00a0 Excel\u00a0 functions\u00a0 e.g.\u00a0 Pivot\u00a0 tables,\nVLOOKUP etc. is a plus)\nAttentive to details with strong analytical skills especially on data filtering & data processing \u00a0\nSelf-starter with integrity \u00a0\nSensitive to numbers\nProactive with can-do attitude\nGood communication and interpersonal skills for collaborating with internal and external parties\nGood command of written and spoken English and Chinese\nWe offer successful candidate an attractive remuneration package and excellent career prospects. Interested parties please send your resume, present and expected salary, contact details and quoting the reference number by clicking \"Apply Now\"\nVisit our web site: http://www.octopus.com.hk/\nThe personal data collected will be used for recruitment purposes only. If you are not contacted by us within six weeks, you may consider your application unsuccessful. Personal data with an unsuccessful applicant will be destroyed 12 months after rejection of the application. During this retention period, you have the right to request for correction or destruction of your personal data at any time. Any request for the correction or destruction of personal data should be addressed in writing to our Human Resources & Administration Department.\nOctopus is an equal opportunity employer and all employment decisions and Human Resources policies are administered; especially those relating to recruitment & selection, compensation & benefits, promotion & transfer, training & development and termination & redundancy; without discrimination on the basis of age, race, colour, religion, sex, national origin, marital status, pregnancy, physical and mental disability and family status but on genuine occupational qualification, job performance, employees\u2019 ability and internal/ external relativities.", "employment_types": ["Full Time", "Permanent"], "selling_points": ["Five-day work", "Degree holder in relevant disciplines", "Minimum 1 year relevant work experience"], "locations": ["Kowloon Bay"], "categories": ["Banking / Finance", "Analyst", "Others", "Risk Management"], "post_time": "2022-01-10T01:36:41Z", "salary": {"currency": null, "max": null, "min": null, "period": "monthly", "term": null}, "salary_visible": false, "title_keywords": ["aml compliance analyst"], "responsibilities": ["due diligence", "quality check", "guidelines", "ad-hoc tasks", "review", "procedures", "checking", "compliance", "customer due diligence", "regular reports for management", "documentation", "company search"], "requirements": {"degrees": ["degree holder"], "majors": [], "languages": ["english", "chinese"], "language_level": ["good command"], "hard_skills": ["excel", "plus", "word", "analytical skills", "vlookup", "processing"], "soft_skills": ["attentive to details", "can-do attitude", "integrity", "analytical skills", "hands-on", "communication and interpersonal skills", "sensitive to numbers", "proactive"], "languages_combined": [{"language": "english", "language_level": ["good command"]}, {"language": "chinese", "language_level": ["good command"]}]}, "experience_required": {"duration": ["minimum 1 year"], "field": ["financial services industry"]}}, {"job_id": "100003009037281", "location_code": "hk", "company": "Page Personnel", "job_title": "Underwriting, Senior Associate - General Insurance", "description": "Our client is a very stable financial group who is strong in providing their general insurance services. They are now looking for candidate who is with at least 5 years Underwriting experience from insurance company to join them.\n\nClient Details\n\nOur client has set up for more than 50 years. They provide extensive insurance services to both individual and corporate clients, covering personal travelling, motor, accident, marine cargo, fire, public liability and property. With their strong capital and networking support from their mother financial group, they have been expanding their business steadily.\n\nTo support their business, they are now looking for candidates with at least 5 years of experience in the field of Underwriting from insurance companies to join them. Candidate would be expected to perform the all-rounded technical support for their General Insurance business. Therefore, candidate who is coming from general insurance or reinsurance background would be on great advantage. The company culture is very stable and candidate could enjoy great work life balance working at the platform.\n\nDescription\n\nRenew the treaty of the reinsurance programs by preparing the statistical data, terms comparison, and the end-to-end process support.\nCalculate and update the statistical data related to the risk profiles, loss data and status to prepare reports for treaty renewal and management review on treaty result.\nPerform calculation on fire accumulation to underwriters on new cases or renewed cases.\nHandle enquiries from external clients and re-insurers.\nAssist management for creating internal planning and managing risk portfolios.\n\nProfile\n\nBachelor degree holder.\nAt least 5 years Underwriting experience from insurance/reinsurance firms.\nCandidate who has achieved ANZIIF/CII would be on advantage.\nGood communication skills in both English and Chinese.\nSelf-motivated teamplayer\n\nJob Offer\n\nWell-established Platform\nStable Company\nWide Exposure\nAnnual Leave\nBirthday Leave\nMedical Benefits\nCover Dependent\nGuaranteed Double Paid\nWork Life Balance\n\nTo apply online please click the 'Apply' button below. For a confidential discussion about this role please contact Ellen Fung on +852 3602 2447.", "employment_types": ["Full Time", "Permanent"], "selling_points": ["Well-established Financial Group", "Work Life Balance", "Double Pay"], "locations": ["Not Specified"], "categories": ["Insurance", "Underwriter", "Banking / Finance", "Risk Management"], "post_time": "2022-01-11T02:18:24Z", "salary": {"currency": "HKD", "max": 29999, "min": 20000, "period": "monthly", "term": null}, "salary_visible": true, "title_keywords": ["senior associate"], "responsibilities": ["management", "data", "technical support", "communication", "handle enquiries", "prepare reports", "insurance", "management review", "planning"], "requirements": {"degrees": ["bachelor degree holder"], "majors": [], "languages": ["english", "chinese"], "language_level": ["good"], "hard_skills": [], "soft_skills": ["communication skills", "stable", "extensive", "self-motivated"], "languages_combined": [{"language": "english", "language_level": ["good"]}, {"language": "chinese", "language_level": ["good"]}]}, "experience_required": {"duration": ["at least 5 years"], "field": ["underwriting", "insurance", "business"]}}, {"job_id": "100003009039626", "location_code": "hk", "company": "Randstad Hong Kong Limited", "job_title": "Operational Risk VP - Regional Corporate Bank", "description": "about the company\nThis is a regional bank with branches across Asia Pacific. Currently they are hiring a senior to join their Operational Risk Department in Hong Kong.\nabout the team\nReporting to the Department Head, you will be working in a sizeable team. The bank offers a supportive and friendly environment. Good work life balance.\nabout the job\nYou will:\nAssist business units to apply operational risk management tools to help identifying, assessing, monitoring and controlling operational risk\nImplement policy for the Fraud framework to meet requirements and legislation in Hong Kong\nDevelop and review policies and guidelines on Business Continuity Planning to incorporate changes in organizational structure and regulatory requirement in a timely manner\nMonitor and follow up for assignments including RCSAs, KRIs, risk profiles etc.\nskills & experiences required\nMinimum 8 years experience in operational and fraud risk experience from banks or enforcement agency\nSolid knowledge in BCP and pysical security would be an advantage\nStrong written and communication skills\nProficient in both English and Chinese\n\nTo apply online, please click on the link. Alternatively, for a confidential discussion please contact Gillian Lam on +852 2232 3442 or gillian.lam@randstad.com.hk", "employment_types": ["Full Time", "Permanent"], "selling_points": [], "locations": ["Not Specified"], "categories": ["Accounting", "Audit", "Banking / Finance", "Corporate Banking", "Risk Management"], "post_time": "2022-01-11T10:15:30Z", "salary": {"currency": "HKD", "max": 89999, "min": 70000, "period": "monthly", "term": null}, "salary_visible": true, "title_keywords": [], "responsibilities": ["reporting", "management", "business continuity", "guidelines", "policies", "review", "monitoring", "a timely manner", "monitor", "develop", "communication", "contact", "planning"], "requirements": {"degrees": [], "majors": [], "languages": ["english", "chinese"], "language_level": ["proficient"], "hard_skills": [], "soft_skills": ["communication skills", "supportive", "organizational", "timely", "friendly"], "languages_combined": [{"language": "english", "language_level": ["proficient"]}, {"language": "chinese", "language_level": ["proficient"]}]}, "experience_required": {"duration": ["minimum 8 years"], "field": ["agency"]}}, {"job_id": "100003009039438", "location_code": "hk", "company": "Guotai Junan International Holdings Limited", "job_title": "Information Security Officer/ Assistant Manager", "description": "Job Description:\n\nAssist in implement remediation security controls based on IT initiatives on technology risk perspective.\nAssist the team to oversight external parties to perform information security assessment including but not limited to; vulnerability scanning, penentration test, technical security assessment and etc.\nAssist the team to conduct periodic review and technical assessment when needed including phishing attack simulation, penetration test, vulnerability scanning and etc\u2026\n\nRequirements:\n\nPassionate in InfoSec and Cybersecurity area\nHolder of Bachelors Degree or above in IT/Computer Science \u00a0related disciplines, other discipline with knowledge in IT are also welcome.\n2+ years' working experience in InfoSec/Cybersecurity/TRM. No experience but with strong cybersecurity knowledge will also consider for a lower title\nWith previous working experience in technology consulting firm or Big 4 is a plus\nCertified in professional certfications is a plus but not necessary, e.g.: CISSP, CISA, CRISC, CEH, etc\u2026\nProficiency in spoken English and Chinese, fluency in Putonghua is a must.\nFresh graduates are welcomed.\n\n\nWe offer an attractive remuneration package to the right candidate. Interested parties please forward your full resume with availability, expected salary by pressing \"Apply now\" or send it to 27/F., Low Block, Grand Millennium Plaza, 181 Queen\u2019s Road, Central, Hong Kong.\n\n(Data collected will be kept strictly confidential and used for recruitment purpose only.)", "employment_types": ["Full Time", "Permanent"], "selling_points": ["Assist in implement remediation security controls", "Assist the team to conduct periodic review", "Oversight external parties to perform assessments"], "locations": ["Central & Western Area"], "categories": ["Information Technology (IT)", "Security", "Others", "Banking / Finance", "Risk Management"], "post_time": "2022-01-11T09:46:31Z", "salary": {"currency": null, "max": null, "min": null, "period": "monthly", "term": null}, "salary_visible": false, "title_keywords": ["officer", "assistant manager"], "responsibilities": ["scanning", "review", "external parties", "information security"], "requirements": {"degrees": ["degree or above"], "majors": ["related disciplines", "it", "computer science"], "languages": ["putonghua", "english", "chinese"], "language_level": ["fluency", "proficiency"], "hard_skills": ["no", "plus"], "soft_skills": ["passionate"], "languages_combined": [{"language": "putonghua", "language_level": ["fluency", "proficiency"]}, {"language": "english", "language_level": ["fluency", "proficiency"]}, {"language": "chinese", "language_level": ["fluency", "proficiency"]}]}, "experience_required": {"duration": ["2+ years"], "field": ["big 4", "consulting"]}}, {"job_id": "100003009030839", "location_code": "hk", "company": "The Bank of East Asia, Limited", "job_title": "Assistant Risk & Compliance Manager, Corporate Risk & Compliance", "description": "Assistant Risk & Compliance Manager, Corporate Risk & Compliance (Job ID3203)\nResponsibilities\nTo be a team member of Corporate Risk & Compliance Department\nTo ensure that procedures and processes are in compliance with all policies, rules, guidelines, requirements prescribed by regulators as well as the Bank\nTo assist in conducting risk control checking on business processes in respect of customer due diligence, transaction monitoring, past due monitoring, consumer credit reference, etc.\nTo assist in developing and implementing operational manuals, guidelines and control measures to rectify issues/ exceptions as identified by internal stakeholders, external auditors and regulators\nTo compile management reports on risk management and compliance related areas\nTo alert and report on regulatory irregularities, breach of guidelines and potential compliance risk\nRequirements\nHKCEE Form 7/HKDSE or above\nAt least 2 years of experience in banking/finance sector\nElementary knowledge of the principle of risks and compliance.\nElementary knowledge of the Bank\u2019s lending policies and standards.\nStrong analytical and problem solving skills\nProficient with Microsoft Office application including Word and Excel\nPlease apply online via the BEA Careers website at https://careers.hkbea.com/psp/hcmprd/EMPLOYEE/HRMS/c/HRS_HRAM.HRS_APP_SCHJOB.GBL?Page=HRS_APP_JBPST&Action=UFOCUS=Applicant&SiteId=1&JobOpeningId=3203&PostingSeq=1 or by clicking the \"Apply Now\" button below. Kindly note that if you are a new user, you have to first create your User Profile before you can apply.\nPersonal data provided by job applicants will be used for recruitment purposes only and will be treated in accordance with the Bank's Personal Information Collection (Employees) Statement and Privacy Policy Statement. Applicants who are not invited for interviews within six weeks may consider their applications unsuccessful and the personal data collected will be destroyed after six months.", "employment_types": ["Full Time", "Permanent"], "selling_points": ["To compile management reports on risk management", "HKCEE Form 7/HKDSE or above", "At least 2 years of experience in banking/finance"], "locations": ["Not Specified"], "categories": ["Banking / Finance", "Others", "Professional Services", "Legal & Compliance", "Risk Management"], "post_time": "2022-01-07T08:26:37Z", "salary": {"currency": null, "max": null, "min": null, "period": "monthly", "term": null}, "salary_visible": false, "title_keywords": ["compliance manager", "assistant"], "responsibilities": ["control", "management", "irregularities", "guidelines", "policies", "compliance", "procedures", "checking", "monitoring", "developing", "customer due diligence", "management reports", "report", "external auditors"], "requirements": {"degrees": ["hkdse"], "majors": [], "languages": [], "language_level": [], "hard_skills": ["excel", "microsoft office", "word", "c", "problem solving skills"], "soft_skills": ["analytical and problem solving skills"], "languages_combined": []}, "experience_required": {"duration": ["at least 2 years"], "field": ["finance", "banking"]}}, {"job_id": "100003009034440", "location_code": "hk", "company": "New Oakland Company Limited", "job_title": "\u5ba4\u5167\u5de5\u7a0b\u52a9\u7406\u7d93\u7406**", "description": "\n\u8077\u8cac :\u4e00\u822c\u5ba4\u5167\u5de5\u7a0b\u52a9\u7406\u7d93\u7406\u5de5\u4f5c\n\n\u8cc7\u6b77 :\u5c08\u4e0a\u6559\u80b2\uff1a\u6587\u6191/\u8b49\u66f8; 3\u5e74\u7d93\u9a57; \u4e00\u822c\u7cb5\u8a9e; \u4e00\u822c\u82f1\u8a9e; \u61c2\u8b80\u5beb\u4e2d\u6587; \u61c2\u8b80\u5beb\u82f1\u6587; \u51773\u5e74\u6216\u4ee5\u4e0a\u5ba4\u5167\u5de5\u7a0b\u7d93\u9a57, \u719f\u6089\u6210\u672c\u4f30\u7b97\u53ca\u5de5\u7a0b\u7a0b\u5e8f, \u80fd\u7368\u7acb\u53ca\u4e3b\u52d5\u5de5\u4f5c, \u61c2AutoCAD \u6216\u5176\u4ed6\u7e6a\u5716\u8edf\u4ef6\n\n\u5f85\u9047 :\u6bcf\u6708$15,000 - $20,000, \u661f\u671f\u4e00\u81f3\u4e94: \u4e0a\u53489\u6642\u534a\u81f3\u4e0b\u53486\u6642\u53ca\u661f\u671f\u516d: \u4e0a\u53489\u6642\u534a\u81f3\u4e0b\u53481\u6642, \u6bcf\u9031\u5de5\u4f5c5\u5929\u534a, \u6bcf\u5929\u5de5\u4f5c 8.5 \u5c0f\u6642\n\n\u7533\u8acb\u9808\u77e5 :\u6c42\u8077\u8005\u53ef\u96fb\u90f5(Apply Now)\u5c65\u6b77\u8868\u7d66\u65b0\u85dd\u90a6\u6709\u9650\u516c\u53f8\u3002\u5982\u8981\u7d22\u53d6\u6536\u96c6\u500b\u4eba\u8cc7\u6599\u8072\u660e, \u8acb\u8207\u6731\u5c0f\u59d0(Email)\u806f\u7d61\u3002\n\n", "employment_types": ["Full Time"], "selling_points": [], "locations": ["Kwun Tong Area"], "categories": ["Banking / Finance", "Risk Management"], "post_time": "2022-01-10T03:23:52Z", "salary": {"currency": null, "max": null, "min": null, "period": "monthly", "term": null}, "salary_visible": false, "title_keywords": [], "responsibilities": [], "requirements": {"degrees": [], "majors": [], "languages": [], "language_level": [], "hard_skills": [], "soft_skills": [], "languages_combined": []}, "experience_required": {"duration": [], "field": []}}, {"job_id": "100003008922960", "location_code": "hk", "company": "Clover Aviation Capital Company Limited", "job_title": "Associate/Senior Associate, Risk Management", "description": "Duties and Responsibilities\n\nMonitor and analyse debtor (airline)\u2019s credit related matters, such as historical financial and business performance, timely prepare draft report to Risk Management Department, senior management and other relevant departments in case of debtor\u2019s credit deterioration;\nMaintain and update airlines credit rating table;\nMonitor and analyse macro economy, geopolitical risks, aviation industry, financial market and conduct deep-dive research to specific risks when required;\nMonitor the Company\u2019s operating asset;\nDraft and update Risk Management Department\u2019s relevant policies and procedures;\nPerform initial review on the assessment of the Company\u2019s operational risk, maintain risk register, and monitor the implementation status on risk mitigation strategies by relevant departments and prepare draft report to senior management;\nConduct internal control review, draft internal control review report, and monitor the mitigation actions of internal control review observations;\nOther relevant tasks assigned by the Company or Risk Management Department.\nQualifications\n\nBachelor and/or above degree in business administration, accounting, finance or other related majors.\n3+ years of risk management, business, accounting or finance experience.\nStrong analytical and logical skills;\nStrong interpersonal, verbal and written communication skills, be able to work efficiently and effectively with other stakeholders;\nClear, accurate and concise writing skills;\nFast learner, strong team player, self-motivated, detail-oriented, multi-tasking skills with strong ability of time management and be able to meet deadlines under pressure;\nroficiency in maths and knowledge in accounting;\nFamiliar with Microsoft Office Suite for financial, credit and portfolio analysis and drawing up documents;\nStrong command of written and spoken English (Japanese is not required but will be an advantage).\n*All information collected will be used for recruitment purpose only.", "employment_types": ["Full Time", "Permanent"], "selling_points": ["Maintain and update airlines credit rating table", "Monitor the operating assets of the company", "Conduct internal control review"], "locations": ["Central"], "categories": ["Banking / Finance", "Risk Management"], "post_time": "2022-01-07T10:35:22Z", "salary": {"currency": null, "max": null, "min": null, "period": "monthly", "term": null}, "salary_visible": false, "title_keywords": ["senior associate", "associate"], "responsibilities": ["administration", "management", "policies", "analysis", "review", "monitor", "procedures", "implementation", "communication", "maintain", "recruitment", "analyse", "senior management", "internal control", "report"], "requirements": {"degrees": ["degree", "bachelor"], "majors": ["finance", "accounting", "business administration"], "languages": ["japanese", "english"], "language_level": ["advantage"], "hard_skills": ["logical skills", "macro", "analysis", "airline", "writing skills", "microsoft office suite", "airlines", "internal control"], "soft_skills": ["communication skills", "self-motivated", "under pressure", "meet deadlines", "timely", "deep", "writing skills", "detail-oriented", "clear", "time management", "multi-tasking skills", "team player", "accurate", "fast learner", "interpersonal"], "languages_combined": [{"language": "japanese", "language_level": ["advantage"]}, {"language": "english", "language_level": ["advantage"]}]}, "experience_required": {"duration": ["3+ years"], "field": ["finance", "risk management", "business", "accounting"]}}, {"job_id": "100003009038928", "location_code": "hk", "company": "Contemporary Scientific Limited", "job_title": "\u6a5f\u68b0\u52a0\u5de5\u751f\u7522\u7d93\u7406", "description": "\n\u8077\u8cac :\u4e00\u822c\u6a5f\u68b0\u52a0\u5de5\u751f\u7522\u7d93\u7406\u5de5\u4f5c (\u51775\u5e74\u4ee5\u4e0a\u6a5f\u68b0\u52a0\u5de5\u751f\u7522\u7ba1\u7406\u53ca\u6a5f\u52a0\u5de5\u8eca\u9593\u7ba1\u7406\u7d93\u9a57,\u6709CNC\u6216\u6578\u63a7\u7a0b\u5f0f\u8a2d\u8a08\u64cd\u4f5c\u7d93\u9a57;\u5177\u6709\u7ba1\u7406\u751f\u7522\u73fe\u5834\u8c50\u5bcc\u7684\u5be6\u8e10\u7d93\u9a57\u548c\u5354\u8abf\u5404\u90e8\u9580\u6e9d\u901a\u8655\u4e8b\u6280\u5de7,\u719f\u6089\u6a5f\u52a0\u5de5\u8eca\u9593\u5404\u9805\u5de5\u4f5c\u6d41\u7a0b\u53ca\u64cd\u4f5c,\u638c\u63e1\u751f\u7522\u4f5c\u696d\u7ba1\u7406\u77e5\u8b58\u6280\u80fd;\u7cbe\u901a\u6a5f\u68b0\u52a0\u5de5\u5de5\u85dd\u6d41\u7a0b\u3001\u5de5\u88dd\u3001\u7a0b\u5f0f\u8a2d\u8a08\u7b49\u5c08\u696d\u77e5\u8b58;\u6a5f\u68b0\u6216\u76f8\u95dc\u5c08\u696d\u4e2d\u5c08\u6216\u4ee5\u4e0a\u5b78\u6b77)(\u9577\u99d0\u6df1\u5733)\n\n\u8cc7\u6b77 :\u5c08\u4e0a\u6559\u80b2\uff1a\u5b78\u58eb\u5b78\u4f4d; 5\u5e74\u7d93\u9a57; \u4e00\u822c\u7cb5\u8a9e; \u826f\u597d\u666e\u901a\u8a71; \u826f\u597d\u82f1\u8a9e; \u7565\u61c2\u8b80\u5beb\u4e2d\u6587; \u61c2\u8b80\u5beb\u82f1\u6587; \u57f7\u884c\u529b\u5f37\uff0c\u6709\u826f\u597d\u7684\u6e9d\u901a\u3001\u7ba1\u7406\u3001\u7d44\u7e54\u548c\u5354\u8abf\u6280\u5de7\uff0c\u80fd\u5920\u7368\u7acb\u89e3\u6c7a\u8655\u7406\u7a81\u767c\u554f\u984c, \u6709\u826f\u597d\u7684\u5718\u968a\u5408\u4f5c\u7cbe\u795e\n\n\u5f85\u9047 :\u6bcf\u6708$25,000 - $40,000, \u661f\u671f\u4e00\u81f3\u4e94: \u4e0a\u53488\u6642\u534a\u81f3\u4e0b\u53485\u664245\u5206\u53ca\u661f\u671f\u516d: \u4e0a\u53488\u6642\u534a\u81f3\u4e2d\u534812\u6642, \u6bcf\u9031\u5de5\u4f5c5\u5929\u534a\n\n\u7533\u8acb\u9808\u77e5 :\u6c42\u8077\u8005\u53ef\u96fb\u90f5(Apply Now)\u5c65\u6b77\u8868\u7d66\u73fe\u4ee3\u79d1\u7814\u6709\u9650\u516c\u53f8\u3002\u5982\u8981\u7d22\u53d6\u6536\u96c6\u500b\u4eba\u8cc7\u6599\u8072\u660e, \u8acb\u8207\u99ac\u5c0f\u59d0(Email)\u806f\u7d61\u3002\n\n", "employment_types": ["Full Time"], "selling_points": [], "locations": ["Not Specified"], "categories": ["Banking / Finance", "Risk Management"], "post_time": "2022-01-11T08:09:52Z", "salary": {"currency": null, "max": null, "min": null, "period": "monthly", "term": null}, "salary_visible": false, "title_keywords": [], "responsibilities": [], "requirements": {"degrees": [], "majors": [], "languages": [], "language_level": [], "hard_skills": [], "soft_skills": [], "languages_combined": []}, "experience_required": {"duration": [], "field": []}}, {"job_id": "100003009034998", "location_code": "hk", "company": "Asia Progress Executive Limited", "job_title": "Associate Credit Risk - Credit Department - Securities Brokerage", "description": "Our client is a Securities Brokerage. To cope with the rapid business expansion, they are now inviting high caliber candidates to join the team\n\nAssociate Credit Risk -\u00a0Credit Department - Securities Brokerage\u00a0\n\n\nJob Description\n\nTo monitor client\u2019s margin level and conduct margin calls\nAssist in gathering and analyzing market information, to help monitor the performance of credit facilities utilization to identify early signs of credit deterioration\nUpload information regarding IPOs to the Company\u2019s website\nTo prepare and update various daily and monthly credit report\n\nRequirements\n\nUniversity degree or above\nAt least 3 years in relevant working experience in securities brokerage\nStrong interpersonal skills which enable close cooperation with other departments\nAbility to work under pressure in fast-paced environment\nProficiency in written and spoken English and Chinese including Putonghua.\n\n\nPlease send full resume with\u00a0present & expected\u00a0salary to expedite sourcing\u00a0in\u00a0MS-WORD\u00a0format by clicking \u201cAPPLY NOW\u201d\n\nPlease quote our reference in your application\n\nPersonal data provided by job applicants will be used strictly in accordance with the employer\u2019s personal data policies, a copy of which will be provided upon request\n\nAll information provided will be used for recruitment purpose only", "employment_types": ["Full Time"], "selling_points": ["handle Credit Margin financing, Margin call", "Degree w/ min. 3yrs exp. in securities brokerage", "Securities Brokerage"], "locations": ["Central & Western Area"], "categories": ["Banking / Finance", "Financial Services", "Equities / Capital Markets", "Risk Management"], "post_time": "2022-01-10T05:04:06Z", "salary": {"currency": null, "max": null, "min": null, "period": "monthly", "term": null}, "salary_visible": false, "title_keywords": ["associate"], "responsibilities": ["market information", "monitor", "website", "monitor the performance", "report"], "requirements": {"degrees": ["degree or above"], "majors": [], "languages": ["putonghua", "english", "chinese"], "language_level": ["proficiency"], "hard_skills": ["ms-word"], "soft_skills": ["fast-paced environment", "interpersonal skills", "work under pressure"], "languages_combined": [{"language": "putonghua", "language_level": ["proficiency"]}, {"language": "english", "language_level": ["proficiency"]}, {"language": "chinese", "language_level": ["proficiency"]}]}, "experience_required": {"duration": ["at least 3 years"], "field": ["securities brokerage", "relevant working experience"]}}, {"job_id": "100003009035572", "location_code": "hk", "company": "Vitasoy International Holdings Ltd", "job_title": "Group Internal Audit Manager, IT", "description": "Key Responsibilities:\u00a0\nDevelop IT audit framework based on the computer environment of the Group\nInitiate, plan and execute the IT audit of the Group under the IT audit framework\nMaintain and document risks and controls based on requirements under the Sarbanes-Oxley Act\nConduct IT related internal audit assignments including IT general controls, application controls, system implementation, change management, business continuity, information security, operations and advisory projects and etc.\nIndependently evaluate system controls, document audit results, make recommendations for value efficiency and effectiveness improvement, and communicate findings to management\nMonitor and lead the review, provide guidance to peers and ensure the audit objectives are properly achieved\nPrepare comprehensive written reports to department head for review\nAssist the department in performing various departmental duties and\u00a0proactively to ensure the smooth operation of\u00a0the department\u00a0and maximize the value of department to the Group\n\nRequirements:\nUniversity graduate in Finance and Accounting, IT or related discipline\nCertified as a CPA, CIA, CISA, CISM or CISSP designation\n6+\u00a0years of internal and/or external audit experience\nExperience in manufacturing and Fast Moving Consumer Goods is an advantage\nAudit experience tin ERP system, IT security and IT operations\nAbility to work independently, provide coaching to peers and provide assistance to other team members\nStrong verbal and written communication skills in English, Cantonese and Putonghua, to effectively present to peers, auditee and management\nKnowledge in computer applications, i.e.: MS Word, Excel, Power Point, Vision, CAATs software etc.\nProblem-solving attitude and good business\u00a0acumen\u00a0\nWays to apply:\u00a0.\u00a0\nInterested parties please send your detailed resume stating your available date, current & expected salary to Human Resources Manager, by clicking the \u201cAPPLY NOW\u201d button below.\n\nAll information provided by applicants will be treated in strict confidence and used only for recruitment purposes. If you do not provide the information mentioned in the advertisement, we may not be able to assess your job application. You have the right to request access to, and correction of, your personal data held by us and you may lodge such request with our Data Protection Officer at pdpo@ vitasoy.com, but any such data access request will only be processed after the completion of the recruitment process.", "employment_types": ["Full Time", "Permanent"], "selling_points": ["Develop IT audit framework", "Initiate, plan and execute the IT audit", "Conduct IT related internal audit assignments"], "locations": ["Tuen Mun Area"], "categories": ["Accounting", "Audit", "Consulting", "Banking / Finance", "Risk Management"], "post_time": "2022-01-10T07:42:49Z", "salary": {"currency": null, "max": null, "min": null, "period": "monthly", "term": null}, "salary_visible": false, "title_keywords": ["manager"], "responsibilities": ["make recommendations", "business continuity", "management", "change management", "internal audit", "information security", "operations", "review", "monitor", "audit", "implementation", "develop", "evaluate", "maintain", "reports", "plan", "provide guidance"], "requirements": {"degrees": ["university graduate"], "majors": ["finance", "accounting", "it"], "languages": ["cantonese", "putonghua", "english"], "language_level": [], "hard_skills": ["excel", "problem-solving", "acumen", "cpa", "erp system", "power point", "ms word"], "soft_skills": ["problem-solving", "communication skills", "work independently", "business acumen"], "languages_combined": [{"language": "cantonese", "language_level": []}, {"language": "putonghua", "language_level": []}, {"language": "english", "language_level": []}]}, "experience_required": {"duration": ["6+ years"], "field": ["manufacturing", "erp system", "it", "security", "audit experience", "it operations"]}}, {"job_id": "100003009034295", "location_code": "hk", "company": "Page Personnel", "job_title": "Account Opening/KYC Analyst - MNC Brokerage", "description": "Perform KYC checking for account opening for retail & institutional clients.\nJoin a leading brokerage firm that is always expanding the business.\n\nClient Details\n\nOur client is a company that operates a digital trading platform that allows access to electronic brokering services that caters to the needs of professional and frequent traders, institutional investors, financial advisors, and introducing brokers.\n\nDescription\n\n* Correspond to inquiries and concerns externally with clients via in-person meetings, telephone, e-mail and on-line chat; internally to sales representatives and customer service representatives\n* Research and resolve a wide variety of client question/issues on the account opening process\n* Multi task with a strong emphasis on AML and KYC knowledge while dealing with incoming customer queries\n* Learn all aspects of the Brokerage platform /policy and offer alternatives and options to satisfy customer concerns while complying with policies, practices and procedures\n* Work closely with Legal and Compliance, Program Developers, and Project Managers to ensure compliance with new and existing procedures and regulatory requirements.\n\nProfile\n\n* Bachelor's degree\n* 2-3 years in Customer Service and/or Financial Service preferred. Fresh graduates who are motivated will also be considered\n* Excellent written and oral communication skills in English/Cantonese/Mandarin\n* Basic understanding of brokerage regulations and rules that govern client accounts\n* Demonstrates experience in handling client concerns and issues with tact and diplomacy\n* Ability to work independently and effectively as part of a team, while handling multiple tasks and responsibilities simultaneously\n\nJob Offer\n\n18 AL\nMedical\nMPF\nAnnual bonus\nOther MNC benefits\n\nTo apply online please click the 'Apply' button below. For a confidential discussion about this role please contact Matt O'Shaughnessy on +852 3602 2438", "employment_types": ["Full Time", "Permanent"], "selling_points": ["Join a leading MNC financial services company", "International culture", "Stable working hours"], "locations": ["Not Specified"], "categories": ["Banking / Finance", "Financial Services", "Equities / Capital Markets", "Risk Management"], "post_time": "2022-01-10T03:06:13Z", "salary": {"currency": "HKD", "max": 29999, "min": 20000, "period": "monthly", "term": null}, "salary_visible": true, "title_keywords": ["analyst"], "responsibilities": ["regulations", "aml", "mpf", "account opening", "brokerage", "policies", "procedures", "checking", "compliance", "ensure compliance", "regulatory requirements", "communication", "customer service", "kyc", "customer queries"], "requirements": {"degrees": ["degree", "bachelor"], "majors": [], "languages": ["cantonese", "english", "mandarin"], "language_level": ["excellent"], "hard_skills": ["account opening", "basic", "aml", "kyc"], "soft_skills": ["communication skills", "oral", "work independently", "multiple tasks", "motivated", "customer service"], "languages_combined": [{"language": "cantonese", "language_level": ["excellent"]}, {"language": "english", "language_level": ["excellent"]}, {"language": "mandarin", "language_level": ["excellent"]}]}, "experience_required": {"duration": [], "field": []}}, {"job_id": "100003009032628", "location_code": "hk", "company": "Hays", "job_title": "Market Risk in Risk Management Department", "description": "Market Risk Roles in Multiple Banks from Chinese and Foreign with Large Exposure\n\nYour new company\nMultiple hiring for market risk positions, covering market risk, liquidity risk and counterparty risk, in top-tier Chinese and foreign banks with large exposure.\n\nYour new role\nYou will be focusing on market risk duties, including market risk trade analysis, daily reports, market risk stress test, risk limit, etc. You will identify, measure and monitor market risk of trading book and banking book's fixed income, interest rate and FX business.\n\nWhat you'll need to succeed\n\nUniversity degree or above in Finance, Risk Management, Accounting, Financial Engineering or other related discipline\nExperience in market risk / liquidity risk / risk management, covered fixed income / interest rate / FX / related derivatives\nDetailed-minded with good organization, interpersonal and communication skills\n\n\nWhat you'll get in return\n\nMultiple levels of market risk job opportunities\nLarge exposure and competitive base salary\nOpportunity to expand your exposure in corporate banking\n\n\nWhat you need to do now\nIf you're interested in this role, click 'apply now' or for further information and a confidential discussion on this role or to find out about more opportunities in credit, contact Jane Chan at Hays on +852 2101 0050 or email jane.chan@hays.com.hk\n\nAt Hays, we value diversity and are passionate about placing people in a role where they can flourish and succeed. We actively encourage people from diverse backgrounds to apply.", "employment_types": ["Full Time", "Permanent"], "selling_points": ["Multiple levels of market risk job opportunities", "Large exposure and competitive base salary", "Opportunity to expand in corporate banking"], "locations": ["Not Specified"], "categories": ["Banking / Finance", "Corporate Banking", "Treasury", "Risk Management"], "post_time": "2022-01-07T12:00:44Z", "salary": {"currency": "HKD", "max": 54999, "min": 20000, "period": "monthly", "term": null}, "salary_visible": true, "title_keywords": [], "responsibilities": ["management", "analysis", "monitor", "communication", "contact", "banking", "daily reports"], "requirements": {"degrees": ["degree or above"], "majors": ["finance", "accounting", "engineering", "risk management"], "languages": ["chinese"], "language_level": [], "hard_skills": ["analysis"], "soft_skills": ["communication skills", "interested in", "diverse", "interpersonal", "passionate about", "detailed"], "languages_combined": [{"language": "chinese", "language_level": []}]}, "experience_required": {"duration": [], "field": ["related", "risk management", "market risk"]}}, {"job_id": "100003009038525", "location_code": "hk", "company": "MSIG Insurance (Hong Kong) Limited", "job_title": "Manager, Internal Audit", "description": "Key Responsibilities: \u00a0\n\nPlan and implement Internal Audit Strategic Plan through dedicated audit plan, audit programs and audit field work on identified risky areas\nDevelop new strategies to enhance audit efficiency and quality to achieve audit objectives and safeguard the company from risks\nMonitor and execute internal audits in accordance with the regulatory requirement, regional guidelines and company policies\nVerify and evaluate the validity and effectiveness of business performance, internal control and business management conditions\nCommunicate recommendations for improvements with different stakeholders, drive the action plans and follow up the progress of implementation of remedial actions\nCommunicate the audit findings with senior management and prepare audit reports for the Board and Audit Committee\u2019s review\nEnsure the quality of internal audit function by leading and coaching subordinates in planning and conducting audit programs and audit field work, and reviewing the audit work done by the same\n\nRequirement:\n\nDegree holder in Business/Accounting/Finance or related disciplines\nAt least 8 years of experience in internal or external audit or risk management process improvement, preferably with 3 years in managerial level in sizable insurance or financial institutions\nProfessional qualification or member of related professional bodies (such as CPA, CIA, etc.)\nMature, independent, self-motivated, detail-oriented with excellent communication skills\nStrong analytical, problem-solving, report writing and presentation skills\nExcellent command of written and spoken English and Chinese\n\nInterested parties please send full resume with current and expected salary by clicking the \"APPLY NOW\" button below.\n\nPersonal data collected will be used for recruitment purpose only and all applications will be treated in strict confidence. Unsuccessful applications will be destroyed after 12 months.", "employment_types": ["Full Time", "Permanent"], "selling_points": ["Plan and lead team to execute audit strategic plan", "Internal control improvement and risk mitigation", "Double pay/ 5-days work/ Medical/ Training subsidy"], "locations": ["Tai Koo"], "categories": ["Accounting", "Audit", "Insurance", "Others", "Banking / Finance", "Risk Management"], "post_time": "2022-01-11T07:14:26Z", "salary": {"currency": null, "max": null, "min": null, "period": "monthly", "term": null}, "salary_visible": false, "title_keywords": ["manager"], "responsibilities": ["management", "internal audit", "guidelines", "policies", "review", "quality", "audit", "monitor", "develop", "evaluate", "implementation", "planning", "reports", "plan", "audits", "plans", "senior management", "internal control"], "requirements": {"degrees": ["degree holder"], "majors": ["related disciplines", "finance", "business", "accounting"], "languages": ["english", "chinese"], "language_level": ["excellent"], "hard_skills": ["cpa", "problem-solving"], "soft_skills": ["communication skills", "self-motivated", "independent", "problem-solving", "mature", "detail-oriented", "presentation skills"], "languages_combined": [{"language": "english", "language_level": ["excellent"]}, {"language": "chinese", "language_level": ["excellent"]}]}, "experience_required": {"duration": ["at least 8 years", "3 years"], "field": ["risk management", "managerial", "audit", "financial institutions", "insurance"]}}, {"job_id": "100003009035155", "location_code": "hk", "company": "The Bank of East Asia, Limited", "job_title": "Senior Risk Manager (Credit Assessment)", "description": "Senior Risk Manager (Credit Assessment) (Job ID: 3059)\nResponsibilities\nTo be a team member of Credit Risk Management Department\nTo play a key role in the credit assessment on credit applications submitted from business units\nTo execute delegated lending authority in credit approval under the centralised risk management framework, covering Hong Kong and overseas lending portfolio\nTo assist section heads / Co-Head of Credit Risk Management Department in the identification, assessment and reporting of credit risk according to the Bank\u2019s credit policies and the prevailing regulatory requirements and HKMA\u2019s guidelines\nTo support Co-Head of Credit Risk Management Department in ad hoc projects of credit risk for the Bank Group\nTo maintain direct and regular dialogue with the business units as risk owners for adhering to established risk control guidelines, procedures and measures to identify, assess, report, mitigate and monitor the risks involved in the day-to-day work\nRequirements\nUniversity graduate or relevant professional qualification\nMinimum 8 years of experience in Banking and Finance covering the following:\nAcquaintance with the prevailing HKMA\u2019s supervisory policy manuals\nAttained \u201cProfessional Level\u201d qualification under HKMA\u2019s Enhanced Competency Framework on Credit Risk Management\nIntensive work flow exposure to assessing risks arising from lending products, that related to China would be a benefit\nHands-on exposures to ESG risk management\nOutgoing characters with communication technique with the front lines\nGood report writing and analytical skill\nGood command in both spoken and written English and Chinese\n(Candidates with less working experience will be considered for a Manager position)\n\nPlease apply online via the BEA Careers website at\u00a0https://careers.hkbea.com/psp/hcmprd/EMPLOYEE/HRMS/c/HRS_HRAM.HRS_APP_SCHJOB.GBL?Page=HRS_APP_JBPST&Action=UFOCUS=Applicant&SiteId=1&JobOpeningId=3059&PostingSeq=1 or by clicking the \"Apply Now\" button below. Kindly note that if you are a new user, you have to first create your User Profile before you can apply.\nPersonal data provided by job applicants will be used for recruitment purposes only and will be treated in accordance with the Bank's Personal Information Collection (Employees) Statement and Privacy Policy Statement. Applicants who are not invited for interviews within six weeks may consider their applications unsuccessful and the personal data collected will be destroyed after six months.", "employment_types": ["Full Time", "Permanent"], "selling_points": ["Play a key role in the credit assessment", "Execute delegated authority in credit approval", "University graduate with min. 5 yrs' exp. in bank"], "locations": ["Kwun Tong"], "categories": ["Banking / Finance", "Analyst", "Credit Analysis / Approval", "Risk Management"], "post_time": "2022-01-10T06:13:11Z", "salary": {"currency": null, "max": null, "min": null, "period": null, "term": null}, "salary_visible": false, "title_keywords": ["manager"], "responsibilities": ["reporting", "management", "control", "guidelines", "regulatory requirements", "policies", "procedures", "monitor", "maintain", "ad hoc projects", "report"], "requirements": {"degrees": ["university graduate"], "majors": [], "languages": ["english", "chinese"], "language_level": ["good command"], "hard_skills": ["hkma", "analytical skill", "c"], "soft_skills": ["outgoing", "hands-on", "analytical skill", "communication"], "languages_combined": [{"language": "english", "language_level": ["good command"]}, {"language": "chinese", "language_level": ["good command"]}]}, "experience_required": {"duration": ["minimum 8 years"], "field": ["finance", "banking"]}}, {"job_id": "100003009028969", "location_code": "hk", "company": "The Bank of East Asia, Limited", "job_title": "Credit Manager, Credit Assessment Team", "description": "Credit Manager, Credit Assessment Team (Job ID3238)\nResponsibilities\nTo be a team member of Corporate Risk & Compliance Department\nTo perform credit assessment and revision of credit applications\nTo make recommendation to resolve complex credit issues\nTo formulate credit policies\nTo ensure that all procedures are in compliance with all policies, rules, guidelines, and requirements prescribed by regulators as well as the Bank\nTo advise Relationship Managers with respect to credit policies and lending guidelines\nTo alert and report on account irregularities, breach of guidelines, and potential credit risks\nTo take up ad hoc projects and assignments when required\nRequirements\nUniversity degree, preferably major in risk management, finance or related discipline\nMinimum 3 years of experience in banking field with strong knowledge on credit risk management and analysis\nAnalytical, independent, hardworking with positive working attitude\nGood knowledge of the Bank\u2019s lending policies and standards\nGood command of both spoken and written English and Chinese. Fluent in Putonghua is preferable\nProficient with Microsoft Office application including Word and Excel\nPlease apply online via the BEA Careers website at\u00a0https://careers.hkbea.com/psp/hcmprd/EMPLOYEE/HRMS/c/HRS_HRAM.HRS_APP_SCHJOB.GBL?Page=HRS_APP_JBPST&Action=UFOCUS=Applicant&SiteId=1&JobOpeningId=3238&PostingSeq=1 or by clicking the \"Apply Now\" button below. Kindly note that if you are a new user, you have to first create your User Profile before you can apply.\nPersonal data provided by job applicants will be used for recruitment purposes only and will be treated in accordance with the Bank's Personal Information Collection (Employees) Statement and Privacy Policy Statement. Applicants who are not invited for interviews within six weeks may consider their applications unsuccessful and the personal data collected will be destroyed after six months.", "employment_types": ["Full Time"], "selling_points": ["To alert and report on account irregularities", "University degree", "Minimum 3 years of experience in banking"], "locations": ["Not Specified"], "categories": ["Banking / Finance", "Credit Analysis / Approval", "Others", "Risk Management"], "post_time": "2022-01-07T03:43:42Z", "salary": {"currency": null, "max": null, "min": null, "period": "monthly", "term": null}, "salary_visible": false, "title_keywords": ["manager"], "responsibilities": ["make recommendation", "irregularities", "credit issues", "policies", "guidelines", "compliance", "procedures", "ad hoc projects", "report"], "requirements": {"degrees": ["university degree"], "majors": ["finance", "risk management"], "languages": ["putonghua", "english", "chinese"], "language_level": ["good command", "fluent"], "hard_skills": ["excel", "microsoft office", "analysis", "word", "c"], "soft_skills": ["positive working attitude", "independent", "hardworking"], "languages_combined": [{"language": "putonghua", "language_level": ["fluent"]}, {"language": "english", "language_level": ["good command"]}, {"language": "chinese", "language_level": ["good command"]}]}, "experience_required": {"duration": ["minimum 3 years"], "field": ["management", "credit risk", "banking"]}}, {"job_id": "100003009021795", "location_code": "hk", "company": "Delken Group Limited", "job_title": "Senior Officer / Officer (Admin) (Risk Division) 5-day work", "description": "Our client is a Leading Financial Institution, they invite bright and energetic candidate for the following vacancy:\n\nResponsibilities:\n\nReporting to the Senior Vice President, the incumbent will:\n\n\n\nProvide administrative support to the SVP\nAssist in overseeing the coordination within the Risk Division; and\nAssist in monitoring and expediting the works relating to the various risk committees at the executive and board level.\nRequirements:\n\n\nTertiary educated with a minimum of 10 years' administrative experience supporting senior management in sizable organizations;\nProficient in spoken English and Cantonese;\nExcellent English writing skill a big plus; and\nGood team player.\nImmediately Available will be an advantage\u00a0\n\nInterested candidates, please send your resume (MS Word document) including employment history, present and expected salary to us.\n\nFor more jobs, please visit our website:\u00a0www.delken.com.hk.\n\n(All personal data submitted will be treated in strict confidential and used for recruitment purposes only.)", "employment_types": ["Full Time", "Permanent", "Contract"], "selling_points": ["10 years admin exp, exp in support Sr management", "Good spoken & written English", "5-day work, Medical, 15 days annual leave"], "locations": ["Central"], "categories": ["Admin & HR", "Clerical / Admin Staff", "Banking / Finance", "Order Processing & Operation / Settlement", "Risk Management"], "post_time": "2022-01-05T04:33:28Z", "salary": {"currency": null, "max": null, "min": null, "period": "monthly", "term": null}, "salary_visible": false, "title_keywords": ["senior officer", "admin", "officer"], "responsibilities": ["provide administrative support", "reporting", "monitoring", "coordination"], "requirements": {"degrees": [], "majors": [], "languages": ["cantonese", "english"], "language_level": ["excellent", "proficient"], "hard_skills": ["plus", "writing skill"], "soft_skills": ["good team player", "writing skill"], "languages_combined": [{"language": "cantonese", "language_level": ["proficient"]}, {"language": "english", "language_level": ["excellent", "proficient"]}]}, "experience_required": {"duration": ["minimum of 10 years"], "field": ["management", "administrative"]}}, {"job_id": "100003009028734", "location_code": "hk", "company": "Ambition", "job_title": "AML/KYC Associate, Cryptocurrency", "description": "Job Responsibilities\n\nConduct customer due diligence/enhanced due diligence reviews and research for clients, as part of the firm's AML/CFT Compliance program;\nAnalysis of accounts and client information according to prescribed internal control policies and procedures;\nIdentification and production of information required to satisfy Amber KYC due diligence policies and processes;\nDevelop, maintain, review and enhance AML & compliance related policies and procedures as well as proper control to ensure that the Bank's activities are in compliance with the latest regulatory requirements;\n\nRequirements\n\nBachelor's degree with major in Business Administration or related disciplines\n3-5 years' experience in undertaking AML / KYC reviews within a financial institution;\nWorking knowledge of AML, regulatory compliance and controls within the banking, financial services or fintech;\nGood understanding of AML Compliance functions including KYC/CDD.\nStrong stakeholder management skills. Strong teamwork, organizational, complex problem resolution and initiative;\nGood command of both written and spoken English and Chinese.\n\nIf this job isn't quite right for you, but you know someone who would be great at this role, why not take advantage of our referral scheme? We offer HKD1000 in Apple gift cards for every referred candidate who we place in a role. Terms & Conditions Apply. https://www.ambition.com.hk/refer-a-friend", "employment_types": ["Full Time", "Permanent"], "selling_points": ["Central working location", "Reputable firm with wide exposure", "Strong English and Chinese are preferred"], "locations": ["Not Specified"], "categories": ["Banking / Finance", "Others", "Professional Services", "Legal & Compliance", "Risk Management"], "post_time": "2022-01-07T03:01:38Z", "salary": {"currency": "HKD", "max": 54999, "min": 30000, "period": "monthly", "term": null}, "salary_visible": true, "title_keywords": ["associate"], "responsibilities": ["due diligence", "control", "aml", "due diligence reviews", "policies", "analysis", "compliance", "client information", "procedures", "review", "develop", "regulatory requirements", "customer due diligence", "maintain", "kyc", "internal control"], "requirements": {"degrees": ["degree", "bachelor"], "majors": ["related disciplines", "business administration"], "languages": ["english", "chinese"], "language_level": ["good command"], "hard_skills": ["cdd", "aml", "scheme", "kyc"], "soft_skills": ["organizational", "teamwork", "initiative"], "languages_combined": [{"language": "english", "language_level": ["good command"]}, {"language": "chinese", "language_level": ["good command"]}]}, "experience_required": {"duration": ["3-5 years"], "field": ["financial"]}}, {"job_id": "100003009025328", "location_code": "hk", "company": "Moses Wills Limited", "job_title": "Manager, Enterprise Risk Management", "description": "Our client is a Hong Kong listed group with diversified business. To code with it business strategy, the group is looking to Risk Management Manager (Executive Level) to join the group.\n\nThe Manager would be:\n\nServe as Chief Risk Officer of one of the subsidiaries of the group (G.I Business)\nBe appointed as the key person of insurance business unit\nSupervise the policy, procedure, and manual for the business units to minimize the risk level\nConduct risk analyst for new business project or investment plan\nReport to the board for the enterprise risk management\n\nOur client is expecting:\n\nDegree holder in Finance / Actuarial / Risk Management or related disciplines\nProfessional qualifications in CFA/FRM/PRM/SOA\nMinimum 5-year experience in managerial role\nKnowledge and experience in Insurance industry is preferred\nExperience in dealing with regulators and authorities\n\nOur client offers excellent career exposure with stable working culture. For interested parties, please submit updated CV with current and expected salary. Or contact Kobe Lo (+852 3952 0594) for further discussion.", "employment_types": ["Full Time"], "selling_points": ["Hong Kong listed group", "key person of Insurance Authority", "enterprise risk management"], "locations": ["Admiralty"], "categories": ["Insurance", "Actuarial", "Banking / Finance", "Risk Management"], "post_time": "2022-01-06T04:08:51Z", "salary": {"currency": null, "max": null, "min": null, "period": "monthly", "term": null}, "salary_visible": false, "title_keywords": ["manager"], "responsibilities": ["management", "insurance", "plan", "report"], "requirements": {"degrees": ["degree holder"], "majors": ["related disciplines", "finance", "risk management"], "languages": [], "language_level": [], "hard_skills": ["cfa", "code", "frm", "professional qualifications"], "soft_skills": ["stable"], "languages_combined": []}, "experience_required": {"duration": ["minimum 5-year"], "field": ["managerial", "insurance industry"]}}, {"job_id": "100003009023806", "location_code": "hk", "company": "CEB International Investment Corporation Limited", "job_title": "IT Risk Management - AVP/VP", "description": "Job Responsibilities:\n\nCreate/improve/automate market risk monitoring reports with a number of programming tools such as excel macros, Python, SQL on regular basis;\nIn charge of or working with other teams on new system implementation, testing, or overall project management\nValidate market risk models or tools for fixed incomes/equity/FX products,\u00a0 perform VaR Backtesting and help explaining the changes of risk parameters\nDevelop, review and implement an effective Operational Risk Management Framework covering methodologies, policies, guidelines and tools in line with regulatory requirements and industrial best practices\nProvide reporting to local and HQ Business, Risk and Regulatory stakeholders\n\n\u00a0Job Requirements:\n\nStrong programming skills (Python, VBA, SQL) are required. Excel skills are a must.\u00a0 Quantitative background or CFA/FRM is a plus\n5+ years of market risk experience or operational risk experience or project management experience within investment banking / securities firm are preferred\nStrong knowledge and working experience on fixed income products, market risk management or Bloomberg systems are preferred\nHighly analytical with strong technical capabilities\nProactive and versatile, with real/strong interests in global markets business and risk management\nHighly motivated and strive for excellence, with high professional standards\nAbility to work independently and under pressure\nGood command of written and spoken English and Chinese including Mandarin", "employment_types": ["Full Time", "Permanent"], "selling_points": ["Risk Mgt covering ops risk & system risk", "Experience in both IT and risk mgt", "Familiar with programming tools"], "locations": ["Central"], "categories": ["Information Technology (IT)", "Security", "Network & System", "Banking / Finance", "Risk Management"], "post_time": "2022-01-05T09:50:22Z", "salary": {"currency": null, "max": null, "min": null, "period": "monthly", "term": null}, "salary_visible": false, "title_keywords": [], "responsibilities": ["reporting", "management", "guidelines", "policies", "new system implementation", "review", "teams", "regulatory requirements", "testing", "develop", "project management", "risk monitoring", "reports"], "requirements": {"degrees": [], "majors": [], "languages": ["english", "chinese", "mandarin"], "language_level": ["good command"], "hard_skills": ["vba", "excel", "plus", "bloomberg", "cfa", "sql", "project management", "programming", "python", "frm"], "soft_skills": ["work independently", "under pressure", "versatile", "project management", "strive for excellence", "motivated", "proactive"], "languages_combined": [{"language": "english", "language_level": ["good command"]}, {"language": "chinese", "language_level": ["good command"]}, {"language": "mandarin", "language_level": ["good command"]}]}, "experience_required": {"duration": ["5+ years"], "field": ["management", "securities firm", "project management", "investment", "banking", "market risk"]}}, {"job_id": "100003009030643", "location_code": "hk", "company": "Yonxi International Finance Holdings Limited", "job_title": "Compliance Officer", "description": "Main Duties and Responsibilities\n\nReview and enhance internal control policies and procedures on an on-going basis\nDraft, review and update compliance policies, contracts and procedures\nLiaise with SFC and other regulatory organizations regarding compliance and licensing matters\nPerform KYC, compliance monitoring and investigations and implement AML and CFT program\nPrepare periodic compliance reports and conduct ad hoc assignments as assigned\n\n\u00a0Requirements\n\nDegree Holder in Law, Finance, Accounting or related disciplines\nAbility to discharge functions of compliance independently\nStrong knowledge of relevant rules and regulations issued by SFC, HKEX and other authorities\n\nBenefits\n\n5-days work (Mon-Fri)\n13-month salary compensation package commensurate on experiences\nGroup Medical\nMPF", "employment_types": ["Full Time", "Permanent"], "selling_points": [], "locations": ["Wan Chai"], "categories": ["Banking / Finance", "Financial Services", "Professional Services", "Legal & Compliance", "Risk Management"], "post_time": "2022-01-07T07:59:13Z", "salary": {"currency": null, "max": null, "min": null, "period": "monthly", "term": null}, "salary_visible": false, "title_keywords": ["compliance officer"], "responsibilities": ["aml", "policies", "contracts", "review", "procedures", "compliance", "monitoring", "reports", "ad hoc assignments", "kyc", "liaise with", "internal control"], "requirements": {"degrees": ["degree holder"], "majors": ["related disciplines", "finance", "accounting", "law"], "languages": [], "language_level": [], "hard_skills": [], "soft_skills": ["independently"], "languages_combined": []}, "experience_required": {"duration": [], "field": []}}, {"job_id": "100003009033591", "location_code": "hk", "company": "SinoMab BioScience Ltd", "job_title": "Assistant Internal Audit Manager/Senior Internal Auditor", "description": "Key Roles & Responsibilities:\n\nReporting to the Group CEO and with a dotted reporting line to the Group CFO\nUnderstand the Group\u2019s business risks and controls to perform risk assessment and audit assignments on business operations, corporate governance, listing and regulatory compliance\nCollaborate with the external auditor to determine the scope of the internal audit or review engagements.\u00a0\nProvide quality Risk Assessment and Internal Control Review Reports to the Audit Committee with recommendations which are practical and reflect the context in which the business operates\nLiaise with all levels of management on audit issues and significant risks to ensure risk mitigation\nFacilitate enhancement in company policies and procedures as well as internal control system\nPerform ad-hoc projects/duties whenever assigned\n\nRequirements:\n\nBachelor\u2019s degree in Accounting & Finance, Business Administration or related disciplines.\nHolder or finalist of professional qualification, e.g. HKICPA, ACCA, CIA or equivalent\n4 years of external audit preferably Big 4 experience and/or internal audit from listed companies.\nPreferably with working experience from Biotechnology/ Health Science / Pharmaceutical industry\nGood knowledge of internal controls across various business cycles.\nGood communication & interpersonal skills, a team player, self-motivated and independent.\nProficiency in both written and oral English and Chinese, fluency in Putonghua is a must; and\nWillingness to travel.\n\n\nWe offer\u00a05-day Work\u00a0Week, Bank Holiday,\u00a0Medical & Dental\u00a0insurance,\u00a013-Month Salary,\u00a0Promising Career Path\u00a0and\u00a0Competitive Remuneration\u00a0Package\u00a0to the right candidate. Interested parties please send your detailed resume with\u00a0current and expected salary, contact number and email address by clicking \"Apply Now\".\n(We regret only shortlisted candidates will be notified, personal data collected will be treated as confidential and for recruitment purpose only.)", "employment_types": ["Full Time"], "selling_points": ["Group level audit function", "Attractive Remuneration Package", "5-day work week, 13-month pay, medical benefits"], "locations": ["Shatin Area"], "categories": ["Accounting", "Audit", "Financial Controller", "Banking / Finance", "Risk Management"], "post_time": "2022-01-10T01:14:02Z", "salary": {"currency": null, "max": null, "min": null, "period": "monthly", "term": null}, "salary_visible": false, "title_keywords": ["manager", "internal auditor", "assistant"], "responsibilities": ["collaborate with", "reporting", "management", "internal audit", "operations", "policies", "compliance", "review", "audit", "quality", "procedures", "reports", "liaise with", "ad-hoc projects", "listing", "internal control"], "requirements": {"degrees": ["degree", "bachelor"], "majors": ["related disciplines", "finance", "accounting", "business administration"], "languages": ["putonghua", "english", "chinese"], "language_level": ["fluency", "proficiency"], "hard_skills": ["acca", "hkicpa"], "soft_skills": ["self-motivated", "oral", "independent", "communication", "interpersonal skills", "team player"], "languages_combined": [{"language": "putonghua", "language_level": ["fluency"]}, {"language": "english", "language_level": ["proficiency", "fluency"]}, {"language": "chinese", "language_level": ["proficiency", "fluency"]}]}, "experience_required": {"duration": ["4 years"], "field": ["pharmaceutical", "big 4", "audit"]}}, {"job_id": "100003009027745", "location_code": "hk", "company": "Ambition", "job_title": "VP, Operational Risk", "description": "Our client, a leading retail/corporate banking group, is expanding their headcount for a VP, Operational Risk.\n\nResponsibilities:\n\nReview policies, procedures and reports from various business units\n\nAdvise business units on operational risk and perform risk assessments\n\nConduct reviews and identify possible risk, and make timely suggestions\n\nMonitor and follow up for assignments including RCSAs, KRIs, risk profiles etc.\n\nRequirements:\n\nUniversity graduate from a related discipline\n\nExperience in banking and financial services, preferably in operational risk and/or audit\n\nExcellent command of English and Chinese\n\nContact Elaine CHU on (852) 3103 4366 or elaine.chu@ambition.com.hk / APPLY NOW by clicking the button below\n\nIf this job isn't quite right for you, but you know someone who would be great at this role, why not take advantage of our referral scheme? We offer HKD1000 in Apple gift cards for every referred candidate who we place in a role. Terms & Conditions Apply. https://www.ambition.com.hk/refer-a-friend", "employment_types": ["Full Time", "Permanent"], "selling_points": ["Regional bank with wide exposure", "Central working location", "Good work life balance"], "locations": ["Not Specified"], "categories": ["Banking / Finance", "Corporate Banking", "Retail Banking", "Risk Management"], "post_time": "2022-01-06T11:59:34Z", "salary": {"currency": "HKD", "max": 119999, "min": 70000, "period": "monthly", "term": null}, "salary_visible": true, "title_keywords": [], "responsibilities": ["policies", "review", "monitor", "procedures", "reports"], "requirements": {"degrees": ["university graduate"], "majors": [], "languages": ["english", "chinese"], "language_level": ["excellent"], "hard_skills": ["scheme"], "soft_skills": [], "languages_combined": [{"language": "english", "language_level": ["excellent"]}, {"language": "chinese", "language_level": ["excellent"]}]}, "experience_required": {"duration": [], "field": ["financial services", "audit", "banking"]}}, {"job_id": "100003009029985", "location_code": "hk", "company": "Charterhouse Partnership", "job_title": "VP, Compliance Assurance \u2013 Corporate Banking", "description": "Report to Chief Compliance Officer, the incumbent will lead a small team to establish and maintain an effective and risk-based compliance monitoring framework to identify potential or actual compliance and regulatory risks and propose recommendations in order to protect and enhance the reputation of the Bank and to avoid significant financial loss to the Bank. He/she will act as an independent guardian by planning and conducting effective, objective, risk-based compliance assurance and monitoring activities.\n\nJob Duties & Responsibilities:\n\nConduct compliance self-reviews and monitoring in accordance with the annual Compliance Action Plan and upon request by the management, including:\nDevising and updating an effective compliance self-reviews program to identify key risk areas through an effective risk assessment and conducting a risk-based monitoring activity\nExercise judgement on the reasonableness of the scope of reviews and organize work schedule to ensure effective use of resources\nManage objective compliance reviews and monitoring activities, involving self-reviews on Compliance and AML, through liaison with business stakeholders, a variety of fieldwork approaches, the production of quality deliverables for assurance and review work undertaken\nAssess whether the applicable regulatory requirements are embedded into the Bank\u2019s policies and procedures and complied with effectively\nFoster close co-operation between and develop excellent working relationships with various Risk and Compliance stakeholders, including Regulatory Compliance, Internal Audit, Business and Head Office\nKeep abreast of changes in relevant laws and regulations to the Bank, industry best practice, and changes to business activities and products, through self-managed learning and relationship with Legal & Compliance Department colleagues and business networks\nSupervise and manage the Compliance Assurance Team to ensure they perform the monitoring and self-reviews effectively and efficiently\nReview regular and ad hoc reports to the line manager, Branch management and Head Office\nManage various ad-hoc projects, initiatives and duties as assigned\n\nRequirements:\n\nDegree holder or above in related disciplines, a qualified auditor is an advantage\nMinimum 10 years\u2019 relevant experience in compliance and/or banking audit, prior team leading experience is preferred\nSound knowledge of laws and regulations applicable in banking industry\nGood interpersonal skills and leadership\nA team player with good communication, interpersonal and presentation skills\nAble to meet tight deadlines and work under pressure\nGood command of spoken and written English & Chinese\n\nIf you are interested in finding out more about this career opportunity, please email your resume to Nestor Roldan, nestor.roldan @charterhouse.com.hk\u00a0 Web: www.charterhouse.com.hk\n\nCharterhouse Partnership Hong Kong is here to assist you in your job search. Our experienced recruitment consultants will provide you with career advice and assist you to develop a tailored job search strategy.", "employment_types": ["Full Time"], "selling_points": ["Compliance Assurance management position", "A leading international corporate bank", "Relevant Exp in Compliance Assurance & Audit"], "locations": ["Not Specified"], "categories": ["Accounting", "Audit", "Banking / Finance", "Corporate Banking", "Risk Management"], "post_time": "2022-01-07T06:33:30Z", "salary": {"currency": null, "max": null, "min": null, "period": "monthly", "term": null}, "salary_visible": false, "title_keywords": [], "responsibilities": ["regulations", "internal audit", "regulatory requirements", "quality", "plan", "ad-hoc projects", "ad hoc", "compliance", "develop", "reports", "schedule", "business activities", "management", "monitoring", "review", "procedures", "aml", "bank\u2019s policies", "working relationships"], "requirements": {"degrees": ["degree holder"], "majors": ["related disciplines"], "languages": ["english", "chinese"], "language_level": ["good command"], "hard_skills": ["web"], "soft_skills": ["meet tight deadlines", "interested in", "communication", "presentation skills", "interpersonal skills", "team player", "leadership", "interpersonal", "work under pressure"], "languages_combined": [{"language": "english", "language_level": ["good command"]}, {"language": "chinese", "language_level": ["good command"]}]}, "experience_required": {"duration": ["minimum 10 years"], "field": ["compliance", "audit", "relevant experience", "banking", "team"]}}, {"job_id": "100003009027071", "location_code": "hk", "company": "PERSOLKELLY Hong Kong Limited", "job_title": "Risk Management-International Bank", "description": "PERSOLKELLY\u2019s Snapshot\n\nAn exciting opportunity to work at a reputable international trust bank. Seeking to Solid AVP/SAVP for Risk Management dept.\n\nCompany Profile\n\nOur client is a well-known international bank offers a wide range of financial services for Corporates including asset finance to international clients.\n\nExciting new role for you\n\nYou will responsible for monitoring the risk position and evaluate the performance of the branch\u2019s treasury operation to ensure compliance with Head Office limits and guidelines. It is important role for the branch operational risk control.\n\nRequirements\n\nBachelor\u2019s degree or above with major in Finance, Statistics, Mathematics, Financial Engineering, Risk Management or related disciplines, candidate with postgraduate degree is preferred\nMinimum 5 years\u2019 experience in financial industry\nCombined with a strong sense of accountability and integrity\nGood knowledge and experience in financial risk management or investment related business\nGood communication and presentation skills with good command of written & spoken English and Chinese\nStrong VBA skills are highly preferred\n\nRewards\n\nYou will work as AVP/SAVP, giving you great career exposure for Credit/Treasury Risk Management an international bank.\n\nAction Now\n\nPlease contact Yuko Okamoto via direct line +852 2971 2526\u00a0 for a confidential discussion about this role (Job#44434) and other exciting opportunities.", "employment_types": ["Full Time", "Permanent"], "selling_points": ["Risk Management", "Mathematics, Finance Statistics", "VBA"], "locations": ["Central"], "categories": ["Banking / Finance", "Risk Management"], "post_time": "2022-01-06T09:04:50Z", "salary": {"currency": null, "max": null, "min": null, "period": "monthly", "term": null}, "salary_visible": false, "title_keywords": [], "responsibilities": ["management", "control", "guidelines", "monitoring", "ensure compliance", "evaluate", "communication", "contact"], "requirements": {"degrees": ["degree", "degree or above", "bachelor"], "majors": ["risk management", "mathematics", "engineering", "finance", "statistics", "related disciplines"], "languages": ["english", "chinese"], "language_level": ["good command", "good"], "hard_skills": ["vba"], "soft_skills": ["accountability", "responsible", "integrity", "communication", "presentation skills"], "languages_combined": [{"language": "english", "language_level": ["good command", "good"]}, {"language": "chinese", "language_level": ["good command", "good"]}]}, "experience_required": {"duration": ["minimum 5 years"], "field": ["risk management", "related", "financial industry", "business", "investment", "financial"]}}, {"job_id": "100003009032376", "location_code": "hk", "company": "Welend Limited", "job_title": "Senior Operational Risk Manager", "description": "WeLab operates WeLend and WeLab Bank in Hong Kong, WeLab Digital (\u6211\u6765\u6570\u79d1), Taoxinji (\u6dd8\u65b0\u673a) and Tianmian Lab (\u5929\u5195) in Mainland China and a fintech joint venture AWDA in Indonesia. WeLab aims to bring joy to everyone\u2019s financial journey. We strive to improve people\u2019s lives by reinventing financial services through game-changing technology. We put our people first, whether it\u2019s our customers or our employees.\nWe are an energetic and passionate team that can deliver and execute. We are looking for other intellectually curious, open-minded and smart-working individuals who are just as passionate as we are about making financial services enjoyable. Now you have the opportunity to join us on our journey to achieve our vision and be part of building a better financial future for everyone.\n\nAbout you:\n\nYou're a go-getter with mad juggling skills (or multiple hats) who can thrive in a fast-paced, agile environment\nYou have a strong thirst for knowledge and are driven to find solutions that don't exist yet\nYou are comfortable with ambiguity and extremely resourceful (in your past life you could've been a detective)\nYou always find a way to get things done without sacrificing the quality of your work, integrity and values. No task is off limits for you.\nYou are humble and prioritize the success of the team over your own with an eagerness to help those around you\nYou don't shy away from challenges and have the ability to bounce back from setbacks\n\nWhat you\u2019ll do and what success looks like in this role\n\nDevelop and oversee operational risk management practices, policies, procedure, internal controls\nApply operational risk management tools to help with identifying, assessing, monitoring and controlling operational risk\nAssess and challenge the current risk control structures by noting any weaknesses, producing report to senior management and monitoring the implementation progress of the enhanced controls\nManage incident reporting including follow up on and ensure effective mitigation of incidents logged by the business and investigation of thematic issues\nReport suspicious activity by escalating and reporting the operational risk issues to the senior management of WeLend and the Group\nConduct due diligence pertaining to new products, services and insourced or outsourced activities, as well as give advice on operational risk management matters\n\nWhat is required and what we\u2019re looking for\n\nDegree holder in Finance, Economics, Business Administration, Accounting or equivalent disciplines. Holder of relevant Professional Qualification (eg. HKIB) will be an advantage\nMinimum 8 years\u2019 experience in financial industry with 5 years\u2019 experience in operational risk or fraud risk management in banking or finance industry, preferably from retail lending environment\nControl conscious with strong sense in risk awareness\nGood logical thinking and analytical skills\nAble to work independently and a good team player\nGood command of both written and spoken English and Chinese\n\nWeLab perks:\n\nCompetitive salary\nLearning and development stipend, because we value lifelong learning and believe the best way to invest in our employees is to encourage them to continue to learn\nWork hard and laugh lots (chicken wings and french toast, etc.) with a high-performing, fun and diverse team\nWeekly afternoon teas and fully stocked fridge\nCoffee stipend\nConveniently located office surrounded by diverse and delicious lunch options\nLively office with gaming consoles and a ping pong table\nFun extracurricular activities with your colleagues like hiking, yoga, badminton, wine tasting, dragon boat racing, rock climbing, etc.\nEmployee referral bonuses\n\nAwards & recognition:\n\nFinancial Times (FT) 2020 Asia-Pacific High-Growth Companies \u2013 #2 ranked company\n2020 CNBC Disruptor 50 List \u2013 #11, only company included from Hong Kong and just one of five from Asia\nWe offer competitive salary package to the successful candidate.\u00a0 If you are interested in joining this exciting team, please apply with resume via the \"Apply\" button.\nAll information provided by applicants will be used for recruitment purposes only. Information of unsuccessful applicants will be destroyed within 24 months of receipt.", "employment_types": ["Full Time", "Permanent"], "selling_points": ["5 days work for leading fintech in hk", "Oversee operational risk management practices", "Competitive salary"], "locations": ["Quarry Bay"], "categories": ["Banking / Finance", "Financial Services", "Professional Services", "Legal & Compliance", "Risk Management"], "post_time": "2022-01-07T10:57:38Z", "salary": {"currency": null, "max": null, "min": null, "period": "monthly", "term": null}, "salary_visible": false, "title_keywords": ["manager"], "responsibilities": ["administration", "reporting", "management", "control", "due diligence", "policies", "monitoring", "quality", "implementation", "investigation", "develop", "banking", "senior management", "report"], "requirements": {"degrees": ["degree holder"], "majors": ["finance", "economics", "business administration", "accounting"], "languages": ["english", "french", "chinese"], "language_level": ["good command"], "hard_skills": ["no", "joy", "agile", "fun", "analytical skills", "go", "mad"], "soft_skills": ["passionate", "work independently", "good team player", "agile", "resourceful", "open-minded", "integrity", "prioritize", "analytical skills", "diverse", "learning", "good logical thinking", "energetic", "driven"], "languages_combined": [{"language": "english", "language_level": ["good command"]}, {"language": "french", "language_level": []}, {"language": "chinese", "language_level": ["good command"]}]}, "experience_required": {"duration": ["5 years", "minimum 8 years"], "field": ["risk management", "financial industry", "banking", "finance industry", "retail"]}}, {"job_id": "100003009026048", "location_code": "hk", "company": "Bank of China (Hong Kong) Limited", "job_title": "Risk Manager/Senior Risk Manager(Integrated Risk Management Division)", "description": "Responsibilities:\n\nTo assist drafting the Group\u2019s integrated risk management report;\nTo assist drafting risk management policies;\nTo assist drafting the Group\u2019s risk management strategies and annual work plan;\nTo coordinate the consolidation of risk management information from various risk management units;\nTo coordinate implementing risk management projects;\nTo keep track of changes in macro economies, regulatory requirements and business development, analyze its impact on risk management, and propose risk management measures accordingly;\nTo assist assessing effectiveness of single type risk management and identifying management loopholes;\nTo assist establishing new types of risks, crossover risks, risks infection, risks aggregation management mechanism; coordinating crossover risks management; strengthening risks infection monitoring.\n\nRequirements:\n\nQualifications of degree or above, major in Economics, Finance, Accounting, Business & Administration or relevant professions;\nWorking experience of 5 years or above in bank with at least 2 years in risk management, such as credit risk, market risk, interest risk;\nExcellent analytical, problem solving, communication and language skills;\nFamiliar with MS Office software, such as MS Word, Excel and PowerPoint;\nExcellent Chinese and English.\n\nWe offer competitive remuneration package and comprehensive fringe benefits including medical and life insurance, and different types of allowances to the right candidate. Interested parties, please submit your application online. For details, please visit our website\u00a0http://www.bochk.com\n\nTo apply:\n\nInterested candidates, please click APPLY NOW \u00a0to apply.\n\nData collected would be used for recruitment purposes only. It might also be disclosed to our subsidiaries or Associated Companies to process the information for appointment. Applicants who do not hear from us within 8 weeks may consider their application unsuccessful and their data will be destroyed within 12 months of receipt.", "employment_types": ["Full Time"], "selling_points": ["drafting risk management policies", "drafting the Group\u2019s risk management strategies", "Working experience of 5 years or above"], "locations": ["Central"], "categories": ["Banking / Finance", "Others", "Risk Management"], "post_time": "2022-01-06T07:08:04Z", "salary": {"currency": null, "max": null, "min": null, "period": "monthly", "term": null}, "salary_visible": false, "title_keywords": ["manager"], "responsibilities": ["management", "policies", "regulatory requirements", "monitoring", "coordinate", "plan", "management report"], "requirements": {"degrees": ["degree or above"], "majors": ["business", "finance", "economics", "accounting"], "languages": ["english", "chinese"], "language_level": ["excellent"], "hard_skills": ["excel", "powerpoint", "problem solving", "ms office", "ms word"], "soft_skills": ["problem solving", "comprehensive", "communication"], "languages_combined": [{"language": "english", "language_level": ["excellent"]}, {"language": "chinese", "language_level": ["excellent"]}]}, "experience_required": {"duration": ["at least 2 years", "of 5 years"], "field": ["risk management", "market risk", "credit risk"]}}, {"job_id": "100003009028295", "location_code": "hk", "company": "Dah Sing Financial Group", "job_title": "Senior Manager, Risk Control", "description": "Job Purpose:\nTo maintain the stress testing program of the Bank and to perform the risk management functions in relation to capital management matters and interest rate risk in the banking book (IRRBB).\nMain Responsibilities:\nMaintain and execute the stress testing program and policies including the review of assumptions and methodologies; Play a central role in bank-wide stress testing such as stress tests for ICAAP, recovery planning, capital planning as well as the regulator driven stress testing;\nHandle risk-related capital management matters such as ICAAP review, recovery planning, capital triggers;\nMeasure, monitor and control the IRRBB exposures against approved risk limits and appetite; Maintain proper policies and procedures on IRRBB management;\nMaintain and develop risk reports for internal risk monitoring as well as regulatory reporting in accordance with the applicable regulatory standards and requirements;\nPerform regular and ad hoc risk analysis, simulations and reporting assigned by the Department Head and senior management including the Asset & Liability Management Committee and other risk committees.\nRequirements:\nOver 7 years\u2019 experience in the risk management of treasury, asset and liability management or finance related areas in the banking industry;\nHands-on experience in database management or statistical tools, e.g. SQL, SAS, VBA, etc.;\nUniversity degree in Finance, Risk Management or equivalent; holder of CFA or FRM an added advantage;\nGood knowledge in treasury markets, products, regulatory requirements on risk management and capital adequacy;\nGood interpersonal skills and a good team member.\nPlease note that only shortlisted candidates will be notified.", "employment_types": ["Permanent"], "selling_points": ["Maintain and execute the stress testing program", "7 years experience in the risk management", "University degree in Finance, Risk Management"], "locations": ["Wan Chai"], "categories": ["Banking / Finance", "Treasury", "Financial Services", "Risk Management"], "post_time": "2022-01-07T01:59:44Z", "salary": {"currency": null, "max": null, "min": null, "period": "monthly", "term": null}, "salary_visible": false, "title_keywords": ["senior manager"], "responsibilities": ["reporting", "management", "control", "ad hoc", "recovery planning", "policies", "review", "monitor", "procedures", "testing", "develop", "risk monitoring", "maintain", "reports", "risk analysis", "senior management", "planning"], "requirements": {"degrees": ["university degree"], "majors": ["finance", "risk management"], "languages": [], "language_level": [], "hard_skills": ["vba", "sas", "cfa", "sql", "frm"], "soft_skills": ["hands-on", "team member", "interpersonal skills"], "languages_combined": []}, "experience_required": {"duration": ["7 years"], "field": ["risk management", "management", "banking industry", "related", "finance", "database management"]}}, {"job_id": "100003009024408", "location_code": "hk", "company": "Ocean Sage Recruitment Consulting Limited", "job_title": "(Senior) Risk Manager / Compliance Manager x 2 (MNC Fund House/ Securities Firm)", "description": "Our clients are global branding\u00a0 Asset Management, Quantitative Fund House and Securities in Hong Kong.\n\nRisk Management (New Headcount)\nJob Responsibilities:\n\nDirect report to CRO in Euro.\nBased within the CRO department, responsible for the daily operations of the risk functions with Hong Kong & Singapore office.\nDaily meetings with regional PMs to discuss P&L attribution, profile risk and market color.\nManaging trading limits for Asia Pacific trading strategies.\nManaging fund level FX exposures and hedging extremely.\u00a0\nManaging desk level FX exposures and hedging exposures against the internal treasury account.\nContributing to the management of the prime broker relationship in APAC.\nSkills Requirements:\n\n5+ years experience in Financial Markets with buy-side experience.\nStrong mathematics academic background\nProficient in both SQL and Python.\nStrong team player and communication skill essential\nCompliance Role (New Headcount)\n\nJob Duty:\n\nMatured and worked independently\nSound accounting / financing / legal / audit background\nFamiliar with SFO, AMLO, HKEx and SFC rules, guidelines and code of conducts\nUnderstanding KYC, AML/CFT procedures and FATF knowledges.\nExperienced in deal with SEHK, HKFE and SFC enquires, inspection and FRR.\nProvide advice and identify compliance issues to colleagues.\nExperienced on drafting, modifying \u00a0and implementing compliance policy and manual must advantage.\nCollaborate with HR department to monitor enforcement of standards and regulations if necessary\nAdvise management on business operations relating to investment, risks and other policy development\n\n", "employment_types": ["Permanent"], "selling_points": [], "locations": ["Central"], "categories": ["Professional Services", "Legal & Compliance", "Banking / Finance", "Risk Management", "Asset Management"], "post_time": "2022-01-05T22:38:20Z", "salary": {"currency": null, "max": null, "min": null, "period": "monthly", "term": null}, "salary_visible": false, "title_keywords": ["manager", "compliance manager"], "responsibilities": ["daily operations", "management", "p&l", "report"], "requirements": {"degrees": [], "majors": [], "languages": [], "language_level": [], "hard_skills": ["aml", "sfc rules", "sql", "sehk", "cft", "kyc", "python", "code", "sfo", "frr"], "soft_skills": ["team player", "communication skill", "independently"], "languages_combined": []}, "experience_required": {"duration": ["5+ years"], "field": ["financial markets"]}}, {"job_id": "100003009021647", "location_code": "hk", "company": "BOCI-Prudential Asset Management Ltd", "job_title": "Analyst, Risk Control (ARC-075-J)", "description": "Our Risk and Compliance Department is currently looking to high caliber candidates to join\n\nResponsibilities\n\nTo develop, test and implement pre-trade and post trade compliance rules in Bloomberg and Portia system as per the investment mandate of the portfolio and regulatory requirements\nTo set up and maintain security master file, reference data and market data in internal systems and perform regular reviews of system data to ensure its accuracy\nTo participate in User Acceptance Testing (UAT) on system automation/enhancements\nTo review and carry out due diligence check on counterparts and handle KYC / AML enquiries\nTo assist in other assigned ad-hoc duties\nRequirements\n\nUniversity graduates in Risk Management, Statistics, Finance or related disciplines with 2 years\u2019 working experience in finance industry is preferred.\u00a0 Candidate with less experience may be considered for a junior level position\nExposure in asset management field with collective investment scheme experience and knowledge in SFC and MPFA regulatory requirements will be an advantage\nKnowledge in Portia, Bloomberg and VBA will be an advantage\nDetail-minded with multi-tasking capabilities, strong analytical and interpersonal skills\nGood command of both written and spoken English, Cantonese and Mandarin\n\nWe offer competitive remuneration package and comprehensive fringe benefit to the right candidates. Interested parties please submit your application by clicking \u201cApply Now\u201d OR\n\nVisit www.boci-pru.com.hk for our latest career opportunities.\n\nAll information received will be treated in strict confidential and only be used for recruitment related purpose. Applicants who are not being contacted within two months may consider their applications unsuccessful and their data will be destroyed within twelve months of receipt.\n\n\u00a0\u00a0\nResponsibility\u00a0\u00a0 *\u00a0\u00a0 Integrity\u00a0\u00a0 *\u00a0\u00a0 Teamwork\u00a0\u00a0 *\u00a0\u00a0 Performance", "employment_types": ["Full Time", "Permanent"], "selling_points": [], "locations": ["Central"], "categories": ["Banking / Finance", "Others", "Risk Management"], "post_time": "2022-01-05T04:22:30Z", "salary": {"currency": null, "max": null, "min": null, "period": "monthly", "term": null}, "salary_visible": false, "title_keywords": ["analyst"], "responsibilities": ["due diligence", "aml", "uat", "ad-hoc duties", "data", "regulatory requirements", "compliance", "review", "develop", "system data", "testing", "maintain", "kyc", "market data", "internal systems"], "requirements": {"degrees": [], "majors": [], "languages": ["cantonese", "english", "mandarin"], "language_level": ["good command"], "hard_skills": ["vba", "bloomberg", "scheme"], "soft_skills": ["detail-minded", "multi-tasking", "interpersonal skills"], "languages_combined": [{"language": "cantonese", "language_level": ["good command"]}, {"language": "english", "language_level": ["good command"]}, {"language": "mandarin", "language_level": ["good command"]}]}, "experience_required": {"duration": ["2 years"], "field": ["risk management", "related", "finance", "statistics", "investment", "finance industry", "asset management"]}}, {"job_id": "100003009027793", "location_code": "hk", "company": "Waystone Governance (HK) Limited", "job_title": "Associate - Fund Governance", "description": "Are you looking for the next step in your career?\u00a0\u00a0Do you have a desire to work in a dynamic environment? Waystone has a fantastic opportunity our on Fund Governance Team for an Associate in our Hong Kong Operations.\n\nWe are seeking an individual with strong organisational and time management skills. The right individual will have excellent communication skills with the ability to work as part of a team and build relationships with key stakeholders.\n\n\u00a0If this sounds like you, we want to hear from you!\n\nThe successful candidate will work closely with and provide support to Directors, Associate Directors of the Fund Governance Team, to ensure client service delivery across global governance product lines, collaborate on various projects within the team and take on a portfolio of clients.\n\nWaystone is a place where talented people are empowered to steer their careers towards greatness. We dare employees to become the best at what they do in a field they love. When they rise to that challenge, great business happens.\n\nESSENTIAL DUTIES AND RESPONSIBILITIES\n\nService complex portfolio of Cayman domiciled hedge funds and companies and provide support to a team of associate directors and directors.\nIndependently manage client correspondence and deliverables such as document review and execution and quality control of provided service, including a 24 hour turn around on all communications and timely saving of relevant information to client management database.\nResponsible for data integrity, accuracy, and completeness in the client management database.\nProvide appropriate materials prepared to a high standard as defined by Waystone protocols, meeting all policy and procedure expectations and timelines.\nDraft documentation based on internal templates.\nArrange client phone calls.\nAssist with common client deliverables for other business units.\nManage the Document Execution Form (\u201cDEF\u201d) workflow for board resolutions, agreements and other transactional documentation prior to director execution.\nProvide excellent customer service and independently liaise in a professional manner with fund service providers.\nDisplay understanding of onboarding required and proactively begin process when relevant new engagement is assigned.\nIdentify and explore opportunities for cross-selling Waystone products.\nBuild to maintain a full portfolio of client relationships following successful completion of training.\nTake responsibility for regulatory and risk management projects on assigned portfolio, including but not limited to:\nCompleteness of performance and investor reporting\nCompleteness of board meeting minutes for the year\nFinancial Statement/Audit reviews and regulatory filing\nImplementation of new regulatory requirements\nFund status, regulatory and service provider information in client management database (weekly, monthly & quarterly projects).\nMonitor the accounts receivable for portfolio of clients, proactively follow up and escalate when necessary.\nProvide support to the Board Support Team on the provision of board meeting services to a portfolio of clients.\nMaintain professional interaction with internal and external clients in conversation and in emails. Ensure clients are phoned when communications are being prolonged by emails and ensure appropriate phone notes are made to the system.\nWhen out of office, provide notes to Manager the day before leaving and complete the out of office checklist regarding all outstanding DEFs, upcoming meetings and any other pending matters related to client portfolio or regulatory projects.\nEvaluate risk involved with each situation and prioritize time and risk levels appropriately.\nDemonstrate understanding of the operational risk associated with Governance clients, including a complete understanding of all Policies & Procedures.\nKeep abreast of all industry developments and regulatory changes and assist in projects related to operational risk and compliance as well as be able to communicate with clients on such as well\nFoster a positive environment through open communication and willingness to work efficiently and effectively with others.\nShare key learning and knowledge lessons at team meetings.\nEngage with Associate Directors, Directors and Business Unit Leaders to further knowledge and to define and grow a career path within Waystone.\nBe able/willing to take on additional duties as and when required. Assist colleagues when capacity permits and notify Manager with availability.\n\nREQUIREMENTS\n\n\n\nTo perform this job successfully, an individual must be able to perform each essential duty satisfactorily. The requirements listed below are representative of the knowledge, skill, and/or ability required. Reasonable accommodations may be made to enable individuals with disabilities to perform the essential functions.\n\nEducation:\n\nBachelors\u2019 degree or internationally recognized professional qualification.\nExperience:\n\nMinimum of 2 \u2013 4 years\u2019 investment fund client service experience.\nA strong working knowledge of fund structures, fund documentation and regulatory requirements is required.\nMust be able to work in a fast-paced environment, including reporting and providing support to various members of a large team and diverse client portfolio complex portfolio of Cayman domiciled hedge funds and companies\nLanguage skills \u2013 Fluency in Cantonese/Mandarin", "employment_types": ["Full Time"], "selling_points": [], "locations": ["Central"], "categories": ["Banking / Finance", "Fund Management", "Risk Management", "Asset Management"], "post_time": "2022-01-07T10:36:09Z", "salary": {"currency": null, "max": null, "min": null, "period": "monthly", "term": null}, "salary_visible": false, "title_keywords": ["associate"], "responsibilities": ["liaise", "reporting", "provide support", "management", "data", "review", "professional manner", "audit", "customer service", "maintain", "quality control", "database", "documentation", "financial statement", "phone calls"], "requirements": {"degrees": ["degree"], "majors": [], "languages": ["cantonese", "mandarin"], "language_level": ["fluency"], "hard_skills": ["documentation"], "soft_skills": ["fast-paced environment", "prioritize", "communication", "diverse", "learning", "willingness to work", "positive"], "languages_combined": [{"language": "cantonese", "language_level": ["fluency"]}, {"language": "mandarin", "language_level": ["fluency"]}]}, "experience_required": {"duration": ["4 years"], "field": ["investment"]}}, {"job_id": "100003009030189", "location_code": "hk", "company": "OnePlatform Asset Management Limited", "job_title": "Senior Manager/Manager, Investment Management (Fund Distribution)", "description": "Due to our business expansion, we are looking for high calibre candidates to share our vision and venture our success.\n\nThis role will be responsible\u00a0for discretionary portfolio management, product development and management.\n\n\nResponsibilities:\n\nImplement investment strategies to manage discretionary portfolios in compliance with established investment guidelines and policies.\nCoordinate and liaise with internal and external parties to ensure the smooth operation of portfolio management.\nClosely track the funds and conduct portfolio reviews to evaluate portfolio performance.\nLead the due diligence and risk classification process for new product launch and ongoing monitoring.\nImplement and improve workflow to ensure full compliance with regulatory and internal requirements.\nCoach and develop team members to ensure quality deliverables in a timely manner.\nPerform ad-hoc assignments and projects if necessary.\n\nRequirements:\n\nBachelor\u2019s degree in finance and Risk Management or other related disciplines, with professional qualification such as CFA will be an advantage.\nSFC RO (sole) for Type 9 is a must, qualified for Type 1 and 4 will be an advantage.\nMinimum of 10 years' experience in financial industry, experience in managing investment products and distributing through multi-channels.\nHighly disciplined, strong business sense and customer driven with analytical mind.\nPossess a high level of knowledge regulatory requirements in order to protect client\u2019s investments and ensure that they are making proper decisions.\nExcellent interpersonal, communication and presentation skills.\nProficiency in computer applications such as Bloomberg, Lipper, MS-Excel, Word, and PowerPoint.\nProficient in written & spoken English and Chinese.\nCandidate with less experience will be considered as Manager role.\nWe offer competitive remuneration including career prospects to the right candidate. Interested parties please send detailed resume with availability, current and expected salaries to\u00a0Human Resources Department, OnePlatform Asset Management Limited, Trust Tower, 68 Johnston Road, Wan Chai, Hong Kong\u00a0or by clicking the\u00a0Apply Now\u00a0button and upload your CV and cover letter.\n\n(All applications will be treated in strict confidence and used for recruitment purpose within OnePlatform Asset Management Limited only. All applicants are kept on file 6 months from the date of the application.)\n\n", "employment_types": ["Full Time", "Permanent"], "selling_points": ["Implement investment strategies", "Lead the due diligence", "Coach and develop team members"], "locations": ["Wan Chai"], "categories": ["Accounting", "Financial Analyst", "Banking / Finance", "Investment", "Risk Management"], "post_time": "2022-01-07T06:56:37Z", "salary": {"currency": null, "max": null, "min": null, "period": "monthly", "term": null}, "salary_visible": false, "title_keywords": ["senior manager", "manager"], "responsibilities": ["due diligence", "management", "investment strategies", "guidelines", "policies", "ad-hoc assignments", "compliance", "internal and external parties", "monitoring", "quality", "develop", "coordinate", "evaluate", "a timely manner", "liaise with"], "requirements": {"degrees": ["degree", "bachelor"], "majors": ["related disciplines", "finance", "risk management"], "languages": ["english", "chinese"], "language_level": ["proficient"], "hard_skills": ["bloomberg", "cfa", "investment products", "word", "powerpoint", "ms-excel"], "soft_skills": ["business sense", "driven", "communication", "presentation skills", "analytical mind", "interpersonal"], "languages_combined": [{"language": "english", "language_level": ["proficient"]}, {"language": "chinese", "language_level": ["proficient"]}]}, "experience_required": {"duration": ["minimum of 10 years"], "field": ["financial industry", "investment"]}}, {"job_id": "100003009026231", "location_code": "hk", "company": "China Vered Financial Holding Corporation Limited", "job_title": "\u5206\u6790\u5458, \u98a8\u96aa\u7ba1\u7406\u90e8", "description": "\u5d17\u4f4d\u8077\u8cac\uff1a\n\n\u8ca0\u8cac\u9805\u76ee\u98a8\u96aa\u8a55\u4f30\u5de5\u4f5c\uff0c\u5305\u62ec\u5be9\u6838\u6750\u6599\u5167\u5bb9\u7684\u5b8c\u5099\u6027\u3001\u6295\u8cc7\u56de\u5831\u6e2c\u7b97\u548c\u6295\u8cc7\u76ee\u6a19\u7d93\u71df\u8ca1\u52d9\u6578\u64da\u7684\u6e96\u78ba\u6027\n\u8ca0\u8cac\u5c31\u6295\u8cc7\u9805\u76ee\u9032\u884c\u76e1\u8077\u8abf\u67e5\n\u5c31\u6295\u8cc7\u9805\u76ee\u5236\u5099\u76f8\u61c9\u7684\u98a8\u96aa\u8a55\u4f30\u5831\u544a\uff0c\u7232\u6295\u59d4\u6703\u63d0\u4f9b\u7368\u7acb\u7684\u98a8\u96aa\u8a55\u4f30\u610f\u898b\n\u8ca0\u8cac\u5236\u4f5c\u6bcf\u65e5\u3001\u6bcf\u5468\u3001\u6708\u5ea6\u53ca\u5b63\u5ea6\u7684\u5b9a\u671f\u5831\u544a\n\u5c31\u6295\u8cc7\u9805\u76ee\u7684\u9000\u51fa\u4f5c\u98a8\u96aa\u7ba1\u7406\u5de5\u4f5c\uff0c\u95dc\u6ce8\u5df2\u6295\u9805\u76ee\u7684\u8f3f\u60c5\u53ca\u8981\u7d20\u8b8a\u5316\uff0c\u8207\u9805\u76ee\u5718\u968a\u5171\u540c\u64ec\u5b9a\u5f8c\u7e8c\u7ba1\u7406\u65b9\u6848\n\n\u00a0\u4efb\u8077\u8cc7\u683c\uff1a\n\n\u6301\u6709\u98a8\u96aa\u7ba1\u7406\u3001\u6cd5\u5f8b\u3001\u91d1\u878d\u3001\u6703\u8a08\u3001\u5de5\u5546\u7ba1\u7406\u6216\u76f8\u95dc\u5c08\u696d\u672c\u79d1\u4ee5\u4e0a\u5b78\u6b77\n\u6301\u6709FRM\u3001CFA\u3001CPA \u6216\u5c08\u696d\u8cc7\u683c\u512a\u5148\n1-2\u5e74\u91d1\u878d\u884c\u696d\u76f8\u95dc\u7d93\u9a57,\u540c\u6642\u6b61\u8fce\u61c9\u5c46\u7562\u696d\u751f\u52a0\u5165\u00a0\u00a0\u00a0\n\u719f\u7df4\u4f7f\u7528Excel\u53ca\u76f8\u95dc\u7a0b\u5f0f\n\u5c0d\u65bc\u50b5\u5238\u5e02\u5834\u3001\u98a8\u96aa\u6a21\u578b\u548c\u7523\u54c1\u6709\u719f\u6089\u4e86\u89e3\n\u5177\u826f\u597d\u7684\u6e9d\u901a\u53ca\u5354\u8abf\u80fd\u529b\n\u5177\u826f\u597d\u7684\u4e2d\u82f1\u6587\u8a9e\u8a00\u53ca\u66f8\u5beb\u80fd\u529b", "employment_types": ["Full Time", "Permanent"], "selling_points": ["\u6301\u6709\u98a8\u96aa\u7ba1\u7406\u3001\u6cd5\u5f8b\u3001\u5de5\u5546\u7ba1\u7406\u7b49\u672c\u79d1\u6216\u4ee5\u4e0a\u5b78\u6b77", "1-2\u5e74\u91d1\u878d\u884c\u696d\u76f8\u95dc\u7d93\u9a57", "\u6b61\u8fce\u61c9\u5c46\u7562\u696d\u751f\u52a0\u5165"], "locations": ["Causeway Bay"], "categories": ["Banking / Finance", "Risk Management"], "post_time": "2022-01-06T07:42:14Z", "salary": {"currency": null, "max": null, "min": null, "period": "monthly", "term": null}, "salary_visible": false, "title_keywords": [], "responsibilities": [], "requirements": {"degrees": [], "majors": [], "languages": [], "language_level": [], "hard_skills": [], "soft_skills": [], "languages_combined": []}, "experience_required": {"duration": [], "field": []}}, {"job_id": "100003009031689", "location_code": "hk", "company": "Page Personnel", "job_title": "Compliance Officer - Investment Bank", "description": "Our division interprets regulatory requirements to ensure the firm is in compliance and determines how to appropriately pursue global market opportunities. Our analysts monitor regulatory trends in every jurisdiction where the firm operates and we work with regulators to manage financial market risk.\n\nClient Details\n\nThe client is a global investment bank\n\nDescription\n\nProvide advice in real time to the Investment Banking Division on compliance, regulatory, policy and reputational issues, as well as on new business initiatives and significant business changes affecting the firm.\nControls / Surveillance. Create controls and surveillances to verify adherence to laws, regulations and firm policies and procedures. Assess and determine how to mitigate risk to the firm by analyzing transactional processes used in the Investment Banking Division and reviewing the activities and actions of individual bankers.\nPolicies and Procedures. Ensure that appropriate policies and procedures are in place for the Investment Banking Division. Drive completion of updates and the creation of new policies in response to regulatory drivers, external factors and business changes while working closely with Legal and business personnel.\nRegulatory Work with the Investment Banking Division and Legal in responding to regulatory inquiries, investigations and inspections.\nTesting / Monitoring. Test and monitor controls, surveillances and procedures to assess effectiveness in ensuring adherence to laws, regulations and firm policies and procedures.\nPrepare and deliver live and online training to the Investment Banking Division population on divisional policies and procedures and relevant laws, regulations and risks.\n\nProfile\n\nBachelor's degree.\n5 years related work experience, preferably in a compliance or legal role at an investment bank, securities company or a law firm.\nHighly motivated and adaptable team player with a positive, \"can do\" attitude who enjoys working collaboratively.\nQuick learner and self-starter who can work effectively with minimal supervision.\nHighly organized, accurate and detail-oriented with sound judgment and integrity.\nExcellent interpersonal, communication and presentation skills, both written and verbal.\nStrong analytical, research and fact-gathering skills.\nAbility to work well under pressure and to multi-task effectively while adapting to new situations and a dynamic work environment.\nLegal or Compliance experience in the finance industry, including experience with exposure to Equity Capital Markets or M&A transactions.\nFluency in English and Mandarin with a strong command of speaking, reading and writing in both languages is preferred.\n\nJob Offer\n\nCompetitive package and opportunities for career growth.", "employment_types": ["Full Time", "Temporary"], "selling_points": ["International working environment", "Scope for career growth", "Competitive package"], "locations": ["Not Specified"], "categories": ["Banking / Finance", "Risk Management"], "post_time": "2022-01-07T09:39:42Z", "salary": {"currency": null, "max": null, "min": null, "period": "monthly", "term": null}, "salary_visible": false, "title_keywords": ["compliance officer"], "responsibilities": ["regulations", "business initiatives", "firm policies and procedures", "regulatory requirements", "policies", "compliance", "monitor", "procedures", "monitoring", "testing", "communication", "transactions", "provide advice", "banking"], "requirements": {"degrees": ["degree", "bachelor"], "majors": [], "languages": ["english", "mandarin"], "language_level": ["fluency"], "hard_skills": ["dynamic"], "soft_skills": ["work effectively", "organized", "under pressure", "multi-task", "adaptable", "integrity", "quick learner", "detail-oriented", "communication", "presentation skills", "motivated", "dynamic", "team player", "accurate", "interpersonal", "positive"], "languages_combined": [{"language": "english", "language_level": ["fluency"]}, {"language": "mandarin", "language_level": ["fluency"]}]}, "experience_required": {"duration": ["5 years"], "field": ["legal", "related", "compliance", "capital markets", "finance industry", "securities", "investment bank"]}}, {"job_id": "100003009030278", "location_code": "hk", "company": "Hang Seng Bank Ltd", "job_title": "Assistant Client Services Manager (Client Onboarding)", "description": "Commercial Banking \u2013 Wholesale Client Services\n\nHang Seng\u2019s Commercial Banking business provides customized one-stop financial solutions to our corporate customers, from prime small and medium-sized businesses to publicly listed companies. \u00a0\n\nFor customers conducting business locally or around the world, we offer a comprehensive range of services including corporate lending, trade and receivables finance, structured loan, cash management, investment, treasury services, insurance and e-Banking services. \u00a0As a reliable financial partner, we attend to the specific business needs of our customers and provide efficient tailor-made banking solutions through our relationship managers and dedicated specialists.\n\nWe are currently seeking a high caliber professional to join our department as\u00a0Assistant Client Services Manager.\n\n\n\nPrincipal responsibilities\n\nEngage new and existing Commercial Banking (CMB) customers in the completion of account opening requests\u00a0\nIdentify CDD requirement gap by analyzing customer information to ensure collection of sufficient information and supporting documents required for the completion of the account opening\u00a0\nMake recommendations on all client on-boarding decisions according to the sufficiency in fulfilling CDD requirements and raise exception / variance approval requests with sufficient justifications\nParticipate in account opening related process reviews and make recommendation with an aim to improve customer experience and service turnaround time\n\nRequirements\n\nUniversity degree in Business Administration or related disciplines\nMinimum of 2 years of work experience in providing high standard of customer service preferred\nKnowledge in commercial banking and Know Your Customer (KYC) regulatory requirements on corporate customers\nExperience in handling CDD review for corporate customers preferred\nGood communication and interpersonal skills\nProficiency in both spoken and written English and Chinese\nHigh level of customer centricity mindset with dedication to deliver exceptional quality services for customers\n\n(Candidate\u00a0with less experience will be considered as Client Services Officer)\n\nIf you would like to explore other opportunities at Hang Seng Hong Kong, please visit\u00a0www.hangseng.com/careers/\u00a0for details.\n\nThe health and safety of our employees and candidates is very important to us. Due to the current situation related to the Novel Coronavirus (2019-nCoV), we\u2019re leveraging our digital capabilities to ensure we can continue to recruit top talent at the HSBC Group. \u00a0As your application progresses, you may be asked to use one of our digital tools to help you through your recruitment journey. \u00a0If so, one of our Resourcing colleagues will explain how our video-interviewing technology will be used throughout the recruitment process and will be on hand to answer any questions you might have.\n\nAll information provided by applicants will be used only for recruitment purposes and will be used strictly in accordance with the Bank's personal data policies, a copy of which may be obtained by the applicant upon request. Unless otherwise instructed in writing by the applicant concerned, applicants may be considered for other suitable positions within the Bank and its related companies. The personal data of unsuccessful job applicants may be retained for a maximum of two years from the date when the job application is rejected and such data may be retained for a longer period if there is a subsisting reason that obliges the Bank to do so, after which the personal data will be destroyed.", "employment_types": ["Full Time", "Permanent"], "selling_points": [], "locations": ["Not Specified"], "categories": ["Banking / Finance", "Corporate Banking", "Others", "Risk Management"], "post_time": "2022-01-07T07:08:38Z", "salary": {"currency": null, "max": null, "min": null, "period": "monthly", "term": null}, "salary_visible": false, "title_keywords": ["client services manager", "assistant"], "responsibilities": ["make recommendations", "make recommendation", "cdd", "account opening", "banking"], "requirements": {"degrees": ["university degree"], "majors": ["related disciplines", "business administration"], "languages": ["english", "chinese"], "language_level": ["proficiency"], "hard_skills": ["cdd", "kyc", "reason", "know your customer"], "soft_skills": ["novel", "customer service", "communication and interpersonal skills"], "languages_combined": [{"language": "english", "language_level": ["proficiency"]}, {"language": "chinese", "language_level": ["proficiency"]}]}, "experience_required": {"duration": ["minimum of 2 years"], "field": ["customer service"]}}, {"job_id": "100003009021435", "location_code": "hk", "company": "BUPA Asia Limited", "job_title": "Risk and Controls Officer", "description": "\u00a0Responsibilities\n\u00a0\n\nUplift risk information across the business\u00a0which includes risk and control logs, risk appetites, emerging risks and incident capture and analysis\nSupport business areas in consistently applying and improving the RMF to identify, assess, manage, monitor and report all material risks using appropriate tools (e.g. risk registers) and at the appropriate granularity\nHelp with ensuring that an appropriate structure of governance and oversight is in place and operating effectively and to a 3LOD risk management model including; the HK Insurance business\u2019s Enterprise Risk Committee (ERC) and, where required, Boards and Regulated Entities Risk Committees\nProvide 1st line assistance, advice, guidance, oversight and challenge to the business. Assist the business in control and process development.\nEnsure that the data used by the firm to assess its risks are fit for purpose in terms of quality, quantity and breadth\nProvide risk \u201copinion\u201d on material projects, investments, initiatives or incidents as required\nDevelop, manage and refine regular risk reporting information from across HK to support effective decision making by senior executives and risk committees\nProvide risk management advice and guidance to all Hong Kong business areas\n\n\n\n\u00a0Qualifications, Training and Experience\n\n\n\n3+ years of risk management or control development experience.\n\n\nBupa offers 5 days\u2019 work per week and comprehensive remuneration packages including base salary, study assistance plan, company pension plan, life and medical benefit, dental benefit, annual leave, examination leave, etc.\n\nBupa is an equal opportunity employer and welcomes applications from qualified candidates. Information provided will be treated in strict confidence and only be used for consideration of application with Bupa.\n\nPersonal data collected will be used for recruitment purposes only. Only candidates selected for interviews will be contacted. Bupa will be in touch for any opportunities that matches your profile. All personal data of unsuccessful application will be destroyed 24 months from the date of receiving the application.", "employment_types": ["Full Time", "Permanent"], "selling_points": ["3+ years of related exp", "Uplift risk information across the business", "Provide 1st line assistance"], "locations": ["Not Specified"], "categories": ["Management", "General Management", "Insurance", "Others", "Banking / Finance", "Risk Management"], "post_time": "2022-01-05T03:57:51Z", "salary": {"currency": null, "max": null, "min": null, "period": "monthly", "term": null}, "salary_visible": false, "title_keywords": ["officer"], "responsibilities": ["guidance", "control", "management", "reporting", "data", "analysis", "monitor", "quality", "develop", "recruitment", "plan", "personal data", "insurance", "report"], "requirements": {"degrees": [], "majors": [], "languages": [], "language_level": [], "hard_skills": ["analysis"], "soft_skills": ["comprehensive", "confidence", "decision making"], "languages_combined": []}, "experience_required": {"duration": ["3+ years"], "field": ["risk management", "development", "training"]}}, {"job_id": "100003009027380", "location_code": "hk", "company": "Conners Consulting Limited", "job_title": "Market Risk or Liquidity Risk Management (Multiple bank openings 35K - 60k)", "description": "Our client are well-known and expanding commercial banks and now looking for high calibre to join their group.\n\n\u00a0Responsibilities\n\nHandle liquidity risk measurement, monitoring market / liquidity risk, PnL for Trading and Banking book, IRRBB, stress test and ALCO materials and reporting\nSupport to implement strategies over Bank\u2019s asset and liabilities, balance sheet growth and projection, with an on-going monitoring of the result\nSupport risk projects and review on market and liquidity risk policies and procedures\nContribute to the expansion and improvement of the region's funding risk assessment by in depth review and analysis\n\n\u00a0Requirements\n\nDegree holder in Finance, Risk Management, Accounting, or other quantitative discipline, preferably with professional qualification in CPA, FRM or CFA\nIn depth knowledge on the market risk or liquidity risk management\nWith minimum work experience of 2 years from banking industry\nMature, able to work independently under pressure and cooperate well with teammates\u00a0\nProficient in written and spoken English and Chinese\u00a0\n\nTo apply, please send your detailed resume to winnie[at]connersconsulting[dot]com or contact Winnie Lai at 3618 8348 for a confidential discussion.\n\nOnly shortlisted candidates will be notified.\n\nApplicants who are not contacted within two weeks may consider their applications unsuccessful.\n\nAll data collected will be used for recruitment purpose only & will be used strictly confidential.\n\nConners Consulting Limited\n2005 Kai Tak Commercial Building 317 Des Voeux Road Central Hong Kong\n\n\nTel: (852) 3996 8090\n\nWebsite: www.connersconsulting.com", "employment_types": ["Full Time", "Permanent"], "selling_points": ["Urgent with attractive remuneration", "Excellent staff welfare", "Market or Liquidity Risk Management"], "locations": ["Central & Western Area"], "categories": ["Banking / Finance", "Analyst", "Treasury", "Risk Management"], "post_time": "2022-01-06T09:51:03Z", "salary": {"currency": null, "max": null, "min": null, "period": "monthly", "term": null}, "salary_visible": false, "title_keywords": [], "responsibilities": ["reporting", "policies", "analysis", "monitoring", "measurement", "review", "procedures", "banking", "balance sheet"], "requirements": {"degrees": ["degree holder"], "majors": ["finance", "accounting", "risk management"], "languages": ["english", "chinese"], "language_level": ["proficient"], "hard_skills": ["cfa", "cpa", "frm"], "soft_skills": ["work independently", "under pressure", "mature", "detailed"], "languages_combined": [{"language": "english", "language_level": ["proficient"]}, {"language": "chinese", "language_level": ["proficient"]}]}, "experience_required": {"duration": ["of 2 years"], "field": ["banking industry"]}}, {"job_id": "100003009024131", "location_code": "hk", "company": "Shanxi Securities International Financial Holdings Limited", "job_title": "Risk Management \u2013 VP/SVP/Director", "description": "Responsibilities:\n\nReport to the Head of Risk & Compliance Department and Chief Risk Officer, overseeing the company\u2019s risk management function, ensuring that all day-to-day risk management tasks are effectively implemented\nInitiate and lead the team to perform periodic risk management policies and procedures review, periodic post-loan and post-investment projects review and other periodic tasks as required by the company and the headquarter\nBeing the first point of contact person on risk management related issues that facing the businesses covering security margin financing, futures and options, FICC, asset management, trade finance, ECM and DCM\nInitiate and lead the ad hoc projects such as risk management work procedure refinement (e.g. work automation) and other projects as required\n\nRequirements:\n\nBachelor degree or above with major in Finance, Risk Management, Accounting, Business or other relevant discipline\nCFA, FRM or other professional qualifications are an advantage\n5 years or above of solid credit risk management experience earned from brokerage firms, investment banks or financial institutions. Previous leadership experience is an advantage. Candidate with more relevant work experience will be considered a more senior title\nMust be versatile, feel confident and comfortable and in communicating and interacting with other stakeholders\nMust be able to read and write in Chinese and English\nGood command of spoken Cantonese, Mandarin and English is preferred\n\nWhat we could offer:\n\nAttractive and competitive salary packages\nGain huge exposure to different risks type and business\nCareer path development \u2013 candidate will be trained to become a capable Head of Risk / CRO in the future\nGuarantee work life balance and low-pressure working environment\n\nInterested parties please submit\u00a0your\u00a0resume to Human Resources Department (1). by post to\u00a0Unit A, 29/F., Tower 1, Admiralty Centre, 18 Harcourt Road, Admiralty,\u00a0Hong Kong; or (2). by using\u00a0\"Apply Now\"\u00a0button.\u00a0All applications will be treated in strict confidence and personal data provided by job applicants will be used for recruitment purposes only", "employment_types": ["Full Time", "Permanent"], "selling_points": [], "locations": ["Admiralty"], "categories": ["Banking / Finance", "Financial Services", "Others", "Risk Management"], "post_time": "2022-01-05T11:01:24Z", "salary": {"currency": null, "max": null, "min": null, "period": "monthly", "term": null}, "salary_visible": false, "title_keywords": ["director"], "responsibilities": ["management", "policies", "compliance", "procedures", "review", "asset management", "ad hoc projects", "contact", "report"], "requirements": {"degrees": ["degree or above", "bachelor"], "majors": ["business", "finance", "accounting", "risk management"], "languages": ["cantonese", "english", "chinese", "mandarin"], "language_level": ["good command"], "hard_skills": ["cfa", "frm", "professional qualifications"], "soft_skills": ["confident", "versatile", "leadership", "capable"], "languages_combined": [{"language": "cantonese", "language_level": ["good command"]}, {"language": "english", "language_level": ["good command"]}, {"language": "chinese", "language_level": []}, {"language": "mandarin", "language_level": ["good command"]}]}, "experience_required": {"duration": ["5 years"], "field": ["management", "investment banks", "brokerage", "financial institutions", "credit risk"]}}, {"job_id": "100003009027795", "location_code": "hk", "company": "Waystone Governance (HK) Limited", "job_title": "Associate Director - Compliance Services", "description": "Are you looking for the next step in your career?\u00a0\u00a0Do you have a desire to work in a dynamic environment? Waystone has a fantastic opportunity our on Compliance Services Team for an Associate Director in our Hong Kong Operations.\n\nThe successful candidate will work serve as an AML Compliance Officer (\u201cAMLCO\u201d), Money Laundering Reporting Officer (\u201cMLRO\u201d) and/or Deputy MLRO (\u201cDMLRO\u201d) for a diverse portfolio of Cayman Islands funds. Fund clients will include hedge funds, funds of funds, private equity funds, private credit funds and real estate funds with a broad range of investment strategies, managed by investment advisors located primarily in the Asia-Pacific region.\n\nWaystone is a place where talented people are empowered to steer their careers towards greatness. We dare employees to become the best at what they do in a field they love. When they rise to that challenge, great business happens.\n\nESSENTIAL DUTIES AND RESPONSIBILITIES\n\nTake on appointments as AMLCO, MLRO and/or DMLRO for a diverse portfolio of Cayman Islands funds.\nOversee clients\u2019 AML compliance programs, to ensure that systems and controls are developed and maintained in line with Cayman Islands\u2019 Anti-Money Laundering Regulations and relevant legislation.\nOversee regular audits of clients\u2019 AML compliance programs.\nReport periodically to clients\u2019 boards of directors on the adequacy of the AML systems and controls, including key findings and recommendations.\nMonitor the Money Laundering Reporting functions for each client.\nCommunicate with clients to resolve any potential AML issues.\nAssist in the supervision and monitoring of each Waystone employee who acts in a supporting role to the AMLCO, MLRO and/or DMLRO (with respect to performance of those roles).\nDevelop and maintain detailed knowledge of Waystone operations and the regulatory implications thereof.\nTrack laws, regulations and best practices that might affect Waystone & Waystone client services.\nProvide expert advice and assist in transformation projects and in the implementation of best practices.\nCoordinate with Waystone's internal Compliance Department and manage project tasks as appropriate as directed by the Executive Director.\nCarry out duties with minimal oversight.\nDevelop, organize, and/or deliver consistent AML compliance related training.\nManage ad hoc projects in the Cayman Compliance Services function.\nMaintain a high standard in the performance of daily duties and escalate concerns to the Executive Director on a timely basis.\n\nREQUIREMENTS\n\n\nTo perform this job successfully, an individual must be able to perform each essential duty satisfactorily. The requirements listed below are representative of the knowledge, skill, and/or ability required. Reasonable accommodations may be made to enable individuals with disabilities to perform the essential functions.\n\nEducation:\n\nAn internationally recognized professional qualification.\nExperience:\n\nMinimum of 7-10 years of relevant experience in compliance, governance, risk, financial or consulting roles in the financial services sector.\nKnowledge of the Cayman Islands AML regulatory framework would be beneficial.\nExcellent interpersonal and communication skills, both written and verbal.\nProficient in English, Mandarin and Cantonese.\nStrong leadership and organizational skills.\nPrior Cayman Islands AML compliance experience would be an asset.", "employment_types": ["Full Time"], "selling_points": [], "locations": ["Central"], "categories": ["Banking / Finance", "Fund Management", "Risk Management", "Asset Management"], "post_time": "2022-01-07T10:37:20Z", "salary": {"currency": null, "max": null, "min": null, "period": "monthly", "term": null}, "salary_visible": false, "title_keywords": ["associate director"], "responsibilities": ["regulations", "reporting", "communicate with", "aml", "operations", "compliance", "systems", "monitor", "monitoring", "relevant legislation", "develop", "expert advice", "implementation", "maintain", "coordinate with", "ad hoc projects", "audits", "report"], "requirements": {"degrees": [], "majors": [], "languages": ["cantonese", "english", "mandarin"], "language_level": ["proficient"], "hard_skills": ["aml"], "soft_skills": ["communication skills", "leadership", "interpersonal", "organizational skills"], "languages_combined": [{"language": "cantonese", "language_level": ["proficient"]}, {"language": "english", "language_level": ["proficient"]}, {"language": "mandarin", "language_level": ["proficient"]}]}, "experience_required": {"duration": ["minimum of 7-10 years"], "field": ["consulting", "compliance", "financial services", "relevant experience", "financial"]}}, {"job_id": "100003009027390", "location_code": "hk", "company": "Guosen Securities (HK) Financial Holdings Company, Limited", "job_title": "Risk Management Officer", "description": "Responsibilities:\n\nWork closely with business units to identify, assess, monitor and control operational risk\nConduct reviews to identify possible operational risks and provide recommendations to address the control weakness; monitor the implementation progress of the enhanced controls\nConduct due diligence pertaining to new products/ services as well as insourced/ outsourced activities, give advice on operational risk management matters\nWork closely with business/ support units to effectively manage operational risk in accordance with legal, regulatory and internal requirements\nProvide training on operational risk management\nAsset management pre trade and post trade compliance checking\nTo perform ad hoc projects as required\n\nRequirements:\n\nDegree or above with major in Finance, Economics, Information system or other related discipline\n3 years\u2019 work experience in operational risk or related areas\nFamiliar with the operations of securities firm\nKnowledge / Experience in Information Technology operations would be advantages\nAttention to details, good analytical and interpersonal skills\nGood command of written and spoken English and Chinese, fluency in Putonghua\n\n\nAttractive remuneration will be offered to the right candidate.\u00a0 Interested parties please email your full resume with present & expected salary and date of availability to hrm @guosen.com.hk or via \"Apply Now\".\n\nPersonal data collected would be used for recruitment purpose only.", "employment_types": ["Full Time", "Permanent"], "selling_points": ["Manage operational risk & review policy", "Familiar with the operations of securities firm", "Familiar with the operations of IT"], "locations": ["Central & Western Area"], "categories": ["Banking / Finance", "Financial Services", "Information Technology (IT)", "IT Auditing", "Risk Management"], "post_time": "2022-01-06T10:04:37Z", "salary": {"currency": null, "max": null, "min": null, "period": "monthly", "term": null}, "salary_visible": false, "title_keywords": ["risk management officer"], "responsibilities": ["provide training", "due diligence", "control", "management", "compliance", "monitor", "implementation", "checking", "provide recommendations", "ad hoc projects", "asset management"], "requirements": {"degrees": ["degree or above"], "majors": ["finance", "economics"], "languages": ["putonghua", "english", "chinese"], "language_level": ["fluency", "good command"], "hard_skills": ["information system"], "soft_skills": ["interpersonal skills", "attention to details"], "languages_combined": [{"language": "putonghua", "language_level": ["fluency", "good command"]}, {"language": "english", "language_level": ["fluency", "good command"]}, {"language": "chinese", "language_level": ["fluency", "good command"]}]}, "experience_required": {"duration": ["3 years"], "field": ["related", "information technology"]}}, {"job_id": "100003009028749", "location_code": "hk", "company": "Bank of China (Hong Kong) Limited", "job_title": "Senior Credit Risk Manager/ Credit Risk Manager (Credit Model Management)", "description": "Responsibility\nSupport the pioneer use of Fin-tech (including Big Data, Machine Learning & Artificial Intelligence, etc.) in credit risk management area\nDevelop and maintain internal credit risk models\nPerform model related data analyses and MIS\nCoordinate with users on model related enquiries and trainings\nResponsible for user requirements and acceptance tests on model settings and rating system workflow\nFollow the latest development and compliance requirements from regulators on Fin-tech and Basel related areas\nRequirements:\nBachelor degree holder or above in Mathematics, Statistics, Actuarial, Fin-tech or data science related disciplines, preferably with CFA/FRM qualifications\nMinimum 8 years\u2019 experience in credit risk modeling or at least 3 years in advanced Fin-tech areas on credit risk management or business development of any financial institutes. Candidate with less relevant experience may apply for Deputy Manager/Manager\nGood analytical and communication skills\nIndependent, proactive and able to work under pressure\nGood command of written and spoken Chinese and English. Fluent Mandarin will be an advantage\nProficiency in Python/R and SAS", "employment_types": ["Permanent"], "selling_points": ["Risk Manager", "Banking", "Credit Model"], "locations": ["Central"], "categories": ["Banking / Finance", "Risk Management"], "post_time": "2022-01-07T03:04:43Z", "salary": {"currency": null, "max": null, "min": null, "period": "monthly", "term": null}, "salary_visible": false, "title_keywords": ["model", "manager"], "responsibilities": ["management", "data", "compliance", "big data", "coordinate with", "develop", "maintain"], "requirements": {"degrees": ["bachelor degree holder"], "majors": ["related disciplines", "mathematics", "statistics", "data science"], "languages": ["english", "chinese", "mandarin"], "language_level": ["advantage", "good command", "fluent"], "hard_skills": ["sas", "cfa", "python", "r", "frm"], "soft_skills": ["communication skills", "independent", "advanced", "proactive", "work under pressure"], "languages_combined": [{"language": "english", "language_level": ["good command"]}, {"language": "chinese", "language_level": ["good command"]}, {"language": "mandarin", "language_level": ["fluent", "advantage"]}]}, "experience_required": {"duration": ["at least 3 years", "minimum 8 years"], "field": ["management", "tech", "business development", "relevant experience", "credit risk", "financial"]}}]