[{"job_id": "100003009053292", "location_code": "hk", "company": "Sinochem Hong Kong (Group) Company Limited", "job_title": "Corporate Finance \u2013 Treasury specialist \u8cc7\u91d1\u5c08\u54e1", "description": "Responsibilities:\n\n\u00a0Cash operation planning, payment processing and closing balance analysis\n\u00a0Perform Daily analysis of cash pool operation results, and solicit new customers to\u00a0 \u00a0join cash pool, and meet the savings target\n\u00a0Handle various ad hoc projects.\nRequirements:\n\n\u00a0Degree holder in Finance / Accounting or related disciplines\n\u00a0At least 3 years of finance experience\n\u00a0Strong analytical and co-ordination skills\n\u00a0Proficient in MS Excel, MS Word and MS PowerPoint\n\u00a0Good command of spoken and written English, Chinese and Mandarin\n\u00a0Good knowledge of corporate treasury function and cash pooling\n\u00a0Independent, outgoing, well-organized, detail and result-oriented person\nSalary:\n\n\n20k~28k with double pay, bonus\n\nBenefits & Others:\n5 days work week\nMedical Insurance coverage\nO.T. allowance", "employment_types": ["Full Time"], "selling_points": [], "locations": ["Wan Chai"], "categories": ["Accounting", "Treasurer", "Banking / Finance", "Corporate Finance", "Treasury"], "post_time": "2022-01-17T07:24:52Z", "salary": {"currency": null, "max": null, "min": null, "period": "monthly", "term": null}, "salary_visible": false, "title_keywords": ["specialist", "corporate finance"], "responsibilities": ["payment", "analysis", "ad hoc projects", "planning"], "requirements": {"degrees": ["degree holder"], "majors": ["related disciplines", "finance", "accounting"], "languages": ["english", "chinese", "mandarin"], "language_level": ["good command"], "hard_skills": ["ms powerpoint", "ms excel", "ms word"], "soft_skills": ["outgoing", "result-oriented", "independent", "well-organized"], "languages_combined": [{"language": "english", "language_level": ["good command"]}, {"language": "chinese", "language_level": ["good command"]}, {"language": "mandarin", "language_level": ["good command"]}]}, "experience_required": {"duration": ["at least 3 years"], "field": ["finance"]}}, {"job_id": "100003009052473", "location_code": "hk", "company": "Hong Kong Huafa Investment Holdings Limited", "job_title": "Treasury/ Finance Manager \u8cc7\u91d1\u7ba1\u7406\u7d93\u7406", "description": "Hong Kong Huafa Investment Holdings Ltd. is a key platform for Huafa Group to reach out to the overseas market. Representing Huafa Group, Hong Kong Huafa is responsible for overseas investments, cross-border lending and listings of core assets. To meet the demands of growing business, we are now seeking a high-caliber finance professional to join our Treasury Team, this position will support all treasury operation activities for the Hong Kong Huafa and subsidiaries of Huafa Group.\n\nJob Duties\n\nDevelop and maintain networks and collaborative partnerships with financial institutions\nExplore and identify potential business opportunities, including but not limited to, corporate lending, structured transactions, syndications, treasury, trade financing and other financial products\nPrepare and review documentation in relation to bank accounts management and financing activities\nManage cash flow and budgeting with accurate forecasting\nPerform ad hoc duties as assigned\nRequirements\n\nBachelor degree or above in Business Administration, Finance, Accounting or a related discipline\nAt least 3 years' experience in corporate lending\nProficient in both spoken and written English and Chinese, Putonghua is preferred\nAbility to work independently and be able to work under pressure, with good communication, interpersonal and analytical skills\nCandidate with more experience will be considered as Manager/ Senior Manager\n\u5de5\u4f5c\u8077\u8cac\n\n\u8207\u91d1\u878d\u6a5f\u69cb\u7dad\u6301\u826f\u597d\u7684\u5408\u4f5c\u95dc\u4fc2\n\u63a2\u7d22\u4f01\u696d\u8cb8\u6b3e\u3001\u7d50\u69cb\u6027\u4ea4\u6613\u3001\u8cc7\u91d1\u7ba1\u7406\u3001\u8cbf\u6613\u878d\u8cc7\u3001\u5176\u4ed6\u91d1\u878d\u7522\u54c1\u7b49\u7684\u5546\u696d\u6a5f\u6703\n\u6e96\u5099\u53ca\u8986\u6838\u9280\u884c\u53ca\u878d\u8cc7\u6d3b\u52d5\u76f8\u95dc\u6587\u4ef6\n\u5354\u52a9\u73fe\u91d1\u6d41\u91cf\u9810\u6e2c\u53ca\u8ca1\u52d9\u9810\u7b97\u7684\u7ba1\u7406\n\u5b8c\u6210\u4e0a\u53f8\u4ea4\u8fa6\u7684\u5176\u4ed6\u5de5\u4f5c\u53ca\u9805\u76ee\n\u4efb\u8077\u8981\u6c42\n\n\u5927\u5b78\u672c\u79d1\u6216\u4ee5\u4e0a\u5b78\u6b77\uff0c\u4fee\u8b80\u5de5\u5546\u7ba1\u7406\u3001\u91d1\u878d\u3001\u6703\u8a08\u6216\u76f8\u95dc\u5c08\u696d\u7562\u696d\n\u81f3\u5c113\u5e74\u7684\u516c\u53f8\u8cb8\u6b3e\u76f8\u95dc\u5de5\u4f5c\u7d93\u9a57\n\u7cbe\u901a\u4e2d\u82f1\u6587\u53e3\u8a9e\u548c\u66f8\u5beb\uff0c\u719f\u6089\u666e\u901a\u8a71\u8005\u5c07\u7372\u512a\u5148\u8003\u616e\n\u5177\u826f\u597d\u7684\u5206\u6790\u80fd\u529b\u3001\u7368\u7acb\u5de5\u4f5c\u80fd\u529b\u3001\u4eba\u969b\u6e9d\u901a\u80fd\u529b\uff0c\u80fd\u7368\u7acb\u5de5\u4f5c\uff0c\u4e26\u627f\u53d7\u58d3\u529b\n\u5177\u8f03\u9ad8\u8cc7\u6b77\u7684\u7533\u8acb\u4eba\u53ef\u7372\u8003\u616e\u8058\u7528\u70ba\u7d93\u7406\uff0f\u9ad8\u7d1a\u7d93\u7406\n\nWe offer attractive remuneration package to the right candidates, including year-end double pay, discretionary bonus, allowances, group medical insurance, annual health check, and etc. Interested parties please apply directly by clicking \"Apply Now\".", "employment_types": ["Full Time", "Permanent"], "selling_points": ["Candidates with strong treasury exposure preferred", "At least 3 years' experience in corporate lending", "Nurturing professional in treasury team"], "locations": ["Central"], "categories": ["Accounting", "Finance / Accounting Manager", "Banking / Finance", "Loan", "Treasury"], "post_time": "2022-01-17T03:07:22Z", "salary": {"currency": null, "max": null, "min": null, "period": "monthly", "term": null}, "salary_visible": false, "title_keywords": ["finance manager"], "responsibilities": ["ad hoc duties", "management", "budgeting", "business opportunities", "review", "transactions", "develop", "cash flow", "maintain", "documentation", "forecasting"], "requirements": {"degrees": ["degree or above", "bachelor"], "majors": ["finance", "accounting", "business administration"], "languages": ["putonghua", "english", "chinese"], "language_level": ["proficient"], "hard_skills": ["analytical skills"], "soft_skills": ["work independently", "analytical skills", "communication", "interpersonal", "work under pressure"], "languages_combined": [{"language": "putonghua", "language_level": ["proficient"]}, {"language": "english", "language_level": ["proficient"]}, {"language": "chinese", "language_level": ["proficient"]}]}, "experience_required": {"duration": ["at least 3 years"], "field": []}}, {"job_id": "100003009052495", "location_code": "hk", "company": "China Development Bank Hong Kong Branch", "job_title": "Treasury Associate (Money Markets)   \u8cc7\u91d1\u4ea4\u6613", "description": "Department: Treasury Department\nResponsibilities\n\nResponsible for short-term financing activities at the branch.\nManages inter-bank lending /borrowing/ FX Swap and repo within the pre-determined risk profile.\nAdministers / assists liquidity management. \u00a0Daily cash flow and liquidity monitoring and to ensure all risk indicators are in compliance with internal limit and regulatory requirements.\nConducts analysis and research on money markets and FX swap market. Executes trading within the pre-determined risk profile.\nMaintains close relationship with industry peers, facilitates inter-bank co-operations and transactions, and understands market movement.\nEnsures up-to-date documentation of all activities and procedures.\nKeeps abreast of developments in short-term financing, and ensures timely notification of relevant parties on changes impacting the strategies and operations of the branch.\n\nRequirements\n\nBachelor degree or above in Finance or related disciplines\nMinimum \u00a03-5 years money market experience in banks or financial institutions\nStrong understanding of Treasury operations, policies and practices\nFamiliar with short-term financing and money market products\nExperience in inter-bank relationship management\nProficiency in spoken and written in English and Chinese (Putonghua and Cantonese)\n\n\n\u5de5\u4f5c\u8077\u8cac:\n\n\u8ca8\u5e63\u5e02\u5834\u3001\u5916\u532f\u5e02\u5834\u5206\u6790\u8207\u7814\u7a76\n\u5916\u532f\u5e02\u5834\u4ea4\u6613\n.\u5b58\u6b3e\u5831\u50f9\n.\u6d41\u52d5\u6027\u7ba1\u7406\u76f8\u95dc\u7684\u62c6\u501f\u3001\u56de\u8cfc\u4ea4\u6613\n.\u8ca0\u8cac\u7dad\u8b77\u8207\u91d1\u878d\u540c\u696d\u9593\u7684\u5408\u4f5c\u95dc\u4fc2\n\u4efb\u8077\u8005\u8981\u6c42:\n\u5177\u5099\u7d93\u6fdf\u5b78\u3001\u91d1\u878d\u5b78\u6216\u76f8\u95dc\u5b78\u79d1\u672c\u79d1\u6216\u4ee5\u4e0a\u5b78\u6b77\n\u5177\u5099\u81f3\u5c11-3-5 \u5e74\u9280\u884c\u6216\u91d1\u878d\u6a5f\u69cb\u8cc7\u672c\u5e02\u5834\u76f8\u95dc\u7d93\u9a57\n\u5177\u5099\u5168\u9762\u7684\u91d1\u878d\u53ca\u9280\u884c\u9593\u5e02\u5834\u77e5\u8b58\uff0c\u719f\u6089\u53c3\u8207\u5e02\u5834\u7684\u91d1\u878d\u6a5f\u69cb\n\u5c0d\u5e02\u5834\u98a8\u96aa\u6709\u9ad8\u5ea6\u7684\u654f\u611f\u6027\uff0c\u5224\u65b7\u548c\u628a\u63e1\u5e02\u5834\u7684\u80fd\u529b\u8f03\u5f37\n\u719f\u6089\u570b\u969b\u8cc7\u672c\u8207\u5916\u532f\u5e02\u5834", "employment_types": ["Full Time", "Permanent"], "selling_points": ["Bachelor degree", "Minimum  3-5 years money market experience", "Suite 3307-3315, One IFC, No.1 Harbour View Street"], "locations": ["Central"], "categories": ["Banking / Finance", "Analyst", "Treasury", "Equities / Capital Markets"], "post_time": "2022-01-17T03:55:38Z", "salary": {"currency": null, "max": null, "min": null, "period": "monthly", "term": null}, "salary_visible": false, "title_keywords": ["associate"], "responsibilities": ["management", "regulatory requirements", "analysis", "compliance", "monitoring", "operations", "transactions", "procedures", "cash flow", "documentation"], "requirements": {"degrees": ["degree or above", "bachelor"], "majors": ["related disciplines", "finance"], "languages": ["cantonese", "putonghua", "english", "chinese"], "language_level": ["proficiency"], "hard_skills": [], "soft_skills": [], "languages_combined": [{"language": "cantonese", "language_level": ["proficiency"]}, {"language": "putonghua", "language_level": ["proficiency"]}, {"language": "english", "language_level": ["proficiency"]}, {"language": "chinese", "language_level": ["proficiency"]}]}, "experience_required": {"duration": ["3-5 years"], "field": ["financial institutions", "management"]}}, {"job_id": "100003009054349", "location_code": "hk", "company": "Industrial Bank Co., Ltd.", "job_title": "Treasury Sales  - FX/Fixed Income", "description": "Responsibilities\n\nResponsible for sales & marketing on FX/Fixed income products, include cash bond, FX, structure deposit, repo, credit derivatives etc.\nResponsible for client onboarding and managing a portfolio of a wide array of institutional clients including banks, security firms, asset managers, insurance companies etc. and development new clients for the bank.\nProvide fixed income trading advice, quote price and execute transactions for mainly financial institutional clients (both bank and non-bank FI).\nRequirements :\n\nBachelor Degree in Finance, Economics or relevant disciplines.\nMinimum\u00a02 year relevant experience with thorough understanding of the flow of Treasury and working experience in FX/Fixed income market.\nFamiliar with onshore and offshore China Bond market, familiar with Bond Connect business will be a plus.\nHolder of\u00a0 licenses for Type 1 and/ or 4 regulated activities.\nSelf-initiative and a good team player.\nExperience on conducting financial institutional client onboard process will be a plus.\nFluent in English and Mandarin is a must, Cantonese will be a plus.\nCandidate with more experience will be considered as Senior role.\n\nPlease enclose full C.V. with\u00a0present and expected salary\u00a0to the Head of Human Resources, Industrial Bank Co., Ltd. Hong Kong Branch, 12/F, One International Finance Centre, 1 Harbour View Street, Central, Hong Kong\u00a0or apply directly by clicking \u201cApply Now\u201d.\n\nPersonal data provided by job applicants will be used for recruitment purpose only. Applicants who are not contacted within 8 weeks may consider their applications unsuccessful. All data of unsuccessful applicants will be destroyed in 1 year.", "employment_types": ["Full Time"], "selling_points": ["Responsible for sales & marketing  FX/Fixed income", "Minimum 2 year relevant experience", "Client onboarding and managing portfolio"], "locations": ["Central"], "categories": ["Banking / Finance", "Corporate Banking", "Investment", "Treasury"], "post_time": "2022-01-17T09:13:43Z", "salary": {"currency": null, "max": null, "min": null, "period": "monthly", "term": null}, "salary_visible": false, "title_keywords": ["sales"], "responsibilities": ["insurance", "transactions"], "requirements": {"degrees": ["degree", "bachelor"], "majors": ["finance", "economics"], "languages": ["cantonese", "english", "mandarin"], "language_level": ["fluent"], "hard_skills": ["plus", "c", "harbour"], "soft_skills": ["good team player", "self-initiative", "thorough"], "languages_combined": [{"language": "cantonese", "language_level": []}, {"language": "english", "language_level": ["fluent"]}, {"language": "mandarin", "language_level": ["fluent"]}]}, "experience_required": {"duration": ["minimum 2 year"], "field": ["relevant experience", "financial"]}}, {"job_id": "100003009052712", "location_code": "hk", "company": "Atom International Technology Limited", "job_title": "Accountant / Accounting Officer", "description": "Job Highlights\ndaily accounting\npayment\naudit\nJob Description\n\nResponsibilities\u00a0include:\n\nPerform daily accounting duties, including data entries and preparation of vouchers for receipt, payment and general journals transactions\nLiaise with audit team, clients & IRD\nPrepare annual statutory filing (including renewal, tax filing and others)\nInvolve in marketing campaign regarding accounting service crossover with other brands and partners.\nEnsure timely and accurate financial reporting\nHandle other adhoc tasks and administrative work as required\n\nUltimately, you will help our Accounting department run smoothly, ensuring transparency and efficiency in all transactions.\n\nRequirements\n\nAs a minimum you will have a Diploma or above in Accounting or related disciplines and Proficient in English, Mandarin and Cantonese.\n2 years or above of work experience in accounting is preferred.\nKnowledge of modern accounting software is essential. Knowledge in XERO is distinct advantage\nFamiliarity with finance regulations\nStrong organization skills\nAbility to handle sensitive, confidential information\nA final pre-requisite is that you be based in Hong Kong with valid working visa", "employment_types": ["Full Time"], "selling_points": ["Accounting", "Finance", "Assurance"], "locations": ["North Point"], "categories": ["Accounting", "Accountant", "Accounting Clerk / Supervisor", "Banking / Finance", "Treasury"], "post_time": "2022-01-17T03:46:58Z", "salary": {"currency": null, "max": null, "min": null, "period": "monthly", "term": null}, "salary_visible": false, "title_keywords": ["accountant", "accounting officer"], "responsibilities": ["administrative work", "data", "tax filing", "accounting service", "audit", "transactions", "payment", "financial reporting", "liaise with", "daily accounting"], "requirements": {"degrees": ["diploma or above"], "majors": ["related disciplines", "accounting"], "languages": ["cantonese", "english", "mandarin"], "language_level": ["proficient"], "hard_skills": ["accounting software", "xero"], "soft_skills": ["organization skills", "sensitive"], "languages_combined": [{"language": "cantonese", "language_level": ["proficient"]}, {"language": "english", "language_level": ["proficient"]}, {"language": "mandarin", "language_level": ["proficient"]}]}, "experience_required": {"duration": ["2 years"], "field": ["accounting"]}}, {"job_id": "100003009051050", "location_code": "hk", "company": "The Wharf Group", "job_title": "Treasury Operation Officer", "description": "Responsibilities :\n\nResponsible for coordinating with banks on daily funding arrangement, payment settlement for various transactions, loan administration and related documentation, deposit placement, inter-company transfer transactions, and preparation of treasury reports.\u00a0 \u00a0\u00a0\n\n\nRequirements :\nDegree holders in related disciplines with 5 years\u2019 relevant experience preferably acquired from large corporations or banks.\u00a0 Possessing good communication, interpersonal, analytical and problem-solving skills; self-motivated, well organized, detail-minded, proficient in English and Chinese and having advanced knowledge of Microsoft Word and Excel.\u00a0\nCandidates with less experience may be considered as Assistant Treasury Operation Officer.\n\n\nWe work 5 days per week.\n\n\nInterested parties, please click \"APPLY NOW\" and attach with your application letter and full resume.\n\n\nFor further information of the Wharf Group, please visit our website: www.wharfholdings.com", "employment_types": ["Full Time", "Permanent"], "selling_points": [], "locations": ["Tsim Sha Tsui"], "categories": ["Banking / Finance", "Loan", "Treasury", "Fund Management"], "post_time": "2022-01-15T19:11:47Z", "salary": {"currency": null, "max": null, "min": null, "period": null, "term": null}, "salary_visible": false, "title_keywords": ["operation officer"], "responsibilities": ["related documentation", "transactions", "payment", "reports", "administration"], "requirements": {"degrees": ["degree"], "majors": ["related disciplines"], "languages": ["english", "chinese"], "language_level": ["proficient"], "hard_skills": ["problem-solving skills", "microsoft word", "excel"], "soft_skills": ["detail-minded", "self-motivated", "advanced", "well organized", "communication", "problem-solving skills", "interpersonal"], "languages_combined": [{"language": "english", "language_level": ["proficient"]}, {"language": "chinese", "language_level": ["proficient"]}]}, "experience_required": {"duration": ["5 years"], "field": ["related", "operation", "relevant experience"]}}, {"job_id": "100003009053005", "location_code": "hk", "company": "Aston Carter", "job_title": "Treasury Product Manager, Retail Banking", "description": "Responsibilities:\n\n\nImplement business strategy and manage the execution to drive the Bank\u2019s treasury business to meet financial commitments.\nConduct portfolio analysis including currency portfolio movement, customer behavior and revenue trend to identify incremental business opportunities.\nFormulate effective marketing strategies to maintain competitiveness in the market.\nParticipate in new product development project as required to continuously enhance end-to-end client experience.\nDevelop competent system platform to ensure smooth execution at all sales channels.\nDesign sales processes and ensure proper operation control and governance.\nConduct on-going training to support product/system launch.\nLiaise with Marketing and Digital teams to optimize customer outreach to target audience including prospect and existing clients to maintain market competitiveness.\nCoordinate with internal stakeholders including Legal, Compliance, Control and Risk to ensure end-to-end process compliance with internal and external regulatory requirements\n\n\nQualifications:\n\n\nUniversity degree holder, preferably in Business Management, Finance or relevant discipline.\nMinimum 5 years experience in banking industry, preferably in investment or FX product management. Candidate with less experience could be considered for a junior role.\nExcellent product knowledge in deposits and FX products with strong sense in forex markets. Prior experience in selling FX products would be an added advantage.\nHands-on project management experience in system platform development and user scenario testing would be essential for this role.\nGood understanding in market practices as well as regulatory requirements.\nPossess can-do attitude and ability to work with people at all levels.\nSelf-motivated and able to work independently. Able to perform under pressure. Supervisory experience would be an added advantage.\nExcellent communication, presentation and problem solving skills are required.\nExcellent command of written and spoken English and Chinese\nInterested one please send you updated CV to cherry.lai@astoncarter. com", "employment_types": ["Full Time", "Permanent"], "selling_points": ["Treasury  / FX", "Banking", "Business Strategy"], "locations": ["Not Specified"], "categories": ["Banking / Finance", "Retail Banking", "Treasury", "Wealth Management"], "post_time": "2022-01-17T04:58:45Z", "salary": {"currency": null, "max": null, "min": null, "period": "monthly", "term": null}, "salary_visible": false, "title_keywords": ["product manager"], "responsibilities": ["control", "management", "marketing strategies", "regulatory requirements", "analysis", "business opportunities", "teams", "coordinate with", "design", "develop", "compliance", "project management", "testing", "maintain", "communication", "banking", "liaise with"], "requirements": {"degrees": ["university degree"], "majors": ["finance", "business"], "languages": ["english", "chinese"], "language_level": ["excellent"], "hard_skills": ["business management", "project management", "analysis", "problem solving skills"], "soft_skills": ["self-motivated", "work independently", "under pressure", "can-do attitude", "competent", "communication", "project management", "hands-on", "smooth", "problem solving skills", "presentation"], "languages_combined": [{"language": "english", "language_level": ["excellent"]}, {"language": "chinese", "language_level": ["excellent"]}]}, "experience_required": {"duration": ["minimum 5 years"], "field": ["banking industry", "development", "testing", "product management", "project management", "investment", "supervisory experience", "product development"]}}, {"job_id": "100003009043723", "location_code": "hk", "company": "BDO Financial Services Limited", "job_title": "Finance Manager, Treasury and Cash Management", "description": "Requirements:\n\n\nBachelor\u2019s degree in banking, finance, accounting or related disciplines preferred\nMinimum 10 years\u2019 relevant experience in treasury or settlement in banking and/or sizable organizations.\nSensitive to numbers and with good interpersonal skills\nProven English proficiency, fluency in Putonghua preferred\nFamiliar with PC software e.g. MS Word, Excel, PowerPoint\n\nResponsibilities:\n\n\nTake charge of money market and assist in other treasury functions\nEnsure timely settlement of capital market transactions and liaison with treasury team for PRC operations\nCo-ordinate cashflow monitoring & follow-up on execution of syndicated loans, bilateral loans, bonds\nPrepare reports for management review\n\nGood remuneration and attractive fringe benefits will be offered to the successful applicant. Interested parties please apply with full resume, present and expected salary, available date by clicking \"Apply Now\".\n\nWe are an equal opportunity employer and welcome applications from all qualified candidates. All personal data collected will be used for recruitment purpose only.\u00a0 Applicants not hearing from us within 3 months may consider their applications unsuccessful.\u00a0 All personal data collected will be destroyed within 24 months.", "employment_types": ["Full Time", "Permanent"], "selling_points": ["Digital Transformation", "Cashflow management", "Attractive Remuneration"], "locations": ["Not Specified"], "categories": ["Accounting", "Accountant", "Banking / Finance", "Treasury", "Professional Services", "Business Analysis / Data Analysis"], "post_time": "2022-01-13T01:40:25Z", "salary": {"currency": null, "max": null, "min": null, "period": "monthly", "term": null}, "salary_visible": false, "title_keywords": ["finance manager", "cash management"], "responsibilities": ["operations", "monitoring", "transactions", "management review", "prepare reports", "timely settlement"], "requirements": {"degrees": ["degree", "bachelor"], "majors": ["related disciplines", "finance", "accounting"], "languages": ["putonghua", "english"], "language_level": ["fluency", "proficiency"], "hard_skills": ["powerpoint", "pc", "excel", "ms word"], "soft_skills": ["sensitive to numbers", "interpersonal skills"], "languages_combined": [{"language": "putonghua", "language_level": ["fluency"]}, {"language": "english", "language_level": ["proficiency"]}]}, "experience_required": {"duration": ["minimum 10 years"], "field": ["relevant experience", "banking"]}}, {"job_id": "100003009046397", "location_code": "hk", "company": "Wheelock Properties (Hong Kong) Ltd", "job_title": "Manager \u2013 Banking (Treasury)", "description": "Our client is a HK listed company with businesses across HK, China and overseas.\u00a0 As a result of a team expansion plan, a rare opportunity has arisen for a capable Treasury Manager to support their daily finance operations.\n\n\nResponsibilities\u200b\n\nLeading a team to ensure smooth cashflow to meet daily cash requirement of the company and monthly inter-company settlement\nPrepare treasury reporting package for management review\u00a0\u00a0\nCompile weekly/monthly cash-flow forecasting\u00a0\nEnsure sound internal control is in place throughout the payment process\nParticipate in finance digital transformation and process re-engineering for cash management, cheque payment and other treasury related matters\nInvolved in loans negotiation, loan documentation, loan drawdown and on-going loan compliance\n\nRequirements\n\nA qualified accountant and a degree holder in Finance, Accounting or other related disciplines\u00a0\nAt least 8-10 years of treasury operations experience in a sizable firm\nSolid experience in finance/treasury system, e-payment platforms and automation improvement for the treasury function\nProficiency in accounting systems such as SUN, SAP, Oracle\nA good team player and able to work independently\nGood interpersonal and communication skills\nGood written and spoken English and Chinese\n\nInterested parties please send your application with full career history, current and expected salary by clicking Apply Now button. Applications will be treated in strict confidence. Personal data collected will be used for recruitment purposes only.", "employment_types": ["Full Time", "Permanent"], "selling_points": [], "locations": ["Central"], "categories": ["Banking / Finance", "Corporate Banking", "Corporate Finance", "Treasury"], "post_time": "2022-01-13T18:55:19Z", "salary": {"currency": null, "max": null, "min": null, "period": null, "term": null}, "salary_visible": false, "title_keywords": ["manager"], "responsibilities": ["loan compliance", "reporting", "management", "re-engineering", "payment", "payment process", "documentation", "forecasting", "management review", "internal control"], "requirements": {"degrees": ["degree holder"], "majors": ["related disciplines", "finance", "accounting"], "languages": ["english", "chinese"], "language_level": ["good"], "hard_skills": ["accounting systems", "sap", "oracle"], "soft_skills": ["communication skills", "good team player", "interpersonal", "work independently"], "languages_combined": [{"language": "english", "language_level": ["good"]}, {"language": "chinese", "language_level": ["good"]}]}, "experience_required": {"duration": ["at least 8-10 years"], "field": ["finance"]}}, {"job_id": "100003009053897", "location_code": "hk", "company": "Hang Seng Bank Ltd", "job_title": "Senior Treasury Solution Dealer II", "description": "Responsibilities:\n\n\nManage corporate cashflow, financing position and portfolio risks with the aim of avoiding over-concentration and minimize financing cost\nEnsure fund availability for business development needs\nUpdate regularly treasury report to facilitate management\u2019s discussion and decision making\nOversee corporate treasury function to ensure error-free operation\nPublish peers analysis, marketing tracking dashboard and market intelligence to keep management updated on market activities and trend\nRequirements:\n\nBachelor or Master Degree holder in accounting, business, finance or legal discipline\nMinimum 12 years solid experience on corporate financing and securities analysis\nProfessional qualification such as CPA or CFA is preferred\nGood knowledge in listing rules, company law and other relevant rules and\u00a0 regulations\nOutgoing, dynamic, analytical and detail-minded and capable of meeting tight schedules and working under pressure with minimal supervision\nExcellent presentation, communication and interpersonal skill with good numeric and business sense\nAdvanced level in Microsoft PowerPoint and Excel for financial analysis\nProficiency in both written and spoken English and Chinese\n\nWe offer ample opportunities for career development and attractive salary package commensurate with experience and qualifications. \u00a0Interested parties please apply with full resume via\u00a0\u201cAPPLY NOW\u201d.\u00a0\n\nFor further information on Wheelock Properties (Hong Kong) Limited, please visit our website: www.wheelockpropertieshk.com\n\nWe are an equal opportunities employer and invite applications from all qualified candidates. Personal data collected will be treated in strict confidence and handled by authorized persons for recruitment-related purposes only within the Wheelock & Wharf Group.\u00a0 Applicants not hearing from us within two months may consider their applications unsuccessful.", "employment_types": ["Full Time", "Permanent"], "selling_points": [], "locations": ["Not Specified"], "categories": ["Banking / Finance", "Treasury", "Asset Management"], "post_time": "2022-01-17T07:43:05Z", "salary": {"currency": null, "max": null, "min": null, "period": "monthly", "term": null}, "salary_visible": false, "title_keywords": ["dealer"], "responsibilities": ["cost", "management", "analysis", "report", "tracking"], "requirements": {"degrees": ["bachelor", "master degree"], "majors": ["business", "finance", "accounting"], "languages": ["english", "chinese"], "language_level": ["proficiency"], "hard_skills": ["excel", "cfa", "analysis", "microsoft powerpoint", "financial analysis", "cpa", "dynamic"], "soft_skills": ["outgoing", "detail-minded", "under pressure", "capable", "advanced", "business sense", "interpersonal skill", "communication", "dynamic", "presentation"], "languages_combined": [{"language": "english", "language_level": ["proficiency"]}, {"language": "chinese", "language_level": ["proficiency"]}]}, "experience_required": {"duration": ["minimum 12 years"], "field": ["securities", "financing"]}}, {"job_id": "100003009047367", "location_code": "hk", "company": "Nameson Industrial Ltd", "job_title": "Assistant Manager / Senior Accounting Officer (Treasury)", "description": "Global Banking and Markets \u2013 Global Markets\n\nHang Seng's Global Markets business provides superior service, fully integrated solutions and 24-hour global markets coverage. Our support framework is substantial. Our advanced technologies deliver quick access to key markets. Our capital strength allows us to tailor competitively-priced solutions for specific client business around the world. We provide a full spectrum of treasury services to our customers, including foreign exchange, interest rate risk management, derivatives products, capital markets instruments, as well as market intelligence on global trends and key developments.\n\nWe are currently seeking a high caliber professional to join our department as\u00a0Senior Treasury Solution Dealer II.\n\u00a0\u00a0\n\nPrincipal responsibilities\n\nServe and provide treasury solutions / products to the Bank\u2019s client with focus on corporate clients;\nIndentify sales opportunities or initiatives that address clients\u2019 need;\nMaintain business relationships with clients in assigned area of responsibility;\nSupport the Head of Treasury Solution on business initiatives;\nCollaborate with internal stakeholders, including Relationship Managers and other product groups to maximise cross-selling opportunities for the Bank;\nDealing of treasury vanilla products and structure derivatives\nRequirements\nUniversity degree holder;\nMinimum of five\u00a0years\u2019 working experience as treasury sales with strong connection of corporate clients;\nStrong treasury product knowledge especially in FX and interest rate derivatives;\nStrong communication and interpersonal skills;\nCreative, with growth mindset and highly adaptable to changes and transformation;\nProficiency in both English and Chinese, fluency in Putonghua an advantage;\nHigh level of customer centricity mindset with dedication to deliver exceptional quality services for customers\n\nIf you would like to explore other opportunities at Hang Seng Hong Kong, please\u00a0visit\u00a0www.hangseng.com/careers/\u00a0for details.\n\nThe health and safety of our employees and candidates is very important to us. Due to the current situation related to the Novel Coronavirus (2019-nCoV), we\u2019re leveraging our digital capabilities to ensure we can continue to recruit top talent at the HSBC Group. \u00a0As your application progresses, you may be asked to use one of our digital tools to help you through your recruitment journey.\u00a0 If so, one of our Resourcing colleagues will explain how our video-interviewing technology will be used throughout the recruitment process and will be on hand to answer any questions you might have.\u00a0\n\nAll information provided by applicants will be used only for recruitment purposes and will be used strictly in accordance with the Bank's personal data policies, a copy of which may be obtained by the applicant upon request. Unless otherwise instructed in writing by the applicant concerned, applicants may be considered for other suitable positions within the Bank and its related companies. The personal data of unsuccessful job applicants may be retained for a maximum of two years from the date when the job application is rejected and such data may be retained for a longer period if there is a subsisting reason that obliges the Bank to do so, after which the personal data will be destroyed.", "employment_types": ["Full Time", "Permanent"], "selling_points": [], "locations": ["Tai Po Area"], "categories": ["Accounting", "Accounting Clerk / Supervisor", "Others", "Banking / Finance", "Treasury"], "post_time": "2022-01-14T02:55:01Z", "salary": {"currency": null, "max": null, "min": null, "period": "monthly", "term": null}, "salary_visible": false, "title_keywords": ["assistant manager", "senior accounting officer"], "responsibilities": ["business initiatives", "maintain", "collaborate with"], "requirements": {"degrees": ["university degree"], "majors": [], "languages": ["putonghua", "english", "chinese"], "language_level": ["fluency", "advantage", "proficiency"], "hard_skills": ["reason"], "soft_skills": ["adaptable", "novel", "communication and interpersonal skills", "creative"], "languages_combined": [{"language": "putonghua", "language_level": ["fluency"]}, {"language": "english", "language_level": ["proficiency", "fluency", "advantage"]}, {"language": "chinese", "language_level": ["proficiency", "fluency", "advantage"]}]}, "experience_required": {"duration": ["minimum of five years"], "field": []}}, {"job_id": "100003009049383", "location_code": "hk", "company": "Shanghai Commercial Bank Ltd", "job_title": "Officer, Treasury Settlement", "description": "Job Responsibilities:\n\nCarry out daily treasury operations, including loan administration\nExecuting inter-account transactions and cash pooling\nCoordinate with banks for funding arrangements\nPrepare treasury reports, bank account opening and closing documents\nMonitor cash flow and prepare funding plans\nHandle ad-hoc duties as assigned\n\n\nJob Requirements:\n\nBachelor degree in Accounting or Finance\nPrevious working experience in bank operations or treasury function is an advantage\n3 to 5 treasury or account related working experience\nDetail-minded, hands-on and able to be multi-task\nHands-on computer applications, e.g., Word, Excel, Access & PowerPoint\nGood command of spoken and written English, Chinese and Mandarin\nImmediately available will be an advantage\nWork in Tai Po\n\n\nInterested parties please e-mail by clicking \"Apply Now\" for application details. (Personal data collected will be used for recruitment purpose only.)", "employment_types": ["Full Time", "Permanent"], "selling_points": ["Process settlement payments and receipts", "Perform user acceptance test (UAT)", "Performing daily settlement of all transactions"], "locations": ["Kwai Hing"], "categories": ["Banking / Finance", "Treasury", "Others", "Order Processing & Operation / Settlement"], "post_time": "2022-01-15T03:50:21Z", "salary": {"currency": null, "max": null, "min": null, "period": "monthly", "term": null}, "salary_visible": false, "title_keywords": ["officer"], "responsibilities": ["operations", "account opening", "coordinate with", "monitor", "transactions", "cash flow", "executing", "reports", "ad-hoc duties", "plans", "administration"], "requirements": {"degrees": ["degree", "bachelor"], "majors": ["finance", "accounting"], "languages": ["english", "chinese", "mandarin"], "language_level": ["good command"], "hard_skills": ["excel", "word", "powerpoint"], "soft_skills": ["detail-minded", "hands-on", "multi-task"], "languages_combined": [{"language": "english", "language_level": ["good command"]}, {"language": "chinese", "language_level": ["good command"]}, {"language": "mandarin", "language_level": ["good command"]}]}, "experience_required": {"duration": [], "field": ["related"]}}, {"job_id": "100003009047248", "location_code": "hk", "company": "JPMorgan Chase Bank, N.A.", "job_title": "Treasury and Chief Investment Office - Treasury Funding - Vice President", "description": "Job\n\nLead and monitor the settlement support operation, review the operation to enhance work quality and efficiency to reduce settlement and repayment risk\nEnsure compliance of internal policies and procedures and statutory requirements\n\n\u00a0Requirements\n\nDegree or above in Business Administration, Banking, Finance, Economics, Accounting or related disciplines\nAt least 5 years\u2019 working experience in settlement operation, FX operations, remittance and funds transfer and with 2 years in managerial position\nFamiliar with inward/outward remittance and Anti-money laundering requirements\nHigh integrity and initiative, good team-player, meticulous and able to work independently\nGood PC skills and proficient in English and Cantonese (Putonghua is an advantage)\n\nWe offer attractive remuneration and benefits, comprehensive career development opportunities and 5-day week to the qualified candidate.\n\nInterested parties please send detailed resume including current salary and expected salary to:\u00a0HR Dept, 25/F, Two Exchange Square, 8 Connaught Place, Central, HK\n\nAll personal information provided by applicants will be treated in strict confidence and used solely for recruitment purpose.\u00a0 All information of unsuccessful candidates will be destroyed within 12 months from the date of this advertisement.", "employment_types": ["Full Time"], "selling_points": [], "locations": ["Not Specified"], "categories": ["Banking / Finance", "Investment", "Treasury", "Management", "General Management"], "post_time": "2022-01-14T02:39:33Z", "salary": {"currency": null, "max": null, "min": null, "period": "monthly", "term": null}, "salary_visible": false, "title_keywords": ["vice president"], "responsibilities": ["policies", "operations", "review", "monitor", "procedures", "ensure compliance", "statutory requirements", "work quality", "banking", "administration"], "requirements": {"degrees": ["degree or above"], "majors": ["business administration", "finance", "economics", "related disciplines", "accounting"], "languages": ["cantonese", "putonghua", "english"], "language_level": ["advantage", "proficient", "good"], "hard_skills": ["pc skills", "anti-money laundering"], "soft_skills": ["meticulous", "work independently", "team-player", "integrity", "initiative"], "languages_combined": [{"language": "cantonese", "language_level": ["proficient", "good"]}, {"language": "putonghua", "language_level": ["advantage", "proficient", "good"]}, {"language": "english", "language_level": ["proficient", "good"]}]}, "experience_required": {"duration": ["2 years", "at least 5 years"], "field": ["managerial", "operation"]}}, {"job_id": "100003009054607", "location_code": "hk", "company": "Asia Progress Executive Limited", "job_title": "Associate, Fixed Income Trader - PRC Securities Brokerage firm", "description": "J.P. Morgan is a global leader in financial services, providing strategic advice and products to the world's most prominent corporations, governments, wealthy individuals and institutional investors. Our first-class business in a first-class way approach to serving clients drives everything we do. We strive to build trusted, long-term partnerships to help our clients achieve their business objectives.\n\nTreasury manages the firm's capital, balance sheet, structural interest rate risk, liquidity and daily funding positions.\n\nThe candidate will be based in Hong Kong and will report to the Hong Kong Treasurer. Focus will be primarily on JPMCB Hong Kong and related entities in Hong Kong.\n\nRoles & Responsibilities\n\nManage daily funding positions for the branch and related entities in Hong Kong\nManage liquidity to ensure compliance with both regulatory and internal liquidity ratios and limits.\nManage Banking book Interest Rate Risk and Market Risk within assigned limits\nDaily pricing and publishing of FTP Rates on Loans and Deposits\nPerform daily HIBOR submission\nDaily P&L estimation\nAssist the Treasurer on ad-hoc front-office projects/ business initiatives such as cashflow/balance sheet analysis, systems implementation testing, etc.\nQualifications\n\nPrevious working experience in Treasury/ALM role is preferred\nHigh levels of self-motivation\nStrong attention to detail\nStrong communication and interpersonal skills\nWe recognize that our people are our strength and the diverse talents they bring to our global workforce are directly linked to our success. We are an equal opportunity employer and place a high value on diversity and inclusion at our company. We do not discriminate on the basis of any protected attribute, including race, religion, color, national origin, gender, sexual orientation, gender identity, gender expression, age, marital or veteran status, pregnancy or disability, or any other basis protected under applicable law. In accordance with applicable law, we make reasonable accommodations for applicants' and employees' religious practices and beliefs, as well as any mental health or physical disability needs.\n\nInterested parties please click \u201cApply Now\u201d to apply job.\n\nAll applications applied through our system will be delivered directly to the advertiser and privacy of personal data of the applicant will be ensured with security.", "employment_types": ["Full Time"], "selling_points": ["Responsible for fixed income trading for DCM Team", "Deg 3yrs fixed income trader / equity products", "Familiar w/ fixed income and equity markets"], "locations": ["Central & Western Area"], "categories": ["Banking / Finance", "Treasury", "Dealing & Trading", "Equities / Capital Markets"], "post_time": "2022-01-17T10:13:58Z", "salary": {"currency": null, "max": null, "min": null, "period": "monthly", "term": null}, "salary_visible": false, "title_keywords": ["associate"], "responsibilities": ["ad-hoc", "business initiatives", "balance sheet", "analysis", "systems", "implementation", "p&l", "ensure compliance", "testing", "communication", "banking", "report"], "requirements": {"degrees": [], "majors": [], "languages": [], "language_level": [], "hard_skills": ["make", "focus", "analysis"], "soft_skills": ["first-class", "diverse", "communication and interpersonal skills", "self-motivation", "attention to detail", "focus"], "languages_combined": []}, "experience_required": {"duration": [], "field": []}}, {"job_id": "100003009051027", "location_code": "hk", "company": "The Wharf Group", "job_title": "Treasury (Banking) Manager", "description": "Our client is PRC\u00a0Top Tier Chinese Investment Bank/ Securities Brokerage . \u00a0To cope with the rapid business expansion, they are now inviting high caliber candidates to join the team\n\nAssociate, Fixed Income Trader - PRC Securities Brokerage firm\u00a0\n\nJob Responsibilities\n\nBe responsible for fixed income\u00a0trading for client accounts\nWork as part of the DCM team to provide real-time market\u00a0colour,\u00a0identify\u00a0investment opportunities, and implement effective trades\u00a0derive profits\n\u00a0Assist in client marketing and day to day client communication\nMaintain and develop new trading instruments and other relevant\u00a0products to enhance investment returns\n\nRequirements:\n\n\u00a0Degree holder in Finance, business or any similar field\n\u00a0 3 - 5 years of relevant trading experience in fixed income or equity\n\u00a0 Familiar with the fixed income and equity markets ecosystem\n\u00a0 Solid understanding of investment products and trading strategies\n\u00a0 Ability to work accurately under stress;\n\u00a0 Fast learner, proactive and quick reaction to market changes\n\u00a0 Proficiency in written and spoken English and Chinese including Putonghua.\n\nPlease send full resume with\u00a0present & expected\u00a0salary to expedite sourcing\u00a0in\u00a0MS-WORD\u00a0format by clicking \u201cAPPLY NOW\u201d\n\nPlease quote our reference in your application\n\nPersonal data provided by job applicants will be used strictly in accordance with the employer\u2019s personal data policies, a copy of which will be provided upon request\n\nAll information provided will be used for recruitment purpose only", "employment_types": ["Full Time", "Permanent"], "selling_points": [], "locations": ["Tsim Sha Tsui"], "categories": ["Accounting", "Treasurer", "Banking / Finance", "Corporate Finance", "Treasury"], "post_time": "2022-01-15T01:17:13Z", "salary": {"currency": null, "max": null, "min": null, "period": null, "term": null}, "salary_visible": false, "title_keywords": ["manager"], "responsibilities": ["communication", "maintain", "investment returns", "develop"], "requirements": {"degrees": ["degree holder"], "majors": ["finance", "business"], "languages": ["putonghua", "english", "chinese"], "language_level": ["proficiency"], "hard_skills": ["ms-word", "investment products"], "soft_skills": ["proactive", "fast learner"], "languages_combined": [{"language": "putonghua", "language_level": ["proficiency"]}, {"language": "english", "language_level": ["proficiency"]}, {"language": "chinese", "language_level": ["proficiency"]}]}, "experience_required": {"duration": ["3 - 5 years"], "field": ["trading"]}}, {"job_id": "100003009045785", "location_code": "hk", "company": "Resource Solutions Consulting Hong Kong Limited", "job_title": "Project Manager - Treasury Operations (12-month Contract)", "description": "Responsibilities\u00a0:\n\nArranging bank loans and bonds issuance\nResponsible for banking liaison, agreement negotiation, and completing documentation for bank loan, bond, MTN program update and ISDA documents\nPreparing regular and ad hoc reports and analysis for management review\nAanlyzing market data and recommend solutions for risk management or cost saving\n\nRequirements :\n\nBachelor Degree in accounting, finance or related disciplines; CPA is preferred\nMinimum 7 years solid experience in corporate financing or banking\nProactive, analytical and detail-minded with good communication and interpersonal skills\nGood business sense and problem-solving skills\nAble to work under pressure and meet tight deadlines\nProficiency in MS Excel, Word and PowerPoint\nProficiency in English and Chinese\n\n\nWe work 5 days per week.\n\n\nInterested parties, please click \"APPLY NOW\" and attach with your application letter and full resume.\n\n\nFor further information of the Wharf Group, please visit our website: www.wharfholdings.com", "employment_types": ["Full Time", "Temporary", "Contract"], "selling_points": ["Treasury Operations", "Opportunity to work in Global Bank", "Global scope of project"], "locations": ["Quarry Bay"], "categories": ["Banking / Finance", "Treasury"], "post_time": "2022-01-13T08:40:57Z", "salary": {"currency": null, "max": null, "min": null, "period": "monthly", "term": null}, "salary_visible": false, "title_keywords": ["project manager", "operations"], "responsibilities": ["management", "cost", "ad hoc", "analysis", "reports", "banking", "documentation", "market data", "management review"], "requirements": {"degrees": ["degree", "bachelor"], "majors": ["related disciplines", "finance", "accounting"], "languages": ["english", "chinese"], "language_level": ["proficiency"], "hard_skills": ["word", "powerpoint", "cpa", "ms excel", "problem-solving skills"], "soft_skills": ["detail-minded", "meet tight deadlines", "business sense", "communication and interpersonal skills", "problem-solving skills", "proactive", "work under pressure"], "languages_combined": [{"language": "english", "language_level": ["proficiency"]}, {"language": "chinese", "language_level": ["proficiency"]}]}, "experience_required": {"duration": ["minimum 7 years"], "field": ["financing", "banking"]}}, {"job_id": "100003009044619", "location_code": "hk", "company": "The Hong Kong Mortgage Corporation Limited", "job_title": "Associate (Treasury Operations)", "description": "About Our Client\n\nOur client is a prestigious international bank with a long history of providing corporate banking solutions to businesses and to large local companies, financial institutions and multinationals. We look for talented, tenacious individuals who are hungry to progress and eager to grow their knowledge.\n\nResponsibilities\n\nProject Management\n\nAssist in formulation and regular review of Project and tracking project progress.\nFollow up project tasks related to operations sector includes coordinate meetings & workshops, documentations, UAT plan & execution with designated departments in accordance to project timeline and report progress to supervisor.\nCoordinate with Branch Operations to align with Updated Global Operations Policy.\nTo perform BAU coverage on Branch Operations upon required.\nContribute to process improvements while abiding to control guidelines on day-to-day process.\nMinimizing operational failure, including but not exclusively, the risk of fraud, by helping to devise, and by implementing, sufficient regular controls\nEnsuring appropriate escalation to management and/or Permanent Control (or Compliance as appropriate) as soon as an issue is identified.\nContribute to the implementation of operational permanent control policies and procedures in day\u0002-to-day business activities, such as Control Plan.\nComply with regulatory requirements and internal guidelines. \u2022 Direct contribution to operational permanent control framework.\n\nRequired Skills/Experience\n\n\n3-5 years of relevant experience in Project Management\n3+ years working experience in Treasury Operation will be an advantage\nStrong product knowledge (FXMM/Rate/Bonds) products & operations process\u00a0\nStrong analytical and strong risk sense, able to work under pressure\nExcellent communication skills in English and Chinese\nValues and Diversity\n\nDynamic working gives everyone at our client the opportunity to integrate professional and personal lives, if you have a need for flexibility then please discuss this with the hiring manager. They are an equal opportunity employer and are opposed to discrimination on any grounds. It is the policy of our client to ensure equal employment opportunity without discrimination or harassment on the basis of race, colour, creed, religion, national origin, alienage or citizenship status, age, sex, sexual orientation, gender identity or expression, marital or domestic/civil partnership status, disability, veteran status, genetic information, or any other basis protected by law.", "employment_types": ["Full Time"], "selling_points": [], "locations": ["Kwun Tong"], "categories": ["Banking / Finance", "Loan", "Treasury", "Order Processing & Operation / Settlement"], "post_time": "2022-01-13T08:18:53Z", "salary": {"currency": null, "max": null, "min": null, "period": "monthly", "term": null}, "salary_visible": false, "title_keywords": ["operations", "associate"], "responsibilities": ["operations", "regulatory requirements", "regular review", "communication", "plan", "work under pressure", "control", "uat", "compliance", "project progress", "implementation", "banking", "business activities", "report", "management", "coordinate with", "procedures", "tracking", "guidelines", "policies", "coordinate", "project management"], "requirements": {"degrees": [], "majors": [], "languages": ["english", "chinese"], "language_level": ["excellent"], "hard_skills": ["workshops", "project management", "dynamic", "documentations"], "soft_skills": ["communication skills", "project management", "dynamic", "tenacious", "work under pressure"], "languages_combined": [{"language": "english", "language_level": ["excellent"]}, {"language": "chinese", "language_level": ["excellent"]}]}, "experience_required": {"duration": ["3+ years", "3-5 years"], "field": ["project management", "operation", "relevant experience"]}}, {"job_id": "100003009046602", "location_code": "hk", "company": "Links International", "job_title": "Treasury Manager - New Headcount with US Listed MNC", "description": "Job Descriptions:\nTo support treasury operations and settlements for all treasury activities, including documentation review and payment execution;\nTo perform daily account and position reconciliation;\nTo support loan administration duties and monitor the performance of appointed loan servicers and agents;\nTo conduct financial calculation and data analysis with MS Excel and Access;\nTo provide documents management services;\nTo participate in ad hoc duties or projects; and\nThe employment will be on contract basis subject to renewal.\nRequirements:\n\n\nBachelor degree in Finance, Accounting, Business Administration or related discipline, preferably with 1 year of working experience in commercial banks or financial institutions;\nAttention to details, high degree of accuracy, able to work independently, under pressure and meet tight deadlines;\nSelf-motivated, proactive working attitude, eager to learn and willing to take up new responsibilities;\nExcellent command of written and spoken English and Chinese;\nProficient in computer operation including MS Word and MS Excel, knowledge in MS Access an added advantage; and\nFresh graduates will also be considered.\nInterested parties please send your full resume stating current and expected salary by 26 January 2022.\nPlease visit\u00a0http://www.hkmc.com.hk/eng/careers/job_openings.html\u00a0for other application methods.\nPlease ensure that all information provided to the HKMC Group is accurate, complete and updated. Data provided which is inaccurate or incomplete may influence the process and outcome of the recruitment exercise.\u00a0 Please read the HKMC Group Personal Information Collection Statement for Job Applicants at the HKMC website before completing the application form.\u00a0 Personal data collected will be used for recruitment purposes only.\u00a0 Candidates not invited for interview within 8 weeks may consider their application unsuccessful.\u00a0", "employment_types": ["Full Time", "Permanent"], "selling_points": ["APAC job scope", "Stable working hours (9-5pm)", "International working environment"], "locations": ["Central & Western Area"], "categories": ["Accounting", "Finance / Accounting Manager", "Treasurer", "Banking / Finance", "Treasury"], "post_time": "2022-01-13T16:12:54Z", "salary": {"currency": null, "max": null, "min": null, "period": "monthly", "term": null}, "salary_visible": false, "title_keywords": ["manager"], "responsibilities": ["ad hoc duties", "management", "operations", "review", "data analysis", "payment", "monitor the performance", "documentation", "administration"], "requirements": {"degrees": ["degree", "bachelor"], "majors": ["finance", "accounting", "business administration"], "languages": ["english", "chinese"], "language_level": ["excellent"], "hard_skills": ["ms excel", "ms word"], "soft_skills": ["work independently", "self-motivated", "under pressure", "meet tight deadlines", "eager to learn", "attention to details", "proactive"], "languages_combined": [{"language": "english", "language_level": ["excellent"]}, {"language": "chinese", "language_level": ["excellent"]}]}, "experience_required": {"duration": ["1 year"], "field": ["business administration", "related", "finance", "commercial", "financial institutions", "accounting"]}}, {"job_id": "100003009039251", "location_code": "hk", "company": "Cosco Shipping Investment Holdings Co., Limited", "job_title": "Treasury Officer (\u8d44\u91d1\u7ba1\u7406\u90e8\u4e3b\u4efb\uff09", "description": "Key Responsibilities:\n* Cash flow management, which includes estimates; calculations of net cash position, analysis of\ncash flow activities and assessments of investing/borrowing activities\n* Develop hedging recommendations\n* Implementing and administering currency and interest rates to the hedging program\n* Administer bank accounts globally and maintain cash, debt, and interest schedules in accordance\nwith accounting standards\n* Support the VP, Finance & Operations in identifying improvement opportunities\n* Managing the delivery of all Treasury initiatives and projects\n* Assist HQ to manage banking and lending relationships\n* Provide technical and other support for mergers, acquisitions and other projects as needed\n\nExperience, Education and Designations:\n* 5 to 7 years' experience in a similar role\n* Undergraduate degree in finance or accounting, a CTP designation is a plus, or CPA, CMA, CGA\n* Experience with multiple currencies and international operations strongly preferred in a\nmanufacturing environment\n* Experience preparing cash forecasts and cash flow analyses\n* Experience working in private equity ownership environment\n* Experience in building complex financial models to evaluate various financial plans\n\n", "employment_types": ["Full Time"], "selling_points": ["Bachelor\u2019s degree or above in Finance", "3 to 5 years work experiences in financial", "Proficient user of Ms Office software"], "locations": ["Sheung Wan"], "categories": ["Accounting", "Accounting Clerk / Supervisor", "Treasurer", "Banking / Finance", "Treasury"], "post_time": "2022-01-11T09:17:47Z", "salary": {"currency": null, "max": null, "min": null, "period": "monthly", "term": null}, "salary_visible": false, "title_keywords": ["officer"], "responsibilities": ["management", "schedules", "operations", "analysis", "financial models", "develop", "evaluate", "cash flow", "maintain", "banking", "financial plans"], "requirements": {"degrees": ["degree"], "majors": ["finance", "accounting"], "languages": [], "language_level": [], "hard_skills": ["cpa", "analysis", "private equity", "plus"], "soft_skills": [], "languages_combined": []}, "experience_required": {"duration": ["5 to 7 years"], "field": ["financial", "education"]}}, {"job_id": "100003009045867", "location_code": "hk", "company": "Bank of China (Hong Kong) Limited", "job_title": "Senior Treasury Marketing Manager", "description": "\u00a0Job Description\nResponsible for opening/closing/maintenance of the on-shore and off-shore bank accounts.\nResponsible for routine matters related to internet-banking system, including user and cash pool management.\nResponsible for maintaining the statistics of bank account information.\nAssisting in treasury-management matters, including FX Spot transactions, application for banking facilities, reviewing finance documents, post-lending matters.\nAssisting in maintaining statistics of cash flows and interest-bearing debts.\n\u8d1f\u8d23\u516c\u53f8\u94f6\u884c\u5728\u5cb8/\u79bb\u5cb8\u8d26\u6237\u7ba1\u7406\u5de5\u4f5c\uff0c\u5305\u62ec\u8d26\u6237\u5f00\u7acb\u3001\u53d8\u66f4\u4e0e\u6ce8\u9500\uff1b\n\u8d1f\u8d23\u7f51\u4e0a\u94f6\u884c\u7cfb\u7edf\u7ba1\u7406\u5de5\u4f5c\uff0c\u5305\u62ec\u7f51\u4e0a\u94f6\u884c\u7528\u6237\u7ba1\u7406\u4e0e\u8d44\u91d1\u6c60\u7ef4\u62a4\uff1b\n\u8d1f\u8d23\u8d26\u6237\u4fe1\u606f\u7684\u7edf\u8ba1\u5de5\u4f5c\uff1b\n\u534f\u52a9\u8d44\u91d1\u7ba1\u7406\u5de5\u4f5c\uff0c\u5305\u62ec\u5916\u6c47\u5373\u671f\u4ea4\u6613\u3001\u7533\u8bf7\u94f6\u884c\u6388\u4fe1\u3001\u5408\u540c\u5ba1\u9605\u3001\u8d37\u540e\u4e8b\u9879\u7b49\uff1b\n\u534f\u52a9\u8d44\u91d1\u4e0e\u5e26\u606f\u8d1f\u503a\u7684\u7edf\u8ba1\u5de5\u4f5c\u3002\u00a0 \u00a0\u00a0\nRequirements\n\nEducational Requirements: Bachelor\u2019s degree or above in Economics, Finance, accounting or other related majors.\nWork Experience: 3 to 5 years work experiences in financial service industries are preferred.\nLanguage Requirements: Proficient speaker of Cantonese, Mandarin and English.\nOther Requirements: Proficient user of Ms Office software; personalities of prudence and earnestness, a great sense of responsibility and teamwork; compliance with rules and regulations; obedience to other work assignments from superiors.\n\u5b66\u5386\u8981\u6c42\uff1a\u7ecf\u6d4e\u3001\u91d1\u878d\u3001\u4f1a\u8ba1\u6216\u5176\u4ed6\u76f8\u5173\u4e13\u4e1a\u672c\u79d1\u6bd5\u4e1a\u6216\u4ee5\u4e0a\uff1b\n\u5de5\u4f5c\u7ecf\u9a8c\uff1a3\u81f35\u5e74\uff0c\u91d1\u878d\u884c\u4e1a\u80cc\u666f\u4f18\u5148\uff1b\n\u8bed\u8a00\u8981\u6c42\uff1a\u719f\u7ec3\u4f7f\u7528\u5e7f\u4e1c\u8bdd\u3001\u666e\u901a\u8bdd\u4e0e\u82f1\u8bed\uff1b\n\u5176\u4ed6\u8981\u6c42\uff1a\u719f\u7ec3\u4f7f\u7528Ms Office\u529e\u516c\u8f6f\u4ef6\uff1b\u5de5\u4f5c\u8e0f\u5b9e\u8ba4\u771f\uff0c\u5177\u6709\u8d23\u4efb\u5fc3\u4e0e\u56e2\u961f\u610f\u8bc6\uff1b\u9075\u5b88\u516c\u53f8\u5404\u9879\u89c4\u7ae0\u5236\u5ea6\uff0c\u670d\u4ece\u4e0a\u53f8\u5de5\u4f5c\u5b89\u6392\u3002", "employment_types": ["Full Time"], "selling_points": ["Treasury Marketing", "Global Markets", "-"], "locations": ["Others"], "categories": ["Banking / Finance", "Treasury"], "post_time": "2022-01-13T08:58:11Z", "salary": {"currency": null, "max": null, "min": null, "period": "monthly", "term": null}, "salary_visible": false, "title_keywords": ["marketing manager"], "responsibilities": ["management", "maintaining", "maintenance", "transactions", "banking"], "requirements": {"degrees": ["degree or above", "bachelor"], "majors": ["finance", "economics", "accounting"], "languages": ["cantonese", "english", "mandarin"], "language_level": ["proficient"], "hard_skills": ["ms office"], "soft_skills": ["teamwork", "sense of responsibility"], "languages_combined": [{"language": "cantonese", "language_level": ["proficient"]}, {"language": "english", "language_level": ["proficient"]}, {"language": "mandarin", "language_level": ["proficient"]}]}, "experience_required": {"duration": ["3 to 5 years"], "field": ["financial"]}}, {"job_id": "100003009047730", "location_code": "hk", "company": "Global Executive Consultants Ltd.", "job_title": "Business Analyst (Securities/Fund/FX/Treasury) (HK$30K - $40K) (Ref. No.: 25335)", "description": "Responsibilities:\n\nExecute tasks delegated by supervisors (Including Global Markets Department of Southeast Asia entities)\n\nDevelop business strategy and working plan for financial institutional and corporate customers (Including Global Markets Department of Southeast Asia entities)\n\nCoordinate with relationship managers to develop and maintain the client relationship by providing professional consulting and trading services. Be responsible for customizing financing solutions to help clients reduce their financing costs as well as managing risk for bond syndication (public/private placement), and providing professional advice on the package of products to seize hedging or investing opportunities. (Including Global Markets Department of Southeast Asia entities)\n\nProvide timely information/insights to supervisors regarding market opportunities and changes of clients\u2019 needs, and update the marketing strategy accordingly. (Including Global Markets Department of Southeast Asia entities)\n\nAfter acquiring securities intermediary qualification, conduct regulated activities under the Hong Kong Securities and Futures Commission regulation, such as advising on securities, dealing in securities, executing orders from clients and providing analyses on equities, bonds or other markets (Including Global Markets Department of Southeast Asia entities)\n\nSet and achieve annual financial target for the team or individual (in accordance with market practice, department budget and other factors)\n\nAssist direct supervisor in managing daily operation of business; Oversee the progress of business projects to meet the preset target (Including Global Markets Department of Southeast Asia entities)\n\nPlan and conduct internal trainings as well as develop strategies and marketing plans to sell existing treasury products, and support other departments to launch marketing campaigns (Including Global Markets Department of Southeast Asia entities)\n\nComply with local laws, regulations and other guidance as well as bank's policies, risk management and operating procedures in order to control risks, and report any problems to supervisors or related departments when necessary and prompt follow up action. (Including Global Markets Department of Southeast Asia entities)\n\nComply with regulators\u2019 rules and bank\u2019s policies regarding money laundering and client due diligence, the corresponding performance will be evaluated as part of the KPI.\n\nRequirements:\n\nMinimum 7 years of financial business experience and 5 years of \u00a0treasury business experience\n\nStrong learning ability, communication and coordination ability and team spirit, full of passion, and able to adapt to higher intensity work requirements;\n\nHighly self-motivated; ability to work individually and within a team.\n\nExcellent communication skills in Mandarin and English is a must. Fluent in Cantonese is a plus.", "employment_types": ["Full Time", "Permanent"], "selling_points": ["Familiar in securities / treasury system", "Coordinate the testing activities", "Communication with IT and business units"], "locations": ["Not Specified"], "categories": ["Banking / Finance", "Investment", "Treasury", "Information Technology (IT)", "Product Management / Business Analyst"], "post_time": "2022-01-14T08:57:19Z", "salary": {"currency": null, "max": null, "min": null, "period": "monthly", "term": null}, "salary_visible": false, "title_keywords": ["business analyst"], "responsibilities": ["regulations", "consulting", "marketing plans", "budget", "maintain", "plan", "costs", "due diligence", "control", "business projects", "develop", "marketing campaigns", "report", "guidance", "management", "coordinate with", "procedures", "executing", "develop strategies", "bank\u2019s policies", "policies", "daily operation"], "requirements": {"degrees": [], "majors": [], "languages": ["cantonese", "english", "mandarin"], "language_level": ["excellent", "fluent"], "hard_skills": ["plus"], "soft_skills": ["communication skills", "self-motivated", "team spirit", "learning ability", "communication", "coordination"], "languages_combined": [{"language": "cantonese", "language_level": ["fluent"]}, {"language": "english", "language_level": ["excellent"]}, {"language": "mandarin", "language_level": ["excellent"]}]}, "experience_required": {"duration": ["5 years", "minimum 7 years"], "field": ["business", "financial"]}}, {"job_id": "100003009054920", "location_code": "hk", "company": "Sun Hung Kai Properties Ltd", "job_title": "ASSISTANT TREASURY MANAGER", "description": "Requirements:\n\n\nBachelor\u2019s degree in banking, finance, accounting or related disciplines preferred\nMinimum 10 years\u2019 relevant experience in treasury or settlement in banking and/or sizable organizations.\nSensitive to numbers and with good interpersonal skills\nProven English proficiency, fluency in Putonghua preferred\nFamiliar with PC software e.g. MS Word, Excel, PowerPoint\n\nResponsibilities:\n\n\nTake charge of money market and assist in other treasury functions\nEnsure timely settlement of capital market transactions and liaison with treasury team for PRC operations\nCo-ordinate cashflow monitoring & follow-up on execution of syndicated loans, bilateral loans, bonds\nPrepare reports for management review\n\nGood remuneration and attractive fringe benefits will be offered to the successful applicant. Interested parties please apply with full resume, present and expected salary, available date by clicking \"Apply Now\".\n\nWe are an equal opportunity employer and welcome applications from all qualified candidates. All personal data collected will be used for recruitment purpose only.\u00a0 Applicants not hearing from us within 3 months may consider their applications unsuccessful.\u00a0 All personal data collected will be destroyed within 24 months.", "employment_types": ["Full Time", "Permanent"], "selling_points": ["10 yrs' exp in treasury or settlement in banking", "Take charge of money market", "Co-ordinate cashflow monitoring"], "locations": ["Wan Chai"], "categories": ["Accounting", "Treasurer", "Banking / Finance", "Corporate Finance", "Treasury"], "post_time": "2022-01-17T13:57:03Z", "salary": {"currency": null, "max": null, "min": null, "period": null, "term": null}, "salary_visible": false, "title_keywords": ["manager", "assistant"], "responsibilities": ["operations", "monitoring", "transactions", "management review", "prepare reports", "timely settlement"], "requirements": {"degrees": ["degree", "bachelor"], "majors": ["related disciplines", "finance", "accounting"], "languages": ["putonghua", "english"], "language_level": ["fluency", "proficiency"], "hard_skills": ["powerpoint", "pc", "excel", "ms word"], "soft_skills": ["sensitive to numbers", "interpersonal skills"], "languages_combined": [{"language": "putonghua", "language_level": ["fluency"]}, {"language": "english", "language_level": ["proficiency"]}]}, "experience_required": {"duration": ["minimum 10 years"], "field": ["relevant experience", "banking"]}}, {"job_id": "100003009051105", "location_code": "hk", "company": "ORIX Asia Limited", "job_title": "Manager, Treasury - Settlement", "description": "Job\n\nLead and monitor the settlement support operation, review the operation to enhance work quality and efficiency to reduce settlement and repayment risk\nEnsure compliance of internal policies and procedures and statutory requirements\n\n\u00a0Requirements\n\nDegree or above in Business Administration, Banking, Finance, Economics, Accounting or related disciplines\nAt least 5 years\u2019 working experience in settlement operation, FX operations, remittance and funds transfer and with 2 years in managerial position\nFamiliar with inward/outward remittance and Anti-money laundering requirements\nHigh integrity and initiative, good team-player, meticulous and able to work independently\nGood PC skills and proficient in English and Cantonese (Putonghua is an advantage)\n\nWe offer attractive remuneration and benefits, comprehensive career development opportunities and 5-day week to the qualified candidate.\n\nInterested parties please send detailed resume including current salary and expected salary to:\u00a0HR Dept, 25/F, Two Exchange Square, 8 Connaught Place, Central, HK\n\nAll personal information provided by applicants will be treated in strict confidence and used solely for recruitment purpose.\u00a0 All information of unsuccessful candidates will be destroyed within 12 months from the date of this advertisement.", "employment_types": ["Full Time", "Permanent"], "selling_points": [], "locations": ["Central"], "categories": ["Banking / Finance", "Treasury"], "post_time": "2022-01-15T02:18:19Z", "salary": {"currency": null, "max": null, "min": null, "period": "monthly", "term": null}, "salary_visible": false, "title_keywords": ["manager"], "responsibilities": ["policies", "operations", "review", "monitor", "procedures", "ensure compliance", "statutory requirements", "work quality", "banking", "administration"], "requirements": {"degrees": ["degree or above"], "majors": ["business administration", "finance", "economics", "related disciplines", "accounting"], "languages": ["cantonese", "putonghua", "english"], "language_level": ["advantage", "proficient", "good"], "hard_skills": ["pc skills", "anti-money laundering"], "soft_skills": ["meticulous", "work independently", "team-player", "integrity", "initiative"], "languages_combined": [{"language": "cantonese", "language_level": ["proficient", "good"]}, {"language": "putonghua", "language_level": ["advantage", "proficient", "good"]}, {"language": "english", "language_level": ["proficient", "good"]}]}, "experience_required": {"duration": ["2 years", "at least 5 years"], "field": ["managerial", "operation"]}}, {"job_id": "100003009042966", "location_code": "hk", "company": "Chong Hing Bank Ltd", "job_title": "Treasury and Markets Trainee", "description": "To handle the control and reporting function of a bank\u2019s treasury function,including profit attribution analysis, MTM reporting and analysis. Conduct price verification on financial products. Responsible for the assessment of the valuation adjustment, off-market rate checking. Maintain internal control standards on valuation, front to back position break reconciliation etc. Understanding of product control and able to adapt to different bank's policy, procedures quickly. Setup of new controls framework and implementation either due to regulatory changes or new business.Provide advice on control implication on their new business / new product. Participate discussions on Change initiatives, articulate the user requirements, provide input and solutions to new deals/products/initiatives.Participate in system implementation and various projects on financial products .\n\n\u00a0Requirements:\n\nDegree holder in Risk Management, Statistic, Economics, Finance, Quantitative Analysis or relevant disciplines, with professional qualifications of CFA, FRM, CPA or equivalent is preferred;\n\u00a0At least 5 years\u2019 product control market risk management experiences;\nStrong knowledge in treasury / global markets products, such as FX products, Fixed Income, Derivatives & OTC products and financial product analytical skill is preferred;\nFamiliar with trading front & back office systems;\nProficient in MS Excel and practical skill in VBA & SQL;\nStrong communication and analytical skills;\nProficient in both spoken and written English and Chinese, fluent in Putonghua is preferable.\n\nIf you are flexible enough and zeal for a harmonious and supportive working environment where enables you to grow and succeed professionally, please send a full resume indicating your public examination results (HKCEE and HKALE / HKDSE), your present and expected salary and quoting reference number attention to\u00a0Talent Acquisition Division, Nanyang Commercial Bank, 151 Des Voeux Road Central, \u00a0Hong Kong or apply through email. For details, please visit\u00a0https://www.ncb.com.hkhttps//www.ncb.com.hk/ and select the page Recruit.\n\nWe are an Equal Opportunities Employer. Data collected would be used for recruitment purposes only. Applicants who do not hear from us within 8 weeks may consider their applications unsuccessful and their data will be destroyed within 12 months of receipt.", "employment_types": ["Full Time", "Permanent"], "selling_points": ["Provided w/ development & learning opportunities", "University graduate in Computer Science, Finance", "Strong technical /numerical background is prefer"], "locations": ["Central"], "categories": ["Banking / Finance", "Treasury", "Equities / Capital Markets", "Asset Management"], "post_time": "2022-01-12T09:19:34Z", "salary": {"currency": null, "max": null, "min": null, "period": "monthly", "term": null}, "salary_visible": false, "title_keywords": ["trainee"], "responsibilities": ["reporting", "control", "valuation", "management", "data", "analysis", "systems", "procedures", "checking", "implementation", "back office", "communication", "maintain", "provide advice", "recruitment", "setup", "internal control"], "requirements": {"degrees": ["hkdse", "degree holder"], "majors": ["finance", "risk management", "economics"], "languages": ["putonghua", "english", "chinese"], "language_level": ["fluent", "proficient"], "hard_skills": ["vba", "analytical skill", "professional qualifications", "cfa", "analysis", "analytical skills", "sql", "cpa", "ms excel", "system implementation", "frm", "internal control"], "soft_skills": ["flexible", "analytical skill", "supportive", "responsible", "harmonious", "analytical skills", "communication", "articulate"], "languages_combined": [{"language": "putonghua", "language_level": ["fluent", "proficient"]}, {"language": "english", "language_level": ["fluent", "proficient"]}, {"language": "chinese", "language_level": ["fluent", "proficient"]}]}, "experience_required": {"duration": ["at least 5 years"], "field": ["management", "market risk"]}}, {"job_id": "100003009050354", "location_code": "hk", "company": "Nanyang Commercial Bank", "job_title": "Treasury Marketing Manager (Ref: RH8003-00-JDB)", "description": "We are looking for high calibre individuals to join our Treasury and Markets for developing a long-term career with us.\u00a0 Treasury and Markets Trainees are provided with development and learning opportunities comprising on-the-job training, job rotation and coaching which equip you with relevant knowledge and skills for career advancement. \u00a0We also offer support to you to pursue relevant professional qualifications in order to enhance your professionalism.\n\nWe now offer development opportunities in following professional teams:\n\nSales and Marketing\nAsset Management\nProduct Structuring\n\nWe welcome all young talents who meet the following requirements:\n\nUniversity graduate in Computer Science, Finance, Economics, Mathematics, Business or related disciplines (strong technical / numerical background is preferred)\nExcellent analytical, interpersonal and communication skills\nStrong self-motivation and drive to achieve excellence\nPassionate, committed and a good team player\nSelf-disciplined and able to work under pressure\u00a0\u00a0\nGood computer knowledge in VBA and Macros\n\n\nWe offer competitive remuneration package and promising career opportunities to the successful candidates. Interested parties, please send full resume with current & expected salary and the date of availability to\u00a0The HR Division, G.P.O. Box 2535, HK\u00a0, or by clicking Apply Now. Please quote reference on your application. Information provided will be treated in strict confidence and only be used for recruitment purposes. Personal data of unsuccessful applications will be destroyed 24 months after the completion of the recruitment and selection exercise.", "employment_types": ["Full Time", "Permanent"], "selling_points": ["Formulate strategic business plans", "Provide market information and trading strategies", "At least 5 years working experience in Banking"], "locations": ["Sheung Wan"], "categories": ["Banking / Finance", "Treasury", "Wealth Management"], "post_time": "2022-01-15T03:51:02Z", "salary": {"currency": null, "max": null, "min": null, "period": "monthly", "term": null}, "salary_visible": false, "title_keywords": ["marketing manager"], "responsibilities": ["teams", "developing", "communication", "asset management", "work under pressure"], "requirements": {"degrees": ["university graduate"], "majors": ["mathematics", "finance", "economics", "related disciplines", "business", "computer science"], "languages": [], "language_level": [], "hard_skills": ["vba", "professional qualifications"], "soft_skills": ["passionate", "communication skills", "good team player", "committed", "learning", "self-motivation", "interpersonal", "work under pressure"], "languages_combined": []}, "experience_required": {"duration": [], "field": []}}, {"job_id": "100003009045105", "location_code": "hk", "company": "Wellesley Associates Limited", "job_title": "FX Specialist / Treasury Specialist- Premier Banking", "description": "Formulate strategic business plans and participate in new product development. Maintain clients' relationship and develop marketing plans. Provide market information and trading strategies to clients. Promote treasury products to clients and execute clients\u2019 order. Achieve sales target allocated by management.\n\nRequirements\n\nWith Bachelor Degree or above, preferably with major in Finance, Economics, Accounting, business Administration or related disciplines;\nAt least\u00a05 years working experience in Banking industry, of which at least 3 years working experience in handling treasury products or wealth management products;\nProfessional qualifications in CFA, FRM and equivalent will be an advantage;\nLicensed to dealing in securities (Type 1) and advising on securities (Type 4) is a must;\nFamiliar with treasury systems e.g Reuters, Bloomberg, Kondor+;\nGood presentation, negotiation and analytical skills; Excellent communication and interpersonal skills;\nHigh proficiency in professional computer applications;\nProficient in both spoken and written English and Chinese, fluent in Putonghua is preferable.\n\n(Candidate with less experience will be considered as Assistant Treasury Marketing Manager.)\n\nIf you are flexible enough and zeal for a harmonious and supportive working environment where enables you to grow and succeed professionally, please send a full resume indicating your public examination results (HKCEE and HKALE / HKDSE), your present and expected salary and quoting reference number attention to Talent Acquisition Division, Nanyang Commercial Bank, 151 Des Voeux Road Central, Hong Kong or apply through email. For details, please visit https://www.ncb.com.hk/ and select the page Recruit.\n\nWe are an Equal Opportunities Employer. Data collected would be used for recruitment purposes only. Applicants who do not hear from us within 8 weeks may consider their applications unsuccessful and their data will be destroyed within 12 months of receipt.", "employment_types": ["Full Time", "Permanent"], "selling_points": ["Join a team with great dynamics", "Strong support from management", "Attractive total compensation package"], "locations": ["Not Specified"], "categories": ["Banking / Finance", "Retail Banking", "Treasury"], "post_time": "2022-01-13T07:10:36Z", "salary": {"currency": null, "max": null, "min": null, "period": "monthly", "term": null}, "salary_visible": false, "title_keywords": ["specialist"], "responsibilities": ["management", "market information", "data", "marketing plans", "sales target", "systems", "business plans", "develop", "communication", "maintain", "recruitment", "computer applications", "banking", "administration"], "requirements": {"degrees": ["degree or above", "bachelor", "hkdse"], "majors": ["business administration", "finance", "economics", "related disciplines", "accounting"], "languages": ["putonghua", "english", "chinese"], "language_level": ["fluent", "proficient"], "hard_skills": ["bloomberg", "professional qualifications", "cfa", "analytical skills", "frm"], "soft_skills": ["flexible", "supportive", "negotiation", "harmonious", "analytical skills", "communication and interpersonal skills", "presentation"], "languages_combined": [{"language": "putonghua", "language_level": ["fluent", "proficient"]}, {"language": "english", "language_level": ["fluent", "proficient"]}, {"language": "chinese", "language_level": ["fluent", "proficient"]}]}, "experience_required": {"duration": ["at least 3 years", "at least 5 years"], "field": ["banking industry", "management", "marketing"]}}, {"job_id": "100003009046039", "location_code": "hk", "company": "Bank of China (Hong Kong) Limited", "job_title": "Senior Treasury Product Manager\uff08Fixed-Income\uff09", "description": "My client is a well-established and top tier foreign bank with global presence and a comprehensive facility in banking & wealth management. They\u2019re looking FX Specialist / Treasury Specialist to join their team.\n\n\nDuties:\n\nGiving house view and FX market update to the floor and clients\nGenerate Foreign Exchange product ideas to the floor that are suitable to clients\nHelp Relationship Managers and Investment Counsellors in pitching clients on optimal Foreign Exchange solutions\nExecutes Foreign Exchange orders, including cash, options, and structured notes, and works closely\nResponsible for driving pairing Bankers to meet team goals, including coaching\n\nRequirements:\n\n2 years of experience in FX margin clients and individual accounts\nStrong knowledge and experience in Foreign Exchange market\nAble to derive and deliver Foreign Exchange recommendations across multiple currencies and forecasting\nSolid dealing capabilities, with attention to details and good knowledge in dealing systems\nAble to work under pressure and execute client orders accurately and effectively\nGood knowledge in MS word / Excel / PowerPoint\nLicensed in HKSI paper 1, 7, 8\nIf you're interested in this role, forward an up-to-date copy of your CV via email, or call directly on +852 2847 9962. If this job isn't quite right for you but you are opened for a new position within banking / wealth management side, please contact me for a confidential discussion on your career", "employment_types": ["Full Time"], "selling_points": ["Treasury Product", "Fixed Income", "Global Markets"], "locations": ["Others"], "categories": ["Banking / Finance", "Treasury"], "post_time": "2022-01-13T09:28:19Z", "salary": {"currency": null, "max": null, "min": null, "period": "monthly", "term": null}, "salary_visible": false, "title_keywords": [], "responsibilities": ["ideas"], "requirements": {"degrees": [], "majors": [], "languages": [], "language_level": [], "hard_skills": ["excel", "hksi paper", "powerpoint", "exchange", "ms word"], "soft_skills": ["interested in", "attention to details", "work under pressure"], "languages_combined": []}, "experience_required": {"duration": ["2 years"], "field": []}}, {"job_id": "100003009049403", "location_code": "hk", "company": "Shanghai Commercial Bank Ltd", "job_title": "Associate, Settlement & Securities Processing", "description": "Responsibilities:\nGood indepth knowledge of the principles, functions, risk factors and application skills of various treasury products especially on fixed income products in the Asia region.\nGood insights into market opportunities and customer needs; provide solutions for new product due diligence;\nTaking initiatives and point for new treasury product business development (mainly fixed income products) and assist in completion of existing product due diligence \u00a0\u00a0\nParticipate in important and large-scale marketing and inter-department training tasks.\nInitiate and be responsible for product development tasks, making professional recommendations in the process.\nStrong communication and internal coordination skills.\nConduct business strictly in compliance with regulatory and the bank's requirements, as well as supervising the subordinate's professional ethics; assist Southeast Asia Subsidiaries/Branches Global Markets in understanding and fulfilling professional requirements.\nComply with local laws, regulations or codes of conduct, bank policies, relevant risk management policies and procedures, and relevant rules; identify and mitigate various existing or potential risks at work, report to supervisors and related units in a timely manner, and formulate corrective and follow up actions accordingly (including Southeast Asia Subsidiaries/Branches).\nRequirements:\nPossess specialist knowledge in Fixed Income Products\nFamiliar with Global Markets Instruments and their applications\nAbility to articulate and capitalized on market opportunities via various trading strategies and structured products ideas\nAbility to engage with Sales with effective product communication and presentations for client's meeting requirements\nWorking with Sales, Trading, Relationship Management, Operations to identify, assess, propose and execute operational process improvements.\nStaying up to date with the latest market trends and products evolutions including exchange traded funds.\u00a0\nStrong written and oral communication skills in English and Mandarin", "employment_types": ["Full Time", "Contract"], "selling_points": ["Responsible for performing daily settlement", "Process settlement payments and receipts", "Support User Acceptance Test (UAT)"], "locations": ["Not Specified"], "categories": ["Banking / Finance", "Treasury", "Others", "Order Processing & Operation / Settlement"], "post_time": "2022-01-15T03:50:23Z", "salary": {"currency": null, "max": null, "min": null, "period": "monthly", "term": null}, "salary_visible": false, "title_keywords": ["associate"], "responsibilities": ["regulations", "management", "supervising", "product due diligence", "policies", "compliance", "procedures", "a timely manner", "provide solutions", "communication", "coordination", "report"], "requirements": {"degrees": [], "majors": [], "languages": ["english", "mandarin"], "language_level": [], "hard_skills": ["presentations", "exchange"], "soft_skills": ["communication skills", "oral", "communication", "articulate", "structured"], "languages_combined": [{"language": "english", "language_level": []}, {"language": "mandarin", "language_level": []}]}, "experience_required": {"duration": [], "field": []}}, {"job_id": "100003009036730", "location_code": "hk", "company": "The Hong Kong Jockey Club", "job_title": "Senior Data Analyst (Treasury)", "description": "Responsibilities:\n\nResponsible for performing daily settlement of all transactions initiated by Treasury and Investment Products Department, including Foreign Exchange, Money Market, securities, options, futures and other investment products in a timely and effective manner\nProcess settlement payments and receipts, and prepare summary reports\nEnsure all transactions are in full compliance with internal / external rules and regulations\nSupport User Acceptance Test (UAT) and participate in any projects as assigned\n\nRequirements:\n\nDegree holder in Business Administration or related disciplines\nWell-organized, self-motivated and attention to details\nGood command of written and spoken English and Chinese\nProficient in MS Word, Excel and Chinese Word processing\n\nAttractive remuneration package will be offered to the right candidates. Interested parties please click \"Apply Now\" to submit your full resume with current and expected salary to the Human Resources Division.\n\nPlease visit us at www.shacombank.com.hk for more information about our Bank.\n\nAll personal data collected will be used for recruitment related purposes strictly in accordance with the Bank's personal data policies, a copy of which will be provided immediately upon request by contacting our Personal Data Compliance Officer. Applicants who are not contacted within two months may consider their applications unsuccessful and the personal data collected from the applicants will be retained for no longer than two years from the date of rejection during which the applicants may be considered for other suitable positions within the Bank.", "employment_types": ["Full Time"], "selling_points": ["a minimum of 4 yrs\u2019 experience in data analytics", "experience in using data visualization software", "knowledge in banking, finance or treasury"], "locations": ["Causeway Bay"], "categories": ["Banking / Finance", "Treasury"], "post_time": "2022-01-10T13:11:26Z", "salary": {"currency": null, "max": null, "min": null, "period": null, "term": null}, "salary_visible": false, "title_keywords": ["data analyst"], "responsibilities": ["regulations", "receipts", "uat", "compliance", "transactions", "payments", "reports"], "requirements": {"degrees": ["degree holder"], "majors": ["related disciplines", "business administration"], "languages": ["english", "chinese"], "language_level": ["good command", "proficient"], "hard_skills": ["excel", "chinese word processing", "ms word"], "soft_skills": ["self-motivated", "well-organized", "attention to details"], "languages_combined": [{"language": "english", "language_level": ["good command"]}, {"language": "chinese", "language_level": ["good command", "proficient"]}]}, "experience_required": {"duration": [], "field": []}}, {"job_id": "100003009048174", "location_code": "hk", "company": "Louis Vuitton Pacific Limited", "job_title": "Assistant Manager - Financial Control", "description": "The Department\n\nOur Treasury Department manages the Club\u2019s treasury operations and handles a large volume of cash flow data.\n\nThe Job\n\nYou will:\n\n\u00a0\u00a0\u00a0\u00a0\u00a0\u00a0\u00a0\u00a0 act as the in-house expert to unlock the value of Treasury data\n\u00a0\u00a0\u00a0\u00a0\u00a0\u00a0\u00a0\u00a0 work closely with the other team members in Treasury to make use of the market and operational data for predictive modelling and analysis\n\u00a0\u00a0\u00a0\u00a0\u00a0\u00a0\u00a0\u00a0 design, manage and optimize process for data intake, validation, mining, modelling as well as visualisation\n\u00a0\u00a0\u00a0\u00a0\u00a0\u00a0\u00a0\u00a0 coordinate treasury projects in analysing data from complex datasets and derive management insights useful for cash flow projection, financial risk management and credit exposure management\n\u00a0\u00a0\u00a0\u00a0\u00a0\u00a0\u00a0\u00a0 provide actionable insights from analytic initiatives to support data-driven decision on treasury management issues\n\u00a0\u00a0\u00a0\u00a0\u00a0\u00a0\u00a0\u00a0 support the data visualisation projects for migrating the management reports to the visual analytics platform for more real-time and insightful reporting\n\u00a0\u00a0\u00a0\u00a0\u00a0\u00a0\u00a0\u00a0 participate in the Robotic Process Automation (RPA) projects for enhancing the operational efficiency\n\nAbout You\n\nYou should have:\n\n\u00a0\u00a0\u00a0\u00a0\u00a0\u00a0\u00a0\u00a0 a degree or recognised qualifications in Data Analytics, FinTech, Information Technology, Computer Science\n\u00a0\u00a0\u00a0\u00a0\u00a0\u00a0\u00a0\u00a0 a minimum of 4 years\u2019 experience in data analytics\n\u00a0\u00a0\u00a0\u00a0\u00a0\u00a0\u00a0\u00a0 proven experience in executing data analytics initiatives\n\u00a0\u00a0\u00a0\u00a0\u00a0\u00a0\u00a0\u00a0 experience in using data visualization software (e.g. Tableau) is a plus\n\u00a0\u00a0\u00a0\u00a0\u00a0\u00a0\u00a0\u00a0 knowledge in banking, finance or treasury is an advantage but not a must\n\nTerms of Employment\n\nThe level of appointment will be commensurate with qualifications and experience.\n\nHow to Apply\n\nPlease send your resume, complete with expected salary and job reference by clicking the Apply Now button or to:\n\nFax: \u00a0\u00a0\u00a0\u00a0\u00a0\u00a0 2576-1987\n\nMail:\u00a0\u00a0\u00a0\u00a0\u00a0 The Human Resources Department,\n\n\u00a0\u00a0\u00a0\u00a0\u00a0\u00a0\u00a0\u00a0\u00a0\u00a0\u00a0\u00a0\u00a0\u00a0\u00a0 The Hong Kong Jockey Club,\n\n\u00a0\u00a0\u00a0\u00a0\u00a0\u00a0\u00a0\u00a0\u00a0\u00a0\u00a0\u00a0\u00a0\u00a0\u00a0 1 Sports Road, Happy Valley,\n\n\u00a0\u00a0\u00a0\u00a0\u00a0\u00a0\u00a0\u00a0\u00a0\u00a0\u00a0\u00a0\u00a0\u00a0\u00a0 Hong Kong", "employment_types": ["Full Time", "Permanent"], "selling_points": ["Career Opportunity with Louis Vuitton", "Finance/ Treasury operations - APAC exposure", "5 day work week, competitive remuneration"], "locations": ["Quarry Bay"], "categories": ["Accounting", "Financial Controller", "Banking / Finance", "Corporate Finance", "Treasury"], "post_time": "2022-01-14T05:39:26Z", "salary": {"currency": null, "max": null, "min": null, "period": "monthly", "term": null}, "salary_visible": false, "title_keywords": ["assistant manager"], "responsibilities": ["reporting", "management", "visualization", "software", "data", "operations", "analysis", "banking", "design", "coordinate", "cash flow", "management reports", "executing", "visual"], "requirements": {"degrees": ["degree"], "majors": ["computer science", "information technology"], "languages": [], "language_level": [], "hard_skills": ["plus", "data analytics", "analysis", "tableau", "rpa", "make", "management reports", "data visualization"], "soft_skills": ["driven"], "languages_combined": []}, "experience_required": {"duration": ["minimum of 4 years"], "field": []}}, {"job_id": "100003009050929", "location_code": "hk", "company": "Bank of Communications Co., Ltd. Hong Kong Branch", "job_title": "Manager, Treasury Products (Business Control \u2013 Global Markets)", "description": "The Assistant Manager - Financial Control position takes care of\u00a0cash flow consolidation, treasury and cash management, payment system, banking relationship and insurance management in Asia Pacific region. He/ she will be based in Hong Kong corporate office.\n\nJob Duties & Responsibilities:\n\nAnalytical review and reporting on the consolidated balance sheet and cash flow statement for Asia-Pacific region.\u00a0\nEnsure smooth cashflow to meet daily cash requirement of the company and monthly inter-company settlement.\nImplement group treasury initiatives, maintain cash management control for the Asia Pacific region. Prepare monthly treasury report for HQ review.\nMaintain authorization matrix. Support bank account opening & closing, authorized signatories updated, KYC and compliance monitoring.\nReview cashflow forecast, optimize group financing, and achieve treasury objectives.\nMaintain insurance & banking relationship.\nInsurance coverage review for the region; placing insurance for special events and store constructions, manage insurance claims with broker/adjustors.\nProfile & Key Requirements:\n\nA qualified accountant and a degree holder in Accounting or Finance\nAt least 5 years of finance/treasury operations experience from MNC is preferred\nSolid experience in treasury system and e-payment platforms\nGood interpersonal and good written and spoken communication skills in both English and Chinese\nStrong analytical and problem solving skills\nGood at dealing with mass data and figures in multi-currencies; detail-oriented\nMature, self-motivated and independent\nAll applications will be treated in strict confidence and used only for recruitment purpose. Applicants who are not invited for interview within four weeks may be considered for other suitable positions within the Group over a one-year period, after which their personal data will be destroyed.", "employment_types": ["Full Time", "Permanent"], "selling_points": [], "locations": ["Not Specified"], "categories": ["Banking / Finance", "Treasury", "Financial Services", "Others"], "post_time": "2022-01-14T11:49:54Z", "salary": {"currency": null, "max": null, "min": null, "period": null, "term": null}, "salary_visible": false, "title_keywords": ["manager"], "responsibilities": ["reporting", "management", "control", "account opening", "review", "compliance", "monitoring", "banking", "cash flow", "maintain", "forecast", "kyc", "report", "insurance", "balance sheet"], "requirements": {"degrees": ["degree holder"], "majors": ["finance", "accounting"], "languages": ["english", "chinese"], "language_level": ["good"], "hard_skills": ["problem solving skills"], "soft_skills": ["communication skills", "self-motivated", "confidence", "independent", "mature", "detail-oriented", "analytical and problem solving skills", "interpersonal"], "languages_combined": [{"language": "english", "language_level": ["good"]}, {"language": "chinese", "language_level": ["good"]}]}, "experience_required": {"duration": ["at least 5 years"], "field": ["finance"]}}, {"job_id": "100003009044257", "location_code": "hk", "company": "OCBC Wing Hang Bank Limited", "job_title": "VP/AVP, China Offshore Institutional Sales", "description": "Career Level\nSenior\nQualification\nDegree\nYears of Experience\n5 years\nJob Type\nFull Time, Permanent\nJob Functions\nBanking / Finance, Treasury, Financial Services, Others", "employment_types": ["Full Time", "Permanent"], "selling_points": ["Distribute FICC derivatives", "Solicit new business opportunities", "Actively identify potential business"], "locations": ["Sheung Wan"], "categories": ["Banking / Finance", "Corporate Banking", "Corporate Finance", "Treasury"], "post_time": "2022-01-13T03:34:34Z", "salary": {"currency": null, "max": null, "min": null, "period": "monthly", "term": null}, "salary_visible": false, "title_keywords": ["sales"], "responsibilities": ["banking"], "requirements": {"degrees": ["degree"], "majors": [], "languages": [], "language_level": [], "hard_skills": [], "soft_skills": [], "languages_combined": []}, "experience_required": {"duration": [], "field": []}}, {"job_id": "100003009049101", "location_code": "hk", "company": "Bank of China (Hong Kong) Limited", "job_title": "Senior Treasury Product Manager/Treasury Product Manager(GM)", "description": "\u00a0\nResponsibilities\n\n- Distribute FICC derivatives, structured products, and cross boarder solutions to Chinese institutional clients\n- Solicit new business opportunities and continue to grow and strengthen existing relationship and institutional client networks\n- Work closely with bond syndicate and onshore China team to drive the Fixed Income business\n- Actively identify potential business by working with trading and structuring to deliver tailor-made solutions to institutional clients\n\nRequirements\n\n- Bachelor degree in business or related disciplines\n- A minimum of 5 to 7 years' of relevant experience in FICC sales, covering China-based bank and non-bank financial institutional clients\n- Demonstrated track record in developing and implementing strategies to achieve sales results\n- Strong knowledge in global financial markets, fixed income products, derivatives, and structured products\n- Native in Mandarin is a MUST. Proficiency in both spoken and written Chinese and English\n- Excellent interpersonal and communication skills, self-driven and a good team player\n- Strong work ethic, attention to details and willing to learn\n- Well versed in Bloomberg, MS Excel/Word/Powerpoint\n\nAttractive remuneration package will be offered to the right candidate. Please apply with full resume stating present & expected salary and contact phone number\u00a0to\u00a0The Human Resources Manager, 10/F, 161 Queen\u2019s Road Central, Hong Kong.\u00a0Please quote the reference.\n\nPersonal data collected will be used for recruitment purpose only. For more information, please visit our website:\u00a0http://www.ocbcwhhk.com.", "employment_types": ["Full Time"], "selling_points": ["Perform product development tasks", "Licensed for HKMA Type 1 and Type 4", "5-8 years relevant working experience"], "locations": ["Not Specified"], "categories": ["Banking / Finance", "Treasury", "Others"], "post_time": "2022-01-14T08:07:48Z", "salary": {"currency": null, "max": null, "min": null, "period": "monthly", "term": null}, "salary_visible": false, "title_keywords": ["product manager"], "responsibilities": ["business opportunities"], "requirements": {"degrees": ["degree", "bachelor"], "majors": ["related disciplines", "business"], "languages": ["english", "chinese", "mandarin"], "language_level": ["native", "proficiency"], "hard_skills": ["powerpoint", "ms excel", "bloomberg", "word"], "soft_skills": ["communication skills", "good team player", "interpersonal", "willing to learn", "work ethic", "attention to details", "structured", "driven"], "languages_combined": [{"language": "english", "language_level": ["proficiency"]}, {"language": "chinese", "language_level": ["proficiency"]}, {"language": "mandarin", "language_level": ["native"]}]}, "experience_required": {"duration": ["minimum of 5 to 7 years"], "field": ["relevant experience", "financial"]}}, {"job_id": "100003009040791", "location_code": "hk", "company": "Page Personnel", "job_title": "Investment Operations Analyst - Leading Bank", "description": "Customer Propositions and Management\n\nWe are currently seeking a high caliber professional to join our department as\u00a0Manager, Deposits Transactional Banking and FX (FX).\u00a0\u00a0\n\n\n\nPrincipal responsibilities\n\nManage and execute implementation of deposits & FX infrastructure change initiatives, ensure quality deliverables which meet internal and external customers' requirements\nPlan, formulate and deliver business strategic KPIs or initiatives aimed at achieving seamless customer experience, streamlining the end-to-end operation process, sustaining business growth and competitive edge of deposits & FX products and services\nMaintain timely communication with IT teams and various stakeholders throughout the project lifecycle to ensure requirements are aligned with business objectives\nLiaise with various stakeholders to manage ad hoc projects to address the changing customer and business needs\nPrepare relevant strategy papers, business proposals and reports for presentation to senior management\nKeep abreast of the latest compliance requirements of the Group, Bank and regulatory authorities, initiate necessary internal and external communication plan, internal procedural and system changes\n\nRequirements\n\nUniversity Degree or other relevant post graduate qualifications\nSound knowledge of retail deposits, FX products management and payment, prior experience in retail digital channel development or multi-functional projects would be an asset\nExcellent Project Management skills including ability to manage multiple projects simultaneously with strong problem solving and influencing skills\nNumerate, positive, flexible and self-motivated individual\nStrong business acumen and analytic skills, able to navigate conflicting priorities\nShown strong situation awareness, strong desire to learn and able to work in Agile environment\nProficiency in both English and Chinese\u00a0\n\nIf you would like to explore other opportunities at Hang Seng Hong Kong, please visit\u00a0www.hangseng.com/careers/\u00a0for details.\n\n\nThe health and safety of our employees and candidates is very important to us. Due to the current situation related to the Novel Coronavirus (2019-nCoV), we\u2019re leveraging our digital capabilities to ensure we can continue to recruit top talent at the HSBC Group. \u00a0As your application progresses, you may be asked to use one of our digital tools to help you through your recruitment journey. \u00a0If so, one of our \u00a0Resourcing colleagues will explain how our video-interviewing technology will be used throughout the recruitment process and will be on hand to answer any questions you might have.\n\nAll information provided by applicants will be used only for recruitment purposes and will be used strictly in accordance with the Bank's personal data policies, a copy of which may be obtained by the applicant upon request. Unless otherwise instructed in writing by the applicant concerned, applicants may be considered for other suitable positions within the Bank and its related companies. The personal data of unsuccessful job applicants may be retained for a maximum of two years from the date when the job application is rejected and such data may be retained for a longer period if there is a subsisting reason that obliges the Bank to do so, after which the personal data will be destroyed.", "employment_types": ["Full Time", "Temporary"], "selling_points": ["High exposure in investment operations", "Excellent training and potential growth", "Opportunities for career progression"], "locations": ["Not Specified"], "categories": ["Banking / Finance", "Investment", "Treasury", "Order Processing & Operation / Settlement"], "post_time": "2022-01-12T03:04:37Z", "salary": {"currency": null, "max": null, "min": null, "period": "monthly", "term": null}, "salary_visible": false, "title_keywords": ["operations analyst"], "responsibilities": ["internal and external customers", "infrastructure", "quality", "implementation", "teams", "compliance", "communication", "maintain", "ad hoc projects", "reports", "plan", "liaise with", "kpis", "senior management", "system changes"], "requirements": {"degrees": ["university degree"], "majors": [], "languages": ["english", "chinese"], "language_level": ["proficiency"], "hard_skills": ["agile", "reason", "problem solving", "project management", "analytic skills", "acumen"], "soft_skills": ["flexible", "self-motivated", "manage multiple projects simultaneously", "agile", "project management skills", "problem solving", "business acumen", "novel", "positive"], "languages_combined": [{"language": "english", "language_level": ["proficiency"]}, {"language": "chinese", "language_level": ["proficiency"]}]}, "experience_required": {"duration": [], "field": ["digital", "management", "retail", "development"]}}, {"job_id": "100003009045925", "location_code": "hk", "company": "Conners Consulting Limited", "job_title": "Relationship Manager-Trade Finance", "description": "Our client is looking for an Investment Operations Analyst to join their growing business. The ideal candidate will have 1+ years of experience in operations/ accounting management within banking.\n\nClient Details\n\nOur client is one of Hong Kong's largest banks with more than 80 years of history. Its main services include private banking, retail banking, investment services and wealth management. The bank provides a massive network of more than 200 service outlets in Hong Kong and has established its network in most major cities in mainland China.\n\nDescription\n\nHandle investment operations processes include trade management and support\nMonitor life cycle management and settlement, and oversight treasury positions\nLiaise with custodian banks, auditors, and internal/external counterparties to monitor the quality of services\nEnsure the arrangements with relevant service providers are being appropriately applied\nAssist in new product enablement coordinate with middle office service providers and custodian banks\n\nProfile\n\nUniversity degree in Business Administration or other relevant qualifications\nPrevious experience of operations/ accounting management is highly preferred\nGood PC skills including MS Word and Excel\nVBA and Bloomberg knowledge is an advantage\nGood command of written and spoken English and Cantonese\n\nJob Offer\n\nWorking days and time: Mon - Fri, 0900 - 1800\nWork location: MongKok\nHigh exposure in investment operations\nExcellent training and potential growth\nOpportunities for career progression\n\nTo apply online please click the 'Apply' button below. For a confidential discussion about this role please contact Kira Tang on +852 2258 3538.", "employment_types": ["Full Time"], "selling_points": ["min 3-year experience as Relationship Manager", "Attractive compensation", "Excellent communication skill"], "locations": ["Central"], "categories": ["Banking / Finance", "Corporate Banking", "Retail Banking", "Treasury"], "post_time": "2022-01-13T09:09:25Z", "salary": {"currency": null, "max": null, "min": null, "period": "monthly", "term": null}, "salary_visible": false, "title_keywords": ["relationship manager"], "responsibilities": ["management", "operations", "monitor", "quality", "coordinate with", "banking", "liaise with", "administration"], "requirements": {"degrees": ["university degree"], "majors": ["business administration"], "languages": ["cantonese", "english"], "language_level": ["good command"], "hard_skills": ["excel", "vba", "bloomberg", "pc skills", "ms word"], "soft_skills": ["ideal"], "languages_combined": [{"language": "cantonese", "language_level": ["good command"]}, {"language": "english", "language_level": ["good command"]}]}, "experience_required": {"duration": ["1+ years"], "field": ["management", "accounting", "banking"]}}, {"job_id": "100003009039092", "location_code": "hk", "company": "China CITIC Bank International Limited", "job_title": "Senior Manager/Assistant Vice President, Business Control (Documentation Control)", "description": "Responsibilities\nMaintain, develop and expand customer relationships by providing trade finance products and general banking services.\nDevelop new accounts and relationship with corporate/commercial customers, and cross-sell the Bank's products and services.\nPrepare credit proposals and conduct regular reviews to monitor the credit-worthiness of existing customers.\nWork effectively across geographic borders with customers and mainland branches to deepen relationship with the Bank.\nFamilar with the Banks Compliance Policy on Know Your Customer Policy and Procedure, Money Laundering Prevention Guidelines/Procedure.\nRequirements\nUniversity degree in Accounting / Finance / Business Administration or equivalent\nMinimum 3 years experience in marketing or credit in banking industry\nWell versed in banking ordinance and related regulatory requirements\nDetailed-minded with good organization, interpersonal and communication skills\nProficient in MS office applications\nGood command of written and spoken English and Chinese (preferably fluent in Mandarin)\nCandidate with more experience would consider the role of Senior Manager\n\nTo apply, please send your detailed resume or contact Ms Lam at 3996 8092 for a confidential discussion.\n\nOnly shortlisted candidates will be notified.\u00a0\n\nApplicants who are not contacted within two weeks may consider their applications unsuccessful.\n\nAll data collected will be used for recruitment purpose only & will be used strictly confidential.\n\nConners Consulting Limited\n\n2005 Kai Tak Commercial Building 317 Des Voeux Road Central Hong Kong\n\nTel: (852) 3996 8090\u00a0\u00a0\u00a0\u00a0\u00a0 Website: www.connersconsulting.com\n\n\n\n", "employment_types": ["Full Time", "Permanent"], "selling_points": ["Implement internal controls for trader & marketer", "Negotiate, review and execute master agreements", "Exp. in negotiating global markets documentations"], "locations": ["Tsim Sha Tsui"], "categories": ["Banking / Finance", "Treasury", "Others"], "post_time": "2022-01-11T08:55:10Z", "salary": {"currency": null, "max": null, "min": null, "period": "monthly", "term": null}, "salary_visible": false, "title_keywords": ["senior manager", "assistant vice president"], "responsibilities": ["guidelines", "compliance", "monitor", "develop", "maintain", "banking"], "requirements": {"degrees": ["university degree"], "majors": ["finance", "accounting", "business administration"], "languages": ["english", "chinese", "mandarin"], "language_level": ["good command", "fluent"], "hard_skills": ["ms office"], "soft_skills": ["communication skills", "interpersonal", "detailed"], "languages_combined": [{"language": "english", "language_level": ["fluent", "good command"]}, {"language": "chinese", "language_level": ["fluent", "good command"]}, {"language": "mandarin", "language_level": ["fluent", "good command"]}]}, "experience_required": {"duration": ["minimum 3 years"], "field": ["banking industry", "marketing"]}}, {"job_id": "100003009042232", "location_code": "hk", "company": "Hang Seng Bank Ltd", "job_title": "Manager, Deposits Transactional Banking and FX (Transactional Banking)", "description": "Key Responsibilities\n\nImplement effective internal controls to ensure daily activities of Treasury traders and marketers are in compliance to regulators\u2019 guidelines and the Bank\u2019s internal procedures.\nWork with internal parties to review and update on Treasury related workflows, procedures and guidelines.\nNegotiate, review and execute master agreements, including but not limited to ISDA Schedule, CSA, GMRA, with financial institutions and corporate clients.\nLead in template development and work with internal legal & compliance and external legal counsel to facilitate business needs.\nParticipate in projects or discussion where amendments of contracts/agreements are necessary.\nRequirements\u00a0\n\n\nDegree holder in Law, Business, Economics,\u00a0 Finance or related discipline.\nMinimum 5 years related experience in banking industry. Experience in negotiating global markets documentation and ISDA Master Agreements is preferred.\nSound knowledge in treasury products and related regulatory guidelines and familiar with ISDA definitions and their developments.\nGood interpersonal and communication skills.\nGood command of written and spoken English and Chinese (including Putonghua).\n\nFor more details about career opportunities with the Bank, please visit our website http://www.cncbinternational.com/careers/en/index.jsp. Please apply with full resume stating current and expected salaries.\nPersonal data collected will be used for recruitment related purposes only. Applicants not invited for interview within 6 weeks may consider their applications unsuccessful. However, applicants may be considered for other suitable positions within the Group for a period of not more than 2 years. Personal data will be destroyed at any time after 3 months.\nChina CITIC Bank International is committed to being an equal opportunities employer and intends to provide a work environment free of unlawful discrimination or harassment. All employment decisions will be made in a non-discriminatory manner.", "employment_types": ["Full Time", "Permanent"], "selling_points": [], "locations": ["Not Specified"], "categories": ["Banking / Finance", "Retail Banking", "Treasury", "Financial Services"], "post_time": "2022-01-12T06:40:46Z", "salary": {"currency": null, "max": null, "min": null, "period": "monthly", "term": null}, "salary_visible": false, "title_keywords": ["manager"], "responsibilities": ["guidelines", "contracts", "review", "compliance", "procedures", "schedule", "internal parties"], "requirements": {"degrees": ["master", "degree holder"], "majors": ["finance", "economics", "business", "law"], "languages": ["putonghua", "english", "chinese"], "language_level": ["good command"], "hard_skills": ["documentation"], "soft_skills": ["communication skills", "committed", "interpersonal"], "languages_combined": [{"language": "putonghua", "language_level": ["good command"]}, {"language": "english", "language_level": ["good command"]}, {"language": "chinese", "language_level": ["good command"]}]}, "experience_required": {"duration": ["minimum 5 years"], "field": ["related", "banking industry"]}}, {"job_id": "100003009042360", "location_code": "hk", "company": "EYuan Technology Limited", "job_title": "Financial Accounting Manager", "description": "Personal Banking Products\n\nWe are currently seeking a high caliber professional to join our department as\u00a0Manager, Deposits Transactional Banking and FX (Transactional Banking).\u00a0\u00a0\n\nPrincipal responsibilities\n\nDevelop and execute deposits account usage growth initiatives, facilitate sustainable growth in CASA and expand active deposits account customer base\nActively interact with various stakeholders, including all sales channels, Transformation, IT, Back Office, customer experience team to establish rapport and ensure efficient execution of business activities\nDevelop insightful analytics and customer / product MIs to understand customer behavior and usage trend, and in turn drive continuous improvement of product development and profitability management\nImplement change and fine-tune processes to shorten processing time and improve customer journey\nWork with Marketing in the planning, development and implementation of creative and cost-effective marketing campaigns to drive the Bank's deposits growth, enhance deposit products, payroll and transactional banking services, and create incremental revenue to the business\nEnsure relevant control measures are in place to minimize the risk exposure of the Bank as well as meeting all the internal standard, compliance, policies & regulation\n\nRequirements\n\nUniversity Degree in Finance or\u00a0other relevant disciplines/ qualifications\nRelevant experience in deposits, product management, payroll propositions, retail payment, customer journey development within Retail Banking\nGreat sense of ownership and servicing mindset to ensure efficient and effective customer service delivery\nStrong project management; proven ability to manage complex projects with multiple deadlines and shifting priorities\u00a0\nStrong analytical reasoning and problem solving capabilities\nNumerate individual, with excellent interpersonal skills\u00a0\nSound knowledge of application software such as MS Excel, PowerPoint\nProficiency in both English and Chinese\n\nIf you would like to explore other opportunities at Hang Seng Hong Kong, please visit\u00a0www.hangseng.com/careers/\u00a0for details.\n\n\nThe health and safety of our employees and candidates is very important to us. Due to the current situation related to the Novel Coronavirus (2019-nCoV), we\u2019re leveraging our digital capabilities to ensure we can continue to recruit top talent at the HSBC Group. \u00a0As your application progresses, you may be asked to use one of our digital tools to help you through your recruitment journey. \u00a0If so, one of our \u00a0Resourcing colleagues will explain how our video-interviewing technology will be used throughout the recruitment process and will be on hand to answer any questions you might have.\n\nAll information provided by applicants will be used only for recruitment purposes and will be used strictly in accordance with the Bank's personal data policies, a copy of which may be obtained by the applicant upon request. Unless otherwise instructed in writing by the applicant concerned, applicants may be considered for other suitable positions within the Bank and its related companies. The personal data of unsuccessful job applicants may be retained for a maximum of two years from the date when the job application is rejected and such data may be retained for a longer period if there is a subsisting reason that obliges the Bank to do so, after which the personal data will be destroyed.", "employment_types": ["Full Time"], "selling_points": ["At least 3 years working experience in fund accoun", "Highly paid", "Great room for Development"], "locations": ["Sheung Wan"], "categories": ["Accounting", "Finance / Accounting Manager", "Banking / Finance", "Treasury"], "post_time": "2022-01-12T07:42:19Z", "salary": {"currency": "HKD", "max": 34999, "min": 20000, "period": "monthly", "term": null}, "salary_visible": true, "title_keywords": ["accounting manager"], "responsibilities": ["management", "cost", "control", "policies", "compliance", "back office", "implementation", "develop", "marketing campaigns", "banking", "payroll", "business activities", "planning"], "requirements": {"degrees": ["university degree"], "majors": ["finance"], "languages": ["english", "chinese"], "language_level": ["proficiency"], "hard_skills": ["problem solving capabilities", "powerpoint", "reason", "project management", "ms excel"], "soft_skills": ["efficient", "problem solving", "project management", "customer service", "interpersonal skills", "novel"], "languages_combined": [{"language": "english", "language_level": ["proficiency"]}, {"language": "chinese", "language_level": ["proficiency"]}]}, "experience_required": {"duration": [], "field": ["development", "retail banking", "product management", "relevant experience", "payroll", "retail"]}}, {"job_id": "100003009039580", "location_code": "hk", "company": "IT Solutions Ltd.", "job_title": "Major Bank (QA): Project Assistants / Admin Assistants (Treasury System Project)", "description": "\u804c\u8d23\n1.\u76d1\u7763\u548c\u5904\u7406\u65e5\u5e38\u4f1a\u8ba1\uff0c\u9884\u7b97\u548c\u8d22\u52a1\u76f8\u5173\u4e1a\u52a1;\n2\u3001\u5904\u7406\u6240\u6709\u4e0e\u4e1a\u52a1\u76f8\u5173\u7684\u4ea4\u6613\u4ea4\u6613\uff0c\u5e76\u5907\u6848\u6240\u6709\u76f8\u5173\u8bb0\u5f55;\n3. \u4e0e\u94f6\u884c\u3001\u7a0e\u52a1\u5c40\u3001\u516c\u53f8\u7b49\u76f8\u5173\u65b9\u7ef4\u62a4\u548c\u5b9e\u65bd\u8d22\u52a1\u3001\u7a0e\u52a1\u7b49\u76f8\u5173\u4e8b\u5b9c\uff0c\u786e\u4fdd\u7b26\u5408\u4f1a\u8ba1\u51c6\u5219\u548c\u6cd5\u5b9a\u62ab\u9732\u8981\u6c42;\n4\u3001\u51c6\u5907\u672c\u5730\u53ca\u6d77\u5916\u5408\u5e76\u3001\u7ba1\u7406\u62a5\u544a\u3001\u9884\u7b97\u3001\u9884\u6d4b;\n5. \u5904\u7406\u4e34\u65f6\u9879\u76ee\uff0c\u652f\u6301\u7ba1\u7406\u5c42\u51b3\u7b56\u3002\n\u8981\u6c42\uff1a\n1\u3001\u8d22\u52a1\u3001\u4f1a\u8ba1\u6216\u76f8\u5173\u4e13\u4e1a\u672c\u79d1\u53ca\u4ee5\u4e0a\u5b66\u5386;\n2\u3001\u5177\u6709\u4f1a\u8ba1\u8d44\u683c\u6216\u5b8c\u6210\u4e13\u4e1a\u4f1a\u8ba1\u673a\u6784\u804c\u4e1a\u8003\u8bd5\u7684\u4eba\u5458\uff0c\u5e94\u4e88\u8003\u8651;\n3\u30013\u5e74\u4ee5\u4e0a\u91d1\u878d\u884c\u4e1a\u5de5\u4f5c\u7ecf\u9a8c\uff0c\u6709\u8d38\u6613\u516c\u53f8/\u6295\u8d44\u94f6\u884c\u5de5\u4f5c\u7ecf\u9a8c\u8005\u4f18\u5148;\n4. \u624e\u5b9e\u7684\u8bc1\u5238\u4f1a\u8ba1\u3001\u8bc1\u76d1\u4f1a\u8d22\u52a1\u8d44\u6e90\u89c4\u5219\u53ca/\u6216\u8d22\u52a1\u7533\u62a5\u8868\u7ecf\u9a8c;\n5\u3001\u6709\u8d23\u4efb\u5fc3\u3001\u5403\u82e6\u8010\u52b3\u3001\u5177\u6709\u826f\u597d\u7684\u56e2\u961f\u5408\u4f5c\u7cbe\u795e\uff0c\u5177\u6709\u9ad8\u5ea6\u7684\u4e2a\u4eba\u8bda\u4fe1;\n6. \u826f\u597d\u7684\u666e\u901a\u8bdd\u548c\u82f1\u8bed\u53e3\u8bed\u548c\u4e66\u9762\u8868\u8fbe\u80fd\u529b\n\u6ce8\u610f\uff1a\u901a\u8fc7\u81ea\u613f\u63d0\u4ea4\u6536\u96c6\u7684\u7b80\u5386\u5c06\u5728\u804c\u4f4d\u53d1\u5e03\u540e\u4e00\u4e2a\u6708\u5185\u9500\u6bc1\u3002\n\n", "employment_types": ["Full Time"], "selling_points": ["Develop career in Banking & IT field", "Bank Operations", "Training will be provided"], "locations": ["Central"], "categories": ["Admin & HR", "Clerical / Admin Staff", "Banking / Finance", "Treasury", "Information Technology (IT)", "Testing / QA"], "post_time": "2022-01-11T10:09:37Z", "salary": {"currency": null, "max": null, "min": null, "period": "monthly", "term": null}, "salary_visible": false, "title_keywords": ["admin"], "responsibilities": [], "requirements": {"degrees": [], "majors": [], "languages": [], "language_level": [], "hard_skills": [], "soft_skills": [], "languages_combined": []}, "experience_required": {"duration": [], "field": []}}, {"job_id": "100003009042501", "location_code": "hk", "company": "Bank of China (Hong Kong) Limited", "job_title": "Operation Manager / Senior Operation Manager (RMB Clearing)", "description": "Responsibilities:\nManage the daily operation of the RMB Clearing Business, which includes supervision of the team, monitoring of the systems\nIdentify, control, and report promptly to management various types of potential or existing risks, as well as other emergency matters as the case may be, and set up mitigating actions and monitor the process on adopting corrective measures\nFormulate and implement the yearly work plan\nPursue productivity-enhancement initiatives to reduce manual workload of operational activities, and improve RMB clearing efficiency and customers' satisfaction\nManage project plans for system enhancements in phases such as development of system requirements, User Acceptance Test (UAT), system implementation, and assess the effectiveness of projects\nCo-ordinate and organize the annual Disaster Drill (DD), review and prepare Business Continuity Plan (BCP)\nComplete ad-hoc tasks as assigned by superiors\nRequirements:\nDegree or above with major in Business Administration or related disciplines\nAt least 5 years experience in the Banking industry, experience in international payments operation would be a definite advantage\nStrong leadership, planning, project management, analytical, problem solving and decision making skills\nDemonstrate good organization, communication and negotiation skills\nFamiliar with the latest economic / financial market development of the Mainland of China\nGood command of both written and spoken English and Chinese, including Mandarin\nProficient in computer applications (e.g. Lotus Notes, MS Word, Excel, and\u00a0PowerPoint, etc.), and\u00a0Chinese word processing\nEvening shift duty\u00a0is\u00a0required", "employment_types": ["Permanent"], "selling_points": ["RMB Clearing Business", "international payments operation", "economic / financial market"], "locations": ["Mong Kok"], "categories": ["Banking / Finance", "Treasury"], "post_time": "2022-01-12T07:48:42Z", "salary": {"currency": null, "max": null, "min": null, "period": "monthly", "term": null}, "salary_visible": false, "title_keywords": ["operation manager"], "responsibilities": ["business continuity", "control", "management", "uat", "ad-hoc tasks", "monitoring", "daily operation", "systems", "monitor", "implementation", "review", "plan", "plans", "report"], "requirements": {"degrees": ["degree or above"], "majors": ["related disciplines", "business administration"], "languages": ["english", "chinese", "mandarin"], "language_level": ["good command"], "hard_skills": ["excel", "chinese word processing", "powerpoint", "problem solving", "project management", "ms word"], "soft_skills": ["decision making skills", "problem solving", "project management", "communication", "negotiation skills", "leadership"], "languages_combined": [{"language": "english", "language_level": ["good command"]}, {"language": "chinese", "language_level": ["good command"]}, {"language": "mandarin", "language_level": ["good command"]}]}, "experience_required": {"duration": ["at least 5 years"], "field": ["banking industry", "operation"]}}, {"job_id": "100003009042212", "location_code": "hk", "company": "Hang Seng Bank Ltd", "job_title": "Head of FX Products & Portfolio Management", "description": "Personal Banking Products\n\nWe are currently seeking a high caliber professional to join our department as\u00a0Head of FX Products & Portfolio Management.\u00a0\u00a0\n\u00a0\n\nPrincipal responsibilities\n\nDevelop and drive Cash FX business growth strategies and activities, deliver sustainable growth in turnover and expand active Cash FX customer base\nLead and influence various stakeholders for implementing Cash FX business growth initiatives to meet customers\u2019 changing needs across different distribution channels\nDevelop robust tools and MI, drive concrete analytic insight to understand revenue dynamics and trend, proactively identify incremental new business potential by managing pricing/product packaging to maximise profitability\nKeep abreast of latest market environment, regularly benchmark with market players to ensure our FX products and pricing are competitive and actively explore new business opportunities\nPrepare relevant strategy papers, business proposals and reports for presentation to senior management\nEmpower and drive the team development, mobility and capability to sustain a high performing workforce\u00a0\nMonitor and manage products costs and control, ensure relevant control measures are in place to minimize the risk exposure of the Bank as well as meeting all the internal standard, compliance, policies & regulation\n\nRequirements\n\nUniversity Degree in Finance or other relevant disciplines/qualifications\u00a0\nMinimum of 10 years' relevant experience in FX / investment products management or retail digital payment\u00a0\nResults oriented with proven track record of driving business growth, change leader with excellent influencing skills\nNumerate individual, highly effective communicator across various business lines at senior levels within the organization, with excellent interpersonal skills\nAble to navigate conflicting priorities\nProficiency in both English and Chinese\u00a0\nGreat sense of ownership and servicing mind-set to ensure efficient and effective customer service delivery\n\nIf you would like to explore other opportunities at Hang Seng Hong Kong, please visit\u00a0www.hangseng.com/careers/\u00a0for details.\n\n\nThe health and safety of our employees and candidates is very important to us. Due to the current situation related to the Novel Coronavirus (2019-nCoV), we\u2019re leveraging our digital capabilities to ensure we can continue to recruit top talent at the HSBC Group.\u00a0As your application progresses, you may be asked to use one of our digital tools to help you through your recruitment journey.\u00a0If so, one of our Resourcing colleagues will explain how our video-interviewing technology will be used throughout the recruitment process and will be on hand to answer any questions you might have.\nAll information provided by applicants will be used only for recruitment purposes and will be used strictly in accordance with the Bank's personal data policies, a copy of which may be obtained by the applicant upon request. Unless otherwise instructed in writing by the applicant concerned, applicants may be considered for other suitable positions within the Bank and its related companies. The personal data of unsuccessful job applicants may be retained for a maximum of two years from the date when the job application is rejected and such data may be retained for a longer period if there is a subsisting reason that obliges the Bank to do so, after which the personal data will be destroyed.\u00a0", "employment_types": ["Full Time", "Permanent"], "selling_points": [], "locations": ["Not Specified"], "categories": ["Banking / Finance", "Treasury", "Others", "Wealth Management"], "post_time": "2022-01-12T06:38:40Z", "salary": {"currency": null, "max": null, "min": null, "period": "monthly", "term": null}, "salary_visible": false, "title_keywords": [], "responsibilities": ["control", "explore new business opportunities", "policies", "compliance", "monitor", "develop", "reports", "senior management", "product packaging", "costs"], "requirements": {"degrees": ["university degree"], "majors": ["finance"], "languages": ["english", "chinese"], "language_level": ["proficiency"], "hard_skills": ["investment products", "reason"], "soft_skills": ["efficient", "customer service", "interpersonal skills", "novel", "communicator"], "languages_combined": [{"language": "english", "language_level": ["proficiency"]}, {"language": "chinese", "language_level": ["proficiency"]}]}, "experience_required": {"duration": ["minimum of 10 years"], "field": ["management", "relevant experience", "investment", "digital", "retail"]}}, {"job_id": "100003009033737", "location_code": "hk", "company": "Bank of Communications Co., Ltd. Hong Kong Branch", "job_title": "Manager, Treasury Products (Business Control \u2013 Global Markets)", "description": "Career Level\nSenior\nQualification\nDegree\nYears of Experience\n5 years\nJob Type\nFull Time, Permanent\nJob Functions\nBanking / Finance, Treasury, Financial Services, Others", "employment_types": ["Full Time", "Permanent"], "selling_points": [], "locations": ["Not Specified"], "categories": ["Banking / Finance", "Treasury", "Financial Services", "Others"], "post_time": "2022-01-10T01:43:20Z", "salary": {"currency": null, "max": null, "min": null, "period": null, "term": null}, "salary_visible": false, "title_keywords": ["manager"], "responsibilities": ["banking"], "requirements": {"degrees": ["degree"], "majors": [], "languages": [], "language_level": [], "hard_skills": [], "soft_skills": [], "languages_combined": []}, "experience_required": {"duration": [], "field": []}}, {"job_id": "100003009035545", "location_code": "hk", "company": "E.SUN Commercial Bank, Ltd.", "job_title": "Treasury Sales, Corporate Banking", "description": "Job Duties:\n\nResponsible for sales & marketing on treasury products, maintaining clients\u2019 relationship and provide marketing ideas, promoting treasury products and executing clients\u2019 order.\nIn collaboration with Relationship Managers to provide hedging / investment solutions and fulfill clients\u2019 needs.\nProactively support treasury product team and ideas on FX options, Interest rates derivatives or structured products.\nEnsure all sales activities in compliance with the Bank\u2019s guidelines.\n\nRequirement:\n\nMinimum 1~2 years of working experience in treasury marketing or related field.\nBachelor degree or higher in Finance, Economics or related discipline.\nSelf-motivated with strong communication, interpersonal and analytical skills.\n\nWe offer an attractive remuneration package including five-day workweek, double pay, medical insurance coverage, performance bonus, OT allowance, public holiday, excellent career development opportunities, and other benefit packages to the right candidate. Interested parties please forward your resume including a Chinese self-introduction with current and expected salary to Human Resources Department by \"APPLY NOW\".\u00a0\n\nPlease visit our website at https://www.esunbank.com.tw/bank/corporate/overseas-branch/overseas-branch/hong-kong for more information.\u00a0\n\nAll information received will be kept strictly confidential and only for employment-related purposes.", "employment_types": ["Full Time", "Permanent"], "selling_points": ["Sales & marketing on treasury products", "Young and Energetic Working Culture", "One of the Leading Bank in Taiwan"], "locations": ["Tsim Sha Tsui"], "categories": ["Banking / Finance", "Corporate Banking", "Treasury", "Equities / Capital Markets"], "post_time": "2022-01-10T07:36:39Z", "salary": {"currency": null, "max": null, "min": null, "period": "monthly", "term": null}, "salary_visible": false, "title_keywords": ["sales"], "responsibilities": ["sales activities", "ideas", "maintaining", "guidelines", "compliance", "executing"], "requirements": {"degrees": ["degree", "bachelor"], "majors": ["finance", "economics"], "languages": [], "language_level": [], "hard_skills": ["analytical skills"], "soft_skills": ["communication", "self-motivated", "interpersonal", "analytical skills"], "languages_combined": []}, "experience_required": {"duration": ["minimum 1~2 years"], "field": ["related", "marketing"]}}, {"job_id": "100003009025365", "location_code": "hk", "company": "Treasury Markets Association", "job_title": "Officer, HIBOR administration (TMA)", "description": "Company: \u00a0\u00a0\u00a0\u00a0\u00a0 \u00a0\u00a0\u00a0\u00a0\u00a0\u00a0\u00a0\u00a0\u00a0\u00a0\u00a0 An International Corporate Bank\u00a0\nPosition: \u00a0\u00a0\u00a0\u00a0\u00a0\u00a0\u00a0 \u00a0\u00a0\u00a0\u00a0\u00a0\u00a0\u00a0\u00a0\u00a0\u00a0\u00a0 Risk AVP\nLocation:\u00a0\u00a0\u00a0\u00a0\u00a0\u00a0\u00a0 \u00a0\u00a0\u00a0\u00a0\u00a0\u00a0\u00a0\u00a0\u00a0\u00a0\u00a0 Hong Kong\n\nFUNCTION:\u00a0\u00a0\u00a0\u00a0\u00a0\u00a0\u00a0\u00a0\u00a0\u00a0\n\nResponsible for monitoring the risk position and evaluate the performance of the branch\u2019s treasury operations to ensure compliance with Head Office limits and guidelines. Play a key role for the branch operational risk control.\n\n\nMAIN DUTIES AND RESPONSIBILITIES:\u00a0\n\nCredit Risk Management:\n\nUpdate the branch management and Credit Risk Meeting of any material considerations affecting the loan portfolio, loan policy and individual loan transactions.\nAdminister and monitor the loan portfolio including portfolio quality control.\nManage and direct the work of the officers in their respective responsibilities.\nResponsible for overall risk assessment of the department\u2019s area of responsibility, including overall portfolio risk.\nCarry out adhoc assignments requested by the branch management to support Business Promotion Department.\nUpdate Credit Risk Management Procedure Manual.\nPerform any other duties as assigned.\n\nTreasury Risk Management:\n\nPrepare periodical reports for Head Office and management on the risk position and performance of the Treasury Department in an accurate and timely manner.\nEnsure compliance with Head Office limits and guidelines by treasury staff in the course of the department operations.\nCheck the logic built into the systems involved and implement such changes to the systems, procedures and rules as the case may require.\nDevelop, review and enhance risk-related reports to provide better support to management.\nConduct regular review and update of job processes and procedures within the department to ensure fast and effective response to changing conditions, and compliance with internal and external regulations.\nSupervise the work of junior staff and train the staff to gain a better understanding of the work carried out so as to ensure accuracy in work output and to aid staff\u2019s development.\u00a0\n\nREQUIREMENTS:\n\nDegree holder\nAt least 4 years of experience in market/treasury risk management from commercial/wholesale/corporate banks\nStrong sense of responsibility, good communication and organizational skill\nFluent in Cantonese and English", "employment_types": ["Full Time", "Permanent"], "selling_points": ["Salary range from 15K - 25K with performance bonus", "15 days AL and medical insurance with dental", "Work life balance"], "locations": ["Sheung Wan"], "categories": ["Banking / Finance", "Treasury", "Information Technology (IT)", "Support"], "post_time": "2022-01-06T04:14:33Z", "salary": {"currency": "HKD", "max": 24999, "min": 14000, "period": "monthly", "term": null}, "salary_visible": true, "title_keywords": ["officer"], "responsibilities": ["regulations", "any other duties", "management", "guidelines", "operations", "systems", "monitor", "procedures", "transactions", "ensure compliance", "develop", "review", "regular review", "compliance", "reports", "quality control"], "requirements": {"degrees": ["degree holder"], "majors": [], "languages": ["cantonese", "english"], "language_level": ["fluent"], "hard_skills": [], "soft_skills": ["communication", "organizational skill", "sense of responsibility"], "languages_combined": [{"language": "cantonese", "language_level": ["fluent"]}, {"language": "english", "language_level": ["fluent"]}]}, "experience_required": {"duration": ["at least 4 years"], "field": ["risk management", "commercial"]}}, {"job_id": "100003009035015", "location_code": "hk", "company": "WIT Talent Solutions Limited", "job_title": "Risk AVP - Corporate Banking", "description": "The Treasury Markets Association (TMA) was incorporated through\u00a0the institutionalisation of the Treasury Markets Forum of Hong Kong and the merger with ACI-The Financial Markets Association of Hong Kong in 2005. Principal functions of the TMA include promoting co-operation and synergy among market practitioners with a view to enhancing professionalism and the overall competitiveness of the treasury markets in Hong Kong, thereby maintaining the role as an international financial centre. Also, as the administrator of major financial benchmarks (such as HIBOR) in Hong Kong, the TMA\u00a0uphold the robustness and credibility of the administered benchmarks. This includes reviewing whether and how to refine benchmarks administered having regard to international recommendations and local market conditions. We are currently looking for a candidate to join the benchmark administration team.\n\nResponsible for daily benchmark monitoring/surveillance process and its reporting;\nundertake ad-hoc project and testing as required\n\n\u00a0Job Requirements\n\nBachelor\u2019s degree holder (Business degree most preferred) and fresh graduates will also be considered;\nExercising due diligence and attention to detail is crucial;\nGood communication, problem-solving and time management skills\n\nInterested parties please send application letters with full resume and expected salary via email to the TMA office.\n\nData collected will be used for recruitment purposes. Applicants may assume their applications unsuccessful if they are not contacted within one month from the application.", "employment_types": ["Full Time", "Permanent"], "selling_points": [], "locations": ["Central"], "categories": ["Banking / Finance", "Corporate Banking", "Treasury", "Risk Management"], "post_time": "2022-01-10T05:14:54Z", "salary": {"currency": null, "max": null, "min": null, "period": "monthly", "term": null}, "salary_visible": false, "title_keywords": [], "responsibilities": ["ad-hoc", "reporting", "due diligence", "management", "maintaining", "monitoring", "testing", "communication", "administration"], "requirements": {"degrees": ["degree", "bachelor", "degree holder"], "majors": ["business"], "languages": [], "language_level": [], "hard_skills": ["problem-solving"], "soft_skills": ["responsible", "time management skills", "problem-solving", "communication", "attention to detail"], "languages_combined": []}, "experience_required": {"duration": [], "field": []}}, {"job_id": "100003009033628", "location_code": "hk", "company": "OCBC Wing Hang Bank Limited", "job_title": "Associate, Market Risk", "description": "Responsibilities\n\u200b\u200bSupport management of market risk management activities on the compliance with policies, control framework and exposure monitoring\nEnsure the market risk framework and measures are consistent with group policies and meet local regulatory requirements\nAnalyze and report risks to front office and general management in a timely manner Ensure the market risks are well understood, correctly measured and timely reported\nPerform regular stress test and ad-hoc stress tests ahead of notable market events\nParticipate in projects of various complexity, including FRTB, system implementation, and new businesses\nRequirements\n\u200bDegree in Finance/Statistics or a related quantitative/analytical discipline\nAround 1-2 years\u2019 relevant experience in banking industry\nStrong MS Excel & VBA skills, with knowledge in Bloomberg/Murex will be an advantage\nGood team player with strong interpersonal and communication skills\nFresh graduates are also welcome and will be considered for Associate\n\n\n\nAttractive remuneration package will be offered to the right candidate. Please apply with full resume stating present & expected salary and contact phone number\u00a0to\u00a0The Human Resources Manager, 10/F, 161 Queen\u2019s Road Central, Hong Kong.\u00a0Please quote the reference.\n\nPersonal data collected will be used for recruitment purpose only. For more information, please visit our website:\u00a0http://www.ocbcwhhk.com.", "employment_types": ["Full Time", "Permanent"], "selling_points": ["Market Risk", "Finance / Statisitcs", "Fresh Graduate"], "locations": ["Sheung Wan"], "categories": ["Banking / Finance", "Retail Banking", "Treasury", "Risk Management"], "post_time": "2022-01-10T01:25:03Z", "salary": {"currency": null, "max": null, "min": null, "period": "monthly", "term": null}, "salary_visible": false, "title_keywords": ["associate"], "responsibilities": ["ad-hoc", "management", "control", "policies", "regulatory requirements", "compliance", "monitoring", "a timely manner", "implementation", "report"], "requirements": {"degrees": [], "majors": [], "languages": [], "language_level": [], "hard_skills": ["vba", "ms excel", "bloomberg"], "soft_skills": ["communication skills", "good team player", "interpersonal"], "languages_combined": []}, "experience_required": {"duration": ["1-2 years"], "field": ["banking industry", "relevant experience"]}}, {"job_id": "100003009028920", "location_code": "hk", "company": "China Construction Bank (Asia) Corporation Limited", "job_title": "Assistant Manager/ Manager, Treasury Settlement", "description": "\u00a0Responsibilities\n\nEnsure timely and quality delivery of operations processes in the day-to-day operations of back office processing, life-cycle events, clearing and settlements of Treasury Products, margin / collateral management and transaction reporting\nComply with HKMA/Regulatory standards and internal policy and procedure\nHandle exceptions and issues in an orderly manner and escalate as appropriate\nLiaise with internal / external stakeholders to carry out the duties efficiently and effectively\nParticipate in projects regarding product launch or system enhancement and other regulatory initiatives; undertake ad hoc projects as assigned\nEnsure the process flow is efficient and adopt the relevant technology (eg. RPA) as appropriate\nPrepare/review management reports, regulatory and compliance reports for Treasury related business\nAssist management to maintain and update operational policies & procedures, including contingency plan or any other tasks as assigned\nPRC business trips may be required\nProvide business support on HK holidays where applicable\nRequirements\n\nDegree holder or above with good business acumen\nAt least 3 years of relevant working experience with strong product knowledge, regulatory requirements and guidelines in Treasury Products (including FX/MM, debt securities, repo, cleared\u00a0 / OTC derivatives etc.)\nGood knowledge of market best practice and familiar with the Settlement & Confirmation process of Treasury Products, including common industry infrastructure (eg. SWIFT, RTGS, Euroclear, Clearstream, CMU etc.)\nGood understanding of treasury products documentation (ISDA definitions, CSA, GMRA etc.), reporting requirements (HKTR), central clearing practices, margining requirements, risk mitigation measures and other regulatory and compliance requirements for Treasury business\nStrong drive and commitment, hardworking, excellent ability in problem solving, able to perform under pressure and deliver on schedule\nOpen for change and believe in team work\nGood command of written and spoken English, Chinese and Putonghua\nKnowledgeable in general PC applications (Word & Excel), VBA and Macro knowledge would be an advantage\nCandidates with less experience will be considered for a junior position\n\nPlease send your CV with\u00a0current and\u00a0expected salary\u00a0for the application.\n\n\n\nApplicants who are not contacted within 8 weeks may consider their applications unsuccessful and their personal data will be retained by the bank for a period up to two years.\n\nAll information provided by applicants will be used for recruitment purposes only and will be used strictly in accordance with the bank\u2019s personal data policies, a copy of which will be provided upon request.\n\n\n", "employment_types": ["Full Time", "Permanent"], "selling_points": ["Daily trade processing, collateral management", "System/ procedure enhancement projects", "At least 3 years of relevant working experience"], "locations": ["Kowloon Bay"], "categories": ["Banking / Finance", "Treasury", "Financial Services", "Order Processing & Operation / Settlement"], "post_time": "2022-01-07T03:35:17Z", "salary": {"currency": null, "max": null, "min": null, "period": "monthly", "term": null}, "salary_visible": false, "title_keywords": ["assistant manager", "manager"], "responsibilities": ["reporting", "management", "operations", "policies", "review", "day-to-day operations", "quality", "back office", "compliance", "procedures", "other tasks", "management reports", "maintain", "ad hoc projects", "reports", "plan", "liaise with"], "requirements": {"degrees": ["degree holder"], "majors": ["business"], "languages": ["putonghua", "english", "chinese"], "language_level": ["good command"], "hard_skills": ["excel", "vba", "documentation", "macro", "word", "pc applications", "problem solving", "swift", "acumen"], "soft_skills": ["business acumen", "problem solving", "under pressure", "hardworking"], "languages_combined": [{"language": "putonghua", "language_level": ["good command"]}, {"language": "english", "language_level": ["good command"]}, {"language": "chinese", "language_level": ["good command"]}]}, "experience_required": {"duration": ["at least 3 years"], "field": ["securities", "relevant working experience"]}}, {"job_id": "100003009026108", "location_code": "hk", "company": "China CITIC Bank International Limited", "job_title": "Officer / Senior Officer (Treasury Settlement / Operations, 1-year Contract)", "description": "Job Purpose\n\nResponsible for handling of settlement operations relating to Fixed Income, REPO & Reverse Repo, Debt Capital Market and custodian, and participating in projects for the settlement team\n\nKey Responsibilities\n\nSupport treasury product processing including fixed Income, REPO & Reverse Repo, Debt Capital Market and custodian operations\nParticipate in new business initiatives, and ongoing regulatory project support for Capital Market Settlement team (i.e. BondConnect and Bond short selling)\nManage and develop expertise in support of mainland related business including internal driven (i.e. The Group) and market driven (i.e. BondConnect)\nSupport the Group related treasury business include initiative, networking, operation service and reporting obligation\u00a0\n\nRequirements\n\nDegree holder / Secondary education or above\nPreferably with 1 year of banking experience in treasury settlement\nGood understanding of treasury products including Fixed Income, Repo & Revere Repo and DCM\nGood command of both written and spoken English and Chinese\n\nCandidates with more experience will be considered as Senior Officer\n\n\n\n\nFor more details about career opportunities with the Bank, please visit our website http://www.cncbinternational.com/careers/en/index.jsp. Please apply with full resume stating current and expected salaries.\n\nPersonal data collected will be used for recruitment related purposes only. Applicants not invited for interview within 6 weeks may consider their applications unsuccessful. However, applicants may be considered for other suitable positions within the Group for a period of not more than 2 years. Personal data will be destroyed at any time after 3 months.\n\nChina CITIC Bank International is committed to being an equal opportunities employer and intends to provide a work environment free of unlawful discrimination or harassment. All employment decisions will be made in a non-discriminatory manner.", "employment_types": ["Full Time", "Permanent"], "selling_points": ["Support treasury settlement operations", "Participate in settlement related projects", "Good understanding of treasury products"], "locations": ["Tsim Sha Tsui"], "categories": ["Banking / Finance", "Investment", "Treasury", "Order Processing & Operation / Settlement"], "post_time": "2022-01-06T07:21:02Z", "salary": {"currency": null, "max": null, "min": null, "period": "monthly", "term": null}, "salary_visible": false, "title_keywords": ["officer", "senior officer", "operations"], "responsibilities": ["operations", "business initiatives", "reporting", "develop"], "requirements": {"degrees": ["secondary education", "degree holder"], "majors": [], "languages": ["english", "chinese"], "language_level": ["good command"], "hard_skills": [], "soft_skills": ["committed"], "languages_combined": [{"language": "english", "language_level": ["good command"]}, {"language": "chinese", "language_level": ["good command"]}]}, "experience_required": {"duration": ["1 year"], "field": ["banking experience"]}}, {"job_id": "100003009027660", "location_code": "hk", "company": "HKT", "job_title": "Assistant Officer / Officer - Group Treasury (Fresh graduate welcome)", "description": "The role\n\nSupport daily operations of Corporate Treasury Department\nPrepare the issuance and maintenance of bank guarantees, letters of credit and other related instruments\nHandle settlement and maintain proper record of other treasury transactions\u00a0\nPerform other duties as required\n\nTo succeed in this role\n\nA university degree in Business or Finance preferred\nRelevant experience in banks and/or sizable corporations\u00a0\nGood command of written and spoken English\nCandidate with more experience will be considered for more senior position\nFresh graduates are welcome to apply\n\nIf you have the desire for an exciting and rewarding career, please apply by sending your resume immediately, quoting your present and expected salary by clicking \"Apply Now\".\u00a0\n\nFor more information on other job opportunities of PCCW/HKT Corporate Functions, please visit our website. (http://www.hkt.com/about-hkt/careers/job-opportunities)", "employment_types": ["Full Time"], "selling_points": [], "locations": ["Quarry Bay"], "categories": ["Banking / Finance", "Corporate Finance", "Treasury"], "post_time": "2022-01-06T10:57:14Z", "salary": {"currency": null, "max": null, "min": null, "period": "monthly", "term": null}, "salary_visible": false, "title_keywords": ["assistant officer", "officer"], "responsibilities": ["perform other duties", "maintenance", "letters", "website", "transactions", "daily operations", "maintain proper record"], "requirements": {"degrees": ["university degree"], "majors": ["finance", "business"], "languages": ["english"], "language_level": ["good command"], "hard_skills": ["maintenance"], "soft_skills": [], "languages_combined": [{"language": "english", "language_level": ["good command"]}]}, "experience_required": {"duration": [], "field": ["relevant experience"]}}, {"job_id": "100003009026107", "location_code": "hk", "company": "China CITIC Bank International Limited", "job_title": "Senior Officer (Treasury Operations \u2013 Project Management)", "description": "Job Purpose\n\nResponsible for processing automation, analysis and MIS reporting support for Treasury and Markets Operations\n\nKey Responsibilities\n\nReview, analysis and develop solution to automate and streamline operations workflow\nCollect, analyze and prepare user requirements\nCoordinate, prepare and handle user acceptance tests\nPrepare regular / ad-hoc MIS reporting and regulatory reports\nDevelop tools for MIS report such as MS Access and MS Excel\nWork closely with various departments and service provider to support new business initiative and project implementation\n\n\u00a0Requirements\n\nDegree holder in Finance, Financial Engineering or related disciplines\nMinimum 2 years of banking experience, preferably in middle office / treasury settlement\nGood Knowledge of treasury and global markets products not limited to Derivatives, FX/MM, capital markets and securities\nGood knowledge of middle office, operational risk, front office and settlement functions\nProficient in MS Access, MS Excel and VBA is preferred\nGood command of both written and spoken English and Chinese\n\nFor more details about career opportunities with the Bank, please visit our website http://www.cncbinternational.com/careers/en/index.jsp.\u00a0 Please apply with full resume stating current and expected salaries.\n\nPersonal data collected will be used for recruitment related purposes only. Applicants not invited for interview within 6 weeks may consider their applications unsuccessful. However, applicants may be considered for other suitable positions within the Group for a period of not more than 2 years. Personal data will be destroyed at any time after 3 months.\n\nChina CITIC Bank International is committed to being an equal opportunities employer and intends to provide a work environment free of unlawful discrimination or harassment.\u00a0 All employment decisions will be made in a non-discriminatory manner.", "employment_types": ["Full Time", "Contract"], "selling_points": ["Support on processing automation and projects", "Prepare MIS reporting", "Good knowledge of treasury products"], "locations": ["Tsim Sha Tsui"], "categories": ["Banking / Finance", "Treasury", "Equities / Capital Markets", "Order Processing & Operation / Settlement"], "post_time": "2022-01-06T07:21:01Z", "salary": {"currency": null, "max": null, "min": null, "period": "monthly", "term": null}, "salary_visible": false, "title_keywords": ["senior officer", "operations"], "responsibilities": ["operations", "analysis", "review", "develop"], "requirements": {"degrees": ["degree holder"], "majors": ["related disciplines", "finance", "engineering"], "languages": ["english", "chinese"], "language_level": ["good command"], "hard_skills": ["vba", "ms excel"], "soft_skills": ["committed", "initiative"], "languages_combined": [{"language": "english", "language_level": ["good command"]}, {"language": "chinese", "language_level": ["good command"]}]}, "experience_required": {"duration": ["minimum 2 years"], "field": ["banking experience"]}}, {"job_id": "100003009027225", "location_code": "hk", "company": "DBS Bank Ltd", "job_title": "Vice President, Corporate Treasury, Finance", "description": "Business Function\n\nGroup Finance aims to deliver world-class standards in reporting, financial planning and finance processes. We provide insights and analyses that help the bank make sound business decisions \u2013 whether in the areas of product development or customer profitability. We also provide capital management, business planning, forecasting, and tax and accounting advisory services.\n\nResponsibilities\n\nHong Kong ALCO and Balance Sheet Management:\n\nAssist the Team Head and HK ALCO in formulating balance sheet strategies and presenting this in an effective manner to ALCO/senior management. Maintain close on-the-ground engagements with the business units to understand business drivers and execute balance sheet steers efficiently.\n\nFunds Transfer Pricing (FTP) Calibration:\n\nBe familiar with FTP policies and principles. Manage day-to-day FTP setting in line with the Hong Kong ALCO strategy. Interact with the business units for any FTP quotations and program discussions.\n\nBalance Sheet Analytics:\n\nProvide data-driven insights into balance sheet trends, risks, and mitigation strategies, which would lead to increased balance sheet efficiency (Net Interest Income, Net Interest Margin, Return on Equity, etc). Be familiar with analytics tools available.\n\nMarkets:\n\nSupport local execution of the HQLA duration rebalancing portfolio and contribute to market views. Manage HK wholesale funding requirements to maintain structural liquidity ratios.\n\nRegulatory & Others:\n\nEnsure all relevant regulatory liquidity ratios managed by CT are adhered to. Be familiar with Central Operations market risk limits and ensure adherence.\n\nAssist the Team Head in management reporting and provide CT support to strategic projects when required.\n\nRequirements\n\n5+ years in balance sheet management (Asset Liability Management, Funding & Liquidity, Market and Liquidity risk, Capital, etc.) functions. Business experience with close interaction with ALCO/ balance sheet management functions would be considered.\nHaving experience working in a dealing room environment will be an advantage.\nUniversity degree in finance/ accounting/ economics/ risk management/ engineering, preferably with CPA/CFA/FRM qualifications and/or Certified Treasury Management Professional under HKMA\u2019s Enhanced Competency Framework in Treasury Management (ECF-TM).\nA strong understanding of financial markets products \u2013 FX swaps, derivatives, MTNs, regulatory assets (HQLA), etc\nUnderstanding key drivers of balance sheet management \u2013 liquidity ratios, FTP, capital\nFamiliar with liquidity regulations in HK\nKeeping abreast of macro-economic environment and implications on funding markets/liquidity condition.\nStrong communication and interpersonal skills in stakeholders\u2019 management\nSelf-starter with ability to multi-task, strong desire to learn and to be a team player\nDemonstrated ability to deliver against tight deadlines\nMotivated to establish and drive projects within Finance team and with Group\nFamiliarity with market data systems (Reuters, Bloomberg) and Murex would be an advantage.\n\nApply Now\n\nWe offer a competitive salary and benefits package and the professional advantages of a dynamic environment that supports your development and recognises your achievements.\n\nWe regret only shortlisted candidates will be notified.", "employment_types": ["Full Time"], "selling_points": ["Pension Fund Scheme", "Medical Coverage for Family", "Career Development"], "locations": ["Central"], "categories": ["Accounting", "Treasurer", "Banking / Finance", "Corporate Banking", "Treasury"], "post_time": "2022-01-06T09:25:36Z", "salary": {"currency": null, "max": null, "min": null, "period": "monthly", "term": null}, "salary_visible": false, "title_keywords": ["vice president"], "responsibilities": [], "requirements": {"degrees": [], "majors": [], "languages": [], "language_level": [], "hard_skills": [], "soft_skills": [], "languages_combined": []}, "experience_required": {"duration": [], "field": []}}, {"job_id": "100003009036762", "location_code": "hk", "company": "Industrial and Commercial Bank of China (Asia) Limited", "job_title": "Senior Fixed Income Sales Manager, Global Capital Financing", "description": "Job Responsibilities\nAssist the team head in fixed income distribution to achieve annual business targets and develop strong customer distribution channel\nTo perform the functions of marketing, customer service, order taking, dealing duties and team administration\nHandle all inquiries from customers, external counterparts and internal colleagues\nWork closely with Relationship Managers on trading account set up and limit application\nProvide idea and deliver solution to assist formulating and implementing distribution strategies/programs\nTo study feasibility of new products, ideas and to keep abreast of market development\nTo take up ad hoc assignment when required.\u00a0\nJob Requirements\nUniversity graduate with major in Economics, Finance and Business, preferably with MBA /CFA\nHolder of SFC Type 1 & 4 licenses\n3 year of relevant fixed income experience\nSound knowledge of bonds pricing and bonds marketing\nExperience in managing bonds transactions for private banking institutions, banks, financial institutions and asset managers in Hong Kong and China is preferable\nGood presentation and interpersonal skills\u2022Strong analytical mind and numerical senses\nSelf-motivated, responsible and result-oriented\nAble to work under pressure, independently and be a good team player\nFluent in both written and spoken English and Chinese, including Putonghua", "employment_types": ["Full Time", "Permanent"], "selling_points": [], "locations": ["Central"], "categories": ["Banking / Finance", "Treasury", "Financial Services", "Equities / Capital Markets"], "post_time": "2022-01-10T13:37:47Z", "salary": {"currency": null, "max": null, "min": null, "period": "monthly", "term": null}, "salary_visible": false, "title_keywords": ["sales manager"], "responsibilities": ["ideas", "ad hoc assignment", "develop", "customer service", "order taking", "administration"], "requirements": {"degrees": ["university graduate"], "majors": ["business", "finance", "economics"], "languages": ["putonghua", "english", "chinese"], "language_level": ["fluent"], "hard_skills": ["cfa"], "soft_skills": ["result-oriented", "self-motivated", "independently", "good team player", "responsible", "presentation", "analytical mind", "interpersonal", "work under pressure"], "languages_combined": [{"language": "putonghua", "language_level": ["fluent"]}, {"language": "english", "language_level": ["fluent"]}, {"language": "chinese", "language_level": ["fluent"]}]}, "experience_required": {"duration": ["3 year"], "field": ["financial institutions", "banking"]}}, {"job_id": "100003009033711", "location_code": "hk", "company": "Bank of Communications Co., Ltd. Hong Kong Branch", "job_title": "Relationship Manager (Financial Institutions Department)", "description": "Career Level\nMiddle\nQualification\nDegree\nYears of Experience\n8 years\nJob Type\nFull Time, Permanent\nJob Functions\nBanking / Finance, Corporate Banking, Treasury, Dealing & Trading", "employment_types": ["Full Time", "Permanent"], "selling_points": [], "locations": ["Not Specified"], "categories": ["Banking / Finance", "Corporate Banking", "Treasury", "Dealing & Trading"], "post_time": "2022-01-10T01:37:58Z", "salary": {"currency": null, "max": null, "min": null, "period": null, "term": null}, "salary_visible": false, "title_keywords": ["relationship manager"], "responsibilities": ["banking"], "requirements": {"degrees": ["degree"], "majors": [], "languages": [], "language_level": [], "hard_skills": [], "soft_skills": [], "languages_combined": []}, "experience_required": {"duration": [], "field": []}}, {"job_id": "100003009032176", "location_code": "hk", "company": "Trinity Limited", "job_title": "Senior Manager / Manager - Finance (1 year contract)", "description": "Responsibilities:\n\nEnsure the completion of monthly group reporting\nPrepare and review financial schedules and analysis on a timely basis for management\nHandle bank related documents and schedules\nAssist the implementation of accounting system\nHandle interim and annual reporting and prepare statutory accounts\nEnsure all financial practices are in compliance with corporate policies, guidelines and statutory requirements\nEnhance internal controls in relation to finance and accounting functions and business operations\nParticipate in ad hoc projects as assigned\n\nRequirements:\n\nDegree Holder in Finance, Accounting or related disciplines.\nHaving 8-10 years\u2019 relevant experience in accounting field, preferably with audit experience and 1-2 years in supervisory level\nQualified Accountant (HKICPA/ACCA)\nProficiency in MS Office, Chinese word processing and familiar with accounting softwares such as Microsoft D365, Sun system\nAbility to work independently with minimal supervision\nGood interpersonal skills and able to communicate and interact with people at all levels\nGood command of spoken and written English and Chinese (Cantonese and Mandarin)\nCandidate with more experiences will be considered as Senior Manager\n\nInterested parties please forward detailed resume stating employment history with expected salary by clicking \"Apply Now\".\n\nAll information provided by applicants will be used only for recruitment purposes and will be used strictly in accordance with the Company's personal data policies.", "employment_types": ["Full Time", "Contract"], "selling_points": ["Ensure the completion of monthly group reporting", "Handle interim and annual reporting", "Qualified Accountant (HKICPA/ACCA)"], "locations": ["Wan Chai"], "categories": ["Accounting", "Finance / Accounting Manager", "Financial Analyst", "Banking / Finance", "Treasury"], "post_time": "2022-01-07T10:27:11Z", "salary": {"currency": null, "max": null, "min": null, "period": "monthly", "term": null}, "salary_visible": false, "title_keywords": ["senior manager", "manager"], "responsibilities": ["reporting", "management", "schedules", "related documents", "analysis", "review", "compliance", "implementation", "policies", "guidelines", "operations", "statutory requirements", "ad hoc projects", "interim and annual reporting"], "requirements": {"degrees": ["degree holder"], "majors": ["related disciplines", "finance", "accounting"], "languages": ["cantonese", "english", "chinese", "mandarin"], "language_level": ["proficiency", "good command"], "hard_skills": ["acca", "chinese word processing", "hkicpa", "accounting softwares", "ms office"], "soft_skills": ["work independently", "interpersonal skills"], "languages_combined": [{"language": "cantonese", "language_level": ["good command"]}, {"language": "english", "language_level": ["good command"]}, {"language": "chinese", "language_level": ["proficiency", "good command"]}, {"language": "mandarin", "language_level": ["good command"]}]}, "experience_required": {"duration": ["1-2 years", "8-10 years"], "field": ["supervisory level", "audit experience", "accounting", "relevant experience"]}}, {"job_id": "100003009018538", "location_code": "hk", "company": "Sumitomo Mitsui Banking Corporation", "job_title": "ASSOCIATE (12-MONTH CONTRACT) \u2013 TREASURY OPERATIONS", "description": "Reporting to the VP, the incumbent is responsible for checking and approving the clerical works in Foreign Exchange team of Treasury Operations:\n\n\nJob Duties & Responsibilities:\nAssist team head to train up and supervise junior staff in handling routine operations\nCo-ordinate with various departments on settlement matter on Treasury Market transactions\nEnsure correct and updated information is posted and checking the work prepared by the colleague for the section\u2019s daily operation of Treasury Market transaction settlement\nMonitor routine operational duties including checking and approving payments, confirming details of trades and monitor of completeness of documentation exchanged with counter parties or concerning sections\nPrepare and ensure the accuracy of regular or timely reports of Treasury Market Transactions to Head Office\nTackle various problems coming up to the Section and deal with unsettled instructions and prepare the instructions via CHATS / RTGS, SWIFT, CMU and advice to counter-parties\nRequirements:\nHKDSE Level or above with good academic results. Degree or diploma holder in related discipline with lesser experience will also be considered\nOver 5 years of relevant experience in handling Treasury settlement\nKnowledge of operating Treasury Market products, SWIFT message, RTGS-CHATS and\u00a0\u00a0 CMU systems\nGood P.C. knowledge in MS Office application\nEfficient and accurate to complete the work on time\nWilling to accept extra tasks with good prioritizing the works\nA team player and able to maintain a pleasant relationship with colleagues\nPlease apply with detailed resume stating latest and expected salary by email via \"Apply now\".\nApplication details will be used only for recruitment purposes, and will be destroyed after 1 year. Applicants not contacted after 6 weeks may consider their applications unsuccessful.", "employment_types": ["Full Time", "Contract"], "selling_points": ["Responsible for checking & approving the clerical", "Degree or diploma holder in related discipline", "Over 5 years of relevant experience"], "locations": ["Not Specified"], "categories": ["Banking / Finance", "Treasury", "Others", "Order Processing & Operation / Settlement"], "post_time": "2022-01-04T03:52:12Z", "salary": {"currency": null, "max": null, "min": null, "period": null, "term": null}, "salary_visible": false, "title_keywords": ["operations", "associate"], "responsibilities": ["co-ordinate with", "operations", "daily operation", "checking", "transactions", "monitor", "timely reports", "payments", "documentation", "operational duties"], "requirements": {"degrees": ["diploma holder", "degree", "hkdse"], "majors": [], "languages": [], "language_level": [], "hard_skills": ["swift", "c", "ms office"], "soft_skills": ["efficient", "pleasant", "team player", "accurate", "prioritizing", "detailed"], "languages_combined": []}, "experience_required": {"duration": ["5 years"], "field": ["related", "relevant experience"]}}, {"job_id": "100003009026870", "location_code": "hk", "company": "Bangkok Bank Public Co Ltd", "job_title": "Treasury FX Dealer (Ref: TR-08/167/240-DB)", "description": "We are now seeking a high caliber candidate to join our Hong Kong Branch.\n\nResponsibilities:\n\nAchieve assigned FX budget within agreed trading limit(s)\nProvide competitive rate quotation for both internal and external parties\nMonitor FX exposures\nPrepare FX commentary and FX reports\nParticipate in New Core Banking System development projects\nEnhance desk efficiency\nBack up team members within department\nComply with internal and external regulatory requirements and also follow code of conducts set by bank and industry\nMaintain supervision and coaching of junior trader\n\nRequirements:\n\n\nDegree holder or above\nMinimum 5 years of relevant experience. Trading knowledge in spot, forward and swap is a MUST\nProficiency in computer applications such as Excel, Word and PowerPoint. Well-versed in performing e-platform trading\nGood team player with strong analytical, problem solving and interpersonal skills\nSelf-motivated and able to work under pressure and overtime\n\nWe offer excellent career prospects to the right candidate. Salary will be commensurate with qualifications and experience. Interested parties please apply with full resume, stating current / expected salary and availability to The Human Resources Manager, Bangkok Bank Public Co. Ltd., Bangkok Bank Building, 28 Des Voeux Road Central, Hong Kong.\n\nPersonal data provided by job applicants will be used solely for considering suitability for the post and strictly in accordance with our personal data policies which are available on request.\n\n(Only shortlisted candidates will be contacted.)", "employment_types": ["Full Time"], "selling_points": [], "locations": ["Central"], "categories": ["Banking / Finance", "Corporate Banking", "Treasury"], "post_time": "2022-01-06T08:49:05Z", "salary": {"currency": null, "max": null, "min": null, "period": "monthly", "term": null}, "salary_visible": false, "title_keywords": ["dealer"], "responsibilities": ["regulatory requirements", "quotation", "monitor", "budget", "internal and external parties", "maintain", "reports", "banking"], "requirements": {"degrees": ["degree holder"], "majors": [], "languages": [], "language_level": [], "hard_skills": ["problem solving", "excel", "word", "powerpoint"], "soft_skills": ["good team player", "self-motivated", "problem solving", "interpersonal skills", "work under pressure"], "languages_combined": []}, "experience_required": {"duration": ["minimum 5 years"], "field": ["relevant experience"]}}, {"job_id": "100003009027380", "location_code": "hk", "company": "Conners Consulting Limited", "job_title": "Market Risk or Liquidity Risk Management (Multiple bank openings 35K - 60k)", "description": "Our client are well-known and expanding commercial banks and now looking for high calibre to join their group.\n\n\u00a0Responsibilities\n\nHandle liquidity risk measurement, monitoring market / liquidity risk, PnL for Trading and Banking book, IRRBB, stress test and ALCO materials and reporting\nSupport to implement strategies over Bank\u2019s asset and liabilities, balance sheet growth and projection, with an on-going monitoring of the result\nSupport risk projects and review on market and liquidity risk policies and procedures\nContribute to the expansion and improvement of the region's funding risk assessment by in depth review and analysis\n\n\u00a0Requirements\n\nDegree holder in Finance, Risk Management, Accounting, or other quantitative discipline, preferably with professional qualification in CPA, FRM or CFA\nIn depth knowledge on the market risk or liquidity risk management\nWith minimum work experience of 2 years from banking industry\nMature, able to work independently under pressure and cooperate well with teammates\u00a0\nProficient in written and spoken English and Chinese\u00a0\n\nTo apply, please send your detailed resume to winnie[at]connersconsulting[dot]com or contact Winnie Lai at 3618 8348 for a confidential discussion.\n\nOnly shortlisted candidates will be notified.\n\nApplicants who are not contacted within two weeks may consider their applications unsuccessful.\n\nAll data collected will be used for recruitment purpose only & will be used strictly confidential.\n\nConners Consulting Limited\n2005 Kai Tak Commercial Building 317 Des Voeux Road Central Hong Kong\n\n\nTel: (852) 3996 8090\n\nWebsite: www.connersconsulting.com", "employment_types": ["Full Time", "Permanent"], "selling_points": ["Urgent with attractive remuneration", "Excellent staff welfare", "Market or Liquidity Risk Management"], "locations": ["Central & Western Area"], "categories": ["Banking / Finance", "Analyst", "Treasury", "Risk Management"], "post_time": "2022-01-06T09:51:03Z", "salary": {"currency": null, "max": null, "min": null, "period": "monthly", "term": null}, "salary_visible": false, "title_keywords": [], "responsibilities": ["reporting", "policies", "analysis", "monitoring", "measurement", "review", "procedures", "banking", "balance sheet"], "requirements": {"degrees": ["degree holder"], "majors": ["finance", "accounting", "risk management"], "languages": ["english", "chinese"], "language_level": ["proficient"], "hard_skills": ["cfa", "cpa", "frm"], "soft_skills": ["work independently", "under pressure", "mature", "detailed"], "languages_combined": [{"language": "english", "language_level": ["proficient"]}, {"language": "chinese", "language_level": ["proficient"]}]}, "experience_required": {"duration": ["of 2 years"], "field": ["banking industry"]}}, {"job_id": "100003009019772", "location_code": "hk", "company": "China Everbright Securities International Company Limited", "job_title": "FX Dealer", "description": "Ref: D/EBSHKFX/040122DB/61\n\u00a0\n\n\nResponsibilities\n\n\nHandle the execution and operation functions on Forex\nProvide general assistance to clients over the phone or via the web\nSit on the Forex desk and support the client on-boarding process\nHandle account opening and prepare\u00a0various reports\nMaintain good relationship with existing clients\n\nRequirements\n\nSecondary school graduate or above\nMinimum 1 year's relevant experience\u00a0in foreign exchange\nHolder of SFC\u00a0license for\u00a0Type 3\u00a0regulated activity\u00a0preferred\nGood interpersonal skills and detail-oriented\nGood command of both written and spoken English and Chinese. Fluency in Putonghua an advantage\nShift duty may require\nCandidate with more experience will be considered as Senior\u00a0Dealer.\n\n\n\nWe offer a competitive remuneration package to the right candidate. If you are interested in the post, please send your resume together with\u00a0your present\u00a0and\u00a0expected salaries\u00a0by clicking\u00a0\u201cApply Now\u201d.\n\n\nFor more information about China Everbright Securities International Company Limited, please visit\u00a0www.ebshk.com.\n\nWe are an equal opportunity employer\u00a0and welcome applications from all qualified candidates. All applications will be treated in the strictest confidence. Personal data provided will be used for recruitment purposes only. The job applicant will assume all or any risks arising out of or in connection with the job application transmission process prior to our actual receipt of the same including but not limited to accidental or unauthorized loss or disclosure of personal information, to which we will not be responsible in any way.\n\u00a0\nUnder the Personal Data (Privacy) Ordinance, you may request access to, and / or correction of your personal data in relation to your application. If you wish to do so, please email to us.", "employment_types": ["Full Time", "Permanent"], "selling_points": [], "locations": ["Causeway Bay"], "categories": ["Banking / Finance", "Retail Banking", "Treasury", "Dealing & Trading"], "post_time": "2022-01-04T10:32:01Z", "salary": {"currency": null, "max": null, "min": null, "period": "monthly", "term": null}, "salary_visible": false, "title_keywords": ["dealer"], "responsibilities": ["account opening", "reports", "maintain good relationship"], "requirements": {"degrees": [], "majors": [], "languages": ["putonghua", "english", "chinese"], "language_level": ["fluency", "advantage", "good command"], "hard_skills": ["sfc license", "exchange"], "soft_skills": ["interpersonal skills", "detail-oriented"], "languages_combined": [{"language": "putonghua", "language_level": ["fluency", "advantage"]}, {"language": "english", "language_level": ["good command"]}, {"language": "chinese", "language_level": ["good command"]}]}, "experience_required": {"duration": ["minimum 1 year"], "field": ["relevant experience"]}}, {"job_id": "100003009030390", "location_code": "hk", "company": "Hays", "job_title": "Foreign Bank - Product Control Manager", "description": "Your new company\nA leading Corporate Bank in Asia, providing a wide range of banking and financial services and products both locally and regionally, is currently looking for a Product Conduct to drive effective product control and valuation control related to Global Markets products, FX, MM, while coordinating with treasury system enhancement projects and streamlining related policy and procedures.\n\nYour new role\nAs a Product Control Manager, you will be working in a team of 3 focusing on Greater China and local financial products, you are expected to perform P&L analysis, financial statement analysis and provide advise on the accounting treatments with different products.\n\nWhat you'll need to succeed\n\nMinimum 8 years of hands-on product control and accounting experience\nBachelor Degree or above in relevant disciplines;\nKnowledge and experience in VBA, SQL or related programming languages (C++ or Java) preferred;\n\nWhat you'll get in return\n\nSuccessful candidate will be offered with a monthly salary ranging from HKD 45,000 to 65,000 depending on your interview performance and level of experience;\nWith regional reporting exposure and comprehensive employee benefits;\nA great career advancement opportunity with a stable bank in the region.\n\n\nWhat you need to do now\nIf you're interested to this role or would like to consult for other Accounting / Audit / Finance opportunities within the banking industry, please send your CV in Microsoft Word format to Freeman.Pang@hays.com.hk", "employment_types": ["Full Time", "Permanent"], "selling_points": ["Prime Office Location", "Comprehensive Employee Benefits Package", "Flat-team structure with wide scope of products"], "locations": ["Admiralty"], "categories": ["Accounting", "Accountant", "Financial Controller", "Banking / Finance", "Treasury"], "post_time": "2022-01-07T07:23:40Z", "salary": {"currency": "HKD", "max": 54999, "min": 45000, "period": "monthly", "term": null}, "salary_visible": true, "title_keywords": ["manager"], "responsibilities": ["valuation", "control", "analysis", "procedures", "p&l", "banking", "financial statement", "enhancement projects"], "requirements": {"degrees": ["degree or above", "bachelor"], "majors": [], "languages": [], "language_level": [], "hard_skills": ["vba", "java", "c++", "analysis", "sql", "programming"], "soft_skills": ["hands-on"], "languages_combined": []}, "experience_required": {"duration": ["minimum 8 years"], "field": ["sql", "programming", "accounting experience", "related"]}}, {"job_id": "100003009015659", "location_code": "hk", "company": "Bank of China (Hong Kong) Limited", "job_title": "Senior Treasury Marketing Manager/Treasury Marketing Manager\uff08GM-Institutional Sales\uff09", "description": "Responsibilities:\n\nExecute tasks delegated by supervisors\n\nDevelop business strategy and working plan for institutional customers\n\nCoordinate with relationship managers to develop and maintain institutional client relationship by providing professional consulting and trading services. Be responsible for customizing financing solutions to help clients reduce their financing costs or currency risks, and providing professional advice on packaging of products to seize hedging or investing opportunities.\n\nProvide timely information/insights to supervisors regarding market opportunities and changes of clients\u2019 needs, and update the marketing strategy accordingly.\n\nAssist direct supervisor in managing daily operation of business; Oversee the progress of business projects to meet the preset target\n\nComply with regulators\u2019 rules and bank\u2019s policies regarding money laundering and due diligence. The corresponding performance will be evaluated.\n\nRequirements:\n\nExcellent analytical and marketing skills\n\nA strong sense of responsibility and willingness to learn regarding the innovation and application of financial products\n\nAdhere to professional conduct with good personal qualities\n\nLicensed for dealing in securities (Type 1) and advising on securities (Type 4) ;other necessary professional qualification licenses for treasury marketing\n\nAt least 3 years\u2019 experience in financial services industry including 1 years\u2019 experience in Treasury Marketing.\n\nExcellent command of both spoken and written English and Chinese including Mandarin\n\nWell understand treasury products including their basic principles, features and risk factors\n\nExcellent skills of providing investment and hedging strategy for customers", "employment_types": ["Full Time"], "selling_points": ["Treasury Marketing", "Global Markets", "Southeast Asia"], "locations": ["Others"], "categories": ["Banking / Finance", "Treasury"], "post_time": "2022-01-03T07:17:15Z", "salary": {"currency": null, "max": null, "min": null, "period": "monthly", "term": null}, "salary_visible": false, "title_keywords": ["marketing manager", "sales"], "responsibilities": ["due diligence", "consulting", "business projects", "bank\u2019s policies", "coordinate with", "daily operation", "develop", "maintain", "plan", "costs"], "requirements": {"degrees": [], "majors": [], "languages": ["english", "chinese", "mandarin"], "language_level": ["excellent"], "hard_skills": ["marketing skills", "basic"], "soft_skills": ["sense of responsibility"], "languages_combined": [{"language": "english", "language_level": ["excellent"]}, {"language": "chinese", "language_level": ["excellent"]}, {"language": "mandarin", "language_level": ["excellent"]}]}, "experience_required": {"duration": ["at least 3 years", "1 years"], "field": ["financial services industry", "marketing"]}}, {"job_id": "100003009026294", "location_code": "hk", "company": "Bank of China (Hong Kong) Limited", "job_title": "Senior Treasury Product Manager/Treasury Product Manager(GM)", "description": "Responsibilities:\n\nWith reasonable sensitivity to the market and solid financial product knowledge and experience, dynamically capture customer needs and discover potential market opportunities, and provide the management with timely and professional product development strategies and recommendations\nFast learner and able to integrate information from multiple aspects to achieve a deep understanding. Apply new market trends and new technologies in product development with consideration of reality needs.\nAble to independently perform product development tasks, including but not limited to drafting system UR, conducting PDD and coordinating development projects, etc.\nAble to continuously review daily products and processes with a developmental perspective, and propose and complete optimization in time\nParticipate in marketing, employee training, etc.\nCustomer-centric, sensitive to risks and always adhere to compliance principles, and focus on efficiency and effectiveness\n\nRequirements:\n\nDegree holder or above with major in Business Administration, Finance, Investment, Economics or related discipline\nProfessional qualifications in CFA, FRM and equivalent will be an advantage\nLicensed for HKMA Type 1 (dealing in securities) and Type 4 (advising on securities) or equivalent\n5-8 years relevant working experience in treasury product development and management in banking / financial industry\nProfound knowledge and understanding of the relevant regulations and policies of the financial market in both China and Hong Kong, especially for the CNY market\nStrong project management skills\nStrong planning, coordination and communication skills\nExcellent command of\u00a0spoken and written English and Chinese, Putonghua speaking will be an advantage\n\nWe offer competitive remuneration package and comprehensive fringe benefits including medical and life insurance, and different types of allowances to the right candidate. Interested parties, please submit your application online. For details, please visit our website\u00a0http://www.bochk.com\n\nTo apply:\u00a0\u00a0\n\nInterested candidates, please click APPLY NOW \u00a0to apply.\n\nData collected would be used for recruitment purposes only. It might also be disclosed to our subsidiaries or Associated Companies to process the information for appointment. Applicants who do not hear from us within 8 weeks may consider their application unsuccessful and their data will be destroyed within 12 months of receipt.", "employment_types": ["Full Time"], "selling_points": ["With reasonable sensitivity to the market", "With solid financial product knowledge", "5-8 years relevant working experience"], "locations": ["Not Specified"], "categories": ["Banking / Finance", "Treasury", "Others"], "post_time": "2022-01-06T07:54:41Z", "salary": {"currency": null, "max": null, "min": null, "period": "monthly", "term": null}, "salary_visible": false, "title_keywords": ["product manager"], "responsibilities": ["compliance", "management", "review"], "requirements": {"degrees": ["degree holder"], "majors": ["finance", "economics", "business administration"], "languages": ["putonghua", "english", "chinese"], "language_level": ["advantage", "excellent"], "hard_skills": ["professional qualifications", "hkma", "cfa", "project management", "frm"], "soft_skills": ["communication skills", "project management skills", "comprehensive", "coordination"], "languages_combined": [{"language": "putonghua", "language_level": ["excellent"]}, {"language": "english", "language_level": ["advantage", "excellent"]}, {"language": "chinese", "language_level": ["advantage", "excellent"]}]}, "experience_required": {"duration": ["5-8 years"], "field": ["management", "financial industry", "relevant working experience", "banking", "product development"]}}, {"job_id": "100003009014140", "location_code": "hk", "company": "Be Myjob Company Limited", "job_title": "Manager / VP - Treasury Operations", "description": "Responsibilities:\n\nManage and oversee the Treasury operations activities, day-to-day clearing and settlements of Treasury products, corporate actions for fixed income, OTC market and lending products to meet the financial obligations of the Bank.\nMonitor all SWIFT/ RTGS/ JETCO and FPS payments that are timely executed and reconciled.\nDesign the workflow and control for Treasury and Payment operations to ensure full regulatory compliance with the Bank and HKMA.\nPerform timely reconciliation for Treasury and Payment Operations and settlement functions, discrepancy review, resolving breaks and exceptions.\nHandle onboarding process and application documentations for Interbank account opening\nManage and perform Treasury and Payment system UAT testing, deployment process and enhancement\n\nRequirements:\n\nDegree holder in business administration or related discipline\nMinimum of 10 years\u2019 experience in Treasury and Payment Operations with at least 5 years in supervisory function.\u00a0\nSolid knowledge and understanding treasury and payment products and systems\nSolid understanding of risk mitigation of fraud in Treasury and Payment Operations\nIndependent, enthusiastic and able to work under pressure\nProficiency in MS Office, basic VBA programming skills preferred\nGood command of written and spoken English and Chinese, proficiency in Putonghua is a preferred.", "employment_types": ["Full Time"], "selling_points": ["Treasury Operation / Payments", "Treasury Settlement / Interbank Account Opening", "Less Experience will be considered as Manager"], "locations": ["Quarry Bay"], "categories": ["Banking / Finance", "Retail Banking", "Treasury", "Order Processing & Operation / Settlement"], "post_time": "2022-01-03T03:04:48Z", "salary": {"currency": null, "max": null, "min": null, "period": "monthly", "term": null}, "salary_visible": false, "title_keywords": ["operations", "manager"], "responsibilities": ["control", "operations", "account opening", "compliance", "monitor", "review", "design", "uat testing", "payment", "payments"], "requirements": {"degrees": ["degree holder"], "majors": ["business administration"], "languages": ["putonghua", "english", "chinese"], "language_level": ["proficiency", "good command"], "hard_skills": ["vba", "basic", "programming", "ms office"], "soft_skills": ["work under pressure", "independent", "enthusiastic"], "languages_combined": [{"language": "putonghua", "language_level": ["proficiency", "good command"]}, {"language": "english", "language_level": ["proficiency", "good command"]}, {"language": "chinese", "language_level": ["proficiency", "good command"]}]}, "experience_required": {"duration": ["at least 5 years", "minimum of 10 years"], "field": ["supervisory"]}}, {"job_id": "100003009019429", "location_code": "hk", "company": "Wellesley Associates Limited", "job_title": "FX Specialist / Treasury Specialist- Consumer Banking  (Relationship Managers are welcomed)", "description": "My client is a well-established and top tier foreign bank with global presence and a comprehensive facility in banking & wealth management. They\u2019re looking FX Specialist / Treasury Specialist to join their team.\n\n\nDuties:\n\nGiving house view and FX market update to the floor and clients\nGenerate Foreign Exchange product ideas to the floor that are suitable to clients\nHelp Relationship Managers and Investment Counsellors in pitching clients on optimal Foreign Exchange solutions\nExecutes Foreign Exchange orders, including cash, options, and structured notes, and works closely\nResponsible for driving pairing Bankers to meet team goals, including coaching\n\nRequirements:\n\n2 years of experience in FX margin clients and individual accounts\nStrong knowledge and experience in Foreign Exchange market\nAble to derive and deliver Foreign Exchange recommendations across multiple currencies and forecasting\nSolid dealing capabilities, with attention to details and good knowledge in dealing systems\nAble to work under pressure and execute client orders accurately and effectively\nGood knowledge in MS word / Excel / PowerPoint\nLicensed in HKSI paper 1, 7, 8\nIf you're interested in this role, forward an up-to-date copy of your CV via email, or call directly on +852 2847 9962. If this job isn't quite right for you but you are opened for a new position within banking / wealth management side, please contact me for a confidential discussion on your career", "employment_types": ["Full Time", "Permanent"], "selling_points": ["Join a team with great dynamics", "Strong support from management", "Attractive total compensation package"], "locations": ["Not Specified"], "categories": ["Banking / Finance", "Retail Banking", "Treasury"], "post_time": "2022-01-04T07:39:34Z", "salary": {"currency": null, "max": null, "min": null, "period": "monthly", "term": null}, "salary_visible": false, "title_keywords": ["specialist"], "responsibilities": ["ideas"], "requirements": {"degrees": [], "majors": [], "languages": [], "language_level": [], "hard_skills": ["excel", "hksi paper", "powerpoint", "exchange", "ms word"], "soft_skills": ["interested in", "attention to details", "work under pressure"], "languages_combined": []}, "experience_required": {"duration": ["2 years"], "field": []}}, {"job_id": "100003009027258", "location_code": "hk", "company": "Zhongtai Financial International Limited", "job_title": "Asset Management - Product Manager \u8d44\u4ea7\u7ba1\u7406\u90e8 - \u56fa\u6536\u4ea7\u54c1\u7d93\u7406", "description": "Responsibilities:\n\nResearch and structure new product ideas. Familiar with product design procedures, prepare legal documents for fund launching;\nUnderstand the needs of Asset Management market, able to identify product opportunities in the market and matching to targeted customer;\nCoordinate with sales team in presenting on-the-shelf products to distribution channels & targeting customers;\nAssessing feasibility and profitability of various ad hoc investment proposals;\n\nRequirements:\nMinimum 1 years\u2019 experience in finance field, preferable in renowned Asset Management Company;\nExperience with offshore fund market will be an advantage;\nAble to work independently with good problem solving skill and analytical mindset;\nGood team player with excellent communication and interpersonal skills;\nGood command of spoken and written Mandarin and English is a MUST.", "employment_types": ["Full Time"], "selling_points": ["Familiar with product design procedures", "Minimum 1 years\u2019 experience in finance field", "Research and structure new product ideas"], "locations": ["Central"], "categories": ["Banking / Finance", "Treasury", "Fund Management", "Asset Management"], "post_time": "2022-01-06T09:30:07Z", "salary": {"currency": null, "max": null, "min": null, "period": "monthly", "term": null}, "salary_visible": false, "title_keywords": ["product manager", "asset management"], "responsibilities": ["ideas", "ad hoc", "coordinate with", "procedures", "product design", "sales team", "asset management"], "requirements": {"degrees": [], "majors": [], "languages": ["english", "mandarin"], "language_level": ["good command"], "hard_skills": ["problem solving"], "soft_skills": ["good team player", "work independently", "communication and interpersonal skills", "problem solving skill"], "languages_combined": [{"language": "english", "language_level": ["good command"]}, {"language": "mandarin", "language_level": ["good command"]}]}, "experience_required": {"duration": ["minimum 1 years"], "field": ["finance", "asset management"]}}, {"job_id": "100003009022095", "location_code": "hk", "company": "Asia Progress Executive Limited", "job_title": "Director/VP/AVP; Fixed Income Sales ( many post ) - Securities Brokerage", "description": "Our client is a Top Tier Chinese Investment Bank.To cope with the rapid business expansion, they are now inviting high caliber candidates to join the team\n\nDirector/VP/AVP; Fixed Income Sales-\u00a0Securities Brokerage /PRC investment\u00a0\n\nKey Responsibilities\n\nDevelop and maintain relationships with institution clients including but not limited to banks, insurance companies, large corporates, fund houses and family offices\nPromote and distribute company's primary fixed income deals from marketing, selling to complete execution\nAbility to explore and execute clients' secondary fixed income flows\nHandle client on-boarding matters, daily inquiries and market updates\nSolicit new business opportunities from clients/market and work closely with DCM team\nDistribute fixed income products in primary market and trade in secondary market\n\nSkills and experience required\n\nDegree holder / related in Finance\nMinimum 3 years of sales experience in Fixed Income, having strong institutional client connection particularly in Greater China market\nMaster degree in Finance, Economics, Accounting or Business Administration from a renowned university, CFA is preferred\nBusiness centric and has good analytical skills and extensive product knowledge\nStrong communication/liaison skills and ability to work independently under pressure in achieving business targets\nFluent in Mandarin and English is a must, Cantonese is a plus but not required\n\nPlease send full resume with\u00a0present & expected\u00a0salary to expedite sourcing\u00a0in\u00a0MS-WORD\u00a0format by clicking \u201cAPPLY NOW\u201d\nPlease quote our reference in your application\nPersonal data provided by job applicants will be used strictly in accordance with the employer\u2019s personal data policies, a copy of which will be provided upon request\nAll information provided will be used for recruitment purpose only", "employment_types": ["Full Time"], "selling_points": ["Deg/abv at 3-5 yr Fixed Income Sales in China mkt", "Fixed Income Sales in Securities Brokerage", "Fixed income/Bonds /Structure products in FI"], "locations": ["Central & Western Area"], "categories": ["Banking / Finance", "Investment", "Treasury", "Financial Services"], "post_time": "2022-01-05T05:00:49Z", "salary": {"currency": null, "max": null, "min": null, "period": "monthly", "term": null}, "salary_visible": false, "title_keywords": ["director", "sales"], "responsibilities": ["maintain relationships", "brokerage", "business opportunities", "policies", "develop", "communication", "recruitment", "personal data", "insurance", "administration"], "requirements": {"degrees": ["master degree", "degree holder"], "majors": ["finance", "economics", "business administration", "accounting"], "languages": ["cantonese", "english", "chinese", "mandarin"], "language_level": ["fluent"], "hard_skills": ["ms-word", "plus", "cfa", "analytical skills", "rapid"], "soft_skills": ["work independently", "under pressure", "analytical skills", "communication", "extensive"], "languages_combined": [{"language": "cantonese", "language_level": ["fluent"]}, {"language": "english", "language_level": ["fluent"]}, {"language": "chinese", "language_level": []}, {"language": "mandarin", "language_level": ["fluent"]}]}, "experience_required": {"duration": ["minimum 3 years"], "field": []}}, {"job_id": "100003009024574", "location_code": "hk", "company": "China CITIC Bank International Limited", "job_title": "Senior Manager/Assistant Vice President, Securities Services (Agency & Trust)", "description": "Job Purpose\nThis role is principally responsible for the execution and delivery of corporate trust and agency services around capital market and structured finance transactions, with additional opportunities to support new business and platform development initiatives for the Agency & Trust business.\nIt provides great exposure to professionals across the corporate trust, loan agency, issuer services or related industry sectors who are motivated to develop new business platform and relationship as well as to utilize their execution and delivery experience in agency and trust products.\n\nKey Responsibilities\n\n\n(I)\u00a0Product and Business Development\n\n\nAssist with the development and implementation of product program and business plans\nAssist with the development and ongoing enhancement of product materials, procedures and guidelines for Agency and Trust products\nEstablish internal and external business relationships to advocate Agency and Trust products\n(II)\u00a0\u00a0 Collaboration & Execution\nLiaise with clients, deal parties as well as stakeholders such as Relationship Managers, Legal & Compliance, Operations, Clearing Systems to perform review of transaction documentation and deal mechanics from Agency and Trust\u2019s perspective\nWork closely with clients and deal parties to facilitate seamless transaction execution and closing in Agency and Trust\u2019s capacities\nCoordinate transaction implementation to ensure client and transaction requirements are fully delivered\n(III)\u00a0 Post-closing Transaction Services Delivery\nManage all aspects of assigned transactions and client portfolio in a manner that complies with transaction documentation, legal and regulatory requirements as well as internal control policies and procedures to ensure superior client and delivery experience\nPerform monitoring of covenants compliance as per transaction documentation, and undertake periodic review of transactions and accounts\nAssist in developing and enhancing our client experience\nRequirements\n\nDegree holder in Law, Economics, Finance or related disciplines\nAt least 3-5 years of relevant work experience in related areas ideally in corporate trust, agency or capital markets\nWorking knowledge of key capital market instruments and transaction structure such as Eurobond, structured finance, syndicated loans, escrow, equity, securities fund, and other investment products\nMotivated and enthusiastic working-attitude and team-spirit\nStrong relationship building and interpersonal skills\nStrong analytical and problem solving skills\nGood command of written and spoken English and Chinese (including Putonghua)\nFor more details about career opportunities with the Bank, please visit our website http://www.cncbinternational.com/careers/en/index.jsp. Please apply with full resume stating current and expected salaries.\n\n\nPersonal data collected will be used for recruitment related purposes only. Applicants not invited for interview within 6 weeks may consider their applications unsuccessful. However, applicants may be considered for other suitable positions within the Group for a period of not more than 2 years. Personal data will be destroyed at any time after 3 months.\n\nChina CITIC Bank International is committed to being an equal opportunities employer and intends to provide a work environment free of unlawful discrimination or harassment. All employment decisions will be made in a non-discriminatory manner.", "employment_types": ["Full Time", "Permanent"], "selling_points": ["Support new business and platform development", "Product and Business Development", "At least 3-5 years of relevant work experience"], "locations": ["Tsim Sha Tsui"], "categories": ["Banking / Finance", "Treasury", "Financial Services", "Fund Management"], "post_time": "2022-01-06T01:48:18Z", "salary": {"currency": null, "max": null, "min": null, "period": "monthly", "term": null}, "salary_visible": false, "title_keywords": ["senior manager", "assistant vice president"], "responsibilities": ["liaise with clients", "policies", "guidelines", "operations", "regulatory requirements", "compliance", "procedures", "implementation", "business plans", "systems", "review", "coordinate", "transactions", "monitoring", "developing", "documentation", "internal control"], "requirements": {"degrees": ["degree holder"], "majors": ["related disciplines", "finance", "economics", "law"], "languages": ["putonghua", "english", "chinese"], "language_level": ["good command"], "hard_skills": ["problem solving skills", "investment products"], "soft_skills": ["analytical and problem solving skills", "committed", "motivated", "interpersonal skills", "enthusiastic", "structured"], "languages_combined": [{"language": "putonghua", "language_level": ["good command"]}, {"language": "english", "language_level": ["good command"]}, {"language": "chinese", "language_level": ["good command"]}]}, "experience_required": {"duration": ["at least 3-5 years"], "field": ["related", "agency", "capital markets"]}}, {"job_id": "100003009024675", "location_code": "hk", "company": "China CITIC Bank International Limited", "job_title": "Analyst, Corporate Marketing (Contract)", "description": "Key Responsibilities\n\n\nSupport Corporate Marketing team on all Global Markets sales activities/ transactions for Corporate Banking clients, in particular the execution of marketing plans and the budget delivery.\nConduct marketing calls and follow up on all necessary actions.\nFollow up with all necessary reports and take prompt actions for day-to-day reporting and monitoring works.\nConsolidate feedback from clients for improving and sustaining excellent service level.\nParticipate in Global Markets related projects/ business plans as required.\nBuild and maintain accurate MIS for business analysis purposes.\nRequirements\n\nDegree holder in Business Administration, Economics, Finances or related discipline.\nPreferably with 1-2 years\u2019 experience in financial institutions\nBasic knowledge in treasury structured products, sales procedure and compliance requirements\nPossess the required qualifications and license under SFC for dealing in securities.\nStrong analytical skills, self-motivated with high degree of initiatives.\nGood interpersonal and communication skills.\nGood command of written and spoken English and Chinese (including Putonghua).\n\n* Fresh graduate will also be considered.\n\n\n\n\u00a0For more details about career opportunities with the Bank, please visit our website http://www.cncbinternational.com/careers/en/index.jsp. Please apply with full resume stating current and expected salaries.\n\nPersonal data collected will be used for recruitment related purposes only. Applicants not invited for interview within 6 weeks may consider their applications unsuccessful. However, applicants may be considered for other suitable positions within the Group for a period of not more than 2 years. Personal data will be destroyed at any time after 3 months.\n\nChina CITIC Bank International is committed to being an equal opportunities employer and intends to provide a work environment free of unlawful discrimination or harassment. All employment decisions will be made in a non-discriminatory manner.", "employment_types": ["Full Time", "Contract"], "selling_points": ["Support Global Markets sales activities & projects", "Maintain MIS for business analysis purposes", "Conduct marketing calls & consolidate feedback"], "locations": ["Tsim Sha Tsui"], "categories": ["Banking / Finance", "Analyst", "Treasury", "Others"], "post_time": "2022-01-06T07:57:12Z", "salary": {"currency": null, "max": null, "min": null, "period": "monthly", "term": null}, "salary_visible": false, "title_keywords": ["analyst"], "responsibilities": ["sales activities", "reporting", "marketing plans", "budget", "monitoring", "transactions", "business plans", "maintain", "reports", "banking", "business analysis"], "requirements": {"degrees": ["degree", "fresh graduate", "degree holder"], "majors": ["economics", "business administration"], "languages": ["putonghua", "english", "chinese"], "language_level": ["good command"], "hard_skills": ["basic", "analytical skills"], "soft_skills": ["communication skills", "self-motivated", "analytical skills", "committed", "structured", "interpersonal"], "languages_combined": [{"language": "putonghua", "language_level": ["good command"]}, {"language": "english", "language_level": ["good command"]}, {"language": "chinese", "language_level": ["good command"]}]}, "experience_required": {"duration": ["1-2 years"], "field": ["financial institutions"]}}, {"job_id": "100003009032628", "location_code": "hk", "company": "Hays", "job_title": "Market Risk in Risk Management Department", "description": "Market Risk Roles in Multiple Banks from Chinese and Foreign with Large Exposure\n\nYour new company\nMultiple hiring for market risk positions, covering market risk, liquidity risk and counterparty risk, in top-tier Chinese and foreign banks with large exposure.\n\nYour new role\nYou will be focusing on market risk duties, including market risk trade analysis, daily reports, market risk stress test, risk limit, etc. You will identify, measure and monitor market risk of trading book and banking book's fixed income, interest rate and FX business.\n\nWhat you'll need to succeed\n\nUniversity degree or above in Finance, Risk Management, Accounting, Financial Engineering or other related discipline\nExperience in market risk / liquidity risk / risk management, covered fixed income / interest rate / FX / related derivatives\nDetailed-minded with good organization, interpersonal and communication skills\n\n\nWhat you'll get in return\n\nMultiple levels of market risk job opportunities\nLarge exposure and competitive base salary\nOpportunity to expand your exposure in corporate banking\n\n\nWhat you need to do now\nIf you're interested in this role, click 'apply now' or for further information and a confidential discussion on this role or to find out about more opportunities in credit, contact Jane Chan at Hays on +852 2101 0050 or email jane.chan@hays.com.hk\n\nAt Hays, we value diversity and are passionate about placing people in a role where they can flourish and succeed. We actively encourage people from diverse backgrounds to apply.", "employment_types": ["Full Time", "Permanent"], "selling_points": ["Multiple levels of market risk job opportunities", "Large exposure and competitive base salary", "Opportunity to expand in corporate banking"], "locations": ["Not Specified"], "categories": ["Banking / Finance", "Corporate Banking", "Treasury", "Risk Management"], "post_time": "2022-01-07T12:00:44Z", "salary": {"currency": "HKD", "max": 54999, "min": 20000, "period": "monthly", "term": null}, "salary_visible": true, "title_keywords": [], "responsibilities": ["management", "analysis", "monitor", "communication", "contact", "banking", "daily reports"], "requirements": {"degrees": ["degree or above"], "majors": ["finance", "accounting", "engineering", "risk management"], "languages": ["chinese"], "language_level": [], "hard_skills": ["analysis"], "soft_skills": ["communication skills", "interested in", "diverse", "interpersonal", "passionate about", "detailed"], "languages_combined": [{"language": "chinese", "language_level": []}]}, "experience_required": {"duration": [], "field": ["related", "risk management", "market risk"]}}, {"job_id": "100003009028295", "location_code": "hk", "company": "Dah Sing Financial Group", "job_title": "Senior Manager, Risk Control", "description": "Job Purpose:\nTo maintain the stress testing program of the Bank and to perform the risk management functions in relation to capital management matters and interest rate risk in the banking book (IRRBB).\nMain Responsibilities:\nMaintain and execute the stress testing program and policies including the review of assumptions and methodologies; Play a central role in bank-wide stress testing such as stress tests for ICAAP, recovery planning, capital planning as well as the regulator driven stress testing;\nHandle risk-related capital management matters such as ICAAP review, recovery planning, capital triggers;\nMeasure, monitor and control the IRRBB exposures against approved risk limits and appetite; Maintain proper policies and procedures on IRRBB management;\nMaintain and develop risk reports for internal risk monitoring as well as regulatory reporting in accordance with the applicable regulatory standards and requirements;\nPerform regular and ad hoc risk analysis, simulations and reporting assigned by the Department Head and senior management including the Asset & Liability Management Committee and other risk committees.\nRequirements:\nOver 7 years\u2019 experience in the risk management of treasury, asset and liability management or finance related areas in the banking industry;\nHands-on experience in database management or statistical tools, e.g. SQL, SAS, VBA, etc.;\nUniversity degree in Finance, Risk Management or equivalent; holder of CFA or FRM an added advantage;\nGood knowledge in treasury markets, products, regulatory requirements on risk management and capital adequacy;\nGood interpersonal skills and a good team member.\nPlease note that only shortlisted candidates will be notified.", "employment_types": ["Permanent"], "selling_points": ["Maintain and execute the stress testing program", "7 years experience in the risk management", "University degree in Finance, Risk Management"], "locations": ["Wan Chai"], "categories": ["Banking / Finance", "Treasury", "Financial Services", "Risk Management"], "post_time": "2022-01-07T01:59:44Z", "salary": {"currency": null, "max": null, "min": null, "period": "monthly", "term": null}, "salary_visible": false, "title_keywords": ["senior manager"], "responsibilities": ["reporting", "management", "control", "ad hoc", "recovery planning", "policies", "review", "monitor", "procedures", "testing", "develop", "risk monitoring", "maintain", "reports", "risk analysis", "senior management", "planning"], "requirements": {"degrees": ["university degree"], "majors": ["finance", "risk management"], "languages": [], "language_level": [], "hard_skills": ["vba", "sas", "cfa", "sql", "frm"], "soft_skills": ["hands-on", "team member", "interpersonal skills"], "languages_combined": []}, "experience_required": {"duration": ["7 years"], "field": ["risk management", "management", "banking industry", "related", "finance", "database management"]}}, {"job_id": "100003009011792", "location_code": "hk", "company": "China Construction Bank (Asia) Corporation Limited", "job_title": "Dealer \u2013 Debt Securities Investment, Treasury (Ref no.: DR/DSI/TR/JDB)", "description": "Main responsibilities:\n\nAssist to formulate Debt Investment Strategy.\nLeverage on market intelligence to make debt investment recommendations.\nExecute bond transactions within given risk limits.\nAssist in debt securities portfolio management to achieve profit target.\nPrepare analytical reports on market updates and portfolio review.\nUndertake credit analysis and make rebalancing recommendations.\n\nRequirements:\n\nBachelor degree or above preferably with major in Finance, Economics, Accounting or related disciplines\nMinimum 3 years\u2019 experience in fixed income related working experience including fixed income trading, credit analysis, asset management, etc.\nQualification for Enhanced Competency Framework on Treasury Management is preferable.\nProficiency in computer applications including Bloomberg Terminal, MS Office/ Excel/ Words/PPT.\nGood command of both spoken and written English and Chinese, including Mandarin.\nCandidate with more experience will be considered as Senior Dealer.\n\nTo apply, please send your detailed resume stating present and expected salary to one of the following channels:-\n\nBy Email\nBy Fax: 3718 2910\n\nApplicants who are not contacted within 8 weeks may consider their applications unsuccessful and their personal data will be retained by the bank for a period up to two years.\n\nAll information provided by applicants will be used for recruitment purposes only and will be used strictly in accordance with the bank's personal data policies, a copy of which will be provided upon request.", "employment_types": ["Full Time", "Permanent"], "selling_points": ["Bachelor degree major in Finance, Economics, Acct", "Minimum 3 years\u2019 experience in fixed income", "Enhanced Competency Framework on Treasury Manageme"], "locations": ["Central"], "categories": ["Banking / Finance", "Investment", "Treasury", "Dealing & Trading"], "post_time": "2021-12-31T08:18:40Z", "salary": {"currency": null, "max": null, "min": null, "period": "monthly", "term": null}, "salary_visible": false, "title_keywords": ["dealer"], "responsibilities": ["management", "profit target", "analysis", "review", "transactions", "reports"], "requirements": {"degrees": ["degree or above", "bachelor"], "majors": ["related disciplines", "finance", "economics", "accounting"], "languages": ["english", "chinese", "mandarin"], "language_level": ["good command"], "hard_skills": ["excel", "bloomberg", "words", "credit analysis", "ms office"], "soft_skills": ["detailed"], "languages_combined": [{"language": "english", "language_level": ["good command"]}, {"language": "chinese", "language_level": ["good command"]}, {"language": "mandarin", "language_level": ["good command"]}]}, "experience_required": {"duration": ["minimum 3 years"], "field": ["related", "trading", "asset management"]}}, {"job_id": "100003009011694", "location_code": "hk", "company": "Industrial and Commercial Bank of China (Asia) Limited", "job_title": "Assistant Risk Manager (Fixed Income), Hong Kong Treasury Centre - Hong Kong Branch", "description": "Job Descriptions\n\n\nPerform daily trade review of Fixed Income transactions as second line of defense\nResponsible for product control through daily risk monitoring and reporting\nPerform business analysis of fixed income business line\nHandle risk evaluation of new product and system enhancement\nPerform ad-hoc projects assigned\nRequirements\nBachelor degree or above in Business, Finance or related disciplines\n1- 3 years\u2019 experience in risk management will be an advantage\nGood understanding of financial markets and major risks, especially for fixed income products\nAccurate and detail-oriented with sound judgment and integrity\nTeam player with positive attitude and strong work ethic\nProficient to advanced skills with MS Office (Excel, PowerPoint, Word), familiarity with Bloomberg is preferred\nFresh graduates are also welcomed\nPersonal data collected will be used for recruitment purpose only", "employment_types": ["Full Time", "Permanent"], "selling_points": [], "locations": ["Central & Western Area"], "categories": ["Banking / Finance", "Analyst", "Treasury", "Risk Management"], "post_time": "2021-12-31T08:06:05Z", "salary": {"currency": null, "max": null, "min": null, "period": null, "term": null}, "salary_visible": false, "title_keywords": ["manager", "assistant"], "responsibilities": ["reporting", "control", "review", "transactions", "risk monitoring", "evaluation", "business analysis", "ad-hoc projects"], "requirements": {"degrees": ["degree or above", "bachelor"], "majors": ["related disciplines", "finance", "business"], "languages": [], "language_level": [], "hard_skills": ["excel", "bloomberg", "word", "powerpoint", "ms office"], "soft_skills": ["advanced", "integrity", "detail-oriented", "positive attitude", "work ethic", "team player", "accurate"], "languages_combined": []}, "experience_required": {"duration": ["1- 3 years"], "field": ["risk management"]}}, {"job_id": "100003009009680", "location_code": "hk", "company": "Delta Asia Financial Group", "job_title": "Treasury Analyst  (Ref.: TA_211231_JD974)", "description": "Responsibilities\n\nAnalyze financial data and prepare investment strategy recommendation to ALCO\nKeep abreast of financial markets & global economic for assessing funding & investment opportunities\nPerform in-depth research on fixed income market and fixed income instruments\nGood understanding of the risks of fixed income securities and underlying companies\nProvide quality and timely research reports\nEvaluate investment portfolio performance and present analysis to management\nSupport monitoring and analyzing the Group's interest rate and liquidity risk positions\nResponsible for updating and maintaining the Group's bank credit facilities where applicable\u00a0\u00a0\nParticipate in preparation of annual operating and business plans (budgets) related to investments and related areas\nDevelop financial forecasts and monitors financial health of the Group\nAssist in setting up and maintaining the Group Treasury policies and procedures\nDevelop cash management, investment, and risk mitigation strategies\nPerform other ad hoc duties as required\n\nRequirements\n\nDegree holder in Finance, Risk Management, Accounting or related disciplines\n2+ years of experience working in banking or financial industry, preferably in treasury, risk management or asset & liability management\nCTP or CFA is preferred\nExperience with financial management systems, such as Hyperion & GTreasury\nProficient in computer applications including Excel and Macros\nExceptional analytical and problem-solving skills\nExcellent communication and report writing skills\nA highly-motivated individual with positive and proactive attitude, detail oriented, and able to prioritize tasks\n\nApplication\n\n\nWe offer competitive remuneration and fringe benefits including but not limited to the followings:\n\n15 up to 20 days' Annual Leave\nCaring Leave (including birthday leave, graduation leave, wedding leave, volunteer leave, children graduation leave, children wedding leave, etc.)\nInterested parties, please click \"APPLY NOW\".\u00a0For more information or enquiry, please contact us at +852 9882 7957.\n\n\n\nAll information provided will be treated in strict confidence and only be used for recruitment purpose.\n\n\nWebsite: www.delta-asia.com", "employment_types": ["Full Time", "Permanent"], "selling_points": ["5-day work with competitive remuneration package", "15 up to 20 days AL, birthday leave, wedding leave", "Immediately available is highly preferred"], "locations": ["Wan Chai"], "categories": ["Banking / Finance", "Investment", "Treasury", "Wealth Management"], "post_time": "2021-12-31T01:54:32Z", "salary": {"currency": null, "max": null, "min": null, "period": "monthly", "term": null}, "salary_visible": false, "title_keywords": ["analyst"], "responsibilities": ["ad hoc duties", "budgets", "management", "maintaining", "data", "policies", "analysis", "monitoring", "quality", "procedures", "business plans", "develop", "evaluate", "reports"], "requirements": {"degrees": ["degree holder"], "majors": ["related disciplines", "finance", "accounting", "risk management"], "languages": [], "language_level": [], "hard_skills": ["problem-solving skills", "cfa", "excel", "writing skills"], "soft_skills": ["able to prioritize", "detail oriented", "writing skills", "communication", "motivated individual", "problem-solving skills", "proactive", "positive"], "languages_combined": []}, "experience_required": {"duration": ["2+ years"], "field": ["risk management", "management", "financial industry", "banking", "financial"]}}, {"job_id": "100003009011794", "location_code": "hk", "company": "China Construction Bank (Asia) Corporation Limited", "job_title": "Treasury Marketing Professional", "description": "Job Descriptions:\n\n\nProvide comprehensive solutions to targeted clients, including timely market indication, execution, and trading strategies. Engage in daily maintenance work such as clientele relationship management, P&L reconciliation, monitor fund settlement etc.\nExpand treasury products (FX, fixed income, etc.) to meet the needs of targeted customers with specific business plan and Policy & Procedure, be able to solve problems during the launch of new products. Ensure adherence to Head Office and local regulatory requirements as well as the Bank\u2019s relevant Audit, Credit, Compliance, and Risk policies.\nDemonstrate business acumen on onshore and offshore market and relevant regulatory requirements.\u00a0 Prepare research report and business analysis for the decision-making of supervisor and management.\nExplore business opportunities in Treasury products to achieve the team\u2019s revenue target. Complete tasks assigned in a timely manner.\nManage good relationships with different customer units and middle and back office of the Bank to expand customer base, which can help to meet profit budget goals. Optimize product flow and process as necessary.\nTake up other ad-hoc works as required.\n\nRequirements:\n\nBachelor Degree holder or above, preferably in Economics, Finance, Mathematics or Statistics.\nMinimum 5 years\u2019 relevant experience in financial markets, e.g. FX and bonds.\nSelf-motivated with strong analytical, communication, interpersonal, multi-tasking skill. A good team player with integrity. Be able to work under stress and complete tasks assigned within dead line.\nSound knowledge of treasury products, with favorable personality and high professional ethics standards. No tracking record of penalty.\nGood command of both spoken and written English and Chinese, including Mandarin. Solid Chinese writing skill is preferred.\n\nTo apply, please send the detailed resume to the designated email address or by fax at 3718 2910.\n\nApplicants who are not contacted within 8 weeks may consider their applications unsuccessful and their personal data will be retained by the bank for a period up to two years.\n\nAll information provided by applicants will be used for recruitment purposes only and will be used strictly in accordance with the bank\u2019s personal data policies, a copy of which will be provided upon request.", "employment_types": ["Full Time", "Permanent"], "selling_points": ["treasury marketing", "FX, ELN, Bonds", "Degree holder + min. 2 yrs relevant exp."], "locations": ["Central"], "categories": ["Banking / Finance", "Treasury", "Dealing & Trading", "Equities / Capital Markets"], "post_time": "2021-12-31T08:18:41Z", "salary": {"currency": null, "max": null, "min": null, "period": "monthly", "term": null}, "salary_visible": false, "title_keywords": [], "responsibilities": ["ad-hoc", "management", "business analysis", "maintenance", "regulatory requirements", "ensure adherence", "compliance", "monitor", "audit", "p&l", "policies", "business opportunities", "a timely manner", "back office", "budget", "business plan", "report"], "requirements": {"degrees": ["bachelor degree holder"], "majors": ["finance", "economics", "statistics", "mathematics"], "languages": ["english", "chinese", "mandarin"], "language_level": ["good command"], "hard_skills": ["no", "writing skill"], "soft_skills": ["good team player", "self-motivated", "multi-tasking skill", "integrity", "writing skill", "communication", "interpersonal", "detailed"], "languages_combined": [{"language": "english", "language_level": ["good command"]}, {"language": "chinese", "language_level": ["good command"]}, {"language": "mandarin", "language_level": ["good command"]}]}, "experience_required": {"duration": ["minimum 5 years"], "field": ["financial markets", "relevant experience"]}}, {"job_id": "100003009011695", "location_code": "hk", "company": "Industrial and Commercial Bank of China (Asia) Limited", "job_title": "Fixed Income Researcher, Hong Kong Treasury Centre - Hong Kong Branch", "description": "Job responsibilities\n\nControl the cash and liquidity of the company, ensure the cash activities are carried out properly and the balances are remained safe\nManage the daily cash transactions, such as in and out settlements\nMaintain effective and long-term relationship with banks, manage the bank accounts\nCarry out interest payment and derivatives settlement\nCarry out corporate funding projects\nKeep abreast of financial markets & global economic for assessing funding & investment opportunities\nDevelop cash management, investment, and risk mitigation strategies\n\nJob requirements\n\nDegree in Finance, Economics, or related disciplines\nMinimum 2 years of related working experience\nGood command in both written and spoken English, Cantonese, and Mandarin\nProficient in PC skills, including MS Office\n\nIf you are interested in the position, please feel free to send your updated resume to cindy.wong@manpowergrc.hk", "employment_types": ["Full Time", "Permanent"], "selling_points": [], "locations": ["Central & Western Area"], "categories": ["Banking / Finance", "Analyst", "Credit Analysis / Approval", "Treasury"], "post_time": "2021-12-31T08:06:05Z", "salary": {"currency": null, "max": null, "min": null, "period": null, "term": null}, "salary_visible": false, "title_keywords": ["researcher"], "responsibilities": ["control", "management", "transactions", "develop", "payment", "maintain"], "requirements": {"degrees": ["degree"], "majors": ["related disciplines", "finance", "economics"], "languages": ["cantonese", "english", "mandarin"], "language_level": ["good command"], "hard_skills": ["pc skills", "ms office"], "soft_skills": ["interested in"], "languages_combined": [{"language": "cantonese", "language_level": ["good command"]}, {"language": "english", "language_level": ["good command"]}, {"language": "mandarin", "language_level": ["good command"]}]}, "experience_required": {"duration": ["minimum 2 years"], "field": ["related"]}}, {"job_id": "100003009015920", "location_code": "hk", "company": "Randstad Hong Kong Limited", "job_title": "FX/MM settlement (3+ years experience)", "description": "As a FX/MM operations associate, you will be responsible for :\n\ncapture/validation of payment messages via SWIFT\nHandle confirmation matching and timely chasing with counter-parties.\nManage the full processing cycle of trades and payments which includes communication, booking, confirmation, reconciliation and settlement.\nProcess the custody service by checking and maintaining the cash movement of the custodian account and assist to investigate if any discrepancy\nKeep an audit of all tasks performed to meet Permanent Control requests.\nPerform investigation in settlement discrepancies and related outstanding issues.\n\nRequirements:\n\nDegree holder with at least 3 years of FX/MM settlement experience.\nGood Knowledge in handling Swift messages\nGood command of written & spoken English and Chinese\n\nTo apply online please click the Apply button below. For a confidential discussion, feel free to contact Gladys Chan on +852 2232 3492 or email gladys.chan@randstad.com.hk", "employment_types": ["Full Time", "Permanent"], "selling_points": [], "locations": ["Not Specified"], "categories": ["Banking / Finance", "Treasury", "Others", "Order Processing & Operation / Settlement"], "post_time": "2022-01-03T07:53:58Z", "salary": {"currency": "HKD", "max": 34999, "min": 25000, "period": "monthly", "term": null}, "salary_visible": true, "title_keywords": [], "responsibilities": ["control", "maintaining", "operations", "checking", "audit", "investigation", "communication", "payment", "payments", "booking", "contact"], "requirements": {"degrees": ["degree holder"], "majors": [], "languages": ["english", "chinese"], "language_level": ["good command"], "hard_skills": ["swift", "processing"], "soft_skills": ["communication", "timely", "responsible"], "languages_combined": [{"language": "english", "language_level": ["good command"]}, {"language": "chinese", "language_level": ["good command"]}]}, "experience_required": {"duration": ["at least 3 years"], "field": []}}, {"job_id": "100003009011793", "location_code": "hk", "company": "China Construction Bank (Asia) Corporation Limited", "job_title": "Treasury Product Management Professional", "description": "Job Descriptions:\n\nResponsible for review and update for treasury products lists, and product due diligence procedures & process\nHelp conduct financial analysis and cost modelling, potential risks and opportunities analysis according to the treasury products strategies\nPrepare relevant market products research & relevant data analysis\nLiaise with internal & external business partners and stakeholders\n\nRequirements:\u00a0\n\nDegree holder or above in Banking / Finance / Economics or related discipline\nMinimum 2 year experience in financial markets or Treasury IT system development, with year exemption due to outstanding performance recognition, experience in treasury product development preferred\nSensitive to market changes with good knowledge in Fintech, financial market trend, and regulatory requirements\nProficient in IT applications, including Office software and trading system functions\nGood command of both spoken and written English and Chinese, including Mandarin\nResult-oriented, energetic, and a good team player\nStrong communication, good interpersonal skills to work with different levels of talents in the Bank\n\nApplicants who are not contacted within 8 weeks may consider their applications unsuccessful and their personal data will be retained by the bank for a period up to two years.\n\nAll information provided by applicants will be used for recruitment purposes only and will be used strictly in accordance with the bank's personal data policies, a copy of which will be provided upon request.", "employment_types": ["Full Time", "Permanent"], "selling_points": ["Treasury product management", "Fintech, market trend, and regulatory requirements", "Treasury IT system development"], "locations": ["Central"], "categories": ["Banking / Finance", "Treasury", "Others"], "post_time": "2021-12-31T08:18:40Z", "salary": {"currency": null, "max": null, "min": null, "period": "monthly", "term": null}, "salary_visible": false, "title_keywords": [], "responsibilities": ["cost", "product due diligence", "analysis", "review", "procedures", "financial analysis", "data analysis", "products research", "liaise with"], "requirements": {"degrees": ["degree holder"], "majors": ["finance", "economics"], "languages": ["english", "chinese", "mandarin"], "language_level": ["good command"], "hard_skills": ["office software"], "soft_skills": ["good team player", "communication", "sensitive to", "interpersonal skills", "energetic", "result-oriented"], "languages_combined": [{"language": "english", "language_level": ["good command"]}, {"language": "chinese", "language_level": ["good command"]}, {"language": "mandarin", "language_level": ["good command"]}]}, "experience_required": {"duration": ["minimum 2 year"], "field": ["financial markets", "product development", "it system development"]}}, {"job_id": "100003009011556", "location_code": "hk", "company": "China Construction Bank (Asia) Corporation Limited", "job_title": "Internal Control Professional - Treasury", "description": "Job Descriptions:\n\nPerform challenging role with large exposure in Treasury products with changing associated risks and requirements from regulators / Head Office.\nInterpret regulations, review trading/ sales authorities, policies and procedures;\nAssist in identify, analyze and control potential unauthorized trading risks;\nCoordinate and liaise with different stakeholders to ensure business and operations are conducted in accordance with relevant requirements;\nManage treasury trading systems, including user permissions and folder management of trading systems\nAd hoc assignments could be involved, partnership with stakeholders within Treasury Division, internal or external parties to deliver driving result on different topics/ projects.\n\nRequirements:\u00a0\n\nDegree holder or above, preferable in Banking or Finance.\nMinimum 2-5 years' relevant experience in financial markets, candidates from internal control/ risk/ audit/ treasury settlement or related areas would be welcome and considered.\nGood knowledge of the related business practice and principles.\nFast Learner with good working attitude and commitment.\nExcellent communication and people skills to work with others of different levels within the Bank.\nMulti-tasking with strong organizational skill and paying attention to details.\nBe enthusiastic and able to work in a team environment.\nProficient in Microsoft applications (Excel, Word and PowerPoint).\nGood in written and spoken English, Cantonese & Putonghua.\nQualification for Enhanced Competency Framework on Treasury Management is preferable.\n\nApplicants who are not contacted within 8 weeks may consider their applications unsuccessful and their personal data will be retained by the bank for a period up to two years.\n\nAll information provided by applicants will be used for recruitment purposes only and will be used strictly in accordance with the bank's personal data policies, a copy of which will be provided upon request.", "employment_types": ["Full Time", "Permanent"], "selling_points": ["Treasury internal control", "Trading/ sales authorities, policies & procedures", "Identify, analyze & control potential unauthorize"], "locations": ["Central"], "categories": ["Banking / Finance", "Treasury", "Others", "Trading"], "post_time": "2021-12-31T07:47:05Z", "salary": {"currency": null, "max": null, "min": null, "period": "monthly", "term": null}, "salary_visible": false, "title_keywords": [], "responsibilities": ["regulations", "control", "management", "policies", "operations", "review", "procedures", "systems", "external parties", "coordinate", "ad hoc assignments", "liaise with"], "requirements": {"degrees": ["degree holder"], "majors": ["finance"], "languages": ["cantonese", "putonghua", "english"], "language_level": ["good"], "hard_skills": ["excel", "microsoft applications", "word", "powerpoint", "internal control"], "soft_skills": ["good working attitude", "organizational skill", "communication", "multi-tasking", "attention to details", "enthusiastic", "fast learner"], "languages_combined": [{"language": "cantonese", "language_level": ["good"]}, {"language": "putonghua", "language_level": ["good"]}, {"language": "english", "language_level": ["good"]}]}, "experience_required": {"duration": ["minimum 2-5 years"], "field": ["related", "financial markets", "relevant experience", "audit"]}}, {"job_id": "100003009014991", "location_code": "hk", "company": "Connexe Search Limited", "job_title": "Compliance Manager, Private Wealth Management (60k)", "description": "Our client is a well-regarded regional bank. They are currently looking for Manager, Private Banking Compliance in Legal and Compliance Department.\n\n\n\nResponsibilities:\n\nReport to Compliance Unit Head and Department Head\nProvide compliance advisory, training and monitoring\u00a0to Private Banking business and staff\nReview Investment Product Due Diligence (PDD) performed by Product Teams in Private Banking\nUpdate and implement policies & procedures, compliance plan and manuals related to Private Banking business\nEnsure business in compliance to local regulatory requirements and internal policies & procedures\n\nRequirements:\n\nDegree or above\nGood communication skills and sound knowledge of Banking Ordinance, Securities & Futures Ordinance, selling process and PI requirements\n5+ years' experience in general compliance in private banking/ wealth management\nCAMS/ CPA is a plus\nProficient spoken and written English and Chinese (Cantonese & Mandarin)\u00a0\n\nPlease click Apply Now or email your full resume in MS Word format quoting the job reference N211413 in the subject field. Your interest will be treated in strict confidence. Only shortlisted candidates will be notified.", "employment_types": ["Full Time"], "selling_points": ["5+ years in private banking compliance", "compliance advisory & training, monitoring", "PDD review, investment products"], "locations": ["Central & Western Area"], "categories": ["Banking / Finance", "Private Banking", "Treasury", "Professional Services", "Legal & Compliance"], "post_time": "2022-01-03T04:49:28Z", "salary": {"currency": null, "max": null, "min": null, "period": "monthly", "term": null}, "salary_visible": false, "title_keywords": ["wealth management", "compliance manager"], "responsibilities": ["product due diligence", "policies", "regulatory requirements", "review", "monitoring", "compliance", "teams", "procedures", "plan", "banking", "report"], "requirements": {"degrees": ["degree or above"], "majors": [], "languages": ["cantonese", "english", "chinese", "mandarin"], "language_level": ["proficient"], "hard_skills": ["cpa", "plus", "ms word"], "soft_skills": ["communication skills", "confidence"], "languages_combined": [{"language": "cantonese", "language_level": ["proficient"]}, {"language": "english", "language_level": ["proficient"]}, {"language": "chinese", "language_level": ["proficient"]}, {"language": "mandarin", "language_level": ["proficient"]}]}, "experience_required": {"duration": ["5+ years"], "field": ["management", "general compliance", "banking"]}}, {"job_id": "100003009003909", "location_code": "hk", "company": "Inspire Executive Limited", "job_title": "Treasury Head-Leading Chinese-based Financial Group", "description": "Our client is a leading Chinese-based Financial Group who is looking for a Treasury Head to join their team. Skilled Candidates with treasury working experience in securities firms are welcome. Base HK\n\n\n\nJob Responsibilities:\n\nManage all cash management functions including cash concentration, wires, account funding. Ensure adequate liquidity for working capital needs and invest short term excess cash.\nOversee cash management banking and financial institution relationships.\nEnsure compliance with internal controls, policies and procedures. Develop and monitor treasury operational policies.\n\nJob Requirements:\nMust possess overall experience in cash management, capital markets, and/ or corporate finance in a corporate or a banking environment.\nStrong analytical, financial and systems skills are required.\nExperience working in securities firms a plus.\nMandarin and English is a must; Cantonese preferred.", "employment_types": ["Full Time"], "selling_points": ["Treasury", "Finance", "Accounting"], "locations": ["Central & Western Area"], "categories": ["Banking / Finance", "Treasury"], "post_time": "2021-12-28T11:43:29Z", "salary": {"currency": null, "max": null, "min": null, "period": "monthly", "term": null}, "salary_visible": false, "title_keywords": [], "responsibilities": ["management", "policies", "procedures", "monitor", "ensure compliance", "develop", "banking"], "requirements": {"degrees": [], "majors": [], "languages": ["cantonese", "english", "mandarin"], "language_level": [], "hard_skills": ["plus"], "soft_skills": [], "languages_combined": [{"language": "cantonese", "language_level": []}, {"language": "english", "language_level": []}, {"language": "mandarin", "language_level": []}]}, "experience_required": {"duration": [], "field": ["management", "corporate finance", "securities firms", "banking", "capital markets"]}}, {"job_id": "100003009015682", "location_code": "hk", "company": "Randstad Hong Kong Limited", "job_title": "Corporate Action Analyst (1-3 years experience)", "description": "Job Responsibilities:\n\nAnalyse and execute the corporate action event (dividend, spin off, shares split etc)\nHandle the research and implementation of corporate actions for equities (e.g. increases and decreases of capital stocks, IPOs, M&A activities, dividend payments, stock splits, spin-offs, etc.)\nManage data: sourcing, cleansing, and organising of corporate events, reference and ownership data\nClosely work with Europe and North America offices regarding market data enquires\nTake charge of different projects to develop the team in Hong Kong\n\nRequirements:\n\nExperience in CCASS / Bloomberg will be an advantage\nFluent in English, Mandarin and Cantonese.\n1+ years relevant experience\n\nTo apply online please click the Apply button below. For a confidential discussion, feel free to contact Gladys Chan on +852 2232 3492 or email gladys.chan@randstad.com.hk", "employment_types": ["Full Time", "Permanent"], "selling_points": [], "locations": ["Not Specified"], "categories": ["Banking / Finance", "Treasury", "Equities / Capital Markets", "Others"], "post_time": "2022-01-03T07:20:56Z", "salary": {"currency": "HKD", "max": 29999, "min": 20000, "period": "monthly", "term": null}, "salary_visible": true, "title_keywords": ["analyst"], "responsibilities": ["data", "cleansing", "implementation", "develop", "payments", "market data", "analyse"], "requirements": {"degrees": [], "majors": [], "languages": ["cantonese", "english", "mandarin"], "language_level": ["fluent"], "hard_skills": ["bloomberg", "ccass"], "soft_skills": [], "languages_combined": [{"language": "cantonese", "language_level": ["fluent"]}, {"language": "english", "language_level": ["fluent"]}, {"language": "mandarin", "language_level": ["fluent"]}]}, "experience_required": {"duration": ["1+ years"], "field": ["relevant experience"]}}, {"job_id": "100003009012101", "location_code": "hk", "company": "Shanghai Commercial Bank Ltd", "job_title": "Vice President, Project Manager (Treasury & Wealth) - Information Technology", "description": "Responsibilities:\n\nAssist to develop and maintain technical solution implementation road map to achieve the strategic goals of the Bank and facilitate business development through adoption of suitable technologies\u00a0\u00a0\nDrive and lead technical implementation to realize tactical initiatives from inception to completion\nManage IT projects end-to-end including solution evaluation, proposal preparation, project initiation/planning, risk assessment/mitigation, reporting and documentation preparation, change management as well as post-implementation and audit reviews\nCollaborate with different stake holders, business partners and team members to achieve project objectives in an effective and efficient manner\n\nRequirements:\n\nDegree holder in Information Technology or related disciplines\nMinimum 10 years\u2019 relevant IT project management experience, preferably with relevant experience in Treasury, Wealth and Investment Services and operations.\nGood knowledge of latest technology development and applications, multiple best-of-breed solutions, products, tools, architecture, external ecosystems and integration strategies\nStrive for continuous improvement and strong organisational skills including the ability to plan, prioritize and schedule activities to achieve deliverables\nGood writing and presentation skills to present program, reports and project plans to management and stakeholders\nAbility to influence others and facilitate change management through collaboration and leadership, proficiency in vendor management, team management, business user liaison\n\nAttractive remuneration package will be offered to the right candidates. Interested parties please click\u00a0\"Apply Now\"\u00a0to submit your full resume with current and expected salary to the\u00a0Human Resources Division.\n\nPlease visit us at\u00a0www.shacombank.com.hk\u00a0for more information about our Bank.\n\nAll personal data collected will be used for recruitment related purposes strictly in accordance with the Bank's personal data policies, a copy of which will be provided immediately upon request by contacting our Personal Data Compliance Officer. Applicants who are not contacted within two months may consider their applications unsuccessful and the personal data collected from the applicants will be retained for no longer than two years from the date of rejection during which the applicants may be considered for other suitable positions within the Bank.", "employment_types": ["Full Time", "Permanent"], "selling_points": ["Drive and lead technical implementation", "Manage IT projects end-to-end", "Collaborate with different stake holders"], "locations": ["Not Specified"], "categories": ["Banking / Finance", "Treasury", "Others", "Wealth Management"], "post_time": "2022-01-01T19:40:34Z", "salary": {"currency": null, "max": null, "min": null, "period": "monthly", "term": null}, "salary_visible": false, "title_keywords": ["vice president", "project manager"], "responsibilities": ["collaborate with", "reporting", "change management", "implementation", "audit", "develop", "maintain", "evaluation", "documentation", "planning"], "requirements": {"degrees": ["degree holder"], "majors": ["related disciplines", "information technology"], "languages": [], "language_level": [], "hard_skills": ["integration", "project management", "vendor"], "soft_skills": ["prioritize", "project management", "presentation skills", "organisational skills", "leadership"], "languages_combined": []}, "experience_required": {"duration": ["minimum 10 years"], "field": ["project management", "it", "relevant experience", "investment"]}}, {"job_id": "100003009012548", "location_code": "hk", "company": "China Everbright Bank Company Limited", "job_title": "Manager, FX and Interest Rates Derivates", "description": "Job Responsibilities:\n\nPerform FX and Interest Rates Derivates trading, and manage the relevant risks;\nConduct pre/post trades and ad-hoc assignments ;\nConsistently perform accurate and timely quote for sales and clients;\nDevelop trading strategy and make market updates for sales marketing;\nEnhance the new product process through interaction with different stakeholders;\nStrictly follow trading mandates, including but not restricted to limits, exposure in the individual level and firm level;\nAssume ad hoc duties as assigned by the Team Head.\u00a0\n\nJob Requirements:\n\nDegree holder in Accounting, Finance, Mathematics, Statistics, Finance or related disciplines\nMinimum 5 years working experience in FX and Interest Rates Derivatives, including but not restricted to IRS, CCS, Option on major currencies\nExposure with China onshore rates and rates-related bonds is an advantage\nFamiliar with dealing systems, such as Reuters, Bloomberg etc\nProficient in professional computer applications, such as VBA, Excel, Word etc\nWill have exposure into other products such as onshore rates-related bonds\nStrong communication and interpersonal skills, good analytical skill, strong report writing and self-motivated\nAbility to work independently\nProficient in both spoken and written English and Chinese; fluent in Putonghua is highly preferable\n\nCandidates with less experience will be considered as Assistant Manager.", "employment_types": ["Full Time"], "selling_points": ["Perform FX and Interest Rates Derivates trading", "Develop trading strategy and make market updates", "Strictly follow trading mandates"], "locations": ["Wan Chai"], "categories": ["Banking / Finance", "Treasury"], "post_time": "2022-01-01T02:37:46Z", "salary": {"currency": null, "max": null, "min": null, "period": "monthly", "term": null}, "salary_visible": false, "title_keywords": ["manager"], "responsibilities": ["ad hoc duties", "ad-hoc assignments", "develop"], "requirements": {"degrees": ["degree holder"], "majors": ["mathematics", "finance", "statistics", "related disciplines", "accounting"], "languages": ["putonghua", "english", "chinese"], "language_level": ["fluent", "proficient"], "hard_skills": ["vba", "analytical skill", "excel", "bloomberg", "word"], "soft_skills": ["analytical skill", "communication and interpersonal skills", "work independently", "self-motivated"], "languages_combined": [{"language": "putonghua", "language_level": ["fluent"]}, {"language": "english", "language_level": ["proficient"]}, {"language": "chinese", "language_level": ["proficient"]}]}, "experience_required": {"duration": ["minimum 5 years"], "field": []}}, {"job_id": "100003009002007", "location_code": "hk", "company": "Grey Anderson Limited", "job_title": "Treasury Analyst - Global Fintech Company", "description": "Responsibilities\u200b\n\nResponsible for daily Treasury functions, including cash flow management, foreign exchange hedging, risk management, and analysis\nCompile daily liquidity positions from bank account statement data, weekly cash, and debt reporting for the regions\nPrepare periodic treasury reports, forecast, budget, and various financial analyses for management review\nAssist in cash projection, streamlining treasury analysis, reporting, and operational process\nOther ad-hoc assignments as requested\n\nRequirements\n\nDegree holder in Finance, Accounting or other related disciplines\u00a0and member of recognized accounting body\n1-3 years of\u00a0financial operations\u00a0experience in\u00a0financial institutions\u00a0is preferred\nA good team player and able to work independently\nGood interpersonal and communication skills\nGood written and spoken English and Chinese", "employment_types": ["Full Time"], "selling_points": ["Global Exposure; Great Remuneration Package", "Cash Management", "1-3 years experience"], "locations": ["Causeway Bay"], "categories": ["Accounting", "Financial Analyst", "Banking / Finance", "Treasury", "Financial Services"], "post_time": "2021-12-28T03:34:21Z", "salary": {"currency": "HKD", "max": 34999, "min": 20000, "period": "monthly", "term": null}, "salary_visible": true, "title_keywords": ["analyst"], "responsibilities": ["reporting", "management", "data", "ad-hoc assignments", "analysis", "budget", "cash flow", "reports", "forecast", "management review"], "requirements": {"degrees": ["degree holder"], "majors": ["related disciplines", "finance", "accounting"], "languages": ["english", "chinese"], "language_level": ["good"], "hard_skills": [], "soft_skills": ["communication skills", "good team player", "interpersonal", "work independently"], "languages_combined": [{"language": "english", "language_level": ["good"]}, {"language": "chinese", "language_level": ["good"]}]}, "experience_required": {"duration": ["1-3 years"], "field": ["financial institutions", "financial"]}}, {"job_id": "100003009020134", "location_code": "hk", "company": "Gravitas Recruitment Group", "job_title": "Java developer - Junior / Senior java developer - Bank", "description": "Our client is one of the Global Banks who is looking for passionate and strong Java Developers to join their team. For this role, you will be closely with Front Office and Middle Office to design, implement and maintain Java-based solutions that meets the Treasury business requirement within the Bank.\n\nThey are looking for 1 Junior and 1 Senior passionate Java developer to join their team. This is a great opportunity for Junior java specialists to get into a Financial sector, and for Senior java specialist to take on a Leadership role.\n\nJava Developer - Why Apply?\n* Work closely with the Front and Middle Office team.\n* Get to work on Risk management system, which consist of pre-trade and post-trade functionality.\n* Work in a multicultural team including global users.\n* Attractive remuneration package and rewards, including meal allowance $1,000/month.\n\nJava Developer - What is required?\n* Degree holder in Computer Science/Information Technology or related disciplines\n* For Junior - at least 1 year relevant work experience in Java.\n* For Senior - at least 5 years relevant work experience in Java, banking ground would be an advantage.\n* Solid skill in Java development (Java 8 or above is preferred).\n* Familiar with typical Spring REST stack (eg: JPA, security, Swagger).\n* Fluent in English, Cantonese and Mandarin.\n\nInterest parties please send your CV to k.ching@gravitasgroup.com", "employment_types": ["Full Time", "Permanent"], "selling_points": ["Java developer", "Treasury", "Investment Bank"], "locations": ["Not Specified"], "categories": ["Banking / Finance", "Treasury", "Information Technology (IT)", "Software Development"], "post_time": "2022-01-04T10:00:14Z", "salary": {"currency": "HKD", "max": 69999, "min": 25000, "period": "monthly", "term": null}, "salary_visible": true, "title_keywords": ["developer", "junior"], "responsibilities": ["management", "maintain", "design", "banking"], "requirements": {"degrees": ["degree holder"], "majors": ["related disciplines", "computer science", "information technology"], "languages": ["cantonese", "english", "mandarin"], "language_level": ["fluent"], "hard_skills": ["java", "spring"], "soft_skills": ["passionate", "leadership"], "languages_combined": [{"language": "cantonese", "language_level": ["fluent"]}, {"language": "english", "language_level": ["fluent"]}, {"language": "mandarin", "language_level": ["fluent"]}]}, "experience_required": {"duration": ["at least 5 years", "at least 1 year"], "field": ["banking"]}}, {"job_id": "100003009011503", "location_code": "hk", "company": "Hang Seng Bank Ltd", "job_title": "Senior Treasury Solution Dealer II", "description": "Global Banking and Markets \u2013 Global Markets\n\nHang Seng's Global Markets business provides superior service, fully integrated solutions and 24-hour global markets coverage. Our support framework is substantial. Our advanced technologies deliver quick access to key markets. Our capital strength allows us to tailor competitively-priced solutions for specific client business around the world. We provide a full spectrum of treasury services to our customers, including foreign exchange, interest rate risk management, derivatives products, capital markets instruments, as well as market intelligence on global trends and key developments.\n\nWe are currently seeking a high caliber professional to join our department as\u00a0Senior Treasury Solution Dealer II.\n\u00a0\u00a0\n\nPrincipal responsibilities\n\nServe and provide treasury solutions / products to the Bank\u2019s client with focus on corporate clients;\nIndentify sales opportunities or initiatives that address clients\u2019 need;\nMaintain business relationships with clients in assigned area of responsibility;\nSupport the Head of Treasury Solution on business initiatives;\nCollaborate with internal stakeholders, including Relationship Managers and other product groups to maximise cross-selling opportunities for the Bank;\nDealing of treasury vanilla products and structure derivatives\nRequirements\nUniversity degree holder;\nMinimum of five\u00a0years\u2019 working experience as treasury sales with strong connection of corporate clients;\nStrong treasury product knowledge especially in FX and interest rate derivatives;\nStrong communication and interpersonal skills;\nCreative, with growth mindset and highly adaptable to changes and transformation;\nProficiency in both English and Chinese, fluency in Putonghua an advantage;\nHigh level of customer centricity mindset with dedication to deliver exceptional quality services for customers\n\nIf you would like to explore other opportunities at Hang Seng Hong Kong, please\u00a0visit\u00a0www.hangseng.com/careers/\u00a0for details.\n\nThe health and safety of our employees and candidates is very important to us. Due to the current situation related to the Novel Coronavirus (2019-nCoV), we\u2019re leveraging our digital capabilities to ensure we can continue to recruit top talent at the HSBC Group. \u00a0As your application progresses, you may be asked to use one of our digital tools to help you through your recruitment journey.\u00a0 If so, one of our Resourcing colleagues will explain how our video-interviewing technology will be used throughout the recruitment process and will be on hand to answer any questions you might have.\u00a0\n\nAll information provided by applicants will be used only for recruitment purposes and will be used strictly in accordance with the Bank's personal data policies, a copy of which may be obtained by the applicant upon request. Unless otherwise instructed in writing by the applicant concerned, applicants may be considered for other suitable positions within the Bank and its related companies. The personal data of unsuccessful job applicants may be retained for a maximum of two years from the date when the job application is rejected and such data may be retained for a longer period if there is a subsisting reason that obliges the Bank to do so, after which the personal data will be destroyed.", "employment_types": ["Full Time", "Permanent"], "selling_points": [], "locations": ["Not Specified"], "categories": ["Banking / Finance", "Treasury", "Dealing & Trading", "Asset Management"], "post_time": "2021-12-31T07:39:13Z", "salary": {"currency": null, "max": null, "min": null, "period": "monthly", "term": null}, "salary_visible": false, "title_keywords": ["dealer"], "responsibilities": ["business initiatives", "maintain", "collaborate with"], "requirements": {"degrees": ["university degree"], "majors": [], "languages": ["putonghua", "english", "chinese"], "language_level": ["fluency", "advantage", "proficiency"], "hard_skills": ["reason"], "soft_skills": ["adaptable", "novel", "communication and interpersonal skills", "creative"], "languages_combined": [{"language": "putonghua", "language_level": ["fluency"]}, {"language": "english", "language_level": ["proficiency", "fluency", "advantage"]}, {"language": "chinese", "language_level": ["proficiency", "fluency", "advantage"]}]}, "experience_required": {"duration": ["minimum of five years"], "field": []}}, {"job_id": "100003009011242", "location_code": "hk", "company": "Conners Consulting Limited", "job_title": "VP (Project Manager) - Deposits and Remittance Operation (Multinational Bank)", "description": "Our client is well-known multinational bank and now looking for high calibre to join their group.\n\nResponsibilities\n\nManage process improvement and system projects to streamline work flows and procedures\u00a0\u00a0\nSupport daily deposits and remittance function of the bank in compliance with statutory requirements\nWork closely with business, marketing, control and risk units for new product development and conduct system UAT\nLiaise with regulators, auditors and compliance staff on latest regulatory, control and compliance requirements\n\n\u00a0Requirements\n\nUniversity degree holder\nSound knowledge of bank operations with at least 7 years in bank operations and project management experience\nStrong knowledge of all aspects of local and overseas remittance and deposits operations and practices\nEnergetic personality with strong people management and communications skills\n\nTo apply, please send your detailed resume to winnie[at]connersconsulting.com or contact Winnie Lai at 3618 8348 for a confidential discussion.\nOnly shortlisted candidates will be notified.\nApplicants who are not contacted within two weeks may consider their applications unsuccessful.\nAll data collected will be used for recruitment purpose only & will be used strictly confidential.\n\nConners Consulting Limited\n2005 Kai Tak Commercial Building 317 Des Voeux Road Central Hong Kong\u00a0\nTel: (852) 3996 8090\nWebsite:\u00a0www.connersconsulting.com", "employment_types": ["Full Time", "Permanent"], "selling_points": ["Attractive remuneration and bonus scheme", "Operations / Deposits / Remittance", "Work life balance, excellent job security"], "locations": ["Central & Western Area"], "categories": ["Banking / Finance", "Loan", "Treasury", "Order Processing & Operation / Settlement"], "post_time": "2022-01-01T19:40:24Z", "salary": {"currency": null, "max": null, "min": null, "period": "monthly", "term": null}, "salary_visible": false, "title_keywords": ["project manager"], "responsibilities": ["control", "uat", "compliance", "procedures", "statutory requirements", "liaise with"], "requirements": {"degrees": ["university degree"], "majors": [], "languages": [], "language_level": [], "hard_skills": ["project management"], "soft_skills": ["project management", "energetic", "detailed"], "languages_combined": []}, "experience_required": {"duration": ["at least 7 years"], "field": ["project management"]}}, {"job_id": "100003009008487", "location_code": "hk", "company": "E.SUN Commercial Bank, Ltd.", "job_title": "Fixed Income Specialist", "description": "Job Duties:\n\nProvide the diversified portfolio and risk analysis to the investment committee. Day-to-day portfolio discussion based on movement in rates/credit market.\nBuild and manage cash bonds for trading and investment purpose.\nManage daily routines on fixed income portfolio with high efficiency and accuracy.\n\nRequirement:\n\nMinimum 1~2 years of working experience in fixed income investment or related field.\nBachelor degree or higher in Finance, Economics or related discipline.\nSelf-motivated with strong communication, interpersonal and analytical skills.\n\nWe offer an attractive remuneration package including five-day workweek, double pay, medical insurance coverage, performance bonus, OT allowance, public holiday, excellent career development opportunities, and other benefit packages to the right candidate. Interested parties please forward your resume including a Chinese self-introduction with current and expected salary to Human Resources Department by \"APPLY NOW\".\u00a0\n\nPlease visit our website at https://www.esunbank.com.tw/bank/corporate/overseas-branch/overseas-branch/hong-kong for more information.\u00a0\n\nAll information received will be kept strictly confidential and only for employment-related purposes.", "employment_types": ["Full Time", "Permanent"], "selling_points": ["Diversified portfolio and risk analysis", "Young and Energetic Working Culture", "One of the Leading Bank in Taiwan"], "locations": ["Tsim Sha Tsui"], "categories": ["Banking / Finance", "Corporate Banking", "Treasury", "Equities / Capital Markets"], "post_time": "2021-12-30T08:11:09Z", "salary": {"currency": null, "max": null, "min": null, "period": "monthly", "term": null}, "salary_visible": false, "title_keywords": ["specialist"], "responsibilities": ["risk analysis"], "requirements": {"degrees": ["degree", "bachelor"], "majors": ["finance", "economics"], "languages": [], "language_level": [], "hard_skills": ["analytical skills"], "soft_skills": ["communication", "self-motivated", "interpersonal", "analytical skills"], "languages_combined": []}, "experience_required": {"duration": ["minimum 1~2 years"], "field": ["related", "investment"]}}, {"job_id": "100003009005863", "location_code": "hk", "company": "Livi Bank Limited", "job_title": "Senior Manager, Treasury and Payment Operations", "description": "Responsibilities:\n\nManage and oversee the Treasury operations activities, day-to-day clearing and settlements of Treasury products, corporate actions for fixed income, OTC market and lending products to meet the financial obligations of the Bank.\nMonitor all SWIFT/ RTGS/ JETCO and FPS payments that are timely executed and reconciled.\nDesign the workflow and control for Treasury and Payment operations to ensure full regulatory compliance with the Bank and HKMA.\nPerform timely reconciliation for Treasury and Payment Operations and settlement functions, discrepancy review, resolving breaks and exceptions.\nHandle onboarding process and application documentations for Interbank account opening\nLiaise with cross functional team such as Treasury and Finance, Risk Management, Technology and for resolving any operational, settlement and system issues relating to Treasury and payment products\nManage and perform Treasury and Payment system UAT testing, deployment process and enhancement\n\nRequirements:\n\nDegree holder in business administration or related discipline\nMinimum of 10 years\u2019 experience in Treasury and Payment Operations with at least 5 years in supervisory function. Less experience will be considered for a manager role.\nSolid knowledge and understanding treasury and payment products and systems\nSolid understanding of risk mitigation of fraud in Treasury and Payment Operations\nCompetence and capable of leading people and cross-functional project teams\nHands on experience in SWIFT, eMBT, eCMT, HKTR\nIndependent, enthusiastic and able to work under pressure\nProficiency in MS Office, basic VBA programming skills preferred\nGood command of written and spoken English and Chinese, proficiency in Putonghua is a preferred.\nWe offer competitive salary package to the successful candidate.\u202f If you are interested in joining this exciting team, please send your full resume including your\u202fCURRENT\u202fand\u202fEXPECTED\u202fsalary for our consideration.", "employment_types": ["Full Time", "Permanent"], "selling_points": ["Digital / Virtual Banking", "Dynamic Working Culture", "Banking Operations / Treasury Operations"], "locations": ["Quarry Bay"], "categories": ["Banking / Finance", "Retail Banking", "Treasury", "Order Processing & Operation / Settlement"], "post_time": "2021-12-29T05:32:11Z", "salary": {"currency": null, "max": null, "min": null, "period": "monthly", "term": null}, "salary_visible": false, "title_keywords": ["senior manager", "operations"], "responsibilities": ["control", "management", "operations", "account opening", "compliance", "monitor", "review", "design", "uat testing", "payment", "payments", "liaise with"], "requirements": {"degrees": ["degree holder"], "majors": ["business administration"], "languages": ["putonghua", "english", "chinese"], "language_level": ["proficiency", "good command"], "hard_skills": ["vba", "basic", "programming", "swift", "ms office"], "soft_skills": ["independent", "capable", "hands on", "enthusiastic", "work under pressure"], "languages_combined": [{"language": "putonghua", "language_level": ["proficiency", "good command"]}, {"language": "english", "language_level": ["proficiency", "good command"]}, {"language": "chinese", "language_level": ["proficiency", "good command"]}]}, "experience_required": {"duration": ["at least 5 years", "minimum of 10 years"], "field": ["supervisory"]}}, {"job_id": "100003009015932", "location_code": "hk", "company": "BRS Limited", "job_title": "Team Head / Senior Manager / Manager \u2013 Risk Management (Stress Test programmes)", "description": "Our client, a reputable Chinese bank in Hong Kong, is seeking high calibre to fill the above position:\n\nResponsibilities:\n\n\nMaintain and execute the stress testing program of the Bank and to perform the risk management functions in relation to capital management matters and interest rate risk in the banking book (IRRBB)\nReview assumptions and methodologies of Bank\u2019s stress testing programs; Play a central role in bank-wide stress testing such as stress tests for ICAAP, recovery planning, capital planning as well as the regulator driven stress testing\nHandle risk-related capital management matters such as ICAAP review, recovery planning, capital triggers\nMeasure, monitor and control the IRRBB exposures against approved risk limits and appetite\nMaintain and develop risk reports for internal risk monitoring as well as regulatory reporting in accordance with regulatory requirements\n\nRequirements:\n\nDegree holder in Risk Management, Quantitative Finance, Accounting or related disciplines\nRelevant experience in the risk management of treasury, asset and liability management or finance related areas in banking industry\nGood command of PC and programming skills such as SAS, Excel VBA, Access SQL, Python\nInterested parties please forward your CV in Word Format with current and expected salary to Vicki Ho of BRS Limited.\n\n\n\n[All applications will be treated strictly confidential and will be used for recruitment purpose only]", "employment_types": ["Full Time", "Permanent"], "selling_points": ["Maintain and execute the stress testing program", "Handle risk-related capital management matters", "Measure, monitor and control the IRRBB exposures"], "locations": ["Central"], "categories": ["Banking / Finance", "Treasury", "Others", "Risk Management"], "post_time": "2022-01-03T07:55:53Z", "salary": {"currency": null, "max": null, "min": null, "period": "monthly", "term": null}, "salary_visible": false, "title_keywords": ["senior manager", "manager"], "responsibilities": ["reporting", "management", "control", "recovery planning", "regulatory requirements", "review", "monitor", "testing", "develop", "risk monitoring", "maintain", "reports", "banking", "planning"], "requirements": {"degrees": ["degree holder"], "majors": ["finance", "risk management", "related disciplines", "accounting"], "languages": [], "language_level": [], "hard_skills": ["vba", "excel", "sas", "sql", "programming", "python", "pc"], "soft_skills": [], "languages_combined": []}, "experience_required": {"duration": [], "field": ["risk management", "management", "banking industry", "related", "finance", "relevant experience"]}}, {"job_id": "100003009002481", "location_code": "hk", "company": "Industrial and Commercial Bank of China (Asia) Limited", "job_title": "FX & Swap Trader - G10 FX & Commodity, Global Markets (Treasury)", "description": "Job Duties\nAssist in dealing activities in foreign exchange market to achieve individual profit target\nMaintain timely, professional, services of good quality, including quoting managing orders of both internal and external clients\nProvide market information & forecast for Management to formulate business strategies\nPrepare commentary & reporting when required\nJob Requirements\nBachelor Degree or above in Economics, Finance or Quantitative Disciplines\nMinimum 3 years of experience or above in active FX/Forward/Swap trade execution/dealing\nStrong HKD market knowledge including spot, forward and swap is a plus\nStrong track records of trading profit\nSelf motivated with strong communication, interpersonal and analytical skills\nFluent in both spoken and written English & Chinese, includes Putonghua", "employment_types": ["Full Time", "Permanent"], "selling_points": [], "locations": ["Central"], "categories": ["Banking / Finance", "Treasury", "Dealing & Trading"], "post_time": "2021-12-28T05:57:45Z", "salary": {"currency": null, "max": null, "min": null, "period": "monthly", "term": null}, "salary_visible": false, "title_keywords": [], "responsibilities": ["reporting", "management", "market information", "profit target", "quality", "maintain", "forecast"], "requirements": {"degrees": ["degree or above", "bachelor"], "majors": ["finance", "economics"], "languages": ["putonghua", "english", "chinese"], "language_level": ["fluent"], "hard_skills": ["plus", "analytical skills"], "soft_skills": ["analytical skills", "self motivated", "communication", "active", "interpersonal"], "languages_combined": [{"language": "putonghua", "language_level": ["fluent"]}, {"language": "english", "language_level": []}, {"language": "chinese", "language_level": []}]}, "experience_required": {"duration": ["minimum 3 years"], "field": []}}, {"job_id": "100003009008058", "location_code": "hk", "company": "Midas Associates Limited", "job_title": "Treasury Settlement Manager", "description": "\n\n\nOur client, a Reputable Bank, is looking for high caliber candidate for the position.\n\n\u00a0Requirements:\n\nUniversity graduate in Business, Accounting or related discipline\nMinimum\u00a08 years of experience in treasury settlement or related areas\nFamiliar with local and overseas settlement system/practices such as CCASS\nSound\u00a0knowledge of eIPO, SWIFT, RTGS or other related systems\nGood understanding of trade repository reporting of HKMA (\u201cTR\u201d) and collateral management\nFamiliar with SFO and related regulatory requirements\nAttention to details, mature, self-motivated and able to work under pressure.\nGood command of written and spoken English and Chinese. Putonghua speaking is definite an asset\n\n\u00a0Interested parties, please send update resume with present and expect salary.", "employment_types": ["Permanent"], "selling_points": ["RTGS, CCASS, TR", "Fixed Income, Funds, Bonds, Derivatives,", "System Project"], "locations": ["Others"], "categories": ["Banking / Finance", "Treasury", "Financial Services", "Order Processing & Operation / Settlement"], "post_time": "2021-12-30T06:29:23Z", "salary": {"currency": "HKD", "max": 44999, "min": 35000, "period": "monthly", "term": null}, "salary_visible": true, "title_keywords": ["settlement manager"], "responsibilities": ["reporting", "management", "regulatory requirements", "systems", "work under pressure"], "requirements": {"degrees": ["university graduate"], "majors": ["business", "accounting"], "languages": ["putonghua", "english", "chinese"], "language_level": ["good command"], "hard_skills": ["swift", "sfo", "hkma", "ccass"], "soft_skills": ["mature", "self-motivated", "attention to details", "work under pressure"], "languages_combined": [{"language": "putonghua", "language_level": []}, {"language": "english", "language_level": ["good command"]}, {"language": "chinese", "language_level": ["good command"]}]}, "experience_required": {"duration": ["minimum 8 years"], "field": ["related"]}}, {"job_id": "100003009010527", "location_code": "hk", "company": "PERSOLKELLY Hong Kong Limited", "job_title": "Banking Operations (12-months contract, multiple opening),15-25k + benefits + gratuity", "description": "Snapshot\n\nAn exciting opportunity to join a sizeable foreign bank as part of the Operation Team (Loans Operations/ Treasury Operations/ Remittance)\n\nCompany Profile\n\nOur client, a sizeable foreign bank, is currently expanding and looking for multiple headcounts for various operation teams.\n\nExciting new role for you\n\nLoans Operations: To process/check daily loan transaction covering loan drawdown, rollover, fee collection, SWIFT payment, loan confirmation etc.;\nTreasury Operations: To process/check all clerical works in treasury market transactions, confirming details of trades and prepare the instructions via CHATS / RTGS, SWIFT, CMU\nRemittance: Process various types of inward / outward payment, internal transfer, local and foreign as well as cross-border transactions via different payment systems\n\nRequirements\n\nMinimum 2 years of relevant experience in banking operations/support function\nDiploma holder or above, degree holder would be a plus\nA team player with good communication and interpersonal skills\nGood command of both English and Chinese, knowledge in Mandarin would be an advantage\n\nRewards\n\n12-months contract with employee benefits and gratuity (contract to perm), International platform with extensive career exposure\n\nAction Now\n\nPlease directly apply and call Suzanne Tsang at +852 2281 0041 to have a confidential discussion about this role and other exciting opportunities with you.", "employment_types": ["Contract"], "selling_points": ["Banking Operations, multiple opening", "12-months contract with benefit + gratuity", "15-25k"], "locations": ["Tsim Sha Tsui"], "categories": ["Banking / Finance", "Loan", "Treasury", "Order Processing & Operation / Settlement"], "post_time": "2021-12-31T04:04:24Z", "salary": {"currency": null, "max": null, "min": null, "period": "monthly", "term": null}, "salary_visible": false, "title_keywords": ["operations"], "responsibilities": ["operations", "systems", "teams", "transactions", "communication", "payment", "banking"], "requirements": {"degrees": ["diploma holder", "degree holder"], "majors": [], "languages": ["english", "chinese", "mandarin"], "language_level": ["advantage", "good command"], "hard_skills": ["swift", "plus"], "soft_skills": ["team player", "communication and interpersonal skills"], "languages_combined": [{"language": "english", "language_level": ["advantage", "good command"]}, {"language": "chinese", "language_level": ["advantage", "good command"]}, {"language": "mandarin", "language_level": ["advantage", "good command"]}]}, "experience_required": {"duration": ["minimum 2 years"], "field": ["relevant experience", "banking"]}}, {"job_id": "100003009002028", "location_code": "hk", "company": "Trinity Search Limited", "job_title": "Senior Treasury Officer / Treasury Officer - Conglomerate", "description": "Our client is a top-tier Chinese conglomerate with multiple facets of businesses. They are currently seeking for a Senior Treasury Officer / Officer to join the team in Hong Kong.\nResponsibilities:\nResponsible for the central treasury function covering cash management & planning, payment, liquidity management, forex contract, forecast, financial risk management etc\nMonitor the Group\u2019s debt and capital structure, assist in negotiation and completion of banking facilities, review financing agreements and loan administration\nFoster and manage existing relationships with banks\nEnsure compliance in accordance to corporate governance and internal policies\nRequirements:\nBachelor degree holder in Finance, Accounting or other related disciplines\nCandidates with banking experience would be advantageous\nMinimum 2 years relevant experience in corporate treasury management / FI / bank\nFluency in English and Mandarin is essential\nCandidates with less experience would also be considered for the position Treasury Officer", "employment_types": ["Full Time"], "selling_points": ["Treasury Senior Officer / Officer", "Excellent Career Trajectory & Corporate Culture", "Min. 2 Years Relevant Experience"], "locations": ["Central & Western Area"], "categories": ["Banking / Finance", "Loan", "Treasury", "Fund Management"], "post_time": "2021-12-28T03:39:55Z", "salary": {"currency": null, "max": null, "min": null, "period": "monthly", "term": null}, "salary_visible": false, "title_keywords": ["officer"], "responsibilities": ["administration", "management", "policies", "review", "monitor", "ensure compliance", "payment", "forecast", "banking", "planning"], "requirements": {"degrees": ["bachelor degree holder"], "majors": ["related disciplines", "finance", "accounting"], "languages": ["english", "mandarin"], "language_level": ["fluency"], "hard_skills": [], "soft_skills": [], "languages_combined": [{"language": "english", "language_level": ["fluency"]}, {"language": "mandarin", "language_level": ["fluency"]}]}, "experience_required": {"duration": ["minimum 2 years"], "field": ["management", "relevant experience", "banking experience"]}}, {"job_id": "100003009007485", "location_code": "hk", "company": "Conners Consulting Limited", "job_title": "Market or Liquidity Risk Management", "description": "Our client are well-known and expanding commercial banks and now looking for high calibre to join their group.\n\n\u00a0Responsibilities\n\nHandle liquidity risk measurement, monitoring market / liquidity risk, PnL for Trading and Banking book, IRRBB, stress test and ALCO materials and reporting\nSupport to implement strategies over Bank\u2019s asset and liabilities, balance sheet growth and projection, with an on-going monitoring of the result\nSupport risk projects and review on market and liquidity risk policies and procedures\nContribute to the expansion and improvement of the region's funding risk assessment by in depth review and analysis\n\n\u00a0Requirements\n\nDegree holder in Finance, Risk Management, Accounting, or other quantitative discipline, preferably with professional qualification in CPA, FRM or CFA\nStrong knowledge on the market risk or liquidity risk management\nWith minimum 2 years experience from banking industry\nProficient in written and spoken English and Chinese\u00a0\n\n\nTo apply, please send your detailed resume to winnie[at]connersconsulting[dot]com or contact Winnie Lai at 3618 8348 for a confidential discussion.\n\n\nOnly shortlisted candidates will be notified.\n\nApplicants who are not contacted within two weeks may consider their applications unsuccessful.\n\nAll data collected will be used for recruitment purpose only & will be used strictly confidential.\n\nConners Consulting Limited\n\n2005 Kai Tak Commercial Building 317 Des Voeux Road Central Hong Kong\n\n\nTel: (852) 3996 8090\n\nWebsite: www.connersconsulting.com", "employment_types": ["Full Time", "Permanent"], "selling_points": ["Attractive package", "minimum. 2 years of experience", "Market or Liquidity Risk Management"], "locations": ["Central & Western Area"], "categories": ["Banking / Finance", "Analyst", "Treasury", "Risk Management"], "post_time": "2021-12-30T03:05:00Z", "salary": {"currency": null, "max": null, "min": null, "period": "monthly", "term": null}, "salary_visible": false, "title_keywords": [], "responsibilities": ["reporting", "policies", "analysis", "monitoring", "measurement", "review", "procedures", "banking", "balance sheet"], "requirements": {"degrees": ["degree holder"], "majors": ["finance", "accounting", "risk management"], "languages": ["english", "chinese"], "language_level": ["proficient"], "hard_skills": ["cfa", "cpa", "frm"], "soft_skills": ["detailed"], "languages_combined": [{"language": "english", "language_level": ["proficient"]}, {"language": "chinese", "language_level": ["proficient"]}]}, "experience_required": {"duration": ["minimum 2 years"], "field": ["banking industry"]}}, {"job_id": "100003009002486", "location_code": "hk", "company": "-", "job_title": "Senior FX & Swap Trader - G10 FX & Commodity", "description": "Job Duties\nGenerate trading profit by trading in G7 Ccys and HKD market to maximize profitability\nProvide competitive pricing quotations to support treasury sales team and other departments\nMaintain timely, professional, services of good quality, including quoting managing orders of both internal and external clients\nProvide market information & forecast for Management to formulate business strategies\nPrepare commentary & reporting when required\nJob Requirements\nBachelor Degree or above in Economics, Finance or Quantitative Disciplines\nMinimum 3 years of experience or above in active FX/Forward/Swap trade execution/dealing\nStrong HKD market knowledge including spot, forward and swap is a plus\nStrong track records of trading profit\nSelf motivated with strong communication, interpersonal and analytical skills\nFluent in both spoken and written English & Chinese, includes Putonghua", "employment_types": ["Full Time", "Permanent"], "selling_points": [], "locations": ["Central"], "categories": ["Banking / Finance", "Treasury", "Dealing & Trading"], "post_time": "2021-12-28T05:58:14Z", "salary": {"currency": null, "max": null, "min": null, "period": "monthly", "term": null}, "salary_visible": false, "title_keywords": [], "responsibilities": ["reporting", "management", "market information", "quality", "maintain", "sales team", "forecast"], "requirements": {"degrees": ["degree or above", "bachelor"], "majors": ["finance", "economics"], "languages": ["putonghua", "english", "chinese"], "language_level": ["fluent"], "hard_skills": ["plus", "analytical skills"], "soft_skills": ["analytical skills", "self motivated", "communication", "active", "interpersonal"], "languages_combined": [{"language": "putonghua", "language_level": ["fluent"]}, {"language": "english", "language_level": []}, {"language": "chinese", "language_level": []}]}, "experience_required": {"duration": ["minimum 3 years"], "field": []}}, {"job_id": "100003009006605", "location_code": "hk", "company": "CUHK Medical Centre Limited", "job_title": "Senior Manager, Finance", "description": "Key Responsibilities\n\nLead a team of professional and clerical staffs in operations and oversees the Shroff, Revenue and Account Receivable Function;\nWork with relevant departments and parties in formulating and reviewing the billing procedures;\nPrepare the financial analysis, management and performance reports and implement the internal control procedure;\nParticipate the development and enhancement of the financial system; and\nPerform any other duties assigned by supervisors and may need to be on duty call after office hours.\n\u00a0\n\u00a0\n\nJob Requirements\n\nHolder of a Bachelor Degree in Accounting, Finance or a related discipline\nProfessional qualification in Accounting, Finance or a related discipline gained from recognised professional bodies\nAt least 10 years' work experience of which 3 years should be in managerial position.\u00a0 Experience in healthcare, retail or hotel industry preferred.\nCandidates with less experience will be considered for the post of Finance Manager\nGood problem solving, communication and interpersonal skill\nGood command of both spoken and written English and Chinese\nProficient in MS Office applications\n\nCompensation and Employment Terms\n\nWe provide a unique employment experience for people seeking careers in hospital and healthcare industry; and offer competitive remuneration packages to the successful candidates. Appointment will be made on a 3-year contract with contract-end gratuity, renewable subject to good performance and mutual agreement.\n\nApplication Closing Date\n\n11 January 2022\n\nPersonal Information Collection Statement\n\nData collected will only be used for job application processing. Applicants not contacted by CUHK Medical Centre Limited within eight weeks from the application closing date may assume their applications unsuccessful. All personal data collected will be kept for a period of 12 months from the application closing date, and will be destroyed thereafter.", "employment_types": ["Full Time", "Contract"], "selling_points": ["10 years' work experience", "3 years in managerial position", "Bachelor Degree in Accounting, Finance"], "locations": ["Shatin Area"], "categories": ["Banking / Finance", "Treasury", "Financial Services", "Credit Collection"], "post_time": "2021-12-29T09:34:42Z", "salary": {"currency": null, "max": null, "min": null, "period": "monthly", "term": null}, "salary_visible": false, "title_keywords": ["senior manager"], "responsibilities": ["any other duties", "management", "financial system", "performance reports", "operations", "procedures", "financial analysis", "lead a team", "internal control"], "requirements": {"degrees": ["degree", "bachelor"], "majors": ["finance", "accounting"], "languages": ["english", "chinese"], "language_level": ["good command"], "hard_skills": ["problem solving", "ms office"], "soft_skills": ["problem solving", "communication", "interpersonal skill"], "languages_combined": [{"language": "english", "language_level": ["good command"]}, {"language": "chinese", "language_level": ["good command"]}]}, "experience_required": {"duration": ["at least 10 years", "3 years"], "field": ["managerial", "healthcare", "hotel industry", "finance manager", "retail"]}}, {"job_id": "100003009002317", "location_code": "hk", "company": "China Forestry Treasury Center Company Limited", "job_title": "Vice President - Finance and Investment", "description": "Responsibilities:\n\nResponsible for initiating and exploring financing channels from all currently available financing sources in Hong Kong for generation of liabilities/equity in the CTC, with specialty on bond issuance or other financial instruments issuance;\nAssist Management to manage DCM deal sourcing and syndicate function including but not limited to deal process, price bargaining, term sheet structuring;\nLiaise with investors, other departments and customers to ensure efficient and effective communication among all parties;\nLead the overall end to end process to expedite the revenue generation and risk control;\nSupervise development credit applications and monitor client portfolio;\nSupervise allotted account portfolio and ensure excellent customer service;\nPreparation of management reports for identification of business opportunities and internal monitoring;\nAnalyse all business objectives and ensure achievement of all product mix for all relationships with customers;\nMaintain knowledge on all bank products in order to provide efficient customer services;\nAd hoc projects assigned by department head.\n\n\u00a0Requirements:\n\nBachelor\u2019s degree or above in Accounting, Business Studies or relevant disciplines, professional qualification CPA/CFA is preferable;\nHolder of Representative licenses under HKMA/SFC regulated activities for Type 1, 4 & 9 is preferable;\n5 to 8 years or above working experience in the field of finance sectors or treasurer in Corporate, experience in DCM is preferable;\nPositive work attitude and good team player;\nProactive and strong communication skills;\nStrong attention to figures and details with good organization skills;\nAble to work under pressure, self-motivated, detail minded and able to manage multiple tasks;\nGood command of written and spoken English, Cantonese and Mandarin;\nLiterate in Microsoft office applications;\nLess experience will be considered the position of AVP.", "employment_types": ["Full Time", "Permanent"], "selling_points": ["Responsible for exploring financing channels", "Manage DCM deal sourcing & syndicate function", "Liaise with investors, clients & inter-departments"], "locations": ["Sheung Wan"], "categories": ["Banking / Finance", "Treasury"], "post_time": "2021-12-28T04:34:51Z", "salary": {"currency": null, "max": null, "min": null, "period": "monthly", "term": null}, "salary_visible": false, "title_keywords": ["vice president"], "responsibilities": ["management", "control", "business opportunities", "monitoring", "monitor", "customer services", "communication", "management reports", "customer service", "maintain", "ad hoc projects", "liaise with", "analyse"], "requirements": {"degrees": ["degree or above", "bachelor"], "majors": ["business", "accounting"], "languages": ["cantonese", "english", "mandarin"], "language_level": ["good command"], "hard_skills": ["cfa", "cpa", "hkma", "microsoft office"], "soft_skills": ["communication skills", "good team player", "self-motivated", "multiple tasks", "organization skills", "proactive", "positive work attitude", "work under pressure"], "languages_combined": [{"language": "cantonese", "language_level": ["good command"]}, {"language": "english", "language_level": ["good command"]}, {"language": "mandarin", "language_level": ["good command"]}]}, "experience_required": {"duration": ["5 to 8 years"], "field": ["finance"]}}, {"job_id": "100003009002474", "location_code": "hk", "company": "Industrial and Commercial Bank of China (Asia) Limited", "job_title": "IT Project Manager, Global Markets (Treasury)", "description": "Job Responsibilities\nProvide support and follow-up both hardware & software production cases in Global Market Department.\nCoordinate with Technical department\uff0cexternal vendors and related entities for system development, enhancement or incident cases/ project.\nTake a role of project manager to plan, organize, coordinate and execute system or financial product related project on behalf of front office.\nAssist in handling the matters of Business Continuity Plan and Deposit Protection Scheme.\nFacilitate and manage UAT environment as well as perform UAT with end users, responsible for arranging users training and reviewing procedure by the end of the project life cycle.\nManaging and reviewing treasury system users and parameter setup.\nJob Requirements\nBachelor degree or above, preferably with major in Economics, Information Technology or related disciplines.\nAt least\u00a03 years\u2019 experience in banking business, and \u00a0familiar with treasury products and systems\nGood PC operation skills.\nExcellent communication and interpersonal skills.\nFluent in\u00a0 English, Cantonese, and Mandarin\nCandidate with less experiences will also be considered\n\nIndustrial and Commercial Bank of China (Asia) Limited (\u201cICBC (Asia)\u201d) is the flagship of overseas business of Industrial and Commercial Bank of China Limited (\u201cICBC\u201d) \u2013 currently the largest commercial bank in China, and it is one of the domestic systemically important banks (D-SIBs) in Hong Kong. Currently, ICBC (Asia) has 57 retail outlets (including 29 \u201cElite Club\u201d Wealth Management Centres) in Hong Kong. It is engaged in commercial banking, investment banking and other financial services, including those of securities, insurance and funds, with a focus on commercial and retail banking as well as global market business. Chinese Mercantile Bank and ICBC Asset Management (Global) Company Limited, two wholly-owned subsidiaries of ICBC (Asia), specialize in Renminbi services in mainland China and ICBC\u2019s global asset management business respectively.\n\n-", "employment_types": ["Permanent"], "selling_points": [], "locations": ["Central"], "categories": ["Banking / Finance", "Treasury", "Information Technology (IT)", "Support", "Software Development"], "post_time": "2021-12-28T05:56:23Z", "salary": {"currency": null, "max": null, "min": null, "period": "monthly", "term": null}, "salary_visible": false, "title_keywords": ["it project manager"], "responsibilities": ["business continuity", "provide support", "software", "uat", "coordinate with", "coordinate", "hardware", "plan", "setup"], "requirements": {"degrees": ["degree or above", "bachelor"], "majors": ["related disciplines", "economics", "information technology"], "languages": ["cantonese", "english", "chinese", "mandarin"], "language_level": ["fluent"], "hard_skills": ["pc", "focus"], "soft_skills": ["focus", "communication and interpersonal skills"], "languages_combined": [{"language": "cantonese", "language_level": ["fluent"]}, {"language": "english", "language_level": ["fluent"]}, {"language": "chinese", "language_level": []}, {"language": "mandarin", "language_level": ["fluent"]}]}, "experience_required": {"duration": ["at least 3 years"], "field": ["business", "banking"]}}, {"job_id": "100003009006507", "location_code": "hk", "company": "GF Holdings (Hong Kong) Corporation Ltd", "job_title": "Vice President, Product Control (Finance)", "description": "Responsibilities\n\nAnalyze and valuate a wide range of financial products, including but not limited to bonds, structure notes, other structured products, etc;\nPrepare daily P&L reporting, Calculate P&Ls of different investment pools;\nCoordinate with internal stakeholders including front desk, Risk Department on the development of valuation model;\nParticipate in related valuation system enhancement projects;\nProduce daily and quarterly product control reports to management;\nAd-hoc analysis and PNL reporting as needed;\nHandle other ad-hoc tasks as assigned by Financial Controller.\nRequirement\n\nDegree holder, major in accounting or other finance related subjects\nMinimum 5 years\u2019 work experience in the field of Product Control in sizable financial institutions;\nFamiliar with the valuation of different financial products, especially in Fixed Income Products (bonds, structure notes, etc);\nStrong & Solid knowledge on financial instruments & market operations\nProficient in setting up valuation model;\nIndependent, strong analytical abilities and communication skill, good time management and high attention to details\nExcellent written and oral English and Chinese, Mandarin preferred\nWe offer attractive remuneration package and fringe benefits to the right candidate. Interested applicants please send detailed resume stating present & expected salaries and date of availability to Human Resources Department by clicking \"APPLY NOW\".\n\nFurther information about our group companies can be found at www.gfgroup.com.hk and www.gf.com.cn.\n\nAll applications will be treated in the strictest confidence and personal data collected will be used for recruitment purpose only.", "employment_types": ["Full Time"], "selling_points": ["Product Control in sizable financial institutions", "Knowledge on financial instruments", "Minimum 5 years\u2019 work experience"], "locations": ["Sheung Wan"], "categories": ["Banking / Finance", "Treasury", "Equities / Capital Markets", "Risk Management"], "post_time": "2021-12-29T09:09:31Z", "salary": {"currency": null, "max": null, "min": null, "period": "monthly", "term": null}, "salary_visible": false, "title_keywords": ["vice president"], "responsibilities": ["ad-hoc", "valuation", "reporting", "control", "management", "analysis", "ad-hoc tasks", "coordinate with", "p&l", "reports", "enhancement projects"], "requirements": {"degrees": ["degree holder"], "majors": ["finance", "accounting"], "languages": ["english", "chinese", "mandarin"], "language_level": ["excellent"], "hard_skills": [], "soft_skills": ["oral", "independent", "communication skill", "attention to details", "time management"], "languages_combined": [{"language": "english", "language_level": ["excellent"]}, {"language": "chinese", "language_level": ["excellent"]}, {"language": "mandarin", "language_level": []}]}, "experience_required": {"duration": ["minimum 5 years"], "field": ["financial institutions"]}}, {"job_id": "100003009003951", "location_code": "hk", "company": "Industrial and Commercial Bank of China (Asia) Limited", "job_title": "Global Markets Sales Manager, Margin Trading, Treasury", "description": "Job Responsibilities\nMarket treasury margin products to target customers\nTake, monitor and execute customers\u2019 order\nProvide marketing information and trading strategies to customers\nMonitor the margin deposit of customers\u2019 account\nPrepare credit proposals for customers\nAssist in business planning, budget preparation and reporting\nAchieve the target allocated by Supervisor\nKnowledge & Skills\nBachelor Degree or above\nHolder of SFC Type 1, 4 licenses is a must.\nMinimum 3 years of relevant experience in handling treasury products and operations.\nPrompt reaction to customer needs and familiar with treasury systems like Reuters, Bloomberg, Kondor\nGood presentation, negotiation and analytical skills\nGood communication and interpersonal skills\nFluent in both spoken and written English and Chinese, includes Putonghua.\n\u00a0", "employment_types": ["Permanent"], "selling_points": [], "locations": ["Central"], "categories": ["Banking / Finance", "Treasury", "Financial Services", "Dealing & Trading"], "post_time": "2021-12-28T12:56:56Z", "salary": {"currency": null, "max": null, "min": null, "period": "monthly", "term": null}, "salary_visible": false, "title_keywords": ["sales manager"], "responsibilities": ["reporting", "operations", "budget", "monitor", "systems", "communication", "planning"], "requirements": {"degrees": ["degree or above", "bachelor"], "majors": [], "languages": ["putonghua", "english", "chinese"], "language_level": ["fluent"], "hard_skills": ["bloomberg", "analytical skills"], "soft_skills": ["negotiation", "prompt", "analytical skills", "communication and interpersonal skills", "presentation"], "languages_combined": [{"language": "putonghua", "language_level": ["fluent"]}, {"language": "english", "language_level": []}, {"language": "chinese", "language_level": []}]}, "experience_required": {"duration": ["minimum 3 years"], "field": ["relevant experience"]}}]