[{"job_id": "100003009049073", "location_code": "hk", "company": "John Swire & Sons (HK) Limited", "job_title": "Assistant Accountant / Accountant", "description": "A highly-diversified and global corporation, the Swire Group\u2019s businesses encompass property, aviation, beverages and food chain, as well as marine services and trading & industrial activities. Its core businesses are mainly focused in Asia, with its key operations in Hong Kong and the Chinese Mainland. Within Asia, Swire's activities come under the Group's publicly quoted arm, Swire Pacific Limited, which is the major shareholder in two Hong Kong listed companies: Swire Properties and Cathay Pacific Airways.\nJohn Swire & Sons (H.K.) Limited is the holding company of the publicly-listed conglomerate, Swire Pacific Ltd. Our Group Finance Department is now inviting candidates to apply for the following position:\n\nAssistant Accountant / Accountant\n\n\nThis role aims to be responsible for the accounting functions of Swire Pacific head office, with supervision by the Financial Accountant.\n\nResponsibilities:\nHandle full set of accounts and oversee daily accounting operations\nPerform month end closing, prepare schedules, financial reports and analysis\nLook after daily cashflow and plan fund transfer\nMaintain payment schedule, and ensure accurate settlement and confirmation procedures for Treasury deals (loan interests, deposits, SWAP settlements, etc.)\nHandle intercompany fund transfer and reconcile loan balance with subsidiaries\nReview payments, expense claims and petty cash\nLiaise with auditors in respect of internal/external audits\nAssist in other ad-hoc duties and tasks assigned\n\nRequirements:\n\nBachelor\u2019s degree holder in accounting, or related disciplines with at least 3 years of full set accounting experience\nHolder of ACCA, HKICPA or equivalent qualifications. Student member will also be considered\nProficient in Microsoft Office Suite and Word Processing applications\nSolid knowledge of SUN Accounting System will be desirable\nIndependent, responsible, and able to meet deadlines\nExcellent communication skills in both written and spoken English and Chinese. Fluent Putonghua is required\n\nApplication:\n\nAt Swire, we are committed to creating an inclusive and supportive working environment for all our people regardless of their age, gender, gender identity, sexual orientation, relationship, family status, disability, race, ethnicity, nationality, religious or political beliefs. We believe in creating an environment where people feel comfortable at work and are able to realise their full potential.\nWe offer a competitive package to the right candidate. If you meet the qualifications and are interested in this position, you can send your application by clicking \u2018Apply Now\u2019. We will contact all shortlisted candidates.\nThe Swire group is an equal opportunity employer. All applications will be used exclusively for selection purposes and handled confidentially by authorised personnel only. Your application may also be considered for other suitable positions within the Swire group (please indicate clearly on your application if you would not like to be considered for other positions within the group.) Following the data privacy ordinance, all unsuccessful applications will be destroyed after an appropriate time.", "employment_types": ["Full Time", "Permanent"], "selling_points": ["3+ years of full set accounting experience", "Holder of ACCA, HKICPA or equivalent qualification", "Solid knowledge of SUN Accounting System is a plus"], "locations": ["Quarry Bay"], "categories": ["Accounting", "Accountant"], "post_time": "2022-01-14T08:04:03Z", "salary": {"currency": null, "max": null, "min": null, "period": null, "term": null}, "salary_visible": false, "title_keywords": ["accountant", "assistant accountant"], "responsibilities": ["month end closing", "financial reports", "analysis", "full set of accounts", "procedures", "daily accounting operations", "review", "audits", "payment", "maintain", "payments", "schedule", "plan", "ad-hoc duties", "liaise with", "prepare schedules"], "requirements": {"degrees": ["bachelor", "degree holder"], "majors": ["related disciplines", "accounting"], "languages": ["putonghua", "english", "chinese"], "language_level": ["excellent", "fluent"], "hard_skills": ["acca", "word processing", "microsoft office suite", "accounting system", "hkicpa"], "soft_skills": ["communication skills", "supportive", "independent", "responsible", "committed", "meet deadlines"], "languages_combined": [{"language": "putonghua", "language_level": ["fluent"]}, {"language": "english", "language_level": ["excellent"]}, {"language": "chinese", "language_level": ["excellent"]}]}, "experience_required": {"duration": ["at least 3 years"], "field": ["related", "accounting experience", "accounting"]}}, {"job_id": "100003009051826", "location_code": "hk", "company": "The Great Eagle Group of Companies", "job_title": "Assistant Accountant / Accountant", "description": "Responsibilities:\n\nPrepare full set of monthly management accounts and month-end closing independently\nPrepare statutory financial statements and liaise with external auditors\nAnalytical review on management reports to explain business performance\nHandle budgeting and forecasting\nAssist in group consolidation and prepare financials for results announcement\nHandle ad hoc tasks and assignments as required\n\nRequirements:\n\nDegree holder in Accountancy, Finance or other related disciplines\nMember of recognized accounting bodies (HKICPA, ACCA or equivalent) is preferred\n3 \u2013 5 years relevant experience, preferably gained in listed companies or sized CPA firms\nExperience in real estate or hospitality industry is an advantage\nKnowledge of IFRS / HKFRS\nProficient in MS Office Application\nSelf-motivated, detail-oriented, proactive and able to work independently\nGood communication and interpersonal skills\nGood command of both written and spoken English and Chinese\n\nSalary and benefits will be commensurate with qualifications and experience.\u00a0 Interested parties, please send a full resume with present and expected salary, and date available to The Human Resources Department, 32/F., Great Eagle Centre, 23 Harbour Road, Wanchai, Hong Kong or e-mail to us.\u00a0(Please quote the reference no. on the envelope and the covering letter.)\n\nTo know more about us, please visit our website at http://www.greateagle.com.hk.\n\nWe are an equal opportunity employer and welcome applications from all qualified candidates.\n\nPersonal data collected will be treated in strict confidence and used only for recruitment-related purpose. Applicants who have not heard from us within four weeks may consider their applications unsuccessful. All personal data will be destroyed after 12 months.", "employment_types": ["Full Time", "Permanent"], "selling_points": ["Monthly report & month-end closing", "Handle budgeting and forecasting", "HKICPA, ACCA or equivalent is preferred"], "locations": ["Wan Chai"], "categories": ["Accounting", "Accountant", "Accounting Clerk / Supervisor", "Financial Analyst"], "post_time": "2022-01-17T01:18:24Z", "salary": {"currency": null, "max": null, "min": null, "period": "monthly", "term": null}, "salary_visible": false, "title_keywords": ["accountant", "assistant accountant"], "responsibilities": ["management", "budgeting", "review", "ad hoc tasks", "financial statements", "management reports", "month-end closing", "liaise with", "forecasting", "external auditors"], "requirements": {"degrees": ["degree holder"], "majors": ["related disciplines", "finance", "accountancy"], "languages": ["english", "chinese"], "language_level": ["good command"], "hard_skills": ["acca", "ifrs", "hkfrs", "cpa", "ms office", "hkicpa"], "soft_skills": ["self-motivated", "work independently", "detail-oriented", "communication and interpersonal skills", "proactive"], "languages_combined": [{"language": "english", "language_level": ["good command"]}, {"language": "chinese", "language_level": ["good command"]}]}, "experience_required": {"duration": ["5 years"], "field": ["hospitality industry", "relevant experience"]}}, {"job_id": "100003009052296", "location_code": "hk", "company": "Chef's Garden Limited", "job_title": "Accountant", "description": "Responsibilities:\n\nPrepare annual audit schedules, accounts reconciliation, provide appropriate follow-up actions, and manage the audit process;\nHandle and assist any ad-hoc tasks as assigned\nRequirements:\n\nDiploma/ Certificate in Accounting\n3 years accounting/ audit experience\nPrevious experience in restaurant/ retail business, Peachtree, Xero is an advantage\nProficiency in Excel and other MS office applications\nStable, self-motivated, hardworking, well-organized, detail-minded with strong sense of responsibilities, good interpersonal and communication skills;\nImmediately available\n\nWe\u00a0offer five-day work and Free meals\n\nInterested parties please apply by sending full resume with current and expected salary by clicking \"Apply Now\".\u00a0\n\n(All information and personal data collected relating to employment applications will be kept confidential and will be used \u00a0for recruitment purpose only.)", "employment_types": ["Full Time"], "selling_points": ["exp. in retail/catering business is a plus", "immediate available is preferable", "Be able to handle full set of accounts"], "locations": ["Sai Ying Pun"], "categories": ["Accounting", "Accountant", "Others", "Hospitality / F & B", "Food & Beverage"], "post_time": "2022-01-17T03:58:31Z", "salary": {"currency": null, "max": null, "min": null, "period": "monthly", "term": null}, "salary_visible": false, "title_keywords": ["accountant"], "responsibilities": ["schedules", "ad-hoc tasks", "audit", "annual audit"], "requirements": {"degrees": ["certificate", "diploma"], "majors": ["accounting"], "languages": [], "language_level": [], "hard_skills": ["excel", "peachtree", "xero", "ms office"], "soft_skills": ["detail-minded", "communication skills", "self-motivated", "well-organized", "stable", "interpersonal", "hardworking", "sense of responsibilities"], "languages_combined": []}, "experience_required": {"duration": ["3 years"], "field": ["restaurant", "business", "audit experience", "accounting", "retail"]}}, {"job_id": "100003009054839", "location_code": "hk", "company": "Hong Kong Parkview", "job_title": "Accountant - Hong Kong Parkview Group", "description": "Duties and Responsibilities\nResponsibilities:\nAssist in daily accounting operations for the Hong Kong Parkview Group.\nHandle full set of accounts, financial analysis and management reports.\nConduct basic accounting system maintenance.\nSupport in ad-hoc duties.\nRequirements:\nHigher Diploma or Degree holder in Accounting or related discipline; member of HKICPA or equivalent is preferrable\nAt least 4 years audit / accounting experience.\nWell versed with MS Excel.\nGood command of spoken and written English, Cantonese and Putonghua.\nWe offer competitive remuneration package including 5-day work week, family medical plan, duty meal and free shuttle bus (to and from Central, Admiralty, and Aberdeen; to Causeway Bay and Wanchai) and excellent career opportunities to the right candidate. \u00a0\nPlease send full resume, expected salary and contact telephone number to\nHong Kong Parkview\nHuman Resources Department\n88 Tai Tam Reservoir Road, Hong Kong\nConfidential Fax No. 28123490\nEmail via \"Apply Now\"\n\n(All data collected will be used for recruitment purpose only)", "employment_types": ["Full Time", "Permanent"], "selling_points": ["Conduct basic accounting system maintenance", "Support in ad-hoc duties", "At least 4 years audit / accounting experience"], "locations": ["Wan Chai Area"], "categories": ["Accounting", "Accountant", "Audit", "Financial Analyst"], "post_time": "2022-01-17T11:37:40Z", "salary": {"currency": null, "max": null, "min": null, "period": "monthly", "term": null}, "salary_visible": false, "title_keywords": ["accountant"], "responsibilities": ["maintenance", "full set of accounts", "daily accounting operations", "financial analysis", "management reports", "ad-hoc duties"], "requirements": {"degrees": ["diploma", "degree holder"], "majors": ["accounting"], "languages": ["cantonese", "putonghua", "english"], "language_level": ["good command"], "hard_skills": ["no", "ms excel", "hkicpa"], "soft_skills": [], "languages_combined": [{"language": "cantonese", "language_level": ["good command"]}, {"language": "putonghua", "language_level": ["good command"]}, {"language": "english", "language_level": ["good command"]}]}, "experience_required": {"duration": ["at least 4 years"], "field": ["accounting experience", "audit"]}}, {"job_id": "100003009054857", "location_code": "hk", "company": "Liu Chong Hing Investment Ltd", "job_title": "Accountant / Senior Accountant", "description": "To cope with our continuous business growth, we are looking for passionate and competent candidates to join us.\n\nJob Responsibilities\n\nHandle full set of accounts, month-end closing and daily accounting entries.\nPerform general accounting functions such as voucher and cheque preparation, cashflow management, bank account reconciliation, accounts receivables and payables.\nPrepare financial management reports, analysis, budget and forecast.\nLiaise with external auditors, bankers and vendors.\nParticipate in ad hoc projects and tasks as assigned by Department Head.\n\n\u00a0Job Requirements\n\nDegree holder or above in Accounting or Finance or equivalent.\nMinimum 5 years\u2019 relevant experience in consolidation and financial accounting, preferably in HK Listed Company.\nMember of HKICPA / ACCA or equivalent professional accounting bodies.\nGood knowledge in accounting standards and taxation.\nSelf-motivated, detail-minded and able to work under pressure.\nStrong analytical and communication skills.\nGood command in English, Cantonese and Mandarin.\nCandidate with PRC / audit experience is preferred.\nPRC travel may be required.\nCandidate with more experience will be considered as Senior Accountant.\u00a0\n\nWe offer a\u00a05-day work week\u00a0with\u00a0attractive remuneration package to the right candidate. Interested parties\u00a0please apply with full resume, contact number, date available and expected salary by\u00a0clicking \"Apply Now\".\u00a0\n\nTo learn more about us, please visit our website\u00a0Liu Chong Hing Investment Ltd.\n\u00a0\nPersonal data provided by job applicants will be used for recruitment purpose only.", "employment_types": ["Full Time", "Permanent"], "selling_points": ["Degree holder Accounting or Finance", "Member of HKICPA / ACCA", "5 -day work week with medical insurance"], "locations": ["Central & Western Area"], "categories": ["Accounting", "Accountant", "Accounting Clerk / Supervisor", "Others"], "post_time": "2022-01-17T11:55:10Z", "salary": {"currency": null, "max": null, "min": null, "period": "monthly", "term": null}, "salary_visible": false, "title_keywords": ["accountant", "senior accountant"], "responsibilities": ["management", "analysis", "full set of accounts", "budget", "management reports", "month-end closing", "ad hoc projects", "forecast", "liaise with", "daily accounting", "external auditors"], "requirements": {"degrees": ["degree holder"], "majors": ["finance", "accounting"], "languages": ["cantonese", "english", "mandarin"], "language_level": ["good command"], "hard_skills": ["acca", "hkicpa"], "soft_skills": ["detail-minded", "communication skills", "self-motivated", "work under pressure"], "languages_combined": [{"language": "cantonese", "language_level": ["good command"]}, {"language": "english", "language_level": ["good command"]}, {"language": "mandarin", "language_level": ["good command"]}]}, "experience_required": {"duration": ["minimum 5 years"], "field": ["consolidation", "senior accountant", "relevant experience", "audit experience", "accounting", "financial"]}}, {"job_id": "100003009053217", "location_code": "hk", "company": "CEMG Management Limited", "job_title": "Accountant", "description": "Job Highlights\n\nOversee daily financial operations of the Group\nHandle full set of accounts\n5 days work and Medical Insurance\nUniversity graduate or Higher Accounting(LCC&I) or equivalent\n\nReporting to the Account Manager, you will be responsible for\n\nResponsibilities\n\nAssist in the preparation of accounts and financial reports, including general ledger accounting entries, account receivable, account payable, related party transactions;\nPrepare monthly management reports, budgeting and forecasting;\nPrepare monthly financial report package including profit and loss accounts, statement of financial positions, cash flow statements; analyze and provide commentary on the key accounts;\nPerform periodical physical stock count and variance reconciliation;\nPerform RPT reconciliation and bank reconciliation;\nMaintain proper documentation of financial record;\nPerform ad hoc assignments as required.\n\nRequirements:\n\nUniversity graduate or Higher Accounting (LCC&I) or equivalent\nAudit experience is highly referred\nFluent in Mandarin, Cantonese and English\nProficient in MS office (Excel, Word and Powerpoint)\nTeam player with excellent communication and interpersonal skills\nAble to work independently with a strong sense of\u00a0responsibility, self-motivation and able to meet tight schedules\nExperienced in ERP system implementation is an advantage\nWorking experience in healthcare service industry is an advantage\n\n\n\n\nWe offer a competitive remuneration package including excellent career prospects to the right candidate. Interested parties please click \"Quick Apply\" now.\n\nAll data collected will be used for recruitment purpose only.", "employment_types": ["Full Time"], "selling_points": ["5 days work and Medical Insurance", "Handle full set of accounts", "University graduate or Higher Accounting(LCC&I)"], "locations": ["Tin Hau"], "categories": ["Accounting", "Accountant", "Accounting Clerk / Supervisor", "Financial Analyst"], "post_time": "2022-01-17T06:27:44Z", "salary": {"currency": null, "max": null, "min": null, "period": "monthly", "term": null}, "salary_visible": false, "title_keywords": ["accountant"], "responsibilities": ["financial reports", "general ledger", "budgeting", "bank reconciliation", "transactions", "maintain proper documentation", "management reports", "cash flow", "financial report", "ad hoc assignments", "forecasting"], "requirements": {"degrees": ["university graduate"], "majors": ["accounting"], "languages": ["cantonese", "english", "mandarin"], "language_level": ["fluent"], "hard_skills": ["excel", "word", "powerpoint", "erp system", "ms office"], "soft_skills": ["work independently", "sense of responsibility", "communication and interpersonal skills", "self-motivation", "team player", "meet tight schedules"], "languages_combined": [{"language": "cantonese", "language_level": ["fluent"]}, {"language": "english", "language_level": ["fluent"]}, {"language": "mandarin", "language_level": ["fluent"]}]}, "experience_required": {"duration": [], "field": ["healthcare", "audit experience", "service industry"]}}, {"job_id": "100003009052675", "location_code": "hk", "company": "Oxford Asset Management Limited", "job_title": "Accountant", "description": "We\u00a0are a\u00a0well-established\u00a0property\u00a0leasing,\u00a0management and investment company located in Wanchai-Admiralty area, now inviting an experienced candidate for the position of\u00a0Accountant.\n\n\nResponsibilities:\n\nReview daily accounting operation, handle month end/year end closing and prepare monthly management reports.\nAssist in consolidated financial reporting preparation\nAssist in budget & forecast and audit & tax issues\nCoordinate with different operation teams in PRC and overseas;\nImplementation of proper internal control procedures, accounting\u00a0policies and procedures;\nLiaise with banks, auditors, IRD and tax authorities in Hong Kong and overseas;\nPerform ad hoc project / assignment as required\u00a0\n\nRequirements:\n\n\u00a0University Degree in Accounting/HKICPA student member;\n\u00a0Minimum 4-5 years relevant experience in accounting/audit preferably in property industry;\nHands-on experience in full sets of books and accounting operations\nProficiency in MS Excel; Hands-on experience in FlexSystem (FION & FIONA)\nProficiency in written & spoken English and Mandarin.\nInitiative, deadline and result oriented, pro-active and be a great team member;\nWork independently\u00a0\n\nWe offer an attractive remuneration package and excellent career prospects to the right candidate. Please send full resume, recent photo, current and expected salary, contact number and the availability for interview.\n\n\nPersonal data collected will be used for recruitment purpose only.", "employment_types": ["Full Time"], "selling_points": [], "locations": ["Wan Chai"], "categories": ["Accounting", "Accountant", "Accounting Clerk / Supervisor"], "post_time": "2022-01-17T03:41:10Z", "salary": {"currency": null, "max": null, "min": null, "period": "monthly", "term": null}, "salary_visible": false, "title_keywords": ["accountant"], "responsibilities": ["tax", "ad hoc", "review", "budget", "audit", "coordinate with", "teams", "implementation", "procedures", "management reports", "accounting policies", "financial reporting", "forecast", "liaise with", "daily accounting", "internal control"], "requirements": {"degrees": ["university degree"], "majors": ["accounting"], "languages": ["english", "mandarin"], "language_level": ["proficiency"], "hard_skills": ["ms excel", "flexsystem", "hkicpa"], "soft_skills": ["work independently", "result oriented", "hands-on", "pro-active", "team member", "initiative"], "languages_combined": [{"language": "english", "language_level": ["proficiency"]}, {"language": "mandarin", "language_level": ["proficiency"]}]}, "experience_required": {"duration": ["minimum 4-5 years"], "field": ["accounting", "relevant experience", "audit"]}}, {"job_id": "100003009054548", "location_code": "hk", "company": "Pine Peak Capital Group (Hong Kong) Limited", "job_title": "Accountant", "description": "Responsibilities:\n- Handle full set accounting duties for the private Companies;\n- Handle accounts payable, accounts receivable and invoice settlement;\n- Prepare cheque payment and fund transfer;\n- Liaise with the external auditors to carry out audit exercise;\n- Update the organization chart;\n- Handle the ad hoc tasks assigned by the Chairman.\n\nRequirements:\n- Degree holder in Accounting or related discipline, qualified member of ACCA / HKICPA is preferred but not a must;\n- At least 3 years of solid experience in accounting field, gained from private Company is highly preferred;\n- Strong PC skills especially MS Excel;\n- Good command of both written and spoken in English and Chinese, fluency in Putonghua is highly preferred.\n\nWe offer attractive remuneration package to the right candidate. Interested parties, please send full resume with current, expected salary and availability by clicking \"Apply Now\".\n\nCollected personal data is used for recruitment purpose only.", "employment_types": ["Full Time", "Permanent"], "selling_points": [], "locations": ["Central"], "categories": ["Accounting", "Accountant", "Accounting Clerk / Supervisor", "Finance / Accounting Manager"], "post_time": "2022-01-17T09:57:15Z", "salary": {"currency": null, "max": null, "min": null, "period": "monthly", "term": null}, "salary_visible": false, "title_keywords": ["accountant"], "responsibilities": ["handle full set accounting", "accounts receivable", "invoice", "ad hoc tasks", "audit", "payment", "liaise with", "accounts payable", "external auditors"], "requirements": {"degrees": ["degree holder"], "majors": ["accounting"], "languages": ["putonghua", "english", "chinese"], "language_level": ["fluency", "good command"], "hard_skills": ["acca", "pc skills", "ms excel", "hkicpa"], "soft_skills": [], "languages_combined": [{"language": "putonghua", "language_level": ["fluency", "good command"]}, {"language": "english", "language_level": ["good command"]}, {"language": "chinese", "language_level": ["good command"]}]}, "experience_required": {"duration": ["at least 3 years"], "field": ["accounting"]}}, {"job_id": "100003009052766", "location_code": "hk", "company": "GDC Technology Limited", "job_title": "Accountant", "description": "Responsibilities:\n\nHandle month-end closing\nPrepare management reports of various subsidiaries\nPrepare consolidated financial reports and financial analysis\nReview management reports submitted by overseas branches\nLiaise with various operation teams and external auditors\nHandle ad hoc projects\u00a0\n\nRequirements:\n\nBachelor\u2019s degree holder in Accounting\nMinimum 3 years\u2019 relevant working experience\nExperience gained in Big-4 or MNC preferred\nFamiliar with ERP system and proficient in Excel\nSelf-initiative, responsible and good communication skills\nGood command in both written and spoken English and Chinese (multi-national working environment)\nImmediate available is preferred\n\nAttractive remuneration package will be offered.\n\nAll information provided by applicants will be treated in strict confidence and used only for processing application.", "employment_types": ["Full Time"], "selling_points": [], "locations": ["North Point"], "categories": ["Accounting", "Accountant"], "post_time": "2022-01-17T03:58:53Z", "salary": {"currency": null, "max": null, "min": null, "period": "monthly", "term": null}, "salary_visible": false, "title_keywords": ["accountant"], "responsibilities": ["financial reports", "review", "teams", "financial analysis", "management reports", "month-end closing", "ad hoc projects", "liaise with", "external auditors"], "requirements": {"degrees": ["bachelor", "degree holder"], "majors": ["accounting"], "languages": ["english", "chinese"], "language_level": ["good command"], "hard_skills": ["excel", "erp system", "processing"], "soft_skills": ["communication skills", "confidence", "self-initiative", "responsible"], "languages_combined": [{"language": "english", "language_level": ["good command"]}, {"language": "chinese", "language_level": ["good command"]}]}, "experience_required": {"duration": ["minimum 3 years"], "field": ["relevant working experience"]}}, {"job_id": "100003009053625", "location_code": "hk", "company": "Babyzen Limited", "job_title": "Accountant / Assistant Accountant", "description": "Role & Responsibilities:\n\nResponsible for daily accounting duties, including payment preparation and bank reconciliations\nHandle full set of accounts, including GL, AR & AP, preparation of financial statements and management reporting, variance analysis and schedules\nCo-ordinate and assist the team to ensure smooth operations\nLiaise and coordinate with internal and external parties to handle regular and ad-hoc assignments, analysis and reporting as required\nAssist on the report development and automation\u00a0\n\nRequirements:\n\nDegree holder/Professional Qualification in Accounting, Finance or other related discipline\nMinimum of 5 years' relevant experience, preferably from sizeable institutions\nProficiency in MS Excel, Word and Chinese input\nGood command of spoken and written English and Chinese\nSelf-motivated, independent, strong sense of responsibility, detail-oriented, and able to handle multi-tasking\nExperience with ERP systems is a must\nImmediate availability is highly preferable\n\nCandidate with less experience will be considered for Assistant Accountant position.\n\nPlease apply with full resume together with current and expected salary\u00a0by clicking \"Apply Now\".\u00a0\n\nPersonal data collected will be used for recruitment purpose only.", "employment_types": ["Full Time", "Permanent"], "selling_points": ["Handle full set of accounts", "Degree holder, min 5 years relevant experience", "Immediately available is preferred"], "locations": ["Kowloon Bay"], "categories": ["Accounting", "Accountant"], "post_time": "2022-01-17T07:15:36Z", "salary": {"currency": null, "max": null, "min": null, "period": "monthly", "term": null}, "salary_visible": false, "title_keywords": ["accountant", "assistant accountant"], "responsibilities": ["ap", "liaise", "reporting", "ar", "schedules", "ad-hoc assignments", "analysis", "full set of accounts", "coordinate with", "bank reconciliations", "financial statements", "internal and external parties", "variance analysis", "payment", "management reporting", "ensure smooth operations", "daily accounting", "report"], "requirements": {"degrees": ["degree holder"], "majors": ["finance", "accounting"], "languages": ["english", "chinese"], "language_level": ["proficiency", "good command"], "hard_skills": ["chinese input", "erp systems", "ms excel", "word"], "soft_skills": ["self-motivated", "independent", "sense of responsibility", "detail-oriented", "multi-tasking"], "languages_combined": [{"language": "english", "language_level": ["good command"]}, {"language": "chinese", "language_level": ["proficiency", "good command"]}]}, "experience_required": {"duration": ["minimum of 5 years"], "field": ["relevant experience"]}}, {"job_id": "100003009053000", "location_code": "hk", "company": "Angliss Hong Kong Food Service Ltd", "job_title": "Accountant (Reporting)", "description": "Responsibilities:\n\nPrepare consolidated financial and management reporting, breakdowns and analysis\nHandle full set of accounts, month-end closing, inter-company reconciliation and prepare group reporting reports\nCompile financial analysis to facilitate businesses performance review and management decision making\nHandle PRC local finance department queries and escalate the accounting issue to Financial controller\nOccasional travel to PRC may be required\nParticipate in other accounting related and ad-hoc assignments\n\n\u00a0Requirement:\n\nDegree holder in Accounting, Finance or related discipline\n5 years\u2019 relevant experience of PRC accounting\nResult-driven, well organized and independent\nStrong analytical mind and good communication skills\nProficient in MS Office, knowledge in Kingdee would be an advantage\nFluent in written and spoken English, Chinese and Mandarin\n\nWe offer an attractive remuneration package including a competitive salary, fringe benefits and good career prospects to the right candidates.\u00a0\n\nInterestedarties please apply with a detailed resume together with expected salary and contact telephone no. to the\u00a0Human Resources Department, Angliss\u00a0Hong Kong Food Service Limited, 47- 51 Kwai Fung Crescent, Kwai Chung, New Territories, Hong Kong\u00a0or fax 2439 5168 or clicking the\u00a0\"Apply now\"\u00a0button for application.\n\n(We regret that only successful candidates will be notified.)\n\n(Data collected will be used for recruitment purpose only.)", "employment_types": ["Full Time", "Permanent"], "selling_points": ["Financial and management reporting", "Handle full set of accounts", "Has experience in PRC accounting"], "locations": ["Kwai Fong"], "categories": ["Accounting", "Accountant", "Hospitality / F & B", "Food & Beverage"], "post_time": "2022-01-17T04:56:49Z", "salary": {"currency": null, "max": null, "min": null, "period": "monthly", "term": null}, "salary_visible": false, "title_keywords": ["accountant"], "responsibilities": ["reporting", "management", "ad-hoc assignments", "analysis", "full set of accounts", "review", "financial analysis", "month-end closing", "reports", "management reporting"], "requirements": {"degrees": ["degree holder"], "majors": ["finance", "accounting"], "languages": ["english", "chinese", "mandarin"], "language_level": ["fluent"], "hard_skills": ["ms office", "prc accounting"], "soft_skills": ["communication skills", "independent", "well organized", "analytical mind", "driven"], "languages_combined": [{"language": "english", "language_level": ["fluent"]}, {"language": "chinese", "language_level": ["fluent"]}, {"language": "mandarin", "language_level": ["fluent"]}]}, "experience_required": {"duration": ["5 years"], "field": ["accounting", "relevant experience"]}}, {"job_id": "100003009053487", "location_code": "hk", "company": "Global Life Immigration (HK) Limited", "job_title": "Accountant/ Assistant Accountant", "description": "Key Responsibilities\uff1a\n\n\u00a0Preparation of full set of accounts, financial report and management report\n\u00a0Responsible for daily accounting operation\n\u00a0Provide administrative and clerical support\n\u00a0Assist in ad hoc assignments\n\n\u00a0Requirements:\n\n\nF. 6 or above\n1-2 years accounting experience\nProficiency in MS Office application and Chinese Word Processing\nGood communication and presentation skill\nHardworking, good in team work, able to work under pressure\nGood in Chinese, English and Mandarin\nLess experience / Fresh graduate is also welcome\n\nWe offer\n\nWe offer attractive remuneration package, 5-day work, performance bonus, medical allowance, birthday leave and career prospects to successful candidates. \u00a0Interested parties please apply in full resume with your employment history, current\u00a0and expected salary, and click APPLY NOW.", "employment_types": ["Full Time", "Permanent"], "selling_points": ["F. 6 or above", "1-2 years accounting experience", "Attractive remuneration package"], "locations": ["Tsim Sha Tsui"], "categories": ["Accounting", "Accountant", "Accounting Clerk / Supervisor", "Treasurer"], "post_time": "2022-01-17T07:02:44Z", "salary": {"currency": null, "max": null, "min": null, "period": "monthly", "term": null}, "salary_visible": false, "title_keywords": ["accountant", "assistant accountant"], "responsibilities": ["full set of accounts", "financial report", "ad hoc assignments", "administrative and clerical support", "daily accounting", "management report"], "requirements": {"degrees": ["fresh graduate"], "majors": [], "languages": ["english", "chinese", "mandarin"], "language_level": ["proficiency", "good"], "hard_skills": ["presentation skill", "chinese word processing", "ms office"], "soft_skills": ["communication", "presentation skill", "hardworking", "work under pressure"], "languages_combined": [{"language": "english", "language_level": ["good"]}, {"language": "chinese", "language_level": ["proficiency", "good"]}, {"language": "mandarin", "language_level": ["good"]}]}, "experience_required": {"duration": ["1-2 years"], "field": ["accounting experience"]}}, {"job_id": "100003009052302", "location_code": "hk", "company": "Somfy Co Ltd", "job_title": "Assistant Accountant / Accountant", "description": "Responsibilities:\n\n\nRecords accounting transactions on a daily basis including collecting, coordinating, and verifying accounting data\nResponsible for maintaining the account as well as the monthly statement including cash flow statement and bank reconciliation\u00a0\nAssist in analyses accounting situations (preparation and use of dashboards, ad-hoc reports and analysis as and when required.)\nPerforms financial, fiscal, and social accounting procedures, provide accurate and timely financial reports and information according to Somfy group rules and local GAAP for statutory and management purposes\nContributes to the improvement of management tools and accounting procedures\nSecures the approval flow of segregation of duties, as well as internal BU procedures and processes, are in place to prevent and to detect fraud, accounting and reporting errors\nDigitizes\u00a0among the document flows across the team and accounting documents\nAssist to Controller in tax matters, external & internal audits, company secretarial, banking, legal compliance, insurance and leasing matters when required\nResponsible for\u00a0Accounts Receivable including managing collection duties with the support\u00a0from the Sales team and participating in implementing effective credit policy with regular review to protect the interests of the company\nEnsure the\u00a0payment processes are properly validated according to the procedures by authority and prepare the bank payment in order\u00a0\nCarry out ad-hoc duties to cope with business needs as and when necessary\n\nRequirements:\n\nBachelor\u2019s degree holder or above in Accounting, Finance, or related disciplines\nFresh graduate will also be considered\nWith hands-on experience gained from sizable organization or MNC will be an advantage\nProficient in PC Skills especially MS 365 applications and possess experience in ERP system such as SAP, Hyperion is a plus\nGood problem solving, analytical skills and able to work independently\nDemonstrate ability to interact and communicate effectively at all levels\nDetail-oriented, committed, pro-active and deadline-driven\nGood command of both written and spoken English and Chinese\nCandidates with more experience will be considered as Accountant\n\nFor Interested parties, please send your full resume with expected salary and availability to the Senior\u00a0Human Resources Manager, Asia Pacific. You are most welcome to visit our company web-site at\u00a0http://www.somfy.com\u00a0for more company information.\n\nOnly short-listed candidates will be informed.\u00a0\u00a0\n\nWe are an equal opportunity employer and welcome applications from all qualified candidates. Personal data collected will be treated in strict confidence and used for recruitment purposes only within the Somfy Group of Companies. The personal data of unsuccessful applicants will be retained for a period of 6 months.", "employment_types": ["Full Time", "Permanent"], "selling_points": [], "locations": ["Quarry Bay"], "categories": ["Accounting", "Accountant"], "post_time": "2022-01-17T02:42:07Z", "salary": {"currency": null, "max": null, "min": null, "period": "monthly", "term": null}, "salary_visible": false, "title_keywords": ["accountant", "assistant accountant"], "responsibilities": ["ad-hoc", "data", "bank reconciliation", "transactions", "regular review", "payment", "tax matters", "maintaining", "accounts receivable", "compliance", "reports", "banking", "reporting", "management", "procedures", "cash flow", "ad-hoc duties", "audits", "financial reports", "analysis", "sales team", "insurance"], "requirements": {"degrees": ["bachelor", "fresh graduate", "degree holder"], "majors": ["related disciplines", "finance", "accounting"], "languages": ["english", "chinese"], "language_level": ["good command"], "hard_skills": ["plus", "sap", "analytical skills", "problem solving", "erp system", "pc skills"], "soft_skills": ["work independently", "detail-oriented", "problem solving", "analytical skills", "hands-on", "committed", "pro-active", "driven"], "languages_combined": [{"language": "english", "language_level": ["good command"]}, {"language": "chinese", "language_level": ["good command"]}]}, "experience_required": {"duration": [], "field": ["sizable organization", "erp system"]}}, {"job_id": "100003009053260", "location_code": "hk", "company": "GenieBiome Limited", "job_title": "Assistant Accountant", "description": "Responsible for daily finance operations including keeping of full set of accounts, ledger posting, bank reconciliation, accounts payables and accounts receivables etc.\nManage intercompany transactions and reconciliation\nPrepare sales invoice, control stock in and out distribution with internal and external parties in ERP\nProvide supports to various departments in operation and business related to financial aspects\nAssist in ad hoc projects assignment\u00a0\n\nJob requirements:\n\nForm 5/DSE, with LCCI Intermediate, Level 3 or above\nAt least 3 years' accounting or finance experience\u00a0\nProficiency in MS Office application, including Excel, Chinese word processing and Powerpoint;\nKnowledge of Kingdee is an advantage\nKnowledge & experience in Ecommerce is a plus\nGood command of written and spoken English and Chinese (Mandarin a plus)\nSelf-motivated, proactive and able to work under pressure\nImmediate available is preferred\n\nWe offer competitive remuneration package to the right candidate. Interested parties, please send your resume with expected salary and date of availability via \u201cQuick Apply\u201d.\u00a0Please quote the Reference no: GB-AA/17012022/001 on your application.\n\nAll personal data collected will be used for recruitment purpose only.", "employment_types": ["Full Time", "Permanent"], "selling_points": ["Higher Diploma or Degree holder in accounting", "Career development opportunities, Biotech. Co.", "5 working days"], "locations": ["Wan Chai"], "categories": ["Accounting", "Accountant"], "post_time": "2022-01-17T06:36:12Z", "salary": {"currency": null, "max": null, "min": null, "period": "monthly", "term": null}, "salary_visible": false, "title_keywords": ["assistant accountant"], "responsibilities": ["control", "invoice", "full set of accounts", "prepare sales", "bank reconciliation", "transactions", "internal and external parties", "finance operations", "ad hoc projects", "work under pressure"], "requirements": {"degrees": ["form 5", "dse"], "majors": [], "languages": ["english", "chinese", "mandarin"], "language_level": ["proficiency", "good command"], "hard_skills": ["excel", "plus", "chinese word processing", "powerpoint", "erp", "ms office"], "soft_skills": ["self-motivated", "proactive", "responsible", "work under pressure"], "languages_combined": [{"language": "english", "language_level": ["good command"]}, {"language": "chinese", "language_level": ["proficiency", "good command"]}, {"language": "mandarin", "language_level": ["good command"]}]}, "experience_required": {"duration": ["at least 3 years"], "field": ["ecommerce", "finance", "accounting"]}}, {"job_id": "100003009052712", "location_code": "hk", "company": "Atom International Technology Limited", "job_title": "Accountant / Accounting Officer", "description": "Job Highlights\ndaily accounting\npayment\naudit\nJob Description\n\nResponsibilities\u00a0include:\n\nPerform daily accounting duties, including data entries and preparation of vouchers for receipt, payment and general journals transactions\nLiaise with audit team, clients & IRD\nPrepare annual statutory filing (including renewal, tax filing and others)\nInvolve in marketing campaign regarding accounting service crossover with other brands and partners.\nEnsure timely and accurate financial reporting\nHandle other adhoc tasks and administrative work as required\n\nUltimately, you will help our Accounting department run smoothly, ensuring transparency and efficiency in all transactions.\n\nRequirements\n\nAs a minimum you will have a Diploma or above in Accounting or related disciplines and Proficient in English, Mandarin and Cantonese.\n2 years or above of work experience in accounting is preferred.\nKnowledge of modern accounting software is essential. Knowledge in XERO is distinct advantage\nFamiliarity with finance regulations\nStrong organization skills\nAbility to handle sensitive, confidential information\nA final pre-requisite is that you be based in Hong Kong with valid working visa", "employment_types": ["Full Time"], "selling_points": ["Accounting", "Finance", "Assurance"], "locations": ["North Point"], "categories": ["Accounting", "Accountant", "Accounting Clerk / Supervisor", "Banking / Finance", "Treasury"], "post_time": "2022-01-17T03:46:58Z", "salary": {"currency": null, "max": null, "min": null, "period": "monthly", "term": null}, "salary_visible": false, "title_keywords": ["accountant", "accounting officer"], "responsibilities": ["administrative work", "data", "tax filing", "accounting service", "audit", "transactions", "payment", "financial reporting", "liaise with", "daily accounting"], "requirements": {"degrees": ["diploma or above"], "majors": ["related disciplines", "accounting"], "languages": ["cantonese", "english", "mandarin"], "language_level": ["proficient"], "hard_skills": ["accounting software", "xero"], "soft_skills": ["organization skills", "sensitive"], "languages_combined": [{"language": "cantonese", "language_level": ["proficient"]}, {"language": "english", "language_level": ["proficient"]}, {"language": "mandarin", "language_level": ["proficient"]}]}, "experience_required": {"duration": ["2 years"], "field": ["accounting"]}}, {"job_id": "100003009051611", "location_code": "hk", "company": "Infinity Cargo Express Limited", "job_title": "Cost Accountant", "description": "Job\u00a0Description:\n\n-\u00a0\u00a0\u00a0\u00a0\u00a0 Handle daily AP accounting transactions,\n\n-\u00a0\u00a0\u00a0\u00a0\u00a0 Responsible for weekly cash forecast\n\n-\u00a0\u00a0\u00a0\u00a0\u00a0 Responsible for monthly airfreight job closing and GP analysis\n\n-\u00a0\u00a0\u00a0\u00a0\u00a0 Check and review airline Tonnage and EQ adjustment report\n\n-\u00a0\u00a0\u00a0\u00a0\u00a0 Assist with annual audit.\n\n-\u00a0\u00a0\u00a0\u00a0\u00a0 Perform other Ad-hoc duties as assigned\n\nQualifications and Experience:\n\n-\u00a0 \u00a0Diploma in accountancy with experience in e-commerce platforms/Freight forwarding industry will be advantage\n\n- \u00a0\u00a0\u00a03- 5 years relevant working experiences\n\n-\u00a0\u00a0\u00a0 Proficiency in Excel (e.g. Pivot & Vlookup) and Word processing\n\n-\u00a0\u00a0\u00a0 Good command of English and conversational Putonghua\n\n-\u00a0\u00a0 \u00a0Immediate available is highly preferred\n\n\n\nBenefits\n\nYear-end Double pay, MPF, Group Medical, Bank Holidays, 12 days Annual Leave\nWork life balance\n\nWorking Location: Tsuen Wan\n\nInterested candidates, please contact us at 24060820 for company details.\n\nAll information provided by applicants will be treated in strict confidential and used only for the recruitment purpose", "employment_types": ["Full Time"], "selling_points": ["Double Pay, 12 days AL, Group Medical", "Experience in Freight forwarding is an advantage", "Immediate Available is preferred"], "locations": ["Tsuen Wan Area"], "categories": ["Accounting", "Accountant", "Accounting Clerk / Supervisor", "Banking / Finance", "Financial Services"], "post_time": "2022-01-16T14:32:23Z", "salary": {"currency": null, "max": null, "min": null, "period": "monthly", "term": null}, "salary_visible": false, "title_keywords": ["accountant"], "responsibilities": ["ap", "annual audit", "analysis", "review", "e-commerce platforms", "transactions", "forecast", "ad-hoc duties", "report"], "requirements": {"degrees": ["diploma"], "majors": ["e-commerce", "accountancy"], "languages": ["putonghua", "english"], "language_level": ["conversational", "good command"], "hard_skills": ["ap", "excel", "e-commerce", "analysis", "airline", "word processing", "vlookup"], "soft_skills": ["responsible", "ad-hoc duties"], "languages_combined": [{"language": "putonghua", "language_level": ["good command"]}, {"language": "english", "language_level": ["conversational", "good command"]}]}, "experience_required": {"duration": ["3- 5 years"], "field": ["e-commerce"]}}, {"job_id": "100003009051879", "location_code": "hk", "company": "The Great Eagle Group of Companies", "job_title": "Accounts Supervisor - Payable", "description": "Responsibilities:\n\nPerform daily accounting payable duties and ensure all accounting transactions are recorded in accordance with corporate guidelines with integrity and accuracy\nMonitor cash flow, vendor payments, fund request & transfer, bank reconciliations\nAssist in preparing cash management related analysis and management reports\nSupervise subordinates to perform their duties and work as a team\nPerform ad hoc assignments as required\n\nRequirements:\n\nDiploma or above with at least 4 years\u2019 accounting experience, preferably gained in sizeable organization\nIndependent and self-motivated, well-organized and willing to learn\nGood communication and interpersonal skills\nProficiency in MS Office applications and knowledge of Oracle system will be an advantage\nGood command of both spoken and written English and Chinese\n\nSalary and benefits will be commensurate with qualifications and experience.\u00a0 Interested parties, please send a full resume with present and expected salary, and date available to The Human Resources Department, 32/F., Great Eagle Centre, 23 Harbour Road, Wanchai, Hong Kong or e-mail to us.\u00a0(Please quote the reference no. on the envelope and the covering letter.)\n\nTo know more about us, please visit our website at http://www.greateagle.com.hk.\n\nWe are an equal opportunity employer and welcome applications from all qualified candidates.\n\nPersonal data collected will be treated in strict confidence and used only for recruitment-related purpose. Applicants who have not heard from us within four weeks may consider their applications unsuccessful. All personal data will be destroyed after 12 months.", "employment_types": ["Full Time", "Permanent"], "selling_points": ["Perform daily accounting payable duties", "Monitor cash flow, vendor payments etc.", "Independent and self-motivated"], "locations": ["Wan Chai"], "categories": ["Accounting", "Accountant", "Accounting Clerk / Supervisor"], "post_time": "2022-01-17T01:26:10Z", "salary": {"currency": null, "max": null, "min": null, "period": "monthly", "term": null}, "salary_visible": false, "title_keywords": ["accounts supervisor"], "responsibilities": ["management", "guidelines", "analysis", "monitor", "bank reconciliations", "transactions", "cash flow", "management reports", "payments", "ad hoc assignments", "daily accounting"], "requirements": {"degrees": ["diploma or above"], "majors": ["accounting"], "languages": ["english", "chinese"], "language_level": ["good command"], "hard_skills": ["oracle system", "ms office"], "soft_skills": ["self-motivated", "independent", "willing to learn", "well-organized", "communication and interpersonal skills"], "languages_combined": [{"language": "english", "language_level": ["good command"]}, {"language": "chinese", "language_level": ["good command"]}]}, "experience_required": {"duration": ["at least 4 years"], "field": ["accounting experience"]}}, {"job_id": "100003009051481", "location_code": "hk", "company": "AXA International Limited", "job_title": "Accountant / Senior Accountant", "description": "Responsibilities:\n\nReview full set of account, costing, taxation and ad hoc assignments of each office\nSupervise and monitor the daily accounting and finance operations of different companies\nPrepare monthly reports, financial statements, cash flow forecast and\u00a0management analysis reports\nConsolidate financial reports, review and prepare of budgeting and management reports to align with business objectives\nEnsure the accounting records and documentation in compliance with the local statutory requirement and company accounting policy\nDeal with both internal and external parties including auditor and tax agent etc.\nSupport year-end audit and taxation\nHandle ad hoc assignment\n\nRequirements:\n\nDegree holder major in accountancy\nStudent member or finalist of HKICPA or ACCA\nMinimum 5 years accounting experience with 3 years in manufacturing industry\nKnowledge in PRC taxation\nProficiency in Microsoft office and applications; well versed in Excel\nWilling to visit China and review financial operation when needed\nGood communication skills with foreign investment parties, able to work and interface well with personnel at various levels\nGood command of written English and Chinese\nFluent in spoken English, Mandarin and Cantonese\nStrong manufacturing analytical, presentation and report writing skills\nImmediately available or short notice will be an advantage", "employment_types": ["Full Time"], "selling_points": [], "locations": ["Wan Chai"], "categories": ["Accounting", "Accountant", "Taxation"], "post_time": "2022-01-16T03:54:01Z", "salary": {"currency": null, "max": null, "min": null, "period": "monthly", "term": null}, "salary_visible": false, "title_keywords": ["accountant", "senior accountant"], "responsibilities": ["monthly reports", "analysis reports", "budgeting", "internal and external parties", "audit", "financial statements", "finance operations", "ad hoc assignment", "compliance", "monitor", "forecast", "management", "review", "cash flow", "documentation", "tax", "taxation", "financial reports", "year-end", "management reports", "ad hoc assignments", "daily accounting"], "requirements": {"degrees": ["degree holder"], "majors": ["accountancy"], "languages": ["cantonese", "english", "chinese", "mandarin"], "language_level": ["good command", "fluent"], "hard_skills": ["excel", "acca", "microsoft office", "writing skills", "hkicpa"], "soft_skills": ["communication skills", "presentation", "writing skills"], "languages_combined": [{"language": "cantonese", "language_level": ["fluent"]}, {"language": "english", "language_level": ["good command", "fluent"]}, {"language": "chinese", "language_level": ["good command"]}, {"language": "mandarin", "language_level": ["fluent"]}]}, "experience_required": {"duration": ["3 years", "minimum 5 years"], "field": ["accounting experience", "manufacturing industry"]}}, {"job_id": "100003009054541", "location_code": "hk", "company": "China Eagle Management Limited", "job_title": "Accountant / Finance Manager (5-day work)", "description": "\u00a0Responsibilities:\n\n\u00a0Assist to Finance Manager to oversee finance and accounting functions of the group and ensure compliance with the Hong Kong Listing Rules, International Accounting Standards (\u201cIAS\u201d) and the Companies Ordinance\nPrepare monthly consolidated financial information for the Group and co-ordinate to issue notices, announcements and circulars for compliance with the Listing Rules and other statutory requirements\nPrepare annual, interim and quarterly financial reports and relevant disclosure notes and liaise with external auditors in all aspects of the financial reporting\nPrepare financial analysis, budgeting, forecast, cash flow projection, and management reports\nAssist in managing funds and liaison with banks\nAssist in reviewing, monitoring and enhancing internal controls of the Group\nAssist in tax planning, treasury functions and any ad hoc projects for the Group\n\nRequirements:\n\nDegree holder in Accounting and possess HKICPA/ACCA or other equivalent\n4-5 years of relevant work experienceof which at least 1-2 years in a Hong Kong listed company.\nStrong analytical and excellent interpersonal skills\nPositive attitude, good team work ethic , highly responsibility and able to work under pressure\nDriven, enthusiastic, highly self-motivated, and able to operate independently\nConversant in accounting principles; experience in tax issues and legal practice preferred\nExcellent communication skills, fluent in English, Cantonese and Mandarin\nCandidates with more working experience will be considered as senior position", "employment_types": ["Full Time"], "selling_points": ["oversee finance and accounting functions", "1-2 years in a Hong Kong listed company", "5-day work & medical insurance"], "locations": ["Central"], "categories": ["Accounting", "Accountant", "Finance / Accounting Manager", "Treasurer"], "post_time": "2022-01-17T09:56:44Z", "salary": {"currency": null, "max": null, "min": null, "period": "monthly", "term": null}, "salary_visible": false, "title_keywords": ["accountant", "finance manager"], "responsibilities": ["tax", "financial reports", "budgeting", "compliance", "monitoring", "ensure compliance", "financial analysis", "statutory requirements", "cash flow", "management reports", "planning", "financial reporting", "forecast", "ad hoc projects", "liaise with", "listing", "external auditors"], "requirements": {"degrees": ["degree holder"], "majors": ["accounting"], "languages": ["cantonese", "english", "mandarin"], "language_level": ["excellent", "fluent"], "hard_skills": ["acca", "hkicpa"], "soft_skills": ["good team work", "communication skills", "self-motivated", "independently", "positive attitude", "interpersonal skills", "enthusiastic", "driven", "work under pressure"], "languages_combined": [{"language": "cantonese", "language_level": ["excellent", "fluent"]}, {"language": "english", "language_level": ["excellent", "fluent"]}, {"language": "mandarin", "language_level": ["excellent", "fluent"]}]}, "experience_required": {"duration": [], "field": ["legal"]}}, {"job_id": "100003009051712", "location_code": "hk", "company": "ASM Technology Hong Kong Limited", "job_title": "Contract General Accountant", "description": "Job description\nSupport daily data processing and voucher postings\nPerform month-end closing tasks and financial reporting packages\nAssist in preparation of annual accounts\nConduct analytical review of the financial data\nHandle other ad hoc duties as required\nJob requirements\nDegree in Accounting, Finance or relevant disciplines\nAt least 3 years working experience in accounting\nExperience in using SAP will be an advantage\nProficient in MS office application\nSelf-motivated and committed to continuous improvement\nAble to work independently and be a team player\nImmediately available is highly preferred\n\nWorking location: Tsing Yi, Hong Kong\n\nAttractive salary and fringe benefits package will be offered to the right candidates.\n\nInterested parties please submit your application with cover letter, resume, certificate and transcripts.\n\nData collected will be used for recruitment purpose only. Suitable candidates may be referred to other vacancies within our company.", "employment_types": ["Full Time", "Contract"], "selling_points": ["Degree in Accounting, Finance", "At least 3 years working experience", "Support daily data processing and voucher postings"], "locations": ["Tsing Yi"], "categories": ["Accounting", "Accountant", "Accounting Clerk / Supervisor", "Others"], "post_time": "2022-01-16T21:51:02Z", "salary": {"currency": null, "max": null, "min": null, "period": "monthly", "term": null}, "salary_visible": false, "title_keywords": ["accountant"], "responsibilities": ["ad hoc duties", "data", "review", "data processing", "month-end closing", "financial reporting"], "requirements": {"degrees": ["degree"], "majors": ["finance", "accounting"], "languages": [], "language_level": [], "hard_skills": ["sap", "ms office"], "soft_skills": ["committed", "self-motivated", "team player", "work independently"], "languages_combined": []}, "experience_required": {"duration": ["at least 3 years"], "field": ["accounting"]}}, {"job_id": "100003009052341", "location_code": "hk", "company": "China Mobile Hong Kong \u4e2d\u570b\u79fb\u52d5\u9999\u6e2f", "job_title": "Accountant (Fixed Asset)", "description": "CHINA MOBILE HONG KONG COMPANY LIMITED\u00a0(\"CMHK\") is the wholly-owned subsidiary of China Mobile Limited (HKEx: 941) (NYSE: CHL), which ranks 65th on the Fortune Global 500.\n\nOur company strives to offer superior service experience and to become the preferable digital partner for customers. We are preserving an environment with trust, responsibility and caring. At CMHK, we commit to maximizing people\u2019s potential and paving the way toward success for every striver. We are now inviting high caliber professional to join us.\n\nDivision:\u00a0 Finance Division - Financial Accounting & Reporting Department\n\nIn this position, you will:\n\n\nAssist in month-end closing\nPrepare reports, reconciliations and schedules\nSupport daily operations on the fixed assets area\nCo-ordinate with business users on projects and accounting issues\nArrange and coordinate stocktaking and inspection of fixed assets\nOther ad hoc duties/projects assigned\nTo be successful in this position, you should meet the following requirements:\u00a0\n\nDegree in Accountancy or related disciplines\nOver 5 years relevant working experience, prior fixed asset management experience will be an advantage.\nProactive, independent, persistent and able to work under pressure to meet deadline\nGood knowledge in MS Excel/ Word, Macro / MS Access preferred\nExperience in using Oracle is an advantage\nGood command of both written and spoken English and Chinese (both Cantonese and Mandarin)\nImmediate Available is preferable\n\nWhen you work:\n\n\n5 days work\n8 hours/day\n\nWhat you enjoy:\n\nDouble pay\nDiscretionary Performance bonus\nLife insurance\nMedical insurance\nEducation subsidies\nBirthday gift\nMarriage leave\nBirthday leave\nStaff discount\n\nCMHK is committed to be an equal opportunity employer. We offer exceptional benefits package and the opportunity to work in a challenging environment. Personal data provided by applicants will be treated strictly in accordance with our personal data policy and for recruitment purposes only.\n\nPlease submit your application to us by clicking the APPLY NOW button and send your full resume with your availability, current and expected salary to us.", "employment_types": ["Full Time", "Permanent"], "selling_points": ["Double pay & Performance bonus", "Experience in using Oracle", "Good knowledge in MS Excel, Word and Access"], "locations": ["Kwai Hing"], "categories": ["Accounting", "Accountant", "Accounting Clerk / Supervisor", "Treasurer"], "post_time": "2022-01-17T02:57:40Z", "salary": {"currency": null, "max": null, "min": null, "period": null, "term": null}, "salary_visible": false, "title_keywords": ["accountant"], "responsibilities": ["ad hoc duties", "reporting", "schedules", "co-ordinate with", "work under pressure", "inspection", "coordinate", "reconciliations", "daily operations", "month-end closing", "prepare reports", "insurance", "asset management"], "requirements": {"degrees": ["degree"], "majors": ["related disciplines", "accountancy"], "languages": ["cantonese", "english", "chinese", "mandarin"], "language_level": ["good command"], "hard_skills": ["macro", "word", "mobile", "ms excel", "oracle"], "soft_skills": ["independent", "persistent", "committed", "proactive", "superior", "work under pressure"], "languages_combined": [{"language": "cantonese", "language_level": ["good command"]}, {"language": "english", "language_level": ["good command"]}, {"language": "chinese", "language_level": ["good command"]}, {"language": "mandarin", "language_level": ["good command"]}]}, "experience_required": {"duration": ["5 years"], "field": ["digital", "relevant working experience", "asset management"]}}, {"job_id": "100003009052193", "location_code": "hk", "company": "Fed-Supremetech Limited", "job_title": "Assistant Accountant", "description": "Electrical Engineering firm in Shatin invites candidates for the following vacancy :-\n\nASSISTANT ACCOUNTANT\n\nJob Responsibilities\n- To handle full set of books and accounts\n- To prepare vouchers and cheques.\u00a0 To handle relevant accounting entry, monitoring payment schedule\n- Keep track of bank balance and cash flow forecast\n- Handle month-end closing, remittance and reports\n- Assist in preparing annual financial budget\n\n\u00a0Requirements\n\n-Holder of LCC Higher Certificate of Accounting or equivalent\n-At least 5 years relevant working experience\n-Good communication skills; fluent Cantonese and English, Mandarin is essential\n-Proficient PC skills in MS office\n\n\nWe offer attractive package, including public holidays, alternate Saturday, double pay, Bonus, 14days annual leave,etc.\u00a0to suitable candidates. Interested\u00a0candidates please send application with full resume, availability and expected salary by email\u00a0\n\nPersonal data collected will be used for recruitment purpose only.\n\n\n\n", "employment_types": ["Full Time"], "selling_points": [], "locations": ["Shatin Area"], "categories": ["Accounting", "Accountant", "Accounting Clerk / Supervisor", "Others"], "post_time": "2022-01-17T02:26:00Z", "salary": {"currency": null, "max": null, "min": null, "period": "monthly", "term": null}, "salary_visible": false, "title_keywords": ["assistant accountant"], "responsibilities": ["monitoring", "budget", "payment", "cheques", "cash flow", "schedule", "forecast", "month-end closing", "reports"], "requirements": {"degrees": ["higher certificate"], "majors": ["accounting"], "languages": ["cantonese", "english", "mandarin"], "language_level": ["fluent"], "hard_skills": ["pc skills", "lcc", "ms office"], "soft_skills": ["communication skills"], "languages_combined": [{"language": "cantonese", "language_level": ["fluent"]}, {"language": "english", "language_level": ["fluent"]}, {"language": "mandarin", "language_level": []}]}, "experience_required": {"duration": ["least 5 years"], "field": ["relevant working experience"]}}, {"job_id": "100003009054450", "location_code": "hk", "company": "SMCP Asia Limited", "job_title": "Senior Accountant", "description": "Reporting to:\u00a0Regional Accounting Manager\n\n\nResponsibilities:\n\n\n\nSpecific scope on Hong Kong and Macau entities:\n\n\nHandle CAPEX related payable invoices and corresponding accruals\nPrepare and update Fixed Assets related schedules\nPrepare audit schedules and handle annual audit process\nScope on Asia region:\nPrepare cashflow forecast\nPrepare inventory reconciliation\nReview related payable invoices and corresponding accruals\nReview general ledger entries\nReview Fixed Assets related schedules\nOthers :\u00a0\n\nAssist in other projects and duties as assigned\n\nRequirements :\u00a0\n\n\n\nDegree in Accounting / Finance or related discipline\nQualified member of one of the major accountancy associations\nMinimum 6 years relevant experience in accounting, preferably in retail industry with audit background will be a plus\nGood command of both spoken and written English, Mandarin and Cantonese\nHands-on experience in Oracle ERP system is an advantage\nDetail-oriented, able to work independently, meet tight deadline and show ownership at work\nGood communication skills, be a good team player and agile when managing tasks and projects", "employment_types": ["Full Time", "Permanent"], "selling_points": ["Min 6 years of relevant exp in related field", "Hands-on exp in Oracle ERP system is an advantage", "Detail oriented,proactive & can work independently"], "locations": ["Central"], "categories": ["Accounting", "Accountant", "Banking / Finance", "Others"], "post_time": "2022-01-17T09:35:31Z", "salary": {"currency": null, "max": null, "min": null, "period": "monthly", "term": null}, "salary_visible": false, "title_keywords": ["senior accountant"], "responsibilities": ["invoices", "annual audit", "schedules", "general ledger", "inventory", "review", "capex", "audit", "forecast"], "requirements": {"degrees": ["degree"], "majors": ["finance", "accounting"], "languages": ["cantonese", "english", "mandarin"], "language_level": ["good command"], "hard_skills": ["plus", "agile", "oracle erp"], "soft_skills": ["communication skills", "work independently", "good team player", "agile", "detail-oriented", "hands-on", "meet tight deadline"], "languages_combined": [{"language": "cantonese", "language_level": ["good command"]}, {"language": "english", "language_level": ["good command"]}, {"language": "mandarin", "language_level": ["good command"]}]}, "experience_required": {"duration": ["minimum 6 years"], "field": ["retail industry", "audit", "erp system", "relevant experience", "accounting"]}}, {"job_id": "100003009054160", "location_code": "hk", "company": "The Hong Kong Polytechnic University", "job_title": "Associate Accountant (Accounting Operations Section)", "description": "FINANCE OFFICE\n\nAssociate Accountant (Accounting Operations Section) (Ref. 22011708-E4)\n\nDuties\n\nThe appointee will be required to:\n\n(a) perform staff cost analyses and projections for the management and funding bodies;\n\n(b) assist in reviewing and outlining the financial implications on pay level and adjustment reviews for Council\u2019s decision;\n\n(c) assist in enhancement and implementation of systems related to payroll, staff claims and payments;\n\n(d) supervise daily operations of payroll, benefits, staff claims and related payments of the University and its subsidiaries, including verifying payments and related tax filing, and ensuring compliance with the relevant statutory requirements, policies, rules and regulations;\n\n(e) handle general office administration; and\n\n(f) perform any other duties as assigned by the Director of Finance and her delegates.\n\nQualifications\u00a0\n\nApplicants should have:\n\n(a) a recognized degree in Accounting or related disciplines;\n\n(b) a professional accounting qualification or equivalent;\n\n(c) at least three years of post-qualification experience in accounting, auditing or other related fields, preferably with experience in payroll operations, staff benefits, claims processing and/or system enhancement;\u00a0\n\n(d) some supervisory experience;\n\n(e) proficiency in Microsoft Office software including Excel, Word and PowerPoint;\n\n(f) a good command of both written and spoken English and Chinese; and\n\n(g) good communication and interpersonal skills.\n\nShortlisted candidates will be invited to sit for a written test.\n\nApplicants who have responded to the previous advertisement need not re-apply.\n\nRemuneration and Conditions of Service\n\nA highly competitive remuneration package will be offered. \u00a0Initial appointment will be on a fixed-term gratuity-bearing contract.\u00a0 Re-engagement thereafter is subject to mutual agreement.\u00a0 Applicants should state their current and expected salary in the application.\n\nApplication\n\nPlease send a completed application form by post to Human Resources Office, 13/F, Li Ka Shing Tower, The Hong Kong Polytechnic University, Hung Hom, Kowloon, Hong Kong or via email by clicking \"Apply Now\".\u00a0 Application forms can be downloaded from https://www.polyu.edu.hk/hro/careers/guidelines_and_forms/forms.\u00a0 If a separate curriculum vitae is to be provided, please still complete the application form which will help speed up the recruitment process. The closing date for application is Monday, 31 January 2022.\u00a0 Applicants who are not invited to an interview within two months from the closing date should consider their applications unsuccessful. The University\u2019s Personal Information Collection Statement for recruitment can be found at https://www.polyu.edu.hk/hro/careers/guidelines_and_forms/pics_for_recruitment.\n\nPolyU is an equal opportunity employer committed to diversity and inclusivity.\u00a0 All qualified applicants will receive consideration for employment without regard to gender, ethnicity, nationality, family status or physical or mental disabilities.", "employment_types": ["Full Time"], "selling_points": [], "locations": ["Not Specified"], "categories": ["Accounting", "Accountant", "Accounting Clerk / Supervisor", "Audit"], "post_time": "2022-01-17T08:40:30Z", "salary": {"currency": null, "max": null, "min": null, "period": null, "term": null}, "salary_visible": false, "title_keywords": ["operations", "associate", "accountant", "accounting"], "responsibilities": ["regulations", "any other duties", "software", "operations", "communication", "statutory requirements", "office administration", "tax filing", "compliance", "implementation", "cost", "management", "daily operations", "recruitment process", "payroll", "policies", "systems", "payments", "recruitment", "auditing"], "requirements": {"degrees": ["degree"], "majors": ["related disciplines", "accounting"], "languages": ["english", "chinese"], "language_level": ["good command"], "hard_skills": ["excel", "word", "powerpoint", "c", "microsoft office software", "processing"], "soft_skills": ["committed", "communication and interpersonal skills"], "languages_combined": [{"language": "english", "language_level": ["good command"]}, {"language": "chinese", "language_level": ["good command"]}]}, "experience_required": {"duration": ["at least three years"], "field": ["post-qualification", "related", "payroll", "supervisory experience", "accounting"]}}, {"job_id": "100003009054615", "location_code": "hk", "company": "Hop Hing Management Company (Hong Kong) Limited", "job_title": "Senior Accountant (Ref No.: SA/1701/22)", "description": "Job Responsibilities:\n\nPrepare Group Management accounts and consolidated report\nRegular review and monitor the accounting function of the Group's business in the PRC\nCoordinate annual audit and handle tax issues\nPrepare Budget and Forecast\nRequirements:\n\nUniversity graduated in Accounting, Finance or other related discipline\nQualified accountant with at least 5 years of experience and 2 years in supervisory level\nPrevious experience PRC accounting is an advantage\nExperience in JD Edwards will be an advantage\nPeriodic travel to PRC is required\n\nInterested parties, please send detail resume and expected salary to HR Department.\n\nPersonal data to be collected for recruitment purpose only.", "employment_types": ["Full Time"], "selling_points": ["University graduated in Accounting", "At least 5 years of experience", "Periodic travel to PRC is required"], "locations": ["Yuen Long"], "categories": ["Accounting", "Accountant"], "post_time": "2022-01-17T10:15:16Z", "salary": {"currency": null, "max": null, "min": null, "period": "monthly", "term": null}, "salary_visible": false, "title_keywords": ["senior accountant"], "responsibilities": ["tax", "management", "annual audit", "budget", "monitor", "regular review", "coordinate", "forecast", "report"], "requirements": {"degrees": [], "majors": [], "languages": [], "language_level": [], "hard_skills": ["prc accounting"], "soft_skills": [], "languages_combined": []}, "experience_required": {"duration": ["2 years", "at least 5 years"], "field": ["supervisory level", "accounting"]}}, {"job_id": "100003009054485", "location_code": "hk", "company": "Prolinair Asia Limited", "job_title": "Accountant / Senior Accountant (5 day work week)", "description": "Job Highlights\n\nSenior Accountant\nFreight forwarding / logistics company\nImmediate available\n\nJob Description\n\nJob Highlights\n\n\u00a0\u00a0\u00a0\u00a0\u00a0\u00a0\u00a0\u00a0 Min 10 years\u2019 experience in accounting field\n\u00a0\u00a0\u00a0\u00a0\u00a0\u00a0\u00a0\u00a0 Support daily accounting duties and admin work\n\nJob Description\n\nWhat you\u2019ll be doing?\n\n\u00a0\u00a0\u00a0\u00a0\u00a0\u00a0\u00a0\u00a0 Support\u00a0daily accounting duties, including account receivable and payable\n\u00a0\u00a0\u00a0\u00a0\u00a0\u00a0\u00a0\u00a0 Liaise with customers for account receivable settlement\u00a0\n\u00a0\u00a0\u00a0\u00a0\u00a0\u00a0\u00a0\u00a0 Prepare monthly variance reports for\u00a0profit and loss and balance sheet items\n\u00a0\u00a0\u00a0\u00a0\u00a0\u00a0\u00a0\u00a0 Assist in budget preparation, monthly financial analyses and reports\n\u00a0\u00a0\u00a0\u00a0\u00a0\u00a0\u00a0\u00a0 Prepare monthly agent reconciliation and issue customers' statements\n\u00a0\u00a0\u00a0\u00a0\u00a0\u00a0\u00a0\u00a0 Provide clerical support on administration works\n\nWho\u00a0are\u00a0we\u00a0looking\u00a0for?\n\n\u00a0\u00a0\u00a0\u00a0\u00a0\u00a0\u00a0\u00a0 A\u00a0candidate\u00a0with\u00a0 Higher Diploma / Associate degree in accounting or equivalent qualification\n\u00a0\u00a0\u00a0\u00a0\u00a0\u00a0\u00a0\u00a0 Minimum 10 years\u2019 experience in accounting field\n\u00a0\u00a0\u00a0\u00a0\u00a0\u00a0\u00a0\u00a0 Strong analytical, Self-motivated, well-organized and able to work independently\n\u00a0\u00a0\u00a0\u00a0\u00a0Proficiency in MS office and experience with online accounting system\n\u00a0\u00a0\u00a0\u00a0\u00a0\u00a0\u00a0\u00a0 Good command of both written & spoken English and Chinese, including Mandarin\n\u00a0\u00a0\u00a0\u00a0\u00a0\u00a0\u00a0\u00a0 You will have an advantage if you are\n\n-\u00a0\u00a0\u00a0\u00a0\u00a0\u00a0\u00a0\u00a0\u00a0 With Experience\u00a0in consolidating\u00a0subsidiary accounts\n-\u00a0\u00a0\u00a0\u00a0\u00a0\u00a0\u00a0\u00a0\u00a0 With experience in freight forwarding / logistics company\n-\u00a0 \u00a0 \u00a0 \u00a0 \u00a0 With experience in using CargoWise software\n-\u00a0\u00a0\u00a0\u00a0\u00a0\u00a0\u00a0\u00a0\u00a0 Immediate available\n\nWhy you should consider this opportunity:\nWe offer attractive remuneration package with fringe benefits to right candidates.\u00a0\u00a0\u00a0\u00a0\u00a0\u00a0\u00a0\u00a0\u00a0\u00a0\u00a0\u00a0\u00a0\u00a0\u00a0\u00a0\n\nIf you have the positive thinking, energy to add to our velocity. Please send your resume with expected salary and date of available by clicking\u00a0\"Apply Now\".\n\n(Personal data collected will be used for recruitment purpose only.)", "employment_types": ["Full Time"], "selling_points": [], "locations": ["Lai Chi Kok"], "categories": ["Accounting", "Accountant"], "post_time": "2022-01-17T09:44:52Z", "salary": {"currency": null, "max": null, "min": null, "period": "monthly", "term": null}, "salary_visible": false, "title_keywords": ["accountant", "senior accountant"], "responsibilities": ["provide clerical support", "administration", "software", "budget", "logistics", "reports", "liaise with", "daily accounting", "balance sheet"], "requirements": {"degrees": ["associate degree", "diploma"], "majors": ["accounting"], "languages": ["english", "chinese", "mandarin"], "language_level": ["good command"], "hard_skills": ["accounting system", "ms office"], "soft_skills": ["self-motivated", "well-organized", "work independently"], "languages_combined": [{"language": "english", "language_level": ["good command"]}, {"language": "chinese", "language_level": ["good command"]}, {"language": "mandarin", "language_level": ["good command"]}]}, "experience_required": {"duration": ["minimum 10 years", "min 10 years"], "field": ["accounting", "logistics"]}}, {"job_id": "100003009051629", "location_code": "hk", "company": "China Telecom Global Limited", "job_title": "Assistant Accountant", "description": "Responsibilities:\n\nDaily operation processing of Accounts Payable and the Account Reconciliations\nAssist in month-end closing processes, financial reporting, and other management\u00a0reporting\nAssist in tax calculation preparation work and tax return filing preparation works\nKeep record of fixed asset registry\nPerform other duties and ad-hoc projects as assigned\n\nJob Requirements:\n\nDegree holder in Accounting or Business related studies\nFamiliar with IFRS/HKFRS, HK Inland Revenue rules is an advantage\nExperience in using ERP System or Accounting System\nProficient in MS Office applications include Excel, Word and PowerPoint\nGood command of written and spoken English and Chinese\nPleasant personality with excellent management, well organized, communication, and interpersonal skills\nDetail oriented, Self-motivated, with good sense of responsibility to take up challenges\nImmediate availability is preferred\n\nWe offer 5 days work, competitive salary package and attractive career development opportunities to the right candidate.\n\nInterested parties please email your full resume with your current & expected salary to us.\n\nApplicants not invited for interview within 3 months may assume their applications unsuccessful.\n\nIf you are interested in other job opportunities, please check with below career website.\n\nPersonal data collected would be used for recruitment purpose only.", "employment_types": ["Full Time", "Permanent"], "selling_points": ["Degree holder in Accounting or Business related", "Exp. of accounting & financial reporting", "Exp. in telecom industry will be a plus"], "locations": ["Wan Chai"], "categories": ["Accounting", "Accountant", "Accounting Clerk / Supervisor"], "post_time": "2022-01-16T15:39:55Z", "salary": {"currency": null, "max": null, "min": null, "period": "monthly", "term": null}, "salary_visible": false, "title_keywords": ["assistant accountant"], "responsibilities": ["tax", "perform other duties", "daily operation", "reconciliations", "month-end closing", "financial reporting", "management reporting", "ad-hoc projects", "accounts payable"], "requirements": {"degrees": ["degree holder"], "majors": ["business", "accounting"], "languages": ["english", "chinese"], "language_level": ["good command"], "hard_skills": ["excel", "ifrs", "hkfrs", "word", "powerpoint", "erp system", "hk inland revenue rules", "accounting system", "ms office"], "soft_skills": ["self-motivated", "sense of responsibility", "detail oriented", "well organized", "pleasant", "communication", "interpersonal skills"], "languages_combined": [{"language": "english", "language_level": ["good command"]}, {"language": "chinese", "language_level": ["good command"]}]}, "experience_required": {"duration": [], "field": ["erp system", "accounting"]}}, {"job_id": "100003009051303", "location_code": "hk", "company": "Aozora Asia Pacific Finance Limited", "job_title": "Senior Accounting Officer", "description": "Aozora Asia Pacific Finance Limited (\"AAPF\") is a wholly owned subsidiary of Aozora Bank, Ltd. (formerly known as Nippon Credit Bank), a leading bank in Japan.\u00a0 We are now looking for high caliber professionals to support our Finance function:\n\nResponsibilities:\n\nHandle full set of accounts.\nPrepare financial reports package to Head Office.\nHandle treasury management on funding of loans.\nPerform cash management functions of the Company.\nResponsible for accounts receivable and accounts payable controlling.\nHandle all payments including employees\u2019 reimbursements.\nLiaise with Internal and External Auditors on audit matters.\nRequirements\n\nBachelor\u2019s Degree in Accounting or related disciplines.\nAt least 5 years\u2019 relevant experience in finance industry, preferably in lending business.\nHand on experience in maintaining general ledger system, SAP.\nKnowledge with electronic payment system such as SWIFT.\nProficiency in spoken and written English and Chinese Languages (Cantonese and Mandarin).\nProficiency in PC (Microsoft Excel and Word, etc.).\nIndependent, with strong analytical and problem solving skills.\nWe offer competitive salary package including 5-day work week. Interested parties please apply in strict confidence with full resume stating availability, current and expected salary.\u00a0\u00a0Personal data collected will be used for recruitment purpose only.", "employment_types": ["Full Time"], "selling_points": ["Handle full set of accounts and financial reports", "Bachelor\u2019s Degree in Accounting, 5 years' exp.", "Good in MS Excel & Word, Knowledge on SAP & SWIFT"], "locations": ["Central"], "categories": ["Accounting", "Accountant", "Accounting Clerk / Supervisor", "Finance / Accounting Manager"], "post_time": "2022-01-15T07:52:17Z", "salary": {"currency": null, "max": null, "min": null, "period": "monthly", "term": null}, "salary_visible": false, "title_keywords": ["senior accounting officer"], "responsibilities": ["financial reports", "management", "accounts receivable", "full set of accounts", "audit", "payments", "liaise with", "accounts payable", "external auditors"], "requirements": {"degrees": ["degree", "bachelor"], "majors": ["related disciplines", "accounting"], "languages": ["cantonese", "english", "chinese", "mandarin"], "language_level": ["proficiency"], "hard_skills": ["sap", "word", "microsoft excel", "swift", "pc", "problem solving skills"], "soft_skills": ["analytical and problem solving skills", "independent"], "languages_combined": [{"language": "cantonese", "language_level": ["proficiency"]}, {"language": "english", "language_level": ["proficiency"]}, {"language": "chinese", "language_level": ["proficiency"]}, {"language": "mandarin", "language_level": ["proficiency"]}]}, "experience_required": {"duration": ["at least 5 years"], "field": ["business", "relevant experience", "finance industry"]}}, {"job_id": "100003009049073", "location_code": "hk", "company": "John Swire & Sons (HK) Limited", "job_title": "Assistant Accountant / Accountant", "description": "A highly-diversified and global corporation, the Swire Group\u2019s businesses encompass property, aviation, beverages and food chain, as well as marine services and trading & industrial activities. Its core businesses are mainly focused in Asia, with its key operations in Hong Kong and the Chinese Mainland. Within Asia, Swire's activities come under the Group's publicly quoted arm, Swire Pacific Limited, which is the major shareholder in two Hong Kong listed companies: Swire Properties and Cathay Pacific Airways.\nJohn Swire & Sons (H.K.) Limited is the holding company of the publicly-listed conglomerate, Swire Pacific Ltd. Our Group Finance Department is now inviting candidates to apply for the following position:\n\nAssistant Accountant / Accountant\n\n\nThis role aims to be responsible for the accounting functions of Swire Pacific head office, with supervision by the Financial Accountant.\n\nResponsibilities:\nHandle full set of accounts and oversee daily accounting operations\nPerform month end closing, prepare schedules, financial reports and analysis\nLook after daily cashflow and plan fund transfer\nMaintain payment schedule, and ensure accurate settlement and confirmation procedures for Treasury deals (loan interests, deposits, SWAP settlements, etc.)\nHandle intercompany fund transfer and reconcile loan balance with subsidiaries\nReview payments, expense claims and petty cash\nLiaise with auditors in respect of internal/external audits\nAssist in other ad-hoc duties and tasks assigned\n\nRequirements:\n\nBachelor\u2019s degree holder in accounting, or related disciplines with at least 3 years of full set accounting experience\nHolder of ACCA, HKICPA or equivalent qualifications. Student member will also be considered\nProficient in Microsoft Office Suite and Word Processing applications\nSolid knowledge of SUN Accounting System will be desirable\nIndependent, responsible, and able to meet deadlines\nExcellent communication skills in both written and spoken English and Chinese. Fluent Putonghua is required\n\nApplication:\n\nAt Swire, we are committed to creating an inclusive and supportive working environment for all our people regardless of their age, gender, gender identity, sexual orientation, relationship, family status, disability, race, ethnicity, nationality, religious or political beliefs. We believe in creating an environment where people feel comfortable at work and are able to realise their full potential.\nWe offer a competitive package to the right candidate. If you meet the qualifications and are interested in this position, you can send your application by clicking \u2018Apply Now\u2019. We will contact all shortlisted candidates.\nThe Swire group is an equal opportunity employer. All applications will be used exclusively for selection purposes and handled confidentially by authorised personnel only. Your application may also be considered for other suitable positions within the Swire group (please indicate clearly on your application if you would not like to be considered for other positions within the group.) Following the data privacy ordinance, all unsuccessful applications will be destroyed after an appropriate time.", "employment_types": ["Full Time", "Permanent"], "selling_points": ["3+ years of full set accounting experience", "Holder of ACCA, HKICPA or equivalent qualification", "Solid knowledge of SUN Accounting System is a plus"], "locations": ["Quarry Bay"], "categories": ["Accounting", "Accountant"], "post_time": "2022-01-14T08:04:03Z", "salary": {"currency": null, "max": null, "min": null, "period": null, "term": null}, "salary_visible": false, "title_keywords": ["accountant", "assistant accountant"], "responsibilities": ["month end closing", "financial reports", "analysis", "full set of accounts", "procedures", "daily accounting operations", "review", "audits", "payment", "maintain", "payments", "schedule", "plan", "ad-hoc duties", "liaise with", "prepare schedules"], "requirements": {"degrees": ["bachelor", "degree holder"], "majors": ["related disciplines", "accounting"], "languages": ["putonghua", "english", "chinese"], "language_level": ["excellent", "fluent"], "hard_skills": ["acca", "word processing", "microsoft office suite", "accounting system", "hkicpa"], "soft_skills": ["communication skills", "supportive", "independent", "responsible", "committed", "meet deadlines"], "languages_combined": [{"language": "putonghua", "language_level": ["fluent"]}, {"language": "english", "language_level": ["excellent"]}, {"language": "chinese", "language_level": ["excellent"]}]}, "experience_required": {"duration": ["at least 3 years"], "field": ["related", "accounting experience", "accounting"]}}, {"job_id": "100003009052296", "location_code": "hk", "company": "Chef's Garden Limited", "job_title": "Accountant", "description": "Responsibilities:\n\nPrepare annual audit schedules, accounts reconciliation, provide appropriate follow-up actions, and manage the audit process;\nHandle and assist any ad-hoc tasks as assigned\nRequirements:\n\nDiploma/ Certificate in Accounting\n3 years accounting/ audit experience\nPrevious experience in restaurant/ retail business, Peachtree, Xero is an advantage\nProficiency in Excel and other MS office applications\nStable, self-motivated, hardworking, well-organized, detail-minded with strong sense of responsibilities, good interpersonal and communication skills;\nImmediately available\n\nWe\u00a0offer five-day work and Free meals\n\nInterested parties please apply by sending full resume with current and expected salary by clicking \"Apply Now\".\u00a0\n\n(All information and personal data collected relating to employment applications will be kept confidential and will be used \u00a0for recruitment purpose only.)", "employment_types": ["Full Time"], "selling_points": ["exp. in retail/catering business is a plus", "immediate available is preferable", "Be able to handle full set of accounts"], "locations": ["Sai Ying Pun"], "categories": ["Accounting", "Accountant", "Others", "Hospitality / F & B", "Food & Beverage"], "post_time": "2022-01-17T03:58:31Z", "salary": {"currency": null, "max": null, "min": null, "period": "monthly", "term": null}, "salary_visible": false, "title_keywords": ["accountant"], "responsibilities": ["schedules", "ad-hoc tasks", "audit", "annual audit"], "requirements": {"degrees": ["certificate", "diploma"], "majors": ["accounting"], "languages": [], "language_level": [], "hard_skills": ["excel", "peachtree", "xero", "ms office"], "soft_skills": ["detail-minded", "communication skills", "self-motivated", "well-organized", "stable", "interpersonal", "hardworking", "sense of responsibilities"], "languages_combined": []}, "experience_required": {"duration": ["3 years"], "field": ["restaurant", "business", "audit experience", "accounting", "retail"]}}, {"job_id": "100003009054839", "location_code": "hk", "company": "Hong Kong Parkview", "job_title": "Accountant - Hong Kong Parkview Group", "description": "Duties and Responsibilities\nResponsibilities:\nAssist in daily accounting operations for the Hong Kong Parkview Group.\nHandle full set of accounts, financial analysis and management reports.\nConduct basic accounting system maintenance.\nSupport in ad-hoc duties.\nRequirements:\nHigher Diploma or Degree holder in Accounting or related discipline; member of HKICPA or equivalent is preferrable\nAt least 4 years audit / accounting experience.\nWell versed with MS Excel.\nGood command of spoken and written English, Cantonese and Putonghua.\nWe offer competitive remuneration package including 5-day work week, family medical plan, duty meal and free shuttle bus (to and from Central, Admiralty, and Aberdeen; to Causeway Bay and Wanchai) and excellent career opportunities to the right candidate. \u00a0\nPlease send full resume, expected salary and contact telephone number to\nHong Kong Parkview\nHuman Resources Department\n88 Tai Tam Reservoir Road, Hong Kong\nConfidential Fax No. 28123490\nEmail via \"Apply Now\"\n\n(All data collected will be used for recruitment purpose only)", "employment_types": ["Full Time", "Permanent"], "selling_points": ["Conduct basic accounting system maintenance", "Support in ad-hoc duties", "At least 4 years audit / accounting experience"], "locations": ["Wan Chai Area"], "categories": ["Accounting", "Accountant", "Audit", "Financial Analyst"], "post_time": "2022-01-17T11:37:40Z", "salary": {"currency": null, "max": null, "min": null, "period": "monthly", "term": null}, "salary_visible": false, "title_keywords": ["accountant"], "responsibilities": ["maintenance", "full set of accounts", "daily accounting operations", "financial analysis", "management reports", "ad-hoc duties"], "requirements": {"degrees": ["diploma", "degree holder"], "majors": ["accounting"], "languages": ["cantonese", "putonghua", "english"], "language_level": ["good command"], "hard_skills": ["no", "ms excel", "hkicpa"], "soft_skills": [], "languages_combined": [{"language": "cantonese", "language_level": ["good command"]}, {"language": "putonghua", "language_level": ["good command"]}, {"language": "english", "language_level": ["good command"]}]}, "experience_required": {"duration": ["at least 4 years"], "field": ["accounting experience", "audit"]}}, {"job_id": "100003009054857", "location_code": "hk", "company": "Liu Chong Hing Investment Ltd", "job_title": "Accountant / Senior Accountant", "description": "To cope with our continuous business growth, we are looking for passionate and competent candidates to join us.\n\nJob Responsibilities\n\nHandle full set of accounts, month-end closing and daily accounting entries.\nPerform general accounting functions such as voucher and cheque preparation, cashflow management, bank account reconciliation, accounts receivables and payables.\nPrepare financial management reports, analysis, budget and forecast.\nLiaise with external auditors, bankers and vendors.\nParticipate in ad hoc projects and tasks as assigned by Department Head.\n\n\u00a0Job Requirements\n\nDegree holder or above in Accounting or Finance or equivalent.\nMinimum 5 years\u2019 relevant experience in consolidation and financial accounting, preferably in HK Listed Company.\nMember of HKICPA / ACCA or equivalent professional accounting bodies.\nGood knowledge in accounting standards and taxation.\nSelf-motivated, detail-minded and able to work under pressure.\nStrong analytical and communication skills.\nGood command in English, Cantonese and Mandarin.\nCandidate with PRC / audit experience is preferred.\nPRC travel may be required.\nCandidate with more experience will be considered as Senior Accountant.\u00a0\n\nWe offer a\u00a05-day work week\u00a0with\u00a0attractive remuneration package to the right candidate. Interested parties\u00a0please apply with full resume, contact number, date available and expected salary by\u00a0clicking \"Apply Now\".\u00a0\n\nTo learn more about us, please visit our website\u00a0Liu Chong Hing Investment Ltd.\n\u00a0\nPersonal data provided by job applicants will be used for recruitment purpose only.", "employment_types": ["Full Time", "Permanent"], "selling_points": ["Degree holder Accounting or Finance", "Member of HKICPA / ACCA", "5 -day work week with medical insurance"], "locations": ["Central & Western Area"], "categories": ["Accounting", "Accountant", "Accounting Clerk / Supervisor", "Others"], "post_time": "2022-01-17T11:55:10Z", "salary": {"currency": null, "max": null, "min": null, "period": "monthly", "term": null}, "salary_visible": false, "title_keywords": ["accountant", "senior accountant"], "responsibilities": ["management", "analysis", "full set of accounts", "budget", "management reports", "month-end closing", "ad hoc projects", "forecast", "liaise with", "daily accounting", "external auditors"], "requirements": {"degrees": ["degree holder"], "majors": ["finance", "accounting"], "languages": ["cantonese", "english", "mandarin"], "language_level": ["good command"], "hard_skills": ["acca", "hkicpa"], "soft_skills": ["detail-minded", "communication skills", "self-motivated", "work under pressure"], "languages_combined": [{"language": "cantonese", "language_level": ["good command"]}, {"language": "english", "language_level": ["good command"]}, {"language": "mandarin", "language_level": ["good command"]}]}, "experience_required": {"duration": ["minimum 5 years"], "field": ["consolidation", "senior accountant", "relevant experience", "audit experience", "accounting", "financial"]}}, {"job_id": "100003009052675", "location_code": "hk", "company": "Oxford Asset Management Limited", "job_title": "Accountant", "description": "We\u00a0are a\u00a0well-established\u00a0property\u00a0leasing,\u00a0management and investment company located in Wanchai-Admiralty area, now inviting an experienced candidate for the position of\u00a0Accountant.\n\n\nResponsibilities:\n\nReview daily accounting operation, handle month end/year end closing and prepare monthly management reports.\nAssist in consolidated financial reporting preparation\nAssist in budget & forecast and audit & tax issues\nCoordinate with different operation teams in PRC and overseas;\nImplementation of proper internal control procedures, accounting\u00a0policies and procedures;\nLiaise with banks, auditors, IRD and tax authorities in Hong Kong and overseas;\nPerform ad hoc project / assignment as required\u00a0\n\nRequirements:\n\n\u00a0University Degree in Accounting/HKICPA student member;\n\u00a0Minimum 4-5 years relevant experience in accounting/audit preferably in property industry;\nHands-on experience in full sets of books and accounting operations\nProficiency in MS Excel; Hands-on experience in FlexSystem (FION & FIONA)\nProficiency in written & spoken English and Mandarin.\nInitiative, deadline and result oriented, pro-active and be a great team member;\nWork independently\u00a0\n\nWe offer an attractive remuneration package and excellent career prospects to the right candidate. Please send full resume, recent photo, current and expected salary, contact number and the availability for interview.\n\n\nPersonal data collected will be used for recruitment purpose only.", "employment_types": ["Full Time"], "selling_points": [], "locations": ["Wan Chai"], "categories": ["Accounting", "Accountant", "Accounting Clerk / Supervisor"], "post_time": "2022-01-17T03:41:10Z", "salary": {"currency": null, "max": null, "min": null, "period": "monthly", "term": null}, "salary_visible": false, "title_keywords": ["accountant"], "responsibilities": ["tax", "ad hoc", "review", "budget", "audit", "coordinate with", "teams", "implementation", "procedures", "management reports", "accounting policies", "financial reporting", "forecast", "liaise with", "daily accounting", "internal control"], "requirements": {"degrees": ["university degree"], "majors": ["accounting"], "languages": ["english", "mandarin"], "language_level": ["proficiency"], "hard_skills": ["ms excel", "flexsystem", "hkicpa"], "soft_skills": ["work independently", "result oriented", "hands-on", "pro-active", "team member", "initiative"], "languages_combined": [{"language": "english", "language_level": ["proficiency"]}, {"language": "mandarin", "language_level": ["proficiency"]}]}, "experience_required": {"duration": ["minimum 4-5 years"], "field": ["accounting", "relevant experience", "audit"]}}, {"job_id": "100003009054548", "location_code": "hk", "company": "Pine Peak Capital Group (Hong Kong) Limited", "job_title": "Accountant", "description": "Responsibilities:\n- Handle full set accounting duties for the private Companies;\n- Handle accounts payable, accounts receivable and invoice settlement;\n- Prepare cheque payment and fund transfer;\n- Liaise with the external auditors to carry out audit exercise;\n- Update the organization chart;\n- Handle the ad hoc tasks assigned by the Chairman.\n\nRequirements:\n- Degree holder in Accounting or related discipline, qualified member of ACCA / HKICPA is preferred but not a must;\n- At least 3 years of solid experience in accounting field, gained from private Company is highly preferred;\n- Strong PC skills especially MS Excel;\n- Good command of both written and spoken in English and Chinese, fluency in Putonghua is highly preferred.\n\nWe offer attractive remuneration package to the right candidate. Interested parties, please send full resume with current, expected salary and availability by clicking \"Apply Now\".\n\nCollected personal data is used for recruitment purpose only.", "employment_types": ["Full Time", "Permanent"], "selling_points": [], "locations": ["Central"], "categories": ["Accounting", "Accountant", "Accounting Clerk / Supervisor", "Finance / Accounting Manager"], "post_time": "2022-01-17T09:57:15Z", "salary": {"currency": null, "max": null, "min": null, "period": "monthly", "term": null}, "salary_visible": false, "title_keywords": ["accountant"], "responsibilities": ["handle full set accounting", "accounts receivable", "invoice", "ad hoc tasks", "audit", "payment", "liaise with", "accounts payable", "external auditors"], "requirements": {"degrees": ["degree holder"], "majors": ["accounting"], "languages": ["putonghua", "english", "chinese"], "language_level": ["fluency", "good command"], "hard_skills": ["acca", "pc skills", "ms excel", "hkicpa"], "soft_skills": [], "languages_combined": [{"language": "putonghua", "language_level": ["fluency", "good command"]}, {"language": "english", "language_level": ["good command"]}, {"language": "chinese", "language_level": ["good command"]}]}, "experience_required": {"duration": ["at least 3 years"], "field": ["accounting"]}}, {"job_id": "100003009052766", "location_code": "hk", "company": "GDC Technology Limited", "job_title": "Accountant", "description": "Responsibilities:\n\nHandle month-end closing\nPrepare management reports of various subsidiaries\nPrepare consolidated financial reports and financial analysis\nReview management reports submitted by overseas branches\nLiaise with various operation teams and external auditors\nHandle ad hoc projects\u00a0\n\nRequirements:\n\nBachelor\u2019s degree holder in Accounting\nMinimum 3 years\u2019 relevant working experience\nExperience gained in Big-4 or MNC preferred\nFamiliar with ERP system and proficient in Excel\nSelf-initiative, responsible and good communication skills\nGood command in both written and spoken English and Chinese (multi-national working environment)\nImmediate available is preferred\n\nAttractive remuneration package will be offered.\n\nAll information provided by applicants will be treated in strict confidence and used only for processing application.", "employment_types": ["Full Time"], "selling_points": [], "locations": ["North Point"], "categories": ["Accounting", "Accountant"], "post_time": "2022-01-17T03:58:53Z", "salary": {"currency": null, "max": null, "min": null, "period": "monthly", "term": null}, "salary_visible": false, "title_keywords": ["accountant"], "responsibilities": ["financial reports", "review", "teams", "financial analysis", "management reports", "month-end closing", "ad hoc projects", "liaise with", "external auditors"], "requirements": {"degrees": ["bachelor", "degree holder"], "majors": ["accounting"], "languages": ["english", "chinese"], "language_level": ["good command"], "hard_skills": ["excel", "erp system", "processing"], "soft_skills": ["communication skills", "confidence", "self-initiative", "responsible"], "languages_combined": [{"language": "english", "language_level": ["good command"]}, {"language": "chinese", "language_level": ["good command"]}]}, "experience_required": {"duration": ["minimum 3 years"], "field": ["relevant working experience"]}}, {"job_id": "100003009044141", "location_code": "hk", "company": "Accenture Company Limited", "job_title": "Accountant/ Senior Accountant", "description": "Responsibilities:\n\nPrepare consolidated financial and management reporting, breakdowns and analysis\nHandle full set of accounts, month-end closing, inter-company reconciliation and prepare group reporting reports\nCompile financial analysis to facilitate businesses performance review and management decision making\nHandle PRC local finance department queries and escalate the accounting issue to Financial controller\nOccasional travel to PRC may be required\nParticipate in other accounting related and ad-hoc assignments\n\n\u00a0Requirement:\n\nDegree holder in Accounting, Finance or related discipline\n5 years\u2019 relevant experience of PRC accounting\nResult-driven, well organized and independent\nStrong analytical mind and good communication skills\nProficient in MS Office, knowledge in Kingdee would be an advantage\nFluent in written and spoken English, Chinese and Mandarin\n\nWe offer an attractive remuneration package including a competitive salary, fringe benefits and good career prospects to the right candidates.\u00a0\n\nInterestedarties please apply with a detailed resume together with expected salary and contact telephone no. to the\u00a0Human Resources Department, Angliss\u00a0Hong Kong Food Service Limited, 47- 51 Kwai Fung Crescent, Kwai Chung, New Territories, Hong Kong\u00a0or fax 2439 5168 or clicking the\u00a0\"Apply now\"\u00a0button for application.\n\n(We regret that only successful candidates will be notified.)\n\n(Data collected will be used for recruitment purpose only.)", "employment_types": ["Full Time"], "selling_points": ["5-day work week, Performance bonus", "1 year working experience in accounting field", "Immediate available is preferred"], "locations": ["Kowloon Bay"], "categories": ["Accounting", "Accountant", "Accounting Clerk / Supervisor", "Others"], "post_time": "2022-01-13T03:12:03Z", "salary": {"currency": null, "max": null, "min": null, "period": "monthly", "term": null}, "salary_visible": false, "title_keywords": ["accountant", "senior accountant"], "responsibilities": ["reporting", "management", "ad-hoc assignments", "analysis", "full set of accounts", "review", "financial analysis", "month-end closing", "reports", "management reporting"], "requirements": {"degrees": ["degree holder"], "majors": ["finance", "accounting"], "languages": ["english", "chinese", "mandarin"], "language_level": ["fluent"], "hard_skills": ["ms office", "prc accounting"], "soft_skills": ["communication skills", "independent", "well organized", "analytical mind", "driven"], "languages_combined": [{"language": "english", "language_level": ["fluent"]}, {"language": "chinese", "language_level": ["fluent"]}, {"language": "mandarin", "language_level": ["fluent"]}]}, "experience_required": {"duration": ["5 years"], "field": ["accounting", "relevant experience"]}}, {"job_id": "100003009052302", "location_code": "hk", "company": "Somfy Co Ltd", "job_title": "Assistant Accountant / Accountant", "description": "Responsibilities:\n\n\nRecords accounting transactions on a daily basis including collecting, coordinating, and verifying accounting data\nResponsible for maintaining the account as well as the monthly statement including cash flow statement and bank reconciliation\u00a0\nAssist in analyses accounting situations (preparation and use of dashboards, ad-hoc reports and analysis as and when required.)\nPerforms financial, fiscal, and social accounting procedures, provide accurate and timely financial reports and information according to Somfy group rules and local GAAP for statutory and management purposes\nContributes to the improvement of management tools and accounting procedures\nSecures the approval flow of segregation of duties, as well as internal BU procedures and processes, are in place to prevent and to detect fraud, accounting and reporting errors\nDigitizes\u00a0among the document flows across the team and accounting documents\nAssist to Controller in tax matters, external & internal audits, company secretarial, banking, legal compliance, insurance and leasing matters when required\nResponsible for\u00a0Accounts Receivable including managing collection duties with the support\u00a0from the Sales team and participating in implementing effective credit policy with regular review to protect the interests of the company\nEnsure the\u00a0payment processes are properly validated according to the procedures by authority and prepare the bank payment in order\u00a0\nCarry out ad-hoc duties to cope with business needs as and when necessary\n\nRequirements:\n\nBachelor\u2019s degree holder or above in Accounting, Finance, or related disciplines\nFresh graduate will also be considered\nWith hands-on experience gained from sizable organization or MNC will be an advantage\nProficient in PC Skills especially MS 365 applications and possess experience in ERP system such as SAP, Hyperion is a plus\nGood problem solving, analytical skills and able to work independently\nDemonstrate ability to interact and communicate effectively at all levels\nDetail-oriented, committed, pro-active and deadline-driven\nGood command of both written and spoken English and Chinese\nCandidates with more experience will be considered as Accountant\n\nFor Interested parties, please send your full resume with expected salary and availability to the Senior\u00a0Human Resources Manager, Asia Pacific. You are most welcome to visit our company web-site at\u00a0http://www.somfy.com\u00a0for more company information.\n\nOnly short-listed candidates will be informed.\u00a0\u00a0\n\nWe are an equal opportunity employer and welcome applications from all qualified candidates. Personal data collected will be treated in strict confidence and used for recruitment purposes only within the Somfy Group of Companies. The personal data of unsuccessful applicants will be retained for a period of 6 months.", "employment_types": ["Full Time", "Permanent"], "selling_points": [], "locations": ["Quarry Bay"], "categories": ["Accounting", "Accountant"], "post_time": "2022-01-17T02:42:07Z", "salary": {"currency": null, "max": null, "min": null, "period": "monthly", "term": null}, "salary_visible": false, "title_keywords": ["accountant", "assistant accountant"], "responsibilities": ["ad-hoc", "data", "bank reconciliation", "transactions", "regular review", "payment", "tax matters", "maintaining", "accounts receivable", "compliance", "reports", "banking", "reporting", "management", "procedures", "cash flow", "ad-hoc duties", "audits", "financial reports", "analysis", "sales team", "insurance"], "requirements": {"degrees": ["bachelor", "fresh graduate", "degree holder"], "majors": ["related disciplines", "finance", "accounting"], "languages": ["english", "chinese"], "language_level": ["good command"], "hard_skills": ["plus", "sap", "analytical skills", "problem solving", "erp system", "pc skills"], "soft_skills": ["work independently", "detail-oriented", "problem solving", "analytical skills", "hands-on", "committed", "pro-active", "driven"], "languages_combined": [{"language": "english", "language_level": ["good command"]}, {"language": "chinese", "language_level": ["good command"]}]}, "experience_required": {"duration": [], "field": ["sizable organization", "erp system"]}}, {"job_id": "100003009053260", "location_code": "hk", "company": "GenieBiome Limited", "job_title": "Assistant Accountant", "description": "Responsible for daily finance operations including keeping of full set of accounts, ledger posting, bank reconciliation, accounts payables and accounts receivables etc.\nManage intercompany transactions and reconciliation\nPrepare sales invoice, control stock in and out distribution with internal and external parties in ERP\nProvide supports to various departments in operation and business related to financial aspects\nAssist in ad hoc projects assignment\u00a0\n\nJob requirements:\n\nForm 5/DSE, with LCCI Intermediate, Level 3 or above\nAt least 3 years' accounting or finance experience\u00a0\nProficiency in MS Office application, including Excel, Chinese word processing and Powerpoint;\nKnowledge of Kingdee is an advantage\nKnowledge & experience in Ecommerce is a plus\nGood command of written and spoken English and Chinese (Mandarin a plus)\nSelf-motivated, proactive and able to work under pressure\nImmediate available is preferred\n\nWe offer competitive remuneration package to the right candidate. Interested parties, please send your resume with expected salary and date of availability via \u201cQuick Apply\u201d.\u00a0Please quote the Reference no: GB-AA/17012022/001 on your application.\n\nAll personal data collected will be used for recruitment purpose only.", "employment_types": ["Full Time", "Permanent"], "selling_points": ["Higher Diploma or Degree holder in accounting", "Career development opportunities, Biotech. Co.", "5 working days"], "locations": ["Wan Chai"], "categories": ["Accounting", "Accountant"], "post_time": "2022-01-17T06:36:12Z", "salary": {"currency": null, "max": null, "min": null, "period": "monthly", "term": null}, "salary_visible": false, "title_keywords": ["assistant accountant"], "responsibilities": ["control", "invoice", "full set of accounts", "prepare sales", "bank reconciliation", "transactions", "internal and external parties", "finance operations", "ad hoc projects", "work under pressure"], "requirements": {"degrees": ["form 5", "dse"], "majors": [], "languages": ["english", "chinese", "mandarin"], "language_level": ["proficiency", "good command"], "hard_skills": ["excel", "plus", "chinese word processing", "powerpoint", "erp", "ms office"], "soft_skills": ["self-motivated", "proactive", "responsible", "work under pressure"], "languages_combined": [{"language": "english", "language_level": ["good command"]}, {"language": "chinese", "language_level": ["proficiency", "good command"]}, {"language": "mandarin", "language_level": ["good command"]}]}, "experience_required": {"duration": ["at least 3 years"], "field": ["ecommerce", "finance", "accounting"]}}, {"job_id": "100003009051611", "location_code": "hk", "company": "Infinity Cargo Express Limited", "job_title": "Cost Accountant", "description": "Job\u00a0Description:\n\n-\u00a0\u00a0\u00a0\u00a0\u00a0 Handle daily AP accounting transactions,\n\n-\u00a0\u00a0\u00a0\u00a0\u00a0 Responsible for weekly cash forecast\n\n-\u00a0\u00a0\u00a0\u00a0\u00a0 Responsible for monthly airfreight job closing and GP analysis\n\n-\u00a0\u00a0\u00a0\u00a0\u00a0 Check and review airline Tonnage and EQ adjustment report\n\n-\u00a0\u00a0\u00a0\u00a0\u00a0 Assist with annual audit.\n\n-\u00a0\u00a0\u00a0\u00a0\u00a0 Perform other Ad-hoc duties as assigned\n\nQualifications and Experience:\n\n-\u00a0 \u00a0Diploma in accountancy with experience in e-commerce platforms/Freight forwarding industry will be advantage\n\n- \u00a0\u00a0\u00a03- 5 years relevant working experiences\n\n-\u00a0\u00a0\u00a0 Proficiency in Excel (e.g. Pivot & Vlookup) and Word processing\n\n-\u00a0\u00a0\u00a0 Good command of English and conversational Putonghua\n\n-\u00a0\u00a0 \u00a0Immediate available is highly preferred\n\n\n\nBenefits\n\nYear-end Double pay, MPF, Group Medical, Bank Holidays, 12 days Annual Leave\nWork life balance\n\nWorking Location: Tsuen Wan\n\nInterested candidates, please contact us at 24060820 for company details.\n\nAll information provided by applicants will be treated in strict confidential and used only for the recruitment purpose", "employment_types": ["Full Time"], "selling_points": ["Double Pay, 12 days AL, Group Medical", "Experience in Freight forwarding is an advantage", "Immediate Available is preferred"], "locations": ["Tsuen Wan Area"], "categories": ["Accounting", "Accountant", "Accounting Clerk / Supervisor", "Banking / Finance", "Financial Services"], "post_time": "2022-01-16T14:32:23Z", "salary": {"currency": null, "max": null, "min": null, "period": "monthly", "term": null}, "salary_visible": false, "title_keywords": ["accountant"], "responsibilities": ["ap", "annual audit", "analysis", "review", "e-commerce platforms", "transactions", "forecast", "ad-hoc duties", "report"], "requirements": {"degrees": ["diploma"], "majors": ["e-commerce", "accountancy"], "languages": ["putonghua", "english"], "language_level": ["conversational", "good command"], "hard_skills": ["ap", "excel", "e-commerce", "analysis", "airline", "word processing", "vlookup"], "soft_skills": ["responsible", "ad-hoc duties"], "languages_combined": [{"language": "putonghua", "language_level": ["good command"]}, {"language": "english", "language_level": ["conversational", "good command"]}]}, "experience_required": {"duration": ["3- 5 years"], "field": ["e-commerce"]}}, {"job_id": "100003009051879", "location_code": "hk", "company": "The Great Eagle Group of Companies", "job_title": "Accounts Supervisor - Payable", "description": "Responsibilities:\n\nPerform daily accounting payable duties and ensure all accounting transactions are recorded in accordance with corporate guidelines with integrity and accuracy\nMonitor cash flow, vendor payments, fund request & transfer, bank reconciliations\nAssist in preparing cash management related analysis and management reports\nSupervise subordinates to perform their duties and work as a team\nPerform ad hoc assignments as required\n\nRequirements:\n\nDiploma or above with at least 4 years\u2019 accounting experience, preferably gained in sizeable organization\nIndependent and self-motivated, well-organized and willing to learn\nGood communication and interpersonal skills\nProficiency in MS Office applications and knowledge of Oracle system will be an advantage\nGood command of both spoken and written English and Chinese\n\nSalary and benefits will be commensurate with qualifications and experience.\u00a0 Interested parties, please send a full resume with present and expected salary, and date available to The Human Resources Department, 32/F., Great Eagle Centre, 23 Harbour Road, Wanchai, Hong Kong or e-mail to us.\u00a0(Please quote the reference no. on the envelope and the covering letter.)\n\nTo know more about us, please visit our website at http://www.greateagle.com.hk.\n\nWe are an equal opportunity employer and welcome applications from all qualified candidates.\n\nPersonal data collected will be treated in strict confidence and used only for recruitment-related purpose. Applicants who have not heard from us within four weeks may consider their applications unsuccessful. All personal data will be destroyed after 12 months.", "employment_types": ["Full Time", "Permanent"], "selling_points": ["Perform daily accounting payable duties", "Monitor cash flow, vendor payments etc.", "Independent and self-motivated"], "locations": ["Wan Chai"], "categories": ["Accounting", "Accountant", "Accounting Clerk / Supervisor"], "post_time": "2022-01-17T01:26:10Z", "salary": {"currency": null, "max": null, "min": null, "period": "monthly", "term": null}, "salary_visible": false, "title_keywords": ["accounts supervisor"], "responsibilities": ["management", "guidelines", "analysis", "monitor", "bank reconciliations", "transactions", "cash flow", "management reports", "payments", "ad hoc assignments", "daily accounting"], "requirements": {"degrees": ["diploma or above"], "majors": ["accounting"], "languages": ["english", "chinese"], "language_level": ["good command"], "hard_skills": ["oracle system", "ms office"], "soft_skills": ["self-motivated", "independent", "willing to learn", "well-organized", "communication and interpersonal skills"], "languages_combined": [{"language": "english", "language_level": ["good command"]}, {"language": "chinese", "language_level": ["good command"]}]}, "experience_required": {"duration": ["at least 4 years"], "field": ["accounting experience"]}}, {"job_id": "100003009051481", "location_code": "hk", "company": "AXA International Limited", "job_title": "Accountant / Senior Accountant", "description": "Responsibilities:\n\nReview full set of account, costing, taxation and ad hoc assignments of each office\nSupervise and monitor the daily accounting and finance operations of different companies\nPrepare monthly reports, financial statements, cash flow forecast and\u00a0management analysis reports\nConsolidate financial reports, review and prepare of budgeting and management reports to align with business objectives\nEnsure the accounting records and documentation in compliance with the local statutory requirement and company accounting policy\nDeal with both internal and external parties including auditor and tax agent etc.\nSupport year-end audit and taxation\nHandle ad hoc assignment\n\nRequirements:\n\nDegree holder major in accountancy\nStudent member or finalist of HKICPA or ACCA\nMinimum 5 years accounting experience with 3 years in manufacturing industry\nKnowledge in PRC taxation\nProficiency in Microsoft office and applications; well versed in Excel\nWilling to visit China and review financial operation when needed\nGood communication skills with foreign investment parties, able to work and interface well with personnel at various levels\nGood command of written English and Chinese\nFluent in spoken English, Mandarin and Cantonese\nStrong manufacturing analytical, presentation and report writing skills\nImmediately available or short notice will be an advantage", "employment_types": ["Full Time"], "selling_points": [], "locations": ["Wan Chai"], "categories": ["Accounting", "Accountant", "Taxation"], "post_time": "2022-01-16T03:54:01Z", "salary": {"currency": null, "max": null, "min": null, "period": "monthly", "term": null}, "salary_visible": false, "title_keywords": ["accountant", "senior accountant"], "responsibilities": ["monthly reports", "analysis reports", "budgeting", "internal and external parties", "audit", "financial statements", "finance operations", "ad hoc assignment", "compliance", "monitor", "forecast", "management", "review", "cash flow", "documentation", "tax", "taxation", "financial reports", "year-end", "management reports", "ad hoc assignments", "daily accounting"], "requirements": {"degrees": ["degree holder"], "majors": ["accountancy"], "languages": ["cantonese", "english", "chinese", "mandarin"], "language_level": ["good command", "fluent"], "hard_skills": ["excel", "acca", "microsoft office", "writing skills", "hkicpa"], "soft_skills": ["communication skills", "presentation", "writing skills"], "languages_combined": [{"language": "cantonese", "language_level": ["fluent"]}, {"language": "english", "language_level": ["good command", "fluent"]}, {"language": "chinese", "language_level": ["good command"]}, {"language": "mandarin", "language_level": ["fluent"]}]}, "experience_required": {"duration": ["3 years", "minimum 5 years"], "field": ["accounting experience", "manufacturing industry"]}}, {"job_id": "100003009054541", "location_code": "hk", "company": "China Eagle Management Limited", "job_title": "Accountant / Finance Manager (5-day work)", "description": "\u00a0Responsibilities:\n\n\u00a0Assist to Finance Manager to oversee finance and accounting functions of the group and ensure compliance with the Hong Kong Listing Rules, International Accounting Standards (\u201cIAS\u201d) and the Companies Ordinance\nPrepare monthly consolidated financial information for the Group and co-ordinate to issue notices, announcements and circulars for compliance with the Listing Rules and other statutory requirements\nPrepare annual, interim and quarterly financial reports and relevant disclosure notes and liaise with external auditors in all aspects of the financial reporting\nPrepare financial analysis, budgeting, forecast, cash flow projection, and management reports\nAssist in managing funds and liaison with banks\nAssist in reviewing, monitoring and enhancing internal controls of the Group\nAssist in tax planning, treasury functions and any ad hoc projects for the Group\n\nRequirements:\n\nDegree holder in Accounting and possess HKICPA/ACCA or other equivalent\n4-5 years of relevant work experienceof which at least 1-2 years in a Hong Kong listed company.\nStrong analytical and excellent interpersonal skills\nPositive attitude, good team work ethic , highly responsibility and able to work under pressure\nDriven, enthusiastic, highly self-motivated, and able to operate independently\nConversant in accounting principles; experience in tax issues and legal practice preferred\nExcellent communication skills, fluent in English, Cantonese and Mandarin\nCandidates with more working experience will be considered as senior position", "employment_types": ["Full Time"], "selling_points": ["oversee finance and accounting functions", "1-2 years in a Hong Kong listed company", "5-day work & medical insurance"], "locations": ["Central"], "categories": ["Accounting", "Accountant", "Finance / Accounting Manager", "Treasurer"], "post_time": "2022-01-17T09:56:44Z", "salary": {"currency": null, "max": null, "min": null, "period": "monthly", "term": null}, "salary_visible": false, "title_keywords": ["accountant", "finance manager"], "responsibilities": ["tax", "financial reports", "budgeting", "compliance", "monitoring", "ensure compliance", "financial analysis", "statutory requirements", "cash flow", "management reports", "planning", "financial reporting", "forecast", "ad hoc projects", "liaise with", "listing", "external auditors"], "requirements": {"degrees": ["degree holder"], "majors": ["accounting"], "languages": ["cantonese", "english", "mandarin"], "language_level": ["excellent", "fluent"], "hard_skills": ["acca", "hkicpa"], "soft_skills": ["good team work", "communication skills", "self-motivated", "independently", "positive attitude", "interpersonal skills", "enthusiastic", "driven", "work under pressure"], "languages_combined": [{"language": "cantonese", "language_level": ["excellent", "fluent"]}, {"language": "english", "language_level": ["excellent", "fluent"]}, {"language": "mandarin", "language_level": ["excellent", "fluent"]}]}, "experience_required": {"duration": [], "field": ["legal"]}}, {"job_id": "100003009051712", "location_code": "hk", "company": "ASM Technology Hong Kong Limited", "job_title": "Contract General Accountant", "description": "Job description\nSupport daily data processing and voucher postings\nPerform month-end closing tasks and financial reporting packages\nAssist in preparation of annual accounts\nConduct analytical review of the financial data\nHandle other ad hoc duties as required\nJob requirements\nDegree in Accounting, Finance or relevant disciplines\nAt least 3 years working experience in accounting\nExperience in using SAP will be an advantage\nProficient in MS office application\nSelf-motivated and committed to continuous improvement\nAble to work independently and be a team player\nImmediately available is highly preferred\n\nWorking location: Tsing Yi, Hong Kong\n\nAttractive salary and fringe benefits package will be offered to the right candidates.\n\nInterested parties please submit your application with cover letter, resume, certificate and transcripts.\n\nData collected will be used for recruitment purpose only. Suitable candidates may be referred to other vacancies within our company.", "employment_types": ["Full Time", "Contract"], "selling_points": ["Degree in Accounting, Finance", "At least 3 years working experience", "Support daily data processing and voucher postings"], "locations": ["Tsing Yi"], "categories": ["Accounting", "Accountant", "Accounting Clerk / Supervisor", "Others"], "post_time": "2022-01-16T21:51:02Z", "salary": {"currency": null, "max": null, "min": null, "period": "monthly", "term": null}, "salary_visible": false, "title_keywords": ["accountant"], "responsibilities": ["ad hoc duties", "data", "review", "data processing", "month-end closing", "financial reporting"], "requirements": {"degrees": ["degree"], "majors": ["finance", "accounting"], "languages": [], "language_level": [], "hard_skills": ["sap", "ms office"], "soft_skills": ["committed", "self-motivated", "team player", "work independently"], "languages_combined": []}, "experience_required": {"duration": ["at least 3 years"], "field": ["accounting"]}}, {"job_id": "100003009052193", "location_code": "hk", "company": "Fed-Supremetech Limited", "job_title": "Assistant Accountant", "description": "Electrical Engineering firm in Shatin invites candidates for the following vacancy :-\n\nASSISTANT ACCOUNTANT\n\nJob Responsibilities\n- To handle full set of books and accounts\n- To prepare vouchers and cheques.\u00a0 To handle relevant accounting entry, monitoring payment schedule\n- Keep track of bank balance and cash flow forecast\n- Handle month-end closing, remittance and reports\n- Assist in preparing annual financial budget\n\n\u00a0Requirements\n\n-Holder of LCC Higher Certificate of Accounting or equivalent\n-At least 5 years relevant working experience\n-Good communication skills; fluent Cantonese and English, Mandarin is essential\n-Proficient PC skills in MS office\n\n\nWe offer attractive package, including public holidays, alternate Saturday, double pay, Bonus, 14days annual leave,etc.\u00a0to suitable candidates. Interested\u00a0candidates please send application with full resume, availability and expected salary by email\u00a0\n\nPersonal data collected will be used for recruitment purpose only.\n\n\n\n", "employment_types": ["Full Time"], "selling_points": [], "locations": ["Shatin Area"], "categories": ["Accounting", "Accountant", "Accounting Clerk / Supervisor", "Others"], "post_time": "2022-01-17T02:26:00Z", "salary": {"currency": null, "max": null, "min": null, "period": "monthly", "term": null}, "salary_visible": false, "title_keywords": ["assistant accountant"], "responsibilities": ["monitoring", "budget", "payment", "cheques", "cash flow", "schedule", "forecast", "month-end closing", "reports"], "requirements": {"degrees": ["higher certificate"], "majors": ["accounting"], "languages": ["cantonese", "english", "mandarin"], "language_level": ["fluent"], "hard_skills": ["pc skills", "lcc", "ms office"], "soft_skills": ["communication skills"], "languages_combined": [{"language": "cantonese", "language_level": ["fluent"]}, {"language": "english", "language_level": ["fluent"]}, {"language": "mandarin", "language_level": []}]}, "experience_required": {"duration": ["least 5 years"], "field": ["relevant working experience"]}}, {"job_id": "100003009054003", "location_code": "hk", "company": "Hang Lung Properties Limited", "job_title": "Accountant (China Reporting)", "description": "Responsibilities\u00a0\u00a0\n\nDeliver the monthly management and analysis reports of the Group\nEngage in budgeting and long term financial planning\nPromote standardization of the Group accounting and financial policies/ procedures\nSupport resolving financial and accounting issues of the Group companies in Mainland China\nSupport annual audit/interim review and results announcements\nWork on ad-hoc assignments as required\n\n\u00a0Requirements\n\nDegree in Accounting, Finance or related discipline and member of HKICPA or equivalent\nAt least 5 years of solid experience in listed sizable organization\nCandidate with experience in Big Four CPA firm is definitely an advantage\nSound knowledge of Mainland China accounting, taxation and regulations are essential\nAnalytical mind with ability to work in fast paced environment\nStrong communication and interpersonal skills\nGood command of spoken and written English and Chinese; proficiency in Mandarin is a must\nFamiliar with Oracle and Yonyou is highly preferred", "employment_types": ["Full Time", "Permanent"], "selling_points": ["Knowledges of Mainland Accounting & Taxation", "Experience in Big Four CPA firm", "Familiar with Oracle and Yonyou"], "locations": ["Mong Kok"], "categories": ["Accounting", "Accountant", "Financial Analyst"], "post_time": "2022-01-17T08:39:09Z", "salary": {"currency": null, "max": null, "min": null, "period": null, "term": null}, "salary_visible": false, "title_keywords": ["accountant"], "responsibilities": ["management", "annual audit", "analysis reports", "budgeting", "ad-hoc assignments", "financial policies", "procedures", "review", "planning"], "requirements": {"degrees": ["degree"], "majors": ["finance", "accounting"], "languages": ["english", "chinese", "mandarin"], "language_level": ["proficiency", "good command"], "hard_skills": ["cpa", "oracle", "hkicpa"], "soft_skills": ["analytical mind", "communication and interpersonal skills"], "languages_combined": [{"language": "english", "language_level": ["good command"]}, {"language": "chinese", "language_level": ["good command"]}, {"language": "mandarin", "language_level": ["proficiency"]}]}, "experience_required": {"duration": ["at least 5 years"], "field": ["sizable organization", "cpa firm", "big four"]}}, {"job_id": "100003009054450", "location_code": "hk", "company": "SMCP Asia Limited", "job_title": "Senior Accountant", "description": "Reporting to:\u00a0Regional Accounting Manager\n\n\nResponsibilities:\n\n\n\nSpecific scope on Hong Kong and Macau entities:\n\n\nHandle CAPEX related payable invoices and corresponding accruals\nPrepare and update Fixed Assets related schedules\nPrepare audit schedules and handle annual audit process\nScope on Asia region:\nPrepare cashflow forecast\nPrepare inventory reconciliation\nReview related payable invoices and corresponding accruals\nReview general ledger entries\nReview Fixed Assets related schedules\nOthers :\u00a0\n\nAssist in other projects and duties as assigned\n\nRequirements :\u00a0\n\n\n\nDegree in Accounting / Finance or related discipline\nQualified member of one of the major accountancy associations\nMinimum 6 years relevant experience in accounting, preferably in retail industry with audit background will be a plus\nGood command of both spoken and written English, Mandarin and Cantonese\nHands-on experience in Oracle ERP system is an advantage\nDetail-oriented, able to work independently, meet tight deadline and show ownership at work\nGood communication skills, be a good team player and agile when managing tasks and projects", "employment_types": ["Full Time", "Permanent"], "selling_points": ["Min 6 years of relevant exp in related field", "Hands-on exp in Oracle ERP system is an advantage", "Detail oriented,proactive & can work independently"], "locations": ["Central"], "categories": ["Accounting", "Accountant", "Banking / Finance", "Others"], "post_time": "2022-01-17T09:35:31Z", "salary": {"currency": null, "max": null, "min": null, "period": "monthly", "term": null}, "salary_visible": false, "title_keywords": ["senior accountant"], "responsibilities": ["invoices", "annual audit", "schedules", "general ledger", "inventory", "review", "capex", "audit", "forecast"], "requirements": {"degrees": ["degree"], "majors": ["finance", "accounting"], "languages": ["cantonese", "english", "mandarin"], "language_level": ["good command"], "hard_skills": ["plus", "agile", "oracle erp"], "soft_skills": ["communication skills", "work independently", "good team player", "agile", "detail-oriented", "hands-on", "meet tight deadline"], "languages_combined": [{"language": "cantonese", "language_level": ["good command"]}, {"language": "english", "language_level": ["good command"]}, {"language": "mandarin", "language_level": ["good command"]}]}, "experience_required": {"duration": ["minimum 6 years"], "field": ["retail industry", "audit", "erp system", "relevant experience", "accounting"]}}, {"job_id": "100003009054160", "location_code": "hk", "company": "The Hong Kong Polytechnic University", "job_title": "Associate Accountant (Accounting Operations Section)", "description": "FINANCE OFFICE\n\nAssociate Accountant (Accounting Operations Section) (Ref. 22011708-E4)\n\nDuties\n\nThe appointee will be required to:\n\n(a) perform staff cost analyses and projections for the management and funding bodies;\n\n(b) assist in reviewing and outlining the financial implications on pay level and adjustment reviews for Council\u2019s decision;\n\n(c) assist in enhancement and implementation of systems related to payroll, staff claims and payments;\n\n(d) supervise daily operations of payroll, benefits, staff claims and related payments of the University and its subsidiaries, including verifying payments and related tax filing, and ensuring compliance with the relevant statutory requirements, policies, rules and regulations;\n\n(e) handle general office administration; and\n\n(f) perform any other duties as assigned by the Director of Finance and her delegates.\n\nQualifications\u00a0\n\nApplicants should have:\n\n(a) a recognized degree in Accounting or related disciplines;\n\n(b) a professional accounting qualification or equivalent;\n\n(c) at least three years of post-qualification experience in accounting, auditing or other related fields, preferably with experience in payroll operations, staff benefits, claims processing and/or system enhancement;\u00a0\n\n(d) some supervisory experience;\n\n(e) proficiency in Microsoft Office software including Excel, Word and PowerPoint;\n\n(f) a good command of both written and spoken English and Chinese; and\n\n(g) good communication and interpersonal skills.\n\nShortlisted candidates will be invited to sit for a written test.\n\nApplicants who have responded to the previous advertisement need not re-apply.\n\nRemuneration and Conditions of Service\n\nA highly competitive remuneration package will be offered. \u00a0Initial appointment will be on a fixed-term gratuity-bearing contract.\u00a0 Re-engagement thereafter is subject to mutual agreement.\u00a0 Applicants should state their current and expected salary in the application.\n\nApplication\n\nPlease send a completed application form by post to Human Resources Office, 13/F, Li Ka Shing Tower, The Hong Kong Polytechnic University, Hung Hom, Kowloon, Hong Kong or via email by clicking \"Apply Now\".\u00a0 Application forms can be downloaded from https://www.polyu.edu.hk/hro/careers/guidelines_and_forms/forms.\u00a0 If a separate curriculum vitae is to be provided, please still complete the application form which will help speed up the recruitment process. The closing date for application is Monday, 31 January 2022.\u00a0 Applicants who are not invited to an interview within two months from the closing date should consider their applications unsuccessful. The University\u2019s Personal Information Collection Statement for recruitment can be found at https://www.polyu.edu.hk/hro/careers/guidelines_and_forms/pics_for_recruitment.\n\nPolyU is an equal opportunity employer committed to diversity and inclusivity.\u00a0 All qualified applicants will receive consideration for employment without regard to gender, ethnicity, nationality, family status or physical or mental disabilities.", "employment_types": ["Full Time"], "selling_points": [], "locations": ["Not Specified"], "categories": ["Accounting", "Accountant", "Accounting Clerk / Supervisor", "Audit"], "post_time": "2022-01-17T08:40:30Z", "salary": {"currency": null, "max": null, "min": null, "period": null, "term": null}, "salary_visible": false, "title_keywords": ["operations", "associate", "accountant", "accounting"], "responsibilities": ["regulations", "any other duties", "software", "operations", "communication", "statutory requirements", "office administration", "tax filing", "compliance", "implementation", "cost", "management", "daily operations", "recruitment process", "payroll", "policies", "systems", "payments", "recruitment", "auditing"], "requirements": {"degrees": ["degree"], "majors": ["related disciplines", "accounting"], "languages": ["english", "chinese"], "language_level": ["good command"], "hard_skills": ["excel", "word", "powerpoint", "c", "microsoft office software", "processing"], "soft_skills": ["committed", "communication and interpersonal skills"], "languages_combined": [{"language": "english", "language_level": ["good command"]}, {"language": "chinese", "language_level": ["good command"]}]}, "experience_required": {"duration": ["at least three years"], "field": ["post-qualification", "related", "payroll", "supervisory experience", "accounting"]}}, {"job_id": "100003009054615", "location_code": "hk", "company": "Hop Hing Management Company (Hong Kong) Limited", "job_title": "Senior Accountant (Ref No.: SA/1701/22)", "description": "Job Responsibilities:\n\nPrepare Group Management accounts and consolidated report\nRegular review and monitor the accounting function of the Group's business in the PRC\nCoordinate annual audit and handle tax issues\nPrepare Budget and Forecast\nRequirements:\n\nUniversity graduated in Accounting, Finance or other related discipline\nQualified accountant with at least 5 years of experience and 2 years in supervisory level\nPrevious experience PRC accounting is an advantage\nExperience in JD Edwards will be an advantage\nPeriodic travel to PRC is required\n\nInterested parties, please send detail resume and expected salary to HR Department.\n\nPersonal data to be collected for recruitment purpose only.", "employment_types": ["Full Time"], "selling_points": ["University graduated in Accounting", "At least 5 years of experience", "Periodic travel to PRC is required"], "locations": ["Yuen Long"], "categories": ["Accounting", "Accountant"], "post_time": "2022-01-17T10:15:16Z", "salary": {"currency": null, "max": null, "min": null, "period": "monthly", "term": null}, "salary_visible": false, "title_keywords": ["senior accountant"], "responsibilities": ["tax", "management", "annual audit", "budget", "monitor", "regular review", "coordinate", "forecast", "report"], "requirements": {"degrees": [], "majors": [], "languages": [], "language_level": [], "hard_skills": ["prc accounting"], "soft_skills": [], "languages_combined": []}, "experience_required": {"duration": ["2 years", "at least 5 years"], "field": ["supervisory level", "accounting"]}}, {"job_id": "100003009051629", "location_code": "hk", "company": "China Telecom Global Limited", "job_title": "Assistant Accountant", "description": "Responsibilities:\n\nDaily operation processing of Accounts Payable and the Account Reconciliations\nAssist in month-end closing processes, financial reporting, and other management\u00a0reporting\nAssist in tax calculation preparation work and tax return filing preparation works\nKeep record of fixed asset registry\nPerform other duties and ad-hoc projects as assigned\n\nJob Requirements:\n\nDegree holder in Accounting or Business related studies\nFamiliar with IFRS/HKFRS, HK Inland Revenue rules is an advantage\nExperience in using ERP System or Accounting System\nProficient in MS Office applications include Excel, Word and PowerPoint\nGood command of written and spoken English and Chinese\nPleasant personality with excellent management, well organized, communication, and interpersonal skills\nDetail oriented, Self-motivated, with good sense of responsibility to take up challenges\nImmediate availability is preferred\n\nWe offer 5 days work, competitive salary package and attractive career development opportunities to the right candidate.\n\nInterested parties please email your full resume with your current & expected salary to us.\n\nApplicants not invited for interview within 3 months may assume their applications unsuccessful.\n\nIf you are interested in other job opportunities, please check with below career website.\n\nPersonal data collected would be used for recruitment purpose only.", "employment_types": ["Full Time", "Permanent"], "selling_points": ["Degree holder in Accounting or Business related", "Exp. of accounting & financial reporting", "Exp. in telecom industry will be a plus"], "locations": ["Wan Chai"], "categories": ["Accounting", "Accountant", "Accounting Clerk / Supervisor"], "post_time": "2022-01-16T15:39:55Z", "salary": {"currency": null, "max": null, "min": null, "period": "monthly", "term": null}, "salary_visible": false, "title_keywords": ["assistant accountant"], "responsibilities": ["tax", "perform other duties", "daily operation", "reconciliations", "month-end closing", "financial reporting", "management reporting", "ad-hoc projects", "accounts payable"], "requirements": {"degrees": ["degree holder"], "majors": ["business", "accounting"], "languages": ["english", "chinese"], "language_level": ["good command"], "hard_skills": ["excel", "ifrs", "hkfrs", "word", "powerpoint", "erp system", "hk inland revenue rules", "accounting system", "ms office"], "soft_skills": ["self-motivated", "sense of responsibility", "detail oriented", "well organized", "pleasant", "communication", "interpersonal skills"], "languages_combined": [{"language": "english", "language_level": ["good command"]}, {"language": "chinese", "language_level": ["good command"]}]}, "experience_required": {"duration": [], "field": ["erp system", "accounting"]}}, {"job_id": "100003009053062", "location_code": "hk", "company": "Andrew Moore & Associates Limited", "job_title": "Credit Controller / Accountant", "description": "Job Description\nResponsible for full set of accounts independently\nHandle daily inter-company transaction / activities & general ledger\nAssist and monitor daily inventory/ import / export business & Custom EDI activities\nProcess A/P & A/R, credit control, P&L, payroll & various accounting matters of companies (HK & PRC)\nLiaise with Mainland China counterpart on accounting and taxation matters\nPrepare month-end closing schedules, costing analysis and related accounting reports\nAssist in other ad-hoc assignments\n\nRequirements\n\nDiploma holder or above or related discipline\n3-5 years working experience\nExperience in handling full-sets accounts\nProficient in MS Office, ERP and systematic documents processing\nGood command of both spoken and written Chinese and English\nWilling to travel overseas and mainland China in Post-Covid Period\nGood figure sense with proactive attitude and good communication skill\n\nYou will have an advantage if you are:\nHands-on experience in knowledge of financial / accounting / taxation regulation and policy in both HK & China\nDetails oriented, good communication and negotiation skills\nGood in problem solving, analytical and interpersonal skill\nSelf-motivated, committed and able to work under pressure, independently and support team works\nImmediate available\n\nWe offer attractive remuneration package with fringe benefits to right candidates\n\nLocation: walk 3 mins from Chai Wan MTR Station\n\nInterested parties please send email with current and expected salary and date of available by clicking \u201cApply Now\u201d\n\nPersonal Data collected will be used for recruitment purpose only.\n\nNo Recruitment Agency", "employment_types": ["Full Time", "Part Time"], "selling_points": [], "locations": ["Aberdeen"], "categories": ["Accounting", "Accountant"], "post_time": "2022-01-17T05:39:53Z", "salary": {"currency": null, "max": null, "min": null, "period": "monthly", "term": null}, "salary_visible": false, "title_keywords": ["accountant"], "responsibilities": ["taxation", "control", "schedules", "general ledger", "inventory", "full set of accounts", "monitor", "ad-hoc assignments", "p&l", "month-end closing", "costing analysis", "reports", "liaise with", "payroll"], "requirements": {"degrees": ["diploma holder"], "majors": [], "languages": ["english", "chinese"], "language_level": ["good command"], "hard_skills": ["problem solving", "processing", "erp", "ms office"], "soft_skills": ["self-motivated", "independently", "communication skill", "systematic", "interpersonal skill", "communication", "problem solving", "hands-on", "negotiation skills", "committed", "proactive", "work under pressure"], "languages_combined": [{"language": "english", "language_level": ["good command"]}, {"language": "chinese", "language_level": ["good command"]}]}, "experience_required": {"duration": ["3-5 years"], "field": ["accounting", "financial"]}}, {"job_id": "100003009052770", "location_code": "hk", "company": "Noble Ventures Group Limited", "job_title": "Assistant Accountant", "description": "Andrew Moore & Associates (AMA) was originally formed in 1989 in Hong Kong to provide a diverse range of consultancy and survey options to local and international clients.\u00a0 We are now inviting high caliber to join our company.\n\nCredit Controller / Accountant \u00a0\u2013 HONG KONG\n\nResponsibilities\n\n\u2022\u00a0\u00a0\u00a0\u00a0\u00a0\u00a0\u00a0 Billing, updating and monitoring of outstanding AR accounts.\n\n\u2022\u00a0\u00a0\u00a0\u00a0\u00a0\u00a0\u00a0 To assist in general / daily, monthly and yearly accounting duties, prepare reports on time\n\n\u2022\u00a0\u00a0\u00a0\u00a0\u00a0\u00a0\u00a0 Maintain records, filing and some out duty banking work as may be required;\n\n\u2022\u00a0\u00a0\u00a0\u00a0\u00a0\u00a0\u00a0 Ad hoc assignments\n\nRequirements\n\n\u2022\u00a0\u00a0\u00a0\u00a0\u00a0\u00a0\u00a0 At least five years relevant working experiences, university graduate preferred;\n\n\u2022\u00a0\u00a0\u00a0\u00a0\u00a0\u00a0\u00a0 Strong Excel and analytical skills, LCC Higher and ACCA accounting qualifications\n\n\u2022\u00a0\u00a0\u00a0\u00a0\u00a0\u00a0\u00a0 Experience in MYOB or ERP system is highly preferred\n\n\u2022\u00a0\u00a0\u00a0\u00a0\u00a0\u00a0\u00a0 Good computer skills in MS Office and Outlook email operations\n\n\u2022\u00a0\u00a0\u00a0\u00a0\u00a0\u00a0\u00a0 Good Cantonese, Fluent Mandarin, and a good written and spoken English\n\n\u2022\u00a0\u00a0\u00a0\u00a0\u00a0\u00a0 Self motivated, meticulous in work and in numbers, well organized and independent, good communication and interpersonal skills\n\n\u2022\u00a0\u00a0\u00a0\u00a0\u00a0\u00a0 Full time.\u00a0 Part time application also welcome.\n\n\n15days annual leave and attractive remuneration package will be offered to the right candidate.\n\nInterested parties please email your resume with current and expected salary to us.", "employment_types": ["Permanent"], "selling_points": ["Fast Growing Company", "Best-in-class teams", "Rapid Career Progression"], "locations": ["North Point"], "categories": ["Accounting", "Accountant"], "post_time": "2022-01-17T03:59:41Z", "salary": {"currency": null, "max": null, "min": null, "period": "monthly", "term": null}, "salary_visible": false, "title_keywords": ["assistant accountant"], "responsibilities": ["ar", "monitoring", "maintain", "ad hoc assignments", "banking", "prepare reports", "accounting duties"], "requirements": {"degrees": ["university graduate"], "majors": [], "languages": ["cantonese", "english", "mandarin"], "language_level": ["fluent", "good"], "hard_skills": ["excel", "acca", "analytical skills", "erp system", "computer skills", "lcc", "outlook", "myob", "ms office"], "soft_skills": ["meticulous", "independent", "well organized", "analytical skills", "self motivated", "communication and interpersonal skills"], "languages_combined": [{"language": "cantonese", "language_level": ["good", "fluent"]}, {"language": "english", "language_level": ["fluent"]}, {"language": "mandarin", "language_level": ["good", "fluent"]}]}, "experience_required": {"duration": ["at least five years"], "field": ["erp system"]}}, {"job_id": "100003009051548", "location_code": "hk", "company": "Verint Systems (Asia Pacific) Ltd", "job_title": "Assistant Accountant/ Accountant", "description": "Accountant & Admin. Officer\u00a0\n\nJob Responsibilities:\u00a0\u00a0\n\nHandling daily accounting operations and a full set of accounts independently\nPreparation of aging reports, bank reconciliation, and other management reports e.g. Sales Report, Cash Flow Forecast\nHandle all HR matters included prepare Employment Contract, recording staff leave records, Payroll and MPF, Salary Tax Return\u2026.etc\nLiaison with the external auditor\nPrepare project handbook and related documents and duty on regular checking project status\nHandle office administration and ad hoc duties assigned by Management.\u00a0\n\nRequirements:\n\nDegree holder in Accountancy, good command of English and Cantonese\nDetail-minded, well-organized, self-motivated, hardworking, responsible, willing to learn, and able to work independently and under pressure\nTrustworthy, discreet in handling confidential information\nKnowledge of using the Peachtree accounting system is a must\nGood communication and interpersonal skills\nProficient in Microsoft\u00a0Office;\u00a0Excel (VLOOKUP), SQL Server\nImmediately available is preferred\nCandidates with less experience will be considered for Account Clerk\u00a0", "employment_types": ["Full Time"], "selling_points": ["Hands-on experience in Accounting and Oracle", "Immediate availability is highly preferred", "Work location: Cyberport"], "locations": ["Pok Fu Lam"], "categories": ["Accounting", "Accountant", "Accounting Clerk / Supervisor"], "post_time": "2022-01-16T10:07:51Z", "salary": {"currency": null, "max": null, "min": null, "period": "monthly", "term": null}, "salary_visible": false, "title_keywords": ["accountant", "assistant accountant"], "responsibilities": ["tax", "ad hoc duties", "management", "sales report", "mpf", "related documents", "office administration", "hr", "full set of accounts", "daily accounting operations", "bank reconciliation", "checking", "management reports", "cash flow", "reports", "forecast", "staff leave", "payroll"], "requirements": {"degrees": ["degree holder"], "majors": ["accountancy"], "languages": ["cantonese", "english"], "language_level": ["good command"], "hard_skills": ["excel", "peachtree accounting system", "microsoft office", "sql", "server", "vlookup"], "soft_skills": ["detail-minded", "self-motivated", "work independently", "under pressure", "responsible", "trustworthy", "well-organized", "willing to learn", "communication and interpersonal skills", "hardworking"], "languages_combined": [{"language": "cantonese", "language_level": ["good command"]}, {"language": "english", "language_level": ["good command"]}]}, "experience_required": {"duration": [], "field": []}}, {"job_id": "100003009051627", "location_code": "hk", "company": "Harvi Morrison Executive Search", "job_title": "Accountant / Assistant Accountant", "description": "This role will perform general accounting entries, account reconciliations, handling payment transactions, and filing as well.\u00a0\n\nKey Accountabilities\n\nReview the work of payment process prepared by the Share Service Centre, monitor and ensure payments are settled in a timely manner\nPrepare journal vouchers and perform data entries\nAssist in month-end closing, prepare accounts reconciliation and maintain GL\nEnsure proper document filing and provide support to the department\nCarry out ad-hoc assignments as required\nRequirements\n\nDegree in Accounting or equivalent\u00a0\nAt least 2 years hands-on experience in accounting, the candidate with less experience will be considered as Accounting Assistant\nDetail-oriented, organized and self-motivated\nGood computer literacy in MS Word and Excel\nProficient in Oracle system is a plus\nGood written and spoken English & Cantonese\nImmediate availability is preferred\n\nWe offer attractive remuneration package to the right candidate. Please click \"Apply Now\" to\u00a0submit your full resume with current and expected salary.\u00a0\n\n(All applications will be treated strictly confidential and be used in relations to recruitment purpose only.)", "employment_types": ["Full Time", "Permanent"], "selling_points": ["Minimum 4 years related accounting experience", "Good communication & interpersonal skill", "Good command of English & Chinese"], "locations": ["Central & Western Area"], "categories": ["Accounting", "Accountant", "Accounting Clerk / Supervisor", "Others"], "post_time": "2022-01-17T01:30:39Z", "salary": {"currency": null, "max": null, "min": null, "period": "monthly", "term": null}, "salary_visible": false, "title_keywords": ["accountant", "assistant accountant"], "responsibilities": ["journal vouchers", "document filing", "provide support", "data", "ad-hoc assignments", "payment transactions", "review", "monitor", "a timely manner", "reconciliations", "month-end closing", "payments", "maintain", "payment process"], "requirements": {"degrees": ["degree"], "majors": ["accounting"], "languages": ["cantonese", "english"], "language_level": ["good"], "hard_skills": ["excel", "plus", "oracle system", "ms word"], "soft_skills": ["organized", "self-motivated", "timely", "detail-oriented", "computer literacy", "hands-on"], "languages_combined": [{"language": "cantonese", "language_level": ["good"]}, {"language": "english", "language_level": ["good"]}]}, "experience_required": {"duration": ["at least 2 years"], "field": ["accounting"]}}, {"job_id": "100003009054075", "location_code": "hk", "company": "Classy Wheeler Limited", "job_title": "Accountant (Retail Industry)", "description": "Job Offers\n\nDouble Pay\nDiscretionary performance bonus\nMarriage leave\nVolunteer leave\nGroup Medical & Life Insurance coverage including dependents\nTraining sponsorship\nFriendly working environment\nComplimentary Shuttle bus service from Tsing Yi station to office (5 minutes\u2019 drive way)\n\nKey Responsibilities:\n\nManage overheads and support in all issues related to accounts payable and receivable;\nManage the suppliers\u2019 invoices and payments;\nCarry out cost studies, cost planning and control and cost analysis;\nEnsure the agents account reconciliation are up to date and collection is done on time;\nReview services contract with global legal team and the client;\nAssist with Global Services Office operating cost control;\nOther ad hoc duties as assigned.\nJob Requirements:\nBachelor degree in Accounting/ Finance or above;\nMinimum 6 years\u2019 working experience in accounting field;\nExcellent skill in MS Office application;\nProficient in verbal and written English and Chinese;\nMature and with pleasant personality;\nDetail-oriented, able to handle multi-tasks and work under pressure.\n\nCandidate with less experience will be considered as Accountant.\n\nYou are invited to send in your full CV by email to [via Apply Now ].\n\nInformation provided will be treated strictly confidential and only be used for recruitment purposes.\n\nFor more information of Aramex, please visit us at aramex.com.", "employment_types": ["Full Time", "Permanent"], "selling_points": ["Luxury Italian shoes brand", "5 years of accounting experience in retail sector", "Competitive remuneration package and benefit"], "locations": ["Not Specified"], "categories": ["Accounting", "Accountant", "Accounting Clerk / Supervisor", "Finance / Accounting Manager"], "post_time": "2022-01-17T08:19:20Z", "salary": {"currency": null, "max": null, "min": null, "period": "monthly", "term": null}, "salary_visible": false, "title_keywords": ["accountant"], "responsibilities": ["ad hoc duties", "cost", "control", "invoices", "review", "cost planning", "payments", "cost control", "cost analysis", "accounts payable"], "requirements": {"degrees": ["degree", "bachelor"], "majors": ["finance", "accounting"], "languages": ["english", "chinese"], "language_level": ["proficient"], "hard_skills": ["ms office"], "soft_skills": ["multi-tasks", "mature", "detail-oriented", "pleasant", "work under pressure"], "languages_combined": [{"language": "english", "language_level": ["proficient"]}, {"language": "chinese", "language_level": ["proficient"]}]}, "experience_required": {"duration": ["minimum 6 years"], "field": ["accounting"]}}, {"job_id": "100003009051881", "location_code": "hk", "company": "Luen Tai Group (China) Limited", "job_title": "Accounting Officer / Assistant Accountant", "description": "Our Client\n\nOur client, an Italian luxury shoes brand, is looking for an Accountant to join their professional team in Hong Kong and support Hong Kong accounting team\n\nJob Responsibilities\n\nReport to Financial Controller\nProvide finance support to Hong Kong sales & operations team\nHandle full set of accounts and bookkeeping for local business\nArrange payment for local business and ensure compliance with brand payment procedures\nPrepare weekly cash flow forecast and project cash flow plans\nConsolidate sales statements and overall control on local invoices and issuing\nSupport annual filings as required by local tax bureau\nCoordinate for transfer price documentation, if any\nMaintain Fixed Asset Registrar and perform regular physical check of fixed asset\nComplete the bookkeeping and financial reporting\nProvide necessary financial training and coaching to local sales staff, or any other concerned employees\nSupport internal / external audit as necessary\nAny other tasks or projects assigned by Financial Controller\n\nJob Requirements\n\nBachelor degree in Accounting\nOver 5 years\u2019 of work experience in retail finance role, and hands-on experience in different finance aspects could be a plus\nWell organized and attention to details\nGood command of both spoken and written English and Chinese\nExcellent interpersonal and communication skills\nGood team spirit\n\nInterested applicants, please send your detailed resume quoting position title, reference number, current and expected salary.\n\nPersonal data provided by job applicants will be used\u00a0strictly in accordance with the employer's personal data policies and for recruitment purposes only.", "employment_types": ["Full Time"], "selling_points": [], "locations": ["Wong Tai Sin Area"], "categories": ["Accounting", "Accountant", "Accounting Clerk / Supervisor", "Chief Accountant"], "post_time": "2022-01-17T01:26:15Z", "salary": {"currency": null, "max": null, "min": null, "period": "monthly", "term": null}, "salary_visible": false, "title_keywords": ["assistant accountant", "accounting officer"], "responsibilities": ["tax", "control", "invoices", "operations", "full set of accounts", "procedures", "audit", "ensure compliance", "coordinate", "other tasks", "payment", "cash flow", "maintain", "financial reporting", "forecast", "documentation", "plans", "report"], "requirements": {"degrees": ["degree", "bachelor"], "majors": ["accounting"], "languages": ["english", "chinese"], "language_level": ["good command"], "hard_skills": ["plus"], "soft_skills": ["communication skills", "team spirit", "well organized", "hands-on", "attention to details", "interpersonal", "detailed"], "languages_combined": [{"language": "english", "language_level": ["good command"]}, {"language": "chinese", "language_level": ["good command"]}]}, "experience_required": {"duration": ["5 years"], "field": ["finance", "retail"]}}, {"job_id": "100003009053137", "location_code": "hk", "company": "Sinopec Chemical Commercial Holding (Hong Kong) Company Limited", "job_title": "Assistant Accountant", "description": "Responsibilites:\n-\u00a0Handle\u00a0full\u00a0set\u00a0of\u00a0accounts in HK\n-\u00a0Handle\u00a0AR\u00a0&\u00a0AP\u00a0invoices\u00a0&\u00a0settlement,\u00a0accounts\u00a0reconciliation\n-\u00a0Handle\u00a0bank\u00a0payments\u00a0and\u00a0receipts\u00a0including\u00a0L/C\n-\u00a0Prepare\u00a0timely\u00a0cash flow\u00a0statement to top management\n-\u00a0Maintain\u00a0up-to-date\u00a0data\u00a0in\u00a0accounting\u00a0system\u00a0and\u00a0filing\u00a0records\n-\u00a0Assist\u00a0in\u00a0preparing\u00a0month\u00a0end\u00a0closing\u00a0reports\u00a0and\u00a0annual\u00a0audit\n-\u00a0Handle\u00a0ad\u00a0hoc\u00a0projects\u00a0as\u00a0required\n-\u00a0Report\u00a0to\u00a0Accounting\u00a0Manager\n\n\n\nRequirements:\n- Diploma or above in Accounting\n- 3-5 years or above accounting experience\n- Membership of professional group is essential\n- PRC manufacturing experience would be an advantage\n- Proficiency in using MS office, knowledge of\u00a0 ERP system is a plus\n- Mature, responsible, detailed mind with ability to handle multiple tasks independently under pressure\n- Strong organization, good interpersonal and communication skills\n- Good command of both written and spoken in English, Cantonese and Mandarin\n- Immediate available or short notice is highly preferable\n\nWe offer the competitive remuneration to right candidates. Applicant with more experience or qualification will be considered as \"Assistant Accountant\"\n\nInterest parties please send us full resume & expected salary to us.\n\n\"Personal data collected will be used for recruitment purpose only.\"", "employment_types": ["Full Time", "Permanent"], "selling_points": [], "locations": ["Wan Chai"], "categories": ["Accounting", "Accountant", "Accounting Clerk / Supervisor", "Others"], "post_time": "2022-01-17T06:03:37Z", "salary": {"currency": null, "max": null, "min": null, "period": "monthly", "term": null}, "salary_visible": false, "title_keywords": ["assistant accountant"], "responsibilities": ["ap", "management", "month end closing", "invoices", "ar", "receipts", "data", "annual audit", "full set of accounts", "cash flow", "maintain", "payments", "reports", "ad hoc projects", "report"], "requirements": {"degrees": ["diploma or above"], "majors": ["accounting"], "languages": ["cantonese", "english", "mandarin"], "language_level": ["good command"], "hard_skills": ["prc manufacturing", "erp system", "plus", "ms office"], "soft_skills": ["communication skills", "independently", "under pressure", "responsible", "mature", "handle multiple tasks", "detailed mind", "interpersonal"], "languages_combined": [{"language": "cantonese", "language_level": ["good command"]}, {"language": "english", "language_level": ["good command"]}, {"language": "mandarin", "language_level": ["good command"]}]}, "experience_required": {"duration": ["3-5 years"], "field": ["accounting experience", "manufacturing"]}}, {"job_id": "100003009054377", "location_code": "hk", "company": "Strategic Public Relations Group Limited", "job_title": "Assistant Accountant / Accountant (5-day work)", "description": "Main Job Duties:\n\n\nPreparing monthly reports and analysis\nCoordinate with Sales & Operation Department and verify the correctness of revenue and cost postings\nMonth-end closing\nReview sales/purchase contracts and agreements\nCommunicate with overseas representation office, prepare the management accounts and handle\u00a0finance-related issues remotely\nPerform routine accounting works includes voucher entries and filling etc.\nOther ad hoc tasks as assigned\n\nRequirements:\n\n\nBachelor degree in Accounting, Finance, or equivalent\nMember of ACCA or QP or equivalent is preferred\nProficiency in MS Excel and Word\nProficiency in English and Chinese (Mandarin is a must)\nAble to work independently and work under pressure to meet tight deadlines\nPositive attitude, detail-minded, self-motivated\nWilling to learn and work overtime especially for month-end closing\n1-3 years accounting experience\nFresh graduates will also be considered.\n\nWe offer 5 days work with good career prospects for the right candidates. Interested parties please send your application with detailed CV including availability, current and expected salary (IS A MUST) in MS Word format by clicking Apply Now.", "employment_types": ["Full Time", "Permanent"], "selling_points": ["Handle full set of books/ month end/ 3-5 yrs exp.", "5 Days Work with D.Bonus/ Bank Holiday", "12 Days AL/ Birthday Leave/ Medical&Life Insurance"], "locations": ["Admiralty"], "categories": ["Accounting", "Accountant", "Accounting Clerk / Supervisor", "Others"], "post_time": "2022-01-17T09:18:50Z", "salary": {"currency": null, "max": null, "min": null, "period": "monthly", "term": null}, "salary_visible": false, "title_keywords": ["accountant", "assistant accountant"], "responsibilities": ["communicate with", "cost", "management", "monthly reports", "contracts", "analysis", "review", "coordinate with", "ad hoc tasks", "purchase", "month-end closing"], "requirements": {"degrees": ["degree", "bachelor"], "majors": ["finance", "accounting"], "languages": ["english", "chinese", "mandarin"], "language_level": ["proficiency"], "hard_skills": ["acca", "ms excel", "word"], "soft_skills": ["detail-minded", "work independently", "meet tight deadlines", "self-motivated", "work overtime", "willing to learn", "positive attitude", "work under pressure"], "languages_combined": [{"language": "english", "language_level": ["proficiency"]}, {"language": "chinese", "language_level": ["proficiency"]}, {"language": "mandarin", "language_level": []}]}, "experience_required": {"duration": ["1-3 years"], "field": ["accounting experience"]}}, {"job_id": "100003009043218", "location_code": "hk", "company": "Hutchison Property Management Company Limited", "job_title": "ACCOUNTANT [Ref. A-PRC]", "description": "Responsibilities:\n\nHandle full set of accounts\nPrepare and review accounting records, financial statements and other financial reports\nMonitor, review and assist in day to day accounting functions, including incomes,\u00a0payments, inter-company controls and transactions\nDevelop, maintain, and analyze budgets as well as cash flow forecasts\nSupervise and provide guidance to subordinates on daily operations and help the team in solving work-related issues\nStreamline the accounting workflow and lead the implementation of internal control policies\n\n\u00a0Job Requirements:\n\nBachelor degree in Accounting or other related disciplines\n5 years or above relevant experience, preferably with supervision or management experience\nHands-on experience in handling full sets of accounts independently\nGood accounting software and computer skills; proficient in MS Excel is preferred\nKnowledge of Peachtree Accounting System is a definite advantage\nDetail-oriented with strong sense of accuracy\nSelf-motivated, independent, detail-minded, able to work under pressure and strong sense of responsibility\nImmediate available is highly preferred\n\nInterested parties please complete the standard application form by clicking the\u00a0Apply now\u00a0button. You can also attach your tailored CV and Cover letter with your current and expected salary which we will use to review applications.\n\nIt is Our Company policy to comply with the requirements of the Personal Data (Privacy) Ordinance (Cap. 486) of the Laws of the Hong Kong Special Administrative Region. Any personal data which is collected shall be handled in accordance with this Personal Information Collection Statement (\u201cPICS\u201d).\n\nThe personal data collected from you will be used for purposes relating to your application for employment with the Company. You must ensure that all personal data provided to the Company are accurate, complete and up-to-date. For correction of or access to personal data after submission of the job application or enquiries on recruitment matters, please contact the HR or subject officer as specified in the recruitment advertisement.\n\nWebsite:\u00a0 \u00a0 \u00a0www.sprg.com.hk\u00a0/\u00a0www.sprg.asia\nFacebook:\u00a0\u00a0https://www.facebook.com/SPRGAsia\u00a0/\u00a0https://www.facebook.com/CSR.SPRG", "employment_types": ["Full Time", "Permanent"], "selling_points": ["Degree holder", "3 years' relevant experience", "Qualified member of ACCA / HKICPA or equivalent"], "locations": ["Hung Hom"], "categories": ["Accounting", "Accountant", "Audit", "Others"], "post_time": "2022-01-17T11:26:21Z", "salary": {"currency": null, "max": null, "min": null, "period": null, "term": null}, "salary_visible": false, "title_keywords": ["accountant"], "responsibilities": ["budgets", "financial reports", "policies", "review", "full set of accounts", "monitor", "financial statements", "transactions", "develop", "implementation", "cash flow", "maintain", "payments", "daily operations", "provide guidance", "internal control"], "requirements": {"degrees": ["degree", "bachelor"], "majors": ["related disciplines", "accounting"], "languages": [], "language_level": [], "hard_skills": ["accounting software", "ms excel", "computer skills", "peachtree accounting system"], "soft_skills": ["detail-minded", "self-motivated", "independently", "independent", "sense of responsibility", "detail-oriented", "hands-on", "work under pressure"], "languages_combined": []}, "experience_required": {"duration": ["5 years"], "field": ["management", "relevant experience"]}}, {"job_id": "100003009054750", "location_code": "hk", "company": "NAHC Limited", "job_title": "JUNIOR ACCOUNTANT", "description": "Degree holder in Accounting and qualified member of ACCA / HKICPA or equivalent\nMinimum 3 years' relevant experience in financial and management accounting, preferably with consolidation experience\nAudit experience in sizable audit firm an advantage\nKnowledge in PRC to HK GAAP conversion\nReview full set of accounts, accounting schedule, budget, forecast, financial analysis and management reports\nReview monthly treasury reports of PRC and offshore companies\nPrepare and review audited accounts and management accounts\nHandle Hong Kong Profits Tax computation and CBCR reporting\nAnalytical, self-motivated, detail-oriented and able to meet tight deadlines\nProficient in Oracle and MS Office\nFluent in written and spoken English and Chinese, including Putonghua\n\nWe offer salary and benefits commensurate with qualifications and experience. Please send a full resume with contact number and expected salary to General Manager - Human Resources & Administration, Hutchison Property Management Company Limited, 3/F., One Harbourfront, 18 Tak Fung Street, Hunghom, Kowloon (Please quote reference on envelope) or by clicking \"Apply Now\".\n\nWe are an equal opportunity employer and welcome applications from all qualified candidates. The information provided will be treated in strict confidence and be used only for consideration of your application for relevant/similar post(s).\n\nApplicants not hearing from us within six weeks from the date of advertisement may consider their applications unsuccessful. All personal data of unsuccessful applicants will be destroyed after the recruitment exercise when no longer required.", "employment_types": ["Full Time", "Permanent"], "selling_points": ["Young and dyanmic team culture", "Flexible working hours", "Excellent Career Path"], "locations": ["Not Specified"], "categories": ["Accounting", "Accountant", "Accounting Clerk / Supervisor"], "post_time": "2022-01-17T10:53:27Z", "salary": {"currency": null, "max": null, "min": null, "period": "monthly", "term": null}, "salary_visible": false, "title_keywords": ["junior accountant"], "responsibilities": ["reporting", "management", "tax computation", "review", "full set of accounts", "audit", "budget", "financial analysis", "management reports", "reports", "schedule", "forecast"], "requirements": {"degrees": ["degree holder"], "majors": ["accounting"], "languages": ["putonghua", "english", "chinese"], "language_level": ["fluent"], "hard_skills": ["acca", "financial analysis", "hkicpa", "management reports", "ms office", "oracle"], "soft_skills": ["self-motivated", "meet tight deadlines", "detail-oriented"], "languages_combined": [{"language": "putonghua", "language_level": ["fluent"]}, {"language": "english", "language_level": ["fluent"]}, {"language": "chinese", "language_level": ["fluent"]}]}, "experience_required": {"duration": ["minimum 3 years"], "field": ["management accounting", "consolidation", "audit", "relevant experience", "audit experience", "financial"]}}, {"job_id": "100003009054672", "location_code": "hk", "company": "A.S. Watson Retail (HK) Limited", "job_title": "Accountant (Financial Reporting & Internal Control) - Group Finance", "description": "Our client is a fast-growing eCommerce company. Recently, they are expanding their accounting team to cope with the growth of the business. They are looking for a high-caliber candidate who are attention to details and willing to learn to join their young and dynamic team.\u00a0\n\nResponsibilities\n\nAssist in month-end closing, full set of entity-level accounts, monthly financial reports, and other reports as required by management\nPrepare bank reconciliation and general entries; handling account receivable/ payable and purchase payment cycle on a regular basis\nAssist in annual auditing and tax preparation\nHandle ad-hoc projects as assigned\nRequirements\nDegree Holder in Accounting or Finance related discipline\nDetailed mindset, positive, \u201ccan-do\u201d attitude, and strong interpersonal skills\nDisciplined and proactive approach, demonstrated ability to build positive relationships with peers\nContinuously open to learning with genuine curiosity\nImmediately Available is highly preferred", "employment_types": ["Full Time", "Permanent"], "selling_points": ["Financial Reporting", "Annual Budget, Forecast review and analysis", "Perform internal control assignment"], "locations": ["Shatin Area"], "categories": ["Accounting", "Accountant", "Audit", "Professional Services", "Business Analysis / Data Analysis"], "post_time": "2022-01-17T10:29:25Z", "salary": {"currency": null, "max": null, "min": null, "period": "monthly", "term": null}, "salary_visible": false, "title_keywords": ["accountant"], "responsibilities": ["tax", "financial reports", "management", "bank reconciliation", "purchase", "month-end closing", "reports", "payment", "ad-hoc projects", "auditing"], "requirements": {"degrees": ["degree holder"], "majors": ["finance", "accounting"], "languages": [], "language_level": [], "hard_skills": [], "soft_skills": ["genuine", "learning", "interpersonal skills", "can-do", "proactive", "positive", "detailed"], "languages_combined": []}, "experience_required": {"duration": [], "field": []}}, {"job_id": "100003009045975", "location_code": "hk", "company": "The Core Securities Company Limited", "job_title": "Accounting Officer/Accountant", "description": "Responsibilities:\n\nHandling daily accounting operations including AR/AP, general journal entries, bills and payments, bank reconciliation;\nHandle full set of accounts including bank reconciliation, general ledger, fixed assets register, prepayment, accruals and month-end closing and etc;\nPrepare monthly management accounts with accounting schedules and reconciliations on timely basis, including trust reconciliation against client assets;\nLiaise with external auditor and tax representatives for the preparation of statutory financial reports and tax filing.\nPerform ad-hoc assignments as required\n\nRequirements:\n\nDegree holder in Accounting, Finance or related discipline;\nMinimum 2-3 years accounting experience for the financial services sector;\nHighly independent, self-motivated, enthusiastic, capable to meet deadline and work under pressure\nGood command of written and spoken Chinese, English and Mandarin;\nGood interpersonal and communications skills;\nSelf-motivated, detail oriented, strong sense of responsibility and multi-tasked", "employment_types": ["Full Time", "Permanent"], "selling_points": ["Full Set of Accounts", "Statutory financial reports and tax filing", "Prepare monthly management accounts"], "locations": ["Central"], "categories": ["Accounting", "Accountant", "Accounting Clerk / Supervisor", "Others"], "post_time": "2022-01-13T09:17:28Z", "salary": {"currency": null, "max": null, "min": null, "period": "monthly", "term": null}, "salary_visible": false, "title_keywords": ["accountant", "accounting officer"], "responsibilities": ["ap", "tax", "management", "financial reports", "ar", "schedules", "general ledger", "ad-hoc assignments", "full set of accounts", "tax filing", "daily accounting operations", "bank reconciliation", "reconciliations", "month-end closing", "payments", "journal entries", "liaise with"], "requirements": {"degrees": ["degree holder"], "majors": ["finance", "accounting"], "languages": ["english", "chinese", "mandarin"], "language_level": ["good command"], "hard_skills": [], "soft_skills": ["highly independent", "self-motivated", "capable", "sense of responsibility", "detail oriented", "multi-tasked", "enthusiastic", "interpersonal", "work under pressure"], "languages_combined": [{"language": "english", "language_level": ["good command"]}, {"language": "chinese", "language_level": ["good command"]}, {"language": "mandarin", "language_level": ["good command"]}]}, "experience_required": {"duration": ["minimum 2-3 years"], "field": ["accounting experience", "financial services"]}}, {"job_id": "100003009051736", "location_code": "hk", "company": "Tat Ming Wallpaper Company Limited", "job_title": "Accounting officer \u2013 5day work", "description": "Role Objective / Purpose\n\n\nThe role of Business Analyst is responsible for all accounting and finance functions of IPSOS HK and to ensure proper accounting records are kept for internal and statutory audits.\n\nRole & Responsibilities:\n\nResponsible for monitoring the operational and accounting system\nMonitor and review the budget and actual spending of projects to ensure data integrity\nOversee the daily accounting functions to ensure accounting records are kept in compliance with the group accounting policies.\nMonitor and supervise the month end closing to ensure all management reports are submitted on time and accurate.\nPrepare monthly financial charts/reports for all IPSOS HK divisions.\nCompile various periodic analytical reports (e.g. Contribution Report, Job Summary Report etc.) and hold discussion meeting with divisional heads regularly so as to make them aware of their updated divisional performance.\nCommunicate with Research Departments regularly to understand and provide necessary support to them\nAssist the statutory audit of IPSOS HK to ensure audit deadline is met.\nParticipate in the group internal audits to make sure proper control procedures are in place.\nReview the existing internal control system and make recommendations on the existing work procedures so as to improve the efficiency.\nAssist in the annual budget process to understand the budget components of each division.\nAssist in the set-up of new accounting software to ensure it meets our business requirement.\nProvide support to Chief Financial Officer for ad hoc reporting so as to meet the tight reporting deadlines.\n\n\nPerson specification\n\nQualification\uff1a\n\nBachelor Degree in Accounting or equivalent with minimum 5 years of audit or accounting experience\n\nKnowledge (including general and IPSOS specific knowledge)\uff1a\n\nKnowledge in SAP system is a definite advantage\nAccounting standards and principles.\nRecent computing development especially in accounting software packages.\nKnowledge in market research products e.g. methodology, product type and client type etc. is preferred.\n\nSkill (including technical and people skill)\uff1a\n\nGood communication and interpersonal skills and able to communicate with people from different background and with different seniority.\nGood language skill both verbal and writing.\nBasic grasp of the market research industry.\nGood computer skill especially in Microsoft Excel, Word, and PowerPoint\nGood presentation skill.\n\nOther Requirements\n\nResponsible and able to work independently.\nDedication and good determination to meet deadlines.\n\nWe offer an attractive remuneration package with 5-day work week to the right candidates. Interested parties please send\u00a0resume with current and expected salary to us. All information collected will be used for recruitment purpose only.", "employment_types": ["Part Time"], "selling_points": ["5-Day work week, Double pay & Performance bonus", "Higher Diploma or above in Accounting", "Over 2 years related experience"], "locations": ["Not Specified"], "categories": ["Accounting", "Accountant", "Accounting Clerk / Supervisor", "Others"], "post_time": "2022-01-16T21:51:18Z", "salary": {"currency": null, "max": null, "min": null, "period": "monthly", "term": null}, "salary_visible": false, "title_keywords": ["accounting officer"], "responsibilities": ["software", "data", "budget", "audit", "communication", "accounting policies", "internal control", "make recommendations", "month end closing", "control", "ad hoc", "compliance", "monitor", "reports", "report", "reporting", "provide support", "review", "monitoring", "procedures", "audits", "communicate with", "market research", "management reports", "daily accounting"], "requirements": {"degrees": [], "majors": [], "languages": [], "language_level": [], "hard_skills": [], "soft_skills": ["work independently", "meet deadlines", "responsible"], "languages_combined": []}, "experience_required": {"duration": [], "field": []}}, {"job_id": "100003009053192", "location_code": "hk", "company": "The Lok Sin Tong Benevolent Society, Kowloon", "job_title": "Accounting Officer \u6703\u8a08\u4e3b\u4efb", "description": "Job Responsibilities:\n\nTake full accounting responsibilities.\nPerform month end closing, prepare schedules, financial reports and analysis\nLook after daily cashflow and plan fund transfer\nMaintain payment schedule, and ensure accurate settlement and confirmation procedures for Treasury deals (loan interests, deposits, SWAP settlements, etc.)\nHandle intercompany fund transfer and reconcile loan balance with subsidiaries\nReview payments, expense claims and petty cash\nLiaise with auditors in respect of internal/external audits\nResponsible for all-round HR functions including recruitment, compensation & benefits, employees relations etc.\nHandle monthly payroll calculation, MPF and tax returns\nReview and update various companies procedures and regulations to ensure compliance with legal requirements\nMaintain employee attendance and leave records\nManage general office administration duties, e.g. office supplies replenishment, office facilities and equipment management, staff's expenses claim checking etc.\nPerform ad-hoc duties as required\n\nJob Requirements:\n\nTertiary education or above in Accounting or related discipline\nHolder of ACCA or other relevant qualifications\nMinimum 3 years' experience for Asst Manager post, preferably in IT/Media industry.\u00a0 Lesser experience will be considered for officer post.\nWell-versed in HK Taxation and Employment Ordinance, MPF, taxation related ordinances and\u00a0other business related legislation\nGood command of written and spoken English and Chinese\nFamiliar with MS Office application including Word, Excel and Chinese word processing\nWell-organized, self-motivated,\u00a0detail-minded and able to work independently and under pressure\nImmediate available preferred", "employment_types": ["Full Time"], "selling_points": [], "locations": ["Kowloon City"], "categories": ["Accounting", "Accountant", "Accounting Clerk / Supervisor", "Others"], "post_time": "2022-01-17T06:22:45Z", "salary": {"currency": null, "max": null, "min": null, "period": "monthly", "term": null}, "salary_visible": false, "title_keywords": ["accounting officer"], "responsibilities": ["month end closing", "financial reports", "analysis", "review", "procedures", "audits", "payment", "maintain", "payments", "schedule", "plan", "liaise with", "prepare schedules"], "requirements": {"degrees": [], "majors": [], "languages": [], "language_level": [], "hard_skills": [], "soft_skills": [], "languages_combined": []}, "experience_required": {"duration": [], "field": []}}, {"job_id": "100003009051730", "location_code": "hk", "company": "Whampoa Property Management Limited", "job_title": "ASSISTANT ACCOUNTANT [Ref. WPML-AA]", "description": "Job Duty\uff1a\u00a0\nHandle full set of accounts and month end closing\nPrepare monthly statement and breakdown\nMaintain good accounting and operation control\nMonitor other staff\u00a0accounting duties\nAssist in annual audit\n\nRequirements:\n\nBachelor degree holder in Accounting\n3 years\u2019 relevant working experience\nProficient in MS applications both in English and Chinese (including Excel & Word)\nExperienced in accounting software such as Flex System\nAuditing experience will be an advantage\nHave initiative, detail-minded, responsible, integrity and good interpersonal skills\n\nApplications with full resume and expected salary should be\u00a0email to\u00a0us.\n\n(All applications will be treated in strict confidence and used solely for the purpose of recruitment)", "employment_types": ["Full Time", "Permanent"], "selling_points": ["Degree holder", "Minimum 4 years' relevant working experience", "Student member of ACCA / HKICPA"], "locations": ["Tsing Yi"], "categories": ["Accounting", "Accountant", "Accounting Clerk / Supervisor", "Others"], "post_time": "2022-01-16T21:51:14Z", "salary": {"currency": null, "max": null, "min": null, "period": null, "term": null}, "salary_visible": false, "title_keywords": ["assistant accountant"], "responsibilities": ["month end closing", "control", "software", "annual audit", "full set of accounts", "monitor", "maintain", "recruitment", "accounting duties", "auditing"], "requirements": {"degrees": ["bachelor degree holder"], "majors": ["accounting"], "languages": ["english", "chinese"], "language_level": ["proficient"], "hard_skills": ["excel", "ms applications", "accounting software", "word", "flex system"], "soft_skills": ["detail-minded", "confidence", "responsible", "integrity", "interpersonal skills", "initiative"], "languages_combined": [{"language": "english", "language_level": ["proficient"]}, {"language": "chinese", "language_level": ["proficient"]}]}, "experience_required": {"duration": ["3 years"], "field": ["relevant working experience"]}}, {"job_id": "100003009054347", "location_code": "hk", "company": "Wu Wong Consultants Limited", "job_title": "Senior Accounting Officer", "description": "A quality manufacturer of semiconductor packaging solutions\n\n\u00a0Position: Assistant Accountant\n\n\u00a0Job Requirements:\n\n1)\u00a0\u00a0\u00a0 Degree holder in Accounting\n\n2)\u00a0\u00a0\u00a0 At least three years\u2019 working experience\n\n3)\u00a0\u00a0\u00a0 Good PC knowledge\n\n4)\u00a0\u00a0\u00a0 Able to work independently", "employment_types": ["Full Time"], "selling_points": [], "locations": ["Yau Tsim Mong Area"], "categories": ["Accounting", "Accountant", "Accounting Clerk / Supervisor"], "post_time": "2022-01-17T09:13:39Z", "salary": {"currency": null, "max": null, "min": null, "period": "monthly", "term": null}, "salary_visible": false, "title_keywords": ["senior accounting officer"], "responsibilities": ["quality"], "requirements": {"degrees": ["degree holder"], "majors": ["accounting"], "languages": [], "language_level": [], "hard_skills": ["pc knowledge"], "soft_skills": ["work independently"], "languages_combined": []}, "experience_required": {"duration": ["at least three years"], "field": []}}, {"job_id": "100003009052261", "location_code": "hk", "company": "China Mobile International Limited", "job_title": "Assistant Treasury Manager/ Senior Accountant, Revenue & Treasury (CMIJD-1111-RTFINHK)", "description": "We\u00a0are a\u00a0well-established\u00a0property\u00a0leasing,\u00a0management and investment company located in Wanchai-Admiralty area, now inviting an experienced candidate for the position of\u00a0Assistant Accountant/Senior Accounts Assistant.\n\nResponsibilities:\n\nHandle full sets of account independently;\nHandle daily accounting works;\nBook keeping and accounting data entry;\nAssist in month-end closing and ad hoc duties assigned by supervisors;\nAssist in management of accounting filing system.\n\n\nRequirements:\u00a0\n\nHigher Diploma in accounting or related disciplines;\nAt least 5 years accounting experience;\nProficiency in MS office and Flex system is a must;\nAble to meet reporting deadlines and work under pressure;\nInitiative, well organized and self-motivated\nExperience in system implementation/change\n\nWe offer an attractive remuneration package and excellent career prospects to the right candidate.\u00a0 Please send full resume, current and expected salary, contact number and the availability to us for interview.\n\nPersonal data collected will be used for recruitment purpose only.", "employment_types": ["Full Time", "Permanent"], "selling_points": ["Plan & modernize treasury process and policy", "Manage HK & Overseas bank accounts & platforms", "Formulate & implement hedging plans & execution"], "locations": ["Kwai Hing"], "categories": ["Accounting", "Accountant", "Finance / Accounting Manager", "Treasurer"], "post_time": "2022-01-17T02:36:06Z", "salary": {"currency": null, "max": null, "min": null, "period": "monthly", "term": null}, "salary_visible": false, "title_keywords": ["manager", "senior accountant", "assistant"], "responsibilities": ["ad hoc duties", "management", "data entry", "month-end closing", "daily accounting"], "requirements": {"degrees": ["diploma"], "majors": ["related disciplines", "accounting"], "languages": [], "language_level": [], "hard_skills": ["system implementation", "flex system", "ms office"], "soft_skills": ["self-motivated", "well organized", "initiative", "work under pressure"], "languages_combined": []}, "experience_required": {"duration": ["at least 5 years"], "field": ["accounting experience"]}}, {"job_id": "100003009052270", "location_code": "hk", "company": "Lubuds F&B Group", "job_title": "Assistant Accountant (LUBUDS AXIS)", "description": "Job Responsibilities:\n\nManage bank account opening/ closing/ signature updates for Hong Kong and overseas entities\nResponsible for online banking platforms setting\nHandle bank transactions including loans, LC, guarantees\nPlan and modernize treasury process and policy\nResponsible for liaison with internal and external auditors\nEnsure the compliance of Treasury policy and SOX\nAssist in formulating and implementing hedging plans and its execution\nHandle ad hoc projects assigned\n\nJob Requirements:\n\nDegree holder in Accounting, Finance or related disciplines\nQualified Accountant under ACCA/HKICPA\nAt least 5 years relevant treasury management experience, preferably from sizeable multinational corporations or financial institutions\nSolid experience in cash management and foreign exchange\nGood knowledge in hedging, risk management, financial products and derivatives Knowledge in accounting for derivatives and hedging preferred\nProficiency in excel VBA, Powerpoint, Word (Chinese & English),\nPositive, self-motivated, good analytical skills and communication skills\nGood interpersonal skills\nGood command of spoken and written Chinese and English, proficiency in Putonghua is a MUST\nCandidates with less experience would be considered as Senior Accountant\n\nInterested parties please send your full resume with current & expected salary\u00a0by clicking \"Apply Now\".\n\nAll personal data provided will be used for consideration of your job application only.\n\nManage bank account opening/closing/signature updates for Hong Kong and overseas entities", "employment_types": ["Full Time", "Permanent"], "selling_points": [], "locations": ["Southern Area"], "categories": ["Accounting", "Accountant", "Accounting Clerk / Supervisor", "Finance / Accounting Manager"], "post_time": "2022-01-17T02:37:33Z", "salary": {"currency": null, "max": null, "min": null, "period": "monthly", "term": null}, "salary_visible": false, "title_keywords": ["assistant accountant"], "responsibilities": ["account opening", "compliance", "transactions", "ad hoc projects", "plan", "banking", "plans", "external auditors"], "requirements": {"degrees": ["degree holder"], "majors": ["related disciplines", "finance", "accounting"], "languages": ["putonghua", "english", "chinese"], "language_level": ["proficiency", "good command"], "hard_skills": ["excel", "acca", "vba", "word", "powerpoint", "analytical skills", "hkicpa", "exchange"], "soft_skills": ["communication skills", "self-motivated", "analytical skills", "interpersonal skills", "positive"], "languages_combined": [{"language": "putonghua", "language_level": ["proficiency", "good command"]}, {"language": "english", "language_level": ["good command"]}, {"language": "chinese", "language_level": ["proficiency", "good command"]}]}, "experience_required": {"duration": ["at least 5 years"], "field": ["management", "financial institutions", "senior accountant"]}}, {"job_id": "100003009051628", "location_code": "hk", "company": "China Telecom Global Limited", "job_title": "Senior Finance and Accounting Officer", "description": "Responsibilities\n\n\nHandle full set of accounts including but not limited to the preparation of vouchers, accounting schedules, bank reconciliation, and various accounting reports\nMonitor daily cash flow\nIssue quotation and invoice to company\u2019s client\nLiaise with Contractor and Sub-contractor regarding the payment issue\nClosely work with project team on daily accounting operations\nOther ad hoc assignments as assigned\n\nJob Requirements\n\n\nPossess Higher Diploma in Accounting or Finance or LCCI Level 3 certificate\nAt least 5 years of working experience in accounting field is required\nWorking experience in Interior Design Company is highly preferred\nProficiency in MS Excel & Word, familiar with accounting systems\nAn effective team player,\u00a0positive attitude and customer service oriented\nSelf-motivated and willing to learn\nGood command of written and spoken English and Chinese\nImmediate available is highly preferred\nExperienced candidates may be considered as Accountant\n\nBenefits\n\n\n5-Day work week\n2 days Birthday Leave\nPaid Sick Leave\nStaff Discount\n\nWe provide coaching and guidance on professional development and excellent career opportunities to our team members. Interested parties,\u00a0please send full resume with your current and expected salary by \u201cApply Now\u201d.\n\n\nInformation collected will be treated in strict confidence and used for recruitment purposes only.\u00a0 Only suitable candidates will be notified.", "employment_types": ["Full Time", "Permanent"], "selling_points": ["Exp. of accounting & financial reporting", "Exp. in telecom industry will be a plus", "Competitive salary package"], "locations": ["Wan Chai"], "categories": ["Accounting", "Accountant", "Others"], "post_time": "2022-01-16T15:32:24Z", "salary": {"currency": null, "max": null, "min": null, "period": "monthly", "term": null}, "salary_visible": false, "title_keywords": ["accounting officer"], "responsibilities": ["schedules", "invoice", "full set of accounts", "monitor", "bank reconciliation", "quotation", "daily accounting operations", "cash flow", "payment", "reports", "ad hoc assignments", "liaise with"], "requirements": {"degrees": ["certificate", "diploma"], "majors": ["finance", "accounting"], "languages": ["english", "chinese"], "language_level": ["good command"], "hard_skills": ["accounting systems", "ms excel", "word"], "soft_skills": ["self-motivated", "customer service oriented", "willing to learn", "positive attitude", "team player"], "languages_combined": [{"language": "english", "language_level": ["good command"]}, {"language": "chinese", "language_level": ["good command"]}]}, "experience_required": {"duration": ["at least 5 years"], "field": ["accounting", "design"]}}, {"job_id": "100003009054675", "location_code": "hk", "company": "Polygroup Holdings Limited", "job_title": "Assistant Accountant / Accounting Clerk (Non-group)", "description": "Key Responsibilities\uff1a\n\nMaintain the strong knowledge of the latest accounting regulation development and corporate reporting requirements\nAssist the processing in the preparation of month end journal entries and produce reliable and auditable information for disclosure to external auditors and the parent company\nRegularly provide internal training, issue policy guidance and coordinate with regionals team among various jurisdictions\nParticipate in ad hoc corporate projects\n\nJob Requirements\uff1a\n\nDegree or above in Accounting, preferable HKICPA, ACCA, CICPA member or equivalent\nOver 3\u00a0years of relevant accounting experience,\u00a0 with relevant Chinese-funded overseas headquarter enterprise or auditing background in external audit firms is preferred\nWork experience\u00a0in telecom industry will be a plus\nFamiliar with Chinese Accounting Standards and International Accounting Standards will be a plus\nExcellent command of both written and spoken English and Chinese\nCandidate with much experience will be considered as senior position\u00a0\n\nWe offer 5 days work, competitive salary package and attractive career development opportunities to the right candidate.\u00a0\n\nInterested parties please email your full resume with your current & expected salary to us.\n\nApplicants not invited for interview within 3 months may assume their applications unsuccessful.\u00a0\n\nIf you are interested in other job opportunities, please check with below career website.\n\nPersonal data collected would be used for recruitment purpose only.\u00a0", "employment_types": ["Full Time", "Permanent"], "selling_points": ["Dynamic and energetic work environment", "5 day work & high stability", "good benefit"], "locations": ["Admiralty"], "categories": ["Accounting", "Accountant"], "post_time": "2022-01-17T10:30:46Z", "salary": {"currency": null, "max": null, "min": null, "period": "monthly", "term": null}, "salary_visible": false, "title_keywords": ["accounting clerk", "assistant accountant"], "responsibilities": ["guidance", "reporting", "ad hoc", "coordinate with", "maintain", "journal entries", "external auditors"], "requirements": {"degrees": ["degree or above"], "majors": ["accounting"], "languages": ["english", "chinese"], "language_level": ["excellent"], "hard_skills": ["acca", "plus", "hkicpa"], "soft_skills": [], "languages_combined": [{"language": "english", "language_level": ["excellent"]}, {"language": "chinese", "language_level": ["excellent"]}]}, "experience_required": {"duration": ["3 years"], "field": ["accounting experience", "audit"]}}, {"job_id": "100003009054699", "location_code": "hk", "company": "The Hong Kong Jockey Club", "job_title": "Financial Accountant (General Ledger) (6-month contract)", "description": "Job Descriptions\n\nHandle daily payment issues & monitor Group\u2019s daily bank status\nHandle full set of book-keeping & month-end closing\nHandle simple tax and audit matters to ensure in compliance with local statutory requirements\nLiaise with auditors and different business partners\nHandle ad-hoc tasks assigned by management\n\nRequirements\n\nDegree holder in Accounting / Finance or related disciplines\nMinimum 3 years relevant working experience\nGood command in spoken and written of English and Chinese (Putonghua and Cantonese)\nGood team player, energetic, responsible, high initiative, detail-minded, eager to learn, well-organized and team spirit\nCandidate with more experience will be considered as Assistant Accountant\nImmediate available is highly preferred", "employment_types": ["Contract"], "selling_points": ["conduct any job-related researches when necessary", "Involve in the monthly and year-end book closing", "Maintain updates of financial reporting standards"], "locations": ["Causeway Bay"], "categories": ["Accounting", "Accountant", "Accounting Clerk / Supervisor", "Banking / Finance", "Corporate Finance"], "post_time": "2022-01-17T10:38:18Z", "salary": {"currency": null, "max": null, "min": null, "period": null, "term": null}, "salary_visible": false, "title_keywords": ["accountant"], "responsibilities": ["tax", "management", "ad-hoc tasks", "compliance", "monitor", "audit", "statutory requirements", "payment", "month-end closing", "book-keeping", "liaise with"], "requirements": {"degrees": ["degree holder"], "majors": ["related disciplines", "finance", "accounting"], "languages": ["cantonese", "putonghua", "english", "chinese"], "language_level": ["good command"], "hard_skills": [], "soft_skills": ["detail-minded", "good team player", "team spirit", "responsible", "well-organized", "eager to learn", "energetic", "initiative"], "languages_combined": [{"language": "cantonese", "language_level": ["good command"]}, {"language": "putonghua", "language_level": ["good command"]}, {"language": "english", "language_level": ["good command"]}, {"language": "chinese", "language_level": ["good command"]}]}, "experience_required": {"duration": ["minimum 3 years"], "field": ["relevant working experience"]}}, {"job_id": "100003009054880", "location_code": "hk", "company": "Ogilvy & Mather (Hong Kong) Private Ltd", "job_title": "Regional Senior Accountant (MNC)", "description": "The jobs:\n\nAccounts receivable section, Submit ageing report regularly and communication with oversea\nHandle intercompany transactions and transfer\nPrepare monthly financial reports including P&L, Balance Sheet and Cash Flow\nResponsible for banking account reconciliation\n\nRequirements:\n\n\nHKCEE/HKDSE or above\nAccounting with LCCI intermediate or above\n3-4 years or above of relevant experience\nGood PC knowledge eg. MS Word and Excel; knowledge of Flex System is a plus\nWell-organized, independent, proactive with good interpersonal skills\nGood command of English and Chinese\nImmediate available is preferred", "employment_types": ["Full Time", "Permanent"], "selling_points": ["Degree in Accounting", "Finalist/Qualified accountant with 3 yrs acct. exp", "Knowledge of SOX compliance is an advantage"], "locations": ["Quarry Bay"], "categories": ["Accounting", "Accountant", "Accounting Clerk / Supervisor", "Others"], "post_time": "2022-01-17T12:23:10Z", "salary": {"currency": null, "max": null, "min": null, "period": "monthly", "term": null}, "salary_visible": false, "title_keywords": ["senior accountant"], "responsibilities": ["financial reports", "balance sheet", "accounts receivable", "transactions", "p&l", "communication", "cash flow", "banking", "report"], "requirements": {"degrees": ["hkdse"], "majors": [], "languages": ["english", "chinese"], "language_level": ["good command"], "hard_skills": ["excel", "plus", "flex system", "pc knowledge", "ms word"], "soft_skills": ["independent", "proactive", "well-organized", "interpersonal skills"], "languages_combined": [{"language": "english", "language_level": ["good command"]}, {"language": "chinese", "language_level": ["good command"]}]}, "experience_required": {"duration": ["3-4 years"], "field": ["relevant experience"]}}, {"job_id": "100003009054880", "location_code": "hk", "company": "Ogilvy & Mather (Hong Kong) Private Ltd", "job_title": "Regional Senior Accountant (MNC)", "description": "We are looking for a suitable candidate to join our Regional Accounting Team based in Hong Kong.\n\nCore Responsibilities:\n\nResponsible for month end closing\nManage intercompany transactions with Asia Pacific operating companies\nAssist in quarterly forecast planning & budgeting\nProvide support for annual audit and tax related matters\nHandle ad-hoc assignments\n\nKey Requirements:\n\nDegree in Accounting\nFinalist/Qualified accountant with 3 years of accounting experience or above\nPreferable with audit experience\nKnowledge of SOX compliance is an advantage\nDetail-oriented, good analytical and communications skills\nProficient in Word, Excel and knowledge in computerized environment\nFluency in English and Chinese, both written and spoken\nAble to work under pressure and manage multiple assignments\nHardworking and willing to work overtime\nImmediate available is preferable\nLess experience will be considered as Accountant\n\nWe offer 5-day work with attractive salary, fringe benefits and good career prospects to the right candidates.\n\nAll information will be treated in the strictest confidence and used for recruitment purposes. Only short-listed candidates will be contacted for interview.", "employment_types": ["Full Time", "Permanent"], "selling_points": ["Degree in Accounting", "Finalist/Qualified accountant with 3 yrs acct. exp", "Knowledge of SOX compliance is an advantage"], "locations": ["Quarry Bay"], "categories": ["Accounting", "Accountant", "Accounting Clerk / Supervisor", "Others"], "post_time": "2022-01-17T12:23:10Z", "salary": {"currency": null, "max": null, "min": null, "period": "monthly", "term": null}, "salary_visible": false, "title_keywords": ["senior accountant"], "responsibilities": ["tax", "month end closing", "provide support", "annual audit", "budgeting", "ad-hoc assignments", "transactions", "forecast", "planning"], "requirements": {"degrees": ["degree"], "majors": ["accounting"], "languages": ["english", "chinese"], "language_level": ["fluency"], "hard_skills": ["excel", "word"], "soft_skills": ["work under pressure", "work overtime", "hardworking", "detail-oriented"], "languages_combined": [{"language": "english", "language_level": ["fluency"]}, {"language": "chinese", "language_level": ["fluency"]}]}, "experience_required": {"duration": ["3 years"], "field": ["accounting experience", "audit experience"]}}, {"job_id": "100003009052232", "location_code": "hk", "company": "Kai Fu Property Services Co Ltd", "job_title": "Accounting Assistant/ Assistant Accounting Officer", "description": "Our future success depends on the diverse talent and performance of dedicated employees. We now call for applications to fill this position which is under the Corporate Services Department in the organization structure of HKFA. Reporting to the Finance Manager (functional report to the Senior Accounting Officer), the appointee will be responsible for assisting in all round Finance activities. The main duties are listed below:\n\n\nJob Descriptions\nHandle daily payment transaction\nHandle monthly autopay function for helpers\nPrepare monthly statement for Hong Kong Premier League football clubs\nAssist in management report preparation including expenses accrual, bank reconciliation, journal preparation and other relevant tasks\nAssist in administering the fixed assets and inventory record kept by the Finance Section\nAssist in general ledger update and housekeeping\nClerical and administrative support for the Finance Section\nUndertaking ad hoc projects as assigned\nQualifications and Experience\nForm 5 or above with 5 passes in Hong Kong Certificate of Education Examination (HKCEE) / Hong Kong Diploma of Secondary Education (HKDSE) (including English, Chinese and Mathematics) & London Chamber of Commerce and Industry (LCCI) higher level\n1 year relevant working experience is preferred,\u00a0fresh graduate will also be considered\nStrong communication and analytical skills\nSelf-motivated, independent and detail-oriented\nProficient in MS Office Application\nFluent in English and Cantonese\nKnowledge in Flex System is a plus\nThe successful candidate will be offered on a contract term employment. Starting salary will be commensurate with qualifications and experience. Our employee benefits include Group Medical and Life Insurance to the right candidate.\u00a0\nDeadline: 30 January 2022\nPlease ensure that you have explored the following official link which lists the relevant instructions before making an application:\nwww.hkfa.com/en/load_page/82\n\nThe information provided by the applicants will be treated in strict confidence and will only be used for the purpose of considering your employment application.\nPLEASE DO NOT USE \u201cAPPLY NOW\u201d FUNCTION.", "employment_types": ["Full Time", "Permanent"], "selling_points": [], "locations": ["Kowloon Bay"], "categories": ["Accounting", "Accountant", "Accounting Clerk / Supervisor", "Others"], "post_time": "2022-01-17T02:31:28Z", "salary": {"currency": null, "max": null, "min": null, "period": "monthly", "term": null}, "salary_visible": false, "title_keywords": ["accounting assistant", "assistant accounting officer"], "responsibilities": ["reporting", "administrative support", "housekeeping", "general ledger", "expenses", "bank reconciliation", "inventory record", "communication", "payment", "ad hoc projects", "accrual", "autopay", "management report", "report"], "requirements": {"degrees": ["fresh graduate", "secondary education", "certificate", "diploma", "hkdse", "form 5 or above"], "majors": ["mathematics"], "languages": ["cantonese", "english", "chinese"], "language_level": ["fluent"], "hard_skills": ["plus", "ms office", "flex system", "analytical skills"], "soft_skills": ["self-motivated", "independent", "responsible", "analytical skills", "communication", "diverse", "detail-oriented"], "languages_combined": [{"language": "cantonese", "language_level": ["fluent"]}, {"language": "english", "language_level": ["fluent"]}, {"language": "chinese", "language_level": []}]}, "experience_required": {"duration": ["1 year"], "field": ["relevant working experience"]}}, {"job_id": "100003009052820", "location_code": "hk", "company": "The Hong Kong Football Association Ltd", "job_title": "Accounting Assistant", "description": "We invite an aspiring, energetic committed candidate to join us. Your duties will include:\n\nHandle full set accounts\nPrepare monthly management and financial reports\nCo-ordinate the monthly stock count and ensure an accurate inventory record\nAnalyzing and providing timely, useful and quality financial information and participating in monthly business reviews\nSupervising Junior staffs in daily accounting duties\nPerform ad-hoc duties assigned by supervisor\n\nWe are looking for following eligible person:\n\nDiploma or above in Accounting\nAt least 3 years solid experience in accounting and financial reporting, more experience and qualification will be considered as Accountant\nProactive with excellent interpersonal, organizational & communication skills\nAble to work under pressure, self-motivated, responsible and detail minded\nProficiency in MS Office, especially Excel\nFluency in both written and spoken English and Chinese\nImmediately available\nWe\u00a0Offer:\n12 days annual leave\nBirthday leave\nMedical and dental benefit\nStaff purchases discount\nClear career development path\nMany others\u2026", "employment_types": ["Full Time", "Contract"], "selling_points": [], "locations": ["Mong Kok"], "categories": ["Accounting", "Accountant", "Accounting Clerk / Supervisor", "Others"], "post_time": "2022-01-17T04:09:51Z", "salary": {"currency": null, "max": null, "min": null, "period": "monthly", "term": null}, "salary_visible": false, "title_keywords": ["accounting assistant"], "responsibilities": ["management", "supervising", "financial reports", "quality", "inventory record", "communication", "financial reporting", "ad-hoc duties", "daily accounting", "work under pressure"], "requirements": {"degrees": ["diploma or above"], "majors": ["accounting"], "languages": ["english", "chinese"], "language_level": ["fluency"], "hard_skills": ["excel", "ms office"], "soft_skills": ["communication skills", "self-motivated", "proactive", "accurate", "responsible", "organizational", "timely", "committed", "ad-hoc duties", "energetic", "interpersonal", "work under pressure"], "languages_combined": [{"language": "english", "language_level": ["fluency"]}, {"language": "chinese", "language_level": ["fluency"]}]}, "experience_required": {"duration": ["at least 3 years"], "field": ["accounting", "financial"]}}, {"job_id": "100003009049877", "location_code": "hk", "company": "BioCycle (Hong Kong) Limited", "job_title": "Assistant Accountant / Accountant", "description": "Job Responsibilities:\n\nResponsible daily accounting operation and administrative matters;\nPrepare bank reconciliations monthly;\nPrepare month-end & year-end documents;\nPrepare auditing documents to auditor annually:\nMaintain efficient filing of accounting records;\nResponsible stock management;\nProvide support to ad hoc tasks as assigned.\nRequirements:\n\nForm 5 or DSE graduate with LCCI Level 2 or above (fresh graduated may be considered);\nPrefer 2 -3 years relevant accounting & administration experience;\nKnowledge in DacEasy / MYOB system will be preferable;\nFamiliar with EXCEL and MS Office;\nTeam player, pro-active, willing to meet challenge and learn attitude;\nGood command in spoken and written Cantonese, English and Mandarin;\nImmediate available would be highly preferred.\n\n\u00a0We offer 5-day work with attractive salary and fringe benefits to the right candidate.\n\n\u00a0Please send your full resume with availability, current & expected salary to HR Department.", "employment_types": ["Full Time", "Permanent"], "selling_points": [], "locations": ["Wong Tai Sin Area"], "categories": ["Accounting", "Accountant", "Accounting Clerk / Supervisor", "Others"], "post_time": "2022-01-14T09:22:50Z", "salary": {"currency": null, "max": null, "min": null, "period": "monthly", "term": null}, "salary_visible": false, "title_keywords": ["accountant", "assistant accountant"], "responsibilities": ["year-end", "provide support", "stock management", "ad hoc tasks", "month-end", "bank reconciliations", "maintain", "daily accounting", "auditing"], "requirements": {"degrees": ["form 5", "dse"], "majors": [], "languages": ["cantonese", "english", "mandarin"], "language_level": ["good command"], "hard_skills": ["excel", "myob", "ms office"], "soft_skills": ["team player", "pro-active"], "languages_combined": [{"language": "cantonese", "language_level": ["good command"]}, {"language": "english", "language_level": ["good command"]}, {"language": "mandarin", "language_level": ["good command"]}]}, "experience_required": {"duration": ["2 -3 years"], "field": ["accounting", "administration"]}}, {"job_id": "100003009044750", "location_code": "hk", "company": "Jones Lang LaSalle Management Services Ltd", "job_title": "Senior Accountant/ Accountant \u2013 GL", "description": "Job Duty:\u00a0 \u00a0\n\n(Assistant Accountant post)\n-\u00a0 \u00a0 Handle bank transactions\n-\u00a0\u00a0\u00a0 Assist in month-end closing of entities, group cash management, preparation of various reports\n- \u00a0\u00a0 Perform daily accounting operation and fulfill company\u2019s regulating requirement\n-\u00a0\u00a0\u00a0 Handle ad hoc assignments\n\n(Accountant post)\n-\u00a0 \u00a0 Handle daily accounting operations\n-\u00a0 \u00a0 Prepare monthly group financial and management reports\n-\u00a0 \u00a0 Assist in preparation of various reports\n-\u00a0 \u00a0 Coordinate with external auditor and tax consultant for year-end audit and tax computation\n-\u00a0 \u00a0 Handle ad hoc assignments\n\nRequirement:\n\n(Assistant Accountant post)\n-\u00a0 \u00a0 1 year\u00a0accounting experience is preferred, fresh graduate may also be considered\n-\u00a0\u00a0\u00a0 Diploma or above, major in Accounting, finance or related discipline\n\n(Accountant post)\n-\u00a0 \u00a0 At least 4 years of\u00a0accounting or audit\u00a0\n-\u00a0 \u00a0\u00a0Group consolidation experience is preferred\n-\u00a0 \u00a0 Member of ACCA / HKICPA or equivalent\n-\u00a0 \u00a0 Degree holder in Accounting\u00a0or related discipline is preferred\n-\u00a0 \u00a0 Experience in \u4e45\u5176 format report of PRC State Owned Enterprise is a plus\n\n(Two posts)\n-\u00a0 \u00a0 Good command of English & Chinese (include Cantonese & Mandarin)\n-\u00a0 \u00a0 Solid skills in MS office applications and Chinese word processing\n-\u00a0 \u00a0 Proactive team player with strong sense of responsibility, detail-oriented, good interpersonal & communication skills.\n\nWe Offer\u00a0 fringe benefits including double pay, medical insurance & 5 days work to the right candidates.\n\nInterested applicants, please apply with full resume stating the position, current and expected salary in Ms Word format.\u00a0For more information, please contact us at 25892037.\n\n(All\u00a0Personal data collected will be used for recruitment purpose only)", "employment_types": ["Full Time", "Permanent"], "selling_points": ["Higher Diploma or above", "Accounts Receivable / General Ledger", "5 years' relevant experience"], "locations": ["Quarry Bay"], "categories": ["Accounting", "Accountant", "Accounting Clerk / Supervisor", "Property / Real Estate", "Others"], "post_time": "2022-01-15T03:49:18Z", "salary": {"currency": null, "max": null, "min": null, "period": null, "term": null}, "salary_visible": false, "title_keywords": ["accountant", "senior accountant"], "responsibilities": ["tax", "year-end", "management", "tax computation", "coordinate with", "daily accounting operations", "transactions", "audit", "communication", "management reports", "month-end closing", "reports", "ad hoc assignments", "daily accounting", "report"], "requirements": {"degrees": ["diploma or above", "fresh graduate", "degree holder"], "majors": ["finance", "accounting"], "languages": ["cantonese", "english", "chinese", "mandarin"], "language_level": ["good command"], "hard_skills": ["acca", "plus", "chinese word processing", "hkicpa", "management reports", "ms office"], "soft_skills": ["communication skills", "sense of responsibility", "detail-oriented", "team player", "proactive", "interpersonal"], "languages_combined": [{"language": "cantonese", "language_level": ["good command"]}, {"language": "english", "language_level": ["good command"]}, {"language": "chinese", "language_level": ["good command"]}, {"language": "mandarin", "language_level": ["good command"]}]}, "experience_required": {"duration": ["1 year"], "field": ["accounting experience", "consolidation"]}}, {"job_id": "100003009046631", "location_code": "hk", "company": "Shougang Holding (Hong Kong) Limited", "job_title": "Assistant Accountant /Accountant", "description": "\n\u8077\u8cac :\u8655\u7406\u5168\u76e4\u6703\u8a08\u5e33\u76ee\uff1b\u8ca0\u8cac\u65e5\u5e38\u6703\u8a08\u4e8b\u52d9\uff0c\u4f8b\u5982AR/AP\uff1b\u8ddf\u9032\u5ba2\u6236\u672a\u4ed8\u6b3e\u9805\uff1b\u88fd\u4f5c\u6bcf\u6708\u8ca1\u52d9\u5831\u544a\uff1b\u5354\u52a9\u5e74\u5ea6\u5be9\u8a08\u53ca\u5831\u7a05\u4e8b\u5b9c\uff1b\u5354\u52a9\u8fa6\u516c\u5ba4\u884c\u653f\u5de5\u4f5c\u53ca\u5176\u4ed6\u6307\u6d3e\u5de5\u4f5c\n\n\u8cc7\u6b77 :\u4e2d\u4e94\u7a0b\u5ea6; 1\u5e74\u7d93\u9a57; \u826f\u597d\u7cb5\u8a9e; \u4e00\u822c\u82f1\u8a9e; \u61c2\u8b80\u5beb\u4e2d\u6587; \u7565\u61c2\u8b80\u5beb\u82f1\u6587; \u61c2MS Word; \u61c2MS Excel; \u6301\u6709LCC\u4e2d\u7d1a\u8b49\u66f8; \u61c2\u82f1\u6587\u6253\u5b57; \u61c2\u4e2d\u6587\u6253\u5b57\n\n\u5f85\u9047 :\u6bcf\u6708$18,000 - $20,000, \u661f\u671f\u4e00\u81f3\u4e94: \u4e0a\u53489\u6642\u81f3\u4e0b\u53486\u6642\u53ca\u661f\u671f\u516d: \u4e0a\u53489\u6642\u81f3\u4e0b\u53481\u6642, \u6bcf\u9031\u5de5\u4f5c5\u5929\u534a\n\n\u7533\u8acb\u9808\u77e5 :\u6c42\u8077\u8005\u53ef\u96fb\u90f5(Apply Now)\u5c65\u6b77\u8868\u7d66\u96c5\u6f54\u6e05\u6f54\u5de5\u7a0b\u6709\u9650\u516c\u53f8\u3002\u5982\u8981\u7d22\u53d6\u6536\u96c6\u500b\u4eba\u8cc7\u6599\u8072\u660e, \u8acb\u8207\u5f35\u5148\u751f(Email)\u806f\u7d61\u3002\n\n", "employment_types": ["Permanent"], "selling_points": [], "locations": ["Wan Chai"], "categories": ["Accounting", "Accountant", "Accounting Clerk / Supervisor"], "post_time": "2022-01-13T18:09:05Z", "salary": {"currency": null, "max": null, "min": null, "period": "monthly", "term": null}, "salary_visible": false, "title_keywords": ["accountant", "assistant accountant"], "responsibilities": [], "requirements": {"degrees": [], "majors": [], "languages": [], "language_level": [], "hard_skills": ["excel", "word"], "soft_skills": [], "languages_combined": []}, "experience_required": {"duration": [], "field": []}}, {"job_id": "100003009053889", "location_code": "hk", "company": "E & K Cleaning Services Limited", "job_title": "\u6703\u8a08\u4e3b\u4efb", "description": "Job Duties\n\nPrepare monthly\u00a0financial reports, management\u00a0reports and analysis reports\nAssist in group reporting, budgeting, forecast\u00a0and analyze financial data\nLiaise with bankers, tax consultants, external auditors for statutory audit and tax filing matters\nSupervise and review the works of subordinates\u00a0\nPerform ad hoc assignments\n\nRequirements\n\nDegree holder in Accounting or Finance\nMember of HKICPA or equivalent professional qualifications\nMinimum 4-6 years of auditing and commercial experience in listed companies, preferably with experience gained from Big 4 CPA firms\nStrong sense of internal control\nMature, self-motivated and independent\nGood analytical and problem solving skills\nGood command of both written and spoken English and Chinese including Mandarin\nKnowledge in application of Sun System / Infor Q&A would be an advantage\nProficient in MS Office applications\n\nWe offer attractive remuneration to successful candidates. To apply, please send your full resume stating date available, present and expected salary by mail to Group Human Resources & Administration Controller, eSun Holdings Limited, 11/F Lai Sun Commercial Centre, 680 Cheung Sha Wan Road, Kowloon or click the button \"APPLY NOW\" shown below to send your application via email.\n\nWebsite: www.laisun.com\n\nPersonal data provided in the employment applications will be treated in strict confidence and used only for recruitment purpose by the Lai Sun Group Companies. All unsuccessful applications will be destroyed upon completion of the process.\n\n\nA member of the Lai Sun Group", "employment_types": ["Full Time"], "selling_points": [], "locations": ["Tsuen Wan Area"], "categories": ["Accounting", "Accountant", "Accounting Clerk / Supervisor", "Audit"], "post_time": "2022-01-17T07:42:15Z", "salary": {"currency": null, "max": null, "min": null, "period": "monthly", "term": null}, "salary_visible": false, "title_keywords": [], "responsibilities": ["tax", "reporting", "financial reports", "data", "analysis reports", "budgeting", "tax filing", "review", "audit", "management reports", "ad hoc assignments", "forecast", "liaise with", "external auditors"], "requirements": {"degrees": ["degree holder"], "majors": ["finance", "accounting"], "languages": ["english", "chinese", "mandarin"], "language_level": ["good command"], "hard_skills": ["professional qualifications", "big 4 cpa firms", "hkicpa", "problem solving skills", "ms office", "internal control"], "soft_skills": ["analytical and problem solving skills", "self-motivated", "independent", "mature"], "languages_combined": [{"language": "english", "language_level": ["good command"]}, {"language": "chinese", "language_level": ["good command"]}, {"language": "mandarin", "language_level": ["good command"]}]}, "experience_required": {"duration": ["minimum 4-6 years"], "field": ["commercial", "big 4"]}}, {"job_id": "100003009047500", "location_code": "hk", "company": "eSun Holdings Limited", "job_title": "Senior Accountant", "description": "Responsibilities:\n\n\nSupervise a small team for providing comprehensive accounting services and support\nReview full set of accounts including accounts receivable, accounts payable, general ledger and month-end reports\nPrepare consolidated financial statements & management schedules, annual budget, regular forecasts and analysis reports\nPrepare cash flow projection\nHandle tax computation and related matters\nAssist in annual audit and tax computation\nHandle ad hoc tasks as assigned\nRequirements:\n\nDegree in Accounting/Finance or related disciplines\nQualified accountant with at least 6 years\u2019 relevant experience gained from international professional accounting firm or sizeable commercial organizations\nSound accounting and taxation knowledge, familiar with latest accounting standards\nCapable of handling full set of financial books and management reports independently\nExperience in property development industry will be an advantage\nCan work under tight deadlines and pressure\nEnjoy teamwork, highly organized, detail-oriented and with good analytical, interpersonal & communication skills\nStrong in Excel, Word and knowledge of Oracle or other ERP systems\nGood command of written English is essential\nWe offer ample opportunities for career development and attractive salary package commensurate with experience and qualifications. \u00a0Interested parties please apply with full resume via\u00a0\u201cAPPLY NOW\u201d.\u00a0\n\n\nFor further information on Wheelock Properties (Hong Kong) Limited, please visit our website:\u00a0www.wheelockpropertieshk.com.\n\nWe are an equal opportunities employer and invite applications from all qualified candidates. Personal data collected will be treated in strict confidence and handled by authorized persons for recruitment-related purposes only within The Wheelock & Wharf Group. Applicants not hearing from us within 2 months may consider their applications unsuccessful.\u00a0", "employment_types": ["Full Time", "Permanent"], "selling_points": ["Prepare monthly financial & management reports", "Assist in group reporting, budgeting & forecast", "Maintain proper internal control"], "locations": ["Lai Chi Kok"], "categories": ["Accounting", "Accountant", "Audit", "Financial Analyst"], "post_time": "2022-01-14T03:20:32Z", "salary": {"currency": null, "max": null, "min": null, "period": "monthly", "term": null}, "salary_visible": false, "title_keywords": ["senior accountant"], "responsibilities": ["management", "tax computation", "accounts receivable", "annual audit", "schedules", "general ledger", "analysis reports", "review", "full set of accounts", "month-end", "financial statements", "budget", "ad hoc tasks", "cash flow", "reports", "accounts payable"], "requirements": {"degrees": ["degree"], "majors": ["related disciplines", "finance", "accounting"], "languages": ["english"], "language_level": ["good command"], "hard_skills": ["excel", "erp systems", "word", "management reports", "oracle"], "soft_skills": ["organized", "communication skills", "independently", "capable", "teamwork", "detail-oriented", "interpersonal"], "languages_combined": [{"language": "english", "language_level": ["good command"]}]}, "experience_required": {"duration": ["at least 6 years"], "field": ["commercial", "development", "accounting", "relevant experience"]}}, {"job_id": "100003009046490", "location_code": "hk", "company": "HKIA Services Holdings Limited", "job_title": "Accountant", "description": "We are a Hong Kong based company professional hygiene solution suppliers and commercial dishwasher and hygiene commercial products manufacturer. To cope with our business expansion, we are now inviting dynamic professional to join our professional team.\n\nKey Responsibilities\n\nReport to the Finance Manager\uff1b\nOverseeing the daily operations especially accounts payable and inventory of the Finance department and month end process\uff1b\nAssist in monitoring financial system and database ;\nAssist in preparing financial statements.\n\n\u00a0The ideal candidate should process the following qualities:\n\nDegree holder in accounting discipline and a semi-qualified accountant\uff1b\nA least 4 years of working experience, of which 2 years are gained from audit firms\uff1b\nFamiliar with the accounting standards\uff1b\nFamiliar with ERP and database\uff1b\nGood analytical skills\uff1b\nExcellent command in spoken & written English, Mandarin and Cantonese\nAttractive remuneration package\n\nCompetitive salary, performance bonus, medical insurance, child subsidy and education subsidy\nInterested candidates, please apply with a cover letter and your updated CV with current and expected salary and availability by clicking\u00a0\u201cApply Now\u201d. The information provided will be treated in strict confidence and used solely for recruitment purpose. All applicants' information will be destroyed after 12 months.\n\nFor more information about us, please visit our website at\u00a0http://www.champion-chem.com/en/", "employment_types": ["Full Time", "Permanent"], "selling_points": ["Attractive Package", "Accountant", "Finance"], "locations": ["Airport Area"], "categories": ["Accounting", "Accountant"], "post_time": "2022-01-13T11:59:39Z", "salary": {"currency": null, "max": null, "min": null, "period": "monthly", "term": null}, "salary_visible": false, "title_keywords": ["accountant"], "responsibilities": ["financial system", "inventory", "monitoring", "audit", "financial statements", "hygiene", "daily operations", "database", "insurance", "accounts payable", "report"], "requirements": {"degrees": ["degree holder"], "majors": ["accounting"], "languages": ["cantonese", "english", "mandarin"], "language_level": ["excellent"], "hard_skills": ["dynamic", "erp", "analytical skills"], "soft_skills": ["dynamic", "analytical skills", "ideal"], "languages_combined": [{"language": "cantonese", "language_level": ["excellent"]}, {"language": "english", "language_level": ["excellent"]}, {"language": "mandarin", "language_level": ["excellent"]}]}, "experience_required": {"duration": ["least 4 years", "2 years"], "field": ["audit"]}}, {"job_id": "100003009043459", "location_code": "hk", "company": "Alpha Calibration (Hong Kong) Limited", "job_title": "Accountant", "description": "Responsibilities:\n\nResponsible for general accounting duties such as A/P, A/R, journal, and bank reconciliation\nTo prepare payment and receipt vouchers\nTo issue invoices, cheques, and receipts\nData input of accounting entries\nEnsure data input in a timely and accurate manner\nAssist in preparing accounting schedule and daily worker payroll\nPerform other ad hoc duties when required\n\nRequirements:\n\nl\u00a0\u00a0 Diploma or above in Accounting\n\nl\u00a0\u00a0 Holder of LCCI Intermediate or above\n\nl\u00a0\u00a0 Minimum 2 years\u2019 accounting experience\n\nl\u00a0\u00a0 Able to work independently, and Initiative-taking\n\nl\u00a0\u00a0 Experience in Peachtree is preferred\n\nl\u00a0\u00a0 Familiar with MS Word and Excel\n\n\nInterested candidates please send your full resume with expected salary by clicking 'Apply Now'\n\n(Personal data collected will be used for recruitment purpose only.)", "employment_types": ["Full Time", "Permanent"], "selling_points": [], "locations": ["Central"], "categories": ["Accounting", "Accountant", "Banking / Finance", "Financial Services", "Professional Services", "Legal & Compliance"], "post_time": "2022-01-13T02:06:56Z", "salary": {"currency": null, "max": null, "min": null, "period": "monthly", "term": null}, "salary_visible": false, "title_keywords": ["accountant"], "responsibilities": ["ad hoc duties", "invoices", "receipts", "bank reconciliation", "data input", "payment", "cheques", "general accounting duties", "schedule", "payroll"], "requirements": {"degrees": ["diploma or above"], "majors": ["accounting"], "languages": [], "language_level": [], "hard_skills": ["excel", "peachtree", "ms word"], "soft_skills": ["work independently", "initiative"], "languages_combined": []}, "experience_required": {"duration": ["minimum 2 years"], "field": ["accounting experience"]}}, {"job_id": "100003009025183", "location_code": "hk", "company": "Konway Corporation Limited", "job_title": "Accounting & Admin Officer/ Assistant Accountant (5 Days Work)", "description": "What you\u2019ll be doing?\u00a0\n\nPreparing daily bookkeeping, stocktaking, and accounting duties.\nPreparing month-end accounting submissions to accountant.\nAssisting in cash settlement and recording sales performance.\nMonitoring account receivables and payables.\nPreparing and issuing quotations and invoices to customers.\nAnalysing business performance and reporting it to the management.\nPerforming general administrative and clerical duties.\nPreparing salary slips and MPF submission.\nAd-hoc duties as assigned.\u00a0\n\nWho are we looking for?\u00a0\n\nDegree in Accounting/Finance/Business Administration or related disciplines\nResponsible, self-motivated, organized, pleasant and hard-working. Sensitivity in dealing with confidential matters\nKnowledge in accounting software, Sage Peachtree, and knowledge in POS system preferable\nStrong in computer skills including Excel, Words, PowerPoint, Chinese input\nChinese/English/Mandarin\u00a0\nWe Offer:\n\nDiscretionary bonus\nStaff discounts\nCompany medical allowance\n5-day work (9:45am \u2013 6:45pm; Mon-Fri)\nExcellent career path\n$19000 - $25000/month (negotiable)\n\nInterested parties, please send your full resume with expect salary by clicking APPLY NOW.\u00a0\u00a0\n", "employment_types": ["Full Time"], "selling_points": ["Degree in Accounting/Finance", "5-day work, medical allowance, Discretionary bonus", "Excellent career path"], "locations": ["Not Specified"], "categories": ["Accounting", "Accountant", "Accounting Clerk / Supervisor", "Admin & HR", "Clerical / Admin Staff"], "post_time": "2022-01-12T23:26:05Z", "salary": {"currency": null, "max": null, "min": null, "period": "monthly", "term": null}, "salary_visible": false, "title_keywords": ["admin", "accounting", "officer", "assistant accountant"], "responsibilities": ["reporting", "management", "invoices", "mpf", "software", "sales performance", "monitoring", "month-end", "ad-hoc duties", "accounting duties", "administration"], "requirements": {"degrees": ["degree"], "majors": ["related disciplines", "finance", "accounting", "business administration"], "languages": ["english", "chinese", "mandarin"], "language_level": [], "hard_skills": ["chinese input", "excel", "words", "accounting software", "sage peachtree", "pos system", "powerpoint", "computer skills"], "soft_skills": ["organized", "self-motivated", "responsible", "sensitivity", "pleasant", "hard-working", "ad-hoc duties"], "languages_combined": [{"language": "english", "language_level": []}, {"language": "chinese", "language_level": []}, {"language": "mandarin", "language_level": []}]}, "experience_required": {"duration": [], "field": []}}, {"job_id": "100003009049015", "location_code": "hk", "company": "PHM Contracting Co. Limited", "job_title": "Accounting Assistant", "description": "Responsibilities\nHandle full set of company\u2019s accounts including AR, AP, GL, month end closing and financial reports\nResponsible for daily accounting operations, including preparation of data input, invoices, payments, vouchers, filing\nResponsible for monthly reports and cash management\nResponsible for year-end audit, schedule, Liaise with auditors independent\nResponsible inter-company reconciliation\nReview PRC companies account books\nLiaise with bankers for bank KYC and other issue\nOthers related duties\nRequirements:\nLCC 3rd level or above\nMinimum 5 years relevant experience\nGood in written and spoken English and Chinese\nProficient in MS Office - Excel, Word\nMature, independent, good communication skills\nExperience in SAGE 50 accounting software is preferable\nQualified parties, please email your resume, including personal particulars, employment history, present and expected salary via \"Apply Now\" (Data collected are strictly used for recruitment purpose only)", "employment_types": ["Full Time"], "selling_points": ["Responsible for full set of accounts", "Able to work independently, Initiative-taking", "Experience in construction field is an advantage"], "locations": ["Kwun Tong"], "categories": ["Accounting", "Accountant", "Accounting Clerk / Supervisor", "Others"], "post_time": "2022-01-17T03:55:33Z", "salary": {"currency": null, "max": null, "min": null, "period": "monthly", "term": null}, "salary_visible": false, "title_keywords": ["accounting assistant"], "responsibilities": ["ap", "year-end", "month end closing", "financial reports", "management", "ar", "invoices", "monthly reports", "review", "daily accounting operations", "data input", "audit", "payments", "schedule", "kyc", "liaise with"], "requirements": {"degrees": [], "majors": [], "languages": ["english", "chinese"], "language_level": ["good"], "hard_skills": ["excel", "accounting software", "word", "lcc", "ms office"], "soft_skills": ["communication skills", "independent", "mature"], "languages_combined": [{"language": "english", "language_level": ["good"]}, {"language": "chinese", "language_level": ["good"]}]}, "experience_required": {"duration": ["minimum 5 years"], "field": ["accounting", "relevant experience"]}}, {"job_id": "100003009050595", "location_code": "hk", "company": "Standard Motor Company Limited", "job_title": "Accounting officer / Accountant", "description": "Job Description\n\nHandle full set of accounts\nKeep records of financial transactions and ensure accuracy of data\nPerform month-end closing including journal entry postings, provisions and accruals etc.\nPrepare period-end schedules and monthly reconciliation\nLiaise with various departments and external parties\nHandle other ad hoc assignments as required\n\nRequirements\n\n\nDiploma in accounting or F.5 or above with LCCI Certificate\nAt least 3 years relevant experience in accounting, experience in construction industry is advantage\nStrong skills in MS Office is a must,experience in MYOB is advantage\nAble to work independently, under pressure and meet tight reporting deadlines\nGood command in English and Chinese\nImmediate available is an advantage\nApplicants with no current and expected salaries may not be considered\nWorking Location: Hung Hom\n5.5 days work\nInterested parties, please send your application with full resume and expected salary by clicking \"Apply Now\".\u00a0\u00a0", "employment_types": ["Full Time", "Permanent"], "selling_points": [], "locations": ["Not Specified"], "categories": ["Accounting", "Accountant", "Accounting Clerk / Supervisor", "Others"], "post_time": "2022-01-14T10:52:30Z", "salary": {"currency": null, "max": null, "min": null, "period": "monthly", "term": null}, "salary_visible": false, "title_keywords": ["accountant", "accounting officer"], "responsibilities": ["data", "schedules", "full set of accounts", "external parties", "transactions", "liaise with various departments", "month-end closing", "ad hoc assignments"], "requirements": {"degrees": ["certificate", "diploma"], "majors": ["accounting"], "languages": ["english", "chinese"], "language_level": ["good command"], "hard_skills": ["no", "myob", "ms office"], "soft_skills": ["work independently", "under pressure"], "languages_combined": [{"language": "english", "language_level": ["good command"]}, {"language": "chinese", "language_level": ["good command"]}]}, "experience_required": {"duration": ["at least 3 years"], "field": ["accounting", "relevant experience", "construction industry"]}}, {"job_id": "100003009051143", "location_code": "hk", "company": "Red Apple Furniture HK Limited", "job_title": "Senior Accounting Officer", "description": "To cope with our business growth and expansion, we are currently looking for an individual with high caliber to join our team.\n\nJob Responsibilities:\n\nAssist in overseeing all aspects of finance and accounting operations of group companies in multi-franchise motor and motor insurance\u00a0businesses in HK\nPrepare hands-on financial reporting and analysis for business line / management review\nLead the finance team to troubleshoot all month-end closing matters and ensure timely completion of monthly / quarterly\u00a0group reporting submission\nPrepare the annual budget and rolling forecast\nCo-ordinate and support the operational units through ascertaining their needs and recommending solutions to business and financial problems\nMonitor and ensure compliance with corporate policies and guidelines and statutory requirements\nHandle statutory audit and prepare audited financial statements\nReview and drive the enhancement of internal control procedure as well as streamline the financial processes and participate in system enhancements\nLiaise and work closely with finance service center team in Kuala Lumpur, operational units, external auditors and relevant professionals\nParticipate in ad hoc projects as assigned\n\nRequirements:\u00a0\n\nDegree holder in Finance or Accounting discipline\nQualified HKICPA or equivalent internationally recognized accounting qualification\nMinimum 8 years of working experience in accounting field and auditing field\u00a0gained in sizable organization\u00a0with some managerial experience\nSubsidiary level reporting experience in matrix organization or experience in motor industry would be a definite advantage\nStrong financial analysis mindset with business sense\nWilling to work overtime (weekend/ public holiday overtime work for monthly closing with compensation leave)\nProactive, detail-oriented\u00a0with good analytical and problem-solving capabilities\nAbility to work independently with minimal supervision\nWilling to take challenges and able to multitask in a demanding and fast-paced environment and meet tight reporting timeline\nGood interpersonal skills and able to communicate effectively with all levels\nGood command of both spoken and written English and Chinese\nImmediately availability is highly preferred\nWork location: Tsuen Wan (near MTR)\n\nWe offer attractive remuneration package, 5-day work week, competitive fringe benefits and excellent career development opportunity to the right candidate. Interested parties please send your full resume quoting job reference number with present salary, expected salary and\u00a0available date via e-mail to\u00a0ghr-recruitment.sdms @simedarby.com.hk\u00a0\n\nFor more information about us, please visit our\u00a0Website.\nFollow us on\u00a0our\u00a0LinkedIn\u00a0and stay tuned!\n\nAll information provided by applicants will be treated in strict confidence and used for recruitment purpose only.", "employment_types": ["Full Time", "Permanent"], "selling_points": ["Handle Full Set of Accounts", "At least 5 years related experience", "LCCI / ACCA or equivalent professional body"], "locations": ["Shatin Area"], "categories": ["Accounting", "Accountant", "Accounting Clerk / Supervisor"], "post_time": "2022-01-15T03:27:33Z", "salary": {"currency": null, "max": null, "min": null, "period": "monthly", "term": null}, "salary_visible": false, "title_keywords": ["senior accounting officer"], "responsibilities": ["liaise", "operations", "budget", "audit", "financial statements", "statutory requirements", "troubleshoot", "management review", "internal control", "monitor", "finance team", "reporting", "review", "rolling forecast", "guidelines", "policies", "analysis", "ensure compliance", "month-end closing", "ad hoc projects", "financial reporting", "insurance", "external auditors"], "requirements": {"degrees": ["degree holder"], "majors": ["finance", "accounting"], "languages": ["english", "chinese"], "language_level": ["good command"], "hard_skills": ["financial analysis", "problem-solving", "hkicpa"], "soft_skills": ["work overtime", "work independently", "business sense", "fast-paced environment", "problem-solving", "detail-oriented", "multitask", "overtime work", "interpersonal skills", "proactive"], "languages_combined": [{"language": "english", "language_level": ["good command"]}, {"language": "chinese", "language_level": ["good command"]}]}, "experience_required": {"duration": ["minimum 8 years"], "field": ["sizable organization", "managerial", "accounting"]}}, {"job_id": "100003009048324", "location_code": "hk", "company": "Novation Solutions Limited", "job_title": "Assistant Accountant", "description": "\n\u8981\u6c42\uff1a\n\u2022 \u5354\u52a9\u7d44\u7e54\u516c\u53f8\u5e74\u5ea6\u9810\u7b97\u7684\u7de8\u5236\u548c\u5b63\u5ea6\u3001\u6708\u5ea6\u9810\u7b97\u8a08\u5283; \u8ca0\u8cac\u65e5\u5e38\u6703\u8a08\u5165\u8cec\u53ca\u7de8\u5236\u5404\u985e\u6703\u8a08\u5831\u8868; \u5354\u52a9\u7de8\u5236\u4e0a\u5e02\u516c\u53f8\u5e74\u5831\uff0c\u534a\u5e74\u5831\u544a\u53ca\u76f8\u95dc\u5831\u8868; \u5176\u5b83\u65e5\u5e38\u8ca1\u52d9\u5de5\u4f5c\u3002\n\u2022 \u5c08\u4e0a\u6559\u80b2\uff1a\u5927\u5b78\u672c\u79d1\u53ca\u4ee5\u4e0a\u5b78\u6b77\uff0c\u4e3b\u4fee\u6703\u8a08, CPA\u8cc7\u683c\u6216\u8005\u6301\u6709\u5167\u5730\u6703\u8a08\u5e2b\u8b49\u512a\u5148\u8003\u616e, \u826f\u597d\u7cb5\u8a9e; \u826f\u597d\u666e\u901a\u8a71; \u826f\u597d\u82f1\u8a9e; 3-5\u5e74\u4ee5\u4e0a\u4e0a\u5e02\u516c\u53f8\u76f8\u95dc\u5de5\u4f5c\u7d93\u9a57;\u00a0\n\u85aa\u91d1\uff1a \u9762\u8b70\n\u00a0\n\u5f85\u9047\uff1a \u9280\u884c\u5047\u671f\uff0c\u91ab\u7642\u798f\u5229\uff0c\u6709\u82b1\u7d05\uff0cOT\u88dc\u52a9\uff0c\u6649\u6607\u6a5f\u6703\uff0c\u65c5\u904a\u734e\u8cde\u7b49\n\u6709\u610f\u8005\u8acb\u96fb\u90f5\u81f3 [via\u00a0 Apply Now ]", "employment_types": ["Full Time", "Permanent"], "selling_points": ["General Accounting & Accounts Payable", "5 day work, medical, AL,", "3-5 years working experience"], "locations": ["Ngau Tau Kok"], "categories": ["Accounting", "Accountant"], "post_time": "2022-01-14T06:14:26Z", "salary": {"currency": null, "max": null, "min": null, "period": "monthly", "term": null}, "salary_visible": false, "title_keywords": ["assistant accountant"], "responsibilities": [], "requirements": {"degrees": [], "majors": [], "languages": [], "language_level": [], "hard_skills": [], "soft_skills": [], "languages_combined": []}, "experience_required": {"duration": [], "field": []}}, {"job_id": "100003009042679", "location_code": "hk", "company": "Honestar Technologies Company Limited", "job_title": "SENIOR ACCOUNT CLERK", "description": "\u00a0Responsibilities:\n\nResponsible for daily accounting operations and month end closing;\nPrepare management reports, financial analysis and monthly consolidation reporting packages;\nAssist in budget & forecast and audit & tax issues;\nPerform ad hoc projects / assignments as required\n\n\n\u00a0Requirements:\n\nBachelor in Accounting with professional accounting qualification;\nMinimum 5 years solid accounting experience, preferably in freight forwarding industry;\nProficient in accounting systems (preferably Oracle) and Microsoft Office;\nGood command of written and spoken English and Chinese, Mandarin is an advantage;\nSelf-motivated, detail-minded, good team player and able to work under pressure;\nImmediate availability is highly preferred;\nCandidates with lower qualification / less experience will be considered as Assistant Accountant.\n\nInterested parties please send\u00a0your detailed resume and expected salary to\u00a0Human Resources and Administration Department, Hutchison Logistics (HK) Limited\u00a0(i) by fax to\u00a03544-3530;\u00a0\u00a0or (ii) by email. Please visit our website http://www.hutchisonlogistics.com/\u00a0for further details.\u00a0\n\nWe are an equal opportunity employer and welcome applications from all qualified candidates. The information provided will be treated in strict confidence and used only for consideration of application for relevant /similar positions within the Hutchison Group of Companies.\u00a0Applicants not invited for interview in 6 weeks after job posting may consider their application unsuccessful and your personal data will be destroyed after a period of 6 months.", "employment_types": ["Full Time"], "selling_points": ["\u9280\u884c\u5047\u671f\uff0c\u91ab\u7642\u798f\u5229", "OT\u88dc\u52a9", "\u6649\u6607\u6a5f\u6703\uff0c\u65c5\u904a\u734e\u8cde\u7b49"], "locations": ["Kwai Hing"], "categories": ["Accounting", "Accountant", "Accounting Clerk / Supervisor"], "post_time": "2022-01-16T21:50:13Z", "salary": {"currency": null, "max": null, "min": null, "period": "monthly", "term": null}, "salary_visible": false, "title_keywords": ["senior account clerk"], "responsibilities": ["tax", "reporting", "month end closing", "budget", "daily accounting operations", "audit", "financial analysis", "management reports", "ad hoc projects", "forecast"], "requirements": {"degrees": ["bachelor"], "majors": ["accounting"], "languages": ["english", "chinese", "mandarin"], "language_level": ["advantage", "good command"], "hard_skills": ["accounting systems", "microsoft office", "oracle"], "soft_skills": ["detail-minded", "good team player", "self-motivated", "work under pressure"], "languages_combined": [{"language": "english", "language_level": ["advantage", "good command"]}, {"language": "chinese", "language_level": ["advantage", "good command"]}, {"language": "mandarin", "language_level": ["advantage", "good command"]}]}, "experience_required": {"duration": ["minimum 5 years"], "field": ["accounting experience"]}}, {"job_id": "100003009044943", "location_code": "hk", "company": "Hutchison Logistics (HK) Limited", "job_title": "Accountant ( 5-Day Work Week )", "description": "Responsibilities1. Handle daily payment to the bank's accounts and affairs\n2. Prepare receipt, payment and journal vouchers, cheques and bank transfer and bank reconciliation\n3. Posting and reconciling Petty Cash\n4. Preparation of monthly budget cashflow\n5. Handle ad-hoc assignment as requiredRequirements1. Form 7 and with LCC Higher or similar qualification\n2. At least\u00a03\u00a0years experience in AP, AR\n3. Proficiency in MS Excel,\u00a0MS Word\n4. Good communication skill in English and\u00a0Chinese\n5. Strong sense of responsibility, high accuracy, well-organized, hard working and under pressure\n6. Immediate available is highly desired", "employment_types": ["Full Time", "Permanent"], "selling_points": [], "locations": ["Kwai Tsing Area"], "categories": ["Accounting", "Accountant"], "post_time": "2022-01-13T06:42:04Z", "salary": {"currency": null, "max": null, "min": null, "period": "monthly", "term": null}, "salary_visible": false, "title_keywords": ["accountant"], "responsibilities": ["ad-hoc", "journal vouchers", "ap", "ar", "budget", "bank reconciliation", "communication", "payment", "cheques"], "requirements": {"degrees": [], "majors": [], "languages": ["english", "chinese"], "language_level": ["good"], "hard_skills": ["ap", "ar", "ms excel", "lcc", "ms word"], "soft_skills": ["under pressure", "sense of responsibility", "hard working", "communication skill", "well-organized"], "languages_combined": [{"language": "english", "language_level": ["good"]}, {"language": "chinese", "language_level": ["good"]}]}, "experience_required": {"duration": ["at least 3 years"], "field": []}}, {"job_id": "100003009044691", "location_code": "hk", "company": "Aussco Hong Kong Limited", "job_title": "Accountant/Assistant Accountant", "description": "Responsibilities:\n\nResponsible for handling daily accounting matters, month-end closing & internal control\nClose liaison with business units and other departments on budget, forecast and cost control\nPrepare financial reports, schedules, reconciliation & perform financial analysis\nPerform any ad hoc tasks as assigned\n\nRequirements:\n\nDegree in Accountancy, Finance or similar discipline\nProfessional qualifications are preferred\nMinimum 4 years\u2019 relevant experience with background in construction / engineering industry is an advantage\nProficiency in Microsoft office and applications; well versed in Excel, VBA knowledge/ experience is highly preferred\nKnowledge in ERP and experience in Microsoft AX is an advantage\nGood communication skills, able to work and interface well with personnel at various levels\nProactive, independent, committed and with strong sense of responsibility to meet tight deadlines\nProficient in both written and spoken English and Chinese\nLess experience can be considered as Assistant Accountant\n\nPlease click the Apply Now button to send your full resume stating relevant job reference, present and expected salary and availability.\n\nPersonal data collected will be treated in strict confidence and used for recruitment related purposes only.", "employment_types": ["Part Time", "Temporary"], "selling_points": ["accounting", "accounts clerk", "finance clerk"], "locations": ["Kwun Tong"], "categories": ["Accounting", "Accountant", "Accounting Clerk / Supervisor", "Admin & HR", "Clerical / Admin Staff"], "post_time": "2022-01-13T05:27:57Z", "salary": {"currency": null, "max": null, "min": null, "period": "hourly", "term": null}, "salary_visible": false, "title_keywords": ["accountant", "assistant accountant"], "responsibilities": ["financial reports", "schedules", "budget", "ad hoc tasks", "financial analysis", "month-end closing", "forecast", "cost control", "daily accounting", "internal control"], "requirements": {"degrees": ["degree"], "majors": ["finance", "accountancy"], "languages": ["english", "chinese"], "language_level": ["proficient"], "hard_skills": ["excel", "vba", "microsoft office", "professional qualifications", "erp"], "soft_skills": ["communication skills", "meet tight deadlines", "confidence", "independent", "sense of responsibility", "committed", "proactive"], "languages_combined": [{"language": "english", "language_level": ["proficient"]}, {"language": "chinese", "language_level": ["proficient"]}]}, "experience_required": {"duration": ["minimum 4 years"], "field": ["relevant experience", "construction", "engineering"]}}, {"job_id": "100003009050140", "location_code": "hk", "company": "ATAL Engineering Ltd", "job_title": "Accountant (REF: FIN/A)", "description": "Responsibilities:\n\nAnalyzing monthly and quarterly management reports of various subsidiaries located in Hong Kong, Singapore and PRC, and preparing GAAP adjustments for consolidation purpose;\nAssist in quarterly group consolidation, semi-annual and annual results announcement in Singapore Stock Exchange, and Annual Report preparation work;\nParticipate in annual budgeting and cash flow forecasting process and ad-hoc assignments;\nLiaise with auditors in connection with annual audit process.\n\nRequirements:\n\nDegree holder in accounting\u00a0or related disciplines;\nMember of professional accounting bodies or equivalent;\nMinimum 4 years' relevant working experience or audit experience (preferably gained from sizable CPA firm);\nExposure in the PRC accounting and tax regulations is an advantage;\nHardworking, meticulous, able to work well under pressure and to meet tight reporting deadlines;\nStrong analytical skill & problem solving skill with proactive attitude and able to work independently are required;\nProficiency in Cantonese, English and Mandarin;\nImmediate available is preferred;\nTravelling to PRC is NOT required.\n\nWorking on the headquarter level in Hong Kong (Admiralty Office), we offer 5 days work and attractive remuneration package to right candidate.\u00a0\u00a0Interested parties please email your full resume with availability, current and expected salary to\u00a0us.", "employment_types": ["Full Time", "Permanent"], "selling_points": ["financial analysis", "consolidation", "financial reports"], "locations": ["North Point"], "categories": ["Accounting", "Accountant"], "post_time": "2022-01-15T03:50:51Z", "salary": {"currency": null, "max": null, "min": null, "period": "monthly", "term": null}, "salary_visible": false, "title_keywords": ["accountant"], "responsibilities": ["annual audit", "annual budgeting", "ad-hoc assignments", "management reports", "cash flow", "liaise with", "forecasting", "report"], "requirements": {"degrees": ["degree holder"], "majors": ["related disciplines", "accounting"], "languages": ["cantonese", "english", "mandarin"], "language_level": ["proficiency"], "hard_skills": ["problem solving", "cpa", "analytical skill", "prc accounting"], "soft_skills": ["meticulous", "analytical skill", "work independently", "under pressure", "problem solving skill", "proactive", "hardworking"], "languages_combined": [{"language": "cantonese", "language_level": ["proficiency"]}, {"language": "english", "language_level": ["proficiency"]}, {"language": "mandarin", "language_level": ["proficiency"]}]}, "experience_required": {"duration": ["minimum 4 years"], "field": ["audit experience", "cpa firm", "relevant working experience"]}}, {"job_id": "100003009045678", "location_code": "hk", "company": "Yanlord Land Group Limited", "job_title": "SENIOR ACCOUNTANT / ACCOUNTANT (5-Day Work)", "description": "Reporting to Senior Manager, Accounting and Tax, you will lead a small team to manage Internal Control and Treasury functions, coordinate internal and external audits and to ensure proper internal controls are in place.\n\nResponsibilities:\n\nInternal Control\n\nReview internal control self-assessments to ensure compliance with Group\u2019s policy and local requirement at all times\nPerform operational and financial review to identify areas of improvement\nProvide feasible recommendation and initiate new measures to enhance process efficiency, internal control, risk management, corporate governance and cost saving\nHandle external audit, internal audit and other compliance activities\n\nTreasury\n\nManage account payable, fixed asset and treasury functions\nReview daily payment and treasury work performed by subordinates and shared service centre\nCollaborate with various Departments to implement corporate initiatives and projects\n\nRequirements:\n\nQualified accountant with at least 3-year post qualification working experience\nMinimum 6 years\u2019 solid experience in external audit, internal audit, internal control or related areas, with at least 2 years in commercial sector\nExposure in payment and treasury is an advantage but not mandatory\nFamiliar with accounting standards, taxation laws and Companies Ordinance\nStrong leadership with excellent influencing, communication and presentation skills\nExcellent analytical and problem solving skills with strong business acumen\nExcellent command of spoken and written English and Chinese\nProficient PC skills, knowledge in SAP is an advantage\n\nPersonal Information Collection Statement pertaining to Recruitment\n\nDHL Express (Hong Kong) Limited / DHL Aviation (Hong Kong) Limited (\u201cDHL\u201d) is committed to protecting and respecting your privacy in accordance with the Personal Data (Privacy) Ordinance of Hong Kong (the \u201cOrdinance\u201d) and DHL\u2019s Personal Data Protection Policy (the \u201cPolicy\u201d) at\u00a0https://www.dhl.com/hk-en/home/footer/local-privacy-notice.html\n\nBy proceeding to respond to this recruitment advertisement, you consent that we may use, retain, process, transfer or otherwise handle the personal data that we collect from you for recruitment,\u00a0 application processing, assessment and communication purposes (including any other purposes directly related thereto) in accordance with the Policy.\n\nAll personal data of unsuccessful applicants will be retained for future recruitment purposes for a period of not more than two (2) years after which such data will be destroyed.\n\nYou have the right at any time to make a data access or correction request concerning your personal data held by us. In addition, you may request us to delete your personal data that is no longer required for the relevant purposes which you have given consent. Should you wish to exercise such rights or have any question in relation to your personal data or the Policy, please contact our Human Resources Division in writing.", "employment_types": ["Full Time", "Permanent"], "selling_points": ["Member of Professional Accounting Bodies", "AL (14-18 Days), B-day/Marriage/Exam Leaves", "Double Pay, Medical Insurance"], "locations": ["Admiralty"], "categories": ["Accounting", "Accountant", "Accounting Clerk / Supervisor", "Others"], "post_time": "2022-01-13T08:20:12Z", "salary": {"currency": null, "max": null, "min": null, "period": "monthly", "term": null}, "salary_visible": false, "title_keywords": ["accountant", "senior accountant"], "responsibilities": ["collaborate with", "management", "cost", "internal audit", "review", "compliance", "audit", "ensure compliance", "payment", "internal control"], "requirements": {"degrees": [], "majors": [], "languages": ["english", "chinese"], "language_level": ["excellent"], "hard_skills": ["no", "sap", "processing", "html", "make", "companies ordinance", "problem solving skills", "pc skills", "internal control", "acumen"], "soft_skills": ["communication", "analytical and problem solving skills", "presentation skills", "committed", "business acumen", "leadership"], "languages_combined": [{"language": "english", "language_level": ["excellent"]}, {"language": "chinese", "language_level": ["excellent"]}]}, "experience_required": {"duration": ["at least 2 years", "at least 3-year", "minimum 6 years"], "field": ["related", "commercial", "audit"]}}, {"job_id": "100003009053198", "location_code": "hk", "company": "DHL EXPRESS (HONG KONG) LIMITED", "job_title": "Controller - Accounting (Internal Control Manager)", "description": "Job Responsibilities:\nOperational duties\nTo calculate Net Asset Values and be responsible of the perimeter of NAV\u2019s cycle\nTo deliver on time\nTo ensure first level control of produced NAV\nTo respect the internal procedures for NAV\u2019s calculation and controls\nTo deal with cash, stocks and holdings reconciliations\nTo investigate on discrepancies and/or exceptions\nTo liaise with various departments of our local and European offices\nTo answer internal & external clients\u2019 request\nSupervisory duties if applicable\nTo work autonomously\nTo train the staff\nTo handle complex topics\nTo be in charge of projects\nTo liaise with management and communicate about operational issues\nTo take charge of any tasks the manager delegates\nTo encourage team spirit\nRequirement:\nDegree holder, with a major in accounting or finance, qualified accountant / professional qualifications\nSupervisory experience required for senior role\n\nTeam spirit combined with the ability to work autonomously and pro-actively\nExcellent communication skills and well organized\nFluency in English/ Mandarin. Knowledge in French/ Japanese/ Korean and other Asian/ foreign languages would be an advantage\nCandidate with less experience will be considered for a junior role.\nCompetitive remuneration package will be offered to the successful applicant. We offer an environment that encourages diversity and professional continuous development. Aspiring talents please send your resume via JobsDB. Personal data provided in job applications will be used strictly in accordance with\u00a0 our personal data policy, a copy of which is available upon request.\nFor more information about the Group, please visit www.caceis.com", "employment_types": ["Full Time"], "selling_points": ["Review internal control self-assessments", "Perform operational and financial review", "Minimum 6 years\u2019 solid experience"], "locations": ["Ngau Tau Kok"], "categories": ["Accounting", "Accountant", "Audit", "Treasurer"], "post_time": "2022-01-17T06:24:53Z", "salary": {"currency": null, "max": null, "min": null, "period": "monthly", "term": null}, "salary_visible": false, "title_keywords": ["accounting", "manager"], "responsibilities": ["control", "management", "procedures", "liaise with various departments", "reconciliations", "liaise with", "operational duties"], "requirements": {"degrees": ["degree holder"], "majors": ["finance", "accounting"], "languages": ["english", "french", "mandarin", "japanese", "korean"], "language_level": ["fluency", "advantage"], "hard_skills": ["professional qualifications"], "soft_skills": ["communication skills", "team spirit", "well organized"], "languages_combined": [{"language": "english", "language_level": ["fluency"]}, {"language": "french", "language_level": ["advantage"]}, {"language": "mandarin", "language_level": ["fluency"]}, {"language": "japanese", "language_level": ["advantage"]}, {"language": "korean", "language_level": ["advantage"]}]}, "experience_required": {"duration": [], "field": ["supervisory experience"]}}, {"job_id": "100003009052164", "location_code": "hk", "company": "CACEIS Hong Kong Trust Company Limited", "job_title": "Fund Accountant/ Senior Fund Accountant", "description": "Responsibilities\nHandle full set of accounts and related financial accounting duties\nProvide daily accounting support, including analysis, related accounting reports and management reports\nDevelop financial statements, financial budgeting, cost & expenses management and control system\nPerform assigned ad-hoc reports\nJob Requirements\nDiploma or equivalent qualification\n2 - 4 years of relevant working experience\nExperience in SAP is an advantage\nAble to work independently\nWell organized and highly motivated with a positive attitude\nGood communication and interpersonal skills\nCandidate with higher capability will be considered as Accountant\nPlease send your CV with your expected salary and availability, and by quoting reference number (FAAC001) in the subject via \"Apply Now\"\n\nCandidates who are not contacted within 8 weeks should consider their application as unsuccessful.", "employment_types": ["Full Time", "Permanent"], "selling_points": [], "locations": ["Admiralty"], "categories": ["Accounting", "Accountant", "Banking / Finance", "Financial Services", "Fund Management"], "post_time": "2022-01-17T02:18:36Z", "salary": {"currency": null, "max": null, "min": null, "period": "monthly", "term": null}, "salary_visible": false, "title_keywords": ["accountant"], "responsibilities": ["ad-hoc", "cost", "management", "control", "budgeting", "analysis", "full set of accounts", "expenses", "financial statements", "develop", "management reports", "reports", "daily accounting", "accounting duties"], "requirements": {"degrees": ["diploma"], "majors": [], "languages": [], "language_level": [], "hard_skills": ["sap"], "soft_skills": ["work independently", "well organized", "positive attitude", "motivated", "communication and interpersonal skills"], "languages_combined": []}, "experience_required": {"duration": ["2 - 4 years"], "field": ["relevant working experience"]}}, {"job_id": "100003009053882", "location_code": "hk", "company": "Morgan Half International (Hong Kong) Limited", "job_title": "Accountant / Assistant Accountant | AP Account Payable (Up to HKD 28K * 13 months guarantee)", "description": "Responsibilities\n\nAssist in handle assignments independently;\nInvolving in public offerings, listings, due diligence and private placements;\nAssist in analyze financial results of clients\u2019 companies;\nAssist in providing support to clients regarding different regulatory regimes, listing rules and related regulations;\nKeep up-to-date on regulatory developments;\nAssist in preparing business plans and IPO business proposals; Developing effective business relationships with clients;\nHandle ad hoc matters assigned.\n\nRequirements\n\nHigher Diploma\u00a0in accounting or related discipline.\nStudent member of HKICPA/ACCA/CPAA or other relevant professional bodies;\n0-1 year of accounting/audit experience in any field;\nSelf-motivated, willing to take job ownership, manage deadlines and able to work as a team player;\nProficient in MS Excel and word and knowledge of computerized accounting system is highly preferred;\nGood\u00a0analytical, interpersonal and communication skill is highly preferred;\nGood command in written and spoken English, Chinese and Mandarin;\nBusiness travel is required;\nFresh graduates are welcome;\nImmediate available is preferred.\n\nWhat we offered?\n\n5-day work week\nImportant festivals early leave\nOvertime meal allowance\nDiscretionary bonus\nFull-paid sick leave\nStudy & Exam leave\nGraduation leave\nWedding leave\nCompassionate leave\nMedical Insurance Scheme\nTraining reimbursement\nInterested parties please send your full resume with your\u00a0working experience, academic and professional qualification, expected salary, and date of availability\u00a0to HR Department.\nPersonal data collected will be used for recruitment purpose only.", "employment_types": ["Permanent"], "selling_points": ["Manufacturing Company", "AP + GL", "3 years or above experience"], "locations": ["Not Specified"], "categories": ["Accounting", "Accountant", "Accounting Clerk / Supervisor", "Audit"], "post_time": "2022-01-17T07:40:57Z", "salary": {"currency": null, "max": null, "min": null, "period": "monthly", "term": null}, "salary_visible": false, "title_keywords": ["accountant", "assistant accountant"], "responsibilities": ["regulations", "due diligence", "ad hoc", "developing", "providing support", "preparing business plans", "listing"], "requirements": {"degrees": ["diploma"], "majors": ["accounting"], "languages": ["english", "chinese", "mandarin"], "language_level": ["good command"], "hard_skills": ["acca", "word", "ms excel", "accounting system", "hkicpa"], "soft_skills": ["self-motivated", "communication skill", "interpersonal", "work as a team"], "languages_combined": [{"language": "english", "language_level": ["good command"]}, {"language": "chinese", "language_level": ["good command"]}, {"language": "mandarin", "language_level": ["good command"]}]}, "experience_required": {"duration": ["0-1 year"], "field": ["audit experience", "accounting"]}}, {"job_id": "100003009053254", "location_code": "hk", "company": "APEC Group International Limited", "job_title": "Accountant Trainee/Associate (Financial Advisory Team)", "description": "Our client is a leading international company in the computer software industry. Today, they are looking for an accountant to join their team in Hong Kong.\nYou will be working with the Finance Manager to provide financial information and reports to the management. Your responsibilities include but are not limited to:\nHandling accounting entries, bookkeeping and daily accounting operations (e.g invoicing, payments to vendors, account inquiries etc)\u00a0\nAssist with month-end and year-end closing\nAccounts Receivable(AR)/ Accounts Payable (AP) management\nArrange customers' debt repayment and establish repayment schedules\nLocate overdue accounts and review the terms of sales, service, or credit contract\nAssist with accounts reconciliation activities\nAssist with financial audits\nOccasionally liaise with CFO in Belgium office\nQualification:\n\nBachelor degree in Accounting\n2 years of relevant experience\nA very strong willingness to learn a new accounting system\u00a0\nFluent in English, Cantonese and Mandarin is a plus\nTeam spirit and excellent communication skills\nAdvanced MS Excel skills\nSelf-motivated with strong sense of responsibility", "employment_types": ["Full Time", "Part Time", "Permanent", "Contract"], "selling_points": ["Fresh graduates are welcome", "5-day work week", "Excellent career promotion prospect"], "locations": ["Sheung Wan"], "categories": ["Accounting", "Accountant", "Audit", "Consulting"], "post_time": "2022-01-17T06:32:55Z", "salary": {"currency": null, "max": null, "min": null, "period": "monthly", "term": null}, "salary_visible": false, "title_keywords": ["associate", "accountant", "trainee"], "responsibilities": ["ap", "management", "month-end and year-end closing", "software", "schedules", "review", "daily accounting operations", "invoicing", "liaise with", "communication", "reports", "payments", "audits", "accounts payable"], "requirements": {"degrees": ["degree", "bachelor"], "majors": ["accounting"], "languages": ["cantonese", "english", "mandarin"], "language_level": ["fluent"], "hard_skills": ["ap", "plus", "ms excel", "accounting system"], "soft_skills": ["communication skills", "self-motivated", "team spirit", "advanced", "sense of responsibility"], "languages_combined": [{"language": "cantonese", "language_level": ["fluent"]}, {"language": "english", "language_level": ["fluent"]}, {"language": "mandarin", "language_level": ["fluent"]}]}, "experience_required": {"duration": ["2 years"], "field": ["relevant experience"]}}, {"job_id": "100003009043695", "location_code": "hk", "company": "The French Chamber of Commerce and Industry in HK", "job_title": "Accountant", "description": "Ref. No.: JDB/HLD01/AS-A\n\nACCA / HKICPA Finalist or equivalent\nMinimum 4 years' experience in financial accounting field\nPrevious accounting experience in handling investment securities business will be an advantage\nProficiency in PC applications including Chinese word-processing\nWilling to work under pressure, mature & self-motivated\nCandidates with less experience will be considered for the post of Deputy Accounting Supervisor / Assistant Accounting Supervisor\n\n\nAttractive salary and fringe benefits will be offered to the successful candidates. Please apply with full resume by mail to\u00a0Human Resources Department, Henderson Land Development Co. Ltd., 71/F, Two International Finance Centre, 8 Finance Street, Central, Hong Kong\u00a0or by fax at\u00a02905 1855\u00a0or visit our homepage at\u00a0http://www.hld.com\u00a0or\u00a0by clicking \"Apply Now\".\n\n(Please quote the ref. no. on letter)\n\nPersonal data provided by job applicants will be used for recruitment purpose only.", "employment_types": ["Full Time", "Permanent"], "selling_points": ["GAAP experience", "International work environment", "Dynamic and friendly team"], "locations": ["Sai Ying Pun"], "categories": ["Accounting", "Accountant", "Finance / Accounting Manager"], "post_time": "2022-01-13T01:31:06Z", "salary": {"currency": null, "max": null, "min": null, "period": "monthly", "term": null}, "salary_visible": false, "title_keywords": ["accountant"], "responsibilities": ["work under pressure"], "requirements": {"degrees": [], "majors": [], "languages": ["chinese"], "language_level": ["proficiency"], "hard_skills": ["no", "acca", "chinese word-processing", "pc applications", "hkicpa"], "soft_skills": ["self-motivated", "mature", "work under pressure"], "languages_combined": [{"language": "chinese", "language_level": ["proficiency"]}]}, "experience_required": {"duration": ["minimum 4 years"], "field": ["accounting experience", "business", "investment", "securities", "accounting", "financial"]}}, {"job_id": "100003009048684", "location_code": "hk", "company": "Henderson Land Development Company Limited", "job_title": "ACCOUNTING SUPERVISOR / DEPUTY ACCOUNTING SUPERVISOR / ASSISTANT ACCOUNTING SUPERVISOR", "description": "Qualification & Requirement:\nDegree or above\nLCC higher level or equivalent\nGood PC skills, including Excel and Chinese Typing\nKnowledge or Experience in use of MYOB software\nFluent in Cantonese and English.\n3-5 years' relevant working experience\nAvailable immediately is an advantage.\n\nJob duties:\n\nProvide\u00a0clerical support for the Head of Finance and the Management\nFull set accounting, prepare vouchers and record transactions, AR & AP & Bank reconciliation\nProjected cashflow report and job analysis\nPrepare other ad hoc assignments on request\n\nBenefits:\n\n5 days work\nPerformance bonus\nBirthday leave\n\nTo apply, please email resume with expected salary by clicking \"Apply Now\"\n\nPersonal data will be used for recruitment purpose only.", "employment_types": ["Full Time", "Permanent"], "selling_points": ["Medical Allowance", "Education Allowance", "Free Lunch"], "locations": ["Central"], "categories": ["Accounting", "Accountant", "Accounting Clerk / Supervisor", "Others"], "post_time": "2022-01-14T07:02:31Z", "salary": {"currency": null, "max": null, "min": null, "period": "monthly", "term": null}, "salary_visible": false, "title_keywords": ["supervisor", "accounting supervisor", "assistant accounting"], "responsibilities": ["provide clerical support", "ap", "management", "ar", "analysis", "bank reconciliation", "transactions", "full set accounting", "ad hoc assignments", "report"], "requirements": {"degrees": ["degree or above"], "majors": [], "languages": ["cantonese", "english", "chinese"], "language_level": ["fluent", "good"], "hard_skills": ["excel", "myob software", "typing", "lcc", "pc skills"], "soft_skills": [], "languages_combined": [{"language": "cantonese", "language_level": ["fluent"]}, {"language": "english", "language_level": ["fluent"]}, {"language": "chinese", "language_level": ["good"]}]}, "experience_required": {"duration": ["3-5 years"], "field": ["relevant working experience"]}}, {"job_id": "100003009050410", "location_code": "hk", "company": "Canvas Digital Limited", "job_title": "Accounting Officer", "description": "Job Duties:\n\nHandle full set of accounts\nBank and online transactions reconciliation\nInvoice and cheque preparation\nPayroll processing\nPrepare accounting schedules for month-end & year-end closing\nPerform any other duties assigned from time to time & ad-hoc projects\nKnowledge of Oracle and SAP (P2P) systems will be an advantage\n\nRequirements:\u00a0\n\nHigher Diploma /Associate Degree in Accounting or above / completion of ACCA Foundation\u00a0 or equivalent\nSelf-motivated, well organized, independent, responsible, able to work under pressure and meet tight deadlines\nProficiency in MS Excel. Experiences in using accounting system such as Oracle and SAP are preferred\nStrong analytical and problem solving skills\nHigh level of integrity and able to meet tight deadline\nGood command of written English\nA minimum of 4 years accounting experience\nImmediate available is preferred\n\nA competitive salary commensurate with qualifications and experience will be offered\n\n\nApplication: A detailed C.V. stating current and expected salary with covering letter\n\nClosing date for application:\u00a0Monday 31 January 2022\n\n\nWebsite: www.idp.com/hongkong\n\nPersonal data collected will be used for recruitment purpose only.\n\nWe are an Equal Opportunities employer and welcome applications from any member of the community who\u00a0meets the selection criteria for the position.", "employment_types": ["Full Time"], "selling_points": ["Accounting", "Accounting Officer", "accountant"], "locations": ["Eastern Area"], "categories": ["Accounting", "Accountant", "Accounting Clerk / Supervisor"], "post_time": "2022-01-14T10:20:15Z", "salary": {"currency": null, "max": null, "min": null, "period": "monthly", "term": null}, "salary_visible": false, "title_keywords": ["accounting officer"], "responsibilities": ["any other duties", "invoice", "schedules", "full set of accounts", "systems", "month-end", "transactions", "year-end closing", "ad-hoc projects", "payroll"], "requirements": {"degrees": ["associate degree", "diploma"], "majors": ["accounting"], "languages": ["english"], "language_level": ["good command"], "hard_skills": ["acca", "sap", "ms excel", "c", "accounting system", "problem solving skills", "oracle"], "soft_skills": ["self-motivated", "meet tight deadlines", "independent", "responsible", "well organized", "integrity", "detailed", "analytical and problem solving skills", "meet tight deadline", "work under pressure"], "languages_combined": [{"language": "english", "language_level": ["good command"]}]}, "experience_required": {"duration": ["minimum of 4 years"], "field": ["accounting experience", "accounting"]}}, {"job_id": "100003009041321", "location_code": "hk", "company": "S. P. Engineering (Hong Kong) Limited", "job_title": "Accountant / Assistant Accountant", "description": "Our Company is a well-established company whose principal activity is engaged in provision of beauty parlor services in Hong Kong and are looking for an Accountant/Assistant Accountant to cope with the ongoing development of the group.\n\nResponsibilities:\n\n\u00a0\u00a0\u00a0\u00a0\u00a0\u00a0\u00a0 Team work on daily accounting operations and co-ordinate with internal parties\n\u00a0\u00a0\u00a0\u00a0\u00a0\u00a0\u00a0 Team work on month-end closing\n\u00a0\u00a0\u00a0\u00a0\u00a0\u00a0\u00a0 Walk-through check on POS system\n\u00a0\u00a0\u00a0\u00a0\u00a0\u00a0\u00a0 Data consolidation and analysis\n\nRequirements:\n\n\u00a0\u00a0\u00a0\u00a0\u00a0\u00a0\u00a0 Minimum 5 years of accounting experience, retail experience is advantage\n\u00a0\u00a0\u00a0\u00a0\u00a0\u00a0\u00a0 Prior working experience in audit is advantage\n\u00a0\u00a0\u00a0\u00a0\u00a0\u00a0\u00a0 Higher Diploma or above in\u00a0Accounting or related disciplines\n\u00a0\u00a0\u00a0\u00a0\u00a0\u00a0\u00a0 Excellent Skills in use of Microsoft Excel\n\u00a0\u00a0\u00a0\u00a0\u00a0\u00a0\u00a0 Knowledge of MYOB Accounting System is preferred\n\u00a0\u00a0\u00a0\u00a0\u00a0\u00a0\u00a0 Strong sense of responsibility, able to work independently, well organized,\u00a0 detailed-minded and self-motivated\n\u00a0\u00a0\u00a0\u00a0\u00a0\u00a0\u00a0 Good working attitude and hardworking\n\u00a0\u00a0\u00a0\u00a0\u00a0\u00a0\u00a0 Immediately available is preferred\n\nInterested parties, please send your full resume with expected salary to us.\n\n(All personal data collected will be used for recruitment purpose only.)", "employment_types": ["Full Time"], "selling_points": [], "locations": ["Shatin Area"], "categories": ["Accounting", "Accountant", "Accounting Clerk / Supervisor"], "post_time": "2022-01-12T03:44:45Z", "salary": {"currency": null, "max": null, "min": null, "period": "monthly", "term": null}, "salary_visible": false, "title_keywords": ["accountant", "assistant accountant"], "responsibilities": ["data", "co-ordinate with", "analysis", "daily accounting operations", "month-end closing", "internal parties"], "requirements": {"degrees": ["higher diploma or above"], "majors": ["related disciplines", "accounting"], "languages": [], "language_level": [], "hard_skills": ["myob", "accounting system", "microsoft excel"], "soft_skills": ["good working attitude", "work independently", "self-motivated", "sense of responsibility", "well organized", "hardworking", "detailed"], "languages_combined": []}, "experience_required": {"duration": ["minimum 5 years"], "field": ["accounting experience", "retail", "audit"]}}, {"job_id": "100003009043687", "location_code": "hk", "company": "Vegas 360 Beauty Limited", "job_title": "Accountant/Assistant Accountant", "description": "Responsibilities\n\nPrepare full sets of accounting and day-to-day management of all accounting activities in a timely and efficient manner\nHandle daily routine accounting operation including, but not limited to, invoicing and cheque payments\nHandle month-end closing and intercompany reconciliation\nSupport and review tasks prepared by subordinate\nReview default interest statement, debtor aging reports and petty cash schedules\u00a0\nWork closely with leasing team of Property Department on leasing matters\nProvide support for annual audit, tax computation and prepare reporting package for external auditors\nAct as a mentor to subordinate and provide support when required\nAssist in FLEX system update and amend posted vouchers\nPerform any ad hoc responsibilities as assigned\nRequirements:\n\nBachelor Degree or above in Accounting or related discipline\nDesignations of ACCA / HKICPA or related professional qualification, finalist will also be considered\n\nMinimum 4 year relevant working experience in full set of accounts\nMinimum 2 years\u2019 of supervisory experience\nResponsible, self-motivated, well-organized, detail-minded and eager to learn new things\nAble to perform under tight deadlines\nAble to prioritise assigned duties effectively with outstanding problem- solving skill and communication skill\nGood team player as well as able to work independently\nGood interpersonal skills with positive attitude and innovative\n\nWe offer an attractive compensation package, bank holidays, medical benefits and paid examination leave to the right candidate.\n\nInterested candidates please send your detailed resume with present and expected salary by clicking the \u201cApply Now\u201d button for submission.\n\nEmployment application data held by the Group will be treated in strict confidence and used only for recruitment purposes. Applicants who are not contacted within 2 months may consider their applications unsuccessful. The Group will retain the applications for a maximum period of one year and may refer suitable applicants to other vacancies within the Group.", "employment_types": ["Full Time"], "selling_points": [], "locations": ["Tsuen Wan Area"], "categories": ["Accounting", "Accountant"], "post_time": "2022-01-13T01:29:46Z", "salary": {"currency": null, "max": null, "min": null, "period": "monthly", "term": null}, "salary_visible": false, "title_keywords": ["accountant", "assistant accountant"], "responsibilities": ["reporting", "provide support", "ad hoc responsibilities", "tax computation", "annual audit", "schedules", "system update", "review", "day-to-day management", "invoicing", "month-end closing", "payments", "reports", "external auditors"], "requirements": {"degrees": ["degree or above", "bachelor"], "majors": ["accounting"], "languages": [], "language_level": [], "hard_skills": ["acca", "hkicpa"], "soft_skills": ["detail-minded", "self-motivated", "good team player", "work independently", "responsible", "communication skill", "well-organized", "prioritise", "positive attitude", "eager to learn", "interpersonal skills", "innovative"], "languages_combined": []}, "experience_required": {"duration": ["minimum 4 year", "minimum 2 years"], "field": ["relevant working experience", "supervisory experience"]}}]