[{"job_id": "100003009054931", "location_code": "hk", "company": "N&W Group (International) Limited", "job_title": "Accounting Clerk / \u6703\u8a08\u6587\u54e1", "description": "Company Brief Introduction:\n\nNutritionus (FB/IG: thenutritionus)\n\nWe focus on selling fresh goods, healthy snacks, and nutrition products\nWe promote and educate fitness and healthy lifestyle (IG: thenutritionus)\nOur Headquarter (working location) is at Fo Tan, N.T.\n\nWhat will you be doing:\n\nBook keeping, accounting related paper work\nMaintain office systems, data management, filing, utilities payment\nAssist in billing & auditing process\nAttend to incoming emails, and redirecting it to corresponding staff if necessary\nManage courier services, stationary inventories, office equipment maintenance etc.\nAttendance and salary management\nManage tasks allocate by manager\nAid in company\u2019s daily opertaion\n\nWhat you need for this position:\n\nProficient in English and Mandarin.\nCheerful, self-driven, a good team player.\nBook keeping/accounting related academic background\nProficient in using MS Office include Chinese word processing\nHaving accounting experience/certificate would be an asset\nFresh graduate candidate is always welcomed.\nHaving clerical experience would be an asset\nHaving accounting software experience would be an asset", "employment_types": ["Full Time"], "selling_points": ["accounting experience/certificate would be asset", "Bookkeeping/accounting related academic background", "Fresh graduate candidate is always welcomed"], "locations": ["Shatin Area"], "categories": ["Accounting", "Accounting Clerk / Supervisor"], "post_time": "2022-01-17T14:22:18Z", "salary": {"currency": null, "max": null, "min": null, "period": "monthly", "term": null}, "salary_visible": false, "title_keywords": ["accounting clerk"], "responsibilities": ["attendance", "management", "software", "data", "systems", "payment", "maintain", "office equipment maintenance", "auditing"], "requirements": {"degrees": ["certificate", "fresh graduate"], "majors": ["accounting"], "languages": ["english", "chinese", "mandarin"], "language_level": ["proficient"], "hard_skills": ["chinese word processing", "data management", "maintenance", "accounting software", "focus", "ms office"], "soft_skills": ["good team player", "focus", "cheerful", "driven"], "languages_combined": [{"language": "english", "language_level": ["proficient"]}, {"language": "chinese", "language_level": []}, {"language": "mandarin", "language_level": ["proficient"]}]}, "experience_required": {"duration": [], "field": ["accounting experience", "accounting", "clerical"]}}, {"job_id": "100003009052794", "location_code": "hk", "company": "Ferrari Logistics (Asia) Ltd", "job_title": "Accounts Clerk", "description": "Job Descriptions:\n\nAccounts receivables, invoicing and general accounting duties.\nWork closely with other department for daily operations.\nFiling and data entries.\nPrepare ad-hoc assignment from time to time assigned by Manager.\nRequirements:\nForm 5 or above.\nAt least 1 year of experience in accounting.\nProficiency in computer application, especially in MS Word and Excel.\nHigh threshold for paperwork and detail-minded.\nProficiency in both written and spoken English and Chinese\u00a0(Cantonese and Putonghua).\nImmediate availability is highly preferred.\nInterested parties please submit your FULL RESUME with AVAILABILITY, CURRENT and EXPECTED SALARY by clicking\u00a0APPLY NOW.\nAll information of candidates will be treated as strictly confidential and used for recruitment purposes only.\u00a0\u00a0", "employment_types": ["Full Time", "Permanent"], "selling_points": ["Accounts receivables", "Dynamic culture", "Excellent fringe benefits"], "locations": ["Kwai Hing"], "categories": ["Accounting", "Accounting Clerk / Supervisor", "Admin & HR", "Others"], "post_time": "2022-01-17T04:05:25Z", "salary": {"currency": null, "max": null, "min": null, "period": "monthly", "term": null}, "salary_visible": false, "title_keywords": ["accounts clerk"], "responsibilities": ["ad-hoc", "data", "invoicing", "daily operations", "general accounting duties"], "requirements": {"degrees": ["form 5 or above"], "majors": [], "languages": ["cantonese", "putonghua", "english", "chinese"], "language_level": ["proficiency"], "hard_skills": ["excel", "ms word"], "soft_skills": ["detail-minded"], "languages_combined": [{"language": "cantonese", "language_level": []}, {"language": "putonghua", "language_level": []}, {"language": "english", "language_level": ["proficiency"]}, {"language": "chinese", "language_level": ["proficiency"]}]}, "experience_required": {"duration": ["at least 1 year"], "field": ["accounting"]}}, {"job_id": "100003009053058", "location_code": "hk", "company": "Jibsen Industrial Ltd", "job_title": "Accounting & Admin. Officer", "description": "Hong Kong based company with more than 20 years experience in bag manufacturing URGENTLY requires in our Kwun Tong office:\n\nAccounting & Admin. Officer\n\nResponsibilities:\n\nDaily accounting operations including general journal entries, payments, petty cash, staff reimbursement, preparing monthly reports, etc.\nGeneral office administrative work\nManaging staff attendance and leave record\nAd-hoc assignments\n\nRequirements:\n\nMin. 2 years experience; Fresh graduate will be considered;\nDiploma in accounting;\nProficient in MS Office, Chinese Word Processing;\nPrior experience with ERP is an advantage;\nGood spoken & written English, Chinese & Mandarin;\nAble to work independently, responsible, self-motivated, hardworking & eager to learn;\nImmediate available is preferred.\n\nInterested parties please send resume with salary expected to Jibsen Industrial Ltd by pressing APPLY NOW\n\n(Data collected will be used for recruitment purpose only.)", "employment_types": ["Full Time"], "selling_points": ["5-day work", "Group Medical Insurance", "Annual Leave 11 days"], "locations": ["Kwun Tong"], "categories": ["Accounting", "Accounting Clerk / Supervisor", "Admin & HR", "Clerical / Admin Staff", "Others", "Others"], "post_time": "2022-01-17T05:28:21Z", "salary": {"currency": null, "max": null, "min": null, "period": "monthly", "term": null}, "salary_visible": false, "title_keywords": ["admin", "accounting", "officer"], "responsibilities": ["attendance", "administrative work", "monthly reports", "ad-hoc assignments", "daily accounting operations", "payments", "journal entries"], "requirements": {"degrees": ["diploma", "fresh graduate"], "majors": ["accounting"], "languages": ["english", "chinese", "mandarin"], "language_level": ["good", "proficient"], "hard_skills": ["chinese word processing", "erp", "ms office"], "soft_skills": ["work independently", "self-motivated", "responsible", "eager to learn", "hardworking"], "languages_combined": [{"language": "english", "language_level": ["good"]}, {"language": "chinese", "language_level": ["good", "proficient"]}, {"language": "mandarin", "language_level": ["good"]}]}, "experience_required": {"duration": ["2 years"], "field": []}}, {"job_id": "100003009051987", "location_code": "hk", "company": "Ec InfoTech Limited", "job_title": "Account Clerk", "description": "Responsibilities:\n\nPerform accounting functions including Accounts Receivable, Accounts Payable and Invoicing, etc.;\nHandle administrative work including preparation of payment vouchers and cheque;\nMaintain accounting records and perform data entry;\nAssist in ad-hoc assignments;\nOther duties assigned by supervisor\n\nRequirements:\n\nDiploma or above qualification in accounting or LCCI Intermediate above preferred;\nWith 2 years or above relevant experiences, prefer Property Management field;\nProficiency in MS office application & Chinese WordProcessing;\nProficient in Cantonese and English;\nIndependent, stable, attentive to details, multi-tasking, able to work under pressure and adaptive to given challenges;\nImmediate available is highly preferable\n\nMethod to Apply:\n\nl\u00a0 Interested parties please submit your application with expected salaries and availability to Ec InfoTech Ltd Human Resources Department by clicking to Apply Now.\n\nl\u00a0 \u00a0Data collected will be used for recruitment purpose only and Applicants who are not invited to interview within 2 months may consider their applicants unsuccessful.", "employment_types": ["Full Time"], "selling_points": ["Performs daily clerical job", "Accounting", "Administrative"], "locations": ["Kwun Tong"], "categories": ["Accounting", "Accounting Clerk / Supervisor"], "post_time": "2022-01-17T01:45:50Z", "salary": {"currency": null, "max": null, "min": null, "period": "monthly", "term": null}, "salary_visible": false, "title_keywords": ["account clerk"], "responsibilities": ["administrative work", "accounts receivable", "data entry", "other duties", "ad-hoc assignments", "invoicing", "payment", "maintain", "accounts payable"], "requirements": {"degrees": ["diploma or above"], "majors": ["accounting"], "languages": ["cantonese", "english", "chinese"], "language_level": ["proficiency", "proficient"], "hard_skills": ["ms office"], "soft_skills": ["independent", "attentive to details", "multi-tasking", "stable", "work under pressure"], "languages_combined": [{"language": "cantonese", "language_level": ["proficient"]}, {"language": "english", "language_level": ["proficient"]}, {"language": "chinese", "language_level": ["proficiency"]}]}, "experience_required": {"duration": ["2 years"], "field": ["management"]}}, {"job_id": "100003009052980", "location_code": "hk", "company": "Progressive Timepieces Limited", "job_title": "ACCOUNTS CLERK", "description": "Responsibilities:\n\nResponsible for handle full set of accounts (Bookkeeping, monthly reports, year end reports)\nDaily cash flow management as well as bank and cheque transactions\nUndertake administrative works and daily operations\n\nRequirements:\n\nF.6 or above with LCCI Higher \u00a0\n2 years relevant experience or above \u00a0\nGood command of spoken and written English and Chinese (Mandarin is preferred) \u00a0\nPeachtree Accounting & ERP System & PC Knowledge (MS Word & Excel) \u00a0\nSelf-motivated, organized and detail oriented \u00a0\nStationed in Hong Kong\n5 days work\n\nInterested parties please send full resume with expected salary by clicking \"Apply Now\"\u00a0", "employment_types": ["Full Time"], "selling_points": ["KWAI CHUNG AREA", "5 DAYS WORK", "GROUP MEDICAL"], "locations": ["Kwai Hing"], "categories": ["Accounting", "Accounting Clerk / Supervisor"], "post_time": "2022-01-17T07:13:15Z", "salary": {"currency": null, "max": null, "min": null, "period": "monthly", "term": null}, "salary_visible": false, "title_keywords": ["accounts clerk"], "responsibilities": ["management", "monthly reports", "full set of accounts", "transactions", "cash flow", "daily operations", "reports"], "requirements": {"degrees": [], "majors": [], "languages": ["english", "chinese", "mandarin"], "language_level": ["good command"], "hard_skills": ["excel", "erp system", "peachtree", "pc knowledge", "ms word"], "soft_skills": ["organized", "self-motivated", "detail oriented"], "languages_combined": [{"language": "english", "language_level": ["good command"]}, {"language": "chinese", "language_level": ["good command"]}, {"language": "mandarin", "language_level": ["good command"]}]}, "experience_required": {"duration": ["2 years"], "field": ["relevant experience"]}}, {"job_id": "100003009053932", "location_code": "hk", "company": "Prince Jewellery and Watch Company Limited", "job_title": "Accounts Assistant/ Accounts Clerk", "description": "We are now seeking a high caliber\u00a0candidate to join our expanding family with the following responsibilities:\n\nResponsibilities:\n\nSupporting AR & AP functions\nPreparing reconciliation for shop daily sales and accounts receivable\nHandling daily accounting duties including voucher preparing, cheque issuing, refund to customer, bank reconciliation and documents filing\nParticipating in ad-hoc duties as assigned\n\nRequirements:\n\nHigher Diploma or above in Accounting or related disciplines\n2 years' relevant experience preferably in retail industry\nKnowledge in using Microsoft Window AX\u00a0will be an advantage\nProficient\u00a0in Microsoft Office (MS Word, Excel, Chinese WP)\nGood command of spoken and written English and Chinese\nImmediately available is preferred\nCandidate with less experience will be considered as Accounts Clerk\n\nWe offer attractive remuneration package to successful candidates. Interested parties please send full resume by clicking \"Apply Now\"\u00a0or by mail to Room 1729-30, Star House, 3 Salisbury Road, T.S.T, H.K.\n\nAll information received will be treated strictly confidential and for employment purpose only\u00a0", "employment_types": ["Full Time", "Permanent"], "selling_points": ["Supporting AR & AP functions", "Preparing reconciliation for shop daily sales", "Handling daily accounting duties"], "locations": ["Tsim Sha Tsui"], "categories": ["Accounting", "Accounting Clerk / Supervisor"], "post_time": "2022-01-17T07:47:49Z", "salary": {"currency": null, "max": null, "min": null, "period": "monthly", "term": null}, "salary_visible": false, "title_keywords": ["accounts clerk", "accounts assistant"], "responsibilities": ["ap", "documents filing", "ar", "accounts receivable", "bank reconciliation", "ad-hoc duties", "daily accounting"], "requirements": {"degrees": ["higher diploma or above"], "majors": ["related disciplines", "accounting"], "languages": ["english", "chinese"], "language_level": ["good command", "proficient"], "hard_skills": ["ms word", "excel", "chinese wp", "microsoft office"], "soft_skills": [], "languages_combined": [{"language": "english", "language_level": ["good command"]}, {"language": "chinese", "language_level": ["good command", "proficient"]}]}, "experience_required": {"duration": ["2 years"], "field": ["retail industry", "relevant experience"]}}, {"job_id": "100003009054793", "location_code": "hk", "company": "Sage Dignity Services Limited", "job_title": "ACCOUNTS CLERK", "description": "Responsibilities\n\nHandle full set accounting and month end closing;\nPrepare full set of accounts including general ledger, accounts receivable and accounts payable;\nPrepare management reports and financial analysis on a timely basis;\nAssist in reviewing Taiwan and Macau companies\u2019 management reports;\nAssist in annual audit, final accounts and budget;\nOther ad hoc tasks as assigned.\n\nRequirements\n\nDegree holder in Accounting, Finance or related discipline;\n5 years relevant experience;\nFamiliar with MS office, particularly in MS Excel and word;\nAble to work independently and under pressure;\nSelf-motivated, detail oriented, strong sense of responsibility and multi-tasked;\nGood interpersonal, communication, analytical and problem-solving skills;\nGood communication in both English, Chinese and Mandarin.", "employment_types": ["Full Time", "Permanent"], "selling_points": ["Degree holder in Accounting", "5 years relevant experience", "Handle full set accounting"], "locations": ["Kwun Tong"], "categories": ["Accounting", "Accounting Clerk / Supervisor"], "post_time": "2022-01-17T11:06:25Z", "salary": {"currency": null, "max": null, "min": null, "period": "monthly", "term": null}, "salary_visible": false, "title_keywords": ["accounts clerk"], "responsibilities": ["month end closing", "handle full set accounting", "accounts receivable", "annual audit", "general ledger", "full set of accounts", "budget", "ad hoc tasks", "financial analysis", "management reports", "accounts payable"], "requirements": {"degrees": ["degree holder"], "majors": ["finance", "accounting"], "languages": ["english", "chinese", "mandarin"], "language_level": ["good"], "hard_skills": ["problem-solving skills", "ms excel", "word", "ms office"], "soft_skills": ["work independently", "self-motivated", "under pressure", "sense of responsibility", "detail oriented", "communication", "multi-tasked", "problem-solving skills", "interpersonal"], "languages_combined": [{"language": "english", "language_level": ["good"]}, {"language": "chinese", "language_level": ["good"]}, {"language": "mandarin", "language_level": ["good"]}]}, "experience_required": {"duration": ["5 years"], "field": ["relevant experience"]}}, {"job_id": "100003009053097", "location_code": "hk", "company": "Winon Industrial Company Limited", "job_title": "\u6703\u8a08 (Accounting Clerk)", "description": "\n\u4e3b\u8981\u8ca0\u8cac\u9999\u6e2f\u6703\u8a08\u5168\u76e4\u8cec\u76ee.\n\u5de5\u4f5c\u5305\u62ec\u8655\u7406\u65e5\u5e38\u5982\u7cfb\u7d71\u8cc7\u6599\u8f38\u5165\u7b49, \u61c9\u6536,\u61c9\u4ed8, \u51fa\u7ce7, \u9280\u884c\u67e5\u5e33/\u5c0d\u5e33 \u548c \u7e3d\u5e33;\n\u9700\u5b89\u6392\u6bcf\u6708\u7d50\u7b97, \u92b7\u552e\u4f63\u91d1, \u5206\u6790\u5831\u8868, \u5831\u92b7\u55ae\u64da, \u5168\u5957\u5e33\u6236, \u8ca1\u52d9\u5831\u544a\u548c\u7e3d\u5e33;\n\u9700\u4e0d\u5b9a\u6642\u8207\u6703\u8a08\u5e2b\u6e9d\u901a\u5b8c\u6210\u6bcf\u5e74\u5be9\u8a08\u53ca\u4e3b\u7ba1\u59d4\u6d3e\u4e4b\u5de5\u4f5c.\n\u53e6\u9700\u8655\u7406\u65e5\u5e38\u884c\u653f\u4e8b\u52d9, \u63a1\u8cfc\u548c\u9032\u51fa\u53e3\u5831\u95dc.", "employment_types": ["Full Time"], "selling_points": [], "locations": ["Kwai Hing"], "categories": ["Accounting", "Accounting Clerk / Supervisor"], "post_time": "2022-01-17T05:47:59Z", "salary": {"currency": null, "max": null, "min": null, "period": "monthly", "term": null}, "salary_visible": false, "title_keywords": ["accounting clerk"], "responsibilities": [], "requirements": {"degrees": [], "majors": [], "languages": [], "language_level": [], "hard_skills": [], "soft_skills": [], "languages_combined": []}, "experience_required": {"duration": [], "field": []}}, {"job_id": "100003009044767", "location_code": "hk", "company": "The Hong Kong Society for the Aged", "job_title": "\u6703\u8a08\u6587\u54e1Accounting Clerk (\u8077\u4f4d\u7de8\u865f\uff1aACC - 220102)", "description": "\u8ca0\u8cac\u6587\u66f8\u53ca\u5168\u76e4\u6703\u8a08\u5de5\u4f5c\n\u4e2d\u4e94\u6216\u4ee5\u4e0a\u7a0b\u5ea6\n2\u5e74\u6216\u4ee5\u4e0a\u6703\u8a08\u7d93\u9a57\n\u6301\u6709\u521d\u7d1a\u7c3f\u8a18\u8b49\u66f8\u53ca\u6709\u904b\u7528\u7532\u9aa8\u6587(Oracle)\u6703\u8a08\u8edf\u4ef6\u7d93\u9a57\u512a\u5148\u8003\u616e\n\u5165\u8077\u85aa\u916c\u70ba$14,410\u6216\u6309\u76f8\u95dc\u5e74\u8cc7\u8a08\u7b97\n\u8343\u8475\u9752\u7d9c\u5408\u5bb6\u5c45\u7167\u9867\u670d\u52d9\uff08\u8475\u6d8c\u5927\u7aa9\u53e3\u90a8\uff09\u5de5\u4f5c\n\n\u7533\u8acb\u8fa6\u6cd5\uff1a\u8acb\u5c07\u5c65\u6b77\u8868\u6216\u8077\u4f4d\u7533\u8acb\u8868 (\u7533\u8acb\u8868\u53ef\u65bc\u672c\u6703\u7db2\u9801http://www.sage.org.hk\u4e4b\u300c\u95dc\u65bc\u6211\u5011\u300d\uff0d\u300c\u4e0b\u8f09\u8868\u683c\u300d\uff0d\u300c\u8077\u4f4d\u7533\u8acb\u8868\u683c\u300d\u4e0b\u8f09) \u90f5\u5bc4\u81f3\u65b0\u754c\u8475\u6d8c\u5927\u7aa9\u53e3\u90a8\u5bcc\u9038\u6a13\u5730\u4e0b\u8006\u5eb7\u6703\u8343\u8475\u9752\u7d9c\u5408\u5bb6\u5c45\u7167\u9867\u670d\u52d9\u4e2d\u5fc3\u4e3b\u4efb\u6536\u6216\u96fb\u90f5\u81f3Apply Now\uff0c\u4e26\u8a3b\u660e\u8981\u6c42\u85aa\u91d1\u53ca\u65bc\u4fe1\u5c01\u9762\u8a3b\u660e\u7533\u8acb\u8077\u4f4d\u53ca\u8077\u4f4d\u7de8\u865f\uff0c\u67e5\u8a62\u96fb\u8a71\uff1a2425 1282\u3002\n\n\u622a\u6b62\u7533\u8acb\u65e5\u671f\uff1a2022\u5e741\u670824\u65e5\n\n\u672c\u6703\u63d0\u4f9b\u5b8c\u5584\u798f\u5229\uff0c\u5305\u62ec\uff1a\u91ab\u7642\u4fdd\u96aa\u3001\u6700\u9ad810%\u00a0\u5f37\u7a4d\u91d1\u50f1\u4e3b\u4f9b\u6b3e\u53ca\u5c08\u696d\u57f9\u8a13\u7b49\u3002\n\n\u4e00\u5207\u7533\u8acb\u8cc7\u6599\u7d55\u5c0d\u4fdd\u5bc6\u53ca\u53ea\u7528\u4f5c\u62db\u8058\u6709\u95dc\u8077\u4f4d\uff0c\u672a\u7372\u7d04\u898b\u8005\uff0c\u4f5c\u843d\u9078\u8ad6\uff0c\u6055\u4e0d\u53e6\u51fd\u901a\u77e5\u3002\u800c\u7533\u8acb\u4eba\u4e4b\u500b\u4eba\u8cc7\u6599\u4ea6\u5c07\u5728\u5b8c\u6210\u62db\u8058\u7a0b\u5e8f\u5f8c\u92b7\u6bc0\u3002", "employment_types": ["Full Time", "Contract"], "selling_points": [], "locations": ["Kwai Tsing Area"], "categories": ["Accounting", "Accounting Clerk / Supervisor"], "post_time": "2022-01-15T19:11:22Z", "salary": {"currency": null, "max": null, "min": null, "period": "monthly", "term": null}, "salary_visible": false, "title_keywords": ["clerk"], "responsibilities": [], "requirements": {"degrees": [], "majors": [], "languages": [], "language_level": [], "hard_skills": [], "soft_skills": [], "languages_combined": []}, "experience_required": {"duration": [], "field": []}}, {"job_id": "100003009053614", "location_code": "hk", "company": "\u601d\u8b00\u96c6\u5718\u6709\u9650\u516c\u53f8", "job_title": "Treasury clerk", "description": "Responsibilities1. Handle daily payment to the bank's accounts and affairs\n2. Prepare receipt, payment and journal vouchers, cheques and bank transfer and bank reconciliation\n3. Posting and reconciling Petty Cash\n4. Preparation of monthly budget cashflow\n5. Handle ad-hoc assignment as requiredRequirements1. Form 7 and with LCC Higher or similar qualification\n2. At least\u00a03\u00a0years experience in AP, AR\n3. Proficiency in MS Excel,\u00a0MS Word\n4. Good communication skill in English and\u00a0Chinese\n5. Strong sense of responsibility, high accuracy, well-organized, hard working and under pressure\n6. Immediate available is highly desired", "employment_types": ["Full Time"], "selling_points": ["Handle  payment to the bank's accounts and affairs", "Preparation of monthly budget cashflow", "Posting and reconciling Petty Cash"], "locations": ["Shatin Area"], "categories": ["Accounting", "Accountant", "Accounting Clerk / Supervisor", "Treasurer"], "post_time": "2022-01-17T07:14:34Z", "salary": {"currency": null, "max": null, "min": null, "period": "monthly", "term": null}, "salary_visible": false, "title_keywords": ["clerk"], "responsibilities": ["ad-hoc", "journal vouchers", "ap", "ar", "budget", "bank reconciliation", "communication", "payment", "cheques"], "requirements": {"degrees": [], "majors": [], "languages": ["english", "chinese"], "language_level": ["good"], "hard_skills": ["ap", "ar", "ms excel", "lcc", "ms word"], "soft_skills": ["under pressure", "sense of responsibility", "hard working", "communication skill", "well-organized"], "languages_combined": [{"language": "english", "language_level": ["good"]}, {"language": "chinese", "language_level": ["good"]}]}, "experience_required": {"duration": ["at least 3 years"], "field": []}}, {"job_id": "100003009042679", "location_code": "hk", "company": "Honestar Technologies Company Limited", "job_title": "SENIOR ACCOUNT CLERK", "description": "\n\u8981\u6c42\uff1a\n\u2022 \u5354\u52a9\u7d44\u7e54\u516c\u53f8\u5e74\u5ea6\u9810\u7b97\u7684\u7de8\u5236\u548c\u5b63\u5ea6\u3001\u6708\u5ea6\u9810\u7b97\u8a08\u5283; \u8ca0\u8cac\u65e5\u5e38\u6703\u8a08\u5165\u8cec\u53ca\u7de8\u5236\u5404\u985e\u6703\u8a08\u5831\u8868; \u5354\u52a9\u7de8\u5236\u4e0a\u5e02\u516c\u53f8\u5e74\u5831\uff0c\u534a\u5e74\u5831\u544a\u53ca\u76f8\u95dc\u5831\u8868; \u5176\u5b83\u65e5\u5e38\u8ca1\u52d9\u5de5\u4f5c\u3002\n\u2022 \u5c08\u4e0a\u6559\u80b2\uff1a\u5927\u5b78\u672c\u79d1\u53ca\u4ee5\u4e0a\u5b78\u6b77\uff0c\u4e3b\u4fee\u6703\u8a08, CPA\u8cc7\u683c\u6216\u8005\u6301\u6709\u5167\u5730\u6703\u8a08\u5e2b\u8b49\u512a\u5148\u8003\u616e, \u826f\u597d\u7cb5\u8a9e; \u826f\u597d\u666e\u901a\u8a71; \u826f\u597d\u82f1\u8a9e; 3-5\u5e74\u4ee5\u4e0a\u4e0a\u5e02\u516c\u53f8\u76f8\u95dc\u5de5\u4f5c\u7d93\u9a57;\u00a0\n\u85aa\u91d1\uff1a \u9762\u8b70\n\u00a0\n\u5f85\u9047\uff1a \u9280\u884c\u5047\u671f\uff0c\u91ab\u7642\u798f\u5229\uff0c\u6709\u82b1\u7d05\uff0cOT\u88dc\u52a9\uff0c\u6649\u6607\u6a5f\u6703\uff0c\u65c5\u904a\u734e\u8cde\u7b49\n\u6709\u610f\u8005\u8acb\u96fb\u90f5\u81f3 [via\u00a0 Apply Now ]", "employment_types": ["Full Time"], "selling_points": ["\u9280\u884c\u5047\u671f\uff0c\u91ab\u7642\u798f\u5229", "OT\u88dc\u52a9", "\u6649\u6607\u6a5f\u6703\uff0c\u65c5\u904a\u734e\u8cde\u7b49"], "locations": ["Kwai Hing"], "categories": ["Accounting", "Accountant", "Accounting Clerk / Supervisor"], "post_time": "2022-01-16T21:50:13Z", "salary": {"currency": null, "max": null, "min": null, "period": "monthly", "term": null}, "salary_visible": false, "title_keywords": ["senior account clerk"], "responsibilities": [], "requirements": {"degrees": [], "majors": [], "languages": [], "language_level": [], "hard_skills": [], "soft_skills": [], "languages_combined": []}, "experience_required": {"duration": [], "field": []}}, {"job_id": "100003009053734", "location_code": "hk", "company": "Alpha Quant Financial Technology Limited", "job_title": "Accounting Clerk", "description": "\nJob Description\n-Reconciliation of bank statement and invoice\n-Perform daily accounting operations\n-Other ad hoc duties\nRequirements\n-Degree in Accounting/ other discipline\n-Proficiency in computer operations (PC, MS Office, Excel, Chinese word typing)\n-Experience and knowledge in accounting work\nSalary: Competitive, Negotiable\nJob Types: Full-time, Contract, Permanent\nJob Types: Full-time, Permanent, Contract\nSalary: $10,000.00 - $20,000.00 per month\nSchedule:\n\u2022 Monday to Friday\n\n", "employment_types": ["Full Time"], "selling_points": [], "locations": ["Tsim Sha Tsui"], "categories": ["Accounting", "Accounting Clerk / Supervisor", "Others", "Admin & HR", "Others"], "post_time": "2022-01-17T07:25:38Z", "salary": {"currency": null, "max": null, "min": null, "period": "monthly", "term": null}, "salary_visible": false, "title_keywords": ["accounting clerk"], "responsibilities": ["invoice", "daily accounting operations", "ad hoc duties"], "requirements": {"degrees": [], "majors": [], "languages": ["chinese"], "language_level": [], "hard_skills": ["excel", "typing", "word", "pc", "ms office"], "soft_skills": [], "languages_combined": [{"language": "chinese", "language_level": []}]}, "experience_required": {"duration": [], "field": []}}, {"job_id": "100003009053889", "location_code": "hk", "company": "E & K Cleaning Services Limited", "job_title": "\u6703\u8a08\u4e3b\u4efb", "description": "\n\u8077\u8cac :\u8655\u7406\u5168\u76e4\u6703\u8a08\u5e33\u76ee\uff1b\u8ca0\u8cac\u65e5\u5e38\u6703\u8a08\u4e8b\u52d9\uff0c\u4f8b\u5982AR/AP\uff1b\u8ddf\u9032\u5ba2\u6236\u672a\u4ed8\u6b3e\u9805\uff1b\u88fd\u4f5c\u6bcf\u6708\u8ca1\u52d9\u5831\u544a\uff1b\u5354\u52a9\u5e74\u5ea6\u5be9\u8a08\u53ca\u5831\u7a05\u4e8b\u5b9c\uff1b\u5354\u52a9\u8fa6\u516c\u5ba4\u884c\u653f\u5de5\u4f5c\u53ca\u5176\u4ed6\u6307\u6d3e\u5de5\u4f5c\n\n\u8cc7\u6b77 :\u4e2d\u4e94\u7a0b\u5ea6; 1\u5e74\u7d93\u9a57; \u826f\u597d\u7cb5\u8a9e; \u4e00\u822c\u82f1\u8a9e; \u61c2\u8b80\u5beb\u4e2d\u6587; \u7565\u61c2\u8b80\u5beb\u82f1\u6587; \u61c2MS Word; \u61c2MS Excel; \u6301\u6709LCC\u4e2d\u7d1a\u8b49\u66f8; \u61c2\u82f1\u6587\u6253\u5b57; \u61c2\u4e2d\u6587\u6253\u5b57\n\n\u5f85\u9047 :\u6bcf\u6708$18,000 - $20,000, \u661f\u671f\u4e00\u81f3\u4e94: \u4e0a\u53489\u6642\u81f3\u4e0b\u53486\u6642\u53ca\u661f\u671f\u516d: \u4e0a\u53489\u6642\u81f3\u4e0b\u53481\u6642, \u6bcf\u9031\u5de5\u4f5c5\u5929\u534a\n\n\u7533\u8acb\u9808\u77e5 :\u6c42\u8077\u8005\u53ef\u96fb\u90f5(Apply Now)\u5c65\u6b77\u8868\u7d66\u96c5\u6f54\u6e05\u6f54\u5de5\u7a0b\u6709\u9650\u516c\u53f8\u3002\u5982\u8981\u7d22\u53d6\u6536\u96c6\u500b\u4eba\u8cc7\u6599\u8072\u660e, \u8acb\u8207\u5f35\u5148\u751f(Email)\u806f\u7d61\u3002\n\n", "employment_types": ["Full Time"], "selling_points": [], "locations": ["Tsuen Wan Area"], "categories": ["Accounting", "Accountant", "Accounting Clerk / Supervisor", "Audit"], "post_time": "2022-01-17T07:42:15Z", "salary": {"currency": null, "max": null, "min": null, "period": "monthly", "term": null}, "salary_visible": false, "title_keywords": [], "responsibilities": [], "requirements": {"degrees": [], "majors": [], "languages": [], "language_level": [], "hard_skills": ["excel", "word"], "soft_skills": [], "languages_combined": []}, "experience_required": {"duration": [], "field": []}}, {"job_id": "100003009053908", "location_code": "hk", "company": "Alliance Medical Group Holdings Limited", "job_title": "Accounting Clerk", "description": "\u4e0a\u73ed\u5730\u9ede : \u89c0\u5858\n\n\u4e0a\u73ed\u6642\u9593 : \u4e94\u5929\u5de5\u4f5c 10am-7pm\n\n\u5de5\u4f5c\u5167\u5bb9 :\n\n\u5354\u52a9\u8655\u7406\u61c9\u4ed8\u8cec\u76ee\u3001\u61c9\u6536\u8cec\u76ee\u53ca\u4e00\u822c\u6703\u8a08\u8cec\u76ee\n\u8cc7\u6599\u8f38\u5165\u3001\u5b58\u6a94\u53ca\u6587\u66f8\u5de5\u4f5c\u7b49\n\u8655\u7406\u65e5\u5e38\u6536\u652f\u53ca\u4e00\u822c\u6703\u8a08\u55ae\u64da\n\u57f7\u884c\u4e0a\u53f8\u59d4\u6d3e\u5de5\u4f5c\n\u5de5\u4f5c\u8981\u6c42 :\n\n\u7121\u9808\u7d93\u9a57\nLCCI \u4e2d\u7d1a\u512a\u5148\n\u61c2\u4e2d\u6587\u8f38\u5165\u6cd5\n\u61c2\u4f7f\u7528 MS Office\n\u7d30\u5fc3\u3001\u8aa0\u5be6\u52e4\u596e\u3001\u5bcc\u8cac\u4efb\u611f\u53ca\u5718\u968a\u7cbe\u795e\n\n\u5168\u8077\u5f85\u9047\uff1a\n\n\u00a0\u00a0\u00a0\u00a0\u00a0\u00a0\u00a0\u52e4\u5de5\u734e\u91d1\n\u00a0\u00a0\u00a0\u00a0\u00a0\u00a0\u00a0\u9280\u884c\u5047\u671f\n\n\u6c42\u8077\u8005\u63d0\u4f9b\u7684\u500b\u4eba\u8cc7\u6599\u5c07\u56b4\u683c\u6309\u7167\u50f1\u4e3b\u7684\u500b\u4eba\u8cc7\u6599\u653f\u7b56\u4f7f\u7528\uff0c\u50c5\u4f9b\u62db\u8058\u7528\u9014\u3002", "employment_types": ["Full Time"], "selling_points": ["\u6708\u85aa$15000+", "\u4e94\u5929\u5de5\u4f5c, \u9280\u884c\u5047\u671f", "\u7121\u9808\u7d93\u9a57"], "locations": ["Kwun Tong"], "categories": ["Accounting", "Accounting Clerk / Supervisor"], "post_time": "2022-01-17T07:44:21Z", "salary": {"currency": null, "max": null, "min": null, "period": "monthly", "term": null}, "salary_visible": false, "title_keywords": ["accounting clerk"], "responsibilities": [], "requirements": {"degrees": [], "majors": [], "languages": [], "language_level": [], "hard_skills": ["ms office"], "soft_skills": [], "languages_combined": []}, "experience_required": {"duration": [], "field": []}}, {"job_id": "100003009052585", "location_code": "hk", "company": "Forsters & Company", "job_title": "Accounting Officer", "description": "Requirements\n\nUniversity graduate of Accounting Studies\n2-3 years relevant experience in daily accounting support\nExperience in AP, AR, preferably in multinational corporations\nPrevious experience in handling vendor payment is preferable\nDetail-minded, adaptable, energetic and sense of responsibilities\nWell-versed in using Microsoft Office and accounting software\nGood command of English and fair in spoken Mandarin\nImmediate available is highly preferred\n\nResponsibilities\n\nPerform general accounting duties including payable and receivable\nHandle monthly bank reconciliation and arrange vendor payment\nResponsible for intercompany transactions and preparing monthly reports\nMaintain accurate accounting system and assist in month-end closing\n\nWe offer attractive remuneration package and promising career prospect to the right candidates. Interested parties please send full resume with expected/last salary and date of available by clicking \u2018Apply Now\u2019", "employment_types": ["Full Time", "Permanent"], "selling_points": [], "locations": ["Not Specified"], "categories": ["Accounting", "Accounting Clerk / Supervisor", "Others"], "post_time": "2022-01-17T06:15:51Z", "salary": {"currency": null, "max": null, "min": null, "period": "monthly", "term": null}, "salary_visible": false, "title_keywords": ["accounting officer"], "responsibilities": ["monthly reports", "bank reconciliation", "transactions", "payment", "maintain", "general accounting duties", "month-end closing"], "requirements": {"degrees": ["university graduate"], "majors": ["accounting"], "languages": ["english", "mandarin"], "language_level": ["good command"], "hard_skills": ["ap", "ar", "microsoft office", "accounting software", "vendor"], "soft_skills": ["detail-minded", "energetic", "adaptable", "sense of responsibilities"], "languages_combined": [{"language": "english", "language_level": ["good command"]}, {"language": "mandarin", "language_level": ["good command"]}]}, "experience_required": {"duration": ["2-3 years"], "field": ["accounting", "relevant experience"]}}, {"job_id": "100003009044579", "location_code": "hk", "company": "The Hong Kong Society for the Aged", "job_title": "\u884c\u653f\u53ca\u6703\u8a08\u6587\u54e1Administration and Accounting Clerk (\u8077\u4f4d\u7de8\u865f\uff1aADC - 220102)", "description": "\u8ca0\u8cac\u6587\u66f8\u3001\u5168\u76e4\u6703\u8a08\u3001\u884c\u653f\u53ca\u9662\u52d9\u5de5\u4f5c\n\u4e2d\u4e94\u6216\u4ee5\u4e0a\u7a0b\u5ea6\n2\u5e74\u6216\u4ee5\u4e0a\u6703\u8a08\u7d93\u9a57\n\u6301\u6709\u521d\u7d1a\u7c3f\u8a18\u8b49\u66f8\u53ca\u6709\u904b\u7528\u7532\u9aa8\u6587(Oracle)\u6703\u8a08\u8edf\u4ef6\u7d93\u9a57\u512a\u5148\u8003\u616e\n\u5165\u8077\u85aa\u916c\u70ba$14,410\u6216\u6309\u76f8\u95dc\u5e74\u8cc7\u8a08\u7b97\n\u77f3\u570d\u89d2\u8b77\u7406\u5b89\u8001\u9662\uff08\u8343\u7063\u77f3\u570d\u89d2\u90a8\uff09\u5de5\u4f5c\n\n\u7533\u8acb\u8fa6\u6cd5\uff1a\u8acb\u5c07\u5c65\u6b77\u8868\u6216\u8077\u4f4d\u7533\u8acb\u8868 (\u7533\u8acb\u8868\u53ef\u65bc\u672c\u6703\u7db2\u9801http://www.sage.org.hk\u4e4b\u300c\u95dc\u65bc\u6211\u5011\u300d\uff0d\u300c\u4e0b\u8f09\u8868\u683c\u300d\uff0d\u300c\u8077\u4f4d\u7533\u8acb\u8868\u683c\u300d\u4e0b\u8f09) \u90f5\u5bc4\u81f3\u65b0\u754c\u8343\u7063\u77f3\u570d\u89d2\u90a8\u77f3\u84ee\u6a13\u4e8c\u6a13\u8006\u5eb7\u6703\u77f3\u570d\u89d2\u8b77\u7406\u5b89\u8001\u9662\u9662\u9577\u6536\u6216\u96fb\u90f5\u81f3Apply Now\uff0c\u4e26\u8a3b\u660e\u8981\u6c42\u85aa\u91d1\u53ca\u65bc\u4fe1\u5c01\u9762\u8a3b\u660e\u7533\u8acb\u8077\u4f4d\u53ca\u8077\u4f4d\u7de8\u865f\uff0c\u67e5\u8a62\u96fb\u8a71\uff1a2498 0423\u3002\n\n\u622a\u6b62\u7533\u8acb\u65e5\u671f\uff1a2022\u5e741\u670824\u65e5\n\n\u672c\u6703\u63d0\u4f9b\u5b8c\u5584\u798f\u5229\uff0c\u5305\u62ec\uff1a\u91ab\u7642\u4fdd\u96aa\u3001\u6700\u9ad810% \u5f37\u7a4d\u91d1\u50f1\u4e3b\u4f9b\u6b3e\u53ca\u5c08\u696d\u57f9\u8a13\u7b49\u3002\n\n\u4e00\u5207\u7533\u8acb\u8cc7\u6599\u7d55\u5c0d\u4fdd\u5bc6\u53ca\u53ea\u7528\u4f5c\u62db\u8058\u6709\u95dc\u8077\u4f4d\uff0c\u672a\u7372\u7d04\u898b\u8005\uff0c\u4f5c\u843d\u9078\u8ad6\uff0c\u6055\u4e0d\u53e6\u51fd\u901a\u77e5\u3002\u800c\u7533\u8acb\u4eba\u4e4b\u500b\u4eba\u8cc7\u6599\u4ea6\u5c07\u5728\u5b8c\u6210\u62db\u8058\u7a0b\u5e8f\u5f8c\u92b7\u6bc0\u3002", "employment_types": ["Full Time", "Contract"], "selling_points": [], "locations": ["Tsuen Wan Area"], "categories": ["Accounting", "Accounting Clerk / Supervisor"], "post_time": "2022-01-15T19:11:26Z", "salary": {"currency": null, "max": null, "min": null, "period": "monthly", "term": null}, "salary_visible": false, "title_keywords": ["accounting clerk"], "responsibilities": [], "requirements": {"degrees": [], "majors": [], "languages": [], "language_level": [], "hard_skills": [], "soft_skills": [], "languages_combined": []}, "experience_required": {"duration": [], "field": []}}, {"job_id": "100003009049015", "location_code": "hk", "company": "PHM Contracting Co. Limited", "job_title": "Accounting Assistant", "description": "Responsibilities:\n\nResponsible for general accounting duties such as A/P, A/R, journal, and bank reconciliation\nTo prepare payment and receipt vouchers\nTo issue invoices, cheques, and receipts\nData input of accounting entries\nEnsure data input in a timely and accurate manner\nAssist in preparing accounting schedule and daily worker payroll\nPerform other ad hoc duties when required\n\nRequirements:\n\nl\u00a0\u00a0 Diploma or above in Accounting\n\nl\u00a0\u00a0 Holder of LCCI Intermediate or above\n\nl\u00a0\u00a0 Minimum 2 years\u2019 accounting experience\n\nl\u00a0\u00a0 Able to work independently, and Initiative-taking\n\nl\u00a0\u00a0 Experience in Peachtree is preferred\n\nl\u00a0\u00a0 Familiar with MS Word and Excel\n\n\nInterested candidates please send your full resume with expected salary by clicking 'Apply Now'\n\n(Personal data collected will be used for recruitment purpose only.)", "employment_types": ["Full Time"], "selling_points": ["Responsible for full set of accounts", "Able to work independently, Initiative-taking", "Experience in construction field is an advantage"], "locations": ["Kwun Tong"], "categories": ["Accounting", "Accountant", "Accounting Clerk / Supervisor", "Others"], "post_time": "2022-01-17T03:55:33Z", "salary": {"currency": null, "max": null, "min": null, "period": "monthly", "term": null}, "salary_visible": false, "title_keywords": ["accounting assistant"], "responsibilities": ["ad hoc duties", "invoices", "receipts", "bank reconciliation", "data input", "payment", "cheques", "general accounting duties", "schedule", "payroll"], "requirements": {"degrees": ["diploma or above"], "majors": ["accounting"], "languages": [], "language_level": [], "hard_skills": ["excel", "peachtree", "ms word"], "soft_skills": ["work independently", "initiative"], "languages_combined": []}, "experience_required": {"duration": ["minimum 2 years"], "field": ["accounting experience"]}}, {"job_id": "100003009053709", "location_code": "hk", "company": "Biel Crystal (HK) Manufactory Limited", "job_title": "Senior Accounting Clerk  -   Kwun Tong near MTR Station", "description": "We are the leading smart phone cover glass supplier in the world. \u00a0Our customers include all the well-known smart phone brands.\u00a0 Due to business needs, we are looking for talents to join our Finance team in Hong Kong.\n\n\u00a0Responsibilities:\n\nAssist in daily accounting duties including but not limited to data input, filing, preparing accounting journal entries, bank reconciliations, etc.\nPrepare monthly financial statements for overseas branch, schedules and analysis\nLiaise with China and overseas colleagues in monthly inter-company transactions reconciliation\nProcess data input in system and perform testing when implementation of new functions in system\nAssist in all ad-hoc assignments\n\nRequirements:\n\nReasonable level of accounting knowledge\n2 years accounting experience is preferred\nStrong communication and interpersonal skills to interact with people at different levels\nAble to work in a fast pace working environment\nProficient in MS Office (Word, Excel), Chinese Word processing\nGood command of both written and spoken English\nAbility to speak Chinese Putonghua is necessary\nRecent university graduate in business will also be considered\nImmediately available is preferred\n\nWork location is in Kwun Tong near MTR Station.\u00a0 We offer good career prospects with an attractive salary remuneration including double-pay,\u00a0discretionary bonus and\u00a0medical insurance\u00a0to the right candidate. \u00a0\n\n(Applicants not contacted within six weeks should consider their application unsuccessful. \u00a0Personal data provided by applicants will be strictly used for recruitment purpose only.)", "employment_types": ["Full Time", "Permanent"], "selling_points": [], "locations": ["Kwun Tong"], "categories": ["Accounting", "Accounting Clerk / Supervisor", "Financial Analyst"], "post_time": "2022-01-17T07:23:17Z", "salary": {"currency": null, "max": null, "min": null, "period": "monthly", "term": null}, "salary_visible": false, "title_keywords": ["accounting clerk"], "responsibilities": ["schedules", "ad-hoc assignments", "analysis", "data input", "bank reconciliations", "transactions", "testing", "implementation", "prepare monthly financial statements", "journal entries", "liaise with", "daily accounting"], "requirements": {"degrees": ["university graduate"], "majors": ["business"], "languages": ["putonghua", "english", "chinese"], "language_level": ["good command", "proficient"], "hard_skills": ["excel", "chinese word processing", "word", "ms office"], "soft_skills": ["communication and interpersonal skills"], "languages_combined": [{"language": "putonghua", "language_level": []}, {"language": "english", "language_level": ["good command"]}, {"language": "chinese", "language_level": ["proficient"]}]}, "experience_required": {"duration": ["2 years"], "field": ["accounting experience"]}}, {"job_id": "100003009051881", "location_code": "hk", "company": "Luen Tai Group (China) Limited", "job_title": "Accounting Officer / Assistant Accountant", "description": "Responsibilites:\n-\u00a0Handle\u00a0full\u00a0set\u00a0of\u00a0accounts in HK\n-\u00a0Handle\u00a0AR\u00a0&\u00a0AP\u00a0invoices\u00a0&\u00a0settlement,\u00a0accounts\u00a0reconciliation\n-\u00a0Handle\u00a0bank\u00a0payments\u00a0and\u00a0receipts\u00a0including\u00a0L/C\n-\u00a0Prepare\u00a0timely\u00a0cash flow\u00a0statement to top management\n-\u00a0Maintain\u00a0up-to-date\u00a0data\u00a0in\u00a0accounting\u00a0system\u00a0and\u00a0filing\u00a0records\n-\u00a0Assist\u00a0in\u00a0preparing\u00a0month\u00a0end\u00a0closing\u00a0reports\u00a0and\u00a0annual\u00a0audit\n-\u00a0Handle\u00a0ad\u00a0hoc\u00a0projects\u00a0as\u00a0required\n-\u00a0Report\u00a0to\u00a0Accounting\u00a0Manager\n\n\n\nRequirements:\n- Diploma or above in Accounting\n- 3-5 years or above accounting experience\n- Membership of professional group is essential\n- PRC manufacturing experience would be an advantage\n- Proficiency in using MS office, knowledge of\u00a0 ERP system is a plus\n- Mature, responsible, detailed mind with ability to handle multiple tasks independently under pressure\n- Strong organization, good interpersonal and communication skills\n- Good command of both written and spoken in English, Cantonese and Mandarin\n- Immediate available or short notice is highly preferable\n\nWe offer the competitive remuneration to right candidates. Applicant with more experience or qualification will be considered as \"Assistant Accountant\"\n\nInterest parties please send us full resume & expected salary to us.\n\n\"Personal data collected will be used for recruitment purpose only.\"", "employment_types": ["Full Time"], "selling_points": [], "locations": ["Wong Tai Sin Area"], "categories": ["Accounting", "Accountant", "Accounting Clerk / Supervisor", "Chief Accountant"], "post_time": "2022-01-17T01:26:15Z", "salary": {"currency": null, "max": null, "min": null, "period": "monthly", "term": null}, "salary_visible": false, "title_keywords": ["assistant accountant", "accounting officer"], "responsibilities": ["ap", "management", "month end closing", "invoices", "ar", "receipts", "data", "annual audit", "full set of accounts", "cash flow", "maintain", "payments", "reports", "ad hoc projects", "report"], "requirements": {"degrees": ["diploma or above"], "majors": ["accounting"], "languages": ["cantonese", "english", "mandarin"], "language_level": ["good command"], "hard_skills": ["prc manufacturing", "erp system", "plus", "ms office"], "soft_skills": ["communication skills", "independently", "under pressure", "responsible", "mature", "handle multiple tasks", "detailed mind", "interpersonal"], "languages_combined": [{"language": "cantonese", "language_level": ["good command"]}, {"language": "english", "language_level": ["good command"]}, {"language": "mandarin", "language_level": ["good command"]}]}, "experience_required": {"duration": ["3-5 years"], "field": ["accounting experience", "manufacturing"]}}, {"job_id": "100003009052559", "location_code": "hk", "company": "Precious Blood Hospital (Caritas)", "job_title": "\u52a9\u7406\u6587\u54e1 (\u8cec\u6236\u670d\u52d9)", "description": "\u8077\u8cac\uff1a\n\n\u8655\u7406\u4f4f\u9662\u75c5\u4eba\u8cec\u6236\u670d\u52d9\u53ca\u6536\u8cbb\u7a0b\u5e8f\uff1b\n\u5354\u52a9\u89e3\u7b54\u4e00\u822c\u8cec\u55ae\u554f\u984c\uff1b\n\u8655\u7406\u4e00\u822c\u6587\u66f8\u5de5\u4f5c\u3001\u5982\u8cc7\u6599\u8f38\u5165\u53ca\u6587\u4ef6\u5b58\u6a94\uff1b\n\u63a5\u807d\u96fb\u8a71\u53ca\u8ca0\u8cac\u65e5\u5e38\u806f\u7d61\u5de5\u4f5c\uff1b\n\u8ffd\u6536\u5ba2\u6236\u53ca\u4fdd\u96aa\u516c\u53f8\u5230\u671f\u8cec\u55ae\u3002\n\n\u00a0\u8077\u4f4d\u8981\u6c42\uff1a\n\n\u4e2d\u4e94\u7a0b\u5ea6\u6216\u4ee5\u4e0a\uff1b\n\u81f3\u5c11\u5169\u5e74\u76f8\u95dc\u5de5\u4f5c\u7d93\u9a57\uff1b\n\u6709\u79ae\u8c8c\uff0c\u826f\u597d\u6e9d\u901a\u6280\u5de7\uff1b\n\u80fd\u7368\u7acb\u5de5\u4f5c\u3001\u5de5\u4f5c\u9808\u7d30\u5fc3\u53ca\u8ca0\u8cac\u4efb\uff1b\n\u719f\u6089\u5fae\u8edf Office (Word , Excel), \u6709\u6578\u64da\u5eab\u7ba1\u7406\u7d93\u9a57\u512a\u5148\u8003\u616e\uff1b\n\u9808\u8f2a\u73ed\u5de5\u4f5c\u3002", "employment_types": ["Full Time"], "selling_points": [], "locations": ["Sham Shui Po"], "categories": ["Accounting", "Accounting Clerk / Supervisor"], "post_time": "2022-01-17T03:25:12Z", "salary": {"currency": null, "max": null, "min": null, "period": "monthly", "term": null}, "salary_visible": false, "title_keywords": ["\u52a9\u7406\u6587\u54e1"], "responsibilities": [], "requirements": {"degrees": [], "majors": [], "languages": [], "language_level": [], "hard_skills": ["excel", "word"], "soft_skills": [], "languages_combined": []}, "experience_required": {"duration": [], "field": []}}, {"job_id": "100003009054708", "location_code": "hk", "company": "Sky Base Investments Limited", "job_title": "Senior Accounts Clerk", "description": "Key Responsibilities:\n\nPerform data input into ERP Accounting & Retail system;\u00a0\u00a0\nMainly responsible for A/P section, bills settlement & maintain bank books;\nAssist in preparing various simple reports, accounting schedules and bank reconciliation;\nFull set of account experience is definite advantage;\nPerform other ad hoc tasks as assigned.\n\n\u00a0Job Requirements:\n\nF.5 with LCCI Inter or above;\nAt least 5 years\u2019 solid experience in accounting or auditing;\nExperience in Accounting & ERP system is a definite advantage;\nRetail accounting experience is definite advantage;\nStrong sense of responsibility, hardworking and willing to\u00a0LEARN;\nProficiency in MS office, especially Excel spreadsheet & outlook;\nQuick typing skill on both Chinese and English;\nImmediately available is highly preferred.\n\nWe offer permanent job with basically 5-day work per week, excellent career opportunities and remuneration package to the right candidates. Interested parties please apply with\u00a0detailed resume,\u00a0salary expected,\u00a0contact numbers\u00a0in strict confidence and quoting reference in your application by clicking \u201cApply Now\u201d.\n\nAll information provided will be treated in strict confidence and only be used for recruitment purposes.\u00a0\u00a0Candidates without salary expectation will not be considered.", "employment_types": ["Full Time", "Permanent"], "selling_points": [], "locations": ["Shatin Area"], "categories": ["Accounting", "Accountant", "Accounting Clerk / Supervisor"], "post_time": "2022-01-17T10:39:53Z", "salary": {"currency": null, "max": null, "min": null, "period": "monthly", "term": null}, "salary_visible": false, "title_keywords": ["senior accounts clerk"], "responsibilities": ["schedules", "ad hoc tasks", "data input", "bank reconciliation", "maintain", "reports"], "requirements": {"degrees": [], "majors": [], "languages": ["english", "chinese"], "language_level": [], "hard_skills": ["excel", "typing", "erp system", "outlook", "spreadsheet", "ms office"], "soft_skills": ["willing to learn", "hardworking", "sense of responsibility"], "languages_combined": [{"language": "english", "language_level": []}, {"language": "chinese", "language_level": []}]}, "experience_required": {"duration": ["at least 5 years"], "field": ["accounting experience", "erp system", "accounting", "retail"]}}, {"job_id": "100003009049732", "location_code": "hk", "company": "Jackel Porter Co Ltd", "job_title": "Accounts Clerk", "description": "Responsibilities\n\nProcurement or ordering of sales items\nBank reconciliation\nData entries\nStock ledger control\nAccounts payable\nPrepare accounts breakdowns\nAd-hoc assignments by the manager\nRequirements\u00a0\n\nF5/DSE or above\nLCC Intermediate or above\n2 years working experience with experience in accounting\nDetail-oriented and good communication skills\nGood command in English, Cantonese, and Mandarin\nFamiliar MS Words & Excel\nShort notice or immediate available is preferred", "employment_types": ["Full Time"], "selling_points": ["Accounting experience", "LCCI", "Free shuttle bus"], "locations": ["Tai Po Area"], "categories": ["Accounting", "Accounting Clerk / Supervisor"], "post_time": "2022-01-14T09:10:30Z", "salary": {"currency": null, "max": null, "min": null, "period": "monthly", "term": null}, "salary_visible": false, "title_keywords": ["accounts clerk"], "responsibilities": ["control", "data", "ad-hoc assignments", "bank reconciliation", "accounts payable"], "requirements": {"degrees": ["dse"], "majors": [], "languages": ["cantonese", "english", "mandarin"], "language_level": ["good command"], "hard_skills": ["excel", "lcc", "ms words"], "soft_skills": ["communication skills", "detail-oriented"], "languages_combined": [{"language": "cantonese", "language_level": ["good command"]}, {"language": "english", "language_level": ["good command"]}, {"language": "mandarin", "language_level": ["good command"]}]}, "experience_required": {"duration": ["2 years"], "field": ["accounting"]}}, {"job_id": "100003009052598", "location_code": "hk", "company": "Takasago Thermal Engineering (Hong Kong) Co Ltd", "job_title": "Account Clerk / Senior Account Clerk", "description": "\u00a0Responsibilities:\n\nResponsible for routine accounting operation\nPrepare monthly financial reports\nAssist senior to prepare for both local & Japan audit accounting\n\nRequirements:\n\nDegree / High diploma in\u00a0Accounting or equivalent;\nKnowledge of MYOB accounting system\nFluent spoken and written English and Cantonese\nProficient in Microsoft\u00a0Excel, Word\nIndependent, hardworking, organized, self-motivated and strong sense of responsibility\n1 - 2 years\u00a0relevant accounting experiences\n\nSalary / Allowance:\n\nCompetitive remuneration package consist of 12 days annual leave, 5.5 days per week (long/short week Saturday), travel allowance and group medical / life insurance, double payment and etc.\n\nApplication Method\n\nInterested parties please send full resume with expected salary to us.\u00a0\n\nTarget Commencement Date: Immediate available is highly preferred\u00a0", "employment_types": ["Full Time", "Permanent"], "selling_points": ["12 days annual leave, bank holidays", "End of year payment", "5/ 5.5 days work"], "locations": ["Sheung Wan"], "categories": ["Accounting", "Accountant", "Accounting Clerk / Supervisor"], "post_time": "2022-01-17T03:30:17Z", "salary": {"currency": null, "max": null, "min": null, "period": "monthly", "term": null}, "salary_visible": false, "title_keywords": ["account clerk", "senior account clerk"], "responsibilities": ["financial reports", "audit"], "requirements": {"degrees": ["high diploma", "degree"], "majors": ["accounting"], "languages": ["cantonese", "english"], "language_level": ["fluent"], "hard_skills": ["myob", "word", "accounting system", "microsoft excel"], "soft_skills": ["organized", "self-motivated", "independent", "sense of responsibility", "hardworking"], "languages_combined": [{"language": "cantonese", "language_level": ["fluent"]}, {"language": "english", "language_level": ["fluent"]}]}, "experience_required": {"duration": ["1 - 2 years"], "field": ["accounting"]}}, {"job_id": "100003009052692", "location_code": "hk", "company": "Sunlight Jewelers Limited", "job_title": "Accounts Clerk", "description": "Responsibilities & Requirements \u8077\u8cac\u53ca\u8981\u6c42\n\n-\u00a0\u00a0\u00a0\u00a0\u00a0\u00a0\u00a0 Around 3 years relevant experience, preferable in Jewellery industry\n\n-\u00a0\u00a0\u00a0\u00a0\u00a0\u00a0\u00a0 Handle AR Collection & AP Payment, assist in month-end closing & follow up outstanding Receivables\n\n-\u00a0\u00a0\u00a0\u00a0\u00a0\u00a0\u00a0 Basic proficiency in English, Cantonese and Mandarin\n\n-\u00a0\u00a0\u00a0\u00a0\u00a0\u00a0\u00a0 Other ad hoc task assigned by management\n\n-\u00a0\u00a0\u00a0\u00a0\u00a0\u00a0\u00a0 Form 5 graduate or above\n\n-\u00a0\u00a0\u00a0\u00a0\u00a0\u00a0\u00a0 Familiar with using MYOB or PJS is an advantage\n\n-\u00a0\u00a0\u00a0\u00a0\u00a0\u00a0\u00a0 Well organized, self-motivated & responsible\n\n\n\nWe offer 5 \u00bd-day work, Medical Scheme & Bank holidays to the right candidate.\u00a0 Interested parties, please send FULL RESUME with expected salary to: apply now", "employment_types": ["Full Time"], "selling_points": [], "locations": ["Hung Hom"], "categories": ["Accounting", "Accounting Clerk / Supervisor", "Others", "Admin & HR", "Clerical / Admin Staff"], "post_time": "2022-01-17T03:55:51Z", "salary": {"currency": null, "max": null, "min": null, "period": "monthly", "term": null}, "salary_visible": false, "title_keywords": ["accounts clerk"], "responsibilities": [], "requirements": {"degrees": ["form 5"], "majors": [], "languages": ["cantonese", "english", "mandarin"], "language_level": ["proficiency", "basic"], "hard_skills": ["ap", "myob", "basic", "ar"], "soft_skills": ["self-motivated", "well organized", "responsible"], "languages_combined": [{"language": "cantonese", "language_level": ["proficiency", "basic"]}, {"language": "english", "language_level": ["proficiency", "basic"]}, {"language": "mandarin", "language_level": ["proficiency", "basic"]}]}, "experience_required": {"duration": ["3 years"], "field": ["relevant experience"]}}, {"job_id": "100003009054931", "location_code": "hk", "company": "N&W Group (International) Limited", "job_title": "Accounting Clerk / \u6703\u8a08\u6587\u54e1", "description": "Company Brief Introduction:\n\nNutritionus (FB/IG: thenutritionus)\n\nWe focus on selling fresh goods, healthy snacks, and nutrition products\nWe promote and educate fitness and healthy lifestyle (IG: thenutritionus)\nOur Headquarter (working location) is at Fo Tan, N.T.\n\nWhat will you be doing:\n\nBook keeping, accounting related paper work\nMaintain office systems, data management, filing, utilities payment\nAssist in billing & auditing process\nAttend to incoming emails, and redirecting it to corresponding staff if necessary\nManage courier services, stationary inventories, office equipment maintenance etc.\nAttendance and salary management\nManage tasks allocate by manager\nAid in company\u2019s daily opertaion\n\nWhat you need for this position:\n\nProficient in English and Mandarin.\nCheerful, self-driven, a good team player.\nBook keeping/accounting related academic background\nProficient in using MS Office include Chinese word processing\nHaving accounting experience/certificate would be an asset\nFresh graduate candidate is always welcomed.\nHaving clerical experience would be an asset\nHaving accounting software experience would be an asset", "employment_types": ["Full Time"], "selling_points": ["accounting experience/certificate would be asset", "Bookkeeping/accounting related academic background", "Fresh graduate candidate is always welcomed"], "locations": ["Shatin Area"], "categories": ["Accounting", "Accounting Clerk / Supervisor"], "post_time": "2022-01-17T14:22:18Z", "salary": {"currency": null, "max": null, "min": null, "period": "monthly", "term": null}, "salary_visible": false, "title_keywords": ["accounting clerk"], "responsibilities": ["attendance", "management", "software", "data", "systems", "payment", "maintain", "office equipment maintenance", "auditing"], "requirements": {"degrees": ["certificate", "fresh graduate"], "majors": ["accounting"], "languages": ["english", "chinese", "mandarin"], "language_level": ["proficient"], "hard_skills": ["chinese word processing", "data management", "maintenance", "accounting software", "focus", "ms office"], "soft_skills": ["good team player", "focus", "cheerful", "driven"], "languages_combined": [{"language": "english", "language_level": ["proficient"]}, {"language": "chinese", "language_level": []}, {"language": "mandarin", "language_level": ["proficient"]}]}, "experience_required": {"duration": [], "field": ["accounting experience", "accounting", "clerical"]}}, {"job_id": "100003009052794", "location_code": "hk", "company": "Ferrari Logistics (Asia) Ltd", "job_title": "Accounts Clerk", "description": "Job Descriptions:\n\nAccounts receivables, invoicing and general accounting duties.\nWork closely with other department for daily operations.\nFiling and data entries.\nPrepare ad-hoc assignment from time to time assigned by Manager.\nRequirements:\nForm 5 or above.\nAt least 1 year of experience in accounting.\nProficiency in computer application, especially in MS Word and Excel.\nHigh threshold for paperwork and detail-minded.\nProficiency in both written and spoken English and Chinese\u00a0(Cantonese and Putonghua).\nImmediate availability is highly preferred.\nInterested parties please submit your FULL RESUME with AVAILABILITY, CURRENT and EXPECTED SALARY by clicking\u00a0APPLY NOW.\nAll information of candidates will be treated as strictly confidential and used for recruitment purposes only.\u00a0\u00a0", "employment_types": ["Full Time", "Permanent"], "selling_points": ["Accounts receivables", "Dynamic culture", "Excellent fringe benefits"], "locations": ["Kwai Hing"], "categories": ["Accounting", "Accounting Clerk / Supervisor", "Admin & HR", "Others"], "post_time": "2022-01-17T04:05:25Z", "salary": {"currency": null, "max": null, "min": null, "period": "monthly", "term": null}, "salary_visible": false, "title_keywords": ["accounts clerk"], "responsibilities": ["ad-hoc", "data", "invoicing", "daily operations", "general accounting duties"], "requirements": {"degrees": ["form 5 or above"], "majors": [], "languages": ["cantonese", "putonghua", "english", "chinese"], "language_level": ["proficiency"], "hard_skills": ["excel", "ms word"], "soft_skills": ["detail-minded"], "languages_combined": [{"language": "cantonese", "language_level": []}, {"language": "putonghua", "language_level": []}, {"language": "english", "language_level": ["proficiency"]}, {"language": "chinese", "language_level": ["proficiency"]}]}, "experience_required": {"duration": ["at least 1 year"], "field": ["accounting"]}}, {"job_id": "100003009053058", "location_code": "hk", "company": "Jibsen Industrial Ltd", "job_title": "Accounting & Admin. Officer", "description": "Hong Kong based company with more than 20 years experience in bag manufacturing URGENTLY requires in our Kwun Tong office:\n\nAccounting & Admin. Officer\n\nResponsibilities:\n\nDaily accounting operations including general journal entries, payments, petty cash, staff reimbursement, preparing monthly reports, etc.\nGeneral office administrative work\nManaging staff attendance and leave record\nAd-hoc assignments\n\nRequirements:\n\nMin. 2 years experience; Fresh graduate will be considered;\nDiploma in accounting;\nProficient in MS Office, Chinese Word Processing;\nPrior experience with ERP is an advantage;\nGood spoken & written English, Chinese & Mandarin;\nAble to work independently, responsible, self-motivated, hardworking & eager to learn;\nImmediate available is preferred.\n\nInterested parties please send resume with salary expected to Jibsen Industrial Ltd by pressing APPLY NOW\n\n(Data collected will be used for recruitment purpose only.)", "employment_types": ["Full Time"], "selling_points": ["5-day work", "Group Medical Insurance", "Annual Leave 11 days"], "locations": ["Kwun Tong"], "categories": ["Accounting", "Accounting Clerk / Supervisor", "Admin & HR", "Clerical / Admin Staff", "Others", "Others"], "post_time": "2022-01-17T05:28:21Z", "salary": {"currency": null, "max": null, "min": null, "period": "monthly", "term": null}, "salary_visible": false, "title_keywords": ["admin", "accounting", "officer"], "responsibilities": ["attendance", "administrative work", "monthly reports", "ad-hoc assignments", "daily accounting operations", "payments", "journal entries"], "requirements": {"degrees": ["diploma", "fresh graduate"], "majors": ["accounting"], "languages": ["english", "chinese", "mandarin"], "language_level": ["good", "proficient"], "hard_skills": ["chinese word processing", "erp", "ms office"], "soft_skills": ["work independently", "self-motivated", "responsible", "eager to learn", "hardworking"], "languages_combined": [{"language": "english", "language_level": ["good"]}, {"language": "chinese", "language_level": ["good", "proficient"]}, {"language": "mandarin", "language_level": ["good"]}]}, "experience_required": {"duration": ["2 years"], "field": []}}, {"job_id": "100003009051808", "location_code": "hk", "company": "Purapharm Corporation Limited", "job_title": "Accounts Clerk", "description": "Job Responsibilities\n\nDaily accounting entries, month-end closing and assist in handling full set of accounts of subsidiaries;\nPerform general daily accounting functions such as A/P, A/R, journal, bank reconciliation, Intercompany reconciliation and etc.;\nAssist in preparing monthly financial statement, costing and related month ended schedules;\nPrepare Sales report;\nParticipate in ad hoc projects and tasks as assigned by Department Head.\n\nRequirements\n\nLCC & I Level 2 or above, Higher Certificate in Accounting is preferred;\n3-5 years of accounting experience preferably in group companies;\nProficient in MS Office;\nExperience in U8+ and Microsoft Dynamic 365 accounting system would be advantage;\nAble to work under pressure;\nStrong communication skills;\nImmediate availabile is preferred.\n\nWorking Location: Hong Kong Science Park, Tai Po, N.T.\n\nWe offer 5-day working week and an attractive remuneration package. Interested party please submit your resume with current and expected salary by clicking \u201cAPPLY NOW\u201d. For company details, please visit www.purapharm.com.\n\nOur company is an equal opportunity employer. All personal data collected will be used for recruitment purpose only, while the personal data of the unsuccessful applicants will be destroyed within 6 months after the recruitment process.", "employment_types": ["Full Time", "Permanent"], "selling_points": ["Listed Company", "Full Set of Accounts", "3-5 Years of Accounting Experience"], "locations": ["Tai Po Area"], "categories": ["Accounting", "Accounting Clerk / Supervisor", "Others"], "post_time": "2022-01-17T01:14:32Z", "salary": {"currency": null, "max": null, "min": null, "period": "monthly", "term": null}, "salary_visible": false, "title_keywords": ["accounts clerk"], "responsibilities": ["schedules", "full set of accounts", "prepare sales", "bank reconciliation", "month-end closing", "ad hoc projects", "financial statement", "daily accounting", "report"], "requirements": {"degrees": ["higher certificate"], "majors": ["accounting"], "languages": [], "language_level": [], "hard_skills": ["dynamic", "lcc", "accounting system", "ms office"], "soft_skills": ["communication skills", "dynamic", "work under pressure"], "languages_combined": []}, "experience_required": {"duration": ["3-5 years"], "field": ["accounting experience", "accounting"]}}, {"job_id": "100003009051987", "location_code": "hk", "company": "Ec InfoTech Limited", "job_title": "Account Clerk", "description": "Responsibilities:\n\nPerform accounting functions including Accounts Receivable, Accounts Payable and Invoicing, etc.;\nHandle administrative work including preparation of payment vouchers and cheque;\nMaintain accounting records and perform data entry;\nAssist in ad-hoc assignments;\nOther duties assigned by supervisor\n\nRequirements:\n\nDiploma or above qualification in accounting or LCCI Intermediate above preferred;\nWith 2 years or above relevant experiences, prefer Property Management field;\nProficiency in MS office application & Chinese WordProcessing;\nProficient in Cantonese and English;\nIndependent, stable, attentive to details, multi-tasking, able to work under pressure and adaptive to given challenges;\nImmediate available is highly preferable\n\nMethod to Apply:\n\nl\u00a0 Interested parties please submit your application with expected salaries and availability to Ec InfoTech Ltd Human Resources Department by clicking to Apply Now.\n\nl\u00a0 \u00a0Data collected will be used for recruitment purpose only and Applicants who are not invited to interview within 2 months may consider their applicants unsuccessful.", "employment_types": ["Full Time"], "selling_points": ["Performs daily clerical job", "Accounting", "Administrative"], "locations": ["Kwun Tong"], "categories": ["Accounting", "Accounting Clerk / Supervisor"], "post_time": "2022-01-17T01:45:50Z", "salary": {"currency": null, "max": null, "min": null, "period": "monthly", "term": null}, "salary_visible": false, "title_keywords": ["account clerk"], "responsibilities": ["administrative work", "accounts receivable", "data entry", "other duties", "ad-hoc assignments", "invoicing", "payment", "maintain", "accounts payable"], "requirements": {"degrees": ["diploma or above"], "majors": ["accounting"], "languages": ["cantonese", "english", "chinese"], "language_level": ["proficiency", "proficient"], "hard_skills": ["ms office"], "soft_skills": ["independent", "attentive to details", "multi-tasking", "stable", "work under pressure"], "languages_combined": [{"language": "cantonese", "language_level": ["proficient"]}, {"language": "english", "language_level": ["proficient"]}, {"language": "chinese", "language_level": ["proficiency"]}]}, "experience_required": {"duration": ["2 years"], "field": ["management"]}}, {"job_id": "100003009052980", "location_code": "hk", "company": "Progressive Timepieces Limited", "job_title": "ACCOUNTS CLERK", "description": "Responsibilities:\n\nResponsible for handle full set of accounts (Bookkeeping, monthly reports, year end reports)\nDaily cash flow management as well as bank and cheque transactions\nUndertake administrative works and daily operations\n\nRequirements:\n\nF.6 or above with LCCI Higher \u00a0\n2 years relevant experience or above \u00a0\nGood command of spoken and written English and Chinese (Mandarin is preferred) \u00a0\nPeachtree Accounting & ERP System & PC Knowledge (MS Word & Excel) \u00a0\nSelf-motivated, organized and detail oriented \u00a0\nStationed in Hong Kong\n5 days work\n\nInterested parties please send full resume with expected salary by clicking \"Apply Now\"\u00a0", "employment_types": ["Full Time"], "selling_points": ["KWAI CHUNG AREA", "5 DAYS WORK", "GROUP MEDICAL"], "locations": ["Kwai Hing"], "categories": ["Accounting", "Accounting Clerk / Supervisor"], "post_time": "2022-01-17T07:13:15Z", "salary": {"currency": null, "max": null, "min": null, "period": "monthly", "term": null}, "salary_visible": false, "title_keywords": ["accounts clerk"], "responsibilities": ["management", "monthly reports", "full set of accounts", "transactions", "cash flow", "daily operations", "reports"], "requirements": {"degrees": [], "majors": [], "languages": ["english", "chinese", "mandarin"], "language_level": ["good command"], "hard_skills": ["excel", "erp system", "peachtree", "pc knowledge", "ms word"], "soft_skills": ["organized", "self-motivated", "detail oriented"], "languages_combined": [{"language": "english", "language_level": ["good command"]}, {"language": "chinese", "language_level": ["good command"]}, {"language": "mandarin", "language_level": ["good command"]}]}, "experience_required": {"duration": ["2 years"], "field": ["relevant experience"]}}, {"job_id": "100003009053932", "location_code": "hk", "company": "Prince Jewellery and Watch Company Limited", "job_title": "Accounts Assistant/ Accounts Clerk", "description": "We are now seeking a high caliber\u00a0candidate to join our expanding family with the following responsibilities:\n\nResponsibilities:\n\nSupporting AR & AP functions\nPreparing reconciliation for shop daily sales and accounts receivable\nHandling daily accounting duties including voucher preparing, cheque issuing, refund to customer, bank reconciliation and documents filing\nParticipating in ad-hoc duties as assigned\n\nRequirements:\n\nHigher Diploma or above in Accounting or related disciplines\n2 years' relevant experience preferably in retail industry\nKnowledge in using Microsoft Window AX\u00a0will be an advantage\nProficient\u00a0in Microsoft Office (MS Word, Excel, Chinese WP)\nGood command of spoken and written English and Chinese\nImmediately available is preferred\nCandidate with less experience will be considered as Accounts Clerk\n\nWe offer attractive remuneration package to successful candidates. Interested parties please send full resume by clicking \"Apply Now\"\u00a0or by mail to Room 1729-30, Star House, 3 Salisbury Road, T.S.T, H.K.\n\nAll information received will be treated strictly confidential and for employment purpose only\u00a0", "employment_types": ["Full Time", "Permanent"], "selling_points": ["Supporting AR & AP functions", "Preparing reconciliation for shop daily sales", "Handling daily accounting duties"], "locations": ["Tsim Sha Tsui"], "categories": ["Accounting", "Accounting Clerk / Supervisor"], "post_time": "2022-01-17T07:47:49Z", "salary": {"currency": null, "max": null, "min": null, "period": "monthly", "term": null}, "salary_visible": false, "title_keywords": ["accounts clerk", "accounts assistant"], "responsibilities": ["ap", "documents filing", "ar", "accounts receivable", "bank reconciliation", "ad-hoc duties", "daily accounting"], "requirements": {"degrees": ["higher diploma or above"], "majors": ["related disciplines", "accounting"], "languages": ["english", "chinese"], "language_level": ["good command", "proficient"], "hard_skills": ["ms word", "excel", "chinese wp", "microsoft office"], "soft_skills": [], "languages_combined": [{"language": "english", "language_level": ["good command"]}, {"language": "chinese", "language_level": ["good command", "proficient"]}]}, "experience_required": {"duration": ["2 years"], "field": ["retail industry", "relevant experience"]}}, {"job_id": "100003009054906", "location_code": "hk", "company": "Eugina Limited", "job_title": "Accounts Clerk", "description": "Trading Company in Kwai Chung invites candidates for the following post:\n\n\u00a0Accounts Clerk\n\n\u00a0Job Responsibilities:\n\nPerform daily accounting duties, including prepare payment, receipt and journal vouchers, documents filing and full spectrum of book-keeping and accounting work;\nPrepare monthly accounting schedules, bank reconciliations and reconcile intercompany balance and transactions;\nAssist in month/year-end financial reporting, stocktaking and etc.; and\nAd hoc assignments as required.\n\nRequirements:\n\n\nForm 5 or above with LCC&I 3rd Level or above with min. 3 years relevant working experience;\nProficient in MS Office, advanced Excel skills would be an advantage and experience in using ERP;\nGood command of spoken/written English and Chinese;\nMature, pro-active, strong sense of responsibility, analytical & detail-minded, able to work independently and good team player;\nImmediate available is highly preferred.\n\nInterested parties, please send your full resume stating career history, qualifications, current and expected salary, and availability to us by click \u201cApply Now\u201d to submit your application.", "employment_types": ["Full Time", "Permanent"], "selling_points": [], "locations": ["Kwai Tsing Area"], "categories": ["Accounting", "Accounting Clerk / Supervisor", "Others"], "post_time": "2022-01-17T13:31:10Z", "salary": {"currency": null, "max": null, "min": null, "period": "monthly", "term": null}, "salary_visible": false, "title_keywords": ["accounts clerk"], "responsibilities": ["journal vouchers", "documents filing", "year-end", "schedules", "bank reconciliations", "transactions", "payment", "book-keeping", "financial reporting", "ad hoc assignments", "daily accounting"], "requirements": {"degrees": ["form 5 or above"], "majors": [], "languages": ["english", "chinese"], "language_level": ["good command"], "hard_skills": ["excel", "erp", "ms office"], "soft_skills": ["detail-minded", "work independently", "good team player", "advanced", "sense of responsibility", "mature", "pro-active"], "languages_combined": [{"language": "english", "language_level": ["good command"]}, {"language": "chinese", "language_level": ["good command"]}]}, "experience_required": {"duration": ["3 years"], "field": ["relevant working experience"]}}, {"job_id": "100003009054793", "location_code": "hk", "company": "Sage Dignity Services Limited", "job_title": "ACCOUNTS CLERK", "description": "Responsibilities\n\nHandle full set accounting and month end closing;\nPrepare full set of accounts including general ledger, accounts receivable and accounts payable;\nPrepare management reports and financial analysis on a timely basis;\nAssist in reviewing Taiwan and Macau companies\u2019 management reports;\nAssist in annual audit, final accounts and budget;\nOther ad hoc tasks as assigned.\n\nRequirements\n\nDegree holder in Accounting, Finance or related discipline;\n5 years relevant experience;\nFamiliar with MS office, particularly in MS Excel and word;\nAble to work independently and under pressure;\nSelf-motivated, detail oriented, strong sense of responsibility and multi-tasked;\nGood interpersonal, communication, analytical and problem-solving skills;\nGood communication in both English, Chinese and Mandarin.", "employment_types": ["Full Time", "Permanent"], "selling_points": ["Degree holder in Accounting", "5 years relevant experience", "Handle full set accounting"], "locations": ["Kwun Tong"], "categories": ["Accounting", "Accounting Clerk / Supervisor"], "post_time": "2022-01-17T11:06:25Z", "salary": {"currency": null, "max": null, "min": null, "period": "monthly", "term": null}, "salary_visible": false, "title_keywords": ["accounts clerk"], "responsibilities": ["month end closing", "handle full set accounting", "accounts receivable", "annual audit", "general ledger", "full set of accounts", "budget", "ad hoc tasks", "financial analysis", "management reports", "accounts payable"], "requirements": {"degrees": ["degree holder"], "majors": ["finance", "accounting"], "languages": ["english", "chinese", "mandarin"], "language_level": ["good"], "hard_skills": ["problem-solving skills", "ms excel", "word", "ms office"], "soft_skills": ["work independently", "self-motivated", "under pressure", "sense of responsibility", "detail oriented", "communication", "multi-tasked", "problem-solving skills", "interpersonal"], "languages_combined": [{"language": "english", "language_level": ["good"]}, {"language": "chinese", "language_level": ["good"]}, {"language": "mandarin", "language_level": ["good"]}]}, "experience_required": {"duration": ["5 years"], "field": ["relevant experience"]}}, {"job_id": "100003009053097", "location_code": "hk", "company": "Winon Industrial Company Limited", "job_title": "\u6703\u8a08 (Accounting Clerk)", "description": "\n\u4e3b\u8981\u8ca0\u8cac\u9999\u6e2f\u6703\u8a08\u5168\u76e4\u8cec\u76ee.\n\u5de5\u4f5c\u5305\u62ec\u8655\u7406\u65e5\u5e38\u5982\u7cfb\u7d71\u8cc7\u6599\u8f38\u5165\u7b49, \u61c9\u6536,\u61c9\u4ed8, \u51fa\u7ce7, \u9280\u884c\u67e5\u5e33/\u5c0d\u5e33 \u548c \u7e3d\u5e33;\n\u9700\u5b89\u6392\u6bcf\u6708\u7d50\u7b97, \u92b7\u552e\u4f63\u91d1, \u5206\u6790\u5831\u8868, \u5831\u92b7\u55ae\u64da, \u5168\u5957\u5e33\u6236, \u8ca1\u52d9\u5831\u544a\u548c\u7e3d\u5e33;\n\u9700\u4e0d\u5b9a\u6642\u8207\u6703\u8a08\u5e2b\u6e9d\u901a\u5b8c\u6210\u6bcf\u5e74\u5be9\u8a08\u53ca\u4e3b\u7ba1\u59d4\u6d3e\u4e4b\u5de5\u4f5c.\n\u53e6\u9700\u8655\u7406\u65e5\u5e38\u884c\u653f\u4e8b\u52d9, \u63a1\u8cfc\u548c\u9032\u51fa\u53e3\u5831\u95dc.", "employment_types": ["Full Time"], "selling_points": [], "locations": ["Kwai Hing"], "categories": ["Accounting", "Accounting Clerk / Supervisor"], "post_time": "2022-01-17T05:47:59Z", "salary": {"currency": null, "max": null, "min": null, "period": "monthly", "term": null}, "salary_visible": false, "title_keywords": ["accounting clerk"], "responsibilities": [], "requirements": {"degrees": [], "majors": [], "languages": [], "language_level": [], "hard_skills": [], "soft_skills": [], "languages_combined": []}, "experience_required": {"duration": [], "field": []}}, {"job_id": "100003009053717", "location_code": "hk", "company": "\u827e\u838e\u96c6\u5718\u6709\u9650\u516c\u53f8", "job_title": "Accounting Clerk", "description": "Responsibilities:\n\nDaily accounting operations including general journal entries, payments, petty cash, staff reimbursement, preparing monthly reports, etc.\nMonitor daily sales transactions are in line with compliance and company policy\nProcess monthly payroll, final payment and MPF for both front & back office employees\nLiaise with auditors for audit matters of the Hong Kong companies\nGeneral office administrative work\nManaging staff attendance and leave record\nAd-hoc assignments\n\nRequirements:\n\nMin. 2 years experience;\nDiploma in accounting is preferred;\nProficient in MS Office, Chinese Word Processing;\nGood spoken & written English & Chinese\u00a0\nAble to work independently, responsible, self-motivated, hardworking & eager to learn;\nImmediate available is preferred.\n\nBenefits:\n\nCompetitive salary package and benefits\nDiscretionary Bonus\nBirthday pocket money\nComprehensive medical insurance\nStaff intimate welfare\nBanking Holidays\n12-14 days Annual leave\nInterested parties please send resume with salary expected to ALYSSA\u00a0or by pressing APPLY NOW\n", "employment_types": ["Full Time"], "selling_points": ["Comprehensive medical insurance", "12 days annual leave", "Banking Holidays"], "locations": ["Lai Chi Kok"], "categories": ["Accounting", "Accountant", "Accounting Clerk / Supervisor"], "post_time": "2022-01-17T07:25:44Z", "salary": {"currency": "HKD", "max": 24999, "min": 17000, "period": "monthly", "term": null}, "salary_visible": true, "title_keywords": ["accounting clerk"], "responsibilities": ["attendance", "mpf", "administrative work", "monthly reports", "ad-hoc assignments", "compliance", "monitor", "daily accounting operations", "transactions", "back office", "audit", "payment", "payments", "journal entries", "liaise with", "payroll"], "requirements": {"degrees": ["diploma"], "majors": ["accounting"], "languages": ["english", "chinese"], "language_level": ["good", "proficient"], "hard_skills": ["chinese word processing", "ms office"], "soft_skills": ["work independently", "self-motivated", "responsible", "eager to learn", "hardworking"], "languages_combined": [{"language": "english", "language_level": ["good"]}, {"language": "chinese", "language_level": ["good", "proficient"]}]}, "experience_required": {"duration": ["2 years"], "field": []}}, {"job_id": "100003009044767", "location_code": "hk", "company": "The Hong Kong Society for the Aged", "job_title": "\u6703\u8a08\u6587\u54e1Accounting Clerk (\u8077\u4f4d\u7de8\u865f\uff1aACC - 220102)", "description": "\u8ca0\u8cac\u6587\u66f8\u53ca\u5168\u76e4\u6703\u8a08\u5de5\u4f5c\n\u4e2d\u4e94\u6216\u4ee5\u4e0a\u7a0b\u5ea6\n2\u5e74\u6216\u4ee5\u4e0a\u6703\u8a08\u7d93\u9a57\n\u6301\u6709\u521d\u7d1a\u7c3f\u8a18\u8b49\u66f8\u53ca\u6709\u904b\u7528\u7532\u9aa8\u6587(Oracle)\u6703\u8a08\u8edf\u4ef6\u7d93\u9a57\u512a\u5148\u8003\u616e\n\u5165\u8077\u85aa\u916c\u70ba$14,410\u6216\u6309\u76f8\u95dc\u5e74\u8cc7\u8a08\u7b97\n\u8343\u8475\u9752\u7d9c\u5408\u5bb6\u5c45\u7167\u9867\u670d\u52d9\uff08\u8475\u6d8c\u5927\u7aa9\u53e3\u90a8\uff09\u5de5\u4f5c\n\n\u7533\u8acb\u8fa6\u6cd5\uff1a\u8acb\u5c07\u5c65\u6b77\u8868\u6216\u8077\u4f4d\u7533\u8acb\u8868 (\u7533\u8acb\u8868\u53ef\u65bc\u672c\u6703\u7db2\u9801http://www.sage.org.hk\u4e4b\u300c\u95dc\u65bc\u6211\u5011\u300d\uff0d\u300c\u4e0b\u8f09\u8868\u683c\u300d\uff0d\u300c\u8077\u4f4d\u7533\u8acb\u8868\u683c\u300d\u4e0b\u8f09) \u90f5\u5bc4\u81f3\u65b0\u754c\u8475\u6d8c\u5927\u7aa9\u53e3\u90a8\u5bcc\u9038\u6a13\u5730\u4e0b\u8006\u5eb7\u6703\u8343\u8475\u9752\u7d9c\u5408\u5bb6\u5c45\u7167\u9867\u670d\u52d9\u4e2d\u5fc3\u4e3b\u4efb\u6536\u6216\u96fb\u90f5\u81f3Apply Now\uff0c\u4e26\u8a3b\u660e\u8981\u6c42\u85aa\u91d1\u53ca\u65bc\u4fe1\u5c01\u9762\u8a3b\u660e\u7533\u8acb\u8077\u4f4d\u53ca\u8077\u4f4d\u7de8\u865f\uff0c\u67e5\u8a62\u96fb\u8a71\uff1a2425 1282\u3002\n\n\u622a\u6b62\u7533\u8acb\u65e5\u671f\uff1a2022\u5e741\u670824\u65e5\n\n\u672c\u6703\u63d0\u4f9b\u5b8c\u5584\u798f\u5229\uff0c\u5305\u62ec\uff1a\u91ab\u7642\u4fdd\u96aa\u3001\u6700\u9ad810%\u00a0\u5f37\u7a4d\u91d1\u50f1\u4e3b\u4f9b\u6b3e\u53ca\u5c08\u696d\u57f9\u8a13\u7b49\u3002\n\n\u4e00\u5207\u7533\u8acb\u8cc7\u6599\u7d55\u5c0d\u4fdd\u5bc6\u53ca\u53ea\u7528\u4f5c\u62db\u8058\u6709\u95dc\u8077\u4f4d\uff0c\u672a\u7372\u7d04\u898b\u8005\uff0c\u4f5c\u843d\u9078\u8ad6\uff0c\u6055\u4e0d\u53e6\u51fd\u901a\u77e5\u3002\u800c\u7533\u8acb\u4eba\u4e4b\u500b\u4eba\u8cc7\u6599\u4ea6\u5c07\u5728\u5b8c\u6210\u62db\u8058\u7a0b\u5e8f\u5f8c\u92b7\u6bc0\u3002", "employment_types": ["Full Time", "Contract"], "selling_points": [], "locations": ["Kwai Tsing Area"], "categories": ["Accounting", "Accounting Clerk / Supervisor"], "post_time": "2022-01-15T19:11:22Z", "salary": {"currency": null, "max": null, "min": null, "period": "monthly", "term": null}, "salary_visible": false, "title_keywords": ["clerk"], "responsibilities": [], "requirements": {"degrees": [], "majors": [], "languages": [], "language_level": [], "hard_skills": [], "soft_skills": [], "languages_combined": []}, "experience_required": {"duration": [], "field": []}}, {"job_id": "100003009053614", "location_code": "hk", "company": "\u601d\u8b00\u96c6\u5718\u6709\u9650\u516c\u53f8", "job_title": "Treasury clerk", "description": "Responsibilities1. Handle daily payment to the bank's accounts and affairs\n2. Prepare receipt, payment and journal vouchers, cheques and bank transfer and bank reconciliation\n3. Posting and reconciling Petty Cash\n4. Preparation of monthly budget cashflow\n5. Handle ad-hoc assignment as requiredRequirements1. Form 7 and with LCC Higher or similar qualification\n2. At least\u00a03\u00a0years experience in AP, AR\n3. Proficiency in MS Excel,\u00a0MS Word\n4. Good communication skill in English and\u00a0Chinese\n5. Strong sense of responsibility, high accuracy, well-organized, hard working and under pressure\n6. Immediate available is highly desired", "employment_types": ["Full Time"], "selling_points": ["Handle  payment to the bank's accounts and affairs", "Preparation of monthly budget cashflow", "Posting and reconciling Petty Cash"], "locations": ["Shatin Area"], "categories": ["Accounting", "Accountant", "Accounting Clerk / Supervisor", "Treasurer"], "post_time": "2022-01-17T07:14:34Z", "salary": {"currency": null, "max": null, "min": null, "period": "monthly", "term": null}, "salary_visible": false, "title_keywords": ["clerk"], "responsibilities": ["ad-hoc", "journal vouchers", "ap", "ar", "budget", "bank reconciliation", "communication", "payment", "cheques"], "requirements": {"degrees": [], "majors": [], "languages": ["english", "chinese"], "language_level": ["good"], "hard_skills": ["ap", "ar", "ms excel", "lcc", "ms word"], "soft_skills": ["under pressure", "sense of responsibility", "hard working", "communication skill", "well-organized"], "languages_combined": [{"language": "english", "language_level": ["good"]}, {"language": "chinese", "language_level": ["good"]}]}, "experience_required": {"duration": ["at least 3 years"], "field": []}}, {"job_id": "100003009042679", "location_code": "hk", "company": "Honestar Technologies Company Limited", "job_title": "SENIOR ACCOUNT CLERK", "description": "\n\u8981\u6c42\uff1a\n\u2022 \u5354\u52a9\u7d44\u7e54\u516c\u53f8\u5e74\u5ea6\u9810\u7b97\u7684\u7de8\u5236\u548c\u5b63\u5ea6\u3001\u6708\u5ea6\u9810\u7b97\u8a08\u5283; \u8ca0\u8cac\u65e5\u5e38\u6703\u8a08\u5165\u8cec\u53ca\u7de8\u5236\u5404\u985e\u6703\u8a08\u5831\u8868; \u5354\u52a9\u7de8\u5236\u4e0a\u5e02\u516c\u53f8\u5e74\u5831\uff0c\u534a\u5e74\u5831\u544a\u53ca\u76f8\u95dc\u5831\u8868; \u5176\u5b83\u65e5\u5e38\u8ca1\u52d9\u5de5\u4f5c\u3002\n\u2022 \u5c08\u4e0a\u6559\u80b2\uff1a\u5927\u5b78\u672c\u79d1\u53ca\u4ee5\u4e0a\u5b78\u6b77\uff0c\u4e3b\u4fee\u6703\u8a08, CPA\u8cc7\u683c\u6216\u8005\u6301\u6709\u5167\u5730\u6703\u8a08\u5e2b\u8b49\u512a\u5148\u8003\u616e, \u826f\u597d\u7cb5\u8a9e; \u826f\u597d\u666e\u901a\u8a71; \u826f\u597d\u82f1\u8a9e; 3-5\u5e74\u4ee5\u4e0a\u4e0a\u5e02\u516c\u53f8\u76f8\u95dc\u5de5\u4f5c\u7d93\u9a57;\u00a0\n\u85aa\u91d1\uff1a \u9762\u8b70\n\u00a0\n\u5f85\u9047\uff1a \u9280\u884c\u5047\u671f\uff0c\u91ab\u7642\u798f\u5229\uff0c\u6709\u82b1\u7d05\uff0cOT\u88dc\u52a9\uff0c\u6649\u6607\u6a5f\u6703\uff0c\u65c5\u904a\u734e\u8cde\u7b49\n\u6709\u610f\u8005\u8acb\u96fb\u90f5\u81f3 [via\u00a0 Apply Now ]", "employment_types": ["Full Time"], "selling_points": ["\u9280\u884c\u5047\u671f\uff0c\u91ab\u7642\u798f\u5229", "OT\u88dc\u52a9", "\u6649\u6607\u6a5f\u6703\uff0c\u65c5\u904a\u734e\u8cde\u7b49"], "locations": ["Kwai Hing"], "categories": ["Accounting", "Accountant", "Accounting Clerk / Supervisor"], "post_time": "2022-01-16T21:50:13Z", "salary": {"currency": null, "max": null, "min": null, "period": "monthly", "term": null}, "salary_visible": false, "title_keywords": ["senior account clerk"], "responsibilities": [], "requirements": {"degrees": [], "majors": [], "languages": [], "language_level": [], "hard_skills": [], "soft_skills": [], "languages_combined": []}, "experience_required": {"duration": [], "field": []}}, {"job_id": "100003009053734", "location_code": "hk", "company": "Alpha Quant Financial Technology Limited", "job_title": "Accounting Clerk", "description": "\nJob Description\n-Reconciliation of bank statement and invoice\n-Perform daily accounting operations\n-Other ad hoc duties\nRequirements\n-Degree in Accounting/ other discipline\n-Proficiency in computer operations (PC, MS Office, Excel, Chinese word typing)\n-Experience and knowledge in accounting work\nSalary: Competitive, Negotiable\nJob Types: Full-time, Contract, Permanent\nJob Types: Full-time, Permanent, Contract\nSalary: $10,000.00 - $20,000.00 per month\nSchedule:\n\u2022 Monday to Friday\n\n", "employment_types": ["Full Time"], "selling_points": [], "locations": ["Tsim Sha Tsui"], "categories": ["Accounting", "Accounting Clerk / Supervisor", "Others", "Admin & HR", "Others"], "post_time": "2022-01-17T07:25:38Z", "salary": {"currency": null, "max": null, "min": null, "period": "monthly", "term": null}, "salary_visible": false, "title_keywords": ["accounting clerk"], "responsibilities": ["invoice", "daily accounting operations", "ad hoc duties"], "requirements": {"degrees": [], "majors": [], "languages": ["chinese"], "language_level": [], "hard_skills": ["excel", "typing", "word", "pc", "ms office"], "soft_skills": [], "languages_combined": [{"language": "chinese", "language_level": []}]}, "experience_required": {"duration": [], "field": []}}, {"job_id": "100003009053889", "location_code": "hk", "company": "E & K Cleaning Services Limited", "job_title": "\u6703\u8a08\u4e3b\u4efb", "description": "\n\u8077\u8cac :\u8655\u7406\u5168\u76e4\u6703\u8a08\u5e33\u76ee\uff1b\u8ca0\u8cac\u65e5\u5e38\u6703\u8a08\u4e8b\u52d9\uff0c\u4f8b\u5982AR/AP\uff1b\u8ddf\u9032\u5ba2\u6236\u672a\u4ed8\u6b3e\u9805\uff1b\u88fd\u4f5c\u6bcf\u6708\u8ca1\u52d9\u5831\u544a\uff1b\u5354\u52a9\u5e74\u5ea6\u5be9\u8a08\u53ca\u5831\u7a05\u4e8b\u5b9c\uff1b\u5354\u52a9\u8fa6\u516c\u5ba4\u884c\u653f\u5de5\u4f5c\u53ca\u5176\u4ed6\u6307\u6d3e\u5de5\u4f5c\n\n\u8cc7\u6b77 :\u4e2d\u4e94\u7a0b\u5ea6; 1\u5e74\u7d93\u9a57; \u826f\u597d\u7cb5\u8a9e; \u4e00\u822c\u82f1\u8a9e; \u61c2\u8b80\u5beb\u4e2d\u6587; \u7565\u61c2\u8b80\u5beb\u82f1\u6587; \u61c2MS Word; \u61c2MS Excel; \u6301\u6709LCC\u4e2d\u7d1a\u8b49\u66f8; \u61c2\u82f1\u6587\u6253\u5b57; \u61c2\u4e2d\u6587\u6253\u5b57\n\n\u5f85\u9047 :\u6bcf\u6708$18,000 - $20,000, \u661f\u671f\u4e00\u81f3\u4e94: \u4e0a\u53489\u6642\u81f3\u4e0b\u53486\u6642\u53ca\u661f\u671f\u516d: \u4e0a\u53489\u6642\u81f3\u4e0b\u53481\u6642, \u6bcf\u9031\u5de5\u4f5c5\u5929\u534a\n\n\u7533\u8acb\u9808\u77e5 :\u6c42\u8077\u8005\u53ef\u96fb\u90f5(Apply Now)\u5c65\u6b77\u8868\u7d66\u96c5\u6f54\u6e05\u6f54\u5de5\u7a0b\u6709\u9650\u516c\u53f8\u3002\u5982\u8981\u7d22\u53d6\u6536\u96c6\u500b\u4eba\u8cc7\u6599\u8072\u660e, \u8acb\u8207\u5f35\u5148\u751f(Email)\u806f\u7d61\u3002\n\n", "employment_types": ["Full Time"], "selling_points": [], "locations": ["Tsuen Wan Area"], "categories": ["Accounting", "Accountant", "Accounting Clerk / Supervisor", "Audit"], "post_time": "2022-01-17T07:42:15Z", "salary": {"currency": null, "max": null, "min": null, "period": "monthly", "term": null}, "salary_visible": false, "title_keywords": [], "responsibilities": [], "requirements": {"degrees": [], "majors": [], "languages": [], "language_level": [], "hard_skills": ["excel", "word"], "soft_skills": [], "languages_combined": []}, "experience_required": {"duration": [], "field": []}}, {"job_id": "100003009053908", "location_code": "hk", "company": "Alliance Medical Group Holdings Limited", "job_title": "Accounting Clerk", "description": "\u4e0a\u73ed\u5730\u9ede : \u89c0\u5858\n\n\u4e0a\u73ed\u6642\u9593 : \u4e94\u5929\u5de5\u4f5c 10am-7pm\n\n\u5de5\u4f5c\u5167\u5bb9 :\n\n\u5354\u52a9\u8655\u7406\u61c9\u4ed8\u8cec\u76ee\u3001\u61c9\u6536\u8cec\u76ee\u53ca\u4e00\u822c\u6703\u8a08\u8cec\u76ee\n\u8cc7\u6599\u8f38\u5165\u3001\u5b58\u6a94\u53ca\u6587\u66f8\u5de5\u4f5c\u7b49\n\u8655\u7406\u65e5\u5e38\u6536\u652f\u53ca\u4e00\u822c\u6703\u8a08\u55ae\u64da\n\u57f7\u884c\u4e0a\u53f8\u59d4\u6d3e\u5de5\u4f5c\n\u5de5\u4f5c\u8981\u6c42 :\n\n\u7121\u9808\u7d93\u9a57\nLCCI \u4e2d\u7d1a\u512a\u5148\n\u61c2\u4e2d\u6587\u8f38\u5165\u6cd5\n\u61c2\u4f7f\u7528 MS Office\n\u7d30\u5fc3\u3001\u8aa0\u5be6\u52e4\u596e\u3001\u5bcc\u8cac\u4efb\u611f\u53ca\u5718\u968a\u7cbe\u795e\n\n\u5168\u8077\u5f85\u9047\uff1a\n\n\u00a0\u00a0\u00a0\u00a0\u00a0\u00a0\u00a0\u52e4\u5de5\u734e\u91d1\n\u00a0\u00a0\u00a0\u00a0\u00a0\u00a0\u00a0\u9280\u884c\u5047\u671f\n\n\u6c42\u8077\u8005\u63d0\u4f9b\u7684\u500b\u4eba\u8cc7\u6599\u5c07\u56b4\u683c\u6309\u7167\u50f1\u4e3b\u7684\u500b\u4eba\u8cc7\u6599\u653f\u7b56\u4f7f\u7528\uff0c\u50c5\u4f9b\u62db\u8058\u7528\u9014\u3002", "employment_types": ["Full Time"], "selling_points": ["\u6708\u85aa$15000+", "\u4e94\u5929\u5de5\u4f5c, \u9280\u884c\u5047\u671f", "\u7121\u9808\u7d93\u9a57"], "locations": ["Kwun Tong"], "categories": ["Accounting", "Accounting Clerk / Supervisor"], "post_time": "2022-01-17T07:44:21Z", "salary": {"currency": null, "max": null, "min": null, "period": "monthly", "term": null}, "salary_visible": false, "title_keywords": ["accounting clerk"], "responsibilities": [], "requirements": {"degrees": [], "majors": [], "languages": [], "language_level": [], "hard_skills": ["ms office"], "soft_skills": [], "languages_combined": []}, "experience_required": {"duration": [], "field": []}}, {"job_id": "100003009044579", "location_code": "hk", "company": "The Hong Kong Society for the Aged", "job_title": "\u884c\u653f\u53ca\u6703\u8a08\u6587\u54e1Administration and Accounting Clerk (\u8077\u4f4d\u7de8\u865f\uff1aADC - 220102)", "description": "\u8ca0\u8cac\u6587\u66f8\u3001\u5168\u76e4\u6703\u8a08\u3001\u884c\u653f\u53ca\u9662\u52d9\u5de5\u4f5c\n\u4e2d\u4e94\u6216\u4ee5\u4e0a\u7a0b\u5ea6\n2\u5e74\u6216\u4ee5\u4e0a\u6703\u8a08\u7d93\u9a57\n\u6301\u6709\u521d\u7d1a\u7c3f\u8a18\u8b49\u66f8\u53ca\u6709\u904b\u7528\u7532\u9aa8\u6587(Oracle)\u6703\u8a08\u8edf\u4ef6\u7d93\u9a57\u512a\u5148\u8003\u616e\n\u5165\u8077\u85aa\u916c\u70ba$14,410\u6216\u6309\u76f8\u95dc\u5e74\u8cc7\u8a08\u7b97\n\u77f3\u570d\u89d2\u8b77\u7406\u5b89\u8001\u9662\uff08\u8343\u7063\u77f3\u570d\u89d2\u90a8\uff09\u5de5\u4f5c\n\n\u7533\u8acb\u8fa6\u6cd5\uff1a\u8acb\u5c07\u5c65\u6b77\u8868\u6216\u8077\u4f4d\u7533\u8acb\u8868 (\u7533\u8acb\u8868\u53ef\u65bc\u672c\u6703\u7db2\u9801http://www.sage.org.hk\u4e4b\u300c\u95dc\u65bc\u6211\u5011\u300d\uff0d\u300c\u4e0b\u8f09\u8868\u683c\u300d\uff0d\u300c\u8077\u4f4d\u7533\u8acb\u8868\u683c\u300d\u4e0b\u8f09) \u90f5\u5bc4\u81f3\u65b0\u754c\u8343\u7063\u77f3\u570d\u89d2\u90a8\u77f3\u84ee\u6a13\u4e8c\u6a13\u8006\u5eb7\u6703\u77f3\u570d\u89d2\u8b77\u7406\u5b89\u8001\u9662\u9662\u9577\u6536\u6216\u96fb\u90f5\u81f3Apply Now\uff0c\u4e26\u8a3b\u660e\u8981\u6c42\u85aa\u91d1\u53ca\u65bc\u4fe1\u5c01\u9762\u8a3b\u660e\u7533\u8acb\u8077\u4f4d\u53ca\u8077\u4f4d\u7de8\u865f\uff0c\u67e5\u8a62\u96fb\u8a71\uff1a2498 0423\u3002\n\n\u622a\u6b62\u7533\u8acb\u65e5\u671f\uff1a2022\u5e741\u670824\u65e5\n\n\u672c\u6703\u63d0\u4f9b\u5b8c\u5584\u798f\u5229\uff0c\u5305\u62ec\uff1a\u91ab\u7642\u4fdd\u96aa\u3001\u6700\u9ad810% \u5f37\u7a4d\u91d1\u50f1\u4e3b\u4f9b\u6b3e\u53ca\u5c08\u696d\u57f9\u8a13\u7b49\u3002\n\n\u4e00\u5207\u7533\u8acb\u8cc7\u6599\u7d55\u5c0d\u4fdd\u5bc6\u53ca\u53ea\u7528\u4f5c\u62db\u8058\u6709\u95dc\u8077\u4f4d\uff0c\u672a\u7372\u7d04\u898b\u8005\uff0c\u4f5c\u843d\u9078\u8ad6\uff0c\u6055\u4e0d\u53e6\u51fd\u901a\u77e5\u3002\u800c\u7533\u8acb\u4eba\u4e4b\u500b\u4eba\u8cc7\u6599\u4ea6\u5c07\u5728\u5b8c\u6210\u62db\u8058\u7a0b\u5e8f\u5f8c\u92b7\u6bc0\u3002", "employment_types": ["Full Time", "Contract"], "selling_points": [], "locations": ["Tsuen Wan Area"], "categories": ["Accounting", "Accounting Clerk / Supervisor"], "post_time": "2022-01-15T19:11:26Z", "salary": {"currency": null, "max": null, "min": null, "period": "monthly", "term": null}, "salary_visible": false, "title_keywords": ["accounting clerk"], "responsibilities": [], "requirements": {"degrees": [], "majors": [], "languages": [], "language_level": [], "hard_skills": [], "soft_skills": [], "languages_combined": []}, "experience_required": {"duration": [], "field": []}}, {"job_id": "100003009049015", "location_code": "hk", "company": "PHM Contracting Co. Limited", "job_title": "Accounting Assistant", "description": "Responsibilities:\n\nResponsible for general accounting duties such as A/P, A/R, journal, and bank reconciliation\nTo prepare payment and receipt vouchers\nTo issue invoices, cheques, and receipts\nData input of accounting entries\nEnsure data input in a timely and accurate manner\nAssist in preparing accounting schedule and daily worker payroll\nPerform other ad hoc duties when required\n\nRequirements:\n\nl\u00a0\u00a0 Diploma or above in Accounting\n\nl\u00a0\u00a0 Holder of LCCI Intermediate or above\n\nl\u00a0\u00a0 Minimum 2 years\u2019 accounting experience\n\nl\u00a0\u00a0 Able to work independently, and Initiative-taking\n\nl\u00a0\u00a0 Experience in Peachtree is preferred\n\nl\u00a0\u00a0 Familiar with MS Word and Excel\n\n\nInterested candidates please send your full resume with expected salary by clicking 'Apply Now'\n\n(Personal data collected will be used for recruitment purpose only.)", "employment_types": ["Full Time"], "selling_points": ["Responsible for full set of accounts", "Able to work independently, Initiative-taking", "Experience in construction field is an advantage"], "locations": ["Kwun Tong"], "categories": ["Accounting", "Accountant", "Accounting Clerk / Supervisor", "Others"], "post_time": "2022-01-17T03:55:33Z", "salary": {"currency": null, "max": null, "min": null, "period": "monthly", "term": null}, "salary_visible": false, "title_keywords": ["accounting assistant"], "responsibilities": ["ad hoc duties", "invoices", "receipts", "bank reconciliation", "data input", "payment", "cheques", "general accounting duties", "schedule", "payroll"], "requirements": {"degrees": ["diploma or above"], "majors": ["accounting"], "languages": [], "language_level": [], "hard_skills": ["excel", "peachtree", "ms word"], "soft_skills": ["work independently", "initiative"], "languages_combined": []}, "experience_required": {"duration": ["minimum 2 years"], "field": ["accounting experience"]}}, {"job_id": "100003009053709", "location_code": "hk", "company": "Biel Crystal (HK) Manufactory Limited", "job_title": "Senior Accounting Clerk  -   Kwun Tong near MTR Station", "description": "We are the leading smart phone cover glass supplier in the world. \u00a0Our customers include all the well-known smart phone brands.\u00a0 Due to business needs, we are looking for talents to join our Finance team in Hong Kong.\n\n\u00a0Responsibilities:\n\nAssist in daily accounting duties including but not limited to data input, filing, preparing accounting journal entries, bank reconciliations, etc.\nPrepare monthly financial statements for overseas branch, schedules and analysis\nLiaise with China and overseas colleagues in monthly inter-company transactions reconciliation\nProcess data input in system and perform testing when implementation of new functions in system\nAssist in all ad-hoc assignments\n\nRequirements:\n\nReasonable level of accounting knowledge\n2 years accounting experience is preferred\nStrong communication and interpersonal skills to interact with people at different levels\nAble to work in a fast pace working environment\nProficient in MS Office (Word, Excel), Chinese Word processing\nGood command of both written and spoken English\nAbility to speak Chinese Putonghua is necessary\nRecent university graduate in business will also be considered\nImmediately available is preferred\n\nWork location is in Kwun Tong near MTR Station.\u00a0 We offer good career prospects with an attractive salary remuneration including double-pay,\u00a0discretionary bonus and\u00a0medical insurance\u00a0to the right candidate. \u00a0\n\n(Applicants not contacted within six weeks should consider their application unsuccessful. \u00a0Personal data provided by applicants will be strictly used for recruitment purpose only.)", "employment_types": ["Full Time", "Permanent"], "selling_points": [], "locations": ["Kwun Tong"], "categories": ["Accounting", "Accounting Clerk / Supervisor", "Financial Analyst"], "post_time": "2022-01-17T07:23:17Z", "salary": {"currency": null, "max": null, "min": null, "period": "monthly", "term": null}, "salary_visible": false, "title_keywords": ["accounting clerk"], "responsibilities": ["schedules", "ad-hoc assignments", "analysis", "data input", "bank reconciliations", "transactions", "testing", "implementation", "prepare monthly financial statements", "journal entries", "liaise with", "daily accounting"], "requirements": {"degrees": ["university graduate"], "majors": ["business"], "languages": ["putonghua", "english", "chinese"], "language_level": ["good command", "proficient"], "hard_skills": ["excel", "chinese word processing", "word", "ms office"], "soft_skills": ["communication and interpersonal skills"], "languages_combined": [{"language": "putonghua", "language_level": []}, {"language": "english", "language_level": ["good command"]}, {"language": "chinese", "language_level": ["proficient"]}]}, "experience_required": {"duration": ["2 years"], "field": ["accounting experience"]}}, {"job_id": "100003009052559", "location_code": "hk", "company": "Precious Blood Hospital (Caritas)", "job_title": "\u52a9\u7406\u6587\u54e1 (\u8cec\u6236\u670d\u52d9)", "description": "\u8077\u8cac\uff1a\n\n\u8655\u7406\u4f4f\u9662\u75c5\u4eba\u8cec\u6236\u670d\u52d9\u53ca\u6536\u8cbb\u7a0b\u5e8f\uff1b\n\u5354\u52a9\u89e3\u7b54\u4e00\u822c\u8cec\u55ae\u554f\u984c\uff1b\n\u8655\u7406\u4e00\u822c\u6587\u66f8\u5de5\u4f5c\u3001\u5982\u8cc7\u6599\u8f38\u5165\u53ca\u6587\u4ef6\u5b58\u6a94\uff1b\n\u63a5\u807d\u96fb\u8a71\u53ca\u8ca0\u8cac\u65e5\u5e38\u806f\u7d61\u5de5\u4f5c\uff1b\n\u8ffd\u6536\u5ba2\u6236\u53ca\u4fdd\u96aa\u516c\u53f8\u5230\u671f\u8cec\u55ae\u3002\n\n\u00a0\u8077\u4f4d\u8981\u6c42\uff1a\n\n\u4e2d\u4e94\u7a0b\u5ea6\u6216\u4ee5\u4e0a\uff1b\n\u81f3\u5c11\u5169\u5e74\u76f8\u95dc\u5de5\u4f5c\u7d93\u9a57\uff1b\n\u6709\u79ae\u8c8c\uff0c\u826f\u597d\u6e9d\u901a\u6280\u5de7\uff1b\n\u80fd\u7368\u7acb\u5de5\u4f5c\u3001\u5de5\u4f5c\u9808\u7d30\u5fc3\u53ca\u8ca0\u8cac\u4efb\uff1b\n\u719f\u6089\u5fae\u8edf Office (Word , Excel), \u6709\u6578\u64da\u5eab\u7ba1\u7406\u7d93\u9a57\u512a\u5148\u8003\u616e\uff1b\n\u9808\u8f2a\u73ed\u5de5\u4f5c\u3002", "employment_types": ["Full Time"], "selling_points": [], "locations": ["Sham Shui Po"], "categories": ["Accounting", "Accounting Clerk / Supervisor"], "post_time": "2022-01-17T03:25:12Z", "salary": {"currency": null, "max": null, "min": null, "period": "monthly", "term": null}, "salary_visible": false, "title_keywords": ["\u52a9\u7406\u6587\u54e1"], "responsibilities": [], "requirements": {"degrees": [], "majors": [], "languages": [], "language_level": [], "hard_skills": ["excel", "word"], "soft_skills": [], "languages_combined": []}, "experience_required": {"duration": [], "field": []}}, {"job_id": "100003009054708", "location_code": "hk", "company": "Sky Base Investments Limited", "job_title": "Senior Accounts Clerk", "description": "Key Responsibilities:\n\nPerform data input into ERP Accounting & Retail system;\u00a0\u00a0\nMainly responsible for A/P section, bills settlement & maintain bank books;\nAssist in preparing various simple reports, accounting schedules and bank reconciliation;\nFull set of account experience is definite advantage;\nPerform other ad hoc tasks as assigned.\n\n\u00a0Job Requirements:\n\nF.5 with LCCI Inter or above;\nAt least 5 years\u2019 solid experience in accounting or auditing;\nExperience in Accounting & ERP system is a definite advantage;\nRetail accounting experience is definite advantage;\nStrong sense of responsibility, hardworking and willing to\u00a0LEARN;\nProficiency in MS office, especially Excel spreadsheet & outlook;\nQuick typing skill on both Chinese and English;\nImmediately available is highly preferred.\n\nWe offer permanent job with basically 5-day work per week, excellent career opportunities and remuneration package to the right candidates. Interested parties please apply with\u00a0detailed resume,\u00a0salary expected,\u00a0contact numbers\u00a0in strict confidence and quoting reference in your application by clicking \u201cApply Now\u201d.\n\nAll information provided will be treated in strict confidence and only be used for recruitment purposes.\u00a0\u00a0Candidates without salary expectation will not be considered.", "employment_types": ["Full Time", "Permanent"], "selling_points": [], "locations": ["Shatin Area"], "categories": ["Accounting", "Accountant", "Accounting Clerk / Supervisor"], "post_time": "2022-01-17T10:39:53Z", "salary": {"currency": null, "max": null, "min": null, "period": "monthly", "term": null}, "salary_visible": false, "title_keywords": ["senior accounts clerk"], "responsibilities": ["schedules", "ad hoc tasks", "data input", "bank reconciliation", "maintain", "reports"], "requirements": {"degrees": [], "majors": [], "languages": ["english", "chinese"], "language_level": [], "hard_skills": ["excel", "typing", "erp system", "outlook", "spreadsheet", "ms office"], "soft_skills": ["willing to learn", "hardworking", "sense of responsibility"], "languages_combined": [{"language": "english", "language_level": []}, {"language": "chinese", "language_level": []}]}, "experience_required": {"duration": ["at least 5 years"], "field": ["accounting experience", "erp system", "accounting", "retail"]}}, {"job_id": "100003009049732", "location_code": "hk", "company": "Jackel Porter Co Ltd", "job_title": "Accounts Clerk", "description": "Responsibilities\n\nProcurement or ordering of sales items\nBank reconciliation\nData entries\nStock ledger control\nAccounts payable\nPrepare accounts breakdowns\nAd-hoc assignments by the manager\nRequirements\u00a0\n\nF5/DSE or above\nLCC Intermediate or above\n2 years working experience with experience in accounting\nDetail-oriented and good communication skills\nGood command in English, Cantonese, and Mandarin\nFamiliar MS Words & Excel\nShort notice or immediate available is preferred", "employment_types": ["Full Time"], "selling_points": ["Accounting experience", "LCCI", "Free shuttle bus"], "locations": ["Tai Po Area"], "categories": ["Accounting", "Accounting Clerk / Supervisor"], "post_time": "2022-01-14T09:10:30Z", "salary": {"currency": null, "max": null, "min": null, "period": "monthly", "term": null}, "salary_visible": false, "title_keywords": ["accounts clerk"], "responsibilities": ["control", "data", "ad-hoc assignments", "bank reconciliation", "accounts payable"], "requirements": {"degrees": ["dse"], "majors": [], "languages": ["cantonese", "english", "mandarin"], "language_level": ["good command"], "hard_skills": ["excel", "lcc", "ms words"], "soft_skills": ["communication skills", "detail-oriented"], "languages_combined": [{"language": "cantonese", "language_level": ["good command"]}, {"language": "english", "language_level": ["good command"]}, {"language": "mandarin", "language_level": ["good command"]}]}, "experience_required": {"duration": ["2 years"], "field": ["accounting"]}}, {"job_id": "100003009052598", "location_code": "hk", "company": "Takasago Thermal Engineering (Hong Kong) Co Ltd", "job_title": "Account Clerk / Senior Account Clerk", "description": "\u00a0Responsibilities:\n\nResponsible for routine accounting operation\nPrepare monthly financial reports\nAssist senior to prepare for both local & Japan audit accounting\n\nRequirements:\n\nDegree / High diploma in\u00a0Accounting or equivalent;\nKnowledge of MYOB accounting system\nFluent spoken and written English and Cantonese\nProficient in Microsoft\u00a0Excel, Word\nIndependent, hardworking, organized, self-motivated and strong sense of responsibility\n1 - 2 years\u00a0relevant accounting experiences\n\nSalary / Allowance:\n\nCompetitive remuneration package consist of 12 days annual leave, 5.5 days per week (long/short week Saturday), travel allowance and group medical / life insurance, double payment and etc.\n\nApplication Method\n\nInterested parties please send full resume with expected salary to us.\u00a0\n\nTarget Commencement Date: Immediate available is highly preferred\u00a0", "employment_types": ["Full Time", "Permanent"], "selling_points": ["12 days annual leave, bank holidays", "End of year payment", "5/ 5.5 days work"], "locations": ["Sheung Wan"], "categories": ["Accounting", "Accountant", "Accounting Clerk / Supervisor"], "post_time": "2022-01-17T03:30:17Z", "salary": {"currency": null, "max": null, "min": null, "period": "monthly", "term": null}, "salary_visible": false, "title_keywords": ["account clerk", "senior account clerk"], "responsibilities": ["financial reports", "audit"], "requirements": {"degrees": ["high diploma", "degree"], "majors": ["accounting"], "languages": ["cantonese", "english"], "language_level": ["fluent"], "hard_skills": ["myob", "word", "accounting system", "microsoft excel"], "soft_skills": ["organized", "self-motivated", "independent", "sense of responsibility", "hardworking"], "languages_combined": [{"language": "cantonese", "language_level": ["fluent"]}, {"language": "english", "language_level": ["fluent"]}]}, "experience_required": {"duration": ["1 - 2 years"], "field": ["accounting"]}}, {"job_id": "100003009052692", "location_code": "hk", "company": "Sunlight Jewelers Limited", "job_title": "Accounts Clerk", "description": "Responsibilities & Requirements \u8077\u8cac\u53ca\u8981\u6c42\n\n-\u00a0\u00a0\u00a0\u00a0\u00a0\u00a0\u00a0 Around 3 years relevant experience, preferable in Jewellery industry\n\n-\u00a0\u00a0\u00a0\u00a0\u00a0\u00a0\u00a0 Handle AR Collection & AP Payment, assist in month-end closing & follow up outstanding Receivables\n\n-\u00a0\u00a0\u00a0\u00a0\u00a0\u00a0\u00a0 Basic proficiency in English, Cantonese and Mandarin\n\n-\u00a0\u00a0\u00a0\u00a0\u00a0\u00a0\u00a0 Other ad hoc task assigned by management\n\n-\u00a0\u00a0\u00a0\u00a0\u00a0\u00a0\u00a0 Form 5 graduate or above\n\n-\u00a0\u00a0\u00a0\u00a0\u00a0\u00a0\u00a0 Familiar with using MYOB or PJS is an advantage\n\n-\u00a0\u00a0\u00a0\u00a0\u00a0\u00a0\u00a0 Well organized, self-motivated & responsible\n\n\n\nWe offer 5 \u00bd-day work, Medical Scheme & Bank holidays to the right candidate.\u00a0 Interested parties, please send FULL RESUME with expected salary to: apply now", "employment_types": ["Full Time"], "selling_points": [], "locations": ["Hung Hom"], "categories": ["Accounting", "Accounting Clerk / Supervisor", "Others", "Admin & HR", "Clerical / Admin Staff"], "post_time": "2022-01-17T03:55:51Z", "salary": {"currency": null, "max": null, "min": null, "period": "monthly", "term": null}, "salary_visible": false, "title_keywords": ["accounts clerk"], "responsibilities": [], "requirements": {"degrees": ["form 5"], "majors": [], "languages": ["cantonese", "english", "mandarin"], "language_level": ["proficiency", "basic"], "hard_skills": ["ap", "myob", "basic", "ar"], "soft_skills": ["self-motivated", "well organized", "responsible"], "languages_combined": [{"language": "cantonese", "language_level": ["proficiency", "basic"]}, {"language": "english", "language_level": ["proficiency", "basic"]}, {"language": "mandarin", "language_level": ["proficiency", "basic"]}]}, "experience_required": {"duration": ["3 years"], "field": ["relevant experience"]}}, {"job_id": "100003009052874", "location_code": "hk", "company": "Sensory Artisan Group Limited", "job_title": "Accounting Assistant ( 5 Days )", "description": "Responsibilities\n\n\nAssist in general routine accounting functions, perform clerical duties such as data entry and filing, reviewing invoices\nperform daily accounting operations include general journal entries, payments, bank reconciliation, stock check\nAdministrative tasks include visiting shops to collect the bills and supporting documents for the purpose of keeping proper books and records.\nHandling ad-hoc assignments when required\n\n\u00a0Requirements\n\nDiploma or above in Finance, Accounting or related discipline\nAt least one year\u2019s experience in accounting field\nProficiency in MS Office (Word/Excel) and Chinese Word Processing\nSelf-motivated, work independently, detail-oriented and with good communication skills.\n\n\nWe offer attractive remuneration package including 5-day work per week, bank holidays and excellent career development opportunities to the right candidates.\n\u00a0\nInterested parties please send full resume\u00a0with current and expected salary\u00a0to us by clicking \"Apply Now\".\n\nAll information received will be kept in strict confidentiality and used for recruitment purpose only.", "employment_types": ["Full Time"], "selling_points": ["general routine accounting functions", "At least one year\u2019s experience in accounting field", "Accounting Assistant ( 5 Days )"], "locations": ["Kwun Tong"], "categories": ["Accounting", "Accountant", "Accounting Clerk / Supervisor"], "post_time": "2022-01-17T04:23:17Z", "salary": {"currency": "HKD", "max": 16999, "min": 14000, "period": "monthly", "term": null}, "salary_visible": true, "title_keywords": ["accounting assistant"], "responsibilities": ["data entry and filing", "invoices", "ad-hoc assignments", "daily accounting operations", "bank reconciliation", "payments", "journal entries", "administrative tasks"], "requirements": {"degrees": ["diploma or above"], "majors": ["finance", "accounting"], "languages": ["chinese"], "language_level": ["proficiency"], "hard_skills": ["excel", "chinese word processing", "word", "ms office"], "soft_skills": ["communication skills", "self-motivated", "work independently", "detail-oriented"], "languages_combined": [{"language": "chinese", "language_level": ["proficiency"]}]}, "experience_required": {"duration": ["at least one year"], "field": ["accounting"]}}, {"job_id": "100003009053357", "location_code": "hk", "company": "Havas Worldwide Hong Kong Limited", "job_title": "Senior Account Clerk", "description": "Responsibility:\n\nFocus on handling intercompany transactions\nAssist in handling daily accounting matters, month-end closing & internal control\nAssist in interim and annual audit preparation\nClose liaison with Business units and related intercompany matters\nPerform ad hoc assignments as required\n\nRequirement:\n\nMinimum 1-2 years relevant experience\nDiploma in Finance or Accounting will be is definitely an advantage\nLCC Level II or above\nFluent in both spoken & written English and Chinese\nGood knowledge in MS Office applications\nBasic knowledge on accounting software\nIndependent, responsible, good team player and able to work under pressure\nCandidate without current, expected salary and availability will not be considered\nImmediately available is preferred\nWe offer 5-day work week, birthday and other special leaves, staff training, good salary package with MPF and Medical Coverage.\u00a0Interested parties please apply with full resume stating availability, current and expected salaries by clicking \"APPLY NOW\"\u00a0.\n\nFurther information about Havas Group is available on the company\u2019s website: havasgroup.com\n\nDue to high volume of applications, only eligible or matching candidates will be contacted by us. All personal data received will only be used for recruitment purpose and will be destroyed after the position is filled.", "employment_types": ["Full Time", "Permanent"], "selling_points": ["5-day work week, birthday and other special leaves", "Minimum 1-2 years relevant experience", "Immediately available is preferred"], "locations": ["Kwun Tong"], "categories": ["Accounting", "Accountant", "Accounting Clerk / Supervisor"], "post_time": "2022-01-17T06:50:38Z", "salary": {"currency": null, "max": null, "min": null, "period": "monthly", "term": null}, "salary_visible": false, "title_keywords": ["senior account clerk"], "responsibilities": ["annual audit", "transactions", "month-end closing", "ad hoc assignments", "daily accounting", "internal control"], "requirements": {"degrees": ["diploma"], "majors": ["finance", "accounting"], "languages": ["english", "chinese"], "language_level": ["fluent"], "hard_skills": ["accounting software", "basic", "lcc", "ms office"], "soft_skills": ["good team player", "independent", "responsible", "work under pressure"], "languages_combined": [{"language": "english", "language_level": ["fluent"]}, {"language": "chinese", "language_level": ["fluent"]}]}, "experience_required": {"duration": ["minimum 1-2 years"], "field": ["relevant experience"]}}, {"job_id": "100003009054097", "location_code": "hk", "company": "Luen Hop Metal and Aluminium Engineering Company Limited", "job_title": "Senior Account Clerk", "description": "We are now seeking an Accounting\u00a0Officer to join our family. If you think you are suited for it. Contact us!\n\nResponsibilities:\n\nPerform daily accounting operations and administrative duties\nAssist in preparing management accounting reports and month-end closing\nMaintain proper and systematic filing system\nProcess payroll and tax affairs\nProvide support in ad hoc projects assigned by Director\n\nRequirements:\n\nDiploma\u00a0or above in accountancy or related disciplines with LCC middle level\nFamiliar with accounting package, preferably\u00a0Peach-tree\nPC Knowledge of MS Word, Excel, PowerPoint and Chinese word-processing\n1-2 years relevant working experience\nImmediately available highly preferred\n\nWe offer excellent career prospects to the right candidates. Our attractive remuneration includes:\n\nBank Holidays\nPaid sick leave\nAnnual leave\nVariable bonus\n\nPrivacy Statement\n\nData collected will be used for recruitment purposes only. Personal data provided will be used strictly in accordance with the relevant data protection law of Hong Kong Special Administration Region.\n\nAll applications applied through our system will be delivered directly to the advertiser and privacy of personal data of the applicant will be ensured with security.\n\nWe are looking forward to your application.\n\nInterest parties please click \u201cAPPLY NOW\u201d to submit your application\n\n(Personal data collected will be used for recruitment purpose only.)", "employment_types": ["Full Time", "Permanent"], "selling_points": ["Diploma or above in Accountancy", "5 years  relevant working experience", "Know MYOB will be an advantage"], "locations": ["Shatin Area"], "categories": ["Accounting", "Accounting Clerk / Supervisor", "Finance / Accounting Manager", "Admin & HR", "Clerical / Admin Staff"], "post_time": "2022-01-17T08:31:31Z", "salary": {"currency": "HKD", "max": 24999, "min": 20000, "period": "monthly", "term": null}, "salary_visible": true, "title_keywords": ["senior account clerk"], "responsibilities": ["tax", "management", "provide support", "daily accounting operations", "month-end closing", "administrative duties", "reports", "maintain", "ad hoc projects", "payroll"], "requirements": {"degrees": ["diploma or above"], "majors": ["related disciplines", "accountancy"], "languages": ["chinese"], "language_level": [], "hard_skills": ["excel", "chinese word-processing", "powerpoint", "lcc", "pc knowledge", "ms word"], "soft_skills": [], "languages_combined": [{"language": "chinese", "language_level": []}]}, "experience_required": {"duration": ["1-2 years"], "field": ["relevant working experience"]}}, {"job_id": "100003009054608", "location_code": "hk", "company": "Wealth Capital Limited", "job_title": "Account clerk", "description": "Job Responsibilities:\u00a0\n\nHandle full set of accounts & month end closing independently.\nHandle daily accounting operation,account payable & receivable,treasury,bank activities,\u00a0Voucher preparation & administration.\nPrepare monthly schedules, various analysis reports & general ledger.\nPerform auditing, forecasting & budgeting, handle accounts reconciliation.\nDevelop & implement accounting & finance policies & operation process.\nHandle the Accounting Team as one-man band professional and provide advice to\u00a0management to review operation and financial performance.\nPerform adhoc duties assigned by supervisor\u00a0\n\nJob Requirements:\n\nDiploma or above in Accountancy or related discipline\n\n5 year or above relevant working experience in construction field\n\nGood command of written and spoken English\nProficient in MS office, strong in Excel (is a must)\nKnow MYOB will be an advantage", "employment_types": ["Full Time"], "selling_points": ["5-day work week", "Nice working environment", "development opportunities"], "locations": ["Southern Area"], "categories": ["Accounting", "Accounting Clerk / Supervisor"], "post_time": "2022-01-17T10:14:00Z", "salary": {"currency": null, "max": null, "min": null, "period": "monthly", "term": null}, "salary_visible": false, "title_keywords": ["account clerk"], "responsibilities": ["month end closing", "management", "schedules", "voucher preparation", "analysis reports", "full set of accounts", "general ledger", "budgeting", "policies", "develop", "review", "provide advice", "daily accounting", "forecasting", "auditing", "administration"], "requirements": {"degrees": ["diploma or above"], "majors": ["accountancy"], "languages": ["english"], "language_level": ["good command"], "hard_skills": ["excel", "myob", "ms office"], "soft_skills": [], "languages_combined": [{"language": "english", "language_level": ["good command"]}]}, "experience_required": {"duration": ["5 year"], "field": ["construction", "relevant working experience"]}}, {"job_id": "100003009052997", "location_code": "hk", "company": "LC Industrial (Hong Kong) Ltd", "job_title": "Senior / Accounting Officer", "description": "Requirements:\n\nPrepare annual closing schedules especially bank reconciliation and support year-end closing\nSupport statutory audit and prepare audit schedules\nSupport ad hoc projects and duties as assigned\nGood command of written and spoken English & Chinese/Mandarin\nHonest, self-discipline and good interpersonal communication skill\n\nQualifications:\n\nDiploma or above in Accountancy or equivalent\n2 years\u2019 relevant working experience\nProficient in Microsoft Office including Word, Excel and Outlook\nProficient in Peachtree accounting software will be an advantage\n\nBenefits:\n\nAnnual leave\nPerformance Related Bonus\nPaid Study and Exam leaves for professional exams\nOn-job training\nMedical, meal and travelling allowance\nGood working environment\n\nInterested parties, please send detailed resume to Charterway Secretarial Limited by clicking \u201cApply Now\u201d or please call Miss Rebecca Lau at 2542 2800", "employment_types": ["Full Time"], "selling_points": ["F.5 or above with LCC + , 4 years relevant exp.", "Handle full set of accounting", "Bank Reconciliation , reports, bills, taxation"], "locations": ["Ngau Tau Kok"], "categories": ["Accounting", "Accounting Clerk / Supervisor"], "post_time": "2022-01-17T04:55:13Z", "salary": {"currency": null, "max": null, "min": null, "period": "monthly", "term": null}, "salary_visible": false, "title_keywords": ["accounting officer"], "responsibilities": ["software", "schedules", "bank reconciliation", "audit", "communication", "ad hoc projects", "year-end closing"], "requirements": {"degrees": ["diploma or above"], "majors": ["accountancy"], "languages": ["english", "chinese", "mandarin"], "language_level": ["good command"], "hard_skills": ["excel", "microsoft office", "accounting software", "word", "outlook", "peachtree"], "soft_skills": ["communication skill", "interpersonal", "honest"], "languages_combined": [{"language": "english", "language_level": ["good command"]}, {"language": "chinese", "language_level": ["good command"]}, {"language": "mandarin", "language_level": ["good command"]}]}, "experience_required": {"duration": ["2 years"], "field": ["relevant working experience"]}}, {"job_id": "100003009053003", "location_code": "hk", "company": "Citybase Property Management Limited", "job_title": "Accounting Clerk", "description": "Senior / Accounting Officer\u00a0\n\nJob Highlights\n\n-\u00a0 \u00a0 \u00a0 \u00a0Handle full set of accounting duties , including AP and AR ;\u00a0\u00a0\n-\u00a0 \u00a0 \u00a0 Minimum 4 year relevant experience.\n\nJob descriptions\n\n-\u00a0\u00a0\u00a0\u00a0\u00a0\u00a0\u00a0 Handle daily accounting duties include voucher preparation, invoice billing, cheque payment and journal entries\n\n-\u00a0\u00a0\u00a0\u00a0\u00a0\u00a0\u00a0 Data entry for accounting aspects and maintain proper records of receipt, payment and billing\n\n-\u00a0\u00a0\u00a0\u00a0\u00a0\u00a0\u00a0 Follow up receivables collection and handle discrepancy reconciliation with customer\n\n-\u00a0\u00a0\u00a0\u00a0\u00a0\u00a0\u00a0 Schedule payments to vendors and cash flow control\n\n-\u00a0\u00a0\u00a0\u00a0\u00a0\u00a0\u00a0 Provide reports, such as management report, bank reconciliation,\u00a0bills and\n\npayment ;\u00a0aging and cash flow forecasts\n\nRequirements\n\n-\u00a0\u00a0\u00a0\u00a0\u00a0\u00a0\u00a0 F.5 or above with LCC or related accounting knowledge and minimum 4 year relevant experience.\n\n-\u00a0\u00a0\u00a0\u00a0\u00a0\u00a0\u00a0 Good interpersonal and communication skills with patience on discrepancy reconciliation\n\n-\u00a0\u00a0\u00a0\u00a0\u00a0\u00a0\u00a0 Proficient in MS Excel, Word, Chinese word processing and basic computer knowledge\n\n-\u00a0\u00a0\u00a0\u00a0\u00a0\u00a0\u00a0 Familiar with MYOB is an advantage\n\n-\u00a0\u00a0\u00a0\u00a0\u00a0\u00a0\u00a0 Immediate availability preferred.\n\n-\u00a0\u00a0\u00a0\u00a0\u00a0\u00a0\u00a0 Fresh graduate can be considered\n\nOffer:\n\n-\u00a0\u00a0\u00a0\u00a0\u00a0\u00a0\u00a0 5.5 days\u2019 work per week\n\n-\u00a0\u00a0\u00a0\u00a0\u00a0\u00a0\u00a0 Competitive Salary Package\n\n-\u00a0\u00a0\u00a0\u00a0\u00a0\u00a0\u00a0 13 months' End-end bonus\n\n-\u00a0\u00a0\u00a0\u00a0\u00a0\u00a0\u00a0 Group Medical Scheme\n\n-\u00a0\u00a0\u00a0\u00a0\u00a0\u00a0\u00a0 Salary - $15-20k", "employment_types": ["Full Time", "Permanent"], "selling_points": ["Form 5 / Diploma holder", "LCC&I Intermediate", "Proficiency in MS Office"], "locations": ["Mong Kok"], "categories": ["Accounting", "Accounting Clerk / Supervisor", "Others"], "post_time": "2022-01-17T04:57:19Z", "salary": {"currency": null, "max": null, "min": null, "period": "monthly", "term": null}, "salary_visible": false, "title_keywords": ["accounting clerk"], "responsibilities": ["control", "data entry", "invoice", "voucher preparation", "bank reconciliation", "provide reports", "payment", "cash flow", "journal entries", "schedule", "payments", "maintain proper records", "daily accounting", "management report"], "requirements": {"degrees": ["fresh graduate"], "majors": [], "languages": ["chinese"], "language_level": ["basic", "proficient"], "hard_skills": ["chinese word processing", "basic", "word", "scheme", "ms excel", "lcc", "myob"], "soft_skills": ["communication skills", "interpersonal", "patience"], "languages_combined": [{"language": "chinese", "language_level": ["basic", "proficient"]}]}, "experience_required": {"duration": ["minimum 4 year"], "field": ["related", "accounting", "relevant experience"]}}, {"job_id": "100003009053358", "location_code": "hk", "company": "Herbs Generation International Limited", "job_title": "Part-time Accounting Clerk", "description": "Job Description\n\nManage AR, AP, issue cheque\nProvide general administrative and clerical supports\nHandle both internal and external documents delivery requirements\nHandle ad-hoc assignments as required\n\nJob Requirement\n\nF.5 / Diploma Holder or above with at least 2 years working experience\nLCC & I\u00a0 Intermediate in accounting or equivalent\nSelf- motivated,\u00a0responsible, well organized and willing to learn\nProficient in MS Office, Excel\u00a0/ Word\u00a0\u00a0\nImmediate available is preferred\nWe will offer attractive compensation package to the right candidate. Please send application enclosing resume stating career and salary history, expected salary and date of availability to HR Manager, Citybase Property Management Limited, Unit No.1, 6/F, Hampton Loft, 11 Hoi Fan Road, Tai Kok Tsui, Kowloon by fax at 2717 4717 or by clicking ''Apply Now'' (in Word format). Please quote the reference of the position you apply for in all correspondences.\nWe are an equal opportunity employer and welcome applications from all qualified candidates. Personal data collected will be treated in strictest confidence and handled confidentially by authorized personnel for recruitment-related purposes within the Group. Applicants not hearing from us within six weeks from the date of advertisement may consider their applications unsuccessful.", "employment_types": ["Part Time"], "selling_points": [], "locations": ["Lai Chi Kok"], "categories": ["Accounting", "Accounting Clerk / Supervisor", "Others", "Admin & HR", "Clerical / Admin Staff"], "post_time": "2022-01-17T06:52:24Z", "salary": {"currency": null, "max": null, "min": null, "period": "hourly", "term": null}, "salary_visible": false, "title_keywords": ["accounting clerk"], "responsibilities": ["ap", "ad-hoc assignments", "ar", "documents delivery"], "requirements": {"degrees": ["diploma holder"], "majors": [], "languages": [], "language_level": [], "hard_skills": ["excel", "no", "word", "lcc", "ms office"], "soft_skills": ["confidence", "responsible", "well organized", "willing to learn", "motivated"], "languages_combined": []}, "experience_required": {"duration": ["at least 2 years"], "field": []}}, {"job_id": "100003009051736", "location_code": "hk", "company": "Tat Ming Wallpaper Company Limited", "job_title": "Accounting officer \u2013 5day work", "description": "Responsibilities:\nSupport daily accounting duty, data entry, documentation & report\nPerform accounting functions mainly A/R, A/P and assist in month end closing\nReconcile account balance\nProvide support in ad hoc projects and assignments\nWorking hours are Monday to Friday from 9:00am to 6:00pm\nRequirement:\nDiploma or above, LCCI 3\nAround 1 year solid A/C field experience\nSelf-motivated, work independent and able to work under pressure\nA fast learner with high flexibility and detail minded\nGood communication skills in English, Cantonese and Mandarin\nProficiency in computer skill (e.g. MS Office)\nImmediate available is highly preferred\nInterested parties please send full resume with expected salary to HRA Department by e-mail via \"Apply Now\"\n\nLearn more about us at www.herbs.hk/ www.zino.hk/ www.zinomall.com\n*Personal data collected will be used for recruitment purpose only.", "employment_types": ["Part Time"], "selling_points": ["5-Day work week, Double pay & Performance bonus", "Higher Diploma or above in Accounting", "Over 2 years related experience"], "locations": ["Not Specified"], "categories": ["Accounting", "Accountant", "Accounting Clerk / Supervisor", "Others"], "post_time": "2022-01-16T21:51:18Z", "salary": {"currency": null, "max": null, "min": null, "period": "monthly", "term": null}, "salary_visible": false, "title_keywords": ["accounting officer"], "responsibilities": ["month end closing", "provide support", "data entry", "ad hoc projects", "documentation", "daily accounting", "report"], "requirements": {"degrees": ["diploma or above"], "majors": [], "languages": ["cantonese", "english", "mandarin"], "language_level": ["good"], "hard_skills": ["c", "computer skill", "ms office"], "soft_skills": ["communication skills", "self-motivated", "independent", "fast learner", "work under pressure"], "languages_combined": [{"language": "cantonese", "language_level": ["good"]}, {"language": "english", "language_level": ["good"]}, {"language": "mandarin", "language_level": ["good"]}]}, "experience_required": {"duration": ["1 year"], "field": []}}, {"job_id": "100003009052586", "location_code": "hk", "company": "HKD Global Limited", "job_title": "Accounts Clerk", "description": "Tat Ming Flooring\n\nResponsibilites:\nHandle full set of accounts \u2013 ERP system\nHandle AR & AP invoices & settlement, accounts reconciliation\nAssist in preparing financial reports, year end closing and annual audit\nReport to Accounting Manager\nRequirement :\nHigher Diploma or above in Accounting\nOver 2 years related experience\nProficiency in MS Excel\nMature, self-motivated, responsible\nImmediate available is highly preferred\nRemuneration\nGood career path opportunities\n5-Day work week\nDouble pay & Performance bonus\nBank holidays\nMedical scheme (Dental & Clinical)\nStaff purchase discount\nInterest parties: please apply in confidence with comprehensive details of work history, salary expectation and contact number e-mail via \"Apply Now' or fax to 2838-0805.\nWebsite : www.tatming.com\n", "employment_types": ["Full Time", "Permanent"], "selling_points": [], "locations": ["North Point"], "categories": ["Accounting", "Accounting Clerk / Supervisor"], "post_time": "2022-01-17T03:48:49Z", "salary": {"currency": null, "max": null, "min": null, "period": "monthly", "term": null}, "salary_visible": false, "title_keywords": ["accounts clerk"], "responsibilities": ["ap", "financial reports", "invoices", "ar", "annual audit", "full set of accounts", "report"], "requirements": {"degrees": ["higher diploma or above"], "majors": ["accounting"], "languages": [], "language_level": [], "hard_skills": ["ms excel", "scheme"], "soft_skills": ["self-motivated", "confidence", "responsible", "mature", "comprehensive"], "languages_combined": []}, "experience_required": {"duration": ["2 years"], "field": ["related"]}}, {"job_id": "100003009052455", "location_code": "hk", "company": "I. T. H. K. Limited", "job_title": "Accounts Clerk  (Italian Tomato)", "description": "\u2022 F.6 or above with LCCI higher diploma in Accounting\n\n\u2022 Good PC skills, proficient in Excel is a must\n\n\u2022 Good Command of written and spoken English\n\u2022 Self-motivated, responsible and well-organized\n\n\n\n\nInterested parties, please forward your resume by clicking\u00a0\u201cApply Now\u201d.\n\nThe information provided by candidates will be treated in strict confidential and use for recruitment purpose only", "employment_types": ["Full Time", "Permanent"], "selling_points": [], "locations": ["Tsuen Wan Area"], "categories": ["Accounting", "Accounting Clerk / Supervisor", "Others"], "post_time": "2022-01-17T03:04:20Z", "salary": {"currency": null, "max": null, "min": null, "period": "monthly", "term": null}, "salary_visible": false, "title_keywords": ["accounts clerk"], "responsibilities": [], "requirements": {"degrees": ["diploma"], "majors": ["accounting"], "languages": ["english"], "language_level": ["good command"], "hard_skills": ["excel", "pc skills"], "soft_skills": ["self-motivated", "well-organized", "responsible"], "languages_combined": [{"language": "english", "language_level": ["good command"]}]}, "experience_required": {"duration": [], "field": []}}, {"job_id": "100003009051755", "location_code": "hk", "company": "Wing Han Imports & Exports Trading Company Limited", "job_title": "ACCOUNTS CLERK (5-DAY WORK)", "description": "Responsibilities\n\n\nDay to day operation in Accounts Receivables/ Accounts Payables, Inventory.\nAssist in ad hoc assignment as required.\n\nRequirements\n\n\nDSE or above with certification of LCC&I level 2\n1 - 2 years' relevant working experience\nProficiency in PC skills, especially EXCEL and Flex Accounting System\nPleasant, self-initiative, possess good interpersonal skills and analytical mind\nAble to work independently\nImmediate availability is highly preferred\n\nBenefits & Package\n\n5 days work (9:30 \u2013 18:00)\nFriendly working environment\nAnnual Leave 12 days\nGroup Medical\nMarriage Leave / Compassionate Leave\nStaff Purchase Discount\nOn the Job Training\n\nInterested parties, please send full resume with availability, current and expected salary by clicking \u201cAPPLY NOW\u201d.\u00a0Application without expected salary will not be entertained.\n\n(All personal data collected will be kept in strict confidence and to be used for recruitment related purpose only.)", "employment_types": ["Full Time", "Permanent"], "selling_points": [], "locations": ["Sheung Wan"], "categories": ["Accounting", "Accounting Clerk / Supervisor"], "post_time": "2022-01-17T00:29:52Z", "salary": {"currency": null, "max": null, "min": null, "period": null, "term": null}, "salary_visible": false, "title_keywords": ["accounts clerk"], "responsibilities": ["inventory", "ad hoc assignment"], "requirements": {"degrees": ["dse"], "majors": [], "languages": [], "language_level": [], "hard_skills": ["excel", "flex accounting", "pc skills"], "soft_skills": ["work independently", "pleasant", "analytical mind", "self-initiative", "interpersonal skills"], "languages_combined": []}, "experience_required": {"duration": ["1 - 2 years"], "field": ["relevant working experience"]}}, {"job_id": "100003009053384", "location_code": "hk", "company": "YOOV Internet Technology (HK) Limited", "job_title": "Assistant Accounting Officer (5-day work)", "description": "Accounts Clerk (5-day work)\n\nMain Responsibilities:\n\nPerform daily accounting duties including preparing vouchers, journal entries, account receivable, account payable and bank reconciliation, etc.\nPrepare regular reports for month-end closing and year-end closing\nFiling and general accounting duties\nAssist in other accounting related and ad-hoc assignments\n\nRequirements:\n\nForm 5 or above with Diploma in Accounting\u00a0\nAttained LCCI II level certificate\nProficient at using MS Windows (Excel and Word)\nAt least 2 years accounting experience\nKnowledge in FlexSystem accounting software is preferred\nStrong sense of responsibility, hardworking\nImmediate available is preferred\nInterested parties, please send your resume and expected salary to Joanne Lee.", "employment_types": ["Full Time", "Permanent"], "selling_points": ["Accounting Officer, Asst Acc Officer, Accounting", "Full set, Payroll, Tax", "Fast Growing Company with Good Prospect"], "locations": ["Kwun Tong"], "categories": ["Accounting", "Accounting Clerk / Supervisor", "Treasurer", "Others", "Student / Fresh Graduate / No Experience"], "post_time": "2022-01-17T06:54:08Z", "salary": {"currency": null, "max": null, "min": null, "period": "monthly", "term": null}, "salary_visible": false, "title_keywords": ["assistant accounting officer"], "responsibilities": ["preparing vouchers", "ad-hoc assignments", "bank reconciliation", "month-end closing", "journal entries", "reports", "year-end closing", "general accounting duties", "daily accounting"], "requirements": {"degrees": ["certificate", "diploma", "form 5 or above"], "majors": ["accounting"], "languages": [], "language_level": [], "hard_skills": ["excel", "flexsystem", "ms windows", "accounting software", "word"], "soft_skills": ["hardworking", "sense of responsibility"], "languages_combined": []}, "experience_required": {"duration": ["at least 2 years"], "field": ["accounting experience"]}}, {"job_id": "100003009054448", "location_code": "hk", "company": "Weltronics Component Ltd", "job_title": "Temporary Accounts Clerk (6 months contract)", "description": "To cope with our business growth, we are currently looking for a high calibre candidate to join us as an Assistant Accounting Officer, assisting in Accounting & Admin Department.\n\nResponsibilities\n\nResponsible for daily accounting operations including AR/AP, general entries, bills and payments, bank reconciliation\nAssist in month end closing and preparation of financial report\nProcess payroll and tax affairs\nMaintain proper and systematic filing system\nPerform ad-hoc assignments when required\n\nRequirements\n\nDiploma or above, major in Accounting or related discipline\n1-2 years relevant working experience\nEnthusiastic, detail-minded, mature with positive attitude and a good team player\nGood command of both spoken & written English and Chinese\u00a0\nProficiency in MS Office applications including Excel, Work. Knowledge in Xero would be an advantage\nImmediately available is highly preferred\n\nInterested candidates please send your job application to our HR Department by \u201cAPPLY NOW\u201d. Please indicate the details of your working experience, current and expected salary, and your date of availability in your CV.\n\n(Only shortlisted candidates will be contacted)\u00a0\n\nPersonal Information Collection Statement (PICS)\n\nThe personal data collected will be used by our member(s) of the recruitment team for recruitment purpose only. It is our policy to retain the personal data of unsuccessful applicants for future recruitment purposes for a period of 3 months. When there are vacancies in our subsidiary or associate companies during that period, we may transfer the candidate\u2019s application to them for consideration of employment. And, all information will be kept confidential during that period and be destroyed after use.\n", "employment_types": ["Full Time", "Permanent"], "selling_points": ["5 days work", "bank holiday", "Data Input, Clerical Work"], "locations": ["Cheung Sha Wan"], "categories": ["Accounting", "Accounting Clerk / Supervisor"], "post_time": "2022-01-17T09:35:09Z", "salary": {"currency": null, "max": null, "min": null, "period": "monthly", "term": null}, "salary_visible": false, "title_keywords": ["accounts clerk"], "responsibilities": ["ap", "tax", "month end closing", "ar", "ad-hoc assignments", "daily accounting operations", "bank reconciliation", "maintain", "payments", "financial report", "payroll"], "requirements": {"degrees": ["diploma or above"], "majors": ["accounting"], "languages": ["english", "chinese"], "language_level": ["good command"], "hard_skills": ["excel", "xero", "ms office"], "soft_skills": ["detail-minded", "good team player", "mature", "positive attitude", "enthusiastic"], "languages_combined": [{"language": "english", "language_level": ["good command"]}, {"language": "chinese", "language_level": ["good command"]}]}, "experience_required": {"duration": ["1-2 years"], "field": ["relevant working experience"]}}, {"job_id": "100003009053928", "location_code": "hk", "company": "Hara Facility and Security Service Limited", "job_title": "Accounting Supervisor", "description": "Responsibities:\n\nProvide clerical support eg. data entry, record updating, invoicing, scanning and filing\nRequirements\n\nDSE or above\nWell organized, strong sense of responsibility, detail-minded\nProficiency in MS Office Excel application and Chinese word processing\nImmediate available is highly preferred\n\nWe offer 5-day week and competitive remuneration based on qualifications and experience. \u00a0Interested parties please send detailed resume with present and expected salary by clicking \"Apply Now\"\n\n\nData collected will be used for recruitment purpose only", "employment_types": ["Full Time"], "selling_points": [], "locations": ["Kwun Tong"], "categories": ["Accounting", "Accounting Clerk / Supervisor"], "post_time": "2022-01-17T07:47:51Z", "salary": {"currency": null, "max": null, "min": null, "period": "monthly", "term": null}, "salary_visible": false, "title_keywords": ["accounting supervisor"], "responsibilities": ["provide clerical support", "invoicing", "scanning", "data entry"], "requirements": {"degrees": ["dse"], "majors": [], "languages": ["chinese"], "language_level": ["proficiency"], "hard_skills": ["excel", "chinese word processing", "ms office"], "soft_skills": ["detail-minded", "well organized", "sense of responsibility"], "languages_combined": [{"language": "chinese", "language_level": ["proficiency"]}]}, "experience_required": {"duration": [], "field": []}}, {"job_id": "100003009053192", "location_code": "hk", "company": "The Lok Sin Tong Benevolent Society, Kowloon", "job_title": "Accounting Officer \u6703\u8a08\u4e3b\u4efb", "description": "Accounting Supervisor ( 5 working days, Property Management)\n\n\u00a0Job Highlights\n\n5 working days (Mon-Fri:09:00-18:00)\nDiscretionary bonus\nBank HolidaysWorking location: Kwun Tong (2 minutes to MTR)\nMore experience can be considered as Assistant Accounting Manager\nImmediate available is highly preferredExperience in property management is preferred\n\u00a0Job Description\n\nResponsibilities\nSolid experience in handle full set of accounting books\nPrepare monthly management reports and yearly financial reports\nAssist in accounts payable, accounts receivable, invoice issuing\nUndertake ad hoc assignment\nProactive work attitude with good communication and interpersonal skills\n\nRequirements\nBachelor holder in Accounting or related disciplines\nStudent member of professional accounting bodies\nAt least 4-5 years working experience in accounting or audit field\nExperience in property management industry is an advantage\n\nProficiency in MS office and computerized systems is a must\nStrong sense of responsibility, self-motivated, detail-oriented and independent\nGood command of written and spoken Cantonese and English\nAble to work under pressure and handle multiple tasks\n\nInterested parties please send a full resume indicating with your\u00a0present\u00a0and\u00a0expected\u00a0salary and earliest date available by clicking \"Apply Now\".\n\nThe information provided will be treated in strict confidence & be used only for consideration of your application. We may retain the unsuccessful applications for a maximum period of 24 months.", "employment_types": ["Full Time"], "selling_points": [], "locations": ["Kowloon City"], "categories": ["Accounting", "Accountant", "Accounting Clerk / Supervisor", "Others"], "post_time": "2022-01-17T06:22:45Z", "salary": {"currency": null, "max": null, "min": null, "period": "monthly", "term": null}, "salary_visible": false, "title_keywords": ["accounting officer"], "responsibilities": ["financial reports", "accounts receivable", "invoice", "ad hoc assignment", "handle full set of accounting", "communication", "management reports", "accounts payable"], "requirements": {"degrees": ["bachelor"], "majors": ["related disciplines", "accounting"], "languages": ["cantonese", "english"], "language_level": ["good command"], "hard_skills": ["ms office"], "soft_skills": ["self-motivated", "independent", "sense of responsibility", "detail-oriented", "handle multiple tasks", "work under pressure"], "languages_combined": [{"language": "cantonese", "language_level": ["good command"]}, {"language": "english", "language_level": ["good command"]}]}, "experience_required": {"duration": ["at least 4-5 years"], "field": ["management", "accounting", "audit"]}}, {"job_id": "100003009053554", "location_code": "hk", "company": "Technik Performance Limited", "job_title": "Account & Admin Clerk", "description": "Job Duty\uff1a\u00a0\nHandle full set of accounts and month end closing\nPrepare monthly statement and breakdown\nMaintain good accounting and operation control\nMonitor other staff\u00a0accounting duties\nAssist in annual audit\n\nRequirements:\n\nBachelor degree holder in Accounting\n3 years\u2019 relevant working experience\nProficient in MS applications both in English and Chinese (including Excel & Word)\nExperienced in accounting software such as Flex System\nAuditing experience will be an advantage\nHave initiative, detail-minded, responsible, integrity and good interpersonal skills\n\nApplications with full resume and expected salary should be\u00a0email to\u00a0us.\n\n(All applications will be treated in strict confidence and used solely for the purpose of recruitment)", "employment_types": ["Full Time"], "selling_points": ["Accounting work and office administration", "Immediate available is preferable", "Bank holiday"], "locations": ["Kowloon Bay"], "categories": ["Accounting", "Accounting Clerk / Supervisor", "Admin & HR", "Clerical / Admin Staff"], "post_time": "2022-01-17T09:25:23Z", "salary": {"currency": null, "max": null, "min": null, "period": "monthly", "term": null}, "salary_visible": false, "title_keywords": ["admin clerk"], "responsibilities": ["month end closing", "control", "software", "annual audit", "full set of accounts", "monitor", "maintain", "recruitment", "accounting duties", "auditing"], "requirements": {"degrees": ["bachelor degree holder"], "majors": ["accounting"], "languages": ["english", "chinese"], "language_level": ["proficient"], "hard_skills": ["excel", "ms applications", "accounting software", "word", "flex system"], "soft_skills": ["detail-minded", "confidence", "responsible", "integrity", "interpersonal skills", "initiative"], "languages_combined": [{"language": "english", "language_level": ["proficient"]}, {"language": "chinese", "language_level": ["proficient"]}]}, "experience_required": {"duration": ["3 years"], "field": ["relevant working experience"]}}, {"job_id": "100003009053441", "location_code": "hk", "company": "Hong Kong Breast Cancer Foundation Limited", "job_title": "Accounting Officer", "description": "Job Highlights\n\nAccounting work and office administration\nImmediate available is preferable\nBank holiday\n\nJob Description\n\nProvide office clerical and administration support Manage project filing system\n\nReport to company Directors and Managers Accounting Records\nProvide full spectrum of secretarial support to Director on business, personal and social affairs\nProvide office clerical and administration support\nHandle goods import related shipments independently and follow up quotation with forwarders\nAssisting in purchase order / quotation follow-up\nReport and analyze on warehouse, inventory and sales data to support company growth\n\n\u00a0Requirements:\n\nDegree holder with formal secretarial training\n\n2-3 years working experience\nLCCI level 2 Certificate\nGood communication skills\nPatient, Polite and well-mannered\nWorking experience in automotive industry will be an advantage\nAttentive to detail, strong sense of responsibility and cooperative\nCreative, sensitive to numbers, detail-minded, good presentation and interpersonal skills\nProactive, discreet, well-organized with good interpersonal skills, able to prioritize and multitask\nGood command of both spoken & written in English and Chinese\nWell-versed in MS Words, Excel, PowerPoint\nImmediate available is preferable\nAccounting and Peachtree Software Knowledge will be an advantage\n\nBenefits:\n\nMedical insurance, discretionary bonus, attendance bonus, bank holiday\nWorking location: Kowloon Bay\nAttractive remuneration, fringe benefits\n\nPlease send your full resume with the available date, current, and expected salary by clicking \"Apply Now\". All information provided will be treated in strict confidence and used for recruitment purposes only.", "employment_types": ["Full Time", "Permanent"], "selling_points": [], "locations": ["North Point"], "categories": ["Accounting", "Accounting Clerk / Supervisor", "Others"], "post_time": "2022-01-17T06:59:22Z", "salary": {"currency": null, "max": null, "min": null, "period": "monthly", "term": null}, "salary_visible": false, "title_keywords": ["accounting officer"], "responsibilities": ["administration", "data", "inventory", "quotation", "purchase", "secretarial support", "report"], "requirements": {"degrees": ["certificate", "degree holder"], "majors": [], "languages": ["english", "chinese"], "language_level": ["good command"], "hard_skills": ["excel", "peachtree", "powerpoint", "ms words"], "soft_skills": ["detail-minded", "communication skills", "proactive", "attentive to detail", "polite", "able to prioritize", "sense of responsibility", "cooperative", "well-organized", "multitask", "interpersonal skills", "patient", "sensitive to numbers", "creative", "presentation"], "languages_combined": [{"language": "english", "language_level": ["good command"]}, {"language": "chinese", "language_level": ["good command"]}]}, "experience_required": {"duration": ["2-3 years"], "field": ["automotive industry"]}}, {"job_id": "100003009053230", "location_code": "hk", "company": "Alliance Contracting Co Ltd", "job_title": "Accounts Clerk", "description": "Responsibilities:\n\nHandle full set of accounts independently, including preparation and reviewing ledger balances and monthly accounts\nPrepare journal entries and related function\nMaintain records of all receipts and payments\nHandle general account queries\nPerform accounting and clerical functions to support supervisors\nCompile statistics and prepare reporting package to the HKBCF\u2019s funding bodies\nEnsure operation process and procedures are in compliance with the HKBCF\u2019s policies and statutory accounting requirements of the HKSAR\nPerform outdoor works when necessary\nRequirements:\n\nHigh Diploma / Associate Degree in Accounting or related disciplines.\nAt least\u00a01 year\u2019s relevant working experience in Accounting,preferably gained from non-profit charitable organisation.\nSound knowledge in bookkeeping and business acumen. Practical knowledge and experience in Flex system operations is an advantage.\nProficient in MS Office, especially Word, Excel and Chinese word processing.\nGood command of written and spoken English and Chinese.\nDetailed-minded, well organised, responsible, independent and able to meet tight deadline.\n\nPlease send your full resume stating expected salary and date of availability to\u00a0Hong Kong Breast Cancer Foundation Limited\u00a0by post to\u00a0Units 1705-06, 17/F, Jupiter Tower, 9 Jupiter Street, North Point\u00a0or click \u201cAPPLY NOW\u201d.\u00a0 All applications will be treated with complete confidentiality.\u00a0 Consideration of applications will continue until the position is filled.\u00a0 Only shortlisted applicants will be contacted.\n\n(Personal data collected will be used for recruitment purposes only.)", "employment_types": ["Full Time", "Permanent"], "selling_points": [], "locations": ["To Kwa Wan"], "categories": ["Accounting", "Accounting Clerk / Supervisor"], "post_time": "2022-01-17T06:29:49Z", "salary": {"currency": null, "max": null, "min": null, "period": "monthly", "term": null}, "salary_visible": false, "title_keywords": ["accounts clerk"], "responsibilities": ["reporting", "receipts", "policies", "full set of accounts", "procedures", "compliance", "maintain", "payments", "journal entries"], "requirements": {"degrees": ["high diploma", "associate degree"], "majors": ["related disciplines", "accounting"], "languages": ["english", "chinese"], "language_level": ["good command", "proficient"], "hard_skills": ["excel", "chinese word processing", "word", "acumen", "flex system", "ms office"], "soft_skills": ["independent", "responsible", "organisation", "organised", "business acumen", "meet tight deadline", "detailed"], "languages_combined": [{"language": "english", "language_level": ["good command"]}, {"language": "chinese", "language_level": ["good command", "proficient"]}]}, "experience_required": {"duration": ["at least 1 year"], "field": ["accounting", "relevant working experience"]}}, {"job_id": "100003009053863", "location_code": "hk", "company": "iAsia Online Systems Limited", "job_title": "Accounting Assistant (Fresh Graduate will also be considered)", "description": "Job duties:\n\n\nTo provide accounting and clerical support including preparation of voucher, bank reconciliation, maintain document registers and ad hoc assignment as needed\n\nJob requirements:\n\n\nForm 5 graduate or above\nLCCI level 2 or above\n1 year relevant experience\u00a0\nProficiency in Microsoft Word and Excel\nFresh graduates will also be considered\n\nInterested parties, please send your detailed resume including employment history and expected salary by clicking \"Apply Now\".\n\nInformation provided by applicants will be treated in strict confidence and used only for recruitment purposes.\u00a0The Company will retain unsuccessful job applications for a maximum period of one year.", "employment_types": ["Permanent"], "selling_points": ["Perform daily accounting duties", "1-2 years working experience in Accounting", "Attractive remuneration package"], "locations": ["Yau Tsim Mong Area"], "categories": ["Accounting", "Accounting Clerk / Supervisor", "Others", "Admin & HR", "Clerical / Admin Staff"], "post_time": "2022-01-17T07:38:49Z", "salary": {"currency": null, "max": null, "min": null, "period": "monthly", "term": null}, "salary_visible": false, "title_keywords": ["accounting assistant"], "responsibilities": ["ad hoc assignment", "maintain", "clerical support", "bank reconciliation"], "requirements": {"degrees": ["form 5"], "majors": [], "languages": [], "language_level": [], "hard_skills": ["excel", "microsoft word"], "soft_skills": [], "languages_combined": []}, "experience_required": {"duration": ["1 year"], "field": ["relevant experience"]}}, {"job_id": "100003009054689", "location_code": "hk", "company": "Our Hong Kong Foundation Limited", "job_title": "Assistant Accounting Officer", "description": "Primary Responsibilities\n\n\u00a0 \u00a0 \u00a0 \u00a0\u00a0 Perform daily accounting duties including invoicing, AP, AR,\u00a0 \u00a0 \u00a0 \u00a0 \u00a0 \u00a0 \u00a0GL, petty cash and data entry\n\u00a0 \u00a0 \u00a0 \u00a0 \u00a0Prepare\u00a0monthly bank reconciliation\n\u00a0\u00a0\u00a0\u00a0\u00a0\u00a0\u00a0\u00a0 Assist in month-end closing and audit\n\u00a0\u00a0\u00a0\u00a0\u00a0\u00a0\u00a0\u00a0 Prepare ledger breakdown\n\u00a0\u00a0\u00a0\u00a0\u00a0\u00a0\u00a0\u00a0 Perform ad hoc tasks as required\n\nRequirements\n\n\u00a0\u00a0\u00a0\u00a0\u00a0\u00a0\u00a0\u00a0 HKDSE or above with LCCI level II certificate\n\u00a0\u00a0\u00a0\u00a0\u00a0\u00a0\u00a0\u00a0 2 years working experience in Accounting function\n\u00a0\u00a0\u00a0\u00a0\u00a0\u00a0\u00a0\u00a0 Proficiency in MS Office (Excel, Word)\n\u00a0\u00a0\u00a0\u00a0\u00a0\u00a0\u00a0\u00a0 Proficiency in Peachtree is an advantage\n\u00a0\u00a0\u00a0\u00a0\u00a0\u00a0\u00a0\u00a0 Strong sense of responsibility and well-organized\n\n\u00a0We Offer\n\nCareer advancement opportunities\nAttractive remuneration package\n5-day work week and bank holiday\u00a0\nCompany medical insurance, life insurance and dental insurance\nYear End Discretionary Bonus\nOn job training and training allowance\nEducation sponsorship\nFriendly working environment\nStaff Activities & Events e.g. Happy Friday Gathering, Annual Dinner, Festival Gift, Christmas Party, etc\n\nInterested parties please apply by clicking \"Apply Now\" to send full resume with current & expected salary.\n\nFor more information of our company, please visit our website address:\u00a0http://www.iasia.com.hk\n\n(Data collected would be used for recruitment purpose only)", "employment_types": ["Full Time", "Permanent"], "selling_points": ["Fresh graduates in related disciplines welcome", "Friendly working team in a fast-paced environment", "Opportunity to learn and grow"], "locations": ["Central & Western Area"], "categories": ["Accounting", "Accounting Clerk / Supervisor", "Others", "Others", "Student / Fresh Graduate / No Experience"], "post_time": "2022-01-17T10:35:25Z", "salary": {"currency": null, "max": null, "min": null, "period": "monthly", "term": null}, "salary_visible": false, "title_keywords": ["assistant accounting officer"], "responsibilities": ["ap", "ar", "data entry", "ad hoc tasks", "bank reconciliation", "audit", "invoicing", "month-end closing", "daily accounting"], "requirements": {"degrees": ["certificate", "hkdse"], "majors": [], "languages": [], "language_level": [], "hard_skills": ["peachtree", "excel", "word", "ms office"], "soft_skills": ["well-organized", "sense of responsibility"], "languages_combined": []}, "experience_required": {"duration": ["2 years"], "field": ["accounting"]}}, {"job_id": "100003009053356", "location_code": "hk", "company": "Fung Heung Yuen Bakery Ltd", "job_title": "Accounting and Administration Assistant", "description": "We are looking for high-caliber finance professionals who are willing to embrace challenges and grow with the organization.\n\nResponsibilities:\n\nDaily accounting operations include general journal entries, bills and payments, bank reconciliation and staff reimbursements\nAdministrative tasks include going to banks, filing and maintenance of books and records and other supporting documents\nAssist in preparing month-end schedules and reports\nAssist in fixed assets count and maintenance of fixed assets register\nAssist in other ad hoc administrative tasks as assigned\n\nRequirements:\n\n\nFresh graduates in related disciplines welcome\nDetail-oriented, multi-tasking, organize and a team player\nEnjoy working in a fast-paced and dynamic environment\nGood command of spoken and written English and Chinese\nProficient in MS Office and Chinese Word Processing\n\nInterested parties please send:\n\nFull resume;\nCover letter;\nCopies of academic transcripts (including public examination results if applicable);\nPresent and expected salary;\nAvailability\n\n\nBy clicking 'Apply Now' or by post to: Our Hong Kong Foundation Limited, 19/F, Nan Fung Tower, 88 Connaught Road Central, Hong Kong. Applicants who are not invited to an interview within two months from the date of this advertisement should consider their applications unsuccessful.\u00a0\n\nAll information provided by applicants will be handled with strictest confidence and will be solely used for the purpose of recruitment.", "employment_types": ["Full Time"], "selling_points": ["Fresh graduate will also be considered", "Development opportunities", "Immediate available is preferred"], "locations": ["Kwai Hing"], "categories": ["Accounting", "Accounting Clerk / Supervisor", "Admin & HR", "Clerical / Admin Staff"], "post_time": "2022-01-17T06:50:26Z", "salary": {"currency": null, "max": null, "min": null, "period": "monthly", "term": null}, "salary_visible": false, "title_keywords": ["accounting and administration assistant"], "responsibilities": ["ad hoc", "maintenance", "schedules", "daily accounting operations", "bank reconciliation", "month-end", "payments", "journal entries", "reports", "administrative tasks"], "requirements": {"degrees": [], "majors": [], "languages": ["english", "chinese"], "language_level": ["good command", "proficient"], "hard_skills": ["dynamic", "chinese word processing", "ms office"], "soft_skills": ["dynamic environment", "enjoy working", "detail-oriented", "multi-tasking", "team player"], "languages_combined": [{"language": "english", "language_level": ["good command"]}, {"language": "chinese", "language_level": ["good command", "proficient"]}]}, "experience_required": {"duration": [], "field": []}}, {"job_id": "100003009054697", "location_code": "hk", "company": "Lane Crawford (Hong Kong) Limited", "job_title": "Accounting Officer", "description": "Responsibilities:\nResponsible for daily accounting operations such as issue cheque\nResponsible for maintain the bank books and recording daily transactions\nAssist in accounting system implementation project\nPrepare bank reconciliations\nSupport Admin projects as and when required. Such as arrange Interview, filing,\u00a0Stock Receiving. etc.\nAd-hoc tasks as assigned by supervisor\n\n\nRequirements:\n\nForm 5 / HKDSE with LCCI Intermediate level or above\nMinimum 2 years working experience in accounting field\nProficiency in Microsoft Excel, Word and Chinese Word processing\nGood command of English and Chinese\nDetail-minded, self-motivated, willing to learn and able to work under timeline\nKnowledge in ERP is an advantage\nExperience in F&B field is an advantage\nFresh graduate will also be considered\nImmediate available is preferred", "employment_types": ["Permanent"], "selling_points": ["Accounts Payable experience in Retail", "Strong communication and collaboration", "immediately available is preferred"], "locations": ["Southern Area"], "categories": ["Accounting", "Accounting Clerk / Supervisor", "Financial Analyst", "Others"], "post_time": "2022-01-17T10:37:23Z", "salary": {"currency": null, "max": null, "min": null, "period": null, "term": null}, "salary_visible": false, "title_keywords": ["accounting officer"], "responsibilities": ["ad-hoc tasks", "bank reconciliations", "daily accounting operations", "transactions", "implementation", "maintain"], "requirements": {"degrees": ["form 5", "hkdse", "fresh graduate"], "majors": [], "languages": ["english", "chinese"], "language_level": ["proficiency", "good command"], "hard_skills": ["chinese word processing", "word", "erp", "microsoft excel"], "soft_skills": ["detail-minded", "self-motivated", "willing to learn"], "languages_combined": [{"language": "english", "language_level": ["good command"]}, {"language": "chinese", "language_level": ["proficiency", "good command"]}]}, "experience_required": {"duration": ["minimum 2 years"], "field": ["f&b", "accounting"]}}, {"job_id": "100003009052087", "location_code": "hk", "company": "INSTA SPECIALILST CO.LTD", "job_title": "Administrative/Operations Assistant (Contract) \u884c\u653f\u6216\u71df\u904b\u52a9\u7406 (\u5408\u7d04\u5236)", "description": "Job Purpose:\u00a0\n\n\u201cTo coordinate and perform administrative support duties to the Enterprise and Product team.\u201d\n\nKey Accountabilities:\n\nIn addition to following Lane Crawford\u2019s policies and procedures, key accountabilities include, but are not limited to:\n\nAccount Management (30%)\n\nFunction as key contact to Product team seeking to onboard a new supplier\nResponsible for vendor account creation through supplier portal and oracle systems\nFollow through with vendors on required documentations including trademark registration\nCoordinate with the Legal team to walkthrough and solicit suppliers to accept portal for Essential terms\n\nCommunication (40%)\n\nLead as the central point of contact for suppliers in communicating policies and guidelines on :\nLegal \u00a0\u00a0\u00a0\u00a0\u00a0\u00a0\u00a0\u00a0\u00a0\u00a0\u00a0\u00a0\u00a0\u00a0\u00a0\u00a0\u00a0 \u00a0\u00a0\u00a0\u00a0\u00a0\u00a0\u00a0\u00a0\u00a0\u00a0\u00a0\u00a0\u00a0 (Essential business terms)\nLogistics \u00a0\u00a0\u00a0\u00a0\u00a0\u00a0\u00a0\u00a0\u00a0\u00a0 \u00a0\u00a0\u00a0\u00a0\u00a0\u00a0\u00a0\u00a0\u00a0\u00a0\u00a0\u00a0\u00a0 (Shipping reference and Invoice guide, China Customs)\nAccount Payable\u00a0\u00a0\u00a0\u00a0\u00a0\u00a0\u00a0\u00a0\u00a0\u00a0 (Invoice and payment procedures)\nSupport in answering enquiries from suppliers\nCoordinate with other teams to ensure timely and quality responses to enquiries\nWork with Account Payable to manage invoicing, timely payments, resolve discrepancies and issues,\u00a0 correspond with vendors and respond to payment-related inquiries\n\n\u00a0Process Management\n\nDevelop procedures, guidelines and tools to achieve efficiency\nPlan and develop special project and system enhancement to support service quality standards\nEnsure compliance with Policies and Procedures\n\nRequirements:\n\n\n*Candidates with immediate availability is required*\nAt least 3 years of Accounts Payable working experience in Retail industry\nGood understanding of Trade invoices payment process\nStrong communication skills as need to deal with buying team and multiple vendors\nGood coordination skills and team player\nFamiliar with Oracle Accounting System is not essential but a plus\nBachelor's Degree or any equivalent qualification in Finance or Accounting\n", "employment_types": ["Full Time", "Contract"], "selling_points": [], "locations": ["Cheung Sha Wan"], "categories": ["Accounting", "Accounting Clerk / Supervisor", "Admin & HR", "Clerical / Admin Staff"], "post_time": "2022-01-17T02:03:58Z", "salary": {"currency": null, "max": null, "min": null, "period": "monthly", "term": null}, "salary_visible": false, "title_keywords": ["operations assistant"], "responsibilities": ["shipping", "quality", "communication", "payment", "plan", "invoices", "teams", "develop", "logistics", "management", "administrative support", "invoice", "procedures", "coordinate with", "contact", "guidelines", "policies", "systems", "ensure compliance", "coordinate", "invoicing", "payments", "payment process", "coordination", "accounts payable"], "requirements": {"degrees": ["degree", "bachelor"], "majors": ["finance", "accounting"], "languages": [], "language_level": [], "hard_skills": ["plus", "vendor", "accounting system", "documentations", "oracle"], "soft_skills": ["communication skills", "coordination skills", "responsible", "timely", "communication", "team player"], "languages_combined": []}, "experience_required": {"duration": ["at least 3 years"], "field": ["retail industry"]}}, {"job_id": "100003009054921", "location_code": "hk", "company": "Eternity Consultants (HK) Ltd", "job_title": "Account Clerk / Senior Account Clerk - Trading (Fresh graduate will consider)", "description": "Responsibilities:\n\nResponsible for daily accounting functions including data input, payroll, issue invoice, quotation, receipt, filling;\nResponsible for coordination of daily operations, liaison with product/services providers, handling of customers enquiries;\nCreate and update records and databases, financial and other data;\nSupport cheque payment, and bookkeeping procedures;\nAssist in Ad hoc tasks or projects assigned by operation staffs;\nWorking Location: Cheung Sha Wan;\nSalary: Negotiable.\n\u00a0 \u00a0* Fresh graduates are welcomed to apply.\n\n\u8077\u8cac:\n\n\u8ca0\u8cac\u4e00\u822c\u6587\u66f8\u53ca\u666e\u901a\u6703\u8a08\u5de5\u4f5c\uff0c\u5305\u62ec\u6587\u4ef6\u5b58\u6a94\uff0c\u8cc7\u6599\u8f38\u5165\uff0c\u8907\u5370\uff0c\u7de8\u5236\u5831\u544a\u7b49\uff0c\u63a5\u807d\u96fb\u8a71\uff0c\u958b\u767c\u7968\uff0c\u652f\u7968\u7b49\uff0c\u5354\u52a9\u516c\u53f8\u8655\u7406\u81e8\u6642\u4efb\u52d9\uff1b\n\u8ca0\u8cac\u5354\u8abf\u65e5\u5e38\u904b\u71df\uff0c\u8207\u7522\u54c1/\u670d\u52d9\u4f9b\u61c9\u5546\u7684\u806f\u7d61\uff0c\u8655\u7406\u5ba2\u6236\u67e5\u8a62\uff1b\n\u8655\u7406\u8fa6\u516c\u5ba4\u96dc\u52d9\u53ca\u5916\u52e4\u4e8b\u52d9\u4ee5\u53ca\u5404\u7a2e\u884c\u653f\u76f8\u95dc\u554f\u984c\uff0c\u5305\u62ec\u6587\u4ef6\u9001\u905e\uff0c\u9280\u884c\u5165\u5e33\uff1b\n\u8058\u7528\u5f62\u5f0f\uff1a\u9577\u5de5\uff1b\n\u5de5\u4f5c\u5730\u9ede\uff1a\u9577\u6c99\u7063\uff1b\n\u85aa\u91d1\u9762\u8b70\u3002\n* \u6b61\u8fce\u61c9\u5c46\u7562\u696d\u751f\u7533\u8acb\u3002\n", "employment_types": ["Full Time", "Permanent"], "selling_points": ["5 days, bank holiday, medical.", "F.7/+  w/ LCC Intermedicate/ Accounting Diploma", "2-4 year experience in accounting field"], "locations": ["Others"], "categories": ["Accounting", "Accounting Clerk / Supervisor", "Taxation", "Treasurer"], "post_time": "2022-01-17T13:57:23Z", "salary": {"currency": null, "max": null, "min": null, "period": "monthly", "term": null}, "salary_visible": false, "title_keywords": ["account clerk", "senior account clerk"], "responsibilities": ["data", "invoice", "quotation", "procedures", "data input", "ad hoc tasks", "daily operations", "payment", "coordination", "databases", "daily accounting", "payroll"], "requirements": {"degrees": [], "majors": [], "languages": [], "language_level": [], "hard_skills": ["wan", "databases"], "soft_skills": ["coordination", "responsible"], "languages_combined": []}, "experience_required": {"duration": [], "field": []}}, {"job_id": "100003009052820", "location_code": "hk", "company": "The Hong Kong Football Association Ltd", "job_title": "Accounting Assistant", "description": "Trading\nJob Responsibilities:\n\nAccount Receivable, Account Payable\nPerform daily accounting functions including prepare voucher input and various payments\nAssist in projects and other ad hoc assignment\n\nJob Requirements :\n\nDiploma in Accounting\n2-4 year working experience in accounting field\u00a0\nFamiliar with Excel, Word and Chinese word processing\nInitiative, well-organised, hard working and willing to learn\n\nBenefit:\n\n5 days, bank holiday, medical scheme\n\n*Interested parties, please send full resume with current & expected salary & date available in MS WORD FORMAT ONLY to us\u00a0or fax to 3527 0634*\n\nWe are welcome applicants resend resumes to us even you have applied jobs in our company before.\n\nFor more jobs, please visit our website: www.hketernity.com\n\n(Personal data submitted are for recruitment purpose only.)", "employment_types": ["Full Time", "Contract"], "selling_points": [], "locations": ["Mong Kok"], "categories": ["Accounting", "Accountant", "Accounting Clerk / Supervisor", "Others"], "post_time": "2022-01-17T04:09:51Z", "salary": {"currency": null, "max": null, "min": null, "period": "monthly", "term": null}, "salary_visible": false, "title_keywords": ["accounting assistant"], "responsibilities": ["daily accounting", "ad hoc assignment", "payments"], "requirements": {"degrees": ["diploma"], "majors": ["accounting"], "languages": ["chinese"], "language_level": [], "hard_skills": ["excel", "chinese word processing", "word"], "soft_skills": ["well-organised", "hard working", "willing to learn", "initiative"], "languages_combined": [{"language": "chinese", "language_level": []}]}, "experience_required": {"duration": ["2-4 year"], "field": ["accounting"]}}, {"job_id": "100003009054862", "location_code": "hk", "company": "Abouthai (Hong Kong) Limited", "job_title": "Accounting Assistant (Welcome Fresh Graduate)", "description": "Responsibilities:\n\u2022 Perform daily accounting functions and maintain full sets of accounts;\n\u2022 Responsible for month-end closing, year-end closing and monitor the daily operation\n\u2022 Timely conduct monthly financial reports and analysis for management review\n\u2022 Handle inter-company transactions and reconciliation\n\u2022 Prepare banking documents and responsible for bank transactions\n\u2022 Assist in ad hoc assignments assigned\n\nRequirements:\n\nDegree holder in Accounting / Finance or a relevant business discipline\nMinimum 5 years of experience in accounting firms or Finance department of commercial firms\nKnowledge of general and cost accounting\nProficiency with MS Office applications MYOB and SAP system\nStrong command of spoken and written English and Chinese (including both Cantonese & Mandarin) is essential\nGood interpersonal skills and ability to clearly communicate with others\nResponsible, well organized, detail-minded and able to work as a team\nAbility to complete tasks while maintaining all confidentiality requirements\nImmediately available is highly preferred\n\nLocation: Kwai Hing", "employment_types": ["Full Time", "Permanent"], "selling_points": ["Accounting Assistant", "Fresh Graduate", "General accounting duties"], "locations": ["Tsuen Wan Area"], "categories": ["Accounting", "Accounting Clerk / Supervisor"], "post_time": "2022-01-17T12:01:32Z", "salary": {"currency": null, "max": null, "min": null, "period": "monthly", "term": null}, "salary_visible": false, "title_keywords": ["accounting assistant"], "responsibilities": ["financial reports", "analysis", "monitor", "daily operation", "transactions", "maintain", "month-end closing", "ad hoc assignments", "year-end closing", "banking", "daily accounting", "management review"], "requirements": {"degrees": ["degree holder"], "majors": ["business", "finance", "accounting"], "languages": ["cantonese", "english", "chinese", "mandarin"], "language_level": [], "hard_skills": ["myob", "sap", "ms office"], "soft_skills": ["detail-minded", "work as a team", "responsible", "well organized", "interpersonal skills"], "languages_combined": [{"language": "cantonese", "language_level": []}, {"language": "english", "language_level": []}, {"language": "chinese", "language_level": []}, {"language": "mandarin", "language_level": []}]}, "experience_required": {"duration": ["minimum 5 years"], "field": ["finance", "accounting", "commercial"]}}, {"job_id": "100003009053388", "location_code": "hk", "company": "ACCOLADE Corporate Services Limited", "job_title": "Accounts Assistant / Accountant", "description": "Responsibilities:\n\nPerform general accounting duties including AR, AP, data entry and document filing\nPerform daily sales and receipt reconciliation\nAssist in ad hoc assignments\n\nRequirements:\n\nDiploma in Accounting or with LCCI Level II\n1 year working\u00a0experience\nSelf-motivated, detail-minded, responsible, hardworking and independent\nGood organizational, communication and interpersonal skills\nProficiency in using MS Office\nGood command of written & spoken English and Chinese\nImmediate available is highly preferred\n\nInterested parties, please send full resume with present & expected salaries & date availability to HR Department by \u201cApply Now\u201d below.\n\nAll information will be treated in strict confidence and will be used for recruitment related purpose only. Information of unsuccessful applicants will be destroyed upon completion of the recruitment process.", "employment_types": ["Full Time", "Permanent"], "selling_points": ["Responsible for Account Receivable collection proc", "With 2 years relevant working experience", "Knowledge in using ZOHO system"], "locations": ["Sheung Wan"], "categories": ["Accounting", "Accountant", "Accounting Clerk / Supervisor", "Credit Control"], "post_time": "2022-01-17T06:56:50Z", "salary": {"currency": null, "max": null, "min": null, "period": "monthly", "term": null}, "salary_visible": false, "title_keywords": ["accountant", "accounts assistant"], "responsibilities": ["ap", "document filing", "ar", "data entry", "general accounting duties", "ad hoc assignments"], "requirements": {"degrees": ["diploma"], "majors": ["accounting"], "languages": ["english", "chinese"], "language_level": ["good command"], "hard_skills": ["ms office"], "soft_skills": ["detail-minded", "self-motivated", "independent", "responsible", "organizational", "communication and interpersonal skills", "hardworking"], "languages_combined": [{"language": "english", "language_level": ["good command"]}, {"language": "chinese", "language_level": ["good command"]}]}, "experience_required": {"duration": ["1 year"], "field": []}}, {"job_id": "100003009053185", "location_code": "hk", "company": "Arts with the Disabled Association Hong Kong", "job_title": "Accounts Clerk ( Part-Time )", "description": "\u00a0Responsibilities:\n\nResponsible for Account Receivable collection process\nHandle daily invoices, bills, vouchers and Accounts documents checking\nAssist in preparing general ledger, month end closing, auditing and taxation affairs\nAssist in others ad hoc task as requested\n\nRequirements:\n\nDiploma holder or above in accounting or related disciplines\nWith 2-3 years relevant working experience in accounts receivable\nKnowledge in using ZOHO system would be an advantage\nSelf-motivated, stable and willing to work under pressure, work independently and good communication skills\nProficient in MS Office (Word & Excel)\nGood command in English and Mandarin\nImmediate available is preferred", "employment_types": ["Part Time"], "selling_points": [], "locations": ["North Point"], "categories": ["Accounting", "Accounting Clerk / Supervisor"], "post_time": "2022-01-17T06:25:19Z", "salary": {"currency": null, "max": null, "min": null, "period": "monthly", "term": null}, "salary_visible": false, "title_keywords": ["accounts clerk"], "responsibilities": ["taxation", "month end closing", "ad hoc", "invoices", "general ledger", "checking", "auditing"], "requirements": {"degrees": ["diploma holder"], "majors": ["related disciplines", "accounting"], "languages": ["english", "mandarin"], "language_level": ["good command"], "hard_skills": ["excel", "word", "ms office"], "soft_skills": ["communication skills", "work independently", "self-motivated", "stable", "work under pressure"], "languages_combined": [{"language": "english", "language_level": ["good command"]}, {"language": "mandarin", "language_level": ["good command"]}]}, "experience_required": {"duration": ["2-3 years"], "field": ["relevant working experience"]}}, {"job_id": "100003009052232", "location_code": "hk", "company": "Kai Fu Property Services Co Ltd", "job_title": "Accounting Assistant/ Assistant Accounting Officer", "description": "\u00a0Responsibilities:\n\nTo handle data entry, G/L,A/R,A/P and bank reconciliation;\nFamiliar with internet Banking preferable\nSupport as-hoc duties as assigned by supervisor.\n\n\u00a0Requirements:\n\nHKDSE or above with LCCI Intermediate level (Level 2);\nProficient in MS Word, Excel, Chinese word procesing;\nAt least 1 year relevant working experience;\nImmediate available is preferable.\nWorking hours:\n\n\nMonday to Friday (a.m.) - 4 hours per day\nSalary:\n\n\nHK$8,000.00 per month\n\nQualified candidates are invited to apply with full resume, stating present and expected salary together with\u00a0available date\u00a0to\u00a0Administration Manager, Arts with the Disabled Association Hong Kong, 4/F Causeway Bay Community Centre, 7 Fook Yum Road, Causeway Bay, Hong Kong\u00a0or click\"APPLY NOW\"\u00a0on or before \u00a023 January 2022.\n\nPersonal data will be used for recruitment purpose only.", "employment_types": ["Full Time", "Permanent"], "selling_points": [], "locations": ["Kowloon Bay"], "categories": ["Accounting", "Accountant", "Accounting Clerk / Supervisor", "Others"], "post_time": "2022-01-17T02:31:28Z", "salary": {"currency": null, "max": null, "min": null, "period": "monthly", "term": null}, "salary_visible": false, "title_keywords": ["accounting assistant", "assistant accounting officer"], "responsibilities": ["banking", "bank reconciliation", "data entry"], "requirements": {"degrees": ["hkdse"], "majors": [], "languages": ["chinese"], "language_level": ["proficient"], "hard_skills": ["excel", "word", "ms word"], "soft_skills": [], "languages_combined": [{"language": "chinese", "language_level": ["proficient"]}]}, "experience_required": {"duration": ["at least 1 year"], "field": ["relevant working experience"]}}, {"job_id": "100003009053528", "location_code": "hk", "company": "Inno Consultants Services Limited", "job_title": "Accounts Clerk", "description": "Job duties:\n\nPerform daily accounting operations including daily bank operation (arrange cheque deposit, cheque payment, bank transfer and authorised signatures) filing, book keeping etc.\nProvide clerical support to the Department\nResponsible for outdoor working\nAssist in ad-hoc assignment\n\nRequirements:\n\nHolder of a Associate Degree/Higher Diploma\u00a0or above\u00a0\n\nHolding LCC Elementary or above\n1 year relevant experience\u00a0or above\nWell organized, self-motivated, hardworking and willing to learn\nWilling to work under pressure and meet tight deadline\nGood organization, analytical and Excel skills\nFresh graduates will also be considered\nImmediate available is preferred\n\n**Salary and position will commensurate with\u00a0qualifications and\u00a0relevant working experiences.", "employment_types": ["Full Time"], "selling_points": [], "locations": ["Kwun Tong Area"], "categories": ["Accounting", "Accounting Clerk / Supervisor", "Others", "Admin & HR", "Others"], "post_time": "2022-01-17T07:06:30Z", "salary": {"currency": null, "max": null, "min": null, "period": "monthly", "term": null}, "salary_visible": false, "title_keywords": ["accounts clerk"], "responsibilities": ["provide clerical support", "ad-hoc", "payment", "daily accounting operations"], "requirements": {"degrees": ["associate degree", "higher diploma or above"], "majors": [], "languages": [], "language_level": [], "hard_skills": ["excel", "lcc"], "soft_skills": ["self-motivated", "willing to learn", "well organized", "meet tight deadline", "hardworking", "work under pressure"], "languages_combined": []}, "experience_required": {"duration": ["1 year"], "field": ["relevant experience"]}}, {"job_id": "100003009040323", "location_code": "hk", "company": "REWE Far East Limited", "job_title": "Assistant Accounting Officer", "description": "\nProfessional Business Consultancy Company\nResponsibilities:\n\u2022 Bookkeeping\n\u2022 Data entry\n\u2022 Document processing\n\u2022 Liaison with clients\nRequirements:\nF.5 (or equivalent) or above\n\u2022 Min 1 year working experience\n\u2022 Proficiency in Cantonese, English and Mandarin\nProficiency in MS (particularly Words, Excel)\n\u2022 Office located in Kowloon Bay\n\u5de5\u4f5c\u7bc4\u570d\uff1a\n\u2022 \u7c3f\u8a18\n\u2022 \u8f38\u5165\u8cc7\u6599\n\u2022 \u6587\u4ef6\u8655\u7406\n\u2022 \u8207\u5ba2\u6236\u806f\u7cfb\n\u5c65\u6b77\uff1a\n\u2022 \u4e2d\u4e94\u6216\u4ee5\u4e0a\n\u2022 \u4e00\u5e74\u5de5\u4f5c\u7d93\u9a57\n\u2022 \u61c2\u8aaa\u5beb\u7cb5\u8a9e\u3001\u82f1\u8a9e\u548c\u666e\u901a\u8a71\n\u61c2\u5fae\u8edf\u7cfb\u7d71 (Words, Excel)\n\u2022 \u4e0a\u73ed\u5730\u9ede: \u4e5d\u9f8d\u7063\nApply please email to [via\u00a0 Apply Now ]\n\n", "employment_types": ["Full Time", "Permanent"], "selling_points": ["Finance & Accounting", "EU buying office, Mobile Working, Flex Working Hr", "13th Month Bonus, Discretionary Bonus"], "locations": ["Kwun Tong Area"], "categories": ["Accounting", "Accounting Clerk / Supervisor", "Audit", "Admin & HR", "Clerical / Admin Staff"], "post_time": "2022-01-16T21:50:04Z", "salary": {"currency": null, "max": null, "min": null, "period": "monthly", "term": null}, "salary_visible": false, "title_keywords": ["assistant accounting officer"], "responsibilities": ["data entry"], "requirements": {"degrees": [], "majors": [], "languages": ["cantonese", "english", "mandarin"], "language_level": ["proficiency"], "hard_skills": ["excel", "words"], "soft_skills": [], "languages_combined": [{"language": "cantonese", "language_level": ["proficiency"]}, {"language": "english", "language_level": ["proficiency"]}, {"language": "mandarin", "language_level": ["proficiency"]}]}, "experience_required": {"duration": ["min 1 year"], "field": []}}, {"job_id": "100003009052438", "location_code": "hk", "company": "Kingkey Securities Group Limited", "job_title": "Accounting Officer", "description": "Key Responsibilities\n\nPerform efficient maintenance and processing of accounts payable transactions for Hong Kong office and overseas representative offices.\nWork closely with merchandising and quality teams for invoice issuing and checking, settlement status and account reconciliations.\nReview the payments requests to ensure payment deadlines and compliance with policy and procedure.\nAssist HK team on monthly closing and reporting, and yearly auditing.\nLiaise with overseas representative offices and assist in monthly closing for representative offices.\nPerform accounts analysis and reconciliation.\nReview the month end closing accounts (AP and AR).\n\n\nJob Requirements\n\nLCCI higher or Accounting Diploma holder.\nAt least 1 year relevant accounting experience.\nIndependent with initiative, good team player and able to work under pressure.\nAttention to detail and accuracy.\nWell organized, cooperative, and willing to assist others.\nKnowledge of MS Office, especially MS Excel and MS Word.\nGood command of both spoken & written English and Chinese (Cantonese & Mandarin).\nFresh graduates may be considered.\n\nIf you are interested in the position, please submit your full resume with cover letter, current and expected salary and available date via JobsDB.\n\nAll\u00a0personal information is collected for recruitment purpose only and will be treated in strict confidentiality.\u00a0\u00a0", "employment_types": ["Full Time", "Permanent"], "selling_points": [], "locations": ["Wan Chai"], "categories": ["Accounting", "Accounting Clerk / Supervisor", "Banking / Finance", "Financial Services"], "post_time": "2022-01-17T03:02:57Z", "salary": {"currency": null, "max": null, "min": null, "period": "monthly", "term": null}, "salary_visible": false, "title_keywords": ["accounting officer"], "responsibilities": ["merchandising", "quality", "transactions", "payment", "liaise with", "ap", "month end closing", "compliance", "teams", "reporting", "ar", "invoice", "review", "checking", "reconciliations", "maintenance", "analysis", "payments", "accounts payable", "auditing"], "requirements": {"degrees": ["diploma holder"], "majors": ["accounting"], "languages": ["cantonese", "english", "chinese", "mandarin"], "language_level": ["good command"], "hard_skills": ["ms word", "ms excel", "ms office"], "soft_skills": ["good team player", "independent", "cooperative", "interested in", "well organized", "attention to detail", "initiative", "work under pressure"], "languages_combined": [{"language": "cantonese", "language_level": ["good command"]}, {"language": "english", "language_level": ["good command"]}, {"language": "chinese", "language_level": ["good command"]}, {"language": "mandarin", "language_level": ["good command"]}]}, "experience_required": {"duration": ["at least 1 year"], "field": ["accounting experience"]}}, {"job_id": "100003009052085", "location_code": "hk", "company": "\"K\" Line Logistics (Hong Kong) Ltd", "job_title": "Assistant Accountant (RE0122/01)", "description": "Job Description:\n\nResponsible for daily accounting journal entries and check payment\nPreparation of billing and\u00a0account receivable report\nHandle of receipt and preparation of daily collection reports\nPreparation of bank reconciliation\nHandle matter opening and closing\u00a0\nHandle staff reimbursement\nUpload fee note to our system\nPerform any ad-hoc duties as assigned\n\n\u00a0Requirements:\n\nDiploma or above\nMinimum 2 years\u2019 working experience in law firm but not a must\nSelf-motivated, able to work independently with good communication skills and mature\nProficient in MS Word, Excel and Chinese word-processing\n\nBenefits:\n\n5 Days work\nMedical Insurance\nlunch allowance\n\nWe offer attractive remuneration package to the right candidate. Interest parties please send your detailed resume with current/last and expected salary by clicking \"Apply Now\u201d", "employment_types": ["Full Time", "Permanent"], "selling_points": [], "locations": ["Lai Chi Kok"], "categories": ["Accounting", "Accounting Clerk / Supervisor", "Others", "Transportation & Logistics", "Freight Forwarding"], "post_time": "2022-01-17T02:03:36Z", "salary": {"currency": null, "max": null, "min": null, "period": "monthly", "term": null}, "salary_visible": false, "title_keywords": ["assistant accountant"], "responsibilities": ["bank reconciliation", "payment", "journal entries", "reports", "ad-hoc duties", "daily accounting", "report"], "requirements": {"degrees": ["diploma or above"], "majors": [], "languages": ["chinese"], "language_level": ["proficient"], "hard_skills": ["excel", "chinese word-processing", "ms word"], "soft_skills": ["communication skills", "self-motivated", "work independently", "mature"], "languages_combined": [{"language": "chinese", "language_level": ["proficient"]}]}, "experience_required": {"duration": ["minimum 2 years"], "field": []}}, {"job_id": "100003009052570", "location_code": "hk", "company": "Mitsui & Co (HK) Ltd", "job_title": "Administrative Officer (Finance & Accounting)", "description": "\u201cK\u201d Line Logistics (Hong Kong) Limited is a global logistics company offering total logistics solution including air and ocean freight, land transport and distribution etc.\u00a0 Our headquarters is based in Japan and our international network links more than 150 countries and cities worldwide. To cope with our expansion, we are inviting high caliber professional for the following position:\n\nASSISTANT ACCOUNTANT\u00a0\n\u00a0\n(Working location: Lai Chi Kok)\n\nThis position will be responsible to handle daily bank operations including payment & receipt vouchers as well as autopay arrangement, bank reconciliation, book-keeping, staff reimbursement. You are required to handle some ad hoc jobs.\n\n\nRequirements:\n\nForm 5 / DSE or above, Diploma or above in Accounting discipline;\nLCCI higher / ACCA level 1 or above;\nAt least 1 year accounting experience in which exposure in freight forwarder industry is an advantage;\nGood in spoken and written English and Chinese, Mandarin speaking is an advantage;\nGood computer skills with MS Office, Flex Accounting is preferable;\nStrong in communication and problem solving skills;\nDetailed minded, reliable, self-motivated and team player;\nImmediate available preferred\n\nWe offer attractive fringe benefits which include 5 days work-week, Double Pay, Performance Bonus, Training Allowances, Overtime Allowances, Medical & Dental Scheme, Mandatory Provident Fund and 12-21 days Annual Leave.\n\nIf you are interested in this position, please send application with detailed qualifications, experience, current and expected salary by click \u201cApply Now\u201d to submit your application.\n\n(All information provided are kept confidential and all personal data provided will be used for the recruitment purpose only)\n", "employment_types": ["Full Time", "Permanent"], "selling_points": [], "locations": ["Admiralty"], "categories": ["Accounting", "Accounting Clerk / Supervisor", "Others", "Banking / Finance", "Order Processing & Operation / Settlement"], "post_time": "2022-01-17T03:26:35Z", "salary": {"currency": null, "max": null, "min": null, "period": "monthly", "term": null}, "salary_visible": false, "title_keywords": ["administrative officer", "accounting"], "responsibilities": ["ad hoc", "operations", "bank reconciliation", "communication", "payment", "logistics", "book-keeping", "recruitment", "personal data", "autopay"], "requirements": {"degrees": ["diploma or above", "form 5", "dse"], "majors": ["accounting"], "languages": ["english", "chinese", "mandarin"], "language_level": ["advantage", "good"], "hard_skills": ["acca", "scheme", "flex accounting", "computer skills", "problem solving skills", "ms office"], "soft_skills": ["self-motivated", "responsible", "interested in", "communication", "team player", "problem solving skills", "reliable", "detailed"], "languages_combined": [{"language": "english", "language_level": ["advantage", "good"]}, {"language": "chinese", "language_level": ["advantage", "good"]}, {"language": "mandarin", "language_level": ["good"]}]}, "experience_required": {"duration": ["at least 1 year"], "field": ["accounting experience"]}}, {"job_id": "100003009052712", "location_code": "hk", "company": "Atom International Technology Limited", "job_title": "Accountant / Accounting Officer", "description": "We are now inviting candidate of high calibre to join us in the following capacity in our Finance & Accounting Division.\n\nJob Duties:\n\nHandling various accounting input and reports with the support of supervisor (monthly biz reports, forex reports, reports to HQ, etc.)\nSupport for import & export transaction processing and checking\nPrepare report of market risk for marketable products, such as LME transaction\n\nRequirements:\n\n\nAt least 2 \u2013 3 years\u2019 relevant working experience\nUtilization on SAP (ECC) system is preferable\nPossess Basic financial and accounting concept is preferable\nGood command of English and Mandarin\nGood command of Microsoft Office Tools (e.g. Word, Excel, etc.)\nInterested parties please apply with your full resume stating present and expected salary.\n\n\n\nAll information will be kept confidential and used for recruitment purpose only. Although we endeavour to respond to every applicant, this may not always be possible so if you receive no response within 60 days, please consider your application for this specific vacancy to be unsuccessful.\n\n", "employment_types": ["Full Time"], "selling_points": ["Accounting", "Finance", "Assurance"], "locations": ["North Point"], "categories": ["Accounting", "Accountant", "Accounting Clerk / Supervisor", "Banking / Finance", "Treasury"], "post_time": "2022-01-17T03:46:58Z", "salary": {"currency": null, "max": null, "min": null, "period": "monthly", "term": null}, "salary_visible": false, "title_keywords": ["accountant", "accounting officer"], "responsibilities": ["prepare report", "reports", "checking", "transaction processing"], "requirements": {"degrees": [], "majors": [], "languages": ["english", "mandarin"], "language_level": ["good command"], "hard_skills": ["excel", "basic", "sap", "microsoft office", "ecc", "word"], "soft_skills": [], "languages_combined": [{"language": "english", "language_level": ["good command"]}, {"language": "mandarin", "language_level": ["good command"]}]}, "experience_required": {"duration": ["3 years"], "field": ["relevant working experience"]}}, {"job_id": "100003009054213", "location_code": "hk", "company": "SinoPac Securities (Asia) Limited", "job_title": "Accounts Officer", "description": "Job Highlights\ndaily accounting\npayment\naudit\nJob Description\n\nResponsibilities\u00a0include:\n\nPerform daily accounting duties, including data entries and preparation of vouchers for receipt, payment and general journals transactions\nLiaise with audit team, clients & IRD\nPrepare annual statutory filing (including renewal, tax filing and others)\nInvolve in marketing campaign regarding accounting service crossover with other brands and partners.\nEnsure timely and accurate financial reporting\nHandle other adhoc tasks and administrative work as required\n\nUltimately, you will help our Accounting department run smoothly, ensuring transparency and efficiency in all transactions.\n\nRequirements\n\nAs a minimum you will have a Diploma or above in Accounting or related disciplines and Proficient in English, Mandarin and Cantonese.\n2 years or above of work experience in accounting is preferred.\nKnowledge of modern accounting software is essential. Knowledge in XERO is distinct advantage\nFamiliarity with finance regulations\nStrong organization skills\nAbility to handle sensitive, confidential information\nA final pre-requisite is that you be based in Hong Kong with valid working visa", "employment_types": ["Full Time", "Permanent"], "selling_points": ["5-days work", "degree holder", "Immediate available is preferred"], "locations": ["Causeway Bay"], "categories": ["Accounting", "Accountant", "Accounting Clerk / Supervisor", "Others"], "post_time": "2022-01-17T08:49:54Z", "salary": {"currency": null, "max": null, "min": null, "period": "monthly", "term": null}, "salary_visible": false, "title_keywords": ["accounts officer"], "responsibilities": ["administrative work", "data", "tax filing", "accounting service", "audit", "transactions", "payment", "financial reporting", "liaise with", "daily accounting"], "requirements": {"degrees": ["diploma or above"], "majors": ["related disciplines", "accounting"], "languages": ["cantonese", "english", "mandarin"], "language_level": ["proficient"], "hard_skills": ["accounting software", "xero"], "soft_skills": ["organization skills", "sensitive"], "languages_combined": [{"language": "cantonese", "language_level": ["proficient"]}, {"language": "english", "language_level": ["proficient"]}, {"language": "mandarin", "language_level": ["proficient"]}]}, "experience_required": {"duration": ["2 years"], "field": ["accounting"]}}, {"job_id": "100003009054347", "location_code": "hk", "company": "Wu Wong Consultants Limited", "job_title": "Senior Accounting Officer", "description": "RESPONSIBILITIES\nAssist in carrying out daily accounting activities including trust account maintenance, daily FRR preparation etc.;\nResponsible for the preparation of full set of accounts for brokerage business ;\nResponsible for the preparation of monthly financial reports and management reports;\nAssist in the preparation of full set of accounts for the group\u2019s proprietary trading business; and\nProcess monthly accounting schedules;\nProcess daily/monthly payment\n\n\u00a0REQUIREMENTS\n\nAccounting degree holder;\nMinimum 2 years relevant experience in leading securities brokers or relevant audit experience in CPA firms;\nProficient in Epicor Accounting software;\nGood understanding of accounting knowledge;\nGood command of written and spoken English, Cantonese and Mandarin;\nWilling to take up new tasks and assignments;\nGood communication skill;\nImmediate available is preferred.\nCandidate with less experience will be considered for the post of Assistant Accounts Officer.\n\n\u00a0A competitive remuneration package will be offered. Please send your detailed resume, including present and expected salary as well as availability date, to Human Resources Department, SinoPac Securities (Asia) Limited, 7/F., Lee Garden Three, 1 Sunning Road, Causeway Bay, Hong Kong or by clicking \u201cApply Now\u201d.\u00a0\n\nAll personal data collected will be used for recruitment purpose only and will be kept strictly confidential. Only short-listed candidates will be notified.", "employment_types": ["Full Time"], "selling_points": [], "locations": ["Yau Tsim Mong Area"], "categories": ["Accounting", "Accountant", "Accounting Clerk / Supervisor"], "post_time": "2022-01-17T09:13:39Z", "salary": {"currency": null, "max": null, "min": null, "period": "monthly", "term": null}, "salary_visible": false, "title_keywords": ["senior accounting officer"], "responsibilities": ["financial reports", "schedules", "brokerage", "full set of accounts", "management reports", "payment", "daily accounting", "account maintenance"], "requirements": {"degrees": ["degree holder"], "majors": ["accounting"], "languages": ["cantonese", "english", "mandarin"], "language_level": ["good command"], "hard_skills": ["accounting software", "cpa"], "soft_skills": ["communication skill", "detailed"], "languages_combined": [{"language": "cantonese", "language_level": ["good command"]}, {"language": "english", "language_level": ["good command"]}, {"language": "mandarin", "language_level": ["good command"]}]}, "experience_required": {"duration": ["minimum 2 years"], "field": ["securities", "relevant experience", "audit experience"]}}, {"job_id": "100003009054377", "location_code": "hk", "company": "Strategic Public Relations Group Limited", "job_title": "Assistant Accountant / Accountant (5-day work)", "description": "Job Descriptions:\u00a0\n\nPrepare monthly report\n\nPerform bank reconciliation\n\nMonitor daily sales transactions are in line with compliance and company policy\n\nAssist in reviewing monthly reports from overseas companies\n\nLiaise and coordinate with internal parties and overseas office to ensure smooth operation\n\nProvide full financial reports, analysis and information timely and accurately to Senior Management\n\nLiaise with auditors for audit matters of the Hong Kong companies\n\nPerform ad-hoc assignments as required\n\nRequirements:\u00a0\n\nDegree in Accounting or Finance\n\n5 years or above experience in accounting and financial reporting\n\nMature, responsible, detailed mind with ability to handle multiple tasks independently under pressure\n\nExcellent command of both written and spoken in English, Cantonese and Putonghua\n\nProficient in MS Words & Excel\n\nFamiliar with Flex system is highly preferred\n\nBenefits:\n\nCompetitive salary package and benefits\n\nCareer development and staff training\n\nBonus\n\nBirthday pocket money\n\nOvertime and night shift allowance\n\nOverseas allowance\n\nComprehensive medical insurance\n\nStaff intimate welfare\n\nTraditional Holiday Gift\n\nMPF\n\nIncentive activities and trips\n\nFertility fund\n\nBanking Holidays\n\n10-21 days Annual leave", "employment_types": ["Full Time", "Permanent"], "selling_points": ["Handle full set of books/ month end/ 3-5 yrs exp.", "5 Days Work with D.Bonus/ Bank Holiday", "12 Days AL/ Birthday Leave/ Medical&Life Insurance"], "locations": ["Admiralty"], "categories": ["Accounting", "Accountant", "Accounting Clerk / Supervisor", "Others"], "post_time": "2022-01-17T09:18:50Z", "salary": {"currency": null, "max": null, "min": null, "period": "monthly", "term": null}, "salary_visible": false, "title_keywords": ["accountant", "assistant accountant"], "responsibilities": ["liaise", "financial reports", "monthly reports", "ad-hoc assignments", "analysis", "compliance", "monitor", "bank reconciliation", "transactions", "coordinate with", "audit", "monthly report", "liaise with", "senior management", "internal parties"], "requirements": {"degrees": ["degree"], "majors": ["finance", "accounting"], "languages": ["cantonese", "putonghua", "english"], "language_level": ["excellent"], "hard_skills": ["excel", "flex system", "ms words"], "soft_skills": ["independently", "under pressure", "responsible", "mature", "handle multiple tasks", "detailed mind"], "languages_combined": [{"language": "cantonese", "language_level": ["excellent"]}, {"language": "putonghua", "language_level": ["excellent"]}, {"language": "english", "language_level": ["excellent"]}]}, "experience_required": {"duration": ["5 years"], "field": ["accounting", "financial"]}}, {"job_id": "100003009052971", "location_code": "hk", "company": "Lee Kum Kee (Hong Kong) Foods Ltd", "job_title": "Accounting Assistant", "description": "Responsibilities:\n\nHandle full set of accounts\nPrepare and review accounting records, financial statements and other financial reports\nMonitor, review and assist in day to day accounting functions, including incomes,\u00a0payments, inter-company controls and transactions\nDevelop, maintain, and analyze budgets as well as cash flow forecasts\nSupervise and provide guidance to subordinates on daily operations and help the team in solving work-related issues\nStreamline the accounting workflow and lead the implementation of internal control policies\n\n\u00a0Job Requirements:\n\nBachelor degree in Accounting or other related disciplines\n5 years or above relevant experience, preferably with supervision or management experience\nHands-on experience in handling full sets of accounts independently\nGood accounting software and computer skills; proficient in MS Excel is preferred\nKnowledge of Peachtree Accounting System is a definite advantage\nDetail-oriented with strong sense of accuracy\nSelf-motivated, independent, detail-minded, able to work under pressure and strong sense of responsibility\nImmediate available is highly preferred\n\nInterested parties please complete the standard application form by clicking the\u00a0Apply now\u00a0button. You can also attach your tailored CV and Cover letter with your current and expected salary which we will use to review applications.\n\nIt is Our Company policy to comply with the requirements of the Personal Data (Privacy) Ordinance (Cap. 486) of the Laws of the Hong Kong Special Administrative Region. Any personal data which is collected shall be handled in accordance with this Personal Information Collection Statement (\u201cPICS\u201d).\n\nThe personal data collected from you will be used for purposes relating to your application for employment with the Company. You must ensure that all personal data provided to the Company are accurate, complete and up-to-date. For correction of or access to personal data after submission of the job application or enquiries on recruitment matters, please contact the HR or subject officer as specified in the recruitment advertisement.\n\nWebsite:\u00a0 \u00a0 \u00a0www.sprg.com.hk\u00a0/\u00a0www.sprg.asia\nFacebook:\u00a0\u00a0https://www.facebook.com/SPRGAsia\u00a0/\u00a0https://www.facebook.com/CSR.SPRG", "employment_types": ["Full Time", "Permanent"], "selling_points": ["Prepare month end schedules & reconciliations", "Associate Degree or above in Accountancy", "1 year exp. (Fresh graduates will be considered)"], "locations": ["Tai Po Area"], "categories": ["Accounting", "Accounting Clerk / Supervisor", "Others"], "post_time": "2022-01-17T04:46:04Z", "salary": {"currency": null, "max": null, "min": null, "period": "monthly", "term": null}, "salary_visible": false, "title_keywords": ["accounting assistant"], "responsibilities": ["budgets", "financial reports", "policies", "review", "full set of accounts", "monitor", "financial statements", "transactions", "develop", "implementation", "cash flow", "maintain", "payments", "daily operations", "provide guidance", "internal control"], "requirements": {"degrees": ["degree", "bachelor"], "majors": ["related disciplines", "accounting"], "languages": [], "language_level": [], "hard_skills": ["accounting software", "ms excel", "computer skills", "peachtree accounting system"], "soft_skills": ["detail-minded", "self-motivated", "independently", "independent", "sense of responsibility", "detail-oriented", "hands-on", "work under pressure"], "languages_combined": []}, "experience_required": {"duration": ["5 years"], "field": ["management", "relevant experience"]}}, {"job_id": "100003009052270", "location_code": "hk", "company": "Lubuds F&B Group", "job_title": "Assistant Accountant (LUBUDS AXIS)", "description": "Responsibilities: -\n\nProcess accounts receivables and incoming payments in compliance with financial policies and procedures\nPerform debt collection by liaising with customers and sales team\nPrepare month end schedules and reconciliations\n\nRequirements: -\n\nAssociate Degree or above in Accountancy or related disciplines\n1 year relevant working experience (Fresh graduates will also be considered)\nProficiency in Excel, Word and Chinese word processing\nFluent in written and spoken English and Chinese\nGood communication and interpersonal skills\nWell organized and willing to learn\nWe offer competitive salary package and attractive fringe benefits including life insurance, medical and dental to the right candidates. We also offer free lunch and free shuttle bus service.\n\n\n\nInterested parties please click \"Apply Now\" to submit your application including expected salary and contact information.\n\n\nFor more information, please visit our website at\u00a0https://corporate.lkk.com.\n\nAll personal data provided by the job applicants will be treated in strictly confidential and will be used exclusively for employment purpose only. You should consider your application as being unsuccessful if you do not hear from us within 3 months. Your application will be retained for 12 months and be considered for other appropriate positions within this period.\u00a0", "employment_types": ["Full Time", "Permanent"], "selling_points": [], "locations": ["Southern Area"], "categories": ["Accounting", "Accountant", "Accounting Clerk / Supervisor", "Finance / Accounting Manager"], "post_time": "2022-01-17T02:37:33Z", "salary": {"currency": null, "max": null, "min": null, "period": "monthly", "term": null}, "salary_visible": false, "title_keywords": ["assistant accountant"], "responsibilities": ["schedules", "financial policies", "compliance", "procedures", "liaising with", "debt collection", "reconciliations", "payments", "sales team"], "requirements": {"degrees": ["degree or above"], "majors": ["related disciplines", "accountancy"], "languages": ["english", "chinese"], "language_level": ["proficiency", "fluent"], "hard_skills": ["excel", "chinese word processing", "word"], "soft_skills": ["communication and interpersonal skills", "well organized", "willing to learn"], "languages_combined": [{"language": "english", "language_level": ["fluent"]}, {"language": "chinese", "language_level": ["proficiency", "fluent"]}]}, "experience_required": {"duration": ["1 year"], "field": ["relevant working experience"]}}, {"job_id": "100003009053487", "location_code": "hk", "company": "Global Life Immigration (HK) Limited", "job_title": "Accountant/ Assistant Accountant", "description": "Responsibilities\n\n\nHandle full set of accounts including but not limited to the preparation of vouchers, accounting schedules, bank reconciliation, and various accounting reports\nMonitor daily cash flow\nIssue quotation and invoice to company\u2019s client\nLiaise with Contractor and Sub-contractor regarding the payment issue\nClosely work with project team on daily accounting operations\nOther ad hoc assignments as assigned\n\nJob Requirements\n\n\nPossess Higher Diploma in Accounting or Finance or LCCI Level 3 certificate\nAt least 5 years of working experience in accounting field is required\nWorking experience in Interior Design Company is highly preferred\nProficiency in MS Excel & Word, familiar with accounting systems\nAn effective team player,\u00a0positive attitude and customer service oriented\nSelf-motivated and willing to learn\nGood command of written and spoken English and Chinese\nImmediate available is highly preferred\nExperienced candidates may be considered as Accountant\n\nBenefits\n\n\n5-Day work week\n2 days Birthday Leave\nPaid Sick Leave\nStaff Discount\n\nWe provide coaching and guidance on professional development and excellent career opportunities to our team members. Interested parties,\u00a0please send full resume with your current and expected salary by \u201cApply Now\u201d.\n\n\nInformation collected will be treated in strict confidence and used for recruitment purposes only.\u00a0 Only suitable candidates will be notified.", "employment_types": ["Full Time", "Permanent"], "selling_points": ["F. 6 or above", "1-2 years accounting experience", "Attractive remuneration package"], "locations": ["Tsim Sha Tsui"], "categories": ["Accounting", "Accountant", "Accounting Clerk / Supervisor", "Treasurer"], "post_time": "2022-01-17T07:02:44Z", "salary": {"currency": null, "max": null, "min": null, "period": "monthly", "term": null}, "salary_visible": false, "title_keywords": ["accountant", "assistant accountant"], "responsibilities": ["schedules", "invoice", "full set of accounts", "monitor", "bank reconciliation", "quotation", "daily accounting operations", "cash flow", "payment", "reports", "ad hoc assignments", "liaise with"], "requirements": {"degrees": ["certificate", "diploma"], "majors": ["finance", "accounting"], "languages": ["english", "chinese"], "language_level": ["good command"], "hard_skills": ["accounting systems", "ms excel", "word"], "soft_skills": ["self-motivated", "customer service oriented", "willing to learn", "positive attitude", "team player"], "languages_combined": [{"language": "english", "language_level": ["good command"]}, {"language": "chinese", "language_level": ["good command"]}]}, "experience_required": {"duration": ["at least 5 years"], "field": ["accounting", "design"]}}, {"job_id": "100003009053041", "location_code": "hk", "company": "GDH Guangnan (Holdings) Limited", "job_title": "Accounting Officer - Finance Department", "description": "Key Responsibilities\uff1a\n\n\u00a0Preparation of full set of accounts, financial report and management report\n\u00a0Responsible for daily accounting operation\n\u00a0Provide administrative and clerical support\n\u00a0Assist in ad hoc assignments\n\n\u00a0Requirements:\n\n\nF. 6 or above\n1-2 years accounting experience\nProficiency in MS Office application and Chinese Word Processing\nGood communication and presentation skill\nHardworking, good in team work, able to work under pressure\nGood in Chinese, English and Mandarin\nLess experience / Fresh graduate is also welcome\n\nWe offer\n\nWe offer attractive remuneration package, 5-day work, performance bonus, medical allowance, birthday leave and career prospects to successful candidates. \u00a0Interested parties please apply in full resume with your employment history, current\u00a0and expected salary, and click APPLY NOW.", "employment_types": ["Full Time", "Permanent"], "selling_points": ["Diploma or above in accounting or similar", "3 years or above accounting/finance experience", "Immediate available is preferred."], "locations": ["Wan Chai"], "categories": ["Accounting", "Accounting Clerk / Supervisor"], "post_time": "2022-01-17T05:20:04Z", "salary": {"currency": null, "max": null, "min": null, "period": "monthly", "term": null}, "salary_visible": false, "title_keywords": ["accounting officer"], "responsibilities": ["full set of accounts", "financial report", "ad hoc assignments", "administrative and clerical support", "daily accounting", "management report"], "requirements": {"degrees": ["fresh graduate"], "majors": [], "languages": ["english", "chinese", "mandarin"], "language_level": ["proficiency", "good"], "hard_skills": ["presentation skill", "chinese word processing", "ms office"], "soft_skills": ["communication", "presentation skill", "hardworking", "work under pressure"], "languages_combined": [{"language": "english", "language_level": ["good"]}, {"language": "chinese", "language_level": ["proficiency", "good"]}, {"language": "mandarin", "language_level": ["good"]}]}, "experience_required": {"duration": ["1-2 years"], "field": ["accounting experience"]}}, {"job_id": "100003009051433", "location_code": "hk", "company": "Welford Properties Limited", "job_title": "Accounting Assistant", "description": "Responsibilities:\n\nHandle full set accounts and daily accounting operation independently;\nPrepare month end closing and financial report;\nAssist in the\u00a0financial forecast on a monthly basis and\u00a0financial budgeting on a yearly basis;\nHandle regular administrative office works;\nParticipate in ad-hoc projects as assigned.\n\nRequirements:\n\nDiploma or above\u00a0in accounting or similar;\n3\u00a0years or above accounting / finance experience, of which with PRC accounting and listed company experience is highly preferred;\nSelf-motivated, well organized, independent, responsible, able to work under pressure and meet tight deadlines;\nProficiency in MS Excel. Experiences in using accounting system such as EBS are preferred;\nStrong command in both spoken and written in English and Chinese (both Mandarin & Cantonese);\nOccasionally travel to Mainland China is required; and\nImmediate available is preferred.", "employment_types": ["Full Time", "Permanent"], "selling_points": [], "locations": ["Not Specified"], "categories": ["Accounting", "Accounting Clerk / Supervisor"], "post_time": "2022-01-15T16:57:09Z", "salary": {"currency": null, "max": null, "min": null, "period": "monthly", "term": null}, "salary_visible": false, "title_keywords": ["accounting assistant"], "responsibilities": ["month end closing", "budgeting", "financial report", "forecast", "daily accounting", "ad-hoc projects"], "requirements": {"degrees": ["diploma or above"], "majors": ["accounting"], "languages": ["cantonese", "english", "chinese", "mandarin"], "language_level": [], "hard_skills": ["ms excel", "accounting system", "prc accounting"], "soft_skills": ["self-motivated", "meet tight deadlines", "independent", "responsible", "well organized", "work under pressure"], "languages_combined": [{"language": "cantonese", "language_level": []}, {"language": "english", "language_level": []}, {"language": "chinese", "language_level": []}, {"language": "mandarin", "language_level": []}]}, "experience_required": {"duration": ["3 years"], "field": ["finance", "accounting"]}}, {"job_id": "100003009052196", "location_code": "hk", "company": "IPSOS Asia Limited", "job_title": "Temporary Accounts Clerk \u2013 Accounts Receivable (1 year renewable contract)", "description": "The Role:\u00a0\n\nResponsible for consolidation accounting, management account for subsidiaries and associated companies\nTo assist daily accounting work;\u00a0 full set of account and reconciliations.\nPrepare monthly accounting schedule bank transactions, AP, AR and general ledger.\nTo assist accounting issues and able to work independently.\n\nRequirements:\n\nDiploma or above in Accounting or equivalent faculty;\n3-5 year working experience in business accounting field.\nDetailed oriented, good in analytical ability and communication skills;\nProficiency in Excel skills and proficient knowledge of computer\nImmediately available is preferred;\n\n\nWe offer permanent jobs with 5-day work per week, excellent career opportunities and remuneration package to the right candidates. Interested parties please reply with expected and present salary to the email for application.", "employment_types": ["Full Time", "Part Time", "Permanent", "Temporary", "Contract", "Freelance"], "selling_points": ["Accounts Receivable", "Handling monthly schedule", "Preparing expense analysis and reporting"], "locations": ["Hung Hom"], "categories": ["Accounting", "Accountant", "Accounting Clerk / Supervisor", "Others"], "post_time": "2022-01-17T02:26:10Z", "salary": {"currency": null, "max": null, "min": null, "period": "monthly", "term": null}, "salary_visible": false, "title_keywords": ["accounts clerk"], "responsibilities": ["ap", "management", "ar", "general ledger", "daily accounting work", "transactions", "communication", "reconciliations", "schedule"], "requirements": {"degrees": ["diploma or above"], "majors": ["accounting"], "languages": [], "language_level": [], "hard_skills": ["ap", "excel", "ar"], "soft_skills": ["communication skills", "work independently", "detailed oriented", "responsible"], "languages_combined": []}, "experience_required": {"duration": ["3-5 year"], "field": ["business", "accounting"]}}, {"job_id": "100003009052730", "location_code": "hk", "company": "South Horizons Management Limited", "job_title": "SENIOR ACCOUNTS CLERK / ACCOUNTS CLERK [Ref. SH-SAC/AC]", "description": "The role of Accounts Clerk \u2013 Accounts Receivable is to assist the Accountant in handling account receivable function, monthly schedule & reconciliation and performing the financial accounting jobs for month end.\n\nRole & Responsibilities:\n\nIssue invoice to customers.\nPerform settlement received from customers and follow up on outstanding balances on a timely manner.\nPrepare management reports relating to accounts receivable.\nPrepare balance sheet and monthly schedules relating to accounts receivable and follow up on outstanding items.\nSupport ad-hoc assignments.\n\nQualification\uff1a\n\nDiploma or above in Accountancy or Finance\nLCCI Inter-mediate level or above with 1-2 years of accounting experience is preferred\n\nKnowledge\uff1a\n\nBasic accounting knowledge\nKnowledge in accounting system is a definite advantage\nProficient in MS Word & Excel\n\nSkill (including technical and people skill):\n\nGood English language skill both verbal and writing\nGood computer skill especially in Microsoft Excel, Word, and PowerPoint\n\nOther Requirements\n\nResponsible and able to work overtime to meet tight report deadlines\nImmediate available is preferred\n\nWe offer an attractive remuneration package with a 5-day workweek to the right candidates. Interested parties please send a resume to us. All information collected will be used for recruitment purposes only. The Company may retain applications for future openings or other appropriate positions within the Company. Resumes received will be destroyed within 12 months.", "employment_types": ["Full Time", "Permanent"], "selling_points": ["5 passes in HKCEE / HKDSE including English", "2 years' relevant working experience", "LCC Intermediate level in accounting"], "locations": ["Aberdeen"], "categories": ["Accounting", "Accounting Clerk / Supervisor", "Others", "Property / Real Estate", "Property Management"], "post_time": "2022-01-17T06:30:00Z", "salary": {"currency": null, "max": null, "min": null, "period": null, "term": null}, "salary_visible": false, "title_keywords": ["accounts clerk", "senior accounts clerk"], "responsibilities": ["accounts receivable", "invoice", "schedules", "ad-hoc assignments", "a timely manner", "management reports", "balance sheet"], "requirements": {"degrees": [], "majors": [], "languages": [], "language_level": [], "hard_skills": [], "soft_skills": ["work overtime", "responsible"], "languages_combined": []}, "experience_required": {"duration": [], "field": []}}, {"job_id": "100003009054426", "location_code": "hk", "company": "HKR International Ltd", "job_title": "Assistant - Accounting / Assistant Accountant", "description": "5 passes in HKCEE / HKDSE including English or equivalent\nHolder of LCC Intermediate level in\u00a0accounting\nMinimum 2 years' relevant working experience\nTo maintain accounting system and daily operation\nTo Handle full sets of book-keeping for management fund accounts\nTo generate debit notes / reminders / receipts from billing system\nTo handle daily cheque register and deposit arrangement\nTo prepare petty cash vouchers and reimbursement arrangement\nTo handle enquiries\nAd-hoc tasks as assigned by immediate supervisor\nProficient in MS Office with knowledge in Oracle system is an added advantage\nFluent in written and spoken English and Chinese\nDetail-oriented, self-motivated and able to work independently\nCandidate with less experience will be considered as Accounts Clerk\n\nWe offer salary and benefits commensurate with qualifications and experience. Please send a full resume with contact telephone number and expected salary to\u00a0General Manager - Human Resources & Administration, South Horizons Management Limited, 3/F., One Harbourfront, 18 Tak Fung Street, Hunghom, Kowloon\u00a0(Please quote reference on envelope)\u00a0or by clicking \"Apply Now\".\n\nWe are an equal opportunity employer and welcome applications from all qualified candidates. The information provided will be treated in strict confidence and be used only for consideration of your application for relevant/similar post(s).\n\nApplicants not hearing from us within six weeks from the date of advertisement may consider their applications unsuccessful. All personal data of unsuccessful applicants will be destroyed after the recruitment exercise when no longer required.", "employment_types": ["Full Time", "Permanent"], "selling_points": ["Higher diploma or above in Accounting", "Fresh university graduates will also be considered", "Work in Tsuen Wan"], "locations": ["Tsuen Wan Area"], "categories": ["Accounting", "Accountant", "Accounting Clerk / Supervisor", "Others"], "post_time": "2022-01-17T09:30:17Z", "salary": {"currency": null, "max": null, "min": null, "period": null, "term": null}, "salary_visible": false, "title_keywords": ["accounting", "assistant accountant", "assistant"], "responsibilities": ["management", "receipts", "ad-hoc tasks", "daily operation", "handle enquiries", "maintain", "book-keeping"], "requirements": {"degrees": ["hkdse"], "majors": [], "languages": ["english", "chinese"], "language_level": ["fluent"], "hard_skills": ["oracle system", "billing system", "lcc", "accounting system", "ms office"], "soft_skills": ["self-motivated", "work independently", "detail-oriented"], "languages_combined": [{"language": "english", "language_level": ["fluent"]}, {"language": "chinese", "language_level": ["fluent"]}]}, "experience_required": {"duration": ["minimum 2 years"], "field": ["relevant working experience"]}}, {"job_id": "100003009053695", "location_code": "hk", "company": "SY Solutions Limited", "job_title": "\u81e8\u6642\u884c\u653f\u52a9\u7406", "description": "Reporting to the Senior Accountant, the incumbent will be responsible for accounts payable & receivable, preparation of vouchers & simple accounting analysis, assisting in month end closing and other ad hoc assignments.\n\nRequirements:\nHigher diploma or above in Accounting or related discipline;\nGood command of both spoken and written English and Chinese;\nGood interpersonal skills;\nSelf-motivated with analytical mind;\nFresh university graduates will also be considered.\n\nWorking location: Tsuen Wan\n\nBenefits:\nWe offer competitive remuneration package including annual leave, discretionary bonus, dental and medical coverage and Top-up MPF. We value our employees\u2019 career development and provide them with a variety of internal and external training opportunities.\n\nApplication Methods:\n\nOnline application \u2013 Visit our website\u00a0http://www.hkri.com\u00a0(Career Opportunities/\u00a0Hong Kong Resort Company Limited) to complete the online application form;\nEmail \u2013 Send your detailed resume and expected salary to \"Apply Now\";\nWhatsapp \u2013 5987 0673;\nFax \u2013 2902 2510", "employment_types": ["Contract"], "selling_points": [], "locations": ["Mong Kok"], "categories": ["Accounting", "Accounting Clerk / Supervisor", "Admin & HR", "Clerical / Admin Staff", "Medical Services", "Others"], "post_time": "2022-01-17T07:22:14Z", "salary": {"currency": null, "max": null, "min": null, "period": "monthly", "term": null}, "salary_visible": false, "title_keywords": [], "responsibilities": ["reporting", "month end closing", "analysis", "ad hoc assignments", "accounts payable"], "requirements": {"degrees": ["higher diploma or above"], "majors": ["accounting"], "languages": ["english", "chinese"], "language_level": ["good command"], "hard_skills": ["simple", "analysis", "wan"], "soft_skills": ["self-motivated", "analytical mind", "interpersonal skills", "responsible"], "languages_combined": [{"language": "english", "language_level": ["good command"]}, {"language": "chinese", "language_level": ["good command"]}]}, "experience_required": {"duration": [], "field": []}}, {"job_id": "100003009053137", "location_code": "hk", "company": "Sinopec Chemical Commercial Holding (Hong Kong) Company Limited", "job_title": "Assistant Accountant", "description": "\n\u8077\u8cac :\u4e00\u822c\u6587\u54e1\u3001\u6587\u66f8\u5de5\u4f5c, \u5305\u62ec\u8cc7\u6599\u8f38\u5165, \u6587\u4ef6\u5b58\u6a94,\u8907\u5370, \u7de8\u5236\u5831\u544a\u7b49\n\n\u8cc7\u6b77 :\u4e2d\u4e94\u7a0b\u5ea6; 1\u5e74\u7d93\u9a57; \u826f\u597d\u7cb5\u8a9e; \u826f\u597d\u666e\u901a\u8a71; \u4e00\u822c\u82f1\u8a9e; \u61c2\u8b80\u5beb\u4e2d\u6587; \u61c2\u8b80\u5beb\u82f1\u6587; \u61c2MS Word; \u61c2MS Excel; \u61c2\u82f1\u6587\u6253\u5b57; \u61c2\u4e2d\u6587\u6253\u5b57; \u5177\u6709\u57fa\u672c\u96fb\u8166\u64cd\u4f5c\u77e5\u8b58; \u5177\u6587\u8077\u7d93\u9a57\u512a\u5148\n\n\u5f85\u9047 :\u6bcf\u6708$13,000 - $15,000, \u661f\u671f\u4e00\u81f3\u4e94: \u4e0a\u53489\u6642\u81f3\u4e0b\u53486\u6642, \u6bcf\u9031\u5de5\u4f5c5\u5929, \u5de5\u4f5c\u671f\u7531 03/2022 \u81f3 07/2022\n\n\u7533\u8acb\u9808\u77e5 :\u6c42\u8077\u8005\u53ef\u50b3\u771f(21040202)\u6216\u96fb\u90f5(Apply Now)\u5c65\u6b77\u8868\u7d66SY SOLUTIONS LIMITED\u3002\u5982\u8981\u7d22\u53d6\u6536\u96c6\u500b\u4eba\u8cc7\u6599\u8072\u660e, \u8acb\u8207\u8521\u5c0f\u59d0(Fax/Email)\u806f\u7d61\u3002\n\n", "employment_types": ["Full Time", "Permanent"], "selling_points": [], "locations": ["Wan Chai"], "categories": ["Accounting", "Accountant", "Accounting Clerk / Supervisor", "Others"], "post_time": "2022-01-17T06:03:37Z", "salary": {"currency": null, "max": null, "min": null, "period": "monthly", "term": null}, "salary_visible": false, "title_keywords": ["assistant accountant"], "responsibilities": [], "requirements": {"degrees": [], "majors": [], "languages": [], "language_level": [], "hard_skills": ["excel", "word"], "soft_skills": [], "languages_combined": []}, "experience_required": {"duration": [], "field": []}}, {"job_id": "100003009054512", "location_code": "hk", "company": "Lai Sun Development Co Ltd", "job_title": "Assistant Accountant (6 months contract)", "description": "Main Job Duties:\n\n\nPreparing monthly reports and analysis\nCoordinate with Sales & Operation Department and verify the correctness of revenue and cost postings\nMonth-end closing\nReview sales/purchase contracts and agreements\nCommunicate with overseas representation office, prepare the management accounts and handle\u00a0finance-related issues remotely\nPerform routine accounting works includes voucher entries and filling etc.\nOther ad hoc tasks as assigned\n\nRequirements:\n\n\nBachelor degree in Accounting, Finance, or equivalent\nMember of ACCA or QP or equivalent is preferred\nProficiency in MS Excel and Word\nProficiency in English and Chinese (Mandarin is a must)\nAble to work independently and work under pressure to meet tight deadlines\nPositive attitude, detail-minded, self-motivated\nWilling to learn and work overtime especially for month-end closing\n1-3 years accounting experience\nFresh graduates will also be considered.\n\nWe offer 5 days work with good career prospects for the right candidates. Interested parties please send your application with detailed CV including availability, current and expected salary (IS A MUST) in MS Word format by clicking Apply Now.", "employment_types": ["Permanent", "Contract"], "selling_points": ["Prepare monthly financial statements and reports", "Process payments settlement", "LCCI Higher"], "locations": ["Cheung Sha Wan"], "categories": ["Accounting", "Accountant", "Accounting Clerk / Supervisor"], "post_time": "2022-01-17T09:50:34Z", "salary": {"currency": null, "max": null, "min": null, "period": "monthly", "term": null}, "salary_visible": false, "title_keywords": ["assistant accountant"], "responsibilities": ["communicate with", "cost", "management", "monthly reports", "contracts", "analysis", "review", "coordinate with", "ad hoc tasks", "purchase", "month-end closing"], "requirements": {"degrees": ["degree", "bachelor"], "majors": ["finance", "accounting"], "languages": ["english", "chinese", "mandarin"], "language_level": ["proficiency"], "hard_skills": ["acca", "ms excel", "word"], "soft_skills": ["detail-minded", "work independently", "meet tight deadlines", "self-motivated", "work overtime", "willing to learn", "positive attitude", "work under pressure"], "languages_combined": [{"language": "english", "language_level": ["proficiency"]}, {"language": "chinese", "language_level": ["proficiency"]}, {"language": "mandarin", "language_level": []}]}, "experience_required": {"duration": ["1-3 years"], "field": ["accounting experience"]}}, {"job_id": "100003009054350", "location_code": "hk", "company": "Strategic Public Relations Group Limited", "job_title": "Accounts Clerk (5-day work)", "description": "We\u2019re hiring!\n\nAon is currently recruiting an\u00a0Accounting Officer\u00a0to join our team in Hong Kong.\n\nAbout Aon\n\nHeadquartered in London, Aon Plc is a leading global professional services firm providing a broad range of risk, retirement and health solutions. Our 50,000 colleagues in 120 countries empower results for clients by using proprietary data and analytics to deliver insights that reduce volatility and improve performance.\n\nAt Aon, you\u2019ll be part of a team which will support and inspire you and provide the opportunities and resources to develop your skills. It\u2019s an environment which encourages you to achieve your best - together we\u2019ll empower results.\u00a0\n\nResponsibilities:\n\nWork in Reinsurance department\nPerform daily accounting operation in account payable and receivable function\nHandle invoice payments, receipts, and reconciliation of accounts with client & reinsurers\nInvestigate if any discrepancies within the reconciliation and follow up with respective units\nParticipate in Short-term project, such as clearance of legacy balance\nLiaise with client manager to understand client\u2019s needs and resolve accounting issues\nParticipate in UAT for system projects in relating to system enhancement if required\nAssist managers on reporting and other ad-hoc tasks.\n\nRequirements:\n\nGraduate with Accounting/ Finance/ Business degree.\nAt least 2-3 years relevant Accounting experience is preferred.\nStrong technical skills in MS Excel.\nProficiency in English and Mandarin.\nGood analytical skill and problem-solving skill.\nGood interpersonal skill\nDetailed minded, proactive, accurate and meticulous.\nMature, independent, self-starter.\nImmediate available preferred.\n\nHow to Apply\n\nYour opportunity to empower results could start right here. Make your mark and apply online today with a brief covering letter and your resume, sharing relevant achievements for this position.\n\nWe Offer You\n\nA competitive total rewards package, continuing education & training, and tremendous potential with a growing worldwide organization.\n\nOur Colleague Experience\n\nEvery day, our colleagues make a difference, work with the best, own their potential, and value one another. Together, we share this one purpose: to empower economic and human possibility around the world. This unifying goal is at the heart of our identity, and it lives in everything we do. To learn more about our colleague experience, visit Aon Colleague Experience.\n\nAon is an equal opportunities employer. We are committed to creating a winning and inclusive culture where everyone feels valued and has opportunities for growth and development.", "employment_types": ["Full Time", "Permanent"], "selling_points": ["Fresh graduates are also welcome", "5 Days Work with D.Bonus/ Bank Holiday", "12 Days AL/Birthday Leave/Medical&Life Insurance"], "locations": ["Admiralty"], "categories": ["Accounting", "Accounting Clerk / Supervisor", "Others", "Sales, CS & Business Devpt", "Others"], "post_time": "2022-01-17T09:14:21Z", "salary": {"currency": null, "max": null, "min": null, "period": "monthly", "term": null}, "salary_visible": false, "title_keywords": ["accounts clerk"], "responsibilities": ["reporting", "receipts", "uat", "invoice", "ad-hoc tasks", "assist managers", "liaise with client", "payments", "daily accounting"], "requirements": {"degrees": ["degree"], "majors": ["business", "finance", "accounting"], "languages": ["english", "mandarin"], "language_level": ["proficiency"], "hard_skills": ["problem-solving", "make", "ms excel", "analytical skill"], "soft_skills": ["meticulous", "analytical skill", "independent", "accurate", "problem-solving", "mature", "interpersonal skill", "technical skills", "proactive", "detailed"], "languages_combined": [{"language": "english", "language_level": ["proficiency"]}, {"language": "mandarin", "language_level": ["proficiency"]}]}, "experience_required": {"duration": ["at least 2-3 years"], "field": ["accounting experience"]}}, {"job_id": "100003009051720", "location_code": "hk", "company": "Advance Thermo Control Ltd", "job_title": "Accounting Supervisor", "description": "Responsibilities:\u00a0\n\nProvide clerical support to the Accounts Department\nBeing the main contact point between the Sales and Accounts Department\nPrepare documentation such as quotations, invoices, debit notes, and data entry\nMaintain the filing system and coordinate all related actions\nAssist in handling full set of accounting records\nPrepare month end closing, inter-co transaction and reconciliation independently\nHandle ad hoc assignment as required\n\nJob Requirements:\n\nDiploma or above\nFresh graduates are also welcome\u00a0\nGood computer skills, in particular MS Office,\u00a0\nSelf-motivated, independent, detail-minded, able to work under pressure and strong sense of responsibility\nFluency in written and spoken English and Mandarin\nImmediate available is highly preferred\n\n\u00a0\nInterested parties please complete the standard application form by clicking the\u00a0Apply now\u00a0button. You can also attach your tailored CV and Cover letter with your current and expected salary which we will use to review applications.\n\nIt is Our Company policy to comply with the requirements of the Personal Data (Privacy) Ordinance (Cap. 486) of the Laws of the Hong Kong Special Administrative Region. Any personal data which is collected shall be handled in accordance with this Personal Information Collection Statement (\u201cPICS\u201d).\n\nThe personal data collected from you will be used for purposes relating to your application for employment with the Company. You must ensure that all personal data provided to the Company are accurate, complete and up-to-date. For correction of or access to personal data after submission of the job application or enquiries on recruitment matters, please contact the HR or subject officer as specified in the recruitment advertisement.\n\n\u00a0Website:\u00a0\u00a0www.sprg.com.hk\u00a0/\u00a0www.sprg.asia\n\nFacebook:\u00a0\u00a0https://www.facebook.com/SPRGAsia\u00a0/\u00a0https://www.facebook.com/CSR.SPRG", "employment_types": ["Full Time"], "selling_points": ["5 working days per week", "Medicine Insurance", "US base complany"], "locations": ["Tsuen Wan Area"], "categories": ["Accounting", "Accounting Clerk / Supervisor"], "post_time": "2022-01-16T21:51:07Z", "salary": {"currency": null, "max": null, "min": null, "period": "monthly", "term": null}, "salary_visible": false, "title_keywords": ["accounting supervisor"], "responsibilities": ["provide clerical support", "month end closing", "invoices", "data entry", "ad hoc assignment", "full set of accounting", "coordinate", "maintain", "contact", "documentation"], "requirements": {"degrees": ["diploma or above"], "majors": [], "languages": ["english", "mandarin"], "language_level": ["fluency"], "hard_skills": ["computer skills", "ms office"], "soft_skills": ["detail-minded", "self-motivated", "independent", "sense of responsibility", "work under pressure"], "languages_combined": [{"language": "english", "language_level": ["fluency"]}, {"language": "mandarin", "language_level": ["fluency"]}]}, "experience_required": {"duration": [], "field": []}}]