[{"job_id": "100003009052393", "location_code": "hk", "company": "Chinastar Services Limited", "job_title": "Assistant Audit Manager/ Audit Manager", "description": "- Be professional, meticulous with exposure to serve foreign clients\n- Can work independently\n- Previous working experience in CPA firm preferred\u00a0\n- Excellent career path to be a partner\n- Flexible working hours and work at home arrangement", "employment_types": ["Permanent"], "selling_points": ["Excellent career path", "Double pay and year end bonus", "5 days work with flexible working hours"], "locations": ["Not Specified"], "categories": ["Accounting", "Audit"], "post_time": "2022-01-17T02:56:10Z", "salary": {"currency": null, "max": null, "min": null, "period": "monthly", "term": null}, "salary_visible": false, "title_keywords": ["manager", "assistant"], "responsibilities": [], "requirements": {"degrees": [], "majors": [], "languages": [], "language_level": [], "hard_skills": ["cpa"], "soft_skills": ["flexible", "meticulous", "work independently"], "languages_combined": []}, "experience_required": {"duration": [], "field": ["cpa firm"]}}, {"job_id": "100003009051474", "location_code": "hk", "company": "BDO", "job_title": "Audit Senior Associate (Ref : AUD / JDB)", "description": "Responsibilities:\n\nResponsible for the planning and execution of audit fieldwork and completing the assigned tasks accordance with the audit plan and our firm's procedures\nSupport and act towards the BDO Global Vision\nBe committed to act with the firm\u2019s core values and competency expectations\n\nRequirements:\n\nDegree holder, major in accounting or\u00a0other\u00a0related disciplines\nAt least 2 year of relevant experience in assurance, gained with sizable accounting firm\nQualified accountant is preferred but not a pre-requisite\n\nA good and effective team player\nExcellent command of both written and spoken English and Chinese; including Mandarin\nBe passionate for providing exceptional quality service and striving for exceeding clients\u2019 expectations\n\nWe are an equal opportunity employer, and offer excellent prospects and career development for the right candidate.\u00a0 Interested parties please send your application with full career history, current and expected salary by clicking\u00a0Apply Now\u00a0button below.\n\nApplications will be treated in strict confidence. Personal data collected will be used for recruitment purposes only.", "employment_types": ["Full Time", "Permanent"], "selling_points": ["At least 2 years of relevant experience", "Qualified accountants are preferred", "Excellent Career Prospects"], "locations": ["Sheung Wan"], "categories": ["Accounting", "Audit"], "post_time": "2022-01-16T03:47:59Z", "salary": {"currency": null, "max": null, "min": null, "period": "monthly", "term": null}, "salary_visible": false, "title_keywords": ["senior associate"], "responsibilities": ["procedures", "audit", "plan", "planning"], "requirements": {"degrees": ["degree holder"], "majors": ["related disciplines", "accounting"], "languages": ["english", "chinese", "mandarin"], "language_level": ["excellent"], "hard_skills": [], "soft_skills": ["passionate", "team player"], "languages_combined": [{"language": "english", "language_level": ["excellent"]}, {"language": "chinese", "language_level": ["excellent"]}, {"language": "mandarin", "language_level": []}]}, "experience_required": {"duration": ["at least 2 year"], "field": ["assurance", "accounting", "relevant experience"]}}, {"job_id": "100003009054121", "location_code": "hk", "company": "Vincent W M Lai & Co", "job_title": "Audit Junior / Intermediate (5-days work)", "description": "Requirements\n\nIVE / Diploma / Associate Degree / Degree holder in Accountancy\n1 year relevant\u00a0working experience in auditing / taxation / accounting\nCandidate with solid experience will be offered as Intermediate\nGood command of written English\nGood command of PC knowledge and MS Office\nHardworking, self-motivated and able to\u00a0work independently\n\nBenefits\n\n5-days week and medical claim\nProfessional training will be provided\nOffer Study & Exam Leaves for recognized professional exam\nOvertime pay\n\nInterested parties please email your full resume with expected salary by clicking \"Apply Now\"\u00a0 of Vincent W M Lai & Co.\n\nPersonal data collected will be used for recruitment purposes only", "employment_types": ["Full Time", "Permanent"], "selling_points": [], "locations": ["Central"], "categories": ["Accounting", "Accountant", "Audit", "Taxation"], "post_time": "2022-01-17T08:28:24Z", "salary": {"currency": null, "max": null, "min": null, "period": "monthly", "term": null}, "salary_visible": false, "title_keywords": ["junior"], "responsibilities": ["taxation", "auditing"], "requirements": {"degrees": ["associate degree", "diploma", "degree holder"], "majors": ["accountancy"], "languages": ["english"], "language_level": ["good command"], "hard_skills": ["pc knowledge", "ms office"], "soft_skills": ["self-motivated", "work independently", "hardworking"], "languages_combined": [{"language": "english", "language_level": ["good command"]}]}, "experience_required": {"duration": ["1 year"], "field": ["accounting", "relevant working experience"]}}, {"job_id": "100003009052880", "location_code": "hk", "company": "YCA Partners CPA Limited", "job_title": "Audit Staff (Junior / Senior) - 5 day work", "description": "Requirements:\n\nDiploma / Degree holder with major in accounting, finance or business related disciplines;\n0-3 year(s) relevant working experience, fresh graduate is welcome;\nGood command in spoken and written English, Cantonese and Putonghua; and\nInitiative, hardworking and able to work under pressure;\n\nBenefits\n\nFive-day work week\nFlexible working hours\nDiscretionary bonus\nBirthday leave\nMedical allowance\u00a0\nExamination leave\nStudy leave\nOvertime compensation leave\n\nCompetitive package will be offered to the right candidate(s), including 5-day work, annual discretionary bonuses, training, examination and study leaves. Interested parties please send in full resume with current & expected salary to our HR Department via \"Apply Now\".\n\nPlease visit\u00a0www.yca.com.hk\u00a0for more information.\n\nPersonal data will be used for recruitment purpose only.", "employment_types": ["Full Time"], "selling_points": ["Five-day work week / Flexible working hours", "Discretionary bonus / Medical allowance", "Birthday leave / Examination leave / Study leave"], "locations": ["Kwun Tong"], "categories": ["Accounting", "Accountant", "Audit", "Others"], "post_time": "2022-01-17T04:24:02Z", "salary": {"currency": null, "max": null, "min": null, "period": "monthly", "term": null}, "salary_visible": false, "title_keywords": ["audit staff", "junior"], "responsibilities": ["work under pressure"], "requirements": {"degrees": ["diploma", "fresh graduate", "degree holder"], "majors": ["business", "finance", "related disciplines", "accounting"], "languages": ["cantonese", "putonghua", "english"], "language_level": ["good command"], "hard_skills": [], "soft_skills": ["initiative", "hardworking", "work under pressure"], "languages_combined": [{"language": "cantonese", "language_level": ["good command"]}, {"language": "putonghua", "language_level": ["good command"]}, {"language": "english", "language_level": ["good command"]}]}, "experience_required": {"duration": [], "field": ["relevant working experience"]}}, {"job_id": "100003009053014", "location_code": "hk", "company": "Lui & Mak CPA Limited", "job_title": "AUDIT ASSOCIATE (All Level) (15-28K) (Fresh Graduates are Welcome)", "description": "Audit Associate\u00a0(15-28K)\n(Authorised Employer of HKICPA)\n\n\u00a0Requirements\u00a0\n\nHigher Diploma / Associate Degree / Degree holder\nComputer literacy and proficient in MS Word and Excel\nInitiative, independent, responsible and hard-working\nGood communication skills in both spoken and written English & Cantonese\nFresh graduate will also be considered\nImmediate available would be an absolute advantage\nFor Senior Level Audit Associate, at least 4 years in CPA firm with experience in handling technical updates (including Financial Reporting Standard, Auditing Standard, Companies Ordinance etc.)\n\n\u00a0Responsibilities\u00a0\n\nResponsible for completing statutory audit assignments of clients\u00a0\nAssist in tax planning and tax-related assignments\nLiaison with clients and colleagues for job coordination\nHandle ad hoc tasks as assigned\n\n\u00a0Interested parties please send full resume (with present & expected salary and availability) to Human Resource Department at Rooms 604-7, Dominion Centre, 43-59 Queen's Road East, Wanchai, Hong Kong or email to \u00a0recruit\uff20luimak.com.hk\u00a0or by clicking below Apply Now.\n\n*Personal data collected will be used for recruitment purposes only.", "employment_types": ["Full Time", "Permanent"], "selling_points": [], "locations": ["Wan Chai"], "categories": ["Accounting", "Audit"], "post_time": "2022-01-17T05:04:06Z", "salary": {"currency": null, "max": null, "min": null, "period": "monthly", "term": null}, "salary_visible": false, "title_keywords": ["associate"], "responsibilities": ["tax", "ad hoc tasks", "audit", "coordination", "planning"], "requirements": {"degrees": ["associate degree", "diploma", "fresh graduate", "degree holder"], "majors": [], "languages": ["cantonese", "english"], "language_level": ["good"], "hard_skills": ["excel", "cpa", "companies ordinance", "ms word"], "soft_skills": ["communication skills", "independent", "responsible", "computer literacy", "hard-working", "initiative"], "languages_combined": [{"language": "cantonese", "language_level": ["good"]}, {"language": "english", "language_level": ["good"]}]}, "experience_required": {"duration": ["at least 4 years"], "field": ["cpa firm", "audit", "financial"]}}, {"job_id": "100003009051762", "location_code": "hk", "company": "W. H. Tse & Company", "job_title": "Audit Semi-Senior", "description": "Requirements:\n\nDegree/Diploma holder, major in Accounting or related subjects\nMember/Student member of Professional Accountancy bodies\n1-3 years of solid auditing experience with ability to handle audit cases independently\nPC Knowledge in MS Office / Windows / Accounting software will be an advantage\nGood command of written and spoken English & Chinese/Mandarin\nSelf-motivated,\u00a0self-discipline and good interpersonal communication skills\n\nBenefits:\n\nAnnual Leave\nPerformance Related Bonus\nStudy and Exam Leaves\nOn-job training\nMedical, meal and travelling allowance\nGood working environment\n\nStatus:\n\n\nWe are an Authorised Employer of HKICPA.\n\n\nInterested parties, please send detailed resume to W. H. Tse & Co., by clicking \u201cApply Now\u201d or please call Miss Rebecca Lau at 2542 2800", "employment_types": ["Full Time", "Permanent"], "selling_points": [], "locations": ["Sheung Wan"], "categories": ["Accounting", "Accountant", "Accounting Clerk / Supervisor", "Audit"], "post_time": "2022-01-17T00:55:43Z", "salary": {"currency": null, "max": null, "min": null, "period": "monthly", "term": null}, "salary_visible": false, "title_keywords": [], "responsibilities": ["communication", "audit", "auditing", "software"], "requirements": {"degrees": ["diploma holder", "degree"], "majors": ["accounting"], "languages": ["english", "chinese", "mandarin"], "language_level": ["good command"], "hard_skills": ["accounting software", "pc knowledge", "ms office"], "soft_skills": ["communication skills", "self-motivated", "independently", "interpersonal"], "languages_combined": [{"language": "english", "language_level": ["good command"]}, {"language": "chinese", "language_level": ["good command"]}, {"language": "mandarin", "language_level": ["good command"]}]}, "experience_required": {"duration": ["1-3 years"], "field": ["audit"]}}, {"job_id": "100003009053595", "location_code": "hk", "company": "Eric Mok & Co., Limited", "job_title": "Audit Junior / Intermediate / Semi-Senior / Senior /Supervisor", "description": "Eric Mok & Co., Limited, CPAs\n\nWe are a professional accounting firm offering audit and assurance, taxation, corporate finance and accounting services to our clients. Our office locates at the China Hong Kong City in Tsim Sha Tsui. We are looking for suitable candidates for the following positions:\n\nAudit Junior / Intermediate / Semi-Senior / Senior /Supervisor\n\nRequirements\n\nDegree / Associate Degree in Accountancy or equivalent\n\nStudent member / member of HKICPA / ACCA / CPA Australia / CPA Canada or equivalent\n\n0 - 5 years\u2019 solid experience in auditing\n\nFor Audit Supervisor, experience in leading juniors, with excellent interpersonal skills\n\nGood command of written and spoken English and Mandarin\n\nSelf motivated, independent and willing to travel\n\nFamiliar with PC application and well-versed with Chinese word processing\n\nAble to work independently, meet deadline and work under pressure\n\nWe offer\n\nAttractive salary and bonus\n\nPaid study and examination leave, and training\n\nMedical allowance and insurance\n\n5-day week\n\nInterested parties please email your application letter specifying post applied and full resume with your present salary, salary expected and availability", "employment_types": ["Full Time"], "selling_points": [], "locations": ["Tsim Sha Tsui"], "categories": ["Accounting", "Audit"], "post_time": "2022-01-17T07:13:20Z", "salary": {"currency": null, "max": null, "min": null, "period": "monthly", "term": null}, "salary_visible": false, "title_keywords": ["supervisor", "junior"], "responsibilities": ["taxation", "audit", "auditing", "work under pressure"], "requirements": {"degrees": ["associate degree", "degree"], "majors": ["accountancy"], "languages": ["english", "chinese", "mandarin"], "language_level": ["good command"], "hard_skills": ["acca", "chinese word processing", "cpa", "pc", "hkicpa"], "soft_skills": ["work independently", "independent", "self motivated", "interpersonal skills", "work under pressure"], "languages_combined": [{"language": "english", "language_level": ["good command"]}, {"language": "chinese", "language_level": []}, {"language": "mandarin", "language_level": ["good command"]}]}, "experience_required": {"duration": ["0 - 5 years"], "field": ["audit"]}}, {"job_id": "100003009054568", "location_code": "hk", "company": "Liu & Wong Certified Public Accountants", "job_title": "Audit Juniors / Seniors \u2013 Multiple Headcounts", "description": "Requirements:\u00a0\u00a0\u00a0\u00a0\u00a0\u00a0\u00a0\u00a0\u00a0\u00a0\u00a0\u00a0\u00a0\u00a0\u00a0\u00a0\u00a0\u00a0\u00a0\u00a0\n\nDegree major in Accounting\nStudent member of HKICPA/ACCA or equivalent\nApplicants with no or less experience are considered as Audit Junior\nAble to handle small to medium size audit assignments independently, and to lead a team of 2 to 3 subordinates, preferably 3-5 years experience in audit and tax field are required for Seniors\nGood command of both written and spoken English and Chinese is essential, fluent in Putonghua\nImmediate available is preferable.\n\nRemuneration Package\u00a0\n\n5-day work\nStudy and examination leaves\nOn-the-job training\nExcellent career prospect\nDiscretionary bonuses\nFriendly working environment\n\nInterested parties please send your application via \"Apply Now\". (All information received will be treated in strict confidence and used for recruitment purpose only)", "employment_types": ["Full Time", "Permanent"], "selling_points": ["5-day work ! Good work-life balance !", "Study and examination leaves! On-the-job training!", "Near Central MTR Station !"], "locations": ["Central"], "categories": ["Accounting", "Audit", "Taxation"], "post_time": "2022-01-17T10:01:36Z", "salary": {"currency": null, "max": null, "min": null, "period": "monthly", "term": null}, "salary_visible": false, "title_keywords": [], "responsibilities": ["tax", "lead a team", "audit"], "requirements": {"degrees": ["degree"], "majors": ["accounting"], "languages": ["putonghua", "english", "chinese"], "language_level": ["good command", "fluent"], "hard_skills": ["no", "acca", "small", "hkicpa"], "soft_skills": ["independently", "friendly"], "languages_combined": [{"language": "putonghua", "language_level": ["fluent", "good command"]}, {"language": "english", "language_level": ["good command"]}, {"language": "chinese", "language_level": ["good command"]}]}, "experience_required": {"duration": ["3-5 years"], "field": ["audit", "team"]}}, {"job_id": "100003009052551", "location_code": "hk", "company": "Deep Blue CPA Limited", "job_title": "Audit Junior/Semi-senior Auditor/Senior Auditor", "description": "Requirements:\n\nDiploma or Degree holder in Accountancy;\n0-3 years experience in audit firm\nGood communication skills in both English and Putonghua;\nExcellent organizational skills, high accuracy and able to meet tightening deadline and ad hoc assignment ;\nResponsible and independent;\nWilling to learn and hardworking;\u00a0and\nPunctual, neat and tidy\u00a0\n\nWe offer\u00a0competitive remuneration package and excellent career prospects to the right candidate including 5-day work.\n\nCandidates should send their application letter, full C.V. with current and expected salary and date of availability\u00a0to us by clicking \"APPLY NOW\u201d for arrangement of an interview. (Please state clearly the position you are applying for)", "employment_types": ["Full Time", "Permanent"], "selling_points": [], "locations": ["Sheung Wan"], "categories": ["Accounting", "Accountant", "Audit", "Taxation"], "post_time": "2022-01-17T03:24:02Z", "salary": {"currency": null, "max": null, "min": null, "period": "monthly", "term": null}, "salary_visible": false, "title_keywords": ["junior"], "responsibilities": ["communication", "ad hoc assignment", "audit"], "requirements": {"degrees": ["diploma", "degree holder"], "majors": ["accountancy"], "languages": ["putonghua", "english"], "language_level": ["good"], "hard_skills": [], "soft_skills": ["communication skills", "organizational skills", "independent", "responsible", "willing to learn", "hardworking"], "languages_combined": [{"language": "putonghua", "language_level": ["good"]}, {"language": "english", "language_level": ["good"]}]}, "experience_required": {"duration": ["0-3 years"], "field": ["audit"]}}, {"job_id": "100003009053765", "location_code": "hk", "company": "WST CPA & Co.", "job_title": "Audit & Accounting Senior / Associate", "description": "\nCPA Firm\nKowloon Bay\nJob Description\n\u2022 2- 5 year experience\n\u2022 Good communication and interpersonal skills\n\u2022 Willing to work under pressure and tight schedule\n\u2022 Good command of both written and spoken in English and Chinese\n\u2022 Flexible working environment and work life balance\n\u2022 Excellent career promotion prospect\nCandidate with less experience(fresh graduate)will be considered as Trainee;\nResponsibilities\n\u2022 Participate in audit, accounting and tax assignments\n\u2022 Deliver professional and effective client management\n\u2022 Handle audit assignments independently;\n\u2022 Preparing tax computation and schedules for tax compliance;\n\u2022 Handle ad hoc matters assigned.\nRequirements\n\u2022 Tertiary education or above with major in accountancy or business related\n\u2022 Able to communicate effectively in English, Chinese and Putonghua\n\u2022 Proficient in MS Word and Excel\n\u2022 Proactive and good interpersonal skills\n\u2022 Independent with initiative\n\u2022 Responsible, stable, dedicated, initiative and self-motivated\nWe offer an attractive remuneration package, including performance bonus, medical scheme, examination leaves, bank holiday, 5-day work week, Training package, excellent career prospects in a warm and friendly working environment.\nInterest parties please send application letter with full resume and expected salary to Apply Now, fresh graduates are welcome.\n(Personal data collected will be used for recruitment purpose only.)\n\n", "employment_types": ["Full Time"], "selling_points": [], "locations": ["Kwun Tong"], "categories": ["Accounting", "Accounting Clerk / Supervisor", "Audit"], "post_time": "2022-01-17T07:29:06Z", "salary": {"currency": null, "max": null, "min": null, "period": "monthly", "term": null}, "salary_visible": false, "title_keywords": ["associate", "accounting"], "responsibilities": ["tax", "management", "ad hoc", "tax computation", "schedules", "compliance", "audit", "communication", "schedule", "work under pressure"], "requirements": {"degrees": [], "majors": [], "languages": ["putonghua", "english", "chinese"], "language_level": [], "hard_skills": ["excel", "scheme", "ms word"], "soft_skills": ["self-motivated", "independent", "responsible", "interpersonal skills", "friendly", "stable", "proactive", "initiative"], "languages_combined": [{"language": "putonghua", "language_level": []}, {"language": "english", "language_level": []}, {"language": "chinese", "language_level": []}]}, "experience_required": {"duration": [], "field": []}}, {"job_id": "100003009051675", "location_code": "hk", "company": "Hong Kong Great Wall CPA Limited", "job_title": "Audit Professionals - All Levels", "description": "Direct reporting to Manager\nManage day to day audit engagements\nPrepare audit schedules, financial statements and tax computation\nDevelop and maintain good working relationship with client personnel\n\nRequirements\n\n\nBachelor degree in Accounting, Finance or Business related disciplines (DSE graduates and candidates from non-degree tertiary also welcome to apply)\nMember or student member (HKICPA, ACCA, CPA Australia etc)\nAble to work independently and meet deadline\nGood interpersonal and communication skills\nGood command of spoken and written English and Chinese\nMature, self-motivated and good team player\n\n\u00a0Benefits\n\n\n\nFive-day work week\nOvertime compensation leave and meal reimbursement\nStudy and exam leave for recognized professional exams\nProfessional exam subsidy\nMedical and travelling expenses reimbursement\nBirthday leave\nFast-track promotion to talented candidates\nSalary is negotiable subject to years of experience\nDiscretionary bonus\nPlease send your resume by e-mail\u00a0\n\n\nData collected will be used for recruitment purpose only.", "employment_types": ["Full Time"], "selling_points": [], "locations": ["Wan Chai"], "categories": ["Accounting", "Accountant", "Audit", "Others"], "post_time": "2022-01-16T21:50:42Z", "salary": {"currency": null, "max": null, "min": null, "period": "monthly", "term": null}, "salary_visible": false, "title_keywords": [], "responsibilities": ["reporting", "tax computation", "schedules", "audit", "financial statements", "develop", "communication", "maintain"], "requirements": {"degrees": ["degree", "bachelor", "dse"], "majors": ["business", "finance", "related disciplines", "accounting"], "languages": ["english", "chinese"], "language_level": ["good command"], "hard_skills": ["cpa", "acca", "hkicpa"], "soft_skills": ["communication skills", "work independently", "self-motivated", "good team player", "mature", "interpersonal"], "languages_combined": [{"language": "english", "language_level": ["good command"]}, {"language": "chinese", "language_level": ["good command"]}]}, "experience_required": {"duration": [], "field": []}}, {"job_id": "100003009054453", "location_code": "hk", "company": "Jobslink Limited", "job_title": "Audit senior associate / Audit associate", "description": "Responsibilities:\n\n\u00a0\u00a0\u00a0\u00a0\u00a0\u00a0 Liaise with clients and colleagues for job coordination\n\u00a0\u00a0\u00a0\u00a0\u00a0\u00a0 Assist in planning, execution and delivery of assurance engagements\n\u00a0\u00a0\u00a0\u00a0\u00a0\u00a0 Handle the client enquiries in accounting, audit and taxation\n\u00a0 \u00a0 \u00a0 \u00a0Involve in\u00a0audit of internal controls over financial reporting and ad-hoc projects such as due diligence\u00a0reviews and merger and acquisition deal\n\nRequirements:\n\n\u00a0\u00a0\u00a0\u00a0\u00a0\u00a0 High Diploma or equivalent qualification in Accountancy\n\u00a0\u00a0\u00a0\u00a0\u00a0\u00a0 Minimum 2 years working experience in audit field / less experience will be consider as audit associate\n\u00a0\u00a0\u00a0\u00a0\u00a0\u00a0 Able to work independently and efficiently in multi-tasking\n\u00a0\u00a0\u00a0\u00a0\u00a0\u00a0 Able to meet deadlines and eager to accomplish higher goals\n\u00a0\u00a0\u00a0\u00a0\u00a0\u00a0 High level of independence and strong motivation\n\u00a0\u00a0\u00a0\u00a0\u00a0\u00a0 Effective problem-solving and interpersonal skills\n\u00a0 \u00a0 \u00a0 \u00a0Good command of written and spoken English, Cantonese and Mandarin\n\nCompetitive package:\n\n\u00a0\u00a0\u00a0\u00a0\u00a0\u00a0 5 day work week\n\u00a0\u00a0\u00a0\u00a0\u00a0\u00a0 paid examination & study leave.\n\u00a0\u00a0\u00a0\u00a0\u00a0\u00a0 In house and external training\nCompensation leave or compensation pay", "employment_types": ["Full Time"], "selling_points": ["Career development", "Work life balance", "Good remuneration"], "locations": ["Tsuen Wan Area"], "categories": ["Accounting", "Accountant", "Audit"], "post_time": "2022-01-17T09:36:19Z", "salary": {"currency": null, "max": null, "min": null, "period": "monthly", "term": null}, "salary_visible": false, "title_keywords": ["senior associate", "associate"], "responsibilities": ["liaise with clients", "taxation", "due diligence reviews", "audit", "financial reporting", "coordination", "ad-hoc projects", "planning"], "requirements": {"degrees": ["high diploma"], "majors": ["accountancy"], "languages": ["cantonese", "english", "mandarin"], "language_level": ["good command"], "hard_skills": ["problem-solving"], "soft_skills": ["work independently", "problem-solving", "multi-tasking", "interpersonal skills", "meet deadlines"], "languages_combined": [{"language": "cantonese", "language_level": ["good command"]}, {"language": "english", "language_level": ["good command"]}, {"language": "mandarin", "language_level": ["good command"]}]}, "experience_required": {"duration": ["minimum 2 years"], "field": ["audit"]}}, {"job_id": "100003009052718", "location_code": "hk", "company": "K. W. Tam & Co.", "job_title": "Junior / Semi-Senior / Senior - Audit Services", "description": "Highlights:\u00a0\n\n\u00a0 \u00a0* examination fee reimbursement, group medical plan\n\u00a0 \u00a0* study, exam, birthday, voluntary service leaves\n\nRequirements:\n\nDegree holder major in accountancy\nFresh graduate or with working experience gain in CPA firms\nComputer literacy and proficient with Windows applications\nMature, self-motivated, independent,\u00a0responsible and good communication skills\nGood command of written and spoken English and Chinese\u00a0\n\nWe offer 5-days work, attractive remuneration, various kinds of fringe benefits including annual leave, study leave, examination leave, birthday leave, voluntary service leave, examination fee reimbursement, medical insurance, bonus, etc. and good career development opportunities. We also encourage our staff to take professional examinations, technical\u00a0and managerial training to enhance their professional\u00a0and managerial knowledge.\n\nInterested parties please send your\u00a0full resume with date of availability, current and expected salaries\u00a0by clicking \"Apply Now\"\u00a0(Please mark the job title applied at the subject of the email).\n\n\nAll information provided by applicants will be used for recruitment related purposes only and will be treated in the strictest confidence by authorized personnel.", "employment_types": ["Full Time", "Permanent"], "selling_points": [], "locations": ["Ngau Tau Kok"], "categories": ["Accounting", "Accountant", "Audit", "Others", "Student / Fresh Graduate / No Experience"], "post_time": "2022-01-17T03:47:21Z", "salary": {"currency": null, "max": null, "min": null, "period": "monthly", "term": null}, "salary_visible": false, "title_keywords": ["junior"], "responsibilities": ["communication", "insurance", "plan", "career development"], "requirements": {"degrees": ["fresh graduate", "degree holder"], "majors": ["accountancy"], "languages": ["english", "chinese"], "language_level": ["good command"], "hard_skills": ["cpa"], "soft_skills": ["communication skills", "self-motivated", "independent", "responsible", "mature", "computer literacy"], "languages_combined": [{"language": "english", "language_level": ["good command"]}, {"language": "chinese", "language_level": ["good command"]}]}, "experience_required": {"duration": [], "field": []}}, {"job_id": "100003009054800", "location_code": "hk", "company": "Public Finance Limited", "job_title": "Audit Executive", "description": "Responsibilities\nTo be responsible for performing audit functions within the Company\nAny ad hoc audit assignments\n\u00a0Requirements\nDiploma in Accountancy, Finance or related disciplines\nNo relevant experience is required. Fresh graduates are also welcome\nGood communication and interpersonal skills\nCandidates with more experience will be considered as Audit Officer\nBenefits\nDouble Pay\nDiscretionary Bonus\nInsurance Benefits\nStudy Subsidy\nApplication Method:\n\nBy Whatsapp : 9309 2925\n\nBy E-mail via \"Apply Now\"\nPersonal data collected will be treated in the strictest confidence in accordance with our\u00a0Personal Information Collection Statement\u00a0and\u00a0Privacy Policy\u00a0and will be handled by authorized personnel for recruitment-related purposes only. All applications will be kept for a maximum period of one year as may be considered for other suitable positions within Public Finance Ltd. and its associated companies. For details, please visit the Company\u2019s website\u00a0http://www.publicfinance.com.hk", "employment_types": ["Full Time", "Permanent"], "selling_points": [], "locations": ["Not Specified"], "categories": ["Accounting", "Accounting Clerk / Supervisor", "Audit", "Others"], "post_time": "2022-01-17T11:08:55Z", "salary": {"currency": null, "max": null, "min": null, "period": "monthly", "term": null}, "salary_visible": false, "title_keywords": ["executive"], "responsibilities": ["ad hoc", "audit"], "requirements": {"degrees": ["diploma"], "majors": ["related disciplines", "finance", "accountancy"], "languages": [], "language_level": [], "hard_skills": ["no"], "soft_skills": ["communication and interpersonal skills"], "languages_combined": []}, "experience_required": {"duration": [], "field": ["relevant experience", "audit"]}}, {"job_id": "100003009053254", "location_code": "hk", "company": "APEC Group International Limited", "job_title": "Accountant Trainee/Associate (Financial Advisory Team)", "description": "Responsibilities\n\nAssist in handle assignments independently;\nInvolving in public offerings, listings, due diligence and private placements;\nAssist in analyze financial results of clients\u2019 companies;\nAssist in providing support to clients regarding different regulatory regimes, listing rules and related regulations;\nKeep up-to-date on regulatory developments;\nAssist in preparing business plans and IPO business proposals; Developing effective business relationships with clients;\nHandle ad hoc matters assigned.\n\nRequirements\n\nHigher Diploma\u00a0in accounting or related discipline.\nStudent member of HKICPA/ACCA/CPAA or other relevant professional bodies;\n0-1 year of accounting/audit experience in any field;\nSelf-motivated, willing to take job ownership, manage deadlines and able to work as a team player;\nProficient in MS Excel and word and knowledge of computerized accounting system is highly preferred;\nGood\u00a0analytical, interpersonal and communication skill is highly preferred;\nGood command in written and spoken English, Chinese and Mandarin;\nBusiness travel is required;\nFresh graduates are welcome;\nImmediate available is preferred.\n\nWhat we offered?\n\n5-day work week\nImportant festivals early leave\nOvertime meal allowance\nDiscretionary bonus\nFull-paid sick leave\nStudy & Exam leave\nGraduation leave\nWedding leave\nCompassionate leave\nMedical Insurance Scheme\nTraining reimbursement\nInterested parties please send your full resume with your\u00a0working experience, academic and professional qualification, expected salary, and date of availability\u00a0to HR Department.\nPersonal data collected will be used for recruitment purpose only.", "employment_types": ["Full Time", "Part Time", "Permanent", "Contract"], "selling_points": ["Fresh graduates are welcome", "5-day work week", "Excellent career promotion prospect"], "locations": ["Sheung Wan"], "categories": ["Accounting", "Accountant", "Audit", "Consulting"], "post_time": "2022-01-17T06:32:55Z", "salary": {"currency": null, "max": null, "min": null, "period": "monthly", "term": null}, "salary_visible": false, "title_keywords": ["associate", "accountant", "trainee"], "responsibilities": ["regulations", "due diligence", "ad hoc", "developing", "providing support", "preparing business plans", "listing"], "requirements": {"degrees": ["diploma"], "majors": ["accounting"], "languages": ["english", "chinese", "mandarin"], "language_level": ["good command"], "hard_skills": ["acca", "word", "ms excel", "accounting system", "hkicpa"], "soft_skills": ["self-motivated", "communication skill", "interpersonal", "work as a team"], "languages_combined": [{"language": "english", "language_level": ["good command"]}, {"language": "chinese", "language_level": ["good command"]}, {"language": "mandarin", "language_level": ["good command"]}]}, "experience_required": {"duration": ["0-1 year"], "field": ["audit experience", "accounting"]}}, {"job_id": "100003009053711", "location_code": "hk", "company": "BDO", "job_title": "(Part Time / Contract / Temporary) Senior Associate / Associate - Assurance (Ref : AUD / JDB)", "description": "Responsibilities:\n\nProvide support in audit engagements\nSupport and act towards the BDO Global Vision\nBe committed to act with the firm\u2019s core values and competency expectations\n\nRequirements:\n\nA good and effective team player\nExcellent command of both written and spoken English and Chinese; including Mandarin\nBe passionate for providing exceptional quality service and striving for exceeding clients\u2019 expectations\n\nWe are an equal opportunity employer, and offer excellent prospects and career development for the right candidate.\u00a0 Interested parties please send your application with full career history, current and expected salary by clicking\u00a0Apply Now\u00a0button below.\n\nApplications will be treated in strict confidence. Personal data collected will be used for recruitment purposes only.", "employment_types": ["Part Time", "Temporary", "Contract"], "selling_points": ["Provide support in audit engagement", "Part Time / Temporary", "A good and effective team player"], "locations": ["Sheung Wan"], "categories": ["Accounting", "Audit"], "post_time": "2022-01-17T07:23:32Z", "salary": {"currency": null, "max": null, "min": null, "period": "monthly", "term": null}, "salary_visible": false, "title_keywords": ["senior associate", "associate"], "responsibilities": ["provide support", "audit"], "requirements": {"degrees": [], "majors": [], "languages": ["english", "chinese", "mandarin"], "language_level": ["excellent"], "hard_skills": [], "soft_skills": ["passionate", "team player"], "languages_combined": [{"language": "english", "language_level": ["excellent"]}, {"language": "chinese", "language_level": ["excellent"]}, {"language": "mandarin", "language_level": []}]}, "experience_required": {"duration": [], "field": []}}, {"job_id": "100003009053770", "location_code": "hk", "company": "WST CPA & Co.", "job_title": "AUDIT Trainee / AUDIT JUNIOR", "description": "\nCPA Firm\nKowloon Bay\nJob Description\n\u2022 0 - 1 year experience\n\u2022 Good communication and interpersonal skills\n\u2022 Willing to work under pressure and tight schedule\n\u2022 Fluent in both written and spoken English, Cantonese and Mandarin\n\u2022 Flexible working environment\n\u2022 Excellent career promotion prospect\nCandidate with less experience(fresh graduate)will be considered as Trainee;\nResponsibilities\n\u2022 Participate in audit, accounting and tax assignments\n\u2022 Deliver professional and effective client management\n\u2022 Handle audit assignments independently;\n\u2022 Preparing tax computation and schedules for tax compliance;\n\u2022 Handle ad hoc matters assigned.\nRequirements\n\u2022 Tertiary education or above with major in accountancy or business related\n\u2022 Able to communicate effectively in English, Chinese and Putonghua\n\u2022 Proficient in MS Word and Excel\n\u2022 Proactive and good interpersonal skills\n\u2022 Independent with initiative\n\u2022 Responsible, stable, dedicated, initiative and self-motivated\u00a0\u00a0\nWe offer an attractive remuneration package, including performance bonus, medical scheme, examination leaves, bank holiday, 5-day work week, Training package, excellent career prospects in a warm and friendly working environment.\nInterest parties please send application letter with full resume and expected salary to Apply Now, fresh graduates are welcome.\n(Personal data collected will be used for recruitment purpose only.)\n\n", "employment_types": ["Full Time"], "selling_points": [], "locations": ["Kwun Tong"], "categories": ["Accounting", "Accounting Clerk / Supervisor", "Audit"], "post_time": "2022-01-17T07:29:40Z", "salary": {"currency": null, "max": null, "min": null, "period": "monthly", "term": null}, "salary_visible": false, "title_keywords": ["trainee", "junior"], "responsibilities": ["tax", "management", "ad hoc", "tax computation", "schedules", "compliance", "audit", "communication", "schedule", "work under pressure"], "requirements": {"degrees": [], "majors": [], "languages": ["putonghua", "english", "chinese"], "language_level": [], "hard_skills": ["excel", "scheme", "ms word"], "soft_skills": ["self-motivated", "independent", "responsible", "interpersonal skills", "friendly", "stable", "proactive", "initiative"], "languages_combined": [{"language": "putonghua", "language_level": []}, {"language": "english", "language_level": []}, {"language": "chinese", "language_level": []}]}, "experience_required": {"duration": [], "field": []}}, {"job_id": "100003009047949", "location_code": "hk", "company": "C. K. Lo & Company Certified Public Accountants", "job_title": "Audit senior / semi-senior / junior", "description": "Audit senior / semi-senior / junior\n\nDegree holder major in accountancy or related field;\nStudent member / member of HKICPA or other professional bodies;\nApplicants with\u00a0no or\u00a0less experience\u00a0are\u00a0considered as Audit\u00a0Junior;\nHardworking, analytical and detail oriented;\nWilling to learn with positive working attitude;\nGood interpersonal and communication skills;\nStrong PC skills & proficiency in MS Word, Excel and Chinese word processing; and\nGood command of English, Chinese and Mandarin\n\nOffer competitive salary to suitable candidate.\u00a0\n\n\nWe offer 5-days work, medical allowance, study and exam leaves, good working condition and valuable experience. Travel is RARELY required.\n\nApply Method:\n\nInterested parties please email your full resume with current and expected salary to us.\n\n\n(data collected used for recruitment purpose only)", "employment_types": ["Full Time", "Permanent"], "selling_points": [], "locations": ["Tsim Sha Tsui"], "categories": ["Accounting", "Accountant", "Audit", "Taxation"], "post_time": "2022-01-15T03:49:02Z", "salary": {"currency": null, "max": null, "min": null, "period": "monthly", "term": null}, "salary_visible": false, "title_keywords": ["junior"], "responsibilities": ["communication", "audit"], "requirements": {"degrees": ["degree holder"], "majors": ["accountancy"], "languages": ["english", "chinese", "mandarin"], "language_level": ["proficiency", "good command"], "hard_skills": ["excel", "no", "chinese word processing", "hkicpa", "pc skills", "ms word"], "soft_skills": ["communication skills", "detail oriented", "willing to learn", "positive working attitude", "interpersonal", "hardworking"], "languages_combined": [{"language": "english", "language_level": ["good command"]}, {"language": "chinese", "language_level": ["proficiency", "good command"]}, {"language": "mandarin", "language_level": ["good command"]}]}, "experience_required": {"duration": [], "field": ["audit"]}}, {"job_id": "100003009052866", "location_code": "hk", "company": "Union Link CPA Limited", "job_title": "Audit Supervisor/ Senior/ Semi-Senior", "description": "At least 3 year's audit experience\nMember/ Finalist of HKICPA/ACCA preferable\nGood organizational skills with the ability to handle multi-tasks and meet deadlines\nA high degree of independence, motivation and technical ability\nCandidate with less experience will be considered as Audit Semi-Senior\nWe offer the right candidates with a competitive remuneration package including study & examination leaves, birthday leave, 12-14 annual leaves, casual Friday and performance bonus.\n\n\nThe salary offered will commensurate with the experience and qualifications of the right candidates. Please send your full resume with expected salary to us by clicking \"APPLY NOW\".", "employment_types": ["Full Time", "Permanent"], "selling_points": ["Work/ Life balance", "NO OT culture/ No overseas travelling", "5-day work (9:30 am to 6:00 pm)"], "locations": ["Wan Chai"], "categories": ["Accounting", "Audit", "Taxation"], "post_time": "2022-01-17T06:33:11Z", "salary": {"currency": null, "max": null, "min": null, "period": "monthly", "term": null}, "salary_visible": false, "title_keywords": ["audit supervisor"], "responsibilities": ["audit"], "requirements": {"degrees": ["degree"], "majors": [], "languages": [], "language_level": [], "hard_skills": ["acca", "hkicpa"], "soft_skills": ["organizational skills", "meet deadlines", "multi-tasks"], "languages_combined": []}, "experience_required": {"duration": ["at least 3 year"], "field": ["audit experience", "audit"]}}, {"job_id": "100003009051476", "location_code": "hk", "company": "BDO", "job_title": "Senior Associate / Associate \u2013 Assurance (Fund Audit)", "description": "Responsibilities:\n\nResponsible for the planning and execution of audit fieldwork and completing the assigned tasks accordance with the audit plan and our firm's procedures\nSupport and act towards the BDO Global Vision\nBe committed to act with the firm\u2019s core values and competency expectations\n\nRequirements:\n\nDegree holder, major in accounting or\u00a0other\u00a0related disciplines\nAt least 1 year of relevant experience in assurance gained with sizable accounting firm. Experience in Fund Industry is highly preferable.\nQualified accountant is preferred\nA good and effective team player\nExcellent command of both written and spoken English and Chinese; including Mandarin\nBe passionate for providing exceptional quality service and striving for exceeding clients\u2019 expectations\nPosition offered will commensurate with the experience of the right candidate\n\nWe are an equal opportunity employer, and offer excellent prospects and career development for the right candidate.\u00a0 Interested parties please send your application with full career history, current and expected salary by clicking\u00a0Apply Now\u00a0button below.\n\nApplications will be treated in strict confidence. Personal data collected will be used for recruitment purposes only.", "employment_types": ["Full Time", "Permanent"], "selling_points": ["At least 1 year of relevant experience", "Qualified accountants are preferred", "Excellent Career Prospects"], "locations": ["Sheung Wan"], "categories": ["Accounting", "Audit", "Banking / Finance", "Fund Management"], "post_time": "2022-01-16T03:48:55Z", "salary": {"currency": null, "max": null, "min": null, "period": "monthly", "term": null}, "salary_visible": false, "title_keywords": ["senior associate", "associate"], "responsibilities": ["procedures", "audit", "plan", "planning"], "requirements": {"degrees": ["degree holder"], "majors": ["related disciplines", "accounting"], "languages": ["english", "chinese", "mandarin"], "language_level": ["excellent"], "hard_skills": [], "soft_skills": ["passionate", "team player"], "languages_combined": [{"language": "english", "language_level": ["excellent"]}, {"language": "chinese", "language_level": ["excellent"]}, {"language": "mandarin", "language_level": []}]}, "experience_required": {"duration": ["at least 1 year"], "field": ["assurance", "accounting", "relevant experience"]}}, {"job_id": "100003009047650", "location_code": "hk", "company": "Moore Associates Limited", "job_title": "Audit Staff \u2013 Associates/Senior Associates", "description": "Responsibilities:\n\nWork on audit assignments for clients from a variety of industries, covering Hong Kong and China\nInvolve in\u00a0audit of internal controls over financial reporting and ad-hoc projects such as due\u00a0diligence reviews, IPO exercises and merger and acquisition deals\nAssist in\u00a0planning, execution and delivery of assurance engagements\n\n\nRequirements:\u00a0\u00a0\n\nDegree holder majoring in Accountancy / Finance\nFresh graduates and candidates with practical audit experience will be considered, preferably gained with another international accounting network\nGood written and spoken English and Chinese\nGood communication / interpersonal skills\nHigh level of independence and strong motivation\nStrong technical ability and keen to\u00a0develop\u00a0a career in the audit profession\n\nCompetitive package will be offered to the right candidate(s), including 5 day work week, paid examination & study leave,\u00a0reimbursement for examination fees,\u00a0subsidy of examination revision course fees, birthday leave & medical insurance coverage. Interested parties please send full resume with working experience, academic and professional qualifications, including present & expected salary by clicking the \"Apply Now\" button.\u00a0 Personal data collected will be used for recruitment purposes only.\n\nSimply click the \u201cApply Now\u201d button\n\nPlease visit our website at\u00a0www.moore.hk\u00a0to know more about us.", "employment_types": ["Full Time", "Permanent"], "selling_points": ["Apart from working on audit assignments", "Degree holder, majoring in accountancy/finance", "Fresh graduates will also be considered"], "locations": ["Tsim Sha Tsui"], "categories": ["Accounting", "Accountant", "Audit", "Others"], "post_time": "2022-01-15T03:49:47Z", "salary": {"currency": null, "max": null, "min": null, "period": "monthly", "term": null}, "salary_visible": false, "title_keywords": ["audit staff"], "responsibilities": ["due diligence reviews", "audit", "financial reporting", "ad-hoc projects", "planning"], "requirements": {"degrees": ["degree holder"], "majors": ["finance", "accountancy"], "languages": ["english", "chinese"], "language_level": ["good"], "hard_skills": [], "soft_skills": ["communication", "keen", "interpersonal skills"], "languages_combined": [{"language": "english", "language_level": ["good"]}, {"language": "chinese", "language_level": ["good"]}]}, "experience_required": {"duration": [], "field": ["audit experience", "accounting"]}}, {"job_id": "100003008990729", "location_code": "hk", "company": "HLB Hodgson Impey Cheng Limited", "job_title": "Audit Accountant I/ Audit Accountant II", "description": "Requirements\n\nBachelor degree holder (Major in Accounting is preferred)\nGood command of both written and spoken in English and Chinese\nFresh graduates will also be considered\n\nWe offer 5 days work. Interested parties please send your resume with expected salary and availability to the\u00a0Human Resources Department\u00a0(AAD 1), HLB Hodgson Impey Cheng Limited, 31/F Gloucester Tower, The Landmark, 11 Pedder Street, Central, Hong Kong or via email to AHon\uff20hic.com.hk\n\nPersonal data collected will be used for recruitment purposes only.", "employment_types": ["Full Time", "Permanent"], "selling_points": ["5-days work, Medical insurance, Exam/ Study Leave", "Degree holder (Fresh Graduates also welcome)", "Opportunity to gain audit experience in listed co."], "locations": ["Central & Western Area"], "categories": ["Accounting", "Accountant", "Audit", "Others"], "post_time": "2022-01-16T21:50:06Z", "salary": {"currency": null, "max": null, "min": null, "period": "monthly", "term": null}, "salary_visible": false, "title_keywords": ["accountant"], "responsibilities": [], "requirements": {"degrees": ["bachelor degree holder"], "majors": ["accounting"], "languages": ["english", "chinese"], "language_level": ["good command"], "hard_skills": [], "soft_skills": [], "languages_combined": [{"language": "english", "language_level": ["good command"]}, {"language": "chinese", "language_level": ["good command"]}]}, "experience_required": {"duration": [], "field": []}}, {"job_id": "100003009053134", "location_code": "hk", "company": "Vision A. S. Limited", "job_title": "ASSISTANT ACCOUNTANT (ACCOUNTS DEPT) & AUDIT ASSISTANT, SEMI-SENIOR, SENIOR", "description": "Requirements:\n\nDegree holder/ IVE graduate in Accountancy\n\nHKICPA/ ACCA/ HKAAT student member or equivalent\nExperience is preferred but not essential. Fresh Graduate is also considered\nCandidate who with good book-keeping/audit experience will be considered as Accountant, Semi-Senior or Senior\nGood command in written and spoken English, Cantonese and Mandarin\nProficient in MS Word and Excel\nIndependently and reliable capability\nImmediate available is preferred\n\n\n\nWe offer 5 days work per week (Mon to Fri : 9:30 am - 6:00 pm), study & examination leave, performance bonus and attractive remuneration package to the right candidate.\n\nInterested candidates please send your full resume with present and expected salary by clicking \"Apply Now\"\n\n\nPersonal data collected will be used for recruitment purpose only.\n\n", "employment_types": ["Full Time", "Permanent"], "selling_points": ["Degree holder/ IVE graduate in Accountancy", "HKICPA/ ACCA/ HKAAT student member or equivalent", "5 days work per week Mon to Fri : 9:30 am-6:00 pm"], "locations": ["Wan Chai"], "categories": ["Accounting", "Audit", "Others"], "post_time": "2022-01-17T06:02:55Z", "salary": {"currency": null, "max": null, "min": null, "period": "monthly", "term": null}, "salary_visible": false, "title_keywords": ["assistant accountant", "assistant"], "responsibilities": ["book-keeping", "audit"], "requirements": {"degrees": ["fresh graduate", "degree holder"], "majors": ["accountancy"], "languages": ["cantonese", "english", "mandarin"], "language_level": ["good command"], "hard_skills": ["ms word", "excel", "acca", "hkicpa"], "soft_skills": ["independently", "reliable"], "languages_combined": [{"language": "cantonese", "language_level": ["good command"]}, {"language": "english", "language_level": ["good command"]}, {"language": "mandarin", "language_level": ["good command"]}]}, "experience_required": {"duration": [], "field": ["audit experience"]}}, {"job_id": "100003009054469", "location_code": "hk", "company": "Honor Information Technology Co., Limited", "job_title": "Treasury & Auditors - HK Finance dept.", "description": "Position Description:\n\nResponsible for the Hong Kong subsidiary's capital plan and budget forecast, to ensure the safety of the treasury, and timely feedback the capital budget forecast to the headquarters cash team;\nResponsible for financial support\uff1b\nResponsible for the Hong Kong subsidiary's budget review and budget model optimization, and formulate the FX control plan;\nResponsible for local accounting and audit support\u3002\n\nWork Experience Requirements:\n\nBachelor degree or above in accounting/finance/business or other related majors\nHands on experience and proven track record of cash and liquidity management\nExcellent analytical, interpersonal and presentation skills\nGood command of English/mandarin and communication skills\nGood problem solving capability, and coordination skills\nHave a thorough understanding of derivatives, hedging, investments, bank account management, and international funds flows.\nStrong local bank relationships\n\nPersonal Characteristics:\n\nGood communication skills, able to work under pressure.\n\nAdditional Information:\n\n\u00a0\u00a0\u00a0\u00a0\u00a0\u00a0\u00a0 Monday to Friday-office hour\n\u00a0\u00a0\u00a0\u00a0\u00a0\u00a0\u00a0 Work location: Tsim Sha Tsui\n\u00a0\u00a0\u00a0\u00a0\u00a0\u00a0\u00a0 Medical Insurance\n\u00a0\u00a0\u00a0\u00a0\u00a0\u00a0\u00a0 We offer attractive remuneration package and excellent career opportunities to the right candidates. Interested parties please send your full resume with available, current and expected salary to The Human Resources Department, Honor Information Technology Co., Limited\nExcellent conditions, salary can be negotiated face to face", "employment_types": ["Full Time", "Permanent"], "selling_points": ["Opportunity for career progression", "International exposure", "Stable working environment"], "locations": ["Tsim Sha Tsui"], "categories": ["Accounting", "Audit", "Treasurer"], "post_time": "2022-01-17T09:40:58Z", "salary": {"currency": null, "max": null, "min": null, "period": "monthly", "term": null}, "salary_visible": false, "title_keywords": [], "responsibilities": ["control", "management", "review", "budget", "audit", "communication", "forecast", "plan", "coordination", "work under pressure"], "requirements": {"degrees": ["degree or above", "bachelor"], "majors": ["business", "finance", "accounting"], "languages": ["english", "mandarin"], "language_level": ["good command"], "hard_skills": ["problem solving"], "soft_skills": ["communication skills", "coordination skills", "responsible", "timely", "problem solving", "presentation skills", "hands on", "thorough", "interpersonal", "work under pressure"], "languages_combined": [{"language": "english", "language_level": ["good command"]}, {"language": "mandarin", "language_level": ["good command"]}]}, "experience_required": {"duration": [], "field": ["management"]}}, {"job_id": "100003009045712", "location_code": "hk", "company": "Crowe (HK) CPA Limited", "job_title": "Junior / Senior Associates - Audit & Assurance", "description": "Requirements:\n\nTertiary education in related disciplines\n1 year audit experience; candidates with more experience will be considered as Senior Associate\nProficiency in English and Chinese (Cantonese and Putonghua)\nCandidates who are interested in audit field with degree holder in other majors / disciplines are also welcome to apply\nSalary will be commensurate with qualification and experience.\u00a0 We offer generous compensation and\u00a0 benefits to the right candidates, including bonus scheme, medical and life insurance, 5-day work week, study & examination leave and birthday leave.\nPlease apply with resume giving full personal particulars, employment history, present and expected salary together with contact telephone number by clicking \"Apply Now\" or by post to: Human Resources Department, Crowe (HK) CPA Limited, 9/F., Leighton Centre, 77 Leighton Road, Causeway Bay, Hong Kong.\nPersonal data provided by job applicants will be used strictly in accordance with employer's personal data policies.\u00a0 A copy of which will be provided immediately upon request.", "employment_types": ["Full Time", "Permanent"], "selling_points": ["5-day work week; Study & Exam Leave", "Competitive package with Bonus Scheme", "Promising career prospects / Fast promotion path"], "locations": ["Causeway Bay"], "categories": ["Accounting", "Accountant", "Audit", "Professional Services", "Business Consultancy"], "post_time": "2022-01-13T10:48:09Z", "salary": {"currency": null, "max": null, "min": null, "period": "monthly", "term": null}, "salary_visible": false, "title_keywords": ["junior"], "responsibilities": ["policies", "audit", "contact", "personal data", "insurance"], "requirements": {"degrees": ["degree holder"], "majors": [], "languages": ["cantonese", "putonghua", "english", "chinese"], "language_level": ["proficiency"], "hard_skills": ["cpa", "scheme"], "soft_skills": ["interested in"], "languages_combined": [{"language": "cantonese", "language_level": []}, {"language": "putonghua", "language_level": []}, {"language": "english", "language_level": ["proficiency"]}, {"language": "chinese", "language_level": ["proficiency"]}]}, "experience_required": {"duration": ["1 year"], "field": ["audit experience"]}}, {"job_id": "100003009035204", "location_code": "hk", "company": "CBD", "job_title": "Auditor all grades (Work life balance and 5 days work with high pay)", "description": "We are hiring the below posts for CBD CPA LIMITED, an CPA firm in Kwun Tong, a worldwide network of independent accounting firms and business advisers. We invite a suitable candidate to fill the following vacancy :-\n\n\nAudit Junior / Semi Senior / Senior / Supervisor / Manager\n\nThe candidate will be in charge of completing various assignments either independently or as a team while reporting to his/her manager in areas such as audit, accountancy and tax compliance including but not limited to the preparation of financial statements, filing of profits and personal tax returns, and responding to IRD enquiries.\n\n\u00a0Requirements:\n\nDegree/Diploma in Accounting or related discipline\n1-5 years working experience in audit field (Fresh graduate is also welcome)\n\nAble to work under pressure and meet deadlines\nAble to work independently\nGood communication in English and Mandarin\nKnowledge of accounting software (especially \u201cQUICKBOOK\u201d) will be advantageous\nProficiency in MS Word, Excel and Chinese Word Processing\nBe proactive by taking initiative and work as a team\nExcellent analytical, interpersonal and communication skills\nBenefits:\n12 days annual leave\n\nBirthday leave, study leave and exam leave\nOT compensation and Medical claim\nWork-Life Balance\nCaring Company and CBD Working location\nFlexible working arrangement\n\nWe offer an attractive remuneration package, excellent career prospect in a warm and friendly atmosphere. Our continuing expansion and growth offer more promotion opportunities.\n\nApplication with personal resume and expected salary should be sent to Ray Wong, Principal of CBD CPA Limited.\n\nPersonal data collected will be used for recruitment purpose only.", "employment_types": ["Full Time", "Permanent"], "selling_points": ["Audit Junior semi senior supervisor", "Salary HK$15K or above, 5 days work", "Warm and friendly atmosphere"], "locations": ["Ngau Tau Kok"], "categories": ["Accounting", "Accountant", "Accounting Clerk / Supervisor", "Audit"], "post_time": "2022-01-16T21:50:10Z", "salary": {"currency": null, "max": null, "min": null, "period": "monthly", "term": null}, "salary_visible": false, "title_keywords": [], "responsibilities": ["tax", "reporting", "software", "compliance", "audit", "financial statements", "communication", "work under pressure"], "requirements": {"degrees": ["diploma", "degree", "fresh graduate"], "majors": ["accounting"], "languages": ["english", "chinese", "mandarin"], "language_level": ["proficiency", "good"], "hard_skills": ["excel", "chinese word processing", "accounting software", "cpa", "ms word"], "soft_skills": ["communication skills", "work independently", "independently", "independent", "work as a team", "interpersonal", "communication", "meet deadlines", "proactive", "initiative", "work under pressure"], "languages_combined": [{"language": "english", "language_level": ["good"]}, {"language": "chinese", "language_level": ["proficiency"]}, {"language": "mandarin", "language_level": ["good"]}]}, "experience_required": {"duration": ["1-5 years"], "field": ["audit"]}}, {"job_id": "100003009052393", "location_code": "hk", "company": "Chinastar Services Limited", "job_title": "Assistant Audit Manager/ Audit Manager", "description": "- Be professional, meticulous with exposure to serve foreign clients\n- Can work independently\n- Previous working experience in CPA firm preferred\u00a0\n- Excellent career path to be a partner\n- Flexible working hours and work at home arrangement", "employment_types": ["Permanent"], "selling_points": ["Excellent career path", "Double pay and year end bonus", "5 days work with flexible working hours"], "locations": ["Not Specified"], "categories": ["Accounting", "Audit"], "post_time": "2022-01-17T02:56:10Z", "salary": {"currency": null, "max": null, "min": null, "period": "monthly", "term": null}, "salary_visible": false, "title_keywords": ["manager", "assistant"], "responsibilities": [], "requirements": {"degrees": [], "majors": [], "languages": [], "language_level": [], "hard_skills": ["cpa"], "soft_skills": ["flexible", "meticulous", "work independently"], "languages_combined": []}, "experience_required": {"duration": [], "field": ["cpa firm"]}}, {"job_id": "100003009051474", "location_code": "hk", "company": "BDO", "job_title": "Audit Senior Associate (Ref : AUD / JDB)", "description": "Responsibilities:\n\nResponsible for the planning and execution of audit fieldwork and completing the assigned tasks accordance with the audit plan and our firm's procedures\nSupport and act towards the BDO Global Vision\nBe committed to act with the firm\u2019s core values and competency expectations\n\nRequirements:\n\nDegree holder, major in accounting or\u00a0other\u00a0related disciplines\nAt least 2 year of relevant experience in assurance, gained with sizable accounting firm\nQualified accountant is preferred but not a pre-requisite\n\nA good and effective team player\nExcellent command of both written and spoken English and Chinese; including Mandarin\nBe passionate for providing exceptional quality service and striving for exceeding clients\u2019 expectations\n\nWe are an equal opportunity employer, and offer excellent prospects and career development for the right candidate.\u00a0 Interested parties please send your application with full career history, current and expected salary by clicking\u00a0Apply Now\u00a0button below.\n\nApplications will be treated in strict confidence. Personal data collected will be used for recruitment purposes only.", "employment_types": ["Full Time", "Permanent"], "selling_points": ["At least 2 years of relevant experience", "Qualified accountants are preferred", "Excellent Career Prospects"], "locations": ["Sheung Wan"], "categories": ["Accounting", "Audit"], "post_time": "2022-01-16T03:47:59Z", "salary": {"currency": null, "max": null, "min": null, "period": "monthly", "term": null}, "salary_visible": false, "title_keywords": ["senior associate"], "responsibilities": ["procedures", "audit", "plan", "planning"], "requirements": {"degrees": ["degree holder"], "majors": ["related disciplines", "accounting"], "languages": ["english", "chinese", "mandarin"], "language_level": ["excellent"], "hard_skills": [], "soft_skills": ["passionate", "team player"], "languages_combined": [{"language": "english", "language_level": ["excellent"]}, {"language": "chinese", "language_level": ["excellent"]}, {"language": "mandarin", "language_level": []}]}, "experience_required": {"duration": ["at least 2 year"], "field": ["assurance", "accounting", "relevant experience"]}}, {"job_id": "100003009054600", "location_code": "hk", "company": "Procon CPA Limited", "job_title": "Junior/Senior Audit Officer(5-day work week)($17000-24000)", "description": "\u00a0Job responsibilities:\u00a0\n\nYou will be assigned to one of our audit teams of 3 \u2013 6 professionals stationing in Hong Kong.\nOur audit practice follows the standard APM issued by HKICPA.\nBook keeping accounting engagements are performed by separate accounting teams, not audit teams.\u00a0\n\nJob requirements:\u00a0\n\nGood command of written and oral English and Chinese\nProficiency in accounting double-entry system.\u00a0 Working experience in book keeping is not required.\nData processing and basic analysis in MS Excel\u00a0\n\nOur offers:\u00a0\n\nCompetitive package to attract talents starting from HK$17,000 \u2013 HK$24,000 per month\nOvertime work is not encouraged but, if incurred, will be compensated.\n5-day working week\nQP bonus of HK$3,000 per month\nAnnual leave: 12 days \u2013 14 days\nPaid exam leaves and study leaves for professional exams\nBirthday leave\nHardship allowance for working outside Hong Kong\nAnnual 3-day training camp in offsite hotel\u00a0\nFresh graduates are welcome\nShort-term contract staff will also be considered\n\nInterested parties can apply with detailed resume,\u00a0date of availability and expected salary\u00a0by email to Ms. Fanny Chau\n", "employment_types": ["Full Time", "Contract"], "selling_points": [], "locations": ["Lai Chi Kok"], "categories": ["Accounting", "Accountant", "Audit", "Taxation"], "post_time": "2022-01-17T10:12:11Z", "salary": {"currency": null, "max": null, "min": null, "period": "monthly", "term": null}, "salary_visible": false, "title_keywords": ["junior"], "responsibilities": ["teams", "audit"], "requirements": {"degrees": [], "majors": [], "languages": ["english", "chinese"], "language_level": ["good command"], "hard_skills": ["analysis", "processing", "basic", "ms excel"], "soft_skills": ["overtime work", "oral"], "languages_combined": [{"language": "english", "language_level": ["good command"]}, {"language": "chinese", "language_level": ["good command"]}]}, "experience_required": {"duration": [], "field": []}}, {"job_id": "100003009054121", "location_code": "hk", "company": "Vincent W M Lai & Co", "job_title": "Audit Junior / Intermediate (5-days work)", "description": "Requirements\n\nIVE / Diploma / Associate Degree / Degree holder in Accountancy\n1 year relevant\u00a0working experience in auditing / taxation / accounting\nCandidate with solid experience will be offered as Intermediate\nGood command of written English\nGood command of PC knowledge and MS Office\nHardworking, self-motivated and able to\u00a0work independently\n\nBenefits\n\n5-days week and medical claim\nProfessional training will be provided\nOffer Study & Exam Leaves for recognized professional exam\nOvertime pay\n\nInterested parties please email your full resume with expected salary by clicking \"Apply Now\"\u00a0 of Vincent W M Lai & Co.\n\nPersonal data collected will be used for recruitment purposes only", "employment_types": ["Full Time", "Permanent"], "selling_points": [], "locations": ["Central"], "categories": ["Accounting", "Accountant", "Audit", "Taxation"], "post_time": "2022-01-17T08:28:24Z", "salary": {"currency": null, "max": null, "min": null, "period": "monthly", "term": null}, "salary_visible": false, "title_keywords": ["junior"], "responsibilities": ["taxation", "auditing"], "requirements": {"degrees": ["associate degree", "diploma", "degree holder"], "majors": ["accountancy"], "languages": ["english"], "language_level": ["good command"], "hard_skills": ["pc knowledge", "ms office"], "soft_skills": ["self-motivated", "work independently", "hardworking"], "languages_combined": [{"language": "english", "language_level": ["good command"]}]}, "experience_required": {"duration": ["1 year"], "field": ["accounting", "relevant working experience"]}}, {"job_id": "100003009052880", "location_code": "hk", "company": "YCA Partners CPA Limited", "job_title": "Audit Staff (Junior / Senior) - 5 day work", "description": "Requirements:\n\nDiploma / Degree holder with major in accounting, finance or business related disciplines;\n0-3 year(s) relevant working experience, fresh graduate is welcome;\nGood command in spoken and written English, Cantonese and Putonghua; and\nInitiative, hardworking and able to work under pressure;\n\nBenefits\n\nFive-day work week\nFlexible working hours\nDiscretionary bonus\nBirthday leave\nMedical allowance\u00a0\nExamination leave\nStudy leave\nOvertime compensation leave\n\nCompetitive package will be offered to the right candidate(s), including 5-day work, annual discretionary bonuses, training, examination and study leaves. Interested parties please send in full resume with current & expected salary to our HR Department via \"Apply Now\".\n\nPlease visit\u00a0www.yca.com.hk\u00a0for more information.\n\nPersonal data will be used for recruitment purpose only.", "employment_types": ["Full Time"], "selling_points": ["Five-day work week / Flexible working hours", "Discretionary bonus / Medical allowance", "Birthday leave / Examination leave / Study leave"], "locations": ["Kwun Tong"], "categories": ["Accounting", "Accountant", "Audit", "Others"], "post_time": "2022-01-17T04:24:02Z", "salary": {"currency": null, "max": null, "min": null, "period": "monthly", "term": null}, "salary_visible": false, "title_keywords": ["audit staff", "junior"], "responsibilities": ["work under pressure"], "requirements": {"degrees": ["diploma", "fresh graduate", "degree holder"], "majors": ["business", "finance", "related disciplines", "accounting"], "languages": ["cantonese", "putonghua", "english"], "language_level": ["good command"], "hard_skills": [], "soft_skills": ["initiative", "hardworking", "work under pressure"], "languages_combined": [{"language": "cantonese", "language_level": ["good command"]}, {"language": "putonghua", "language_level": ["good command"]}, {"language": "english", "language_level": ["good command"]}]}, "experience_required": {"duration": [], "field": ["relevant working experience"]}}, {"job_id": "100003009053014", "location_code": "hk", "company": "Lui & Mak CPA Limited", "job_title": "AUDIT ASSOCIATE (All Level) (15-28K) (Fresh Graduates are Welcome)", "description": "Audit Associate\u00a0(15-28K)\n(Authorised Employer of HKICPA)\n\n\u00a0Requirements\u00a0\n\nHigher Diploma / Associate Degree / Degree holder\nComputer literacy and proficient in MS Word and Excel\nInitiative, independent, responsible and hard-working\nGood communication skills in both spoken and written English & Cantonese\nFresh graduate will also be considered\nImmediate available would be an absolute advantage\nFor Senior Level Audit Associate, at least 4 years in CPA firm with experience in handling technical updates (including Financial Reporting Standard, Auditing Standard, Companies Ordinance etc.)\n\n\u00a0Responsibilities\u00a0\n\nResponsible for completing statutory audit assignments of clients\u00a0\nAssist in tax planning and tax-related assignments\nLiaison with clients and colleagues for job coordination\nHandle ad hoc tasks as assigned\n\n\u00a0Interested parties please send full resume (with present & expected salary and availability) to Human Resource Department at Rooms 604-7, Dominion Centre, 43-59 Queen's Road East, Wanchai, Hong Kong or email to \u00a0recruit\uff20luimak.com.hk\u00a0or by clicking below Apply Now.\n\n*Personal data collected will be used for recruitment purposes only.", "employment_types": ["Full Time", "Permanent"], "selling_points": [], "locations": ["Wan Chai"], "categories": ["Accounting", "Audit"], "post_time": "2022-01-17T05:04:06Z", "salary": {"currency": null, "max": null, "min": null, "period": "monthly", "term": null}, "salary_visible": false, "title_keywords": ["associate"], "responsibilities": ["tax", "ad hoc tasks", "audit", "coordination", "planning"], "requirements": {"degrees": ["associate degree", "diploma", "fresh graduate", "degree holder"], "majors": [], "languages": ["cantonese", "english"], "language_level": ["good"], "hard_skills": ["excel", "cpa", "companies ordinance", "ms word"], "soft_skills": ["communication skills", "independent", "responsible", "computer literacy", "hard-working", "initiative"], "languages_combined": [{"language": "cantonese", "language_level": ["good"]}, {"language": "english", "language_level": ["good"]}]}, "experience_required": {"duration": ["at least 4 years"], "field": ["cpa firm", "audit", "financial"]}}, {"job_id": "100003009051762", "location_code": "hk", "company": "W. H. Tse & Company", "job_title": "Audit Semi-Senior", "description": "Requirements:\n\nDegree/Diploma holder, major in Accounting or related subjects\nMember/Student member of Professional Accountancy bodies\n1-3 years of solid auditing experience with ability to handle audit cases independently\nPC Knowledge in MS Office / Windows / Accounting software will be an advantage\nGood command of written and spoken English & Chinese/Mandarin\nSelf-motivated,\u00a0self-discipline and good interpersonal communication skills\n\nBenefits:\n\nAnnual Leave\nPerformance Related Bonus\nStudy and Exam Leaves\nOn-job training\nMedical, meal and travelling allowance\nGood working environment\n\nStatus:\n\n\nWe are an Authorised Employer of HKICPA.\n\n\nInterested parties, please send detailed resume to W. H. Tse & Co., by clicking \u201cApply Now\u201d or please call Miss Rebecca Lau at 2542 2800", "employment_types": ["Full Time", "Permanent"], "selling_points": [], "locations": ["Sheung Wan"], "categories": ["Accounting", "Accountant", "Accounting Clerk / Supervisor", "Audit"], "post_time": "2022-01-17T00:55:43Z", "salary": {"currency": null, "max": null, "min": null, "period": "monthly", "term": null}, "salary_visible": false, "title_keywords": [], "responsibilities": ["communication", "audit", "auditing", "software"], "requirements": {"degrees": ["diploma holder", "degree"], "majors": ["accounting"], "languages": ["english", "chinese", "mandarin"], "language_level": ["good command"], "hard_skills": ["accounting software", "pc knowledge", "ms office"], "soft_skills": ["communication skills", "self-motivated", "independently", "interpersonal"], "languages_combined": [{"language": "english", "language_level": ["good command"]}, {"language": "chinese", "language_level": ["good command"]}, {"language": "mandarin", "language_level": ["good command"]}]}, "experience_required": {"duration": ["1-3 years"], "field": ["audit"]}}, {"job_id": "100003009053595", "location_code": "hk", "company": "Eric Mok & Co., Limited", "job_title": "Audit Junior / Intermediate / Semi-Senior / Senior /Supervisor", "description": "Eric Mok & Co., Limited, CPAs\n\nWe are a professional accounting firm offering audit and assurance, taxation, corporate finance and accounting services to our clients. Our office locates at the China Hong Kong City in Tsim Sha Tsui. We are looking for suitable candidates for the following positions:\n\nAudit Junior / Intermediate / Semi-Senior / Senior /Supervisor\n\nRequirements\n\nDegree / Associate Degree in Accountancy or equivalent\n\nStudent member / member of HKICPA / ACCA / CPA Australia / CPA Canada or equivalent\n\n0 - 5 years\u2019 solid experience in auditing\n\nFor Audit Supervisor, experience in leading juniors, with excellent interpersonal skills\n\nGood command of written and spoken English and Mandarin\n\nSelf motivated, independent and willing to travel\n\nFamiliar with PC application and well-versed with Chinese word processing\n\nAble to work independently, meet deadline and work under pressure\n\nWe offer\n\nAttractive salary and bonus\n\nPaid study and examination leave, and training\n\nMedical allowance and insurance\n\n5-day week\n\nInterested parties please email your application letter specifying post applied and full resume with your present salary, salary expected and availability", "employment_types": ["Full Time"], "selling_points": [], "locations": ["Tsim Sha Tsui"], "categories": ["Accounting", "Audit"], "post_time": "2022-01-17T07:13:20Z", "salary": {"currency": null, "max": null, "min": null, "period": "monthly", "term": null}, "salary_visible": false, "title_keywords": ["supervisor", "junior"], "responsibilities": ["taxation", "audit", "auditing", "work under pressure"], "requirements": {"degrees": ["associate degree", "degree"], "majors": ["accountancy"], "languages": ["english", "chinese", "mandarin"], "language_level": ["good command"], "hard_skills": ["acca", "chinese word processing", "cpa", "pc", "hkicpa"], "soft_skills": ["work independently", "independent", "self motivated", "interpersonal skills", "work under pressure"], "languages_combined": [{"language": "english", "language_level": ["good command"]}, {"language": "chinese", "language_level": []}, {"language": "mandarin", "language_level": ["good command"]}]}, "experience_required": {"duration": ["0 - 5 years"], "field": ["audit"]}}, {"job_id": "100003009054568", "location_code": "hk", "company": "Liu & Wong Certified Public Accountants", "job_title": "Audit Juniors / Seniors \u2013 Multiple Headcounts", "description": "Requirements:\u00a0\u00a0\u00a0\u00a0\u00a0\u00a0\u00a0\u00a0\u00a0\u00a0\u00a0\u00a0\u00a0\u00a0\u00a0\u00a0\u00a0\u00a0\u00a0\u00a0\n\nDegree major in Accounting\nStudent member of HKICPA/ACCA or equivalent\nApplicants with no or less experience are considered as Audit Junior\nAble to handle small to medium size audit assignments independently, and to lead a team of 2 to 3 subordinates, preferably 3-5 years experience in audit and tax field are required for Seniors\nGood command of both written and spoken English and Chinese is essential, fluent in Putonghua\nImmediate available is preferable.\n\nRemuneration Package\u00a0\n\n5-day work\nStudy and examination leaves\nOn-the-job training\nExcellent career prospect\nDiscretionary bonuses\nFriendly working environment\n\nInterested parties please send your application via \"Apply Now\". (All information received will be treated in strict confidence and used for recruitment purpose only)", "employment_types": ["Full Time", "Permanent"], "selling_points": ["5-day work ! Good work-life balance !", "Study and examination leaves! On-the-job training!", "Near Central MTR Station !"], "locations": ["Central"], "categories": ["Accounting", "Audit", "Taxation"], "post_time": "2022-01-17T10:01:36Z", "salary": {"currency": null, "max": null, "min": null, "period": "monthly", "term": null}, "salary_visible": false, "title_keywords": [], "responsibilities": ["tax", "lead a team", "audit"], "requirements": {"degrees": ["degree"], "majors": ["accounting"], "languages": ["putonghua", "english", "chinese"], "language_level": ["good command", "fluent"], "hard_skills": ["no", "acca", "small", "hkicpa"], "soft_skills": ["independently", "friendly"], "languages_combined": [{"language": "putonghua", "language_level": ["fluent", "good command"]}, {"language": "english", "language_level": ["good command"]}, {"language": "chinese", "language_level": ["good command"]}]}, "experience_required": {"duration": ["3-5 years"], "field": ["audit", "team"]}}, {"job_id": "100003009052949", "location_code": "hk", "company": "Fung, Yu & Co. CPA Limited", "job_title": "ASSISTANT MANAGER / SENIOR ACCOUNTANT - AUDIT & ASSURANCE DEPARTMENT (5 days work)", "description": "In the past 55 years, we have grown rapidly as one of the top-tier local CPA firms and are expanding our foothold across the globe.\u00a0 To support our fast-growing international business, we are seeking professionals with following expertise to be part of us.\n\nOpportunities:\n\nWe offer excellent career advancement opportunities to staff who join our Audit & Assurance Department\nYou will gain valuable experience in providing professional auditing services to our clients across different geographies and sectors\nWe will be your biggest supporter in pursuing your professional qualifications\n\nResponsibilities:\n\nPlay a key role in supporting Audit Managers to provide auditing and assurance services for clients\nDraft and prepare audit reports for Audit Manager\u2019s review\nAssist to plan and conduct internal control reviews for various client industries\nMaintain proper documentations for audit compliance\nPerform other ad hoc tasks as required by superiors\n\nRequirements:\n\nUniversity degree holder preferably in accounting or related disciplines\nAt least 2 to 3 years relevant working experience in audit field\nAble to work under pressure and meet deadlines\nAble to work independently\nGood command of English and Mandarin\nFresh graduates will also be considered\nImmediately available is preferred\n\n5 days work with\u00a019 days annual leave for assistant manager grade and 17 days annual leave for senior grade,\u00a0 birthday leave and medical insurance.\u00a0 We offer a highly competitive salary and benefit package commensurate with qualifications and experience.\u00a0 Please submit your application by clicking \u201cApply Now\u201d button and visit our company website at http://www.fungyucpa.com/join-us/ for more information.\n\nPersonal data collected will only be used for the purpose of recruitment.", "employment_types": ["Full Time", "Permanent"], "selling_points": ["19 days/17 days Annual Leave with annual increment", "Birthday leave, Study leave and Exam leave", "Medical Insurance"], "locations": ["Central & Western Area"], "categories": ["Accounting", "Accountant", "Audit", "Others"], "post_time": "2022-01-17T04:39:35Z", "salary": {"currency": null, "max": null, "min": null, "period": "monthly", "term": null}, "salary_visible": false, "title_keywords": ["assistant manager", "senior accountant"], "responsibilities": [], "requirements": {"degrees": [], "majors": [], "languages": [], "language_level": [], "hard_skills": [], "soft_skills": [], "languages_combined": []}, "experience_required": {"duration": [], "field": []}}, {"job_id": "100003009054254", "location_code": "hk", "company": "", "job_title": "Audit Senior / Semi-Senior", "description": "Responsibilities:\n\n\u00a0\u00a0\u00a0\u00a0\u00a0\u00a0\u00a0 Collect accounting materials and send confirmations\u00a0\n\u00a0\u00a0\u00a0\u00a0\u00a0\u00a0\u00a0 Perform audit procedure by analytical procedures / test of controls\n\u00a0\u00a0\u00a0\u00a0\u00a0\u00a0\u00a0 Prepare Audited Financial Statements and Profits Tax Computation\n\u00a0\u00a0\u00a0\u00a0\u00a0\u00a0\u00a0 Perform ad-hoc assignments as assigned\n\nRequirements:\n\n\u00a0\u00a0\u00a0\u00a0\u00a0\u00a0\u00a0 Relevant audit experience with CPA firm\n\u00a0\u00a0\u00a0\u00a0\u00a0\u00a0\u00a0 Well organized, with good interpersonal & communication skill\n\u00a0\u00a0\u00a0\u00a0\u00a0\u00a0\u00a0 Proficiency in MS office and MYOB\n\u00a0\u00a0\u00a0\u00a0\u00a0\u00a0\u00a0 Self-motivated, with strong sense of commitment and ability to work under pressure and to meet deadlines\n\nCompetitive emoluments package:\n\n\u00a0\u00a0\u00a0\u00a0\u00a0\u00a0\u00a0 Double pay\u00a0\n\u00a0\u00a0\u00a0\u00a0\u00a0\u00a0\u00a0 Transportation allowance\u00a0\n\u00a0\u00a0\u00a0\u00a0\u00a0\u00a0\u00a0 Medical insurance\n\u00a0\u00a0\u00a0\u00a0\u00a0\u00a0\u00a0 Five-day work\n\u00a0\u00a0\u00a0\u00a0\u00a0\u00a0\u00a0 Study and examination leave\nInterested candidates, please contact us at 21000901 for company details before applying.", "employment_types": ["Full Time", "Permanent"], "selling_points": ["Authorized Employer", "Professional training", "Work life balance"], "locations": ["Wan Chai"], "categories": ["Accounting", "Accounting Clerk / Supervisor", "Audit", "Others", "Student / Fresh Graduate / No Experience"], "post_time": "2022-01-17T08:58:13Z", "salary": {"currency": null, "max": null, "min": null, "period": "monthly", "term": null}, "salary_visible": false, "title_keywords": [], "responsibilities": ["tax computation", "ad-hoc assignments", "procedures", "audit", "financial statements"], "requirements": {"degrees": [], "majors": [], "languages": [], "language_level": [], "hard_skills": ["cpa", "myob", "ms office"], "soft_skills": ["self-motivated", "communication skill", "well organized", "meet deadlines", "interpersonal", "work under pressure"], "languages_combined": []}, "experience_required": {"duration": [], "field": ["audit experience", "cpa firm"]}}, {"job_id": "100003009053765", "location_code": "hk", "company": "WST CPA & Co.", "job_title": "Audit & Accounting Senior / Associate", "description": "\nCPA Firm\nKowloon Bay\nJob Description\n\u2022 2- 5 year experience\n\u2022 Good communication and interpersonal skills\n\u2022 Willing to work under pressure and tight schedule\n\u2022 Good command of both written and spoken in English and Chinese\n\u2022 Flexible working environment and work life balance\n\u2022 Excellent career promotion prospect\nCandidate with less experience(fresh graduate)will be considered as Trainee;\nResponsibilities\n\u2022 Participate in audit, accounting and tax assignments\n\u2022 Deliver professional and effective client management\n\u2022 Handle audit assignments independently;\n\u2022 Preparing tax computation and schedules for tax compliance;\n\u2022 Handle ad hoc matters assigned.\nRequirements\n\u2022 Tertiary education or above with major in accountancy or business related\n\u2022 Able to communicate effectively in English, Chinese and Putonghua\n\u2022 Proficient in MS Word and Excel\n\u2022 Proactive and good interpersonal skills\n\u2022 Independent with initiative\n\u2022 Responsible, stable, dedicated, initiative and self-motivated\nWe offer an attractive remuneration package, including performance bonus, medical scheme, examination leaves, bank holiday, 5-day work week, Training package, excellent career prospects in a warm and friendly working environment.\nInterest parties please send application letter with full resume and expected salary to Apply Now, fresh graduates are welcome.\n(Personal data collected will be used for recruitment purpose only.)\n\n", "employment_types": ["Full Time"], "selling_points": [], "locations": ["Kwun Tong"], "categories": ["Accounting", "Accounting Clerk / Supervisor", "Audit"], "post_time": "2022-01-17T07:29:06Z", "salary": {"currency": null, "max": null, "min": null, "period": "monthly", "term": null}, "salary_visible": false, "title_keywords": ["associate", "accounting"], "responsibilities": ["tax", "management", "ad hoc", "tax computation", "schedules", "compliance", "audit", "communication", "schedule", "work under pressure"], "requirements": {"degrees": [], "majors": [], "languages": ["putonghua", "english", "chinese"], "language_level": [], "hard_skills": ["excel", "scheme", "ms word"], "soft_skills": ["self-motivated", "independent", "responsible", "interpersonal skills", "friendly", "stable", "proactive", "initiative"], "languages_combined": [{"language": "putonghua", "language_level": []}, {"language": "english", "language_level": []}, {"language": "chinese", "language_level": []}]}, "experience_required": {"duration": [], "field": []}}, {"job_id": "100003009052160", "location_code": "hk", "company": "BDO", "job_title": "Audit Associate (2022 January Intake) (Ref : AUD / JDB)", "description": "Responsibilities:\n\nParticipate in audit fieldwork and be responsible to auditor in charge for ensuring the work assigned is executed and completed as planned and in accordance to the firm\u2019s policies and procedures\nSupport and act towards the BDO Global Vision\nBe committed to act with the firm\u2019s core values and competency expectations\n\nRequirements:\n\n2021 fresh graduate degree holder, major in accounting or\u00a0other\u00a0related disciplines\nA good and effective team player\nExcellent command of both written and spoken English and Chinese; including Mandarin\nBe passionate for providing exceptional quality service and striving for exceeding clients\u2019 expectations\n\nRemarks:\n\nYou are expected to report duty in late Dec - early Jan 2022.\n\nWe are an equal opportunity employer, and offer excellent prospects and career development for the right candidate.\u00a0 Interested parties please send your application with full career history, current and expected salary by clicking\u00a0Apply Now\u00a0button below.\n\nApplications will be treated in strict confidence. Personal data collected will be used for recruitment purposes only.", "employment_types": ["Full Time", "Permanent"], "selling_points": ["Participate in audit fieldwork", "Structured training program", "Excellent Career Prospects"], "locations": ["Sheung Wan"], "categories": ["Accounting", "Audit", "Others", "Student / Fresh Graduate / No Experience"], "post_time": "2022-01-17T02:17:55Z", "salary": {"currency": null, "max": null, "min": null, "period": "monthly", "term": null}, "salary_visible": false, "title_keywords": ["associate"], "responsibilities": ["policies", "procedures", "audit"], "requirements": {"degrees": ["fresh graduate", "degree holder"], "majors": ["related disciplines", "accounting"], "languages": ["english", "chinese", "mandarin"], "language_level": ["excellent"], "hard_skills": [], "soft_skills": ["passionate", "team player"], "languages_combined": [{"language": "english", "language_level": ["excellent"]}, {"language": "chinese", "language_level": ["excellent"]}, {"language": "mandarin", "language_level": []}]}, "experience_required": {"duration": [], "field": []}}, {"job_id": "100003009051675", "location_code": "hk", "company": "Hong Kong Great Wall CPA Limited", "job_title": "Audit Professionals - All Levels", "description": "Direct reporting to Manager\nManage day to day audit engagements\nPrepare audit schedules, financial statements and tax computation\nDevelop and maintain good working relationship with client personnel\n\nRequirements\n\n\nBachelor degree in Accounting, Finance or Business related disciplines (DSE graduates and candidates from non-degree tertiary also welcome to apply)\nMember or student member (HKICPA, ACCA, CPA Australia etc)\nAble to work independently and meet deadline\nGood interpersonal and communication skills\nGood command of spoken and written English and Chinese\nMature, self-motivated and good team player\n\n\u00a0Benefits\n\n\n\nFive-day work week\nOvertime compensation leave and meal reimbursement\nStudy and exam leave for recognized professional exams\nProfessional exam subsidy\nMedical and travelling expenses reimbursement\nBirthday leave\nFast-track promotion to talented candidates\nSalary is negotiable subject to years of experience\nDiscretionary bonus\nPlease send your resume by e-mail\u00a0\n\n\nData collected will be used for recruitment purpose only.", "employment_types": ["Full Time"], "selling_points": [], "locations": ["Wan Chai"], "categories": ["Accounting", "Accountant", "Audit", "Others"], "post_time": "2022-01-16T21:50:42Z", "salary": {"currency": null, "max": null, "min": null, "period": "monthly", "term": null}, "salary_visible": false, "title_keywords": [], "responsibilities": ["reporting", "tax computation", "schedules", "audit", "financial statements", "develop", "communication", "maintain"], "requirements": {"degrees": ["degree", "bachelor", "dse"], "majors": ["business", "finance", "related disciplines", "accounting"], "languages": ["english", "chinese"], "language_level": ["good command"], "hard_skills": ["cpa", "acca", "hkicpa"], "soft_skills": ["communication skills", "work independently", "self-motivated", "good team player", "mature", "interpersonal"], "languages_combined": [{"language": "english", "language_level": ["good command"]}, {"language": "chinese", "language_level": ["good command"]}]}, "experience_required": {"duration": [], "field": []}}, {"job_id": "100003009054453", "location_code": "hk", "company": "Jobslink Limited", "job_title": "Audit senior associate / Audit associate", "description": "Responsibilities:\n\n\u00a0\u00a0\u00a0\u00a0\u00a0\u00a0 Liaise with clients and colleagues for job coordination\n\u00a0\u00a0\u00a0\u00a0\u00a0\u00a0 Assist in planning, execution and delivery of assurance engagements\n\u00a0\u00a0\u00a0\u00a0\u00a0\u00a0 Handle the client enquiries in accounting, audit and taxation\n\u00a0 \u00a0 \u00a0 \u00a0Involve in\u00a0audit of internal controls over financial reporting and ad-hoc projects such as due diligence\u00a0reviews and merger and acquisition deal\n\nRequirements:\n\n\u00a0\u00a0\u00a0\u00a0\u00a0\u00a0 High Diploma or equivalent qualification in Accountancy\n\u00a0\u00a0\u00a0\u00a0\u00a0\u00a0 Minimum 2 years working experience in audit field / less experience will be consider as audit associate\n\u00a0\u00a0\u00a0\u00a0\u00a0\u00a0 Able to work independently and efficiently in multi-tasking\n\u00a0\u00a0\u00a0\u00a0\u00a0\u00a0 Able to meet deadlines and eager to accomplish higher goals\n\u00a0\u00a0\u00a0\u00a0\u00a0\u00a0 High level of independence and strong motivation\n\u00a0\u00a0\u00a0\u00a0\u00a0\u00a0 Effective problem-solving and interpersonal skills\n\u00a0 \u00a0 \u00a0 \u00a0Good command of written and spoken English, Cantonese and Mandarin\n\nCompetitive package:\n\n\u00a0\u00a0\u00a0\u00a0\u00a0\u00a0 5 day work week\n\u00a0\u00a0\u00a0\u00a0\u00a0\u00a0 paid examination & study leave.\n\u00a0\u00a0\u00a0\u00a0\u00a0\u00a0 In house and external training\nCompensation leave or compensation pay", "employment_types": ["Full Time"], "selling_points": ["Career development", "Work life balance", "Good remuneration"], "locations": ["Tsuen Wan Area"], "categories": ["Accounting", "Accountant", "Audit"], "post_time": "2022-01-17T09:36:19Z", "salary": {"currency": null, "max": null, "min": null, "period": "monthly", "term": null}, "salary_visible": false, "title_keywords": ["senior associate", "associate"], "responsibilities": ["liaise with clients", "taxation", "due diligence reviews", "audit", "financial reporting", "coordination", "ad-hoc projects", "planning"], "requirements": {"degrees": ["high diploma"], "majors": ["accountancy"], "languages": ["cantonese", "english", "mandarin"], "language_level": ["good command"], "hard_skills": ["problem-solving"], "soft_skills": ["work independently", "problem-solving", "multi-tasking", "interpersonal skills", "meet deadlines"], "languages_combined": [{"language": "cantonese", "language_level": ["good command"]}, {"language": "english", "language_level": ["good command"]}, {"language": "mandarin", "language_level": ["good command"]}]}, "experience_required": {"duration": ["minimum 2 years"], "field": ["audit"]}}, {"job_id": "100003009052718", "location_code": "hk", "company": "K. W. Tam & Co.", "job_title": "Junior / Semi-Senior / Senior - Audit Services", "description": "Highlights:\u00a0\n\n\u00a0 \u00a0* examination fee reimbursement, group medical plan\n\u00a0 \u00a0* study, exam, birthday, voluntary service leaves\n\nRequirements:\n\nDegree holder major in accountancy\nFresh graduate or with working experience gain in CPA firms\nComputer literacy and proficient with Windows applications\nMature, self-motivated, independent,\u00a0responsible and good communication skills\nGood command of written and spoken English and Chinese\u00a0\n\nWe offer 5-days work, attractive remuneration, various kinds of fringe benefits including annual leave, study leave, examination leave, birthday leave, voluntary service leave, examination fee reimbursement, medical insurance, bonus, etc. and good career development opportunities. We also encourage our staff to take professional examinations, technical\u00a0and managerial training to enhance their professional\u00a0and managerial knowledge.\n\nInterested parties please send your\u00a0full resume with date of availability, current and expected salaries\u00a0by clicking \"Apply Now\"\u00a0(Please mark the job title applied at the subject of the email).\n\n\nAll information provided by applicants will be used for recruitment related purposes only and will be treated in the strictest confidence by authorized personnel.", "employment_types": ["Full Time", "Permanent"], "selling_points": [], "locations": ["Ngau Tau Kok"], "categories": ["Accounting", "Accountant", "Audit", "Others", "Student / Fresh Graduate / No Experience"], "post_time": "2022-01-17T03:47:21Z", "salary": {"currency": null, "max": null, "min": null, "period": "monthly", "term": null}, "salary_visible": false, "title_keywords": ["junior"], "responsibilities": ["communication", "insurance", "plan", "career development"], "requirements": {"degrees": ["fresh graduate", "degree holder"], "majors": ["accountancy"], "languages": ["english", "chinese"], "language_level": ["good command"], "hard_skills": ["cpa"], "soft_skills": ["communication skills", "self-motivated", "independent", "responsible", "mature", "computer literacy"], "languages_combined": [{"language": "english", "language_level": ["good command"]}, {"language": "chinese", "language_level": ["good command"]}]}, "experience_required": {"duration": [], "field": []}}, {"job_id": "100003009054800", "location_code": "hk", "company": "Public Finance Limited", "job_title": "Audit Executive", "description": "Responsibilities\nTo be responsible for performing audit functions within the Company\nAny ad hoc audit assignments\n\u00a0Requirements\nDiploma in Accountancy, Finance or related disciplines\nNo relevant experience is required. Fresh graduates are also welcome\nGood communication and interpersonal skills\nCandidates with more experience will be considered as Audit Officer\nBenefits\nDouble Pay\nDiscretionary Bonus\nInsurance Benefits\nStudy Subsidy\nApplication Method:\n\nBy Whatsapp : 9309 2925\n\nBy E-mail via \"Apply Now\"\nPersonal data collected will be treated in the strictest confidence in accordance with our\u00a0Personal Information Collection Statement\u00a0and\u00a0Privacy Policy\u00a0and will be handled by authorized personnel for recruitment-related purposes only. All applications will be kept for a maximum period of one year as may be considered for other suitable positions within Public Finance Ltd. and its associated companies. For details, please visit the Company\u2019s website\u00a0http://www.publicfinance.com.hk", "employment_types": ["Full Time", "Permanent"], "selling_points": [], "locations": ["Not Specified"], "categories": ["Accounting", "Accounting Clerk / Supervisor", "Audit", "Others"], "post_time": "2022-01-17T11:08:55Z", "salary": {"currency": null, "max": null, "min": null, "period": "monthly", "term": null}, "salary_visible": false, "title_keywords": ["executive"], "responsibilities": ["ad hoc", "audit"], "requirements": {"degrees": ["diploma"], "majors": ["related disciplines", "finance", "accountancy"], "languages": [], "language_level": [], "hard_skills": ["no"], "soft_skills": ["communication and interpersonal skills"], "languages_combined": []}, "experience_required": {"duration": [], "field": ["relevant experience", "audit"]}}, {"job_id": "100003009053254", "location_code": "hk", "company": "APEC Group International Limited", "job_title": "Accountant Trainee/Associate (Financial Advisory Team)", "description": "Responsibilities\n\nAssist in handle assignments independently;\nInvolving in public offerings, listings, due diligence and private placements;\nAssist in analyze financial results of clients\u2019 companies;\nAssist in providing support to clients regarding different regulatory regimes, listing rules and related regulations;\nKeep up-to-date on regulatory developments;\nAssist in preparing business plans and IPO business proposals; Developing effective business relationships with clients;\nHandle ad hoc matters assigned.\n\nRequirements\n\nHigher Diploma\u00a0in accounting or related discipline.\nStudent member of HKICPA/ACCA/CPAA or other relevant professional bodies;\n0-1 year of accounting/audit experience in any field;\nSelf-motivated, willing to take job ownership, manage deadlines and able to work as a team player;\nProficient in MS Excel and word and knowledge of computerized accounting system is highly preferred;\nGood\u00a0analytical, interpersonal and communication skill is highly preferred;\nGood command in written and spoken English, Chinese and Mandarin;\nBusiness travel is required;\nFresh graduates are welcome;\nImmediate available is preferred.\n\nWhat we offered?\n\n5-day work week\nImportant festivals early leave\nOvertime meal allowance\nDiscretionary bonus\nFull-paid sick leave\nStudy & Exam leave\nGraduation leave\nWedding leave\nCompassionate leave\nMedical Insurance Scheme\nTraining reimbursement\nInterested parties please send your full resume with your\u00a0working experience, academic and professional qualification, expected salary, and date of availability\u00a0to HR Department.\nPersonal data collected will be used for recruitment purpose only.", "employment_types": ["Full Time", "Part Time", "Permanent", "Contract"], "selling_points": ["Fresh graduates are welcome", "5-day work week", "Excellent career promotion prospect"], "locations": ["Sheung Wan"], "categories": ["Accounting", "Accountant", "Audit", "Consulting"], "post_time": "2022-01-17T06:32:55Z", "salary": {"currency": null, "max": null, "min": null, "period": "monthly", "term": null}, "salary_visible": false, "title_keywords": ["associate", "accountant", "trainee"], "responsibilities": ["regulations", "due diligence", "ad hoc", "developing", "providing support", "preparing business plans", "listing"], "requirements": {"degrees": ["diploma"], "majors": ["accounting"], "languages": ["english", "chinese", "mandarin"], "language_level": ["good command"], "hard_skills": ["acca", "word", "ms excel", "accounting system", "hkicpa"], "soft_skills": ["self-motivated", "communication skill", "interpersonal", "work as a team"], "languages_combined": [{"language": "english", "language_level": ["good command"]}, {"language": "chinese", "language_level": ["good command"]}, {"language": "mandarin", "language_level": ["good command"]}]}, "experience_required": {"duration": ["0-1 year"], "field": ["audit experience", "accounting"]}}, {"job_id": "100003009053711", "location_code": "hk", "company": "BDO", "job_title": "(Part Time / Contract / Temporary) Senior Associate / Associate - Assurance (Ref : AUD / JDB)", "description": "Responsibilities:\n\nProvide support in audit engagements\nSupport and act towards the BDO Global Vision\nBe committed to act with the firm\u2019s core values and competency expectations\n\nRequirements:\n\nA good and effective team player\nExcellent command of both written and spoken English and Chinese; including Mandarin\nBe passionate for providing exceptional quality service and striving for exceeding clients\u2019 expectations\n\nWe are an equal opportunity employer, and offer excellent prospects and career development for the right candidate.\u00a0 Interested parties please send your application with full career history, current and expected salary by clicking\u00a0Apply Now\u00a0button below.\n\nApplications will be treated in strict confidence. Personal data collected will be used for recruitment purposes only.", "employment_types": ["Part Time", "Temporary", "Contract"], "selling_points": ["Provide support in audit engagement", "Part Time / Temporary", "A good and effective team player"], "locations": ["Sheung Wan"], "categories": ["Accounting", "Audit"], "post_time": "2022-01-17T07:23:32Z", "salary": {"currency": null, "max": null, "min": null, "period": "monthly", "term": null}, "salary_visible": false, "title_keywords": ["senior associate", "associate"], "responsibilities": ["provide support", "audit"], "requirements": {"degrees": [], "majors": [], "languages": ["english", "chinese", "mandarin"], "language_level": ["excellent"], "hard_skills": [], "soft_skills": ["passionate", "team player"], "languages_combined": [{"language": "english", "language_level": ["excellent"]}, {"language": "chinese", "language_level": ["excellent"]}, {"language": "mandarin", "language_level": []}]}, "experience_required": {"duration": [], "field": []}}, {"job_id": "100003009053770", "location_code": "hk", "company": "WST CPA & Co.", "job_title": "AUDIT Trainee / AUDIT JUNIOR", "description": "\nCPA Firm\nKowloon Bay\nJob Description\n\u2022 0 - 1 year experience\n\u2022 Good communication and interpersonal skills\n\u2022 Willing to work under pressure and tight schedule\n\u2022 Fluent in both written and spoken English, Cantonese and Mandarin\n\u2022 Flexible working environment\n\u2022 Excellent career promotion prospect\nCandidate with less experience(fresh graduate)will be considered as Trainee;\nResponsibilities\n\u2022 Participate in audit, accounting and tax assignments\n\u2022 Deliver professional and effective client management\n\u2022 Handle audit assignments independently;\n\u2022 Preparing tax computation and schedules for tax compliance;\n\u2022 Handle ad hoc matters assigned.\nRequirements\n\u2022 Tertiary education or above with major in accountancy or business related\n\u2022 Able to communicate effectively in English, Chinese and Putonghua\n\u2022 Proficient in MS Word and Excel\n\u2022 Proactive and good interpersonal skills\n\u2022 Independent with initiative\n\u2022 Responsible, stable, dedicated, initiative and self-motivated\u00a0\u00a0\nWe offer an attractive remuneration package, including performance bonus, medical scheme, examination leaves, bank holiday, 5-day work week, Training package, excellent career prospects in a warm and friendly working environment.\nInterest parties please send application letter with full resume and expected salary to Apply Now, fresh graduates are welcome.\n(Personal data collected will be used for recruitment purpose only.)\n\n", "employment_types": ["Full Time"], "selling_points": [], "locations": ["Kwun Tong"], "categories": ["Accounting", "Accounting Clerk / Supervisor", "Audit"], "post_time": "2022-01-17T07:29:40Z", "salary": {"currency": null, "max": null, "min": null, "period": "monthly", "term": null}, "salary_visible": false, "title_keywords": ["trainee", "junior"], "responsibilities": ["tax", "management", "ad hoc", "tax computation", "schedules", "compliance", "audit", "communication", "schedule", "work under pressure"], "requirements": {"degrees": [], "majors": [], "languages": ["putonghua", "english", "chinese"], "language_level": [], "hard_skills": ["excel", "scheme", "ms word"], "soft_skills": ["self-motivated", "independent", "responsible", "interpersonal skills", "friendly", "stable", "proactive", "initiative"], "languages_combined": [{"language": "putonghua", "language_level": []}, {"language": "english", "language_level": []}, {"language": "chinese", "language_level": []}]}, "experience_required": {"duration": [], "field": []}}, {"job_id": "100003009047949", "location_code": "hk", "company": "C. K. Lo & Company Certified Public Accountants", "job_title": "Audit senior / semi-senior / junior", "description": "Audit senior / semi-senior / junior\n\nDegree holder major in accountancy or related field;\nStudent member / member of HKICPA or other professional bodies;\nApplicants with\u00a0no or\u00a0less experience\u00a0are\u00a0considered as Audit\u00a0Junior;\nHardworking, analytical and detail oriented;\nWilling to learn with positive working attitude;\nGood interpersonal and communication skills;\nStrong PC skills & proficiency in MS Word, Excel and Chinese word processing; and\nGood command of English, Chinese and Mandarin\n\nOffer competitive salary to suitable candidate.\u00a0\n\n\nWe offer 5-days work, medical allowance, study and exam leaves, good working condition and valuable experience. Travel is RARELY required.\n\nApply Method:\n\nInterested parties please email your full resume with current and expected salary to us.\n\n\n(data collected used for recruitment purpose only)", "employment_types": ["Full Time", "Permanent"], "selling_points": [], "locations": ["Tsim Sha Tsui"], "categories": ["Accounting", "Accountant", "Audit", "Taxation"], "post_time": "2022-01-15T03:49:02Z", "salary": {"currency": null, "max": null, "min": null, "period": "monthly", "term": null}, "salary_visible": false, "title_keywords": ["junior"], "responsibilities": ["communication", "audit"], "requirements": {"degrees": ["degree holder"], "majors": ["accountancy"], "languages": ["english", "chinese", "mandarin"], "language_level": ["proficiency", "good command"], "hard_skills": ["excel", "no", "chinese word processing", "hkicpa", "pc skills", "ms word"], "soft_skills": ["communication skills", "detail oriented", "willing to learn", "positive working attitude", "interpersonal", "hardworking"], "languages_combined": [{"language": "english", "language_level": ["good command"]}, {"language": "chinese", "language_level": ["proficiency", "good command"]}, {"language": "mandarin", "language_level": ["good command"]}]}, "experience_required": {"duration": [], "field": ["audit"]}}, {"job_id": "100003009052866", "location_code": "hk", "company": "Union Link CPA Limited", "job_title": "Audit Supervisor/ Senior/ Semi-Senior", "description": "At least 3 year's audit experience\nMember/ Finalist of HKICPA/ACCA preferable\nGood organizational skills with the ability to handle multi-tasks and meet deadlines\nA high degree of independence, motivation and technical ability\nCandidate with less experience will be considered as Audit Semi-Senior\nWe offer the right candidates with a competitive remuneration package including study & examination leaves, birthday leave, 12-14 annual leaves, casual Friday and performance bonus.\n\n\nThe salary offered will commensurate with the experience and qualifications of the right candidates. Please send your full resume with expected salary to us by clicking \"APPLY NOW\".", "employment_types": ["Full Time", "Permanent"], "selling_points": ["Work/ Life balance", "NO OT culture/ No overseas travelling", "5-day work (9:30 am to 6:00 pm)"], "locations": ["Wan Chai"], "categories": ["Accounting", "Audit", "Taxation"], "post_time": "2022-01-17T06:33:11Z", "salary": {"currency": null, "max": null, "min": null, "period": "monthly", "term": null}, "salary_visible": false, "title_keywords": ["audit supervisor"], "responsibilities": ["audit"], "requirements": {"degrees": ["degree"], "majors": [], "languages": [], "language_level": [], "hard_skills": ["acca", "hkicpa"], "soft_skills": ["organizational skills", "meet deadlines", "multi-tasks"], "languages_combined": []}, "experience_required": {"duration": ["at least 3 year"], "field": ["audit experience", "audit"]}}, {"job_id": "100003009051476", "location_code": "hk", "company": "BDO", "job_title": "Senior Associate / Associate \u2013 Assurance (Fund Audit)", "description": "Responsibilities:\n\nResponsible for the planning and execution of audit fieldwork and completing the assigned tasks accordance with the audit plan and our firm's procedures\nSupport and act towards the BDO Global Vision\nBe committed to act with the firm\u2019s core values and competency expectations\n\nRequirements:\n\nDegree holder, major in accounting or\u00a0other\u00a0related disciplines\nAt least 1 year of relevant experience in assurance gained with sizable accounting firm. Experience in Fund Industry is highly preferable.\nQualified accountant is preferred\nA good and effective team player\nExcellent command of both written and spoken English and Chinese; including Mandarin\nBe passionate for providing exceptional quality service and striving for exceeding clients\u2019 expectations\nPosition offered will commensurate with the experience of the right candidate\n\nWe are an equal opportunity employer, and offer excellent prospects and career development for the right candidate.\u00a0 Interested parties please send your application with full career history, current and expected salary by clicking\u00a0Apply Now\u00a0button below.\n\nApplications will be treated in strict confidence. Personal data collected will be used for recruitment purposes only.", "employment_types": ["Full Time", "Permanent"], "selling_points": ["At least 1 year of relevant experience", "Qualified accountants are preferred", "Excellent Career Prospects"], "locations": ["Sheung Wan"], "categories": ["Accounting", "Audit", "Banking / Finance", "Fund Management"], "post_time": "2022-01-16T03:48:55Z", "salary": {"currency": null, "max": null, "min": null, "period": "monthly", "term": null}, "salary_visible": false, "title_keywords": ["senior associate", "associate"], "responsibilities": ["procedures", "audit", "plan", "planning"], "requirements": {"degrees": ["degree holder"], "majors": ["related disciplines", "accounting"], "languages": ["english", "chinese", "mandarin"], "language_level": ["excellent"], "hard_skills": [], "soft_skills": ["passionate", "team player"], "languages_combined": [{"language": "english", "language_level": ["excellent"]}, {"language": "chinese", "language_level": ["excellent"]}, {"language": "mandarin", "language_level": []}]}, "experience_required": {"duration": ["at least 1 year"], "field": ["assurance", "accounting", "relevant experience"]}}, {"job_id": "100003009047650", "location_code": "hk", "company": "Moore Associates Limited", "job_title": "Audit Staff \u2013 Associates/Senior Associates", "description": "Responsibilities:\n\nWork on audit assignments for clients from a variety of industries, covering Hong Kong and China\nInvolve in\u00a0audit of internal controls over financial reporting and ad-hoc projects such as due\u00a0diligence reviews, IPO exercises and merger and acquisition deals\nAssist in\u00a0planning, execution and delivery of assurance engagements\n\n\nRequirements:\u00a0\u00a0\n\nDegree holder majoring in Accountancy / Finance\nFresh graduates and candidates with practical audit experience will be considered, preferably gained with another international accounting network\nGood written and spoken English and Chinese\nGood communication / interpersonal skills\nHigh level of independence and strong motivation\nStrong technical ability and keen to\u00a0develop\u00a0a career in the audit profession\n\nCompetitive package will be offered to the right candidate(s), including 5 day work week, paid examination & study leave,\u00a0reimbursement for examination fees,\u00a0subsidy of examination revision course fees, birthday leave & medical insurance coverage. Interested parties please send full resume with working experience, academic and professional qualifications, including present & expected salary by clicking the \"Apply Now\" button.\u00a0 Personal data collected will be used for recruitment purposes only.\n\nSimply click the \u201cApply Now\u201d button\n\nPlease visit our website at\u00a0www.moore.hk\u00a0to know more about us.", "employment_types": ["Full Time", "Permanent"], "selling_points": ["Apart from working on audit assignments", "Degree holder, majoring in accountancy/finance", "Fresh graduates will also be considered"], "locations": ["Tsim Sha Tsui"], "categories": ["Accounting", "Accountant", "Audit", "Others"], "post_time": "2022-01-15T03:49:47Z", "salary": {"currency": null, "max": null, "min": null, "period": "monthly", "term": null}, "salary_visible": false, "title_keywords": ["audit staff"], "responsibilities": ["due diligence reviews", "audit", "financial reporting", "ad-hoc projects", "planning"], "requirements": {"degrees": ["degree holder"], "majors": ["finance", "accountancy"], "languages": ["english", "chinese"], "language_level": ["good"], "hard_skills": [], "soft_skills": ["communication", "keen", "interpersonal skills"], "languages_combined": [{"language": "english", "language_level": ["good"]}, {"language": "chinese", "language_level": ["good"]}]}, "experience_required": {"duration": [], "field": ["audit experience", "accounting"]}}, {"job_id": "100003008990729", "location_code": "hk", "company": "HLB Hodgson Impey Cheng Limited", "job_title": "Audit Accountant I/ Audit Accountant II", "description": "Requirements\n\nBachelor degree holder (Major in Accounting is preferred)\nGood command of both written and spoken in English and Chinese\nFresh graduates will also be considered\n\nWe offer 5 days work. Interested parties please send your resume with expected salary and availability to the\u00a0Human Resources Department\u00a0(AAD 1), HLB Hodgson Impey Cheng Limited, 31/F Gloucester Tower, The Landmark, 11 Pedder Street, Central, Hong Kong or via email to AHon\uff20hic.com.hk\n\nPersonal data collected will be used for recruitment purposes only.", "employment_types": ["Full Time", "Permanent"], "selling_points": ["5-days work, Medical insurance, Exam/ Study Leave", "Degree holder (Fresh Graduates also welcome)", "Opportunity to gain audit experience in listed co."], "locations": ["Central & Western Area"], "categories": ["Accounting", "Accountant", "Audit", "Others"], "post_time": "2022-01-16T21:50:06Z", "salary": {"currency": null, "max": null, "min": null, "period": "monthly", "term": null}, "salary_visible": false, "title_keywords": ["accountant"], "responsibilities": [], "requirements": {"degrees": ["bachelor degree holder"], "majors": ["accounting"], "languages": ["english", "chinese"], "language_level": ["good command"], "hard_skills": [], "soft_skills": [], "languages_combined": [{"language": "english", "language_level": ["good command"]}, {"language": "chinese", "language_level": ["good command"]}]}, "experience_required": {"duration": [], "field": []}}, {"job_id": "100003009053134", "location_code": "hk", "company": "Vision A. S. Limited", "job_title": "ASSISTANT ACCOUNTANT (ACCOUNTS DEPT) & AUDIT ASSISTANT, SEMI-SENIOR, SENIOR", "description": "Requirements:\n\nDegree holder/ IVE graduate in Accountancy\n\nHKICPA/ ACCA/ HKAAT student member or equivalent\nExperience is preferred but not essential. Fresh Graduate is also considered\nCandidate who with good book-keeping/audit experience will be considered as Accountant, Semi-Senior or Senior\nGood command in written and spoken English, Cantonese and Mandarin\nProficient in MS Word and Excel\nIndependently and reliable capability\nImmediate available is preferred\n\n\n\nWe offer 5 days work per week (Mon to Fri : 9:30 am - 6:00 pm), study & examination leave, performance bonus and attractive remuneration package to the right candidate.\n\nInterested candidates please send your full resume with present and expected salary by clicking \"Apply Now\"\n\n\nPersonal data collected will be used for recruitment purpose only.\n\n", "employment_types": ["Full Time", "Permanent"], "selling_points": ["Degree holder/ IVE graduate in Accountancy", "HKICPA/ ACCA/ HKAAT student member or equivalent", "5 days work per week Mon to Fri : 9:30 am-6:00 pm"], "locations": ["Wan Chai"], "categories": ["Accounting", "Audit", "Others"], "post_time": "2022-01-17T06:02:55Z", "salary": {"currency": null, "max": null, "min": null, "period": "monthly", "term": null}, "salary_visible": false, "title_keywords": ["assistant accountant", "assistant"], "responsibilities": ["book-keeping", "audit"], "requirements": {"degrees": ["fresh graduate", "degree holder"], "majors": ["accountancy"], "languages": ["cantonese", "english", "mandarin"], "language_level": ["good command"], "hard_skills": ["ms word", "excel", "acca", "hkicpa"], "soft_skills": ["independently", "reliable"], "languages_combined": [{"language": "cantonese", "language_level": ["good command"]}, {"language": "english", "language_level": ["good command"]}, {"language": "mandarin", "language_level": ["good command"]}]}, "experience_required": {"duration": [], "field": ["audit experience"]}}, {"job_id": "100003009054469", "location_code": "hk", "company": "Honor Information Technology Co., Limited", "job_title": "Treasury & Auditors - HK Finance dept.", "description": "Position Description:\n\nResponsible for the Hong Kong subsidiary's capital plan and budget forecast, to ensure the safety of the treasury, and timely feedback the capital budget forecast to the headquarters cash team;\nResponsible for financial support\uff1b\nResponsible for the Hong Kong subsidiary's budget review and budget model optimization, and formulate the FX control plan;\nResponsible for local accounting and audit support\u3002\n\nWork Experience Requirements:\n\nBachelor degree or above in accounting/finance/business or other related majors\nHands on experience and proven track record of cash and liquidity management\nExcellent analytical, interpersonal and presentation skills\nGood command of English/mandarin and communication skills\nGood problem solving capability, and coordination skills\nHave a thorough understanding of derivatives, hedging, investments, bank account management, and international funds flows.\nStrong local bank relationships\n\nPersonal Characteristics:\n\nGood communication skills, able to work under pressure.\n\nAdditional Information:\n\n\u00a0\u00a0\u00a0\u00a0\u00a0\u00a0\u00a0 Monday to Friday-office hour\n\u00a0\u00a0\u00a0\u00a0\u00a0\u00a0\u00a0 Work location: Tsim Sha Tsui\n\u00a0\u00a0\u00a0\u00a0\u00a0\u00a0\u00a0 Medical Insurance\n\u00a0\u00a0\u00a0\u00a0\u00a0\u00a0\u00a0 We offer attractive remuneration package and excellent career opportunities to the right candidates. Interested parties please send your full resume with available, current and expected salary to The Human Resources Department, Honor Information Technology Co., Limited\nExcellent conditions, salary can be negotiated face to face", "employment_types": ["Full Time", "Permanent"], "selling_points": ["Opportunity for career progression", "International exposure", "Stable working environment"], "locations": ["Tsim Sha Tsui"], "categories": ["Accounting", "Audit", "Treasurer"], "post_time": "2022-01-17T09:40:58Z", "salary": {"currency": null, "max": null, "min": null, "period": "monthly", "term": null}, "salary_visible": false, "title_keywords": [], "responsibilities": ["control", "management", "review", "budget", "audit", "communication", "forecast", "plan", "coordination", "work under pressure"], "requirements": {"degrees": ["degree or above", "bachelor"], "majors": ["business", "finance", "accounting"], "languages": ["english", "mandarin"], "language_level": ["good command"], "hard_skills": ["problem solving"], "soft_skills": ["communication skills", "coordination skills", "responsible", "timely", "problem solving", "presentation skills", "hands on", "thorough", "interpersonal", "work under pressure"], "languages_combined": [{"language": "english", "language_level": ["good command"]}, {"language": "mandarin", "language_level": ["good command"]}]}, "experience_required": {"duration": [], "field": ["management"]}}, {"job_id": "100003009045712", "location_code": "hk", "company": "Crowe (HK) CPA Limited", "job_title": "Junior / Senior Associates - Audit & Assurance", "description": "Requirements:\n\nTertiary education in related disciplines\n1 year audit experience; candidates with more experience will be considered as Senior Associate\nProficiency in English and Chinese (Cantonese and Putonghua)\nCandidates who are interested in audit field with degree holder in other majors / disciplines are also welcome to apply\nSalary will be commensurate with qualification and experience.\u00a0 We offer generous compensation and\u00a0 benefits to the right candidates, including bonus scheme, medical and life insurance, 5-day work week, study & examination leave and birthday leave.\nPlease apply with resume giving full personal particulars, employment history, present and expected salary together with contact telephone number by clicking \"Apply Now\" or by post to: Human Resources Department, Crowe (HK) CPA Limited, 9/F., Leighton Centre, 77 Leighton Road, Causeway Bay, Hong Kong.\nPersonal data provided by job applicants will be used strictly in accordance with employer's personal data policies.\u00a0 A copy of which will be provided immediately upon request.", "employment_types": ["Full Time", "Permanent"], "selling_points": ["5-day work week; Study & Exam Leave", "Competitive package with Bonus Scheme", "Promising career prospects / Fast promotion path"], "locations": ["Causeway Bay"], "categories": ["Accounting", "Accountant", "Audit", "Professional Services", "Business Consultancy"], "post_time": "2022-01-13T10:48:09Z", "salary": {"currency": null, "max": null, "min": null, "period": "monthly", "term": null}, "salary_visible": false, "title_keywords": ["junior"], "responsibilities": ["policies", "audit", "contact", "personal data", "insurance"], "requirements": {"degrees": ["degree holder"], "majors": [], "languages": ["cantonese", "putonghua", "english", "chinese"], "language_level": ["proficiency"], "hard_skills": ["cpa", "scheme"], "soft_skills": ["interested in"], "languages_combined": [{"language": "cantonese", "language_level": []}, {"language": "putonghua", "language_level": []}, {"language": "english", "language_level": ["proficiency"]}, {"language": "chinese", "language_level": ["proficiency"]}]}, "experience_required": {"duration": ["1 year"], "field": ["audit experience"]}}, {"job_id": "100003009035204", "location_code": "hk", "company": "CBD", "job_title": "Auditor all grades (Work life balance and 5 days work with high pay)", "description": "We are hiring the below posts for CBD CPA LIMITED, an CPA firm in Kwun Tong, a worldwide network of independent accounting firms and business advisers. We invite a suitable candidate to fill the following vacancy :-\n\n\nAudit Junior / Semi Senior / Senior / Supervisor / Manager\n\nThe candidate will be in charge of completing various assignments either independently or as a team while reporting to his/her manager in areas such as audit, accountancy and tax compliance including but not limited to the preparation of financial statements, filing of profits and personal tax returns, and responding to IRD enquiries.\n\n\u00a0Requirements:\n\nDegree/Diploma in Accounting or related discipline\n1-5 years working experience in audit field (Fresh graduate is also welcome)\n\nAble to work under pressure and meet deadlines\nAble to work independently\nGood communication in English and Mandarin\nKnowledge of accounting software (especially \u201cQUICKBOOK\u201d) will be advantageous\nProficiency in MS Word, Excel and Chinese Word Processing\nBe proactive by taking initiative and work as a team\nExcellent analytical, interpersonal and communication skills\nBenefits:\n12 days annual leave\n\nBirthday leave, study leave and exam leave\nOT compensation and Medical claim\nWork-Life Balance\nCaring Company and CBD Working location\nFlexible working arrangement\n\nWe offer an attractive remuneration package, excellent career prospect in a warm and friendly atmosphere. Our continuing expansion and growth offer more promotion opportunities.\n\nApplication with personal resume and expected salary should be sent to Ray Wong, Principal of CBD CPA Limited.\n\nPersonal data collected will be used for recruitment purpose only.", "employment_types": ["Full Time", "Permanent"], "selling_points": ["Audit Junior semi senior supervisor", "Salary HK$15K or above, 5 days work", "Warm and friendly atmosphere"], "locations": ["Ngau Tau Kok"], "categories": ["Accounting", "Accountant", "Accounting Clerk / Supervisor", "Audit"], "post_time": "2022-01-16T21:50:10Z", "salary": {"currency": null, "max": null, "min": null, "period": "monthly", "term": null}, "salary_visible": false, "title_keywords": [], "responsibilities": ["tax", "reporting", "software", "compliance", "audit", "financial statements", "communication", "work under pressure"], "requirements": {"degrees": ["diploma", "degree", "fresh graduate"], "majors": ["accounting"], "languages": ["english", "chinese", "mandarin"], "language_level": ["proficiency", "good"], "hard_skills": ["excel", "chinese word processing", "accounting software", "cpa", "ms word"], "soft_skills": ["communication skills", "work independently", "independently", "independent", "work as a team", "interpersonal", "communication", "meet deadlines", "proactive", "initiative", "work under pressure"], "languages_combined": [{"language": "english", "language_level": ["good"]}, {"language": "chinese", "language_level": ["proficiency"]}, {"language": "mandarin", "language_level": ["good"]}]}, "experience_required": {"duration": ["1-5 years"], "field": ["audit"]}}, {"job_id": "100003009052823", "location_code": "hk", "company": "Morgan Half International (Hong Kong) Limited", "job_title": "Audit manager / Audit senior / Audit Junior (2nd Tiers and local CPA firms) - Multiple headcounts", "description": "Multiple headcounts:\n\nWe are now helping multiple CPA firms (Including 2nd Tiers and local CPA firms) looking for audit and technical staffs. No matter you are looking for work life balance or listed company audit exposure or even financial institutions audit exposure, we have jobs referral to you. Currently, we have positions ranging from audit junior to audit senior manager position and technical manager positions. If you are looking forward to any job opportunities in CPA firms, please kindly submit your profile to us and we will get back to you ASAP.\u00a0\n\nRequirements:\n\nBachelor degree holder\nGood team player\nWelcome fresh graduate / experienced audit candidates\u00a0\n\nTo apply online, please press \"Apply Now\" button below. For any inquiries, please email info @morganhalf.com", "employment_types": ["Full Time", "Temporary"], "selling_points": ["Multiple CPA firm headcounts", "Good package", "5 working days"], "locations": ["Not Specified"], "categories": ["Accounting", "Accountant", "Audit", "Taxation"], "post_time": "2022-01-17T04:10:47Z", "salary": {"currency": null, "max": null, "min": null, "period": "monthly", "term": null}, "salary_visible": false, "title_keywords": ["manager", "junior"], "responsibilities": ["audit"], "requirements": {"degrees": ["fresh graduate", "bachelor degree holder"], "majors": [], "languages": [], "language_level": [], "hard_skills": ["cpa", "no"], "soft_skills": ["good team player"], "languages_combined": []}, "experience_required": {"duration": [], "field": []}}, {"job_id": "100003009049265", "location_code": "hk", "company": "Baker Tilly Hong Kong", "job_title": "Audit Associate", "description": "Requirements:\n\n-\u00a0University graduate in Accountancy or Business Administration\n\n- 1 year\u00a0relevant experience on audit\n\n- Fluency on both spoken and written\u00a0English and Chinese, including Mandarin\u00a0\u00a0\n\n- Good communication and interpersonal skills\n\n- Strong sense of responsibility and must be a good teamplayer\n\nWe offer an attractive remuneration package, interesting job exposure, excellent career growth prospects in a warm and friendly atmosphere. Our continuing expansion and growth offer numerous development opportunities to the incumbents.\u00a0\n\nIf you consider yourself the appropriate choice, please forward your CV and salary expectations with the application form\u00a0to the Human Resources Department, 2/F 625 King\u2019s Road, North Point, Hong Kong or by\u00a0clicking \u201cApply Now\u201d.\u00a0\u00a0\u00a0\n\nDownload Application Form\n\nSelected candidates will be notified by phone for interview arrangements within 6 weeks. Applications of unsuccessful candidates will be deleted immediately after screening.\n\nPersonal data provided by job applicants will be used strictly in accordance with the Employer's Personal Data Policies, a copy of which will be provided upon request.\n\nBaker Tilly Hong Kong\u00a0is a leading firm of certified public accountants and business advisers, specialising in providing clients with a range of integrated services. Our firm is driven by 300 directors and professional staff based in Hong Kong.", "employment_types": ["Full Time", "Permanent"], "selling_points": ["1 year relevant experience from CPA firms", "University graduate in Accountancy", "Fluency on English and Chinese"], "locations": ["Quarry Bay"], "categories": ["Accounting", "Accountant", "Audit", "Others"], "post_time": "2022-01-14T08:20:40Z", "salary": {"currency": null, "max": null, "min": null, "period": "monthly", "term": null}, "salary_visible": false, "title_keywords": ["associate"], "responsibilities": ["communication", "audit", "administration"], "requirements": {"degrees": ["university graduate"], "majors": ["business administration", "accountancy"], "languages": ["english", "chinese", "mandarin"], "language_level": ["fluency"], "hard_skills": [], "soft_skills": ["communication and interpersonal skills", "sense of responsibility"], "languages_combined": [{"language": "english", "language_level": ["fluency"]}, {"language": "chinese", "language_level": ["fluency"]}, {"language": "mandarin", "language_level": ["fluency"]}]}, "experience_required": {"duration": ["1 year"], "field": ["relevant experience", "audit"]}}, {"job_id": "100003009052162", "location_code": "hk", "company": "BDO", "job_title": "Associate - Risk Advisory Services (2022 Jan Intake)", "description": "As an Associate in our Risk Advisory Services Department, you will participate in internal audits reviews and advisory engagement.\n\nResponsibilities\n\nParticipate in internal audits review and/or advisory engagements\u00a0\nAssist to provide input to management leaders on suggestions to improve client internal controls\nPrepare\u00a0accurate documentation and high quality reports\nMaintain relationships with key client personnel to obtain an understanding of business operations, processes and functions\nPerform any ad-hoc duties as assigned\n\nRequirements\n\nBachelor degree in Accounting, Finance, Economics or Business related discipline\nAbility to handle\u00a0multi-task successfully while working independently or within a group environment\u00a0\nWilling to learn new knowledge and open to take up new challenges\nExcellent communication and interpersonal skills\nExcellent command of both written and spoken English and Chinese; including Mandarin\nProven ability to work in a deadline-driven environment and willing to travel frequently\nBe passionate for providing exceptional quality service and striving for exceeding clients\u2019 expectations", "employment_types": ["Full Time", "Permanent"], "selling_points": ["Excellent opportunity of career growth", "Good exposure in a sizable CPA firm", "Birthday Leave, Medical and Life Insurance, etc."], "locations": ["Sheung Wan"], "categories": ["Accounting", "Audit", "Consulting", "Professional Services", "Business Consultancy"], "post_time": "2022-01-17T02:17:57Z", "salary": {"currency": null, "max": null, "min": null, "period": "monthly", "term": null}, "salary_visible": false, "title_keywords": ["associate"], "responsibilities": ["maintain relationships", "management", "documentation", "operations", "review", "quality", "reports", "ad-hoc duties", "audits"], "requirements": {"degrees": ["degree", "bachelor"], "majors": ["business", "finance", "accounting", "economics"], "languages": ["english", "chinese", "mandarin"], "language_level": ["excellent"], "hard_skills": [], "soft_skills": ["passionate", "independently", "multi-task", "willing to learn", "communication and interpersonal skills", "driven"], "languages_combined": [{"language": "english", "language_level": ["excellent"]}, {"language": "chinese", "language_level": ["excellent"]}, {"language": "mandarin", "language_level": []}]}, "experience_required": {"duration": [], "field": []}}, {"job_id": "100003009054160", "location_code": "hk", "company": "The Hong Kong Polytechnic University", "job_title": "Associate Accountant (Accounting Operations Section)", "description": "FINANCE OFFICE\n\nAssociate Accountant (Accounting Operations Section) (Ref. 22011708-E4)\n\nDuties\n\nThe appointee will be required to:\n\n(a) perform staff cost analyses and projections for the management and funding bodies;\n\n(b) assist in reviewing and outlining the financial implications on pay level and adjustment reviews for Council\u2019s decision;\n\n(c) assist in enhancement and implementation of systems related to payroll, staff claims and payments;\n\n(d) supervise daily operations of payroll, benefits, staff claims and related payments of the University and its subsidiaries, including verifying payments and related tax filing, and ensuring compliance with the relevant statutory requirements, policies, rules and regulations;\n\n(e) handle general office administration; and\n\n(f) perform any other duties as assigned by the Director of Finance and her delegates.\n\nQualifications\u00a0\n\nApplicants should have:\n\n(a) a recognized degree in Accounting or related disciplines;\n\n(b) a professional accounting qualification or equivalent;\n\n(c) at least three years of post-qualification experience in accounting, auditing or other related fields, preferably with experience in payroll operations, staff benefits, claims processing and/or system enhancement;\u00a0\n\n(d) some supervisory experience;\n\n(e) proficiency in Microsoft Office software including Excel, Word and PowerPoint;\n\n(f) a good command of both written and spoken English and Chinese; and\n\n(g) good communication and interpersonal skills.\n\nShortlisted candidates will be invited to sit for a written test.\n\nApplicants who have responded to the previous advertisement need not re-apply.\n\nRemuneration and Conditions of Service\n\nA highly competitive remuneration package will be offered. \u00a0Initial appointment will be on a fixed-term gratuity-bearing contract.\u00a0 Re-engagement thereafter is subject to mutual agreement.\u00a0 Applicants should state their current and expected salary in the application.\n\nApplication\n\nPlease send a completed application form by post to Human Resources Office, 13/F, Li Ka Shing Tower, The Hong Kong Polytechnic University, Hung Hom, Kowloon, Hong Kong or via email by clicking \"Apply Now\".\u00a0 Application forms can be downloaded from https://www.polyu.edu.hk/hro/careers/guidelines_and_forms/forms.\u00a0 If a separate curriculum vitae is to be provided, please still complete the application form which will help speed up the recruitment process. The closing date for application is Monday, 31 January 2022.\u00a0 Applicants who are not invited to an interview within two months from the closing date should consider their applications unsuccessful. The University\u2019s Personal Information Collection Statement for recruitment can be found at https://www.polyu.edu.hk/hro/careers/guidelines_and_forms/pics_for_recruitment.\n\nPolyU is an equal opportunity employer committed to diversity and inclusivity.\u00a0 All qualified applicants will receive consideration for employment without regard to gender, ethnicity, nationality, family status or physical or mental disabilities.", "employment_types": ["Full Time"], "selling_points": [], "locations": ["Not Specified"], "categories": ["Accounting", "Accountant", "Accounting Clerk / Supervisor", "Audit"], "post_time": "2022-01-17T08:40:30Z", "salary": {"currency": null, "max": null, "min": null, "period": null, "term": null}, "salary_visible": false, "title_keywords": ["operations", "associate", "accountant", "accounting"], "responsibilities": ["regulations", "any other duties", "software", "operations", "communication", "statutory requirements", "office administration", "tax filing", "compliance", "implementation", "cost", "management", "daily operations", "recruitment process", "payroll", "policies", "systems", "payments", "recruitment", "auditing"], "requirements": {"degrees": ["degree"], "majors": ["related disciplines", "accounting"], "languages": ["english", "chinese"], "language_level": ["good command"], "hard_skills": ["excel", "word", "powerpoint", "c", "microsoft office software", "processing"], "soft_skills": ["committed", "communication and interpersonal skills"], "languages_combined": [{"language": "english", "language_level": ["good command"]}, {"language": "chinese", "language_level": ["good command"]}]}, "experience_required": {"duration": ["at least three years"], "field": ["post-qualification", "related", "payroll", "supervisory experience", "accounting"]}}, {"job_id": "100003009051658", "location_code": "hk", "company": "Tung Wah Group of Hospitals", "job_title": "Audit Clerk (REF: A3/AC/AD/JOBS)", "description": "Location: Sheung Wan\n\n\nRoles & responsibilities:\nConduct risk-based audits and reviews;\ndraft audit schedules in accordance with pre-defined audit scope and objectives for the superiors\u2019 consideration;\nsolicit and gather information relevant to audit assignments;\nconduct audit tests, including the compliance and substantive tests;\nidentify audit findings and provide value-added recommendations;\nanalyze and consolidate audit findings to report to superiors;\nassist administrative work of audit team; and\nassist in documenting audit findings.\nThe ideal candidate should possess:\n\n(a) Basic Certificate/Higher Certificate/Diploma in Accounting or Business Administration with 1 year\u2019s accounting/auditing experience; or\n(b) Associate Degree/Higher Diploma/Professional Diploma in Accounting or Business Administration;\n5 passes in HKCEE including Chinese Language, English Language (Syl.B) and Mathematics or equivalent;\nproper technical and communication skills; and\nqualities of hardworking and attentive to details.\n(Please specify in the resume or application form the relevant academic results/qualifications and working experience you have attained in detail.)\n\n\nCompensation & employment terms:\nThe successful candidate will initially be offered a 2-year contract with a remuneration package which will be commensurate with his/her background and experience. The continuation of employment and employment terms thereafter will be subject to mutual agreement. Apart from contributions to the MPF Scheme, other benefits include paid annual leave, medical services, a dental scheme and training sponsorships. The incumbent will normally work under a 5-day week schedule subject to operational needs and exigencies of the service.\n\n\nApplication:\n\nPlease send your resume or a completed application form [F601(n)] with indication of your current and expected salaries to the Head of Human Resources Division, Tung Wah Group of Hospitals at 4/F., Wong Fung Ling Memorial Building, 12 Po Yan Street, Hong Kong by 18 January 2022.\u00a0 Application forms are obtainable in person or can be downloaded from http://www.tungwah.org.hk.\u00a0 The reference code should be marked both in the letter and on the envelope.\u00a0 Underpaid mail items will not be accepted by Tung Wah.\u00a0 For proper delivery of your mail items, please ensure your mail items bear sufficient postage with return address before posting.\u00a0 Personal data provided by applicants will be used strictly for recruitment purpose only and in accordance with the Tung Wah\u2019s personal data policy.\u00a0 Applicants not invited to attend an interview by 30 April 2022 may assume that their applications are unsuccessful.\nWE ARE AN EQUAL OPPORTUNITIES EMPLOYER", "employment_types": ["Full Time", "Contract"], "selling_points": [], "locations": ["Sheung Wan"], "categories": ["Accounting", "Audit", "Public / Civil", "Social Services - Community / Non-profit Organization"], "post_time": "2022-01-16T21:50:33Z", "salary": {"currency": null, "max": null, "min": null, "period": "monthly", "term": null}, "salary_visible": false, "title_keywords": ["audit clerk"], "responsibilities": ["administration", "administrative work", "schedules", "compliance", "audit", "communication", "audits", "auditing", "report"], "requirements": {"degrees": ["certificate", "diploma", "associate degree", "higher certificate"], "majors": ["accounting", "business administration"], "languages": ["english", "chinese"], "language_level": [], "hard_skills": ["wan", "basic"], "soft_skills": ["communication skills", "attentive to details", "hardworking", "ideal"], "languages_combined": [{"language": "english", "language_level": []}, {"language": "chinese", "language_level": []}]}, "experience_required": {"duration": ["2-year", "1 year"], "field": ["accounting", "business administration"]}}, {"job_id": "100003009039732", "location_code": "hk", "company": "Manuel S. F. Tjon & Co.", "job_title": "AUDIT STAFF / ACCOUNTS CLERK", "description": "An expanding CPA firm in Mong Kok and an Authorised Employer of the Hong Kong Institute of Certified Public Accountants needs candidates as follows:\n\nFamiliar with MS Excel\n\nGood command of spoken and written English and Chinese\n\nGood interpersonal skills\n\nAUDIT TRAINEE /\u00a0INTERMEDIATE\u00a0\u00a0\n\nDiploma or Degree holder in accounting\n\nFresh graduates with no experience will be considered as audit trainee.\u00a0\n\nAt least two years solid auditing experience for audit intermediate\n\nASSISTANT ACCOUNTANT / ACCOUNTANT\n\nF.5 or above, IVE or equivalent with at least one year relevant working experience\n\nAt least three years solid accounting experience in CPA firm for Accountant.\n\nAble to prepare full set of accounts for various clients of the firm.\n\nExperience in Peachtree is advantageous\n\nPLEASE SEND DETAILED RESUME WITH EXPECTED SALARY AND AVAILABILITY BY CLICKING \"APPLY NOW\" BUTTON", "employment_types": ["Full Time", "Permanent"], "selling_points": [], "locations": ["Mong Kok"], "categories": ["Accounting", "Accountant", "Accounting Clerk / Supervisor", "Audit"], "post_time": "2022-01-15T03:49:13Z", "salary": {"currency": null, "max": null, "min": null, "period": "monthly", "term": null}, "salary_visible": false, "title_keywords": ["audit staff", "accounts clerk"], "responsibilities": ["full set of accounts", "audit", "auditing"], "requirements": {"degrees": ["diploma", "degree holder"], "majors": ["accounting"], "languages": ["english", "chinese"], "language_level": ["good command"], "hard_skills": ["no", "hong kong institute of certified public accountants", "cpa", "ms excel", "peachtree"], "soft_skills": ["interpersonal skills", "detailed"], "languages_combined": [{"language": "english", "language_level": ["good command"]}, {"language": "chinese", "language_level": ["good command"]}]}, "experience_required": {"duration": ["at least one year", "at least two years", "at least three years"], "field": ["accounting experience", "relevant working experience", "cpa firm", "audit"]}}, {"job_id": "100003009039271", "location_code": "hk", "company": "LIF & Wong CPA Limited", "job_title": "Audit Professionals - Associate / Senior Associate", "description": "Job description\n\nHandling audit and assurance and special engagements for a wide range of clients, including listed clients, under direct supervision of auditors / managers / partners in-charge\nParticipate in specific projects such as internal control review and IPO projects\nCorporate and individual tax compliance assignments\nAssist to complete ad-hoc assignments\nLiaison with clients for job coordination\n\nRequirements\n\nDegree or associate degree holder in Accounting / Finance or related discipline;\nFresh graduate to 5 years working experience in professional CPA firms (other related accounting experience is considered)\n\nAbility to work independently and as a team member in a challenging environment;\nAble to communicate effectively in English, Chinese and Putonghua;\nProficient in using MS Word and Excel; knowledge of MYOB and/or XERO would be an advantage;\nDemonstrate flexibility to travel to the customer locations on need basis; and\nImmediately available is preferred.\n\nWhat we offered?\n\n5-days work week\nDouble pay and discretionary bonus\u00a0\nGood training and extensive job exposure\u00a0\nSponsored lectures organised by reputable accountancy bodies\n\nMedical welfare\nTraveling and meal allowance / hardship\nStudy and Exam leave\nCompensation leave\nBirthday leave", "employment_types": ["Full Time"], "selling_points": ["5-days work week", "Double pay & discretionary bonus", "Study, exam & birthday leave"], "locations": ["Sheung Wan"], "categories": ["Accounting", "Audit"], "post_time": "2022-01-14T10:41:42Z", "salary": {"currency": null, "max": null, "min": null, "period": "monthly", "term": null}, "salary_visible": false, "title_keywords": ["senior associate", "associate"], "responsibilities": ["tax", "ad-hoc assignments", "compliance", "review", "audit", "coordination", "internal control"], "requirements": {"degrees": ["associate degree", "degree", "fresh graduate"], "majors": ["finance", "accounting"], "languages": ["putonghua", "english", "chinese"], "language_level": [], "hard_skills": ["excel", "xero", "cpa", "myob", "ms word"], "soft_skills": ["work independently", "team member"], "languages_combined": [{"language": "putonghua", "language_level": []}, {"language": "english", "language_level": []}, {"language": "chinese", "language_level": []}]}, "experience_required": {"duration": ["5 years"], "field": ["related", "accounting experience"]}}, {"job_id": "100003009051857", "location_code": "hk", "company": "CK Asset Holdings Limited", "job_title": "Senior Auditor, Internal Audit (PRC Team)", "description": "Qualified Accountant with a Degree in Accounting / Business related studies\nAt least 8 years relevant experience in sizable corporation, preferably with PRC exposure and in the field of Statutory Audit / Internal Audit\nKnowledgeable in PRC accounting and taxation\nPossession of good business report writing skills is a must\nSelf-motivated, capable of working independently and under pressure\nThoroughly conversant with MS Office is essential\nProficiency in written & spoken English & Mandarin\nFrequent travel to PRC is required\nWe will offer attractive compensation package to the right candidate.\u00a0 Please send application enclosing resume stating career and salary history, expected salary and date of availability to The Senior Manager, Human Resources Department, CK Asset Holdings Limited, 7/F., Cheung Kong Center, 2 Queen's Road Central, Hong Kong or by clicking \"Apply Now\" (in Word format).\u00a0 Please quote the reference of the position you apply for in all correspondences.\u00a0\n\nWe are an equal opportunity employer and welcome applications from all qualified candidates.\u00a0 Personal data collected will be treated in strictest confidence and handled confidentially by authorized personnel for recruitment-related purposes with the Group.\u00a0 Applicant not hearing from us within six weeks from the date of advertisement may consider their applications unsuccessful.\u00a0", "employment_types": ["Full Time", "Permanent"], "selling_points": ["Qualified Accountant and Degree holder", "Over 8 years of relevant working experience", "Preferably exp. on Statutory Audit/Internal Audit"], "locations": ["Central"], "categories": ["Accounting", "Audit"], "post_time": "2022-01-17T01:23:43Z", "salary": {"currency": null, "max": null, "min": null, "period": "monthly", "term": null}, "salary_visible": false, "title_keywords": [], "responsibilities": ["taxation", "internal audit", "audit", "recruitment", "personal data", "report"], "requirements": {"degrees": ["degree"], "majors": ["business", "accounting"], "languages": ["english", "mandarin"], "language_level": ["proficiency"], "hard_skills": ["ms office", "word", "writing skills", "prc accounting"], "soft_skills": ["self-motivated", "independently", "under pressure", "capable", "confidence", "writing skills"], "languages_combined": [{"language": "english", "language_level": ["proficiency"]}, {"language": "mandarin", "language_level": ["proficiency"]}]}, "experience_required": {"duration": ["at least 8 years"], "field": ["relevant experience", "audit"]}}, {"job_id": "100003009043218", "location_code": "hk", "company": "Hutchison Property Management Company Limited", "job_title": "ACCOUNTANT [Ref. A-PRC]", "description": "Degree holder in Accounting and qualified member of ACCA / HKICPA or equivalent\nMinimum 3 years' relevant experience in financial and management accounting, preferably with consolidation experience\nAudit experience in sizable audit firm an advantage\nKnowledge in PRC to HK GAAP conversion\nReview full set of accounts, accounting schedule, budget, forecast, financial analysis and management reports\nReview monthly treasury reports of PRC and offshore companies\nPrepare and review audited accounts and management accounts\nHandle Hong Kong Profits Tax computation and CBCR reporting\nAnalytical, self-motivated, detail-oriented and able to meet tight deadlines\nProficient in Oracle and MS Office\nFluent in written and spoken English and Chinese, including Putonghua\n\nWe offer salary and benefits commensurate with qualifications and experience. Please send a full resume with contact number and expected salary to General Manager - Human Resources & Administration, Hutchison Property Management Company Limited, 3/F., One Harbourfront, 18 Tak Fung Street, Hunghom, Kowloon (Please quote reference on envelope) or by clicking \"Apply Now\".\n\nWe are an equal opportunity employer and welcome applications from all qualified candidates. The information provided will be treated in strict confidence and be used only for consideration of your application for relevant/similar post(s).\n\nApplicants not hearing from us within six weeks from the date of advertisement may consider their applications unsuccessful. All personal data of unsuccessful applicants will be destroyed after the recruitment exercise when no longer required.", "employment_types": ["Full Time", "Permanent"], "selling_points": ["Degree holder", "3 years' relevant experience", "Qualified member of ACCA / HKICPA or equivalent"], "locations": ["Hung Hom"], "categories": ["Accounting", "Accountant", "Audit", "Others"], "post_time": "2022-01-17T11:26:21Z", "salary": {"currency": null, "max": null, "min": null, "period": null, "term": null}, "salary_visible": false, "title_keywords": ["accountant"], "responsibilities": ["reporting", "management", "tax computation", "review", "full set of accounts", "audit", "budget", "financial analysis", "management reports", "reports", "schedule", "forecast"], "requirements": {"degrees": ["degree holder"], "majors": ["accounting"], "languages": ["putonghua", "english", "chinese"], "language_level": ["fluent"], "hard_skills": ["acca", "financial analysis", "hkicpa", "management reports", "ms office", "oracle"], "soft_skills": ["self-motivated", "meet tight deadlines", "detail-oriented"], "languages_combined": [{"language": "putonghua", "language_level": ["fluent"]}, {"language": "english", "language_level": ["fluent"]}, {"language": "chinese", "language_level": ["fluent"]}]}, "experience_required": {"duration": ["minimum 3 years"], "field": ["management accounting", "consolidation", "audit", "relevant experience", "audit experience", "financial"]}}, {"job_id": "100003009049256", "location_code": "hk", "company": "Baker Tilly Hong Kong", "job_title": "Audit Senior", "description": "Requirements:\n\n- University graduate in Accountancy or Business Administration\n\n- Qualified Members or finalist of HKICPA or other relevant professional bodies\n\n-\u00a03-5\u00a0years\u00a0relevant experience from mid-tier CPA firms.\n\n- Experience on audit of listed or sizable multi-national companies would be an advantage\n\n- Fluency on both spoken and written\u00a0English and Chinese\n\n- Good time management\n\n- Good communication and interpersonal skills\u00a0\u00a0\u00a0\n\nWe offer an attractive remuneration package, excellent career prospects in a warm and friendly atmosphere. Our continuing expansion and growth offer numerous opportunities.\n\nIf you consider yourself the appropriate choice, please forward your CV and salary expectations with the application form\u00a0to the Human Resources Department, 2/F 625 King\u2019s Road, North Point, Hong Kong or by\u00a0clicking \u201cApply Now\u201d.\u00a0\u00a0\u00a0\n\nDownload Application Form\n\nSelected candidates will be notified by phone for interview arrangements within 6 weeks. Applications of unsuccessful candidates will be deleted immediately after screening.\n\nPersonal data provided by job applicants will be used strictly in accordance with the Employer's Personal Data Policies, a copy of which will be provided upon request.\n\nBaker Tilly Hong Kong\u00a0is a leading firm of certified public accountants and business advisers, specialising in providing clients with a range of integrated services. Our firm is driven by 300 directors and professional staff based in Hong Kong.", "employment_types": ["Full Time", "Permanent"], "selling_points": ["3-5 years relevant experience from CPA firms", "University graduate in Accountancy", "Fluency on English and Chinese"], "locations": ["Quarry Bay"], "categories": ["Accounting", "Accountant", "Audit", "Others"], "post_time": "2022-01-14T08:19:54Z", "salary": {"currency": null, "max": null, "min": null, "period": "monthly", "term": null}, "salary_visible": false, "title_keywords": [], "responsibilities": ["communication", "management", "audit", "administration"], "requirements": {"degrees": ["university graduate"], "majors": ["business administration", "accountancy"], "languages": ["english", "chinese"], "language_level": ["fluency"], "hard_skills": ["cpa", "hkicpa"], "soft_skills": ["time management", "communication and interpersonal skills"], "languages_combined": [{"language": "english", "language_level": ["fluency"]}, {"language": "chinese", "language_level": ["fluency"]}]}, "experience_required": {"duration": ["3-5 years"], "field": ["relevant experience", "audit"]}}, {"job_id": "100003009045381", "location_code": "hk", "company": "Joe Chiu & Company", "job_title": "Audit Junior (Fresh graduate is welcome)/ Audit Semi-Senior", "description": "Job description:\n\nPerform audit and accounting\u00a0work\nRequirements:\nDiploma/Associate Degree/Degree in Accounting or related disciplines\nApplicant without experience (e.g. fresh graduate) will be considered for the post of Audit Junior\nMinimum 1 year audit experience is preferred for the post of Semi-Senior.\nKnowledge in Microsoft Office such as Word and Excel\nBenefit:\n\nAttractive remuneration package\n5 days work per week\nBank holiday, study leave, exam leave, 10-14 day annual leave\nOn-job training\nNear Mong Kok MTR Station\u00a0\nNo travelling is expected\nFriendly working environment with minimum pressure\nInterested parties please send to us your full resume showing your present and expected salary by clicking \"Apply Now\".\n\n\nPersonal data collected will be used only for recruitment purpose.\n\n\n\n", "employment_types": ["Full Time"], "selling_points": ["5-day work per week", "No travelling is expected; minimum pressure", "Located near Mong Kok MTR Station"], "locations": ["Mong Kok"], "categories": ["Accounting", "Accountant", "Audit"], "post_time": "2022-01-15T02:21:53Z", "salary": {"currency": null, "max": null, "min": null, "period": "monthly", "term": null}, "salary_visible": false, "title_keywords": ["junior"], "responsibilities": ["audit"], "requirements": {"degrees": ["associate degree", "diploma", "degree", "fresh graduate"], "majors": ["related disciplines", "accounting"], "languages": [], "language_level": [], "hard_skills": ["excel", "word", "microsoft office"], "soft_skills": [], "languages_combined": []}, "experience_required": {"duration": ["minimum 1 year"], "field": ["audit experience"]}}, {"job_id": "100003009047626", "location_code": "hk", "company": "D K Mak & Co", "job_title": "Audit Assistant / Audit Senior", "description": "REQUIREMENTS:\n\nHigher Diploma, Associate Degree or Degree holder with major in accounting\nHKICPA ACCA student member\u00a0\n0-2 years of working experience in audit (fresh graduates are welcome) (for Audit Assistant)\nNot less than 3 years\u00a0 audit experience (for Audit Senior)\nGood knowledge in HKFRS and SME standards\nProficient in written /spoken English with Chinese and Putonghua\nSelf-motivated, good interpersonal skill, responsible and independent\nComputer knowledge and proficient in MS office is an advantage\nImmediate available is preferred\n\nWe offer 5 days work with study and examination leave; competitive salary offered will be commensurate with qualification and experience. Interested candidates please send your application letter with full resume stating expected salary and availability by clicking apply now.", "employment_types": ["Full Time", "Part Time"], "selling_points": ["Good knowledge in HKFRS and SME standards", "HKICPA ACCA student member", "5 days work with study and examination leave"], "locations": ["Central"], "categories": ["Accounting", "Accounting Clerk / Supervisor", "Audit", "Others"], "post_time": "2022-01-14T03:36:28Z", "salary": {"currency": null, "max": null, "min": null, "period": "monthly", "term": null}, "salary_visible": false, "title_keywords": ["assistant"], "responsibilities": ["sme", "audit"], "requirements": {"degrees": ["associate degree", "diploma", "degree holder"], "majors": ["accounting"], "languages": ["putonghua", "english", "chinese"], "language_level": ["proficient"], "hard_skills": ["ms office", "acca", "hkfrs", "hkicpa"], "soft_skills": ["self-motivated", "independent", "responsible", "interpersonal skill"], "languages_combined": [{"language": "putonghua", "language_level": []}, {"language": "english", "language_level": ["proficient"]}, {"language": "chinese", "language_level": []}]}, "experience_required": {"duration": ["3 years", "0-2 years"], "field": ["audit experience", "audit"]}}, {"job_id": "100003009051477", "location_code": "hk", "company": "BDO", "job_title": "Senior Associate / Associate - IT Audit (Ref : RAS)", "description": "Responsibilities:\n\nConduct IT audit over general/ application controls, network security, cybersecurity, blockchain platform operations, and apply Computer Assisted Auditing Technique (\"CAAT\") for data verification, cyber hacking incident investigation\nObtain good understanding of IT infrastructure, programs, networks and database, IT security, identify areas of improvement and make recommendations\nPrepare accurate documentation and high quality reports\nMaintain relationship with key client personnel, including management of listed companies, MNC or government departments\nUphold team spirit within the team\nSupport and act towards the BDO Global Vision\nBe committed to act with the firm\u2019s core values and competency expectations\n\n\u00a0Requirements:\n\nDegree holder major in IT, preferably computer science, computer and information security, cybersecurity or related disciplines\nAt least 1 year of experience in either IT Audit, IT Security, system implementation (e.g. ERP/banking system), cybersecurity, investigation of cyber hacking incidents, etc.\nQualified in or Participant of either CISA, CISSP, ISO27001, CEH, CISM or CHFI (Computer Hacking Forensic Investigator) are preferred but not a must\nExcellent command of written and spoken English, Cantonese and Mandarin\nAbility to successfully multitask while working independently or within a group environment\nAbility to work in a deadline-driven environment and willing to travel\nBe passionate for providing exceptional quality service and striving for exceeding clients\u2019 expectations\nPosition offered will commensurate with the experience of the right candidate\n\nWe are an equal opportunity employer, and offer excellent prospects and career development for the right candidate.\u00a0 Interested parties please send your application\u00a0with full career history, current and expected salary by clicking\u00a0Apply Now\u00a0button below.\u00a0\n\nApplications will be treated in strict confidence. Personal data collected will be used for recruitment purposes only.", "employment_types": ["Full Time", "Permanent"], "selling_points": ["Responsible for IT general/ application controls", "At least 1 year of experience", "Excellent Career Prospect"], "locations": ["Sheung Wan"], "categories": ["Accounting", "Audit", "Information Technology (IT)", "IT Auditing", "Security"], "post_time": "2022-01-16T03:49:19Z", "salary": {"currency": null, "max": null, "min": null, "period": "monthly", "term": null}, "salary_visible": false, "title_keywords": ["senior associate", "associate"], "responsibilities": ["make recommendations", "management", "data verification", "it infrastructure", "operations", "quality", "audit", "investigation", "maintain", "reports", "database", "documentation", "auditing"], "requirements": {"degrees": ["degree holder"], "majors": ["related disciplines", "it", "computer science"], "languages": ["cantonese", "english", "mandarin"], "language_level": ["excellent"], "hard_skills": ["system implementation", "erp"], "soft_skills": ["multitask", "independently", "driven", "passionate"], "languages_combined": [{"language": "cantonese", "language_level": ["excellent"]}, {"language": "english", "language_level": ["excellent"]}, {"language": "mandarin", "language_level": ["excellent"]}]}, "experience_required": {"duration": ["at least 1 year"], "field": ["it", "security", "audit"]}}, {"job_id": "100003009051478", "location_code": "hk", "company": "BDO", "job_title": "Manager / Senior Associate / Associate (IT Audit / Audit Analytics) - Assurance", "description": "Responsibilities:\n\nAssist in planning and scoping of client engagements\nConduct IT audit or independent assessment to evaluate system security and control effectiveness\nDesign and apply appropriate data modelling, analytics and visualization techniques in audit engagements\nCommunicate and report findings to senior management and clients\nSupport and act towards the BDO Global Vision\nBe committed to act with the firm\u2019s core values and competency expectations\n\nRequirements:\n\nBachelor degree or above in Information Technology Management, Computer Science, Mathematics, Accounting or other relevant fields\nExperience in auditing, data analytics or programming is a plus but not a must\nAbility to work independently within a team environment\nExcellent command of written and spoken English and Chinese, including Putonghua\nPosition offered will commensurate with the experience of the right candidate\n\nWe are an equal opportunity employer, and offer excellent prospects and career development for the right candidate.\u00a0 Interested parties please send your application\u00a0with full career history, current and expected salary by clicking the\u00a0Apply Now\u00a0button below.\n\nApplications will be treated in strict confidence. Personal data collected will be used for recruitment purposes only.", "employment_types": ["Full Time", "Permanent"], "selling_points": ["Data Modelling, analytics and visualization", "Conduct IT audit / assessment", "Excellent Career Prospects"], "locations": ["Sheung Wan"], "categories": ["Accounting", "Audit", "Professional Services", "Business Analysis / Data Analysis", "Information Technology (IT)", "IT Auditing"], "post_time": "2022-01-16T03:50:00Z", "salary": {"currency": null, "max": null, "min": null, "period": "monthly", "term": null}, "salary_visible": false, "title_keywords": ["senior associate", "associate", "manager"], "responsibilities": ["control", "visualization", "data", "audit", "design", "evaluate", "system security", "report", "senior management", "planning"], "requirements": {"degrees": ["degree or above", "bachelor"], "majors": ["mathematics", "accounting", "computer science", "information technology"], "languages": ["putonghua", "english", "chinese"], "language_level": ["excellent"], "hard_skills": ["data analytics", "plus", "programming"], "soft_skills": ["work independently"], "languages_combined": [{"language": "putonghua", "language_level": ["excellent"]}, {"language": "english", "language_level": ["excellent"]}, {"language": "chinese", "language_level": ["excellent"]}]}, "experience_required": {"duration": [], "field": ["programming"]}}, {"job_id": "100003009047651", "location_code": "hk", "company": "Moore Associates Limited", "job_title": "Audit Manager", "description": "Responsibilities:\n\nWork on audit assignments for clients from a variety of industries, covering Hong Kong and China, especially listed companies\nInvolve in projects such as due diligence and IPO\u00a0\nTake a leader role in particular projects\n\nRequirements: \u00a0\n\nDegree holder majoring in Accountancy / Finance\nAt least 6 years relevant experience, preferably gained with another international accounting and consulting association\nGood written and spoken English and Chinese\nGood communication / interpersonal skills\nHigh level of independence and strong motivation\nStrong technical ability and keen to develop a career in the audit profession\n\nCompetitive package will be offered to the right candidate(s), including 5 day work week, paid examination & study leave, birthday leave & medical insurance coverage. Interested parties please send full resume with working experience, academic and professional qualifications, including present & expected salary by clicking the \"Apply Now\" button.\u00a0 Personal data collected will be used for recruitment purposes only.\n\nSimply click the \u201cApply Now\u201d button.\n\nPlease visit our website at\u00a0www.moore.hk\u00a0to know more about us.", "employment_types": ["Full Time", "Permanent"], "selling_points": ["Audit assignments from a variety of industries", "Take a leader role in particular projects", "At least 6 years relevant experience"], "locations": ["Tsim Sha Tsui"], "categories": ["Accounting", "Audit", "Others"], "post_time": "2022-01-15T03:49:47Z", "salary": {"currency": null, "max": null, "min": null, "period": "monthly", "term": null}, "salary_visible": false, "title_keywords": ["manager"], "responsibilities": ["due diligence", "audit"], "requirements": {"degrees": ["degree holder"], "majors": ["finance", "accountancy"], "languages": ["english", "chinese"], "language_level": ["good"], "hard_skills": [], "soft_skills": ["communication", "keen", "interpersonal skills"], "languages_combined": [{"language": "english", "language_level": ["good"]}, {"language": "chinese", "language_level": ["good"]}]}, "experience_required": {"duration": ["at least 6 years"], "field": ["accounting", "relevant experience", "consulting"]}}, {"job_id": "100003009052024", "location_code": "hk", "company": "Hongkong Managers and Secretaries Limited", "job_title": "PT Auditor", "description": "Our client is a global audit firm and looking for PT Auditor (External) to join the expanding team.\n\nResponsibilities:\n\nWork with a team of audit professionals on a variety of engagements, including advisory services to local and international clients\nResponsible for performing financial, operational and compliance audits\nSupervise and work with the internal audit team\nAble to analyse, appraise evidential information and identify control weaknesses, provide recommendations for improvement, implement control procedures to address compliance risks, liaise with internal clients to formulate action plans\nResponsible for drafting and presenting audit reports to senior management and the Audit Committee\nOther ad-hoc assignments as requested\n\nRequirements:\n\nQualified accountant with minimum 2 years of experience from a Big 4 or sizable CPA firm\nDegree in Accounting/Finance or related discipline\nExcellent interpersonal and communication skills\nGood command of spoken and written communication in English, Cantonese and Mandarin\nEffective team player, self-motivated, responsible, independent and able to work under pressure\nStudent/fresh graduate with less experience will also be welcomed\nImmediate availability is preferred\n\nWorking hours:\n\nThe working hours\u00a0must be 24 hours per week or more and fixed schedule\n\n\n\nInterested parties please submit your application to our mailbox by clicking\u00a0Apply Now.\n\nPersonal data provided in the employment applications will be treated in strict confidence and used only for recruitment purpose.\n\nStudent/fresh graduate with less experiences in Accounting will also welcomed\nStudent/fresh graduate with less experiences in Accounting will also welcomed", "employment_types": ["Part Time"], "selling_points": ["Part time job, work life balance", "Degree holder", "Friendly working environment"], "locations": ["Causeway Bay"], "categories": ["Accounting", "Accountant", "Audit"], "post_time": "2022-01-17T01:52:13Z", "salary": {"currency": null, "max": null, "min": null, "period": "hourly", "term": null}, "salary_visible": false, "title_keywords": [], "responsibilities": ["control", "internal audit", "ad-hoc assignments", "compliance", "procedures", "audit", "liaise with", "provide recommendations", "reports", "audits", "plans", "senior management", "analyse"], "requirements": {"degrees": ["degree", "fresh graduate"], "majors": ["finance", "accounting"], "languages": ["cantonese", "english", "mandarin"], "language_level": ["good command"], "hard_skills": ["cpa"], "soft_skills": ["communication skills", "self-motivated", "independent", "responsible", "communication", "team player", "interpersonal", "work under pressure"], "languages_combined": [{"language": "cantonese", "language_level": ["good command"]}, {"language": "english", "language_level": ["good command"]}, {"language": "mandarin", "language_level": ["good command"]}]}, "experience_required": {"duration": ["minimum 2 years"], "field": ["cpa firm", "big 4"]}}, {"job_id": "100003009044445", "location_code": "hk", "company": "CCOR & Co.", "job_title": "Auditor (Prospects for Partnership)", "description": "Hardworking during office hour, and enjoy free time after work!\n\u65b0\u751f\u6d3b\u614b\u5ea6\u662f, \u4e0a\u73ed\u52e4\u596e\u5c08\u6ce8\u5730\u5de5\u4f5c, \u4e0b\u73ed\u653e\u9b06\u76e1\u60c5\u53bb\u4eab\u6a02\n\n\nLooking for candidate with\u00a0\nSelf-motivated\nIndependent\nResponsible\n\n\n\nRequirements\u00a0\nHolder of a Bachelor\u2019s Degree / Higher Diploma in Accounting or related discipline\nStudent member of HKICPA / ACCA or other professional bodies\nGood communication in English & Mandarin & Cantonese\u00a0\nProficient computer skills, e.g. MS Office and accounting software such as MYOB\n\nPlease send your resume and expected salary by clicking \"Apply Now\"\n(Personal data collected would be used for recruitment only)", "employment_types": ["Full Time", "Permanent"], "selling_points": [], "locations": ["Tsim Sha Tsui"], "categories": ["Accounting", "Audit"], "post_time": "2022-01-14T03:55:28Z", "salary": {"currency": null, "max": null, "min": null, "period": "monthly", "term": null}, "salary_visible": false, "title_keywords": [], "responsibilities": [], "requirements": {"degrees": ["diploma", "degree", "bachelor"], "majors": ["accounting"], "languages": ["cantonese", "english", "mandarin"], "language_level": ["good"], "hard_skills": ["acca", "accounting software", "hkicpa", "computer skills", "myob", "ms office"], "soft_skills": ["communication"], "languages_combined": [{"language": "cantonese", "language_level": ["good"]}, {"language": "english", "language_level": ["good"]}, {"language": "mandarin", "language_level": ["good"]}]}, "experience_required": {"duration": [], "field": []}}, {"job_id": "100003009053889", "location_code": "hk", "company": "E & K Cleaning Services Limited", "job_title": "\u6703\u8a08\u4e3b\u4efb", "description": "\n\u8077\u8cac :\u8655\u7406\u5168\u76e4\u6703\u8a08\u5e33\u76ee\uff1b\u8ca0\u8cac\u65e5\u5e38\u6703\u8a08\u4e8b\u52d9\uff0c\u4f8b\u5982AR/AP\uff1b\u8ddf\u9032\u5ba2\u6236\u672a\u4ed8\u6b3e\u9805\uff1b\u88fd\u4f5c\u6bcf\u6708\u8ca1\u52d9\u5831\u544a\uff1b\u5354\u52a9\u5e74\u5ea6\u5be9\u8a08\u53ca\u5831\u7a05\u4e8b\u5b9c\uff1b\u5354\u52a9\u8fa6\u516c\u5ba4\u884c\u653f\u5de5\u4f5c\u53ca\u5176\u4ed6\u6307\u6d3e\u5de5\u4f5c\n\n\u8cc7\u6b77 :\u4e2d\u4e94\u7a0b\u5ea6; 1\u5e74\u7d93\u9a57; \u826f\u597d\u7cb5\u8a9e; \u4e00\u822c\u82f1\u8a9e; \u61c2\u8b80\u5beb\u4e2d\u6587; \u7565\u61c2\u8b80\u5beb\u82f1\u6587; \u61c2MS Word; \u61c2MS Excel; \u6301\u6709LCC\u4e2d\u7d1a\u8b49\u66f8; \u61c2\u82f1\u6587\u6253\u5b57; \u61c2\u4e2d\u6587\u6253\u5b57\n\n\u5f85\u9047 :\u6bcf\u6708$18,000 - $20,000, \u661f\u671f\u4e00\u81f3\u4e94: \u4e0a\u53489\u6642\u81f3\u4e0b\u53486\u6642\u53ca\u661f\u671f\u516d: \u4e0a\u53489\u6642\u81f3\u4e0b\u53481\u6642, \u6bcf\u9031\u5de5\u4f5c5\u5929\u534a\n\n\u7533\u8acb\u9808\u77e5 :\u6c42\u8077\u8005\u53ef\u96fb\u90f5(Apply Now)\u5c65\u6b77\u8868\u7d66\u96c5\u6f54\u6e05\u6f54\u5de5\u7a0b\u6709\u9650\u516c\u53f8\u3002\u5982\u8981\u7d22\u53d6\u6536\u96c6\u500b\u4eba\u8cc7\u6599\u8072\u660e, \u8acb\u8207\u5f35\u5148\u751f(Email)\u806f\u7d61\u3002\n\n", "employment_types": ["Full Time"], "selling_points": [], "locations": ["Tsuen Wan Area"], "categories": ["Accounting", "Accountant", "Accounting Clerk / Supervisor", "Audit"], "post_time": "2022-01-17T07:42:15Z", "salary": {"currency": null, "max": null, "min": null, "period": "monthly", "term": null}, "salary_visible": false, "title_keywords": [], "responsibilities": [], "requirements": {"degrees": [], "majors": [], "languages": [], "language_level": [], "hard_skills": ["excel", "word"], "soft_skills": [], "languages_combined": []}, "experience_required": {"duration": [], "field": []}}, {"job_id": "100003009050463", "location_code": "hk", "company": "Faith Hill C.P.A. Limited", "job_title": "AUDIT STAFF - ASSOCIATES TO SENIORS  (5 days week)", "description": "Requirements:\nThree years' audit experience required for Senior to handle small to big companies' audit assisgnments / projects;\nFresh graduate / 1-2 years' audit experience for Associates;\nInitiative, team-work spirit and good inter-personal communication skill\n\nWe provide competitive salary to commensurate with audit experience.\u00a0 We also offer generous fringe benefits to the right candidates including study and examination leave etc.\n\nPlease send full resume and expected salary by email to info @fhcpa.com.hk\n\n** Office location - walking distance from MTR station **", "employment_types": ["Full Time", "Permanent"], "selling_points": [], "locations": ["North Point"], "categories": ["Accounting", "Accountant", "Audit", "Taxation"], "post_time": "2022-01-15T03:51:07Z", "salary": {"currency": null, "max": null, "min": null, "period": "monthly", "term": null}, "salary_visible": false, "title_keywords": ["audit staff"], "responsibilities": ["communication", "audit"], "requirements": {"degrees": ["fresh graduate"], "majors": [], "languages": [], "language_level": [], "hard_skills": ["small"], "soft_skills": ["communication skill", "initiative", "inter-personal"], "languages_combined": []}, "experience_required": {"duration": ["three years", "1-2 years"], "field": ["audit experience", "audit"]}}, {"job_id": "100003009049201", "location_code": "hk", "company": "Baker Tilly Hong Kong", "job_title": "Senior Associate / Associate \u2013 Audit (Listed client exposure)", "description": "Responsibilities:\n\nResponsible for the planning and execution of audit fieldwork for listed, H-shares etc clients\nCompleting the assigned tasks using audit programme \u2018Caseware\u2019\nSupervise and guide subordinates\n\nRequirements:\n\nUniversity graduate in Accountancy or Business Administration At least 2 years of experience in professional firms\nMust be a good team player\nExcellent command of both written and spoken English and Chinese; including Mandarin\nGood communication and interpersonal skills\u00a0\u00a0\u00a0\nQualified Members or finalist of HKICPA or other relevant professional bodies\n\nWe offer an attractive remuneration package, excellent career prospects in a warm and friendly atmosphere. Our continuing expansion and growth offer numerous opportunities.\n\nIf you consider yourself the appropriate choice, please forward your CV and salary expectations with the application form\u00a0to the Human Resources Department, 2/F 625 King\u2019s Road, North Point, Hong Kong or by\u00a0clicking \u201cApply Now\u201d.\u00a0\u00a0\u00a0\n\nDownload Application Form\n\nSelected candidates will be notified by phone for interview arrangements within 6 weeks. Applications of unsuccessful candidates will be deleted immediately after screening.\n\nPersonal data provided by job applicants will be used strictly in accordance with the Employer's Personal Data Policies, a copy of which will be provided upon request.\n\nBaker Tilly Hong Kong\u00a0is a leading firm of certified public accountants and business advisers, specialising in providing clients with a range of integrated services. Our firm is driven by 300 directors and professional staff based in Hong Kong.", "employment_types": ["Full Time", "Permanent"], "selling_points": ["At least 2 yrs of experience in professional firms", "Good team player", "Listed client exposure"], "locations": ["Quarry Bay"], "categories": ["Accounting", "Accountant", "Audit", "Others"], "post_time": "2022-01-14T08:15:52Z", "salary": {"currency": null, "max": null, "min": null, "period": "monthly", "term": null}, "salary_visible": false, "title_keywords": ["senior associate", "associate"], "responsibilities": ["audit", "planning"], "requirements": {"degrees": ["university graduate"], "majors": ["business administration", "accountancy"], "languages": ["english", "chinese", "mandarin"], "language_level": ["excellent"], "hard_skills": ["hkicpa"], "soft_skills": ["good team player", "communication and interpersonal skills"], "languages_combined": [{"language": "english", "language_level": ["excellent"]}, {"language": "chinese", "language_level": ["excellent"]}, {"language": "mandarin", "language_level": []}]}, "experience_required": {"duration": ["at least 2 years"], "field": ["business administration"]}}, {"job_id": "100003009046659", "location_code": "hk", "company": "Horizon (HK) CPA Limited", "job_title": "Audit Junior / Audit Senior (Double Pay)", "description": "Requirements:\u00a0\n\n\n\nDiploma or degree holders, accounting related major is preferred; secondary school completed with accounting subject will also be considered\nGood command of oral and written English, good Putonghua is a plus\n\nWhat\u2019 on Offer:\n\n\n\nAttractive salary package - Double pay and performance bonus\nClear career path", "employment_types": ["Full Time", "Permanent"], "selling_points": ["Double pay and performance bonus", "5-day work week", "Excellent promotion opportunities"], "locations": ["Wan Chai"], "categories": ["Accounting", "Audit"], "post_time": "2022-01-13T18:54:08Z", "salary": {"currency": null, "max": null, "min": null, "period": "monthly", "term": null}, "salary_visible": false, "title_keywords": ["junior"], "responsibilities": [], "requirements": {"degrees": ["diploma", "degree"], "majors": ["accounting"], "languages": ["putonghua", "english"], "language_level": ["good command", "good"], "hard_skills": ["plus"], "soft_skills": ["clear", "oral"], "languages_combined": [{"language": "putonghua", "language_level": ["good", "good command"]}, {"language": "english", "language_level": ["good command"]}]}, "experience_required": {"duration": [], "field": []}}, {"job_id": "100003009049817", "location_code": "hk", "company": "Raymond Y. L. Lai & Co.", "job_title": "Audit Assistant/Audit Intermediate/Audit Semi-Senior/Audit Senior 5-Day Work", "description": "-\u00a0\u00a0\u00a0\u00a0\u00a0\u00a0\u00a0\u00a0\u00a0 Audit of companies and organisations (including specialized businesses such as securities companies, insurance brokerage companies and law firms etc.);\n-\u00a0\u00a0\u00a0\u00a0\u00a0\u00a0\u00a0\u00a0\u00a0 Preparation of financial statements and tax computations;\n-\u00a0\u00a0\u00a0\u00a0\u00a0\u00a0\u00a0\u00a0\u00a0 Other assurance engagements and tax-related engagements;\n-\u00a0\u00a0\u00a0\u00a0\u00a0\u00a0\u00a0\u00a0\u00a0 Performing due diligence reviews.\n\nRequirements:\nRelevant qualification and years of audit experience\nFresh graduates are also considered\nProficient in\u00a0English, Cantonese\u00a0and\u00a0Mandarin\u00a0communication skills\nStrong organization and administrative skills\nSelf Motivative and can work independently\nFamiliar with MS Office & accounting softwares\nApplicants should apply in writing with full resume, present and expected salary, phone no. To : Raymond Y. L. Lai & Co. at 19/F., Shun Feng International Centre, 182 Queen's Road East, Wan Chai Hong Kong.\n\n(All personal data collected will be used for recruitment purpose only.)", "employment_types": ["Full Time", "Permanent"], "selling_points": [], "locations": ["Wan Chai"], "categories": ["Accounting", "Audit"], "post_time": "2022-01-14T09:16:49Z", "salary": {"currency": null, "max": null, "min": null, "period": "monthly", "term": null}, "salary_visible": false, "title_keywords": ["assistant"], "responsibilities": ["tax", "due diligence reviews", "brokerage", "audit", "financial statements", "communication", "recruitment", "personal data", "insurance"], "requirements": {"degrees": [], "majors": [], "languages": ["cantonese", "english", "mandarin"], "language_level": ["proficient"], "hard_skills": ["no", "wan", "accounting softwares", "ms office"], "soft_skills": ["communication skills", "work independently"], "languages_combined": [{"language": "cantonese", "language_level": ["proficient"]}, {"language": "english", "language_level": ["proficient"]}, {"language": "mandarin", "language_level": ["proficient"]}]}, "experience_required": {"duration": [], "field": ["audit experience"]}}, {"job_id": "100003009052950", "location_code": "hk", "company": "Fung, Yu & Co. CPA Limited", "job_title": "Internship - Audit Department/Accounting Services Department", "description": "If you want to\n\ngain valuable internship experience on audit work\nbuild up diversified concepts of doing audit for different business nature companies\nget the skill sets of presentation, interpersonal, communication to enrich your competitiveness in the future career\n\nOur internship program contains\n\nconcepts and practices of audit\nperforming audit work\naudit case study\npresentation\n\nIf you are\n\nwilling to learn\nenergetic and passionate\nHKID Holders\n\nWhat We Offer\n\nwork reference letter\non-job training\n\nWelcome to join us in this winter!\n\nPlease submit your application by clicking \u201cApply Now\u201d button.\n\nWelcome to visit our company website http://www.fungyucpa.com/\u00a0for more information.\n\nPersonal data collected will be used for recruitment purposes only.", "employment_types": ["Internship"], "selling_points": ["University degree holder majoring in accountancy", "Audit/Accounting", "Intern"], "locations": ["Central & Western Area"], "categories": ["Accounting", "Audit", "Consulting", "Taxation"], "post_time": "2022-01-17T04:39:36Z", "salary": {"currency": null, "max": null, "min": null, "period": "monthly", "term": null}, "salary_visible": false, "title_keywords": ["accounting", "internship"], "responsibilities": ["communication", "audit"], "requirements": {"degrees": [], "majors": [], "languages": [], "language_level": [], "hard_skills": [], "soft_skills": ["passionate", "presentation", "willing to learn", "communication", "energetic", "interpersonal"], "languages_combined": []}, "experience_required": {"duration": [], "field": ["audit"]}}, {"job_id": "100003009054031", "location_code": "hk", "company": "Lindy Williams", "job_title": "Account / Audit Officer - Government Funding Programme (Contract)", "description": "Our client is a multi-disciplinary organisation and is inviting the following Contractors:\n\nLocation: Kowloon Tong\n\nTitle: Officer, Compliance & Internal Audit\n\nContract period: asap - 9 months (Mon-Fri, under agency payroll with basic benefits, with gratuity bonus)\n\nJob Duties\n\n\u00b7\u00a0\u00a0\u00a0\u00a0\u00a0\u00a0\u00a0\u00a0 Perform quality check and site visit checking of operations including government funding schemes\n\n\u00b7\u00a0\u00a0\u00a0\u00a0\u00a0\u00a0\u00a0\u00a0 Assist in compiling quality check reports and communicate audit findings with auditee\n\n\u00b7\u00a0\u00a0\u00a0\u00a0\u00a0\u00a0\u00a0\u00a0 Undertake ad hoc assignments as required\n\nJob Requirements:\n\n\u00b7\u00a0\u00a0\u00a0\u00a0\u00a0\u00a0\u00a0\u00a0 Bachelor Degree in Accounting, Finance, Information Technology or related disciplines\n\n\u00b7\u00a0\u00a0\u00a0\u00a0\u00a0\u00a0\u00a0\u00a0 1-2 years of accounting or auditing experience preferred\n\n\u00b7\u00a0\u00a0\u00a0\u00a0\u00a0\u00a0\u00a0\u00a0 Proficient in Excel, Word and Powerpoint\n\n\u00b7\u00a0\u00a0\u00a0\u00a0\u00a0\u00a0\u00a0\u00a0 Good analytical skills\n\n\u00b7\u00a0\u00a0\u00a0\u00a0\u00a0\u00a0\u00a0\u00a0 Good command of both written and spoken English and Chinese\n\n\u00b7\u00a0\u00a0\u00a0\u00a0\u00a0\u00a0\u00a0\u00a0 Mature, independent and self-motivated with strong sense of responsibility\u00a0\n\nAll information collected will be kept in strict confidence and will be used for recruitment purpose only.\n\nPlease submit the application with your resume with your availability & expected salary if you are interested.\n\nWhatsapp No. Ms RM +852 5285 3022\n\nFor more jobs, please visit our website: www.williams-asia.com\n\n(Personal data submitted are for recruitment purpose only.)\n", "employment_types": ["Contract"], "selling_points": ["Degree in Accounting, Finance, IT", "Quality check, government funding schemes", "Auditing"], "locations": ["Others"], "categories": ["Accounting", "Audit"], "post_time": "2022-01-17T08:08:20Z", "salary": {"currency": null, "max": null, "min": null, "period": "monthly", "term": null}, "salary_visible": false, "title_keywords": ["officer"], "responsibilities": [], "requirements": {"degrees": [], "majors": [], "languages": [], "language_level": [], "hard_skills": [], "soft_skills": [], "languages_combined": []}, "experience_required": {"duration": [], "field": []}}, {"job_id": "100003009050515", "location_code": "hk", "company": "KEK Consultancy Company Limited", "job_title": "Audit Trainee/ Assistant/ Senior \u2013 Few posts - Ref. 1498", "description": "Due to company expansions, our clients (CPA firms) are now looking for high calibre candidates to fill the following position:\n\n\nFresh graduates or candidates from non-degree tertiary with accounting discipline are also welcome;\nMain job duty is to provide general audit service to clients;\nGood attitude and willing to learn.\n\n\n\nRemarks:\n\nMonthly salary: HK$13-18K (depends on experience);\nWorking location: Wan Chai/ Jordan;\nGood fringe benefits including medical, study leave, exam leave, etc.\n\nIf the above position is not suitable for you, please also feel free to send your CV to us for our job matching.\n\nInterested parties please click \"APPLY NOW\"\u00a0or send to\u00a0OUR EMAIL\u00a0and attach your updated resume with expected salary in \"MS WORD\" format.\n\n\nPlease quote the\u00a0Job Ref. No.\u00a0and\u00a0Applied Post\u00a0on the subject of your application.\n\nInterest to know our candidates' and clients' comments about our service? Please click\u00a0HERE.\n\nCompany website:\u00a0www.kek.com.hk\n\nThe information provided will only be used for recruitment related purposes.", "employment_types": ["Full Time", "Permanent"], "selling_points": ["Not much OT", "Client base: Listed Co.", "Good and friendly company culture"], "locations": ["Wan Chai"], "categories": ["Accounting", "Accounting Clerk / Supervisor", "Audit", "Others", "Student / Fresh Graduate / No Experience"], "post_time": "2022-01-15T03:51:09Z", "salary": {"currency": null, "max": null, "min": null, "period": "monthly", "term": null}, "salary_visible": false, "title_keywords": ["assistant", "trainee"], "responsibilities": ["audit"], "requirements": {"degrees": ["degree"], "majors": ["accounting"], "languages": [], "language_level": [], "hard_skills": ["cpa", "wan"], "soft_skills": ["willing to learn"], "languages_combined": []}, "experience_required": {"duration": [], "field": []}}, {"job_id": "100003009046918", "location_code": "hk", "company": "DKNT CPA Limited", "job_title": "Semi-Senior / Audit Senior", "description": "Major Responsibilities & Duties\n\nLead client audit engagements, including planning, executing, directing and completing financial audits\nObtain a thorough understanding of HKSQC1, HKSAs and common audit procedures and techniques\nTrain and mentor juniors on audit process\nResearch and analyse financial statements and audit related issues\nAcquire a working knowledge of the client's business\nProactively interact with key client's management to gather information, resolve problems, and make recommendations for business and process improvements\nPerform other job related duties as requirered\n\nRequirements & Qualifications\nThe successful candidate will possess the following basic qualifications:-\n\nExcellent project management, analytical, interpersonal communication skills\nLeadership, training and mentoring skills\nProfessionalism and dependability attitude\nDedicated to superior client service\nStrong organisational skill and attention to details\nMinimum 2-3 years recent audit work experience\nRelevant Accounting degree\nQualified or working towards CPA certification\n\nBenefits\nWe provide a pleasant working environment with modern I.T. facilities.\u00a0 We offer 5-day week, staggered office hours, on-the-job and in-house training, leadership development, study leaves, examination support and good promotion prospect.", "employment_types": ["Full Time"], "selling_points": ["offer 5-day week, staggered office hours,", "on-the-job and in-house training", "leadership development, study leaves,"], "locations": ["Wan Chai"], "categories": ["Accounting", "Audit", "Consulting", "Others"], "post_time": "2022-01-14T01:43:15Z", "salary": {"currency": null, "max": null, "min": null, "period": "monthly", "term": null}, "salary_visible": false, "title_keywords": [], "responsibilities": ["make recommendations", "management", "procedures", "audit", "financial statements", "executing", "analyse", "audits", "planning"], "requirements": {"degrees": ["degree"], "majors": ["accounting"], "languages": [], "language_level": [], "hard_skills": ["project management", "basic", "cpa"], "soft_skills": ["communication skills", "project management", "attention to details", "leadership", "interpersonal", "superior"], "languages_combined": []}, "experience_required": {"duration": ["minimum 2-3 years"], "field": ["audit"]}}, {"job_id": "100003009047738", "location_code": "hk", "company": "Public Bank (Hong Kong) Ltd", "job_title": "Senior Auditor / Auditor (Ref: JD-SAD)", "description": "Conduct branch and operational audits, compliance checking, ad hoc assignments and prepare relevant reports\nEnsure information security and internal operations meet with all regulatory requirements and industry guidelines/ practices\nUniversity Degree holder with 1 to 2 years of relevant experience in financial institutions, qualified accountant preferred\nExperience in financial reporting, compliance, credit, and treasury is a definite advantage\nStrong analytical skills in identifying risks and control implications\nTo apply, interested parties please follow the application methods available in the Bank\u2019s career website https://www.publicbank.com.hk/en/aboutus/careeropportunities. You can send us your resume quoting our job reference number together with present &\u00a0expected salary (a must)\u00a0to the Human Resources Department by email or fax at\u00a02815 3157\u00a0or by post to\u00a0Human Resources Department, 12/F, Public Bank Centre, 120 Des Voeux Road Central, Hong Kong. You may also visit our career website for other career opportunities available within our Group.\n\nPersonal data collected will be used for recruitment purpose only and will be treated in accordance with the Bank\u2019s Personal Information Collection Statement, a copy of which has been available in the Bank\u2019s career website.", "employment_types": ["Full Time", "Permanent"], "selling_points": [], "locations": ["Not Specified"], "categories": ["Accounting", "Audit", "Banking / Finance", "Others", "Professional Services", "Legal & Compliance"], "post_time": "2022-01-15T03:49:03Z", "salary": {"currency": null, "max": null, "min": null, "period": null, "term": null}, "salary_visible": false, "title_keywords": [], "responsibilities": ["relevant reports", "control", "information security", "guidelines", "operations", "regulatory requirements", "compliance", "checking", "ad hoc assignments", "financial reporting", "audits"], "requirements": {"degrees": ["university degree"], "majors": [], "languages": [], "language_level": [], "hard_skills": ["analytical skills"], "soft_skills": ["analytical skills"], "languages_combined": []}, "experience_required": {"duration": ["1 to 2 years"], "field": ["financial institutions", "compliance", "relevant experience", "financial"]}}, {"job_id": "100003009054839", "location_code": "hk", "company": "Hong Kong Parkview", "job_title": "Accountant - Hong Kong Parkview Group", "description": "Duties and Responsibilities\nResponsibilities:\nAssist in daily accounting operations for the Hong Kong Parkview Group.\nHandle full set of accounts, financial analysis and management reports.\nConduct basic accounting system maintenance.\nSupport in ad-hoc duties.\nRequirements:\nHigher Diploma or Degree holder in Accounting or related discipline; member of HKICPA or equivalent is preferrable\nAt least 4 years audit / accounting experience.\nWell versed with MS Excel.\nGood command of spoken and written English, Cantonese and Putonghua.\nWe offer competitive remuneration package including 5-day work week, family medical plan, duty meal and free shuttle bus (to and from Central, Admiralty, and Aberdeen; to Causeway Bay and Wanchai) and excellent career opportunities to the right candidate. \u00a0\nPlease send full resume, expected salary and contact telephone number to\nHong Kong Parkview\nHuman Resources Department\n88 Tai Tam Reservoir Road, Hong Kong\nConfidential Fax No. 28123490\nEmail via \"Apply Now\"\n\n(All data collected will be used for recruitment purpose only)", "employment_types": ["Full Time", "Permanent"], "selling_points": ["Conduct basic accounting system maintenance", "Support in ad-hoc duties", "At least 4 years audit / accounting experience"], "locations": ["Wan Chai Area"], "categories": ["Accounting", "Accountant", "Audit", "Financial Analyst"], "post_time": "2022-01-17T11:37:40Z", "salary": {"currency": null, "max": null, "min": null, "period": "monthly", "term": null}, "salary_visible": false, "title_keywords": ["accountant"], "responsibilities": ["maintenance", "full set of accounts", "daily accounting operations", "financial analysis", "management reports", "ad-hoc duties"], "requirements": {"degrees": ["diploma", "degree holder"], "majors": ["accounting"], "languages": ["cantonese", "putonghua", "english"], "language_level": ["good command"], "hard_skills": ["no", "ms excel", "hkicpa"], "soft_skills": [], "languages_combined": [{"language": "cantonese", "language_level": ["good command"]}, {"language": "putonghua", "language_level": ["good command"]}, {"language": "english", "language_level": ["good command"]}]}, "experience_required": {"duration": ["at least 4 years"], "field": ["accounting experience", "audit"]}}, {"job_id": "100003009046687", "location_code": "hk", "company": "Zhonghui Anda CPA Limited", "job_title": "Audit Trainee/Audit Semi-senior/Audit Senior", "description": "Job Requirements\n\nDiploma, Bachelor Degree or Master Degree in accounting or business related disciplines\nFresh graduates or experience hire from local audit firms, second-tier audit firms and big four audit firms are all welcomed.\nA minimum of 1 to 2 years\u2019 audit experience would be considered as Audit Semi-Senior. More audit experience \u00a0would be considered as Audit Senior.\nProficiency in\u00a0 English, Putonghua and/or Cantonese\nOvertime work and business travel is required\n\nJob Description\n\nAssisting senior(s)/manager(s) to perform various audit testing, analysis and reporting in different kinds of professional audit and accounting service assignments, including annual audit, interim review, merger and acquisition, IPO and other ad hoc assignments.\n\nCompany Overview\n\nZHONGHUI ANDA CPA Limited (http://www.zhcpa.hk) is a\u00a0well-established and rapid-growing CPA firm in Hong Kong, e.g. roughly 10 times growth in headcounts and annual audit listed clients in recent 10 years. We are also the sole member firm located in Hong Kong for the PRC ZHONGHUI group(http://www.zhcpa.cn).\nWe are a young, energetic and fast-growing practice incorporated since 2007 which\u00a0focusingto serve Hong Kong listed clients in the small to mid-cap sector. Currently, we are performing annual audit services for more than 80 public companies listed in the Hong Kong Stock Exchange.\u00a0\u00a0 We are ranking 7th in the market in terms of the number of annual audit for Hong Kong listed clients.\nInternationally, ZHONGHUI is a key member firm to the Kreston International accounting network. There are also network firms of ZHONGHUI in the United States of America and Malaysia.\nWe\u00a0embrace the vision of becoming the most influential, innovative and fast-responding firm in delivery of quality professional services.\nWe are currently seeking talents to join our Hong Kong practice in pursuing service excellence and further expansion.\n\nBenefits & other support\n\nWe offer:\n\nRemuneration\nCompetitive and rewarding remuneration package\n13th month salary\nPerformance bonus\nActual compensation for effective overtime work\nDedication reward scheme\nWorking environment\nFive-day work week\nFlexible working arrangement\nWork from home benefit\nFirm\u2019s support\nStrong team support\nStrong training and technical support\nSufficient study arrangement for examination of accounting professional bodies\nKnowledge sharing and inclusiveness culture\n\nApplication method\n\nFor interested candidates, please send your resume for application by clicking \"Apply Now\"\n\n(Contact person:\u00a0 Miss Ava Ho, Manager, Department of Human Resources \u2013 Talent Acquisition)", "employment_types": ["Full Time"], "selling_points": [], "locations": ["Eastern Area"], "categories": ["Accounting", "Accountant", "Audit", "Others"], "post_time": "2022-01-13T18:54:21Z", "salary": {"currency": null, "max": null, "min": null, "period": "monthly", "term": null}, "salary_visible": false, "title_keywords": ["trainee"], "responsibilities": ["reporting", "annual audit", "analysis", "review", "quality", "audit", "testing", "ad hoc assignments", "accounting service"], "requirements": {"degrees": ["diploma", "degree", "bachelor", "master degree"], "majors": ["business", "related disciplines", "accounting"], "languages": ["cantonese", "putonghua", "english"], "language_level": ["proficiency"], "hard_skills": [], "soft_skills": ["overtime work"], "languages_combined": [{"language": "cantonese", "language_level": ["proficiency"]}, {"language": "putonghua", "language_level": ["proficiency"]}, {"language": "english", "language_level": ["proficiency"]}]}, "experience_required": {"duration": ["minimum of 1 to 2 years"], "field": ["audit experience", "audit", "big four"]}}, {"job_id": "100003009048180", "location_code": "hk", "company": "Eric K. L. Ng & Co.", "job_title": "Audit Trainee & Semi-senior (HIGH PAID, Fresh Graduate welcome, 5-days works, GUARANTEE NO Overtime)", "description": "Responsibilities:\n\nPerforming audit assignments and drafting statutory financial statements\nEngage in tax advisory services including but not limited to prepare profits tax computation\nAnalyze clients\u2019 transactions and communicate the findings with clients\u00a0\nLiaise with local and overseas clients (Occasional travel to clients\u2019 local and China offices required)\nPerform ad-hoc tasks as assigned\n\nBenefits:\n\n5-day Work (9:30am to 6:30pm); Guarantee NO Overtime\nFriendly Team Members and Environment.\n12 Days Annual Leave with Study & Examination Leaves\nPerformance Bonus\nExposure to Businesses Across Industries\nEmployee-friendly Working Environment (5-minute walk from MTR station to Office); Friendly Team Members and Harmony Culture\nContinuous On-the-Job Training\nPromising Career Development Opportunities\nWorking experiences accredited by HKICPA\nRequirements:\n\nHigher Diploma or Degree in Accounting / Finance\nFresh Graduates are welcomed\u00a0\nGeneral command of written and spoken Chinese, English and Putonghua\nGood PC Knowledge in MS Office\nImmediate Available is preferred", "employment_types": ["Full Time", "Part Time", "Permanent", "Temporary", "Contract", "Freelance"], "selling_points": [], "locations": ["Mong Kok"], "categories": ["Accounting", "Audit", "Professional Services", "Company Secretary"], "post_time": "2022-01-14T05:48:51Z", "salary": {"currency": null, "max": null, "min": null, "period": "monthly", "term": null}, "salary_visible": false, "title_keywords": ["trainee"], "responsibilities": ["tax", "tax computation", "ad-hoc tasks", "audit", "transactions", "financial statements", "liaise with"], "requirements": {"degrees": [], "majors": [], "languages": [], "language_level": [], "hard_skills": [], "soft_skills": [], "languages_combined": []}, "experience_required": {"duration": [], "field": []}}, {"job_id": "100003009046906", "location_code": "hk", "company": "DKNT CPA Limited", "job_title": "Audit Junior", "description": "Qualities we are looking for:-\n\nAbility to conceptualize complex ideas and communicate in simple terms\nGood problem solving skill, analytical and creative\nPositive attitude with a mature temperament\nGood communicator\nFluent in English\nAble to interact at all levels\n\n\u00a0Professional Training & Development\n\nWe are a HKICPA Authorised Employer and we take a keen interest in the development of our people into qualified professionals.\n\nTo achieve this goal, you will be assigned a mentor-coach who cares about you as a person, to help you clarify what is expected of you in your work, to provide timely feedback and to encourage you in your professional development.\u00a0 We conduct \u2018Look Back & Learn\u2019 sessions at the completion of each major project.\u00a0 These sessions are participative and are designed for group learning and continuous improvement.\n\nYou will feel your work is important and meaningful because our company\u2019s mission to help clients run better businesses.\u00a0 Everything we do in the company is connected to this purpose.\n\n\u00a0Benefits\n\nWe provide a friendly working environment with modern I.T. facilities.\u00a0 We offer 5-day week, staggered office hours, on-the-job and in-house training, leadership development, study leaves, examination support and good promotion prospect.", "employment_types": ["Full Time"], "selling_points": ["5-day week", "study leaves, examination support", "good promotion prospect"], "locations": ["Wan Chai"], "categories": ["Accounting", "Audit"], "post_time": "2022-01-14T01:41:05Z", "salary": {"currency": null, "max": null, "min": null, "period": "monthly", "term": null}, "salary_visible": false, "title_keywords": ["junior"], "responsibilities": ["ideas"], "requirements": {"degrees": [], "majors": [], "languages": ["english"], "language_level": ["fluent"], "hard_skills": ["simple", "goal", "problem solving", "hkicpa"], "soft_skills": ["keen", "timely", "mature", "positive attitude", "learning", "problem solving skill", "creative", "communicator"], "languages_combined": [{"language": "english", "language_level": ["fluent"]}]}, "experience_required": {"duration": [], "field": []}}, {"job_id": "100003009040078", "location_code": "hk", "company": "CCT & Partners CPA Limited", "job_title": "Junior / Semi-Senior / Senior Auditor", "description": "Diploma or above with major in accounting or finance\n0-2 years solid audit work experience in CPA firm, fresh or recent graduate is also welcome for Junior Auditor\nGood command of both written and spoken English and Chinese; proficiency in Mandarin\nProficient\u00a0with MS Office especially Word and Excel\nResponsible, able to work independently and willing to learn\nTeam player with good interpersonal communication\nImmediate available is preferred\n\n\u00a0Our offers:\n\n\n5-days work week\n12 days of annual leave\nStudy & Examination leave\nAttractive salary plus discretionary performance bonus\n\n\nSalaries are adjustable based on qualifications and experience. Candidates should apply with detailed resume stating personal particulars, employment history, present and expected salary with your availability via email by clicking \u201cApply Now\u201d or fax to: 3743 6038.\n\n\u00a0**Personal data will be used for recruitment purpose only", "employment_types": ["Full Time"], "selling_points": ["0-2 years", "work-life balance", "salary range from $12,500 to $24,000"], "locations": ["Sheung Wan"], "categories": ["Accounting", "Audit"], "post_time": "2022-01-12T01:15:03Z", "salary": {"currency": null, "max": null, "min": null, "period": "monthly", "term": null}, "salary_visible": false, "title_keywords": ["junior"], "responsibilities": ["communication", "personal data", "recruitment", "audit"], "requirements": {"degrees": ["diploma or above"], "majors": ["finance", "accounting"], "languages": ["english", "chinese", "mandarin"], "language_level": ["proficiency", "good command"], "hard_skills": ["excel", "plus", "word", "cpa", "ms office"], "soft_skills": ["work independently", "responsible", "willing to learn", "communication", "team player", "interpersonal", "detailed"], "languages_combined": [{"language": "english", "language_level": ["good command"]}, {"language": "chinese", "language_level": ["good command"]}, {"language": "mandarin", "language_level": ["proficiency"]}]}, "experience_required": {"duration": ["0-2 years"], "field": ["cpa firm", "audit"]}}, {"job_id": "100003009054067", "location_code": "hk", "company": "The Tien Chu (Hong Kong) Company Limited", "job_title": "Accounting Manager", "description": "Responsibilities :\n\n\n\nPrepare consolidated financial statements and handle monthly closing of group companies\nHandle annual and interim audit review. Liaise with external auditors\nEngage in the publication of interim and annual reports\nPrepare statutory accounts and tax filings\nPerform financial analysis\nAssist in ad-hoc tasks as assigned by management\n\nRequirements:\n\n\n\nDegree holder in Accounting or related disciplines\nQualified Accountant of HKICPA or other recognized professional accounting bodies is advantage\nMinimum of 5 years\u2019 working experience in Manufacturing / Trading Company fields;\nExperience in group consolidation, familiar with PRC accounting and tax practices is an added advantage\nDetail-oriented, well-organized, self-motivated with strong sense of responsibility\nHigh competence in written and spoken English and Chinese; proficiency in Putonghua is an advantage;\nAttention to details and accuracy with strong sense of urgency\n\n\n\nWe offer competitive package to right candidate, including but unlimited double pay, performance bonus, free lunch, shuttle bus, education allowance, housing allowance, Medical and other benefits.\n\nWorking hours : Monday to Friday 9:00am to 5:00pm & Saturday 9:00am to 12:00noon\n\nInterested parties please send full resume in Chinese and English in strict confidence with expected salary & earliest availability to us for interview.\n\nFor more details, please visit www.tienchu.com\n\n(Personal data collected is solely for recruitment related purpose\u00a0and will be treated in strict confidence.)", "employment_types": ["Full Time", "Permanent"], "selling_points": ["Accountant", "Manufacturing / Trading Company", "Double pay, bonus, free lunch, shuttle, medical"], "locations": ["Tsing Yi"], "categories": ["Accounting", "Audit", "Finance / Accounting Manager", "Financial Analyst"], "post_time": "2022-01-17T08:17:19Z", "salary": {"currency": null, "max": null, "min": null, "period": "monthly", "term": null}, "salary_visible": false, "title_keywords": ["accounting manager"], "responsibilities": ["tax", "management", "ad-hoc tasks", "review", "audit", "financial statements", "financial analysis", "reports", "liaise with", "publication", "external auditors"], "requirements": {"degrees": ["degree holder"], "majors": ["related disciplines", "accounting"], "languages": ["putonghua", "english", "chinese"], "language_level": ["advantage", "proficiency"], "hard_skills": ["prc accounting", "hkicpa"], "soft_skills": ["self-motivated", "sense of responsibility", "urgency", "well-organized", "detail-oriented", "attention to details"], "languages_combined": [{"language": "putonghua", "language_level": ["proficiency", "advantage"]}, {"language": "english", "language_level": []}, {"language": "chinese", "language_level": []}]}, "experience_required": {"duration": ["minimum of 5 years"], "field": ["manufacturing", "trading", "consolidation", "accounting"]}}, {"job_id": "100003009050028", "location_code": "hk", "company": "UniTax Prism (HK) CPA Limited", "job_title": "Audit Manager", "description": "Job Duties :\n\n\nIn charge of assurance engagements\nLeading and working with audit team to provide professional services to a portfolio of listed and private companies\nManaging relationships with clients effectively\u00a0\nProviding guidance, coaching and constructive feedback to team members\u00a0\n\nRequirements :\n\n\nBachelor degree in accounting or business related discipline\nPreferably with\u00a05 years audit experience or above\nExperience in auditing HK/ PRC listed companies\u00a0will be an advantage\nHigh level of independence and strong motivation\nGood communication, interpersonal and analytical skills\nCandidate with less experience will be considered as Assistant Manager\nBenefits :\n\ncompetitive remuneration package\nmedical/ dental insurance\nexam/study leave\nbirthday leave\n4-day work in office\u00a0", "employment_types": ["Full Time"], "selling_points": ["Competitive remuneration package", "4-Day work in office", "Medical/ dental insurance"], "locations": ["Tsim Sha Tsui"], "categories": ["Accounting", "Audit"], "post_time": "2022-01-14T09:39:37Z", "salary": {"currency": null, "max": null, "min": null, "period": "monthly", "term": null}, "salary_visible": false, "title_keywords": ["manager"], "responsibilities": ["guidance", "audit"], "requirements": {"degrees": ["degree", "bachelor"], "majors": ["business", "accounting"], "languages": [], "language_level": [], "hard_skills": ["analytical skills"], "soft_skills": ["communication", "interpersonal", "analytical skills"], "languages_combined": []}, "experience_required": {"duration": ["5 years"], "field": ["audit experience"]}}, {"job_id": "100003009051518", "location_code": "hk", "company": "EQC Advisory Limited", "job_title": "Fast-Track Management Trainee (Fresh Graduates Welcome) - HK$28,500+, 13 months + bonus", "description": "We are looking for highly proactive and well-rounded individuals to assist with the launch of our new business services,\u00a0including professional firms appraisal services, online training services, and regulatory compliance consultancy services.\u00a0 The opportunity will allow the successful candidate to fast-track into a management position leading a team of professionals in delivering quality professional services that are practical to small and medium sized CPA practices in Hong Kong and overseas.\u00a0 \u00a0\n\nWHAT WE OFFER:\n- Basic Salary from HK$28,500 / month + 13th Month Salary + Performance Bonus\n- Semi-Annual Appraisals and upward salary adjustments & discretionary performance-based bonus\n- 18-month Fast-track to a junior management position\u00a0\u00a0\n- 12+ Annual Leave Days\u00a0\n- Mentoring program by direct supervisor, an industry elite and CPA\n\n\nJOB\u00a0RESPONSIBILITIES:\n\u00b7 Act as project in-charge in providing FRC inspection / compliance consultancy engagements\n\u00b7 Lead the business strategic planning, launch and growth of new service lines\u00a0\n\u00b7 Oversee work progress of subordinates and interns\n\nJOB REQUIREMENTS:\n(FRESH GRADUATES WILL BE CONSIDERED):\n- Interest in developing a career in a startup advisory firm\n- Willing to step out of comfort zone with an entrepreneurial mindset\n\u00b7 1 year of office working experience preferred, but fresh graduates are also welcome\n- Sensitive to numbers with strong business acumen\n- Strong multi-tasking & time management skills\n- Strong communication skills with accountability and follow-through\n- Comfortable with report and research writing\n\u00b7 Comfortable with accounting and financial reporting subjects & quick self-learner\n\u00b7 Fluent in written and spoken English (IELTS 7.5 or above is preferred)\n\u00b7 Degree holder in any discipline, preferably in accounting, finance, or economics\u00a0\n\u00b7 Immediately available is preferred", "employment_types": ["Full Time", "Permanent", "Internship"], "selling_points": ["Fast-track to Management Position", "Fresh Graduates are Welcome", "Fm HK$28,500 / m (Basic) + Bonus + Double Pay"], "locations": ["Causeway Bay"], "categories": ["Accounting", "Audit", "Professional Services", "Business Consultancy", "Management", "Management Trainee"], "post_time": "2022-01-16T07:36:04Z", "salary": {"currency": "HKD", "max": 44999, "min": 30000, "period": "monthly", "term": null}, "salary_visible": true, "title_keywords": ["management trainee"], "responsibilities": [], "requirements": {"degrees": [], "majors": [], "languages": [], "language_level": [], "hard_skills": [], "soft_skills": [], "languages_combined": []}, "experience_required": {"duration": [], "field": []}}, {"job_id": "100003009046689", "location_code": "hk", "company": "Michael Yam & Company", "job_title": "Audit Juniors / Intermediates / Semi-Seniors (5-day work)", "description": "Requirements :\n\n-\u00a0Degree or diploma holder with major study in accounting or equivalent.\n\n-\u00a0Student member of HKICPA or relevant accounting bodies.\n\n-\u00a0Eager to learn, hardworking and capable to work under pressure.\n\n-\u00a0Good communication and language skills.\n\n-\u00a0Grading will depend on relevant audit experience.\n\n- Fresh graduates are welcome.\n\n\nBenefits :\n\n-\u00a05-day work week.\n\n-\u00a0Annual bonus.\n\n-\u00a0Study leave and examination leave for recognised professional examinations.\n\n-\u00a0Allowance for exam fees.\n\n-\u00a0Qualified pay offered.\n\nPlease send us your full resume with details of education, working experience, availability, salary expected and telephone contact number by clicking \"Apply Now\".\u00a0\n\n\u00a0All personal data will be used for recruitment purpose only.", "employment_types": ["Full Time"], "selling_points": [], "locations": ["Wan Chai"], "categories": ["Accounting", "Audit", "Taxation"], "post_time": "2022-01-13T18:54:22Z", "salary": {"currency": null, "max": null, "min": null, "period": "monthly", "term": null}, "salary_visible": false, "title_keywords": [], "responsibilities": ["communication", "audit", "work under pressure"], "requirements": {"degrees": ["diploma holder", "degree"], "majors": ["accounting"], "languages": [], "language_level": [], "hard_skills": ["hkicpa"], "soft_skills": ["capable", "communication", "eager to learn", "hardworking", "work under pressure"], "languages_combined": []}, "experience_required": {"duration": [], "field": ["audit experience"]}}, {"job_id": "100003009048101", "location_code": "hk", "company": "Poon & Partners CPA Limited", "job_title": "AUDIT JUNIOR/AUDIT SEMI-SENIOR/AUDIT SENIOR", "description": "0-4 years relevant experience (fresh graduate student are also considered)\nUniversity Graduate\nStudent Member of HKICPA/ACCA\n\nPlease apply with full resume & expected salary to POON & PARTNERS CPA LIMITED at Room 1802, 18/F., Sunbeam Commercial Building, 469-471 Nathan Road, Kowloon, Hong Kong or by clicking 'Apply Now'.\n\nAll Personal data collected will be used for recruitment purpose only.\n", "employment_types": ["Full Time", "Permanent"], "selling_points": ["Fresh graduate student are also considered", "University Graduate and HKICPA/ACCA Student Member", "Study and Exam Leaves and Exam fee reimubursement"], "locations": ["Yau Ma Tei"], "categories": ["Accounting", "Accounting Clerk / Supervisor", "Audit", "Others", "Student / Fresh Graduate / No Experience"], "post_time": "2022-01-14T04:52:31Z", "salary": {"currency": null, "max": null, "min": null, "period": "monthly", "term": null}, "salary_visible": false, "title_keywords": ["junior"], "responsibilities": ["personal data", "recruitment"], "requirements": {"degrees": ["university graduate", "fresh graduate"], "majors": [], "languages": [], "language_level": [], "hard_skills": ["cpa", "acca", "hkicpa"], "soft_skills": [], "languages_combined": []}, "experience_required": {"duration": ["0-4 years"], "field": ["relevant experience"]}}, {"job_id": "100003009051934", "location_code": "hk", "company": "Octopus Holdings Limited", "job_title": "Head of Internal Audit (Ref: OCL/INA/2022-001 )", "description": "Job Responsibilities:\n\nLead and manage the IA team in conducting independent reviews of the financial reporting process and internal control systems of the companies, taking due considerations of the relevant governing laws, rules and regulations and its supervisory policies, guidelines and codes of practices\nDevelop an appropriate risk based audit approach for the companies to comply with its stored value facility license terms and conditions under the Banking Ordinance\nDevelop audit plans and programs that will achieve the audit objectives for each of the companies\nPerform an independent assessment to maintain effective internal control and compliance with established policies, procedures and plan, and government laws and regulations\nConduct self-assessments and special reviews as required by management, Audit Committee, the Board and Regulators\nFollow up and evaluate the effectiveness of remedial actions taken by management of auditee for ensuring rectification actions are timely taken to address audit findings and recommendations\nReport to the CEO and the Audit Committee with the results of audit work completed, for any fraud, errors, irregularities and other exceptions to the companies\u2019 internal control and/or governance requirements\u00a0\nProvide periodical reports / returns, and special reports when required, to the governing authority and relevant government agents\u00a0\u00a0\nOversee internal audit\u2019s participation in critical business and technology initiatives and projects ensuring that audit\u2019s perspective is effectively voiced and appropriate controls are designed and implemented\nHandle ad-hoc projects as assigned\n\nRequirements:\n\nBachelor degree in accounting, business, information technology or any relevant disciplines; Master degree/MBA holder is preferred\u00a0\nOver 15 years\u2019 working experience in auditing with at least 5 years gained from a major CPA firm; previous experience in leading IA team is essential\u00a0\nProfessional qualification in auditing / accounting, and/or IT audit / security (e.g. HKICPA, CIA, CISA, CISM, CISSP or equivalent)\nWell experienced in conducting IT audits in banks/authorized institutions is desired\nExcellent written and oral communication skills as well as interpersonal skills in dealing with the Board, senior management and other stakeholders.\u00a0\nStrong influencing and persuasion skills with the ability to manage a diverse set of internal and external stakeholders.\u00a0\nTeam player with ability to build, develop and lead a high performing team\u00a0\nResourceful and comfortable with ambiguity; able to self-direct and operate autonomously\u00a0\nAbility to roll up his/her sleeves as needed to drive towards results and adopt best market practices.\u00a0\nCommitment to the highest ethical, compliance and integrity standards\u00a0\nExcellent communication skills and people management skills with proficient in English and Chinese both written and spoken\nWe offer successful candidate an attractive remuneration package and excellent career prospects. Interested parties please send your resume, present and expected salary, contact details and quoting the reference number by clicking \"Apply Now\"\nVisit our web site:\u00a0http://www.octopus.com.hk/\nThe personal data collected will be used for recruitment purposes only. If you are not contacted by us within six weeks, you may consider your application unsuccessful. Personal data with an unsuccessful applicant will be destroyed 12 months after rejection of the application. During this retention period, you have the right to request for correction or destruction of your personal data at any time. Any request for the correction or destruction of personal data should be addressed in writing to our Human Resources & Administration Department.\nWe are an equal opportunity employer and will ensure that every job applicant and staff has equal employment opportunities and will not be disadvantaged because of their sex, pregnancy, marital status, family status, disability or race.", "employment_types": ["Full Time", "Permanent"], "selling_points": ["Develop an appropriate risk based audit approach", "Bachelor degree in accounting, business", "Over 15 years\u2019 working experience in auditing"], "locations": ["Kowloon Bay"], "categories": ["Accounting", "Accountant", "Audit", "Others"], "post_time": "2022-01-17T01:32:44Z", "salary": {"currency": null, "max": null, "min": null, "period": "monthly", "term": null}, "salary_visible": false, "title_keywords": [], "responsibilities": ["regulations", "internal audit", "audit", "maintain", "plan", "plans", "ad-hoc projects", "internal control", "compliance", "develop", "reports", "banking", "report", "management", "rectification", "procedures", "irregularities", "guidelines", "policies", "systems", "evaluate", "financial reporting"], "requirements": {"degrees": ["degree", "bachelor", "master degree"], "majors": ["business", "accounting", "information technology"], "languages": ["english", "chinese"], "language_level": ["excellent", "proficient"], "hard_skills": ["cpa", "hkicpa"], "soft_skills": ["communication skills", "oral", "resourceful", "integrity", "diverse", "interpersonal skills", "ethical", "team player"], "languages_combined": [{"language": "english", "language_level": ["proficient", "excellent"]}, {"language": "chinese", "language_level": ["proficient", "excellent"]}]}, "experience_required": {"duration": ["at least 5 years", "15 years"], "field": ["cpa firm", "team"]}}, {"job_id": "100003009043998", "location_code": "hk", "company": "Roger Kam & Co", "job_title": "Audit Senior / Semi Senior / Intermediate / Junior (5 DAYS WORK)", "description": "Key duties:\n\nCarrying out statutory audit and assurance engagements independently or in a team\nAssist in drafting audited financial statements with reports of directors and auditors\nPreparing tax computation and schedules for tax compliance\n\n\u00a0Requirements:\n\nDiploma or Degree holder in accountancy or related courses\n\n\u00a0We offer:\n\n5-day work\nAnnual leaves from 12 to 15 days according to length of services\u00a0\nPaid birthday holiday\nPaid marriage leave\u00a0\nPaid sick leave, medical insurance benefits\u00a0\nPaid study and examination leaves for attending professional exams \u00a0\nLocal meal allowances\nOvertime compensation benefit (covered non-office hours and non-working days)\nOverseas travel allowances\u00a0\nReimbursement of job-related seminars / course (such as HKICPA QP revision courses) \u00a0\nPerformance bonus two times every year\u00a0\nReimbursement of professional qualification membership fee / initial registration fee\u00a0\n\nSalary will commensurate with qualification and experience.\n\nInterested parties please send your application, full resume and present / expected salary by clicking \"Apply Now\".\u00a0\n\nPersonal data collected will be used for recruitment purpose only.", "employment_types": ["Full Time", "Permanent"], "selling_points": ["5-day work, Sick Leave, Birthday Leave", "Study and exam leaves, training allowances, etc", "Performance bonus (two times every year)"], "locations": ["Tsim Sha Tsui"], "categories": ["Accounting", "Audit", "Taxation", "Others"], "post_time": "2022-01-13T02:44:10Z", "salary": {"currency": null, "max": null, "min": null, "period": "monthly", "term": null}, "salary_visible": false, "title_keywords": ["junior"], "responsibilities": ["tax", "tax computation", "schedules", "compliance", "audit", "financial statements", "reports"], "requirements": {"degrees": ["diploma", "degree holder"], "majors": ["accountancy"], "languages": [], "language_level": [], "hard_skills": [], "soft_skills": [], "languages_combined": []}, "experience_required": {"duration": [], "field": []}}, {"job_id": "100003009045511", "location_code": "hk", "company": "Chang Leung Hui & Li C.P.A. Limited", "job_title": "AUDIT TRAINEE/ SEMI-SENIOR (5 days work)", "description": "Diploma/ Degree (Major in Accountancy is preferred)\nStudents/ Qualified members of HKICPA/ ACCA/ CPA Australia or equivalents\nFresh graduates are welcome\nGood command of both written and spoken English and Chinese. Putonghua speaking is an advantage\nYear end bonus\n10 days annual leave and overtime work leave\nStudy and examination leave\n\nPlease send resume and state expected salary and phone number:\n\nE-mail by clicking 'Apply Now'", "employment_types": ["Full Time", "Permanent"], "selling_points": [], "locations": ["Not Specified"], "categories": ["Accounting", "Audit", "Others"], "post_time": "2022-01-13T07:59:18Z", "salary": {"currency": null, "max": null, "min": null, "period": "monthly", "term": null}, "salary_visible": false, "title_keywords": ["trainee"], "responsibilities": [], "requirements": {"degrees": ["diploma", "degree"], "majors": ["accountancy"], "languages": ["putonghua", "english", "chinese"], "language_level": ["advantage", "good command"], "hard_skills": ["cpa", "acca", "hkicpa"], "soft_skills": ["overtime work"], "languages_combined": [{"language": "putonghua", "language_level": ["advantage"]}, {"language": "english", "language_level": ["good command"]}, {"language": "chinese", "language_level": ["good command"]}]}, "experience_required": {"duration": [], "field": []}}, {"job_id": "100003009040167", "location_code": "hk", "company": "CCTH CPA Limited", "job_title": "Audit Junior / Semi-Senior/ Senior - Audit and Assurance", "description": "\nRequirements:\n\nDegree holder in accounting or equivalent\nHaving audit experience is preferred\nImmediate available is preferred\nSenior positions are available for candidates with relevant experience and professional qualifications\nSalary will be commensurate with qualification and experience. We offer generous fringe benefits to the right candidates, including medical scheme, discretionary bonus, 5-day work week, structured in-house Continuing Professional Development (CPD) programme, annual leave, birthday leave, study and examination leave.\n\nInterested parties, please click \"Apply Now\" to submit your application.\n\nApplications will be treated in strict confidence. Personal data collected will be used for recruitment purposes only.\n", "employment_types": ["Full Time", "Permanent"], "selling_points": ["Good Location:Kowloon Commerce Centre( MTR 2 mins)", "5-day work week, Birthday Leave", "Discretionary bonus, Medical Scheme"], "locations": ["Kwai Hing"], "categories": ["Accounting", "Accountant", "Audit", "Others"], "post_time": "2022-01-12T01:44:08Z", "salary": {"currency": null, "max": null, "min": null, "period": "monthly", "term": null}, "salary_visible": false, "title_keywords": ["junior"], "responsibilities": ["audit"], "requirements": {"degrees": ["degree holder"], "majors": ["accounting"], "languages": [], "language_level": [], "hard_skills": ["scheme", "professional qualifications"], "soft_skills": ["structured"], "languages_combined": []}, "experience_required": {"duration": [], "field": ["audit experience", "relevant experience"]}}, {"job_id": "100003009052383", "location_code": "hk", "company": "Langham Hall Hong Kong Limited", "job_title": "Private Equity Fund Accountant (Fresh graduates are welcome)", "description": "Fund Accountant (Fresh graduates are welcome)\u00a0\nTo support our ongoing growth, our Langham Hall graduate roles provide excellent candidates with the opportunity to learn and train in a structured environment, broad work exposure and, to progress their career quickly. They will receive study support towards their preferred accountancy qualification (e.g. HKICPA, ACCA, CPA), mentoring and have the opportunity to work in a friendly, collaborative, social, stable and supportive environment.\u00a0\n\nTraining and Qualification support:\n\n\nWe offer full training and support via our \u2018Asia - Personal Development Programme\u2019.\u00a0 This covers technical training such as in private equity and real estate funds and understanding the impact of latest accounting standards and exposure drafts applicable to clients.\u00a0 In addition, non-technical skill development is provided such as to include communication, effective team working and organisational skills training.\nWe also offer external examination support including paid exam leave, exam fee support and, practical experience mentoring) to graduates pursuing their professional accountancy qualification\nResponsibilities include:\nSupporting the preparation of financial statements in accordance with IFRS and U.S. GAAP and quarterly investor reporting with financial performance calculations such as multiples and IRR\nLiaison with the client\u2019s working team members\nMaintenance of the full sets of accounts for the fund structure using our Private Equity implementation financial accounting system\nProvide ongoing compliance support for clients including AML/KYC, FATCA and Common Reporting Standard (CRS)\nSupporting the technical calculation of capital call / distribution and preparation of correspondence in accordance with the legal documents of the fund\nSupporting the client during the year-end audit, including the preparation of audit schedules\nRequirements:\nAccounting graduates with a strong academic track and a suitable accounting focused degree\n1-2 years accounting experience is helpful but not essential\nAudit experience or background is welcome\nNon-accounting graduates with a view to pursue professional accounting qualification will also be considered\nIntention to make a career as an accountant and pursue a professional accounting qualification\nA positive attitude, a sense of satisfaction from doing your best and self-discipline are all essential\nExcellent written and spoken communication skills\nExperience in using accounting packages for bookkeeping and report production is helpful but not essential\nMicrosoft Excel and Word experience, including the ability to produce neatly presented work\nApplication procedure:\n\n\nPlease email by clicking \"Apply Now\" with all of the following information:\n\nYour resume\nDetails of your full academic record including exams taken and grades obtained from high school through university (transcripts are not required at this stage)\nWork experience\nCurrent and expected salary\n\n(Applicant without stating the expected salary & work availability will not be considered)\n\n\u00a0All Personal data collected will be used for recruitment purpose only.", "employment_types": ["Full Time", "Permanent"], "selling_points": [], "locations": ["Central"], "categories": ["Accounting", "Accountant", "Audit", "Banking / Finance", "Fund Management"], "post_time": "2022-01-17T02:54:33Z", "salary": {"currency": null, "max": null, "min": null, "period": "monthly", "term": null}, "salary_visible": false, "title_keywords": ["accountant"], "responsibilities": [], "requirements": {"degrees": [], "majors": [], "languages": [], "language_level": [], "hard_skills": [], "soft_skills": [], "languages_combined": []}, "experience_required": {"duration": [], "field": []}}, {"job_id": "100003009041723", "location_code": "hk", "company": "Alfred H.K. Li & Co., CPA", "job_title": "AUDIT JUNIOR, SEMI-SENIOR, SENIOR AUDITORS AND SUPERVISORS", "description": "Alfred H.K. Li & Co., CPA is a fast-growing and highly dynamic CPA firm in Hong Kong.\n\nDue to continuous business expansion, we are looking for Audit junior, Semi-senior, Senior auditors and Supervisors who are conscientious, independent, responsible and hardworking.\n\nRequirements:\n\nDiploma/Associate Degree/Degree major in Accounting;\nStudent member of HKICPA/ACCA or equivalent preferred;\nGood command of both written and spoken English and Chinese is essential;\nWilling to travel to P.R.C. and fluent in Putonghua;\nOne to four years\u2019 audit experiences in audit firms preferred;\nGood command of knowledge in Microsoft Office and accounting software;\nGood interpersonal communication skill;\nAble to work under pressure and carry out multi-tasks independently;\nHardworking, honest, responsible and self\u2013motivated; and\nImmediate available is preferable.\n\nRemuneration will be commensurate with qualification and experiences.\u00a0\u00a0 We offer 5 days\u2019 work, discretionary performance bonus, 12 days annual leave, birthday leave, study and examination leaves and medical allowance.\n\nInterested candidates should forward your resume, expected and present salary and date of availability by clicking Apply Now.\n\nPersonal data collected will be used for recruitment purposes only.", "employment_types": ["Full Time", "Permanent"], "selling_points": [], "locations": ["Kwun Tong"], "categories": ["Accounting", "Accounting Clerk / Supervisor", "Audit", "Taxation"], "post_time": "2022-01-12T04:16:06Z", "salary": {"currency": null, "max": null, "min": null, "period": "monthly", "term": null}, "salary_visible": false, "title_keywords": ["junior"], "responsibilities": ["communication", "audit", "software", "work under pressure"], "requirements": {"degrees": ["associate degree", "diploma", "degree"], "majors": ["accounting"], "languages": ["putonghua", "english", "chinese"], "language_level": ["good command", "fluent"], "hard_skills": ["acca", "microsoft office", "accounting software", "cpa", "dynamic", "c", "r", "hkicpa"], "soft_skills": ["independently", "independent", "responsible", "multi-tasks", "communication skill", "dynamic", "motivated", "honest", "conscientious", "interpersonal", "hardworking", "work under pressure"], "languages_combined": [{"language": "putonghua", "language_level": ["fluent"]}, {"language": "english", "language_level": ["good command"]}, {"language": "chinese", "language_level": ["good command"]}]}, "experience_required": {"duration": ["one to four years"], "field": ["audit"]}}, {"job_id": "100003009046870", "location_code": "hk", "company": "World Link CPA Ltd", "job_title": "Auditor (Junior / Senior)", "description": "What you will have\n\nA platform for long-term career development\nExcellent career prospect\u00a0\nMentorship scheme\nCompetitive remuneration package in accordance with experience and qualification\nAnnual / Birthday / Study / Exam leaves\nGroup medical insurance\nFree beverage & snacks\u00a0\nEnergetic & harmonious working environment\n\nDesired experience & skillsets\n\nDiploma or above in Accounting or related disciplines preferred\nAssociate/student member of HKICPA/CPA(Aust.)/ACCA or other major accountancy associations preferred\u00a0but not a must\nNo relevant experience is required for the post of Auditor\nMinimal 2 years solid experience and strong coaching skills for the post of Senior Auditor\nStrong initiative with passion to pursue career in related field\nMeticulous with good analytical skill\nGood command in English and Putonghua, both written and spoken\nProficient in MS Office\nWilling to travel if required\n\nFor more information about us, please visit our website at www.worldlinkcpa.com.\n\u00a0\nInterested parties, please submit your application with detailed resume including present and expected salary and date of availability by clicking 'Apply Now'. \u00a0\n\nPersonal data collected will be used in accordance with our personal data policy and for recruitment purposes only. Candidates not hearing from us within 2 months may consider their applications unsuccessful. All personal data collected will be destroyed within 24 months. A copy of our Personal Information Collection Statement will be provided upon request.", "employment_types": ["Full Time", "Permanent"], "selling_points": ["Assignments from wide variety of industries", "Clear career path, with mentorship scheme", "5-day work week, people-oriented culture"], "locations": ["Central"], "categories": ["Accounting", "Audit", "Taxation", "Others", "Student / Fresh Graduate / No Experience"], "post_time": "2022-01-14T01:32:42Z", "salary": {"currency": null, "max": null, "min": null, "period": "monthly", "term": null}, "salary_visible": false, "title_keywords": ["junior"], "responsibilities": ["insurance", "website", "career development"], "requirements": {"degrees": ["diploma or above"], "majors": ["related disciplines", "accounting"], "languages": ["putonghua", "english"], "language_level": ["good command"], "hard_skills": ["no", "acca", "analytical skill", "scheme", "ms office", "hkicpa"], "soft_skills": ["meticulous", "analytical skill", "harmonious", "energetic", "initiative"], "languages_combined": [{"language": "putonghua", "language_level": ["good command"]}, {"language": "english", "language_level": ["good command"]}]}, "experience_required": {"duration": ["2 years"], "field": ["relevant experience"]}}, {"job_id": "100003009044075", "location_code": "hk", "company": "KLC Kennic Lui & Co. Limited", "job_title": "Audit Associate", "description": "Requirements:\u00a0\n\nIVE / HKAAT / Diploma / Bachelor Degree holder (from all disciplines)\nGood\u00a0command in written and spoken English and Chinese, and fluency in Putonghua;\nPassionate, committed and eager to learn\nSelf motivated with good analytical and problem-solving skills\nFresh\u00a0graduates will be considered\u00a0\nWe offer competitive remuneration packages and attractive staff fringe benefits to the right candidate.\u00a0\u00a0\nIf you are interested to join our KLC 2022/2023 Graduate Programme, please submit your application and full resume, current and expected salary to our Human Resource Department at 5th Floor, Ho Lee Commercial Building, 38-44 D\u2019Aguilar Street, Central, Hong Kong or click \u201cApply Now\u201d.\u00a0 Personal data will be collected for recruitment purposes only.\u00a0", "employment_types": ["Full Time", "Permanent"], "selling_points": [], "locations": ["Central"], "categories": ["Accounting", "Audit", "Taxation"], "post_time": "2022-01-13T02:58:37Z", "salary": {"currency": null, "max": null, "min": null, "period": "monthly", "term": null}, "salary_visible": false, "title_keywords": ["associate"], "responsibilities": [], "requirements": {"degrees": ["diploma", "bachelor degree holder"], "majors": [], "languages": ["putonghua", "english", "chinese"], "language_level": ["fluency", "good command"], "hard_skills": ["problem-solving skills"], "soft_skills": ["passionate", "self motivated", "committed", "eager to learn", "problem-solving skills"], "languages_combined": [{"language": "putonghua", "language_level": ["fluency", "good command"]}, {"language": "english", "language_level": ["fluency", "good command"]}, {"language": "chinese", "language_level": ["fluency", "good command"]}]}, "experience_required": {"duration": [], "field": []}}]