[{"job_id": "100003009054674", "location_code": "hk", "company": "Moore Associates Limited", "job_title": "MNC in Hong Kong \u2013 Assistant Finance Manager/ Finance Manager", "description": "The company is a well-established lifestyle brand in Europe and now looking to grow and expand in Asia with the right candidate in the Asia Office.\n\nJob Responsibilities\n\nReport to the Head of the regional office for Asia to oversee and manage the finance and accounting function of the region (Station in Hong Kong)\nResponsible for daily accounting operation including treasury, A/P, A/R, costing, GL, invoicing, bank reconciliations\nPrepare regular reporting package such as monthly full-set accounting, financial reporting, management reporting, cashflow statements, group reporting, segment report, using the in-house finance module ERP system\nWork with and report to the GM directly on annual budget and forecast\nIdentify accounting and financial issues, communicate potential impact and recommendations to the GM.\nLiaise with external firm to handle annual audit, tax filing and assist in reviewing finance and accounting work\nReview internal controls and improve overall efficiency of finance functions\nFollow up with customers on overdue payment status\nAd-hoc jobs related to accounting\n\nSuccessful Applicant\n\nUniversity graduate, preferably in finance and accounting, with professional accounting qualification\nAt least 5 years of relevant experience in handling full sets of accounting, budget and forecast, analyst, financial reporting, group reporting with commercial experience\nExperience in retail / fashion wholesale industry is advantageous, but not a must\nProficiency in MS applications, such as Word, Excel and PowerPoint with hands-on experience in finance module ERP system is an advantage\nA good team player who is pro-active and able to work independently\nStrong analytical, communication and interpersonal skills\nExcellent command of English, Cantonese and Mandarin\n\nWe offer a 5-day working week, a competitive remuneration package and generous fringe benefits.\u00a0\n\nInterested candidates please send the full resume with current and expected salary\u00a0by clicking the \"Apply Now\" button\n\nFor more information, please visit our website www.carhartt-wip.com.", "employment_types": ["Full Time", "Permanent"], "selling_points": ["Lifestyle brand in Europe", "Manage the finance and accounting function", "Prepare regular reporting package"], "locations": ["Tsim Sha Tsui"], "categories": ["Accounting", "Accountant", "Chief Accountant", "Others"], "post_time": "2022-01-17T10:30:32Z", "salary": {"currency": null, "max": null, "min": null, "period": "monthly", "term": null}, "salary_visible": false, "title_keywords": ["assistant finance manager", "finance manager"], "responsibilities": ["ad-hoc", "reporting", "annual audit", "budget", "tax filing", "bank reconciliations", "review", "invoicing", "communication", "payment", "financial reporting", "management reporting", "forecast", "liaise with", "daily accounting", "report"], "requirements": {"degrees": ["university graduate"], "majors": ["finance", "accounting"], "languages": ["cantonese", "english", "mandarin"], "language_level": ["excellent"], "hard_skills": ["excel", "ms applications", "word", "powerpoint", "erp system", "gm", "r"], "soft_skills": ["good team player", "work independently", "responsible", "hands-on", "communication and interpersonal skills", "pro-active"], "languages_combined": [{"language": "cantonese", "language_level": ["excellent"]}, {"language": "english", "language_level": ["excellent"]}, {"language": "mandarin", "language_level": ["excellent"]}]}, "experience_required": {"duration": ["at least 5 years"], "field": ["finance", "commercial", "erp system", "relevant experience", "accounting", "retail", "financial"]}}, {"job_id": "100003009051881", "location_code": "hk", "company": "Luen Tai Group (China) Limited", "job_title": "Accounting Officer / Assistant Accountant", "description": "Responsibilites:\n-\u00a0Handle\u00a0full\u00a0set\u00a0of\u00a0accounts in HK\n-\u00a0Handle\u00a0AR\u00a0&\u00a0AP\u00a0invoices\u00a0&\u00a0settlement,\u00a0accounts\u00a0reconciliation\n-\u00a0Handle\u00a0bank\u00a0payments\u00a0and\u00a0receipts\u00a0including\u00a0L/C\n-\u00a0Prepare\u00a0timely\u00a0cash flow\u00a0statement to top management\n-\u00a0Maintain\u00a0up-to-date\u00a0data\u00a0in\u00a0accounting\u00a0system\u00a0and\u00a0filing\u00a0records\n-\u00a0Assist\u00a0in\u00a0preparing\u00a0month\u00a0end\u00a0closing\u00a0reports\u00a0and\u00a0annual\u00a0audit\n-\u00a0Handle\u00a0ad\u00a0hoc\u00a0projects\u00a0as\u00a0required\n-\u00a0Report\u00a0to\u00a0Accounting\u00a0Manager\n\n\n\nRequirements:\n- Diploma or above in Accounting\n- 3-5 years or above accounting experience\n- Membership of professional group is essential\n- PRC manufacturing experience would be an advantage\n- Proficiency in using MS office, knowledge of\u00a0 ERP system is a plus\n- Mature, responsible, detailed mind with ability to handle multiple tasks independently under pressure\n- Strong organization, good interpersonal and communication skills\n- Good command of both written and spoken in English, Cantonese and Mandarin\n- Immediate available or short notice is highly preferable\n\nWe offer the competitive remuneration to right candidates. Applicant with more experience or qualification will be considered as \"Assistant Accountant\"\n\nInterest parties please send us full resume & expected salary to us.\n\n\"Personal data collected will be used for recruitment purpose only.\"", "employment_types": ["Full Time"], "selling_points": [], "locations": ["Wong Tai Sin Area"], "categories": ["Accounting", "Accountant", "Accounting Clerk / Supervisor", "Chief Accountant"], "post_time": "2022-01-17T01:26:15Z", "salary": {"currency": null, "max": null, "min": null, "period": "monthly", "term": null}, "salary_visible": false, "title_keywords": ["assistant accountant", "accounting officer"], "responsibilities": ["ap", "management", "month end closing", "invoices", "ar", "receipts", "data", "annual audit", "full set of accounts", "cash flow", "maintain", "payments", "reports", "ad hoc projects", "report"], "requirements": {"degrees": ["diploma or above"], "majors": ["accounting"], "languages": ["cantonese", "english", "mandarin"], "language_level": ["good command"], "hard_skills": ["prc manufacturing", "erp system", "plus", "ms office"], "soft_skills": ["communication skills", "independently", "under pressure", "responsible", "mature", "handle multiple tasks", "detailed mind", "interpersonal"], "languages_combined": [{"language": "cantonese", "language_level": ["good command"]}, {"language": "english", "language_level": ["good command"]}, {"language": "mandarin", "language_level": ["good command"]}]}, "experience_required": {"duration": ["3-5 years"], "field": ["accounting experience", "manufacturing"]}}, {"job_id": "100003009044675", "location_code": "hk", "company": "Aaron Shum Jewelry Limited", "job_title": "Chief Accountant", "description": "Qualified Accountant and Bachelor\u2019s Degree major in Accounting / Finance.\nAt least 10 years experiences, strong in financial reporting, regulatory reporting, cost accounting, cash flow management and familiar with taxation of both HK and the PRC.\nExperience in Manufacturing industries is required and knowledge in Jewelry field is an advantage.\nResponsible for full set of accounts including consolidation, financial management reporting, preparing account analysis and accounts reconciliation and month end closing.\nExperience in financial audits, budgeting and forecasting.\nCoordinate audit related activities and liaise with auditors during the auditing process.\nSupport as needed with input and reconciliation in group portfolio management accounting software.\nMonitoring the preparation and submission of financial and management reports, and handling ad-hoc assignments as required.\nReview and monitor accounting and taxation related issues.", "employment_types": ["Full Time", "Permanent"], "selling_points": ["Accounting", "Qualified Accountant", "Finance"], "locations": ["Hung Hom"], "categories": ["Accounting", "Accountant", "Chief Accountant", "Financial Controller"], "post_time": "2022-01-13T05:19:07Z", "salary": {"currency": null, "max": null, "min": null, "period": "monthly", "term": null}, "salary_visible": false, "title_keywords": ["accountant"], "responsibilities": ["software", "budgeting", "audit", "liaise with", "month end closing", "full set of accounts", "monitor", "forecasting", "reporting", "cost", "management", "monitoring", "review", "cash flow", "management reporting", "audits", "taxation", "ad-hoc assignments", "analysis", "coordinate", "management reports", "financial reporting", "auditing"], "requirements": {"degrees": ["degree", "bachelor"], "majors": ["finance", "accounting"], "languages": [], "language_level": [], "hard_skills": ["accounting software", "analysis", "management reports"], "soft_skills": ["responsible"], "languages_combined": []}, "experience_required": {"duration": ["at least 10 years"], "field": ["management", "accounting", "manufacturing", "financial"]}}, {"job_id": "100003009052545", "location_code": "hk", "company": "AOSource Company Limited", "job_title": "Finance Manager    (FM-0117-sh-JDB)", "description": "Our client is a Listed group,\u00a0 Current they are looking for potential candidate to join their Finance team in Hong Kong.\n\nResponsibilities;\n\nReport to Head of Finance (General Account & Finance Analysis);\nTo\u00a0Lead a small team of Finance Operation Team in Hong Kong;\n\nHandle full set of account including operaton /finance analysis/ management account etc;\nTo perform and lead the accounting process and procedure, ensuring compliance with the accounting policies and guidelines;\nLead and coaching to a small team to manage accounting reporting & reporting;\nGood communcation with English and Chinese is must.\nRequirements:\n\nDegree or Above in Accounting or related discipline;\n\nHolder of CPA professional qualification and experience in 4A CPA Firm is a plus;\nAbout 8+\u00a0 years working experience in Full set of accounting and Management Accounting;\nExperience in Multi-national group is preferred;\nSolid Experience in Asia Pacific Trading Business is preferred;\nGood experience in dealing with various country business user;\nUsing software with MS Office (Execl, Word, Powerpoint) and Oracle Finance is a plus;\nExcellent spoken and written communication skill in English;\nWork independently and good team leadership.\nOur client will offer competitive remuneration package and good career prospects to the potential candidate, interested parties please quote ref.no.FM-0117-sh-JDB and submit your resume to Ms Fung by our email or enquiry with Tel:3428-6121.\n\n\nAll profiles are handled with strictest confidentiality. Shortlisted candidates would be notified", "employment_types": ["Full Time", "Permanent"], "selling_points": ["MNC Group/ Asia Pacific Trading", "CPA /Full set of Account/ Lead a small team", "Exp. in Trading/ Fin operation/ Mgmt acct"], "locations": ["Not Specified"], "categories": ["Accounting", "Chief Accountant", "Finance / Accounting Manager", "Financial Analyst"], "post_time": "2022-01-17T03:22:52Z", "salary": {"currency": null, "max": null, "min": null, "period": "monthly", "term": null}, "salary_visible": false, "title_keywords": ["finance manager"], "responsibilities": ["reporting", "management", "guidelines", "analysis", "compliance", "lead a small team", "accounting policies", "report"], "requirements": {"degrees": ["degree or above"], "majors": ["accounting"], "languages": ["english"], "language_level": ["excellent"], "hard_skills": ["plus", "oracle", "word", "powerpoint", "cpa", "ms office"], "soft_skills": ["work independently", "communication skill", "leadership"], "languages_combined": [{"language": "english", "language_level": ["excellent"]}]}, "experience_required": {"duration": [], "field": ["management accounting", "cpa firm", "business", "accounting", "trading"]}}, {"job_id": "100003009050021", "location_code": "hk", "company": "Shun Tak Property Management Limited", "job_title": "Accounting Manager", "description": "Job Duties:\n\nTo supervise a team for managing all daily operations of accounting function in Hong Kong and Macau\nTo perform timely and accurate financial reporting\nTo ensure and review the compliance of the group financial policies and procedures\nTo review and enhance workflows for better and efficient financial operation and reporting\nTo support in ad hoc financial evaluation supporting for business planning / development projects\n\nRequirements:\n\nDegree holder in Accounting and processed Accountancy qualifications\nMember of HKICPA / ACCA or equivalent\nMinimum 8 years\u2019 working experiences, exposure in the industry of property management is an advantage\nMature, detail orientated, excellent time management and interpersonal skills\nBusiness acumen with logical presentations in report writing\nTravel occasionally to Macau\n\n\u00a0We will offer attractive compensation package to the right candidate. Please send application enclosing resume stating career and salary history, expected salary and date of availability to The HR Dept, Rooms 908-11, 9/F, West Tower, Shun Tak Centre, 200 Connaught Road Central, Hong Kong by email to pm_hr(at)shuntakgroup.com\u00a0 (in Word format).\u00a0\u00a0Please quote the reference of the position you apply for in all correspondences.\n\nThe information supplied by the applicants will be used in accordance with the Personal Data (Privacy) Policy of Shun Tak Group (a copy of which will be provided upon request). Only shortlisted candidates will be notified. www.shuntakgroup.com", "employment_types": ["Full Time", "Permanent"], "selling_points": ["Accountancy qualifications", "Member of HKICPA/ACCA or equivalent", "Min 8 years relevant working experience"], "locations": ["Sheung Wan"], "categories": ["Accounting", "Chief Accountant", "Finance / Accounting Manager", "Others", "Others"], "post_time": "2022-01-14T09:38:51Z", "salary": {"currency": null, "max": null, "min": null, "period": "monthly", "term": null}, "salary_visible": false, "title_keywords": ["accounting manager"], "responsibilities": ["reporting", "ad hoc", "financial policies", "compliance", "review", "procedures", "daily operations", "financial reporting", "evaluation", "planning"], "requirements": {"degrees": ["degree holder"], "majors": ["accounting", "accountancy"], "languages": [], "language_level": [], "hard_skills": ["acca", "word", "presentations", "hkicpa", "acumen"], "soft_skills": ["mature", "interpersonal skills", "detail orientated", "business acumen", "time management"], "languages_combined": []}, "experience_required": {"duration": ["minimum 8 years"], "field": ["management"]}}, {"job_id": "100003009040095", "location_code": "hk", "company": "", "job_title": "Accountant / Assistant Accountant", "description": "Job Requirements:\n\nDiploma or Degree Holder in Accounting or related discipline\nAt least 2-4 years relevant working experience\nSolid working experience in handling full set of accounts\nProficient in MS Word and Excel\nResponsible and self-motivated\nDetail-minded and independent\nGood communication skills\nPositive and meticulous\nMore experience will be considered as Accountant\n\n5-day work.\u00a0 An attractive package will be offered to the right candidate.\u00a0 Interested parties please\u00a0send resume to Hz Job Consultant Ltd. by email to job@hzjob.com\n\n(All personal data collected will be treated in strict confidence and used for recruitment purpose only)", "employment_types": ["Full Time", "Permanent"], "selling_points": [], "locations": ["Not Specified"], "categories": ["Accounting", "Accountant", "Accounting Clerk / Supervisor", "Chief Accountant"], "post_time": "2022-01-12T01:22:31Z", "salary": {"currency": null, "max": null, "min": null, "period": "monthly", "term": null}, "salary_visible": false, "title_keywords": ["accountant", "assistant accountant"], "responsibilities": ["communication", "full set of accounts"], "requirements": {"degrees": ["diploma", "degree holder"], "majors": ["accounting"], "languages": [], "language_level": [], "hard_skills": ["excel", "ms word"], "soft_skills": ["detail-minded", "communication skills", "self-motivated", "meticulous", "independent", "responsible", "positive"], "languages_combined": []}, "experience_required": {"duration": ["at least 2-4 years"], "field": ["relevant working experience"]}}, {"job_id": "100003009047593", "location_code": "hk", "company": "Hong Huan Group Limited", "job_title": "Financial Controller", "description": "Responsibilities\n\nDevelop and oversee the finance & accounting functions in collaboration with Business Units and head office\nProviding accounting and financial insights to improve operational efficiency\nReporting to CFO, involve in strategic planning with top management related with all accounting and finance functions\nDevise the finance related policies complying to all applicable laws and regulations for the group\nOffer financial advice to management in corporate finance exercises such as M&A, investments etc.\nOn-going review of portfolio companies financial planning, reporting, forecast and budgeting activities\nEnsure timely and accurate preparation and submission of monthly financial and management reports for management review and for group consolidation and reporting purpose\nProvide business advice for process improvement, taxation and corporate governance\n\nRequirements\nQualified accountant with a degree or above in Accounting or Finance or related discipline\nMinimum of 15 years working experience includes proven track record at a senior management level\nAbility to consult and advise operating and corporate leaders on issues related to accounting, financial reporting, internal control and regulatory issues\nStrong leadership skills with high level of self-motivation and initiative\nProven analytical, organizational and problem-solving skills\nStrong interpersonal and communication skills, both verbal and written in English, Cantonese and Mandarin\nSuperior organizational skills and the ability to prioritize in a dynamic working environment\nPossess good communication, interpersonal and stakeholder management skills\nDemonstrate strong business acumen\nInterested parties please send full resume with current and expected salary by clicking the \"APPLY NOW\" button below.\nAll information provided by applicants will be treated in strict confidence and used only for recruitment purposes. Applicants may be considered for other suitable positions by our Company & the subsidiaries over not more than 6 months, after which their personal data will be destroyed.", "employment_types": ["Full Time", "Permanent"], "selling_points": [], "locations": ["Ngau Tau Kok"], "categories": ["Accounting", "Chief Accountant", "Financial Analyst", "Financial Controller"], "post_time": "2022-01-14T03:32:00Z", "salary": {"currency": null, "max": null, "min": null, "period": "monthly", "term": null}, "salary_visible": false, "title_keywords": ["financial controller"], "responsibilities": ["regulations", "reporting", "management", "taxation", "strategic planning", "policies", "budgeting", "review", "develop", "management reports", "forecast", "management review", "planning"], "requirements": {"degrees": ["degree or above"], "majors": ["finance", "accounting"], "languages": ["cantonese", "english", "mandarin"], "language_level": [], "hard_skills": ["problem-solving skills", "dynamic", "acumen", "internal control"], "soft_skills": ["communication skills", "organizational skills", "organizational", "leadership skills", "prioritize", "communication", "self-motivation", "dynamic", "business acumen", "problem-solving skills", "interpersonal", "initiative", "superior"], "languages_combined": [{"language": "cantonese", "language_level": []}, {"language": "english", "language_level": []}, {"language": "mandarin", "language_level": []}]}, "experience_required": {"duration": ["minimum of 15 years"], "field": ["management"]}}, {"job_id": "100003009037431", "location_code": "hk", "company": "Caiyun International Investment Limited", "job_title": "Finance Manager \u8ca1\u52d9\u90e8\u7d93\u7406", "description": "Responsibilities\u00a0\u804c\u8d23\n\nResponsible for financial planning & management, cash flow management, tax planning, auditing, costing and budgeting\n\u8d1f\u8d23\u8d22\u52a1\u89c4\u5212\u4e0e\u7ba1\u7406\u3001\u73b0\u91d1\u6d41\u7ba1\u7406\u3001\u7a0e\u52a1\u89c4\u5212\u3001\u5ba1\u8ba1\u3001\u6210\u672c\u548c\u9884\u7b97\u7b49\nResponsible for corporate finance functions including M&A, financial advisory and fund raising activities\n\u8d1f\u8d23\u4f01\u4e1a\u878d\u8d44\u5de5\u4f5c\uff0c\u5305\u62ec\u5e76\u8d2d\uff0c\u8d22\u52a1\u54a8\u8be2\u548c\u7b79\u96c6\u8d44\u91d1\u7b49\n\nHandling due diligence and execution of corporate finance projects\n\u5bf9\u6295\u878d\u8d44\u9879\u76ee\u8fdb\u884c\u8c03\u7814\u3001\u8bc4\u4f30\u53ca\u7efc\u5408\u8bba\u8bc1\uff0c\u5e76\u53c2\u4e0e\u9879\u76ee\u7acb\u9879\u5de5\u4f5c\nBuild complex financial models, provide quantitative analysis and make recommendations to support decision-making\n\u6784\u5efa\u5b8c\u5584\u7684\u8d22\u52a1\u6a21\u578b\uff0c\u63d0\u4f9b\u7cbe\u51c6\u5206\u6790\u53ca\u826f\u597d\u5efa\u8bae\u4ee5\u652f\u6301\u51b3\u7b56\n\nAnalyse capital structure, balance sheet classification, corporate and project funding and financing options, cost of capital, liquidity, creditworthiness, regulatory and compliance requirements and working capital management\n\u5b9a\u65f6\u5206\u6790\u8d44\u672c\u7ed3\u6784\u3001\u8d44\u4ea7\u8d1f\u503a\u8868\u5206\u7c7b\u3001\u516c\u53f8\u548c\u9879\u76ee\u878d\u8d44\u548c\u878d\u8d44\u9009\u62e9\u3001\u8d44\u672c\u6210\u672c\u3001\u6d41\u52a8\u6027\u3001\u4fe1\u7528\u3001\u76d1\u7ba1\u548c\u5408\u89c4\u8981\u6c42\u4ee5\u53ca\u8425\u8fd0\u8d44\u91d1\u7ba1\u7406\nSubmit RMB audit report, state-owned assets budget to parent\u2019s company and responsible for related affairs of the group\n\u5411\u80a1\u4e1c\u516c\u53f8\u4e0a\u62a5\u4eba\u6c11\u5e01\u5ba1\u8ba1\u62a5\u544a\u3001\u56fd\u8d44\u9884\u51b3\u7b97\u4ee5\u53ca\u5bf9\u63a5\u96c6\u56e2\u76f8\u5173\u4e8b\u52a1\n\nMaintain banking, risk management and borrowing programme\n\u7ef4\u62a4\u94f6\u884c\u3001\u98ce\u9669\u7ba1\u7406\u548c\u501f\u8d37\u8ba1\u5212\nLiaise with Government, bankers, external auditors, legal advisers and tax representatives to ensure compliance of rules and regulations\n\u8d1f\u8d23\u4e0e\u653f\u5e9c\u4ee5\u53ca\u5404\u5927\u91d1\u878d\u673a\u6784\uff0c\u5916\u90e8\u5ba1\u8ba1\u5e08\uff0c\u6cd5\u5f8b\u987e\u95ee\u548c\u7a0e\u52a1\u4ee3\u8868\u4fdd\u6301\u8054\u7edc\uff0c\u5e76\u786e\u4fdd\u9075\u5b88\u6cd5\u5f8b\u6cd5\u89c4\nReview financial policies and systems regularly\u00a0\n\u5b9a\u671f\u5ba1\u67e5\u8d22\u52a1\u653f\u7b56\u548c\u5236\u5ea6\n\nOther ad-hoc projects if required\n\u5176\u4ed6\u4e34\u65f6\u9879\u76ee/\u4efb\u52a1\nOccasionally travel is required\n\u6709\u673a\u4f1a\u51fa\u5dee\u516c\u5e72\n\nRequirement \u5165\u804c\u8981\u6c42\n\nDegree holder in Accountancy or related disciplines, a professional accounting qualification (HKICPA, ACCA) is required\n\u6301\u6709\u4f1a\u8ba1\u6216\u76f8\u5173\u5b66\u4f4d, HKICPA, ACCA \u8d44\u683c\n\nAt least 5 years' relevant Corporate Finance, Accounting, Financing experience\u00a0\n\u81f3\u5c115\u5e74\u4f01\u4e1a\u878d\u8d44/ \u4f1a\u8ba1/ \u8d22\u52a1\u7ecf\u9a8c\nSolid PRC exposure, China background or state-owned enterprise experience preferred\n\u6709\u5185\u5730\u5de5\u4f5c\u7ecf\u9a8c, \u4e2d\u8d44\u80cc\u666f\u53ca\u56fd\u6709\u4f01\u4e1a\u5de5\u4f5c\u7ecf\u9a8c\u8005\u4f18\u5148\n\nTraining in Big 4, commercial exposure in bank industry or financial institutions is preferred\n\u6709\u56db\u5927\u4f1a\u8ba1\u5e08\u884c\u53ca\u91d1\u878d, \u94f6\u884c\u4e1a\u5de5\u4f5c\u7ecf\u9a8c\u8005\u4f18\u5148\nKnowledge in taxation of Hong Kong & China is a plus\n\u4e86\u89e3\u9999\u6e2f\u7a0e\u52a1\u53ca\u5185\u5730\u7a0e\u52a1\n\nFamiliar with financial reporting and procedure of SOE , SASAC(\u56fd\u8d44\u59d4)\u00a0 and NDRC (\u53d1\u6539\u59d4) is an advantage\n\u719f\u6089\u8d22\u52a1\u62a5\u544a\u53ca\u878d\u8d44\u7ecf\u9a8c, \u4f8b\u5982SOE , SASAC(\u56fd\u8d44\u59d4)\u00a0 and NDRC (\u53d1\u6539\u59d4)\n\nGood at typewriting with simplified Chinese is preferred\n\u80fd\u7528\u4e2d\u6587\u7b80\u4f53\u6253\u5b57\u53ca\u64b0\u5199\u4e2d\u6587\u62a5\u544a\nProficiency in spoken and written Mandarin, English and Cantonese\n\u6d41\u5229\u7684\u666e\u901a\u8bdd, \u82f1\u6587\u53ca\u5e7f\u4e1c\u8bdd\u53ca\u4e66\u5199\u80fd\u529b\nImmediate available is highly preferred\n\u5373\u65f6\u4e0a\u73ed\u4f18\u5148\n\nWe offer 5-day work, Monday to Friday 9:00am - 5:30pm, MPF, double pay, 14 days annual leave, medical insurance etc. Quality applicants please submit your \u4e2d\u6587\u7b80\u5386\u00a0with availability, current and expected salary to us.\n\n\u201cPersonal data collected will be treated in strict confidence and used for recruitment process only\u201d", "employment_types": ["Full Time", "Permanent"], "selling_points": [], "locations": ["Wan Chai"], "categories": ["Accounting", "Chief Accountant", "Finance / Accounting Manager", "Banking / Finance", "Corporate Finance"], "post_time": "2022-01-11T02:47:37Z", "salary": {"currency": null, "max": null, "min": null, "period": "monthly", "term": null}, "salary_visible": false, "title_keywords": ["finance manager"], "responsibilities": ["regulations", "budgeting", "budget", "financial policies", "audit", "maintain", "planning", "liaise with", "ad-hoc projects", "make recommendations", "due diligence", "financial models", "project funding", "compliance", "banking", "balance sheet", "report", "management", "cost", "review", "cash flow", "tax", "analysis", "systems", "external auditors", "ensure compliance", "auditing", "analyse"], "requirements": {"degrees": ["degree holder"], "majors": ["related disciplines", "accounting", "accountancy"], "languages": ["cantonese", "english", "chinese", "mandarin"], "language_level": ["proficiency", "good"], "hard_skills": ["acca", "plus", "typewriting", "hkicpa"], "soft_skills": [], "languages_combined": [{"language": "cantonese", "language_level": ["proficiency"]}, {"language": "english", "language_level": ["proficiency"]}, {"language": "chinese", "language_level": ["good"]}, {"language": "mandarin", "language_level": ["proficiency"]}]}, "experience_required": {"duration": ["at least 5 years"], "field": ["accounting", "financing", "corporate finance"]}}, {"job_id": "100003009049782", "location_code": "hk", "company": "Find Asia Limited", "job_title": "Accounting Manager/ Assistant Manager", "description": "Our client, an electronics manufacturing co. is looking for the candidate with the following details:\u00a0\n\n\u00a0Duties\n\nReview the Accounting operation, month-end closing, reporting and forecasting, budgeting and analysis report\nPrepare the regional consolidation and management reporting of the Group\u00a0\nPerform various analysis and provide commentaries to management\u00a0\nLiaise with internal dept. for budgeting, forecast and cost control\u00a0\nEnsure accounting policies and procedures in line with statutory requirement and tax affairs\nSystem implementation\u00a0\nAnalyze regional logistics situation and inventory control\u00a0\n\n\u00a0Requirement\u00a0\n\nGood command of English & Mandarin\nQualified accounting certificate/ CPA\n10 years experience in Accounting in trading or manufacturer\u00a0\nWith experience in consolidating, monitoring and reviewing overseas (e.g. Asian countries) accounting, inventory control and internal control\u00a0\nGood management skill and able to work independent\u00a0\nGood Excel skill, PowerPoint and Chinese Word Processing", "employment_types": ["Full Time", "Permanent"], "selling_points": ["Accounting Manager", "Reporting, budgeting, analysis, consolidation", "5 days, TST"], "locations": ["Tsim Sha Tsui"], "categories": ["Accounting", "Chief Accountant", "Finance / Accounting Manager", "Financial Analyst"], "post_time": "2022-01-15T03:50:35Z", "salary": {"currency": null, "max": null, "min": null, "period": "monthly", "term": null}, "salary_visible": false, "title_keywords": ["assistant manager", "accounting manager"], "responsibilities": ["tax", "reporting", "management", "analysis report", "budgeting", "analysis", "review", "procedures", "implementation", "accounting policies", "month-end closing", "logistics", "management reporting", "forecast", "cost control", "liaise with", "inventory control", "forecasting"], "requirements": {"degrees": ["certificate"], "majors": ["accounting"], "languages": ["english", "chinese", "mandarin"], "language_level": ["good command", "good"], "hard_skills": ["excel", "chinese word processing", "powerpoint", "cpa", "internal control"], "soft_skills": ["independent"], "languages_combined": [{"language": "english", "language_level": ["good command", "good"]}, {"language": "chinese", "language_level": ["good"]}, {"language": "mandarin", "language_level": ["good command", "good"]}]}, "experience_required": {"duration": ["10 years"], "field": ["accounting", "trading"]}}, {"job_id": "100003009054928", "location_code": "hk", "company": "Pure Search International Limited", "job_title": "Senior Accounting Manager / Accounting Manager", "description": "Our Client\nA renowned Multi-National Corporation (MNC) with an industry-leading portfolio of consumer brands. With innovative go-to market strategies and after sales services in their distributor business model, they are continuing their expansion plans across Asia Pacific (APAC) and Hong Kong.\u00a0 They are now seeking for a Senior Accounting Manager / Accounting Manager to join its Finance team in Hong Kong.\n\nJob Description\nReporting to the Financial Controller, you will be managing an outsourced accounting service provider, take ownership of reporting, full set of accounts, such as Account Receivable, Accounts Payables, General Ledger etc. You will ensure books are closed properly and prepare meaningful reports to senior management for decision making. You will manage cashflow and ensure cash position of the company is maintained at a good level. You will work closely with the team and advise them on any new accounting standards, its implications to the business and any compliance issues. You will also be involved in ad hoc projects when needed.\n\nJob Requirements\nYou should have at least 10 years Accounting & Finance experience gained in sizable Multi National Corporations (MNCs). Prior experience working in Big 4 CPA firm or 2nd Tier CPA firm is a must. You should have strong communication and influencing skills, and be able to manage a sizeable team. Comfortable to day to day English Communication & Presentation is a must. Proficiency in English and Chinese is essential. Can-do Attitude is highly preferred.\n\n", "employment_types": ["Full Time"], "selling_points": ["HK$55,000 - 68,000 per month", "Renowned Consumer Business", "MNC culture"], "locations": ["Not Specified"], "categories": ["Accounting", "Chief Accountant", "Finance / Accounting Manager", "Financial Controller"], "post_time": "2022-01-17T14:11:21Z", "salary": {"currency": null, "max": null, "min": null, "period": "monthly", "term": null}, "salary_visible": false, "title_keywords": ["accounting manager"], "responsibilities": ["reporting", "general ledger", "full set of accounts", "compliance", "reports", "ad hoc projects", "accounting service", "senior management"], "requirements": {"degrees": [], "majors": [], "languages": ["english", "chinese"], "language_level": ["proficiency"], "hard_skills": ["cpa"], "soft_skills": ["communication", "presentation", "can-do attitude"], "languages_combined": [{"language": "english", "language_level": ["proficiency"]}, {"language": "chinese", "language_level": ["proficiency"]}]}, "experience_required": {"duration": ["at least 10 years"], "field": ["finance", "accounting", "cpa firm", "big 4"]}}, {"job_id": "100003009051141", "location_code": "hk", "company": "", "job_title": "**URGENT Bank / Finance Experience** - Managerial Position (Special Promotion Packages)", "description": "Manulife (International) Ltd\n\n\n\nRe: **URGENT Bank / Finance Experience** - Managerial Position (Special Promotion Packages)\n\nTo cope with our expansion, we are urgently looking for a high calibre candidate who can work independently and\u00a0confidently.\n\nCandidate with\u00a0bank/finance experience\u00a0would be an advantage.\u00a0 We will offer\u00a0\u00a0SPECIAL PROMOTION PACKAGES.\n\nIf you are\u00a0caring about your future career development, and would like to\u00a0catch up your existing status and income level, this is a good opportunity for you to start with.\u00a0\n\n\nOur Benefits and packages:\n\nMonthly income up to $25000 to $60000 including bonus\nAdditional management overrides after promotion\nInitial training and On-Job training provided\nSPECIAL PROMOTION TRAINING PROGRAM to Team Manager in just 6 months\nExcellent Career Path to Management Ladder\nFirst Year income around $300,000 to $700,000\nLife and Medical Insurance\nBank holidays and Pension scheme\nLow mortgage interest rate\nFlexible working hours\nWork-Life Balance\n\nRequirements:\n\nDegree holder preferred\n3 years working experience or above\nNo need on finance experience, but supervisory or management experience is an advantage\nHKID card holder is a MUST\nFluent Cantonese and English\nImmediate past income not less than $150,000\nMature, responsible, and strong desire for success\nNo bankruptcy\n\nJob Functions:\n\nProvide professional financial planning to individual clients for wealth management, medical and life insurance,\nretirement scheme, investment, etc\nProvide benefits to corporate clients such as MPF, Group Medical, Business Insurance, etc\nTeam building for your career management development\nProvide training and coaching to team-members\n\nInterested candidates please send C.V. via \"APPLY NOW\"\u00a0\n\nOr send to Recruiting Manager: polly_lm_chan @ manulife.com.hk\n\nOr call 69045196 Polly Chan to arrange interview.\n\n\nPersonal data collected will be used for recruitment purposes only.\n\nRemarks: The recruitment offer is subject to the terms & conditions as stipulated in the agreement to be signed.", "employment_types": ["Full Time", "Permanent"], "selling_points": [], "locations": ["Others"], "categories": ["Accounting", "Chief Accountant", "Admin & HR", "Personal / Executive Assistant", "Banking / Finance", "Private Banking"], "post_time": "2022-01-15T03:25:43Z", "salary": {"currency": "HKD", "max": 69999, "min": 25000, "period": "monthly", "term": null}, "salary_visible": true, "title_keywords": [], "responsibilities": ["career development"], "requirements": {"degrees": [], "majors": [], "languages": [], "language_level": [], "hard_skills": [], "soft_skills": ["work independently"], "languages_combined": []}, "experience_required": {"duration": [], "field": ["finance", "managerial"]}}, {"job_id": "100003009042563", "location_code": "hk", "company": "mReferral Corporation (HK) Ltd   \u7d93\u7d61\u96c6\u5718(\u9999\u6e2f)\u6709\u9650\u516c\u53f8", "job_title": "Senior Manager (Finance & HR)", "description": "Responsibilities:\n\nLead the Finance Department over financial control and accounting functions, including management accounts reporting, forecast & budgeting, tax compliance and company secretarial matters handling\nIdentify performance drivers for both revenue and expenses and highlight any business risks and opportunities\nSupport management in key strategic initiatives and business improvement projects\nLead and supervise the HR and Administration team\nOversee full spectrum of HR function, including manpower planning and budgeting, talent acquisition, compensations and benefits, performance management, learning and development, employee relations\nReview and ensure HR policies and procedures are in alignment with operation needs and in compliance with labour regulations\nMonitor all spectrum of administration support to office, including maintenance, clean procurement of office supplies and other administration related matters\n\nRequirement:\n\nDegree holder in Finance or Accounting, qualified CPA and Chartered Secretary\nAt least 10 years' experience in finance and accounting with minimum 3 years' in managerial capacity\nExcellent business acumen with good analytical skills\nProactive, meticulous and able to work independently\nExcellent communication and effective people management skills\n\nWe offer attractive compensation package & career prospects to the right candidates. Interested parties please send your full resume with\u00a0availability,\u00a0present & expected salary to HR Department by clicking \"Apply Now\".\n\nPersonal data collected will be used for recruitment purpose only.", "employment_types": ["Full Time", "Permanent"], "selling_points": ["Qualified CPA and Chartered Secretary", "Min 10 years experience in Finance and Account", "Min 3 years in managerial capacity"], "locations": ["Wan Chai"], "categories": ["Accounting", "Chief Accountant", "Finance / Accounting Manager", "Financial Controller"], "post_time": "2022-01-12T07:59:08Z", "salary": {"currency": null, "max": null, "min": null, "period": "monthly", "term": null}, "salary_visible": false, "title_keywords": ["senior manager", "hr"], "responsibilities": ["tax", "regulations", "control", "management", "maintenance", "office supplies", "budgeting", "hr", "compliance", "expenses", "review", "accounts reporting", "policies", "procedures", "monitor", "planning", "forecast", "administration"], "requirements": {"degrees": ["degree holder"], "majors": ["finance", "accounting"], "languages": [], "language_level": [], "hard_skills": ["cpa", "analytical skills", "acumen"], "soft_skills": ["meticulous", "work independently", "analytical skills", "communication", "business acumen", "proactive"], "languages_combined": []}, "experience_required": {"duration": ["at least 10 years", "minimum 3 years"], "field": ["finance", "accounting", "managerial"]}}, {"job_id": "100003009045837", "location_code": "hk", "company": "Wah Ming Hong Ltd", "job_title": "Senior Accountant", "description": "Job Responsibilities:\n\nPerform all general accounting duties and operations;\nPrepare financial report;\nPrepare consolidated accounting statements;\nPrepare monthly/quarterly management\u00a0report;\nAssist in any other ad-hoc assignments when necessary\u00a0\n\nRequirements:\n\nBachelor degree in accounting or other related area;\nAt least 6 years' relevant experience;\nExcellent communication and interpersonal skills;\nIndependent, initiative, detail-minded and well-organized;\nGood command of spoken and written English and Chinese, able to speak Mandarin\nInteract with external auditor and banks\nIMMEDIATELY AVAILABLE is highly preferred\n\n\u00a0Attractive remuneration package and fringe benefits will be given to the successful candidate.\u00a0 Please send your full resume with current and expected salary via email to hr-hk@enicar.com.\n\n***PLEASE DO NOT USE QUICK APPLY FUNCTION***\n\n(All personal data collected will be used for recruitment purpose only.)", "employment_types": ["Full Time"], "selling_points": ["Willing and capable of doing \"hands on\" work", "Min. 6 years' accounting experience in supervisory", "Must be very experienced in consolidating accounts"], "locations": ["Aberdeen"], "categories": ["Accounting", "Accountant", "Chief Accountant"], "post_time": "2022-01-13T08:52:35Z", "salary": {"currency": null, "max": null, "min": null, "period": "monthly", "term": null}, "salary_visible": false, "title_keywords": ["senior accountant"], "responsibilities": ["operations", "ad-hoc assignments", "general accounting duties", "financial report", "management report"], "requirements": {"degrees": ["degree", "bachelor"], "majors": ["accounting"], "languages": ["english", "chinese", "mandarin"], "language_level": ["good command"], "hard_skills": [], "soft_skills": ["detail-minded", "independent", "well-organized", "communication and interpersonal skills", "initiative"], "languages_combined": [{"language": "english", "language_level": ["good command"]}, {"language": "chinese", "language_level": ["good command"]}, {"language": "mandarin", "language_level": ["good command"]}]}, "experience_required": {"duration": ["at least 6 years"], "field": ["relevant experience"]}}, {"job_id": "100003009045325", "location_code": "hk", "company": "Omnicom Media Group", "job_title": "Billing Manager", "description": "Responsibilities\n\nOversee the billing and revenue (BNR) operations specific to the media industry\nEnsure all BNR transactions are recorded properly, accurately, timely and in compliance with SOX, client and group requirements\nReview monthly working capital analyses and BNR reports\nPrepare monthly media payment plans for cash flow forecasting\nCompile monthly and quarterly BNR forecasts and variance analyses\nPerform SOX testing on a quarterly basis\nAssist in producing client profitability and brand analyses\nParticipate in developing appropriate accounting and internal control systems\nLiaise with clients, vendors, auditors, internal departments and group companies\nHandle ad hoc assignments as required\n\nRequirements\u00a0\u00a0\n\nDiploma holder or above in Accountancy or related disciplines\nAt least 10 years accounting experience preferably in media industry with 5 years in supervisory role\nProactive with excellent interpersonal, organizational, communication, analytical and problem-solving skills\nIndependent, detail-oriented, self-motivated and hard working\nAble to work under pressure and meet tight deadlines\nGood command of English, Cantonese and Mandarin\nProficient in MS office with advanced Excel knowledge\nImmediately available\n\nWorking Location: Cyberport (\u6578\u78bc\u6e2f),\u00a0Hong Kong\n\nWe offer a 5-day work of week, group medical & life insurance coverage and free shuttle bus to the right candidate. Interested parties please send your application letter and resume with current and expected salary\u00a0to click\u00a0\"Apply Now\" button.\u00a0\u00a0\n\nAll information collected will be used for recruitment only and treated in strict confidence. We will retain the personal data of unsuccessful applicants for future recruitment purpose for a maximum period of 2 years.", "employment_types": ["Full Time", "Permanent"], "selling_points": ["Free Shuttle Bus & Free Breakfast", "Birthday, Family Day & Self-Love Day Leave", "5-Day Work Week"], "locations": ["Pok Fu Lam"], "categories": ["Accounting", "Chief Accountant", "Finance / Accounting Manager", "Others"], "post_time": "2022-01-13T07:37:35Z", "salary": {"currency": null, "max": null, "min": null, "period": "monthly", "term": null}, "salary_visible": false, "title_keywords": ["manager"], "responsibilities": ["liaise with clients", "operations", "review", "compliance", "developing", "transactions", "testing", "systems", "payment", "cash flow", "reports", "ad hoc assignments", "plans", "forecasting", "internal control"], "requirements": {"degrees": ["diploma holder"], "majors": ["related disciplines", "accountancy"], "languages": ["cantonese", "english", "mandarin"], "language_level": ["good command"], "hard_skills": ["problem-solving skills", "excel", "ms office"], "soft_skills": ["self-motivated", "meet tight deadlines", "independent", "advanced", "organizational", "hard working", "detail-oriented", "communication", "problem-solving skills", "proactive", "interpersonal", "work under pressure"], "languages_combined": [{"language": "cantonese", "language_level": ["good command"]}, {"language": "english", "language_level": ["good command"]}, {"language": "mandarin", "language_level": ["good command"]}]}, "experience_required": {"duration": ["at least 10 years", "5 years"], "field": ["accounting experience", "supervisory", "media"]}}, {"job_id": "100003009033679", "location_code": "hk", "company": "Luen Tai Group (China) Limited", "job_title": "Accounting Officer / Assistant Accountant", "description": "Responsibilites:\n-\u00a0Handle\u00a0full\u00a0set\u00a0of\u00a0accounts in HK\n-\u00a0Handle\u00a0AR\u00a0&\u00a0AP\u00a0invoices\u00a0&\u00a0settlement,\u00a0accounts\u00a0reconciliation\n-\u00a0Handle\u00a0bank\u00a0payments\u00a0and\u00a0receipts\u00a0including\u00a0L/C\n-\u00a0Prepare\u00a0timely\u00a0cash flow\u00a0statement to top management\n-\u00a0Maintain\u00a0up-to-date\u00a0data\u00a0in\u00a0accounting\u00a0system\u00a0and\u00a0filing\u00a0records\n-\u00a0Assist\u00a0in\u00a0preparing\u00a0month\u00a0end\u00a0closing\u00a0reports\u00a0and\u00a0annual\u00a0audit\n-\u00a0Handle\u00a0ad\u00a0hoc\u00a0projects\u00a0as\u00a0required\n-\u00a0Report\u00a0to\u00a0Accounting\u00a0Manager\n\n\n\nRequirements:\n- Diploma or above in Accounting\n- 3-5 years or above accounting experience\n- Membership of professional group is essential\n- PRC manufacturing experience would be an advantage\n- Proficiency in using MS office, knowledge of\u00a0 ERP system is a plus\n- Mature, responsible, detailed mind with ability to handle multiple tasks independently under pressure\n- Strong organization, good interpersonal and communication skills\n- Good command of both written and spoken in English, Cantonese and Mandarin\n- Immediate available or short notice is highly preferable\n\nWe offer the competitive remuneration to right candidates. Applicant with more experience or qualification will be considered as \"Assistant Accountant\"\n\nInterest parties please send us full resume & expected salary to us.\n\n\"Personal data collected will be used for recruitment purpose only.\"", "employment_types": ["Full Time"], "selling_points": [], "locations": ["Wong Tai Sin Area"], "categories": ["Accounting", "Accountant", "Accounting Clerk / Supervisor", "Chief Accountant"], "post_time": "2022-01-10T01:34:47Z", "salary": {"currency": null, "max": null, "min": null, "period": "monthly", "term": null}, "salary_visible": false, "title_keywords": ["assistant accountant", "accounting officer"], "responsibilities": ["ap", "management", "month end closing", "invoices", "ar", "receipts", "data", "annual audit", "full set of accounts", "cash flow", "maintain", "payments", "reports", "ad hoc projects", "report"], "requirements": {"degrees": ["diploma or above"], "majors": ["accounting"], "languages": ["cantonese", "english", "mandarin"], "language_level": ["good command"], "hard_skills": ["prc manufacturing", "erp system", "plus", "ms office"], "soft_skills": ["communication skills", "independently", "under pressure", "responsible", "mature", "handle multiple tasks", "detailed mind", "interpersonal"], "languages_combined": [{"language": "cantonese", "language_level": ["good command"]}, {"language": "english", "language_level": ["good command"]}, {"language": "mandarin", "language_level": ["good command"]}]}, "experience_required": {"duration": ["3-5 years"], "field": ["accounting experience", "manufacturing"]}}, {"job_id": "100003009048630", "location_code": "hk", "company": "Pathos Consultancy Limited", "job_title": "Finance Manager (Management Reporting), Banking", "description": "The Company\nOur client is hiring a Finance Manager under Management Reporting team.\u00a0\n\nThe Role\n\n\nReport to Head of Management Reporting team\nResponsible for budgeting, forecasting, cashflow and performance analysis such as working capital / P&L analysis, KPI analysis, etc.\nPerform ad hoc analysis and presentation for management business review\nSupport ad hoc projects\u00a0\n\nYour Profile\n\n\nBachelor\u2019s degree in accounting or Finance\nMinimum 5 years FP&A experience gained from sizeable companies\nProficient in preparing presentation and PowerPoint\nFluent Cantonese and English\u00a0\n\nApply Today\nTo apply online (Word attachment only), please click the 'Apply' button. Interested parties please apply with the most updated CV with expected salary and available date via JobsDB. Applicants who do not hear from us within 2 weeks may consider their applications unsuccessful.\u00a0\n\nAbout Pathos\nWe are Pathos Consultancy Limited, a boutique recruitment firm based in Hong Kong strategically placing our candidates across all levels in permanent, temporary and contract roles.\u00a0 We specialize in IT and finance roles for banking, financial services and listed MNC sectors.", "employment_types": ["Full Time", "Permanent"], "selling_points": ["Management Reporting", "Manager", "Presentation"], "locations": ["Central"], "categories": ["Accounting", "Chief Accountant", "Finance / Accounting Manager", "Financial Analyst"], "post_time": "2022-01-14T06:55:35Z", "salary": {"currency": null, "max": null, "min": null, "period": "monthly", "term": null}, "salary_visible": false, "title_keywords": ["finance manager"], "responsibilities": ["management", "ad hoc", "budgeting", "analysis", "review", "p&l", "ad hoc projects", "management reporting", "forecasting", "report"], "requirements": {"degrees": ["degree", "bachelor"], "majors": ["finance", "accounting"], "languages": ["cantonese", "english"], "language_level": ["fluent"], "hard_skills": ["analysis", "word", "powerpoint"], "soft_skills": ["presentation", "responsible"], "languages_combined": [{"language": "cantonese", "language_level": ["fluent"]}, {"language": "english", "language_level": ["fluent"]}]}, "experience_required": {"duration": ["minimum 5 years"], "field": []}}, {"job_id": "100003009047072", "location_code": "hk", "company": "Links International", "job_title": "Treasury Manager - FX & Hedging", "description": "Responsibilities:\n\nSupervise day-to-day treasury operation and cash management\nWorking closely with Finance team on project funding decisions and financial projections\nReview loan and funding documents\nManage foreign exchange and interest rate risk, and FX hedging across APAC\nPrepare and submit treasury reports for senior management review\nAdvise on tax issues regarding investments & M&A projects\nManage and liaise with banks for funding and investment decisions\nBeing a strong business partner with stakeholders across different regions\n\nRequirements:\n\nBachelor Degree in Accounting & Finance or related discipline\nAt least 5 years of experience in treasury, preferably in sizeable MNC and luxury retailer\nSolid experiences in Retail and FMCG related industries are highly preferred\nSmart, energetic person who is ambitious to strive for excellence\nExcellent command of both English and Cantonese\nExcellent communication and presentation\nDynamic personality with an analytical mindset", "employment_types": ["Full Time", "Permanent"], "selling_points": ["Guaranteed 13 months salary", "Work life balance", "Regional exposure"], "locations": ["Not Specified"], "categories": ["Accounting", "Chief Accountant", "Finance / Accounting Manager", "Treasurer"], "post_time": "2022-01-14T02:14:57Z", "salary": {"currency": "HKD", "max": 54999, "min": 45000, "period": "monthly", "term": null}, "salary_visible": true, "title_keywords": ["manager"], "responsibilities": ["tax", "management", "project funding", "review", "reports", "finance team", "liaise with", "senior management"], "requirements": {"degrees": ["degree", "bachelor"], "majors": ["finance", "accounting"], "languages": ["cantonese", "english"], "language_level": ["excellent"], "hard_skills": ["dynamic"], "soft_skills": ["communication", "energetic", "dynamic", "strive for excellence", "presentation"], "languages_combined": [{"language": "cantonese", "language_level": ["excellent"]}, {"language": "english", "language_level": ["excellent"]}]}, "experience_required": {"duration": ["at least 5 years"], "field": ["related", "retail", "fmcg"]}}, {"job_id": "100003009038924", "location_code": "hk", "company": "Perfect Medical Health Management Limited", "job_title": "Finance Manager (China Market)", "description": "Pursue a Career with Impact\n\nAt Perfect Medical, we dare to envision, and we strive for perfection.\n\nPerfect Medical is a leading Medical Beauty Group with over 100 treatment centers worldwide. With our passion for innovation and breakthroughs, our business\u2019 global footprint has been extending from Hong Kong Headquarter to China, Macau, Australia and Singapore with over 2,000 employees across regions.\n\nTo cope with the Company\u2019s rapid expansion, we are currently looking for high caliber and visionary candidates to join our team as Finance Manager\n\nResponsibilities:\n\nManaging internal and external financial reporting requirements including consolidation, compliance and controlling activities\nProvide corporate finance support to the head office team in Hong Kong as well as the retail operation teams in China, Singapore & Australia\nLeading cash and liquidity management and credit risk management;\nLeading forecasting and budgeting\nTo perform additional duties and other ad hoc assignments as requested\n\nRequirements:\n\nDegree holder in Accounting, Finance, Business Administration or related discipline, qualified accountant of HKICPA/ACCA\nAt least 5 years in an all-rounded accounting function, experience with financial reporting and accounting with 2 years\u2019 experience in managerial level\nPresentable, strong business acumen, good interpersonal and communications skills\nStrong analytical ability and forecasting skills with strong attention to detail\nExperience in retail, aesthetics or medical related industry is a plus\nProficient in both written and spoken English & Chinese", "employment_types": ["Full Time"], "selling_points": ["Fast-growing Healthcare & Wellness Company", "HK Listed Company with APAC exposure", "Excellent professional development & career path"], "locations": ["Mong Kok"], "categories": ["Accounting", "Chief Accountant", "Finance / Accounting Manager", "Financial Analyst"], "post_time": "2022-01-11T08:09:04Z", "salary": {"currency": null, "max": null, "min": null, "period": "monthly", "term": null}, "salary_visible": false, "title_keywords": ["finance manager"], "responsibilities": ["management", "budgeting", "additional duties", "compliance", "teams", "financial reporting", "ad hoc assignments", "forecasting"], "requirements": {"degrees": ["degree holder"], "majors": ["finance", "accounting", "business administration"], "languages": ["english", "chinese"], "language_level": ["proficient"], "hard_skills": ["acca", "plus", "acumen", "hkicpa"], "soft_skills": ["business acumen", "interpersonal", "attention to detail", "presentable"], "languages_combined": [{"language": "english", "language_level": ["proficient"]}, {"language": "chinese", "language_level": ["proficient"]}]}, "experience_required": {"duration": ["2 years", "at least 5 years"], "field": ["managerial", "financial", "related", "accounting", "retail", "medical"]}}, {"job_id": "100003009033887", "location_code": "hk", "company": "Regional Insurance Management (International) Ltd", "job_title": "Accounting Clerk / Assistant", "description": "Job Duties\n\nPerform daily accounting functions\nHandle accounts payable and receivable, and general ledger functions\nPrepare month-end closing\nProvide clerical and administrative support, such as data entry, filing and scanning\nPerform other ad-hoc assignments as required\n\nRequirements\n\nForm 5 / DSE or above with accounting knowledge\nMinimum 1-2 years\u2019 relevant working experience\nWell-versed in MS Office application\nWilling to learn and committed to work\nImmediate available is preferred\n\nInterested applicants please send your full resume stating your availability, present and expected salaries to HR Department by clicking \"Apply Now\".", "employment_types": ["Full Time", "Permanent"], "selling_points": ["Year-end bonus and performance bonus", "5-days work week, bank holidays", "development opportunities"], "locations": ["Ngau Tau Kok"], "categories": ["Accounting", "Accountant", "Accounting Clerk / Supervisor", "Chief Accountant"], "post_time": "2022-01-10T02:03:15Z", "salary": {"currency": null, "max": null, "min": null, "period": "monthly", "term": null}, "salary_visible": false, "title_keywords": ["accounting clerk", "assistant"], "responsibilities": ["scanning", "administrative support", "data entry", "general ledger", "ad-hoc assignments", "month-end closing", "daily accounting", "accounts payable"], "requirements": {"degrees": ["form 5", "dse"], "majors": ["accounting"], "languages": [], "language_level": [], "hard_skills": ["ms office"], "soft_skills": ["committed", "willing to learn"], "languages_combined": []}, "experience_required": {"duration": ["minimum 1-2 years"], "field": ["relevant working experience"]}}, {"job_id": "100003009048568", "location_code": "hk", "company": "ConnectedGroup Limited", "job_title": "Finance Manager (Consolidation)", "description": "Finance Manager (Consolidation)\n\nOur client is a highly reputable conglomerate with business operations across the globe. To facilitate their company growth, they are looking for a high-caliber finance manager to join their team.\n\nCPA qualification is a must\nConsolidation & financial reporting\nGlobal exposure\n\nResponsibilities:\n\nResponsible for group consolidation, financial reporting closing, audited finical statements, and tax computation\nPreparate accurate reporting and filing of regulatory required financial reports in compliance with IFRS\nResearch accounting issues, summarize pertinent material, identify the impact and initiate recommendations/actions based on account review findings\nCoordinate communication finance matters with local finance teams across the globe\nHandle ad-hoc tasks from senior management\n\nRequirements:\n\nBachelor's degree in Finance & Accounting or related disciplines with CPA qualification\n6 years of working experience with a minimum of 3 years accounting experience in HK listed companies with consolidation responsibilities\nSelf-motivated, independent, a problem-solver, and able to work independently\nExcellent communication and interpersonal skills\nExcellent PC knowledge (including Excel, Word) and experience in Oracle system is an advantage\nGood command of both spoken and written English, Mandarin, and Cantonese\n\nInterested parties, please send your CV to Ivy Yeung Ivy.Yeung@connectedgroup.com for more details. For other available opportunities, please visit www.connectedgroup.com.", "employment_types": ["Full Time", "Permanent"], "selling_points": ["CPA qualification is a must", "Consolidation & financial reporting", "Global exposure"], "locations": ["Not Specified"], "categories": ["Accounting", "Accounting Clerk / Supervisor", "Chief Accountant", "Finance / Accounting Manager"], "post_time": "2022-01-14T06:49:01Z", "salary": {"currency": "HKD", "max": 44999, "min": 35000, "period": "monthly", "term": null}, "salary_visible": true, "title_keywords": ["finance manager"], "responsibilities": ["reporting", "financial reports", "tax computation", "ad-hoc tasks", "compliance", "review", "teams", "coordinate", "communication", "financial reporting", "senior management"], "requirements": {"degrees": ["degree", "bachelor"], "majors": ["related disciplines", "finance", "accounting"], "languages": ["cantonese", "english", "mandarin"], "language_level": ["good command"], "hard_skills": ["excel", "oracle system", "word", "cpa", "pc knowledge"], "soft_skills": ["self-motivated", "communication and interpersonal skills", "independent", "work independently"], "languages_combined": [{"language": "cantonese", "language_level": ["good command"]}, {"language": "english", "language_level": ["good command"]}, {"language": "mandarin", "language_level": ["good command"]}]}, "experience_required": {"duration": ["6 years", "minimum of 3 years"], "field": ["accounting experience", "consolidation"]}}, {"job_id": "100003009035476", "location_code": "hk", "company": "Wai Chun Strategic Investment Limited", "job_title": "Financial Manager \u8ca1\u52d9\u7d93\u7406", "description": "Reporting to the Chairman and the Board,\u00a0the appointee will lead the group financial functions covering all lines of business in Hong Kong and PRC, and fulfill compliance and company secretary functions.\u00a0\n\nQualifications:\n\nUniversity degree in Accounting with HKICPA/ACCA or equivalent professional qualifications\nOver 8 years of solid experience in budgetary control, financial planning and business partnering plus not less than 3 years\u2019 experience serving as Accounting Manager or above.\nFinance management experience gained from listed companies and sizable multinational corporation preferred\nStrong in evaluating business processes, driving and implementing strategic changes\nSelf-driven, charismatic, confident and project management skills\nExcellent communication and presentation skills\n\nResponsibilities:\n\nCoverage all the accounting and financial management matters of China and Hong Kong business\nExperience in handling joint ventures\nManage the production of the monthly management accounts and report providing value-added analysis and operational performance;\nCash management and related matters;\nOversee all financial compliance matters and regulators in jurisdictions where the group operates;\nResponsible for financial planning, treasury management, investment evaluations, and strategic business planning\n\nLocation: Admiralty\u00a0\n\nWe offer an attractive remuneration package and excellent career prospects to the right candidate.\u00a0\u00a0Please send full resume (Chinese version is a must), current and expected salary, contact number\u00a0and the availability to our e-mail address by clicking \"Apply Now\" for interview.\n\nPersonal data collected will be used for recruitment purpose only.\n\n\u8077\u8cac:\n\n\u8ca0\u8cac\u6240\u6709\u4e2d\u570b\u5927\u9678\u548c\u9999\u6e2f\u696d\u52d9\u7684\u8ca1\u52d9\u7ba1\u7406\u4e8b\u9805\uff1b\n\u8655\u7406\u5408\u8cc7\u4f01\u696d\u7d93\u9a57\uff1b\n\u7ba1\u7406\u6bcf\u6708\u7d9c\u5408\u7ba1\u7406\u8cec\u76ee\u548c\u5831\u544a\uff0c\u63d0\u4f9b\u589e\u503c\u7684\u5206\u6790\u548c\u71df\u904b\u5831\u544a\n\u73fe\u91d1\u7ba1\u7406\u53ca\u76f8\u95dc\u4e8b\u5b9c\uff1b\n\u76e3\u7763\u6240\u6709\u8ca1\u52d9\u5408\u898f\u4e8b\u5b9c\u548c\u53f8\u6cd5\u7ba1\u8f44\u5340\u4e2d\u7684\u76e3\u7ba1\u6a5f\u69cb\uff1b\n\u8ca0\u8cac\u8ca1\u52d9\u898f\u5283\uff0c\u8cc7\u91d1\u7ba1\u7406\uff0c\u6295\u8cc7\u8a55\u4f30\u548c\u4f01\u696d\u6230\u7565\u898f\u5283\u3002\n\n\u8cc7\u683c:\n\n\u5927\u5b78\u5b78\u4f4d\uff0c\u4e3b\u4fee\u6703\u8a08 , \u9999\u6e2f\u6703\u8a08\u5e2b\u516c\u6703\u6216\u570b\u969b\u5c08\u696d\u6703\u8a08\u7d44\u7e54\u6216\u540c\u7b49\u5c08\u696d\uff1b\n8\u5e74\u6216\u4ee5\u4e0a\u9810\u7b97\u63a7\u5236\uff0c\u8ca1\u52d9\u898f\u5283\u548c\u696d\u52d9\u5408\u4f5c\u7d93\u9a57\uff0c\u4ee5\u53ca\u4e0d\u5c11\u65bc3\u5e74\u6703\u8a08\u7d93\u7406\u7d1a\u6216\u4ee5\u4e0a\u7d93\u9a57\uff1b\n\u64c1\u6709\u4e0a\u5e02\u516c\u53f8\u548c\u5927\u578b\u8de8\u570b\u516c\u53f8\u8ca1\u52d9\u7ba1\u7406\u7d93\u9a57\u8005\u512a\u5148\uff1b\n\u5584\u65bc\u8a55\u4f30\u696d\u52d9\u6d41\u7a0b\uff0c\u63a8\u52d5\u548c\u5be6\u65bd\u6230\u7565\u8b8a\u9769\uff1b\n\u4e3b\u52d5\uff0c\u6709\u9b44\u529b\uff0c\u81ea\u4fe1\u548c\u9805\u76ee\u7ba1\u7406\u6280\u80fd\uff1b\n\u826f\u597d\u7684\u6e9d\u901a\u548c\u8868\u9054\u80fd\u529b\u3002\n\n\u5de5\u4f5c\u5730\u9ede: \u91d1\u9418\n\n\n\u6211\u5011\u63d0\u4f9b\u4e86\u4e00\u500b\u53ef\u89c0\u7684\u85aa\u916c\u798f\u5229\u548c\u826f\u597d\u7684\u8077\u696d\u524d\u666f\u7d66\u5408\u9069\u7684\u4eba\u9078\u3002\u8acb\u5c07\u500b\u4eba\u7c21\u6b77(\u5fc5\u9808\u4e2d\u6587\u7c21\u6b77)\uff0c\u76ee\u524d\u53ca\u671f\u671b\u85aa\u91d1\uff0c\u806f\u7d61\u96fb\u8a71\u548c\u5230\u8077\u65e5\u671f\u96fb\u90f5\u7d66\u6211\u53f8\u3002\n\n\u6536\u96c6\u7684\u500b\u4eba\u8cc7\u8a0a\u5c07\u50c5\u7528\u65bc\u62db\u8058\u7528\u9014\u3002", "employment_types": ["Full Time", "Permanent"], "selling_points": ["Finance Manager", "Occasional travel to China is required", "Min 3 years\u2019 serving as Accounting Manager"], "locations": ["Admiralty"], "categories": ["Accounting", "Chief Accountant", "Financial Controller", "Management", "Top Executives (CEO, CFO, CTO, GM, MD etc.)"], "post_time": "2022-01-10T07:20:34Z", "salary": {"currency": null, "max": null, "min": null, "period": "monthly", "term": null}, "salary_visible": false, "title_keywords": ["financial manager"], "responsibilities": ["reporting", "control", "management", "analysis", "compliance", "communication", "project management", "report", "planning"], "requirements": {"degrees": ["university degree"], "majors": ["accounting"], "languages": [], "language_level": [], "hard_skills": ["acca", "plus", "professional qualifications", "analysis", "project management", "hkicpa"], "soft_skills": ["confident", "responsible", "project management skills", "communication", "presentation skills", "driven"], "languages_combined": []}, "experience_required": {"duration": ["3 years", "8 years"], "field": ["management", "financial", "finance", "business", "accounting", "planning"]}}, {"job_id": "100003009042618", "location_code": "hk", "company": "Hunter Base International Company", "job_title": "Senior Accountant (Tseung Kwan O) - Listed Company", "description": "Requirements :\n\n- Degree holder in Accounting, Finance or similar discipline\n\n- At least five years' relevant account experience in sizable company, Preferably from FMCG or\nRetail Industry and e-commerce\u00a0\n\n- Sound knowledge of up-to-date accounting standards and able to meet compliance requirements\n\n- Proficiency in Microsoft office applications\n\n- Flexible, hands-on, strong analytical, problem solving and communication skill\n\n- Proficient in written and spoken Mandarin, English and Chinese\n\n- Immediately available is needed\u00a0\n\n", "employment_types": ["Full Time", "Permanent"], "selling_points": [], "locations": ["Tseung Kwan O"], "categories": ["Accounting", "Accountant", "Chief Accountant", "Finance / Accounting Manager"], "post_time": "2022-01-12T08:11:47Z", "salary": {"currency": null, "max": null, "min": null, "period": "monthly", "term": null}, "salary_visible": false, "title_keywords": ["senior accountant"], "responsibilities": ["communication", "compliance"], "requirements": {"degrees": ["degree holder"], "majors": ["finance", "accounting"], "languages": ["english", "chinese", "mandarin"], "language_level": ["proficient"], "hard_skills": ["microsoft office", "problem solving", "e-commerce"], "soft_skills": ["flexible", "hands-on", "communication skill", "problem solving"], "languages_combined": [{"language": "english", "language_level": ["proficient"]}, {"language": "chinese", "language_level": ["proficient"]}, {"language": "mandarin", "language_level": ["proficient"]}]}, "experience_required": {"duration": ["at least five years"], "field": ["fmcg"]}}, {"job_id": "100003009037433", "location_code": "hk", "company": "Robert Half", "job_title": "Senior Finance Manager", "description": "The Company\n\nA fast-growing servicing company is now looking for a Senior Finance Manager to lead the Finance department and business strategies with Senior Management for Hong Kong business\n\n\n\nThe Role\n\nDirectly report to Head of Finance\nLead and drive financial reporting and P&L balance in Hong Kong and Southeast Asia\nImprove innovation of accurate in management reporting in using BI dashboards and Visualization tools\nLiaise closely with stakeholders across different departments with global teams\nTrack financial performance of the BUs by timely analysing financial data and operating results and report variance against budget/forecast to top management\nAs a Finance business partner to cross functional teams (sales, plant GMs, supply chain, product development, HR and so on) and top management on formulating long-term and short-term strategic plans\nHandle ad-hoc projects.\n\n\n\nYour Profile\n\nQualification CPA with minimum 10 years of relevant experience\nExperience in consumer goods/product-based industries with Professional Audit firm is a big plus\nStrong in hands on experience with Business partner insights\nStrong communication, presentation, and analytical skills. Fluent in English, Mandarin and Cantonese\nIMMEDIATELY AVILABLE IS HIGHLY PREFERRED\n\n\n\nApply Today\n\nTo apply online (Word attachment only), please click the 'Apply' button. Please note that only short-listed candidates will be contacted.", "employment_types": ["Full Time", "Permanent"], "selling_points": ["Global Business Footprints", "Business partnership", "Attractive Renumeration package"], "locations": ["Central & Western Area"], "categories": ["Accounting", "Chief Accountant", "Finance / Accounting Manager", "Financial Analyst"], "post_time": "2022-01-11T02:48:27Z", "salary": {"currency": null, "max": null, "min": null, "period": "monthly", "term": null}, "salary_visible": false, "title_keywords": ["senior finance manager"], "responsibilities": ["liaise", "management", "ad-hoc projects", "strategic plans", "visualization", "data", "hr", "budget", "teams", "audit", "p&l", "communication", "management reporting", "financial reporting", "forecast", "senior management", "report"], "requirements": {"degrees": [], "majors": [], "languages": ["cantonese", "english", "mandarin"], "language_level": ["fluent"], "hard_skills": ["plus", "bi", "word", "analytical skills", "cpa"], "soft_skills": ["timely", "analytical skills", "communication", "hands on", "accurate", "presentation"], "languages_combined": [{"language": "cantonese", "language_level": ["fluent"]}, {"language": "english", "language_level": ["fluent"]}, {"language": "mandarin", "language_level": ["fluent"]}]}, "experience_required": {"duration": ["minimum 10 years"], "field": ["relevant experience", "audit", "business partner"]}}, {"job_id": "100003009031617", "location_code": "hk", "company": "Fortune Quest Limited", "job_title": "Senior Accountant", "description": "Job Description\n\nResponsibilities:\n\nOversee daily accounting works (AR / AP / Bank Accounts / Cash Movements / Cash Flow / Inventory Report / Company Net Position)\nBe responsible for monthly internal consolidated financial reports and analysis, including actuals and forecast\nPrepare annual budget and quarterly forecast with analysis and breakdowns.\nHandle statutory audit and tax filing in HK.\nBe responsible for finance matters of head office and branch offices (monthly expenses, salaries, etc)\nImprove operation efficiency, including system development for consolidation & reporting, and internal control by reviewing current workflow & propose action plans\nLiaise with banks, company secretary, auditors and insurance agents on related matters\n\nRequirements:\n\nDegree in Accounting, Finance or related disciplines with professional qualifications in HKICPA/ACCA or equivalent\nAcquire the experience in external audit, preparing consolidation reports to head office,\u00a0statutory consolidation to external auditor and internal management reports.\nPreferably with\u00a03 years\u2019 experience from CPA firms and 2 years\u2019 experience from in-house accounting department in sizable companies.\nProficiency in MS office application (e.g. Excel, Power-points, Words) and computerized accounting system.\nProactive, meticulous and able to work independently, efficiently and under pressure in a demanding and fast pace environment\nAble to communicate and present effectively across all levels including senior management\nGood people management skills, strong teamwork spirit and able to coach and develop subordinates\nExcellent command of both written & spoken English and Cantonese\n5-day work week\n13 month pay\nPerformance Bonus", "employment_types": ["Full Time"], "selling_points": [], "locations": ["Tsim Sha Tsui"], "categories": ["Accounting", "Chief Accountant"], "post_time": "2022-01-07T09:38:19Z", "salary": {"currency": null, "max": null, "min": null, "period": "monthly", "term": null}, "salary_visible": false, "title_keywords": ["senior accountant"], "responsibilities": ["ap", "reporting", "financial reports", "ar", "inventory", "analysis", "budget", "audit", "tax filing", "expenses", "cash flow", "forecast", "plans", "liaise with", "daily accounting", "insurance", "internal control", "report"], "requirements": {"degrees": ["degree"], "majors": ["related disciplines", "finance", "accounting"], "languages": ["cantonese", "english"], "language_level": ["excellent"], "hard_skills": ["excel", "acca", "words", "professional qualifications", "sizable companies", "cpa", "management reports", "accounting system", "ms office", "hkicpa"], "soft_skills": ["meticulous", "work independently", "under pressure", "teamwork spirit", "proactive"], "languages_combined": [{"language": "cantonese", "language_level": ["excellent"]}, {"language": "english", "language_level": ["excellent"]}]}, "experience_required": {"duration": ["3 years", "2 years"], "field": ["consolidation", "accounting", "audit", "management"]}}, {"job_id": "100003009033617", "location_code": "hk", "company": "", "job_title": "Financial Controller", "description": "We are a market leader in Hong Kong, China and ASEAN road transportation services. With very aggressive business growth agenda in developing new product lines, the company has set up own office and facility network in different continents to serve at customer convenience.\n\n\nJob Responsibilities:\nBudgeting, forecasting and analysis for region, reviewing business strategy and finances\nMonitor daily accounting functions, reporting and working closely with the Regional Finance Function\nManagement of tax planning process, compliance, and transfer pricing\nSupport various internal stakeholders in matters relating to internal controls, tax, and project implementations\nAd hoc assignments and projects\nRequirements:\nACCA, Degree or above in Accounting, Finance, or related disciplines\nAt least 15 years in an all-rounded accounting function, experience with financial reporting and accounting\nPrevious experience working in an audit firm is a plus, team leading experience preferred\nQualified Accountant is required, excellent business acumen and able to work with overseas staff\nExposure to Logistics or FMCG industry preferred\nAble to be based in Hong Kong, with occasional travel to Asian\nFluency in English and Chinese (Cantonese & Mandarin)\nCandidate with less experience will be considered as Senior Finance Manager\nWe offer excellent career development and attractive remuneration package to the right candidate.\n\nInformation supplied will be treated in strict confidence and used in accordance with the Personal Data (Privacy) Ordinance. Applicants not invited for interview within 2 months may consider their applications unsuccessful.\n\nInterested individuals please call +852 2473 2828 for more information. Only suitable candidates will be contacted.\n", "employment_types": ["Full Time", "Permanent"], "selling_points": ["Budgeting, forecasting and analysis for region", "Qualified Accountant with 15ys exp. is required", "Support various internal stakeholders"], "locations": ["Tsuen Wan Area"], "categories": ["Accounting", "Chief Accountant", "Financial Analyst", "Financial Controller"], "post_time": "2022-01-10T01:22:17Z", "salary": {"currency": null, "max": null, "min": null, "period": "monthly", "term": null}, "salary_visible": false, "title_keywords": ["financial controller"], "responsibilities": ["tax", "reporting", "management", "budgeting", "analysis", "planning process", "monitor", "compliance", "ad hoc assignments", "daily accounting", "forecasting"], "requirements": {"degrees": ["degree or above"], "majors": ["related disciplines", "finance", "accounting"], "languages": ["cantonese", "english", "chinese", "mandarin"], "language_level": ["fluency"], "hard_skills": ["acca", "fmcg industry", "acumen", "plus"], "soft_skills": ["business acumen"], "languages_combined": [{"language": "cantonese", "language_level": []}, {"language": "english", "language_level": ["fluency"]}, {"language": "chinese", "language_level": ["fluency"]}, {"language": "mandarin", "language_level": []}]}, "experience_required": {"duration": ["at least 15 years"], "field": ["financial", "finance manager", "audit", "accounting", "team"]}}, {"job_id": "100003009037385", "location_code": "hk", "company": "Robert Half", "job_title": "FP&A Manager", "description": "The Company\n\nA leading specialist in Risk and Compliance resources company is now looking for a high-calibre Regional FP&A Manager to manage the business operations.\n\n\n\nThe Role\n\nDirectly report to CFO\nProvide group level analysis of budget & forecast on monthly basics\nLiaise with regional business managers to prepare yearly budgets\nPropose and steer business performance improvement of pricing optimization, cost saving, automation of tasks, etc.\nMonitoring of Accounting policy, Transfer pricing, Tax regulations to ensure best practices and procedures\nTrack financial performance of the BUs by timely analysing financial data and operating results and report variance against budget/forecast to top management\nAs a Finance business partner to cross functional teams (sales, plant GMs, supply chain, product development, HR and so on) and top management on formulating long-term and short-term strategic plans\nLiaise with regional business managers to prepare yearly budgets\nHandle ad-hoc projects.\n\n\n\nYour Profile\n\nQualification CPA or CFA with minimum 5 years of relevant FP&A experience\nExperience in Supply Chain/ Logistics or Sourcing industry with Professional Audit firm is a big plus\nStrong in Business Partnering and Analysis\nStrong communication, presentation, and analytical skills. Fluent in English, Mandarin and Cantonese\nIMMEDIATELY AVILABLE IS HIGHLY PREFERRED\n\n\n\nApply Today\n\nTo apply online (Word attachment only), please click the 'Apply' button. Please note that only short-listed candidates will be contacted.", "employment_types": ["Full Time", "Permanent"], "selling_points": ["Global scope", "Business partnership", "Attractive Renumeration package"], "locations": ["Central & Western Area"], "categories": ["Accounting", "Chief Accountant", "Finance / Accounting Manager", "Financial Analyst"], "post_time": "2022-01-11T02:40:26Z", "salary": {"currency": null, "max": null, "min": null, "period": "monthly", "term": null}, "salary_visible": false, "title_keywords": ["manager"], "responsibilities": ["regulations", "data", "operations", "budget", "audit", "communication", "liaise with", "ad-hoc projects", "compliance", "teams", "logistics", "forecast", "report", "cost", "management", "monitoring", "procedures", "tax", "budgets", "strategic plans", "analysis", "hr"], "requirements": {"degrees": [], "majors": [], "languages": ["cantonese", "english", "mandarin"], "language_level": ["fluent"], "hard_skills": ["plus", "cfa", "analysis", "word", "analytical skills", "cpa"], "soft_skills": ["communication", "timely", "presentation", "analytical skills"], "languages_combined": [{"language": "cantonese", "language_level": ["fluent"]}, {"language": "english", "language_level": ["fluent"]}, {"language": "mandarin", "language_level": ["fluent"]}]}, "experience_required": {"duration": ["minimum 5 years"], "field": ["cfa", "logistics", "supply chain", "audit"]}}, {"job_id": "100003009039081", "location_code": "hk", "company": "AOSource Company Limited", "job_title": "Manager/Senior Manager (General Accounting, Retail )  [ Ref# ACC-vh-111-JDB ]", "description": "Our client is a well established living product store in Greater China.\u00a0\u00a0 They are looking for a potential candidate to their Finance team.\n\nJob Responsibilities :\n\nReported to Head of Finance and lead a team of General Accounting\nResponsible to prepare financial statements for the CS Group companies in Hong Kong with reference to a set of accounting policies and procedures\nAdvising line managers in the process of developing policies or procedures for their business operations ensuring compliance with the accounting policies and guidelines\nWork with IT for system and equipment development and testing in new store opening projects\nProvide financial advise on the tenant and consignment contract renewal application for management decision making\nLead and provide continuous coaching to a team of staff in carrying out the accounting operations and reporting\nTransfer pricing and review intercompany transaction flows\n\nJob Requirements :\n\nDegree holder in Finance & Accounting or equivalent\nQualified Accountant with 7 years relevant experiences in which at least 5 years in supervisory level in retail / F&B business\nHands on SAP experience\nPresentable, strong business acumen, leadership, interpersonal and communication skills\nGood command of both spoken and written English & Mandarin\nAnalytical, detail-minded, result-oriented , able to meet tight deadline\n\n\u00a0Our client will offer competitive remuneration package and good career prospects to the potential candidate, interested parties please quote the ref. no.\u00a0ACC-vh-111-JDB\u00a0and submit your resume to\u00a0Ms. Vida Hung\u00a0by our email address.\n\nAll profiles are handled with strictest confidentiality. Shortlisted candidates would be notified", "employment_types": ["Full Time"], "selling_points": ["Famous living product retail in Greater China", "Lead Fin team & coaching, fin advice, SAP exp", "Qualified Acct, gd benefits & wkg environment"], "locations": ["Not Specified"], "categories": ["Accounting", "Chief Accountant", "Finance / Accounting Manager", "Financial Controller"], "post_time": "2022-01-11T08:38:19Z", "salary": {"currency": null, "max": null, "min": null, "period": "monthly", "term": null}, "salary_visible": false, "title_keywords": ["senior manager", "manager", "accounting"], "responsibilities": ["reporting", "management", "guidelines", "policies", "operations", "compliance", "procedures", "developing", "financial statements", "testing", "review", "lead a team", "accounting policies"], "requirements": {"degrees": ["degree holder"], "majors": ["finance", "accounting"], "languages": ["english", "mandarin"], "language_level": ["good command"], "hard_skills": ["sap", "acumen"], "soft_skills": ["detail-minded", "communication skills", "result-oriented", "presentable", "hands on", "meet tight deadline", "business acumen", "leadership", "interpersonal"], "languages_combined": [{"language": "english", "language_level": ["good command"]}, {"language": "mandarin", "language_level": ["good command"]}]}, "experience_required": {"duration": ["7 years", "at least 5 years"], "field": ["business", "supervisory level", "f&b", "retail"]}}, {"job_id": "100003009054674", "location_code": "hk", "company": "Moore Associates Limited", "job_title": "MNC in Hong Kong \u2013 Assistant Finance Manager/ Finance Manager", "description": "The company is a well-established lifestyle brand in Europe and now looking to grow and expand in Asia with the right candidate in the Asia Office.\n\nJob Responsibilities\n\nReport to the Head of the regional office for Asia to oversee and manage the finance and accounting function of the region (Station in Hong Kong)\nResponsible for daily accounting operation including treasury, A/P, A/R, costing, GL, invoicing, bank reconciliations\nPrepare regular reporting package such as monthly full-set accounting, financial reporting, management reporting, cashflow statements, group reporting, segment report, using the in-house finance module ERP system\nWork with and report to the GM directly on annual budget and forecast\nIdentify accounting and financial issues, communicate potential impact and recommendations to the GM.\nLiaise with external firm to handle annual audit, tax filing and assist in reviewing finance and accounting work\nReview internal controls and improve overall efficiency of finance functions\nFollow up with customers on overdue payment status\nAd-hoc jobs related to accounting\n\nSuccessful Applicant\n\nUniversity graduate, preferably in finance and accounting, with professional accounting qualification\nAt least 5 years of relevant experience in handling full sets of accounting, budget and forecast, analyst, financial reporting, group reporting with commercial experience\nExperience in retail / fashion wholesale industry is advantageous, but not a must\nProficiency in MS applications, such as Word, Excel and PowerPoint with hands-on experience in finance module ERP system is an advantage\nA good team player who is pro-active and able to work independently\nStrong analytical, communication and interpersonal skills\nExcellent command of English, Cantonese and Mandarin\n\nWe offer a 5-day working week, a competitive remuneration package and generous fringe benefits.\u00a0\n\nInterested candidates please send the full resume with current and expected salary\u00a0by clicking the \"Apply Now\" button\n\nFor more information, please visit our website www.carhartt-wip.com.", "employment_types": ["Full Time", "Permanent"], "selling_points": ["Lifestyle brand in Europe", "Manage the finance and accounting function", "Prepare regular reporting package"], "locations": ["Tsim Sha Tsui"], "categories": ["Accounting", "Accountant", "Chief Accountant", "Others"], "post_time": "2022-01-17T10:30:32Z", "salary": {"currency": null, "max": null, "min": null, "period": "monthly", "term": null}, "salary_visible": false, "title_keywords": ["assistant finance manager", "finance manager"], "responsibilities": ["ad-hoc", "reporting", "annual audit", "budget", "tax filing", "bank reconciliations", "review", "invoicing", "communication", "payment", "financial reporting", "management reporting", "forecast", "liaise with", "daily accounting", "report"], "requirements": {"degrees": ["university graduate"], "majors": ["finance", "accounting"], "languages": ["cantonese", "english", "mandarin"], "language_level": ["excellent"], "hard_skills": ["excel", "ms applications", "word", "powerpoint", "erp system", "gm", "r"], "soft_skills": ["good team player", "work independently", "responsible", "hands-on", "communication and interpersonal skills", "pro-active"], "languages_combined": [{"language": "cantonese", "language_level": ["excellent"]}, {"language": "english", "language_level": ["excellent"]}, {"language": "mandarin", "language_level": ["excellent"]}]}, "experience_required": {"duration": ["at least 5 years"], "field": ["finance", "commercial", "erp system", "relevant experience", "accounting", "retail", "financial"]}}, {"job_id": "100003009051881", "location_code": "hk", "company": "Luen Tai Group (China) Limited", "job_title": "Accounting Officer / Assistant Accountant", "description": "Responsibilites:\n-\u00a0Handle\u00a0full\u00a0set\u00a0of\u00a0accounts in HK\n-\u00a0Handle\u00a0AR\u00a0&\u00a0AP\u00a0invoices\u00a0&\u00a0settlement,\u00a0accounts\u00a0reconciliation\n-\u00a0Handle\u00a0bank\u00a0payments\u00a0and\u00a0receipts\u00a0including\u00a0L/C\n-\u00a0Prepare\u00a0timely\u00a0cash flow\u00a0statement to top management\n-\u00a0Maintain\u00a0up-to-date\u00a0data\u00a0in\u00a0accounting\u00a0system\u00a0and\u00a0filing\u00a0records\n-\u00a0Assist\u00a0in\u00a0preparing\u00a0month\u00a0end\u00a0closing\u00a0reports\u00a0and\u00a0annual\u00a0audit\n-\u00a0Handle\u00a0ad\u00a0hoc\u00a0projects\u00a0as\u00a0required\n-\u00a0Report\u00a0to\u00a0Accounting\u00a0Manager\n\n\n\nRequirements:\n- Diploma or above in Accounting\n- 3-5 years or above accounting experience\n- Membership of professional group is essential\n- PRC manufacturing experience would be an advantage\n- Proficiency in using MS office, knowledge of\u00a0 ERP system is a plus\n- Mature, responsible, detailed mind with ability to handle multiple tasks independently under pressure\n- Strong organization, good interpersonal and communication skills\n- Good command of both written and spoken in English, Cantonese and Mandarin\n- Immediate available or short notice is highly preferable\n\nWe offer the competitive remuneration to right candidates. Applicant with more experience or qualification will be considered as \"Assistant Accountant\"\n\nInterest parties please send us full resume & expected salary to us.\n\n\"Personal data collected will be used for recruitment purpose only.\"", "employment_types": ["Full Time"], "selling_points": [], "locations": ["Wong Tai Sin Area"], "categories": ["Accounting", "Accountant", "Accounting Clerk / Supervisor", "Chief Accountant"], "post_time": "2022-01-17T01:26:15Z", "salary": {"currency": null, "max": null, "min": null, "period": "monthly", "term": null}, "salary_visible": false, "title_keywords": ["assistant accountant", "accounting officer"], "responsibilities": ["ap", "management", "month end closing", "invoices", "ar", "receipts", "data", "annual audit", "full set of accounts", "cash flow", "maintain", "payments", "reports", "ad hoc projects", "report"], "requirements": {"degrees": ["diploma or above"], "majors": ["accounting"], "languages": ["cantonese", "english", "mandarin"], "language_level": ["good command"], "hard_skills": ["prc manufacturing", "erp system", "plus", "ms office"], "soft_skills": ["communication skills", "independently", "under pressure", "responsible", "mature", "handle multiple tasks", "detailed mind", "interpersonal"], "languages_combined": [{"language": "cantonese", "language_level": ["good command"]}, {"language": "english", "language_level": ["good command"]}, {"language": "mandarin", "language_level": ["good command"]}]}, "experience_required": {"duration": ["3-5 years"], "field": ["accounting experience", "manufacturing"]}}, {"job_id": "100003009044675", "location_code": "hk", "company": "Aaron Shum Jewelry Limited", "job_title": "Chief Accountant", "description": "Qualified Accountant and Bachelor\u2019s Degree major in Accounting / Finance.\nAt least 10 years experiences, strong in financial reporting, regulatory reporting, cost accounting, cash flow management and familiar with taxation of both HK and the PRC.\nExperience in Manufacturing industries is required and knowledge in Jewelry field is an advantage.\nResponsible for full set of accounts including consolidation, financial management reporting, preparing account analysis and accounts reconciliation and month end closing.\nExperience in financial audits, budgeting and forecasting.\nCoordinate audit related activities and liaise with auditors during the auditing process.\nSupport as needed with input and reconciliation in group portfolio management accounting software.\nMonitoring the preparation and submission of financial and management reports, and handling ad-hoc assignments as required.\nReview and monitor accounting and taxation related issues.", "employment_types": ["Full Time", "Permanent"], "selling_points": ["Accounting", "Qualified Accountant", "Finance"], "locations": ["Hung Hom"], "categories": ["Accounting", "Accountant", "Chief Accountant", "Financial Controller"], "post_time": "2022-01-13T05:19:07Z", "salary": {"currency": null, "max": null, "min": null, "period": "monthly", "term": null}, "salary_visible": false, "title_keywords": ["accountant"], "responsibilities": ["software", "budgeting", "audit", "liaise with", "month end closing", "full set of accounts", "monitor", "forecasting", "reporting", "cost", "management", "monitoring", "review", "cash flow", "management reporting", "audits", "taxation", "ad-hoc assignments", "analysis", "coordinate", "management reports", "financial reporting", "auditing"], "requirements": {"degrees": ["degree", "bachelor"], "majors": ["finance", "accounting"], "languages": [], "language_level": [], "hard_skills": ["accounting software", "analysis", "management reports"], "soft_skills": ["responsible"], "languages_combined": []}, "experience_required": {"duration": ["at least 10 years"], "field": ["management", "accounting", "manufacturing", "financial"]}}, {"job_id": "100003009052545", "location_code": "hk", "company": "AOSource Company Limited", "job_title": "Finance Manager    (FM-0117-sh-JDB)", "description": "Our client is a Listed group,\u00a0 Current they are looking for potential candidate to join their Finance team in Hong Kong.\n\nResponsibilities;\n\nReport to Head of Finance (General Account & Finance Analysis);\nTo\u00a0Lead a small team of Finance Operation Team in Hong Kong;\n\nHandle full set of account including operaton /finance analysis/ management account etc;\nTo perform and lead the accounting process and procedure, ensuring compliance with the accounting policies and guidelines;\nLead and coaching to a small team to manage accounting reporting & reporting;\nGood communcation with English and Chinese is must.\nRequirements:\n\nDegree or Above in Accounting or related discipline;\n\nHolder of CPA professional qualification and experience in 4A CPA Firm is a plus;\nAbout 8+\u00a0 years working experience in Full set of accounting and Management Accounting;\nExperience in Multi-national group is preferred;\nSolid Experience in Asia Pacific Trading Business is preferred;\nGood experience in dealing with various country business user;\nUsing software with MS Office (Execl, Word, Powerpoint) and Oracle Finance is a plus;\nExcellent spoken and written communication skill in English;\nWork independently and good team leadership.\nOur client will offer competitive remuneration package and good career prospects to the potential candidate, interested parties please quote ref.no.FM-0117-sh-JDB and submit your resume to Ms Fung by our email or enquiry with Tel:3428-6121.\n\n\nAll profiles are handled with strictest confidentiality. Shortlisted candidates would be notified", "employment_types": ["Full Time", "Permanent"], "selling_points": ["MNC Group/ Asia Pacific Trading", "CPA /Full set of Account/ Lead a small team", "Exp. in Trading/ Fin operation/ Mgmt acct"], "locations": ["Not Specified"], "categories": ["Accounting", "Chief Accountant", "Finance / Accounting Manager", "Financial Analyst"], "post_time": "2022-01-17T03:22:52Z", "salary": {"currency": null, "max": null, "min": null, "period": "monthly", "term": null}, "salary_visible": false, "title_keywords": ["finance manager"], "responsibilities": ["reporting", "management", "guidelines", "analysis", "compliance", "lead a small team", "accounting policies", "report"], "requirements": {"degrees": ["degree or above"], "majors": ["accounting"], "languages": ["english"], "language_level": ["excellent"], "hard_skills": ["plus", "oracle", "word", "powerpoint", "cpa", "ms office"], "soft_skills": ["work independently", "communication skill", "leadership"], "languages_combined": [{"language": "english", "language_level": ["excellent"]}]}, "experience_required": {"duration": [], "field": ["management accounting", "cpa firm", "business", "accounting", "trading"]}}, {"job_id": "100003009050021", "location_code": "hk", "company": "Shun Tak Property Management Limited", "job_title": "Accounting Manager", "description": "Job Duties:\n\nTo supervise a team for managing all daily operations of accounting function in Hong Kong and Macau\nTo perform timely and accurate financial reporting\nTo ensure and review the compliance of the group financial policies and procedures\nTo review and enhance workflows for better and efficient financial operation and reporting\nTo support in ad hoc financial evaluation supporting for business planning / development projects\n\nRequirements:\n\nDegree holder in Accounting and processed Accountancy qualifications\nMember of HKICPA / ACCA or equivalent\nMinimum 8 years\u2019 working experiences, exposure in the industry of property management is an advantage\nMature, detail orientated, excellent time management and interpersonal skills\nBusiness acumen with logical presentations in report writing\nTravel occasionally to Macau\n\n\u00a0We will offer attractive compensation package to the right candidate. Please send application enclosing resume stating career and salary history, expected salary and date of availability to The HR Dept, Rooms 908-11, 9/F, West Tower, Shun Tak Centre, 200 Connaught Road Central, Hong Kong by email to pm_hr(at)shuntakgroup.com\u00a0 (in Word format).\u00a0\u00a0Please quote the reference of the position you apply for in all correspondences.\n\nThe information supplied by the applicants will be used in accordance with the Personal Data (Privacy) Policy of Shun Tak Group (a copy of which will be provided upon request). Only shortlisted candidates will be notified. www.shuntakgroup.com", "employment_types": ["Full Time", "Permanent"], "selling_points": ["Accountancy qualifications", "Member of HKICPA/ACCA or equivalent", "Min 8 years relevant working experience"], "locations": ["Sheung Wan"], "categories": ["Accounting", "Chief Accountant", "Finance / Accounting Manager", "Others", "Others"], "post_time": "2022-01-14T09:38:51Z", "salary": {"currency": null, "max": null, "min": null, "period": "monthly", "term": null}, "salary_visible": false, "title_keywords": ["accounting manager"], "responsibilities": ["reporting", "ad hoc", "financial policies", "compliance", "review", "procedures", "daily operations", "financial reporting", "evaluation", "planning"], "requirements": {"degrees": ["degree holder"], "majors": ["accounting", "accountancy"], "languages": [], "language_level": [], "hard_skills": ["acca", "word", "presentations", "hkicpa", "acumen"], "soft_skills": ["mature", "interpersonal skills", "detail orientated", "business acumen", "time management"], "languages_combined": []}, "experience_required": {"duration": ["minimum 8 years"], "field": ["management"]}}, {"job_id": "100003009040095", "location_code": "hk", "company": "", "job_title": "Accountant / Assistant Accountant", "description": "Job Requirements:\n\nDiploma or Degree Holder in Accounting or related discipline\nAt least 2-4 years relevant working experience\nSolid working experience in handling full set of accounts\nProficient in MS Word and Excel\nResponsible and self-motivated\nDetail-minded and independent\nGood communication skills\nPositive and meticulous\nMore experience will be considered as Accountant\n\n5-day work.\u00a0 An attractive package will be offered to the right candidate.\u00a0 Interested parties please\u00a0send resume to Hz Job Consultant Ltd. by email to job@hzjob.com\n\n(All personal data collected will be treated in strict confidence and used for recruitment purpose only)", "employment_types": ["Full Time", "Permanent"], "selling_points": [], "locations": ["Not Specified"], "categories": ["Accounting", "Accountant", "Accounting Clerk / Supervisor", "Chief Accountant"], "post_time": "2022-01-12T01:22:31Z", "salary": {"currency": null, "max": null, "min": null, "period": "monthly", "term": null}, "salary_visible": false, "title_keywords": ["accountant", "assistant accountant"], "responsibilities": ["communication", "full set of accounts"], "requirements": {"degrees": ["diploma", "degree holder"], "majors": ["accounting"], "languages": [], "language_level": [], "hard_skills": ["excel", "ms word"], "soft_skills": ["detail-minded", "communication skills", "self-motivated", "meticulous", "independent", "responsible", "positive"], "languages_combined": []}, "experience_required": {"duration": ["at least 2-4 years"], "field": ["relevant working experience"]}}, {"job_id": "100003009047593", "location_code": "hk", "company": "Hong Huan Group Limited", "job_title": "Financial Controller", "description": "Responsibilities\n\nDevelop and oversee the finance & accounting functions in collaboration with Business Units and head office\nProviding accounting and financial insights to improve operational efficiency\nReporting to CFO, involve in strategic planning with top management related with all accounting and finance functions\nDevise the finance related policies complying to all applicable laws and regulations for the group\nOffer financial advice to management in corporate finance exercises such as M&A, investments etc.\nOn-going review of portfolio companies financial planning, reporting, forecast and budgeting activities\nEnsure timely and accurate preparation and submission of monthly financial and management reports for management review and for group consolidation and reporting purpose\nProvide business advice for process improvement, taxation and corporate governance\n\nRequirements\nQualified accountant with a degree or above in Accounting or Finance or related discipline\nMinimum of 15 years working experience includes proven track record at a senior management level\nAbility to consult and advise operating and corporate leaders on issues related to accounting, financial reporting, internal control and regulatory issues\nStrong leadership skills with high level of self-motivation and initiative\nProven analytical, organizational and problem-solving skills\nStrong interpersonal and communication skills, both verbal and written in English, Cantonese and Mandarin\nSuperior organizational skills and the ability to prioritize in a dynamic working environment\nPossess good communication, interpersonal and stakeholder management skills\nDemonstrate strong business acumen\nInterested parties please send full resume with current and expected salary by clicking the \"APPLY NOW\" button below.\nAll information provided by applicants will be treated in strict confidence and used only for recruitment purposes. Applicants may be considered for other suitable positions by our Company & the subsidiaries over not more than 6 months, after which their personal data will be destroyed.", "employment_types": ["Full Time", "Permanent"], "selling_points": [], "locations": ["Ngau Tau Kok"], "categories": ["Accounting", "Chief Accountant", "Financial Analyst", "Financial Controller"], "post_time": "2022-01-14T03:32:00Z", "salary": {"currency": null, "max": null, "min": null, "period": "monthly", "term": null}, "salary_visible": false, "title_keywords": ["financial controller"], "responsibilities": ["regulations", "reporting", "management", "taxation", "strategic planning", "policies", "budgeting", "review", "develop", "management reports", "forecast", "management review", "planning"], "requirements": {"degrees": ["degree or above"], "majors": ["finance", "accounting"], "languages": ["cantonese", "english", "mandarin"], "language_level": [], "hard_skills": ["problem-solving skills", "dynamic", "acumen", "internal control"], "soft_skills": ["communication skills", "organizational skills", "organizational", "leadership skills", "prioritize", "communication", "self-motivation", "dynamic", "business acumen", "problem-solving skills", "interpersonal", "initiative", "superior"], "languages_combined": [{"language": "cantonese", "language_level": []}, {"language": "english", "language_level": []}, {"language": "mandarin", "language_level": []}]}, "experience_required": {"duration": ["minimum of 15 years"], "field": ["management"]}}, {"job_id": "100003009054928", "location_code": "hk", "company": "Pure Search International Limited", "job_title": "Senior Accounting Manager / Accounting Manager", "description": "Our Client\nA renowned Multi-National Corporation (MNC) with an industry-leading portfolio of consumer brands. With innovative go-to market strategies and after sales services in their distributor business model, they are continuing their expansion plans across Asia Pacific (APAC) and Hong Kong.\u00a0 They are now seeking for a Senior Accounting Manager / Accounting Manager to join its Finance team in Hong Kong.\n\nJob Description\nReporting to the Financial Controller, you will be managing an outsourced accounting service provider, take ownership of reporting, full set of accounts, such as Account Receivable, Accounts Payables, General Ledger etc. You will ensure books are closed properly and prepare meaningful reports to senior management for decision making. You will manage cashflow and ensure cash position of the company is maintained at a good level. You will work closely with the team and advise them on any new accounting standards, its implications to the business and any compliance issues. You will also be involved in ad hoc projects when needed.\n\nJob Requirements\nYou should have at least 10 years Accounting & Finance experience gained in sizable Multi National Corporations (MNCs). Prior experience working in Big 4 CPA firm or 2nd Tier CPA firm is a must. You should have strong communication and influencing skills, and be able to manage a sizeable team. Comfortable to day to day English Communication & Presentation is a must. Proficiency in English and Chinese is essential. Can-do Attitude is highly preferred.\n\n", "employment_types": ["Full Time"], "selling_points": ["HK$55,000 - 68,000 per month", "Renowned Consumer Business", "MNC culture"], "locations": ["Not Specified"], "categories": ["Accounting", "Chief Accountant", "Finance / Accounting Manager", "Financial Controller"], "post_time": "2022-01-17T14:11:21Z", "salary": {"currency": null, "max": null, "min": null, "period": "monthly", "term": null}, "salary_visible": false, "title_keywords": ["accounting manager"], "responsibilities": ["reporting", "general ledger", "full set of accounts", "compliance", "reports", "ad hoc projects", "accounting service", "senior management"], "requirements": {"degrees": [], "majors": [], "languages": ["english", "chinese"], "language_level": ["proficiency"], "hard_skills": ["cpa"], "soft_skills": ["communication", "presentation", "can-do attitude"], "languages_combined": [{"language": "english", "language_level": ["proficiency"]}, {"language": "chinese", "language_level": ["proficiency"]}]}, "experience_required": {"duration": ["at least 10 years"], "field": ["finance", "accounting", "cpa firm", "big 4"]}}, {"job_id": "100003009040817", "location_code": "hk", "company": "Moore Associates Limited", "job_title": "MNC in Hong Kong \u2013 Assistant Finance Manager/ Finance Manager", "description": "The company is a well-established lifestyle brand in Europe and now looking to grow and expand in Asia with the right candidate in the Asia Office.\n\nJob Responsibilities\n\nReport to the Head of the regional office for Asia to oversee and manage the finance and accounting function of the region (Station in Hong Kong)\nResponsible for daily accounting operation including treasury, A/P, A/R, costing, GL, invoicing, bank reconciliations\nPrepare regular reporting package such as monthly full-set accounting, financial reporting, management reporting, cashflow statements, group reporting, segment report, using the in-house finance module ERP system\nWork with and report to the GM directly on annual budget and forecast\nIdentify accounting and financial issues, communicate potential impact and recommendations to the GM.\nLiaise with external firm to handle annual audit, tax filing and assist in reviewing finance and accounting work\nReview internal controls and improve overall efficiency of finance functions\nFollow up with customers on overdue payment status\nAd-hoc jobs related to accounting\n\nSuccessful Applicant\n\nUniversity graduate, preferably in finance and accounting, with professional accounting qualification\nAt least 5 years of relevant experience in handling full sets of accounting, budget and forecast, analyst, financial reporting, group reporting with commercial experience\nExperience in retail / fashion wholesale industry is advantageous, but not a must\nProficiency in MS applications, such as Word, Excel and PowerPoint with hands-on experience in finance module ERP system is an advantage\nA good team player who is pro-active and able to work independently\nStrong analytical, communication and interpersonal skills\nExcellent command of English, Cantonese and Mandarin\n\nWe offer a 5-day working week, a competitive remuneration package and generous fringe benefits.\u00a0\n\nInterested candidates please send the full resume with current and expected salary\u00a0by clicking the \"Apply Now\" button\n\nFor more information, please visit our website www.carhartt-wip.com.", "employment_types": ["Full Time", "Permanent"], "selling_points": ["Lifestyle brand in Europe", "Manage the finance and accounting function", "Prepare regular reporting package"], "locations": ["Tsim Sha Tsui"], "categories": ["Accounting", "Accountant", "Chief Accountant", "Others"], "post_time": "2022-01-12T03:06:41Z", "salary": {"currency": null, "max": null, "min": null, "period": "monthly", "term": null}, "salary_visible": false, "title_keywords": ["assistant finance manager", "finance manager"], "responsibilities": ["ad-hoc", "reporting", "annual audit", "budget", "tax filing", "bank reconciliations", "review", "invoicing", "communication", "payment", "financial reporting", "management reporting", "forecast", "liaise with", "daily accounting", "report"], "requirements": {"degrees": ["university graduate"], "majors": ["finance", "accounting"], "languages": ["cantonese", "english", "mandarin"], "language_level": ["excellent"], "hard_skills": ["excel", "ms applications", "word", "powerpoint", "erp system", "gm", "r"], "soft_skills": ["good team player", "work independently", "responsible", "hands-on", "communication and interpersonal skills", "pro-active"], "languages_combined": [{"language": "cantonese", "language_level": ["excellent"]}, {"language": "english", "language_level": ["excellent"]}, {"language": "mandarin", "language_level": ["excellent"]}]}, "experience_required": {"duration": ["at least 5 years"], "field": ["finance", "commercial", "erp system", "relevant experience", "accounting", "retail", "financial"]}}, {"job_id": "100003009051141", "location_code": "hk", "company": "", "job_title": "**URGENT Bank / Finance Experience** - Managerial Position (Special Promotion Packages)", "description": "Manulife (International) Ltd\n\n\n\nRe: **URGENT Bank / Finance Experience** - Managerial Position (Special Promotion Packages)\n\nTo cope with our expansion, we are urgently looking for a high calibre candidate who can work independently and\u00a0confidently.\n\nCandidate with\u00a0bank/finance experience\u00a0would be an advantage.\u00a0 We will offer\u00a0\u00a0SPECIAL PROMOTION PACKAGES.\n\nIf you are\u00a0caring about your future career development, and would like to\u00a0catch up your existing status and income level, this is a good opportunity for you to start with.\u00a0\n\n\nOur Benefits and packages:\n\nMonthly income up to $25000 to $60000 including bonus\nAdditional management overrides after promotion\nInitial training and On-Job training provided\nSPECIAL PROMOTION TRAINING PROGRAM to Team Manager in just 6 months\nExcellent Career Path to Management Ladder\nFirst Year income around $300,000 to $700,000\nLife and Medical Insurance\nBank holidays and Pension scheme\nLow mortgage interest rate\nFlexible working hours\nWork-Life Balance\n\nRequirements:\n\nDegree holder preferred\n3 years working experience or above\nNo need on finance experience, but supervisory or management experience is an advantage\nHKID card holder is a MUST\nFluent Cantonese and English\nImmediate past income not less than $150,000\nMature, responsible, and strong desire for success\nNo bankruptcy\n\nJob Functions:\n\nProvide professional financial planning to individual clients for wealth management, medical and life insurance,\nretirement scheme, investment, etc\nProvide benefits to corporate clients such as MPF, Group Medical, Business Insurance, etc\nTeam building for your career management development\nProvide training and coaching to team-members\n\nInterested candidates please send C.V. via \"APPLY NOW\"\u00a0\n\nOr send to Recruiting Manager: polly_lm_chan @ manulife.com.hk\n\nOr call 69045196 Polly Chan to arrange interview.\n\n\nPersonal data collected will be used for recruitment purposes only.\n\nRemarks: The recruitment offer is subject to the terms & conditions as stipulated in the agreement to be signed.", "employment_types": ["Full Time", "Permanent"], "selling_points": [], "locations": ["Others"], "categories": ["Accounting", "Chief Accountant", "Admin & HR", "Personal / Executive Assistant", "Banking / Finance", "Private Banking"], "post_time": "2022-01-15T03:25:43Z", "salary": {"currency": "HKD", "max": 69999, "min": 25000, "period": "monthly", "term": null}, "salary_visible": true, "title_keywords": [], "responsibilities": ["career development"], "requirements": {"degrees": [], "majors": [], "languages": [], "language_level": [], "hard_skills": [], "soft_skills": ["work independently"], "languages_combined": []}, "experience_required": {"duration": [], "field": ["finance", "managerial"]}}, {"job_id": "100003009042563", "location_code": "hk", "company": "mReferral Corporation (HK) Ltd   \u7d93\u7d61\u96c6\u5718(\u9999\u6e2f)\u6709\u9650\u516c\u53f8", "job_title": "Senior Manager (Finance & HR)", "description": "Responsibilities:\n\nLead the Finance Department over financial control and accounting functions, including management accounts reporting, forecast & budgeting, tax compliance and company secretarial matters handling\nIdentify performance drivers for both revenue and expenses and highlight any business risks and opportunities\nSupport management in key strategic initiatives and business improvement projects\nLead and supervise the HR and Administration team\nOversee full spectrum of HR function, including manpower planning and budgeting, talent acquisition, compensations and benefits, performance management, learning and development, employee relations\nReview and ensure HR policies and procedures are in alignment with operation needs and in compliance with labour regulations\nMonitor all spectrum of administration support to office, including maintenance, clean procurement of office supplies and other administration related matters\n\nRequirement:\n\nDegree holder in Finance or Accounting, qualified CPA and Chartered Secretary\nAt least 10 years' experience in finance and accounting with minimum 3 years' in managerial capacity\nExcellent business acumen with good analytical skills\nProactive, meticulous and able to work independently\nExcellent communication and effective people management skills\n\nWe offer attractive compensation package & career prospects to the right candidates. Interested parties please send your full resume with\u00a0availability,\u00a0present & expected salary to HR Department by clicking \"Apply Now\".\n\nPersonal data collected will be used for recruitment purpose only.", "employment_types": ["Full Time", "Permanent"], "selling_points": ["Qualified CPA and Chartered Secretary", "Min 10 years experience in Finance and Account", "Min 3 years in managerial capacity"], "locations": ["Wan Chai"], "categories": ["Accounting", "Chief Accountant", "Finance / Accounting Manager", "Financial Controller"], "post_time": "2022-01-12T07:59:08Z", "salary": {"currency": null, "max": null, "min": null, "period": "monthly", "term": null}, "salary_visible": false, "title_keywords": ["senior manager", "hr"], "responsibilities": ["tax", "regulations", "control", "management", "maintenance", "office supplies", "budgeting", "hr", "compliance", "expenses", "review", "accounts reporting", "policies", "procedures", "monitor", "planning", "forecast", "administration"], "requirements": {"degrees": ["degree holder"], "majors": ["finance", "accounting"], "languages": [], "language_level": [], "hard_skills": ["cpa", "analytical skills", "acumen"], "soft_skills": ["meticulous", "work independently", "analytical skills", "communication", "business acumen", "proactive"], "languages_combined": []}, "experience_required": {"duration": ["at least 10 years", "minimum 3 years"], "field": ["finance", "accounting", "managerial"]}}, {"job_id": "100003009045837", "location_code": "hk", "company": "Wah Ming Hong Ltd", "job_title": "Senior Accountant", "description": "Job Responsibilities:\n\nPerform all general accounting duties and operations;\nPrepare financial report;\nPrepare consolidated accounting statements;\nPrepare monthly/quarterly management\u00a0report;\nAssist in any other ad-hoc assignments when necessary\u00a0\n\nRequirements:\n\nBachelor degree in accounting or other related area;\nAt least 6 years' relevant experience;\nExcellent communication and interpersonal skills;\nIndependent, initiative, detail-minded and well-organized;\nGood command of spoken and written English and Chinese, able to speak Mandarin\nInteract with external auditor and banks\nIMMEDIATELY AVAILABLE is highly preferred\n\n\u00a0Attractive remuneration package and fringe benefits will be given to the successful candidate.\u00a0 Please send your full resume with current and expected salary via email to hr-hk@enicar.com.\n\n***PLEASE DO NOT USE QUICK APPLY FUNCTION***\n\n(All personal data collected will be used for recruitment purpose only.)", "employment_types": ["Full Time"], "selling_points": ["Willing and capable of doing \"hands on\" work", "Min. 6 years' accounting experience in supervisory", "Must be very experienced in consolidating accounts"], "locations": ["Aberdeen"], "categories": ["Accounting", "Accountant", "Chief Accountant"], "post_time": "2022-01-13T08:52:35Z", "salary": {"currency": null, "max": null, "min": null, "period": "monthly", "term": null}, "salary_visible": false, "title_keywords": ["senior accountant"], "responsibilities": ["operations", "ad-hoc assignments", "general accounting duties", "financial report", "management report"], "requirements": {"degrees": ["degree", "bachelor"], "majors": ["accounting"], "languages": ["english", "chinese", "mandarin"], "language_level": ["good command"], "hard_skills": [], "soft_skills": ["detail-minded", "independent", "well-organized", "communication and interpersonal skills", "initiative"], "languages_combined": [{"language": "english", "language_level": ["good command"]}, {"language": "chinese", "language_level": ["good command"]}, {"language": "mandarin", "language_level": ["good command"]}]}, "experience_required": {"duration": ["at least 6 years"], "field": ["relevant experience"]}}, {"job_id": "100003009045325", "location_code": "hk", "company": "Omnicom Media Group", "job_title": "Billing Manager", "description": "Responsibilities\n\nOversee the billing and revenue (BNR) operations specific to the media industry\nEnsure all BNR transactions are recorded properly, accurately, timely and in compliance with SOX, client and group requirements\nReview monthly working capital analyses and BNR reports\nPrepare monthly media payment plans for cash flow forecasting\nCompile monthly and quarterly BNR forecasts and variance analyses\nPerform SOX testing on a quarterly basis\nAssist in producing client profitability and brand analyses\nParticipate in developing appropriate accounting and internal control systems\nLiaise with clients, vendors, auditors, internal departments and group companies\nHandle ad hoc assignments as required\n\nRequirements\u00a0\u00a0\n\nDiploma holder or above in Accountancy or related disciplines\nAt least 10 years accounting experience preferably in media industry with 5 years in supervisory role\nProactive with excellent interpersonal, organizational, communication, analytical and problem-solving skills\nIndependent, detail-oriented, self-motivated and hard working\nAble to work under pressure and meet tight deadlines\nGood command of English, Cantonese and Mandarin\nProficient in MS office with advanced Excel knowledge\nImmediately available\n\nWorking Location: Cyberport (\u6578\u78bc\u6e2f),\u00a0Hong Kong\n\nWe offer a 5-day work of week, group medical & life insurance coverage and free shuttle bus to the right candidate. Interested parties please send your application letter and resume with current and expected salary\u00a0to click\u00a0\"Apply Now\" button.\u00a0\u00a0\n\nAll information collected will be used for recruitment only and treated in strict confidence. We will retain the personal data of unsuccessful applicants for future recruitment purpose for a maximum period of 2 years.", "employment_types": ["Full Time", "Permanent"], "selling_points": ["Free Shuttle Bus & Free Breakfast", "Birthday, Family Day & Self-Love Day Leave", "5-Day Work Week"], "locations": ["Pok Fu Lam"], "categories": ["Accounting", "Chief Accountant", "Finance / Accounting Manager", "Others"], "post_time": "2022-01-13T07:37:35Z", "salary": {"currency": null, "max": null, "min": null, "period": "monthly", "term": null}, "salary_visible": false, "title_keywords": ["manager"], "responsibilities": ["liaise with clients", "operations", "review", "compliance", "developing", "transactions", "testing", "systems", "payment", "cash flow", "reports", "ad hoc assignments", "plans", "forecasting", "internal control"], "requirements": {"degrees": ["diploma holder"], "majors": ["related disciplines", "accountancy"], "languages": ["cantonese", "english", "mandarin"], "language_level": ["good command"], "hard_skills": ["problem-solving skills", "excel", "ms office"], "soft_skills": ["self-motivated", "meet tight deadlines", "independent", "advanced", "organizational", "hard working", "detail-oriented", "communication", "problem-solving skills", "proactive", "interpersonal", "work under pressure"], "languages_combined": [{"language": "cantonese", "language_level": ["good command"]}, {"language": "english", "language_level": ["good command"]}, {"language": "mandarin", "language_level": ["good command"]}]}, "experience_required": {"duration": ["at least 10 years", "5 years"], "field": ["accounting experience", "supervisory", "media"]}}, {"job_id": "100003009033679", "location_code": "hk", "company": "Luen Tai Group (China) Limited", "job_title": "Accounting Officer / Assistant Accountant", "description": "Responsibilites:\n-\u00a0Handle\u00a0full\u00a0set\u00a0of\u00a0accounts in HK\n-\u00a0Handle\u00a0AR\u00a0&\u00a0AP\u00a0invoices\u00a0&\u00a0settlement,\u00a0accounts\u00a0reconciliation\n-\u00a0Handle\u00a0bank\u00a0payments\u00a0and\u00a0receipts\u00a0including\u00a0L/C\n-\u00a0Prepare\u00a0timely\u00a0cash flow\u00a0statement to top management\n-\u00a0Maintain\u00a0up-to-date\u00a0data\u00a0in\u00a0accounting\u00a0system\u00a0and\u00a0filing\u00a0records\n-\u00a0Assist\u00a0in\u00a0preparing\u00a0month\u00a0end\u00a0closing\u00a0reports\u00a0and\u00a0annual\u00a0audit\n-\u00a0Handle\u00a0ad\u00a0hoc\u00a0projects\u00a0as\u00a0required\n-\u00a0Report\u00a0to\u00a0Accounting\u00a0Manager\n\n\n\nRequirements:\n- Diploma or above in Accounting\n- 3-5 years or above accounting experience\n- Membership of professional group is essential\n- PRC manufacturing experience would be an advantage\n- Proficiency in using MS office, knowledge of\u00a0 ERP system is a plus\n- Mature, responsible, detailed mind with ability to handle multiple tasks independently under pressure\n- Strong organization, good interpersonal and communication skills\n- Good command of both written and spoken in English, Cantonese and Mandarin\n- Immediate available or short notice is highly preferable\n\nWe offer the competitive remuneration to right candidates. Applicant with more experience or qualification will be considered as \"Assistant Accountant\"\n\nInterest parties please send us full resume & expected salary to us.\n\n\"Personal data collected will be used for recruitment purpose only.\"", "employment_types": ["Full Time"], "selling_points": [], "locations": ["Wong Tai Sin Area"], "categories": ["Accounting", "Accountant", "Accounting Clerk / Supervisor", "Chief Accountant"], "post_time": "2022-01-10T01:34:47Z", "salary": {"currency": null, "max": null, "min": null, "period": "monthly", "term": null}, "salary_visible": false, "title_keywords": ["assistant accountant", "accounting officer"], "responsibilities": ["ap", "management", "month end closing", "invoices", "ar", "receipts", "data", "annual audit", "full set of accounts", "cash flow", "maintain", "payments", "reports", "ad hoc projects", "report"], "requirements": {"degrees": ["diploma or above"], "majors": ["accounting"], "languages": ["cantonese", "english", "mandarin"], "language_level": ["good command"], "hard_skills": ["prc manufacturing", "erp system", "plus", "ms office"], "soft_skills": ["communication skills", "independently", "under pressure", "responsible", "mature", "handle multiple tasks", "detailed mind", "interpersonal"], "languages_combined": [{"language": "cantonese", "language_level": ["good command"]}, {"language": "english", "language_level": ["good command"]}, {"language": "mandarin", "language_level": ["good command"]}]}, "experience_required": {"duration": ["3-5 years"], "field": ["accounting experience", "manufacturing"]}}, {"job_id": "100003009048630", "location_code": "hk", "company": "Pathos Consultancy Limited", "job_title": "Finance Manager (Management Reporting), Banking", "description": "The Company\nOur client is hiring a Finance Manager under Management Reporting team.\u00a0\n\nThe Role\n\n\nReport to Head of Management Reporting team\nResponsible for budgeting, forecasting, cashflow and performance analysis such as working capital / P&L analysis, KPI analysis, etc.\nPerform ad hoc analysis and presentation for management business review\nSupport ad hoc projects\u00a0\n\nYour Profile\n\n\nBachelor\u2019s degree in accounting or Finance\nMinimum 5 years FP&A experience gained from sizeable companies\nProficient in preparing presentation and PowerPoint\nFluent Cantonese and English\u00a0\n\nApply Today\nTo apply online (Word attachment only), please click the 'Apply' button. Interested parties please apply with the most updated CV with expected salary and available date via JobsDB. Applicants who do not hear from us within 2 weeks may consider their applications unsuccessful.\u00a0\n\nAbout Pathos\nWe are Pathos Consultancy Limited, a boutique recruitment firm based in Hong Kong strategically placing our candidates across all levels in permanent, temporary and contract roles.\u00a0 We specialize in IT and finance roles for banking, financial services and listed MNC sectors.", "employment_types": ["Full Time", "Permanent"], "selling_points": ["Management Reporting", "Manager", "Presentation"], "locations": ["Central"], "categories": ["Accounting", "Chief Accountant", "Finance / Accounting Manager", "Financial Analyst"], "post_time": "2022-01-14T06:55:35Z", "salary": {"currency": null, "max": null, "min": null, "period": "monthly", "term": null}, "salary_visible": false, "title_keywords": ["finance manager"], "responsibilities": ["management", "ad hoc", "budgeting", "analysis", "review", "p&l", "ad hoc projects", "management reporting", "forecasting", "report"], "requirements": {"degrees": ["degree", "bachelor"], "majors": ["finance", "accounting"], "languages": ["cantonese", "english"], "language_level": ["fluent"], "hard_skills": ["analysis", "word", "powerpoint"], "soft_skills": ["presentation", "responsible"], "languages_combined": [{"language": "cantonese", "language_level": ["fluent"]}, {"language": "english", "language_level": ["fluent"]}]}, "experience_required": {"duration": ["minimum 5 years"], "field": []}}, {"job_id": "100003009047072", "location_code": "hk", "company": "Links International", "job_title": "Treasury Manager - FX & Hedging", "description": "Responsibilities:\n\nSupervise day-to-day treasury operation and cash management\nWorking closely with Finance team on project funding decisions and financial projections\nReview loan and funding documents\nManage foreign exchange and interest rate risk, and FX hedging across APAC\nPrepare and submit treasury reports for senior management review\nAdvise on tax issues regarding investments & M&A projects\nManage and liaise with banks for funding and investment decisions\nBeing a strong business partner with stakeholders across different regions\n\nRequirements:\n\nBachelor Degree in Accounting & Finance or related discipline\nAt least 5 years of experience in treasury, preferably in sizeable MNC and luxury retailer\nSolid experiences in Retail and FMCG related industries are highly preferred\nSmart, energetic person who is ambitious to strive for excellence\nExcellent command of both English and Cantonese\nExcellent communication and presentation\nDynamic personality with an analytical mindset", "employment_types": ["Full Time", "Permanent"], "selling_points": ["Guaranteed 13 months salary", "Work life balance", "Regional exposure"], "locations": ["Not Specified"], "categories": ["Accounting", "Chief Accountant", "Finance / Accounting Manager", "Treasurer"], "post_time": "2022-01-14T02:14:57Z", "salary": {"currency": "HKD", "max": 54999, "min": 45000, "period": "monthly", "term": null}, "salary_visible": true, "title_keywords": ["manager"], "responsibilities": ["tax", "management", "project funding", "review", "reports", "finance team", "liaise with", "senior management"], "requirements": {"degrees": ["degree", "bachelor"], "majors": ["finance", "accounting"], "languages": ["cantonese", "english"], "language_level": ["excellent"], "hard_skills": ["dynamic"], "soft_skills": ["communication", "energetic", "dynamic", "strive for excellence", "presentation"], "languages_combined": [{"language": "cantonese", "language_level": ["excellent"]}, {"language": "english", "language_level": ["excellent"]}]}, "experience_required": {"duration": ["at least 5 years"], "field": ["related", "retail", "fmcg"]}}, {"job_id": "100003009038924", "location_code": "hk", "company": "Perfect Medical Health Management Limited", "job_title": "Finance Manager (China Market)", "description": "Pursue a Career with Impact\n\nAt Perfect Medical, we dare to envision, and we strive for perfection.\n\nPerfect Medical is a leading Medical Beauty Group with over 100 treatment centers worldwide. With our passion for innovation and breakthroughs, our business\u2019 global footprint has been extending from Hong Kong Headquarter to China, Macau, Australia and Singapore with over 2,000 employees across regions.\n\nTo cope with the Company\u2019s rapid expansion, we are currently looking for high caliber and visionary candidates to join our team as Finance Manager\n\nResponsibilities:\n\nManaging internal and external financial reporting requirements including consolidation, compliance and controlling activities\nProvide corporate finance support to the head office team in Hong Kong as well as the retail operation teams in China, Singapore & Australia\nLeading cash and liquidity management and credit risk management;\nLeading forecasting and budgeting\nTo perform additional duties and other ad hoc assignments as requested\n\nRequirements:\n\nDegree holder in Accounting, Finance, Business Administration or related discipline, qualified accountant of HKICPA/ACCA\nAt least 5 years in an all-rounded accounting function, experience with financial reporting and accounting with 2 years\u2019 experience in managerial level\nPresentable, strong business acumen, good interpersonal and communications skills\nStrong analytical ability and forecasting skills with strong attention to detail\nExperience in retail, aesthetics or medical related industry is a plus\nProficient in both written and spoken English & Chinese", "employment_types": ["Full Time"], "selling_points": ["Fast-growing Healthcare & Wellness Company", "HK Listed Company with APAC exposure", "Excellent professional development & career path"], "locations": ["Mong Kok"], "categories": ["Accounting", "Chief Accountant", "Finance / Accounting Manager", "Financial Analyst"], "post_time": "2022-01-11T08:09:04Z", "salary": {"currency": null, "max": null, "min": null, "period": "monthly", "term": null}, "salary_visible": false, "title_keywords": ["finance manager"], "responsibilities": ["management", "budgeting", "additional duties", "compliance", "teams", "financial reporting", "ad hoc assignments", "forecasting"], "requirements": {"degrees": ["degree holder"], "majors": ["finance", "accounting", "business administration"], "languages": ["english", "chinese"], "language_level": ["proficient"], "hard_skills": ["acca", "plus", "acumen", "hkicpa"], "soft_skills": ["business acumen", "interpersonal", "attention to detail", "presentable"], "languages_combined": [{"language": "english", "language_level": ["proficient"]}, {"language": "chinese", "language_level": ["proficient"]}]}, "experience_required": {"duration": ["2 years", "at least 5 years"], "field": ["managerial", "financial", "related", "accounting", "retail", "medical"]}}, {"job_id": "100003009044280", "location_code": "hk", "company": "Robert Half", "job_title": "Assistant Manager/ Manager, IFRS 17 - Welcome Big 4", "description": "The Company\n\nOur client is well-established insurance company, urgently looking for a IFRS 17 Assistant Manager on a renewable contract basis to join their Hong Kong office.\n\nThe role:\n\nSupport the IFRS 17 implementation project\nCreate quarterly financial reporting in IFRS 17\nHandle financial closing reporting processes under IFRS 17\nPerform reconciliation in IFRS 17 environment against current accounting basis\nCoordinate with other departments in the preparation and review of quarterly and annual financials, forecasts, and budget\nConduct User Acceptance Test (UAT) on IFRS 17\nDevelop reporting tools automation for process improvement\n\nCandidate profile:\n\nDegree holder in accounting / finance or equivalent\nMinimum 4 years of relevant auditing or accounting experience\nBig 4 candidates from commercial and finance Service sector is welcomed to apply\nFamiliar with IFRS, experience in insurance is a plus\nStrong problem solving and analytical skill\nProficient in the use of MS Excel\nCandidate with less experiences will be considered as Senior Accountant\nGood command in Chinese and English\n\nIf this sounds like you, APPLY TODAY!\n\nApply Today\n\nTo apply online (Word attachment only), please click the 'Apply' button. Please note that only short-listed candidates will be contacted.", "employment_types": ["Full Time", "Contract"], "selling_points": ["IFRS 17 implementation", "Contract highly renewable and convert to permanent", "Big 4 candidates are welcomed to apply"], "locations": ["Central & Western Area"], "categories": ["Accounting", "Accountant", "Chief Accountant", "Finance / Accounting Manager"], "post_time": "2022-01-13T03:39:48Z", "salary": {"currency": null, "max": null, "min": null, "period": "monthly", "term": null}, "salary_visible": false, "title_keywords": ["assistant manager", "manager"], "responsibilities": ["reporting", "uat", "review", "coordinate with", "implementation", "budget", "develop", "financial reporting", "insurance", "auditing"], "requirements": {"degrees": ["degree holder"], "majors": ["finance", "accounting"], "languages": ["english", "chinese"], "language_level": ["good command"], "hard_skills": ["ifrs", "analytical skill", "plus", "word", "problem solving", "ms excel"], "soft_skills": ["problem solving and analytical skill"], "languages_combined": [{"language": "english", "language_level": ["good command"]}, {"language": "chinese", "language_level": ["good command"]}]}, "experience_required": {"duration": ["minimum 4 years"], "field": ["accounting experience", "insurance", "senior accountant"]}}, {"job_id": "100003009033887", "location_code": "hk", "company": "Regional Insurance Management (International) Ltd", "job_title": "Accounting Clerk / Assistant", "description": "Job Duties\n\nPerform daily accounting functions\nHandle accounts payable and receivable, and general ledger functions\nPrepare month-end closing\nProvide clerical and administrative support, such as data entry, filing and scanning\nPerform other ad-hoc assignments as required\n\nRequirements\n\nForm 5 / DSE or above with accounting knowledge\nMinimum 1-2 years\u2019 relevant working experience\nWell-versed in MS Office application\nWilling to learn and committed to work\nImmediate available is preferred\n\nInterested applicants please send your full resume stating your availability, present and expected salaries to HR Department by clicking \"Apply Now\".", "employment_types": ["Full Time", "Permanent"], "selling_points": ["Year-end bonus and performance bonus", "5-days work week, bank holidays", "development opportunities"], "locations": ["Ngau Tau Kok"], "categories": ["Accounting", "Accountant", "Accounting Clerk / Supervisor", "Chief Accountant"], "post_time": "2022-01-10T02:03:15Z", "salary": {"currency": null, "max": null, "min": null, "period": "monthly", "term": null}, "salary_visible": false, "title_keywords": ["accounting clerk", "assistant"], "responsibilities": ["scanning", "administrative support", "data entry", "general ledger", "ad-hoc assignments", "month-end closing", "daily accounting", "accounts payable"], "requirements": {"degrees": ["form 5", "dse"], "majors": ["accounting"], "languages": [], "language_level": [], "hard_skills": ["ms office"], "soft_skills": ["committed", "willing to learn"], "languages_combined": []}, "experience_required": {"duration": ["minimum 1-2 years"], "field": ["relevant working experience"]}}, {"job_id": "100003009048568", "location_code": "hk", "company": "ConnectedGroup Limited", "job_title": "Finance Manager (Consolidation)", "description": "Finance Manager (Consolidation)\n\nOur client is a highly reputable conglomerate with business operations across the globe. To facilitate their company growth, they are looking for a high-caliber finance manager to join their team.\n\nCPA qualification is a must\nConsolidation & financial reporting\nGlobal exposure\n\nResponsibilities:\n\nResponsible for group consolidation, financial reporting closing, audited finical statements, and tax computation\nPreparate accurate reporting and filing of regulatory required financial reports in compliance with IFRS\nResearch accounting issues, summarize pertinent material, identify the impact and initiate recommendations/actions based on account review findings\nCoordinate communication finance matters with local finance teams across the globe\nHandle ad-hoc tasks from senior management\n\nRequirements:\n\nBachelor's degree in Finance & Accounting or related disciplines with CPA qualification\n6 years of working experience with a minimum of 3 years accounting experience in HK listed companies with consolidation responsibilities\nSelf-motivated, independent, a problem-solver, and able to work independently\nExcellent communication and interpersonal skills\nExcellent PC knowledge (including Excel, Word) and experience in Oracle system is an advantage\nGood command of both spoken and written English, Mandarin, and Cantonese\n\nInterested parties, please send your CV to Ivy Yeung Ivy.Yeung@connectedgroup.com for more details. For other available opportunities, please visit www.connectedgroup.com.", "employment_types": ["Full Time", "Permanent"], "selling_points": ["CPA qualification is a must", "Consolidation & financial reporting", "Global exposure"], "locations": ["Not Specified"], "categories": ["Accounting", "Accounting Clerk / Supervisor", "Chief Accountant", "Finance / Accounting Manager"], "post_time": "2022-01-14T06:49:01Z", "salary": {"currency": "HKD", "max": 44999, "min": 35000, "period": "monthly", "term": null}, "salary_visible": true, "title_keywords": ["finance manager"], "responsibilities": ["reporting", "financial reports", "tax computation", "ad-hoc tasks", "compliance", "review", "teams", "coordinate", "communication", "financial reporting", "senior management"], "requirements": {"degrees": ["degree", "bachelor"], "majors": ["related disciplines", "finance", "accounting"], "languages": ["cantonese", "english", "mandarin"], "language_level": ["good command"], "hard_skills": ["excel", "oracle system", "word", "cpa", "pc knowledge"], "soft_skills": ["self-motivated", "communication and interpersonal skills", "independent", "work independently"], "languages_combined": [{"language": "cantonese", "language_level": ["good command"]}, {"language": "english", "language_level": ["good command"]}, {"language": "mandarin", "language_level": ["good command"]}]}, "experience_required": {"duration": ["6 years", "minimum of 3 years"], "field": ["accounting experience", "consolidation"]}}, {"job_id": "100003009035476", "location_code": "hk", "company": "Wai Chun Strategic Investment Limited", "job_title": "Financial Manager \u8ca1\u52d9\u7d93\u7406", "description": "Reporting to the Chairman and the Board,\u00a0the appointee will lead the group financial functions covering all lines of business in Hong Kong and PRC, and fulfill compliance and company secretary functions.\u00a0\n\nQualifications:\n\nUniversity degree in Accounting with HKICPA/ACCA or equivalent professional qualifications\nOver 8 years of solid experience in budgetary control, financial planning and business partnering plus not less than 3 years\u2019 experience serving as Accounting Manager or above.\nFinance management experience gained from listed companies and sizable multinational corporation preferred\nStrong in evaluating business processes, driving and implementing strategic changes\nSelf-driven, charismatic, confident and project management skills\nExcellent communication and presentation skills\n\nResponsibilities:\n\nCoverage all the accounting and financial management matters of China and Hong Kong business\nExperience in handling joint ventures\nManage the production of the monthly management accounts and report providing value-added analysis and operational performance;\nCash management and related matters;\nOversee all financial compliance matters and regulators in jurisdictions where the group operates;\nResponsible for financial planning, treasury management, investment evaluations, and strategic business planning\n\nLocation: Admiralty\u00a0\n\nWe offer an attractive remuneration package and excellent career prospects to the right candidate.\u00a0\u00a0Please send full resume (Chinese version is a must), current and expected salary, contact number\u00a0and the availability to our e-mail address by clicking \"Apply Now\" for interview.\n\nPersonal data collected will be used for recruitment purpose only.\n\n\u8077\u8cac:\n\n\u8ca0\u8cac\u6240\u6709\u4e2d\u570b\u5927\u9678\u548c\u9999\u6e2f\u696d\u52d9\u7684\u8ca1\u52d9\u7ba1\u7406\u4e8b\u9805\uff1b\n\u8655\u7406\u5408\u8cc7\u4f01\u696d\u7d93\u9a57\uff1b\n\u7ba1\u7406\u6bcf\u6708\u7d9c\u5408\u7ba1\u7406\u8cec\u76ee\u548c\u5831\u544a\uff0c\u63d0\u4f9b\u589e\u503c\u7684\u5206\u6790\u548c\u71df\u904b\u5831\u544a\n\u73fe\u91d1\u7ba1\u7406\u53ca\u76f8\u95dc\u4e8b\u5b9c\uff1b\n\u76e3\u7763\u6240\u6709\u8ca1\u52d9\u5408\u898f\u4e8b\u5b9c\u548c\u53f8\u6cd5\u7ba1\u8f44\u5340\u4e2d\u7684\u76e3\u7ba1\u6a5f\u69cb\uff1b\n\u8ca0\u8cac\u8ca1\u52d9\u898f\u5283\uff0c\u8cc7\u91d1\u7ba1\u7406\uff0c\u6295\u8cc7\u8a55\u4f30\u548c\u4f01\u696d\u6230\u7565\u898f\u5283\u3002\n\n\u8cc7\u683c:\n\n\u5927\u5b78\u5b78\u4f4d\uff0c\u4e3b\u4fee\u6703\u8a08 , \u9999\u6e2f\u6703\u8a08\u5e2b\u516c\u6703\u6216\u570b\u969b\u5c08\u696d\u6703\u8a08\u7d44\u7e54\u6216\u540c\u7b49\u5c08\u696d\uff1b\n8\u5e74\u6216\u4ee5\u4e0a\u9810\u7b97\u63a7\u5236\uff0c\u8ca1\u52d9\u898f\u5283\u548c\u696d\u52d9\u5408\u4f5c\u7d93\u9a57\uff0c\u4ee5\u53ca\u4e0d\u5c11\u65bc3\u5e74\u6703\u8a08\u7d93\u7406\u7d1a\u6216\u4ee5\u4e0a\u7d93\u9a57\uff1b\n\u64c1\u6709\u4e0a\u5e02\u516c\u53f8\u548c\u5927\u578b\u8de8\u570b\u516c\u53f8\u8ca1\u52d9\u7ba1\u7406\u7d93\u9a57\u8005\u512a\u5148\uff1b\n\u5584\u65bc\u8a55\u4f30\u696d\u52d9\u6d41\u7a0b\uff0c\u63a8\u52d5\u548c\u5be6\u65bd\u6230\u7565\u8b8a\u9769\uff1b\n\u4e3b\u52d5\uff0c\u6709\u9b44\u529b\uff0c\u81ea\u4fe1\u548c\u9805\u76ee\u7ba1\u7406\u6280\u80fd\uff1b\n\u826f\u597d\u7684\u6e9d\u901a\u548c\u8868\u9054\u80fd\u529b\u3002\n\n\u5de5\u4f5c\u5730\u9ede: \u91d1\u9418\n\n\n\u6211\u5011\u63d0\u4f9b\u4e86\u4e00\u500b\u53ef\u89c0\u7684\u85aa\u916c\u798f\u5229\u548c\u826f\u597d\u7684\u8077\u696d\u524d\u666f\u7d66\u5408\u9069\u7684\u4eba\u9078\u3002\u8acb\u5c07\u500b\u4eba\u7c21\u6b77(\u5fc5\u9808\u4e2d\u6587\u7c21\u6b77)\uff0c\u76ee\u524d\u53ca\u671f\u671b\u85aa\u91d1\uff0c\u806f\u7d61\u96fb\u8a71\u548c\u5230\u8077\u65e5\u671f\u96fb\u90f5\u7d66\u6211\u53f8\u3002\n\n\u6536\u96c6\u7684\u500b\u4eba\u8cc7\u8a0a\u5c07\u50c5\u7528\u65bc\u62db\u8058\u7528\u9014\u3002", "employment_types": ["Full Time", "Permanent"], "selling_points": ["Finance Manager", "Occasional travel to China is required", "Min 3 years\u2019 serving as Accounting Manager"], "locations": ["Admiralty"], "categories": ["Accounting", "Chief Accountant", "Financial Controller", "Management", "Top Executives (CEO, CFO, CTO, GM, MD etc.)"], "post_time": "2022-01-10T07:20:34Z", "salary": {"currency": null, "max": null, "min": null, "period": "monthly", "term": null}, "salary_visible": false, "title_keywords": ["financial manager"], "responsibilities": ["reporting", "control", "management", "analysis", "compliance", "communication", "project management", "report", "planning"], "requirements": {"degrees": ["university degree"], "majors": ["accounting"], "languages": [], "language_level": [], "hard_skills": ["acca", "plus", "professional qualifications", "analysis", "project management", "hkicpa"], "soft_skills": ["confident", "responsible", "project management skills", "communication", "presentation skills", "driven"], "languages_combined": []}, "experience_required": {"duration": ["3 years", "8 years"], "field": ["management", "financial", "finance", "business", "accounting", "planning"]}}, {"job_id": "100003009042618", "location_code": "hk", "company": "Hunter Base International Company", "job_title": "Senior Accountant (Tseung Kwan O) - Listed Company", "description": "Requirements :\n\n- Degree holder in Accounting, Finance or similar discipline\n\n- At least five years' relevant account experience in sizable company, Preferably from FMCG or\nRetail Industry and e-commerce\u00a0\n\n- Sound knowledge of up-to-date accounting standards and able to meet compliance requirements\n\n- Proficiency in Microsoft office applications\n\n- Flexible, hands-on, strong analytical, problem solving and communication skill\n\n- Proficient in written and spoken Mandarin, English and Chinese\n\n- Immediately available is needed\u00a0\n\n", "employment_types": ["Full Time", "Permanent"], "selling_points": [], "locations": ["Tseung Kwan O"], "categories": ["Accounting", "Accountant", "Chief Accountant", "Finance / Accounting Manager"], "post_time": "2022-01-12T08:11:47Z", "salary": {"currency": null, "max": null, "min": null, "period": "monthly", "term": null}, "salary_visible": false, "title_keywords": ["senior accountant"], "responsibilities": ["communication", "compliance"], "requirements": {"degrees": ["degree holder"], "majors": ["finance", "accounting"], "languages": ["english", "chinese", "mandarin"], "language_level": ["proficient"], "hard_skills": ["microsoft office", "problem solving", "e-commerce"], "soft_skills": ["flexible", "hands-on", "communication skill", "problem solving"], "languages_combined": [{"language": "english", "language_level": ["proficient"]}, {"language": "chinese", "language_level": ["proficient"]}, {"language": "mandarin", "language_level": ["proficient"]}]}, "experience_required": {"duration": ["at least five years"], "field": ["fmcg"]}}, {"job_id": "100003009037433", "location_code": "hk", "company": "Robert Half", "job_title": "Senior Finance Manager", "description": "The Company\n\nA fast-growing servicing company is now looking for a Senior Finance Manager to lead the Finance department and business strategies with Senior Management for Hong Kong business\n\n\n\nThe Role\n\nDirectly report to Head of Finance\nLead and drive financial reporting and P&L balance in Hong Kong and Southeast Asia\nImprove innovation of accurate in management reporting in using BI dashboards and Visualization tools\nLiaise closely with stakeholders across different departments with global teams\nTrack financial performance of the BUs by timely analysing financial data and operating results and report variance against budget/forecast to top management\nAs a Finance business partner to cross functional teams (sales, plant GMs, supply chain, product development, HR and so on) and top management on formulating long-term and short-term strategic plans\nHandle ad-hoc projects.\n\n\n\nYour Profile\n\nQualification CPA with minimum 10 years of relevant experience\nExperience in consumer goods/product-based industries with Professional Audit firm is a big plus\nStrong in hands on experience with Business partner insights\nStrong communication, presentation, and analytical skills. Fluent in English, Mandarin and Cantonese\nIMMEDIATELY AVILABLE IS HIGHLY PREFERRED\n\n\n\nApply Today\n\nTo apply online (Word attachment only), please click the 'Apply' button. Please note that only short-listed candidates will be contacted.", "employment_types": ["Full Time", "Permanent"], "selling_points": ["Global Business Footprints", "Business partnership", "Attractive Renumeration package"], "locations": ["Central & Western Area"], "categories": ["Accounting", "Chief Accountant", "Finance / Accounting Manager", "Financial Analyst"], "post_time": "2022-01-11T02:48:27Z", "salary": {"currency": null, "max": null, "min": null, "period": "monthly", "term": null}, "salary_visible": false, "title_keywords": ["senior finance manager"], "responsibilities": ["liaise", "management", "ad-hoc projects", "strategic plans", "visualization", "data", "hr", "budget", "teams", "audit", "p&l", "communication", "management reporting", "financial reporting", "forecast", "senior management", "report"], "requirements": {"degrees": [], "majors": [], "languages": ["cantonese", "english", "mandarin"], "language_level": ["fluent"], "hard_skills": ["plus", "bi", "word", "analytical skills", "cpa"], "soft_skills": ["timely", "analytical skills", "communication", "hands on", "accurate", "presentation"], "languages_combined": [{"language": "cantonese", "language_level": ["fluent"]}, {"language": "english", "language_level": ["fluent"]}, {"language": "mandarin", "language_level": ["fluent"]}]}, "experience_required": {"duration": ["minimum 10 years"], "field": ["relevant experience", "audit", "business partner"]}}, {"job_id": "100003009031617", "location_code": "hk", "company": "Fortune Quest Limited", "job_title": "Senior Accountant", "description": "Job Description\n\nResponsibilities:\n\nOversee daily accounting works (AR / AP / Bank Accounts / Cash Movements / Cash Flow / Inventory Report / Company Net Position)\nBe responsible for monthly internal consolidated financial reports and analysis, including actuals and forecast\nPrepare annual budget and quarterly forecast with analysis and breakdowns.\nHandle statutory audit and tax filing in HK.\nBe responsible for finance matters of head office and branch offices (monthly expenses, salaries, etc)\nImprove operation efficiency, including system development for consolidation & reporting, and internal control by reviewing current workflow & propose action plans\nLiaise with banks, company secretary, auditors and insurance agents on related matters\n\nRequirements:\n\nDegree in Accounting, Finance or related disciplines with professional qualifications in HKICPA/ACCA or equivalent\nAcquire the experience in external audit, preparing consolidation reports to head office,\u00a0statutory consolidation to external auditor and internal management reports.\nPreferably with\u00a03 years\u2019 experience from CPA firms and 2 years\u2019 experience from in-house accounting department in sizable companies.\nProficiency in MS office application (e.g. Excel, Power-points, Words) and computerized accounting system.\nProactive, meticulous and able to work independently, efficiently and under pressure in a demanding and fast pace environment\nAble to communicate and present effectively across all levels including senior management\nGood people management skills, strong teamwork spirit and able to coach and develop subordinates\nExcellent command of both written & spoken English and Cantonese\n5-day work week\n13 month pay\nPerformance Bonus", "employment_types": ["Full Time"], "selling_points": [], "locations": ["Tsim Sha Tsui"], "categories": ["Accounting", "Chief Accountant"], "post_time": "2022-01-07T09:38:19Z", "salary": {"currency": null, "max": null, "min": null, "period": "monthly", "term": null}, "salary_visible": false, "title_keywords": ["senior accountant"], "responsibilities": ["ap", "reporting", "financial reports", "ar", "inventory", "analysis", "budget", "audit", "tax filing", "expenses", "cash flow", "forecast", "plans", "liaise with", "daily accounting", "insurance", "internal control", "report"], "requirements": {"degrees": ["degree"], "majors": ["related disciplines", "finance", "accounting"], "languages": ["cantonese", "english"], "language_level": ["excellent"], "hard_skills": ["excel", "acca", "words", "professional qualifications", "sizable companies", "cpa", "management reports", "accounting system", "ms office", "hkicpa"], "soft_skills": ["meticulous", "work independently", "under pressure", "teamwork spirit", "proactive"], "languages_combined": [{"language": "cantonese", "language_level": ["excellent"]}, {"language": "english", "language_level": ["excellent"]}]}, "experience_required": {"duration": ["3 years", "2 years"], "field": ["consolidation", "accounting", "audit", "management"]}}, {"job_id": "100003009033617", "location_code": "hk", "company": "", "job_title": "Financial Controller", "description": "We are a market leader in Hong Kong, China and ASEAN road transportation services. With very aggressive business growth agenda in developing new product lines, the company has set up own office and facility network in different continents to serve at customer convenience.\n\n\nJob Responsibilities:\nBudgeting, forecasting and analysis for region, reviewing business strategy and finances\nMonitor daily accounting functions, reporting and working closely with the Regional Finance Function\nManagement of tax planning process, compliance, and transfer pricing\nSupport various internal stakeholders in matters relating to internal controls, tax, and project implementations\nAd hoc assignments and projects\nRequirements:\nACCA, Degree or above in Accounting, Finance, or related disciplines\nAt least 15 years in an all-rounded accounting function, experience with financial reporting and accounting\nPrevious experience working in an audit firm is a plus, team leading experience preferred\nQualified Accountant is required, excellent business acumen and able to work with overseas staff\nExposure to Logistics or FMCG industry preferred\nAble to be based in Hong Kong, with occasional travel to Asian\nFluency in English and Chinese (Cantonese & Mandarin)\nCandidate with less experience will be considered as Senior Finance Manager\nWe offer excellent career development and attractive remuneration package to the right candidate.\n\nInformation supplied will be treated in strict confidence and used in accordance with the Personal Data (Privacy) Ordinance. Applicants not invited for interview within 2 months may consider their applications unsuccessful.\n\nInterested individuals please call +852 2473 2828 for more information. Only suitable candidates will be contacted.\n", "employment_types": ["Full Time", "Permanent"], "selling_points": ["Budgeting, forecasting and analysis for region", "Qualified Accountant with 15ys exp. is required", "Support various internal stakeholders"], "locations": ["Tsuen Wan Area"], "categories": ["Accounting", "Chief Accountant", "Financial Analyst", "Financial Controller"], "post_time": "2022-01-10T01:22:17Z", "salary": {"currency": null, "max": null, "min": null, "period": "monthly", "term": null}, "salary_visible": false, "title_keywords": ["financial controller"], "responsibilities": ["tax", "reporting", "management", "budgeting", "analysis", "planning process", "monitor", "compliance", "ad hoc assignments", "daily accounting", "forecasting"], "requirements": {"degrees": ["degree or above"], "majors": ["related disciplines", "finance", "accounting"], "languages": ["cantonese", "english", "chinese", "mandarin"], "language_level": ["fluency"], "hard_skills": ["acca", "fmcg industry", "acumen", "plus"], "soft_skills": ["business acumen"], "languages_combined": [{"language": "cantonese", "language_level": []}, {"language": "english", "language_level": ["fluency"]}, {"language": "chinese", "language_level": ["fluency"]}, {"language": "mandarin", "language_level": []}]}, "experience_required": {"duration": ["at least 15 years"], "field": ["financial", "finance manager", "audit", "accounting", "team"]}}, {"job_id": "100003009037385", "location_code": "hk", "company": "Robert Half", "job_title": "FP&A Manager", "description": "The Company\n\nA leading specialist in Risk and Compliance resources company is now looking for a high-calibre Regional FP&A Manager to manage the business operations.\n\n\n\nThe Role\n\nDirectly report to CFO\nProvide group level analysis of budget & forecast on monthly basics\nLiaise with regional business managers to prepare yearly budgets\nPropose and steer business performance improvement of pricing optimization, cost saving, automation of tasks, etc.\nMonitoring of Accounting policy, Transfer pricing, Tax regulations to ensure best practices and procedures\nTrack financial performance of the BUs by timely analysing financial data and operating results and report variance against budget/forecast to top management\nAs a Finance business partner to cross functional teams (sales, plant GMs, supply chain, product development, HR and so on) and top management on formulating long-term and short-term strategic plans\nLiaise with regional business managers to prepare yearly budgets\nHandle ad-hoc projects.\n\n\n\nYour Profile\n\nQualification CPA or CFA with minimum 5 years of relevant FP&A experience\nExperience in Supply Chain/ Logistics or Sourcing industry with Professional Audit firm is a big plus\nStrong in Business Partnering and Analysis\nStrong communication, presentation, and analytical skills. Fluent in English, Mandarin and Cantonese\nIMMEDIATELY AVILABLE IS HIGHLY PREFERRED\n\n\n\nApply Today\n\nTo apply online (Word attachment only), please click the 'Apply' button. Please note that only short-listed candidates will be contacted.", "employment_types": ["Full Time", "Permanent"], "selling_points": ["Global scope", "Business partnership", "Attractive Renumeration package"], "locations": ["Central & Western Area"], "categories": ["Accounting", "Chief Accountant", "Finance / Accounting Manager", "Financial Analyst"], "post_time": "2022-01-11T02:40:26Z", "salary": {"currency": null, "max": null, "min": null, "period": "monthly", "term": null}, "salary_visible": false, "title_keywords": ["manager"], "responsibilities": ["regulations", "data", "operations", "budget", "audit", "communication", "liaise with", "ad-hoc projects", "compliance", "teams", "logistics", "forecast", "report", "cost", "management", "monitoring", "procedures", "tax", "budgets", "strategic plans", "analysis", "hr"], "requirements": {"degrees": [], "majors": [], "languages": ["cantonese", "english", "mandarin"], "language_level": ["fluent"], "hard_skills": ["plus", "cfa", "analysis", "word", "analytical skills", "cpa"], "soft_skills": ["communication", "timely", "presentation", "analytical skills"], "languages_combined": [{"language": "cantonese", "language_level": ["fluent"]}, {"language": "english", "language_level": ["fluent"]}, {"language": "mandarin", "language_level": ["fluent"]}]}, "experience_required": {"duration": ["minimum 5 years"], "field": ["cfa", "logistics", "supply chain", "audit"]}}, {"job_id": "100003009039081", "location_code": "hk", "company": "AOSource Company Limited", "job_title": "Manager/Senior Manager (General Accounting, Retail )  [ Ref# ACC-vh-111-JDB ]", "description": "Our client is a well established living product store in Greater China.\u00a0\u00a0 They are looking for a potential candidate to their Finance team.\n\nJob Responsibilities :\n\nReported to Head of Finance and lead a team of General Accounting\nResponsible to prepare financial statements for the CS Group companies in Hong Kong with reference to a set of accounting policies and procedures\nAdvising line managers in the process of developing policies or procedures for their business operations ensuring compliance with the accounting policies and guidelines\nWork with IT for system and equipment development and testing in new store opening projects\nProvide financial advise on the tenant and consignment contract renewal application for management decision making\nLead and provide continuous coaching to a team of staff in carrying out the accounting operations and reporting\nTransfer pricing and review intercompany transaction flows\n\nJob Requirements :\n\nDegree holder in Finance & Accounting or equivalent\nQualified Accountant with 7 years relevant experiences in which at least 5 years in supervisory level in retail / F&B business\nHands on SAP experience\nPresentable, strong business acumen, leadership, interpersonal and communication skills\nGood command of both spoken and written English & Mandarin\nAnalytical, detail-minded, result-oriented , able to meet tight deadline\n\n\u00a0Our client will offer competitive remuneration package and good career prospects to the potential candidate, interested parties please quote the ref. no.\u00a0ACC-vh-111-JDB\u00a0and submit your resume to\u00a0Ms. Vida Hung\u00a0by our email address.\n\nAll profiles are handled with strictest confidentiality. Shortlisted candidates would be notified", "employment_types": ["Full Time"], "selling_points": ["Famous living product retail in Greater China", "Lead Fin team & coaching, fin advice, SAP exp", "Qualified Acct, gd benefits & wkg environment"], "locations": ["Not Specified"], "categories": ["Accounting", "Chief Accountant", "Finance / Accounting Manager", "Financial Controller"], "post_time": "2022-01-11T08:38:19Z", "salary": {"currency": null, "max": null, "min": null, "period": "monthly", "term": null}, "salary_visible": false, "title_keywords": ["senior manager", "manager", "accounting"], "responsibilities": ["reporting", "management", "guidelines", "policies", "operations", "compliance", "procedures", "developing", "financial statements", "testing", "review", "lead a team", "accounting policies"], "requirements": {"degrees": ["degree holder"], "majors": ["finance", "accounting"], "languages": ["english", "mandarin"], "language_level": ["good command"], "hard_skills": ["sap", "acumen"], "soft_skills": ["detail-minded", "communication skills", "result-oriented", "presentable", "hands on", "meet tight deadline", "business acumen", "leadership", "interpersonal"], "languages_combined": [{"language": "english", "language_level": ["good command"]}, {"language": "mandarin", "language_level": ["good command"]}]}, "experience_required": {"duration": ["7 years", "at least 5 years"], "field": ["business", "supervisory level", "f&b", "retail"]}}, {"job_id": "100003009043391", "location_code": "hk", "company": "Links International", "job_title": "(Assistant) Finance Manager -  Capital Raising", "description": "Responsibilities:\n\nSupervise daily accounting operations and month-end reporting\nDeliver regular consolidated reports and analysis of the Group\nEngage in budgeting, rolling forecast, and long-term financial planning\nSupport CFO in resolving financial and accounting issues of the group companies\nSupport annual audit / interim review and negotiation with Auditor or tax agent\nSupport Investor relationship and fundraising activities\nWork on ad-hoc assignments as required\n\nRequirements:\n\nDegree holder in Accounting or related disciplines, Qualified HKICPA/ACCA\nAt least 5 years of solid experience in the field of commercial accounting + Big 4\nPrefer candidates with start-up experiences, tech start-up is an advantage\nExcellent PC knowledge (including Excel, Word) and experience in ERP system is an advantage\nGood command of spoken and written English and Mandarin\nEmploys a proactive approach and can-do attitude to problem-solving\nResponsible, independent, details oriented, self-motivated and committed to tight deadlines", "employment_types": ["Full Time", "Permanent"], "selling_points": ["Guaranteed 13 months salary", "Very flexible working culture", "All rounded and dynamic role"], "locations": ["Not Specified"], "categories": ["Accounting", "Accountant", "Chief Accountant", "Finance / Accounting Manager"], "post_time": "2022-01-12T11:24:41Z", "salary": {"currency": "HKD", "max": 44999, "min": 35000, "period": "monthly", "term": null}, "salary_visible": true, "title_keywords": ["finance manager", "assistant"], "responsibilities": ["tax", "reporting", "rolling forecast", "annual audit", "budgeting", "analysis", "review", "ad-hoc assignments", "month-end", "daily accounting operations", "reports", "planning"], "requirements": {"degrees": ["degree holder"], "majors": ["related disciplines", "accounting"], "languages": ["english", "mandarin"], "language_level": ["good command"], "hard_skills": ["excel", "acca", "problem-solving", "word", "erp system", "pc knowledge", "hkicpa"], "soft_skills": ["self-motivated", "independent", "responsible", "can-do attitude", "problem-solving", "committed", "proactive"], "languages_combined": [{"language": "english", "language_level": ["good command"]}, {"language": "mandarin", "language_level": ["good command"]}]}, "experience_required": {"duration": ["at least 5 years"], "field": ["tech", "big 4", "commercial", "erp system", "accounting"]}}, {"job_id": "100003009029847", "location_code": "hk", "company": "G.C. Nanda & Sons Limited", "job_title": "Finance and Administration Executive", "description": "Job Description\nHandle daily accounting operations and maintain proper accounting record and ledger\nPerform data entries - receivables and payments\nMaintain proper filing and accounting records\nProvide full spectrum of daily office matters, HR, administrative and admin supporting duties, purchasing of office stationary and other office related equipment and various items.\nOffice and staff medical insurance, car insurance, staff management and supervision etc\nYou need to be\nDegree, Higher Diploma or Diploma holder in Accountancy\nMin 4 years working experience in office admin and accounting (preferably in travel industry)\nProficiency in MS Office, excel, accounting system (MYOB)\nGood command in both written and spoken English and Chinese\nWell organised and detailed minded person with good interpersonal skills and staff interaction\nPosition available immediately\u00a0\n\nInterested parties, please click \"Apply Now\" to submit your application.\nPersonal data collected will be used for recruitment purpose only.", "employment_types": ["Full Time", "Permanent", "Contract"], "selling_points": ["Accounting, administration & staff affairs", "Assistance to Senior Management", "Min 4yrs working experience esp in Travel Industry"], "locations": ["Sheung Wan"], "categories": ["Accounting", "Accountant", "Chief Accountant", "Hospitality / F & B", "Tourism / Travel Agency"], "post_time": "2022-01-10T04:26:13Z", "salary": {"currency": "HKD", "max": 24999, "min": 20000, "period": "monthly", "term": null}, "salary_visible": true, "title_keywords": ["administration executive"], "responsibilities": ["management", "data", "hr", "daily accounting operations", "maintain", "payments", "insurance"], "requirements": {"degrees": ["diploma holder", "diploma", "degree"], "majors": ["accountancy"], "languages": ["english", "chinese"], "language_level": ["good command"], "hard_skills": ["excel", "myob", "accounting system", "ms office"], "soft_skills": ["interpersonal skills", "detailed", "organised"], "languages_combined": [{"language": "english", "language_level": ["good command"]}, {"language": "chinese", "language_level": ["good command"]}]}, "experience_required": {"duration": ["min 4 years"], "field": ["admin", "accounting"]}}, {"job_id": "100003009044510", "location_code": "hk", "company": "Links International", "job_title": "Treasury Manager - Luxury Retail", "description": "Responsibilities:\n\nSupervise day-to-day treasury operation and cash management\nWorking closely with Finance team on project funding decisions and financial projections\nReview loan and funding documents\nManage foreign exchange and interest rate risk, and FX hedging across APAC\nPrepare and submit treasury reports for senior management review\nAdvise on tax issues regarding investments & M&A projects\nManage and liaise with banks for funding and investment decisions\nBeing a strong business partner with stakeholders across different regions\n\nRequirements:\n\nBachelor Degree in Accounting & Finance or related discipline\nAt least 5 years of experience in treasury, preferably in sizeable MNC and luxury retailer\nSolid experiences in Retail and FMCG related industries are highly preferred\nSmart, energetic person who is ambitious to strive for excellence\nExcellent command of both English and Cantonese\nExcellent communication and presentation\nDynamic personality with an analytical mindset", "employment_types": ["Full Time", "Permanent"], "selling_points": ["Guaranteed 13 months salary", "Work life balance", "Regional exposure"], "locations": ["Not Specified"], "categories": ["Accounting", "Chief Accountant", "Finance / Accounting Manager", "Treasurer"], "post_time": "2022-01-13T04:23:52Z", "salary": {"currency": "HKD", "max": 54999, "min": 45000, "period": "monthly", "term": null}, "salary_visible": true, "title_keywords": ["manager"], "responsibilities": ["tax", "management", "project funding", "review", "reports", "finance team", "liaise with", "senior management"], "requirements": {"degrees": ["degree", "bachelor"], "majors": ["finance", "accounting"], "languages": ["cantonese", "english"], "language_level": ["excellent"], "hard_skills": ["dynamic"], "soft_skills": ["communication", "energetic", "dynamic", "strive for excellence", "presentation"], "languages_combined": [{"language": "cantonese", "language_level": ["excellent"]}, {"language": "english", "language_level": ["excellent"]}]}, "experience_required": {"duration": ["at least 5 years"], "field": ["related", "retail", "fmcg"]}}, {"job_id": "100003009041223", "location_code": "hk", "company": "Pure Search International Limited", "job_title": "ACCOUNTING MANAGER | 12 months contract | IMMEDIATE AVAILABILITY", "description": "A European listed organisation and an industry leader in the Consumer business is aggressively expanding their footprint in Asia. As part of their expansion plans, they are seeking for an experienced Accounting Manager to handle Accounting Operations, Statutory account, Financial reporting and corporate tax submissions.\n\nThis is a 12 months contract position with gratuity bonus and medical coverage benefits.\n\nResponsibilities:\n\nReport directly to the Financial Controller and work closely with various members under the Accounting team (e.g. External Vendors, auditors, Tax Consultants, European HQ).\nWorking alongside a stable team to prepare monthly / quarterly / financial statements in a timely matter.\nResponsible for timely and accurate filing of statutory accounts and tax\nAssist in the preparation of group consolidated accounts, P&L and balance sheet schedules & income statement\nReview, analyse and make recommendations on internal control and accounting policies.\nRequirements\n\nBachelor Degree or equivalent\nAt least 8years relevant experience in Finance & Accounting operations with large-scale MNCs at a regional capacity.\u00a0\nCandidates with audit and Big 4 training is preferred\nStrong command of English & Chinese\nAgile, flexible and self-driven\nProblem solver, patient and proactive\nImmediate Availability is preferred", "employment_types": ["Full Time", "Temporary", "Contract"], "selling_points": ["Immediate Availability", "Strong Communication in English & Cantonese", "Up to HK$55,000 / month, with Medical benefits"], "locations": ["Not Specified"], "categories": ["Accounting", "Accounting Clerk / Supervisor", "Chief Accountant", "Finance / Accounting Manager"], "post_time": "2022-01-12T03:37:06Z", "salary": {"currency": "HKD", "max": 54999, "min": 45000, "period": "monthly", "term": null}, "salary_visible": true, "title_keywords": ["accounting manager"], "responsibilities": [], "requirements": {"degrees": [], "majors": [], "languages": [], "language_level": [], "hard_skills": [], "soft_skills": [], "languages_combined": []}, "experience_required": {"duration": [], "field": []}}, {"job_id": "100003009038573", "location_code": "hk", "company": "Spidernet Recruitment Services", "job_title": "Finance Manager / Assistant Finance Manager", "description": "Finance Manager / Assistant Finance Manager\n\nResponsibilities\n\nLead a small team of two to handle daily accounting and treasury function of Hong Kong entities.\nResponsible for sub-group consolidation, monthly and year-end financial reporting closing, audited finical statements and tax computation.\nManage daily treasury functions, including review payment, cash flow forecast, etc.\nLiaise with external auditors for annual audit.\nAssist in ad hoc projects as assigned.\u00a0\n\nRequirements\n\nDegree holder of Accounting/ Finance or related disciplines.\nQualified accountant.\nAt least 7 years of related experience in sizable corporation, with 3 years of managerial capacity.\nDetail-minded, good analytical and interpersonal skills.\nProficient in Oracle, MS Office and Chinese word processing.\nFluent in written and spoken English and Chinese (Cantonese and Mandarin).\n\n\u00a0Attractive remuneration and fringe benefits will be offered to the successful candidate.\n\nInterested candidates should apply with detailed resume, present and expected salaries by clicking the Apply Now button.\n\nAll information received will be treated in strict confidence and used for recruitment purpose only.\n\nOnly shortlisted candidates will be notified.", "employment_types": ["Full Time", "Permanent"], "selling_points": ["Degree in Account, Qualified Accountant, 7 yrs exp", "at least 3 yrs managerial exp prefer listed co exp", "sub-group consolidation, treasury, Fin. reporting"], "locations": ["Not Specified"], "categories": ["Accounting", "Chief Accountant", "Finance / Accounting Manager", "Others"], "post_time": "2022-01-11T07:26:21Z", "salary": {"currency": null, "max": null, "min": null, "period": "monthly", "term": null}, "salary_visible": false, "title_keywords": ["assistant finance manager", "finance manager"], "responsibilities": ["year-end", "tax computation", "annual audit", "lead a small team", "review", "payment", "cash flow", "ad hoc projects", "financial reporting", "forecast", "liaise with", "daily accounting", "external auditors"], "requirements": {"degrees": ["degree holder"], "majors": ["related disciplines", "finance", "accounting"], "languages": ["cantonese", "english", "chinese", "mandarin"], "language_level": ["fluent", "proficient"], "hard_skills": ["chinese word processing", "ms office", "oracle"], "soft_skills": ["detail-minded", "interpersonal skills"], "languages_combined": [{"language": "cantonese", "language_level": ["fluent"]}, {"language": "english", "language_level": ["fluent"]}, {"language": "chinese", "language_level": ["fluent", "proficient"]}, {"language": "mandarin", "language_level": ["fluent"]}]}, "experience_required": {"duration": ["3 years", "at least 7 years"], "field": ["related", "managerial"]}}, {"job_id": "100003009049785", "location_code": "hk", "company": "Michael Page", "job_title": "Finance Manager, 55k, PRC Firm", "description": "Our client is a reputable property company. They are now looking for a talent Finance Manager to join their finance team.\n\nClient Details\n\nOur client is a reputable property company. They are now looking for a talent Finance Manager to join their finance team.\n\nDescription\n\nReporting to the GM Finance, you will be responsible for\n\nPreparing for the Main Board IPO listing for the company\nHandling company secretarial matters after IPO\nPreparing annual and interim reports\nStrengthening internal controls, corporate governance and streamline accounting procedures to comply with the Hong Kong Listing Rules / standards\nProviding recommendations to enhance financial performance and business opportunities\nLiaising with CPA firm for audit and tax related matters\n\nProfile\n\nPRC University is highly preferred\n\nExcellent communication skills (English and Mandarin)\n\nDegree Holder in Business/Accounting/Finance\n\nJob Offer\n\nMain Board IPO Experience\nCompetitive Remuneration\n\nTo apply online please click the 'Apply' button below.\nFor a confidential discussion about this role please contact Nicole Hui on +852 3412 4832.", "employment_types": ["Full Time", "Permanent"], "selling_points": ["CPA is a must", "PRC", "13 Months Guaranteed with Bonus"], "locations": ["Not Specified"], "categories": ["Accounting", "Chief Accountant", "Finance / Accounting Manager", "Financial Controller"], "post_time": "2022-01-14T09:14:04Z", "salary": {"currency": null, "max": null, "min": null, "period": "monthly", "term": null}, "salary_visible": false, "title_keywords": ["finance manager"], "responsibilities": ["tax", "reporting", "business opportunities", "procedures", "liaising with", "audit", "communication", "reports", "finance team", "contact", "listing"], "requirements": {"degrees": ["degree holder"], "majors": ["finance", "business", "accounting"], "languages": ["english", "mandarin"], "language_level": ["excellent"], "hard_skills": ["cpa", "gm"], "soft_skills": ["communication skills", "responsible"], "languages_combined": [{"language": "english", "language_level": ["excellent"]}, {"language": "mandarin", "language_level": ["excellent"]}]}, "experience_required": {"duration": [], "field": []}}, {"job_id": "100003009034735", "location_code": "hk", "company": "Able Choice Personnel Consultancy", "job_title": "Accountant / Senior Accountant (Group Consolidation) (5 Days Work)", "description": "Responsibilities\n\nPrepare group consolidated management reports\nPrepare group monthly financial statements\nControl, monitor & oversee the full range of accounting functions\nHandling ad-hoc projects as assigned\nLead a team of accounting staff\n\nRequirements\n\nDegree holder or above in Finance or Accounting or related discipline\nHKICPA semi-finalist or other professional accounting bodies\nMinimum 3 years\u2019 group accounting consolidation experience in Sizeable Corporation\nProficiency in MS Word, Excel and Chinese Word Processing\nGood command of both written and spoken English and Chinese\nGood team player, well-organized, self-motivated with good interpersonal skills\n\nAttractive benefits will be offered to the right candidates. Interested parties, please send your detailed resume with expected salary to cv@ablechoice. com for interview.", "employment_types": ["Full Time", "Permanent"], "selling_points": ["MNC Trading Co, 5-Day with attractive Benefits", "HKICPA semi-finalist, 3 yrs+ group consolidation", "Good English & Chinese"], "locations": ["Kwun Tong Area"], "categories": ["Accounting", "Accountant", "Audit", "Chief Accountant"], "post_time": "2022-01-10T04:14:07Z", "salary": {"currency": null, "max": null, "min": null, "period": "monthly", "term": null}, "salary_visible": false, "title_keywords": ["accountant", "senior accountant"], "responsibilities": ["control", "monthly financial statements", "monitor", "lead a team", "management reports", "ad-hoc projects"], "requirements": {"degrees": ["degree holder"], "majors": ["finance", "accounting"], "languages": ["english", "chinese"], "language_level": ["proficiency", "good command"], "hard_skills": ["ms word", "excel", "chinese word processing", "hkicpa"], "soft_skills": ["good team player", "well-organized", "self-motivated", "interpersonal skills"], "languages_combined": [{"language": "english", "language_level": ["good command"]}, {"language": "chinese", "language_level": ["proficiency", "good command"]}]}, "experience_required": {"duration": ["minimum 3 years"], "field": ["accounting", "consolidation"]}}, {"job_id": "100003009042324", "location_code": "hk", "company": "JH Partners (Asia) Company Limited", "job_title": "Fluent Japanese Speaking  Accounting Manager (Japanese Insurance company)", "description": "Our Client (Japanese Insurance company\u00a0) is looking for Fluent Japanese Speaking\u00a0 Accounting Manager.\n\nResponsibilities\n\n\n\n\u30fbManagement of accounting and finance members including subsidiaries\n\u30fb Monthly and yearly closing management\n\u30fb Cash flow management\n\u30fb Create management report\n\n\n\nRequirements\n\n\u3010Must\u3011\nFluent Japanese and\u00a0 Business level of English\nAt least 10 years experiences in Accounting and Finance feild\nManagement Experience\n\n\u3010Welcome\u3011\nExperience to manage branch of China and Asean regions\u00a0\nWorking experience in Japan or Japanese Company\n\n\n1) Expected salary\n2) Current salary\n3) Reason for leaving current and past employments\n\nPersonal data collected will be used for employment-related purpose only.\u00a0We\u00a0regret to inform that only shortlisted candidates will be notified, thank you.", "employment_types": ["Full Time"], "selling_points": ["Fluent Japanese", "At least 10 years experiences in Accounting feild", "Management Experience is required"], "locations": ["Tsim Sha Tsui"], "categories": ["Accounting", "Chief Accountant", "Finance / Accounting Manager", "Financial Controller"], "post_time": "2022-01-12T07:02:43Z", "salary": {"currency": null, "max": null, "min": null, "period": "monthly", "term": null}, "salary_visible": false, "title_keywords": ["accounting manager"], "responsibilities": ["management", "management report", "cash flow"], "requirements": {"degrees": [], "majors": [], "languages": ["japanese", "english"], "language_level": ["fluent"], "hard_skills": ["inform", "reason"], "soft_skills": [], "languages_combined": [{"language": "japanese", "language_level": ["fluent", "fluent"]}, {"language": "english", "language_level": ["fluent"]}]}, "experience_required": {"duration": ["at least 10 years"], "field": ["finance", "management", "accounting"]}}, {"job_id": "100003009045024", "location_code": "hk", "company": "Michael Page", "job_title": "Accountant, Law Firm, 38k (Big 8 welcome)", "description": "Our client is a reputable law firm. To cope with their business needs, they are now looking for a talented Accountant to join their finance team.\n\nClient Details\n\nOur client is a reputable law firm. To cope with their business needs, they are now looking for a talented Accountant to join their finance team.\n\nDescription\n\nReporting to the Regional FC in Hong Kong, you will be responsible for:\n\nensuring accurate financial and management reports\nperforming a full spectrum of accounting and finance duties\ntaking part in business partnering and providing financial advice for better business outcomes\n\nProfile\n\nDegree Holder in Business/Accounting/Finance\nProfessional Servicing/Law Firm experience would be a plus\nBig 8 are welcome\nExcellent communication skills (English and Mandarin) is a must\n\nJob Offer\n\nCompetitive remuneration\nFast and dynamic business growth\nReputable company\n\nTo apply online please click the 'Apply' button below.\nFor a confidential discussion about this role please contact Nicole Hui on +852 3412 4832.", "employment_types": ["Full Time", "Permanent"], "selling_points": ["Fluent Mandarin and English is a must", "Renowned Law Firm", "Attractive package with promising career prospect"], "locations": ["Not Specified"], "categories": ["Accounting", "Accountant", "Chief Accountant", "Finance / Accounting Manager"], "post_time": "2022-01-13T06:55:50Z", "salary": {"currency": null, "max": null, "min": null, "period": "monthly", "term": null}, "salary_visible": false, "title_keywords": ["accountant"], "responsibilities": ["reporting", "finance duties", "communication", "management reports", "finance team", "contact"], "requirements": {"degrees": ["degree holder"], "majors": ["finance", "business", "accounting"], "languages": ["english", "mandarin"], "language_level": ["excellent"], "hard_skills": ["management reports", "dynamic", "plus"], "soft_skills": ["communication skills", "dynamic", "accurate", "responsible"], "languages_combined": [{"language": "english", "language_level": ["excellent"]}, {"language": "mandarin", "language_level": ["excellent"]}]}, "experience_required": {"duration": [], "field": []}}, {"job_id": "100003009039815", "location_code": "hk", "company": "Links International", "job_title": "Assistant Finance Manager - FinTech Startup!", "description": "Responsibilities:\n\nSupervise daily accounting operations and month-end reporting\nDeliver regular consolidated reports and analysis of the Group\nEngage in budgeting, rolling forecast, and long-term financial planning\nSupport CFO in resolving financial and accounting issues of the group companies\nSupport annual audit / interim review and negotiation with Auditor or tax agent\nSupport Investor relationship and fundraising activities\nWork on ad-hoc assignments as required\n\nRequirements:\n\nDegree holder in Accounting or related disciplines, Qualified HKICPA/ACCA\nAt least 5 years of solid experience in the field of commercial accounting + Big 4\nPrefer candidates with start-up experiences, tech start-up is an advantage\nExcellent PC knowledge (including Excel, Word) and experience in ERP system is an advantage\nGood command of spoken and written English and Mandarin\nEmploys a proactive approach and can-do attitude to problem-solving\nResponsible, independent, details oriented, self-motivated and committed to tight deadlines", "employment_types": ["Full Time", "Permanent"], "selling_points": ["Guaranteed 13 months salary", "Very flexible working culture", "All rounded and dynamic role"], "locations": ["Not Specified"], "categories": ["Accounting", "Accountant", "Chief Accountant", "Finance / Accounting Manager"], "post_time": "2022-01-11T11:34:27Z", "salary": {"currency": "HKD", "max": 54999, "min": 35000, "period": "monthly", "term": null}, "salary_visible": true, "title_keywords": ["assistant finance manager"], "responsibilities": ["tax", "reporting", "rolling forecast", "annual audit", "budgeting", "analysis", "review", "ad-hoc assignments", "month-end", "daily accounting operations", "reports", "planning"], "requirements": {"degrees": ["degree holder"], "majors": ["related disciplines", "accounting"], "languages": ["english", "mandarin"], "language_level": ["good command"], "hard_skills": ["excel", "acca", "problem-solving", "word", "erp system", "pc knowledge", "hkicpa"], "soft_skills": ["self-motivated", "independent", "responsible", "can-do attitude", "problem-solving", "committed", "proactive"], "languages_combined": [{"language": "english", "language_level": ["good command"]}, {"language": "mandarin", "language_level": ["good command"]}]}, "experience_required": {"duration": ["at least 5 years"], "field": ["tech", "big 4", "commercial", "erp system", "accounting"]}}, {"job_id": "100003009044757", "location_code": "hk", "company": "David James Recruitment Limited", "job_title": "Finance Manager (Payroll & Reporting) \u2013 Global Investment Firm ($50 \u2013 65K)", "description": "Working on behalf of a global investment firm which provides investment management and researching services to clients, we are now searching for a Finance Manager (Payroll & Reporting).\n\nResponsibilities:\n\nReport to CFO and work closely with Financial Controllers\nProvide financial report and strategic advice to senior management including financial presentations, budgeting, forecast and financial analysis\nPrepare monthly financial statements and perform year-end closing\u00a0\nHandle monthly payroll of Hong Kong and China office\nReview and manage external payroll vendors\nPerform ad hoc duties\u00a0\n\nRequirements:\n\nDegree holder in Finance, Accounting, or other relevant disciplines\n6 years + experience (FI or MNC experience would be an advantage)\nGreat attention to details with solid analytical mind set\nGood understanding of HK salary tax and MPF regulations preferred\nGood command of Chinese and English\n\nTo Apply\n\nInterested parties please send us your updated resume with your latest and expected salaries or please call +852\u00a03611 7880\u00a0or email at legal\uff20djrecruit.com\u00a0for a confidential discussion.", "employment_types": ["Full Time", "Permanent"], "selling_points": ["Sizable MNC-style Investment Firm with friendly", "Stable working hours with good benefits", "Fluent in English and Mandarin"], "locations": ["Eastern Area"], "categories": ["Accounting", "Chief Accountant", "Finance / Accounting Manager", "Financial Analyst"], "post_time": "2022-01-13T06:10:22Z", "salary": {"currency": null, "max": null, "min": null, "period": "monthly", "term": null}, "salary_visible": false, "title_keywords": ["finance manager"], "responsibilities": ["ad hoc duties", "budgeting", "review", "presentations", "financial analysis", "prepare monthly financial statements", "financial report", "forecast", "year-end closing", "senior management", "payroll", "report"], "requirements": {"degrees": ["degree holder"], "majors": ["finance", "accounting"], "languages": ["english", "chinese"], "language_level": ["good command"], "hard_skills": ["mpf regulations"], "soft_skills": ["analytical mind", "attention to details"], "languages_combined": [{"language": "english", "language_level": ["good command"]}, {"language": "chinese", "language_level": ["good command"]}]}, "experience_required": {"duration": ["6 years +"], "field": []}}, {"job_id": "100003009031718", "location_code": "hk", "company": "", "job_title": "Financial Controller/Senior Finance Manager", "description": "Responsibilities:\n\nReport to CFO;\nManaging internal and external financial reporting requirements including consolidation, compliance and controlling activities;\nManaging parties including external auditors, tax authorities and internal business units;\nLeading cash and liquidity management and credit risk management;\nLeading forecasting and budgeting;\nSetting departmental KPIs for performance tracking;\nCoordinating company secretarial matters for the Group;\nSupport various internal stakeholders in matters relating to internal controls, tax, and project implementations\nTo perform additional duties and other ad hoc assignments as requested\n\n\u00a0Requirements:\n\nDegree holder in Accounting, Finance, Business Administration or related discipline, qualified accountant of HKICPA/ACCA\nAt least 10-15 years in an all-rounded accounting function, experience with financial reporting and accounting with 5 years\u2019 experience in managerial level\nStrong analytical ability and forecasting skills with strong attention to detail\nKnowledge in China accounting, laws and regulations\nExperience in Big4 or financial institutions is a plus\nExperience in medical related industry is a plus\nProficient in both written and spoken English & Chinese\nGood time management skill and able to work under pressure\nStrong communication skills and connect proactively across various levels in the Business Units\nProficient user in Excel\nCandidate with less experience will be considered as Senior Finance Manager\n\n(Personal data will be used for recruitment purpose only.\u00a0\u00a0All information received will remain confidential and will be destroyed after 6 months.)\n\nInterested candidates, please contact us at 34279018 for company details before applying.", "employment_types": ["Full Time", "Permanent"], "selling_points": [], "locations": ["Central"], "categories": ["Accounting", "Chief Accountant", "Finance / Accounting Manager", "Financial Controller"], "post_time": "2022-01-07T09:45:26Z", "salary": {"currency": null, "max": null, "min": null, "period": "monthly", "term": null}, "salary_visible": false, "title_keywords": ["senior finance manager", "financial controller"], "responsibilities": ["tax", "management", "tracking", "budgeting", "additional duties", "compliance", "financial reporting", "ad hoc assignments", "kpis", "report", "forecasting", "external auditors"], "requirements": {"degrees": ["degree holder"], "majors": ["finance", "accounting", "business administration"], "languages": ["english", "chinese"], "language_level": ["proficient"], "hard_skills": ["excel", "acca", "plus", "hkicpa"], "soft_skills": ["communication skills", "time management skill", "attention to detail", "work under pressure"], "languages_combined": [{"language": "english", "language_level": ["proficient"]}, {"language": "chinese", "language_level": ["proficient"]}]}, "experience_required": {"duration": ["5 years", "at least 10-15 years"], "field": ["managerial", "financial", "related", "finance manager", "financial institutions", "accounting", "medical"]}}, {"job_id": "100003009038178", "location_code": "hk", "company": "ConnectedGroup Limited", "job_title": "Finance Manager", "description": "Finance Manager\n\nOur client is a highly reputable conglomerate with business operations across the globe. To facilitate their company growth, they are looking for a high-caliber finance manager to join their team.\n\nCPA qualification is a must\nConsolidation & financial reporting\nGlobal exposure\n\nResponsibilities:\n\nResponsible for group consolidation, financial reporting closing, audited finical statements, and tax computation\nPreparate accurate reporting and filing of regulatory required financial reports in compliance with IFRS\nResearch accounting issues, summarize pertinent material, identify the impact and initiate recommendations/actions based on account review findings\nCoordinate communication finance matters with local finance teams across the globe\nHandle ad-hoc tasks from senior management\n\nRequirements:\n\nBachelor's degree in Finance & Accounting or related disciplines with CPA qualification\n6 years of working experience with a minimum of 3 years accounting experience in HK listed companies with consolidation responsibilities\nSelf-motivated, independent, a problem-solver, and able to work independently\nExcellent communication and interpersonal skills\nExcellent PC knowledge (including Excel, Word) and experience in Oracle system is an advantage\nGood command of both spoken and written English, Mandarin, and Cantonese\n\nInterested parties, please send your CV to Ivy Yeung Ivy.Yeung@connectedgroup.com for more details. For other available opportunities, please visit www.connectedgroup.com.", "employment_types": ["Full Time", "Permanent"], "selling_points": ["CPA qualification is a must", "Consolidation & financial reporting", "Global exposure"], "locations": ["Not Specified"], "categories": ["Accounting", "Accounting Clerk / Supervisor", "Chief Accountant", "Finance / Accounting Manager"], "post_time": "2022-01-11T05:53:27Z", "salary": {"currency": "HKD", "max": 44999, "min": 35000, "period": "monthly", "term": null}, "salary_visible": true, "title_keywords": ["finance manager"], "responsibilities": ["reporting", "financial reports", "tax computation", "ad-hoc tasks", "compliance", "review", "teams", "coordinate", "communication", "financial reporting", "senior management"], "requirements": {"degrees": ["degree", "bachelor"], "majors": ["related disciplines", "finance", "accounting"], "languages": ["cantonese", "english", "mandarin"], "language_level": ["good command"], "hard_skills": ["excel", "oracle system", "word", "cpa", "pc knowledge"], "soft_skills": ["self-motivated", "communication and interpersonal skills", "independent", "work independently"], "languages_combined": [{"language": "cantonese", "language_level": ["good command"]}, {"language": "english", "language_level": ["good command"]}, {"language": "mandarin", "language_level": ["good command"]}]}, "experience_required": {"duration": ["6 years", "minimum of 3 years"], "field": ["accounting experience", "consolidation"]}}, {"job_id": "100003009020423", "location_code": "hk", "company": "Atkins China Ltd", "job_title": "Senior Accountant", "description": "Responsibilities\u00a0\u00a0\u00a0\u00a0\u00a0\u00a0\u00a0\u00a0\u00a0\u00a0\u00a0\u00a0\u00a0\u00a0\u00a0\u00a0\u00a0\u00a0\u00a0\u00a0\u00a0\u00a0\u00a0\u00a0\n\nBusiness support on project financial reviews, highlight the project risks, issuance of invoices and credit notes and following up debt status;\nMonitor sub-consultancy payments;\nAssist in month-end, year-end closing and management reports;\nConduct financial analysis for business unit performance;\nPrepare annual budget, quarterly forecast and management analysis;\nPrepare presentation and relevant materials for management meeting;\nMonitoring e-timesheet record; and\nParticipate in ad hoc projects as assigned.\n\nQualification Requirements\u00a0 \u00a0\n\nDegree in Accounting or related disciplines with professional qualifications in HKICPA/ACCA or equivalent;\nAt least 5 years relevant working experiences, preferably from MNC;\nMature, responsible and able to work under pressure;\nGood work attitude, well organized and highly systematic;\nAttentive to details and strong analytical mind;\nStrong PC skills & familiar with Microsoft Office;\nKnowledge in JDE and Hyperion would be preferred;\nGood command of spoken and written English and Chinese; and\nImmediately available is an advantage.\nCandidate with less experience will be considered as Accountant", "employment_types": ["Full Time", "Permanent"], "selling_points": ["International engineering consultancy", "Work-life balance with Five-day work week", "Multi-cultural and happy work environment"], "locations": ["Tsim Sha Tsui"], "categories": ["Accounting", "Accountant", "Chief Accountant", "Finance / Accounting Manager"], "post_time": "2022-01-05T02:36:55Z", "salary": {"currency": null, "max": null, "min": null, "period": "monthly", "term": null}, "salary_visible": false, "title_keywords": ["senior accountant"], "responsibilities": ["management", "invoices", "analysis", "budget", "monitor", "month-end", "monitoring", "financial analysis", "management reports", "payments", "ad hoc projects", "year-end closing", "forecast"], "requirements": {"degrees": ["degree"], "majors": ["related disciplines", "accounting"], "languages": ["english", "chinese"], "language_level": ["good command"], "hard_skills": ["acca", "microsoft office", "professional qualifications", "pc skills", "hkicpa"], "soft_skills": ["responsible", "attentive to details", "well organized", "systematic", "mature", "analytical mind", "work under pressure"], "languages_combined": [{"language": "english", "language_level": ["good command"]}, {"language": "chinese", "language_level": ["good command"]}]}, "experience_required": {"duration": ["at least 5 years"], "field": []}}, {"job_id": "100003009018040", "location_code": "hk", "company": "Charisma Resources Limited", "job_title": "Accountant", "description": "Duties:\n\nPreparation of monthly consolidated financial statements, regular management accounts and annual report for the company\nProper filing of the trading transactions, expense claims into XERO accounting system\nPrepare for statutory audit and tax computation\nLiaise with external auditor, banks, insurance companies on related matters\nIssue and/or supervision of the invoices and/or other shipping documents\nInteract with overseas counterparties for reconciliation and settlement\nHandle ad-hoc assignments as required\n\n\u00a0Requirements:\n\nFull set accounting experience is preferred\nProactive, independent, persistent and able to work under pressure to meet deadline with strong sense of responsibility\n3 year's relevant working experience with good knowledge of international accounting standards and practices\nGood command of both written and spoken English and Chinese (both Cantonese and Mandarin)\nCompetency in MS Excel\nExperience in XERO software is preferred\nExperience in international trading is preferred\nImmediate available is preferred\n\nWe offer competitive remuneration package with the salary HKD 15-30K depending on experience and skills, including 5-Day work, discretionary bonus, birthday leave, bank holiday.\n\nInterested parties, please send your full resume with available date and expected salary to us.", "employment_types": ["Full Time"], "selling_points": [], "locations": ["Lantau Island"], "categories": ["Accounting", "Accounting Clerk / Supervisor", "Audit", "Chief Accountant"], "post_time": "2022-01-04T02:57:36Z", "salary": {"currency": null, "max": null, "min": null, "period": "monthly", "term": null}, "salary_visible": false, "title_keywords": ["accountant"], "responsibilities": ["shipping documents", "management", "tax computation", "invoices", "ad-hoc assignments", "audit", "transactions", "financial statements", "liaise with", "insurance", "report"], "requirements": {"degrees": [], "majors": [], "languages": ["cantonese", "english", "chinese", "mandarin"], "language_level": ["good command"], "hard_skills": ["ms excel", "xero"], "soft_skills": ["independent", "sense of responsibility", "persistent", "proactive", "work under pressure"], "languages_combined": [{"language": "cantonese", "language_level": ["good command"]}, {"language": "english", "language_level": ["good command"]}, {"language": "chinese", "language_level": ["good command"]}, {"language": "mandarin", "language_level": ["good command"]}]}, "experience_required": {"duration": ["3 year"], "field": ["accounting experience", "accounting", "trading", "relevant working experience"]}}, {"job_id": "100003009032922", "location_code": "hk", "company": "HH Partners", "job_title": "Accountant/Administration", "description": "Job Responsibilities:\nYou will be responsible for\n\n\nAssist management client related coordination on company secretarial duties.\nHave responsibilities with in-house accounting related matters \u2013 accounts receivables, payables, reporting.\nOffice administrative duties.\nQualifications/Experience:\n\nHigher diploma or above obtained from a recognized tertiary qualification in a accounting or business discipline.\nAt least 4 years of hands-on accounting experience and able to complete a full set of books independently.\nHave experience in handling company secretarial duties, preferred.\nTechnology savvy and able to work with different information technology systems/processes.\u00a0\nProficient in using Office365 suite \u2013 outlook, TEAM, excel and word.\nProactive and detailed oriented.\nFast-paced and good at prioritizing and multi-tasking.\nAble to work with different time zone offices\nExcellent in command in both written and spoken English & Cantonese, fluent in Mandarin shall be an advantage.\nImmediately available \u2013 is preferable.", "employment_types": ["Full Time", "Part Time", "Permanent"], "selling_points": ["Work-life balance - 5 days work", "Flexible working hours", "Wanchai"], "locations": ["Wan Chai"], "categories": ["Accounting", "Accountant", "Audit", "Chief Accountant"], "post_time": "2022-01-08T03:09:34Z", "salary": {"currency": null, "max": null, "min": null, "period": "monthly", "term": null}, "salary_visible": false, "title_keywords": ["accountant"], "responsibilities": ["reporting", "management", "systems", "administrative duties", "coordination"], "requirements": {"degrees": ["higher diploma or above"], "majors": ["business", "accounting"], "languages": ["cantonese", "english", "mandarin"], "language_level": ["advantage", "excellent", "fluent"], "hard_skills": ["excel", "outlook", "word"], "soft_skills": ["independently", "detailed oriented", "responsible", "hands-on", "multi-tasking", "coordination", "proactive", "prioritizing"], "languages_combined": [{"language": "cantonese", "language_level": ["advantage", "excellent"]}, {"language": "english", "language_level": ["advantage", "excellent"]}, {"language": "mandarin", "language_level": ["fluent", "advantage", "excellent"]}]}, "experience_required": {"duration": ["at least 4 years"], "field": ["accounting experience", "secretarial"]}}, {"job_id": "100003009039141", "location_code": "hk", "company": "Links International", "job_title": "Head of Finance - Business Partnering, Aggressive Career!", "description": "Responsibilities:\n\nWork with senior management team and contribute to strategic planning and decision-making of the Group\nDevelop and implement finance and controlling systems & processes that align with the organization's overall vision and its business objectives\nEnsure that all financial and control disciplines in relations to transactions, policies, systems, and procedures meet the organization's short and long-term business objectives and comply with regulations, accounting principles and standards\nReview legal contracts and provide financial, accounting and tax advice to drive business initiatives forward\nOptimize the tax structure of the Group\nManage treasury activities and drive financing transactions of the Group\nProvide cost effective and innovative IT solutions and infrastructure to support the requirements of business growth and productivity improvement\nLead and coach the team to support the businesses and safeguard the Group's financial integrity\n\nRequirements:\n\nAn experienced financial executive with at least 10+ years of successful track record in a commercial environment\nBachelor degree in Accounting, Finance or related discipline\nQualified Accountant with HKICPA/ACCA or equivalent\nIn-depth knowledge of PRC GAAP and IFRS and solid big 4 background is required\nFluency in Cantonese, English and Mandarin is required\nA high degree of flexibility in adapting to a rapidly changing environment\nAbility to manage stakeholders across geographies, businesses and seniorities\nProficient in strategic and tactical thinking about the business, developing actionable business plans and demonstrating to team members how to achieve those plans", "employment_types": ["Full Time", "Permanent"], "selling_points": ["Excellent career progression", "Fast track career path", "Stock options"], "locations": ["Not Specified"], "categories": ["Accounting", "Chief Accountant", "Financial Controller", "Others"], "post_time": "2022-01-11T08:49:27Z", "salary": {"currency": null, "max": null, "min": null, "period": "monthly", "term": null}, "salary_visible": false, "title_keywords": ["head of finance"], "responsibilities": ["regulations", "tax", "control", "business initiatives", "cost", "strategic planning", "policies", "contracts", "systems", "procedures", "review", "transactions", "develop", "infrastructure", "senior management"], "requirements": {"degrees": ["degree", "bachelor"], "majors": ["finance", "accounting"], "languages": ["cantonese", "english", "mandarin"], "language_level": ["fluency"], "hard_skills": ["acca", "ifrs", "hkicpa"], "soft_skills": [], "languages_combined": [{"language": "cantonese", "language_level": ["fluency"]}, {"language": "english", "language_level": ["fluency"]}, {"language": "mandarin", "language_level": ["fluency"]}]}, "experience_required": {"duration": [], "field": []}}, {"job_id": "100003009039743", "location_code": "hk", "company": "Page Personnel", "job_title": "Accounting Officer - Reporting (HK Based Company)", "description": "This role welcomes candidate who has relevant accounting experience in a sizeable company.\n\nClient Details\n\nOur client is a HK based trading company with a diversified business across consumer goods and textile industry. As a leading company, they are currently seeking an experienced candidate as an Accountant on consolidation to join the team.\n\nDescription\n\nPrepare monthly consolidated financial statements and related schedules\nAnalyse and reconcile variance for monthly financial statements\nWork on financial reports for management's review\nReview variance reports and quarterly reconciliation for fund request\nParticipate in month-end consolidation process\nInvolve in process improvement and system enhancement consolidation process and data entries to improve the accuracy & enhance efficiency\n\nProfile\n\nBachelor's degree in Finance or Accounting, preferably with CPA qualification\nAt least 3-5 years relevant experience\nSolid experience in a sizeable company\nExcellent communication skills\nA good command of both written and spoken Chinese and English\nImmediately available is a must\n\nJob Offer\n\nReputable HK company\nERP system exposure\nSupportive working environment\n\nTo apply online please click the Apply button below. For a confidential discussion about this role please contact Iris Choi-Ching Lai on +852 3602 2490", "employment_types": ["Full Time", "Contract"], "selling_points": ["Competitive salary", "Immediate available is a must", "Fluent in English and Chinese"], "locations": ["Cheung Sha Wan"], "categories": ["Accounting", "Accountant", "Accounting Clerk / Supervisor", "Chief Accountant"], "post_time": "2022-01-11T10:51:28Z", "salary": {"currency": null, "max": null, "min": null, "period": "monthly", "term": null}, "salary_visible": false, "title_keywords": ["accounting officer"], "responsibilities": ["financial reports", "management", "data", "schedules", "review", "monthly financial statements", "month-end", "financial statements", "communication", "reports", "contact", "analyse"], "requirements": {"degrees": ["degree", "bachelor"], "majors": ["finance", "accounting"], "languages": ["english", "chinese"], "language_level": ["good command"], "hard_skills": ["cpa", "erp system"], "soft_skills": ["communication skills", "supportive"], "languages_combined": [{"language": "english", "language_level": ["good command"]}, {"language": "chinese", "language_level": ["good command"]}]}, "experience_required": {"duration": ["at least 3-5 years"], "field": ["accounting experience", "relevant experience"]}}, {"job_id": "100003009035079", "location_code": "hk", "company": "Michael Page", "job_title": "Finance Manager, 50k, PRC Education Preferred", "description": "Our client is a reputable property company. They are now looking for a talent Finance Manager to join their finance team.\n\nClient Details\n\nOur client is a reputable property company. They are now looking for a talent Finance Manager to join their finance team.\n\nDescription\n\nReporting to the GM Finance, you will be responsible for\n\nPreparing for the Main Board IPO listing for the company\nHandling company secretarial matters after IPO\nPreparing annual and interim reports\nStrengthening internal controls, corporate governance and streamline accounting procedures to comply with the Hong Kong Listing Rules / standards\nProviding recommendations to enhance financial performance and business opportunities\nLiaising with CPA firm for audit and tax related matters\n\nProfile\n\nPRC University is highly preferred\n\nExcellent communication skills (English and Mandarin)\n\nDegree Holder in Business/Accounting/Finance\n\nJob Offer\n\nMain Board IPO Experience\nCompetitive Remuneration\n\nTo apply online please click the 'Apply' button below.\nFor a confidential discussion about this role please contact Nicole Hui on +852 3412 4832.", "employment_types": ["Full Time", "Permanent"], "selling_points": ["CPA is a must", "PRC Education Preferred - 211 or 958", "13 Months Guaranteed with Bonus"], "locations": ["Not Specified"], "categories": ["Accounting", "Chief Accountant", "Finance / Accounting Manager", "Financial Controller"], "post_time": "2022-01-10T05:51:17Z", "salary": {"currency": null, "max": null, "min": null, "period": "monthly", "term": null}, "salary_visible": false, "title_keywords": ["finance manager"], "responsibilities": ["tax", "reporting", "business opportunities", "procedures", "liaising with", "audit", "communication", "reports", "finance team", "contact", "listing"], "requirements": {"degrees": ["degree holder"], "majors": ["finance", "business", "accounting"], "languages": ["english", "mandarin"], "language_level": ["excellent"], "hard_skills": ["cpa", "gm"], "soft_skills": ["communication skills", "responsible"], "languages_combined": [{"language": "english", "language_level": ["excellent"]}, {"language": "mandarin", "language_level": ["excellent"]}]}, "experience_required": {"duration": [], "field": []}}, {"job_id": "100003009034009", "location_code": "hk", "company": "Links International", "job_title": "(Senior) Finance Manager - Group Financial Reporting", "description": "Responsibilities:\n\nLead and manage a sizable team\nTimely preparation of monthly group consolidation, interim and annual report and other financial reporting functions\nAnalyze the group financial results in details and make assurance of the accuracy and quality of the financial reports\nOversee the reporting from overseas business units and ensure group accounting policies are consistently applied by business units and advise business units on compliance with the Hong Kong Listing Rules requirements\nLiaise with external auditors and professional advisors\nTake initiative to enhance internal controls, drive process improvement and operational efficiency\nAssist in system migration and implementation\nOrganize work schedules and setting priorities in order to meet critical deadlines\nAddress ad-hoc reporting requests work and participate in projects and assignments\n\nRequirements:\n\nDegree holder in Accounting, Finance or a related discipline and member of the HKICPA or a reputable accounting association\nMinimum 5 years' relevant experience gained in listed/ sizeable companies and also with professional experience in an international accounting firm is a must\nSound knowledge in HKFRS, Hong Kong Listing Rules and other financial reporting requirements relevant for a sizeable Hong Kong listed company\nProficiency in Excel, Word and PowerPoint\nFamiliar with SAP applications will be an added advantage\nExcellent command in written and spoken English and Chinese\nProactive, dynamic, good at multi-tasking and able to work independently and meet tight deadlines\nGood communication, interpersonal and analytical skills", "employment_types": ["Full Time", "Permanent"], "selling_points": ["Guaranteed 13 months salary", "Fast track career path", "All rounded and dynamic role"], "locations": ["Not Specified"], "categories": ["Accounting", "Chief Accountant", "Finance / Accounting Manager", "Financial Controller"], "post_time": "2022-01-10T02:23:14Z", "salary": {"currency": "HKD", "max": 69999, "min": 45000, "period": "monthly", "term": null}, "salary_visible": true, "title_keywords": ["finance manager"], "responsibilities": ["ad-hoc", "reporting", "financial reports", "schedules", "compliance", "quality", "implementation", "external auditors", "accounting policies", "financial reporting", "liaise with", "migration", "listing", "report"], "requirements": {"degrees": ["degree holder"], "majors": ["finance", "accounting"], "languages": ["english", "chinese"], "language_level": ["excellent"], "hard_skills": ["excel", "hkfrs", "sap", "word", "powerpoint", "analytical skills", "dynamic", "hkicpa"], "soft_skills": ["work independently", "meet tight deadlines", "analytical skills", "communication", "multi-tasking", "dynamic", "proactive", "interpersonal"], "languages_combined": [{"language": "english", "language_level": ["excellent"]}, {"language": "chinese", "language_level": ["excellent"]}]}, "experience_required": {"duration": ["minimum 5 years"], "field": ["accounting", "relevant experience"]}}, {"job_id": "100003009039591", "location_code": "hk", "company": "Page Personnel", "job_title": "Senior Accountant (HK Listed Property)", "description": "If you are looking to development your leadership skill including training, coaching and career development, it is a good chance for you to join our company to lead subordinates for completing assigned duties. Being the Senior Accountant, you are expected to handle Group Consolidation and review the Accounting Operations prepared by your team from both Property Development team and Investment team.\n\nClient Details\n\nOur client is a Hong Kong Listed Property Conglomerate with more than 30 ongoing projects over the globe as long as Asset Management and Overseas Investment. Due to the expansion, we are seeking an experience candidate to lead our team for further business expansion.\n\nDescription\n\nSitting in the Holding reporting team:\nResponsible for the consolidated financial statements and monthly management reporting\nHandle the financial analysis and forecast reports\nSupport system implementation project (Financial and ERP project)\nParticipate in ad hoc projects assigned by senior management\n\nProfile\n\nBachelor Degree in accounting or finance, with HKICPA or equivalent qualification is an advantage\n5 years of accounting experience, PRC accounting experience is preferred\nKnowledge in Hong Kong Financial Reporting Standards (IFRS) and other regulatory rules\nStrong skills in Excel spreadsheet. Knowledge in SAP is preferred\nSelf-initiative, excellent analytical and interpersonal skills\nFluent in Chinese (Cantonese and Mandarin) & English\n\nJob Offer\n\nWe are offering the right candidate with an attractive package.\n\nGuaranteed 13 months\nUp to 2 months bonus\n15 days annual leave", "employment_types": ["Full Time", "Permanent"], "selling_points": ["Leadership exposure", "HK$ 30,000 - 38,000 per month", "Location: Wan Chai"], "locations": ["Wan Chai Area"], "categories": ["Accounting", "Accountant", "Chief Accountant"], "post_time": "2022-01-11T10:10:29Z", "salary": {"currency": null, "max": null, "min": null, "period": "monthly", "term": null}, "salary_visible": false, "title_keywords": ["senior accountant"], "responsibilities": ["reporting", "lead subordinates", "operations", "review", "implementation", "financial statements", "financial analysis", "reports", "management reporting", "forecast", "career development", "ad hoc projects", "financial reporting", "senior management", "asset management"], "requirements": {"degrees": ["degree", "bachelor"], "majors": ["finance", "accounting"], "languages": ["cantonese", "english", "chinese", "mandarin"], "language_level": ["fluent"], "hard_skills": ["excel", "ifrs", "sap", "erp", "financial analysis", "prc accounting", "system implementation", "spreadsheet", "hkicpa"], "soft_skills": ["leadership skill", "self-initiative", "responsible", "interpersonal skills"], "languages_combined": [{"language": "cantonese", "language_level": ["fluent"]}, {"language": "english", "language_level": ["fluent"]}, {"language": "chinese", "language_level": ["fluent"]}, {"language": "mandarin", "language_level": ["fluent"]}]}, "experience_required": {"duration": ["5 years"], "field": ["accounting experience", "business", "team"]}}, {"job_id": "100003009017204", "location_code": "hk", "company": "Multiable Company", "job_title": "Accounting Manager (Hong Kong & Singapore)", "description": "Responsibilities:\n\nTo assist in overseeing and preparing month end accounts closing and consolidation, financial and management report, forecast and financial analysis;\nTo liaise with auditors, tax representatives and professionals regarding audit, tax and other relevant matters;\nTo work closely with the Singapore team to ensure all transactions are recognized accurately and timely;\nTo co-ordinate with operation and internal IT teams on daily operations and to help solving work related issues;\nTo handle tax filing;\nTo assist in company secretarial matters; and\nTo work with development team to enhance the financial consolidation system\nTo handle ad hoc assignment as requested.\n\nRequirements:\n\nUniversity graduate in Finance or Accounting with professional accounting qualification;\nMinimum 2 years working experience, with Big 4 background;\nSolid experience in Singapore IRAS compliance is an advantage;\nOut-going, independent, self-motivated, strong interpersonal and communication skills, can work under pressure;\nExcellent command of written and spoken English and Cantonese;\nInfrequent travel to Singapore is required;\nCandidates who have less experience will be considered as Accountant.", "employment_types": ["Full Time"], "selling_points": ["Fast Growing Firm", "5-Days Work", "Creative and Dynamic Culture"], "locations": ["Wan Chai"], "categories": ["Accounting", "Accountant", "Chief Accountant", "Finance / Accounting Manager"], "post_time": "2022-01-03T11:10:04Z", "salary": {"currency": null, "max": null, "min": null, "period": "monthly", "term": null}, "salary_visible": false, "title_keywords": ["accounting manager"], "responsibilities": ["tax", "co-ordinate with", "ad hoc assignment", "tax filing", "teams", "audit", "transactions", "financial analysis", "daily operations", "forecast", "liaise with", "management report"], "requirements": {"degrees": ["university graduate"], "majors": ["finance", "accounting"], "languages": ["cantonese", "english"], "language_level": ["excellent"], "hard_skills": [], "soft_skills": ["communication skills", "self-motivated", "independent", "interpersonal", "work under pressure"], "languages_combined": [{"language": "cantonese", "language_level": ["excellent"]}, {"language": "english", "language_level": ["excellent"]}]}, "experience_required": {"duration": ["minimum 2 years"], "field": ["compliance", "big 4"]}}, {"job_id": "100003009038446", "location_code": "hk", "company": "Links International", "job_title": "(Senior) Financial Analyst - Retail, Work Life Balance!", "description": "Responsibilities:\n\nSupport preparation of budget and forecast for APAC Markets\nAssist manager to drive budget/forecast process, support for all FP&A activities\nExecute business performance analytics including store opening, investment/divestment, capital budgeting, and inventory planning\nSupport and partner with cross-function units on key business initiatives and projects at the local and regional level\nAssist with Retail KPI project, data mining and business intelligence\nAnalyse financial and business data, identifying trends and perform variances analysis\nPrepare consolidated management reports and decks for senior management\nAssist in ongoing process improvement and driving standardization and efficiencies\n\nRequirements:\n\nDegree holder in Finance & Accounting or related disciplines\nMinimum 3 years' experience in FP&A, preferably in MNC and experienced in retail business/ distributors model and regional markets\nStrong knowledge and skills in financial analysis and planning, good problem-solving skills, high level of details and accuracy\nStrong business partnership capabilities and commercial sense; self driven and willing to take initiative\nGood communication and interpersonal skills, good team player under multi-cultural environment, strong work ethic and integrity\nStrong spreadsheet and analysis skills\nHands-on experience in using large ERP system will be an advantage\nStrong command of spoken and written English", "employment_types": ["Full Time", "Permanent"], "selling_points": ["Guaranteed 13 months salary", "MNC & flexible work culture", "Global exposure"], "locations": ["Not Specified"], "categories": ["Accounting", "Accountant", "Chief Accountant", "Financial Analyst"], "post_time": "2022-01-11T06:54:28Z", "salary": {"currency": "HKD", "max": 44999, "min": 30000, "period": "monthly", "term": null}, "salary_visible": true, "title_keywords": ["financial analyst"], "responsibilities": ["inventory planning", "business initiatives", "forecast process", "data", "budgeting", "analysis", "budget", "management reports", "forecast", "data mining", "senior management", "analyse"], "requirements": {"degrees": ["degree holder"], "majors": ["related disciplines", "finance", "accounting"], "languages": ["english"], "language_level": [], "hard_skills": ["analysis", "financial analysis", "erp system", "problem-solving skills", "spreadsheet"], "soft_skills": ["good team player", "driven", "integrity", "hands-on", "communication and interpersonal skills", "work ethic", "problem-solving skills", "initiative"], "languages_combined": [{"language": "english", "language_level": []}]}, "experience_required": {"duration": ["minimum 3 years"], "field": ["business", "erp system", "retail"]}}, {"job_id": "100003009037935", "location_code": "hk", "company": "Magic Search Limited", "job_title": "Senior Accounts Clerk  (Fashion Brands)", "description": "Our client is a Fashion brands distributor that carry wide range of products and expand their business rapidly . Their shops locate in prestigious business area. To cope with their business expansion, they are looking for a Senior Accounts Clerk\u00a0to join the team.\n\nKey Responsibilities:\n\nAssist in Full Set of Accounting functions (AR, AP, GL)\nSupport for month-end closing, accounts reconciliation and journal entries.\nAssist in management regular & ad-hoc reports and analysis.\nPrepare and review tax computation and audit schedules.\nAssist in other daily accounting duties and other ad hoc assignment as required.\n\nRequirements:\n\nDegree holder\u00a0in accountancy or similar discipline, qualified HKICPA / ACCA.\nMinimum 2 years experience in accounting, retail industry is preferable.\nGood communication skills, pro-active with strong financial judgment and problem-solving ability.\nAble to perform multi-tasks with prioritization skills, to work under pressure in meeting deadlines and attentive to details.\nPreferably SAP and proficiency in MS applications (conversant with application of Excel formulas is definite an advantage).\nFluent in both written and spoken English and Chinese\n\nAll information provided will be treated in strict confidence and used solely for recruitment purposes. To apply, please quote current and expected salary and send your CV through \" APPLY NOW\"", "employment_types": ["Full Time", "Permanent"], "selling_points": ["Fashion Brand", "2 years relevant working experience", "preferably retail background"], "locations": ["Not Specified"], "categories": ["Accounting", "Accountant", "Accounting Clerk / Supervisor", "Chief Accountant"], "post_time": "2022-01-11T04:19:42Z", "salary": {"currency": null, "max": null, "min": null, "period": "monthly", "term": null}, "salary_visible": false, "title_keywords": ["senior accounts clerk"], "responsibilities": ["ap", "ad-hoc", "management", "ar", "tax computation", "schedules", "analysis", "review", "ad hoc assignment", "audit", "full set of accounting", "month-end closing", "journal entries", "reports", "daily accounting"], "requirements": {"degrees": ["degree holder"], "majors": ["accountancy"], "languages": ["english", "chinese"], "language_level": ["fluent"], "hard_skills": ["excel", "acca", "ms applications", "sap", "problem-solving", "hkicpa"], "soft_skills": ["communication skills", "confidence", "multi-tasks", "attentive to details", "problem-solving", "pro-active", "work under pressure"], "languages_combined": [{"language": "english", "language_level": ["fluent"]}, {"language": "chinese", "language_level": ["fluent"]}]}, "experience_required": {"duration": ["minimum 2 years"], "field": ["retail industry", "accounting"]}}, {"job_id": "100003009032625", "location_code": "hk", "company": "JPC Texson Limited", "job_title": "SENIOR FINANCE MANAGER (55K-70K)  - HK listed entertainment business", "description": "\n\nTHE COMPANY :\n\nHK listed company\nInvestment holding company principally engaged in entertainment business\nWe are looking for\u00a0\u00a0 SENIOR FINANCE MANAGER - with details as follows :\u00a0\nTHE JOB :\nReport to Executive Director\nLead Finance team of 3-4 Accountants\nManage all aspects of accounting functions to perform daily accounting operation, management account and improve structure and quality of accounting information.\nWork closely with the team to formulate and implement accounting and internal control policies and procedures.\nExecute on-going review and enhancement on accounting workflows.\nManage cash flow, ensure adequate funding for operating expenses.\nCo-ordinate the compilation of all relevant corporate taxation returns, company secretary and statutory financial reporting.\nLiaise with external auditors, banks and other departments of the Group.\nAnalyze financial data, communicate findings and recommendations to management.\nResponsible for year budgeting, monthly/ quarterly forecasting.\nEvaluate business proposal and support on ad hoc assignments.\nBachelor degree in Finance or Accounting.\nQualified member of ACCA, HKICPA or equivalent.\nMinimum of six years\u2019 relevant experience in financial reporting or management reporting.\nSolid experience in HK listed companies\nHigh level of analytical and quantitative ability required to perform budgeting/ forecasting support, financial/ accounting management and ad hoc reporting functions, including proficiency with computer-based modeling and analytic techniques.\nWell experience on improvement of internal procedure and control.\nCapability to manage change and implement process improvement is essential.\nProficiency in MS Office applications including Word, Excel, PowerPoint, Outlook and Chinese Word Processing.\n5 days work\nAnnual leave : 12 days\nMedical benefit\nLife insurance benefit\nTO APPLY for this job or similar jobs :\n\n\u00a0\nFor secure and confidential job application, please click the below link to get our email address.\n\u00a0\nhttp://jpc.hk/confidential_apply.htm\n\u00a0\n\u00a0\nWe provide free job hunting services to job seekers.\n\u00a0\nTo speed up our process, please do NOT send us download links.\n\u00a0\nPersonal data provided by job applicants will be used for recruitment purpose only.\n\u00a0\nYour privacy is guaranteed. We will never give out, lease, or sell your personal information.\n\u00a0\nJPC Recruiting Services was established in 1990.\n\u00a0\nhttp://www.facebook.com/pages/JPC-Texson-Ltd/500356593325952\n\n\n\n", "employment_types": ["Full Time", "Permanent"], "selling_points": ["Degree Finance/Accounting & Qualified Accountant", "HK listed co exp ; lead a team of 3-4 Accountants", "Report to Executive Director"], "locations": ["Kwun Tong Area"], "categories": ["Accounting", "Chief Accountant", "Finance / Accounting Manager", "Financial Controller"], "post_time": "2022-01-07T11:55:58Z", "salary": {"currency": null, "max": null, "min": null, "period": "monthly", "term": null}, "salary_visible": false, "title_keywords": ["senior finance manager"], "responsibilities": ["data", "budgeting", "quality", "liaise with", "internal control", "control", "ad hoc", "expenses", "finance team", "forecasting", "report", "reporting", "management", "review", "procedures", "cash flow", "management reporting", "taxation", "policies", "evaluate", "financial reporting", "ad hoc assignments", "daily accounting", "insurance", "external auditors"], "requirements": {"degrees": ["degree", "bachelor"], "majors": ["finance", "accounting"], "languages": ["chinese"], "language_level": ["proficiency"], "hard_skills": ["excel", "acca", "chinese word processing", "word", "powerpoint", "internal control", "outlook", "ms office", "hkicpa"], "soft_skills": ["responsible"], "languages_combined": [{"language": "chinese", "language_level": ["proficiency"]}]}, "experience_required": {"duration": ["minimum of six years"], "field": ["management", "relevant experience", "financial"]}}, {"job_id": "100003009019776", "location_code": "hk", "company": "Moore Associates Limited", "job_title": "MNC in Hong Kong \u2013 Assistant Finance Manager/ Finance Manager", "description": "The company is a well-established lifestyle brand in Europe and now looking to grow and expand in Asia with the right candidate in the Asia Office.\n\nJob Responsibilities\n\nReport to the Head of the regional office for Asia to oversee and manage the finance and accounting function of the region (Station in Hong Kong)\nResponsible for daily accounting operation including treasury, A/P, A/R, costing, GL, invoicing, bank reconciliations\nPrepare regular reporting package such as monthly full-set accounting, financial reporting, management reporting, cashflow statements, group reporting, segment report, using the in-house finance module ERP system\nWork with and report to the GM directly on annual budget and forecast\nIdentify accounting and financial issues, communicate potential impact and recommendations to the GM.\nLiaise with external firm to handle annual audit, tax filing and assist in reviewing finance and accounting work\nReview internal controls and improve overall efficiency of finance functions\nFollow up with customers on overdue payment status\nAd-hoc jobs related to accounting\n\nSuccessful Applicant\n\nUniversity graduate, preferably in finance and accounting, with professional accounting qualification\nAt least 5 years of relevant experience in handling full sets of accounting, budget and forecast, analyst, financial reporting, group reporting with commercial experience\nExperience in retail / fashion wholesale industry is advantageous, but not a must\nProficiency in MS applications, such as Word, Excel and PowerPoint with hands-on experience in finance module ERP system is an advantage\nA good team player who is pro-active and able to work independently\nStrong analytical, communication and interpersonal skills\nExcellent command of English, Cantonese and Mandarin\n\nWe offer a 5-day working week, a competitive remuneration package and generous fringe benefits.\u00a0\n\nInterested candidates please send the full resume with current and expected salary\u00a0by clicking the \"Apply Now\" button\n\nFor more information, please visit our website www.carhartt-wip.com.", "employment_types": ["Full Time", "Permanent"], "selling_points": ["Lifestyle brand in Europe", "Manage the finance and accounting function", "Prepare regular reporting package"], "locations": ["Tsim Sha Tsui"], "categories": ["Accounting", "Accountant", "Chief Accountant", "Others"], "post_time": "2022-01-04T08:41:34Z", "salary": {"currency": null, "max": null, "min": null, "period": "monthly", "term": null}, "salary_visible": false, "title_keywords": ["assistant finance manager", "finance manager"], "responsibilities": ["ad-hoc", "reporting", "annual audit", "budget", "tax filing", "bank reconciliations", "review", "invoicing", "communication", "payment", "financial reporting", "management reporting", "forecast", "liaise with", "daily accounting", "report"], "requirements": {"degrees": ["university graduate"], "majors": ["finance", "accounting"], "languages": ["cantonese", "english", "mandarin"], "language_level": ["excellent"], "hard_skills": ["excel", "ms applications", "word", "powerpoint", "erp system", "gm", "r"], "soft_skills": ["good team player", "work independently", "responsible", "hands-on", "communication and interpersonal skills", "pro-active"], "languages_combined": [{"language": "cantonese", "language_level": ["excellent"]}, {"language": "english", "language_level": ["excellent"]}, {"language": "mandarin", "language_level": ["excellent"]}]}, "experience_required": {"duration": ["at least 5 years"], "field": ["finance", "commercial", "erp system", "relevant experience", "accounting", "retail", "financial"]}}, {"job_id": "100003009035056", "location_code": "hk", "company": "Michael Page", "job_title": "Senior Accountant, Engineering, 36k (Big 10 welcome)", "description": "Our client is a reputable engineering company. To cope with their business needs, they are now looking for a talented Senior Accountant to join their finance team.\n\nClient Details\n\nOur client is a reputable engineering company. To cope with their business needs, they are now looking for a talented Senior Accountant to join their finance team.\n\nDescription\n\nReporting to the CFO in Hong Kong, you will be responsible for:\n\nensuring accurate financial and management reports\nperforming a full spectrum of accounting and finance duties\ntaking part in business partnering and providing financial advice for better business outcomes\n\nProfile\n\nDegree Holder in Business/Accounting/Finance\nQualified is a must\nBig 8 are welcome\nExcellent communication skills (English and Mandarin) is a must\n\nJob Offer\n\nCompetitive remuneration\nFast and dynamic business growth\nReputable company\n\nTo apply online please click the 'Apply' button below.\nFor a confidential discussion about this role please contact Nicole Hui on +852 3412 4832.", "employment_types": ["Full Time", "Permanent"], "selling_points": ["Fluent Mandarin and English is a must", "CPA firm is a must", "Attractive package with promising career prospect"], "locations": ["Not Specified"], "categories": ["Accounting", "Chief Accountant", "Finance / Accounting Manager", "Others"], "post_time": "2022-01-10T05:41:21Z", "salary": {"currency": null, "max": null, "min": null, "period": "monthly", "term": null}, "salary_visible": false, "title_keywords": ["senior accountant"], "responsibilities": ["reporting", "finance duties", "communication", "management reports", "finance team", "contact"], "requirements": {"degrees": ["degree holder"], "majors": ["finance", "business", "accounting"], "languages": ["english", "mandarin"], "language_level": ["excellent"], "hard_skills": ["management reports", "dynamic"], "soft_skills": ["communication skills", "dynamic", "accurate", "responsible"], "languages_combined": [{"language": "english", "language_level": ["excellent"]}, {"language": "mandarin", "language_level": ["excellent"]}]}, "experience_required": {"duration": [], "field": []}}, {"job_id": "100003009027671", "location_code": "hk", "company": "Linkers International Limited", "job_title": "Senior Accountant - European Fashion Brand - Up to 32k", "description": "Our client:\u00a0\nOur client is an European Fashion Brand.\n\nBenefits:\n\nPerformance Bonus\nMedical Insurance\nDental Insurance\n12 AL\n5 days work\n\n\nResponsibilities:\u00a0\n\nOversee HK finance team and logistics team\nAssist in preparing full set of accounts and other general accounting work\nReview accounts payables, accounts receivable and accruals schedules\nAssist in preparing monthly consolidated financial reports, management reports, financial analysis and business information for the Group\nHandle month-end closings, yearly budget and rolling forecast\nAssist in the treasury function e.g. cash management, fixed deposits, loan and forex transactions etc.\nLiaise with external auditors and other ad hoc projects, such as system implementation or process improvement\n\n\nRequirements:\n\nDegree holder in Accounting, Finance or similar discipline\nAt least 5 years\u2019 relevant accounting experience in sizeable company, preferably from FMCG or Retail industry and e-commerce\nSound knowledge of up-to-date accounting standards and able to meet compliance requirements\nProficiency in Microsoft office applications\u00a0\nFlexible, hands-on, strong analytical, problem solving and communication skill", "employment_types": ["Full Time", "Permanent"], "selling_points": ["MNC", "Non CPA / CPA welcome", "Team leader"], "locations": ["Not Specified"], "categories": ["Accounting", "Accountant", "Accounting Clerk / Supervisor", "Chief Accountant"], "post_time": "2022-01-06T11:01:13Z", "salary": {"currency": null, "max": null, "min": null, "period": "monthly", "term": null}, "salary_visible": false, "title_keywords": ["senior accountant"], "responsibilities": [], "requirements": {"degrees": [], "majors": [], "languages": [], "language_level": [], "hard_skills": [], "soft_skills": [], "languages_combined": []}, "experience_required": {"duration": [], "field": []}}, {"job_id": "100003009031033", "location_code": "hk", "company": "Kingsway Personnel Ltd", "job_title": "Senior Accounting Assistant ~24k", "description": "Employment Ref: MA09488\n\nNature of Business: Renowned Japanese Manufacturing Company\nLocation: Shatin Area\nWorking Days: 5 days\n\nBenefits:\n- Double pay\n- Transportation Allowance\n- Overtime allowance\n- Medical insurance\n\nRequirements:\n- Degree holder, good command of English and Mandarin\n- Min. 5yrs full set acct exp. in manufacturing/trading co.\n- Working exp. in Japanese co. will be highly preferred\n\nDuties:\n- Handle full set accounting duties e.g.: monthly and yearly reports, budgeting and forecast\n- Assist in yearend audit\n\nInterested in the above vacancy?\u00a0 Send your resume to us NOW!\n\nOnly short-listed candidates will be notified. Personal data collected will be used for recruitment purpose only", "employment_types": ["Full Time", "Permanent"], "selling_points": ["Min. 5yrs full set acct in manuf./trading co.", "Reports, budgeting and assist in audit", "~24K, double pay, OT allowance, transportation"], "locations": ["Shatin Area"], "categories": ["Accounting", "Accountant", "Accounting Clerk / Supervisor", "Chief Accountant"], "post_time": "2022-01-07T19:20:23Z", "salary": {"currency": null, "max": null, "min": null, "period": "monthly", "term": null}, "salary_visible": false, "title_keywords": ["accounting assistant"], "responsibilities": [], "requirements": {"degrees": [], "majors": [], "languages": [], "language_level": [], "hard_skills": [], "soft_skills": [], "languages_combined": []}, "experience_required": {"duration": [], "field": []}}, {"job_id": "100003009032955", "location_code": "hk", "company": "ConnectedGroup Limited", "job_title": "Regional Senior Accountant, MNC", "description": "Regional Senior Accountant\n\nOur client is a world-leading company with a strong presence in Hong Kong. They are looking for a hands-on and independent Senior Accountant to join their dynamic team.\n\nMNC experience is a must\nMin. 5 years exp in Big4/2nd tier + Commercial\nAttractive benefits package\n\nResponsibilities:\n\nResponsible for financial closing for the APAC entities and ensuring the financial record is in full compliance with IFRS and GAAP requirements\nHandle full sets of accounts for the Group, month-end closing, and daily accounting functions\nLiaise with interdepartmental, cross-functional personnel and regional parties\nPrepare monthly and annual consolidation of various global entities and ensure the integrity and reliability of financial reporting\nFacilitate internal and external audit and tax compliance in accordance with statutory requirements\nAssistant in finance policy review, process improvement, and internal control improvements\nAny ad hoc duties as assigned by Management\n\nRequirements:\n\nBachelor's in Accounting or equivalent\nMinimum 5 years relevant experience, preferably with CPA firms & multinational companies background\nExperienced in all-rounded finance experiences such as month-end closing, internal control, and reporting\nProactive, meticulous, multi-tasking, and able to work independently, efficiently, and under pressure in a demanding and fast-paced environment\n\nInterested parties, please send your CV to Ivy Yeung Ivy.Yeung@connectedgroup.com for more details. For other available opportunities, please visit www.connectedgroup.com.", "employment_types": ["Full Time", "Permanent"], "selling_points": ["MNC experience is a must", "Min. 5 years exp in Big4/2nd tier + Commercial", "Attractive benefits package"], "locations": ["Not Specified"], "categories": ["Accounting", "Accountant", "Accounting Clerk / Supervisor", "Chief Accountant"], "post_time": "2022-01-08T04:00:51Z", "salary": {"currency": null, "max": null, "min": null, "period": "monthly", "term": null}, "salary_visible": false, "title_keywords": ["senior accountant"], "responsibilities": [], "requirements": {"degrees": [], "majors": [], "languages": [], "language_level": [], "hard_skills": [], "soft_skills": [], "languages_combined": []}, "experience_required": {"duration": [], "field": []}}, {"job_id": "100003009033161", "location_code": "hk", "company": "Ambition", "job_title": "Assistant Manager/Manager (Finance Department)", "description": "The Company\n\nOur client is a market leading material manufacturing company. They operate in 29 countries, have more than 40,000 employees around the world. They are now hiring an assistant manager who will report to a Japanese vision manager. This role will be working closely with Japan and China team.\n\nResponsibilities:\n\n\nLead staff in performing full sets of accounts\nSupport supervisor and liaise with the group's accounting teams in overall financial planning & business analysis, consolidation, budget control, cash flow management, tax reporting & operation review\nCoordinate with external auditors in annual statutory audit, tax filing and company secretarial matters\nReview existing financial policies and develop effective control procedures for costing and operations\nPerform any assigned ad-hoc projects\n\n\nRequirements:\n\n\nBachelor's degree in accounting or related disciplines\nMinimum 5-8 years of relevant experience gained from manufacturing company\nPRC Accounting and financing experience is preferred\nExcellent Japanese language skill (Prefer JLPT Level 1)\nExcellent in both written and spoken English, Cantonese and Mandarin\nProficiency in MS Excel and knowledge in ERP system\nHKICPA or equivalent professional qualification is preferable\nHands on audit and company secretarial experience are desirable\nProactive, responsible, well-organized, detail-oriented and able to meet tight deadline\nA good team player with excellent interpersonal and communication skills\nCandidates with more experience will be considered as Manager\n\nInterested parties please contact Bella to at bella.to@ambition.com.hk or call at 3103 4368 or click APPLY NOW quoting reference number # 253108 - Assistant Finance Manager\n\n\nIf this job isn't quite right for you, but you know someone who would be great at this role, why not take advantage of our referral scheme? We offer HKD1000 in Apple gift cards for every referred candidate who we place in a role. Terms & Conditions Apply. https://www.ambition.com.hk/refer-a-friend", "employment_types": ["Full Time", "Permanent"], "selling_points": ["Regional Role", "Japanese Speaking", "Manufacturing Firm Experience"], "locations": ["Not Specified"], "categories": ["Accounting", "Accountant", "Chief Accountant", "Finance / Accounting Manager"], "post_time": "2022-01-08T11:57:53Z", "salary": {"currency": "HKD", "max": 44999, "min": 30000, "period": "monthly", "term": null}, "salary_visible": true, "title_keywords": ["assistant manager", "manager"], "responsibilities": ["operations", "financial policies", "planning", "liaise with", "ad-hoc projects", "budget control", "control", "tax filing", "teams", "develop", "reporting", "management", "review", "coordinate with", "procedures", "cash flow", "annual statutory audit", "tax", "business analysis", "external auditors"], "requirements": {"degrees": ["degree", "bachelor"], "majors": ["related disciplines", "accounting"], "languages": ["cantonese", "japanese", "english", "mandarin"], "language_level": ["excellent"], "hard_skills": ["hkicpa", "ms excel", "erp system", "prc accounting"], "soft_skills": ["communication skills", "good team player", "responsible", "well-organized", "detail-oriented", "hands on", "meet tight deadline", "proactive", "interpersonal"], "languages_combined": [{"language": "cantonese", "language_level": ["excellent"]}, {"language": "japanese", "language_level": ["excellent"]}, {"language": "english", "language_level": ["excellent"]}, {"language": "mandarin", "language_level": ["excellent"]}]}, "experience_required": {"duration": ["minimum 5-8 years"], "field": ["secretarial", "manufacturing", "financing", "audit", "relevant experience", "accounting"]}}, {"job_id": "100003009035064", "location_code": "hk", "company": "Michael Page", "job_title": "Assistant Finance Manager, Retail, 45k", "description": "Our client is a well-established retail company. They are now looking for a talent Assistant Finance Manager to join their company.\n\nClient Details\n\nOur client is a well-established retail company. They are now looking for a talent Assistant Finance Manager to join their company.\n\nDescription\n\nReporting to the Financial Manager, you will be\n\npreparing and reviewing the full sets of account\npreparing the financial reports\nconsolidating the financial and management accounts reporting for the country\nhelping to streamline the financial operations\nreviewing the cash flow forecasting, budgeting and management\nperforming other adhoc tasks\n\nProfile\n\nDegree Holder in Business/Accounting/Finance\nRetail industry is a must\nCPA qualification is a must\nExcellent communication skills (English and Mandarin)\n\nJob Offer\n\n* Competitive remuneration\n* Fast and dynamic business growth\n* Reputable company\n\nTo apply online please click the 'Apply' button below.\nFor a confidential discussion about this role please contact Nicole Hui on +852 3412 4832.", "employment_types": ["Full Time", "Permanent"], "selling_points": ["Retail is a must", "Good English is highly preferred", "CPA Qualified is a must"], "locations": ["Not Specified"], "categories": ["Accounting", "Audit", "Chief Accountant", "Finance / Accounting Manager"], "post_time": "2022-01-10T05:45:17Z", "salary": {"currency": null, "max": null, "min": null, "period": "monthly", "term": null}, "salary_visible": false, "title_keywords": ["assistant finance manager"], "responsibilities": ["reporting", "financial reports", "management", "operations", "budgeting", "accounts reporting", "communication", "cash flow", "contact", "forecasting"], "requirements": {"degrees": ["degree holder"], "majors": ["finance", "business", "accounting"], "languages": ["english", "mandarin"], "language_level": ["excellent"], "hard_skills": ["cpa", "dynamic"], "soft_skills": ["communication skills", "dynamic"], "languages_combined": [{"language": "english", "language_level": ["excellent"]}, {"language": "mandarin", "language_level": ["excellent"]}]}, "experience_required": {"duration": [], "field": []}}, {"job_id": "100003009035075", "location_code": "hk", "company": "Michael Page", "job_title": "(Assistant) Finance Manager, Japanese Speaking N1, 45k", "description": "Our client is a well-established Japan listed company. They are now looking for a talent (Assistant) Finance Manager to join their company.\n\nClient Details\n\nOur client is a well-established Japan listed company. They are now looking for a talent (Assistant) Finance Manager to join their company.\n\nDescription\n\nReporting to the GM Finance, you will be\n\npreparing and reviewing the full sets of account\npreparing the financial reports\nconsolidating the financial and management accounts reporting for the region\nhelping to streamline the financial operations\nreviewing the cash flow forecasting, budgeting and management\nperforming other adhoc tasks\n\nProfile\n\nDegree Holder in Business/Accounting/Finance\nJapanese N1 Level is a must\n\nJob Offer\n\n* Competitive remuneration\n* Fast and dynamic business growth\n* Reputable company\n\nTo apply online please click the 'Apply' button below.\nFor a confidential discussion about this role please contact Nicole Hui on +852 3412 4832.", "employment_types": ["Full Time", "Permanent"], "selling_points": ["Japanese Speaking N1 is a must", "Japan Listed Firm", "Great career progresion"], "locations": ["Not Specified"], "categories": ["Accounting", "Audit", "Chief Accountant", "Finance / Accounting Manager"], "post_time": "2022-01-10T05:50:17Z", "salary": {"currency": null, "max": null, "min": null, "period": "monthly", "term": null}, "salary_visible": false, "title_keywords": ["finance manager", "assistant"], "responsibilities": ["reporting", "financial reports", "management", "operations", "budgeting", "accounts reporting", "cash flow", "contact", "forecasting"], "requirements": {"degrees": ["degree holder"], "majors": ["finance", "business", "accounting"], "languages": ["japanese"], "language_level": [], "hard_skills": ["gm", "dynamic"], "soft_skills": ["dynamic"], "languages_combined": [{"language": "japanese", "language_level": []}]}, "experience_required": {"duration": [], "field": []}}, {"job_id": "100003009022737", "location_code": "hk", "company": "Koon Loi Company Limited", "job_title": "Accountant/Assistant Accountant", "description": "Job Responsibility:\u00a0 \u00a0 \u00a0 \u00a0 \u00a0 \u00a0 \u00a0 \u00a0 \u00a0 \u00a0 \u00a0 \u00a0 \u00a0 \u00a0 \u00a0 \u00a0 \u00a0 \u00a0 \u00a0 \u00a0 \u00a0 \u00a0 \u00a0 \u00a0 \u00a0 \u00a0 \u00a0 \u00a0 \u00a0 \u00a0 \u00a0 \u00a0 \u00a0 \u00a0 \u00a0 \u00a0 \u00a0 \u00a0 \u00a0 \u00a0 \u00a0 \u00a0 \u00a0 \u00a0\u00a0\n\nHandle full set of accounts\nAssist finance managers for daily routine accounting duties\u00a0\nDaily data entry to maintain accounting/inventory journals, ledgers and other records\nComplete and process invoices and reports\nHandle accounts payable & receivable\nPrepare bank reconciliation/receipts, reporting and balancing\nYear-end audit/taxation preparation\nAssist in general administration duties if necessary\nAd-hoc tasks as required\n\nJob\u00a0Requirement:\n\nDegree holder in Accounting and student member of HKICPA/ACCA preferred\n3 to 5 years of working experience in finance/accounting/audit would be highly preferred\nSolid financial accounting and reporting experience\nGood command in spoken and written of English and Chinese\nProactive, well organized, detail-minded, independence, hardworking, self-motivated\nProficient in MS Office applications and general accounting system\nProficient in Word, Excel and Chinese word processing\nImmediate availability is highly preferred\nWorking location: Shatin area\nCandidates with less experience will be considered for the position of Assistant Accountant.", "employment_types": ["Full Time"], "selling_points": [], "locations": ["Shatin Area"], "categories": ["Accounting", "Accountant", "Accounting Clerk / Supervisor", "Chief Accountant"], "post_time": "2022-01-05T06:25:25Z", "salary": {"currency": null, "max": null, "min": null, "period": "monthly", "term": null}, "salary_visible": false, "title_keywords": ["accountant", "assistant accountant"], "responsibilities": ["reporting", "year-end", "taxation", "invoices", "receipts", "data entry", "inventory", "full set of accounts", "ad-hoc tasks", "bank reconciliation", "audit", "maintain", "reports", "accounting duties", "accounts payable", "administration"], "requirements": {"degrees": ["degree holder"], "majors": ["accounting"], "languages": ["english", "chinese"], "language_level": ["good command", "proficient"], "hard_skills": ["excel", "acca", "chinese word processing", "word", "hkicpa", "accounting system", "ms office"], "soft_skills": ["detail-minded", "self-motivated", "well organized", "proactive", "hardworking"], "languages_combined": [{"language": "english", "language_level": ["good command"]}, {"language": "chinese", "language_level": ["good command", "proficient"]}]}, "experience_required": {"duration": ["3 to 5 years"], "field": ["finance", "accounting", "audit", "financial"]}}, {"job_id": "100003009029236", "location_code": "hk", "company": "Tricor Staffing Solutions Limited", "job_title": "(Senior) Accounting Manager - Sizeable & Well-known Japanese Retail F&B Company", "description": "About the job\n\n(Senior) Accounting Manager - Sizeable & Well-known Japanese Retail / F&B Company\n\nOur client is one of the sizeable and well-known Japanese Retail / F&B Company and they are looking for (Senior) Accounting Manager to join their professional team and support the general accounting functions.\n\n\u00b7 Solid experience in general accounting for retail business\n\n\u00b7 5 years\u2019 experience in Supervisory level\n\n\u00b7 HKICPA / ACCA / equivalent qualifications\n\nJob Description:\n\nOversee and manage the general accounting functions, including, but not limited to: accounts payable, accounts receivable, general ledger, and taxes\nHelp with quarterly and year-end financial audit activities and the annual corporate financial controls audit\nAssess current practices and procedures, and make recommendations for improvements\nPrepare, review, and analyze financial statements to ensure accuracy and completeness\nPerform ad hoc analysis and projects as requested\nSupervise and/or manage general ledger accounting functions\nDevelop staff by managing performance, setting goals, providing ongoing training, and maintaining strong employee relationships\nWork with external auditors to ensure correct and timely closing and reporting at year-end\n\nJob Requirements\n\nBachelor degree in Accounting or relevant disciplines\nMinimum 7 years' relevant working experience in which at least 5 years in supervisory level in Retail/ F&B business\nHKICPA or equivalent qualification is a must\nSolid experience in General Accounting for retail business\nStrong interpersonal and organizational skills\nProficient in both written and spoken English and Chinese", "employment_types": ["Full Time", "Permanent"], "selling_points": [], "locations": ["Tsim Sha Tsui"], "categories": ["Accounting", "Accountant", "Chief Accountant", "Others"], "post_time": "2022-01-07T04:21:03Z", "salary": {"currency": null, "max": null, "min": null, "period": "monthly", "term": null}, "salary_visible": false, "title_keywords": ["accounting manager"], "responsibilities": ["make recommendations", "year-end", "reporting", "ad hoc", "accounts receivable", "maintaining", "general ledger", "analysis", "review", "procedures", "audit", "financial statements", "develop", "accounts payable", "external auditors"], "requirements": {"degrees": ["degree", "bachelor"], "majors": ["accounting"], "languages": ["english", "chinese"], "language_level": ["proficient"], "hard_skills": ["hkicpa"], "soft_skills": ["organizational skills", "interpersonal"], "languages_combined": [{"language": "english", "language_level": ["proficient"]}, {"language": "chinese", "language_level": ["proficient"]}]}, "experience_required": {"duration": ["minimum 7 years", "at least 5 years"], "field": ["relevant working experience", "f&b", "business", "supervisory level", "retail", "accounting"]}}, {"job_id": "100003009019869", "location_code": "hk", "company": "Artyzen Hospitality Group Limited", "job_title": "Senior Accountant / Assistant Accounting Manager", "description": "As part of an aggressive and growing company, you will support our Finance Department in\u00a0managing daily accounting duties.\n\nYour job responsibilities are:\u00a0\n\n\nHandling full set of accounts\u00a0and performing accounting function including AR, AP, GL and bank reconciliation\nPreparing monthly reports and analysis.\nAssisting in group consolidation process and financial analysis\n\nAssisting in daily administrative support including expenses reimbursement transactions, approval processing, recording and filing\nLiaising with external auditors and tax representatives for preparation of statutory financial reports and tax filing\nAny other accounting related matters or ad-hoc assignments as required\nDo you have the makings of an Artyzen? We would like to hear from you if you have the following attributes and interested in advancing your career in a dynamic work environment:\n\nDegree holder in Accounting or Finance or relevant discipline\nAt least 5 years of commercial or audit experience, PRC experience is an advantage\n\nProficient in MS Word, Excel, preferably with relevant experience using\u00a0Flex Accounts System and Oracle/Hyperion software\nGood communication and interpersonal skills\nGood team player with positive attitude and strong motivation\nHonest, responsible, hardworking, and\u00a0attentive to details\nGood command of written and spoken English, Cantonese and Mandarin\nCandidate with more experience will be considered as Assistant Accounting Manager\n\nDo our Group values of Progressive, Collaborative and Agile sit well with your personal outlook and way of doing things? If so, you could be a great match for our Group. Please send your resume with expected salary and availability to us by email or apply via JobsDB. Successful applicants will be contacted within six weeks. All personal data collected will be treated in strict confidence and be used for recruitment purposes only.\n", "employment_types": ["Full Time", "Permanent"], "selling_points": ["At least 5 years of relevant work experience", "Corporate office of a growing hotel group", "5-day work week, 12-15 days annual leave"], "locations": ["Sheung Wan"], "categories": ["Accounting", "Accountant", "Chief Accountant", "Finance / Accounting Manager"], "post_time": "2022-01-04T09:27:25Z", "salary": {"currency": null, "max": null, "min": null, "period": "monthly", "term": null}, "salary_visible": false, "title_keywords": ["assistant accounting manager", "senior accountant"], "responsibilities": ["software", "monthly reports", "bank reconciliation", "transactions", "audit", "communication", "personal data", "ap", "full set of accounts", "expenses", "liaising with", "tax filing", "ar", "administrative support", "tax", "financial reports", "ad-hoc assignments", "analysis", "financial analysis", "recruitment", "daily accounting", "external auditors"], "requirements": {"degrees": ["degree holder"], "majors": ["finance", "accounting"], "languages": ["cantonese", "english", "mandarin"], "language_level": ["good command"], "hard_skills": ["ap", "excel", "oracle", "ar", "agile", "analysis", "financial analysis", "dynamic", "outlook", "flex", "processing", "ms word"], "soft_skills": ["good team player", "confidence", "agile", "responsible", "attentive to details", "interested in", "collaborative", "positive attitude", "dynamic", "communication and interpersonal skills", "honest", "progressive", "hardworking"], "languages_combined": [{"language": "cantonese", "language_level": ["good command"]}, {"language": "english", "language_level": ["good command"]}, {"language": "mandarin", "language_level": ["good command"]}]}, "experience_required": {"duration": ["at least 5 years"], "field": ["commercial", "audit experience", "accounting", "relevant experience"]}}, {"job_id": "100003009012933", "location_code": "hk", "company": "Swire Resources Ltd", "job_title": "Senior Accountant (Reporting)", "description": "Responsibilities:\n\n\nSupervise subordinates and oversee daily accounting works\nBe responsible for monthly internal consolidated financial reports and analysis, including actuals and forecast\nBe responsible for monthly consolidated financial statement package to head office and management reporting to senior management on timely basis\nPrepare annual budget and quarterly forecast with analysis and breakdowns.\nHandle statutory audit and tax filing in HK and Macau\nBe responsible for finance matters and analysis of Administrative Support Departments\nImprove operation efficiency, including system development for consolidation & reporting, and internal control by reviewing current workflow & propose action plans\nLiaise with banks, company secretary, auditors and insurance agents on related matters\n\nRequirements:\n\nDegree in Accounting, Finance or related disciplines with professional qualifications in HKICPA/ACCA or equivalent\nAcquire the experience in external audit, preparing consolidation reports to head office, statutory consolidation to external auditor and internal management reports. PRC accounting/finance exposure is a plus\nPreferably with 3 years\u2019 experience from CPA firms and 2 years\u2019 experience from in-house accounting department in retail or sizable companies.\nProficiency in MS office application (e.g. Excel, Power-points, Words) and computerized accounting system.\nProactive, meticulous and able to work independently, efficiently and under pressure in a demanding and fast pace environment\nAble to communicate and present effectively across all levels including senior management\nGood people management skills, strong teamwork spirit and able to coach and develop subordinates\nExcellent command of both written & spoken English and Mandarin\u00a0\n\n\nWe offer competitive remuneration package with\u00a0a wide range of fringe benefits including\n\n5-day work week\nDiscretionary Bonus\nComprehensive Medical Coverage\nStaff Shopping Discount\nNon-contributory Retirement Benefits Scheme\nBirthday Leave\u00a0\u00a0\n\nPlease send resume with present and expected salary to Human Resources Department, Swire Resources Limited, 12/F Kingston International Centre 19 Wang Chiu Road Kowloon Bay Hong Kong or by clicking the \"Apply Now\" button below.\n\nSwire Resources Limited is Equal Opportunity Employer", "employment_types": ["Full Time", "Permanent"], "selling_points": ["Deg in Accounting with professional qualification", "3yrs in CPA firm+2 yrs commercial exp preferred", "Exp in ext audit, preparing consolidation reports"], "locations": ["Kowloon Bay"], "categories": ["Accounting", "Accountant", "Accounting Clerk / Supervisor", "Chief Accountant"], "post_time": "2022-01-02T22:53:05Z", "salary": {"currency": null, "max": null, "min": null, "period": null, "term": null}, "salary_visible": false, "title_keywords": ["senior accountant"], "responsibilities": ["reporting", "financial reports", "administrative support", "analysis", "budget", "tax filing", "audit", "liaise with", "management reporting", "financial statement", "forecast", "plans", "daily accounting", "senior management", "insurance", "internal control"], "requirements": {"degrees": ["degree"], "majors": ["related disciplines", "finance", "accounting"], "languages": ["english", "mandarin"], "language_level": ["excellent"], "hard_skills": ["excel", "acca", "plus", "words", "professional qualifications", "sizable companies", "cpa", "management reports", "accounting system", "prc accounting", "ms office", "hkicpa"], "soft_skills": ["meticulous", "work independently", "under pressure", "teamwork spirit", "proactive"], "languages_combined": [{"language": "english", "language_level": ["excellent"]}, {"language": "mandarin", "language_level": ["excellent"]}]}, "experience_required": {"duration": ["3 years", "2 years"], "field": ["management", "consolidation", "audit", "accounting", "retail"]}}, {"job_id": "100003009023731", "location_code": "hk", "company": "Gemini Personnel Limited", "job_title": "Accounting Manager, MNC, Medical Device   (KIO-J077885)", "description": "A renowned medical devices Co. MNC is hiring to join the Finance & Accounting Department.\n\nResponsibilities:\nResponsible for daily accounting operation and month end closing process\nManage month-end reporting packages and local management reports\nPrepare annual budget, quarterly forecast, and cash flow projections\nPerform variance analysis and support budgetary control\nFormalize and document accounting and finance SOPs to ensure consistency and efficiency\nPeriodic review of financial systems and reporting to ensure analysis and reporting are in line with business needs and a strong system of internal controls are maintained\nLiaise with both internal and external parties to perform J-sox internal and statutory audit\nCoordinate with tax consultant for annual tax filing and Transfer Pricing Local File\u00a0\nSupport for other ad hoc assignments and projects\n\nRequirements:\n\nDegree or above in Finance and Accounting\u00a0\nSAP knowledge and skills are required (with basic excel skills)\nQualified\u00a0accountant with HKICPA or equivalent\nMinimum 5 years relevant experience gained in sizable companies\nEnglish, Cantonese and Putonghua\nCandidate with less experience will be considered as Assistant Manager\nPackages:\n\nFive-day Work Week\nDouble Pay & Bonus\nMedical & Dental Allowance\nFlexible Working Hours\nFeel free to explore with Ms. So at 98651077 or 35529113 for confidential discussion.\n\n", "employment_types": ["Full Time", "Permanent"], "selling_points": ["Accounting Manager", "Inhouse Role, MNC", "SAP"], "locations": ["Kwai Hing"], "categories": ["Accounting", "Chief Accountant", "Finance / Accounting Manager", "Financial Analyst"], "post_time": "2022-01-05T09:37:29Z", "salary": {"currency": null, "max": null, "min": null, "period": "monthly", "term": null}, "salary_visible": false, "title_keywords": ["accounting manager"], "responsibilities": ["budget", "internal and external parties", "audit", "liaise with", "month end closing", "control", "tax filing", "month-end", "forecast", "reporting", "review", "coordinate with", "variance analysis", "cash flow", "sops", "tax", "analysis", "systems", "management reports", "ad hoc assignments", "daily accounting"], "requirements": {"degrees": ["degree or above"], "majors": ["finance", "accounting"], "languages": ["cantonese", "putonghua", "english"], "language_level": [], "hard_skills": ["excel", "basic", "sap", "sizable companies", "hkicpa"], "soft_skills": ["flexible"], "languages_combined": [{"language": "cantonese", "language_level": []}, {"language": "putonghua", "language_level": []}, {"language": "english", "language_level": []}]}, "experience_required": {"duration": ["minimum 5 years"], "field": ["relevant experience"]}}, {"job_id": "100003009034734", "location_code": "hk", "company": "Ambition", "job_title": "VP, FP & A - Foreign Bank", "description": "Established Banking Group\nHands-on FP&A Skills\nHK Based Candidates\n\nOur client is a global banking group with a strong presence in Asia. Due to some internal movements, my client is looking for an experienced VP to join their Financial Planning and Analysis team.\n\nReporting to the Head of the function, you will be part of a lean team responsible for preparing various FP&A reports, and lead their forecasting and budgeting process. You will ensure a smooth month-end review and act as a business partner to key stakeholders in the business. You will be expected to lead and drive process improvements and system efficiency projects. Strong communication and experience in mentoring, and developing junior would be required.\n\nTo qualify, individuals must possess:\n\nBachelor's degree in Accounting, Finance or related discipline. CPA qualification desirable\n10 -12 years' relevant experience in Financial Planning & Analysis in a sizeable financial institution\nExperience working in international banks (US, European) based in HK preferred\nExcellent communication skills in English, other languages a plus\nMust already be based in Hong Kong\n\nInterested parties, please send your updated resume to Rhoda.Rivera@ambition.com.hk quoting RR251684 or click APPLY NOW.\n\nOnly shortlisted candidates will be notified.\n\n#LI-RR1\n#BuildingBetterFutures\n\nIf this job isn't quite right for you, but you know someone who would be great at this role, why not take advantage of our referral scheme? We offer HKD1000 in Apple gift cards for every referred candidate who we place in a role. Terms & Conditions Apply. https://www.ambition.com.hk/refer-a-friend", "employment_types": ["Full Time", "Permanent"], "selling_points": ["Established Banking Group", "Hands-On FP&A Skills", "HK Based Candidates"], "locations": ["Not Specified"], "categories": ["Accounting", "Chief Accountant", "Financial Analyst"], "post_time": "2022-01-10T04:06:13Z", "salary": {"currency": null, "max": null, "min": null, "period": "monthly", "term": null}, "salary_visible": false, "title_keywords": [], "responsibilities": ["reporting", "budgeting", "analysis", "review", "month-end", "developing", "communication", "reports", "banking", "forecasting", "planning"], "requirements": {"degrees": ["degree", "bachelor"], "majors": ["finance", "accounting"], "languages": ["english"], "language_level": ["excellent"], "hard_skills": ["cpa", "analysis", "lean", "plus"], "soft_skills": ["communication skills", "responsible", "communication", "hands-on", "smooth"], "languages_combined": [{"language": "english", "language_level": ["excellent"]}]}, "experience_required": {"duration": ["10 -12 years"], "field": ["planning", "relevant experience", "developing", "financial"]}}, {"job_id": "100003009029442", "location_code": "hk", "company": "Aline Company Limited", "job_title": "Accounting Assistant Manager at Tsuen Wan area", "description": "Job Responsibilities:\n\u25cfAssist in Accounting Activities such as preparing of AR, AP, TB Cash Flow. Projection, reconciliation, supervise and consolidation reporting.\u00a0\n\u25cfAssist in bank reconciliation, inter/intra company reconciliation\n\u25cfPrepare accounting & management reports to Holding company\n\u25cfPrepare budget plans with comparison & analysis\n\u25cf Monitor AR & collection\n\u25cfAd hoc tasks may be required\n\nRequirements\n\u25cfDegree in Accounting or related disciplines\n\u25cfMore than 5 years' relevant working experience, knowledge of PRC account is essential\n\u25cfWith sound analytical mindset, initiative and willing to work under pressure to meet tight deadline\n\u25cfProficiency in MS Excel, Words, Chinese Word Processing & PPT\n\u25cf Good command of written and spoken English and Mandarin\n\u25cfGood analytical skill and able to work independently\n\u25cfWell knowledge of presentation and good communication and interpersonal skill\n\u25cfWork base in HK with occasional travel to overseas might be required", "employment_types": ["Full Time", "Permanent"], "selling_points": ["AR, AP & GP experiences can be consider AC Clerk", "Consolidation report & Contact with PRC offices", "5 days with DP & Bonus, AC skill in China is advan"], "locations": ["Not Specified"], "categories": ["Accounting", "Accountant", "Chief Accountant"], "post_time": "2022-01-07T05:16:05Z", "salary": {"currency": null, "max": null, "min": null, "period": "monthly", "term": null}, "salary_visible": false, "title_keywords": ["accounting assistant", "manager"], "responsibilities": ["ap", "reporting", "ar", "analysis", "budget", "monitor", "bank reconciliation", "ad hoc tasks", "cash flow", "management reports", "plans"], "requirements": {"degrees": ["degree"], "majors": ["related disciplines", "accounting"], "languages": ["english", "chinese", "mandarin"], "language_level": ["proficiency", "good command"], "hard_skills": ["ms excel", "chinese word processing", "words", "analytical skill"], "soft_skills": ["work independently", "analytical skill", "presentation", "interpersonal skill", "communication", "meet tight deadline", "initiative", "work under pressure"], "languages_combined": [{"language": "english", "language_level": ["good command"]}, {"language": "chinese", "language_level": ["proficiency"]}, {"language": "mandarin", "language_level": ["good command"]}]}, "experience_required": {"duration": ["5 years"], "field": ["relevant working experience"]}}, {"job_id": "100003009028550", "location_code": "hk", "company": "Links International", "job_title": "Assistant Finance Manager - FinTech Startup!", "description": "Responsibilities:\n\nHandle full set of accounts, prepare relevant reports and analyses\nParticipate in consolidation process and prepare related schedules\nAssist in organising the annual audit and coordinating with the external auditor\nAssist in annual financial reporting, including preparing notes to financial statements and other schedules for disclosures\nPrepare tax computation for tax reporting\nProvide operational support; and perform ad hoc assignments\n\nRequirements:\n\nDegree holder in Accounting or related disciplines, preferably HKICPA/ACCA finalist\nAt least 3 years of solid experience in the field of commercial accounting or Big 4\nRelevant experience will be a plus\nExcellent PC knowledge (including Excel, Word) and experience in ERP system is an advantage\nGood command of spoken and written English and Mandarin\nEmploys a proactive approach and can-do attitude to problem-solving\nResponsible, independent, details oriented, self-motivated and committed to tight deadlines", "employment_types": ["Full Time", "Permanent"], "selling_points": ["Guaranteed 13 months salary", "Very flexible working culture", "All rounded and dynamic role"], "locations": ["Not Specified"], "categories": ["Accounting", "Accountant", "Chief Accountant", "Finance / Accounting Manager"], "post_time": "2022-01-07T02:32:40Z", "salary": {"currency": "HKD", "max": 44999, "min": 25000, "period": "monthly", "term": null}, "salary_visible": true, "title_keywords": ["assistant finance manager"], "responsibilities": ["tax", "relevant reports", "reporting", "operational support", "tax computation", "annual audit", "schedules", "full set of accounts", "financial statements", "financial reporting", "ad hoc assignments"], "requirements": {"degrees": ["degree holder"], "majors": ["related disciplines", "accounting"], "languages": ["english", "mandarin"], "language_level": ["good command"], "hard_skills": ["excel", "acca", "plus", "problem-solving", "word", "erp system", "pc knowledge", "hkicpa"], "soft_skills": ["self-motivated", "independent", "responsible", "can-do attitude", "problem-solving", "committed", "proactive"], "languages_combined": [{"language": "english", "language_level": ["good command"]}, {"language": "mandarin", "language_level": ["good command"]}]}, "experience_required": {"duration": ["at least 3 years"], "field": ["big 4", "commercial", "erp system", "relevant experience", "accounting"]}}, {"job_id": "100003009021263", "location_code": "hk", "company": "AOSource Company Limited", "job_title": "Finance Manager    (FM-0105-sh-JDB)", "description": "Our client is a Listed group,\u00a0 Current they are looking for potential candidate to join their Finance team in Hong Kong.\n\nResponsibilities;\n\nReport to Head of Finance (General Account & Finance Analysis);\nTo\u00a0Lead a small team of Finance Operation Team in Hong Kong;\n\nHandle full set of account including operaton /finance analysis/ management account etc;\nTo perform and lead the accounting process and procedure, ensuring compliance with the accounting policies and guidelines;\nLead and coaching to a small team to manage accounting reporting & reporting;\nGood communcation with English and Chinese is must.\nRequirements:\n\nDegree or Above in Accounting or related discipline;\n\nHolder of CPA professional qualification and experience in 4A CPA Firm is a plus;\nAbout 8+\u00a0 years working experience in Full set of accounting and Management Accounting;\nExperience in Multi-national group is preferred;\nSolid Experience in Asia Pacific Trading Business is preferred;\nGood experience in dealing with various country business user;\nUsing software with MS Office (Execl, Word, Powerpoint) and Oracle Finance is a plus;\nExcellent spoken and written communication skill in English;\nWork independently and good team leadership.\nOur client will offer competitive remuneration package and good career prospects to the potential candidate, interested parties please quote ref.no.FM-0105-sh-JDB and submit your resume to Ms Fung by our email or enquiry with Tel:3428-6121.\n\n\nAll profiles are handled with strictest confidentiality. Shortlisted candidates would be notified", "employment_types": ["Full Time", "Permanent"], "selling_points": ["MNC Group/ Asia Pacific Trading", "CPA /Full set of Account/ Lead a small team", "Exp. in Trading/ Fin operation/ Mgmt acct"], "locations": ["Not Specified"], "categories": ["Accounting", "Chief Accountant", "Finance / Accounting Manager", "Financial Analyst"], "post_time": "2022-01-05T03:28:45Z", "salary": {"currency": null, "max": null, "min": null, "period": "monthly", "term": null}, "salary_visible": false, "title_keywords": ["finance manager"], "responsibilities": ["reporting", "management", "guidelines", "analysis", "compliance", "lead a small team", "accounting policies", "report"], "requirements": {"degrees": ["degree or above"], "majors": ["accounting"], "languages": ["english"], "language_level": ["excellent"], "hard_skills": ["plus", "oracle", "word", "powerpoint", "cpa", "ms office"], "soft_skills": ["work independently", "communication skill", "leadership"], "languages_combined": [{"language": "english", "language_level": ["excellent"]}]}, "experience_required": {"duration": [], "field": ["management accounting", "cpa firm", "business", "accounting", "trading"]}}, {"job_id": "100003009030193", "location_code": "hk", "company": "Hays", "job_title": "Regional Head of Finance - MNC Financial Service", "description": "Your new company\nYour new company is a leading, Multinational, Life Insurance firm that is looking to find a new Regional Head of Finance to lead & grow the finance team, and to provide strategic support in helping their Digital Business growth. (NOTE: You do NOT need an Insurance Background to apply for this job)\n\nYour new role\nIn your new role, you will be responsible for:\n\nOverseeing the entire finance function\nDeciding and executing on large-scale, cross-country transformation projects\nWorking closely with senior stakeholders on strategy\nWorking with other stakeholders on the execution of Strategy\n\n\nWhat you need to do now\nIf you're interested in this role, click 'apply now' or send your CV to Jason.Tsang@hays.com.hk", "employment_types": ["Full Time", "Permanent"], "selling_points": ["Multinational Firm", "Life Insurance Company", "Great Benefits"], "locations": ["Not Specified"], "categories": ["Accounting", "Chief Accountant", "Finance / Accounting Manager", "Financial Controller"], "post_time": "2022-01-07T06:56:53Z", "salary": {"currency": null, "max": null, "min": null, "period": "monthly", "term": null}, "salary_visible": false, "title_keywords": ["head of finance"], "responsibilities": ["insurance", "executing", "finance team"], "requirements": {"degrees": [], "majors": [], "languages": [], "language_level": [], "hard_skills": [], "soft_skills": ["interested in", "responsible"], "languages_combined": []}, "experience_required": {"duration": [], "field": []}}, {"job_id": "100003009030346", "location_code": "hk", "company": "Michael Page", "job_title": "Finance Manager, 50k, PRC Education Preferred", "description": "Our client is a reputable property company. They are now looking for a talent Finance Manager to join their finance team.\n\nClient Details\n\nOur client is a reputable property company. They are now looking for a talent Finance Manager to join their finance team.\n\nDescription\n\nReporting to the GM Finance, you will be responsible for\n\nPreparing for the Main Board IPO listing for the company\nHandling company secretarial matters after IPO\nPreparing annual and interim reports\nStrengthening internal controls, corporate governance and streamline accounting procedures to comply with the Hong Kong Listing Rules / standards\nProviding recommendations to enhance financial performance and business opportunities\nLiaising with CPA firm for audit and tax related matters\n\nProfile\n\nBig 10 Accounting Firm is a must\n\n211 or 958 PRC University is highly preferred\n\nExcellent communication skills (English and Mandarin)\n\nDegree Holder in Business/Accounting/Finance\n\nJob Offer\n\nMain Board IPO Experience\nCompetitive Remuneration\n\nTo apply online please click the 'Apply' button below.\nFor a confidential discussion about this role please contact Nicole Hui on +852 3412 4832.", "employment_types": ["Full Time", "Permanent"], "selling_points": ["CPA is a must", "PRC Education Preferred", "13 Months Guaranteed with Bonus"], "locations": ["Not Specified"], "categories": ["Accounting", "Chief Accountant", "Finance / Accounting Manager", "Financial Controller"], "post_time": "2022-01-07T07:16:45Z", "salary": {"currency": null, "max": null, "min": null, "period": "monthly", "term": null}, "salary_visible": false, "title_keywords": ["finance manager"], "responsibilities": ["tax", "reporting", "business opportunities", "procedures", "liaising with", "audit", "communication", "reports", "finance team", "contact", "listing"], "requirements": {"degrees": ["degree holder"], "majors": ["finance", "business", "accounting"], "languages": ["english", "mandarin"], "language_level": ["excellent"], "hard_skills": ["cpa", "gm"], "soft_skills": ["communication skills", "responsible"], "languages_combined": [{"language": "english", "language_level": ["excellent"]}, {"language": "mandarin", "language_level": ["excellent"]}]}, "experience_required": {"duration": [], "field": []}}, {"job_id": "100003009030353", "location_code": "hk", "company": "Michael Page", "job_title": "Accountant, Law Firm, 36k (Big 8 welcome)", "description": "Our client is a reputable law firm. To cope with their business needs, they are now looking for a talented Accountant to join their finance team.\n\nClient Details\n\nOur client is a reputable law firm. To cope with their business needs, they are now looking for a talented Accountant to join their finance team.\n\nDescription\n\nReporting to the Regional FC in Hong Kong, you will be responsible for:\n\nensuring accurate financial and management reports\nperforming a full spectrum of accounting and finance duties\ntaking part in business partnering and providing financial advice for better business outcomes\n\nProfile\n\nDegree Holder in Business/Accounting/Finance\nProfessional Servicing/Law Firm experience would be a plus\nBig 8 are welcome\nExcellent communication skills (English and Mandarin) is a must\n\nJob Offer\n\nCompetitive remuneration\nFast and dynamic business growth\nReputable company\n\nTo apply online please click the 'Apply' button below.\nFor a confidential discussion about this role please contact Nicole Hui on +852 3412 4832.", "employment_types": ["Full Time", "Permanent"], "selling_points": ["Fluent Mandarin and English is a must", "Renowned Law Firm", "Attractive package with promising career prospect"], "locations": ["Not Specified"], "categories": ["Accounting", "Chief Accountant", "Finance / Accounting Manager", "Others"], "post_time": "2022-01-07T07:17:45Z", "salary": {"currency": null, "max": null, "min": null, "period": "monthly", "term": null}, "salary_visible": false, "title_keywords": ["accountant"], "responsibilities": ["reporting", "finance duties", "communication", "management reports", "finance team", "contact"], "requirements": {"degrees": ["degree holder"], "majors": ["finance", "business", "accounting"], "languages": ["english", "mandarin"], "language_level": ["excellent"], "hard_skills": ["management reports", "dynamic", "plus"], "soft_skills": ["communication skills", "dynamic", "accurate", "responsible"], "languages_combined": [{"language": "english", "language_level": ["excellent"]}, {"language": "mandarin", "language_level": ["excellent"]}]}, "experience_required": {"duration": [], "field": []}}, {"job_id": "100003009033059", "location_code": "hk", "company": "Michael Page", "job_title": "(Assistant) Finance Manager, Japanese Speaking N1, 45k", "description": "Our client is a well-established Japan listed company. They are now looking for a talent (Assistant) Finance Manager to join their company.\n\nClient Details\n\nOur client is a well-established Japan listed company. They are now looking for a talent (Assistant) Finance Manager to join their company.\n\nDescription\n\nReporting to the GM Finance, you will be\n\npreparing and reviewing the full sets of account\npreparing the financial reports\nconsolidating the financial and management accounts reporting for the region\nhelping to streamline the financial operations\nreviewing the cash flow forecasting, budgeting and management\nperforming other adhoc tasks\n\nProfile\n\nDegree Holder in Business/Accounting/Finance\nJapanese N1 Level is a must\n\nJob Offer\n\n* Competitive remuneration\n* Fast and dynamic business growth\n* Reputable company\n\nTo apply online please click the 'Apply' button below.\nFor a confidential discussion about this role please contact Nicole Hui on +852 3412 4832.", "employment_types": ["Full Time", "Permanent"], "selling_points": ["Japanese Speaking N1 is a must", "Japan Listed Firm", "Great career progresion"], "locations": ["Not Specified"], "categories": ["Accounting", "Audit", "Chief Accountant", "Finance / Accounting Manager"], "post_time": "2022-01-08T07:08:58Z", "salary": {"currency": null, "max": null, "min": null, "period": "monthly", "term": null}, "salary_visible": false, "title_keywords": ["finance manager", "assistant"], "responsibilities": ["reporting", "financial reports", "management", "operations", "budgeting", "accounts reporting", "cash flow", "contact", "forecasting"], "requirements": {"degrees": ["degree holder"], "majors": ["finance", "business", "accounting"], "languages": ["japanese"], "language_level": [], "hard_skills": ["gm", "dynamic"], "soft_skills": ["dynamic"], "languages_combined": [{"language": "japanese", "language_level": []}]}, "experience_required": {"duration": [], "field": []}}]