[{"job_id": "100003009052402", "location_code": "hk", "company": "Luk Fook Financial Services Limited", "job_title": "Corporate Finance \u2013 Associate / Assistant Manager / Manager", "description": "\u00a0Responsibilities\n\nProviding outsourced internal audit services to our clients across various industries locally and internationally;\nDevelop and review risk management frameworks and policies;\nAssist organizations to maintain effective and efficient controls, in order to manage organizational and strategic risks;\nConduct various advisory tasks such as enterprise risk management under ISO31000, COSO Framework etc., compliance reviews and controls related projects, such as PN21/PN2 under the Listing Rules of the Stock Exchange of Hong Kong;\nAssist in operational risk assessment process including collect and verify data for evaluation of operational risk level;\nParticipate and provide risk comments in product development and business projects;\nKeep abreast of market news including customer data protection and fraud prevention;\nAssisting our clients in the risk management process.\n\n\u00a0Requirements\n\nHigher Diploma\u00a0in Accounting/Risk Management/Corporate Governance or related disciplines;\n0-3 year's experience in internal audit and risk services;\nStudent member/ member of HKICPA/ACCA/CPA Australia/IIA or equivalent qualification is preferred;\nPractical experience in internal audit & risk management;\nAttention to detail, able to work independently and as a team member;\nGood communication, interpersonal and analytical skills;\nAbility to interact with all levels of personnel, including senior executives of client management;\nGood command of written English & Chinese, Mandarin is an advantage;\nProficient in MS Office, including Word & Excel\u00a0and Chinese word processing is required;\nAble to travel overseas and the PRC;\nFresh\u00a0graduates are welcome;\nImmediate available is preferred;\nCandidates with more experience will be considered as Senior Associate.\n\nWhat we offered?\n\n5-day work week\nImportant festivals early leave\nOvertime meal allowance\nTraveling allowance\nDiscretionary bonus\nFull-paid sick leave\nStudy & Exam leave\nGraduation leave\nWedding leave\nCompassionate leave\nMedical Insurance Scheme\nTraining reimbursement\n\n\nInterested parties please click \"APPLY NOW\" and send your full resume with your\u00a0working experience, academic and professional qualification, expected salary, and date of availability\u00a0to HR Department.\n\nPersonal data collected will be used for recruitment purpose only.\u00a0", "employment_types": ["Full Time", "Permanent"], "selling_points": ["corporate finance", "client relationships", "professional parties"], "locations": ["Sheung Wan"], "categories": ["Accounting", "Consulting", "Finance / Accounting Manager", "Banking / Finance", "Corporate Finance"], "post_time": "2022-01-17T02:57:32Z", "salary": {"currency": null, "max": null, "min": null, "period": "monthly", "term": null}, "salary_visible": false, "title_keywords": ["assistant manager", "associate", "manager", "corporate finance"], "responsibilities": ["management", "internal audit", "data", "business projects", "policies", "review", "compliance", "comments", "customer data", "develop", "maintain", "evaluation", "listing"], "requirements": {"degrees": ["diploma"], "majors": ["related disciplines", "risk management", "accounting"], "languages": ["english", "chinese", "mandarin"], "language_level": ["advantage", "good command", "proficient"], "hard_skills": ["excel", "acca", "chinese word processing", "word", "analytical skills", "cpa", "hkicpa", "ms office"], "soft_skills": ["work independently", "analytical skills", "communication", "attention to detail", "team member", "interpersonal"], "languages_combined": [{"language": "english", "language_level": ["advantage", "good command"]}, {"language": "chinese", "language_level": ["advantage", "good command", "proficient"]}, {"language": "mandarin", "language_level": ["advantage", "good command"]}]}, "experience_required": {"duration": ["0-3 year"], "field": ["risk management", "audit"]}}, {"job_id": "100003009052313", "location_code": "hk", "company": "PwC", "job_title": "Senior Associate - Tax Controversy Services, ITBC, Tax Services, Hong Kong", "description": "Job Descriptions and Responsibilities\n\nIn recent years, the Hong Kong Inland Revenue Department (\u201cIRD\u201d) has been deploying more resources on tax controversy and taking a more stringent approach in handling tax disputes with both corporate and individual taxpayers. Given the adoption of OECD\u2019s action plan on Base Erosion and Profit Shifting (\u201cBEPS\u201d) and the implementation of new tax regulations, taxpayers are facing more challenges and encountering with more tax controversy issues. To cope with the increasing market demand for tax controversy and dispute resolution services, our Tax Controversy Services (\u201cTCS\u201d) team is expanding and now recruiting experienced talents (preferably those who are familiar with the IRD\u2019s practices and/or with practical experience of dealing with the IRD) to join our TCS team.\n\nOur TCS team consists of ex-officers and tax specialists with strong expertise and experience in handling tax controversy. We are currently seeking high caliber tax professionals to join us and take part in:\n\nAssisting clients in resolving tax disputes, for example, tax audit and appeal cases, tax enquiries, challenges on the entitlement to treaty benefits;\nFormulation of settlement approaches for tax audit and investigation cases;\nNegotiation with the IRD\u2019s officers during the course of case resolving;\nHandling simple tax audit cases independently with direct partner supervision;\nPost-audit restructuring to rectify problems identified during tax audit;\nConducting tax health checks and defense file building;\nAssisting clients in obtaining treaty protection or treaty benefits, and defending against any challenges from the IRD;\nDeveloping and maintaining good client relationship at working level; and\nAssisting in the practice development for the TCS team and PwC.\n\nRequirements\n\nA recognized accounting or equivalent degree\nQualified member of a professional accounting body\nTotal 3- 5 years of experience in Hong Kong profits tax experience, preferably with experience of field audits / tax investigations or other areas of tax controversy\nWith IRD work experience is a plus, particularly experience in the Field Audit and Investigation Unit, Appeals Section or Treaty Section\nFluent in both written and spoken English, Cantonese and Putonghua\nExcellent interpersonal skills would be an advantage\nAnalytical-minded and solid in project management\nCandidates with more experience will be considered for Manager role\n\n\n\nThe PwC China (including Mainland China, Hong Kong, Macau) does not accept unsolicited resumes from search firm recruiters. Fees will not be paid in the event a candidate submitted by a recruiter without an agreement in place is hired; such resumes will be deemed the sole property of PwC China (including Mainland China, Hong Kong, Macau). PwC China (including Mainland China, Hong Kong, Macau) is an equal opportunity employer. All aspects of employment will be based on merit, competence, performance, and business needs. We do not discriminate on the basis of race, color, religion, marital status, age, national origin, ancestry, physical or medical condition, genetic information, gender, sexual orientation, gender identity or expression, veteran status, or any other status protected under the local law.", "employment_types": ["Full Time", "Permanent"], "selling_points": ["Resolving Tax Dispute, Tax Investigations", "3- 5 years Experience in Liaising with IRD", "Fluent in  English and Chinese"], "locations": ["Central"], "categories": ["Accounting", "Consulting", "Taxation"], "post_time": "2022-01-17T02:43:57Z", "salary": {"currency": null, "max": null, "min": null, "period": "monthly", "term": null}, "salary_visible": false, "title_keywords": ["senior associate"], "responsibilities": ["tax", "regulations", "implementation", "resolution", "plan"], "requirements": {"degrees": [], "majors": [], "languages": [], "language_level": [], "hard_skills": [], "soft_skills": [], "languages_combined": []}, "experience_required": {"duration": [], "field": []}}, {"job_id": "100003009053248", "location_code": "hk", "company": "APEC Group International Limited", "job_title": "Management Trainee (Fresh graduates are welcomed)", "description": "Job Highlights:\n\n\u00a05-day work week\n\u00a0Flexible working pattern\n\u00a0Excellent career path to management level\n\n\u00a0Description:\n\nThe trainee will be provided a professional training program including one-to-one coaching and mentoring for financial consultation service including: -\u00a0\n\nRisk Management\nFinancial Advisory Services\nFinancial Management\nI.T. Services and Solutions\nCloud Financial Services\n\nIn order to be trained as one of the most talented professional in the financial sector, the trainees will be undergoing a rotation to explore the mentioned sector in both theoretical and practical way.\n\n\u00a0Requirements:\n\nHigher Diploma or above in Accounting or related disciplines;\nFresh graduates are welcomed\n0 to 1 year of accounting or audit experience in any field is an advance;\nProficient in MS Word & Excel experience is highly preferred;\nBe responsible, communicate well with people at all levels;\nHard working & willing to learn;\nStrong desire to take challenges and make success on career life;\nGood command of both written and spoken English and Chinese; and\nImmediately available is preferred.\n\nWhat we offered?\n\n5-day work week\nImportant festivals early leave\nOvertime meal allowance\nDiscretionary bonus\nFull-paid sick leave\nStudy & Exam leave\nGraduation leave\nWedding leave\nCompassionate leave\nMedical Insurance Scheme\nTraining reimbursement\nInterested parties please send your full resume with your\u00a0working experience, academic and professional qualification, expected salary, and date of availability\u00a0to HR Department.\nPersonal data collected will be used for recruitment purpose only.", "employment_types": ["Full Time", "Permanent"], "selling_points": ["Higher Diploma or above in Accounting", "Fresh graduates are welcomed", "Flexible working pattern"], "locations": ["Sheung Wan"], "categories": ["Accounting", "Accountant", "Consulting", "Financial Analyst"], "post_time": "2022-01-17T06:31:43Z", "salary": {"currency": null, "max": null, "min": null, "period": "monthly", "term": null}, "salary_visible": false, "title_keywords": ["management trainee"], "responsibilities": ["management"], "requirements": {"degrees": ["higher diploma or above"], "majors": ["related disciplines", "accounting"], "languages": ["english", "chinese"], "language_level": ["good command"], "hard_skills": ["excel", "make", "ms word"], "soft_skills": ["hard working", "willing to learn", "responsible"], "languages_combined": [{"language": "english", "language_level": ["good command"]}, {"language": "chinese", "language_level": ["good command"]}]}, "experience_required": {"duration": ["0 to 1 year"], "field": ["audit experience", "accounting"]}}, {"job_id": "100003009051838", "location_code": "hk", "company": "The Great Eagle Group of Companies", "job_title": "Manager - Treasury", "description": "Responsibilities:\n\nResponsible for routine treasury and loan transactions execution and administration including loan documentation negotiation, treasury dealing, KYC and compliance monitoring and relevant treasury reporting\nAssist in fund raising in bank loan market and international debt capital market\nAssist in managing all treasury functions including corporate liquidity, forex hedging, cash flow forecast and risk management\nDrive process and system improvement to increase data integrity and security\nAssist in managing banking relationship\nHandle ad hoc works as assigned by management\n\nRequirements:\n\nDegree holder in Accounting, Finance or other related disciplines\nHolder of CPA or CFA is an advantage\nMinimum 10 years\u2019 experience with corporate treasury, in-depth knowledge of debt, forex, derivative and cash management \u00a0\nStrong analytical and problem solving skills\nGood communication, presentation and interpersonal skills\nResponsible, well-organized, detail-minded, independent and able to work under pressure\nGood team player, willing to learn and take up new tasks\nProficiency in MS Office Applications\nGood command of both spoken and written\u00a0English\u00a0and Chinese (including Putonghua)\n\nSalary and benefits will be commensurate with qualifications and experience.\u00a0 Interested parties, please send a full resume with present and expected salary, and date available to The Human Resources Department, 32/F., Great Eagle Centre, 23 Harbour Road, Wanchai, Hong Kong or e-mail to us.\u00a0\u00a0(Please quote the reference no. on the envelope and the covering letter.)\n\nTo know more about us, please visit our websites at http://www.greateagle.com.hk\n\nWe are an equal opportunity employer and welcome applications from all qualified candidates.\n\nPersonal data collected will be treated in strict confidence and used only for recruitment-related purpose. Applicants who have not heard from us within four weeks may consider their applications unsuccessful. All personal data will be destroyed after 12 months.", "employment_types": ["Full Time", "Permanent"], "selling_points": ["Manage all corporate treasury functions", "Fund raising, debt capital market", "Holder of CPA or CFA is an advantage"], "locations": ["Wan Chai"], "categories": ["Accounting", "Consulting", "Banking / Finance", "Loan", "Dealing & Trading"], "post_time": "2022-01-17T01:20:52Z", "salary": {"currency": null, "max": null, "min": null, "period": "monthly", "term": null}, "salary_visible": false, "title_keywords": ["manager"], "responsibilities": ["reporting", "management", "ad hoc", "data", "compliance", "monitoring", "banking", "transactions", "cash flow", "forecast", "kyc", "documentation", "administration"], "requirements": {"degrees": ["degree holder"], "majors": ["related disciplines", "finance", "accounting"], "languages": ["putonghua", "english", "chinese"], "language_level": ["good command"], "hard_skills": ["cfa", "cpa", "problem solving skills", "ms office"], "soft_skills": ["detail-minded", "good team player", "independent", "responsible", "well-organized", "willing to learn", "communication", "analytical and problem solving skills", "interpersonal skills", "presentation", "work under pressure"], "languages_combined": [{"language": "putonghua", "language_level": ["good command"]}, {"language": "english", "language_level": ["good command"]}, {"language": "chinese", "language_level": ["good command"]}]}, "experience_required": {"duration": ["minimum 10 years"], "field": ["management"]}}, {"job_id": "100003009053254", "location_code": "hk", "company": "APEC Group International Limited", "job_title": "Accountant Trainee/Associate (Financial Advisory Team)", "description": "Responsibilities\n\nAssist in handle assignments independently;\nInvolving in public offerings, listings, due diligence and private placements;\nAssist in analyze financial results of clients\u2019 companies;\nAssist in providing support to clients regarding different regulatory regimes, listing rules and related regulations;\nKeep up-to-date on regulatory developments;\nAssist in preparing business plans and IPO business proposals; Developing effective business relationships with clients;\nHandle ad hoc matters assigned.\n\nRequirements\n\nHigher Diploma\u00a0in accounting or related discipline.\nStudent member of HKICPA/ACCA/CPAA or other relevant professional bodies;\n0-1 year of accounting/audit experience in any field;\nSelf-motivated, willing to take job ownership, manage deadlines and able to work as a team player;\nProficient in MS Excel and word and knowledge of computerized accounting system is highly preferred;\nGood\u00a0analytical, interpersonal and communication skill is highly preferred;\nGood command in written and spoken English, Chinese and Mandarin;\nBusiness travel is required;\nFresh graduates are welcome;\nImmediate available is preferred.\n\nWhat we offered?\n\n5-day work week\nImportant festivals early leave\nOvertime meal allowance\nDiscretionary bonus\nFull-paid sick leave\nStudy & Exam leave\nGraduation leave\nWedding leave\nCompassionate leave\nMedical Insurance Scheme\nTraining reimbursement\nInterested parties please send your full resume with your\u00a0working experience, academic and professional qualification, expected salary, and date of availability\u00a0to HR Department.\nPersonal data collected will be used for recruitment purpose only.", "employment_types": ["Full Time", "Part Time", "Permanent", "Contract"], "selling_points": ["Fresh graduates are welcome", "5-day work week", "Excellent career promotion prospect"], "locations": ["Sheung Wan"], "categories": ["Accounting", "Accountant", "Audit", "Consulting"], "post_time": "2022-01-17T06:32:55Z", "salary": {"currency": null, "max": null, "min": null, "period": "monthly", "term": null}, "salary_visible": false, "title_keywords": ["associate", "accountant", "trainee"], "responsibilities": ["regulations", "due diligence", "ad hoc", "developing", "providing support", "preparing business plans", "listing"], "requirements": {"degrees": ["diploma"], "majors": ["accounting"], "languages": ["english", "chinese", "mandarin"], "language_level": ["good command"], "hard_skills": ["acca", "word", "ms excel", "accounting system", "hkicpa"], "soft_skills": ["self-motivated", "communication skill", "interpersonal", "work as a team"], "languages_combined": [{"language": "english", "language_level": ["good command"]}, {"language": "chinese", "language_level": ["good command"]}, {"language": "mandarin", "language_level": ["good command"]}]}, "experience_required": {"duration": ["0-1 year"], "field": ["audit experience", "accounting"]}}, {"job_id": "100003009052162", "location_code": "hk", "company": "BDO", "job_title": "Associate - Risk Advisory Services (2022 Jan Intake)", "description": "As an Associate in our Risk Advisory Services Department, you will participate in internal audits reviews and advisory engagement.\n\nResponsibilities\n\nParticipate in internal audits review and/or advisory engagements\u00a0\nAssist to provide input to management leaders on suggestions to improve client internal controls\nPrepare\u00a0accurate documentation and high quality reports\nMaintain relationships with key client personnel to obtain an understanding of business operations, processes and functions\nPerform any ad-hoc duties as assigned\n\nRequirements\n\nBachelor degree in Accounting, Finance, Economics or Business related discipline\nAbility to handle\u00a0multi-task successfully while working independently or within a group environment\u00a0\nWilling to learn new knowledge and open to take up new challenges\nExcellent communication and interpersonal skills\nExcellent command of both written and spoken English and Chinese; including Mandarin\nProven ability to work in a deadline-driven environment and willing to travel frequently\nBe passionate for providing exceptional quality service and striving for exceeding clients\u2019 expectations", "employment_types": ["Full Time", "Permanent"], "selling_points": ["Excellent opportunity of career growth", "Good exposure in a sizable CPA firm", "Birthday Leave, Medical and Life Insurance, etc."], "locations": ["Sheung Wan"], "categories": ["Accounting", "Audit", "Consulting", "Professional Services", "Business Consultancy"], "post_time": "2022-01-17T02:17:57Z", "salary": {"currency": null, "max": null, "min": null, "period": "monthly", "term": null}, "salary_visible": false, "title_keywords": ["associate"], "responsibilities": ["maintain relationships", "management", "documentation", "operations", "review", "quality", "reports", "ad-hoc duties", "audits"], "requirements": {"degrees": ["degree", "bachelor"], "majors": ["business", "finance", "accounting", "economics"], "languages": ["english", "chinese", "mandarin"], "language_level": ["excellent"], "hard_skills": [], "soft_skills": ["passionate", "independently", "multi-task", "willing to learn", "communication and interpersonal skills", "driven"], "languages_combined": [{"language": "english", "language_level": ["excellent"]}, {"language": "chinese", "language_level": ["excellent"]}, {"language": "mandarin", "language_level": []}]}, "experience_required": {"duration": [], "field": []}}, {"job_id": "100003009052950", "location_code": "hk", "company": "Fung, Yu & Co. CPA Limited", "job_title": "Internship - Audit Department/Accounting Services Department", "description": "If you want to\n\ngain valuable internship experience on audit work\nbuild up diversified concepts of doing audit for different business nature companies\nget the skill sets of presentation, interpersonal, communication to enrich your competitiveness in the future career\n\nOur internship program contains\n\nconcepts and practices of audit\nperforming audit work\naudit case study\npresentation\n\nIf you are\n\nwilling to learn\nenergetic and passionate\nHKID Holders\n\nWhat We Offer\n\nwork reference letter\non-job training\n\nWelcome to join us in this winter!\n\nPlease submit your application by clicking \u201cApply Now\u201d button.\n\nWelcome to visit our company website http://www.fungyucpa.com/\u00a0for more information.\n\nPersonal data collected will be used for recruitment purposes only.", "employment_types": ["Internship"], "selling_points": ["University degree holder majoring in accountancy", "Audit/Accounting", "Intern"], "locations": ["Central & Western Area"], "categories": ["Accounting", "Audit", "Consulting", "Taxation"], "post_time": "2022-01-17T04:39:36Z", "salary": {"currency": null, "max": null, "min": null, "period": "monthly", "term": null}, "salary_visible": false, "title_keywords": ["accounting", "internship"], "responsibilities": ["communication", "audit"], "requirements": {"degrees": [], "majors": [], "languages": [], "language_level": [], "hard_skills": [], "soft_skills": ["passionate", "presentation", "willing to learn", "communication", "energetic", "interpersonal"], "languages_combined": []}, "experience_required": {"duration": [], "field": ["audit"]}}, {"job_id": "100003009052113", "location_code": "hk", "company": "AVISTA PRO-WIS Risk Advisory Limited", "job_title": "Senior Environmental Consultant (ESG Advisory Services)", "description": "Service: Environmental, Social and Governance (\u201cESG\u201d) Reporting, Sustainability Target Setting, ESG Risk Assessment\nLocation: Hong Kong\n\nJob Description and Responsibilities:\n\nPerform environmental KPI calculation, data analysis and technical research\nPropose environmental management / reduction strategies and deliver such professional advice to clients for follow up actions\nJoin the company team in sustainability research and product development through building know-how, information analysis, benchmarking, market intelligence and solution partnerships\nPerform\u00a0ESG consulting services, conduct ESG benchmarking, ESG due diligence, sustainability strategy development, target setting, carbon management, sustainability rating\nPrepare sustainability/ ESG report and assurance for our clients listed\u00a0in Hong Kong\nAssist in ESG improvement opportunities\u00a0and\u00a0provide value-added recommendations\u00a0\nManage client relationships and consultancy projects in HK, China and overseas.\n\nRequirements:\n\nPractical experience in ESG consulting, sustainability strategy development, target setting, carbon management, sustainability rating\nIn-depth knowledge in climate / environmental science, ESG, TCFD, green building, environmental legislation\nDegree holder in Environmental Studies (Engineering, Science or Management) or related subjects\nLocal or overseas professional qualification(s) preferred (e.g. CEM)\nExcellent command in written and spoken English and Chinese (Cantonese & Mandarin)\nGood team player with the ability to work independently\nExcellent research and analytical skills with attention to detail\nExcellent interpersonal and communication skills with flexibility\nProficiency in computer skills such as word processing, presentation software, data analysis and research documentation;\nTravelling is required\n\nCandidates with more experience will be considered as Assistant Manager\n\nBenefit: We offer attractive remuneration package including a 5-day work week, medical insurance and good career prospect to the suitable candidate.\n\nApplication Procedure: Please send CV with expected salary by clicking \"Apply Now\".\n\nPersonal data will be used for recruitment purpose only.", "employment_types": ["Full Time", "Permanent"], "selling_points": ["ESG consulting, sustainability target setting", "Knowledge in climate/environmental science,TCFD", "More experience will be considered as AM"], "locations": ["Wan Chai"], "categories": ["Accounting", "Consulting", "Banking / Finance", "Financial Services", "Professional Services", "Business Consultancy"], "post_time": "2022-01-17T02:07:37Z", "salary": {"currency": null, "max": null, "min": null, "period": "monthly", "term": null}, "salary_visible": false, "title_keywords": ["senior environmental consultant"], "responsibilities": ["due diligence", "management", "consulting", "analysis", "data analysis", "carbon management", "report"], "requirements": {"degrees": ["degree holder"], "majors": ["science", "engineering"], "languages": ["cantonese", "english", "chinese", "mandarin"], "language_level": ["excellent"], "hard_skills": ["analysis", "word processing", "analytical skills", "computer skills", "documentation"], "soft_skills": ["communication skills", "good team player", "work independently", "presentation", "analytical skills", "attention to detail", "interpersonal"], "languages_combined": [{"language": "cantonese", "language_level": ["excellent"]}, {"language": "english", "language_level": ["excellent"]}, {"language": "chinese", "language_level": ["excellent"]}, {"language": "mandarin", "language_level": ["excellent"]}]}, "experience_required": {"duration": [], "field": ["development", "management", "consulting", "sustainability"]}}, {"job_id": "100003009047701", "location_code": "hk", "company": "Moore Associates Limited", "job_title": "Senior Associates/Manager/Senior Manager - Valuation", "description": "Job Highlights\n\nValuations on businesses, intangible assets, financial instruments and real properties\nM&As, HKEX-IPOs, NASDAQ-IPOs, De-SPAC, etc. related valuations and financial due diligence projects\nCross-border deals and lead advisory services\n\nJob Description\n\nMoore Global Network is the world's tenth-largest global accountancy and consulting network, founded in 1907 and headquartered in London. In Hong Kong, our Transaction Services team provides professional valuation advisory services to private companies, public interest entities, venture capital, private equities, other types of funds and government authorities.\n\nWe uphold the best valuation practices and have a proven valuation track record on supporting IPO, financial reporting, public documentation, merger & acquisition, and litigation & corporate financing. We are also one of the pioneers who have provided valuation and financial due diligence services for De-SPAC transactions in the US Market.\n\nYou will be joining this energetic team and report to the managers and conduct professional work under their guidance.\n\nResponsibility\n\nPreparing professional valuations on different types of assets and liabilities for various purposes such as financial reporting, transaction, litigation, financing;\nProviding second opinions and independent professional review on valuation reports prepared by third-party professionals;\nProviding valuation support to other services lines, such as audit, corporate finance, financial and operational due diligence, litigation support, corporate governance and ESG reporting;\nHandling cross-border M&A advisory projects and liaising with different member firms of the Moore Global Network and the Moore Global Corporate Finance Group.\n\nRequirements\n\n\n2-year+ hands-on experience in business valuation, intangible assets valuation and/or property valuations;\nProfessional qualifications such as CFA Charter, FRM Charter, MRICS and MHKIS are preferred;\nExcellent command of spoken and written English and Chinese, including Mandarin;\nKnowledge in data analysis and programming languages such as VBA, Python, R is a plus; and\nThe final position offered will be commensurate with the experience of the candidate.\n\nA competitive package will be offered to the right candidate(s), including 5 day work week, paid examination & study leave, birthday leave & medical insurance coverage. Interested parties please send a full resume with working experience, academic and professional qualifications, including present & expected salary by clicking the \"Apply Now\" button.\u00a0 Personal data collected will be used for recruitment purposes only.\n\nSimply click the \"Apply Now\" button.\n\nPlease visit our website at\u00a0www.moore.hk\u00a0to know more about us.\n", "employment_types": ["Full Time", "Permanent"], "selling_points": ["Preparing professional valuations", "Handling cross-border M&A advisory projects", "2-year+ hands-on experience in business valuation"], "locations": ["Tsim Sha Tsui"], "categories": ["Accounting", "Consulting", "Banking / Finance", "Financial Services", "Professional Services", "Business Analysis / Data Analysis"], "post_time": "2022-01-15T03:49:49Z", "salary": {"currency": null, "max": null, "min": null, "period": "monthly", "term": null}, "salary_visible": false, "title_keywords": ["senior manager", "manager"], "responsibilities": ["valuation", "due diligence", "guidance", "reporting", "consulting", "review", "audit", "transactions", "liaising with", "reports", "financial reporting", "documentation", "report"], "requirements": {"degrees": [], "majors": [], "languages": ["english", "chinese", "mandarin"], "language_level": ["excellent"], "hard_skills": ["vba", "plus", "professional qualifications", "cfa", "analysis", "programming", "python", "r", "frm"], "soft_skills": ["hands-on"], "languages_combined": [{"language": "english", "language_level": ["excellent"]}, {"language": "chinese", "language_level": ["excellent"]}, {"language": "mandarin", "language_level": ["excellent"]}]}, "experience_required": {"duration": [], "field": ["business"]}}, {"job_id": "100003009045088", "location_code": "hk", "company": "Baker Tilly Hong Kong", "job_title": "Consultant Trainee - Risk Advisory / ESG Advisory", "description": "BAKER TILLY HONG KONG\u00a0is recruiting consultant trainee who will work at one of our operating units,\u00a0BT\u00a0Corporate Governance Limited ('BTCGL').\u00a0BTCGL\u00a0is one of the largest and most active internal control consultancy firms in the Hong Kong capital market, and specializes in providing a wide range of consultancy services, e.g. risk advisory, internal control, compliance advisory, financial due diligence, IT system review, ESG reporting, and forensic accounting, etc. to its clients, including IPO listing candidates and listed companies, in a highly diversified client portfolio of different industry exposures.\n\nDue to its rapid business expansion and development, it is looking for ambitious high calibre candidates to help achieve its business development targets.\n\nConsultant Trainee - Risk Advisory / ESG Advisory\n\nRequirements:\n\n- University graduate in Accountancy, Information System, Corporate Governance, Marketing, Journalism, Environmental Science / Engineering, etc.\n\n- Relevant experience in risk advisory is an advantage but not essential, fresh graduates are welcome\n\n- Proficient in both spoken and written English and Chinese, including Mandarin\n\n- Good analytical, communication and interpersonal skills\n\n- Strong sense of responsibility and must be a good team-player\n\n- Proven ability to work in a deadline-driven environment and willing to travel\n\nWe offer an attractive remuneration package, interesting job exposure, excellent career growth prospects in a warm and friendly atmosphere. Our continuing expansion and growth offer numerous development opportunities to the incumbents.\u00a0\n\nIf you consider yourself the appropriate choice, please forward your CV and salary expectations with the application form\u00a0to the Human Resources Department, 2/F, Foyer, 625 King\u2019s Road, North Point, Hong Kong or by\u00a0clicking \u201cApply Now\u201d.\u00a0\u00a0\u00a0\n\nDownload Application Form\n\nSelected candidates will be notified by phone for interview arrangements within 6 weeks. Applications of unsuccessful candidates will be deleted immediately after screening.\n\nPersonal data provided by job applicants will be used strictly in accordance with the Employer's Personal Data Policies, a copy of which will be provided upon request.\n\nBaker Tilly Hong Kong\u00a0is a leading firm of certified public accountants and business advisers, specialising in providing clients with a range of integrated services. Our firm is driven by 300 directors and professional staff based in Hong Kong.", "employment_types": ["Full Time", "Permanent"], "selling_points": ["University graduates", "Fresh graduates are welcome", "Fluency in spoken English, Cantonese and Putongha"], "locations": ["Quarry Bay"], "categories": ["Accounting", "Audit", "Consulting", "Professional Services", "Business Consultancy"], "post_time": "2022-01-13T07:08:10Z", "salary": {"currency": null, "max": null, "min": null, "period": "monthly", "term": null}, "salary_visible": false, "title_keywords": ["consultant trainee"], "responsibilities": ["due diligence", "reporting", "review", "compliance", "communication", "listing", "internal control"], "requirements": {"degrees": ["university graduate"], "majors": ["engineering", "accountancy", "journalism", "environmental science", "marketing"], "languages": ["english", "chinese", "mandarin"], "language_level": ["proficient"], "hard_skills": ["rapid", "information system", "internal control"], "soft_skills": ["sense of responsibility", "team-player", "communication and interpersonal skills", "active", "driven"], "languages_combined": [{"language": "english", "language_level": ["proficient"]}, {"language": "chinese", "language_level": ["proficient"]}, {"language": "mandarin", "language_level": ["proficient"]}]}, "experience_required": {"duration": [], "field": ["relevant experience"]}}, {"job_id": "100003009048001", "location_code": "hk", "company": "Fiducia Limited", "job_title": "ERP Functional Consultant (China, Hong Kong or Singapore)", "description": "We are looking for a high calibre professional to join our operation team!\n\nPrimary role purpose:\n\nThe ERP Team is responsible for the Microsoft Dynamics 365 Business Central platform at Fiducia Management Consultants. Business Central is used to run business processes across accounting, corporate and trade services, consulting and recruiting. Our talented team is experienced, collaborative, innovative and lots of fun to work with. Our mission is to enable our clients to get the most out of our applications.\n\nOur ERP-Team is accountable for the strategy, implementation & operation of our ERP technologies and journeys. Working with service managers and clients, they provide customer-centric solutions to evolving processes. Our services are at the heart of how Fiducia Management Consultants run the Finance and Accounting services as well as a critical enabler for the supply chain operations of our clients in Mainland China and APAC.\n\nThis is an exciting time to join our team. We are also about to embark on a major ERP Strategy to further grow our services. This will revolutionise ERP for our clients and internal users. Therefore, we are looking to augment our team of outstanding Functional Consultants who will be pivotal to delivering ambitious solutions within the current platform and contributing to shaping the new-direction ERP. It is a great opportunity to play a major role in this programme and develop the depth & breath of your experience. If you are a proactive and detail-oriented consultant with strong ability to communicate with our clients and have the capability to think both tactically & strategically, we would love to speak to you.\n\nYour focus will be the delivery of End to End Microsoft Dynamics 365 business solutions, that meet the business requirements and add business value. As a Functional Consultant in the ERP-team,\u00a0 you will use your expertise, experience, Dynamics365 skills and business process knowledge to design, develop, integrate, test and deploy solutions to help our business achieve its objectives.\n\nJob Description:\n\nAs a key member of the ERP Team you will ensure the design and realisation of functional solutions are fit for purpose and delivered against stated business requirements. You will collaborate with cross functional teams & business stakeholders to implement and oversee operational excellence in maintaining processes by the service units within Fiducia Management Consultants. Be able to identify & assess available technologies and recommend solution options according to the business requirements & drivers. You are expected to collaborate with clients, team members and service managers to clearly understand business journeys and requirements and how they can be simplified and optimised. You may serve as team member in some projects or Functional Team Lead on others; as such, you will work well in partnership with the team and be equally able to work independently. You will be able to do, teach & evangelise all things in the field of ERP and bring colleagues and stakeholders on the journey to best-of-class solutions.\n\n\n\nYour responsibilities:\n\nAbility to perform the role of Functional Consultant on Microsoft Dynamics365 Business Central, Enhancements and Projects including the facilitation of requirement gathering sessions.\nAbility to drive excellence in the delivery of support in this domain, partnering with our internal team and external partners, including successful knowledge transfer to this team and mentoring of partner colleagues.\nAbility to communicate effectively at all levels within the organisation, our implementation partners and pool of freelancers\nDesign and implement best practice business / Dynamics365 Business Central solutions appropriate to the requirements, business needs and strategic direction of the client and the organization\nManage and own enhancements and incidents through to completion adhering to Fiducia Management Consultants standards.\nTo keep up to date with Microsoft Dynamics 365 Business Central capabilities within the whole solution offering\nDelivery of complex integrated solutions\nPreparation of specifications, estimates and solution documentation to support work completed\nFostering and maintaining good relationships with clients and colleagues to meet expected customer service quality\nMay be required to coach and manage the other members within the team\nManaging third party suppliers and delivery of contracted work\nTaking ownership of continuous improvement within the ERP solution\n\nWho are we looking for:\n\nExperience of multiple, full lifecycle project implementations.\nExcellent experience in Microsoft Dynamics 365 Business Central functional configuration and technical support.\nExtensive experience in designing Dynamics 365 Business Central and integrated solutions.\nDeep knowledge & experience in integrating with other applications.\nA creative and innovative mindset to your work and stakeholders while ensuring the highest quality work delivered on time.\nDesire for self-improvement, results and growth oriented mind together with a strong work ethic.\nCertifications in Microsoft Dynamics 365 Business Central or a related field is a plus\nExcellent communication skills & command of English, preferably also Mandarin\n\nPlease refer to our Company Website:\u00a0http://www.fiducia-china.com. Please submit your full CV with expected salary, plus availability to us. If you do not hear from us within four weeks, you can assume that your application is unsuccessful.", "employment_types": ["Full Time", "Permanent"], "selling_points": ["ERP strategy, implementation & operation", "Minimum 3 years related experience", "12-mth Salaries +2 Behavioural Goals Bonuses"], "locations": ["Wan Chai"], "categories": ["Accounting", "Consulting", "Professional Services", "Business Consultancy", "Information Technology (IT)", "Product Management / Business Analyst"], "post_time": "2022-01-14T04:28:03Z", "salary": {"currency": null, "max": null, "min": null, "period": "monthly", "term": null}, "salary_visible": false, "title_keywords": ["consultant"], "responsibilities": ["collaborate with", "consulting", "operations", "microsoft dynamics", "quality", "design", "communication", "business process", "customer service", "deploy", "designing", "maintaining", "configuration", "teams", "implementation", "develop", "company website", "management", "specifications", "documentation", "third party", "communicate with", "technical support"], "requirements": {"degrees": [], "majors": [], "languages": ["english", "mandarin"], "language_level": ["excellent"], "hard_skills": ["plus", "fun", "erp", "documentation", "focus"], "soft_skills": ["communication skills", "work independently", "creative", "responsible", "deep", "accountable", "collaborative", "innovative", "detail-oriented", "team member", "customer service", "organisation", "work ethic", "focus", "proactive", "extensive"], "languages_combined": [{"language": "english", "language_level": ["excellent"]}, {"language": "mandarin", "language_level": ["excellent"]}]}, "experience_required": {"duration": [], "field": ["business", "it", "design", "team"]}}, {"job_id": "100003009044526", "location_code": "hk", "company": "Grant Thornton Hong Kong Limited", "job_title": "Assistant Manager / Senior Associate / Associate (Forensic Technology) \u2013 Advisory", "description": "Responsibilities:\n\nPerform forensics technology and eDiscovery services including preserving, imaging, processing and reviewing electronic data\nIdentify and capture anomalies and suspicious information within structured and unstructured data, visualize and present findings to client\nAssist the teams on financial due diligence and forensic investigation assignments requiring data analytics support\nAssist in forensic technology and data analytics practice development\n\nRequirements:\n\nBachelor's degree, preferably in Computer Science, Information Systems, and Engineering or equivalent\n4+ years (Assistant Manager) / 2+ years experience (Senior Associate) relating to Forensic Technology, with experience in using EnCase, FTK, Nuix and/or Relativity\nStrong analytical mindset and solid problem solving skills\nExperience in forensic technology case management for Assistant Manager role\nExcellent written and oral communication skills in English, Cantonese and Mandarin Chinese\nWilling to travel on business needs\nCandidates with less experience will be considered as Associate\nPreferred:\n\n\nPossess relevant professional qualification or vendor related certification such as GCFA, GCFE, EnCE, RCA, etc\nQualified or working towards qualification such as CPA, CFE, CIA, CISSP\nExperience in Data Analytics/AI investigation tools is a definite advantage\nExperience with scripting language such as Python or VBA\n\n\n\n\nWe offer attractive remuneration packages including medical insurance and a 5-day working week. Interested applicants please submit your full resume, current and expected salary by clicking \u201cAPPLY NOW\u201d or by post to The Human Resources Department, Grant Thornton Hong Kong Limited, 11th Floor, Lee Garden Two, 28 Yun Ping Road, Causeway Bay, Hong Kong. www.grantthornton.cn\n\nNote:\u00a0\u00a0\u00a0\u00a0\u00a0\u00a0 You may consider your application unsuccessful if you do not hear from us within 8 weeks. Your personal data will be destroyed within one month after completion of the recruitment process.", "employment_types": ["Full Time", "Permanent"], "selling_points": ["Degree holder in CS, IS, Engineering", "4+ / 2+ years exp relating to Forensic Technology", "5-day working week"], "locations": ["Causeway Bay"], "categories": ["Accounting", "Consulting", "Others", "Information Technology (IT)", "IT Auditing"], "post_time": "2022-01-13T04:27:10Z", "salary": {"currency": null, "max": null, "min": null, "period": "monthly", "term": null}, "salary_visible": false, "title_keywords": ["assistant manager", "associate", "senior associate"], "responsibilities": ["due diligence", "teams", "investigation", "data"], "requirements": {"degrees": ["degree", "bachelor"], "majors": ["engineering", "computer science"], "languages": ["cantonese", "english", "mandarin chinese"], "language_level": ["excellent"], "hard_skills": ["vba", "ai", "data analytics", "vendor", "cpa", "python", "problem solving skills"], "soft_skills": ["communication skills", "problem solving skills", "oral"], "languages_combined": [{"language": "cantonese", "language_level": ["excellent"]}, {"language": "english", "language_level": ["excellent"]}, {"language": "mandarin chinese", "language_level": ["excellent"]}]}, "experience_required": {"duration": ["2+ years", "4+ years"], "field": ["management"]}}, {"job_id": "100003009043366", "location_code": "hk", "company": "BDO", "job_title": "Senior Associate / Associate \u2013 Specialist Advisory Services (Insolvency)", "description": "Responsibilities\n\nAssist the daily management of insolvency assignments\nConduct the investigation of the financial affairs of the insolvent companies/bankrupts\nDraft reports/documents to the Court, the Official Receiver and other stakeholders to compile with the statutory requirements\nSupport various restructuring and insolvency assignments, including business recovery, corporate insolvency administration, receivership and personal bankruptcy\n\nRequirements\u00a0\n\nDegree holder, major in accounting, finance or other related disciplines\nAt least\u00a01 year of relevant experience in\u00a0restructuring and insolvency\u00a0\nAble to think strategically, with good business sense and commercially awareness\nSound financial and business analytical skills\nExcellent command of both written and spoken English and Chinese. Proficiency in Putonghua is definitely an advantage\nGood report writing skills with the ability to write concise and well-structured reports in English or Chinese\nRelevant PRC exposure and experience are highly preferable\nPosition offered will commensurate with the experience of the right candidate\n\nWe are an equal opportunity employer, and offer excellent prospects and career development for the right candidate.\u00a0 Interested parties please send your application with full career history, current and expected salary by clicking\u00a0Apply Now\u00a0button below.\n\nApplications will be treated in strict confidence. Personal data collected will be used for recruitment purposes only.", "employment_types": ["Full Time", "Permanent"], "selling_points": ["Support in insolvency & restructuring assignments", "Conduct investigation, draft reports & documents", "Excellent career prospects"], "locations": ["Sheung Wan"], "categories": ["Accounting", "Consulting", "Others", "Professional Services", "Business Consultancy"], "post_time": "2022-01-12T11:03:00Z", "salary": {"currency": null, "max": null, "min": null, "period": "monthly", "term": null}, "salary_visible": false, "title_keywords": ["specialist", "senior associate", "associate"], "responsibilities": ["management", "investigation", "statutory requirements", "reports", "administration"], "requirements": {"degrees": ["degree holder"], "majors": ["related disciplines", "finance", "accounting"], "languages": ["putonghua", "english", "chinese"], "language_level": ["advantage", "excellent", "proficiency", "good"], "hard_skills": ["writing skills", "analytical skills"], "soft_skills": ["business sense", "writing skills", "analytical skills", "think strategically", "structured"], "languages_combined": [{"language": "putonghua", "language_level": ["proficiency", "advantage"]}, {"language": "english", "language_level": ["excellent", "good"]}, {"language": "chinese", "language_level": ["excellent", "good"]}]}, "experience_required": {"duration": ["at least 1 year"], "field": ["relevant experience"]}}, {"job_id": "100003009049431", "location_code": "hk", "company": "Wall CPA Limited", "job_title": "Associate \u2013 Audit & Assurance", "description": "Responsibilities:\n\nParticipate in engagements relating to audit, accountancy, tax compliance, merger and acquisition and providing support on ad hoc projects.\n\n\u00a0Requirements:\n\nDiploma in Accounting or above\nStudent member of a recognized accountancy body, preferably HKICPA\nMinimum 1 year relevant working experience (Recent graduate will be considered)\nWilling to work under pressure and travel\nExcellent command of written and spoken English, Cantonese and Mandarin\nImmediately available is preferred\n\nSalary will be commensurate with qualification and experience. We offer generous fringe benefits to the right candidate, including medical scheme, a 5-day work week, annual performance bonus, and study and examination leave. Interested parties please apply with application letter, full resume, expected salary and date of availability.\n\n\u00a0\u201cPersonal data collected will be used for recruitment purposes only.\u201d", "employment_types": ["Full Time", "Permanent"], "selling_points": ["5-day work", "Fresh Graduates are welcome to apply", "HKICPA Authorized Employer"], "locations": ["Wan Chai"], "categories": ["Accounting", "Accountant", "Audit", "Consulting"], "post_time": "2022-01-14T08:37:22Z", "salary": {"currency": null, "max": null, "min": null, "period": "monthly", "term": null}, "salary_visible": false, "title_keywords": ["associate"], "responsibilities": ["tax", "compliance", "audit", "ad hoc projects", "providing support"], "requirements": {"degrees": ["diploma"], "majors": ["accounting"], "languages": ["cantonese", "english", "mandarin"], "language_level": ["excellent"], "hard_skills": ["scheme", "hkicpa"], "soft_skills": ["work under pressure"], "languages_combined": [{"language": "cantonese", "language_level": ["excellent"]}, {"language": "english", "language_level": ["excellent"]}, {"language": "mandarin", "language_level": ["excellent"]}]}, "experience_required": {"duration": ["minimum 1 year"], "field": ["relevant working experience"]}}, {"job_id": "100003009049284", "location_code": "hk", "company": "Baker Tilly Hong Kong", "job_title": "Senior - Tax Services (Elite program)", "description": "Exposure to clients in a wide spectrum of industries on tax consulting assignments\nCompetitive remuneration package and benefits\nFast-track career path\n\nRequirements:\n\nGood honors degree in Accountancy, Business or related disciplines\nA qualified member of HKICPA\nExcellent writing and oral skills in English, with good grades in the public examinations\nCandidate with IELTs score of 8 or above will be considered favourably\nFluency in spoken English, Cantonese and Putonghua. Knowledge of other languages is a plus\nAn independent worker who excels under pressure\nAt least 3\u00a0years solid and relevant Hong Kong tax experience working\u00a0in a sizeable CPA firm in Hong Kong or the Hong Kong Inland Revenue\n\nWe offer an attractive remuneration package, interesting job exposure, excellent career growth prospects in a warm and friendly atmosphere. Our continuing expansion and growth offer numerous development opportunities to the incumbents.\u00a0\n\nIf you consider yourself the appropriate choice, please forward your CV and salary expectations with the application form\u00a0to the Human Resources Department, 2/F 625 King\u2019s Road, North Point, Hong Kong or by\u00a0clicking \u201cApply Now\u201d.\u00a0\u00a0\u00a0\n\nDownload Application Form\n\nSelected candidates will be notified by phone for interview arrangements within 6 weeks. Applications of unsuccessful candidates will be deleted immediately after screening.\n\nPersonal data provided by job applicants will be used strictly in accordance with the Employer's Personal Data Policies, a copy of which will be provided upon request.\n\nBaker Tilly Hong Kong\u00a0is a leading firm of certified public accountants and business advisers, specialising in providing clients with a range of integrated services. Our firm is driven by 300 directors and professional staff based in Hong Kong.", "employment_types": ["Full Time", "Permanent"], "selling_points": ["A qualified member of HKICPA", "3 years Hong Kong tax experience", "Fluency in spoken English, Cantonese and Putonghua"], "locations": ["Quarry Bay"], "categories": ["Accounting", "Consulting", "Taxation", "Professional Services", "Business Consultancy"], "post_time": "2022-01-14T08:22:41Z", "salary": {"currency": null, "max": null, "min": null, "period": "monthly", "term": null}, "salary_visible": false, "title_keywords": [], "responsibilities": ["tax", "consulting"], "requirements": {"degrees": [], "majors": [], "languages": [], "language_level": [], "hard_skills": [], "soft_skills": [], "languages_combined": []}, "experience_required": {"duration": [], "field": []}}, {"job_id": "100003009048295", "location_code": "hk", "company": "Perun Consultants Limited", "job_title": "Forensic Accounting \u2013 Manager / Assistant Manager / Associate", "description": "\nPerun Consultants is the leading independent advisory firm with offices in Hong Kong and Singapore. We specialise in provision of high quality services in the areas of forensic accounting, corporate advisory, restructuring, turnaround and liquidation appointments. At Perun, we promote a work-life balance, value individualism and embrace the differences.\n\nWe are currently seeking an ambitious and qualified candidate with the following attributes to join our Hong Kong office as a Forensic Accounting Manager / Assistant Manager / Associate:\n\n\nBatchelor\u2019s degree in Accounting, Finance, Computer Science, Information Technology, Law or other Business-related discipline preferred.\nCA, CPA, ACCA or equivalent. Consideration will also be given to part qualified candidates, with support given to complete the qualification process;\n4+ years relevant experience for the position of Assistant Manager and 2+ years relevant experience for the position of Associate.\n\u2022 Eager to learn and motivated to succeed;\n\u2022 Proficient in detailed financial and commercial analysis and be able to identify potential areas of sensitivity;\n\u2022 Self-motivated, proactive and mature;\n\u2022 Proficient in Microsoft office applications;\n\u2022 Strong financial, business analytical and report writing skills; and\n\u2022 Excellent written and oral communication skills in both English and Mandarin Chinese, including both technical and business writing.\nThe successful candidate will possess technical knowledge of financial accounting practices and be able to demonstrate experience (commensurate with the applicable employment grade) with the following:\n\nAssessment and quantification of losses and potential damage awards;\nValuation and appraisal of assets;\nDesign and evaluation of financial forecast models;\nReport writing;\nProviding litigation support services, working closely with legal counsel, law enforcement officers and regulatory agencies; and\nAssisting with internal and external investigations.\nInsolvency-related experience; and\nAssisting with internal and external investigations.\n\nIn addition to the above role, we are always interested in hearing from proactive, commercially minded, individuals at all levels of seniority and experience looking to work in a dynamic and flexible environment.\n\nWe offer a competitive remuneration package where you will be rewarded for your individual and team performance. We are committed to being an inclusive employer and are happy to consider flexible working arrangements.\nTo apply, contact us at Apply Now .", "employment_types": ["Full Time"], "selling_points": [], "locations": ["Central"], "categories": ["Accounting", "Consulting", "Professional Services", "Business Consultancy"], "post_time": "2022-01-14T06:09:56Z", "salary": {"currency": null, "max": null, "min": null, "period": "monthly", "term": null}, "salary_visible": false, "title_keywords": ["assistant manager", "associate", "accounting", "manager"], "responsibilities": ["valuation", "analysis", "support services", "quality", "design", "communication", "forecast", "evaluation", "report"], "requirements": {"degrees": ["degree"], "majors": ["law", "finance", "information technology", "business", "computer science", "accounting"], "languages": ["mandarin chinese", "english"], "language_level": ["excellent"], "hard_skills": ["acca", "microsoft office", "analysis", "writing skills", "cpa", "dynamic"], "soft_skills": ["flexible", "communication skills", "self-motivated", "oral", "independent", "sensitivity", "interested in", "mature", "writing skills", "eager to learn", "motivated", "dynamic", "proactive", "detailed"], "languages_combined": [{"language": "mandarin chinese", "language_level": ["excellent"]}, {"language": "english", "language_level": ["excellent"]}]}, "experience_required": {"duration": ["2+ years", "4+ years"], "field": ["related", "accounting", "relevant experience", "financial"]}}, {"job_id": "100003009043357", "location_code": "hk", "company": "BDO", "job_title": "Senior Associate / Associate - Risk Advisory Services (Ref : RAS)", "description": "Responsibilities:\n\nParticipate in internal audits review and/or advisory engagements\u00a0\nAssist to provide input to management leaders on suggestions to improve client internal controls\nPrepare\u00a0accurate documentation and high quality reports\nMaintain relationships with key client personnel to obtain an understanding of business operations, processes and functions\nSupport and act towards the BDO Global Vision\nBe committed to act with\u00a0the firm\u2019s core values and competency expectations\n\n\u00a0Requirements:\n\nUniversity graduate, preferably major in accounting or related disciplines\nAt least 1 year of relevant experience in internal audit and advisory services; preferably gained from sizable accounting firm\nCPA, CIA and/or CISA qualified or finalist\u00a0is preferred\nExcellent communication and interpersonal skills\nExcellent command of both written and spoken English and Chinese; including Mandarin\nAbility to handle\u00a0multi-task successfully while working independently or within a group environment\u00a0\nProven ability to work in a deadline-driven environment and willing to travel frequently\nBe passionate for providing exceptional quality service and striving for exceeding clients\u2019 expectations\nFresh graduate will also be considered\n\nWe are an equal opportunity employer, and offer excellent prospects and career development for the right candidate.\u00a0 Interested parties please send your application\u00a0with full career history, current and expected salary by clicking\u00a0Apply Now\u00a0button below.\n\nApplications will be treated in strict confidence. Personal data collected will be used for recruitment purposes only.", "employment_types": ["Full Time", "Permanent"], "selling_points": ["Responsible for Internal Audit / Control Review", "Maintain relationships with key client", "Excellent Career Opportunity"], "locations": ["Sheung Wan"], "categories": ["Accounting", "Audit", "Consulting", "Professional Services", "Legal & Compliance"], "post_time": "2022-01-12T10:59:52Z", "salary": {"currency": null, "max": null, "min": null, "period": "monthly", "term": null}, "salary_visible": false, "title_keywords": ["senior associate", "associate"], "responsibilities": ["maintain relationships", "management", "documentation", "operations", "review", "quality", "reports", "audits"], "requirements": {"degrees": ["university graduate", "fresh graduate"], "majors": ["related disciplines", "accounting"], "languages": ["english", "chinese", "mandarin"], "language_level": ["excellent"], "hard_skills": ["cpa"], "soft_skills": ["passionate", "independently", "multi-task", "communication and interpersonal skills", "driven"], "languages_combined": [{"language": "english", "language_level": ["excellent"]}, {"language": "chinese", "language_level": ["excellent"]}, {"language": "mandarin", "language_level": []}]}, "experience_required": {"duration": ["at least 1 year"], "field": ["relevant experience", "audit"]}}, {"job_id": "100003009046918", "location_code": "hk", "company": "DKNT CPA Limited", "job_title": "Semi-Senior / Audit Senior", "description": "Major Responsibilities & Duties\n\nLead client audit engagements, including planning, executing, directing and completing financial audits\nObtain a thorough understanding of HKSQC1, HKSAs and common audit procedures and techniques\nTrain and mentor juniors on audit process\nResearch and analyse financial statements and audit related issues\nAcquire a working knowledge of the client's business\nProactively interact with key client's management to gather information, resolve problems, and make recommendations for business and process improvements\nPerform other job related duties as requirered\n\nRequirements & Qualifications\nThe successful candidate will possess the following basic qualifications:-\n\nExcellent project management, analytical, interpersonal communication skills\nLeadership, training and mentoring skills\nProfessionalism and dependability attitude\nDedicated to superior client service\nStrong organisational skill and attention to details\nMinimum 2-3 years recent audit work experience\nRelevant Accounting degree\nQualified or working towards CPA certification\n\nBenefits\nWe provide a pleasant working environment with modern I.T. facilities.\u00a0 We offer 5-day week, staggered office hours, on-the-job and in-house training, leadership development, study leaves, examination support and good promotion prospect.", "employment_types": ["Full Time"], "selling_points": ["offer 5-day week, staggered office hours,", "on-the-job and in-house training", "leadership development, study leaves,"], "locations": ["Wan Chai"], "categories": ["Accounting", "Audit", "Consulting", "Others"], "post_time": "2022-01-14T01:43:15Z", "salary": {"currency": null, "max": null, "min": null, "period": "monthly", "term": null}, "salary_visible": false, "title_keywords": [], "responsibilities": ["make recommendations", "management", "procedures", "audit", "financial statements", "executing", "analyse", "audits", "planning"], "requirements": {"degrees": ["degree"], "majors": ["accounting"], "languages": [], "language_level": [], "hard_skills": ["project management", "basic", "cpa"], "soft_skills": ["communication skills", "project management", "attention to details", "leadership", "interpersonal", "superior"], "languages_combined": []}, "experience_required": {"duration": ["minimum 2-3 years"], "field": ["audit"]}}, {"job_id": "100003009050209", "location_code": "hk", "company": "Capital Advisory Limited", "job_title": "Associate \u2013 Merger & Acquisition", "description": "Responsibilities\nHandle finance projects including IPOs, mergers and acquisitions, and other management advisory projects\n\u00a0Support and communicate in the internal control, auditing, accounting and tax assignments of the projects\nAssist in deals support, such as reviewing target financials, business operation materials and involve in liaising deals structure\nLiaise with other professional parties to support the implementation of projects\n\u00a0Perform ad-hoc assignments\n\nRequirements\n\nDegree holder or above in Accounting, Finance, Business Administration is preferred\n1-2 years working experience in accounting firm\n\u00a0Good command of spoken and written English, Mandarin and Cantonese\n\u00a0Proficiency in Excel\n\u00a0Hardworking and willing to learn new knowledge on top of accounting\n\u00a0Immediate available preferred\nFresh graduates will also be considered\u00a0\nA good opportunity to allow audit junior to transit to capital market\n\nWe offer\n\n\u00a05-days work\n\u00a0Study and examination leave\n\u00a0Discretionary bonus\nDouble pay\nAnnual leave\n\nInterested parties please send your resume with expected salary and availability by clicking \"Apply Now\". All personal data collected will be used for recruitment purpose only.", "employment_types": ["Full Time", "Permanent"], "selling_points": ["Study and examination leave;  5-days work", "Discretionary bonus; Annual leave ; Bank holiday", "Sheung Wan MTR station; Double pay"], "locations": ["Sheung Wan"], "categories": ["Accounting", "Consulting", "Banking / Finance", "Dealing & Trading", "Equities / Capital Markets"], "post_time": "2022-01-14T09:56:47Z", "salary": {"currency": "HKD", "max": 24999, "min": 20000, "period": "monthly", "term": null}, "salary_visible": true, "title_keywords": ["associate"], "responsibilities": ["tax", "business operation", "management", "ad-hoc assignments", "implementation of projects", "liaise with", "auditing", "internal control"], "requirements": {"degrees": ["degree holder"], "majors": ["finance", "accounting", "business administration"], "languages": ["cantonese", "english", "mandarin"], "language_level": ["good command"], "hard_skills": ["excel"], "soft_skills": ["willing to learn", "hardworking"], "languages_combined": [{"language": "cantonese", "language_level": ["good command"]}, {"language": "english", "language_level": ["good command"]}, {"language": "mandarin", "language_level": ["good command"]}]}, "experience_required": {"duration": ["1-2 years"], "field": ["accounting"]}}, {"job_id": "100003009045913", "location_code": "hk", "company": "R & T Corporate Services Limited", "job_title": "Accounts Clerk", "description": "Key duties include\n\nTo prepare financial statement and other financial reports for client\nTo preform ad-hoc assignments as assigned\n\nRequirement\n\nDiploma or Degree holder in accountancy or related courses\nWith accounting experience\u00a0is preferred\nDemonstrable rapid learning capability and able to work under pressure\nGood\u00a0communication and interpersonal skills\nProficiency in written and spoken English and Chinese (including Mandarin) is essential\nProficiency in MS office (especially for Excel) and accounting softcopy e.g. MYOB / QuickBooks / Peachtree etc.\u00a0\u00a0\n\nWe offer:\n\n\u00a0\u00a0\u00a0\u00a0\u00a0\u00a0\u00a0\u00a0 5-day work\n\u00a0\u00a0\u00a0\u00a0\u00a0\u00a0\u00a0\u00a0 Annual leaves from 12 to 15 days according to length of services\u00a0\n\u00a0\u00a0\u00a0\u00a0\u00a0\u00a0\u00a0\u00a0 Paid birthday leave\n\u00a0\u00a0\u00a0\u00a0\u00a0\u00a0\u00a0\u00a0 Paid marriage leave\u00a0\n\u00a0\u00a0\u00a0\u00a0\u00a0\u00a0\u00a0\u00a0 Paid sick leave, medical insurance benefits\u00a0\n\u00a0\u00a0\u00a0\u00a0\u00a0\u00a0\u00a0\u00a0 Paid study and examination leaves for attending professional exams\n\u00a0\u00a0\u00a0\u00a0\u00a0\u00a0\u00a0\u00a0 Performance bonus\n\u00a0\u00a0\u00a0\u00a0\u00a0\u00a0\u00a0\u00a0 Overtime compensation benefit (covered non-office hours and non-working days)\n\u00a0\u00a0\u00a0\u00a0\u00a0\u00a0\u00a0\u00a0 Reimbursement of job-related seminars / course (such as HKICPA QP revision courses) \u00a0\n\u00a0\u00a0\u00a0\u00a0\u00a0\u00a0\u00a0\u00a0 Reimbursement of professional qualification membership fee / initial registration fee\u00a0\n\u00a0\u00a0\u00a0\u00a0\u00a0\u00a0\u00a0\u00a0 Pleasant working environment\n\nSalary will commensurate with qualification and experience.\u00a0\n\nIf you are\u00a0interested in taking the challenge and opportunity of enlarging the horizon of your professional career, please send your full resume and present / expected salary to us.\n\nWebsite: http://www.rnt-consulting.com\n\nPersonal data collected will be used for recruitment purpose only", "employment_types": ["Full Time"], "selling_points": ["Degree in Accounting or related courses", "5-day work, birthday leave, medical benefits", "Performance bonus (two times every year)"], "locations": ["Tsim Sha Tsui"], "categories": ["Accounting", "Accounting Clerk / Supervisor", "Consulting"], "post_time": "2022-01-13T09:05:36Z", "salary": {"currency": null, "max": null, "min": null, "period": "monthly", "term": null}, "salary_visible": false, "title_keywords": ["accounts clerk"], "responsibilities": ["financial statement", "financial reports", "ad-hoc assignments"], "requirements": {"degrees": ["diploma", "degree holder"], "majors": ["accountancy"], "languages": ["english", "chinese", "mandarin"], "language_level": ["proficiency"], "hard_skills": ["excel", "quickbooks", "peachtree", "rapid", "myob", "ms office"], "soft_skills": ["learning", "communication and interpersonal skills", "work under pressure"], "languages_combined": [{"language": "english", "language_level": ["proficiency"]}, {"language": "chinese", "language_level": ["proficiency"]}, {"language": "mandarin", "language_level": ["proficiency"]}]}, "experience_required": {"duration": [], "field": ["accounting experience"]}}, {"job_id": "100003009044021", "location_code": "hk", "company": "Michael Page", "job_title": "Senior Tax Accountant (US Tax)- Big 4 are Welcome (34-45K)", "description": "Our client is a very well known and sizable Design & Creative company in Hong Kong and they are currently seeking for a Senior Tax Accountant with 3-8 years of US Tax experience to join their team to handle US tax matters . If you are a candidate who is hoping for a stable yet challenging career, here is your chance!\n\nClient Details\n\nOur client is one of largest creativity companies in Hong Kong . They are now seeking for a high potential US Tax candidate to join their team. They are looking for an international tax passionate individual. Candidates with CPA qualification or not are also welcomed\n\nDescription\n\nGroup Tax filing. Providing Tax advices to regional partners and stakeholders\nFamiliar with US tax or other APAC regional tax standard\nTax research and analysis, also updating the changes of all region's tax regulations\nUS Tax planning and implementation\n\nProfile\n\nDegree in Accounting, Finance or a related discipline\nBig 4 or 2nd tier CPA Trained. 3-8 years of experiences within Tax\nGood command of written and spoken English\nGood team player, detail-oriented and responsible\n\nJob Offer\n\nCareer development opportunities\nSizable company\nVery stable working environment\n\nTo apply online please click the 'Apply' button below. For a confidential discussion about this role please contact Sunny Chan on +852 3602 2466.", "employment_types": ["Full Time", "Permanent"], "selling_points": ["Minimum OT", "International Tax", "Extremely Sizable Company"], "locations": ["Central & Western Area"], "categories": ["Accounting", "Consulting", "Taxation"], "post_time": "2022-01-13T02:48:53Z", "salary": {"currency": null, "max": null, "min": null, "period": "monthly", "term": null}, "salary_visible": false, "title_keywords": ["accountant"], "responsibilities": ["tax", "regulations", "analysis", "tax filing", "implementation", "design", "contact", "career development", "tax matters", "planning"], "requirements": {"degrees": ["degree"], "majors": ["finance", "accounting"], "languages": ["english"], "language_level": ["good command"], "hard_skills": ["cpa", "analysis"], "soft_skills": ["passionate", "good team player", "responsible", "detail-oriented", "stable", "creative"], "languages_combined": [{"language": "english", "language_level": ["good command"]}]}, "experience_required": {"duration": ["3-8 years"], "field": ["design", "team"]}}, {"job_id": "100003009043571", "location_code": "hk", "company": "Elite Partners Risk Advisory Services Limited", "job_title": "ESG ADVISORY CONSULTANT", "description": "In the world of raising awareness of the fragility and inter-connectedness of all of us, sustainability goes beyond elaborated slogans and pretty charts. At Elite Partners, we are committed to bring positive changes and to advocate these notions.\n\n\nJob Description\nWe are seeking a motivated and dynamic ESG Advisory Consultant\u00a0to join our growing sustainability advisory services practice.\u00a0In this entry-level, client-facing role, you will work directly with senior consultants to provide support on client engagements such as reviewing ESG (environmental, social and governance) data, ratings and rankings, and goal-setting for finance sector clients.\nThis is an excellent opportunity for a junior professional looking to work with an expert consulting team on interesting ESG projects for a wide range of HKEX listed corporations \u2014 helping them achieve positive and tangible social, environmental, and economic impact.\nRESPONSIBILITIES:\nConduct desk-based bench marking and research on clients, industries, and market trends. Analyze client documentation and identify improvement opportunities (gap analysis).\nSynthesize research findings into key themes, analyze information to develop conclusions and draft recommendations for client deliverables.\nSupport the development of corporate sustainability reports, including outlining, writing, editing, and proofreading content and other client communications.\nHold meetings, workshops and arrange questionnaires to develop and carry out stakeholder engagement exercises.\nAssist in general business development research, marketing, and other development tasks.\nREQUIREMENT:\nBachelor\u2019s degree in field Environmental Studies (Engineering, Science or Management) required, we consider a broad range of undergraduate majors and advanced degrees. Candidates with other qualifications but with keen and active interest in the field will also be considered. Fresh graduates will be considered.\nCompetent critical thinking and analytical skills, competent written and oral communication skills (English/Chinese).\nStrong interpersonal skills to interface effectively within multiple levels of consulting staff and client personnel.\nHigh level proficiency in use of Microsoft Office programs.\nAssist in building energy / carbon audits and energy simulation.\nA competitive remuneration package (including study and exam leave, travel allowance) & excellent career prospects will be offered to the right candidate. Elite Partners CPA Limited is accredited as an Authorized Employer by the HKICPA and provides quality training to prospective student members aiming to become Certified Public Accountants in years ahead.\u00a0\nInterest parties please send your full resume (both in English and Chinese) including your employment history and expected salary to Human Resources Department by email.\u00a0\nPersonal data collected will be used for recruitment purpose only.\n\n", "employment_types": ["Full Time", "Permanent"], "selling_points": ["Competent critical thinking and analytical skills", "Strong interpersonal skills", "Assist in general business development research"], "locations": ["Tsim Sha Tsui"], "categories": ["Accounting", "Accountant", "Consulting", "Financial Analyst"], "post_time": "2022-01-12T23:19:02Z", "salary": {"currency": null, "max": null, "min": null, "period": "monthly", "term": null}, "salary_visible": false, "title_keywords": ["consultant"], "responsibilities": ["provide support", "consulting", "data", "analysis", "develop", "proofreading", "reports", "documentation", "editing"], "requirements": {"degrees": ["degree", "bachelor"], "majors": ["science", "engineering"], "languages": ["english", "chinese"], "language_level": [], "hard_skills": ["certified public accountants", "microsoft office", "analytical skills", "cpa", "hkicpa"], "soft_skills": ["communication skills", "oral", "advanced", "competent", "keen", "analytical skills", "interpersonal skills", "active"], "languages_combined": [{"language": "english", "language_level": []}, {"language": "chinese", "language_level": []}]}, "experience_required": {"duration": [], "field": []}}, {"job_id": "100003009038254", "location_code": "hk", "company": "Early Light International (Holdings) Limited", "job_title": "Accountant / Senior Accountant", "description": "Responsibilities\n\n\nTo review financial information prepared by our subsidiaries or overseas consultants\nTo prepare monthly financial and management reports\nTo review tax filing documents\nTo support day-to-day project operations\nTo perform ad hoc assignments as required\u00a0\n\nRequirements\n\n\nDegree holder of accounting, finance or related disciplines\nStudent member of HKICPA or other professional accounting bodies is preferred\nWith minimum 4 years of relevant experience\nPreference will be given to those with exposure in working with property developers or related industries\u00a0\nGood command of spoken / written English and Cantonese, knowledge of Putonghua will be an advantage\nProficiency in MS Office and Chinese Word Processing\nSelf-motivated, responsible, well-organized, analytical and detail-oriented\nAble to work independently and meet the tight deadline\n5.5 days workweek\nThose with more experience will be considered for the post of\u00a0Senior Accountant\nInterested parties, please send your full resume with available date and\u00a0expected salary\u00a0by click \u201cApply Now\u201d. Please visit\u00a0www.earlylight.com.hk\u00a0\u00a0for more Company information.\u00a0", "employment_types": ["Full Time", "Permanent"], "selling_points": ["Review monthly mgt accounts & tax filing document", "Support day to day project operations", "Exposure in property developers preferred"], "locations": ["Sheung Shui"], "categories": ["Accounting", "Audit", "Consulting", "Financial Analyst"], "post_time": "2022-01-13T04:38:00Z", "salary": {"currency": null, "max": null, "min": null, "period": "monthly", "term": null}, "salary_visible": false, "title_keywords": ["accountant", "senior accountant"], "responsibilities": ["operations", "tax filing", "review", "management reports", "ad hoc assignments"], "requirements": {"degrees": ["degree holder"], "majors": ["related disciplines", "finance", "accounting"], "languages": ["cantonese", "putonghua", "english", "chinese"], "language_level": ["advantage", "proficiency", "good command"], "hard_skills": ["chinese word processing", "ms office", "hkicpa"], "soft_skills": ["self-motivated", "work independently", "responsible", "well-organized", "detail-oriented"], "languages_combined": [{"language": "cantonese", "language_level": ["advantage", "good command"]}, {"language": "putonghua", "language_level": ["advantage", "good command"]}, {"language": "english", "language_level": ["advantage", "good command"]}, {"language": "chinese", "language_level": ["proficiency"]}]}, "experience_required": {"duration": ["minimum 4 years"], "field": ["relevant experience", "senior accountant"]}}, {"job_id": "100003009053251", "location_code": "hk", "company": "APEC Group International Limited", "job_title": "Associate / Senior Associate \u2013 Risk Management Advisory (Internal Audit)", "description": "\u00a0Responsibilities\n\nProviding outsourced internal audit services to our clients across various industries locally and internationally;\nDevelop and review risk management frameworks and policies;\nAssist organizations to maintain effective and efficient controls, in order to manage organizational and strategic risks;\nConduct various advisory tasks such as enterprise risk management under ISO31000, COSO Framework etc., compliance reviews and controls related projects, such as PN21/PN2 under the Listing Rules of the Stock Exchange of Hong Kong;\nAssist in operational risk assessment process including collect and verify data for evaluation of operational risk level;\nParticipate and provide risk comments in product development and business projects;\nKeep abreast of market news including customer data protection and fraud prevention;\nAssisting our clients in the risk management process.\n\n\u00a0Requirements\n\nHigher Diploma\u00a0in Accounting/Risk Management/Corporate Governance or related disciplines;\n0-3 year's experience in internal audit and risk services;\nStudent member/ member of HKICPA/ACCA/CPA Australia/IIA or equivalent qualification is preferred;\nPractical experience in internal audit & risk management;\nAttention to detail, able to work independently and as a team member;\nGood communication, interpersonal and analytical skills;\nAbility to interact with all levels of personnel, including senior executives of client management;\nGood command of written English & Chinese, Mandarin is an advantage;\nProficient in MS Office, including Word & Excel\u00a0and Chinese word processing is required;\nAble to travel overseas and the PRC;\nFresh\u00a0graduates are welcome;\nImmediate available is preferred;\nCandidates with more experience will be considered as Senior Associate.\n\nWhat we offered?\n\n5-day work week\nImportant festivals early leave\nOvertime meal allowance\nTraveling allowance\nDiscretionary bonus\nFull-paid sick leave\nStudy & Exam leave\nGraduation leave\nWedding leave\nCompassionate leave\nMedical Insurance Scheme\nTraining reimbursement\n\n\nInterested parties please click \"APPLY NOW\" and send your full resume with your\u00a0working experience, academic and professional qualification, expected salary, and date of availability\u00a0to HR Department.\n\nPersonal data collected will be used for recruitment purpose only.\u00a0", "employment_types": ["Full Time", "Permanent"], "selling_points": ["Internal Control, Risk Management, Internal Audit", "5-day work week", "Excellent career promotion prospect"], "locations": ["Sheung Wan"], "categories": ["Accounting", "Accountant", "Consulting", "Professional Services", "Business Consultancy"], "post_time": "2022-01-17T06:32:16Z", "salary": {"currency": null, "max": null, "min": null, "period": "monthly", "term": null}, "salary_visible": false, "title_keywords": ["senior associate", "associate"], "responsibilities": ["management", "internal audit", "data", "business projects", "policies", "review", "compliance", "comments", "customer data", "develop", "maintain", "evaluation", "listing"], "requirements": {"degrees": ["diploma"], "majors": ["related disciplines", "risk management", "accounting"], "languages": ["english", "chinese", "mandarin"], "language_level": ["advantage", "good command", "proficient"], "hard_skills": ["excel", "acca", "chinese word processing", "word", "analytical skills", "cpa", "hkicpa", "ms office"], "soft_skills": ["work independently", "analytical skills", "communication", "attention to detail", "team member", "interpersonal"], "languages_combined": [{"language": "english", "language_level": ["advantage", "good command"]}, {"language": "chinese", "language_level": ["advantage", "good command", "proficient"]}, {"language": "mandarin", "language_level": ["advantage", "good command"]}]}, "experience_required": {"duration": ["0-3 year"], "field": ["risk management", "audit"]}}, {"job_id": "100003009054461", "location_code": "hk", "company": "Pathos Consultancy Limited", "job_title": "Business Analysis / Data Analytic Officer, 40K, Retail", "description": "The Company\nOne of the largest local leading conglomerates is hiring a FP&A candidate to focus on data analytics for their retail business.\n\nThe Role\n\n\nPerform budget and forecasting, revenue / cost / variance analysis, KPI and performance analysis\nConduct opex / capex analysis and project spending\n\u00a0Liaise with internal stakeholders in business cases, support feasibility study, and target / KPI evaluation\nEnsure company policies and compliance are aligned\nParticipate in ad-hoc projects\n\nYour Profile\n\n\nDegree holder in Finance / Statistics / Quantitative Analysis\nSolid experience in Data Science\nExperience from retail industry preferred\nExcellent communication skills\n\nApply Today\nTo apply online (Word attachment only), please click the 'Apply' button. Interested parties please apply with the most updated CV with expected salary and available date via JobsDB. Applicants who do not hear from us within 2 weeks may consider their applications unsuccessful.\n\nAbout Pathos\nWe are Pathos Consultancy Limited, a boutique recruitment firm based in Hong Kong strategically placing our candidates across all levels in permanent, temporary and contract roles.\u00a0 We specialize in IT and finance roles for banking, financial services and listed MNC sectors.", "employment_types": ["Full Time", "Permanent"], "selling_points": ["Data Analytics / Business Analysis", "FP&A", "Retail background"], "locations": ["Central"], "categories": ["Accounting", "Consulting", "Finance / Accounting Manager", "Financial Analyst"], "post_time": "2022-01-17T09:39:13Z", "salary": {"currency": null, "max": null, "min": null, "period": "monthly", "term": null}, "salary_visible": false, "title_keywords": ["officer"], "responsibilities": ["cost", "data", "policies", "analysis", "budget", "capex", "compliance", "opex", "variance analysis", "communication", "evaluation", "liaise with", "ad-hoc projects", "forecasting"], "requirements": {"degrees": ["degree holder"], "majors": ["finance", "statistics"], "languages": [], "language_level": [], "hard_skills": ["data analytics", "focus", "analysis", "word"], "soft_skills": ["communication skills", "focus"], "languages_combined": []}, "experience_required": {"duration": [], "field": ["retail industry"]}}, {"job_id": "100003009049972", "location_code": "hk", "company": "Sleek Hong Kong Limited", "job_title": "Business Development Executive", "description": "Who are we?\n\nSleek.com\u00a0is the SMEs operating system - we help them register companies in Singapore, Hong Kong, Australia & the United Kingdom and assist them with the management of their accounting, audit and taxes, in a 100% digital manner. We build cutting edge technology to automate manual work, and provide a delightful experience to our 6,000+ clients. Naturally, we are continuously looking for great people to join our dynamic team!\n\nWe are a team of 200+ builders from 17 countries, with offices in Singapore, Hong Kong, Australia, the United Kingdom & the Philippines, committed to delivering a great experience to our clients.\n\nAt Sleek, you will find a fast-paced environment focused on building great solutions, and endless opportunities for learning and knowledge sharing, whether it\u2019s around a coffee with your colleagues at the office, or via video calls with your peers based overseas!\n\nWe are looking for our next sales hustler, to help us grow!\n\nTo do what?\n\n\nEngage discussion with leads, close deals, pass them to the customer success teams\nHelp customers evaluate their needs and how Sleek can help them\nTake care of inbound inquiries and improve acquisition performance in conjunction with internal teams (product, marketing...)\nEngage discussion with partners/intermediaries eager to sell our solution to their audience, in order to build your own pipeline\nBuild and nurture a relationship with prospects, potential partners, and existing clients\n\n\n\nWho are you?\n\n\nA born hustler, networker by heart, hungry for business development\n\nSelf-driven with strategic mind to explore new opportunities and generate business with strong marketing sense\nA minimum of 4 years working with external clients (preferably SMEs), with a proven track record selling complex products/ systems in a simple way\nAn ability to understand Hong Kong\u2019s legal and accounting landscape\nExperience in sales CRM mandatory (Salesforce, Hubspot, Pipedrive\u2026)\nExcellent communication skills, presentation skills and analytical skills\nFluent in English, Cantonese and good in Mandarin\n\nHow about the Company & work environment?\n\nOur values are: Simplicity, Loyalty, Excellence, Entrepreneurship, Kindness\nWe take corporate social responsibility very seriously\u00a0at company level and absorb the yearly carbon footprint of all of our employees\nMulticultural team with 15+ nationalities and as many languages spoken internally!\nOne day of work from home per week\nA pool of HKD 7,000/year of Health & Benefits\nA great and vast high floor corner office in the heart of Central with an amazing view over Hong Kong and the mountains\n\nWhat you need to do now?\n\nSend your full resume with present and expected salary to HR Team by clicking \"APPLY NOW\". Candidates with less experiences will be considered if you are able to proof yourself. We regret that only shortlisted candidates will be notified.\n\n(Information provided will be treated in strict confidence and will only be used for recruitment-related purposes.)", "employment_types": ["Full Time"], "selling_points": ["Asia's fastest growing startup on its market", "Attractive performance bonus", "No ceiling commission"], "locations": ["Central"], "categories": ["Accounting", "Consulting", "Sales, CS & Business Devpt", "Business Development", "Sales - Sales Management"], "post_time": "2022-01-14T09:53:43Z", "salary": {"currency": null, "max": null, "min": null, "period": "monthly", "term": null}, "salary_visible": false, "title_keywords": ["business development executive"], "responsibilities": [], "requirements": {"degrees": [], "majors": [], "languages": [], "language_level": [], "hard_skills": [], "soft_skills": [], "languages_combined": []}, "experience_required": {"duration": [], "field": []}}, {"job_id": "100003009040317", "location_code": "hk", "company": "Taiping Reinsurance Company Limited", "job_title": "Senior Manager/Manager, Group Financial and Regulatory Reporting", "description": "To cope with the continuous growing business needs, we are actively looking for Senior Manager/Manager to join the Group financial and regulatory reporting team.\n\nKey Responsibilities\n\nPrepare and ensure month-end, quarter-end, interim and annual financial closing and reporting processes with good quality in a timely manner;\nLiaise with finance teams of the Group\u2019s subsidiaries and external auditors for any issues related to financial and accounting;\nParticipate in the property valuation matters;\nSupport the deliverables for the Audit Committee and the Board of Directors;\nProvide analytical review on the consolidated financial results;\nWork closely with IT department to support continuous process and system enhancements to drive efficiency and effectiveness of the closing process and\u00a0 the production of deliverables;\nParticipate in the implementation of IFRS 9, IFRS 17, and other new accounting standards;\nAchieve assigned functions accurately and efficiently;\nProvide guidance and technical advice to subsidiaries;\nPerform ad-hoc financial management tasks and duties as assigned.\n\n\u00a0Requirements\n\nBachelor\u2019s Degree in Accounting/Finance or above;\nCPA or equivalent qualification is a MUST;\nMin 10 (for Senior Manager)/ min 5 (for Manager) years strong and solid\u00a0 experience in financial reporting from Big 4 or listed companies;\nSolid experience in complex group consolidation preparation and group\u00a0 financial reporting;\nExcellent problem solving and analytical skills;\nExcellent multi-tasking skills;\nStrong communication skills in written and spoken English, Cantonese and Mandarin;\nStrong leadership skills, sound business acumen and able to work under pressure;\nAbility to support multi stakeholder information needs;\nProficiency in HFM, IFRS and PRC GAAP a plus;\nWork in Hong Kong with occasional travelling to Mainland is required.\n\nRecruitment statement\n\nThis position is posted by China Taiping Insurance Group Ltd (The parent company of Taiping Reinsurance Co., Ltd.) .\n\nFor qualified and interested candidates, please click the following job application link to apply.", "employment_types": ["Full Time", "Permanent"], "selling_points": ["Insurance Group, a HK listed company", "Min 10/min 5 years relevant accounting experience", "CPA, Big 4 candidates"], "locations": ["North Point"], "categories": ["Accounting", "Consulting", "Financial Analyst", "Banking / Finance", "Analyst"], "post_time": "2022-01-12T02:17:40Z", "salary": {"currency": null, "max": null, "min": null, "period": "monthly", "term": null}, "salary_visible": false, "title_keywords": ["senior manager", "manager"], "responsibilities": ["ad-hoc", "reporting", "valuation", "management", "technical advice", "review", "a timely manner", "quality", "month-end", "teams", "audit", "implementation", "liaise with", "provide guidance", "external auditors"], "requirements": {"degrees": ["degree", "bachelor"], "majors": ["finance", "accounting"], "languages": ["cantonese", "english", "mandarin"], "language_level": [], "hard_skills": ["ifrs", "plus", "analytical skills", "problem solving", "cpa", "acumen"], "soft_skills": ["communication skills", "multi-tasking skills", "leadership skills", "problem solving and analytical skills", "business acumen", "work under pressure"], "languages_combined": [{"language": "cantonese", "language_level": []}, {"language": "english", "language_level": []}, {"language": "mandarin", "language_level": []}]}, "experience_required": {"duration": [], "field": ["consolidation", "big 4", "financial"]}}, {"job_id": "100003009046537", "location_code": "hk", "company": "Michael Page", "job_title": "Senior Financial Analyst (retail), 39k", "description": "My client is one of the leading luxury retail brand worldwide and provides variety of luxury brands to the public. They are now hiring a Senior Financial Analyst focusing the FP&A duties to join them.\n\nClient Details\n\nMy client is one of the leading luxury retail brand worldwide and provides variety of luxury brands to the public. They are now hiring a Senior Financial Analyst focusing the FP&A duties to join them.\n\nDescription\n\nResponsibilities:\n\npreparing budgeting reports including annual budget and budgetary control of the company\nhandling the business unit performance analysis and evaluation\npreparing cash flow projections\nconducting financial modelling to different business unit\ndeveloping the feasibility reports and providing business recommendation and analysis\nassisting in ad hoc assignments\n\nProfile\n\nRequirements:\n\nBachelor degree of Accounting or other Finance Discipline\nCPA qualification\nMinimum 5 years of retail working experiences on FP&A\nGood command of both spoken and written English and Chinese\nDetail-minded, proactive and good communication skills\nProficiency with Microsoft Office Excel and PowerPoint\n\nJob Offer\n\nWe will offer competitive package to successful candidates:\n\nExcellent career path and opportunities\nMedical insurance\n\nTo apply online please click the 'Apply' button below. For a confidential discussion about this role please contact Queenie Yu on +852 2848 9578", "employment_types": ["Full Time", "Permanent"], "selling_points": ["5 years of retail experiences", "Sizable company", "MNC working cultrue"], "locations": ["Not Specified"], "categories": ["Accounting", "Consulting", "Financial Analyst", "Others"], "post_time": "2022-01-13T13:32:55Z", "salary": {"currency": null, "max": null, "min": null, "period": "monthly", "term": null}, "salary_visible": false, "title_keywords": ["senior financial analyst"], "responsibilities": ["control", "budgeting", "analysis", "budget", "developing", "cash flow", "reports", "ad hoc assignments", "evaluation"], "requirements": {"degrees": ["degree", "bachelor"], "majors": ["finance", "accounting"], "languages": ["english", "chinese"], "language_level": ["good command"], "hard_skills": ["powerpoint", "cpa", "excel", "microsoft office"], "soft_skills": ["detail-minded", "communication skills", "proactive"], "languages_combined": [{"language": "english", "language_level": ["good command"]}, {"language": "chinese", "language_level": ["good command"]}]}, "experience_required": {"duration": ["minimum 5 years"], "field": ["retail"]}}, {"job_id": "100003009035382", "location_code": "hk", "company": "D & Partners CPA Limited", "job_title": "Audit Trainee / Associate / Senior", "description": "Responsibilities\n\nHandle audit assignments independently;\nPreparing tax computation and schedules for tax compliance;\nHandle ad hoc matters assigned.\n\nRequirements\n\nHigher Diploma\u00a0in Accounting or related discipline;\nStudent member of HKICPA/ACCA/CPAA or other relevant professional bodies;\n0-3 year relevant experience (more relevant experience will be considered as Associate / Senior);\nExcellent skills in MS Excel and knowledge of computerized accounting system;\nExcellent analytical, interpersonal and communication skill;\nAble to work independently towards deadlines and work under pressure;\nGood command of written English & Chinese, Mandarin is an advantage;\nCandidate with less experience(fresh graduate)will be considered as Trainee;\nImmediate available is preferred.\n\n\u00a0What we offered?\n\n5-day work week\nImportant festivals early leave\nDiscretionary bonus\nFull-paid sick leave\nStudy & Exam leave\nGraduation leave\nWedding leave\nCompassionate leave\nMedical Insurance Scheme\nTraining reimbursement\n\nInterested parties please click \"APPLY NOW\" and send your full resume with your\u00a0working experience, academic and professional qualification, expected salary, and date of availability\u00a0to HR Department.\n\n\u00a0Personal data collected will be used for recruitment purpose only.", "employment_types": ["Full Time", "Permanent"], "selling_points": ["5-day work week", "Flexible working environment", "Excellent career promotion prospect"], "locations": ["Sheung Wan"], "categories": ["Accounting", "Accountant", "Audit", "Consulting"], "post_time": "2022-01-10T06:58:48Z", "salary": {"currency": null, "max": null, "min": null, "period": "monthly", "term": null}, "salary_visible": false, "title_keywords": ["associate", "trainee"], "responsibilities": ["tax", "ad hoc", "tax computation", "schedules", "compliance", "audit"], "requirements": {"degrees": ["diploma"], "majors": ["accounting"], "languages": ["english", "chinese", "mandarin"], "language_level": ["advantage", "good command"], "hard_skills": ["acca", "ms excel", "accounting system", "hkicpa"], "soft_skills": ["work independently", "communication skill", "interpersonal", "work under pressure"], "languages_combined": [{"language": "english", "language_level": ["advantage", "good command"]}, {"language": "chinese", "language_level": ["advantage", "good command"]}, {"language": "mandarin", "language_level": ["advantage", "good command"]}]}, "experience_required": {"duration": ["0-3 year"], "field": ["relevant experience"]}}, {"job_id": "100003009043595", "location_code": "hk", "company": "Gain Miles Assurance Consultants Limited", "job_title": "Employee Services - Investment Consultant", "description": "Job Highlights:\nStrong interests in finance & investment market\nSFC License 1, passed HKSI papers 1, 7 & 8\nJob Descriptions\nProactively manage mutual fund investment related matters for our individual clients as an consultant, including advise compliance, address day-to-day enquiries, provide timely market updates\nConduct MPF & financial education member briefing and one-to-one consultation sessions for our corporate clients with communication plan, related materials are provided from internal mid-office\nParticipate in business development activities and initiatives, leads will be provided\nAchieving annual sales target from mutual fund and MPF related product selling\nFollow best-practice work processes to ensure high quality of service and deliverables to clients and compliance to internal control process\nPerform any ad-hoc tasks as assigned\nRequirements\nBachelor\u2019s Degree or equivalent qualification\n1-2 years\u2019 experience in consulting / customer service / business development of Mutual Fund investment or MPF products is preferred\nHolder of Insurance, SFC and MPFA license is a must\nGood communication skills on written and spoken English and Chinese\nGood understanding of MPF and investment\nPossess strong sense of responsibilities and be able to work independently and act as a good team player\nWe Offer\n5-day work\nAttractive monthly basic salary and annual performance bonus\nComprehensive fringe benefits including but not limited to:\n16 working days annual leave up to 24 days depending on years of services\nFamily Care Leave, Maternity and Paternity Leave, Birthday leave, etc.\nFree Life and Health Insurance including both In and Out-patient benefits\nPension Benefits on top of MPF mandatory contribution\nAdequate training and good allowances\nJoin the GM Winning Team today!\nReady to fly high in your career? Interested parties please submit your full resume with availability, current and expected salary by e-mail via clicking \"Apply Now\".\nWritten test as well as aptitude test will be conducted with shortlisted candidates.\nAll personal data provided by job applicants are used only for recruitment purpose and will be treated in strict confidence. Unsuccessful applications will be properly disposed within 3 months.", "employment_types": ["Full Time"], "selling_points": ["5-day work", "Bachelor\u2019s Degree or equivalent qualification", "1-2 years\u2019 experience in consulting"], "locations": ["Not Specified"], "categories": ["Accounting", "Consulting", "Banking / Finance", "Investment", "Sales, CS & Business Devpt", "Business Development"], "post_time": "2022-01-12T23:19:17Z", "salary": {"currency": null, "max": null, "min": null, "period": "monthly", "term": null}, "salary_visible": false, "title_keywords": ["investment consultant"], "responsibilities": ["mpf", "sales target", "compliance", "quality", "ad-hoc tasks", "communication", "plan", "internal control"], "requirements": {"degrees": ["degree", "bachelor"], "majors": [], "languages": ["english", "chinese"], "language_level": ["good"], "hard_skills": [], "soft_skills": ["communication skills", "work independently", "good team player", "customer service", "sense of responsibilities"], "languages_combined": [{"language": "english", "language_level": ["good"]}, {"language": "chinese", "language_level": ["good"]}]}, "experience_required": {"duration": ["1-2 years"], "field": ["mpf", "consulting", "business development", "customer service", "investment"]}}, {"job_id": "100003009038686", "location_code": "hk", "company": "Midland Holdings Limited", "job_title": "Financial Controller", "description": "Responsibilities:\n\nOverseas finance and accounting functions of the Group in HK\nLead HK accounting team & be in charge of overall financial planning, consolidation & reporting, budgeting & forecasting, cost control, treasury management and taxation matters\nProvide strategic advice and suggestions on top management decisions based on financial analysis\nDevelop strategies, review business performance and assess opportunities which will support the group\u2019s continued expansion\nIdentify opportunities for process improvement and key cost driver for cost effectiveness\nFormulate internal control system, and establish/ optimize workflow for operational effectiveness and efficiency\nLiaise with external parties, such as auditors and bankers\n\nRequirements:\n\nQualified Accountant with a degree or above in Accounting or Finance or other related discipline\nAt least 10 years' of financial management experience with a minimum of 6 years at senior managerial level in listed / investment company\nMature, self-motivated, independent combined with good interpersonal and communication skills\nProficiency in both spoken and written English and Chinese\n\nCompetitive Salary will be offered to the right candidate. \u00a0For application, please update your resume by clicking \"APPLY NOW\" or complete the online application form which is available at\u00a0https://www.midland.com.hk/joinus/\u00a0and sent to the corresponding email address together with your full resume, present & expected salary.\n\nAll personal data collected will be used for recruitment purpose only. \u00a0Applicants not hearing from us within 2 months may consider their applications unsuccessful. \u00a0All personal data supplied will be kept for a reasonable period in accordance with the legal requirements.\n\nAs an Equal Opportunities Employer, we are committed to eliminating discrimination in employment. Our vacancy is open to all applicants meeting the basic entry requirement irrespective of their disability, sex, marital status, pregnancy, age, family status, sexual orientation and race.", "employment_types": ["Full Time", "Permanent"], "selling_points": ["Min 6yr at SENIOR managerial level in listed firm", "Develop strategies, review business performance", "Group FP&A,consolidation,cost control,treasury"], "locations": ["Cheung Sha Wan"], "categories": ["Accounting", "Consulting", "Financial Analyst", "Financial Controller"], "post_time": "2022-01-12T03:12:42Z", "salary": {"currency": null, "max": null, "min": null, "period": "monthly", "term": null}, "salary_visible": false, "title_keywords": ["financial controller"], "responsibilities": ["reporting", "management", "taxation", "develop strategies", "cost", "budgeting", "review", "external parties", "financial analysis", "cost control", "liaise with", "forecasting", "internal control", "planning"], "requirements": {"degrees": ["degree or above"], "majors": ["finance", "accounting"], "languages": ["english", "chinese"], "language_level": ["proficiency"], "hard_skills": ["basic"], "soft_skills": ["communication skills", "self-motivated", "independent", "mature", "committed", "interpersonal"], "languages_combined": [{"language": "english", "language_level": ["proficiency"]}, {"language": "chinese", "language_level": ["proficiency"]}]}, "experience_required": {"duration": ["at least 10 years", "minimum of 6 years"], "field": ["managerial", "management", "investment", "financial"]}}, {"job_id": "100003009037636", "location_code": "hk", "company": "Michael Page", "job_title": "Governance and Compliance Director - Business Service Provider", "description": "Summary\n\nWe value diversity at Lidl and this includes creating collaborative teams with colleagues with diverse experiences and backgrounds. Continue your career journey and make a difference with us here at Lidl!\n\nWhat will you do?\nConduct research regarding new relevant technologies and products\nUnderstand technical requirements and specifications to be applied into product development\nCollaborate with merchandising and sourcing teams and factories, regarding technical & engineering aspects of product development\nCoordinate daily development with teams in China, HK and EU Headquarter\u00a0\nProvide support to ad hoc assignment when necessary\u00a0\nWhat will you need?\nHigher Diploma or above\u00a0\n3 years of product development experience in relevant category\nGood sense of market trends\u00a0\nFamiliar with MS Office, Solidworks (or similar CAD software), Adobe Illustrator and Adobe Photoshop\nProactive, self motivated and able to work independently\u00a0\nGood sense for hard goods products UI / UX\u00a0\nAble to work together with cross functional teams\u00a0\nExperience with European companies/markets/designs\u00a0\nFactory experience/having experience dealing with suppliers\u00a0\nWhat do we offer?\n\nWe are dedicated to fostering a family-friendly culture and work environment and have been a proud member of the Caring Company Scheme since 2014. We are an equal opportunities employer and welcome applications from all candidates with the required skills and experience.\n\n\u00a0\nMarket Leading Remuneration Package:\n\nDouble pay and discretionary bonus\nChoice of MPF provider\nLife Insurance\nMedical Insurance\n\u00a0\n\nSupportive Environment:\n\nRental re-imbursement scheme\nOut-Of-Office leave for important appointments\nIn-house training courses\nTraining sponsorship scheme\nHealth Check\nVision Check\nExceptional maternity and paternity leave\nSupporting your child\u2019s education with advice from a leading education consultant\n\u00a0\n\nWork-Life Balance:\n\n5 day week\nCompetitive Annual Leave\nCharity, Community and Sporting Events\n\nWe are dedicated to fostering a family-friendly culture and work environment and have been a proud member of the Caring Company Scheme since 2014. We are an equal opportunities employer and welcome applications from all candidates with the required skills and experience.\n\n\u00a0\nMarket Leading Remuneration Package:\n\nDouble pay and discretionary bonus\nChoice of MPF provider\nLife Insurance\nMedical Insurance\n\u00a0\n\nSupportive Environment:\n\nRental re-imbursement scheme\nOut-Of-Office leave for important appointments\nIn-house training courses\nTraining sponsorship scheme\nHealth Check\nVision Check Supporting your child\u2019s education with advice from a leading education consultant\n\u00a0\n\nWork-Life Balance:\n\n5 day week\nCompetitive Annual Leave\nCharity, Community and Sporting Events", "employment_types": ["Full Time", "Permanent"], "selling_points": ["Exciting new headcount !", "Global Compliance role !", "Open to compliance consulting background !"], "locations": ["Not Specified"], "categories": ["Accounting", "Consulting", "Professional Services", "Business Consultancy", "Legal & Compliance"], "post_time": "2022-01-11T03:20:24Z", "salary": {"currency": "HKD", "max": 119999, "min": 90000, "period": "monthly", "term": null}, "salary_visible": true, "title_keywords": ["director"], "responsibilities": ["collaborate with", "provide support", "software", "ad hoc assignment", "merchandising", "teams", "coordinate", "specifications", "conduct research", "ui"], "requirements": {"degrees": ["higher diploma or above"], "majors": [], "languages": [], "language_level": [], "hard_skills": ["cad", "adobe photoshop", "adobe illustrator", "make", "solidworks", "ms office"], "soft_skills": ["work independently", "collaborative", "self motivated", "diverse", "proactive"], "languages_combined": []}, "experience_required": {"duration": ["3 years"], "field": ["product development"]}}, {"job_id": "100003009039144", "location_code": "hk", "company": "SHINEWING Financial Advisory Services Limited", "job_title": "Staff Accountant I (2022 Graduates) - Financial Advisory Services", "description": "Summary\n\nLidl are hiring an Artwork Officer\u00a0to join our Artwork & Packaging team.\u00a0The successful candidate will be provide support to the team for timely and accurate project completion,\u00a0ensure the packaging layout, label and manual are correct and is delivered on time.\n\nWhat will you do?\nHandle packaging layout, label, and manual proofreading for assigned projects\nLiaise with Merchandising team/Quality team on product details\nLiaise with artwork agencies and factories for project follow-up\nConduct quality control of artwork production\nManage quality of printing and packaging of suppliers / factories\nMaintain and update order-processing system\nWhat will you need?\nForm 6 or above\n2+ years relevant experience\nFamiliar with Adobe Illustrator, InDesign, Photoshop, Adobe Acrobat and MS Office\nPre-print knowledge is preferable\nExperience in printer house is preferable\nGood command in English (especially in writing), Mandarin and Cantonese\nPossess good project management skills and detail-oriented mindset to ensure timely production and delivery schedules are met\nGood communication, well-organised, considerate, independent, and self-motivated\nAble to work under pressure\nWhat do we offer?\n\nWe are dedicated to fostering a family-friendly culture and work environment and we are an equal opportunities employer and welcome applications from all candidates with the required skills and experience.\n\n\u00a0\nMarket Leading Remuneration Package:\n\nDouble pay and discretionary bonus\n\nChoice of MPF provider\n\nLife Insurance\n\nMedical Insurance\n\nSupportive Environment:\n\nRental re-imbursement scheme\n\nFlexible work arrangements\n\nIn-house training courses\n\nTraining sponsorship scheme\n\nHealth Check\n\nVision Check\n\nSupporting your child\u2019s education with advice from a leading education consultant\n\nWork-Life Balance:\n\n5 day week\n\nCompetitive Annual Leave\n\nCharity, Community and Sporting Events\n\nWe are dedicated to fostering a family-friendly culture and work environment and we are an equal opportunities employer and welcome applications from all candidates with the required skills and experience.\n\n\u00a0\nMarket Leading Remuneration Package:\n\nDouble pay and discretionary bonus\n\nChoice of MPF provider\n\nLife Insurance\n\nMedical Insurance\n\nSupportive Environment:\n\nRental re-imbursement scheme\n\nFlexible work arrangements\n\nIn-house training courses\n\nTraining sponsorship scheme\n\nHealth Check\n\nVision Check\n\nSupporting your child\u2019s education with advice from a leading education consultant\n\nWork-Life Balance:\n\n5 day week\n\nCompetitive Annual Leave\n\nCharity, Community and Sporting Events", "employment_types": ["Full Time", "Permanent"], "selling_points": ["M&A due diligence projects", "Bachelor Degree in accounting or business related", "Fresh graduate will be considered"], "locations": ["Causeway Bay"], "categories": ["Accounting", "Audit", "Consulting", "Professional Services", "Business Analysis / Data Analysis"], "post_time": "2022-01-11T08:50:04Z", "salary": {"currency": null, "max": null, "min": null, "period": "monthly", "term": null}, "salary_visible": false, "title_keywords": ["staff accountant"], "responsibilities": ["provide support", "conduct quality control", "schedules", "artwork production", "merchandising", "quality", "communication", "project management", "handle packaging layout", "proofreading", "maintain", "liaise with", "work under pressure"], "requirements": {"degrees": [], "majors": [], "languages": ["cantonese", "english", "mandarin"], "language_level": ["good command"], "hard_skills": ["ms office", "indesign", "adobe illustrator", "project management", "processing", "adobe acrobat", "photoshop"], "soft_skills": ["self-motivated", "independent", "project management skills", "timely", "detail-oriented", "communication", "well-organised", "accurate", "work under pressure"], "languages_combined": [{"language": "cantonese", "language_level": ["good command"]}, {"language": "english", "language_level": ["good command"]}, {"language": "mandarin", "language_level": ["good command"]}]}, "experience_required": {"duration": ["2+ years"], "field": ["relevant experience"]}}, {"job_id": "100003009046431", "location_code": "hk", "company": "Up Recruitment Limited", "job_title": "Internal Audit Manager (Securities Firm)", "description": "Summary\n\nLidl Asia are hiring for a (Senior) Analytics Specialist in our Business Controlling team who will provide analytics driven solutions by adopting analytical models and data science methods.\n\nWhat will you do?\nBe responsible for the quality of your solutions and results, while accounting for best practices from our Global Analytics team during implementation.\nStructure and derive results of the analyses in creating targeted and understandable presentations.\nSupport Analytics in the country roll out and localisation of Analytics data products.\nProvide first-level support to stakeholders related to analytics questions.\nParticipate in deriving and solving analytical questions, either through deep-dive analyses or the development of local analytical solutions for the business.\nOperationalise the solutions by applying analytics methods, including processing and visualisation of results; the implementation can range from simple methods (e.g. exploratory data analysis, linear regression, cluster algorithms) to complex models (e.g. XGBoost, KNN). Usage and development of data sources and feature engineering are also part of the task.\nWhere applicable, be involved in the development of solution templates with other countries.\nImplement separate projects upon request which may result from operational requirements.\nWhat will you need?\n\nStrong knowledge in big-data technologies, machine learning, optimisation, and data mining methods (e.g. with Python, R)\n\nStatistical knowledge and predictive modelling\n\nProven experience of applying time-series / regression analysis, clustering-methods, and effectiveness testing (A-/B-hypotheses testing) to solve diverse business problems\n\nStrong ability to understand complex problems and scenarios, and analysing them in detail\n\nAble to work to tight deadlines and to deliver accurate results\n\nExcellent communication skills and teamwork\n\nSelf-motivated and proactive individual with a can-do attitude and the ability to work on projects and solve problems independently\n\nWhat do we offer?\n\nWe are dedicated to fostering a family-friendly culture and work environment and we are an equal opportunities employer and welcome applications from all candidates with the required skills and experience.\nMarket Leading Remuneration Package:\n\nDouble pay and discretionary bonus\nChoice of MPF provider\nLife Insurance\nMedical Insurance\n\nSupportive Environment:\n\nRental re-imbursement scheme\nFlexible work arrangements\nIn-house training courses\nTraining sponsorship scheme\nHealth Check\nVision Check\nSupporting your child\u2019s education with advice from a leading education consultant\n\nWork-Life Balance:\n\n5 day week\nCompetitive Annual Leave\nCharity, Community and Sporting Events\n\nWe are dedicated to fostering a family-friendly culture and work environment and we are an equal opportunities employer and welcome applications from all candidates with the required skills and experience.\nMarket Leading Remuneration Package:\n\nDouble pay and discretionary bonus\nChoice of MPF provider\nLife Insurance\nMedical Insurance\n\nSupportive Environment:\n\nRental re-imbursement scheme\nFlexible work arrangements\nIn-house training courses\nTraining sponsorship scheme\nHealth Check\nVision Check\nSupporting your child\u2019s education with advice from a leading education consultant\n\nWork-Life Balance:\n\n5 day week\nCompetitive Annual Leave\nCharity, Community and Sporting Events", "employment_types": ["Full Time", "Permanent"], "selling_points": ["CPA/ACCA/CIA/FRM qualification or equivalent", "Manage internal audit procedures and policies", "Identify control weakness & provide solutions"], "locations": ["Central & Western Area"], "categories": ["Accounting", "Audit", "Consulting", "Financial Analyst"], "post_time": "2022-01-13T11:06:11Z", "salary": {"currency": null, "max": null, "min": null, "period": "monthly", "term": null}, "salary_visible": false, "title_keywords": ["manager"], "responsibilities": ["clustering", "data", "analysis", "quality", "implementation", "presentations", "testing", "data analysis", "communication", "data mining"], "requirements": {"degrees": [], "majors": [], "languages": [], "language_level": [], "hard_skills": ["simple", "analysis", "presentations", "python", "data mining", "r", "processing"], "soft_skills": ["communication skills", "self-motivated", "proactive", "independently", "responsible", "can-do attitude", "deep", "teamwork", "diverse", "solve problems", "learning", "accurate", "driven"], "languages_combined": []}, "experience_required": {"duration": [], "field": ["business", "testing"]}}, {"job_id": "100003009042137", "location_code": "hk", "company": "Kingsway Personnel Ltd", "job_title": "Japanese Speaking Accounting Consultant (Japanese Accounting firm) ~25K (negotiable)", "description": "Summary\n\nWe value diversity at Lidl and this includes creating collaborative teams with colleagues with diverse experiences and backgrounds. Continue your career journey and make a difference with us here at Lidl!\n\nWhat will you do?\nWork closely with product sourcing and development teams to ensure the best offers to our customer\u00a0\nConduct product evaluations and benchmarking against relevant market items\u00a0\nNegotiations with supplier and project status responsibility\u00a0\nKeep track of purchase orders\u00a0\nConduct factory inspections and ensure product quality\u00a0\nEnsure on time shipment after production\u00a0\nWork closely with product sourcing and development teams to ensure the best offers to our customer\u00a0\nConduct product evaluations and benchmarking against relevant market items\u00a0\nNegotiations with supplier and project status responsibility\u00a0\nKeep track of purchase orders\u00a0\nConduct factory inspections and ensure product quality\u00a0\nEnsure on time shipment after production\u00a0\nWhat will you need?\nForm 6 or above (HKDSE)/ Form 7 or above (HKALE)\u00a0\nMinimum 3 years of merchandising experience in the European market in relevant category\nFamiliar with the related compliance standard is an advantage\u00a0\nPossess strong project management skills and detail orientated mindset to ensure timely production and delivery schedules are met\u00a0\nHigh degree of work ethics and integrity\u00a0\nMust be self motivated, self organized, responsible, hard working and independent\u00a0\nExperience in liaising with factories and suppliers\u00a0\nGood communication skills in both spoken and written English and Chinese\u00a0\nTravel required\u00a0\nWhat do we offer?\n\nWe are dedicated to fostering a family-friendly culture and work environment and have been a proud member of the Caring Company Scheme since 2014. We are an equal opportunities employer and welcome applications from all candidates with the required skills and experience.\n\n\u00a0\nMarket Leading Remuneration Package:\n\nDouble pay and discretionary bonus\nChoice of MPF provider\nLife Insurance\nMedical Insurance\n\u00a0\n\nSupportive Environment:\n\nRental re-imbursement scheme\nOut-Of-Office leave for important appointments\nIn-house training courses\nTraining sponsorship scheme\nHealth Check\nVision Check\nSupporting your child\u2019s education with advice from a leading education consultant\n\u00a0\n\nWork-Life Balance:\n\n5 day week\nCompetitive Annual Leave\nCharity, Community and Sporting Events\n\nWe are dedicated to fostering a family-friendly culture and work environment and have been a proud member of the Caring Company Scheme since 2014. We are an equal opportunities employer and welcome applications from all candidates with the required skills and experience.\n\n\u00a0\nMarket Leading Remuneration Package:\n\nDouble pay and discretionary bonus\nChoice of MPF provider\nLife Insurance\nMedical Insurance\n\u00a0\n\nSupportive Environment:\n\nRental re-imbursement scheme\nOut-Of-Office leave for important appointments\nIn-house training courses\nTraining sponsorship scheme\nHealth Check\nVision Check\nExceptional maternity and paternity leave\nSupporting your child\u2019s education with advice from a leading education consultant\n\u00a0\n\nWork-Life Balance:\n\n5 day week\nCompetitive Annual Leave\nCharity, Community and Sporting Events", "employment_types": ["Full Time", "Permanent"], "selling_points": ["Business level in Japanese", "Provide accounting services & taxation advice", "~25K (negotiable) with guarantee bonus"], "locations": ["Not Specified"], "categories": ["Accounting", "Accountant", "Accounting Clerk / Supervisor", "Consulting"], "post_time": "2022-01-12T06:21:20Z", "salary": {"currency": null, "max": null, "min": null, "period": "monthly", "term": null}, "salary_visible": false, "title_keywords": ["accounting", "consultant"], "responsibilities": ["schedules", "compliance", "quality", "teams", "merchandising", "liaising with", "communication", "project management", "purchase"], "requirements": {"degrees": ["degree", "hkdse"], "majors": [], "languages": ["english", "chinese"], "language_level": ["good"], "hard_skills": ["make", "project management"], "soft_skills": ["organized", "communication skills", "independent", "responsible", "project management skills", "timely", "hard working", "integrity", "collaborative", "self motivated", "diverse", "detail orientated"], "languages_combined": [{"language": "english", "language_level": ["good"]}, {"language": "chinese", "language_level": ["good"]}]}, "experience_required": {"duration": ["minimum 3 years"], "field": ["merchandising"]}}, {"job_id": "100003009038982", "location_code": "hk", "company": "SHINEWING Risk Services Limited", "job_title": "Senior Accountant/ Staff Accountant - Risk Services (Internal Audit)", "description": "Summary\n\nLidl Asia are looking for a university student to join us part-time as an Assistant Business Controller. You will prepare accurate and timely monthly reports of financials and operational measures to our Headquarter and regional management team. You will also support to build a reliable and efficient reporting and planning infrastructure in Oracle BI and Excel.\n\nWhat will you do?\nPrepare monthly financial and operational performance reports for regional management\nPrepare monthly P&L, investment, and headcount reports and presentations to Headquarters\nUnderstand KPI calculation logic and build reports in BI Oracle for operational performance review\nBuild templates / reports / forms for the business using Excel Macro / VBA to streamline processes\nWhat will you need?\nCurrently studying a university degree, majoring in Business, Accounting & Finance, IT, or another related discipline\nExcellent MS Office skills (Excel Macro and VBA preferred)\nIndependent, proactive, and well organised with a focus on detail and accuracy\nGood interpersonal skills, fluent English speaking\nExperience in financial reporting and KPIs preferred\nExperience with Oracle BI or equivalent tool preferred\nSQL, Python knowledge preferred\nWhat do we offer?\n\nWe are dedicated to fostering a family-friendly culture and work environment and we are an equal opportunities employer and welcome applications from all candidates with the required skills and experience.\n\nMarket Leading Remuneration Package:\n\nDouble pay and discretionary bonus\nChoice of MPF provider\nLife Insurance\nMedical Insurance\n\nSupportive Environment:\n\nRental re-imbursement scheme\nFlexible work arrangements\nIn-house training courses\nTraining sponsorship scheme\nHealth Check\nVision Check\nSupporting your child\u2019s education with advice from a leading education consultant\n\nWork-Life Balance:\n\n5 day week\nCompetitive Annual Leave\nCharity, Community and Sporting Events", "employment_types": ["Full Time", "Permanent"], "selling_points": ["Risk Management, Internal Audit", "Good command in English and Chinese", "Fresh graduates are also welcome"], "locations": ["Causeway Bay"], "categories": ["Accounting", "Audit", "Consulting", "Others"], "post_time": "2022-01-11T08:18:43Z", "salary": {"currency": null, "max": null, "min": null, "period": "monthly", "term": null}, "salary_visible": false, "title_keywords": ["staff accountant", "senior accountant"], "responsibilities": ["management team", "reporting", "management", "performance reports", "monthly reports", "infrastructure", "review", "p&l", "presentations", "reports", "financial reporting", "kpis", "planning"], "requirements": {"degrees": ["university degree"], "majors": ["finance", "business", "it", "accounting"], "languages": ["english"], "language_level": ["fluent", "good"], "hard_skills": ["excel", "macro", "bi", "vba", "presentations", "sql", "python", "focus", "ms office", "oracle"], "soft_skills": ["efficient", "proactive", "independent", "timely", "interpersonal skills", "reliable", "organised", "focus", "accurate"], "languages_combined": [{"language": "english", "language_level": ["fluent", "good"]}]}, "experience_required": {"duration": [], "field": ["financial"]}}, {"job_id": "100003009037487", "location_code": "hk", "company": "Michael Page", "job_title": "Operational Risk Analyst - Asset Management", "description": "Summary\n\nLidl Asia are looking for a Senior Production Support Engineer in our Household team to drive the most cost effective, quality controlled, and on-time production through key building blocks, such as kick-off meetings, pre-production meetings, production schedule, CAPs, and Quality Control inspection program.\n\nWhat will you do?\n\nEnsure all production occurs in line with Lidl HK SOP and Lidl\u2019s strict Ethical Sourcing Policies\n\nTakes control and leads all pre-production meetings in factory as determined by the \u2018kick-off\u2019 meeting at Lidl HQ\n\nProvide manufacturing technical support and procedure to reduce manufacturing costs and / or improve quality levels and production efficiency when identified\n\nNotify key stakeholders of any major or critical production and quality issues identified whilst in factory. Follow up and close off outstanding CAPs with the supplier in question.\n\nDrive compressed production impacts training with any impacting product category\n\nPerform Lidl factory evaluations, implement and control CAPs\n\nMonitor the efficiency of the Lidl China QC team\n\nMonitor the efficiency of the Lidl agency for offshore countries\n\nTravel is required\n\nWhat will you need?\n\nDiploma or degree in electrical or mechanical engineering and at least 5 years\u2019 experience in QA/QC within the Household product category\n\nAutonomous, proactive, detailed and commercially minded\n\nGood command of both spoken and written English and fluent in Mandarin\n\nBasic knowledge of Microsoft applications Word & Excel & Lotus Notes\n\nA can-do attitude with entrepreneurial spirit is a must\n\nWhat do we offer?\n\nWe are dedicated to fostering a family-friendly culture and work environment and we are an equal opportunities employer and welcome applications from all candidates with the required skills and experience.\n\n\u00a0\nMarket Leading Remuneration Package:\n\nDouble pay and discretionary bonus\nChoice of MPF provider\nLife Insurance\nMedical Insurance\n\u00a0\n\nSupportive Environment:\n\nRental re-imbursement scheme\nFlexible work arrangements\nIn-house training courses\nTraining sponsorship scheme\nHealth Check\nVision Check\nSupporting your child\u2019s education with advice from a leading education consultant\n\u00a0\n\nWork-Life Balance:\n\n5 day week\nCompetitive Annual Leave\nCharity, Community and Sporting Events\n\nWe are dedicated to fostering a family-friendly culture and work environment and we are an equal opportunities employer and welcome applications from all candidates with the required skills and experience.\n\n\u00a0\nMarket Leading Remuneration Package:\n\nDouble pay and discretionary bonus\nChoice of MPF provider\nLife Insurance\nMedical Insurance\n\u00a0\n\nSupportive Environment:\n\nRental re-imbursement scheme\nFlexible work arrangements\nIn-house training courses\nTraining sponsorship scheme\nHealth Check\nVision Check\nSupporting your child\u2019s education with advice from a leading education consultant\n\u00a0\n\nWork-Life Balance:\n\n5 day week\nCompetitive Annual Leave\nCharity, Community and Sporting Events", "employment_types": ["Full Time", "Permanent"], "selling_points": ["Exciting new operational risk role !", "International Buyside Firm!", "Buyside Operational risk role!"], "locations": ["Not Specified"], "categories": ["Accounting", "Audit", "Consulting", "Banking / Finance", "Risk Management"], "post_time": "2022-01-11T02:56:37Z", "salary": {"currency": "HKD", "max": 54999, "min": 45000, "period": "monthly", "term": null}, "salary_visible": true, "title_keywords": ["risk analyst", "asset management"], "responsibilities": ["cost", "control", "technical support", "policies", "quality", "monitor", "inspection", "schedule", "quality control", "pre-production", "costs"], "requirements": {"degrees": ["diploma", "degree"], "majors": ["mechanical engineering"], "languages": ["english", "mandarin"], "language_level": ["good command", "fluent"], "hard_skills": ["excel", "basic", "word", "microsoft applications"], "soft_skills": ["determined", "can-do attitude", "autonomous", "ethical", "controlled", "proactive", "detailed"], "languages_combined": [{"language": "english", "language_level": ["fluent", "good command"]}, {"language": "mandarin", "language_level": ["good command"]}]}, "experience_required": {"duration": ["at least 5 years"], "field": ["engineering", "qa"]}}, {"job_id": "100003009038482", "location_code": "hk", "company": "Bluemont Consulting", "job_title": "Insolvency Accountant (Sr Associate / Manager) | Open to qualified auditors", "description": "Summary\n\nLidl are hiring a Senior Production Support Engineer in the Production Support (E&E) team. The successful candidate will be responsible for ensuring that production is cost effective, quality controlled and on time.\n\nWhat will you do?\nEnsures all production occurs in line with Lidl\u2019s strict Ethical Sourcing Policies\nEnsure TnA\u2019s for each IAN confirmed in each Selection is accurate and correct\nReceive, upload, and review weekly production schedules from suppliers\nLiaise with Quality Control Officers and suppliers on capacity planning / schedules\nProvide weekly in production traffic light reporting to Merchandise Managers and General Managers\nNotify key stakeholders of any major or critical production and quality issues identified\u00a0\nWorks closely with Quality Assurance team to resolve any critical or major issues found during production\nSupport or conduct Pre-Production meetings in factory when required\nProvide manufacturing technical support and procedure to reduce manufacturing costs and / or improve quality levels and production efficiency when identified\u00a0\nReviews IVA data provided by QC Officers and ensures IVA form is accurate and correct\nPerform unannounced audits and inspections when requested\nPerform Lidl factory evaluations, implement, and control CAPs\nWhat will you need?\nDiploma or degree in electrical or mechanical engineering or at least 5 years\u2019 experience in a Quality Assurance / Quality Control role in electrical product category\nPossess strong leadership and managerial skills with sound problem solving techniques\nAutonomous, proactive, detailed and commercially minded\nGood command of both spoken and written English and fluent in Mandarin\nStrong knowledge of Microsoft applications especially Excel & Word\nTravel is required\nWhat do we offer?\n\nWe are dedicated to fostering a family-friendly culture and work environment. We are an equal opportunities employer and welcome applications from all candidates with the required skills and experience.\n\n\u00a0\nMarket Leading Remuneration Package:\n\nDouble pay and discretionary bonus\nChoice of MPF provider\nLife Insurance\nMedical Insurance\n\u00a0\n\nSupportive Environment:\n\nRental re-imbursement scheme\nFlexible work arrangements\nIn-house training courses\nTraining sponsorship scheme\nHealth Check\nVision Check\nSupporting your child\u2019s education with advice from a leading education consultant\n\u00a0\n\nWork-Life Balance:\n\n5 day week\nCompetitive Annual Leave\nCharity, Community and Sporting Events", "employment_types": ["Full Time", "Permanent"], "selling_points": ["Open to auditors", "Stable working hours", "Insolvency / Restructuring / Forensic Accounting"], "locations": ["Central"], "categories": ["Accounting", "Consulting"], "post_time": "2022-01-11T07:03:51Z", "salary": {"currency": null, "max": null, "min": null, "period": "monthly", "term": null}, "salary_visible": false, "title_keywords": ["associate", "accountant", "manager"], "responsibilities": ["reporting", "cost", "control", "data", "schedules", "policies", "technical support", "review", "quality", "audits", "quality control", "liaise with", "pre-production", "costs", "planning"], "requirements": {"degrees": ["diploma", "degree"], "majors": ["mechanical engineering"], "languages": ["english", "mandarin"], "language_level": ["good command", "fluent"], "hard_skills": ["problem solving", "excel", "word", "microsoft applications"], "soft_skills": ["proactive", "responsible", "problem solving", "autonomous", "ethical", "controlled", "accurate", "leadership", "detailed"], "languages_combined": [{"language": "english", "language_level": ["fluent", "good command"]}, {"language": "mandarin", "language_level": ["good command"]}]}, "experience_required": {"duration": ["at least 5 years"], "field": ["engineering", "quality control", "quality assurance"]}}, {"job_id": "100003009037292", "location_code": "hk", "company": "Michael Page", "job_title": "FP&A Manager (Energy), 55k", "description": "Summary\n\nLidl are hiring Quality Consultant \u00a0in the Quality Assurance (Electronic - Hi Tech) team. The successful candidate will be responsible for liaising\u00a0on issues and product requirements related to the 3rd party laboratory testing in Germany of related product groups. Provide support to the team.\u00a0Support the Quality Assurance and Production Team on all product and quality requirements of related products.\n\nWhat will you do?\n\u00a0Perform quality checks on product and packaging through sample inspections and report the findings.\n\u00a0Assist in the improvement of quality of samples at all stages of product development and the order\n\u00a0Monitor certificate (EMC, LVD, RED etc.) and testing status, give comment to the draft report and manage the report revision if required.\n\u00a0Arrange the chemical testing to the tetsing lab, and monitor the chemical testing status.\n\u00a0Ability to evaluate samples and recommend appropriate modifications in design of construction\n\u00a0QA Warehouse samples: Arrange samples to be sent to external warehouse or testing laboratory once evaluation completed, ensure samples organized on shelves or allotted area\n\u00a0Carry out checks on artwork i.e. packaging\\manuals\\labelling\n\u00a0Signed sample preparation and approval\n\u00a0Laboratory test quotation review & confirm. Discuss with SQC if there are discrepancies.\n\u00a0Participate in Kick-off meetings\n\u00a0Deal with QSP (In-line) comments from Germany \u2013 Check, review and propose response, where applicable\n\u00a0Test failure analysis and provide recommendations to factory\n\u00a0Arrange the retest once the improved sample is available. On-site product improvement discussion with factory\n\u00a0Assist with updating and recalculating the schedule and inform Merchandising team\n\u00a0Review and discuss (where applicable) CAP reports with Production team\n\u00a0Clarify the testing issues with external laboratory\n\u00a0Monitor the schedule and review on the document/report (Test order, sample review report, DCL, Certification)\n\u00a0Review and submit shipment release documents to SQC and/or Technical Manager\nWhat will you need?\nDegree holder or relevant level of experience\nMinimum 2 relevant experience in Quality Assurance / QC position and factory inspection practice in international sourcing company \u00a0is an advantage\nPossess strong technical expertise in hard-line or hard-goods products\nExperienced in Hi -Tech digital electrionic products\nDetail orientated\nHigh degree of work ethics and integrity\nA can-do attitude is a must\nProficiency in Mandarin, English and Cantonese, both spoken and written\nPC knowledge is essential\nTravel is required\n\u00a0\nWhat do we offer?\n\nMarket Leading Remuneration Package:\n\nDouble pay and discretionary bonus\nChoice of MPF provider\nLife Insurance\nMedical Insurance\n\n\n\u00a0\n\nSupportive Environment:\n\nRental re-imbursement scheme\nOut-Of-Office leave for important appointments\nIn-house training courses\nTraining sponsorship scheme\nHealth Check\nVision Check\nExceptional maternity and paternity leave\nSupporting your child's education with advice from a leading education consultant\n\n\n\u00a0\n\nWork-Life Balance:\n\n5 day week\nCompetitive Annual Leave\nCharity, Community and Sporting Events\n\nMarket Leading Remuneration Package:\n\nDouble pay and discretionary bonus\nChoice of MPF provider\nLife Insurance\nMedical Insurance\n\u00a0\n\nSupportive Environment:\n\nRental re-imbursement scheme\nOut-Of-Office leave for important appointments\nIn-house training courses\nTraining sponsorship scheme\nHealth Check\nVision Check\nExceptional maternity and paternity leave\nSupporting your child's education with advice from a leading education consultant\n\u00a0\n\nWork-Life Balance:\n\n5 day week\nCompetitive Annual Leave\nCharity, Community and Sporting Events", "employment_types": ["Full Time", "Permanent"], "selling_points": ["Big 4 experiences are required", "Stable working environment", "Good company benefits"], "locations": ["Not Specified"], "categories": ["Accounting", "Consulting", "Finance / Accounting Manager", "Financial Analyst"], "post_time": "2022-01-11T02:21:24Z", "salary": {"currency": null, "max": null, "min": null, "period": "monthly", "term": null}, "salary_visible": false, "title_keywords": ["manager"], "responsibilities": ["provide support", "sample preparation", "analysis", "quotation", "quality", "monitor", "design", "testing", "evaluate", "review", "comments", "merchandising", "provide recommendations", "schedule", "reports", "evaluation", "inspection", "report"], "requirements": {"degrees": ["certificate", "degree", "degree holder"], "majors": [], "languages": ["cantonese", "english", "mandarin"], "language_level": ["proficiency"], "hard_skills": ["inform", "dcl", "analysis", "pc knowledge", "red"], "soft_skills": ["organized", "responsible", "can-do attitude", "integrity", "detail orientated"], "languages_combined": [{"language": "cantonese", "language_level": ["proficiency"]}, {"language": "english", "language_level": ["proficiency"]}, {"language": "mandarin", "language_level": ["proficiency"]}]}, "experience_required": {"duration": [], "field": ["relevant experience", "quality assurance"]}}, {"job_id": "100003009039165", "location_code": "hk", "company": "SHINEWING Tax And Business Advisory Limited", "job_title": "Staff Accountant I (2022 Graduates) - Tax & Business Advisory Services", "description": "Summary\n\nLidl are hiring a (Senior) Technical Writer to support the Artwork and Packaging team in enhancing their technical writing capability. The successful candidate will create technical documentation based on product specifications and samples, and will also build up a database for process facilitation.\n\nWhat will you do?\nCreate technical documentations, including instruction manuals, safety / assembling manuals, and quick start guides for a wide variety of consumer goods.\nOrganise materials and complete writing assignments in accordance with all relevant product standards and countries regulations in the EU, UK, and US.\nCreate / edit line drawings, sketches, diagrams, OSD screenshots, table / charts to illustrate material.\nAlign with Merchandising and Quality Assurance teams during the documentation creation and finalisation phases. In terms of on-time delivery and ensuring accuracy of specifications, product assembly steps, and operating procedures of the products.\nUnderstand complex concepts and communicate the information in a way that is engaging and understood by end-users at various technical levels.\nGather feedback on instruction manuals from Quality Assurance team / Testing institutes to improve usability and marketability. Get alignment and execute final changes on instruction manuals to reduce correction loops before and after translations.\nAct as an editor to ensure terminology and style consistency in the documentation across product categories and organisation.\nPrepare / typeset and review instruction manuals for translation process.\nCooperate closely with Design, Translation and Artwork Team in the fields of graphics, artwork and packaging management based on internal quality requirements.\nBuild and maintain content / translation library and templates for standardisation purposes.\nAssist in proofreading, technical problem solving, reviewing test reports, and communicating with testing institutes if required.\nWork in ad-hoc project support and other duties as assigned.\n\nPlease note this is a 12-month contract with the potential to go permanent.\n\nWhat will you need?\n\nUniversity degree in Technical Communication, Technical Translation, or related fields or work experience as Technical Writer\u00a0\n\n2 - 4 years' work experience in the field of technical documentation\u00a0\n\nExperience with Power Tools, SDA, Lightings, and Hi-Tech (smart IoT) product groups will be an advantage\n\nExemplary attention to detail and time management skills\n\nWork independently on written assignments and be a dependable, strong team player with excellent interpersonal and organisational skills\n\nProficiency in Adobe InDesign, Adobe Illustrator, and Acrobat\u00a0\n\nExcellent writing skills in English, proficiency in German or other European languages will be an advantage\n\nAbility to work in a fast-paced environment whilst under pressure to meet tight deadlines\n\nWhat do we offer?\n\nWe are dedicated to fostering a family-friendly culture and work environment and we are an equal opportunities employer and welcome applications from all candidates with the required skills and experience.\n\n\u00a0\nMarket Leading Remuneration Package:\n\nDouble pay and discretionary bonus\n\nChoice of MPF provider\n\nLife Insurance\n\nMedical Insurance\n\nSupportive Environment:\n\nRental re-imbursement scheme\n\nFlexible work arrangements\n\nIn-house training courses\n\nTraining sponsorship scheme\n\nHealth Check\n\nVision Check\n\nSupporting your child\u2019s education with advice from a leading education consultant\n\nWork-Life Balance:\n\n5 day week\n\nCompetitive Annual Leave\n\nCharity, Community and Sporting Events\n\nWe are dedicated to fostering a family-friendly culture and work environment and we are an equal opportunities employer and welcome applications from all candidates with the required skills and experience.\n\n\u00a0\nMarket Leading Remuneration Package:\n\nDouble pay and discretionary bonus\n\nChoice of MPF provider\n\nLife Insurance\n\nMedical Insurance\n\nSupportive Environment:\n\nRental re-imbursement scheme\n\nFlexible work arrangements\n\nIn-house training courses\n\nTraining sponsorship scheme\n\nHealth Check\n\nVision Check\n\nSupporting your child\u2019s education with advice from a leading education consultant\n\nWork-Life Balance:\n\n5 day week\n\nCompetitive Annual Leave\n\nCharity, Community and Sporting Events", "employment_types": ["Full Time", "Permanent"], "selling_points": ["Assist in tax research, fact-finding", "Tax compliance and advisory work", "Bachelor degree in accounting / related discipline"], "locations": ["Causeway Bay"], "categories": ["Accounting", "Consulting", "Taxation"], "post_time": "2022-01-11T08:53:57Z", "salary": {"currency": null, "max": null, "min": null, "period": "monthly", "term": null}, "salary_visible": false, "title_keywords": ["staff accountant"], "responsibilities": ["regulations", "ad-hoc", "merchandising", "quality", "design", "drawings", "communication", "maintain", "database", "product categories", "graphics", "other duties", "teams", "testing", "reports", "management", "review", "procedures", "sketches", "specifications", "proofreading", "documentation", "communicating with"], "requirements": {"degrees": ["university degree"], "majors": [], "languages": ["german", "english"], "language_level": ["advantage", "excellent", "proficiency"], "hard_skills": ["graphics", "acrobat", "adobe indesign", "writing skills", "adobe illustrator", "problem solving", "documentation", "translation", "go", "documentations"], "soft_skills": ["work independently", "meet tight deadlines", "under pressure", "time management skills", "fast-paced environment", "writing skills", "problem solving", "communication", "organisational skills", "attention to detail", "organisation", "team player", "interpersonal"], "languages_combined": [{"language": "german", "language_level": ["proficiency", "advantage", "excellent"]}, {"language": "english", "language_level": ["proficiency", "advantage", "excellent"]}]}, "experience_required": {"duration": ["2 - 4 years"], "field": ["related", "tech"]}}, {"job_id": "100003009035729", "location_code": "hk", "company": "RSM Hong Kong \u7f85\u7533\u7f8e\u6703\u8a08\u5e2b\u4e8b\u52d9\u6240", "job_title": "Consultant / Senior Consultant, Transaction Advisory Services", "description": "Summary\n\nLidl are hiring an Assistant Merchandiser (Electrical Home Appliances)\u00a0to join our cooking appliances department, small domestic appliance\u00a0team.\u00a0The successful candidate will provide daily support to the merchandising team\u00a0and perform operative tasks.\n\nWhat will you do?\nProvide assistance to the Merchandising Department \u2013 Electrical Home Appliances\nPerform administrative support\nCo-ordinating with cross functional teams\nManaging sampling\nCommunication with suppliers\nAssist market survey & benchmark study\nAssign other ad hoc assignments\nWhat will you need?\nForm 6 or above (HKDSE)/ Form 7 or above (HKALE)\n1 tp 2 yeras of merchandising experience for European markets preferred\nGood command of written and spoken English, Mandarin and Cantonese\nDetail-oriented mindset\nMust be self motivated, self organised, responsible, hardworking and independent\nGood working attitude, willing to learn, and a good team player\nProficient in MS Office (specifically Excel)\nFresh graduates will be considered\nWhat do we offer?\n\nWe are dedicated to fostering a family-friendly culture and work environment and have been a proud member of the Caring Company Scheme since 2014. We are an equal opportunities employer and welcome applications from all candidates with the required skills and experience.\n\n\u00a0\nMarket Leading Remuneration Package:\n\nDouble pay and discretionary bonus\nChoice of MPF provider\nLife Insurance\nMedical Insurance\n\u00a0\n\nSupportive Environment:\n\nRental re-imbursement scheme\nOut-Of-Office leave for important appointments\nIn-house training courses\nTraining sponsorship scheme\nHealth Check\nVision Check\nSupporting your child\u2019s education with advice from a leading education consultant\n\u00a0\n\nWork-Life Balance:\n\n5 day week\nCompetitive Annual Leave\nCharity, Community and Sporting Events", "employment_types": ["Full Time", "Permanent"], "selling_points": [], "locations": ["Causeway Bay"], "categories": ["Accounting", "Audit", "Consulting", "Financial Analyst"], "post_time": "2022-01-10T08:17:54Z", "salary": {"currency": null, "max": null, "min": null, "period": "monthly", "term": null}, "salary_visible": false, "title_keywords": ["senior consultant", "consultant"], "responsibilities": ["administrative support", "teams", "merchandising", "communication", "ad hoc assignments", "provide assistance"], "requirements": {"degrees": ["hkdse"], "majors": [], "languages": ["cantonese", "english", "mandarin"], "language_level": ["good command"], "hard_skills": ["small"], "soft_skills": ["communication"], "languages_combined": [{"language": "cantonese", "language_level": ["good command"]}, {"language": "english", "language_level": ["good command"]}, {"language": "mandarin", "language_level": ["good command"]}]}, "experience_required": {"duration": [], "field": ["merchandising"]}}, {"job_id": "100003009038192", "location_code": "hk", "company": "Lauris Walton International Limited", "job_title": "Assistant Manager / Manager - Forensic Accounting / Insolvency & Litigation Support", "description": "Summary\n\nLidl Asia are hiring a Database Officer for our Application Development team to support and enhance the functionality of all database platforms.\n\nWhat will you do?\n\nProvide business-as-usual support for database systems in areas of monitoring, tuning, patching, and managing access\n\nMonitor performance, backups, and proper implementation of database systems and models\n\nSupport users with ad hoc requests from databases, scripting, or ETL\n\nDocumentation and monitoring of disaster recovery procedures\n\nUpdate job knowledge by participating in educational opportunities and professional organisation events\n\nParticipate in projects, handle development and maintenance phases of projects with relational and NoSQL databases, including Oracle, PostgreSQL, and Cosmos DB\n\nSupport Data Architect in other database related projects / activities\n\nWhat will you need?\n\n1+ year database experience in an enterprise production environment\n\nWorking user knowledge of SQL Language or Json, especially Oracle, PostgreSQL, CosmosDB, or MongoDB\n\nWorking user knowledge of Oracle or PostgreSQL is an advantage\n\nWorking user knowledge of cloud technologies is an advantage, especially Microsoft Azure and Oracle Cloud\n\nBe sensitive to data security and performance impact of database work\n\nCustomer-oriented with good troubleshooting, communication, and interpersonal skills\n\nProactive, self-motivated, and able to work in a dynamic environment\n\nKeen learner and able to work both independently and within a team\n\nGood spoken and written communication skills in English\n\nWhat do we offer?\n\nWe are dedicated to fostering a family-friendly culture and work environment and we are an equal opportunities employer and welcome applications from all candidates with the required skills and experience.\n\n\nMarket Leading Remuneration Package:\n\nDouble pay and discretionary bonus\n\nChoice of MPF provider\n\nLife Insurance\n\nMedical Insurance\n\nSupportive Environment:\n\nRental re-imbursement scheme\n\nFlexible work arrangements\n\nIn-house training courses\n\nTraining sponsorship scheme\n\nHealth Check\n\nVision Check\n\nSupporting your child\u2019s education with advice from a leading education consultant\n\nWork-Life Balance:\n\n5 day week\n\nCompetitive Annual Leave\n\nCharity, Community and Sporting Events\n\nWe are dedicated to fostering a family-friendly culture and work environment and we are an equal opportunities employer and welcome applications from all candidates with the required skills and experience.\n\n\nMarket Leading Remuneration Package:\n\nDouble pay and discretionary bonus\n\nChoice of MPF provider\n\nLife Insurance\n\nMedical Insurance\n\nSupportive Environment:\n\nRental re-imbursement scheme\n\nFlexible work arrangements\n\nIn-house training courses\n\nTraining sponsorship scheme\n\nHealth Check\n\nVision Check\n\nSupporting your child\u2019s education with advice from a leading education consultant\n\nWork-Life Balance:\n\n5 day week\n\nCompetitive Annual Leave\n\nCharity, Community and Sporting Events", "employment_types": ["Full Time", "Permanent"], "selling_points": [], "locations": ["Not Specified"], "categories": ["Accounting", "Audit", "Consulting", "Professional Services", "Legal & Compliance"], "post_time": "2022-01-11T05:58:26Z", "salary": {"currency": null, "max": null, "min": null, "period": "monthly", "term": null}, "salary_visible": false, "title_keywords": ["assistant manager", "manager", "accounting"], "responsibilities": ["documentation", "maintenance", "data", "monitor performance", "ad hoc requests", "systems", "monitoring", "implementation", "procedures", "troubleshooting", "communication", "database", "backups", "databases", "application development"], "requirements": {"degrees": [], "majors": [], "languages": ["english"], "language_level": ["good"], "hard_skills": ["azure", "maintenance", "sql", "dynamic", "databases", "documentation", "oracle"], "soft_skills": ["communication skills", "self-motivated", "dynamic environment", "independently", "keen", "troubleshooting", "communication", "sensitive to", "customer-oriented", "interpersonal skills", "organisation", "proactive"], "languages_combined": [{"language": "english", "language_level": ["good"]}]}, "experience_required": {"duration": ["1+ year"], "field": ["database"]}}, {"job_id": "100003009035571", "location_code": "hk", "company": "Vitasoy International Holdings Ltd", "job_title": "Group Senior Internal Auditor", "description": "Summary\n\nLidl are hiring a Quality Consultant\u00a0in the Quality Assurance (Power Tools) team. The successful candidate will be responsible for liaising\u00a0on issues and product requirements related to the 3rd party laboratory testing in Germany of related product groups, support the Quality Assurance and Production Team on all product and quality requirements of related products and provide support to the team.\n\nWhat will you do?\n\nPerform quality checks on product and packaging through sample inspections and report the findings.\n\nAssist in the improvement of quality of samples at all stages of product development and the order\n\nAbility to evaluate samples and recommend appropriate modifications in design of construction\n\nQA Warehouse samples: Arrange samples to be sent to external warehouse or testing laboratory once evaluation completed, ensure samples organized on shelves or allotted area\n\nCarry out checks on artwork i.e. packaging\\manuals\\labelling\n\nSigned sample preparation and approval\n\nLaboratory test quotation review & confirm. Discuss with SQC if there are discrepancies.\n\nParticipate in Kick-off meetings\n\nDeal with QSP (In-line) comments from Germany - Check, review and propose response, where applicable\n\nTest failure analysis and provide recommendations to factory\n\nArrange the retest once the improved sample is available. On-site product improvement discussion with factory\n\nAssist with updating and recalculating the schedule and inform Merchandising team\n\nReview and discuss (where applicable) CAP reports with Production team\n\nClarify the testing issues with external laboratory\n\nMonitor the schedule and review on the document/report (Test order, sample review report, DCL, Certification)\n\nReview and submit shipment release documents to SQC and/or Technical Manager\n\nWhat will you need?\n\nDegree holder or relevant level of experience\n\nMinimum 3 years relevant experience in Power Tools Quality Assurance / QC position and factory inspection practice in international sourcing company is an advantage\n\nPossess strong technical expertise in hard-line or hard-goods products - Power Tools\n\nDetail orientated\n\nAble to read, understand and interprete Regulations/Standards/Guidelines for EU & US market\n\nHigh degree of work ethics and integrity\n\nA can-do attitude is a must\n\nProficiency in Mandarin, English and Cantonese, both spoken and written\n\nTravel is required\n\nWhat do we offer?\n\nMarket Leading Remuneration Package:\n\nDouble pay and discretionary bonus\nChoice of MPF provider\nLife Insurance\nMedical Insurance\n\n\n\u00a0\n\nSupportive Environment:\n\nRental re-imbursement scheme\nOut-Of-Office leave for important appointments\nIn-house training courses\nTraining sponsorship scheme\nHealth Check\nVision Check\nExceptional maternity and paternity leave\nSupporting your child's education with advice from a leading education consultant\n\n\n\u00a0\n\nWork-Life Balance:\n\n5 day week\nCompetitive Annual Leave\nCharity, Community and Sporting Events\n\nMarket Leading Remuneration Package:\n\nDouble pay and discretionary bonus\nChoice of MPF provider\nLife Insurance\nMedical Insurance\n\u00a0\n\nSupportive Environment:\n\nRental re-imbursement scheme\nOut-Of-Office leave for important appointments\nIn-house training courses\nTraining sponsorship scheme\nHealth Check\nVision Check\nExceptional maternity and paternity leave\nSupporting your child's education with advice from a leading education consultant\n\u00a0\n\nWork-Life Balance:\n\n5 day week\nCompetitive Annual Leave\nCharity, Community and Sporting Events", "employment_types": ["Full Time", "Permanent"], "selling_points": ["Execute audit engagements of the Group", "Ensure the audit objectives achieved properly", "Perform specific audit procedures independently"], "locations": ["Tuen Mun Area"], "categories": ["Accounting", "Accountant", "Audit", "Consulting"], "post_time": "2022-01-10T07:42:48Z", "salary": {"currency": null, "max": null, "min": null, "period": "monthly", "term": null}, "salary_visible": false, "title_keywords": ["internal auditor"], "responsibilities": ["regulations", "quotation", "quality", "merchandising", "design", "evaluation", "sample preparation", "monitor", "testing", "reports", "schedule", "report", "provide support", "review", "inspection", "provide recommendations", "guidelines", "analysis", "comments", "evaluate"], "requirements": {"degrees": ["degree", "degree holder"], "majors": [], "languages": ["cantonese", "english", "mandarin"], "language_level": ["proficiency"], "hard_skills": ["dcl", "analysis", "inform"], "soft_skills": ["organized", "responsible", "can-do attitude", "integrity", "detail orientated"], "languages_combined": [{"language": "cantonese", "language_level": ["proficiency"]}, {"language": "english", "language_level": ["proficiency"]}, {"language": "mandarin", "language_level": ["proficiency"]}]}, "experience_required": {"duration": ["minimum 3 years"], "field": ["relevant experience", "quality assurance"]}}, {"job_id": "100003009034430", "location_code": "hk", "company": "Tampa Stone Co.", "job_title": "+++ Consultant Trainee (Welcome Fresh Graduates) +++", "description": "Summary\n\nLidl are looking for a Senior Production Support Operations Manager to deliver the Production and Quality Control department\u2019s strategy and projects. The successful incumbent will ensure production, quality control, and compliance & sustainability operational processes are achieved right the first time to ensure DIFOT to OWIM FOB date.\n\nWhat will you do?\n\nAssist Line Manager in developing and implementing agreed strategy across all responsible teams\n\nAssist Line Manager in setting and managing department budgets, whilst also identifying opportunities for cost saving and tracking those initiatives\n\nBased on the agreed strategies, develop, and deploy best practice processes and operational guidelines to internal and external parties, ensuring one way of working across all teams\n\nMonitor compliance of internal and external stakeholders to Standard Operating Procedures (SOP\u2019s), ensuring department meets all audit requirements\n\nManage, execute, and report on pipeline of departmental projects and those non-departmental projects as required by the business\n\nProactively define, build, analyse and deploy, via traffic light reporting, operational KPI\u2019s as defined to internal and external parties\n\nLead monthly Production Support Management meetings whereby continual analysis is presented to drive improvements in quality and Delivered In Full On Time (DIFOT)\n\nShine light where operational efficiencies and critical path inefficiencies occur\n\nSupport the Production and Quality Control Co-ordinators to ensure process is effective and streamlined \u00a0\n\nDevelop analytical reports and presentation desks for fortnightly 1:1 discussions and general review\n\nReports on quality levels and DIFOT by General Manager - Production Support with improvement plans with factories and suppliers to drive improvements of Critical Path Management\n\nKey owner of driving Excel based operations to automated CBX operations\n\nEnsure the TnA is set up correctly and timely for each Selection\n\nAction ad-hoc requests timely and proactively\n\nWhat will you need?\n\nBachelor\u2019s Degree required, preferably in Engineering, Supply Chain, Economics, Operations, or Business\n\nMinimum 5 years of Supply Planning, Demand Planning, Vendor Forecasting, or Business Management\n\n5 years\u2019 experience in a direct sourcing office or model for a sizable company with at least 3 years\u2019 experience in a managerial level\n\nStrong organisational skills and the ability to prioritise and manage multiple projects simultaneously with complex and demanding deadlines\n\nGood command in English, whilst Chinese (Mandarin and Cantonese) and German are advantageous\n\nExceptional communications, strategic thinking, and interpersonal skills\n\nStrong knowledge of Microsoft applications like Excel and PowerPoint\n\nExperience working across and successfully influencing multiple internal stakeholders (Operations, IT development, supply chain, finance, legal, etc.)\n\nAbility to present complex issues in a clear and concise manner\n\nA positive and proactive can-do attitude with entrepreneurial spirit is a must\n\nA leader by example is key\n\nWhat do we offer?\n\nWe are dedicated to fostering a family-friendly culture and work environment and we are an equal opportunities employer and welcome applications from all candidates with the required skills and experience.\n\n\u00a0\nMarket Leading Remuneration Package:\n\nDouble pay and discretionary bonus\nChoice of MPF provider\nLife Insurance\nMedical Insurance\n\u00a0\n\nSupportive Environment:\n\nRental re-imbursement scheme\nFlexible work arrangements\nIn-house training courses\nTraining sponsorship scheme\nHealth Check\nVision Check\nSupporting your child\u2019s education with advice from a leading education consultant\n\u00a0\n\nWork-Life Balance:\n\n5 day week\nCompetitive Annual Leave\nCharity, Community and Sporting Events\n\nWe are dedicated to fostering a family-friendly culture and work environment and we are an equal opportunities employer and welcome applications from all candidates with the required skills and experience.\n\n\u00a0\nMarket Leading Remuneration Package:\n\nDouble pay and discretionary bonus\nChoice of MPF provider\nLife Insurance\nMedical Insurance\n\u00a0\n\nSupportive Environment:\n\nRental re-imbursement scheme\nFlexible work arrangements\nIn-house training courses\nTraining sponsorship scheme\nHealth Check\nVision Check\nSupporting your child\u2019s education with advice from a leading education consultant\n\u00a0\n\nWork-Life Balance:\n\n5 day week\nCompetitive Annual Leave\nCharity, Community and Sporting Events", "employment_types": ["Full Time", "Permanent", "Internship"], "selling_points": ["Trainee Program", "Fresh Graduates are welcome", "18K or above"], "locations": ["Wan Chai"], "categories": ["Accounting", "Consulting", "Banking / Finance", "Investment", "Marketing / Public Relations", "Management"], "post_time": "2022-01-10T03:22:27Z", "salary": {"currency": null, "max": null, "min": null, "period": "monthly", "term": null}, "salary_visible": false, "title_keywords": ["consultant trainee"], "responsibilities": ["operations", "demand planning", "internal and external parties", "quality", "audit", "planning", "deploy", "develop analytical reports", "plans", "compliance", "teams", "developing", "monitor", "develop", "manage multiple projects", "ad-hoc requests", "general review", "forecasting", "report", "reporting", "cost", "management", "procedures", "difot by general manager", "tracking", "budgets", "reports on quality levels", "guidelines", "cbx operations", "analysis", "quality control", "analyse"], "requirements": {"degrees": ["degree", "bachelor"], "majors": ["business", "economics", "engineering"], "languages": ["german", "cantonese", "english", "mandarin", "chinese"], "language_level": ["good command"], "hard_skills": ["supply planning", "excel", "vendor forecasting", "business management", "microsoft applications", "analysis", "demand planning", "powerpoint"], "soft_skills": ["manage multiple projects simultaneously", "responsible", "strategic thinking", "can-do attitude", "timely", "exceptional communications", "prioritise", "clear", "present complex issues", "organisational skills", "interpersonal skills", "proactive", "presentation", "positive"], "languages_combined": [{"language": "german", "language_level": ["good command"]}, {"language": "cantonese", "language_level": ["good command"]}, {"language": "english", "language_level": ["good command"]}, {"language": "mandarin", "language_level": ["good command"]}, {"language": "chinese", "language_level": ["good command"]}]}, "experience_required": {"duration": ["5 years", "at least 3 years"], "field": ["managerial", "it development", "legal", "finance", "supply chain"]}}, {"job_id": "100003009035731", "location_code": "hk", "company": "RSM Hong Kong \u7f85\u7533\u7f8e\u6703\u8a08\u5e2b\u4e8b\u52d9\u6240", "job_title": "Consultant, Risk Advisory Services (ESG Specialist)", "description": "Summary\n\nLidl Asia are hiring for a Senior Product Developer for our Textiles (Hosiery and Accessories) team to assist in managing the overall product development process from concept through to sample creation in accordance with the company's strategic planning.\n\nWhat will you do?\n\nPerform a range of research into new trends, innovations, and product ideas\n\nCreate seasonal trend / mood and direction boards as required\n\nLiaise with internal and external designers to brief and evaluate mood boards, artworks, product design overviews and tech packs\n\nSelect appropriate trim and fabric\n\nLiaise with the Quality Assurance department to ensure the right fit of the garment\n\nLiaise with the Merchandising team to finalise product designs ready for sample launch\n\nIntroduce seasonal updates and innovations to drive department turnover\n\nPerform seasonal presentations of design developments from trend to product as required\n\nManage the design and development workflow to ensure timelines are maintained\n\nConduct product review and suggest action plan for product development enhancement\n\nWhat will you need?\n\nDegree in product design, graphics design or related discipline\n\nMinimum 3-5 years of product development experience within the hosiery and / or accessories product category\n\nGood sense of typography, strong fashion sense, design talent and creativity\n\nProficient in MS Office (especially PowerPoint), Adobe Creative Suite (Design CAD), Adobe Illustrator and Adobe Photoshop, etc.\n\nMust be proactive and committed to working in a dynamic environment\n\nStrong leadership and communication skills across all levels of the organisation\n\nProficient in both spoken and written English\n\nWilling to travel\n\nWhat do we offer?\n\nWe are dedicated to fostering a family-friendly culture and work environment and we are an equal opportunities employer and welcome applications from all candidates with the required skills and experience.\nMarket Leading Remuneration Package:\n\nDouble pay and discretionary bonus\n\nChoice of MPF provider\n\nLife Insurance\n\nMedical Insurance\n\nSupportive Environment:\n\nRental re-imbursement scheme\n\nFlexible work arrangements\n\nIn-house training courses\n\nTraining sponsorship scheme\n\nHealth Check\n\nVision Check\n\nSupporting your child\u2019s education with advice from a leading education consultant\n\nWork-Life Balance:\n\n5 day week\n\nCompetitive Annual Leave\n\nCharity, Community and Sporting Events\n\nWe are dedicated to fostering a family-friendly culture and work environment and we are an equal opportunities employer and welcome applications from all candidates with the required skills and experience.\nMarket Leading Remuneration Package:\n\nDouble pay and discretionary bonus\n\nChoice of MPF provider\n\nLife Insurance\n\nMedical Insurance\n\nSupportive Environment:\n\nRental re-imbursement scheme\n\nFlexible work arrangements\n\nIn-house training courses\n\nTraining sponsorship scheme\n\nHealth Check\n\nVision Check\n\nSupporting your child\u2019s education with advice from a leading education consultant\n\nWork-Life Balance:\n\n5 day week\n\nCompetitive Annual Leave\n\nCharity, Community and Sporting Events", "employment_types": ["Full Time", "Permanent"], "selling_points": [], "locations": ["Causeway Bay"], "categories": ["Accounting", "Consulting", "Professional Services", "Business Consultancy", "Sciences, Lab, R&D", "Environmental Science / Waste Management"], "post_time": "2022-01-10T08:17:54Z", "salary": {"currency": null, "max": null, "min": null, "period": "monthly", "term": null}, "salary_visible": false, "title_keywords": ["specialist", "consultant"], "responsibilities": ["graphics", "ideas", "strategic planning", "review", "quality", "merchandising", "presentations", "design", "evaluate", "communication", "product design", "plan", "liaise with"], "requirements": {"degrees": ["degree"], "majors": ["design"], "languages": ["english"], "language_level": ["proficient"], "hard_skills": ["graphics", "cad", "adobe photoshop", "powerpoint", "presentations", "adobe illustrator", "dynamic", "adobe creative suite", "ms office"], "soft_skills": ["communication skills", "dynamic environment", "proactive", "committed", "organisation", "creative", "leadership"], "languages_combined": [{"language": "english", "language_level": ["proficient"]}]}, "experience_required": {"duration": ["minimum 3-5 years"], "field": ["product development"]}}, {"job_id": "100003009033926", "location_code": "hk", "company": "Michael Page", "job_title": "Business Analyst (FMCG), 38k", "description": "Summary\n\nLidl are hiring Quality Consultant \u00a0in the Quality Assurance (Small Domestic Appliance) team. The successful candidate will be responsible for liaising\u00a0on issues and product requirements related to the 3rd party laboratory testing in Germany of related product groups, support the Quality Assurance and Production Team on all product and quality requirements of related products and provide support to the team.\n\nWhat will you do?\n\nPerform quality checks on product and packaging through sample inspections and report the findings.\n\nAssist in the improvement of quality of samples at all stages of product development and the order\n\nAbility to evaluate samples and recommend appropriate modifications in design of construction\n\nQA Warehouse samples: Arrange samples to be sent to external warehouse or testing laboratory once evaluation completed, ensure samples organized on shelves or allotted area\n\nCarry out checks on artwork i.e. packaging\\manuals\\labelling\n\nSigned sample preparation and approval\n\nLaboratory test quotation review & confirm. Discuss with SQC if there are discrepancies.\n\nParticipate in Kick-off meetings\n\nDeal with QSP (In-line) comments from Germany - Check, review and propose response, where applicable\n\nTest failure analysis and provide recommendations to factory\n\nArrange the retest once the improved sample is available. On-site product improvement discussion with factory\n\nAssist with updating and recalculating the schedule and inform Merchandising team\n\nReview and discuss (where applicable) CAP reports with Production team\n\nClarify the testing issues with external laboratory\n\nMonitor the schedule and review on the document/report (Test order, sample review report, DCL, Certification)\n\nReview and submit shipment release documents to SQC and/or Technical Manager\n\nWhat will you need?\n\nDegree holder or relevant level of experience\n\nMinimum 3 years relevant experience in Small Domestic Appliance Quality Assurance / QC position and factory inspection practice in international sourcing company is an advantage\n\nPossess strong technical expertise in hard-line or hard-goods products - Small Domestic Appliance\n\nDetail orientated\n\nAble to read, understand and interprete Regulations/Standards/Guidelines for EU & US market\n\nHigh degree of work ethics and integrity\n\nA can-do attitude is a must\n\nProficiency in Mandarin, English and Cantonese, both spoken and written\n\nTravel is required\n\nWhat do we offer?\n\nMarket Leading Remuneration Package:\n\nDouble pay and discretionary bonus\nChoice of MPF provider\nLife Insurance\nMedical Insurance\n\n\n\n\u00a0\n\nSupportive Environment:\n\nRental re-imbursement scheme\nOut-Of-Office leave for important appointments\nIn-house training courses\nTraining sponsorship scheme\nHealth Check\nVision Check\nExceptional maternity and paternity leave\nSupporting your child's education with advice from a leading education consultant\n\n\n\n\u00a0\n\nWork-Life Balance:\n\n5 day week\nCompetitive Annual Leave\nCharity, Community and Sporting Events\n\nMarket Leading Remuneration Package:\n\nDouble pay and discretionary bonus\nChoice of MPF provider\nLife Insurance\nMedical Insurance\n\u00a0\n\nSupportive Environment:\n\nRental re-imbursement scheme\nOut-Of-Office leave for important appointments\nIn-house training courses\nTraining sponsorship scheme\nHealth Check\nVision Check\nExceptional maternity and paternity leave\nSupporting your child's education with advice from a leading education consultant\n\u00a0\n\nWork-Life Balance:\n\n5 day week\nCompetitive Annual Leave\nCharity, Community and Sporting Events", "employment_types": ["Full Time", "Permanent"], "selling_points": ["2-3 years of experiences", "FMCG background is highly preferred", "Welcome Big 4 candidates"], "locations": ["Not Specified"], "categories": ["Accounting", "Consulting", "Financial Analyst", "Others"], "post_time": "2022-01-10T02:09:13Z", "salary": {"currency": null, "max": null, "min": null, "period": "monthly", "term": null}, "salary_visible": false, "title_keywords": ["business analyst"], "responsibilities": ["regulations", "quotation", "quality", "merchandising", "design", "evaluation", "sample preparation", "monitor", "testing", "reports", "schedule", "report", "provide support", "review", "inspection", "provide recommendations", "guidelines", "analysis", "comments", "evaluate"], "requirements": {"degrees": ["degree", "degree holder"], "majors": [], "languages": ["cantonese", "english", "mandarin"], "language_level": ["proficiency"], "hard_skills": ["small", "dcl", "analysis", "inform"], "soft_skills": ["organized", "responsible", "can-do attitude", "integrity", "detail orientated"], "languages_combined": [{"language": "cantonese", "language_level": ["proficiency"]}, {"language": "english", "language_level": ["proficiency"]}, {"language": "mandarin", "language_level": ["proficiency"]}]}, "experience_required": {"duration": ["minimum 3 years"], "field": ["relevant experience", "quality assurance"]}}, {"job_id": "100003009039553", "location_code": "hk", "company": "Global Executive Consultants Ltd.", "job_title": "Senior Risk Management Manager (HK$60K - $80K) (Ref. No.:25322)", "description": "What will you do?\n\n\u2022\u00a0\u00a0 \u00a0Sample Inspection: Ensure sample inspections and \u00a0reports are completed within target time\n\n\u2022\u00a0\u00a0 \u00a0QA Warehouse\\samples: Responsible for arranging samples to be sent to external warehouse or testing laboratory once evaluation completed, ensure samples organized on shelves or allotted area\n\n\u2022\u00a0\u00a0 \u00a0To ensure all critical and major issues in own area being raised and discussed; seek further advice from appropriate team members\n\n\u2022\u00a0\u00a0 \u00a0Communication: Ensure more face to face discussion; reduce e-mails \u201cbombs\u201d, greater use of phone conference with related parties and agreed instant solution whenever possible.\n\n\u2022\u00a0\u00a0 \u00a0Laboratory test quotation issues and discuss with QAM for confirmation\n\n\u2022\u00a0\u00a0 \u00a0Attend Kick-off meetings\n\n\u2022\u00a0\u00a0 \u00a0Test failure analysis and recommendations to factory with SQC\n\n\u00a0 Arrange the retest once the improved sample available\n\u00a0 Update and recalculate the schedule and inform the merchandiser\n\u00a0 Review and discuss (where applicable) CAP report with Production\n\u00a0 Clarify the testing issues with external laboratory\n\u00a0 Update buyer on safety/quality issues directly related to project particularly causing delays\n\n\u2022\u00a0\u00a0 \u00a0Monitor the schedule and review on the document/report (Test order, sample review report, DCL, Certification)\n\n\u2022\u00a0\u00a0 \u00a0Advise/discuss with QAM & Technical Manager the critical and major issues related to projects\n\n\u2022\u00a0\u00a0 \u00a0Work with QAM on additional internal projects i.e. data analysis, SOP\u2019s, Guide for use by factory/production and within QA etc\n\n\u2022\u00a0\u00a0 \u00a0Review or if applicable release shipment release documents\n\nWhat will you need?\n\n\u2022\u00a0\u00a0 \u00a0Degree holder or relevant level of experience\n\n\u2022\u00a0\u00a0 \u00a0Minimum 5 \u2013 7 years relevant experience in Quality Assurance / QC position and factory inspection practice in international sourcing company is an advantage\n\n\u2022\u00a0\u00a0 \u00a0Possess strong technical expertise in hard-line or hard-goods products - Power tools\n\n\u2022\u00a0\u00a0 \u00a0Detail orientated\n\n\u2022\u00a0\u00a0 \u00a0High degree of work ethics and integrity\n\n\u2022\u00a0\u00a0 \u00a0A can-do attitude is a must\n\n\u2022\u00a0\u00a0 \u00a0Proficiency in Mandarin, English and Cantonese, both spoken and written\n\n\u2022\u00a0\u00a0 \u00a0PC knowledge is essential\n\n\u2022\u00a0\u00a0 \u00a0Travel is required\n\nWhat do we offer?\n\nMarket Leading Remuneration Package:\n\nDouble pay and discretionary bonus\nChoice of MPF provider\nLife Insurance\nMedical Insurance\n\n\n\u00a0\n\nSupportive Environment:\n\nRental re-imbursement scheme\nOut-Of-Office leave for important appointments\nIn-house training courses\nTraining sponsorship scheme\nHealth Check\nVision Check\nSupporting your child's education with advice from a leading education consultant\n\n\n\n\u00a0\n\nWork-Life Balance:\n\n5 day week\nCompetitive Annual Leave\nCharity, Community and Sporting Events\n\nMarket Leading Remuneration Package:\n\nDouble pay and discretionary bonus\nChoice of MPF provider\nLife Insurance\nMedical Insurance\n\u00a0\n\nSupportive Environment:\n\nRental re-imbursement scheme\nOut-Of-Office leave for important appointments\nIn-house training courses\nTraining sponsorship scheme\nHealth Check\nVision Check\nSupporting your child's education with advice from a leading education consultant\n\u00a0\n\nWork-Life Balance:\n\n5 day week\nCompetitive Annual Leave\nCharity, Community and Sporting Events", "employment_types": ["Permanent"], "selling_points": ["Appointed as Key Person", "Group\u2019s and Insurance Risk Management", "Excellent written and spoken Chinese"], "locations": ["Not Specified"], "categories": ["Accounting", "Consulting", "Insurance", "Actuarial", "Professional Services", "Legal & Compliance"], "post_time": "2022-01-11T10:03:06Z", "salary": {"currency": null, "max": null, "min": null, "period": "monthly", "term": null}, "salary_visible": false, "title_keywords": ["risk management manager"], "responsibilities": ["analysis", "quotation", "review", "quality", "monitor", "testing", "communication", "inspection", "data analysis", "reports", "schedule", "evaluation", "report"], "requirements": {"degrees": ["degree", "degree holder"], "majors": [], "languages": ["cantonese", "english", "mandarin"], "language_level": ["proficiency"], "hard_skills": ["dcl", "analysis", "inform", "pc knowledge"], "soft_skills": ["organized", "responsible", "can-do attitude", "integrity", "communication", "detail orientated"], "languages_combined": [{"language": "cantonese", "language_level": ["proficiency"]}, {"language": "english", "language_level": ["proficiency"]}, {"language": "mandarin", "language_level": ["proficiency"]}]}, "experience_required": {"duration": ["7 years"], "field": ["relevant experience", "quality assurance"]}}, {"job_id": "100003009037579", "location_code": "hk", "company": "Robert Walters (HK)", "job_title": "Head of Strategic Planning | HK listed bluechip", "description": "Summary\n\nWe value diversity at Lidl and this includes creating collaborative teams with colleagues with diverse experiences and backgrounds. Continue your career journey and make a difference with us here at Lidl!\n\nWhat will you do?\nResponsible for product design and development in kitchenware, \u00a0\nResponsible for product 3D modeling, rendering, product graphics and technical drawing output.\nWork with the team to prepare product design specification and integration documents.\nFollow through from product initiation, strategy, deployment, and testing.\nProvide mood boards, market trend analysis, performance data, product metrics to ensure product measures are on track and always constantly identifying future design & trends in the market.\nCollect end user's habit of using kitchenware to provide advice on new design & development\nInteract with customers to clearly understand product requirements and vision\nRegular communications with factories managing the design and development process to ensure the products are fit with the customer requirements\nStrong communication skills\nWell organized, highly dependable, efficient and detail oriented\nAbility to work in a fast-paced, deadline driven, high impact environment\nAbility to manage several projects in parallel, navigating a complex cross-functional matrix\nAbility to be a team player and work independently\nAffinity for cooking/food, and kitchenware design\nWhat will you need?\n4-5+ years of product design/engineering and development.\nBachelor\u2019s Degree (or equivalent experience) in product design/engineering\nExtensive kitchenware experience, with strong familiarity in European design & trends.\nHands-on experience in 3D software such as Solid-works, Keyshot, Photoshop, Illustrator and MS.\nStrong analytical skills and proven ability of data-driven decision-making, ability to define and manage qualitative and quantitative research and measurement plans\nCan-do attitude, willingness to learn and listen, ability to work independently, and strong drive to get things done\nStrong verbal and written communication skills in Chinese and English. Ability to effectively communicate with vendor and customer\nCreative, self-initiative, flexible and team working personality;\nGood organization and time management\nMay need to travel China sometimes\nA 100% consumer-first perspective when it comes to designing new products/processes or improving current products\nHighly-effective communication skills \u2013 both written (presentation/email) and in-person \u00a0\nStrong project management skills, with the ability to prioritize effectively, manage multiple projects simultaneously, and stay organized in a fast-paced environment\nA desire to learn and grow in a passionate environment\nWhat do we offer?\n\nWhat do we offer?\n\u00a0\n\nDouble pay and discretionary bonus\nChoice of MPF provider\nLife Insurance\nMedical Insurance\n\n\nSupportive Environment:\n\u00a0\n\nRental re-reimbursement scheme\nFlexible work arrangements\nIn-house training courses\nTraining sponsorship scheme\nHealth Check\nVision Check\nSupporting your child\u2019s education with advice from a leading education consultant\n\nWhat do we offer?\n\u00a0\n\nDouble pay and discretionary bonus\nChoice of MPF provider\nLife Insurance\nMedical Insurance\n\n\nSupportive Environment:\n\u00a0\n\nRental re-reimbursement scheme\nFlexible work arrangements\nIn-house training courses\nTraining sponsorship scheme\nHealth Check\nVision Check\nSupporting your child\u2019s education with advice from a leading education consultant", "employment_types": ["Full Time", "Permanent"], "selling_points": ["Hk listed blue chip", "Strategic planning/corporate development", "Stable environment with great culture"], "locations": ["Not Specified"], "categories": ["Accounting", "Consulting", "Media & Advertising", "Strategic Planning", "Professional Services", "Business Consultancy"], "post_time": "2022-01-11T03:11:23Z", "salary": {"currency": "HKD", "max": 159999, "min": 90000, "period": "monthly", "term": null}, "salary_visible": true, "title_keywords": [], "responsibilities": ["software", "data", "design", "communication", "designing", "plans", "graphics", "communications with", "teams", "measurement", "manage multiple projects", "testing", "management", "product design", "technical drawing", "communicate with", "analysis", "project management", "provide advice"], "requirements": {"degrees": ["degree", "bachelor"], "majors": ["engineering", "design"], "languages": ["english", "chinese"], "language_level": [], "hard_skills": ["graphics", "3d software", "analysis", "illustrator", "vendor", "analytical skills", "make", "project management", "deployment", "integration", "photoshop"], "soft_skills": ["can-do attitude", "fast-paced environment", "collaborative", "team player", "time management", "efficient", "diverse", "self-initiative", "team working", "creative", "presentation", "passionate", "communication skills", "work independently", "organized", "detail oriented", "prioritize", "analytical skills", "extensive", "driven", "flexible", "manage multiple projects simultaneously", "responsible", "project management skills", "well organized", "hands-on"], "languages_combined": [{"language": "english", "language_level": []}, {"language": "chinese", "language_level": []}]}, "experience_required": {"duration": [], "field": ["product design", "engineering", "design"]}}, {"job_id": "100003009036619", "location_code": "hk", "company": "Welab Bank Limited", "job_title": "Manager, Finance (Virtual Bank)", "description": "WeLab is a leading fintech company in Asia, \u00a0which operates one of first licensed digital banks in Asia \u2013 WeLab Bank, as well as multiple leading online financial services businesses including WeLend and WeLab Bank in Hong Kong, WeLab Digital (\u6211\u6765\u6570\u79d1), Taoxinji (\u6dd8\u65b0\u673a), Wallet Gugu (\u94b1\u5939\u8c37\u8c37) and Tianmian Tech (\u5929\u5195\u79d1\u6280) in Mainland China and Maucash in Indonesia. WeLab aims to bring joy to everyone\u2019s financial journey. We strive to improve people\u2019s lives by reinventing financial services through game-changing technology. We put our people first, whether it\u2019s our customers or our employees.\nWe are an energetic and passionate team that can deliver and execute. We are looking for other intellectually curious, open-minded and smart-working individuals who are just as passionate as we are about making financial services enjoyable. Now you have the opportunity to join us on our journey to achieve our vision and be part of building a better financial future for everyone.\n\nAbout you\n\nYou're a go-getter with mad juggling skills (or multiple hats) who can thrive in a fast-paced, agile environment\nYou have a strong thirst for knowledge and are driven to find solutions that don't exist yet\nYou are comfortable with ambiguity and extremely resourceful (in your past life you could've been a detective)\nYou always find a way to get things done without sacrificing the quality of your work, integrity and values. No task is off limits for you\nYou are humble and prioritize the success of the team over your own with an eagerness to help those around you\nYou don't shy away from challenges and have the ability to bounce back from setbacks\n\nWhat you\u2019ll do and what success looks like in this role\n\nLead the monthly management deck preparation and analysis to Management / Group office to facilitate business decision making process\nDrive management reporting automation to drive higher efficiency and productivity\nManage Finance system (Oracle Netsuite) to ensure accurate and efficient financial information and management information flow\nLead Head Office reporting\nSupport budget preparing and tracking processes\nSupport communication with internal and external stakeholders\n\nWhat is required and what we\u2019re looking for\n\nUniversity graduate with major in Accounting or Finance\nHKICPA or equivalent professional qualifications\nMinimum of 8 years\u2019 experience in management reporting, preferably in the banking industry\nProficient in MS Office (Excel / PowerPoint)\nExperience in ERP project is an advantage\nA team player with strong analytical mindset, good communication skills and risk awareness\nGood command of both spoken and written English and Cantonese\nCandidate with less experience will be considered as Assistant Manager\n\nWeLab perks\n\nCompetitive salary\nLearning and development stipend, because we value lifelong learning and believe the best way to invest in our employees is to encourage them to continue to learn\nWork hard and laugh lots (chicken wings and french toast, etc.) with a high-performing, fun and diverse team\nHappiness Dollars for spending on anything that makes you happy\nCoffee stipend\nConveniently located office surrounded by diverse and delicious lunch options\nLively office with gaming consoles and a ping pong table\nFun extracurricular activities with your colleagues like hiking, yoga, badminton, wine tasting, rock climbing, etc.\nEmployee referral bonuses\n\nAwards & Recognition\n\nFinancial Times (FT) 2020 Asia-Pacific High-Growth Companies \u2013 #2 ranked company\n2020 CNBC Disruptor 50 List \u2013\u00a0#11, only company included from Hong Kong and just one of five from Asia\n\nWe offer competitive salary package to the successful candidate.\u00a0 If you are interested in joining this exciting team, please apply with resume via the \"Apply\" button.\n\nAll information provided by applicants will be used for recruitment purposes only. Information of unsuccessful applicants will be destroyed within 24 months of receipt.", "employment_types": ["Full Time", "Permanent"], "selling_points": ["Lead the monthly management deck preparation", "Drive management reporting automation", "Manage Finance system (Oracle Netsuite)"], "locations": ["Quarry Bay"], "categories": ["Accounting", "Consulting", "Finance / Accounting Manager", "Financial Controller"], "post_time": "2022-01-10T11:24:53Z", "salary": {"currency": null, "max": null, "min": null, "period": "monthly", "term": null}, "salary_visible": false, "title_keywords": ["manager"], "responsibilities": ["reporting", "management", "analysis", "budget", "quality", "communication", "management reporting", "banking", "tracking"], "requirements": {"degrees": ["university graduate"], "majors": ["finance", "accounting"], "languages": ["cantonese", "english", "french"], "language_level": ["good command"], "hard_skills": ["excel", "no", "oracle", "joy", "agile", "fun", "professional qualifications", "analysis", "powerpoint", "erp", "hkicpa", "go", "ms office", "mad"], "soft_skills": ["passionate", "efficient", "communication skills", "agile", "resourceful", "accurate", "open-minded", "integrity", "prioritize", "communication", "diverse", "learning", "team player", "energetic", "driven", "decision making"], "languages_combined": [{"language": "cantonese", "language_level": ["good command"]}, {"language": "english", "language_level": ["good command"]}, {"language": "french", "language_level": []}]}, "experience_required": {"duration": ["minimum of 8 years"], "field": ["banking industry", "management"]}}, {"job_id": "100003009036810", "location_code": "hk", "company": "IVC Solutions Limited", "job_title": "SAP Solution Logistics / Finance Consultant - Graduate Programme Available", "description": "What we offer you:\n\n\nSAP official training\nMentoring and coaching on consulting skills\nExperience to work on projects for\u00a0reputable corporation\u00a0\nSAP consultant qualifications\u00a0recognized worldwide\n\nResponsibilities:\n\nParticipating in SAP project implementation;\nProviding business consultancy based on SAP solutions\u00a0\nProviding support services to our customers;\nProviding training to customers;\nProviding product demonstration and support to customers\n\nRequirements:\n\nDegree holder majored in Computer Science, Finance or Accounting is preferable\nOr Degree holder majored in Business Administration, Information System or related subjects;\nExperience in SAP or other enterprise software is an advantage;\nExperience in ERP / CRM / business process management is an advantage;\nLogical mind and critical thinking;\nStrong problem-solving and analytical skills;\nFlexibility to learn and work in dynamic environment;\nProactive attitude, with sense of ownership and strong team player;\nGood command of both written and spoken English and Putonghua.\n\nWe offer attractive remuneration and career opportunities to the right candidate. Interested parties please send detailed CV and portfolio with expected and present salary by clicking 'Apply Now'.\n\nAll applications received will be used strictly for selection purposes only.", "employment_types": ["Full Time", "Permanent"], "selling_points": ["SAP Consultant", "Finance or Accounting", "Computer Science"], "locations": ["Not Specified"], "categories": ["Accounting", "Consulting", "Information Technology (IT)", "Application Specialist - Software"], "post_time": "2022-01-10T14:51:20Z", "salary": {"currency": null, "max": null, "min": null, "period": "monthly", "term": null}, "salary_visible": false, "title_keywords": ["logistics", "consultant"], "responsibilities": [], "requirements": {"degrees": [], "majors": [], "languages": [], "language_level": [], "hard_skills": [], "soft_skills": [], "languages_combined": []}, "experience_required": {"duration": [], "field": []}}, {"job_id": "100003009035549", "location_code": "hk", "company": "Kaizen CPA Limited", "job_title": "Auditors (Junior to Senior) (5-Day work)", "description": "Job Responsibilities:\n\nHandle accounting, audit and tax assignments\nCommunicate and follow-up with clients\n\nJob Requirements:\n\nDegree or\u00a0diploma\u00a0holder with major in Accountancy is preferred\nStudent member or member of HKICPA or equivalent; finalist of HKIAAT will also be considered\nFresh graduates are welcome;\nCandidates with more experience in audit and tax field will be considered in senior position\nSelf-motivating and willing to confront seasonal work pressure\nHave a positive work attitude with good communication skills\nFluent in English and Chinese, including Mandarin\nImmediately available or at short notice is an advantage\n\nWe are a HKICPA authorized employer offering benefits, such as:\n\nFive-day work week\nStudy and exam leave\nMedical insurance\nPerformance bonus\nTransportation allowance\n\nInterested parties please email your full resume with present & expected salary \"APPLY NOW\".\n\nFor further details on Kaizen, please visit our website www.kaizencpa.com.", "employment_types": ["Full Time", "Permanent"], "selling_points": ["Group medical insurance, study & exam leave", "Good career prospects and learning opportunities", "Attractive package"], "locations": ["Kwun Tong"], "categories": ["Accounting", "Accountant", "Audit", "Consulting"], "post_time": "2022-01-10T07:37:22Z", "salary": {"currency": null, "max": null, "min": null, "period": "monthly", "term": null}, "salary_visible": false, "title_keywords": ["junior"], "responsibilities": ["tax", "follow-up with clients", "audit"], "requirements": {"degrees": ["diploma holder", "degree"], "majors": ["accountancy"], "languages": ["english", "chinese", "mandarin"], "language_level": ["fluent"], "hard_skills": ["hkicpa"], "soft_skills": ["communication skills", "positive work attitude"], "languages_combined": [{"language": "english", "language_level": ["fluent"]}, {"language": "chinese", "language_level": ["fluent"]}, {"language": "mandarin", "language_level": ["fluent"]}]}, "experience_required": {"duration": [], "field": ["audit"]}}, {"job_id": "100003009031791", "location_code": "hk", "company": "Lau & Au Yeung C. P. A. Limited", "job_title": "Junior Audit Accountants / Senior Audit Accountants", "description": "Responsibilities:\n\nThe candidates will be responsible for handling audit and tax assignments with clients located in Hong Kong and the Mainland China, occasionally travel to other countries may be required.\n\nRequirements:\n\n-\u00a0Degree holder in Accounting (Or equivalent qualification and/or experience);\n\n-\u00a0Strong communication skill and ability to work independently;\n\n-\u00a0Good command of written and spoken English, Chinese (Cantonese and Putonghua)\n\n- Immediate availability is preferred.\u00a0\n\n-\u00a0Fresh graduates will also be considered.\n\nWe offer career prospects and competitive remuneration packages to the right candidates.\u00a0If you welcome the challenge of a fast-paced, dynamic environment, please email your application with availability, present and expected salary by clicking \"Apply Now\" button.\n\n\nApplicants who are not invited within one month may consider their applications unsuccessful. All information provided by applicants will be treated in strict confidence and used only for recruitment purposes. All personal data will be destroyed after one month.", "employment_types": ["Full Time"], "selling_points": ["Degree holder in Accounting", "Fresh graduates are welcome", "Excellent career path"], "locations": ["Wan Chai Area"], "categories": ["Accounting", "Audit", "Consulting", "Taxation"], "post_time": "2022-01-07T09:45:55Z", "salary": {"currency": null, "max": null, "min": null, "period": "monthly", "term": null}, "salary_visible": false, "title_keywords": ["junior"], "responsibilities": ["tax", "audit"], "requirements": {"degrees": ["degree holder"], "majors": ["accounting"], "languages": ["cantonese", "putonghua", "english", "chinese"], "language_level": ["good command"], "hard_skills": [], "soft_skills": ["work independently", "communication skill"], "languages_combined": [{"language": "cantonese", "language_level": ["good command"]}, {"language": "putonghua", "language_level": ["good command"]}, {"language": "english", "language_level": ["good command"]}, {"language": "chinese", "language_level": ["good command"]}]}, "experience_required": {"duration": [], "field": ["accounting"]}}, {"job_id": "100003009027692", "location_code": "hk", "company": "Gravitas Recruitment Group", "job_title": "Top-tier Insurance firms- IFRS 17 M/AM", "description": "Job Description\n\nAct as a finance SME to participate in Group Insurance program driven project for implementation of changes per new accounting standard IFRS 17.\nFacilitate Insurance Business Finance for a smoother transition period on the implementation under the new standard IFRS 17;\nPerform data analysis for CSM data input and analyze finance results of the new standard, assess process flow in new operating model;\nConduct testing on dashboards and forecasting solution, in supporting the management information to be presented under the new standard;\nFacilitate and monitor the progress of regular discussion with various stakeholders, including Project Consultant, Project work groups, etc.;\nConsider any change of new process with SOX risk and initiate any updates on FIMs / DIM\nManage changes, facilitate transition process, and evaluate any risk located with any implementation, communicate with related stakeholders (onshore and offshore teams) on change update and action\n\nRequirements:\n\nUniversity degree holder in Finance, Accounting or a related discipline with a recognised professional accounting qualification\n* 5+ years of experience in accounting / auditing, with knowledge of insurance and financial products would be an advantage;\n* The ability to work independently under pressure and meet tight deadlines\n* Possesses good communication, interpersonal and analytical skills\n* Strong knowledge in application software such as MS Excel and PowerPoint\n* Good command of both spoken and written English and Chinese", "employment_types": ["Full Time", "Permanent"], "selling_points": ["Reputable Insurer", "IFRS17", "Good internal mobility"], "locations": ["Not Specified"], "categories": ["Accounting", "Accountant", "Audit", "Consulting"], "post_time": "2022-01-06T11:12:30Z", "salary": {"currency": "HKD", "max": 69999, "min": 45000, "period": "monthly", "term": null}, "salary_visible": true, "title_keywords": [], "responsibilities": ["communicate with", "forecasting", "management", "monitor", "implementation", "data input", "testing", "data analysis", "evaluate", "teams", "sme", "insurance"], "requirements": {"degrees": ["university degree"], "majors": ["finance", "accounting"], "languages": ["english", "chinese"], "language_level": ["good command"], "hard_skills": ["ms excel", "powerpoint", "analytical skills"], "soft_skills": ["work independently", "meet tight deadlines", "under pressure", "analytical skills", "communication", "interpersonal"], "languages_combined": [{"language": "english", "language_level": ["good command"]}, {"language": "chinese", "language_level": ["good command"]}]}, "experience_required": {"duration": ["5+ years"], "field": ["accounting", "insurance", "financial"]}}, {"job_id": "100003009029065", "location_code": "hk", "company": "Gain Miles Assurance Consultants Limited", "job_title": "Investment Consultant", "description": "Job Highlights:\nStrong interests in finance & investment market\nSFC License 1, passed HKSI papers 1, 7 & 8\nJob Descriptions\nProactively manage mutual fund investment related matters for our individual clients as an consultant, including advise compliance, address day-to-day enquiries, provide timely market updates\nConduct MPF & financial education member briefing and one-to-one consultation sessions for our corporate clients with communication plan, related materials are provided from internal mid-office\nParticipate in business development activities and initiatives, leads will be provided\nAchieving annual sales target from mutual fund and MPF related product selling\nFollow best-practice work processes to ensure high quality of service and deliverables to clients and compliance to internal control process\nPerform any ad-hoc tasks as assigned\nRequirements\nBachelor\u2019s Degree or equivalent qualification\n1-2 years\u2019 experience in consulting / customer service / business development of Mutual Fund investment or MPF products is preferred\nHolder of Insurance, SFC and MPFA license is a must\nGood communication skills on written and spoken English and Chinese\nGood understanding of MPF and investment\nPossess strong sense of responsibilities and be able to work independently and act as a good team player\nWe Offer\n5-day work\nAttractive monthly basic salary and annual performance bonus\nComprehensive fringe benefits including but not limited to:\n16 working days annual leave up to 24 days depending on years of services\nFamily Care Leave, Maternity and Paternity Leave, Birthday leave, etc.\nFree Life and Health Insurance including both In and Out-patient benefits\nPension Benefits on top of MPF mandatory contribution\nAdequate training and good allowances\nJoin the GM Winning Team today!\nReady to fly high in your career? Interested parties please submit your full resume with availability, current and expected salary by e-mail via clicking \"Apply Now\".\nWritten test as well as aptitude test will be conducted with shortlisted candidates.\nAll personal data provided by job applicants are used only for recruitment purpose and will be treated in strict confidence. Unsuccessful applications will be properly disposed within 3 months.", "employment_types": ["Full Time"], "selling_points": ["5-day work", "Bachelor\u2019s Degree or equivalent qualification", "1-2 years\u2019 experience in consulting"], "locations": ["Not Specified"], "categories": ["Accounting", "Consulting", "Banking / Finance", "Investment", "Sales, CS & Business Devpt", "Business Development"], "post_time": "2022-01-07T03:53:48Z", "salary": {"currency": null, "max": null, "min": null, "period": "monthly", "term": null}, "salary_visible": false, "title_keywords": ["investment consultant"], "responsibilities": ["mpf", "sales target", "compliance", "quality", "ad-hoc tasks", "communication", "plan", "internal control"], "requirements": {"degrees": ["degree", "bachelor"], "majors": [], "languages": ["english", "chinese"], "language_level": ["good"], "hard_skills": [], "soft_skills": ["communication skills", "work independently", "good team player", "customer service", "sense of responsibilities"], "languages_combined": [{"language": "english", "language_level": ["good"]}, {"language": "chinese", "language_level": ["good"]}]}, "experience_required": {"duration": ["1-2 years"], "field": ["mpf", "consulting", "business development", "customer service", "investment"]}}, {"job_id": "100003009018173", "location_code": "hk", "company": "Knight Recruitment Services Limited", "job_title": "Investment Analyst (Equity Funds & Asset Management, 5day, Up to HKD$50k)", "description": "Investment Analyst (Equity Funds & Asset Management, 5day, Up to HKD$50k)\n\nOur Client is an asset management firm who is looking for a Investment Analyst to support the evaluation and execution of direct investments and equity funds in US.\u00a0\n\nResponsibilities:\n\nConduct fundamental research on TMT sector and new economy companies in the United States\nPrepare comprehensive financial models, valuations and comparable companies\u2019 analysis\nProvide an insight into economic trends and evaluate investment potential.\nConduct detailed review on relevant financial and political market for decision making\nSupport portfolio management of existing and new investments\nCommunicate the information to management\n\n\u00a0Qualifications:\n\nBachelor Degree in Finance, Economics or related field\nProfessional Qualification such as CFA is definitely an advantage\nAt least 5 years of investment analyst experience from asset management, corporate investment in TMT companies, fund house, or corporate finance\nPrevious experience in TMT sector required\nStrong research, quantitative and financial analysis/modeling skills\nExcellent interpersonal and communication skills with fluency in written and spoken English and Putonghua\nGood project management and organizational skill, analytical and logical skills and sound business acumen\nAbility to work independently, detail-oriented, self-motivated and team working\n\nPlease send your resume along with cover letter to chelsie@ knightrecruits.com\n\nAll information received will be kept in strict confidence and only for employment-related purposes.\n\nData collected will be used for recruitment purposes only. Personal data provided by job applicants will be used strictly in accordance with the Personal Data (Privacy) Ordinance. We regret that only the shortlisted candidates will be notified.\n\nTag:\u00a0investment, fund, equity, fund, United States, US, stocks, fixed income, TMT, new economy, research, analysis, commercial, finance, financial model, valuation, portfolio management, M&A, corporate finance, commerce, accounting, banking, data", "employment_types": ["Full Time", "Permanent"], "selling_points": ["TMT, new econ companies investment analysis in US", "Salary Negotiable! 5 Day", "Good career development opportunity"], "locations": ["Sheung Wan"], "categories": ["Accounting", "Consulting", "Banking / Finance", "Analyst", "Professional Services", "Business Analysis / Data Analysis"], "post_time": "2022-01-05T02:59:45Z", "salary": {"currency": null, "max": null, "min": null, "period": "monthly", "term": null}, "salary_visible": false, "title_keywords": ["analyst", "asset management"], "responsibilities": ["valuation", "management", "data", "financial models", "analysis", "review", "banking", "evaluate", "financial analysis", "communication", "project management", "recruitment", "evaluation", "personal data", "asset management"], "requirements": {"degrees": ["degree", "bachelor"], "majors": ["finance", "economics"], "languages": ["putonghua", "english"], "language_level": ["fluency", "excellent"], "hard_skills": ["logical skills", "cfa", "analysis", "financial analysis", "project management", "acumen"], "soft_skills": ["communication skills", "work independently", "self-motivated", "organizational skill", "confidence", "detailed", "detail-oriented", "project management", "comprehensive", "business acumen", "team working", "interpersonal", "decision making"], "languages_combined": [{"language": "putonghua", "language_level": ["fluency", "excellent"]}, {"language": "english", "language_level": ["fluency", "excellent"]}]}, "experience_required": {"duration": ["at least 5 years"], "field": ["corporate finance", "investment", "asset management"]}}, {"job_id": "100003009032500", "location_code": "hk", "company": "ConnectedGroup Limited", "job_title": "Regional Project Manager (FMCG) (60-80k)", "description": "Regional Project Manager (FMCG)\n\nOur client is leading FMCG business with strong presence around the globe. We are seeking a talented individual to join them as a Project Manager in their regional team.\n\nPosition Responsibilities\n\nReport to the Asia Strategic Director\nWork independently and take a broad business perspective to implement the project management program for Asia\nWork with various functions and leads for projects to shape the approach, methodology, quality, stage gate milestones, costs and governance of these projects\nOversee the delivery of the Asia programs and milestones by leading a best in class PMO approach to efficiently administer the overall program execution, monitoring, tracing and governance\nCoordinate and govern the process of project work and own the process of review meetings with various project leads across various functions\nMonitor financial, interdependencies, critical paths, team performance and own the program tracking dashboard\nWork closely with the various project leads which make up the portfolio of projects managed by the Project Manager to optimize collaboration, resolve issues and tensions while escalating support required when necessary\nDevelop a continuous improvement approach to progress reporting and adherence to plan\nWork with the functions identified to fulfill the ambitions of the Asia Strategy such as Marketing, Sales, Supply Chain, R&D, Supply and Finance\n\nPosition Requirements\n\nDegree holder in Accounting, Finance or similar discipline\nProject Management Qualification or at least 6 years Project Management experience or proven experience working in large scale high impact projects\nPrior FMCG industry exposure is a MUST\nAbility to interact and develop relationships with all levels of associates, including senior management, to influence desired outcomes\nAbility to prioritize work, meet deadlines, and working effectively with manager while managing competing projects and/or demanding clients\nAbility to work independently and efficiently, with minimal supervision in a fast paced environment\nStrong conflict management and influencing without authority skills\nStrong communication, written and interpersonal skill\nAbility to speak fluent English is a MUST\n\nInterested individuals can apply now and send CV to Vivian Wong, or call +852 3972 5831 for more information. Only relevant candidates will be contacted.\n\nFor a more comprehensive list of our vacancies, please visit: www.connectedgroup.com", "employment_types": ["Full Time", "Permanent"], "selling_points": ["International working environment", "APAC exposure", "Large-scale and high-impact project exposure"], "locations": ["Not Specified"], "categories": ["Accounting", "Consulting", "Financial Analyst", "Others"], "post_time": "2022-01-07T11:19:46Z", "salary": {"currency": null, "max": null, "min": null, "period": "monthly", "term": null}, "salary_visible": false, "title_keywords": ["project manager"], "responsibilities": ["reporting", "tracking", "monitoring", "quality", "review", "monitor", "develop", "coordinate", "project management", "plan", "costs", "report"], "requirements": {"degrees": ["degree holder"], "majors": ["finance", "accounting"], "languages": ["english"], "language_level": ["fluent"], "hard_skills": ["project management", "fmcg industry"], "soft_skills": ["work independently", "prioritize", "interpersonal skill", "communication", "project management", "comprehensive", "meet deadlines"], "languages_combined": [{"language": "english", "language_level": ["fluent"]}]}, "experience_required": {"duration": ["at least 6 years"], "field": ["project management"]}}, {"job_id": "100003009028911", "location_code": "hk", "company": "Spring Professional (Hong Kong) Limited", "job_title": "Financial Analyst (MNC)", "description": "About Our Client\nOur client is one of the industry leading companies across global. They have over 20 offices and 3000 employees around the world. Due to their current growth, they are currently looking for Financial Analyst based in Hong Kong to join their team.\n\nWhat You'll Be Doing\n\nProvide Financial analysis for regional and business unit performance\nPartner with Business leaders for business cost evaluation and financial modelling\nConduct management business and financial review analyses for the performance of existing businesses and evaluate investment targets\nCoordinate with the annual budgeting & monthly forecasting and planning process\nConduct market research and provide financial analysis, financial modeling for transaction projects\nSupport ad hoc projects and presentation material\n\n\nWhat We Are Looking For\n\nDegree holder of Finance, Accounting, Business or related discipline\nHolder of CPA/ ACCA/ HKICPA/CFA would be a plus\nMinimum 2 year relevant working experience in MNC / sizable corporate would be preferred\nStrong quantitative skills and able to analyse a business both statistically and conceptually\nProficiency in MS Office particularly in PowerPoint and Excel\nExcellent in both written and communication English and Chinese\n\nInterest & Apply\nAdvance your career to the next level with this unique opportunity in Asia Pacific. To further consult on this role, please reach out to Anson Wong via Anson.wong @ springasia.com\u00a0\n\n", "employment_types": ["Full Time", "Permanent"], "selling_points": ["FP&A, transaction analysis", "Attractive package", "MNC/ Oversea experience"], "locations": ["Central & Western Area"], "categories": ["Accounting", "Accountant", "Consulting", "Financial Analyst"], "post_time": "2022-01-07T03:33:23Z", "salary": {"currency": null, "max": null, "min": null, "period": "monthly", "term": null}, "salary_visible": false, "title_keywords": ["financial analyst"], "responsibilities": ["cost", "management", "annual budgeting", "conduct market research", "review", "coordinate with", "planning process", "financial modeling", "financial analysis", "evaluate", "communication", "ad hoc projects", "evaluation", "forecasting", "analyse"], "requirements": {"degrees": ["degree holder"], "majors": ["business", "finance", "accounting"], "languages": ["english", "chinese"], "language_level": ["excellent"], "hard_skills": ["excel", "acca", "plus", "cfa", "powerpoint", "financial analysis", "cpa", "ms office", "hkicpa"], "soft_skills": ["communication", "presentation", "unique"], "languages_combined": [{"language": "english", "language_level": ["excellent"]}, {"language": "chinese", "language_level": ["excellent"]}]}, "experience_required": {"duration": ["minimum 2 year"], "field": ["relevant working experience"]}}, {"job_id": "100003009035565", "location_code": "hk", "company": "Kaizen CPA Limited", "job_title": "Auditors (Supervisor to Assistant Manager) (5-Day work)", "description": "Job Responsibilities:\n\nLiaise with clients through emails, phone calls, WhatsApp, WeChat, etc\nHandle accounting, audit and tax assignments\nSupervising juniors to carry out assignments\n\nJob Requirements:\n\nFull member of HKICPA (PC holder preferred)\nAt least FIVE years auditing experience in CPA firms, candidates with less experience will be considered as senior\nSelf-motivating and willing to confront seasonal work pressure\nHave a positive work attitude with good communication skills\nFluent in English and Chinese, including Mandarin\nImmediately available or at short notice is an advantage\n\nWe are a HKICPA authorized employer offering benefits, such as:\n\nFive-day work week\nStudy and exam leave\nMedical insurance\nPerformance bonus\nTransportation allowance\n\nInterested parties please email your full resume with present & expected salary via \"APPLY NOW\".\n\nFor further details on Kaizen, please visit our website www.kaizencpa.com.", "employment_types": ["Full Time", "Permanent"], "selling_points": ["Group medical insurance, study & exam leave", "Good career prospects and learning opportunities", "Attractive package"], "locations": ["Kwun Tong"], "categories": ["Accounting", "Accountant", "Audit", "Consulting"], "post_time": "2022-01-10T07:40:25Z", "salary": {"currency": null, "max": null, "min": null, "period": "monthly", "term": null}, "salary_visible": false, "title_keywords": ["assistant manager", "supervisor"], "responsibilities": ["liaise with clients", "tax", "supervising", "audit", "phone calls"], "requirements": {"degrees": [], "majors": [], "languages": ["english", "chinese", "mandarin"], "language_level": ["fluent"], "hard_skills": ["pc", "cpa", "hkicpa"], "soft_skills": ["communication skills", "positive work attitude"], "languages_combined": [{"language": "english", "language_level": ["fluent"]}, {"language": "chinese", "language_level": ["fluent"]}, {"language": "mandarin", "language_level": ["fluent"]}]}, "experience_required": {"duration": ["at least five years"], "field": []}}, {"job_id": "100003009027214", "location_code": "hk", "company": "Michael Page", "job_title": "Business Analyst (FMCG), 38k", "description": "My client is a US listed MNC, and becomes one of the largest FMCG company in the world. They provide wide range of consumer goods including hair, baby, body and feminine care. Currently, they are now hiring a Finance Manager with strong analytical skill to join them.\n\nClient Details\n\nMy client is a US listed MNC, and becomes one of the largest FMCG company in the world. They provide wide range of consumer goods including hair, baby, body and feminine care. Currently, they are now hiring a Finance Manager with strong analytical skill to join them.\n\nDescription\n\nResponsibilities:\n\npresenting financial analysis report on sales, brands and P&L\ninvolving in data analytical projects\nparticipating in different company functions, including sales finance and supply chain management\ncorporation between colleagues from different departments\nassisting in ad hoc assignments\n\nProfile\n\nRequirements:\n\nTop 3 University in Hong Kong or other top university worldwide\n1-3 years of working experiences on related backgrounds\nStrong numerical and analytical skills\nStrong communication and leadership abilities\nIndependent, self-motivated and proactive\nProficiency in MS Office software (Word, Excel)\n\nJob Offer\n\nWe will offer competitive package to successful candidates:\n\nExcellent career path and opportunities\nMedical insurance\n\nTo apply online please click the 'Apply' button below. For a confidential discussion about this role please contact Queenie Yu on +852 2848 9578", "employment_types": ["Full Time", "Permanent"], "selling_points": ["Strong analytical skills", "FMCG background is highly preferred", "Welcome Big 4 candidates"], "locations": ["Not Specified"], "categories": ["Accounting", "Consulting", "Financial Analyst", "Others"], "post_time": "2022-01-06T09:21:31Z", "salary": {"currency": null, "max": null, "min": null, "period": "monthly", "term": null}, "salary_visible": false, "title_keywords": ["business analyst"], "responsibilities": ["management", "data", "p&l", "financial analysis", "ad hoc assignments", "report"], "requirements": {"degrees": [], "majors": [], "languages": [], "language_level": [], "hard_skills": ["excel", "ms office", "word", "analytical skills"], "soft_skills": ["self-motivated", "independent", "analytical skills", "communication", "proactive", "leadership"], "languages_combined": []}, "experience_required": {"duration": ["1-3 years"], "field": ["related"]}}, {"job_id": "100003009031282", "location_code": "hk", "company": "Capital Advisory Limited", "job_title": "Assistant - Audit Assoicate / Trainee (Fresh graduate welcome)", "description": "Responsibilities\n\nu\u00a0 Assist finance projects including IPOs, mergers and \u00a0\u00a0acquisitions, and other\u00a0 \u00a0 \u00a0 \u00a0 \u00a0 \u00a0 \u00a0 \u00a0 \u00a0 management advisory projects\n\nu\u00a0 Support and communicate in the internal controls, auditing, accounting and tax\u00a0 \u00a0 \u00a0 \u00a0 \u00a0 \u00a0 \u00a0 assignments of the projects\n\nu\u00a0 Assist in deals support, such as reviewing target financials, business operation\u00a0 \u00a0 \u00a0 \u00a0 \u00a0 \u00a0 \u00a0 materials and involve in liaising deals structure\n\nu\u00a0 Liaise with other professional parties to support the implementation of projects\n\nu\u00a0 A good opportunity to allow audit junior to transit to capital market\n\nu\u00a0 Perform ad-hoc assignments\n\nRequirements\n\nu\u00a0 Degree holder or above in Accounting, Finance or Business Administration is\u00a0 \u00a0 \u00a0 \u00a0 \u00a0 \u00a0 \u00a0 \u00a0 \u00a0 preferred\n\nu\u00a0 Fresh graduates will also be considered\n\nu\u00a0 1-2 years working experience in accounting firm preferable,\n\nu\u00a0 Good command of spoken and written English, Mandarin and Cantonese\n\nu\u00a0 Proficiency in Excel\n\nu\u00a0 Hardworking and willing to learn new knowledge on top of accounting\n\nu\u00a0 Immediate available preferred\n\nWe offer\n\nu\u00a0 5-days work\n\nu\u00a0 Study and examination leave\n\nu\u00a0 Discretionary bonus\n\nu\u00a0 Double pay\n\nu\u00a0 Annual leave\n\nInterested parties please send your resume with expected salary and availability by clicking \"Apply Now\". All personal data collected will be used for recruitment purpose only.", "employment_types": ["Full Time", "Permanent"], "selling_points": ["Study and examination leave;  5-days work", "Discretionary bonus; Annual leave ; Bank holiday", "Sheung Wan MTR station; Double pay"], "locations": ["Sheung Wan"], "categories": ["Accounting", "Consulting", "Banking / Finance", "Dealing & Trading", "Equities / Capital Markets"], "post_time": "2022-01-07T09:08:12Z", "salary": {"currency": null, "max": null, "min": null, "period": "monthly", "term": null}, "salary_visible": false, "title_keywords": ["assistant", "trainee"], "responsibilities": ["tax", "business operation", "management", "ad-hoc assignments", "audit", "implementation of projects", "liaise with", "auditing"], "requirements": {"degrees": ["degree holder"], "majors": ["finance", "accounting", "business administration"], "languages": ["cantonese", "english", "mandarin"], "language_level": ["good command"], "hard_skills": ["excel"], "soft_skills": ["willing to learn", "hardworking"], "languages_combined": [{"language": "cantonese", "language_level": ["good command"]}, {"language": "english", "language_level": ["good command"]}, {"language": "mandarin", "language_level": ["good command"]}]}, "experience_required": {"duration": ["1-2 years"], "field": ["accounting"]}}]