[{"job_id": "100003009046688", "location_code": "hk", "company": "", "job_title": "Credit Controller", "description": "Job Description\nYour role:\nPerform credit management and debt collection actions\nCarry out debt recovery actions on corporate customers via telephone and demand letters\nExecute routine dunning actions for non-payment accounts on consumer segments\nLiaise with different internal parties in resolving disputes and outstanding accounts\nMonitor customer payment\u2019s behaviour, perform credit assessment and prepare credit risk analysis/MIS reports to management\nMonitor debt collector performance and perform day-to-day operations on debt assignments\nContribute to formulate credit policy and related credit system development\nHandle other credit control issues and ad hoc assignments\n\nTo succeed in this role:\n\nDiploma Holder or above in Business Administration, Accounting, Finance or related discipline\nMinimum 2\u00a0years' solid experience in credit management\nGood command of spoken and written English and Chinese\nProactive, outgoing, enthusiastic and sensitive to market/economic environment\nAnalytical and self-motivated in problem-solving\nCan work under pressure\nExcellent interpersonal and negotiation skills\nProficient MSOffice applications\nCustomer service experience is a plus\nInterested candidates, please contact us at 58016476 for company details before applying.", "employment_types": ["Full Time", "Permanent"], "selling_points": ["Perform credit management and debt collection", "Carry out debt recovery actions", "Execute routine dunning actions"], "locations": ["Kwai Tsing Area"], "categories": ["Accounting", "Credit Control"], "post_time": "2022-01-13T18:54:21Z", "salary": {"currency": "HKD", "max": 24999, "min": 20000, "period": "monthly", "term": null}, "salary_visible": true, "title_keywords": [], "responsibilities": ["management", "control", "work under pressure", "customer service experience", "letters", "monitor", "day-to-day operations", "debt collection", "payment", "reports", "risk analysis", "ad hoc assignments", "liaise with", "internal parties", "administration"], "requirements": {"degrees": ["diploma holder"], "majors": ["finance", "accounting", "business administration"], "languages": ["english", "chinese"], "language_level": ["good command"], "hard_skills": ["problem-solving", "analysis", "msoffice", "plus"], "soft_skills": ["outgoing", "self-motivated", "problem-solving", "sensitive to", "negotiation skills", "customer service", "enthusiastic", "proactive", "interpersonal", "work under pressure"], "languages_combined": [{"language": "english", "language_level": ["good command"]}, {"language": "chinese", "language_level": ["good command"]}]}, "experience_required": {"duration": ["minimum 2 years"], "field": ["management", "customer service"]}}, {"job_id": "100003009053388", "location_code": "hk", "company": "ACCOLADE Corporate Services Limited", "job_title": "Accounts Assistant / Accountant", "description": "\u00a0Responsibilities:\n\nResponsible for Account Receivable collection process\nHandle daily invoices, bills, vouchers and Accounts documents checking\nAssist in preparing general ledger, month end closing, auditing and taxation affairs\nAssist in others ad hoc task as requested\n\nRequirements:\n\nDiploma holder or above in accounting or related disciplines\nWith 2-3 years relevant working experience in accounts receivable\nKnowledge in using ZOHO system would be an advantage\nSelf-motivated, stable and willing to work under pressure, work independently and good communication skills\nProficient in MS Office (Word & Excel)\nGood command in English and Mandarin\nImmediate available is preferred", "employment_types": ["Full Time", "Permanent"], "selling_points": ["Responsible for Account Receivable collection proc", "With 2 years relevant working experience", "Knowledge in using ZOHO system"], "locations": ["Sheung Wan"], "categories": ["Accounting", "Accountant", "Accounting Clerk / Supervisor", "Credit Control"], "post_time": "2022-01-17T06:56:50Z", "salary": {"currency": null, "max": null, "min": null, "period": "monthly", "term": null}, "salary_visible": false, "title_keywords": ["accountant", "accounts assistant"], "responsibilities": ["taxation", "month end closing", "ad hoc", "invoices", "general ledger", "checking", "auditing"], "requirements": {"degrees": ["diploma holder"], "majors": ["related disciplines", "accounting"], "languages": ["english", "mandarin"], "language_level": ["good command"], "hard_skills": ["excel", "word", "ms office"], "soft_skills": ["communication skills", "work independently", "self-motivated", "stable", "work under pressure"], "languages_combined": [{"language": "english", "language_level": ["good command"]}, {"language": "mandarin", "language_level": ["good command"]}]}, "experience_required": {"duration": ["2-3 years"], "field": ["relevant working experience"]}}, {"job_id": "100003009044919", "location_code": "hk", "company": "Wharf Estates Limited", "job_title": "SENIOR ACCOUNTS RECEIVABLE OFFICER / ACCOUNTS RECEIVABLE OFFICER", "description": "Responsibilities:\n\nResponsible for credit control by following up delinquent accounts, monitoring irregularities, and enforcing payments by taking recovery actions\nSupervise billings and payment status of rental collection and prepare monthly account receivable reports\nHandle tenants\u2019 enquiries and complaints\nOther ad-hoc assignments as required\n\nRequirements:\n\nDegree holder in Accounting, Business Administration or related disciplines\nAt least 3 years\u2019 solid credit control experience preferably in billing and rental collection\nResponsible, attentive to details and self-motivated\nGood analytical and interpersonal skills\nProficiency in Microsoft Word and Excel\nGood command in both written and spoken English and Chinese\nLegal knowledge on delinquent accounts related to landlord and tenants will be an advantage\nCandidate with more experience will be considered as Senior Accounts Receivable Officer\n\nWe offer competitive remuneration package that commensurate with experience and qualifications.\u00a0 Interested parties are invited to send full resume stating contact telephone number, date available, present and expected salary to our recruitment email address.\n\n(Personal data provided will be used strictly in accordance with the Company's personal data policy which is available upon request.)", "employment_types": ["Full Time", "Permanent"], "selling_points": ["Responsible for credit control", "Degree holder in Accounting", "At least 3 years\u2019 solid credit control experience"], "locations": ["Tsim Sha Tsui"], "categories": ["Accounting", "Accounting Clerk / Supervisor", "Credit Control", "Others"], "post_time": "2022-01-15T03:49:24Z", "salary": {"currency": null, "max": null, "min": null, "period": null, "term": null}, "salary_visible": false, "title_keywords": ["senior accounts receivable officer", "accounts receivable officer"], "responsibilities": ["control", "irregularities", "ad-hoc assignments", "billings", "monitoring", "payment", "payments", "reports"], "requirements": {"degrees": ["degree holder"], "majors": ["related disciplines", "accounting", "business administration"], "languages": ["english", "chinese"], "language_level": ["good command"], "hard_skills": ["excel", "microsoft word"], "soft_skills": ["attentive to details", "interpersonal skills", "self-motivated", "responsible"], "languages_combined": [{"language": "english", "language_level": ["good command"]}, {"language": "chinese", "language_level": ["good command"]}]}, "experience_required": {"duration": ["at least 3 years"], "field": ["billing"]}}, {"job_id": "100003009043315", "location_code": "hk", "company": "Nesta (Hong Kong) Limited", "job_title": "Credit Control / Collection Officer ( Debt Collection and Credit control - 14-17K, 5days)", "description": "Our client is the world\u2019s premier company specializing in the supply chain is now seeking a high caliber to join their team as\u00a0Credit Control / Collection Officer.\n\n\n\nJOB RESPONSIBILITY\n\nHandle debt collection and credit control functions\nCommunicate with corporate customers for overdue payment collection\nResolve related disputes with internal and external parties in compliance with customer\u2019s / company\u2019s policies & procedures\nIdentify high risk and sensitive businesses to prevent disputes or other credit issues\nHandle credit and billing problems for customers\n\nJOB REQUIREMENT\n\nHigher Diploma holder or above\n2 years experience or above in\u00a0billings, credit collection, credit control, or accounting field\nGood command of written and spoken English\nStrong analytical and debt collection skills", "employment_types": ["Full Time", "Permanent"], "selling_points": ["Handle debt collection", "MNC in Supply Chain", "1years' experience in collection/billing"], "locations": ["Not Specified"], "categories": ["Accounting", "Accountant", "Accounting Clerk / Supervisor", "Credit Control"], "post_time": "2022-01-12T10:40:48Z", "salary": {"currency": "HKD", "max": 24999, "min": 17000, "period": "monthly", "term": null}, "salary_visible": true, "title_keywords": ["officer"], "responsibilities": ["communicate with", "control", "credit issues", "policies", "payment collection", "internal and external parties", "compliance", "procedures", "debt collection"], "requirements": {"degrees": ["higher diploma holder"], "majors": [], "languages": ["english"], "language_level": ["good command"], "hard_skills": [], "soft_skills": [], "languages_combined": [{"language": "english", "language_level": ["good command"]}]}, "experience_required": {"duration": ["2 years"], "field": ["accounting"]}}, {"job_id": "100003009052224", "location_code": "hk", "company": "Aon Services Hong Kong Limited \u6021\u5b89\u670d\u52d9\u9999\u6e2f\u6709\u9650\u516c\u53f8", "job_title": "Accounting Officer", "description": "We\u2019re hiring!\n\nAon is currently recruiting an\u00a0Accounting Officer\u00a0to join our team in Hong Kong.\n\nAbout Aon\n\nHeadquartered in London, Aon Plc is a leading global professional services firm providing a broad range of risk, retirement and health solutions. Our 50,000 colleagues in 120 countries empower results for clients by using proprietary data and analytics to deliver insights that reduce volatility and improve performance.\n\nAt Aon, you\u2019ll be part of a team which will support and inspire you and provide the opportunities and resources to develop your skills. It\u2019s an environment which encourages you to achieve your best - together we\u2019ll empower results.\u00a0\n\nResponsibilities:\n\nWork in Reinsurance department\nPerform daily accounting operation in account payable and receivable function\nHandle invoice payments, receipts, and reconciliation of accounts with client & reinsurers\nInvestigate if any discrepancies within the reconciliation and follow up with respective units\nParticipate in Short-term project, such as clearance of legacy balance\nLiaise with client manager to understand client\u2019s needs and resolve accounting issues\nParticipate in UAT for system projects in relating to system enhancement if required\nAssist managers on reporting and other ad-hoc tasks.\n\nRequirements:\n\nGraduate with Accounting/ Finance/ Business degree.\nAt least 2-3 years relevant Accounting experience is preferred.\nStrong technical skills in MS Excel.\nProficiency in English and Mandarin.\nGood analytical skill and problem-solving skill.\nGood interpersonal skill\nDetailed minded, proactive, accurate and meticulous.\nMature, independent, self-starter.\nImmediate available preferred.\n\nHow to Apply\n\nYour opportunity to empower results could start right here. Make your mark and apply online today with a brief covering letter and your resume, sharing relevant achievements for this position.\n\nWe Offer You\n\nA competitive total rewards package, continuing education & training, and tremendous potential with a growing worldwide organization.\n\nOur Colleague Experience\n\nEvery day, our colleagues make a difference, work with the best, own their potential, and value one another. Together, we share this one purpose: to empower economic and human possibility around the world. This unifying goal is at the heart of our identity, and it lives in everything we do. To learn more about our colleague experience, visit Aon Colleague Experience.\n\nAon is an equal opportunities employer. We are committed to creating a winning and inclusive culture where everyone feels valued and has opportunities for growth and development.", "employment_types": ["Full Time", "Permanent"], "selling_points": [], "locations": ["Quarry Bay"], "categories": ["Accounting", "Accounting Clerk / Supervisor", "Credit Control", "Insurance", "Others"], "post_time": "2022-01-17T02:30:38Z", "salary": {"currency": null, "max": null, "min": null, "period": "monthly", "term": null}, "salary_visible": false, "title_keywords": ["accounting officer"], "responsibilities": ["reporting", "receipts", "uat", "invoice", "ad-hoc tasks", "assist managers", "liaise with client", "payments", "daily accounting"], "requirements": {"degrees": ["degree"], "majors": ["business", "finance", "accounting"], "languages": ["english", "mandarin"], "language_level": ["proficiency"], "hard_skills": ["problem-solving", "make", "ms excel", "analytical skill"], "soft_skills": ["meticulous", "analytical skill", "independent", "accurate", "problem-solving", "mature", "interpersonal skill", "technical skills", "proactive", "detailed"], "languages_combined": [{"language": "english", "language_level": ["proficiency"]}, {"language": "mandarin", "language_level": ["proficiency"]}]}, "experience_required": {"duration": ["at least 2-3 years"], "field": ["accounting experience"]}}, {"job_id": "100003009044918", "location_code": "hk", "company": "Wharf Estates Limited", "job_title": "ASSISTANT ACCOUNTS RECEIVABLE OFFICER", "description": "Responsibilities:\n\nResponsible for billing, rental calculation and collection\nHandle tenants\u2019 enquiries and complaints\nOther ad-hoc assignments as required\n\nRequirements:\n\nHigher Diploma holder in Accounting, Business Administration or related disciplines with LCCI\u00a0Intermediate Level or above\n1-2 years\u2019 relevant working experience preferably in billing and rental collection\nResponsible, attentive to details and self-motivated\nGood organizational and interpersonal skills\nProficiency in Microsoft Word and Excel\nGood command in both written and spoken English and Chinese\nCandidate with more experience will be considered as Accounts Receivable Officer\nWe offer competitive remuneration package that commensurate with experience and qualifications. Interested parties are invited to send full resume stating contact telephone number, date available, present and expected salary to our recruitment email address.\n\n(Personal data provided will be used strictly in accordance with the Company's personal data policy which is available upon request.)", "employment_types": ["Full Time", "Permanent"], "selling_points": ["Responsible for billing & rental calculation", "Higher Diploma holder in Accounting", "1-2 years\u2019 relevant working experience"], "locations": ["Tsim Sha Tsui"], "categories": ["Accounting", "Accounting Clerk / Supervisor", "Credit Control", "Others"], "post_time": "2022-01-15T03:49:24Z", "salary": {"currency": null, "max": null, "min": null, "period": null, "term": null}, "salary_visible": false, "title_keywords": ["assistant accounts receivable officer"], "responsibilities": ["ad-hoc assignments"], "requirements": {"degrees": ["higher diploma holder"], "majors": ["related disciplines", "accounting", "business administration"], "languages": ["english", "chinese"], "language_level": ["good command"], "hard_skills": ["excel", "microsoft word"], "soft_skills": ["self-motivated", "attentive to details", "responsible", "organizational", "interpersonal skills"], "languages_combined": [{"language": "english", "language_level": ["good command"]}, {"language": "chinese", "language_level": ["good command"]}]}, "experience_required": {"duration": ["1-2 years"], "field": ["billing", "relevant working experience"]}}, {"job_id": "100003009049977", "location_code": "hk", "company": "HGC Global Communications Limited", "job_title": "Accounting Officer / Accounting Clerk", "description": "Responsibilities:\n\nResponsible for handing account receivables and billing related issues\nIssue monthly statement of Account, subsequent demand letters and calls\nUpdate the receipt transaction and assist in billing\u00a0\nEnsure the timely collection of outstanding debts and minimize the credit risk exposure\n\u00a0Requirements:\n\nDiploma or above in Accounting or related disciplines\n1 year of accounting experience\nGood command of both written and spoken English and Chinese\nIndependent, assertive and able to work under pressure\nImmediate available is preferred\n\nWe offer competitive salary package and career development opportunity. Free company coach is provided.\u00a0 Interested parties, please quote our reference number and apply with full resume, present and expected salary, by clicking \u201cAPPLY NOW\u201d.\u00a0\n\nWe are an equal opportunity employer and welcome applications from all qualified candidates. Information provided will be treated in strict confidence and only be used for consideration of your application for the relevant post within HGC Global Communications Limited. Personal data provided by job applicants will be used strictly according to our Personal Information Collection Statement, a copy of which will be available upon written request. Information of unsuccessful candidates will be destroyed within six months.", "employment_types": ["Full Time", "Permanent"], "selling_points": ["Diploma in Accounting", "1 years of relevant experience", "Responsible for settlement operations"], "locations": ["Tsing Yi"], "categories": ["Accounting", "Accountant", "Accounting Clerk / Supervisor", "Credit Control"], "post_time": "2022-01-14T09:34:35Z", "salary": {"currency": null, "max": null, "min": null, "period": "monthly", "term": null}, "salary_visible": false, "title_keywords": ["accounting clerk", "accounting officer"], "responsibilities": ["letters"], "requirements": {"degrees": ["diploma or above"], "majors": ["related disciplines", "accounting"], "languages": ["english", "chinese"], "language_level": ["good command"], "hard_skills": [], "soft_skills": ["work under pressure", "independent", "assertive"], "languages_combined": [{"language": "english", "language_level": ["good command"]}, {"language": "chinese", "language_level": ["good command"]}]}, "experience_required": {"duration": ["1 year"], "field": ["accounting experience"]}}, {"job_id": "100003009047888", "location_code": "hk", "company": "Robert Half", "job_title": "Regional AR Accountant, 25-30k | 1 year contract", "description": "The Company\n\nOur client is a US Listed MNC, urgently seeking a 1-year contract AR Accountant to join their HK business, and the ideal candidate will start immediately.\n\nThe Role\n\nResponsible for accounts receivable, ensure royalty reports are processed\nChase debtors on a regular basis, verify royalty reports from licensees\nHandle reconciliation of licensee or agent account balances\nPrepare invoicing summary, aging, open report summary to Category Manager\nAssist in ad hoc projects\n\nYour Profile\n\nDegree holder\nQualified Accountant is a plus\nExperience in credit control and SAP is preferable\nGood command in both written and spoken English and Cantonese\nStrong communication and interpersonal skills, independent and self-motivated\n\nApply Today\n\nTo apply online (Word attachment only), please click the 'Apply' button. Please note that only short-listed candidates will be contacted.", "employment_types": ["Full Time", "Contract"], "selling_points": ["Regional role", "AR/Credit Control/ Royalty Reporting/ Licensing", "Completion bonus"], "locations": ["Yau Tsim Mong Area"], "categories": ["Accounting", "Credit Control"], "post_time": "2022-01-14T04:09:02Z", "salary": {"currency": null, "max": null, "min": null, "period": "monthly", "term": null}, "salary_visible": false, "title_keywords": ["accountant"], "responsibilities": ["control", "ar", "accounts receivable", "invoicing", "communication", "reports", "ad hoc projects", "report"], "requirements": {"degrees": ["degree holder"], "majors": [], "languages": ["cantonese", "english"], "language_level": ["good command"], "hard_skills": ["word", "plus", "ar", "sap"], "soft_skills": ["self-motivated", "independent", "responsible", "communication and interpersonal skills", "ideal"], "languages_combined": [{"language": "cantonese", "language_level": ["good command"]}, {"language": "english", "language_level": ["good command"]}]}, "experience_required": {"duration": [], "field": []}}, {"job_id": "100003009046043", "location_code": "hk", "company": "China Telecom Global Limited", "job_title": "Billing Officer", "description": "Job description:\n\nCarry out billing data & material review, bill customers on the basis of contracts\nConfirm revenue & cost of business side, make sure the record is accurate with compliance to Accounting Standard\nFind & deal with the account record differences between business and finance side, as well as communicate with business partners for reconciliation\nFollow up customer billing enquiry and follow up afterwards\nConfirm financial income according to project progress; Make gross profit analysis of order forms\nMake account receivable management & aging schedule; prompt customers\u2019 collection & reconciliate bank statement\nReceive vendors\u2019 invoices & review bill and other materials & submit settlement payment\nOther duty assigned by superior\nRequirement:\n\nBachelor degree or above in Finance, Accounting, Information & Statistics or related disciplines preferred\nGood communication skills, Initiatives and conscientiousness\nGood at learning and systematic thinking, as well as making analysis and summary\nGood command of written and spoken English and Chinese (Cantonese & Mandarin)\nPrior system integration financial work experience is preferred.\n\nWe offer 5 days work, competitive salary package and attractive career development opportunities to the right candidate.\u00a0\n\nInterested parties please email your full resume with your current & expected salary to us.\n\nApplicants not invited for interview within 3 months may assume their applications unsuccessful.\u00a0\n\nPersonal data collected would be used for recruitment purpose only.\u00a0", "employment_types": ["Full Time", "Permanent"], "selling_points": ["1 year or above billing experience", "Stable working environment", "Excellent salary package and benefit"], "locations": ["Wan Chai"], "categories": ["Accounting", "Accounting Clerk / Supervisor", "Credit Control", "Financial Analyst"], "post_time": "2022-01-13T09:29:09Z", "salary": {"currency": null, "max": null, "min": null, "period": "monthly", "term": null}, "salary_visible": false, "title_keywords": ["billing officer"], "responsibilities": ["communicate with", "cost", "management", "invoices", "data", "contracts", "analysis", "review", "compliance", "project progress", "payment", "schedule"], "requirements": {"degrees": ["degree or above", "bachelor"], "majors": ["related disciplines", "finance", "accounting", "statistics"], "languages": ["cantonese", "english", "chinese", "mandarin"], "language_level": ["good command"], "hard_skills": ["integration", "analysis"], "soft_skills": ["communication skills", "learning", "systematic"], "languages_combined": [{"language": "cantonese", "language_level": ["good command"]}, {"language": "english", "language_level": ["good command"]}, {"language": "chinese", "language_level": ["good command"]}, {"language": "mandarin", "language_level": ["good command"]}]}, "experience_required": {"duration": [], "field": ["financial"]}}, {"job_id": "100003009039843", "location_code": "hk", "company": "Page Personnel", "job_title": "Collection/ Credit Control, Associate-MNC Platform", "description": "Our client is an European insurance company set up for more than 100 years. They are now looking for candidate who is with at least 2 years Collection/Credit Control experience with corporate clients to join them. They also welcome candidate coming from non-insurance background.\n\nClient Details\n\nOur client is an European based insurance company. They have set up for more than 100 years, specialising in general insurance business with corporate clients globally. They operate as a very strong MNC business with global footprint covering more than 200 regions. Setting their Asian hub in Hong Kong for more than 20 years, they have been providing competitive insurance services and products to their corporate clients.\n\nTo support their business growth, they are looking for candidate with Collection or Credit Control experience to join them. Candidate would be expected to negotiate with external counterpart from different countries to manage their collection status. Therefore, they would like to look for candidate who is strong in interpersonal skills and could communicate clearly in both Chinese and English. The company culture is very stable and friendly. They emphasise the career development of their staff by providing ample internal mobility opportunities.\n\nDescription\n\nPerform daily collection activities to manage the debt collection status meeting the assigned target.\nFollow up collection issues with suppliers and provide updated report to clients.\nWork closely with internal risk team for collection management\nHandle all enquiries related to collection issues.\nLiaise and maintain positive relationship with policy holders and brokers.\n\nProfile\n\nBachelor degree holder.\nAt least 2 years Collection/Credit Control experience with corporate clients.\nSolid experience of negotiation or client facing from previous job experiences.\nCandidate with experience of negotiating with regional counterpart would be a plus.\nExcellent command in both English and Chinese.\nSociable and self-motivated teamplayer who is with excellent interpersonal skills.\n\nJob Offer\n\nMNC Platform\nWell-established Business\nAnnual Leave: 14 days Up\nMedical Benefits\nDental Benefits\nBody Check\nExcellent Training\nInternal Mobility/ International Mobility\n\nTo apply online please click the 'Apply' button below. For a confidential discussion about this role please contact Ellen Fung on +852 3602 2447.", "employment_types": ["Full Time", "Permanent"], "selling_points": ["MNC Insurance Platform", "Collection Experience", "Excellent Internal Mobility"], "locations": ["Not Specified"], "categories": ["Accounting", "Credit Control", "Banking / Finance", "Credit Collection", "Risk Management"], "post_time": "2022-01-11T11:57:28Z", "salary": {"currency": "HKD", "max": 34999, "min": 20000, "period": "monthly", "term": null}, "salary_visible": true, "title_keywords": ["associate"], "responsibilities": ["liaise", "control", "management", "debt collection", "maintain", "career development", "insurance", "report"], "requirements": {"degrees": ["bachelor degree holder"], "majors": [], "languages": ["english", "chinese"], "language_level": ["excellent"], "hard_skills": ["plus"], "soft_skills": ["self-motivated", "negotiation", "sociable", "interpersonal skills", "friendly", "stable", "mobility", "positive"], "languages_combined": [{"language": "english", "language_level": ["excellent"]}, {"language": "chinese", "language_level": ["excellent"]}]}, "experience_required": {"duration": ["at least 2 years"], "field": ["business"]}}, {"job_id": "100003009048446", "location_code": "hk", "company": "China Duty Free International Limited", "job_title": "Accounting Officer / Accounting Assistant", "description": "About the role:\n\nResponsible for daily financial management, accounting, financial analysis and other related financial services\nPrepare monthly financial reports to HQ in an accurate and timely manner\nPrepare and exterminate of the company's General Ledger, Subsidiary Ledger, Cash Journal and Deposit Journal\nPerform month-end closing in SAP, analyze GL to ensure proper accounting treatment\nAssist in establish and improve accounting and financial management systems\nComplete other ad-hoc tasks assigned by the manager\n\nYou are the perfect one if you are/have:\n\nBachelor Degree\u00a0in Accounting, or in any relevant field\n2 years of accounting experience\nGood knowledge of Microsoft Office products (Word, Excel, PowerPoint, Outlook) and SAP\nTeam player with the ability to communicate and collaborate with multiple parties\nIndependent, responsible, self-motivated, willing to learn and able to work under pressure\nGood command of both written and spoken English and Chinese, including Cantonese and Mandarin\n\nJoin our productive, innovative, cooperative and fun work environment, share the joy of shopping, and extend the enjoyment of travel!\u00a0We offer 5-day work week, competitive salary and fringe benefits to the perfect one. Ready for your next adventure? Click \"Apply Now\" to start a fantastic\u00a0career with CDFI!\u00a0\n\nTo learn more about CDFI, visit our website at https://www.cdfg.com.cn\n\nAll information provided by applicants will be treated in strict confidence and used for recruitment purpose only. All personal data of unsuccessful applicants will be retained for 6 months for future recruitment purpose and will then be destroyed.", "employment_types": ["Full Time", "Permanent"], "selling_points": ["Accounting", "1-2 years experience", "Double pay + Bonus"], "locations": ["Wan Chai"], "categories": ["Accounting", "Accountant", "Accounting Clerk / Supervisor", "Credit Control"], "post_time": "2022-01-14T06:36:04Z", "salary": {"currency": null, "max": null, "min": null, "period": "monthly", "term": null}, "salary_visible": false, "title_keywords": ["accounting assistant", "accounting officer"], "responsibilities": ["collaborate with", "management", "financial reports", "general ledger", "ad-hoc tasks", "systems", "website", "financial analysis", "month-end closing", "recruitment", "personal data", "work under pressure"], "requirements": {"degrees": ["degree", "bachelor"], "majors": ["accounting"], "languages": ["cantonese", "english", "chinese", "mandarin"], "language_level": ["good command"], "hard_skills": ["excel", "sap", "fun", "word", "microsoft office products", "powerpoint", "financial analysis", "outlook", "joy"], "soft_skills": ["productive", "self-motivated", "confidence", "independent", "responsible", "timely", "cooperative", "willing to learn", "innovative", "team player", "accurate", "work under pressure"], "languages_combined": [{"language": "cantonese", "language_level": ["good command"]}, {"language": "english", "language_level": ["good command"]}, {"language": "chinese", "language_level": ["good command"]}, {"language": "mandarin", "language_level": ["good command"]}]}, "experience_required": {"duration": ["2 years"], "field": ["accounting experience"]}}, {"job_id": "100003008957949", "location_code": "hk", "company": "HKT", "job_title": "Credit Control Officer (Global)", "description": "Your role:\n\nMonitor customer's payment behavior\nFollow-up with the customers on past due invoices\nCarry out necessary debt recovery action according to company procedures\nWork in conjunction with internal parties to clarify any disputes/discrepancies identified\nDevise and recommend alternatives to supervisors on improving the existing systems and procedures\nBe responsible for all tasks relevant to the role such as preparation of operation statistics and reports for management review and perform other ad-hoc assignments as required\n\n\nTo succeed in this role:\n\nHigher Diploma / Degree holder\nMinimum 3 years of solid experience in account receivable management\u00a0\nExperience in telecommunications industry will have definite advantage\nProactive, self-motivated, enthusiastic and sensitive to market/economic environment\nWell versed with MS Office applications &, preferably, exposures to ERP system operation environment\u00a0\nGood command of spoken and written English and Chinese\nGood interpersonal and communication skills\n\nIf you have the desire for an exciting and rewarding career, please apply by sending your resume immediately, quoting your present and expected salary by clicking \"Apply Now\".", "employment_types": ["Full Time"], "selling_points": [], "locations": ["Lai Chi Kok"], "categories": ["Accounting", "Accounting Clerk / Supervisor", "Credit Control", "Banking / Finance", "Order Processing & Operation / Settlement"], "post_time": "2022-01-10T08:37:55Z", "salary": {"currency": null, "max": null, "min": null, "period": "monthly", "term": null}, "salary_visible": false, "title_keywords": ["credit control officer"], "responsibilities": ["management", "invoices", "ad-hoc assignments", "systems", "monitor", "procedures", "management review", "communication", "payment", "reports", "internal parties"], "requirements": {"degrees": ["diploma", "degree holder"], "majors": [], "languages": ["english", "chinese"], "language_level": ["good command"], "hard_skills": ["erp system", "ms office"], "soft_skills": ["communication skills", "self-motivated", "responsible", "sensitive to", "enthusiastic", "proactive", "interpersonal"], "languages_combined": [{"language": "english", "language_level": ["good command"]}, {"language": "chinese", "language_level": ["good command"]}]}, "experience_required": {"duration": ["minimum 3 years"], "field": ["telecommunications", "management"]}}, {"job_id": "100003009041336", "location_code": "hk", "company": "Chevalier AOC Freight Express Holdings Limited", "job_title": "Assistant Accountant / Senior Accounting Officer", "description": "Responsibilities:\n\n-\u00a0\u00a0\u00a0\u00a0\u00a0\u00a0 Prepare monthly financial reports and account schedules\n\n-\u00a0\u00a0\u00a0\u00a0\u00a0\u00a0 Responsible for credit control by following up delinquent accounts, monitoring irregularities, and enforcing payments by taking recovery actions\n\n-\u00a0\u00a0\u00a0\u00a0\u00a0\u00a0 Handle daily accounting operations including journal entries, maintain general ledgers, etc.\n\n-\u00a0\u00a0\u00a0\u00a0\u00a0\u00a0 Prepare reconciliations of bank accounts and inter-company accounts\n\n-\u00a0\u00a0\u00a0\u00a0\u00a0\u00a0 Assist in annual audit, taxation and cash flow management\n\n-\u00a0\u00a0\u00a0\u00a0\u00a0\u00a0 Perform Ad-hoc responsibilities as assigned\n\n\u00a0Requirements:\n\n-\u00a0\u00a0\u00a0\u00a0\u00a0\u00a0 Degree or Diploma in Accounting\n\n-\u00a0\u00a0\u00a0\u00a0\u00a0\u00a0 Knowledge in logistic industry is an advantage\n\n-\u00a0\u00a0\u00a0\u00a0\u00a0\u00a0 Well versed in Microsoft Excel (Pivot table, Vlookup, etc) and computerized accounting system\n\n-\u00a0\u00a0\u00a0\u00a0\u00a0\u00a0 Minimum 3 years relevant working experience, handle full set of accounts preferable\n\n-\u00a0\u00a0\u00a0\u00a0\u00a0\u00a0 Good Command of both English and Chinese (Mandarin and Cantonese)\n\n-\u00a0\u00a0\u00a0\u00a0\u00a0\u00a0 Good team player with can-do attitude, good interpersonal skills and willing to work overtime to meet with tight deadlines\n\n-\u00a0\u00a0\u00a0\u00a0\u00a0\u00a0 Immediate available is preferred, candidates with less experience will be considered as Senior Accounting Officer", "employment_types": ["Full Time", "Permanent"], "selling_points": [], "locations": ["Shatin Area"], "categories": ["Accounting", "Accounting Clerk / Supervisor", "Audit", "Credit Control"], "post_time": "2022-01-12T03:45:39Z", "salary": {"currency": null, "max": null, "min": null, "period": "monthly", "term": null}, "salary_visible": false, "title_keywords": ["senior accounting officer", "assistant accountant"], "responsibilities": ["ad-hoc", "taxation", "financial reports", "control", "irregularities", "management", "annual audit", "schedules", "company accounts", "monitoring", "daily accounting operations", "reconciliations", "cash flow", "maintain", "payments", "journal entries"], "requirements": {"degrees": ["diploma", "degree"], "majors": ["accounting"], "languages": ["cantonese", "english", "chinese", "mandarin"], "language_level": ["good command"], "hard_skills": ["pivot table", "vlookup", "accounting system", "microsoft excel"], "soft_skills": ["good team player", "work overtime", "interpersonal skills", "can-do attitude"], "languages_combined": [{"language": "cantonese", "language_level": ["good command"]}, {"language": "english", "language_level": ["good command"]}, {"language": "chinese", "language_level": ["good command"]}, {"language": "mandarin", "language_level": ["good command"]}]}, "experience_required": {"duration": ["minimum 3 years"], "field": ["accounting", "relevant working experience"]}}, {"job_id": "100003009043100", "location_code": "hk", "company": "A.S. Watson Industries", "job_title": "Assistant Accounting Officer (Account Receivable)", "description": "Assist in monitoring Account Receivable collection process\nEnsure the team to input all daily payment receipts for online & offline collection\nPerform bank reconciliation\nAssist in month end closing\nHandle system UAT and ad hoc projects\nWork with collection team to make sure all settlement on closing schedule\nAd hoc project\n\n\u00a0Job Requirements:\n\n\nDiploma holder or above in Business Administration or related disciplines\nAt least 3 years of relevant working experience in Accounts Receivable, experience in FMCG as preferred\nGood communication, presentation and interpersonal skill\nProficient in MS Excel and experience on Oracle is an advantage\n\nWe offer competitive salary, discretionary performance bonus, medical and retirement benefits, free company coach services and excellent career prospects. Please send your resume together with salary expectation via\u00a0APPLY NOW\n\nFor more information, please visit our website at\u00a0www.aswatson.com\n\nAll information provided will be used for recruitment other employment-related purposes by A.S. Watson & Company Limited (for and on behalf of the A.S. Watson Group of companies). It may be provided to companies/parties authorized to process the information for purposes relating to recruitment, e.g. qualifications assessment.\n\nWith the consent of applicant, all personal data of unsuccessful applicants will be retained for future consideration for two years. Otherwise, all personal data of unsuccessful applicants will be retained for twelve months.\n\nApplication will not be considered if the applicant does not provide all information as requested.\n\nAll information provided will be held in strict confidence.\n\nIf applicant request access to, and to request correction of personal data in relation to the application, please contact our People Department at 2660 1880.", "employment_types": ["Full Time", "Permanent"], "selling_points": ["Assist in Account Receivable collection process", "3 years experience in Accounts Receivable", "Free Shuttle Bus, Discretionary bonus"], "locations": ["Tai Po Area"], "categories": ["Accounting", "Accounting Clerk / Supervisor", "Credit Control", "Others"], "post_time": "2022-01-12T09:48:57Z", "salary": {"currency": null, "max": null, "min": null, "period": "monthly", "term": null}, "salary_visible": false, "title_keywords": ["assistant accounting officer"], "responsibilities": ["month end closing", "ad hoc", "receipts", "uat", "accounts receivable", "monitoring", "bank reconciliation", "website", "communication", "payment", "ad hoc projects", "schedule", "recruitment", "contact", "personal data", "administration"], "requirements": {"degrees": ["diploma holder"], "majors": ["related disciplines", "business administration"], "languages": [], "language_level": [], "hard_skills": ["make", "ms excel", "oracle"], "soft_skills": ["communication", "confidence", "presentation", "interpersonal skill"], "languages_combined": []}, "experience_required": {"duration": ["at least 3 years"], "field": ["fmcg", "relevant working experience"]}}, {"job_id": "100003009048236", "location_code": "hk", "company": "Ambition", "job_title": "Assistant Accountant (HKD20k, no OT, MNC)", "description": "Our client is a well-established and fast-growing company, which has strong presence within Asia. To facilitate their company growth, they are looking for a Assistant Accountant to join their Finance team.\n\nYou will be responsible for:\n\n\nResponsible for daily accounting operations, issue invoice and process payment\nPrepare staff expenses reimbursement, pretty cash, etc.\nConduct payment process and prepare bank reconciliation Liaise with vendors and/or relevant departments regarding payment and expense claim\nAssist in month-end closing and prepare relevant schedules\nPrepare bank reconciliations\nSupport in accounting and other ad hoc assignments\n\nTo qualify, individuals must possess:\n\n\nBachelor's degree in Business Administration or Accounting and Finance or any related disciplines\nAt least 1 year of accounting work experiences\nWilling to learn, good team player, attention to details and good communications\nProficient in written and spoken English and Chinese (Cantonese and Mandarin)\n\nInterested candidates, please submit application with the \"apply now\" button. For a quick application please forward your resume to ariel.chan@ambition.com.hk quoting #245352 Assistant Accountant, MNC\n\n\n\nIf this job isn't quite right for you, but you know someone who would be great at this role, why not take advantage of our referral scheme? We offer HKD1000 in Apple gift cards for every referred candidate who we place in a role. Terms & Conditions Apply. https://www.ambition.com.hk/refer-a-friend", "employment_types": ["Full Time", "Permanent"], "selling_points": ["AP and AR exposure", "Can sign CPA experiences", "13 months guaranteed salary"], "locations": ["Not Specified"], "categories": ["Accounting", "Accountant", "Audit", "Credit Control"], "post_time": "2022-01-14T06:00:02Z", "salary": {"currency": "HKD", "max": 19999, "min": 17000, "period": "monthly", "term": null}, "salary_visible": true, "title_keywords": ["assistant accountant"], "responsibilities": ["invoice", "schedules", "expenses", "daily accounting operations", "bank reconciliation", "bank reconciliations", "payment", "month-end closing", "finance team", "payment process", "ad hoc assignments", "liaise with", "administration"], "requirements": {"degrees": ["degree", "bachelor"], "majors": ["related disciplines", "finance", "accounting", "business administration"], "languages": ["cantonese", "english", "chinese", "mandarin"], "language_level": ["proficient"], "hard_skills": [], "soft_skills": ["good team player", "willing to learn", "attention to details", "responsible"], "languages_combined": [{"language": "cantonese", "language_level": ["proficient"]}, {"language": "english", "language_level": ["proficient"]}, {"language": "chinese", "language_level": ["proficient"]}, {"language": "mandarin", "language_level": ["proficient"]}]}, "experience_required": {"duration": ["at least 1 year"], "field": ["accounting"]}}, {"job_id": "100003009047022", "location_code": "hk", "company": "Toyo Mall Limited", "job_title": "ACCOUNTING OFFICER", "description": "Job Duties & Responsibilities:\n\nMainly responsible for AR related functions;\nPerform daily accounting operations and assist in credit control;\nProvide clerical support to the team including data entry and document filing;\nPerform other ad hoc duties as assigned.\n\nRequirements:\n\nLCCI higher or above;\nAt least 5 years commercial experience with 2 years in AR function is highly preferred;\nMature, good numeric sense, detail-minded and able to work independently;\nGood communication and interpersonal skills;\nProficient in MS Office such as Outlook, Excel and Word;\nFamiliar with Flex System is an advantage;\nImmediate available is highly preferred.\nAttractive package commensurate with experience and qualification will be given to the successful candidate. Our staff members' performance and contribution will be recognized and fairly rewarded.\u00a0 Please apply with full resume, date of available, current & expected salary toHuman Resources Manager, Toyo Mall Limited, 6/F, V Heun Building, 138 Queen\u2019s Road Central, Hong Kong.\u00a0\u00a0Applicants who wish to learn more about our Company may email the Human Resources Manager for more information.\u00a0 Those who do not hear from us within 4 weeks may consider their applications not successful in this instance.", "employment_types": ["Full Time", "Permanent"], "selling_points": [], "locations": ["Central"], "categories": ["Accounting", "Accounting Clerk / Supervisor", "Credit Control", "Property / Real Estate", "Others"], "post_time": "2022-01-14T02:04:04Z", "salary": {"currency": null, "max": null, "min": null, "period": "monthly", "term": null}, "salary_visible": false, "title_keywords": ["accounting officer"], "responsibilities": ["provide clerical support", "document filing", "control", "ad hoc duties", "ar", "data entry", "daily accounting operations"], "requirements": {"degrees": [], "majors": [], "languages": [], "language_level": [], "hard_skills": ["excel", "ar", "word", "outlook", "flex system", "ms office"], "soft_skills": ["detail-minded", "work independently", "communication and interpersonal skills", "mature"], "languages_combined": []}, "experience_required": {"duration": ["2 years", "at least 5 years"], "field": ["commercial"]}}, {"job_id": "100003009050291", "location_code": "hk", "company": "Nanyang Commercial Bank", "job_title": "Senior Credit Risk Manager / Credit Risk Manager   (Ref: OE8014-00-JDB)", "description": "Conduct independent credit assessment and validation of credit applications, including internal ratings, compliance of policies and regulations and make recommendations for approval. The portfolio of clients mainly covers PRC large corporate clients and NBFI, as well as those in the New Economy industries.Conduct on-going monitoring over large exposure, credit rating, early warning and risk concentration.Contribute to the formulation and review of credit risk policies and guidelines to cope with regulatory changes. Perform ad hoc projects or assignments.\n\nRequirements:\n\nMinimum 10 years\u2019 experience in corporate / structured credits and cross border transactions for PRC corporate clients and NBFI, either within a credit risk function or business line in banking industry.\nUniversity graduate with major in Accounting, Finance, Economics, Risk Management or related disciplines\nGood understanding in key market and industry dynamics as well as regulatory changes, especially that of PRC\nStrong expertise in risk and financial analysis, cash flow projections and banking products\nCFA, FRM, Accountant or HKIB ECF-CRM would be an advantage\nProficiency in written Chinese and English, fluency in Putonghua is preferred\nGood PC skills in MS Word and Excel\n\n(Candidate with less relevant experience will be considered as Credit Risk Manager)\n\nIf you are flexible enough and zeal for a harmonious and supportive working environment where enables you to grow and succeed professionally, please send a full resume indicating your public examination results (HKCEE and HKALE / HKDSE), your present and expected salary and quoting reference number attention to\u00a0Talent Acquisition Division, Nanyang Commercial Bank, 151 Des Voeux Road Central, Hong Kong or apply through email. For details, please visit https://www.ncb.com.hk/ and select the page Recruit.\n\nWe are an Equal Opportunities Employer. Data collected would be used for recruitment purposes only. Applicants who do not hear from us within 8 weeks may consider their applications unsuccessful and their data will be destroyed within 12 months of receipt.", "employment_types": ["Full Time", "Permanent"], "selling_points": ["Conduct independent credit assessment", "Conduct on-going monitoring over large exposure", "Minimum 10 years\u2019 experience"], "locations": ["Central & Western Area"], "categories": ["Accounting", "Credit Control", "Banking / Finance", "Credit Analysis / Approval"], "post_time": "2022-01-15T03:50:58Z", "salary": {"currency": null, "max": null, "min": null, "period": "monthly", "term": null}, "salary_visible": false, "title_keywords": ["manager"], "responsibilities": ["regulations", "make recommendations", "management", "data", "guidelines", "policies", "compliance", "monitoring", "review", "transactions", "financial analysis", "cash flow", "ad hoc projects", "recruitment", "banking"], "requirements": {"degrees": ["university graduate", "hkdse"], "majors": ["risk management", "finance", "economics", "related disciplines", "accounting"], "languages": ["putonghua", "english", "chinese"], "language_level": ["fluency", "proficiency"], "hard_skills": ["excel", "cfa", "financial analysis", "make", "pc skills", "frm", "ms word"], "soft_skills": ["make recommendations", "flexible", "supportive", "independent", "harmonious", "structured"], "languages_combined": [{"language": "putonghua", "language_level": ["fluency", "proficiency"]}, {"language": "english", "language_level": ["proficiency"]}, {"language": "chinese", "language_level": ["fluency", "proficiency"]}]}, "experience_required": {"duration": ["minimum 10 years"], "field": ["banking industry", "business", "relevant experience", "credit risk"]}}, {"job_id": "100003009051229", "location_code": "hk", "company": "Easy Job Centre", "job_title": "Senior Accounts Clerk / Accounting Officer", "description": "\u00a0Requirements\u00a0\n\nDiploma / Degree in Accounting or related discipline\n3-5 years or above relevant experience is preferred\nResponsible for daily accounting duties\u00a0\nAssist in month-end closing process & ad hoc projects as assigned\nStrong sense of responsibilities and detail-minded\nProficiency in PC operations including MS Word, Excel\nGood command of both written and spoken in English and Cantonese\nImmediate available is preferred\u00a0\n\nInterested parties, please send your resume with expected salary by clicking the below \"apply now\" button.\u00a0You can ask click on the website\u00a0www.easyjobhk.com\u00a0for more details about the company", "employment_types": ["Full Time"], "selling_points": [], "locations": ["Tsim Sha Tsui"], "categories": ["Accounting", "Accounting Clerk / Supervisor", "Credit Control", "Admin & HR", "Clerical / Admin Staff"], "post_time": "2022-01-15T05:19:58Z", "salary": {"currency": null, "max": null, "min": null, "period": "monthly", "term": null}, "salary_visible": false, "title_keywords": ["senior accounts clerk", "accounting officer"], "responsibilities": ["operations"], "requirements": {"degrees": ["diploma", "degree"], "majors": ["accounting"], "languages": [], "language_level": [], "hard_skills": [], "soft_skills": ["detail-minded", "responsible", "sense of responsibilities"], "languages_combined": []}, "experience_required": {"duration": ["3-5 years"], "field": ["relevant experience"]}}, {"job_id": "100003009049163", "location_code": "hk", "company": "Hays", "job_title": "Credit Analyst", "description": "You will work under the Credit Control team, starting with a 1 year contract with high temp to perm potential.\n\nYour new company\nMy client is a leading overseas investment bank with business across the globe.\n\nYour new role\n\nProvide administrative support, document scanning and record management for the credit control team.\nSupport the process of credit analysis and prepare financial data to improve overall accuracy\nAssist in checking loan documentation and portfolio report preparation\nInput financial data into company's internal system and execute audit handling.\nPerform ad-hoc assignments provided by Team head.\n\n\nWhat you'll need to succeed\n\nBachelor's Degree holder in /Accounting/ Finance/Business Administration/Economics or related disciplines\nBasic knowledge in accounting;\nResponsible, detail-oriented and able to work in a fast-paced environment\nWelcome fresh graduates with internship experience in credit\n\n\nWhat you'll get in return\n\nExcellent exposure to Credit\nOpportunities to develop your career in an overseas bank\nPrime office location\n\n\nWhat you need to do now\nIf you're interested in this role, click 'apply now' to forward an up-to-date copy of your CV to avery.lam@hays.com.hk, or call Avery Lam at 2230 7931 now. If this job isn't quite right for you but you are looking for a new position, please contact us for a confidential discussion on your career.", "employment_types": ["Full Time", "Temporary"], "selling_points": ["Excellent exposure to Credit", "Develop your career in an overseas bank", "Prime office location"], "locations": ["Not Specified"], "categories": ["Accounting", "Credit Control"], "post_time": "2022-01-14T08:12:04Z", "salary": {"currency": "HKD", "max": 16999, "min": 11000, "period": "monthly", "term": null}, "salary_visible": true, "title_keywords": ["credit analyst"], "responsibilities": ["scanning", "administration", "control", "management", "documentation", "data", "ad-hoc assignments", "analysis", "checking", "audit", "develop", "contact", "provide administrative support", "report"], "requirements": {"degrees": ["bachelor", "degree holder"], "majors": ["business administration", "finance", "economics", "related disciplines", "accounting"], "languages": [], "language_level": [], "hard_skills": ["credit analysis", "documentation", "basic"], "soft_skills": ["fast-paced environment", "interested in", "responsible", "detail-oriented"], "languages_combined": []}, "experience_required": {"duration": [], "field": []}}, {"job_id": "100003009044826", "location_code": "hk", "company": "Mizuho Bank", "job_title": "Vice President - Credit Control & Agency Team, Credit Section", "description": "Company Overview\n\nMizuho has a long-term commitment to the Hong Kong market. With strong\u00a0ties to Mizuho\u2019s\u00a0global\u00a0network\u00a0and a workforce of over 600 staff in Hong Kong,\u00a0we are able to help corporations in Hong Kong to expand their business worldwide. Our clients\u00a0primarily\u00a0comprise Japanese and non-Japanese corporations\u00a0(including\u00a0those domiciled in the\u00a0PRC), financial institutions,\u00a0and\u00a0government and quasi-government organizations. We provide a full spectrum of corporate banking services to our customers including syndicated\u00a0loans, treasury, transaction banking, financial advisory, project finance, merger and acquisition, leveraged finance,\u00a0and\u00a0structured finance.\u00a0\n\nWhy Mizuho\n\nAt Mizuho, we provide the stability of an international industry leader with the career trajectory of a growing business. Our steady, strategic growth gives our people at all levels rewarding degrees of responsibility and a richer work experience than a boutique firm or an established giant could offer alone.\n\nIt\u00a0is the local expertise of our employees that makes our global network so powerful. By collaborating with colleagues and clients who have your same ambition and drive, you can amplify your sphere of influence and base of knowledge as part of one of the largest\u2014and growing\u2014banks in the world.\n\nAbout the team\n\nCredit Section is responsible for analyzing and making recommendation on credit applications, checking and reviewing loan documentation, performing credit administration and control function, analyzing branch portfolio and prepare portfolio report and etc.\n\nRole requirements\n\nTo monitor / perform overall daily operations in relation to checking and reviewing of credit & security documents including Syndication Agency Administration function\nTo monitor / perform credit facility registration and customer\u2019s financial data input\nTo monitor and conduct custody operation / scanning of credit documents, specimen signatures update and filing\nTo supervise subordinates in overall daily operations\nTo assist team head to establish, review and revise internal operation procedures periodically\nTo initiate, conduct and implement workflow streamlining\nTo prepare, check periodic internal and management reports\nTo conduct training to the team mates and to other sections, when necessary\nTo learn and prepare for cross back up within and across team of the Section\nTo participate or take lead to operational excellence project/assignment as designated by team head / section head\nTo perform any other duties assigned by supervisor\n\nEssential Functions\n\nEnsure smooth operations of the Team\nSupport, advise and negotiate with CBDs in carrying out the proper credit risk management\nPrepare periodic internal and/or external management reports\nEstablish credit related policies and procedures of HK branch as required and carry out the annual review\nMonitor and ensure all operational excellence project of the team are executed smoothly.\n\nCompetencies\n\nWe are looking for an individual who understands Mizuho\u2019s mission, vision and values.\nHe/she should be able to work independently or in a team.\nThe individual should be able to judge priority among tasks and makes practical scheduling and time management to complete tasks before deadline.\nThe individual should be able to effectively negotiate with his/her external/internal counterparties to executive regular tasks. He/she is an excellent team player and has an innovative spirit.\nHe/she should respect for, and commit to high standards of business conduct and integrity.\n\nWork experience, education and skills\n\nBachelor Degree in Business Administration/Finance/Economics or related discipline\nMinimum 3-4 years\u2019 relevant experience in banking industry\nSolid experience in credit middle function at supervisory role\nGood computer skills and experienced in MS Office applications\nProcess work in a timely, punctual manner, active, open minded\nResponsible, able to work independently and under pressure\n\nApplication\n\nPlease indicate your\u00a0current and expected salary\u00a0on CV for the application.\u00a0\n\nMizuho Bank Limited\n\nMizuho Bank, Ltd. in Hong Kong is an integral part of the Japan-based Mizuho Financial Group, Inc. (NYSE: MFG). The Mizuho group is a global financial services leader with offices in nearly 40 countries, approximately 60,000 employees, and assets of almost USD 2 trillion. Mizuho provides expertise in retail banking, corporate finance, investment banking, asset management, capital markets, and sales and trading, to help businesses develop and find new opportunities for growth. To learn more: www.mizuhogroup.com\n\nPersonal data collected will be kept in strict confidence, and will be used for recruitment purpose only.", "employment_types": ["Full Time"], "selling_points": ["Checking and reviewing of credit & security doc.", "Monitor / perform credit facility registration", "Minimum 3-4 years\u2019 relevant experience"], "locations": ["Tsim Sha Tsui"], "categories": ["Accounting", "Credit Control"], "post_time": "2022-01-13T06:26:03Z", "salary": {"currency": null, "max": null, "min": null, "period": "monthly", "term": null}, "salary_visible": false, "title_keywords": ["vice president"], "responsibilities": ["banking"], "requirements": {"degrees": [], "majors": [], "languages": ["japanese"], "language_level": [], "hard_skills": [], "soft_skills": ["structured"], "languages_combined": [{"language": "japanese", "language_level": []}]}, "experience_required": {"duration": [], "field": []}}, {"job_id": "100003009034972", "location_code": "hk", "company": "Brink's Hong Kong Limited", "job_title": "Credit Control Officer", "description": "Responsibilities:\n\n\nHandle debt collection and credit control functions\nLiaise with local and overseas customers on payment settlement matters\nResolve related disputes\u00a0with internal and external parties\u00a0in compliance with customer\u2019s / company\u2019s policies & procedures\u00a0\nPrepare debt collection status report\nHandle ad-hoc assignments as requested by manager\n\nRequirements:\n\n\nTertiary Education or above\nMinimum 2 years of relevant experience in billings or credit collection in a sizable organization\nBe Mature, independent and adaptable to change\nTake initiative and hold exceptional analytical skills\nPossess good communication skill and able to work under pressure\nProficient in Microsoft Excel and be familiar with computerized accounting system\u00a0\n\nWe offer attractive remuneration package fringe benefits including\u00a0Banking Holidays, Annual Leave, Discretionary Bonus\u00a0& Medical Insurance. If you have the desire to join us, please send us your resume immediately with your present and expected salary via email marking\u00a0Application for Credit Control Officer.\n\n(The information provided will be used for employment related purpose only. All information of unsuccessful applicants will be destroyed within six months.)\n\n\n", "employment_types": ["Full Time", "Permanent"], "selling_points": ["5 day work", "2 yrs of exp in credit collection preferred", "Less experienced candidate will be considered"], "locations": ["Not Specified"], "categories": ["Accounting", "Accounting Clerk / Supervisor", "Credit Control", "Others", "Student / Fresh Graduate / No Experience"], "post_time": "2022-01-10T04:55:00Z", "salary": {"currency": null, "max": null, "min": null, "period": "monthly", "term": null}, "salary_visible": false, "title_keywords": ["credit control officer"], "responsibilities": ["control", "policies", "ad-hoc assignments", "internal and external parties", "compliance", "procedures", "debt collection", "payment", "liaise with", "report"], "requirements": {"degrees": [], "majors": [], "languages": [], "language_level": [], "hard_skills": ["microsoft excel", "accounting system", "analytical skills"], "soft_skills": ["independent", "adaptable", "communication skill", "mature", "analytical skills", "initiative", "work under pressure"], "languages_combined": []}, "experience_required": {"duration": ["minimum 2 years"], "field": ["sizable organization", "relevant experience"]}}, {"job_id": "100003009050161", "location_code": "hk", "company": "Magic Search Limited", "job_title": "Regional Cost Controller (Luxury Brand)", "description": "Our client is a global leading luxury Brand It is now looking for a Regional Finance Manager to join their team.\n\nKey Responsibilities\n\nPrepare and consolidated costing report with comparison against Budget and Forecast with comment\nWork closely with other functional team to ensure alignment and to reconcile any discrepancy\nPrepare other regular cost reporting or ad hoc analysis for management review of business performance\u00a0\nDevelop and replicate excel\u00a0budget/forecast\u00a0templates for\u00a0Asia\u00a0market\u00a0and\u00a0validation\u00a0\u00a0\nAssist\u00a0with the\u00a0budget & forecast\u00a0consolidation and review\u00a0process\nValidate system input and co-ordinate necessary follow-up with market\u00a0finance team\nAssist with analysis during budget and forecast process\nCost Management and Budget follow-up\nAssist in establishing/improving means of regional\u00a0cost\u00a0tracking\u00a0and budget follow-up\u00a0process\nRecommend and develop relevant reports and analysis\nAssist with SAP & Planning and Consolidation tool co-ordination, vendor master data creation and maintenance, and other ad hoc projects\n\nRequirements\n\nBachelor degree in Finance, Accounting or other related subjects\n6-7 years relevant retail working experience\nAbility to extract, organise, analyse and report data\nGood communication skills\nGood command in English and Chinese\u00a0", "employment_types": ["Full Time", "Permanent"], "selling_points": ["6-7 years experience", "luxury brand", "audit experience is a plus"], "locations": ["Not Specified"], "categories": ["Accounting", "Credit Control", "Financial Analyst", "Financial Controller"], "post_time": "2022-01-14T09:53:47Z", "salary": {"currency": null, "max": null, "min": null, "period": "monthly", "term": null}, "salary_visible": false, "title_keywords": [], "responsibilities": ["data", "budget", "system input", "management review", "relevant reports", "ad hoc", "develop", "finance team", "forecast", "report", "reporting", "cost", "management", "review", "tracking", "maintenance", "forecast process", "analysis", "ad hoc projects", "planning"], "requirements": {"degrees": ["degree", "bachelor"], "majors": ["finance", "accounting"], "languages": ["english", "chinese"], "language_level": ["good command"], "hard_skills": [], "soft_skills": ["communication skills"], "languages_combined": [{"language": "english", "language_level": ["good command"]}, {"language": "chinese", "language_level": ["good command"]}]}, "experience_required": {"duration": ["6-7 years"], "field": ["retail"]}}, {"job_id": "100003009042334", "location_code": "hk", "company": "Chance Max Limited", "job_title": "Accountant / Senior Accountant", "description": "RESPONSIBILITIES\n\nResponsible for preparing full set of accounts\nPrepare management and consolidation financial reports on a timely basic\nPrepare the financial reporting schedules, annual budgeting, cash flow analysis and bank reconciliation\nCoordinate with business departments for the accounting related matters and daily accounting transactions\nAssist in establishing, reviewing and improving accounting and procurement procedures and internal control system\nLiaise with auditors in connection with annual audit process and tax filling\nProvide support to the management for ad-hoc assignments\n\nREQUIREMENT\n\nDegree holder in Accounting / Finance or related disciplines\nAt least 5 years of working experience, with experience in Finance industry or China background is an advantage\nIndependent, self-motivated, responsible and detailed oriented\nStrong analytical skill & problem-solving skill with proactive attitude and able to work independently are required\nExcellent command of both written and spoken English & Mandarin & Chinese\nCompetent PC skills in MS Word, Excel and Chinese word processing\nCandidate with less experience will be considered as Accountant\nImmediate available preferred\n\nWe offer competitive remuneration package including 5-day work, performance bonus to the right candidate. Interested parties please send full resume with current and expected salary, availability by email or by clicking \"Apply Now\".\n\n\n(Personal data collected will be used for recruitment purposes only)\n\n", "employment_types": ["Full Time", "Permanent"], "selling_points": [], "locations": ["Tsuen Wan Area"], "categories": ["Accounting", "Accountant", "Credit Control", "Others"], "post_time": "2022-01-12T07:05:59Z", "salary": {"currency": null, "max": null, "min": null, "period": "monthly", "term": null}, "salary_visible": false, "title_keywords": ["accountant", "senior accountant"], "responsibilities": ["schedules", "bank reconciliation", "transactions", "liaise with", "internal control", "annual budgeting", "full set of accounts", "management", "provide support", "annual audit", "coordinate with", "procedures", "cash flow", "tax", "financial reports", "ad-hoc assignments", "analysis", "financial reporting", "daily accounting"], "requirements": {"degrees": ["degree holder"], "majors": ["related disciplines", "finance", "accounting"], "languages": ["english", "chinese", "mandarin"], "language_level": ["excellent"], "hard_skills": ["excel", "analytical skill", "chinese word processing", "problem-solving", "pc skills", "ms word"], "soft_skills": ["self-motivated", "analytical skill", "detailed oriented", "independent", "responsible", "work independently", "competent", "problem-solving", "proactive"], "languages_combined": [{"language": "english", "language_level": ["excellent"]}, {"language": "chinese", "language_level": ["excellent"]}, {"language": "mandarin", "language_level": ["excellent"]}]}, "experience_required": {"duration": ["at least 5 years"], "field": ["finance industry"]}}, {"job_id": "100003009048077", "location_code": "hk", "company": "iPR Ogilvy Limited", "job_title": "Accounting Clerk", "description": "Responsibilities:\n1) Responsible for all accounts functions, including performing accurate and prompt processing all accounts transactions, as well as ensuring all data are entered correctly and appropriately into the accounting system\n2) Coordinate with staff within and outside the department to ensure smooth payment process and handle payable enquiries\n\n3)\u00a0\u00a0Contact customers via email/phone for outstanding invoices\n\n4)\u00a0 Support the month end closing process and prepare reporting package\n5)\u00a0 Assist in any other ad hoc duties as assigned\nJob Requirement:\n1)\u00a0 DSE / HKCEE with LCC intermediate or the equivalent\n\n2)\u00a0 Fresh graduate is welcome to apply\n\n3)\u00a0 Relevant experience in accounting field is an advantage\n4)\u00a0 Capable to work multi-tasks, well organized and detail-minded\n5)\u00a0 Knowledge of Flex system (accounting system) is an advantage\n6)\u00a0 Good command of written and spoken English and Chinese\n7)\u00a0 Strong numeric sense,\u00a0analytical\u00a0and good interpersonal skills\u00a0\n\n8)\u00a0\u00a0Proficient in MS Office\n", "employment_types": ["Full Time", "Contract"], "selling_points": ["General accounting duties", "DSE / HKCEE with LCC intermediate", "Well-organized, self-motivated, independent"], "locations": ["Wan Chai"], "categories": ["Accounting", "Accounting Clerk / Supervisor", "Credit Control", "Others"], "post_time": "2022-01-14T04:43:23Z", "salary": {"currency": null, "max": null, "min": null, "period": "monthly", "term": null}, "salary_visible": false, "title_keywords": ["accounting clerk"], "responsibilities": ["ad hoc duties", "reporting", "month end closing", "invoices", "data", "coordinate with", "contact", "payment process", "accounts transactions"], "requirements": {"degrees": ["fresh graduate", "dse"], "majors": [], "languages": ["english", "chinese"], "language_level": ["good command"], "hard_skills": ["accounting system", "lcc", "flex system", "ms office"], "soft_skills": ["detail-minded", "capable", "multi-tasks", "well organized", "interpersonal skills"], "languages_combined": [{"language": "english", "language_level": ["good command"]}, {"language": "chinese", "language_level": ["good command"]}]}, "experience_required": {"duration": [], "field": ["accounting", "relevant experience"]}}, {"job_id": "100003009047578", "location_code": "hk", "company": "ConnectedGroup Limited", "job_title": "Finance Director, Investment Bank, 85-100k", "description": "Finance Director, Investment Bank, 85-100k\n\nFast growing platform\nFriendly working culture\nAll rounded exposure\n\nA leading investment bank is looking for a Finance Director manager for their Finance team.\n\nManaging a team, you will be responsible for -\n\nOverseeing the financial controld and reportings\nManagement reporting.\nReviewing the regulatory reporting.\nManaging the internal control.\nLeading the accounting policies process.\nCoordinating with external auditors and internal departments on annual audit.\nTax planning.\nHandling other ad hoc projects.\n\nRequirement:\n\nDegree holder in Finance or related disciplines\nOver 12 years' experience in the banking industry/ financial institution\nExcellent analytical skills\nIn-depth knowledge in accounting and financial products.\nStrong communication skills\nStrong team management skills.\nGood command of both spoken and written English and Chinese\nStrong analytical mind\n\nTo apply, pls send your CV with your current and expected salary in WORD format with your current and expected salary.", "employment_types": ["Full Time", "Permanent"], "selling_points": ["Fast growing platform", "Friendly working culture", "All rounded exposure"], "locations": ["Not Specified"], "categories": ["Accounting", "Accountant", "Audit", "Credit Control"], "post_time": "2022-01-14T03:29:59Z", "salary": {"currency": null, "max": null, "min": null, "period": "monthly", "term": null}, "salary_visible": false, "title_keywords": ["director"], "responsibilities": ["tax", "reporting", "management", "annual audit", "external auditors", "communication", "accounting policies", "planning", "ad hoc projects", "management reporting", "finance team", "banking", "managing a team", "internal control"], "requirements": {"degrees": ["degree holder"], "majors": ["related disciplines", "finance"], "languages": ["english", "chinese"], "language_level": ["good command"], "hard_skills": ["word", "analytical skills", "internal control"], "soft_skills": ["communication skills", "responsible", "analytical skills", "analytical mind", "friendly"], "languages_combined": [{"language": "english", "language_level": ["good command"]}, {"language": "chinese", "language_level": ["good command"]}]}, "experience_required": {"duration": ["12 years"], "field": ["banking industry", "financial"]}}, {"job_id": "100003009036791", "location_code": "hk", "company": "BOCI", "job_title": "VP, Credit Control Management, Private Banking", "description": "My client is currently expanding their business in APAC and is looking for an Assistant Accountant to support their APAC finance team.\n\nClient Details\n\nOur client is a US listed company with a strong reputation globally. They have multiple brands and produce different consumer products. Since they are currently expanding their business in APAC, especially HK, they are looking for a high calibre to join their finance team and grow with the business.\n\nDescription\n\nResponsible in accounts receivable (AR) and credit control functions across APAC\nPrepare overdue debtor reports and follow up outstanding invoices\nValidate the invoice details and amount\nHandle bank reconciliation, cash allocation, month-end closing\nAssist in audit and tax related matters\nWork with Share Service Center (SSC) on finance related issues\nSupport ad hoc assignment\n\nProfile\n\nDegree in accounting\nAt least 3 years' accounting / audit experience\nStudent member of accounting qualification (HKICPA, CPAA, ACCA, AICPA, etc.)\nProficient in Microsoft Excel\nFamiliar with SAP or other ERP system is a plus\nGood communications and interpersonal skills\nFluent in English and Cantonese\nCandidate with only audit background / return-to-work is considered\n\nJob Offer\n\nWork-life balance, supportive and dynamic environment\nStrong reputation within the industry\nAttractive remuneration package\nSAP system and APAC exposure", "employment_types": ["Full Time"], "selling_points": ["Credit control team lead function", "8 years+ credit control experience", "Private banking experience is a plus"], "locations": ["Central"], "categories": ["Accounting", "Credit Control", "Banking / Finance", "Private Banking", "Risk Management"], "post_time": "2022-01-10T14:26:22Z", "salary": {"currency": null, "max": null, "min": null, "period": "monthly", "term": null}, "salary_visible": false, "title_keywords": ["private banking"], "responsibilities": ["tax", "control", "ar", "accounts receivable", "invoices", "invoice", "ad hoc assignment", "bank reconciliation", "audit", "month-end closing", "reports", "finance team"], "requirements": {"degrees": ["degree"], "majors": ["accounting"], "languages": ["cantonese", "english"], "language_level": ["fluent"], "hard_skills": ["acca", "plus", "ar", "sap", "microsoft excel", "erp system", "dynamic", "hkicpa"], "soft_skills": ["supportive", "interpersonal skills", "responsible", "dynamic environment"], "languages_combined": [{"language": "cantonese", "language_level": ["fluent"]}, {"language": "english", "language_level": ["fluent"]}]}, "experience_required": {"duration": ["at least 3 years"], "field": ["audit experience", "accounting"]}}, {"job_id": "100003009040107", "location_code": "hk", "company": "Page Personnel", "job_title": "Assistant Accountant - US Listed Company", "description": "Our client is seeking for a candidate who is experienced in billing and credit control function, open to different industry background. You will join their Finance team in Hong Kong and being as a leader in the team to monitor the whole billing & credit activities. Don't miss the chance if you would like to have exposure in legal sector and join the corporate Law Firm Finance team.\n\nClient Details\n\nOur client is one of the top leader in the legal sector. They are the expert in handling equity, debt structured finance, and derivatives. They work closely with World's Top investment banks and largest financial institutions. They are looking for a highly skilled candidate with experiences in Billing and Credit Control to join their Finance Team in Hong Kong. They are offering excellent salary and benefit packages to potential job candidates\n\nDescription\n\nHandle debt collection and credit control functions\nLiaise with local and overseas business partners on payment settlement matters\nRegular communication with matter partners & managers & local finance team on debts status\nMonitor debt collector performance and perform day-today operations on debt assignments=\nResolves related disputes with internal and external parties in compliance with customer's or company's policies and procedures\nDaily monitoring of accounts position, identify and report any potential risk\nEnsure timely and accurate issuance of all bills\nReview and monitor for billing matters\nAssist in daily accounting operations and month-end closing\n\nProfile\n\nDiploma or above in any disciplines\nOpen to any industry background, experience in law firm or service firm is an advantage\nProactive with good interpersonal, communication and able to work independently\nExcellent in spoke and written English\nPrior experience in AX system will be an advantage\nResponsible, attentive to details and self-motivated\n\nJob Offer\n\n5-day work week, from 9:30 am to 6:00 pm\n25 days of AL\nMedical, dental and life insurance\nLaw firm exposure\nStable working condition\nAttractive salary package\n\nTo apply online please click the 'Apply' button below. For a confidential discussion about this role please contact Carmen K Wong on +852 3602 2463.", "employment_types": ["Full Time", "Contract"], "selling_points": ["Attractive remuneration package", "APAC exposure", "Supportive enviroment"], "locations": ["Not Specified"], "categories": ["Accounting", "Accountant", "Accounting Clerk / Supervisor", "Credit Control"], "post_time": "2022-01-12T01:26:34Z", "salary": {"currency": null, "max": null, "min": null, "period": "monthly", "term": null}, "salary_visible": false, "title_keywords": ["assistant accountant"], "responsibilities": ["operations", "internal and external parties", "communication", "payment", "liaise with", "daily monitoring", "control", "compliance", "monitor", "daily accounting operations", "debt collection", "finance team", "report", "review", "procedures", "contact", "policies", "month-end closing", "insurance"], "requirements": {"degrees": ["diploma or above"], "majors": ["any disciplines"], "languages": ["english"], "language_level": ["excellent"], "hard_skills": [], "soft_skills": ["work independently", "proactive", "self-motivated", "accurate", "responsible", "attentive to details", "timely", "communication", "stable", "structured", "interpersonal"], "languages_combined": [{"language": "english", "language_level": ["excellent"]}]}, "experience_required": {"duration": [], "field": ["finance", "billing", "team"]}}, {"job_id": "100003009031998", "location_code": "hk", "company": "Page Personnel", "job_title": "Billing & Credit Controller- MNC Law Firm Exposure", "description": "A global logistic company is looking for an Internal Control Manager to join their expanding team in Hong Kong. Report to CFO and lead a small team to handle the internal control and treasury functions.\n\nResponsibilities:\n\nLead a small team to manage Internal Control and Treasury functions\n70% on internal control/audit (internal & external) and 30% on treasury\nEnsure compliance with Group's policy and local requirement at all times\nEnhance process efficiency, internal control, risk management, corporate governance and cost saving\nManage account payable, fixed asset and treasury functions\nReview daily payment and treasury work performed by subordinates and shared service centre\nCollaborate and communicate with internal stakeholders to implement corporate initiatives and projects\n\n\nRequirements:\n\nDegree holder in Accounting or related discipline\nQualified accountant with minimum 6 years experience in internal/external audit and internal control\nFamiliar with accounting standards, taxation laws and Companies Ordinance\nExcellent communication, interpersonal,influence and leadership skills\nProficient in written and spoken English and Chinese\nProficient PC skills, knowledge in SAP is an advantage", "employment_types": ["Full Time", "Permanent"], "selling_points": ["Stable working environment and friendly culture", "Personal development and growth opportunity", "Excellent salary package and benefit"], "locations": ["Not Specified"], "categories": ["Accounting", "Credit Control", "Finance / Accounting Manager", "Financial Controller"], "post_time": "2022-01-07T10:05:44Z", "salary": {"currency": "HKD", "max": 54999, "min": 45000, "period": "monthly", "term": null}, "salary_visible": true, "title_keywords": [], "responsibilities": ["collaborate", "communicate with", "management", "cost", "lead a small team", "review", "audit", "ensure compliance", "payment", "internal control"], "requirements": {"degrees": ["degree holder"], "majors": ["accounting"], "languages": ["english", "chinese"], "language_level": ["proficient"], "hard_skills": ["companies ordinance", "pc skills", "sap", "internal control"], "soft_skills": ["communication", "leadership skills", "interpersonal"], "languages_combined": [{"language": "english", "language_level": ["proficient"]}, {"language": "chinese", "language_level": ["proficient"]}]}, "experience_required": {"duration": ["minimum 6 years"], "field": ["audit"]}}, {"job_id": "100003009047663", "location_code": "hk", "company": "Robert Walters (HK)", "job_title": "Internal Control Manager", "description": "The Role\n\nResponsible for private banking credit control function.\n\nKey Accountabilities\n\nLead a team to ensure collateral shortfall / limit excess cash overdraft are timely rectified or properly approved\nMonitor account positions, identify and report any potential risk as well as recommend relevant risk mitigation daily\nPerform margin call on daily basis\nReview and enhance existing MIS for credit risk management, propose solutions for automation to streamline the process\nProvide timely statistical credit risk data for effective credit control\nmonitor negative news and alerts which shall trigger review on collateral lending value\nActively participate in, support and coordinate various system projects and enhancement, work closely with IT and project teams in developing, testing and implementing effective credit risk control platform, and follow up on bug fix in systems and reports\nPerform stress test on regular basis and upon request from senior management\n\nSkills & Experience\n\n8 years or above work relevant work experience\nSound financial knowledge and strong programming abilities\nExcellent communication and interpersonal skills\nStrong language skills, including written Chinese and spoken Mandarin\nSkills in Excel VBA or Python preferred\n\nOther Information\n\nNotes to applicants:\n1. Please apply in strict confidence with full resume, academic record, current and expected salaries.\n2. The personal data provided will be used for consideration of recruitment only. All personal data of unsuccessful candidate will be destroyed within 24 months.\n3. Candidates with Enhanced Competency Framework (ECF): please state on the CV.\n\nAbout BOCI\n\nAs a leading investment bank in China and Hong Kong region, the investment banking arm of Bank of China, BOC International Holdings Limited (\u201cBOCI\u201d), is now seeking highly motivated, creative and success-oriented professional who would like to pursue the career in our group.\u00a0", "employment_types": ["Full Time", "Permanent"], "selling_points": ["Leadership role", "Fast growing industry", "Excellent communication skill"], "locations": ["Not Specified"], "categories": ["Accounting", "Audit", "Credit Control", "Treasurer"], "post_time": "2022-01-14T03:41:00Z", "salary": {"currency": null, "max": null, "min": null, "period": "monthly", "term": null}, "salary_visible": false, "title_keywords": ["manager"], "responsibilities": ["control", "management", "data", "review", "monitor", "teams", "developing", "testing", "coordinate", "lead a team", "systems", "communication", "reports", "personal data", "recruitment", "banking", "senior management", "report"], "requirements": {"degrees": [], "majors": [], "languages": ["chinese", "mandarin"], "language_level": [], "hard_skills": ["python", "excel", "vba", "programming"], "soft_skills": ["confidence", "responsible", "timely", "motivated", "communication and interpersonal skills", "creative"], "languages_combined": [{"language": "chinese", "language_level": []}, {"language": "mandarin", "language_level": []}]}, "experience_required": {"duration": ["8 years"], "field": []}}, {"job_id": "100003009046688", "location_code": "hk", "company": "", "job_title": "Credit Controller", "description": "Job Description\nYour role:\nPerform credit management and debt collection actions\nCarry out debt recovery actions on corporate customers via telephone and demand letters\nExecute routine dunning actions for non-payment accounts on consumer segments\nLiaise with different internal parties in resolving disputes and outstanding accounts\nMonitor customer payment\u2019s behaviour, perform credit assessment and prepare credit risk analysis/MIS reports to management\nMonitor debt collector performance and perform day-to-day operations on debt assignments\nContribute to formulate credit policy and related credit system development\nHandle other credit control issues and ad hoc assignments\n\nTo succeed in this role:\n\nDiploma Holder or above in Business Administration, Accounting, Finance or related discipline\nMinimum 2\u00a0years' solid experience in credit management\nGood command of spoken and written English and Chinese\nProactive, outgoing, enthusiastic and sensitive to market/economic environment\nAnalytical and self-motivated in problem-solving\nCan work under pressure\nExcellent interpersonal and negotiation skills\nProficient MSOffice applications\nCustomer service experience is a plus\nInterested candidates, please contact us at 58016476 for company details before applying.", "employment_types": ["Full Time", "Permanent"], "selling_points": ["Perform credit management and debt collection", "Carry out debt recovery actions", "Execute routine dunning actions"], "locations": ["Kwai Tsing Area"], "categories": ["Accounting", "Credit Control"], "post_time": "2022-01-13T18:54:21Z", "salary": {"currency": "HKD", "max": 24999, "min": 20000, "period": "monthly", "term": null}, "salary_visible": true, "title_keywords": [], "responsibilities": ["management", "control", "work under pressure", "customer service experience", "letters", "monitor", "day-to-day operations", "debt collection", "payment", "reports", "risk analysis", "ad hoc assignments", "liaise with", "internal parties", "administration"], "requirements": {"degrees": ["diploma holder"], "majors": ["finance", "accounting", "business administration"], "languages": ["english", "chinese"], "language_level": ["good command"], "hard_skills": ["problem-solving", "analysis", "msoffice", "plus"], "soft_skills": ["outgoing", "self-motivated", "problem-solving", "sensitive to", "negotiation skills", "customer service", "enthusiastic", "proactive", "interpersonal", "work under pressure"], "languages_combined": [{"language": "english", "language_level": ["good command"]}, {"language": "chinese", "language_level": ["good command"]}]}, "experience_required": {"duration": ["minimum 2 years"], "field": ["management", "customer service"]}}, {"job_id": "100003009053388", "location_code": "hk", "company": "ACCOLADE Corporate Services Limited", "job_title": "Accounts Assistant / Accountant", "description": "\u00a0Responsibilities:\n\nResponsible for Account Receivable collection process\nHandle daily invoices, bills, vouchers and Accounts documents checking\nAssist in preparing general ledger, month end closing, auditing and taxation affairs\nAssist in others ad hoc task as requested\n\nRequirements:\n\nDiploma holder or above in accounting or related disciplines\nWith 2-3 years relevant working experience in accounts receivable\nKnowledge in using ZOHO system would be an advantage\nSelf-motivated, stable and willing to work under pressure, work independently and good communication skills\nProficient in MS Office (Word & Excel)\nGood command in English and Mandarin\nImmediate available is preferred", "employment_types": ["Full Time", "Permanent"], "selling_points": ["Responsible for Account Receivable collection proc", "With 2 years relevant working experience", "Knowledge in using ZOHO system"], "locations": ["Sheung Wan"], "categories": ["Accounting", "Accountant", "Accounting Clerk / Supervisor", "Credit Control"], "post_time": "2022-01-17T06:56:50Z", "salary": {"currency": null, "max": null, "min": null, "period": "monthly", "term": null}, "salary_visible": false, "title_keywords": ["accountant", "accounts assistant"], "responsibilities": ["taxation", "month end closing", "ad hoc", "invoices", "general ledger", "checking", "auditing"], "requirements": {"degrees": ["diploma holder"], "majors": ["related disciplines", "accounting"], "languages": ["english", "mandarin"], "language_level": ["good command"], "hard_skills": ["excel", "word", "ms office"], "soft_skills": ["communication skills", "work independently", "self-motivated", "stable", "work under pressure"], "languages_combined": [{"language": "english", "language_level": ["good command"]}, {"language": "mandarin", "language_level": ["good command"]}]}, "experience_required": {"duration": ["2-3 years"], "field": ["relevant working experience"]}}, {"job_id": "100003009044919", "location_code": "hk", "company": "Wharf Estates Limited", "job_title": "SENIOR ACCOUNTS RECEIVABLE OFFICER / ACCOUNTS RECEIVABLE OFFICER", "description": "Responsibilities:\n\nResponsible for credit control by following up delinquent accounts, monitoring irregularities, and enforcing payments by taking recovery actions\nSupervise billings and payment status of rental collection and prepare monthly account receivable reports\nHandle tenants\u2019 enquiries and complaints\nOther ad-hoc assignments as required\n\nRequirements:\n\nDegree holder in Accounting, Business Administration or related disciplines\nAt least 3 years\u2019 solid credit control experience preferably in billing and rental collection\nResponsible, attentive to details and self-motivated\nGood analytical and interpersonal skills\nProficiency in Microsoft Word and Excel\nGood command in both written and spoken English and Chinese\nLegal knowledge on delinquent accounts related to landlord and tenants will be an advantage\nCandidate with more experience will be considered as Senior Accounts Receivable Officer\n\nWe offer competitive remuneration package that commensurate with experience and qualifications.\u00a0 Interested parties are invited to send full resume stating contact telephone number, date available, present and expected salary to our recruitment email address.\n\n(Personal data provided will be used strictly in accordance with the Company's personal data policy which is available upon request.)", "employment_types": ["Full Time", "Permanent"], "selling_points": ["Responsible for credit control", "Degree holder in Accounting", "At least 3 years\u2019 solid credit control experience"], "locations": ["Tsim Sha Tsui"], "categories": ["Accounting", "Accounting Clerk / Supervisor", "Credit Control", "Others"], "post_time": "2022-01-15T03:49:24Z", "salary": {"currency": null, "max": null, "min": null, "period": null, "term": null}, "salary_visible": false, "title_keywords": ["senior accounts receivable officer", "accounts receivable officer"], "responsibilities": ["control", "irregularities", "ad-hoc assignments", "billings", "monitoring", "payment", "payments", "reports"], "requirements": {"degrees": ["degree holder"], "majors": ["related disciplines", "accounting", "business administration"], "languages": ["english", "chinese"], "language_level": ["good command"], "hard_skills": ["excel", "microsoft word"], "soft_skills": ["attentive to details", "interpersonal skills", "self-motivated", "responsible"], "languages_combined": [{"language": "english", "language_level": ["good command"]}, {"language": "chinese", "language_level": ["good command"]}]}, "experience_required": {"duration": ["at least 3 years"], "field": ["billing"]}}, {"job_id": "100003009043315", "location_code": "hk", "company": "Nesta (Hong Kong) Limited", "job_title": "Credit Control / Collection Officer ( Debt Collection and Credit control - 14-17K, 5days)", "description": "Our client is the world\u2019s premier company specializing in the supply chain is now seeking a high caliber to join their team as\u00a0Credit Control / Collection Officer.\n\n\n\nJOB RESPONSIBILITY\n\nHandle debt collection and credit control functions\nCommunicate with corporate customers for overdue payment collection\nResolve related disputes with internal and external parties in compliance with customer\u2019s / company\u2019s policies & procedures\nIdentify high risk and sensitive businesses to prevent disputes or other credit issues\nHandle credit and billing problems for customers\n\nJOB REQUIREMENT\n\nHigher Diploma holder or above\n2 years experience or above in\u00a0billings, credit collection, credit control, or accounting field\nGood command of written and spoken English\nStrong analytical and debt collection skills", "employment_types": ["Full Time", "Permanent"], "selling_points": ["Handle debt collection", "MNC in Supply Chain", "1years' experience in collection/billing"], "locations": ["Not Specified"], "categories": ["Accounting", "Accountant", "Accounting Clerk / Supervisor", "Credit Control"], "post_time": "2022-01-12T10:40:48Z", "salary": {"currency": "HKD", "max": 24999, "min": 17000, "period": "monthly", "term": null}, "salary_visible": true, "title_keywords": ["officer"], "responsibilities": ["communicate with", "control", "credit issues", "policies", "payment collection", "internal and external parties", "compliance", "procedures", "debt collection"], "requirements": {"degrees": ["higher diploma holder"], "majors": [], "languages": ["english"], "language_level": ["good command"], "hard_skills": [], "soft_skills": [], "languages_combined": [{"language": "english", "language_level": ["good command"]}]}, "experience_required": {"duration": ["2 years"], "field": ["accounting"]}}, {"job_id": "100003009052224", "location_code": "hk", "company": "Aon Services Hong Kong Limited \u6021\u5b89\u670d\u52d9\u9999\u6e2f\u6709\u9650\u516c\u53f8", "job_title": "Accounting Officer", "description": "We\u2019re hiring!\n\nAon is currently recruiting an\u00a0Accounting Officer\u00a0to join our team in Hong Kong.\n\nAbout Aon\n\nHeadquartered in London, Aon Plc is a leading global professional services firm providing a broad range of risk, retirement and health solutions. Our 50,000 colleagues in 120 countries empower results for clients by using proprietary data and analytics to deliver insights that reduce volatility and improve performance.\n\nAt Aon, you\u2019ll be part of a team which will support and inspire you and provide the opportunities and resources to develop your skills. It\u2019s an environment which encourages you to achieve your best - together we\u2019ll empower results.\u00a0\n\nResponsibilities:\n\nWork in Reinsurance department\nPerform daily accounting operation in account payable and receivable function\nHandle invoice payments, receipts, and reconciliation of accounts with client & reinsurers\nInvestigate if any discrepancies within the reconciliation and follow up with respective units\nParticipate in Short-term project, such as clearance of legacy balance\nLiaise with client manager to understand client\u2019s needs and resolve accounting issues\nParticipate in UAT for system projects in relating to system enhancement if required\nAssist managers on reporting and other ad-hoc tasks.\n\nRequirements:\n\nGraduate with Accounting/ Finance/ Business degree.\nAt least 2-3 years relevant Accounting experience is preferred.\nStrong technical skills in MS Excel.\nProficiency in English and Mandarin.\nGood analytical skill and problem-solving skill.\nGood interpersonal skill\nDetailed minded, proactive, accurate and meticulous.\nMature, independent, self-starter.\nImmediate available preferred.\n\nHow to Apply\n\nYour opportunity to empower results could start right here. Make your mark and apply online today with a brief covering letter and your resume, sharing relevant achievements for this position.\n\nWe Offer You\n\nA competitive total rewards package, continuing education & training, and tremendous potential with a growing worldwide organization.\n\nOur Colleague Experience\n\nEvery day, our colleagues make a difference, work with the best, own their potential, and value one another. Together, we share this one purpose: to empower economic and human possibility around the world. This unifying goal is at the heart of our identity, and it lives in everything we do. To learn more about our colleague experience, visit Aon Colleague Experience.\n\nAon is an equal opportunities employer. We are committed to creating a winning and inclusive culture where everyone feels valued and has opportunities for growth and development.", "employment_types": ["Full Time", "Permanent"], "selling_points": [], "locations": ["Quarry Bay"], "categories": ["Accounting", "Accounting Clerk / Supervisor", "Credit Control", "Insurance", "Others"], "post_time": "2022-01-17T02:30:38Z", "salary": {"currency": null, "max": null, "min": null, "period": "monthly", "term": null}, "salary_visible": false, "title_keywords": ["accounting officer"], "responsibilities": ["reporting", "receipts", "uat", "invoice", "ad-hoc tasks", "assist managers", "liaise with client", "payments", "daily accounting"], "requirements": {"degrees": ["degree"], "majors": ["business", "finance", "accounting"], "languages": ["english", "mandarin"], "language_level": ["proficiency"], "hard_skills": ["problem-solving", "make", "ms excel", "analytical skill"], "soft_skills": ["meticulous", "analytical skill", "independent", "accurate", "problem-solving", "mature", "interpersonal skill", "technical skills", "proactive", "detailed"], "languages_combined": [{"language": "english", "language_level": ["proficiency"]}, {"language": "mandarin", "language_level": ["proficiency"]}]}, "experience_required": {"duration": ["at least 2-3 years"], "field": ["accounting experience"]}}, {"job_id": "100003009044918", "location_code": "hk", "company": "Wharf Estates Limited", "job_title": "ASSISTANT ACCOUNTS RECEIVABLE OFFICER", "description": "Responsibilities:\n\nResponsible for billing, rental calculation and collection\nHandle tenants\u2019 enquiries and complaints\nOther ad-hoc assignments as required\n\nRequirements:\n\nHigher Diploma holder in Accounting, Business Administration or related disciplines with LCCI\u00a0Intermediate Level or above\n1-2 years\u2019 relevant working experience preferably in billing and rental collection\nResponsible, attentive to details and self-motivated\nGood organizational and interpersonal skills\nProficiency in Microsoft Word and Excel\nGood command in both written and spoken English and Chinese\nCandidate with more experience will be considered as Accounts Receivable Officer\nWe offer competitive remuneration package that commensurate with experience and qualifications. Interested parties are invited to send full resume stating contact telephone number, date available, present and expected salary to our recruitment email address.\n\n(Personal data provided will be used strictly in accordance with the Company's personal data policy which is available upon request.)", "employment_types": ["Full Time", "Permanent"], "selling_points": ["Responsible for billing & rental calculation", "Higher Diploma holder in Accounting", "1-2 years\u2019 relevant working experience"], "locations": ["Tsim Sha Tsui"], "categories": ["Accounting", "Accounting Clerk / Supervisor", "Credit Control", "Others"], "post_time": "2022-01-15T03:49:24Z", "salary": {"currency": null, "max": null, "min": null, "period": null, "term": null}, "salary_visible": false, "title_keywords": ["assistant accounts receivable officer"], "responsibilities": ["ad-hoc assignments"], "requirements": {"degrees": ["higher diploma holder"], "majors": ["related disciplines", "accounting", "business administration"], "languages": ["english", "chinese"], "language_level": ["good command"], "hard_skills": ["excel", "microsoft word"], "soft_skills": ["self-motivated", "attentive to details", "responsible", "organizational", "interpersonal skills"], "languages_combined": [{"language": "english", "language_level": ["good command"]}, {"language": "chinese", "language_level": ["good command"]}]}, "experience_required": {"duration": ["1-2 years"], "field": ["billing", "relevant working experience"]}}, {"job_id": "100003009049977", "location_code": "hk", "company": "HGC Global Communications Limited", "job_title": "Accounting Officer / Accounting Clerk", "description": "Responsibilities:\n\nResponsible for handing account receivables and billing related issues\nIssue monthly statement of Account, subsequent demand letters and calls\nUpdate the receipt transaction and assist in billing\u00a0\nEnsure the timely collection of outstanding debts and minimize the credit risk exposure\n\u00a0Requirements:\n\nDiploma or above in Accounting or related disciplines\n1 year of accounting experience\nGood command of both written and spoken English and Chinese\nIndependent, assertive and able to work under pressure\nImmediate available is preferred\n\nWe offer competitive salary package and career development opportunity. Free company coach is provided.\u00a0 Interested parties, please quote our reference number and apply with full resume, present and expected salary, by clicking \u201cAPPLY NOW\u201d.\u00a0\n\nWe are an equal opportunity employer and welcome applications from all qualified candidates. Information provided will be treated in strict confidence and only be used for consideration of your application for the relevant post within HGC Global Communications Limited. Personal data provided by job applicants will be used strictly according to our Personal Information Collection Statement, a copy of which will be available upon written request. Information of unsuccessful candidates will be destroyed within six months.", "employment_types": ["Full Time", "Permanent"], "selling_points": ["Diploma in Accounting", "1 years of relevant experience", "Responsible for settlement operations"], "locations": ["Tsing Yi"], "categories": ["Accounting", "Accountant", "Accounting Clerk / Supervisor", "Credit Control"], "post_time": "2022-01-14T09:34:35Z", "salary": {"currency": null, "max": null, "min": null, "period": "monthly", "term": null}, "salary_visible": false, "title_keywords": ["accounting clerk", "accounting officer"], "responsibilities": ["letters"], "requirements": {"degrees": ["diploma or above"], "majors": ["related disciplines", "accounting"], "languages": ["english", "chinese"], "language_level": ["good command"], "hard_skills": [], "soft_skills": ["work under pressure", "independent", "assertive"], "languages_combined": [{"language": "english", "language_level": ["good command"]}, {"language": "chinese", "language_level": ["good command"]}]}, "experience_required": {"duration": ["1 year"], "field": ["accounting experience"]}}, {"job_id": "100003009047888", "location_code": "hk", "company": "Robert Half", "job_title": "Regional AR Accountant, 25-30k | 1 year contract", "description": "The Company\n\nOur client is a US Listed MNC, urgently seeking a 1-year contract AR Accountant to join their HK business, and the ideal candidate will start immediately.\n\nThe Role\n\nResponsible for accounts receivable, ensure royalty reports are processed\nChase debtors on a regular basis, verify royalty reports from licensees\nHandle reconciliation of licensee or agent account balances\nPrepare invoicing summary, aging, open report summary to Category Manager\nAssist in ad hoc projects\n\nYour Profile\n\nDegree holder\nQualified Accountant is a plus\nExperience in credit control and SAP is preferable\nGood command in both written and spoken English and Cantonese\nStrong communication and interpersonal skills, independent and self-motivated\n\nApply Today\n\nTo apply online (Word attachment only), please click the 'Apply' button. Please note that only short-listed candidates will be contacted.", "employment_types": ["Full Time", "Contract"], "selling_points": ["Regional role", "AR/Credit Control/ Royalty Reporting/ Licensing", "Completion bonus"], "locations": ["Yau Tsim Mong Area"], "categories": ["Accounting", "Credit Control"], "post_time": "2022-01-14T04:09:02Z", "salary": {"currency": null, "max": null, "min": null, "period": "monthly", "term": null}, "salary_visible": false, "title_keywords": ["accountant"], "responsibilities": ["control", "ar", "accounts receivable", "invoicing", "communication", "reports", "ad hoc projects", "report"], "requirements": {"degrees": ["degree holder"], "majors": [], "languages": ["cantonese", "english"], "language_level": ["good command"], "hard_skills": ["word", "plus", "ar", "sap"], "soft_skills": ["self-motivated", "independent", "responsible", "communication and interpersonal skills", "ideal"], "languages_combined": [{"language": "cantonese", "language_level": ["good command"]}, {"language": "english", "language_level": ["good command"]}]}, "experience_required": {"duration": [], "field": []}}, {"job_id": "100003009046043", "location_code": "hk", "company": "China Telecom Global Limited", "job_title": "Billing Officer", "description": "Job description:\n\nCarry out billing data & material review, bill customers on the basis of contracts\nConfirm revenue & cost of business side, make sure the record is accurate with compliance to Accounting Standard\nFind & deal with the account record differences between business and finance side, as well as communicate with business partners for reconciliation\nFollow up customer billing enquiry and follow up afterwards\nConfirm financial income according to project progress; Make gross profit analysis of order forms\nMake account receivable management & aging schedule; prompt customers\u2019 collection & reconciliate bank statement\nReceive vendors\u2019 invoices & review bill and other materials & submit settlement payment\nOther duty assigned by superior\nRequirement:\n\nBachelor degree or above in Finance, Accounting, Information & Statistics or related disciplines preferred\nGood communication skills, Initiatives and conscientiousness\nGood at learning and systematic thinking, as well as making analysis and summary\nGood command of written and spoken English and Chinese (Cantonese & Mandarin)\nPrior system integration financial work experience is preferred.\n\nWe offer 5 days work, competitive salary package and attractive career development opportunities to the right candidate.\u00a0\n\nInterested parties please email your full resume with your current & expected salary to us.\n\nApplicants not invited for interview within 3 months may assume their applications unsuccessful.\u00a0\n\nPersonal data collected would be used for recruitment purpose only.\u00a0", "employment_types": ["Full Time", "Permanent"], "selling_points": ["1 year or above billing experience", "Stable working environment", "Excellent salary package and benefit"], "locations": ["Wan Chai"], "categories": ["Accounting", "Accounting Clerk / Supervisor", "Credit Control", "Financial Analyst"], "post_time": "2022-01-13T09:29:09Z", "salary": {"currency": null, "max": null, "min": null, "period": "monthly", "term": null}, "salary_visible": false, "title_keywords": ["billing officer"], "responsibilities": ["communicate with", "cost", "management", "invoices", "data", "contracts", "analysis", "review", "compliance", "project progress", "payment", "schedule"], "requirements": {"degrees": ["degree or above", "bachelor"], "majors": ["related disciplines", "finance", "accounting", "statistics"], "languages": ["cantonese", "english", "chinese", "mandarin"], "language_level": ["good command"], "hard_skills": ["integration", "analysis"], "soft_skills": ["communication skills", "learning", "systematic"], "languages_combined": [{"language": "cantonese", "language_level": ["good command"]}, {"language": "english", "language_level": ["good command"]}, {"language": "chinese", "language_level": ["good command"]}, {"language": "mandarin", "language_level": ["good command"]}]}, "experience_required": {"duration": [], "field": ["financial"]}}, {"job_id": "100003009039843", "location_code": "hk", "company": "Page Personnel", "job_title": "Collection/ Credit Control, Associate-MNC Platform", "description": "Our client is an European insurance company set up for more than 100 years. They are now looking for candidate who is with at least 2 years Collection/Credit Control experience with corporate clients to join them. They also welcome candidate coming from non-insurance background.\n\nClient Details\n\nOur client is an European based insurance company. They have set up for more than 100 years, specialising in general insurance business with corporate clients globally. They operate as a very strong MNC business with global footprint covering more than 200 regions. Setting their Asian hub in Hong Kong for more than 20 years, they have been providing competitive insurance services and products to their corporate clients.\n\nTo support their business growth, they are looking for candidate with Collection or Credit Control experience to join them. Candidate would be expected to negotiate with external counterpart from different countries to manage their collection status. Therefore, they would like to look for candidate who is strong in interpersonal skills and could communicate clearly in both Chinese and English. The company culture is very stable and friendly. They emphasise the career development of their staff by providing ample internal mobility opportunities.\n\nDescription\n\nPerform daily collection activities to manage the debt collection status meeting the assigned target.\nFollow up collection issues with suppliers and provide updated report to clients.\nWork closely with internal risk team for collection management\nHandle all enquiries related to collection issues.\nLiaise and maintain positive relationship with policy holders and brokers.\n\nProfile\n\nBachelor degree holder.\nAt least 2 years Collection/Credit Control experience with corporate clients.\nSolid experience of negotiation or client facing from previous job experiences.\nCandidate with experience of negotiating with regional counterpart would be a plus.\nExcellent command in both English and Chinese.\nSociable and self-motivated teamplayer who is with excellent interpersonal skills.\n\nJob Offer\n\nMNC Platform\nWell-established Business\nAnnual Leave: 14 days Up\nMedical Benefits\nDental Benefits\nBody Check\nExcellent Training\nInternal Mobility/ International Mobility\n\nTo apply online please click the 'Apply' button below. For a confidential discussion about this role please contact Ellen Fung on +852 3602 2447.", "employment_types": ["Full Time", "Permanent"], "selling_points": ["MNC Insurance Platform", "Collection Experience", "Excellent Internal Mobility"], "locations": ["Not Specified"], "categories": ["Accounting", "Credit Control", "Banking / Finance", "Credit Collection", "Risk Management"], "post_time": "2022-01-11T11:57:28Z", "salary": {"currency": "HKD", "max": 34999, "min": 20000, "period": "monthly", "term": null}, "salary_visible": true, "title_keywords": ["associate"], "responsibilities": ["liaise", "control", "management", "debt collection", "maintain", "career development", "insurance", "report"], "requirements": {"degrees": ["bachelor degree holder"], "majors": [], "languages": ["english", "chinese"], "language_level": ["excellent"], "hard_skills": ["plus"], "soft_skills": ["self-motivated", "negotiation", "sociable", "interpersonal skills", "friendly", "stable", "mobility", "positive"], "languages_combined": [{"language": "english", "language_level": ["excellent"]}, {"language": "chinese", "language_level": ["excellent"]}]}, "experience_required": {"duration": ["at least 2 years"], "field": ["business"]}}, {"job_id": "100003009048446", "location_code": "hk", "company": "China Duty Free International Limited", "job_title": "Accounting Officer / Accounting Assistant", "description": "About the role:\n\nResponsible for daily financial management, accounting, financial analysis and other related financial services\nPrepare monthly financial reports to HQ in an accurate and timely manner\nPrepare and exterminate of the company's General Ledger, Subsidiary Ledger, Cash Journal and Deposit Journal\nPerform month-end closing in SAP, analyze GL to ensure proper accounting treatment\nAssist in establish and improve accounting and financial management systems\nComplete other ad-hoc tasks assigned by the manager\n\nYou are the perfect one if you are/have:\n\nBachelor Degree\u00a0in Accounting, or in any relevant field\n2 years of accounting experience\nGood knowledge of Microsoft Office products (Word, Excel, PowerPoint, Outlook) and SAP\nTeam player with the ability to communicate and collaborate with multiple parties\nIndependent, responsible, self-motivated, willing to learn and able to work under pressure\nGood command of both written and spoken English and Chinese, including Cantonese and Mandarin\n\nJoin our productive, innovative, cooperative and fun work environment, share the joy of shopping, and extend the enjoyment of travel!\u00a0We offer 5-day work week, competitive salary and fringe benefits to the perfect one. Ready for your next adventure? Click \"Apply Now\" to start a fantastic\u00a0career with CDFI!\u00a0\n\nTo learn more about CDFI, visit our website at https://www.cdfg.com.cn\n\nAll information provided by applicants will be treated in strict confidence and used for recruitment purpose only. All personal data of unsuccessful applicants will be retained for 6 months for future recruitment purpose and will then be destroyed.", "employment_types": ["Full Time", "Permanent"], "selling_points": ["Accounting", "1-2 years experience", "Double pay + Bonus"], "locations": ["Wan Chai"], "categories": ["Accounting", "Accountant", "Accounting Clerk / Supervisor", "Credit Control"], "post_time": "2022-01-14T06:36:04Z", "salary": {"currency": null, "max": null, "min": null, "period": "monthly", "term": null}, "salary_visible": false, "title_keywords": ["accounting assistant", "accounting officer"], "responsibilities": ["collaborate with", "management", "financial reports", "general ledger", "ad-hoc tasks", "systems", "website", "financial analysis", "month-end closing", "recruitment", "personal data", "work under pressure"], "requirements": {"degrees": ["degree", "bachelor"], "majors": ["accounting"], "languages": ["cantonese", "english", "chinese", "mandarin"], "language_level": ["good command"], "hard_skills": ["excel", "sap", "fun", "word", "microsoft office products", "powerpoint", "financial analysis", "outlook", "joy"], "soft_skills": ["productive", "self-motivated", "confidence", "independent", "responsible", "timely", "cooperative", "willing to learn", "innovative", "team player", "accurate", "work under pressure"], "languages_combined": [{"language": "cantonese", "language_level": ["good command"]}, {"language": "english", "language_level": ["good command"]}, {"language": "chinese", "language_level": ["good command"]}, {"language": "mandarin", "language_level": ["good command"]}]}, "experience_required": {"duration": ["2 years"], "field": ["accounting experience"]}}, {"job_id": "100003008957949", "location_code": "hk", "company": "HKT", "job_title": "Credit Control Officer (Global)", "description": "Your role:\n\nMonitor customer's payment behavior\nFollow-up with the customers on past due invoices\nCarry out necessary debt recovery action according to company procedures\nWork in conjunction with internal parties to clarify any disputes/discrepancies identified\nDevise and recommend alternatives to supervisors on improving the existing systems and procedures\nBe responsible for all tasks relevant to the role such as preparation of operation statistics and reports for management review and perform other ad-hoc assignments as required\n\n\nTo succeed in this role:\n\nHigher Diploma / Degree holder\nMinimum 3 years of solid experience in account receivable management\u00a0\nExperience in telecommunications industry will have definite advantage\nProactive, self-motivated, enthusiastic and sensitive to market/economic environment\nWell versed with MS Office applications &, preferably, exposures to ERP system operation environment\u00a0\nGood command of spoken and written English and Chinese\nGood interpersonal and communication skills\n\nIf you have the desire for an exciting and rewarding career, please apply by sending your resume immediately, quoting your present and expected salary by clicking \"Apply Now\".", "employment_types": ["Full Time"], "selling_points": [], "locations": ["Lai Chi Kok"], "categories": ["Accounting", "Accounting Clerk / Supervisor", "Credit Control", "Banking / Finance", "Order Processing & Operation / Settlement"], "post_time": "2022-01-10T08:37:55Z", "salary": {"currency": null, "max": null, "min": null, "period": "monthly", "term": null}, "salary_visible": false, "title_keywords": ["credit control officer"], "responsibilities": ["management", "invoices", "ad-hoc assignments", "systems", "monitor", "procedures", "management review", "communication", "payment", "reports", "internal parties"], "requirements": {"degrees": ["diploma", "degree holder"], "majors": [], "languages": ["english", "chinese"], "language_level": ["good command"], "hard_skills": ["erp system", "ms office"], "soft_skills": ["communication skills", "self-motivated", "responsible", "sensitive to", "enthusiastic", "proactive", "interpersonal"], "languages_combined": [{"language": "english", "language_level": ["good command"]}, {"language": "chinese", "language_level": ["good command"]}]}, "experience_required": {"duration": ["minimum 3 years"], "field": ["telecommunications", "management"]}}, {"job_id": "100003009041336", "location_code": "hk", "company": "Chevalier AOC Freight Express Holdings Limited", "job_title": "Assistant Accountant / Senior Accounting Officer", "description": "Responsibilities:\n\n-\u00a0\u00a0\u00a0\u00a0\u00a0\u00a0 Prepare monthly financial reports and account schedules\n\n-\u00a0\u00a0\u00a0\u00a0\u00a0\u00a0 Responsible for credit control by following up delinquent accounts, monitoring irregularities, and enforcing payments by taking recovery actions\n\n-\u00a0\u00a0\u00a0\u00a0\u00a0\u00a0 Handle daily accounting operations including journal entries, maintain general ledgers, etc.\n\n-\u00a0\u00a0\u00a0\u00a0\u00a0\u00a0 Prepare reconciliations of bank accounts and inter-company accounts\n\n-\u00a0\u00a0\u00a0\u00a0\u00a0\u00a0 Assist in annual audit, taxation and cash flow management\n\n-\u00a0\u00a0\u00a0\u00a0\u00a0\u00a0 Perform Ad-hoc responsibilities as assigned\n\n\u00a0Requirements:\n\n-\u00a0\u00a0\u00a0\u00a0\u00a0\u00a0 Degree or Diploma in Accounting\n\n-\u00a0\u00a0\u00a0\u00a0\u00a0\u00a0 Knowledge in logistic industry is an advantage\n\n-\u00a0\u00a0\u00a0\u00a0\u00a0\u00a0 Well versed in Microsoft Excel (Pivot table, Vlookup, etc) and computerized accounting system\n\n-\u00a0\u00a0\u00a0\u00a0\u00a0\u00a0 Minimum 3 years relevant working experience, handle full set of accounts preferable\n\n-\u00a0\u00a0\u00a0\u00a0\u00a0\u00a0 Good Command of both English and Chinese (Mandarin and Cantonese)\n\n-\u00a0\u00a0\u00a0\u00a0\u00a0\u00a0 Good team player with can-do attitude, good interpersonal skills and willing to work overtime to meet with tight deadlines\n\n-\u00a0\u00a0\u00a0\u00a0\u00a0\u00a0 Immediate available is preferred, candidates with less experience will be considered as Senior Accounting Officer", "employment_types": ["Full Time", "Permanent"], "selling_points": [], "locations": ["Shatin Area"], "categories": ["Accounting", "Accounting Clerk / Supervisor", "Audit", "Credit Control"], "post_time": "2022-01-12T03:45:39Z", "salary": {"currency": null, "max": null, "min": null, "period": "monthly", "term": null}, "salary_visible": false, "title_keywords": ["senior accounting officer", "assistant accountant"], "responsibilities": ["ad-hoc", "taxation", "financial reports", "control", "irregularities", "management", "annual audit", "schedules", "company accounts", "monitoring", "daily accounting operations", "reconciliations", "cash flow", "maintain", "payments", "journal entries"], "requirements": {"degrees": ["diploma", "degree"], "majors": ["accounting"], "languages": ["cantonese", "english", "chinese", "mandarin"], "language_level": ["good command"], "hard_skills": ["pivot table", "vlookup", "accounting system", "microsoft excel"], "soft_skills": ["good team player", "work overtime", "interpersonal skills", "can-do attitude"], "languages_combined": [{"language": "cantonese", "language_level": ["good command"]}, {"language": "english", "language_level": ["good command"]}, {"language": "chinese", "language_level": ["good command"]}, {"language": "mandarin", "language_level": ["good command"]}]}, "experience_required": {"duration": ["minimum 3 years"], "field": ["accounting", "relevant working experience"]}}, {"job_id": "100003009043100", "location_code": "hk", "company": "A.S. Watson Industries", "job_title": "Assistant Accounting Officer (Account Receivable)", "description": "Assist in monitoring Account Receivable collection process\nEnsure the team to input all daily payment receipts for online & offline collection\nPerform bank reconciliation\nAssist in month end closing\nHandle system UAT and ad hoc projects\nWork with collection team to make sure all settlement on closing schedule\nAd hoc project\n\n\u00a0Job Requirements:\n\n\nDiploma holder or above in Business Administration or related disciplines\nAt least 3 years of relevant working experience in Accounts Receivable, experience in FMCG as preferred\nGood communication, presentation and interpersonal skill\nProficient in MS Excel and experience on Oracle is an advantage\n\nWe offer competitive salary, discretionary performance bonus, medical and retirement benefits, free company coach services and excellent career prospects. Please send your resume together with salary expectation via\u00a0APPLY NOW\n\nFor more information, please visit our website at\u00a0www.aswatson.com\n\nAll information provided will be used for recruitment other employment-related purposes by A.S. Watson & Company Limited (for and on behalf of the A.S. Watson Group of companies). It may be provided to companies/parties authorized to process the information for purposes relating to recruitment, e.g. qualifications assessment.\n\nWith the consent of applicant, all personal data of unsuccessful applicants will be retained for future consideration for two years. Otherwise, all personal data of unsuccessful applicants will be retained for twelve months.\n\nApplication will not be considered if the applicant does not provide all information as requested.\n\nAll information provided will be held in strict confidence.\n\nIf applicant request access to, and to request correction of personal data in relation to the application, please contact our People Department at 2660 1880.", "employment_types": ["Full Time", "Permanent"], "selling_points": ["Assist in Account Receivable collection process", "3 years experience in Accounts Receivable", "Free Shuttle Bus, Discretionary bonus"], "locations": ["Tai Po Area"], "categories": ["Accounting", "Accounting Clerk / Supervisor", "Credit Control", "Others"], "post_time": "2022-01-12T09:48:57Z", "salary": {"currency": null, "max": null, "min": null, "period": "monthly", "term": null}, "salary_visible": false, "title_keywords": ["assistant accounting officer"], "responsibilities": ["month end closing", "ad hoc", "receipts", "uat", "accounts receivable", "monitoring", "bank reconciliation", "website", "communication", "payment", "ad hoc projects", "schedule", "recruitment", "contact", "personal data", "administration"], "requirements": {"degrees": ["diploma holder"], "majors": ["related disciplines", "business administration"], "languages": [], "language_level": [], "hard_skills": ["make", "ms excel", "oracle"], "soft_skills": ["communication", "confidence", "presentation", "interpersonal skill"], "languages_combined": []}, "experience_required": {"duration": ["at least 3 years"], "field": ["fmcg", "relevant working experience"]}}, {"job_id": "100003009048236", "location_code": "hk", "company": "Ambition", "job_title": "Assistant Accountant (HKD20k, no OT, MNC)", "description": "Our client is a well-established and fast-growing company, which has strong presence within Asia. To facilitate their company growth, they are looking for a Assistant Accountant to join their Finance team.\n\nYou will be responsible for:\n\n\nResponsible for daily accounting operations, issue invoice and process payment\nPrepare staff expenses reimbursement, pretty cash, etc.\nConduct payment process and prepare bank reconciliation Liaise with vendors and/or relevant departments regarding payment and expense claim\nAssist in month-end closing and prepare relevant schedules\nPrepare bank reconciliations\nSupport in accounting and other ad hoc assignments\n\nTo qualify, individuals must possess:\n\n\nBachelor's degree in Business Administration or Accounting and Finance or any related disciplines\nAt least 1 year of accounting work experiences\nWilling to learn, good team player, attention to details and good communications\nProficient in written and spoken English and Chinese (Cantonese and Mandarin)\n\nInterested candidates, please submit application with the \"apply now\" button. For a quick application please forward your resume to ariel.chan@ambition.com.hk quoting #245352 Assistant Accountant, MNC\n\n\n\nIf this job isn't quite right for you, but you know someone who would be great at this role, why not take advantage of our referral scheme? We offer HKD1000 in Apple gift cards for every referred candidate who we place in a role. Terms & Conditions Apply. https://www.ambition.com.hk/refer-a-friend", "employment_types": ["Full Time", "Permanent"], "selling_points": ["AP and AR exposure", "Can sign CPA experiences", "13 months guaranteed salary"], "locations": ["Not Specified"], "categories": ["Accounting", "Accountant", "Audit", "Credit Control"], "post_time": "2022-01-14T06:00:02Z", "salary": {"currency": "HKD", "max": 19999, "min": 17000, "period": "monthly", "term": null}, "salary_visible": true, "title_keywords": ["assistant accountant"], "responsibilities": ["invoice", "schedules", "expenses", "daily accounting operations", "bank reconciliation", "bank reconciliations", "payment", "month-end closing", "finance team", "payment process", "ad hoc assignments", "liaise with", "administration"], "requirements": {"degrees": ["degree", "bachelor"], "majors": ["related disciplines", "finance", "accounting", "business administration"], "languages": ["cantonese", "english", "chinese", "mandarin"], "language_level": ["proficient"], "hard_skills": [], "soft_skills": ["good team player", "willing to learn", "attention to details", "responsible"], "languages_combined": [{"language": "cantonese", "language_level": ["proficient"]}, {"language": "english", "language_level": ["proficient"]}, {"language": "chinese", "language_level": ["proficient"]}, {"language": "mandarin", "language_level": ["proficient"]}]}, "experience_required": {"duration": ["at least 1 year"], "field": ["accounting"]}}, {"job_id": "100003009047022", "location_code": "hk", "company": "Toyo Mall Limited", "job_title": "ACCOUNTING OFFICER", "description": "Job Duties & Responsibilities:\n\nMainly responsible for AR related functions;\nPerform daily accounting operations and assist in credit control;\nProvide clerical support to the team including data entry and document filing;\nPerform other ad hoc duties as assigned.\n\nRequirements:\n\nLCCI higher or above;\nAt least 5 years commercial experience with 2 years in AR function is highly preferred;\nMature, good numeric sense, detail-minded and able to work independently;\nGood communication and interpersonal skills;\nProficient in MS Office such as Outlook, Excel and Word;\nFamiliar with Flex System is an advantage;\nImmediate available is highly preferred.\nAttractive package commensurate with experience and qualification will be given to the successful candidate. Our staff members' performance and contribution will be recognized and fairly rewarded.\u00a0 Please apply with full resume, date of available, current & expected salary toHuman Resources Manager, Toyo Mall Limited, 6/F, V Heun Building, 138 Queen\u2019s Road Central, Hong Kong.\u00a0\u00a0Applicants who wish to learn more about our Company may email the Human Resources Manager for more information.\u00a0 Those who do not hear from us within 4 weeks may consider their applications not successful in this instance.", "employment_types": ["Full Time", "Permanent"], "selling_points": [], "locations": ["Central"], "categories": ["Accounting", "Accounting Clerk / Supervisor", "Credit Control", "Property / Real Estate", "Others"], "post_time": "2022-01-14T02:04:04Z", "salary": {"currency": null, "max": null, "min": null, "period": "monthly", "term": null}, "salary_visible": false, "title_keywords": ["accounting officer"], "responsibilities": ["provide clerical support", "document filing", "control", "ad hoc duties", "ar", "data entry", "daily accounting operations"], "requirements": {"degrees": [], "majors": [], "languages": [], "language_level": [], "hard_skills": ["excel", "ar", "word", "outlook", "flex system", "ms office"], "soft_skills": ["detail-minded", "work independently", "communication and interpersonal skills", "mature"], "languages_combined": []}, "experience_required": {"duration": ["2 years", "at least 5 years"], "field": ["commercial"]}}, {"job_id": "100003009050291", "location_code": "hk", "company": "Nanyang Commercial Bank", "job_title": "Senior Credit Risk Manager / Credit Risk Manager   (Ref: OE8014-00-JDB)", "description": "Conduct independent credit assessment and validation of credit applications, including internal ratings, compliance of policies and regulations and make recommendations for approval. The portfolio of clients mainly covers PRC large corporate clients and NBFI, as well as those in the New Economy industries.Conduct on-going monitoring over large exposure, credit rating, early warning and risk concentration.Contribute to the formulation and review of credit risk policies and guidelines to cope with regulatory changes. Perform ad hoc projects or assignments.\n\nRequirements:\n\nMinimum 10 years\u2019 experience in corporate / structured credits and cross border transactions for PRC corporate clients and NBFI, either within a credit risk function or business line in banking industry.\nUniversity graduate with major in Accounting, Finance, Economics, Risk Management or related disciplines\nGood understanding in key market and industry dynamics as well as regulatory changes, especially that of PRC\nStrong expertise in risk and financial analysis, cash flow projections and banking products\nCFA, FRM, Accountant or HKIB ECF-CRM would be an advantage\nProficiency in written Chinese and English, fluency in Putonghua is preferred\nGood PC skills in MS Word and Excel\n\n(Candidate with less relevant experience will be considered as Credit Risk Manager)\n\nIf you are flexible enough and zeal for a harmonious and supportive working environment where enables you to grow and succeed professionally, please send a full resume indicating your public examination results (HKCEE and HKALE / HKDSE), your present and expected salary and quoting reference number attention to\u00a0Talent Acquisition Division, Nanyang Commercial Bank, 151 Des Voeux Road Central, Hong Kong or apply through email. For details, please visit https://www.ncb.com.hk/ and select the page Recruit.\n\nWe are an Equal Opportunities Employer. Data collected would be used for recruitment purposes only. Applicants who do not hear from us within 8 weeks may consider their applications unsuccessful and their data will be destroyed within 12 months of receipt.", "employment_types": ["Full Time", "Permanent"], "selling_points": ["Conduct independent credit assessment", "Conduct on-going monitoring over large exposure", "Minimum 10 years\u2019 experience"], "locations": ["Central & Western Area"], "categories": ["Accounting", "Credit Control", "Banking / Finance", "Credit Analysis / Approval"], "post_time": "2022-01-15T03:50:58Z", "salary": {"currency": null, "max": null, "min": null, "period": "monthly", "term": null}, "salary_visible": false, "title_keywords": ["manager"], "responsibilities": ["regulations", "make recommendations", "management", "data", "guidelines", "policies", "compliance", "monitoring", "review", "transactions", "financial analysis", "cash flow", "ad hoc projects", "recruitment", "banking"], "requirements": {"degrees": ["university graduate", "hkdse"], "majors": ["risk management", "finance", "economics", "related disciplines", "accounting"], "languages": ["putonghua", "english", "chinese"], "language_level": ["fluency", "proficiency"], "hard_skills": ["excel", "cfa", "financial analysis", "make", "pc skills", "frm", "ms word"], "soft_skills": ["make recommendations", "flexible", "supportive", "independent", "harmonious", "structured"], "languages_combined": [{"language": "putonghua", "language_level": ["fluency", "proficiency"]}, {"language": "english", "language_level": ["proficiency"]}, {"language": "chinese", "language_level": ["fluency", "proficiency"]}]}, "experience_required": {"duration": ["minimum 10 years"], "field": ["banking industry", "business", "relevant experience", "credit risk"]}}, {"job_id": "100003009051229", "location_code": "hk", "company": "Easy Job Centre", "job_title": "Senior Accounts Clerk / Accounting Officer", "description": "\u00a0Requirements\u00a0\n\nDiploma / Degree in Accounting or related discipline\n3-5 years or above relevant experience is preferred\nResponsible for daily accounting duties\u00a0\nAssist in month-end closing process & ad hoc projects as assigned\nStrong sense of responsibilities and detail-minded\nProficiency in PC operations including MS Word, Excel\nGood command of both written and spoken in English and Cantonese\nImmediate available is preferred\u00a0\n\nInterested parties, please send your resume with expected salary by clicking the below \"apply now\" button.\u00a0You can ask click on the website\u00a0www.easyjobhk.com\u00a0for more details about the company", "employment_types": ["Full Time"], "selling_points": [], "locations": ["Tsim Sha Tsui"], "categories": ["Accounting", "Accounting Clerk / Supervisor", "Credit Control", "Admin & HR", "Clerical / Admin Staff"], "post_time": "2022-01-15T05:19:58Z", "salary": {"currency": null, "max": null, "min": null, "period": "monthly", "term": null}, "salary_visible": false, "title_keywords": ["senior accounts clerk", "accounting officer"], "responsibilities": ["operations"], "requirements": {"degrees": ["diploma", "degree"], "majors": ["accounting"], "languages": [], "language_level": [], "hard_skills": [], "soft_skills": ["detail-minded", "responsible", "sense of responsibilities"], "languages_combined": []}, "experience_required": {"duration": ["3-5 years"], "field": ["relevant experience"]}}, {"job_id": "100003009049163", "location_code": "hk", "company": "Hays", "job_title": "Credit Analyst", "description": "You will work under the Credit Control team, starting with a 1 year contract with high temp to perm potential.\n\nYour new company\nMy client is a leading overseas investment bank with business across the globe.\n\nYour new role\n\nProvide administrative support, document scanning and record management for the credit control team.\nSupport the process of credit analysis and prepare financial data to improve overall accuracy\nAssist in checking loan documentation and portfolio report preparation\nInput financial data into company's internal system and execute audit handling.\nPerform ad-hoc assignments provided by Team head.\n\n\nWhat you'll need to succeed\n\nBachelor's Degree holder in /Accounting/ Finance/Business Administration/Economics or related disciplines\nBasic knowledge in accounting;\nResponsible, detail-oriented and able to work in a fast-paced environment\nWelcome fresh graduates with internship experience in credit\n\n\nWhat you'll get in return\n\nExcellent exposure to Credit\nOpportunities to develop your career in an overseas bank\nPrime office location\n\n\nWhat you need to do now\nIf you're interested in this role, click 'apply now' to forward an up-to-date copy of your CV to avery.lam@hays.com.hk, or call Avery Lam at 2230 7931 now. If this job isn't quite right for you but you are looking for a new position, please contact us for a confidential discussion on your career.", "employment_types": ["Full Time", "Temporary"], "selling_points": ["Excellent exposure to Credit", "Develop your career in an overseas bank", "Prime office location"], "locations": ["Not Specified"], "categories": ["Accounting", "Credit Control"], "post_time": "2022-01-14T08:12:04Z", "salary": {"currency": "HKD", "max": 16999, "min": 11000, "period": "monthly", "term": null}, "salary_visible": true, "title_keywords": ["credit analyst"], "responsibilities": ["scanning", "administration", "control", "management", "documentation", "data", "ad-hoc assignments", "analysis", "checking", "audit", "develop", "contact", "provide administrative support", "report"], "requirements": {"degrees": ["bachelor", "degree holder"], "majors": ["business administration", "finance", "economics", "related disciplines", "accounting"], "languages": [], "language_level": [], "hard_skills": ["credit analysis", "documentation", "basic"], "soft_skills": ["fast-paced environment", "interested in", "responsible", "detail-oriented"], "languages_combined": []}, "experience_required": {"duration": [], "field": []}}, {"job_id": "100003009044826", "location_code": "hk", "company": "Mizuho Bank", "job_title": "Vice President - Credit Control & Agency Team, Credit Section", "description": "Company Overview\n\nMizuho has a long-term commitment to the Hong Kong market. With strong\u00a0ties to Mizuho\u2019s\u00a0global\u00a0network\u00a0and a workforce of over 600 staff in Hong Kong,\u00a0we are able to help corporations in Hong Kong to expand their business worldwide. Our clients\u00a0primarily\u00a0comprise Japanese and non-Japanese corporations\u00a0(including\u00a0those domiciled in the\u00a0PRC), financial institutions,\u00a0and\u00a0government and quasi-government organizations. We provide a full spectrum of corporate banking services to our customers including syndicated\u00a0loans, treasury, transaction banking, financial advisory, project finance, merger and acquisition, leveraged finance,\u00a0and\u00a0structured finance.\u00a0\n\nWhy Mizuho\n\nAt Mizuho, we provide the stability of an international industry leader with the career trajectory of a growing business. Our steady, strategic growth gives our people at all levels rewarding degrees of responsibility and a richer work experience than a boutique firm or an established giant could offer alone.\n\nIt\u00a0is the local expertise of our employees that makes our global network so powerful. By collaborating with colleagues and clients who have your same ambition and drive, you can amplify your sphere of influence and base of knowledge as part of one of the largest\u2014and growing\u2014banks in the world.\n\nAbout the team\n\nCredit Section is responsible for analyzing and making recommendation on credit applications, checking and reviewing loan documentation, performing credit administration and control function, analyzing branch portfolio and prepare portfolio report and etc.\n\nRole requirements\n\nTo monitor / perform overall daily operations in relation to checking and reviewing of credit & security documents including Syndication Agency Administration function\nTo monitor / perform credit facility registration and customer\u2019s financial data input\nTo monitor and conduct custody operation / scanning of credit documents, specimen signatures update and filing\nTo supervise subordinates in overall daily operations\nTo assist team head to establish, review and revise internal operation procedures periodically\nTo initiate, conduct and implement workflow streamlining\nTo prepare, check periodic internal and management reports\nTo conduct training to the team mates and to other sections, when necessary\nTo learn and prepare for cross back up within and across team of the Section\nTo participate or take lead to operational excellence project/assignment as designated by team head / section head\nTo perform any other duties assigned by supervisor\n\nEssential Functions\n\nEnsure smooth operations of the Team\nSupport, advise and negotiate with CBDs in carrying out the proper credit risk management\nPrepare periodic internal and/or external management reports\nEstablish credit related policies and procedures of HK branch as required and carry out the annual review\nMonitor and ensure all operational excellence project of the team are executed smoothly.\n\nCompetencies\n\nWe are looking for an individual who understands Mizuho\u2019s mission, vision and values.\nHe/she should be able to work independently or in a team.\nThe individual should be able to judge priority among tasks and makes practical scheduling and time management to complete tasks before deadline.\nThe individual should be able to effectively negotiate with his/her external/internal counterparties to executive regular tasks. He/she is an excellent team player and has an innovative spirit.\nHe/she should respect for, and commit to high standards of business conduct and integrity.\n\nWork experience, education and skills\n\nBachelor Degree in Business Administration/Finance/Economics or related discipline\nMinimum 3-4 years\u2019 relevant experience in banking industry\nSolid experience in credit middle function at supervisory role\nGood computer skills and experienced in MS Office applications\nProcess work in a timely, punctual manner, active, open minded\nResponsible, able to work independently and under pressure\n\nApplication\n\nPlease indicate your\u00a0current and expected salary\u00a0on CV for the application.\u00a0\n\nMizuho Bank Limited\n\nMizuho Bank, Ltd. in Hong Kong is an integral part of the Japan-based Mizuho Financial Group, Inc. (NYSE: MFG). The Mizuho group is a global financial services leader with offices in nearly 40 countries, approximately 60,000 employees, and assets of almost USD 2 trillion. Mizuho provides expertise in retail banking, corporate finance, investment banking, asset management, capital markets, and sales and trading, to help businesses develop and find new opportunities for growth. To learn more: www.mizuhogroup.com\n\nPersonal data collected will be kept in strict confidence, and will be used for recruitment purpose only.", "employment_types": ["Full Time"], "selling_points": ["Checking and reviewing of credit & security doc.", "Monitor / perform credit facility registration", "Minimum 3-4 years\u2019 relevant experience"], "locations": ["Tsim Sha Tsui"], "categories": ["Accounting", "Credit Control"], "post_time": "2022-01-13T06:26:03Z", "salary": {"currency": null, "max": null, "min": null, "period": "monthly", "term": null}, "salary_visible": false, "title_keywords": ["vice president"], "responsibilities": ["banking"], "requirements": {"degrees": [], "majors": [], "languages": ["japanese"], "language_level": [], "hard_skills": [], "soft_skills": ["structured"], "languages_combined": [{"language": "japanese", "language_level": []}]}, "experience_required": {"duration": [], "field": []}}, {"job_id": "100003009050161", "location_code": "hk", "company": "Magic Search Limited", "job_title": "Regional Cost Controller (Luxury Brand)", "description": "Our client is a global leading luxury Brand It is now looking for a Regional Finance Manager to join their team.\n\nKey Responsibilities\n\nPrepare and consolidated costing report with comparison against Budget and Forecast with comment\nWork closely with other functional team to ensure alignment and to reconcile any discrepancy\nPrepare other regular cost reporting or ad hoc analysis for management review of business performance\u00a0\nDevelop and replicate excel\u00a0budget/forecast\u00a0templates for\u00a0Asia\u00a0market\u00a0and\u00a0validation\u00a0\u00a0\nAssist\u00a0with the\u00a0budget & forecast\u00a0consolidation and review\u00a0process\nValidate system input and co-ordinate necessary follow-up with market\u00a0finance team\nAssist with analysis during budget and forecast process\nCost Management and Budget follow-up\nAssist in establishing/improving means of regional\u00a0cost\u00a0tracking\u00a0and budget follow-up\u00a0process\nRecommend and develop relevant reports and analysis\nAssist with SAP & Planning and Consolidation tool co-ordination, vendor master data creation and maintenance, and other ad hoc projects\n\nRequirements\n\nBachelor degree in Finance, Accounting or other related subjects\n6-7 years relevant retail working experience\nAbility to extract, organise, analyse and report data\nGood communication skills\nGood command in English and Chinese\u00a0", "employment_types": ["Full Time", "Permanent"], "selling_points": ["6-7 years experience", "luxury brand", "audit experience is a plus"], "locations": ["Not Specified"], "categories": ["Accounting", "Credit Control", "Financial Analyst", "Financial Controller"], "post_time": "2022-01-14T09:53:47Z", "salary": {"currency": null, "max": null, "min": null, "period": "monthly", "term": null}, "salary_visible": false, "title_keywords": [], "responsibilities": ["data", "budget", "system input", "management review", "relevant reports", "ad hoc", "develop", "finance team", "forecast", "report", "reporting", "cost", "management", "review", "tracking", "maintenance", "forecast process", "analysis", "ad hoc projects", "planning"], "requirements": {"degrees": ["degree", "bachelor"], "majors": ["finance", "accounting"], "languages": ["english", "chinese"], "language_level": ["good command"], "hard_skills": [], "soft_skills": ["communication skills"], "languages_combined": [{"language": "english", "language_level": ["good command"]}, {"language": "chinese", "language_level": ["good command"]}]}, "experience_required": {"duration": ["6-7 years"], "field": ["retail"]}}, {"job_id": "100003009042334", "location_code": "hk", "company": "Chance Max Limited", "job_title": "Accountant / Senior Accountant", "description": "RESPONSIBILITIES\n\nResponsible for preparing full set of accounts\nPrepare management and consolidation financial reports on a timely basic\nPrepare the financial reporting schedules, annual budgeting, cash flow analysis and bank reconciliation\nCoordinate with business departments for the accounting related matters and daily accounting transactions\nAssist in establishing, reviewing and improving accounting and procurement procedures and internal control system\nLiaise with auditors in connection with annual audit process and tax filling\nProvide support to the management for ad-hoc assignments\n\nREQUIREMENT\n\nDegree holder in Accounting / Finance or related disciplines\nAt least 5 years of working experience, with experience in Finance industry or China background is an advantage\nIndependent, self-motivated, responsible and detailed oriented\nStrong analytical skill & problem-solving skill with proactive attitude and able to work independently are required\nExcellent command of both written and spoken English & Mandarin & Chinese\nCompetent PC skills in MS Word, Excel and Chinese word processing\nCandidate with less experience will be considered as Accountant\nImmediate available preferred\n\nWe offer competitive remuneration package including 5-day work, performance bonus to the right candidate. Interested parties please send full resume with current and expected salary, availability by email or by clicking \"Apply Now\".\n\n\n(Personal data collected will be used for recruitment purposes only)\n\n", "employment_types": ["Full Time", "Permanent"], "selling_points": [], "locations": ["Tsuen Wan Area"], "categories": ["Accounting", "Accountant", "Credit Control", "Others"], "post_time": "2022-01-12T07:05:59Z", "salary": {"currency": null, "max": null, "min": null, "period": "monthly", "term": null}, "salary_visible": false, "title_keywords": ["accountant", "senior accountant"], "responsibilities": ["schedules", "bank reconciliation", "transactions", "liaise with", "internal control", "annual budgeting", "full set of accounts", "management", "provide support", "annual audit", "coordinate with", "procedures", "cash flow", "tax", "financial reports", "ad-hoc assignments", "analysis", "financial reporting", "daily accounting"], "requirements": {"degrees": ["degree holder"], "majors": ["related disciplines", "finance", "accounting"], "languages": ["english", "chinese", "mandarin"], "language_level": ["excellent"], "hard_skills": ["excel", "analytical skill", "chinese word processing", "problem-solving", "pc skills", "ms word"], "soft_skills": ["self-motivated", "analytical skill", "detailed oriented", "independent", "responsible", "work independently", "competent", "problem-solving", "proactive"], "languages_combined": [{"language": "english", "language_level": ["excellent"]}, {"language": "chinese", "language_level": ["excellent"]}, {"language": "mandarin", "language_level": ["excellent"]}]}, "experience_required": {"duration": ["at least 5 years"], "field": ["finance industry"]}}, {"job_id": "100003009048077", "location_code": "hk", "company": "iPR Ogilvy Limited", "job_title": "Accounting Clerk", "description": "Responsibilities:\n1) Responsible for all accounts functions, including performing accurate and prompt processing all accounts transactions, as well as ensuring all data are entered correctly and appropriately into the accounting system\n2) Coordinate with staff within and outside the department to ensure smooth payment process and handle payable enquiries\n\n3)\u00a0\u00a0Contact customers via email/phone for outstanding invoices\n\n4)\u00a0 Support the month end closing process and prepare reporting package\n5)\u00a0 Assist in any other ad hoc duties as assigned\nJob Requirement:\n1)\u00a0 DSE / HKCEE with LCC intermediate or the equivalent\n\n2)\u00a0 Fresh graduate is welcome to apply\n\n3)\u00a0 Relevant experience in accounting field is an advantage\n4)\u00a0 Capable to work multi-tasks, well organized and detail-minded\n5)\u00a0 Knowledge of Flex system (accounting system) is an advantage\n6)\u00a0 Good command of written and spoken English and Chinese\n7)\u00a0 Strong numeric sense,\u00a0analytical\u00a0and good interpersonal skills\u00a0\n\n8)\u00a0\u00a0Proficient in MS Office\n", "employment_types": ["Full Time", "Contract"], "selling_points": ["General accounting duties", "DSE / HKCEE with LCC intermediate", "Well-organized, self-motivated, independent"], "locations": ["Wan Chai"], "categories": ["Accounting", "Accounting Clerk / Supervisor", "Credit Control", "Others"], "post_time": "2022-01-14T04:43:23Z", "salary": {"currency": null, "max": null, "min": null, "period": "monthly", "term": null}, "salary_visible": false, "title_keywords": ["accounting clerk"], "responsibilities": ["ad hoc duties", "reporting", "month end closing", "invoices", "data", "coordinate with", "contact", "payment process", "accounts transactions"], "requirements": {"degrees": ["fresh graduate", "dse"], "majors": [], "languages": ["english", "chinese"], "language_level": ["good command"], "hard_skills": ["accounting system", "lcc", "flex system", "ms office"], "soft_skills": ["detail-minded", "capable", "multi-tasks", "well organized", "interpersonal skills"], "languages_combined": [{"language": "english", "language_level": ["good command"]}, {"language": "chinese", "language_level": ["good command"]}]}, "experience_required": {"duration": [], "field": ["accounting", "relevant experience"]}}, {"job_id": "100003009040107", "location_code": "hk", "company": "Page Personnel", "job_title": "Assistant Accountant - US Listed Company", "description": "My client is currently expanding their business in APAC and is looking for an Assistant Accountant to support their APAC finance team.\n\nClient Details\n\nOur client is a US listed company with a strong reputation globally. They have multiple brands and produce different consumer products. Since they are currently expanding their business in APAC, especially HK, they are looking for a high calibre to join their finance team and grow with the business.\n\nDescription\n\nResponsible in accounts receivable (AR) and credit control functions across APAC\nPrepare overdue debtor reports and follow up outstanding invoices\nValidate the invoice details and amount\nHandle bank reconciliation, cash allocation, month-end closing\nAssist in audit and tax related matters\nWork with Share Service Center (SSC) on finance related issues\nSupport ad hoc assignment\n\nProfile\n\nDegree in accounting\nAt least 3 years' accounting / audit experience\nStudent member of accounting qualification (HKICPA, CPAA, ACCA, AICPA, etc.)\nProficient in Microsoft Excel\nFamiliar with SAP or other ERP system is a plus\nGood communications and interpersonal skills\nFluent in English and Cantonese\nCandidate with only audit background / return-to-work is considered\n\nJob Offer\n\nWork-life balance, supportive and dynamic environment\nStrong reputation within the industry\nAttractive remuneration package\nSAP system and APAC exposure", "employment_types": ["Full Time", "Contract"], "selling_points": ["Attractive remuneration package", "APAC exposure", "Supportive enviroment"], "locations": ["Not Specified"], "categories": ["Accounting", "Accountant", "Accounting Clerk / Supervisor", "Credit Control"], "post_time": "2022-01-12T01:26:34Z", "salary": {"currency": null, "max": null, "min": null, "period": "monthly", "term": null}, "salary_visible": false, "title_keywords": ["assistant accountant"], "responsibilities": ["tax", "control", "ar", "accounts receivable", "invoices", "invoice", "ad hoc assignment", "bank reconciliation", "audit", "month-end closing", "reports", "finance team"], "requirements": {"degrees": ["degree"], "majors": ["accounting"], "languages": ["cantonese", "english"], "language_level": ["fluent"], "hard_skills": ["acca", "plus", "ar", "sap", "microsoft excel", "erp system", "dynamic", "hkicpa"], "soft_skills": ["supportive", "interpersonal skills", "responsible", "dynamic environment"], "languages_combined": [{"language": "cantonese", "language_level": ["fluent"]}, {"language": "english", "language_level": ["fluent"]}]}, "experience_required": {"duration": ["at least 3 years"], "field": ["audit experience", "accounting"]}}, {"job_id": "100003009047663", "location_code": "hk", "company": "Robert Walters (HK)", "job_title": "Internal Control Manager", "description": "A global logistic company is looking for an Internal Control Manager to join their expanding team in Hong Kong. Report to CFO and lead a small team to handle the internal control and treasury functions.\n\nResponsibilities:\n\nLead a small team to manage Internal Control and Treasury functions\n70% on internal control/audit (internal & external) and 30% on treasury\nEnsure compliance with Group's policy and local requirement at all times\nEnhance process efficiency, internal control, risk management, corporate governance and cost saving\nManage account payable, fixed asset and treasury functions\nReview daily payment and treasury work performed by subordinates and shared service centre\nCollaborate and communicate with internal stakeholders to implement corporate initiatives and projects\n\n\nRequirements:\n\nDegree holder in Accounting or related discipline\nQualified accountant with minimum 6 years experience in internal/external audit and internal control\nFamiliar with accounting standards, taxation laws and Companies Ordinance\nExcellent communication, interpersonal,influence and leadership skills\nProficient in written and spoken English and Chinese\nProficient PC skills, knowledge in SAP is an advantage", "employment_types": ["Full Time", "Permanent"], "selling_points": ["Leadership role", "Fast growing industry", "Excellent communication skill"], "locations": ["Not Specified"], "categories": ["Accounting", "Audit", "Credit Control", "Treasurer"], "post_time": "2022-01-14T03:41:00Z", "salary": {"currency": null, "max": null, "min": null, "period": "monthly", "term": null}, "salary_visible": false, "title_keywords": ["manager"], "responsibilities": ["collaborate", "communicate with", "management", "cost", "lead a small team", "review", "audit", "ensure compliance", "payment", "internal control"], "requirements": {"degrees": ["degree holder"], "majors": ["accounting"], "languages": ["english", "chinese"], "language_level": ["proficient"], "hard_skills": ["companies ordinance", "pc skills", "sap", "internal control"], "soft_skills": ["communication", "leadership skills", "interpersonal"], "languages_combined": [{"language": "english", "language_level": ["proficient"]}, {"language": "chinese", "language_level": ["proficient"]}]}, "experience_required": {"duration": ["minimum 6 years"], "field": ["audit"]}}, {"job_id": "100003009036791", "location_code": "hk", "company": "BOCI", "job_title": "VP, Credit Control Management, Private Banking", "description": "The Role\n\nResponsible for private banking credit control function.\n\nKey Accountabilities\n\nLead a team to ensure collateral shortfall / limit excess cash overdraft are timely rectified or properly approved\nMonitor account positions, identify and report any potential risk as well as recommend relevant risk mitigation daily\nPerform margin call on daily basis\nReview and enhance existing MIS for credit risk management, propose solutions for automation to streamline the process\nProvide timely statistical credit risk data for effective credit control\nmonitor negative news and alerts which shall trigger review on collateral lending value\nActively participate in, support and coordinate various system projects and enhancement, work closely with IT and project teams in developing, testing and implementing effective credit risk control platform, and follow up on bug fix in systems and reports\nPerform stress test on regular basis and upon request from senior management\n\nSkills & Experience\n\n8 years or above work relevant work experience\nSound financial knowledge and strong programming abilities\nExcellent communication and interpersonal skills\nStrong language skills, including written Chinese and spoken Mandarin\nSkills in Excel VBA or Python preferred\n\nOther Information\n\nNotes to applicants:\n1. Please apply in strict confidence with full resume, academic record, current and expected salaries.\n2. The personal data provided will be used for consideration of recruitment only. All personal data of unsuccessful candidate will be destroyed within 24 months.\n3. Candidates with Enhanced Competency Framework (ECF): please state on the CV.\n\nAbout BOCI\n\nAs a leading investment bank in China and Hong Kong region, the investment banking arm of Bank of China, BOC International Holdings Limited (\u201cBOCI\u201d), is now seeking highly motivated, creative and success-oriented professional who would like to pursue the career in our group.\u00a0", "employment_types": ["Full Time"], "selling_points": ["Credit control team lead function", "8 years+ credit control experience", "Private banking experience is a plus"], "locations": ["Central"], "categories": ["Accounting", "Credit Control", "Banking / Finance", "Private Banking", "Risk Management"], "post_time": "2022-01-10T14:26:22Z", "salary": {"currency": null, "max": null, "min": null, "period": "monthly", "term": null}, "salary_visible": false, "title_keywords": ["private banking"], "responsibilities": ["control", "management", "data", "review", "monitor", "teams", "developing", "testing", "coordinate", "lead a team", "systems", "communication", "reports", "personal data", "recruitment", "banking", "senior management", "report"], "requirements": {"degrees": [], "majors": [], "languages": ["chinese", "mandarin"], "language_level": [], "hard_skills": ["python", "excel", "vba", "programming"], "soft_skills": ["confidence", "responsible", "timely", "motivated", "communication and interpersonal skills", "creative"], "languages_combined": [{"language": "chinese", "language_level": []}, {"language": "mandarin", "language_level": []}]}, "experience_required": {"duration": ["8 years"], "field": []}}, {"job_id": "100003009049923", "location_code": "hk", "company": "Nanyang Commercial Bank", "job_title": "Credit Monitoring Manager (Ref: OH8020-00-JDB)", "description": "Perform portfolio analysis to identify potential credit risks and provide professional advice on risk mitigation. Gather and analyse market information, monitor the performance of credit facilities utilization to identify early signs of credit deterioration.\u00a0Perform impairment assessment, conduct procedural reviews and relevant MIS reports. Make recommendations and review on credit risk management strategies to comply with relevant regulatory requirements.\n\nRequirements:\n\nDegree holder in Risk Management, Finance, Economics, Accounting, Information System or related disciplines;\nAt least 3 years experience in credit risk management and monitoring;\nSound knowledge in legal and regulatory requirements, Basel III and banking practices on credit risk management;\nHands-on experience of MS Excel, PowerPoint (Knowledge in database management and statistical computer applications is an advantage);\nAnalytical, independent with good communication skills;\nProficient in both spoken and written English and Chinese.\n\n(Candidate with less experience will be considered as Assistant Credit Monitoring Manager.)\n\nIf you are flexible enough and zeal for a harmonious and supportive working environment where enables you to grow and succeed professionally, please send a full resume indicating your public examination results (HKCEE and HKALE / HKDSE), your present and expected salary and quoting reference number attention to\u00a0Talent Acquisition Division, Nanyang Commercial Bank, 151 Des Voeux Road Central, Hong Kong or apply through email. For details, please visit https://www.ncb.com.hk/ and select the page Recruit.\n\nWe are an Equal Opportunities Employer. Data collected would be used for recruitment purposes only. Applicants who do not hear from us within 8 weeks may consider their applications unsuccessful and their data will be destroyed within 12 months of receipt.", "employment_types": ["Full Time", "Permanent"], "selling_points": ["Perform portfolio analysis to identify risks", "Analyse and review market information", "At least 4 years relevant working experience"], "locations": ["Central & Western Area"], "categories": ["Accounting", "Credit Control", "Banking / Finance", "Credit Analysis / Approval"], "post_time": "2022-01-15T03:50:41Z", "salary": {"currency": null, "max": null, "min": null, "period": "monthly", "term": null}, "salary_visible": false, "title_keywords": ["manager"], "responsibilities": ["make recommendations", "management", "market information", "data", "regulatory requirements", "analysis", "review", "monitoring", "communication", "reports", "monitor the performance", "database", "banking", "computer applications", "recruitment", "analyse"], "requirements": {"degrees": ["hkdse", "degree holder"], "majors": ["risk management", "finance", "economics", "related disciplines", "accounting"], "languages": ["english", "chinese"], "language_level": ["proficient"], "hard_skills": ["analysis", "information system", "powerpoint", "make", "ms excel"], "soft_skills": ["make recommendations", "communication skills", "flexible", "supportive", "independent", "harmonious", "hands-on"], "languages_combined": [{"language": "english", "language_level": ["proficient"]}, {"language": "chinese", "language_level": ["proficient"]}]}, "experience_required": {"duration": ["at least 3 years"], "field": ["management", "database management", "credit risk"]}}, {"job_id": "100003009036948", "location_code": "hk", "company": "The Hong Kong And China Gas Co Ltd", "job_title": "Receivable Officer", "description": "The Role:\n\nArrange billings and perform credit control functions for sales and installations\nReconcile and follow up Receivable and General Ledger accounts\nFollow up customer messages and prepare related account adjustments\nPrepare required documents and carry out dunning with the customers having outstanding balances\nPrepare monthly reports and analysis\nAssist to perform ad-hoc assignments with receivable related issues\nThe Person:\n\nDegree holder or Higher Diploma in Business/Finance/Accounting or related disciplines\nAt least 3 years\u2019 relevant experiences in the receivable and/or credit control field\nProficient in PC applications; knowledge of SAP is preferred\nGood communication skills to cooperate and negotiate with internal parties and external parties Responsible, self-motivated and able to work independently\nGood command of written & spoken English and Chinese including Putonghua\n\nApplication with full details stating current and expected salary to:\u00a0APPLY\u00a0NOW\n\nPlease quote the reference number (CTD/RO/JDB01/22) in your application.\n\n(All personal data provided will be treated in strict confidence and used for recruitment purposes only.)", "employment_types": ["Full Time"], "selling_points": ["Receivable Officer", "Treasury", "Finance/Accounting"], "locations": ["Quarry Bay"], "categories": ["Accounting", "Credit Control", "Banking / Finance", "Treasury"], "post_time": "2022-01-11T00:56:14Z", "salary": {"currency": null, "max": null, "min": null, "period": "monthly", "term": null}, "salary_visible": false, "title_keywords": ["officer"], "responsibilities": ["control", "monthly reports", "general ledger", "billings", "analysis", "ad-hoc assignments", "external parties", "communication", "recruitment", "personal data", "internal parties"], "requirements": {"degrees": ["diploma", "degree holder"], "majors": ["related disciplines", "finance", "business", "accounting"], "languages": ["putonghua", "english", "chinese"], "language_level": ["good command"], "hard_skills": ["analysis", "sap", "pc applications"], "soft_skills": ["communication skills", "self-motivated", "confidence", "work independently", "responsible"], "languages_combined": [{"language": "putonghua", "language_level": ["good command"]}, {"language": "english", "language_level": ["good command"]}, {"language": "chinese", "language_level": ["good command"]}]}, "experience_required": {"duration": ["at least 3 years"], "field": []}}, {"job_id": "100003009037965", "location_code": "hk", "company": "Cheil Hong Kong Limited", "job_title": "Billing Assistant (2-3 days per week)", "description": "Responsibilities:\n\nEnsure bill payment records are updated in the system accurately and timely\nWork with internal parties to clarify and resolve any discrepancy\nVerify accuracy of billing data and work with external parties to revise any error\nProcess and verify billing data and monthly invoices\nPerform ad hoc tasks as assigned\n\n\u00a0Requirement:\n\nDiploma holder in Business Administration, Finance, Information Systems or other related discipline with minimum 1 year of relevant working experience\nWell-organized, detail-minded and proactive\nIndependent, self-motivated, analytical and able to work under tight deadlines\nGood communication skills, interpersonal skills and problem-solving skills\nGood command of spoken and written English and Chinese\nProficient in Microsoft Office applications", "employment_types": ["Part Time", "Contract"], "selling_points": ["2-3 days per week", "Detail-minded", "Experience in billing handling"], "locations": ["Sheung Wan"], "categories": ["Accounting", "Credit Control", "Others", "Banking / Finance", "Credit Collection"], "post_time": "2022-01-11T04:27:14Z", "salary": {"currency": null, "max": null, "min": null, "period": "monthly", "term": null}, "salary_visible": false, "title_keywords": ["assistant"], "responsibilities": ["invoices", "data", "external parties", "ad hoc tasks", "payment", "internal parties"], "requirements": {"degrees": ["diploma holder"], "majors": ["finance", "business administration"], "languages": ["english", "chinese"], "language_level": ["good command"], "hard_skills": ["problem-solving skills", "microsoft office"], "soft_skills": ["detail-minded", "communication skills", "self-motivated", "independent", "well-organized", "interpersonal skills", "problem-solving skills", "proactive"], "languages_combined": [{"language": "english", "language_level": ["good command"]}, {"language": "chinese", "language_level": ["good command"]}]}, "experience_required": {"duration": ["minimum 1 year"], "field": ["related", "finance", "business administration", "relevant working experience"]}}, {"job_id": "100003009038487", "location_code": "hk", "company": "Crowne Plaza Hong Kong Causeway Bay", "job_title": "Finance Supervisor", "description": "Job Responsibilities\n\nAssist to prepare and review F&B items and store inventories;\nConduct inventory check on F&B and operating equipment items;\nPrepare daily costing reports;\nParticipate in month-end closing;\nAssist to income audit matters and daily accounting activities;\nPrepare and perform control activities for operation;\nAssist other ad hoc assignments as assigned.\n\nRequirements\n\nDegree / Diploma holder in Accounting, Hospitality or related discipline;\nMinimum 3 years related experience;\nPrevious experience in Hospitality industry would be an advantageous;\nProficiency in MS Office applications;\nGood command in both written and spoken English and Mandarin;\nKnowledge of PMS system (Opera) and POS system would be advantageous;\nLess experience will be considered as Senior Finance Clerk.", "employment_types": ["Full Time", "Permanent"], "selling_points": ["Prepare daily costing reports", "Assist to daily accounting activities", "Minimum 3 years related experience"], "locations": ["Causeway Bay"], "categories": ["Accounting", "Accounting Clerk / Supervisor", "Audit", "Credit Control"], "post_time": "2022-01-11T07:04:53Z", "salary": {"currency": null, "max": null, "min": null, "period": "monthly", "term": null}, "salary_visible": false, "title_keywords": ["supervisor"], "responsibilities": ["control", "inventory check", "review", "audit", "month-end closing", "reports", "ad hoc assignments", "daily accounting"], "requirements": {"degrees": ["diploma holder", "degree"], "majors": ["hospitality", "accounting"], "languages": ["english", "mandarin"], "language_level": ["good command"], "hard_skills": ["pos system", "ms office"], "soft_skills": [], "languages_combined": [{"language": "english", "language_level": ["good command"]}, {"language": "mandarin", "language_level": ["good command"]}]}, "experience_required": {"duration": ["minimum 3 years"], "field": ["related", "finance", "hospitality industry"]}}, {"job_id": "100003009043380", "location_code": "hk", "company": "ADECCO", "job_title": "Credit Monitoring Specialist (12-month Contract Renewable)", "description": "Our client is a leading bank; they are looking for a Credit Monitoring Specialist to join their team\n\nResponsibilities:\n\n\u2022 Contact clients to gather financial data and documentation\n\u2022 Perform impairment assessment\n\u2022 Analyze potential credit risks and market information\n\u2022 Analyze risks and approve or reject loan requests\n\nRequirements:\n\n\u2022 Analytical, independent with good communication skills\n\u2022 Bachelor\u2019s degree in related disciplines or relevant qualifications\n\u2022 Any relevant working experiences is preferred, but not necessary\n\u2022 Ability to create and process financial spreadsheets (MS Excel)\n\u2022 Familiar with general banking and the financial institution will be an advantage\n\nIf you're interested in this role, please CLICK HERE or click 'Apply Now' to apply the position via the Adecco website with your CV.\n\nPlease note that only shortlisted candidates will be notified. All information gathered will be treated in strict confidence and solely used for recruitment purposes.", "employment_types": ["Contract"], "selling_points": [], "locations": ["Kowloon Bay"], "categories": ["Accounting", "Credit Control", "Banking / Finance", "Credit Analysis / Approval", "Credit Collection"], "post_time": "2022-01-12T11:11:45Z", "salary": {"currency": null, "max": null, "min": null, "period": "monthly", "term": null}, "salary_visible": false, "title_keywords": ["specialist"], "responsibilities": ["documentation", "market information", "contact", "data"], "requirements": {"degrees": ["degree", "bachelor"], "majors": ["related disciplines"], "languages": [], "language_level": [], "hard_skills": ["ms excel"], "soft_skills": ["communication skills", "interested in", "independent", "confidence"], "languages_combined": []}, "experience_required": {"duration": [], "field": []}}, {"job_id": "100003009021036", "location_code": "hk", "company": "HKT", "job_title": "(Assistant) Credit Control Officer", "description": "Your role:\nPerform credit management and debt collection actions\nCarry out debt recovery actions on corporate customers via telephone and demand letters\nExecute routine dunning actions for non-payment accounts on consumer segments\nLiaise with different internal parties in resolving disputes and outstanding accounts\nMonitor customer payment\u2019s behaviour, perform credit assessment and prepare credit risk analysis/MIS reports to management\nMonitor debt collector performance and perform day-to-day operations on debt assignments\nContribute to formulate credit policy and related credit system development\nHandle other credit control issues and ad hoc assignments\n\nTo succeed in this role:\n\nDiploma Holder or above in Business Administration, Accounting, Finance or related discipline\nMinimum 2\u00a0years' solid experience in credit management\nGood command of spoken and written English and Chinese\nProactive, outgoing, enthusiastic and sensitive to market/economic environment\nAnalytical and self-motivated in problem-solving\nCan work under pressure\nExcellent interpersonal and negotiation skills\nProficient MSOffice applications\nCustomer service experience is a plus\n\nFast learners with less working experience (or fresh graduate) may also be considered. Higher caliber candidate may be considered as Credit Control Officer\n\nIf you have the desire for an exciting and rewarding career, please apply by sending your resume immediately, quoting your present and expected salary by clicking \"Apply Now\".", "employment_types": ["Full Time"], "selling_points": ["Perform credit management and debt collection", "Carry out debt recovery actions", "Execute routine dunning actions"], "locations": ["Lai Chi Kok"], "categories": ["Accounting", "Accounting Clerk / Supervisor", "Credit Control", "Others"], "post_time": "2022-01-05T02:56:33Z", "salary": {"currency": null, "max": null, "min": null, "period": "monthly", "term": null}, "salary_visible": false, "title_keywords": ["credit control officer", "assistant"], "responsibilities": ["management", "control", "work under pressure", "customer service experience", "letters", "monitor", "day-to-day operations", "debt collection", "payment", "reports", "risk analysis", "ad hoc assignments", "liaise with", "internal parties", "administration"], "requirements": {"degrees": ["diploma holder", "fresh graduate"], "majors": ["finance", "accounting", "business administration"], "languages": ["english", "chinese"], "language_level": ["good command"], "hard_skills": ["problem-solving", "analysis", "msoffice", "plus"], "soft_skills": ["outgoing", "self-motivated", "problem-solving", "sensitive to", "negotiation skills", "customer service", "enthusiastic", "proactive", "interpersonal", "work under pressure"], "languages_combined": [{"language": "english", "language_level": ["good command"]}, {"language": "chinese", "language_level": ["good command"]}]}, "experience_required": {"duration": ["minimum 2 years"], "field": ["management", "customer service"]}}, {"job_id": "100003009024568", "location_code": "hk", "company": "Spacebox Limited", "job_title": "Accounting Supervisor \u2013 Account Receivable - AR", "description": "Why Spacebox?\n\nSpacebox is the leading on-demand storage Company in Hong Kong. See how our service works HERE. We provide an outstanding service that helps Hong Kong people make the most of the space they have.\n\nWe have been successful because we are committed to our clients and to our team. This is a Company that offers a space to thrive and do your best work in a highly supportive environment.\n\nOur mission is to transform the storage industry in Hong Kong and to be the industry leader. When we started there were exactly zero customer centric companies in this industry. We are proud to have changed this and we continue to push ourselves to set new standards every day.\n\n\nWhat you\u2019ll be doing?\n\nManage Account Receivable operations: payment methods, payment processors, billing system, dunning & collection process, bad debt and write off process;\nDevelop, document, and maintain Billing, AR & Collections policies;\nGuide and supervise daily performance of billing and credit officers: distribute targets and assure performance, train and develop as required;\nEnsure billing and client database accuracy and drive process improvement and automation efforts to streamline revenue reconciliation and accounting;\nMonitor DSO and Average Collection Period to determine if adjustments to collection policies are necessary;\nWork closely with management and all other departments to continuously improve company AR collection results;\nProvide world-class customer service to external and internal customers (i.e., Sales, Customer Success, Operations, etc);\nCollaborate with the IT team on automation and enhancement projects to continuously improve processes;\nManage month-end close tasks, including income recognition and P&L income side accuracy;\nSupport management on cash forecasting, provide management with regular AR performance metrics and other ad-hoc reports;\nSupport ad hoc projects and assignments as required.\n\nWho we are looking for?\n\nYou have at least 6 years working experience in accounting, with 3 years in account receivable and at least 2 years in a supervisory function.\nExperience in high volume AR environment, subscription billing experience preferred;\nComfortable with ambiguity and comfortable in a fast-paced, evolving environment;\nStrong understanding of operational accounting procedures and month-end and quarter-end close processes;\nQualification of HKICPA, ACCA or equivalent will be an advantage, other recognised CPA qualification will be considered;\nProficient in advanced excel and accounting systems, at ease with adopting new IT platforms;\nStrong interpersonal communication skills;\nFluent in English.", "employment_types": ["Full Time"], "selling_points": ["5 days work, Kwai Chung District", "Young & Energetic environment", "$26,000-$29,000/month"], "locations": ["Kwai Hing"], "categories": ["Accounting", "Accountant", "Credit Control", "Finance / Accounting Manager"], "post_time": "2022-01-06T01:45:41Z", "salary": {"currency": null, "max": null, "min": null, "period": "monthly", "term": null}, "salary_visible": false, "title_keywords": ["accounting supervisor"], "responsibilities": [], "requirements": {"degrees": [], "majors": [], "languages": [], "language_level": [], "hard_skills": [], "soft_skills": [], "languages_combined": []}, "experience_required": {"duration": [], "field": []}}, {"job_id": "100003009038930", "location_code": "hk", "company": "Jacobson Medical (HK) Ltd", "job_title": "Account Clerk", "description": "Key Roles and Responsibilities\u00a0\n\nResponsible for Accounts duties, including handling daily transactions, data input and processing, compilation of report etc;\nCoordinate with other departments in Accounts issues;\nAssist in handling book-keeping and accounting tasks; &\nAd hoc tasks as assigned.\n\n\u00a0Qualification and Experience\n\nForm 5 or above, with LCCI 2nd Level or above;\nAt least 1-2 year's relevant working experience would be preferable;\nFamiliar with MS Office, especially in excel;\nExperience of working with FLEX Accounting system is a definite advantage; &\nImmediately available is highly preferable.\n\nHow to Apply\nYou are invited to send in your application and CV stating your expected salary (please remember to mention your expected salary), either by\u00a0Clicking\u00a0\"Apply Now\"\u00a0as below.\n\nJacobson Medical (HK) Ltd\u00a0is an equal opportunities employer. The information provided will be treated in strict confidence and used only for consideration of application for relevant/similar post(s).\u00a0 All personal data of unsuccessful applicants will be destroyed within 6 months.", "employment_types": ["Full Time", "Permanent"], "selling_points": [], "locations": ["Tai Po Area"], "categories": ["Accounting", "Accountant", "Accounting Clerk / Supervisor", "Credit Control"], "post_time": "2022-01-11T08:09:54Z", "salary": {"currency": null, "max": null, "min": null, "period": "monthly", "term": null}, "salary_visible": false, "title_keywords": ["account clerk"], "responsibilities": ["coordinate with", "data input", "transactions", "ad hoc tasks", "book-keeping", "personal data", "report"], "requirements": {"degrees": ["form 5 or above"], "majors": [], "languages": [], "language_level": [], "hard_skills": ["excel", "flex accounting", "processing", "ms office"], "soft_skills": ["confidence", "responsible"], "languages_combined": []}, "experience_required": {"duration": ["at least 1-2 year"], "field": ["accounting", "relevant working experience"]}}, {"job_id": "100003009036667", "location_code": "hk", "company": "HKT", "job_title": "(Assistant) Accounting Officer, Cash Management - Collections", "description": "Your role:\n\nFollow up daily bank receipts collected from bill-receipting agencies, card companies and customers\nPerform daily bank balance reconciliation and monitor the performance of various bill-receipting agencies\nSupport daily operations of cash management division\nAssist in month-end closing, prepare management reports and analysis\nAssist in ad-hoc assignment\n\n\u00a0\nTo succeed in this role:\n\nDSE / Higher Diploma / Degree in Business Administration, Accounting, Finance or related discipline\n1-2 years of accounting experience in Telecommunications or Finance industry\nSelf-motivated and strong passion to deliver result\nGood analytical and problem solving skills\nAbility to work under pressure and tight deadlines\nProficient in MS Office applications and experience in Oracle Financial is an advantage\nGood interpersonal and communication skills\nGood command of both spoken and written English and Chinese\nImmediately available is preferred.\n\nCandidates with more experience will be considered as Accounting Officer.\n\nIf you have the desire for an exciting and rewarding career, please apply by sending your resume immediately, quoting your present and expected salary by clicking \"Apply Now\".", "employment_types": ["Full Time"], "selling_points": [], "locations": ["Lai Chi Kok"], "categories": ["Accounting", "Accounting Clerk / Supervisor", "Credit Control", "Others"], "post_time": "2022-01-10T12:12:48Z", "salary": {"currency": null, "max": null, "min": null, "period": "monthly", "term": null}, "salary_visible": false, "title_keywords": ["accounting officer", "cash management", "assistant"], "responsibilities": ["ad-hoc", "management", "receipts", "work under pressure", "analysis", "communication", "daily operations", "month-end closing", "management reports", "monitor the performance", "administration"], "requirements": {"degrees": ["diploma", "degree", "dse"], "majors": ["finance", "accounting", "business administration"], "languages": ["english", "chinese"], "language_level": ["good command"], "hard_skills": ["analysis", "management reports", "problem solving skills", "ms office", "oracle"], "soft_skills": ["communication skills", "self-motivated", "analytical and problem solving skills", "interpersonal", "work under pressure"], "languages_combined": [{"language": "english", "language_level": ["good command"]}, {"language": "chinese", "language_level": ["good command"]}]}, "experience_required": {"duration": ["1-2 years"], "field": ["accounting experience", "finance industry", "telecommunications", "accounting", "financial"]}}, {"job_id": "100003009034296", "location_code": "hk", "company": "Dyxnet Limited", "job_title": "Manager / Senior Manager, Contract and System Management (SAP)", "description": "Responsibilities:\n\nLead and manager the HK and China team to provide the contract and system management service, including sales support, purchasing, and billing services.\nResponsible for proposing and control of the terms of the sales contract and distribution the sales leads.\nAnalyze the sales and operation data, calculate the BP commission and provide the sales performance analysis.\nResponsible to maintain and develop the sales contract system.\u00a0\u00a0Provide the monthly data and report to management.\nEstablish and maintain strong relationships with Software and others department to develop and maintain the internal systems to enhance work efficiency and accuracy.\nCooperate with Group Director, Customer Service and Sales Support to realize the company's mission and vision.\n\nQualifications:\n\nDegree or above in Business Administration or any related discipline\nMinimum of 5 years relevant work experience, with at least 3 years in management level.\nKnowledge of customer service administration, supplier management and inventory management.\nKnowledge in IT and understanding of network services.\nGood command in spoken and written Chinese, English, Mandarin\nAdvanced Word, Excel and access skills.\nPositive attitude, fast-learning, energetic, able to perform in challenging environment.\n\n\n\nAttractive remuneration and compensation package, including year end bonus, medical scheme, life insurance, as well as career development opportunities will be offered.\n\nInterested parties please send your resume with expected salary and availability to Human Resources Department, Dyxnet Group, 37/F, Tower 1, Metoplaza, 223 Hing Fong Road, Kwai Fong.\n\nWelcome to visit our website: http://www.dyxnet.com for further information of our company.\n\nData collected will be used for recruitment purpose only.", "employment_types": ["Full Time", "Permanent"], "selling_points": ["Lead contract and system management service team", "Maintain and develop the sales contract system", "Five days work"], "locations": ["Kwai Fong"], "categories": ["Accounting", "Credit Control", "Admin & HR", "Administration / Operation Manager", "Sales, CS & Business Devpt", "Customer Service - Manager"], "post_time": "2022-01-10T03:06:14Z", "salary": {"currency": null, "max": null, "min": null, "period": "monthly", "term": null}, "salary_visible": false, "title_keywords": ["senior manager", "manager"], "responsibilities": ["administration", "management", "control", "software", "data", "sales performance", "analysis", "develop", "inventory management", "maintain", "customer service", "career development", "insurance", "cooperate with", "internal systems", "report"], "requirements": {"degrees": ["degree or above"], "majors": ["business administration"], "languages": ["english", "chinese", "mandarin"], "language_level": ["good command"], "hard_skills": ["excel", "sales support", "analysis", "word", "scheme"], "soft_skills": ["advanced", "responsible", "fast-learning", "positive attitude", "customer service", "energetic"], "languages_combined": [{"language": "english", "language_level": ["good command"]}, {"language": "chinese", "language_level": ["good command"]}, {"language": "mandarin", "language_level": ["good command"]}]}, "experience_required": {"duration": ["at least 3 years", "minimum of 5 years"], "field": ["management"]}}, {"job_id": "100003009023409", "location_code": "hk", "company": "Rise Associates Asia Limited", "job_title": "Accounting Officer - AR & Credit Control (Property Developer)", "description": "Our client is one of the largest property developers in Hong Kong with an extensive portfolio in Mainland China. Due to continuous development, they are looking for an Accounting Officer to assist in AR functions.\n\u00a0\nJob Descriptions:\n\nMainly perform Accounts Receivables duties\nAssist in daily accounting operations and month-end / year-end closing\nAssist in monitoring outstanding accounts and perform debt collection actions via telephone or email\nHandle customers inquires and complaints on billing issues\nAssist in\u00a0preparing analysis reports for the review of management\nLiaise with other departments in resolving disputes and outstanding accounts\nParticipate in ad hoc projects\nRequirements:\n\nHigher Diploma / Degree holder in Business Administration or Accounting or related disciplines\n5 years or above accounting experience, preferably in credit administration, credit control and debt collection\nGood reporting and coordinating skills for credit control\nGood communication skills\nProficiency in Microsoft Word and Excel Applications", "employment_types": ["Permanent"], "selling_points": ["Perform AR duties & monitor outstanding A/C", "Good communication skill", "Stable platform with good career prospect"], "locations": ["Not Specified"], "categories": ["Accounting", "Accounting Clerk / Supervisor", "Credit Control", "Banking / Finance", "Credit Collection"], "post_time": "2022-01-05T08:35:25Z", "salary": {"currency": null, "max": null, "min": null, "period": "monthly", "term": null}, "salary_visible": false, "title_keywords": ["developer", "accounting officer"], "responsibilities": ["management", "analysis reports", "monitoring", "review", "month-end", "daily accounting operations", "debt collection", "ad hoc projects", "year-end closing", "liaise with"], "requirements": {"degrees": ["diploma", "degree holder"], "majors": ["related disciplines", "accounting", "business administration"], "languages": [], "language_level": [], "hard_skills": ["excel", "microsoft word"], "soft_skills": ["communication skills"], "languages_combined": []}, "experience_required": {"duration": ["5 years"], "field": ["accounting experience", "administration"]}}, {"job_id": "100003009019898", "location_code": "hk", "company": "Smith & Associates Far East Ltd", "job_title": "Credit Analyst/ Credit & AR Coordinator/ AR Specialist (APAC role) *New Headcount*", "description": "Responsibilities:\n\nCreate new and update existing accounts\nSupport daily credit review and order release\nHandle cash receipts and AR settlement\nAssist in managing daily collection activities\nPrepare and analyze AR aging and DSO report\nCommunicate with other departments, as well as, management to alert them to any problems and/or high risk situations\nNegotiate with customers to expedite collection efforts in a customer centric manner\nEvaluate new account applications and establish credit parameters for all transactions to control the credit risk\nAssist the Asia Credit Manager to support daily operations and ad-hoc assignment\n\nRequirements:\n\nDegree/ Higher Diploma holder in Accounting or Finance related discipline or equivalent experience in Accounts Receivable and/or Credit Review\nGood interpersonal and communication skills\nAbility to analyze financial statements and review Credit report\nProficient in MS Office and Accounting Systems\nGood command of both verbal and written English and Chinese (Cantonese and Mandarin)", "employment_types": ["Full Time"], "selling_points": ["Well established MNC", "Regional exposure", "Stable and friendly work environment"], "locations": ["Kowloon Bay"], "categories": ["Accounting", "Accountant", "Credit Control", "Others"], "post_time": "2022-01-04T09:29:36Z", "salary": {"currency": null, "max": null, "min": null, "period": "monthly", "term": null}, "salary_visible": false, "title_keywords": ["specialist", "coordinator", "credit analyst"], "responsibilities": ["order release", "communicate with", "management", "control", "ad-hoc", "ar", "receipts", "review", "transactions", "evaluate", "daily operations", "report"], "requirements": {"degrees": ["degree", "higher diploma holder"], "majors": ["finance", "accounting"], "languages": ["cantonese", "english", "chinese", "mandarin"], "language_level": ["good command"], "hard_skills": ["accounting systems", "ms office"], "soft_skills": ["ability to analyze", "communication skills", "interpersonal"], "languages_combined": [{"language": "cantonese", "language_level": ["good command"]}, {"language": "english", "language_level": ["good command"]}, {"language": "chinese", "language_level": ["good command"]}, {"language": "mandarin", "language_level": ["good command"]}]}, "experience_required": {"duration": [], "field": ["related", "finance", "accounting"]}}, {"job_id": "100003009028341", "location_code": "hk", "company": "CUHK Medical Centre Limited", "job_title": "Billing Officer", "description": "Key Responsibilities\n\nSupport day to day operation of billing and revenue management;\nHandle patient billing issues and ensure accuracy and completeness of chargeable items;\nHandle budget estimate of hospital stays;\nShift duty is required; and\nPerform any other duties as assigned.\n\nJob Requirements\n\nHolder of a Diploma in any discipline\nAt least 2 years\u2019 relevant work experience\nExperience in hospital / healthcare field is preferred\nGood command of both spoken and written English and Chinese\nProficient in MS Office applications\n\nCompensation and Employment Terms\n\nWe provide a unique employment experience for people seeking careers in hospital and healthcare industry; and offer competitive remuneration packages to the successful candidates. Appointment will be made on a 3-year contract with contract-end gratuity, renewable subject to good performance and mutual agreement.\n\nApplication Closing Date\n\n20 January 2022\n\nPersonal Information Collection Statement\n\nData collected will only be used for job application processing. Applicants not contacted by CUHK Medical Centre Limited within eight weeks from the application closing date may assume their applications unsuccessful. All personal data collected will be kept for a period of 12 months from the application closing date, and will be destroyed thereafter.", "employment_types": ["Full Time", "Contract"], "selling_points": ["Holder of a Diploma in any discipline", "2 years\u2019 relevant work experience", "Exp in hospital / healthcare field is preferred"], "locations": ["Shatin Area"], "categories": ["Accounting", "Credit Control", "Insurance", "Claims Officer", "Medical Services", "Others"], "post_time": "2022-01-07T02:05:12Z", "salary": {"currency": null, "max": null, "min": null, "period": "monthly", "term": null}, "salary_visible": false, "title_keywords": ["billing officer"], "responsibilities": ["any other duties", "management", "budget"], "requirements": {"degrees": ["diploma"], "majors": [], "languages": ["english", "chinese"], "language_level": ["good command"], "hard_skills": ["ms office"], "soft_skills": [], "languages_combined": [{"language": "english", "language_level": ["good command"]}, {"language": "chinese", "language_level": ["good command"]}]}, "experience_required": {"duration": ["at least 2 years"], "field": ["healthcare"]}}, {"job_id": "100003009036670", "location_code": "hk", "company": "HKT", "job_title": "Senior Accounting Executive, Cash Management", "description": "Your role:\n\nMonitor daily operations of the team including daily receipts reconciliation between receivable system and different payment channels such as autopay, credit card, PPS, ATM, 7-Eleven, e-wallet etc.\nCarry out ad-hoc assignment and system testing\nPerform monthly general ledger posting and bank reconciliation\nProvide support for finance and audits conducted by both internal and external sources\nRecommend policies, procedures and new workflow to administer bill receipt process for operational improvement\nPrepare monthly MIS reports\n\nTo succeed in this role:\n\nDegree in Business Administration, Accounting, Finance, Information Technology or related discipline\nMinimum 5 years of relevant experience in Online purchase, Payment Card, Telecommunications or Finance industry\nStrong leadership, self-motivated and strong passion to deliver result\nGood analytical and problem solving skills\nAbility to work under pressure and tight deadlines\nProficient in MS Office applications and experience in project management is an advantage\nTeam player with good interpersonal and communication skills\nGood command of both spoken and written English and Chinese\n\nCandidate with less experience will be considered as Accounting Executive.\n\nIf you have the desire for an exciting and rewarding career, please apply by sending your resume immediately, quoting your present and expected salary by clicking \"Apply Now\".", "employment_types": ["Full Time"], "selling_points": [], "locations": ["Lai Chi Kok"], "categories": ["Accounting", "Accounting Clerk / Supervisor", "Credit Control", "Others"], "post_time": "2022-01-10T12:14:35Z", "salary": {"currency": null, "max": null, "min": null, "period": "monthly", "term": null}, "salary_visible": false, "title_keywords": ["accounting executive", "cash management"], "responsibilities": ["ad-hoc", "receipts", "general ledger", "bank reconciliation", "communication", "payment", "purchase", "work under pressure", "administration", "monitor", "testing", "reports", "autopay", "provide support", "procedures", "daily operations", "audits", "policies", "project management"], "requirements": {"degrees": ["degree"], "majors": ["finance", "accounting", "business administration", "information technology"], "languages": ["english", "chinese"], "language_level": ["good command"], "hard_skills": ["project management", "problem solving skills", "ms office"], "soft_skills": ["communication skills", "self-motivated", "analytical and problem solving skills", "project management", "team player", "leadership", "interpersonal", "work under pressure"], "languages_combined": [{"language": "english", "language_level": ["good command"]}, {"language": "chinese", "language_level": ["good command"]}]}, "experience_required": {"duration": ["minimum 5 years"], "field": ["project management", "relevant experience", "finance industry", "telecommunications", "accounting"]}}, {"job_id": "100003009037174", "location_code": "hk", "company": "Peoplus Recruitment", "job_title": "Internal Control Manager RM220111-01", "description": "Our client is a MNC Supply Chain Solution group in worldwide\u00a0is now seeking a candidate for their openings\n\nResponsibilities:\n\nReporting to Senior Manager and responsible to lead a small team to manage Internal Control and Treasury functions, and also coordinate internal and external audits\nResponsible to review internal control self-assessments to ensure compliance with Group\u2019s policy and local requirement\nReview operational and financial to identify areas of improvement\nWork with senior manager and responsible to provide recommendation and initiate new measures to improve process efficiency, internal control, risk management, corporate governance and cost saving\nHandle external audit, internal audit and other compliance activities\nWork as supervisor to manage account payable, fixed asset and treasury functions\nReview subordinates and shared service centre daily payment and treasury work\nWork closely with different departments to implement corporate initiatives and projects\n\nRequirements:\n\nQualified accountant with at least 3-year post qualification working experiences with at least 6 years\u2019 solid experience in external audit, internal audit, internal control or related areas, with at least 2 years in commercial sector\nFamiliar with accounting standards, taxation laws and Companies Ordinance\nStrong leadership with excellent influencing, communication and presentation skills\nExcellent analytical and problem solving skills with strong business acumen\nExcellent command of spoken and written English and Chinese\nProficient PC skills, knowledge in SAP is an advantage\n\nInterested parties please send full resume with followings to ryan\u00a0@peoplus.com.hk\n\n\n\n1. Current & Expected Salary\n2. Date of Availability\u00a0\n3. Quoting the Emp. Ref. No. : RM220111-01\n4. Date of Achievement : Academic Result\n\nFor a confidential discussion about this role please contact\u00a0Ryan at 3998 4490\n\nAll personal data provided by job applicants will be used for recruitment purpose only.", "employment_types": ["Full Time", "Permanent"], "selling_points": ["Perform operational and financial review", "Review internal control self-assessments", "Min. 6 related exp. & lead a small team"], "locations": ["Kwun Tong Area"], "categories": ["Accounting", "Accountant", "Credit Control", "Treasurer"], "post_time": "2022-01-11T01:58:46Z", "salary": {"currency": null, "max": null, "min": null, "period": "monthly", "term": null}, "salary_visible": false, "title_keywords": ["manager"], "responsibilities": ["reporting", "management", "cost", "internal audit", "lead a small team", "internal and external audits", "review", "audit", "compliance", "ensure compliance", "coordinate", "provide recommendation", "payment", "internal control"], "requirements": {"degrees": [], "majors": [], "languages": ["english", "chinese"], "language_level": ["excellent"], "hard_skills": ["sap", "companies ordinance", "problem solving skills", "pc skills", "internal control", "acumen"], "soft_skills": ["communication", "analytical and problem solving skills", "presentation skills", "business acumen", "leadership"], "languages_combined": [{"language": "english", "language_level": ["excellent"]}, {"language": "chinese", "language_level": ["excellent"]}]}, "experience_required": {"duration": ["at least 6 years", "at least 3-year", "at least 2 years"], "field": ["related", "commercial", "audit"]}}, {"job_id": "100003009019322", "location_code": "hk", "company": "Intertek Testing Services H.K. Ltd.", "job_title": "Credit Assistant / Credit Control Administrator (AR)", "description": "Our purpose is to bring safety, quality and sustainability to life.\n\nThe Job\n\nHandle daily operation in account receivable and debt collection\n\nClosely contact with internal / external customers to follow up debt collection\nCoordinate with division in resolving payment disputes\nFollow up credit\u00a0limit / account release issue\nResponsible for AR Reporting and other ad hoc duty\n\nThe Person\n\nHigher diploma\u00a0or above,\u00a0in Accounting\u00a0/\u00a0Business\u00a0or other disciplines\nSolid experiences in Credit Control/ Account Receivable/ Customer Services experience would be an advantage\nSelf-motivated, good team player and good communication skills\u00a0\nGood PC knowledge, and strong in use of MS Excel\nGood command of both spoken & written in English & Chinese\nImmediate available is preferred\n\nThe Package\n\nFive day work week\nDouble pay\nMedical benefit\nDental plan with discount\n14 days annual leave\nLife insurance\nGood career prospects\n\nJoin us in bringing quality and safety to life\n\nInterested parties please forward full resume stating your availability, present and expected salary to The Human Resources Manager, Intertek Testing Services HK Ltd., via ONE of the following channels: (Pls quote ref. no. on all correspondence.)\n\n\nAddress:\u00a02/F, Garment Centre, 576 Castle Peak Rd., Kowloon, Hong Kong SAR, China\n\nE-mail: \u00a0Please click''APPLY NOW''\u00a0 \u00a0 \u00a0 \u00a0Fax: 3403 2437\u00a0\u00a0;\u00a0\u00a0Whatsapp: 6329 0464\n\nWelcome to visit our website\u00a0http://www.intertek.com.hk for corporate information\n\n\nConfidentiality assured and all applications will be kept solely for recruitment purpose for not more than 6 months.", "employment_types": ["Full Time", "Permanent"], "selling_points": ["Daily operation in account receivable", "Higher diploma in Accounting / Business", "Five day work week"], "locations": ["Lai Chi Kok"], "categories": ["Accounting", "Credit Control", "Others", "Sciences, Lab, R&D", "Laboratory"], "post_time": "2022-01-04T07:20:06Z", "salary": {"currency": null, "max": null, "min": null, "period": null, "term": null}, "salary_visible": false, "title_keywords": ["administrator", "assistant"], "responsibilities": ["reporting", "ad hoc", "ar", "daily operation", "coordinate with", "debt collection", "payment", "contact"], "requirements": {"degrees": ["higher diploma or above"], "majors": ["business", "accounting"], "languages": ["english", "chinese"], "language_level": ["good command"], "hard_skills": ["pc knowledge", "ms excel"], "soft_skills": ["communication skills", "good team player", "self-motivated"], "languages_combined": [{"language": "english", "language_level": ["good command"]}, {"language": "chinese", "language_level": ["good command"]}]}, "experience_required": {"duration": [], "field": ["customer services"]}}, {"job_id": "100003009027099", "location_code": "hk", "company": "A.S. Watson Industries", "job_title": "Assistant Credit Officer (Account Receivable)", "description": "Assist in monitoring Account Receivable collection process\nEnsure the team to input all daily payment receipts for online & offline collection\nPerform bank reconciliation\nAssist in month end closing\nHandle system UAT and ad hoc projects\nWork with collection team to make sure all settlement on closing schedule\nAd hoc project\n\n\u00a0Job Requirements:\n\n\nDiploma holder or above in Business Administration or related disciplines\nAt least 3 years of relevant working experience in Accounts Receivable, experience in FMCG as preferred\nGood communication, presentation and interpersonal skill\nProficient in MS Excel and experience on Oracle is an advantage\n\nWe offer competitive salary, discretionary performance bonus, medical and retirement benefits, free company coach services and excellent career prospects. Please send your resume together with salary expectation via\u00a0APPLY NOW\n\nFor more information, please visit our website at\u00a0www.aswatson.com\n\nAll information provided will be used for recruitment other employment-related purposes by A.S. Watson & Company Limited (for and on behalf of the A.S. Watson Group of companies). It may be provided to companies/parties authorized to process the information for purposes relating to recruitment, e.g. qualifications assessment.\n\nWith the consent of applicant, all personal data of unsuccessful applicants will be retained for future consideration for two years. Otherwise, all personal data of unsuccessful applicants will be retained for twelve months.\n\nApplication will not be considered if the applicant does not provide all information as requested.\n\nAll information provided will be held in strict confidence.\n\nIf applicant request access to, and to request correction of personal data in relation to the application, please contact our People Department at 2660 1880.", "employment_types": ["Full Time", "Permanent"], "selling_points": ["Assist in Account Receivable collection process", "3 years experience in Accounts Receivable", "Free Shuttle Bus, Discretionary bonus"], "locations": ["Tai Po Area"], "categories": ["Accounting", "Accounting Clerk / Supervisor", "Credit Control", "Others"], "post_time": "2022-01-06T09:07:14Z", "salary": {"currency": null, "max": null, "min": null, "period": "monthly", "term": null}, "salary_visible": false, "title_keywords": ["officer", "assistant"], "responsibilities": ["month end closing", "ad hoc", "receipts", "uat", "accounts receivable", "monitoring", "bank reconciliation", "website", "communication", "payment", "ad hoc projects", "schedule", "recruitment", "contact", "personal data", "administration"], "requirements": {"degrees": ["diploma holder"], "majors": ["related disciplines", "business administration"], "languages": [], "language_level": [], "hard_skills": ["make", "ms excel", "oracle"], "soft_skills": ["communication", "confidence", "presentation", "interpersonal skill"], "languages_combined": []}, "experience_required": {"duration": ["at least 3 years"], "field": ["fmcg", "relevant working experience"]}}, {"job_id": "100003009013011", "location_code": "hk", "company": "DHL EXPRESS (HONG KONG) LIMITED", "job_title": "Credit Agent / Accounts Receivable Assistant", "description": "Working Location: Ngau Tau Kok\nReporting to Credit Supervisor, you will be responsible for managing credit control and payment collection of corporate customers.\nResponsibilities:\nParticipate in payment collection plan formulation\nCommunicate with corporate customers for overdue payment collection\nCoordinate with customers and internal parties to resolve credit and billing issues\nMaintain daily payment collection records and prepare regular reports\nMaintain good relationship with customers while meeting business targets\nRequirements:\nDiploma holder with 2 years\u2019 experience in credit control or accounting field with customer interface exposure\nEffective communication and telephone handling skills\nCustomer-oriented and able to solve customer problems independently\nSelf-initiative, able to work with tight deadlines and under pressure\nExperience in using accountings systems is an advantage\nGood command in spoken and written English and Chinese (Cantonese and Mandarin)\nProficient with MS Office applications, especially Excel\nApplication:\nClick \"Apply Now\" or apply on line via the following link: https://dhlexpress.taleo.net/careersection/ex/jobdetail.ftl?job=2100CSO&iniurl.src=CWS-10001&tz=GMT%2B08%3A00&tzname=\nalso indicating your current and expected salary, and availability.\u00a0 For more job opportunities, please visit our website at https://www.dpdhl.jobs/\nPersonal Information Collection Statement pertaining to Recruitment\nDHL Express (Hong Kong) Limited / DHL Aviation (Hong Kong) Limited (\u201cDHL\u201d) is committed to protecting and respecting your privacy in accordance with the Personal Data (Privacy) Ordinance of Hong Kong (the \u201cOrdinance\u201d) and DHL\u2019s Personal Data Protection Policy (the \u201cPolicy\u201d) at\u00a0https://www.dhl.com/hk-en/home/footer/local-privacy-notice.html\nBy proceeding to respond to this recruitment advertisement, you consent that we may use, retain, process, transfer or otherwise handle the personal data that we collect from you for recruitment,\u00a0 application processing, assessment and communication purposes (including any other purposes directly related thereto) in accordance with the Policy.\nAll personal data of unsuccessful applicants will be retained for future recruitment purposes for a period of not more than two (2) years after which such data will be destroyed.\nYou have the right at any time to make a data access or correction request concerning your personal data held by us. In addition, you may request us to delete your personal data that is no longer required for the relevant purposes which you have given consent. Should you wish to exercise such rights or have any question in relation to your personal data or the Policy, please contact our Human Resources Division in writing.\n", "employment_types": ["Full Time"], "selling_points": ["Participate in payment collection plan", "Diploma holder with 2 years\u2019 experience", "Experience in using accountings systems"], "locations": ["Ngau Tau Kok"], "categories": ["Accounting", "Accounting Clerk / Supervisor", "Credit Control", "Banking / Finance", "Credit Collection"], "post_time": "2022-01-03T01:07:56Z", "salary": {"currency": null, "max": null, "min": null, "period": "monthly", "term": null}, "salary_visible": false, "title_keywords": ["assistant"], "responsibilities": ["communicate with", "payment collection", "coordinate with", "maintain good relationship", "maintain", "reports", "plan", "internal parties"], "requirements": {"degrees": ["diploma holder"], "majors": ["accounting"], "languages": ["cantonese", "english", "chinese", "mandarin"], "language_level": ["good command"], "hard_skills": ["excel", "no", "html", "make", "processing", "ms office"], "soft_skills": ["independently", "under pressure", "communication", "committed", "customer-oriented", "self-initiative"], "languages_combined": [{"language": "cantonese", "language_level": ["good command"]}, {"language": "english", "language_level": ["good command"]}, {"language": "chinese", "language_level": ["good command"]}, {"language": "mandarin", "language_level": ["good command"]}]}, "experience_required": {"duration": ["2 years"], "field": ["accounting"]}}, {"job_id": "100003009015975", "location_code": "hk", "company": "CK Asset Holdings Limited", "job_title": "Senior Officer, Credit Control", "description": "Higher Diploma / Degree holder, preferably in Business Administration / Accounting\n3 years or above experience in credit administration, credit control and debt collection\nGood reporting and coordinating skills for credit control\nIndependent and detail minded\nStrong interpersonal and negotiation skills\nProficiency in Microsoft Word and Excel Applications\n\nWe will offer attractive compensation package to the right candidate. Please send application enclosing resume stating career and salary history, expected salary and date of availability\u00a0to The\u00a0Senior Manager, Human Resources\u00a0Department, CK Asset\u00a0Holdings Limited, 7/F Cheung Kong Center, 2 Queen's Road Central, Hong Kong or by clicking\u00a0\"Apply Now\" (in Word format). Please quote the reference of the position you apply for in all correspondences.\n\nWe are an equal opportunity employer and welcome applications from all qualified candidates. Personal data collected will be treated in strictest confidence and handled confidentially by authorized personnel for recruitment-related purposes within the Group. Applicants not hearing from us within six weeks from the date of advertisement may consider their applications unsuccessful.", "employment_types": ["Full Time", "Permanent"], "selling_points": ["Higher Diploma or above in Accounting", "3 years experience in credit control", "Good reporting and coordinating skills"], "locations": ["Central"], "categories": ["Accounting", "Credit Control", "Property / Real Estate", "Property Consultancy", "Property Management"], "post_time": "2022-01-04T06:46:57Z", "salary": {"currency": null, "max": null, "min": null, "period": null, "term": null}, "salary_visible": false, "title_keywords": ["senior officer"], "responsibilities": ["reporting", "control", "debt collection", "recruitment", "personal data", "administration"], "requirements": {"degrees": ["diploma", "degree holder"], "majors": ["accounting", "business administration"], "languages": [], "language_level": [], "hard_skills": ["excel", "microsoft word", "word"], "soft_skills": ["negotiation skills", "confidence", "independent", "interpersonal"], "languages_combined": []}, "experience_required": {"duration": ["3 years"], "field": ["administration"]}}, {"job_id": "100003009024616", "location_code": "hk", "company": "Dah Chong Hong Holdings Limited", "job_title": "Assistant / Accounting Officer (Contract) (Ref: GFN_CON-OTC)", "description": "The incumbent will be responsible for monitoring receivable aging and ensure timely collection of outstanding debts, performing credit assessment to existing and new credit applications with the established guidelines, ensure timely and efficient resolution of all queries, both internal and external, Issue monthly debtors' statements and subsequent demand letters, preparing AR aging reports and ad hoc assignment.\n\nHigh Diploma or Graduated in Accounting, Business Administration, or related disciplines;\n3-4 years of solid working experience in Account Receivable;\nCustomer oriented with good inter-personal and communication skills;\nGood Command of written and spoken English and Chinese.\nIndependent, proactive, detail-oriented and able to work under pressure\nProficiency in MS applications, especially MS Office and Excel & VBA;\n\nInterested candidates please send your resume by email or clicking \u201cApply Now\u201d.\n\nWe are equal opportunities employer. Applicants who are not invited within 2 months may consider their application unsuccessful. All applicants may be considered for other suitable positions with DCH Group / CITIC Pacific Group and will be deleted from our files after 6 months from the date of application.", "employment_types": ["Contract"], "selling_points": [], "locations": ["Kowloon Bay"], "categories": ["Accounting", "Accounting Clerk / Supervisor", "Credit Control", "Banking / Finance", "Credit Collection"], "post_time": "2022-01-06T01:58:27Z", "salary": {"currency": null, "max": null, "min": null, "period": "monthly", "term": null}, "salary_visible": false, "title_keywords": ["accounting officer", "assistant"], "responsibilities": ["ar", "guidelines", "work under pressure", "ad hoc assignment", "monitoring", "letters", "resolution", "communication", "reports", "administration"], "requirements": {"degrees": ["high diploma"], "majors": ["related disciplines", "accounting", "business administration"], "languages": ["english", "chinese"], "language_level": ["good command"], "hard_skills": ["excel", "vba", "ms applications", "ar", "ms office"], "soft_skills": ["efficient", "communication skills", "independent", "responsible", "inter-personal", "timely", "detail-oriented", "proactive", "work under pressure"], "languages_combined": [{"language": "english", "language_level": ["good command"]}, {"language": "chinese", "language_level": ["good command"]}]}, "experience_required": {"duration": ["3-4 years"], "field": []}}, {"job_id": "100003009032878", "location_code": "hk", "company": "ConnectedGroup Limited", "job_title": "Finance Manager", "description": "Finance Manager\n\nOur client is an international trading company. They are now looking for an all-rounded and detail-minded Finance manager, directly report to the CFO.\n\nQualified CPA member\nAll-rounded finance role, FP&A, business analysis\nExcellent communication skills in English\n\nResponsibilities:\n\nLead a small team to provide financial reports, including monthly accounts, annual budget, and quarterly forecast on a timely and accurate basis\nProvide insightful financial analysis on business performance to support management decisions and business growth\nManage cash flow, treasury, and funds arrangement\nLiaise with bankers and auditors on all finance and accounting related matters\nKeep reviewing and strengthening ERP and internal control systems\nPerform other ad hoc projects and assignment\n\nRequirements:\n\nBachelor's degree in Finance & Accounting or related disciplines with CPA qualification\nAt least 8 years relevant experience in accounting and finance field with at least 2years in supervisory level, preferably with trading/ sourcing background\nStrong business and financial acumen with excellent problem-solving skills\nSmart, detail-minded with an ambition to strive for excellence\nExcellent communication and presentation skills\nProficient in Excel skills and with exposure in financial models\n\nInterested parties, please send your CV to Ivy Yeung Ivy.Yeung@connectedgroup.com for more details. For other available opportunities, please visit www.connectedgroup.com.", "employment_types": ["Full Time", "Permanent"], "selling_points": ["Qualified CPA member", "All-rounded finance role, FP&A, business analysis", "Excellent communication skills in English"], "locations": ["Not Specified"], "categories": ["Accounting", "Accountant", "Credit Control", "Finance / Accounting Manager"], "post_time": "2022-01-08T02:00:51Z", "salary": {"currency": null, "max": null, "min": null, "period": "monthly", "term": null}, "salary_visible": false, "title_keywords": ["finance manager"], "responsibilities": ["financial reports", "management", "lead a small team", "budget", "systems", "financial analysis", "cash flow", "ad hoc projects", "forecast", "liaise with", "internal control"], "requirements": {"degrees": ["degree", "bachelor"], "majors": ["related disciplines", "finance", "accounting"], "languages": [], "language_level": [], "hard_skills": ["problem-solving skills", "cpa", "excel", "acumen"], "soft_skills": ["detail-minded", "communication", "presentation skills", "problem-solving skills", "strive for excellence"], "languages_combined": []}, "experience_required": {"duration": ["at least 8 years"], "field": ["finance", "relevant experience", "supervisory level", "accounting", "trading"]}}, {"job_id": "100003009019891", "location_code": "hk", "company": "OCBC Wing Hang Credit Limited", "job_title": "Collection Associate - Consumer Loans", "description": "Responsibilities\n\u200bMonitor loans accounts and carry out appropriate actions for delinquent or problematic accounts\nPrepare and check proposals, monitoring reports and statistic reports\nTake legal action against debtors according to instructions from managers and make recommendations / suggestions on actions against debtors\nPrepare relevant documents for legal actions\nAssist managers to monitor overall performance of delinquent accounts and control delinquent ratio\nPerform administrative duties and provide clerical support\nRequirements\n\u200bHigher Diploma or above\nMinimum 2 years\u2019 relevant experience in consumer loans collection\nGood telephone manner, mature and able to work independently\nGood communication skill and emotional control\nGood concept on debt collection\nGood PC skills\n\n\n\nAttractive remuneration package will be offered to the right candidate. Please apply with full resume stating present & expected salary and contact phone number to\u00a0The Human Resources Manager, 10/F, 161 Queen\u2019s Road Central, Hong Kong.\u00a0Please quote the reference.\n\nPersonal data collected will be used for recruitment purpose only. For more information, please visit our website:\u00a0http://www.ocbcwhhk.com.", "employment_types": ["Full Time", "Permanent"], "selling_points": ["Monitor loan accounts", "Carry out actions for delinquent / problematic ac", "Prepare monitoring reports"], "locations": ["Wan Chai"], "categories": ["Accounting", "Credit Control", "Banking / Finance", "Loan", "Credit Collection"], "post_time": "2022-01-04T09:28:56Z", "salary": {"currency": null, "max": null, "min": null, "period": "monthly", "term": null}, "salary_visible": false, "title_keywords": ["associate"], "responsibilities": ["make recommendations", "provide clerical support", "control", "monitoring", "monitor", "assist managers", "reports", "administrative duties"], "requirements": {"degrees": ["diploma or above"], "majors": [], "languages": [], "language_level": [], "hard_skills": ["pc skills"], "soft_skills": ["work independently", "communication skill", "telephone manner", "mature"], "languages_combined": []}, "experience_required": {"duration": ["minimum 2 years"], "field": ["relevant experience"]}}, {"job_id": "100003009030224", "location_code": "hk", "company": "Vickmans Laboratories Ltd", "job_title": "Temporary Account Clerk (3 months)", "description": "Key Roles and Responsibilities\u00a0\n\nResponsible for Accounts duties, including handling daily transactions, data input and processing, compilation of report etc;\nCoordinate with other departments in Accounts issues;\nAssist in handling book-keeping and accounting tasks; &\nAd hoc tasks as assigned.\n\n\u00a0Qualification and Experience\n\nForm 5 or above, with LCCI 2nd Level or above;\nAt least 1-2 year's relevant working experience would be preferable;\nFamiliar with MS Office, especially in excel;\nExperience of working with FLEX Accounting system is a definite advantage; &\nImmediately available is highly preferable.\n\n\n\nHow to Apply\n\nYou are invited to send in your application and CV stating the position you are applying for together with your current and expected salary by clicking the \"apply button\".\n\n\u00a0\nVickmans\u00a0LaboratoriesLimited is an Equal Opportunities Employer. Personal data provided by job applicants will be used strictly in accordance with our personal data policy and for recruitment purposes only. We aim to respond to successful applicants within 8 weeks and related information will be kept in our file for up to 12 months for other suitable vacancies in our organization and thereafter destroyed", "employment_types": ["Temporary"], "selling_points": [], "locations": ["Ngau Tau Kok"], "categories": ["Accounting", "Accountant", "Accounting Clerk / Supervisor", "Credit Control"], "post_time": "2022-01-07T07:00:33Z", "salary": {"currency": null, "max": null, "min": null, "period": null, "term": null}, "salary_visible": false, "title_keywords": ["account clerk"], "responsibilities": ["coordinate with", "data input", "transactions", "ad hoc tasks", "book-keeping", "recruitment", "personal data", "report"], "requirements": {"degrees": ["form 5 or above"], "majors": [], "languages": [], "language_level": [], "hard_skills": ["excel", "flex accounting", "processing", "ms office"], "soft_skills": ["responsible"], "languages_combined": []}, "experience_required": {"duration": ["at least 1-2 year"], "field": ["accounting", "relevant working experience"]}}, {"job_id": "100003009025333", "location_code": "hk", "company": "China Construction Bank (Asia) Corporation Limited", "job_title": "Assistant Officer, Authorization (Credit Card Focus)", "description": "Responsibilities:\n\nDeal with authorization requests related to cardholders up to the credit limit set for purchases and cash advances.\nHandle reporting lost card for VISA, MasterCard and UnionPay Card.\nMonitor account\u2019s activities to detect possible fraud transaction.\nRequirements:\n\nDiploma graduate with minimum 3 years\u2019 relevant experience in credit card authorization field\u00a0\nGood credit sense and sound knowledge of VISA, MasterCard and UnionPay operation.\nBe customer oriented with good negotiation, communication and interpersonal skills.\nWilling to work off-hours / shift duty.\nGood command of written and spoken English and Chinese, preferably proficiency in Putonghua\nKnowledge of PC software application (Word, Excel)", "employment_types": ["Full Time", "Permanent"], "selling_points": ["Credit card authorization & lost reporting", "Fraud transaction monitoring", "3 years\u2019 relevant experience in credit card"], "locations": ["Kowloon Bay"], "categories": ["Accounting", "Credit Control", "Admin & HR", "Administration / Operation Manager", "Banking / Finance", "Credit Collection"], "post_time": "2022-01-06T04:09:56Z", "salary": {"currency": null, "max": null, "min": null, "period": "monthly", "term": null}, "salary_visible": false, "title_keywords": ["assistant officer"], "responsibilities": ["reporting", "monitor"], "requirements": {"degrees": ["diploma"], "majors": [], "languages": ["putonghua", "english", "chinese"], "language_level": ["proficiency", "good command"], "hard_skills": ["pc", "word", "excel"], "soft_skills": ["communication and interpersonal skills", "negotiation"], "languages_combined": [{"language": "putonghua", "language_level": ["proficiency", "good command"]}, {"language": "english", "language_level": ["proficiency", "good command"]}, {"language": "chinese", "language_level": ["proficiency", "good command"]}]}, "experience_required": {"duration": ["minimum 3 years"], "field": ["credit card", "relevant experience"]}}, {"job_id": "100003009015858", "location_code": "hk", "company": "China Mobile International Limited", "job_title": "Senior Accountant, Settlement & Credit Control (6-month renewable contract)", "description": "Responsibilities:\n\n\nPerform customer credit assessment and review company contract to protect customer financial risk\nPrepare monthly AR aging reports, netting reports for collection purpose\nFollow up overdue customers\u2019 payment and work closely with business units and billing team to resolve dispute issues\nSupport monthly closing and regular audit activities\nParticipate in system automation to improve operation efficiency\nSupport the team on ad hoc projects\n\nRequirements:\n\nUniversity Degree or above in Accounting or related disciplines\nQualified Accountant is an advantage\nMinimum 5 years\u2019 accounting experience\nMS office, especially in MS Excel & PowerPoint\nGood communication and interpersonal skills, can work under pressure with tight schedule independently\nGood command of both written and spoken English and Chinese (Cantonese)\nFluent in Mandarin will be an advantage\n\nInterested parties please send your full resume with current & expected salary by clicking \"Apply Now\".\u00a0\u00a0\n\n\u00a0All personal data provided will be used for consideration of your job application only.", "employment_types": ["Full Time", "Temporary", "Contract"], "selling_points": ["Perform credit assessment", "AP, AR, GL, Contract renewal", "HKICPA / ACCA/ CPAA"], "locations": ["Kwai Hing"], "categories": ["Accounting", "Accountant", "Credit Control", "Financial Analyst"], "post_time": "2022-01-03T07:46:04Z", "salary": {"currency": null, "max": null, "min": null, "period": "monthly", "term": null}, "salary_visible": false, "title_keywords": ["senior accountant"], "responsibilities": ["ar", "review", "audit", "payment", "reports", "ad hoc projects", "support the team"], "requirements": {"degrees": ["degree or above"], "majors": ["related disciplines", "accounting"], "languages": ["cantonese", "english", "chinese", "mandarin"], "language_level": ["advantage", "good command", "fluent"], "hard_skills": ["ms excel", "powerpoint", "ms office"], "soft_skills": ["independently", "communication and interpersonal skills", "work under pressure"], "languages_combined": [{"language": "cantonese", "language_level": ["good command"]}, {"language": "english", "language_level": ["good command"]}, {"language": "chinese", "language_level": ["good command"]}, {"language": "mandarin", "language_level": ["fluent", "advantage"]}]}, "experience_required": {"duration": ["minimum 5 years"], "field": ["accounting experience"]}}, {"job_id": "100003009014946", "location_code": "hk", "company": "Manpower Services (Hong Kong) Limited", "job_title": "Financial Assistant/Credit Control Assistant (Electronic Industry) (Up to 16K)", "description": "Job Duties:\n\nHandle company's account issues, pending orders, and invoice discrepancies.\nEnsure the regional order with using correct currency\ncredit investigations, and collection contacts\nCollect outstanding accounts and contact to potential and existing problem accounts\nSolve payment discrepancies and reconcile wire payments\nProvides company credit services\nOther duties as assigned.\n\nRequirements:\n\nHigh Diploma in financial, account or related disciplines\nAt least 1year relevant experience in financial is preferred\nProficiency in MS office skills\nSensitive in number is preferred\nGood communication Skill\nExcellent command of spoken and written English, Cantonese, and Mandarin\nFresh graduate will also be considered", "employment_types": ["Permanent"], "selling_points": ["Fresh graduate will also be considered", "Contact to problem accounts by email", "Provides company credit services"], "locations": ["Kwun Tong"], "categories": ["Accounting", "Credit Control", "Admin & HR", "Clerical / Admin Staff", "Others", "Student / Fresh Graduate / No Experience"], "post_time": "2022-01-03T04:36:16Z", "salary": {"currency": null, "max": null, "min": null, "period": "monthly", "term": null}, "salary_visible": false, "title_keywords": ["assistant"], "responsibilities": ["other duties", "invoice", "payment", "payments", "contact"], "requirements": {"degrees": ["high diploma", "fresh graduate"], "majors": ["related disciplines"], "languages": ["cantonese", "english", "mandarin"], "language_level": ["excellent"], "hard_skills": ["ms office"], "soft_skills": ["communication skill", "sensitive"], "languages_combined": [{"language": "cantonese", "language_level": ["excellent"]}, {"language": "english", "language_level": ["excellent"]}, {"language": "mandarin", "language_level": ["excellent"]}]}, "experience_required": {"duration": [], "field": ["relevant experience", "financial"]}}, {"job_id": "100003009025504", "location_code": "hk", "company": "Ambition", "job_title": "Assistant Accountant (HKD20k, no OT, MNC)", "description": "Our client is a well-established and fast-growing company, which has strong presence within Asia. To facilitate their company growth, they are looking for a Assistant Accountant to join their Finance team.\n\nYou will be responsible for:\n\nResponsible for daily accounting operations, issue invoice and process payment\nPrepare staff expenses reimbursement, pretty cash, etc.\nConduct payment process and prepare bank reconciliation Liaise with vendors and/or relevant departments regarding payment and expense claim\nAssist in month-end closing and prepare relevant schedules\nPrepare bank reconciliations\nSupport in accounting and other ad hoc assignments\n\nTo qualify, individuals must possess:\n\nBachelor's degree in Business Administration or Accounting and Finance or any related disciplines\nAt least 1 year of accounting work experiences\nWilling to learn, good team player, attention to details and good communications\nProficient in written and spoken English and Chinese (Cantonese and Mandarin)\n\nInterested candidates, please submit application with the \"apply now\" button. For a quick application please forward your resume to ariel.chan@ambition.com.hk quoting #245352 Assistant Accountant, MNC no OT\n\n\nIf this job isn't quite right for you, but you know someone who would be great at this role, why not take advantage of our referral scheme? We offer HKD1000 in Apple gift cards for every referred candidate who we place in a role. Terms & Conditions Apply. https://www.ambition.com.hk/refer-a-friend", "employment_types": ["Full Time", "Permanent"], "selling_points": ["AP and AR exposure", "Can sign CPA experiences", "13 months guaranteed salary"], "locations": ["Not Specified"], "categories": ["Accounting", "Accountant", "Audit", "Credit Control"], "post_time": "2022-01-06T04:47:27Z", "salary": {"currency": "HKD", "max": 19999, "min": 14000, "period": "monthly", "term": null}, "salary_visible": true, "title_keywords": ["assistant accountant"], "responsibilities": ["invoice", "schedules", "expenses", "daily accounting operations", "bank reconciliation", "bank reconciliations", "payment", "month-end closing", "finance team", "payment process", "ad hoc assignments", "liaise with", "administration"], "requirements": {"degrees": ["degree", "bachelor"], "majors": ["related disciplines", "finance", "accounting", "business administration"], "languages": ["cantonese", "english", "chinese", "mandarin"], "language_level": ["proficient"], "hard_skills": [], "soft_skills": ["good team player", "willing to learn", "attention to details", "responsible"], "languages_combined": [{"language": "cantonese", "language_level": ["proficient"]}, {"language": "english", "language_level": ["proficient"]}, {"language": "chinese", "language_level": ["proficient"]}, {"language": "mandarin", "language_level": ["proficient"]}]}, "experience_required": {"duration": ["at least 1 year"], "field": ["accounting"]}}, {"job_id": "100003009028309", "location_code": "hk", "company": "Castco Testing Centre Ltd", "job_title": "Accounting Clerk/ Senior Accounting Clerk (Full-time/ 1 Year Contract)", "description": "Responsibilities:\nHandle general accounting duties\nFollow up on receivable collections\nHandle ad hoc assignments as required\nRequirements:\nAt least 1 year accounting working experience is preferred\nCompleted Form 5 or above\nLCC Intermediate or above\nResponsible, self-motivated, well-organized and independent\nHelpful personality with good interpersonal skills\nGood computer skills such as MS Excel, Word and Chinese Word Processing\nImmediately available is preferred\nRenewable contract subject to satisfactory performance\nInterested parties, please send your application together with a detailed resume, stating expected salary by clicking \u201cApply Now\u201d.\n\nCollected application information is used for recruitment purpose only by the Company or its group of companies. Application can be considered unsuccessful if no response is received within 3 months.\n\n", "employment_types": ["Full Time", "Permanent", "Contract"], "selling_points": [], "locations": ["Fanling"], "categories": ["Accounting", "Accounting Clerk / Supervisor", "Credit Control", "Others"], "post_time": "2022-01-07T01:59:42Z", "salary": {"currency": null, "max": null, "min": null, "period": "monthly", "term": null}, "salary_visible": false, "title_keywords": ["accounting clerk"], "responsibilities": ["general accounting duties", "ad hoc assignments"], "requirements": {"degrees": ["form 5 or above"], "majors": [], "languages": ["chinese"], "language_level": ["good"], "hard_skills": ["chinese word processing", "word", "ms excel", "computer skills", "lcc"], "soft_skills": ["self-motivated", "independent", "responsible", "well-organized", "interpersonal skills"], "languages_combined": [{"language": "chinese", "language_level": ["good"]}]}, "experience_required": {"duration": ["at least 1 year"], "field": ["accounting"]}}, {"job_id": "100003009013628", "location_code": "hk", "company": "Vaform (HK) Company", "job_title": "Accountant / Assistant Accountant", "description": "Job Requirements\n\nDegree holder in Accounting Studies\n3-5 years relevant experience in credit control and month-end closing\nSolid experience in the whole cycle of account receivable functions\nPrevious experience in trading or manufacturing company is required\nAble to follow up credit facilities and trading terms with bankers\nGood command of English and fair in spoken Mandarin\nWell-versed in using MS Word, Excel and accounting software\nImmediate available is a definite advantage\n\nJob Responsibilities\n\nAssist in managing the accounting operation and cycle of AR functions\nResponsible for preparing credit analysis reports and settlement schedules\nCommunicate with bankers on credit facilities and trading terms & limits\nEnsure all the trading facilities are in accordance with company guidelines\nSupport on month-end closing and updating accounting data in the system\n\nWe offer attractive career development prospects and excellent fringe benefits to the right candidates. Interested parties please send full resume with date of available, last and expected salary by clicking \u2018Apply Now\u2019", "employment_types": ["Full Time", "Permanent"], "selling_points": [], "locations": ["Not Specified"], "categories": ["Accounting", "Accountant", "Accounting Clerk / Supervisor", "Credit Control"], "post_time": "2022-01-03T03:13:16Z", "salary": {"currency": null, "max": null, "min": null, "period": "monthly", "term": null}, "salary_visible": false, "title_keywords": ["accountant", "assistant accountant"], "responsibilities": ["communicate with", "ar", "data", "analysis reports", "schedules", "company guidelines", "month-end closing"], "requirements": {"degrees": ["degree holder"], "majors": ["accounting"], "languages": ["english", "mandarin"], "language_level": ["good command"], "hard_skills": ["accounting software", "excel", "ms word"], "soft_skills": [], "languages_combined": [{"language": "english", "language_level": ["good command"]}, {"language": "mandarin", "language_level": ["good command"]}]}, "experience_required": {"duration": ["3-5 years"], "field": ["manufacturing", "relevant experience", "trading"]}}, {"job_id": "100003009016821", "location_code": "hk", "company": "Winnitex Limited", "job_title": "Accounts Clerk (Accounts Receivable) \u2013 5 Days Work", "description": "Responsibilities\n\n\n\u00a0Monitoring receivable aging and ensure timely collection of outstanding debts\n\u00a0Ensure timely and efficient resolution of all queries, both internal and external\nPerform day-to-day account receivable and credit control functions\nResponsible for daily accounting routines including data entry and bank receipt operation\n\nRequirements\n\nDiploma in Accounting\n2-3 years of relevant experience\nStrong communication and interpersonal skills\nIndependent, proactive, detail-oriented and able to work under pressure\nGood command of written and spoken of English, Mandarin and Chinese\nProficiency in Microsoft Word and Excel\nImmediate available is highly preferred", "employment_types": ["Full Time"], "selling_points": [], "locations": ["Tsuen Wan Area"], "categories": ["Accounting", "Credit Control"], "post_time": "2022-01-03T09:54:35Z", "salary": {"currency": null, "max": null, "min": null, "period": "monthly", "term": null}, "salary_visible": false, "title_keywords": ["accounts clerk"], "responsibilities": ["control", "data entry", "monitoring", "resolution", "daily accounting"], "requirements": {"degrees": ["diploma"], "majors": ["accounting"], "languages": ["english", "chinese", "mandarin"], "language_level": ["good command"], "hard_skills": ["excel", "microsoft word"], "soft_skills": ["independent", "detail-oriented", "communication and interpersonal skills", "proactive", "work under pressure"], "languages_combined": [{"language": "english", "language_level": ["good command"]}, {"language": "chinese", "language_level": ["good command"]}, {"language": "mandarin", "language_level": ["good command"]}]}, "experience_required": {"duration": ["2-3 years"], "field": ["relevant experience"]}}, {"job_id": "100003009020104", "location_code": "hk", "company": "Hong Kong Science & Technology Parks Corporation", "job_title": "Assistant Manager, Corporate Facilities Management (CFM)  Quality Assurance [JDB/AMCFMQA/220104]", "description": "Responsibilities:\n\nAssures consistent quality of service by developing and enforcing good Facilities Management (FM) and Customer Service (CS) operation manuals, procedures and guidelines (SOP).\nReviews, evaluates, and analyzes complex information for the purpose of ensuring the department meets established quality standards and remains compliant.\nStrictly adhere to and comply with HKSTP Corporate policies, regulations and statutory requirements;\nVerifies accuracy of documents submitted from service providers and CFM colleagues to determine eligibility, and accuracy of reporting according to the HKSTP Corporate Policy and Procedures.\nProvides regular tracking of file submissions and effectively communicates outcomes and findings of case reviews with Internal Audits (IA) and ICAC.\nEffectively manages all CFM caseload and meets established performance targets, while adhering to HKSAR regulatory and statutory requirements with timely follow-up.\nValidate CFM processes and procedures through auditing and quality assurance reviews.\nFacilitate problem-solving discussions with a focus on quality improvement.\nOrganizes data into a logical format for presentation and in written reports as requested by management.\nFacilitate and participate in routine meetings with other staff members and management to discuss the accuracy of report submissions.\nProvide and compile accurate data and information to management for internal use upon request.\nDevelop, track and submit KPI information in management reporting format.\nFormulate strategic improvement plan for the betterment of service level improvements and operational effectiveness of CFM.\nAcquires and maintains up to date trackers for all statutory required licenses and services.\nPerform other duties as assigned by Senior Manager, Associate Director, Director of Corporate Facilities Management and Head of Operations and Leasing.\n\nRequirements:\n\nUniversity degree and above in Building Studies, Property / Facilities Management, Finance, Cost Control or relevant field is preferred;\nMinimum 5 years\u2019 experience working in quality assurance and facilities management or related field;\nExperience in Facilities Management Services operations, and expose to the latest CRM, technology of intelligent building and conversant with FM-Maintenance Management System and related systems and software is preferred;\nCorporate membership of ISO Management System, HKIS, RICS or equivalent is an added advantage;\nProficiency in both written and spoken English and Chinese (including Putonghua);\nExceptionally well organized with an aptitude for data and possess strong analytic skills;\nExcellent communication, planning, organizational, management skills; self-motivated, confident, creative and have a strong desire to achieve excellence;\nExceptional presentation skills, able to explain concepts concisely and accurately;\nStrong interpersonal, creative thinking skills and ability to provide timely solutions to solve issues and problems;\nAble to deal with different levels of internal and external stakeholders.\n\n\n\n\nWe offer market competitive compensation, 5-day work week, and generous benefits including medical and life insurance; and voluntary contribution in addition to the legal minimum MPF. \u00a0To apply, please send your full resume with current and expected salary to the Human Resources & Office Administration Department, Hong Kong Science and Technology Parks Corporation, 5/F, Building 5E, 5 Science Park East Avenue, Hong Kong Science Park, Hong Kong or, by email\u00a0on or before 17 January 2022.\u00a0 \u00a0Please quote the reference number on the email subject/envelope and the application letter.\u00a0\n\nPersonal data provided will be treated in strict confidence and used for recruitment purpose only.\u00a0 All personal data collected will be used strictly in accordance with employer\u2019s personal data policies, you can access to HKSTP\u2019s Personal Information Collection Statement at https://www.hkstp.org/hkstp_web/en/hkstp/personal-information-collection-statement-recruitment\n\nApplicants not invited for interview within four weeks after application deadline may consider their applications unsuccessful.\u00a0 Personal data of unsuccessful applicants will be retained for a maximum of two years.\u00a0\n\nwww.hkstp.org", "employment_types": ["Full Time"], "selling_points": [], "locations": ["Shatin Area"], "categories": ["Accounting", "Credit Control", "Building & Construction", "Building / Construction / QS", "Property / Real Estate", "Property Management"], "post_time": "2022-01-04T09:55:42Z", "salary": {"currency": null, "max": null, "min": null, "period": "monthly", "term": null}, "salary_visible": false, "title_keywords": ["assistant manager,"], "responsibilities": ["regulations", "data", "operations", "quality", "statutory requirements", "customer service", "plan", "perform other duties", "developing", "develop", "reports", "report", "reporting", "management", "procedures", "management reporting", "audits", "tracking", "guidelines", "policies", "auditing"], "requirements": {"degrees": ["university degree"], "majors": ["finance", "building studies"], "languages": ["putonghua", "english", "chinese"], "language_level": ["proficiency"], "hard_skills": ["hkis", "maintenance", "rics", "facilities management", "analytic skills"], "soft_skills": ["confident", "self-motivated", "organizational", "timely", "well organized", "communication", "presentation skills", "creative", "interpersonal"], "languages_combined": [{"language": "putonghua", "language_level": []}, {"language": "english", "language_level": ["proficiency"]}, {"language": "chinese", "language_level": ["proficiency"]}]}, "experience_required": {"duration": ["minimum 5 years"], "field": ["related", "management", "maintenance", "quality assurance"]}}, {"job_id": "100003009027226", "location_code": "hk", "company": "DBS Bank Ltd", "job_title": "VP, Specialist, Credit Risk Management, SME Banking", "description": "Business Function\u00a0\n\nRisk Management Group (RMG) is responsible for the development and maintenance of risk management and internal control frameworks. We provide independent review and challenge to business to ensure that appropriate balance is considered in risk/return decisions. In addition, RMG is responsible for the monitoring and reporting on key risk issues of the Bank. To manage risk effectively and deliver strong financial performance, we invest significantly in our people and infrastructure.\n\nResponsibilities\n\nReview and approve credit applications\nEnsure and maintain good credit quality and data accuracy in credit underwriting process\nEnsure adherence to credit process and regulatory requirement\nWork closely with partners in building, implementing digital lending strategies\nCollaborates with stakeholders to ensure project scope definition meets business objectives\nMaintain and enhance various application service turnaround\n\nRequirement\n\nBachelor Degree or above major in Statistics / Finance / Business Administration\nHolder of Enhanced Competency Framework on\u00a0Credit Risk Management (ECF-CRM) is preferred\nMinimum 10 years on credit underwriting process / risk management / policy formulation in major financial institutions\nProven working experience as credit risk manager\nStrong credit sense and judgment skills with good product knowledge in commercial lending product, additional knowledge on digital lending product, credit modeling is preferred.\nStrong analytical skills with the ability to collect, organize, analyze, and disseminate information with attention to detail and accuracy\nA team player to work with other credit units / other departments in result delivery\nStrong written and verbal communication skills with the ability to present analysis in a succinct manner\n\nApply Now\n\nWe offer a competitive salary and benefits package and the professional advantages of a dynamic environment that supports your development and recognises your achievements.\n\nWe regret only shortlisted candidates will be notified.", "employment_types": ["Full Time"], "selling_points": ["Pension Fund Scheme", "Medical Coverage for Family", "Flexible Working Arrangement"], "locations": ["Others"], "categories": ["Accounting", "Credit Control", "Banking / Finance", "Credit Analysis / Approval", "Credit Collection"], "post_time": "2022-01-06T09:25:41Z", "salary": {"currency": null, "max": null, "min": null, "period": "monthly", "term": null}, "salary_visible": false, "title_keywords": ["specialist", "credit risk management"], "responsibilities": [], "requirements": {"degrees": [], "majors": [], "languages": [], "language_level": [], "hard_skills": [], "soft_skills": [], "languages_combined": []}, "experience_required": {"duration": [], "field": []}}, {"job_id": "100003009027589", "location_code": "hk", "company": "KOS International Limited", "job_title": "Project Manager (HK Residential)", "description": "About our client:\n\nOur client is a leading HK listed property developer focuses on Property development, investment and sales with projects ranging from industrial spaces, residential units, commercial leasing and office rentals to hotels in Hong Kong and China. Due to business expansion plan, there is a hiring needs of Project Manager for Hong Kong team.\n\nAbout your role:\n\n\n\nResponsible for the overall implementation of residential construction projects from land potential feasibility at land bidding stage to completion of construction, coordination for sales launch and estate managements, all aspects during these phases of the projects.\nKey phases including lands rezoning applications; government lands bidding process; consolidate design of the development among professional parties within the Corporate\nEstablish and lead the professional consultancy teams; tender for contractors; supervise statutory submissions and monitor construction progress;\nControl construction programme and budget; coordination for sales launch\nmonitor handover of completed projects and estate maintenance within defects liability period.\n\nRequirement:\n\n\n\nMember of a recognized professional institution in the Architecture industry preferred,\nMinimum 10 years of experience in architects with solid design experience. Strong knowledge in overall design, detailing and use of materials,\nExperience in project and design management, with experiences in architectural office preferred,\nSolid experience in hand sketches and strong in formulating design concepts to project implementation,\nExcellent communication skills with good command of spoken and written English, Chinese\n\nClick \"Apply Now\" to apply for this position or call Jason Li at +852 3180 4962 for a confidential discussion. All information collected will be kept in strict confidence and will be used for recruitment purpose only.", "employment_types": ["Full Time", "Permanent"], "selling_points": ["Newly Created Role", "Rapidly Growing HK based Developer", "HK residential & commercial projects"], "locations": ["Central"], "categories": ["Accounting", "Credit Control", "Building & Construction", "Architectural Services", "Others"], "post_time": "2022-01-06T10:28:31Z", "salary": {"currency": null, "max": null, "min": null, "period": "monthly", "term": null}, "salary_visible": false, "title_keywords": ["project manager"], "responsibilities": ["design concepts", "control", "maintenance", "budget", "teams", "implementation", "design", "monitor", "sketches", "communication", "recruitment", "coordination", "plan", "tender", "design management", "architecture"], "requirements": {"degrees": [], "majors": [], "languages": ["english", "chinese"], "language_level": ["excellent", "good command"], "hard_skills": ["maintenance"], "soft_skills": ["communication skills", "coordination", "confidence", "responsible"], "languages_combined": [{"language": "english", "language_level": ["excellent", "good command"]}, {"language": "chinese", "language_level": ["excellent", "good command"]}]}, "experience_required": {"duration": ["minimum 10 years"], "field": ["management", "design"]}}, {"job_id": "100003009016055", "location_code": "hk", "company": "ADECCO", "job_title": "Billing Officer $16K-$18K", "description": "Our client is the leading on-demand storage company. They are looking a Billing Officer to support their team.\n\nResponsibilities:\n\n\nCarry out billing and collection functions\nEnsure bill payment records are updated to the system timely and accurately\nProcess and verify billing data and monthly invoices\nSupport supervisor to maintain billing records and reporting\nRespond to client queries concerning billing\n\nRequirements:\n\nDiploma / Higher Diploma holder\nMinimum 1 year of solid experience in billing management / AR collections\nGood interpersonal and communication skills\nExcellent in accounting system and MS Office, including MS Word and Excel\n\nWorking Location: Kwai Chung\n\nWork Schedule: 9:00-18:30 (5-Day roster work from Monday to Saturday, WFH on Saturday if needed)\n\nInterested parties, please apply\u00a0Click Here\u00a0online. Please note that only short listed candidates will be notified. All information gathered will be treated in strict confidence and solely used for recruitment purposes.", "employment_types": ["Full Time"], "selling_points": ["1 year contract renewable", "5-day work (Mon-Sat roster), WFH support on Sat", "$16K-$18K"], "locations": ["Kwai Hing"], "categories": ["Accounting", "Accounting Clerk / Supervisor", "Credit Control", "Others"], "post_time": "2022-01-03T08:13:36Z", "salary": {"currency": null, "max": null, "min": null, "period": "monthly", "term": null}, "salary_visible": false, "title_keywords": ["billing officer"], "responsibilities": ["reporting", "invoices", "data", "payment", "maintain"], "requirements": {"degrees": ["diploma", "higher diploma holder"], "majors": [], "languages": [], "language_level": [], "hard_skills": ["excel", "ar", "accounting system", "ms office", "ms word"], "soft_skills": ["communication skills", "interpersonal"], "languages_combined": []}, "experience_required": {"duration": ["minimum 1 year"], "field": ["billing", "management"]}}, {"job_id": "100003009020395", "location_code": "hk", "company": "China Everbright Bank Company Limited", "job_title": "Manager, Credit Risk", "description": "Job Responsibilities:\nDevelop and maintain MIS for credit control and monitoring;\nMonitor internal and external credit information system to track any negative information on existing customers, and prepare \u201cAlert\u201d report accordingly;\u00a0\u00a0\nPrepare the daily collateral monitoring reports and annual/quarterly review list;\nMaintain filing system to ensure all credit review documents are properly filed and recorded;\nHandle credit administration and the post loan-drawdown monitoring and control work;\nPrepare and compile various credit control and monitoring reports, and ensure it is implemented in accordance with the Bank's prevailing credit strategy, policy and procedure;\nPerform ad hoc assignment as and when required by Senior Management.\nJob Requirements:\nDegree holder in Business, Banking, Finance or related disciplines;\nMinimum 5 years of relevant experiences in credit risk management,preferably have system development and credit control experience with reputable banks;\nRelevant experience in Chinese Bank is a plus;\nFamiliar with PRC laws and regulations;\nHand-on experience in system development;\nAnalytical, detailed-oriented , strong numerical and business sense;\nGood communication and interpersonal skills;\nAble to work independently and as part of a team;\nProficient in written and spoken English and Chinese (including Putonghua).\nInterested candidates please apply in full resume with earliest availability, contact number, current & expected salary to HR Department by email.\n\n\nPersonal data provided will be used for recruitment and related purposes, strictly in accordance with our Personal Data Policy for Applicants for Employment, a copy of which is available on request. Applicants who are not contacted within 6 weeks may consider your applications unsuccessful and the personal data collected will be destroyed after six months.", "employment_types": ["Full Time"], "selling_points": ["Develop and maintain MIS for credit control", "Prepare the daily collateral monitoring reports", "Minimum 5 years of relevant experiences"], "locations": ["Admiralty"], "categories": ["Accounting", "Credit Control", "Banking / Finance", "Credit Analysis / Approval", "Risk Management"], "post_time": "2022-01-04T10:51:19Z", "salary": {"currency": null, "max": null, "min": null, "period": "monthly", "term": null}, "salary_visible": false, "title_keywords": ["manager"], "responsibilities": ["administration", "control", "ad hoc assignment", "monitoring", "monitor", "review", "develop", "maintain", "reports", "senior management", "report"], "requirements": {"degrees": ["degree holder"], "majors": ["related disciplines", "finance", "business"], "languages": ["putonghua", "english", "chinese"], "language_level": ["proficient"], "hard_skills": ["plus"], "soft_skills": ["work independently", "communication and interpersonal skills", "business sense", "detailed"], "languages_combined": [{"language": "putonghua", "language_level": ["proficient"]}, {"language": "english", "language_level": ["proficient"]}, {"language": "chinese", "language_level": ["proficient"]}]}, "experience_required": {"duration": ["minimum 5 years"], "field": ["management", "relevant experience", "credit risk", "system development"]}}, {"job_id": "100003009024093", "location_code": "hk", "company": "David James Recruitment Limited", "job_title": "Billing Assistant \u2013 Int\u2019 Law Firm ($15 \u2013 20K)", "description": "Representing a reputable international law firm, we are seeking a Billing Assistant to join their Accounting and Finance Team.\n\nResponsibilities:\n\nWork closely with internal stakeholders to create invoices and ensure the billing information is accurate and on-time\nHandle billing enquiries and follow up on outstanding invoices\nPrepare bill, WIP and relevant reports \u00a0\nPerform ad hoc duties when required \u00a0\nCandidates with more experience will be considered as Assistant Billing Officer\n\nRequirements:\n\n1 year+ experience in handling billing matters, experience from law firm is an advantage\nFamiliar with Elite/Aderant billing system\nGood command of written and spoken English and Chinese\nA good team player with good presentation and time management skills\n\nTo Apply\n\nInterested parties please send us your updated resume with your latest and expected salaries or please call +852 3611 7880 for a confidential discussion.", "employment_types": ["Full Time", "Permanent"], "selling_points": ["Handle Billing matters", "Stable working environment", "Attractive Remuneration Package"], "locations": ["Wan Chai"], "categories": ["Accounting", "Accounting Clerk / Supervisor", "Credit Control", "Professional Services", "Legal & Compliance"], "post_time": "2022-01-05T10:39:07Z", "salary": {"currency": null, "max": null, "min": null, "period": "monthly", "term": null}, "salary_visible": false, "title_keywords": ["assistant"], "responsibilities": ["ad hoc duties", "relevant reports", "invoices"], "requirements": {"degrees": [], "majors": [], "languages": ["english", "chinese"], "language_level": ["good command"], "hard_skills": ["billing system"], "soft_skills": ["time management skills", "good team player", "presentation"], "languages_combined": [{"language": "english", "language_level": ["good command"]}, {"language": "chinese", "language_level": ["good command"]}]}, "experience_required": {"duration": [], "field": ["billing"]}}, {"job_id": "100003009027232", "location_code": "hk", "company": "DBS Bank Ltd", "job_title": "VP, Team Lead, Credit Risk Management, Consumer Banking", "description": "Business Function\u00a0\n\nRisk Management Group (RMG) is responsible for the development and maintenance of risk management and internal control frameworks. We provide independent review and challenge to business to ensure that appropriate balance is considered in risk/return decisions. In addition, RMG is responsible for the monitoring and reporting on key risk issues of the Bank. To manage risk effectively and deliver strong financial performance, we invest significantly in our people and infrastructure.\n\nResponsibilities\n\nDevelop resource plan and streamline operating process and procedure to maintain and enhance various application turnaround\nMonitor quality control report to improve credit quality and data accuracy in credit approval process\nAssess and approve new secured / unsecured product applications, portfolio credit limit management and recommend deviation in credit underwriting process\nCoordinate and conduct UAT test for system / project development\nEnhance existing risk governance framework such as improving quality assurance framework and monitoring critical trigger.\nEnsure and maintain good credit quality and data accuracy in credit underwriting process\nMaintain and enhance various application service turnaround\n\nRequirement\n\nBachelor Degree or above major in Statistics / Finance / Business Administration\nMinimum 12 years on credit underwriting process / risk management / policy formulation in major financial institutions\nProven working experience as credit underwriting manager or credit risk manager\nStrong credit sense and judgment skills with good product knowledge in consumer lending product, with additional knowledge on investment lending product is preferred.\nStrong analytical skills with the ability to collect, organize, analyze, and disseminate information with attention to detail and accuracy\nA team player to work with other credit units / other departments in result delivery\n\nApply Now\n\nWe offer a competitive salary and benefits package and the professional advantages of a dynamic environment that supports your development and recognises your achievements.\n\nWe regret only shortlisted candidates will be notified.", "employment_types": ["Full Time"], "selling_points": ["Pension Fund Scheme", "Medical Coverage for Family", "Extra Day Off"], "locations": ["Quarry Bay"], "categories": ["Accounting", "Credit Control", "Banking / Finance", "Credit Analysis / Approval", "Credit Collection"], "post_time": "2022-01-06T09:26:01Z", "salary": {"currency": null, "max": null, "min": null, "period": "monthly", "term": null}, "salary_visible": false, "title_keywords": ["credit risk management", "lead"], "responsibilities": [], "requirements": {"degrees": [], "majors": [], "languages": [], "language_level": [], "hard_skills": [], "soft_skills": [], "languages_combined": []}, "experience_required": {"duration": [], "field": []}}, {"job_id": "100003009023650", "location_code": "hk", "company": "CNPC Finance (HK) Limited", "job_title": "Risk Management Officer", "description": "Responsibilities\n\nPerform risk assessment on credit proposals submitted by front line, exercise credit judgment and make credit recommendations\nEnsure all internal credit policies and procedures are aligned with regulatory requirements\nAssist in preparing credit reports / proposal to management\nPrepare reports for credit committee\nReview and design credit control framework\n\nRequirements\n\nBachelor or above in Risk Management, Business Administration, Finance, Economics, Accountancy, or related disciplines\nAt least 1 years or above experience in credit risk management or corporate credit approval\nSound understanding of the risk issues across a wide variety of corporations, industries, and regions.\nExcellent analytical, communications and interpersonal skill\nGood command of both written and spoken English and Chinese. Proficient in Mandarin will an advantage\nGood at using MS Word, Excel and PowerPoint", "employment_types": ["Full Time"], "selling_points": [], "locations": ["Wan Chai"], "categories": ["Accounting", "Credit Control", "Banking / Finance", "Corporate Finance", "E-commerce", "Product Management / Business Analyst"], "post_time": "2022-01-05T09:22:27Z", "salary": {"currency": null, "max": null, "min": null, "period": "monthly", "term": null}, "salary_visible": false, "title_keywords": ["risk management officer"], "responsibilities": ["management", "control", "policies", "regulatory requirements", "review", "procedures", "design", "reports", "prepare reports"], "requirements": {"degrees": ["bachelor"], "majors": ["risk management", "business administration", "finance", "economics", "accountancy", "related disciplines"], "languages": ["english", "chinese", "mandarin"], "language_level": ["advantage", "good command", "proficient"], "hard_skills": ["excel", "powerpoint", "ms word"], "soft_skills": ["interpersonal skill"], "languages_combined": [{"language": "english", "language_level": ["good command"]}, {"language": "chinese", "language_level": ["good command"]}, {"language": "mandarin", "language_level": ["proficient", "advantage"]}]}, "experience_required": {"duration": ["at least 1 years"], "field": ["management", "credit risk"]}}, {"job_id": "100003009003026", "location_code": "hk", "company": "Alcon Hong Kong, Limited", "job_title": "AR Collection Officer (12-month contract)", "description": "Job Responsibilities\n\nOn-site collection and follow up payback to ensure that all AR is acknowledged by customer and paid on time;\nPrepare invoice, account statement and supporting documents and deliver to customer in an efficient and timely way;\nProvide accurate matching of AR collection with invoice for AR clearing;\nReport any bad debt or credit risk noticed;\nOther ad hoc task as required.\n\n\u00a0Job Requirements\n\nHigher certificate or Diploma in Accounting, Finance, Business Administration, Commerce or equivalent\nGood command of English and Chinese (including Putonghua)\n3 years' experience in similar position\nWith on-site collection and retail industry experience preferred\nGood communication and problem solving skills\n\nRemuneration package will be commensurate with qualifications and experience.\u00a0 Interested parties please send your application with full resume together with your expected salary to Human Resources Department by clicking \"APPLY NOW\".\u00a0", "employment_types": ["Full Time", "Contract"], "selling_points": ["5-day work week", "Competitive Salary", "Medical Insurance"], "locations": ["Quarry Bay"], "categories": ["Accounting", "Accountant", "Credit Control", "Banking / Finance", "Credit Collection"], "post_time": "2021-12-28T07:59:26Z", "salary": {"currency": null, "max": null, "min": null, "period": "monthly", "term": null}, "salary_visible": false, "title_keywords": ["officer"], "responsibilities": ["invoice", "ad hoc", "ar", "report"], "requirements": {"degrees": ["diploma", "higher certificate"], "majors": ["finance", "accounting", "business administration"], "languages": ["putonghua", "english", "chinese"], "language_level": ["good command"], "hard_skills": ["problem solving skills"], "soft_skills": ["communication", "problem solving skills"], "languages_combined": [{"language": "putonghua", "language_level": ["good command"]}, {"language": "english", "language_level": ["good command"]}, {"language": "chinese", "language_level": ["good command"]}]}, "experience_required": {"duration": ["3 years"], "field": ["retail industry"]}}, {"job_id": "100003009019371", "location_code": "hk", "company": "Mott MacDonald Hong Kong Limited", "job_title": "Account Assistant / Graduate", "description": "Your Next Challenge\n\nBeing a member of Central Finance team, and under training and supervision of assigned line manager,\n\nHandle overall accounts receivable & payable\nJournal posting and bank reconciliation\nMaintain proper records and books of account in compliance with prevailing Accounting Standards, Company policies and procedures\nAssist in monthly review (and year-end statutory audit) including preparation of supporting schedules and annual tax filing.\nAssist in the annual budget, forecasts and ad hoc reports as assigned\nWhat You'll Need\nDegree in Accounting equivalent education\nHave good analytical and communication skills in both English & Chinese.\nA team player, proactive and highly motivated\nDetailed mind and able to work in a fast pace environment\nWe offer competitive remuneration package including MPF plan, group medical insurance for dependents and 13th month salary.\u00a0\n\n\nInterested parties, please click 'Apply now' to submit your application with full resume including your current and expected salary, or send your full resume to MMHK_Finance@ mottmac.com.\n\nTo explore more opportunities with us, please visit www.mottmac.com/careers.\n\nAll personal data collected will be treated in strict confidence and be used for recruitment purpose only.\u00a0\n\nWe are an equal opportunity employer and value diversity at our company. We do not discriminate, and take positive steps to create an inclusive culture.", "employment_types": ["Full Time", "Permanent"], "selling_points": ["MNC, regional multi-country accouting exposure", "All round training to meet chartership requirement", "5 days\u2019 work, 13 month salary"], "locations": ["Kwun Tong Area"], "categories": ["Accounting", "Accounting Clerk / Supervisor", "Credit Control", "Banking / Finance", "Corporate Finance"], "post_time": "2022-01-04T07:30:25Z", "salary": {"currency": null, "max": null, "min": null, "period": "monthly", "term": null}, "salary_visible": false, "title_keywords": ["account assistant"], "responsibilities": ["year-end", "ad hoc", "accounts receivable", "policies", "compliance", "procedures", "bank reconciliation", "review", "audit", "tax filing", "budget", "supporting schedules", "communication", "reports", "finance team", "maintain proper records"], "requirements": {"degrees": ["degree"], "majors": ["accounting"], "languages": ["english", "chinese"], "language_level": ["good"], "hard_skills": [], "soft_skills": ["communication skills", "motivated", "team player", "proactive", "detailed mind"], "languages_combined": [{"language": "english", "language_level": ["good"]}, {"language": "chinese", "language_level": ["good"]}]}, "experience_required": {"duration": [], "field": []}}, {"job_id": "100003009019391", "location_code": "hk", "company": "Mott MacDonald Hong Kong Limited", "job_title": "Finance Assistant - Account Payable (Part time / 6 months contract)", "description": "Job Highlights\n\nAP focused regional role\nSupportive working culture\nJob Descriptions\n\nPerform accounts payable daily operation\nInput supplier invoices, check coding and approvals in compliance with company\u2019s policies and procedures\nHandle other ad-hoc tasks when required\nRequirements\nDegree or Diploma in Accountancy or related discipline (Fresh Graduate are welcome)\nExperience in handling high volume of payable transactions\nStrong sense of responsibility, detail-minded, good work attitude, and able to meet tight deadline\u00a0\nGood command in spoken and written English and Cantonese\nImmediately available is highly preferred\nInterested parties, please click 'Apply now' to submit your application with full resume including your current and expected salary, or send your full resume to MMHK_Finance@ mottmac.com.\n\n\nTo explore more opportunities with us, please visit www.mottmac.com/careers.\n\nAll personal data collected will be treated in strict confidence and be used for recruitment purpose only.\u00a0\n\nWe are an equal opportunity employer and value diversity at our company. We do not discriminate, and take positive steps to create an inclusive culture.", "employment_types": ["Part Time", "Temporary", "Contract"], "selling_points": ["Well establish MNC, regional exposure", "Fresh graduate and part time is welcomed", "Perform accounts payable daily operation"], "locations": ["Kwun Tong Area"], "categories": ["Accounting", "Accounting Clerk / Supervisor", "Credit Control", "Banking / Finance", "Corporate Finance"], "post_time": "2022-01-04T07:31:58Z", "salary": {"currency": null, "max": null, "min": null, "period": "monthly", "term": null}, "salary_visible": false, "title_keywords": ["finance assistant"], "responsibilities": ["invoices", "policies", "ad-hoc tasks", "compliance", "daily operation", "procedures", "coding", "accounts payable"], "requirements": {"degrees": ["diploma", "degree", "fresh graduate"], "majors": ["accountancy"], "languages": ["cantonese", "english"], "language_level": ["good command"], "hard_skills": [], "soft_skills": ["detail-minded", "meet tight deadline", "sense of responsibility"], "languages_combined": [{"language": "cantonese", "language_level": ["good command"]}, {"language": "english", "language_level": ["good command"]}]}, "experience_required": {"duration": [], "field": []}}, {"job_id": "100003009003584", "location_code": "hk", "company": "Arrow Asia Pac Ltd", "job_title": "Senior Credit Analyst/ Assistant Credit Manager", "description": "What You\u2019ll Be Doing\n\nManage Credit analysis & evaluations and handle Credit release for Greater China business\nSupport customer data maintenance in system\nPrepare month-end closing & inter-company reconciliations on AR module\nPrepare regular reports, involving in collection matters and some management reports\nAssist in Ad-hoc projects as required\n\n\u00a0What We Are Looking For\n\nBachelor\u2019s degree or above in Accounting, Finance or related.\nAt least 5 years of experience in handling AR collection, reporting, credit evaluation and administration including L/C matters\nGood command in spoken Cantonese, Mandarin and written English is preferred\nResult-oriented, detail-minded, proactive, and committed team player\nCandidates with less experience will be considered as Credit Analyst\n\nWhat\u2019s In It For You\nAt Arrow, we recognize that financial rewards and great benefits are important aspects of an ideal job. That\u2019s why we offer competitive financial compensation, including various compensation plans, and a solid benefits package.\n\nDouble Pay\nPerformance Bonus\nMedical & Dental\nLife Insurance\nMPF with additional employer contributions\nPaid Time Off\nFree Shuttle to HKSTP Office\n5-Day Work Week\nGrowth Opportunities\nAnd More!", "employment_types": ["Full Time", "Permanent"], "selling_points": ["Credit Analysis & Assessment", "Fortune 102 company", "Candidates with less experience will be considered"], "locations": ["Shatin Area"], "categories": ["Accounting", "Credit Control", "Banking / Finance", "Credit Analysis / Approval", "Risk Management"], "post_time": "2021-12-28T09:39:01Z", "salary": {"currency": null, "max": null, "min": null, "period": "monthly", "term": null}, "salary_visible": false, "title_keywords": ["manager", "assistant", "credit analyst"], "responsibilities": ["reporting", "evaluation", "ar", "maintenance", "analysis", "reconciliations", "management reports", "month-end closing", "reports", "customer data", "ad-hoc projects", "administration"], "requirements": {"degrees": ["degree or above", "bachelor"], "majors": ["finance", "accounting"], "languages": ["cantonese", "english", "mandarin"], "language_level": ["good command"], "hard_skills": ["ar", "maintenance", "management reports", "c", "credit analysis"], "soft_skills": ["detail-minded", "committed", "team player", "proactive", "result-oriented"], "languages_combined": [{"language": "cantonese", "language_level": ["good command"]}, {"language": "english", "language_level": ["good command"]}, {"language": "mandarin", "language_level": ["good command"]}]}, "experience_required": {"duration": ["at least 5 years"], "field": ["administration"]}}, {"job_id": "100003009015230", "location_code": "hk", "company": "ConnectedGroup Limited", "job_title": "Finance Manager,", "description": "Finance Manager\n\nOur client is an international trading company. They are now looking for an all-rounded and detail-minded Finance manager, directly report to the CFO.\n\nQualified CPA member\nAll-rounded finance role, FP&A, business analysis\nExcellent communication skills in English\n\nResponsibilities:\n\nLead a small team to provide financial reports, including monthly accounts, annual budget, and quarterly forecast on a timely and accurate basis\nProvide insightful financial analysis on business performance to support management decisions and business growth\nManage cash flow, treasury, and funds arrangement\nLiaise with bankers and auditors on all finance and accounting related matters\nKeep reviewing and strengthening ERP and internal control systems\nPerform other ad hoc projects and assignment\n\nRequirements:\n\nBachelor's degree in Finance & Accounting or related disciplines with CPA qualification\nAt least 8 years relevant experience in accounting and finance field with at least 2years in supervisory level, preferably with trading/ sourcing background\nStrong business and financial acumen with excellent problem-solving skills\nSmart, detail-minded with an ambition to strive for excellence\nExcellent communication and presentation skills\nProficient in Excel skills and with exposure in financial models\n\nInterested parties, please send your CV to Ivy Yeung Ivy.Yeung@connectedgroup.com for more details. For other available opportunities, please visit www.connectedgroup.com.", "employment_types": ["Full Time", "Permanent"], "selling_points": ["Qualified CPA member", "All-rounded finance role, FP&A, business analysis", "Excellent communication skills in English"], "locations": ["Not Specified"], "categories": ["Accounting", "Accountant", "Credit Control", "Finance / Accounting Manager"], "post_time": "2022-01-03T06:12:55Z", "salary": {"currency": null, "max": null, "min": null, "period": "monthly", "term": null}, "salary_visible": false, "title_keywords": ["finance manager"], "responsibilities": ["financial reports", "management", "lead a small team", "budget", "systems", "financial analysis", "cash flow", "ad hoc projects", "forecast", "liaise with", "internal control"], "requirements": {"degrees": ["degree", "bachelor"], "majors": ["related disciplines", "finance", "accounting"], "languages": [], "language_level": [], "hard_skills": ["problem-solving skills", "cpa", "excel", "acumen"], "soft_skills": ["detail-minded", "communication", "presentation skills", "problem-solving skills", "strive for excellence"], "languages_combined": []}, "experience_required": {"duration": ["at least 8 years"], "field": ["finance", "relevant experience", "supervisory level", "accounting", "trading"]}}, {"job_id": "100003009002247", "location_code": "hk", "company": "Ambition", "job_title": "Credit Controller (International law firm)", "description": "Our client is international law firm with great culture and benefits. To cope with their recent business expansion, they are now looking for a Credit Controller to join their Hong Kong Finance team:\n\nReport to Finance manger in HK, you are responsible for:\n\nResponsible for credit control services and make sure its comply with the firm's payment terms and policy\nPerform Debt collection activities, aging report and credit management\nRegular communication with matter partners / managers and local finance team on debts status\nAd hoc work as required\n\nRequirements:\n\nDegree in Accounting or Finance or related disciplines\nAt least 2 years of experience in credit control or accounts receivable\nExcellent communication skills and attention to details\nGood command of English and Chinese (Cantonese and Mandarin)\n\nPlease contact Ariel Chan at (852) 3103 4336 or ariel.chan@ambition.com.hk click APPLY NOW quoting reference number #250105 - Credit Controller (International law firm). For more information, please visit http://www.ambition.com.hk\n\nIf this job isn't quite right for you, but you know someone who would be great at this role, why not take advantage of our referral scheme? We offer HKD1000 in Apple gift cards for every referred candidate who we place in a role. Terms & Conditions Apply. https://www.ambition.com.hk/refer-a-friend", "employment_types": ["Full Time", "Permanent"], "selling_points": ["International law firm", "Young and energetic team", "2 years AR experiences"], "locations": ["Not Specified"], "categories": ["Accounting", "Accountant", "Accounting Clerk / Supervisor", "Credit Control"], "post_time": "2021-12-28T04:18:51Z", "salary": {"currency": "HKD", "max": 24999, "min": 20000, "period": "monthly", "term": null}, "salary_visible": true, "title_keywords": [], "responsibilities": [], "requirements": {"degrees": [], "majors": [], "languages": [], "language_level": [], "hard_skills": [], "soft_skills": [], "languages_combined": []}, "experience_required": {"duration": [], "field": []}}, {"job_id": "100003009013290", "location_code": "hk", "company": "Dongxing Securities (Hong Kong) Financial Holdings Limited", "job_title": "Risk Control \u2013 Associate/Senior Associate Level", "description": "Job Description\n\nSet up and implement an appropriate risk control framework for the company's investment portfolio (including FICC, equity, etc.)\nPerform day-to-day risk management of FICC, equity, analyze large P/L events VaR movement, ensure limits are well monitored and properly reported, identify material risks and propose risk mitigations\nCreate and produce/automate risk monitoring reports (daily, monthly) with a number of risk management measures including performance and attribution analysis, concentration analysis, etc. on regular basis\nAssist in reviewing the risk control terms of structured products\n\nRequirement\n\nMaster degree or above with minimum 2 years working experience in market risk function in asecurity house, bank or other relevant financial institution\nBackground in Science/Mathematics/Financial Engineering/Risk Management, FRM/CFA is a plus\nA solid understanding of market risk parameters and product knowledge (e.g. FICC/structured product)\nGood written and communication skills in Mandarin is a must\nProficient in the use of related systems and software, such as Bloomberg, Wind, can use VBA, Python is preferred", "employment_types": ["Full Time", "Permanent"], "selling_points": ["Degree holder or above", "Minimum of 2 years", "Excellent communication and interpersonal skills"], "locations": ["Others"], "categories": ["Accounting", "Credit Control", "Banking / Finance", "Credit Analysis / Approval", "Risk Management"], "post_time": "2022-01-03T01:59:17Z", "salary": {"currency": null, "max": null, "min": null, "period": "monthly", "term": null}, "salary_visible": false, "title_keywords": ["senior associate", "associate"], "responsibilities": ["control", "management", "analysis", "risk monitoring", "reports"], "requirements": {"degrees": ["degree or above", "master"], "majors": [], "languages": ["mandarin"], "language_level": ["good"], "hard_skills": ["vba", "plus", "bloomberg", "cfa", "python", "frm"], "soft_skills": ["communication skills", "structured"], "languages_combined": [{"language": "mandarin", "language_level": ["good"]}]}, "experience_required": {"duration": ["minimum 2 years"], "field": ["market risk", "financial"]}}]