[{"job_id": "100003009052550", "location_code": "hk", "company": "The Luxe Manor", "job_title": "Financial Controller / Assistant Financial Controller", "description": "Responsibilities:\nOversee the finance and accounting functions\n\nHandle all aspects of financial controls, reviews and planning\n\nCompile financial budget and perform operational and costing analysis\n\nHighlight and investigate significant issues of operating units, make recommendations on corrective measures\n\nConduct independent review and evaluations of operating units\u2019 financial / operational policies and procedures for the purpose of improving the efficiency and effectiveness\n\nEnforce internal control systems to ensure that the assets, revenues and costs are under effective control\n\nImplement cost effective control policies and procedures, ensure that the internal control systems operate properly and comply with Group and Company policies\n\nRequirements:\nDegree holder in Accounting / Finance or equivalent and with a recognized accounting qualification, preferable ACCA/HKICPA/AICPA\n\nMinimum 10 years\u2019 managerial experience in financial control function in sizable organization and accounting experience in HK listed or multinational corporations\n\nStrong business sense, proven management, analytical and leadership skills\n\nExcellent interpersonal and communication skills and ability to collaborate with all departments in an organization\n\nGood understanding of HK & China accounting rules and regulations\n\nFamiliar with HK & China operations in finance, taxation and audit\n\nSolid hotel experience\n\nInterested parties please send your detailed resume with current and expected salary by clicking Apply Now.\n\nAll applications will be handled in the strictest confidence and personal data collected will be used for recruitment purposes only. Applicants not invited for an interview within 6 weeks may consider their applications unsuccessful. Applicant contact details will be held for 6 months, from the date of application.", "employment_types": ["Full Time"], "selling_points": ["Compile financial budget", "Enforce internal control systems", "Minimum 10 years\u2019 relevant experience"], "locations": ["Not Specified"], "categories": ["Accounting", "Finance / Accounting Manager", "Financial Controller"], "post_time": "2022-01-17T03:24:03Z", "salary": {"currency": null, "max": null, "min": null, "period": "monthly", "term": null}, "salary_visible": false, "title_keywords": ["assistant financial controller", "financial controller"], "responsibilities": ["make recommendations", "control", "cost", "policies", "review", "budget", "procedures", "systems", "costing analysis", "internal control", "costs", "planning"], "requirements": {"degrees": ["degree holder"], "majors": ["finance", "accounting"], "languages": [], "language_level": [], "hard_skills": ["acca", "hkicpa"], "soft_skills": ["communication skills", "leadership skills", "interpersonal", "business sense"], "languages_combined": []}, "experience_required": {"duration": ["minimum 10 years"], "field": ["sizable organization", "managerial", "accounting experience", "financial"]}}, {"job_id": "100003009054922", "location_code": "hk", "company": "Sun Hung Kai Properties Ltd", "job_title": "FINANCIAL CONTROLLER \u2013 HOTEL DIVISION", "description": "Requirements:\n\n\nBachelor\u2019s degree holder, with CPA or other professional qualification in accounting. Prior working experience in audit preferred\nAt least 15 years\u2019 working experience, including relevant experience as Director of Finance in sizable hotels with extensive F&B and other facilites\nSolid working experience for hotels in Hong Kong and mainland China\nStrong analytical skills, good business acumen and ownership perspective\nBe resilient and able to cope with high work pressure and demanding deadlines\nHighly motivated, detail-minded and result oriented with multi-tasking skills\nProactive and a good team player\nGood communication and interpersonal skills\nProficient in both spoken and written English and Chinese\n\nResponsibilities:\n\n\nResponsible for the overall accounting and financial review matters, including reporting and analysis of the portfolio hotels in Hong Kong and mainland China\nWorking closely with headquarter corporate offices and finance teams of portfolio hotels\nProvide consolidated management reports and analysis with value-added views on business and good interpretation of financial data\nPerform regular reviews on financial controls\n\nGood remuneration and attractive fringe benefits will be offered to the successful applicant. Interested parties please apply with full resume, present and expected salary, available date by clicking \u201cApply Now\u201d.\n\nFor further information, please visit our company website: http://www.shkp.com/.\n\nWe are an equal opportunity employer and welcome applications from all qualified candidates. All personal data collected will be used for recruitment purpose only.\u00a0 Applicants not hearing from us within 3 months may consider their applications unsuccessful.\u00a0 All personal data collected will be destroyed within 24 months.", "employment_types": ["Full Time", "Permanent"], "selling_points": ["Bachelor degree with CPA qualification", "Exp as Director of Finance in sizable hotels", "Accounting & financial review of HK & PRC hotels"], "locations": ["Wan Chai"], "categories": ["Accounting", "Finance / Accounting Manager", "Financial Analyst", "Financial Controller"], "post_time": "2022-01-17T14:01:55Z", "salary": {"currency": null, "max": null, "min": null, "period": null, "term": null}, "salary_visible": false, "title_keywords": ["financial controller"], "responsibilities": ["reporting", "data", "analysis", "review", "teams", "management reports"], "requirements": {"degrees": ["bachelor", "degree holder"], "majors": ["accounting"], "languages": ["english", "chinese"], "language_level": ["proficient"], "hard_skills": ["cpa", "acumen", "analytical skills"], "soft_skills": ["detail-minded", "good team player", "multi-tasking skills", "analytical skills", "result oriented", "motivated", "communication and interpersonal skills", "business acumen", "proactive", "extensive"], "languages_combined": [{"language": "english", "language_level": ["proficient"]}, {"language": "chinese", "language_level": ["proficient"]}]}, "experience_required": {"duration": ["at least 15 years"], "field": ["finance", "audit", "f&b", "relevant experience", "hotels"]}}, {"job_id": "100003009047593", "location_code": "hk", "company": "Hong Huan Group Limited", "job_title": "Financial Controller", "description": "Responsibilities\n\nDevelop and oversee the finance & accounting functions in collaboration with Business Units and head office\nProviding accounting and financial insights to improve operational efficiency\nReporting to CFO, involve in strategic planning with top management related with all accounting and finance functions\nDevise the finance related policies complying to all applicable laws and regulations for the group\nOffer financial advice to management in corporate finance exercises such as M&A, investments etc.\nOn-going review of portfolio companies financial planning, reporting, forecast and budgeting activities\nEnsure timely and accurate preparation and submission of monthly financial and management reports for management review and for group consolidation and reporting purpose\nProvide business advice for process improvement, taxation and corporate governance\n\nRequirements\nQualified accountant with a degree or above in Accounting or Finance or related discipline\nMinimum of 15 years working experience includes proven track record at a senior management level\nAbility to consult and advise operating and corporate leaders on issues related to accounting, financial reporting, internal control and regulatory issues\nStrong leadership skills with high level of self-motivation and initiative\nProven analytical, organizational and problem-solving skills\nStrong interpersonal and communication skills, both verbal and written in English, Cantonese and Mandarin\nSuperior organizational skills and the ability to prioritize in a dynamic working environment\nPossess good communication, interpersonal and stakeholder management skills\nDemonstrate strong business acumen\nInterested parties please send full resume with current and expected salary by clicking the \"APPLY NOW\" button below.\nAll information provided by applicants will be treated in strict confidence and used only for recruitment purposes. Applicants may be considered for other suitable positions by our Company & the subsidiaries over not more than 6 months, after which their personal data will be destroyed.", "employment_types": ["Full Time", "Permanent"], "selling_points": [], "locations": ["Ngau Tau Kok"], "categories": ["Accounting", "Chief Accountant", "Financial Analyst", "Financial Controller"], "post_time": "2022-01-14T03:32:00Z", "salary": {"currency": null, "max": null, "min": null, "period": "monthly", "term": null}, "salary_visible": false, "title_keywords": ["financial controller"], "responsibilities": ["regulations", "reporting", "management", "taxation", "strategic planning", "policies", "budgeting", "review", "develop", "management reports", "forecast", "management review", "planning"], "requirements": {"degrees": ["degree or above"], "majors": ["finance", "accounting"], "languages": ["cantonese", "english", "mandarin"], "language_level": [], "hard_skills": ["problem-solving skills", "dynamic", "acumen", "internal control"], "soft_skills": ["communication skills", "organizational skills", "organizational", "leadership skills", "prioritize", "communication", "self-motivation", "dynamic", "business acumen", "problem-solving skills", "interpersonal", "initiative", "superior"], "languages_combined": [{"language": "cantonese", "language_level": []}, {"language": "english", "language_level": []}, {"language": "mandarin", "language_level": []}]}, "experience_required": {"duration": ["minimum of 15 years"], "field": ["management"]}}, {"job_id": "100003009050044", "location_code": "hk", "company": "Summergate Limited", "job_title": "Finance Manager / Assistant Controller", "description": "Reporting to Financial Controller, you will lead a finance team to cover all financial functions in HK and MC, and you\u2019ll also need to work collaboratively with people across the business at all levels.\n\nKEY RESPONSIBILITIES\n\nOverseeing all finance, accounting, tax, treasury, and company secretarial matters for Summergate HK and MC entities.\nFull responsibility for balance sheet control and reconciliations to ensure integrity of financial and accounting information.\nEnsure timely and accurate closing and reporting to head quarter.\nLead the relations with auditors, tax agents, and other external parties to manage statutory obligations for the entities.\nLead the finance team to manage day-to-day operations and finance administrative issues.\nDrive and deliver continuous improvement initiatives across end-to-end business processes, systems and reporting to align head quarter guidance and controls.\nAssist in yearly budget process for HKMC entities, and coordinate with the FP&A team in head quarter to provide business analysis to local business partners.\nMonitor and manage cash flow projections for HKMC entities, and ensure controls over fund transfers and cash management.\nLead, train, and coach the team members to build and maintain a sustainable team to support the local business.\nPerform other ad-hoc projects/assignments as required.\n\nKEY COMPETENCIES / EXPERIENCE\u00a0\n\nMinimum 8 years+ in finance accounting , with above 2-3 years\u2019 experience in managing full-scope finance functions in MNC or sizable local corporations;\nCA/CPA qualification preferred.\nExperience with JDE or Dynamic 365 highly advantageous;\nExperience in a big-4 or other accounting firm desirable;\nStrong leadership with the ability to drive and execute improvements;\nStrong inter-personal and communication skills with good command in written and spoken English. Chinese not essential but advantageous.\nCan-do attitude with strong sense of ownership.\nSelf-motivated and able to work under pressure;\nAbility to be hands on where necessary;", "employment_types": ["Full Time", "Permanent"], "selling_points": [], "locations": ["Lai Chi Kok"], "categories": ["Accounting", "Finance / Accounting Manager", "Financial Controller"], "post_time": "2022-01-14T09:41:00Z", "salary": {"currency": null, "max": null, "min": null, "period": "monthly", "term": null}, "salary_visible": false, "title_keywords": ["finance manager", "assistant"], "responsibilities": ["external parties", "day-to-day operations", "budget", "communication", "maintain", "ad-hoc projects", "work under pressure", "control", "monitor", "finance team", "balance sheet", "reporting", "guidance", "management", "coordinate with", "reconciliations", "cash flow", "tax", "systems", "business analysis"], "requirements": {"degrees": [], "majors": [], "languages": ["english", "chinese"], "language_level": ["good command"], "hard_skills": ["cpa", "analysis", "dynamic"], "soft_skills": ["communication skills", "self-motivated", "inter-personal", "can-do attitude", "timely", "integrity", "dynamic", "hands on", "accurate", "leadership", "work under pressure"], "languages_combined": [{"language": "english", "language_level": ["good command"]}, {"language": "chinese", "language_level": []}]}, "experience_required": {"duration": ["2-3 years"], "field": ["finance", "accounting"]}}, {"job_id": "100003009049547", "location_code": "hk", "company": "Thornstone Professional Services Limited", "job_title": "Financial Controller - Listed Company", "description": "Our Client is a listed food company in Hong Kong, to cope with their fast expansion, they are currently seeking a Financial Controller cum Company Secretary to join their team.\n\n\n\nResponsibilities:\n\nOversee and manage the whole finance, accounting and taxation functions\u00a0in HK\nEnsure all accounting procedures comply with the internal policy and legal compliance\nAdvise the Board on appropriate financial policies and strategies in order to achieve the organization\u2019s mission and objectives.\nPrepare monthly financial reports and consolidated management reports\nPrepare budget & forecast, raise out any potential variances\nLiaise with auditors and other professionals in annual audit, tax and company\u00a0secretarial filing\nImproving efficiencies and reducing costs across the business\nAd hoc projects and assignments\n\n\u00a0Requirements:\n\nDegree holder in Accounting, Finance or a related discipline\nQualified Accountant and memberof HKICPA, ACCA, CPAA\nAt least 10 years of accounting experience in listed companies with all rounded and hands on operation accounting background preferably with company secretary knowledge\nGood knowledge of Hong Kong listing rules, Hong Kong tax regulations policies and accounting system\nFMCG, manufacturing or food industry experience is preferable\nStrong command of languages (English, Cantonese and Mandarin)\nAdaptable, demonstrate strong leadership and able to communicate well with different level of colleagues", "employment_types": ["Full Time"], "selling_points": ["Listed Company", "Excellent Exposure", "Stable Environment"], "locations": ["Not Specified"], "categories": ["Accounting", "Finance / Accounting Manager", "Financial Controller", "Professional Services", "Company Secretary"], "post_time": "2022-01-14T08:51:55Z", "salary": {"currency": null, "max": null, "min": null, "period": "monthly", "term": null}, "salary_visible": false, "title_keywords": ["financial controller"], "responsibilities": ["tax", "taxation", "financial reports", "annual audit", "financial policies", "compliance", "procedures", "budget", "management reports", "ad hoc projects", "forecast", "liaise with", "costs"], "requirements": {"degrees": ["degree holder"], "majors": ["finance", "accounting"], "languages": ["cantonese", "english", "mandarin"], "language_level": [], "hard_skills": ["acca", "accounting system", "hkicpa"], "soft_skills": ["adaptable", "hands on", "leadership"], "languages_combined": [{"language": "cantonese", "language_level": []}, {"language": "english", "language_level": []}, {"language": "mandarin", "language_level": []}]}, "experience_required": {"duration": ["at least 10 years"], "field": ["manufacturing", "fmcg", "accounting experience", "food industry", "operation", "accounting"]}}, {"job_id": "100003009053700", "location_code": "hk", "company": "PwC", "job_title": "Manager - Finance Practice Support - PwC Tax - Hong Kong", "description": "Duties\n\nAssist in preparing and reviewing financial management and statistics reports\nPerform analytical review on financial results\nPerform data quality review on Tax systems\nCarry out monthly actions to improve financial management\nAssist in financial projects and ad-hoc assignments\nAssist in financial reports automation\nManage database / systems\nCo-ordinate with departments, e.g., GTS, Central FIN, Client First team, etc. on Tax finance matters\n\n\u00a0Requirements\n\nBachelor degree in any discipline\nMinimum 5 years\u2019 experience in Finance in MNC or professional services firm is preferred\nGood logical and analytical skill\nGood coordination, interpersonal and problem-solving skills\nGood project management skill\nAble to manage multiple tasks under deadlines while maintaining quality of work delivered\nAble to communicate with impact to peer groups, leaders and stakeholders\nAble to maintain good relationship with teammates and users\nDemonstrate creativity and able to contribute new ideas and knowledge where appropriate\nOpen minded, agile with change and practical\nCommitted to self-development and coaching of others for growth\nProficient in MS Office, especially in MS Excel & PowerPoint.\u00a0 Experience in using Outlook and technology tools such as Alteryx and Power BI, is a desirable\nGood in both spoken and written English and Chinese", "employment_types": ["Full Time", "Permanent"], "selling_points": ["Financial Management for Tax Practice", "ex-Professional Staff welcome", "Urgent Hire"], "locations": ["Central"], "categories": ["Accounting", "Finance / Accounting Manager", "Financial Controller"], "post_time": "2022-01-17T07:22:26Z", "salary": {"currency": null, "max": null, "min": null, "period": "monthly", "term": null}, "salary_visible": false, "title_keywords": ["manager"], "responsibilities": ["tax", "management", "financial reports", "data", "co-ordinate with", "ad-hoc assignments", "review", "quality", "systems", "reports", "database"], "requirements": {"degrees": ["degree", "bachelor"], "majors": [], "languages": ["english", "chinese"], "language_level": ["good"], "hard_skills": ["analytical skill", "bi", "agile", "powerpoint", "project management", "ms excel", "outlook", "alteryx", "problem-solving skills", "ms office"], "soft_skills": ["analytical skill", "agile", "multiple tasks", "committed", "open minded", "coordination", "project management skill", "problem-solving skills", "interpersonal"], "languages_combined": [{"language": "english", "language_level": ["good"]}, {"language": "chinese", "language_level": ["good"]}]}, "experience_required": {"duration": ["minimum 5 years"], "field": ["finance"]}}, {"job_id": "100003009048137", "location_code": "hk", "company": "Amazin Consultants Limited", "job_title": "Financial Controller and Company Secretary (Circa$800K p.a)", "description": "Our client is a reputable listed company with business in food retail, manufacturing and trading.\u00a0 They are inviting an experienced financial controller to lead the finance team.\n\n\n\nResponsibilities:\n\nOversee and manage the whole finance, accounting\u00a0and taxation functions\u00a0in Hong Kong.\nEnsure all accounting procedures comply with the internal policy and legal compliance\nAdvise Board on appropriate financial policies and strategies in order to achieve the organization\u2019s mission and objectives.\nHandle company secretarial duties and liaise with 3rd parties such as lawyer, SFC authorities, bankers etc. as necessary.\nPrepare monthly financial reports and consolidated management reports.\nPrepare budget & forecast, raise out any potential variances.\nLiaise with auditors and other professionals in annual audit, tax and company\u00a0secretarial filing.\nImproving efficiencies and reducing costs across the business.\u00a0\n\nRequirements:\n\nDegree holder in Accounting, Finance\u00a0or a related discipline\nQualified Accountant\u00a0and member\u00a0of HKICPA, ACCA, CPAA.\nAssociate member of ACS, ACIS preferred but not a must.\nAt least 5 years of accounting experience\u00a0in listed companies\u00a0with all rounded and hands-on operation accounting background.\nGood knowledge of Hong Kong listing rules, Hong Kong tax regulations policies and accounting system\nFMCG, manufacturing\u00a0or trading industry experience is an advantage.\nProficient in Cantonese, Mandarin and English.\nImmediate available is an advantage.\n\n\u00a0For interested parties, please send your full resume\u00a0 to\u00a0resume@ amazinhr.com\n\nPersonal information is collected and used for the purposes of recruitment only. We use your personal information to contact you for the position you apply and/or for the vacancy that matches with your profile.", "employment_types": ["Full Time", "Permanent"], "selling_points": ["Expanding listed company with established brand", "Finance and named company secretary role", "Work-life balance environment"], "locations": ["Others"], "categories": ["Accounting", "Finance / Accounting Manager", "Financial Controller"], "post_time": "2022-01-14T05:12:14Z", "salary": {"currency": "HKD", "max": 69999, "min": 55000, "period": "monthly", "term": null}, "salary_visible": true, "title_keywords": ["company secretary", "financial controller"], "responsibilities": ["tax", "taxation", "financial reports", "annual audit", "financial policies", "compliance", "procedures", "budget", "management reports", "forecast", "liaise with", "costs"], "requirements": {"degrees": ["degree holder"], "majors": ["finance", "accounting"], "languages": ["cantonese", "english", "mandarin"], "language_level": ["proficient"], "hard_skills": ["acca", "accounting system", "hkicpa"], "soft_skills": ["hands-on"], "languages_combined": [{"language": "cantonese", "language_level": ["proficient"]}, {"language": "english", "language_level": ["proficient"]}, {"language": "mandarin", "language_level": ["proficient"]}]}, "experience_required": {"duration": ["at least 5 years"], "field": ["manufacturing", "fmcg", "accounting experience", "operation", "accounting", "trading"]}}, {"job_id": "100003009050240", "location_code": "hk", "company": "Robert Walters (HK)", "job_title": "Finance Manager/ Financial Controller (Open to Big4 M level)", "description": "It is a HK main board listed company. This role reports to the chairman directly.\n\nJob Responsibilities:\n\nEnsure proper and consistent consolidated financial reporting standard compile with listing rules requirement\nReview the monthly consolidated management account package and commentary for Board reference Oversee and coordinate the annual budget process of the group\nOversee and coordinate the group annual audit, tax and company secretarial filling\nReview and liaise legal advice and support on major contracts at corporate level\nLiaise with banks on investment financing\nMange the cashflow and investment portfolios\n\nJob Requirements:\n\nQualified Accountant and degree holder in accounting or related discipline\nBig 4 trained candidate with minimum 8 years of working experience\nFamiliar with listing rules\nGood command of written and spoken in English, Mandarin and Cantonese", "employment_types": ["Full Time", "Permanent"], "selling_points": ["Main board listed", "Stable working environment", "Familiar with listing rules"], "locations": ["Not Specified"], "categories": ["Accounting", "Financial Controller"], "post_time": "2022-01-14T10:00:04Z", "salary": {"currency": null, "max": null, "min": null, "period": "monthly", "term": null}, "salary_visible": false, "title_keywords": ["finance manager", "financial controller"], "responsibilities": ["tax", "liaise", "management", "annual audit", "contracts", "review", "budget", "investment portfolios", "coordinate", "financial reporting", "liaise with", "listing"], "requirements": {"degrees": ["degree holder"], "majors": ["accounting"], "languages": ["cantonese", "english", "mandarin"], "language_level": ["good command"], "hard_skills": [], "soft_skills": [], "languages_combined": [{"language": "cantonese", "language_level": ["good command"]}, {"language": "english", "language_level": ["good command"]}, {"language": "mandarin", "language_level": ["good command"]}]}, "experience_required": {"duration": ["minimum 8 years"], "field": ["big 4"]}}, {"job_id": "100003009054928", "location_code": "hk", "company": "Pure Search International Limited", "job_title": "Senior Accounting Manager / Accounting Manager", "description": "Our Client\nA renowned Multi-National Corporation (MNC) with an industry-leading portfolio of consumer brands. With innovative go-to market strategies and after sales services in their distributor business model, they are continuing their expansion plans across Asia Pacific (APAC) and Hong Kong.\u00a0 They are now seeking for a Senior Accounting Manager / Accounting Manager to join its Finance team in Hong Kong.\n\nJob Description\nReporting to the Financial Controller, you will be managing an outsourced accounting service provider, take ownership of reporting, full set of accounts, such as Account Receivable, Accounts Payables, General Ledger etc. You will ensure books are closed properly and prepare meaningful reports to senior management for decision making. You will manage cashflow and ensure cash position of the company is maintained at a good level. You will work closely with the team and advise them on any new accounting standards, its implications to the business and any compliance issues. You will also be involved in ad hoc projects when needed.\n\nJob Requirements\nYou should have at least 10 years Accounting & Finance experience gained in sizable Multi National Corporations (MNCs). Prior experience working in Big 4 CPA firm or 2nd Tier CPA firm is a must. You should have strong communication and influencing skills, and be able to manage a sizeable team. Comfortable to day to day English Communication & Presentation is a must. Proficiency in English and Chinese is essential. Can-do Attitude is highly preferred.\n\n", "employment_types": ["Full Time"], "selling_points": ["HK$55,000 - 68,000 per month", "Renowned Consumer Business", "MNC culture"], "locations": ["Not Specified"], "categories": ["Accounting", "Chief Accountant", "Finance / Accounting Manager", "Financial Controller"], "post_time": "2022-01-17T14:11:21Z", "salary": {"currency": null, "max": null, "min": null, "period": "monthly", "term": null}, "salary_visible": false, "title_keywords": ["accounting manager"], "responsibilities": ["reporting", "general ledger", "full set of accounts", "compliance", "reports", "ad hoc projects", "accounting service", "senior management"], "requirements": {"degrees": [], "majors": [], "languages": ["english", "chinese"], "language_level": ["proficiency"], "hard_skills": ["cpa"], "soft_skills": ["communication", "presentation", "can-do attitude"], "languages_combined": [{"language": "english", "language_level": ["proficiency"]}, {"language": "chinese", "language_level": ["proficiency"]}]}, "experience_required": {"duration": ["at least 10 years"], "field": ["finance", "accounting", "cpa firm", "big 4"]}}, {"job_id": "100003009043137", "location_code": "hk", "company": "Ever Good Industries (International) Limited", "job_title": "Financial Controller and Company Secretary", "description": "Job Duties:\n\nReporting to CEO and directors, involve in strategic planning with top management related with all accounting and finance functions\nOn-going review of portfolio companies financial planning, reporting, forecast and budgeting activities\nResponsible for information disclosure of a Hong Kong main board listed company, including draft or review announcements, circulars, financial statements, interim and annual reports etc;\nMaintain effective interfaces with external parties including auditors, lawyers, government authorities, banks, and regulators such as SEHK and SFC\nAssist on the Company internal and external audit and ad hoc assignments as well as execute follow-up actions on audit findings including any irregularities or incidents\nManage cashflow and investment portfolio\nManage the budgeting and forecasting;\nActing as the named company secretary\n\nRequirements\uff1a\n\nA qualified accountant (HKICPA/ACCA) with a degree in Accounting, Finance or related discipline\nAt least 10 years of accounting experience\u00a0in listed companies\u00a0with all rounded and hands on operation accounting background preferably with company secretary knowledge\nCompany secretarial experiences in HK listed companies is essential\nA proactive and responsible candidate with excellent ethical standards\nConfidence and proven ability to present financial information and influence decision making\nProficiency in Hong Kong accounting standards, taxation and listing rules\u00a0\nKnowledge in China accounting, taxation, laws and regulations\n\u00a0Fluent in English, Cantonese and Mandarin\nImmediate availability preferred\n\nInterested parties, please send a detailed resume including the cover letter, the latest and expected salary and date of availability to the Human Resources Department by clicking \"APPLY NOW\".\n\n(Personal information collected\u00a0for recruitment purpose only)", "employment_types": ["Full Time"], "selling_points": [], "locations": ["Hung Hom"], "categories": ["Accounting", "Financial Controller"], "post_time": "2022-01-12T10:12:00Z", "salary": {"currency": null, "max": null, "min": null, "period": "monthly", "term": null}, "salary_visible": false, "title_keywords": ["company secretary", "financial controller"], "responsibilities": ["reporting", "management", "irregularities", "strategic planning", "budgeting", "review", "external parties", "audit", "financial statements", "maintain", "reports", "ad hoc assignments", "forecast", "forecasting", "planning"], "requirements": {"degrees": ["degree"], "majors": ["finance", "accounting"], "languages": ["cantonese", "english", "mandarin"], "language_level": ["fluent"], "hard_skills": ["acca", "hkicpa"], "soft_skills": ["confidence", "responsible", "hands on", "ethical", "proactive", "decision making"], "languages_combined": [{"language": "cantonese", "language_level": ["fluent"]}, {"language": "english", "language_level": ["fluent"]}, {"language": "mandarin", "language_level": ["fluent"]}]}, "experience_required": {"duration": ["at least 10 years"], "field": ["accounting experience", "operation", "accounting", "secretarial"]}}, {"job_id": "100003009043736", "location_code": "hk", "company": "KeeReal Consulting Limited", "job_title": "Finance Manager / Financial Controller (Private Equity & Venture Capital | Attractive Package)", "description": "Our client is a fast glowing private equity & venture capital company with regional offices. They are currently looking for a Finance Manager / Financial Controller (Private Equity & Venture Capital | Attractive Package) in the Hong Kong office to join their Finance dynamic team.\n\nResponsibilities:\nPrepare and review NAV, reconciliation on daily basis and monitor cash activity of the funds\nManage full set of fund accounting, reconciliation, and compliance duties\nPrepare and review internal and external reports for the funds' investors and other stakeholders\nResponsible for capital calls and review waterfall calculation\nPlan, implement and review the financial strategies of the corporation including budgeting, financing, taxation handling and compliance\nPrepare cash flow projection and forecasting for\u00a0 the corporation\nCoordinate SFC regulated activities for the licensed corporation and associated entities\nSupport management in key strategic initiatives and business improvement projects\nAny other ad hoc assignments assigned by the management team\nRequirements:\n\nDegree holder or above\u00a0in Accounting or Finance is required\nCPA qualified holder\nStrong understanding of regulations especially SFO\nAt least 5 years of experience in Fund Accounting\nStrong oral and written communication skills in English and Chinese", "employment_types": ["Full Time", "Permanent"], "selling_points": ["8 years of FI experience", "Attractive remuneration package", "Private Equity & Venture Capital"], "locations": ["Not Specified"], "categories": ["Accounting", "Financial Controller", "Banking / Finance", "Financial Services", "Fund Management"], "post_time": "2022-01-13T01:43:40Z", "salary": {"currency": null, "max": null, "min": null, "period": "monthly", "term": null}, "salary_visible": false, "title_keywords": ["finance manager", "financial controller"], "responsibilities": ["taxation", "management", "management team", "budgeting", "compliance", "review", "monitor", "coordinate", "cash flow", "reports", "ad hoc assignments", "plan", "forecasting"], "requirements": {"degrees": ["degree holder"], "majors": ["finance", "accounting"], "languages": ["english", "chinese"], "language_level": [], "hard_skills": ["cpa", "sfo"], "soft_skills": ["communication skills", "oral"], "languages_combined": [{"language": "english", "language_level": []}, {"language": "chinese", "language_level": []}]}, "experience_required": {"duration": ["at least 5 years"], "field": ["accounting"]}}, {"job_id": "100003009046429", "location_code": "hk", "company": "Michael Page", "job_title": "Financial Controller - HK Listed Co", "description": "Financial leadership opportunity\nCorporate Finance and Strategy focused\n\nClient Details\n\nOur client is a listed retail company with strong presence in PRC. In contributing to the market growth and business strategy, they are looking for a high calibre candidate to join their management as a Financial Controller.\n\nDescription\n\nDevelop and oversee the finance & accounting functions in collaboration with regional and head offices\nProvide supervision over the finance and accounting team\nDevise the finance related policies complying to all applicable laws and regulations for the group\nDemonstrate leadership and drive the upgrade of the current reporting work flow, processes and procedures, and any other matters to optimise the operational effectiveness and efficiency\nConstantly review the designed process, system and procedures to avoid any possible business and financial risks\nAct as a key business partner with the senior management and executive in offering strategic and financial insights and recommendations for business management and decision\nOffer financial advice to management in corporate finance exercises such as M&A, investments etc.\n\nProfile\n\nQualified accountant with a degree or above in Accounting or Finance or related discipline\nMinimum of 15 years working experience includes proven track record at a senior management level\nMandatory BIG 4 training with experience at corporate level with HK listed companies\nStrong knowledge with listing compliance and statutory requirements\nPossess good communication, interpersonal and stakeholder management skills\nDemonstrate strong business acumen\nGood command of spoken and written English, Cantonese and Mandarin\n\nJob Offer\n\nAttractive remuneration package\nstable work environment\nOffice location: Central\nSenior leadership position\nRenowned and long standing brand - market leader\n\nTo apply online please click the 'Apply' button below. For a confidential discussion about this role please contact Yamen Cheung on +852 2848 9575.", "employment_types": ["Full Time", "Permanent"], "selling_points": ["Business partnering and startegy focused", "Senior position in the leadership team", "Regional exposure"], "locations": ["Not Specified"], "categories": ["Accounting", "Finance / Accounting Manager", "Financial Controller", "Treasurer"], "post_time": "2022-01-13T11:05:52Z", "salary": {"currency": null, "max": null, "min": null, "period": "monthly", "term": null}, "salary_visible": false, "title_keywords": ["financial controller"], "responsibilities": ["regulations", "reporting", "management", "policies", "review", "procedures", "compliance", "provide supervision", "develop", "communication", "statutory requirements", "contact", "senior management", "listing"], "requirements": {"degrees": ["degree or above"], "majors": ["finance", "accounting"], "languages": ["cantonese", "english", "mandarin"], "language_level": ["good command"], "hard_skills": ["business management", "acumen"], "soft_skills": ["focused", "communication", "business acumen", "stable", "leadership", "interpersonal"], "languages_combined": [{"language": "cantonese", "language_level": ["good command"]}, {"language": "english", "language_level": ["good command"]}, {"language": "mandarin", "language_level": ["good command"]}]}, "experience_required": {"duration": ["minimum of 15 years"], "field": ["management", "training", "big 4"]}}, {"job_id": "100003009050202", "location_code": "hk", "company": "Robert Walters (HK)", "job_title": "Regional Finance Controller (FMCG/ retail/ F&B)", "description": "My client is an US based FMCG company. They are looking for a Regional Finance Controller for their new business line due to expansion. It is a new headcount reports to the US headquarter directly.\n\nJob Responsibilities:\n\nAs part of the start-up team, the role will serve as the bridge between the local Asia offices in Asia and the headquarter in US\nReview and consolidate the financial packs submitted by local finance teams\nEnsure the monthly reporting in the Group system is submitted timely and accurately\nConsistently improve and monitor the financial processes and internal control procedures are put in place and comply with group requirements\nEnsure that Group financial policies are put in place and implemented across all APAC countries\nManage statutory accounting, reporting and submission process for all legal entities in the region and ensure timely, accurate and correct submission\nProvide support and coaching to country finance team members\nParticipate in and drive global finance projects and initiatives\n\nJob Requirements:\n\nBachelor degree holder in accounting or related discipline, qualified accountant\nMinimum 8 years of relevant working experience with regional exposure, ideally with big4 background\nRelevant experience in retail/ FMCG/ F&B industry will be added advantage\nTechnically strong in IFRS, ideal to have knowledge in US GAAP\nExerience in system implementation/ process improvements is highly preferred\nStrong communication skills and able to work under multi-tasking environment\nDetail-minded and self-driven with strong project management skill", "employment_types": ["Full Time", "Permanent"], "selling_points": ["New headcount, part of the setup team", "Finance controllership role for Asia", "MNC working environment- energetic and fun"], "locations": ["Not Specified"], "categories": ["Accounting", "Finance / Accounting Manager", "Financial Controller"], "post_time": "2022-01-14T09:56:03Z", "salary": {"currency": null, "max": null, "min": null, "period": "monthly", "term": null}, "salary_visible": false, "title_keywords": [], "responsibilities": ["reporting", "provide support", "review", "monitor", "teams", "procedures", "financial policies", "finance team", "internal control"], "requirements": {"degrees": ["bachelor degree holder"], "majors": ["accounting"], "languages": [], "language_level": [], "hard_skills": ["system implementation", "project management", "ifrs"], "soft_skills": ["detail-minded", "communication skills", "multi-tasking", "project management skill", "driven", "ideal"], "languages_combined": []}, "experience_required": {"duration": ["minimum 8 years"], "field": ["fmcg", "relevant working experience", "f&b", "relevant experience", "retail"]}}, {"job_id": "100003009043981", "location_code": "hk", "company": "Peninsula Merchandising Limited", "job_title": "Director of Finance", "description": "Reporting to General Manager,\u00a0you will\u00a0lead and drive the financial performance of the Company with sound financial acumen and accuracy, and to lead and manage all matters related to legal, compliance, insurance and IT of PML to ensure compliance to regulatory requirements and proper internal control is in place. You will also be part of the Executive Committee\u00a0of the Company to\u00a0develop and drive business strategies, including but not limited to the 5-year/10-year\u00a0growth and development plans.\u00a0Please find the details below:\n\nExceptional market leading benefits such as comprehensive family medical insurance (including dependents), 17 paid statutory holidays,\u00a020 vacation days and\u00a03 days paid carers leave.\n\nKey Responsibilities:\n\nLead, build & develop the Accounting, Quality Assurance and IT team; retain and develop talent to cope with business\u2019s requirements; manage performance issues and recognize good performance.\nCreate and execute business plan and 5-/10-year-plan for the current and new business units.\nDrive financial planning and analysis by leading budgeting & forecasting exercises and cash flow management, address financial issues and risks with advising feasible solutions.\nLead Monthly Business review process to drive performance against plan and identify opportunities to improve profitability; ensure all financial reports are prepared in an accurate and timely manner in accordance with accounting standards (HK GAAP), statutory requirements and Head Office requirements.\nOversee internal and external audit activities and local and overseas taxation of the company.\nManage all compliance matters and insurances of the company to comply with all local and overseas regulatory requirements and to minimize the company\u2019s risk, maintain and record all contracts, leases & tenancy agreements, licenses, insurance policies and all legal and financial documents.\u00a0\nEstablish, review, and execute policies & procedures of finance, QA and IT to ensure compliance to both Group\u2019s and legal requirements, and meet the business needs.\nProvide advice to continuously improve operational efficiencies with proper internal control across Finance and other functions of the company.\nManage Quality Assurance function to optimize vendor\u2019s performance and minimize the risks on product quality.\nLead IT functions to drive efficiency on IT tools, software, infrastructure; drive IT projects to meet business needs; optimize IT security as per Group\u2019s requirements; drive system upgrades and investments to improve operational efficiency.\n\nRequirements:\n\nMinimum of 12 years of related experience, with at least 4 years in team head.\nExperience in IT project management and business process transformation are must.\nExperience in retail or FMCG industry is an advantage.\nDegree holder in Financial Management / Accounting Management or related disciplines.\nHKICPA or equivalent or with proper accounting qualifications.\nStrong analytical, communications and leadership skills.\nStrategic thinking, ability to develop business plan, strong finance acumen. \u00a0\nProficiency in spoken and written English and Chinese is essential.\nWelcome candidates who are currently in associate director or financial controller position, with meeting the requirements above.\n\nWe are delighted to receive your application for further consideration. Click apply now with your latest CV and salary information.\n\n\n\nPersonal data collected will be used for recruitment purposes only and may be retained for up to 2 years as per our Job Candidacy Privacy Notice listed on our company website.", "employment_types": ["Full Time", "Permanent"], "selling_points": ["Join a highly prestigious retail brand", "At least 12 years of relevant experience", "Competitive benefits with family medical coverage"], "locations": ["Tsim Sha Tsui"], "categories": ["Accounting", "Financial Controller", "Others", "Information Technology (IT)", "IT Management"], "post_time": "2022-01-13T02:40:13Z", "salary": {"currency": null, "max": null, "min": null, "period": "monthly", "term": null}, "salary_visible": false, "title_keywords": ["director"], "responsibilities": ["software", "budgeting", "regulatory requirements", "quality", "audit", "statutory requirements", "maintain", "plan", "internal control", "contracts", "compliance", "infrastructure", "develop", "business plan", "forecasting", "management", "upgrades", "review", "procedures", "cash flow", "insurances", "taxation", "financial reports", "policies", "analysis", "ensure compliance", "provide advice", "insurance", "planning"], "requirements": {"degrees": ["degree holder"], "majors": ["related disciplines", "accounting"], "languages": ["english", "chinese"], "language_level": ["proficiency"], "hard_skills": ["project management", "fmcg industry", "acumen", "hkicpa"], "soft_skills": ["project management", "leadership skills", "strategic thinking"], "languages_combined": [{"language": "english", "language_level": ["proficiency"]}, {"language": "chinese", "language_level": ["proficiency"]}]}, "experience_required": {"duration": ["at least 4 years", "minimum of 12 years"], "field": ["fmcg", "related", "project management", "it", "business", "retail", "team"]}}, {"job_id": "100003009048910", "location_code": "hk", "company": "Kingsway Personnel Ltd", "job_title": "\u65e5\u672c\u8a9e\u30cd\u30a4\u30c6\u30a3\u30d6\u7d4c\u7406\u8ca1\u52d9\u30de\u30cd\u30fc\u30b8\u30e3\u30fc ~$45K\uff08\u7d4c\u9a13\u306b\u3088\u308b\uff09", "description": "Reference No.: NR09559\nNature of Business: Medical Services co.\nLocation: T.S.T\nWorking Days: 5 Days\n\nBenefits:\n- Medical Insurance\n- \u4ea4\u901a\u8cbb\u652f\u7d66\n- \u6709\u7d66\u521d\u5e74\u5ea610\u65e5\n\nResponsibilities:\n- \u7d4c\u7406\u8ca1\u52d9\u696d\u52d9\u5168\u822c\n- \u30b9\u30bf\u30c3\u30d5\u7ba1\u7406\n- \u5404\u7a2e\u30ec\u30dd\u30fc\u30c8\u4f5c\u6210\n- \u6d77\u5916\u652f\u5e97\u306e\u8ca1\u52d9\u7ba1\u7406\u3068\u30ea\u30b9\u30af\u7ba1\u7406\n\nRequirement:\n- \u8ca1\u52d9\u30fb\u4f1a\u8a08\u7d4c\u9a1310\u5e74\u4ee5\u4e0a\n- \u65e5\u672c\u8a9e\u30cd\u30a4\u30c6\u30a3\u30d6\u30ec\u30d9\u30eb\u3001\u30d3\u30b8\u30cd\u30b9\u30ec\u30d9\u30eb\u4ee5\u4e0a\u306e\u82f1\u8a9e\n- \u00a0Peachtree\u306a\u3069\u4f1a\u8a08\u30b7\u30b9\u30c6\u30e0\u4f7f\u7528\u7d4c\u9a13\u306e\u6709\u308b\u65b9\u6b53\u8fce\n- \u6771\u5357\u30a2\u30b8\u30a2\u3084\u5317\u7c73\u306e\u8ca1\u52d9\u4f1a\u8a08\u77e5\u8b58\u304c\u3042\u308c\u3070\u5c1a\u826f\u3044\n- \u7d4c\u9a13\u306b\u5fdc\u3058\u3066VISA\u5bfe\u5fdc\u53ef\u80fd\n\n\n\nInterested in the above vacancy?\u00a0 Send your resume to us NOW!\nOnly short-listed candidates will be notified. Personal data collected will be used for recruitment purpose only", "employment_types": ["Full Time", "Permanent"], "selling_points": ["\u65e5\u672c\u8a9e\u30cd\u30a4\u30c6\u30a3\u30d6\u8ca1\u52d9\u7d4c\u7406", "Full set of account", "5days, TST, stable company"], "locations": ["Tsim Sha Tsui"], "categories": ["Accounting", "Accountant", "Finance / Accounting Manager", "Financial Controller"], "post_time": "2022-01-16T21:50:22Z", "salary": {"currency": null, "max": null, "min": null, "period": "monthly", "term": null}, "salary_visible": false, "title_keywords": [], "responsibilities": [], "requirements": {"degrees": [], "majors": [], "languages": [], "language_level": [], "hard_skills": [], "soft_skills": [], "languages_combined": []}, "experience_required": {"duration": [], "field": []}}, {"job_id": "100003009043788", "location_code": "hk", "company": "ConnectedGroup Limited", "job_title": "Financial Controller & Company Secretary (HK Listed)", "description": "Financial Controller & Company Secretary (HK Listed)\n\nOur client is a HK main board listed manufacturing company with global presence. They are now looking for a Financial Controller & Company Secretary to head their global Finance team.\n\nPosition Responsibilities\n\nReport directly to the Chairman and lead a team of 2\nOversee finance & accounting, corporate communication, treasury, tax filing, budgeting, internal control, corporate governance, corporate communication and business analysis\nPerform all company secretarial duties, business and compliance advisories\nResponsible for announcements, press release, circulars, annual and interim report\nEnsure compliance with Listing Rules, companies' ordinances, statutory requirements etc.\nMaintain effective interfaces with external parties including auditors, lawyers, government authorities, banks, and regulators such as SEHK and SFC\nAssist on the Company internal audit and ad hoc audit as well as execute follow-up actions on audit findings including any irregularities or incidents\nBuilds strong relationships and fosters teamwork among department and staff to maximize team performance\nManage cashflow and investment portfolio\nDrive and improve efficiencies and reduce costs across the business\nHandle personal investment portfolio of the Chairman and participate in ad hoc projects as assigned\n\nPosition Requirements\n\nA qualified accountant with a degree in Accounting, Finance or related discipline\nBig 4 Accounting background with HK listed companies' experiences is a MUST\nAt least 8 years all-rounded Finance & Accounting experiences in which over 4 years gained from HK listed companies\nCompany secretarial experiences in HK listed companies is essential\nA proactive and responsible candidate with excellent ethical standards\nConfidence and proven ability to present financial information and influence decision making\nAbility to relate well with people at all levels with strong sense of responsibility\nFluency in Cantonese, Mandarin and English is a must\n\nInterested individuals can apply now and send CV to Vivian Wong, or call +852 3972 5831 for more information. Only relevant candidates will be contacted.\n\nFor a more comprehensive list of our vacancies, please visit: www.connectedgroup.com", "employment_types": ["Full Time", "Permanent"], "selling_points": ["One of the market leading players in the industry", "Key senior management in the business", "Attractive package with promising career prospect"], "locations": ["Not Specified"], "categories": ["Accounting", "Finance / Accounting Manager", "Financial Controller", "Others"], "post_time": "2022-01-13T01:56:54Z", "salary": {"currency": null, "max": null, "min": null, "period": "monthly", "term": null}, "salary_visible": false, "title_keywords": ["company secretary", "financial controller"], "responsibilities": ["internal audit", "budgeting", "external parties", "audit", "communication", "statutory requirements", "maintain", "listing", "costs", "internal control", "ad hoc", "tax filing", "compliance", "report", "irregularities", "ensure compliance", "lead a team", "ad hoc projects", "business analysis"], "requirements": {"degrees": ["degree"], "majors": ["finance", "accounting"], "languages": ["cantonese", "english", "mandarin"], "language_level": ["fluency"], "hard_skills": [], "soft_skills": ["confidence", "responsible", "sense of responsibility", "comprehensive", "ethical", "proactive", "decision making"], "languages_combined": [{"language": "cantonese", "language_level": ["fluency"]}, {"language": "english", "language_level": ["fluency"]}, {"language": "mandarin", "language_level": ["fluency"]}]}, "experience_required": {"duration": ["at least 8 years", "4 years"], "field": ["finance", "secretarial", "accounting", "big 4"]}}, {"job_id": "100003009029275", "location_code": "hk", "company": "", "job_title": "Financial Controller", "description": "Responsibilities:\n\n\u00a0\u00a0\u00a0\u00a0\u00a0\u00a0\u00a0\u00a0\u00a0\u00a0\u00a0\u00a0\u00a0 Report to CFO;\n\u00a0\u00a0\u00a0\u00a0\u00a0\u00a0\u00a0\u00a0\u00a0\u00a0\u00a0\u00a0\u00a0 Managing internal and external financial reporting requirements including consolidation, compliance and controlling activities;\n\u00a0\u00a0\u00a0\u00a0\u00a0\u00a0\u00a0\u00a0\u00a0\u00a0\u00a0\u00a0\u00a0 Managing parties including external auditors, tax authorities and internal business units;\n\u00a0\u00a0\u00a0\u00a0\u00a0\u00a0\u00a0\u00a0\u00a0\u00a0\u00a0\u00a0\u00a0 Leading cash and liquidity management and credit risk management;\n\u00a0\u00a0\u00a0\u00a0\u00a0\u00a0\u00a0\u00a0\u00a0\u00a0\u00a0\u00a0\u00a0 Leading forecasting and budgeting;\n\u00a0\u00a0\u00a0\u00a0\u00a0\u00a0\u00a0\u00a0\u00a0\u00a0\u00a0\u00a0\u00a0 Setting departmental KPIs for performance tracking;\n\u00a0\u00a0\u00a0\u00a0\u00a0\u00a0\u00a0\u00a0\u00a0\u00a0\u00a0\u00a0\u00a0 Coordinating company secretarial matters for the Group;\n\u00a0\u00a0\u00a0\u00a0\u00a0\u00a0\u00a0\u00a0\u00a0\u00a0\u00a0\u00a0\u00a0 Support various internal stakeholders in matters relating to internal controls, tax, and project implementations\n\u00a0\u00a0\u00a0\u00a0\u00a0\u00a0\u00a0\u00a0\u00a0\u00a0\u00a0\u00a0\u00a0 To perform additional duties and other ad hoc assignments as requested\n\nRequirements:\n\n\u00a0\u00a0\u00a0\u00a0\u00a0\u00a0\u00a0\u00a0\u00a0\u00a0\u00a0\u00a0\u00a0 Degree holder in Accounting, Finance, Business Administration or related discipline, qualified accountant of HKICPA/ACCA\n\u00a0\u00a0\u00a0\u00a0\u00a0\u00a0\u00a0\u00a0\u00a0\u00a0\u00a0\u00a0\u00a0 At least 10-15 years in an all-rounded accounting function, experience with financial reporting and accounting with 5 years\u2019 experience in managerial level\n\u00a0\u00a0\u00a0\u00a0\u00a0\u00a0\u00a0\u00a0\u00a0\u00a0\u00a0\u00a0\u00a0 Strong analytical ability and forecasting skills with strong attention to detail\n\u00a0\u00a0\u00a0\u00a0\u00a0\u00a0\u00a0\u00a0\u00a0\u00a0\u00a0\u00a0\u00a0 Knowledge in China accounting, laws and regulations\n\u00a0\u00a0\u00a0\u00a0\u00a0\u00a0\u00a0\u00a0\u00a0\u00a0\u00a0\u00a0\u00a0 Experience in Big4 or financial institutions is a plus\n\u00a0\u00a0\u00a0\u00a0\u00a0\u00a0\u00a0\u00a0\u00a0\u00a0\u00a0\u00a0\u00a0 Experience in medical related industry is a plus\n\u00a0\u00a0\u00a0\u00a0\u00a0\u00a0\u00a0\u00a0\u00a0\u00a0\u00a0\u00a0\u00a0 Proficient in both written and spoken English & Chinese\n\u00a0\u00a0\u00a0\u00a0\u00a0\u00a0\u00a0\u00a0\u00a0\u00a0\u00a0\u00a0\u00a0 Good time management skill and able to work under pressure\n\u00a0\u00a0\u00a0\u00a0\u00a0\u00a0\u00a0\u00a0\u00a0\u00a0\u00a0\u00a0\u00a0 Strong communication skills and connect proactively across various levels in the Business Units\n\u00a0\u00a0\u00a0\u00a0\u00a0\u00a0\u00a0\u00a0\u00a0\u00a0\u00a0\u00a0\u00a0 Proficient user in Excel\nInterest parties please click \"apply now\" or please contact\u00a03427 9018 for more information.", "employment_types": ["Full Time"], "selling_points": [], "locations": ["Central"], "categories": ["Accounting", "Financial Controller"], "post_time": "2022-01-09T16:25:46Z", "salary": {"currency": null, "max": null, "min": null, "period": "monthly", "term": null}, "salary_visible": false, "title_keywords": ["financial controller"], "responsibilities": ["tax", "management", "tracking", "budgeting", "additional duties", "compliance", "financial reporting", "ad hoc assignments", "kpis", "report", "forecasting", "external auditors"], "requirements": {"degrees": ["degree holder"], "majors": ["finance", "accounting", "business administration"], "languages": ["english", "chinese"], "language_level": ["proficient"], "hard_skills": ["excel", "acca", "plus", "hkicpa"], "soft_skills": ["communication skills", "time management skill", "attention to detail", "work under pressure"], "languages_combined": [{"language": "english", "language_level": ["proficient"]}, {"language": "chinese", "language_level": ["proficient"]}]}, "experience_required": {"duration": ["5 years", "at least 10-15 years"], "field": ["managerial", "financial", "related", "financial institutions", "accounting", "medical"]}}, {"job_id": "100003009037754", "location_code": "hk", "company": "PrimeLink Executive Recruitment Consultants Ltd", "job_title": "Finance & Administration Manager", "description": "Hong Kong Food & Beverage Trading Company\n\n\nOur client, an established food and beverage trading company in Hong Kong, is seeking a high calibre Finance professional to join the management team.\n\nReporting to the Managing Director, you will provide leadership and management to a finance team and adopt full responsibility for all accounting processes, cashflow planning, costing, sales analysis, budgeting, forecasting, financial reporting and treasury.\u00a0 You will also liaise with external professional parties for statutory reporting and taxation issues, as well as oversee other operations including IT, human resources and general administration.\u00a0 The continuous improvement of internal and financial controls, and the streamlining of policies and procedures are imperative to ensuring maximum efficiency to support the business. \u00a0\u00a0\u00a0\n\nThe successful candidate will be a qualified accountant and have over 15 years\u2019 experience, ideally within the food trading or FMCG sector.\u00a0 Strong interpersonal skills with a hands-on, proactive, independent and energetic approach are essential.\u00a0 Fluency in English and Chinese are required.\n\nTo apply, please send your detailed resume in MS-Word by e-mail to Cynthia Au-Yeung by APPLY NOW\n", "employment_types": ["Full Time", "Permanent"], "selling_points": ["Provide leadership & management to a finance team", "Experience within the food trading or FMCG sector", "A qualified accountant"], "locations": ["Not Specified"], "categories": ["Accounting", "Finance / Accounting Manager", "Financial Controller", "Hospitality / F & B", "Food & Beverage"], "post_time": "2022-01-12T23:26:09Z", "salary": {"currency": null, "max": null, "min": null, "period": "monthly", "term": null}, "salary_visible": false, "title_keywords": ["finance & administration manager"], "responsibilities": ["administration", "management team", "management", "reporting", "taxation", "budgeting", "analysis", "operations", "policies", "procedures", "finance team", "financial reporting", "liaise with", "forecasting", "planning"], "requirements": {"degrees": [], "majors": [], "languages": ["english", "chinese"], "language_level": ["fluency"], "hard_skills": ["ms-word", "analysis"], "soft_skills": ["independent", "hands-on", "energetic", "interpersonal skills", "proactive", "leadership", "detailed"], "languages_combined": [{"language": "english", "language_level": ["fluency"]}, {"language": "chinese", "language_level": ["fluency"]}]}, "experience_required": {"duration": ["15 years"], "field": ["food", "fmcg", "trading"]}}, {"job_id": "100003009038686", "location_code": "hk", "company": "Midland Holdings Limited", "job_title": "Financial Controller", "description": "Responsibilities:\n\nOverseas finance and accounting functions of the Group in HK\nLead HK accounting team & be in charge of overall financial planning, consolidation & reporting, budgeting & forecasting, cost control, treasury management and taxation matters\nProvide strategic advice and suggestions on top management decisions based on financial analysis\nDevelop strategies, review business performance and assess opportunities which will support the group\u2019s continued expansion\nIdentify opportunities for process improvement and key cost driver for cost effectiveness\nFormulate internal control system, and establish/ optimize workflow for operational effectiveness and efficiency\nLiaise with external parties, such as auditors and bankers\n\nRequirements:\n\nQualified Accountant with a degree or above in Accounting or Finance or other related discipline\nAt least 10 years' of financial management experience with a minimum of 6 years at senior managerial level in listed / investment company\nMature, self-motivated, independent combined with good interpersonal and communication skills\nProficiency in both spoken and written English and Chinese\n\nCompetitive Salary will be offered to the right candidate. \u00a0For application, please update your resume by clicking \"APPLY NOW\" or complete the online application form which is available at\u00a0https://www.midland.com.hk/joinus/\u00a0and sent to the corresponding email address together with your full resume, present & expected salary.\n\nAll personal data collected will be used for recruitment purpose only. \u00a0Applicants not hearing from us within 2 months may consider their applications unsuccessful. \u00a0All personal data supplied will be kept for a reasonable period in accordance with the legal requirements.\n\nAs an Equal Opportunities Employer, we are committed to eliminating discrimination in employment. Our vacancy is open to all applicants meeting the basic entry requirement irrespective of their disability, sex, marital status, pregnancy, age, family status, sexual orientation and race.", "employment_types": ["Full Time", "Permanent"], "selling_points": ["Min 6yr at SENIOR managerial level in listed firm", "Develop strategies, review business performance", "Group FP&A,consolidation,cost control,treasury"], "locations": ["Cheung Sha Wan"], "categories": ["Accounting", "Consulting", "Financial Analyst", "Financial Controller"], "post_time": "2022-01-12T03:12:42Z", "salary": {"currency": null, "max": null, "min": null, "period": "monthly", "term": null}, "salary_visible": false, "title_keywords": ["financial controller"], "responsibilities": ["reporting", "management", "taxation", "develop strategies", "cost", "budgeting", "review", "external parties", "financial analysis", "cost control", "liaise with", "forecasting", "internal control", "planning"], "requirements": {"degrees": ["degree or above"], "majors": ["finance", "accounting"], "languages": ["english", "chinese"], "language_level": ["proficiency"], "hard_skills": ["basic"], "soft_skills": ["communication skills", "self-motivated", "independent", "mature", "committed", "interpersonal"], "languages_combined": [{"language": "english", "language_level": ["proficiency"]}, {"language": "chinese", "language_level": ["proficiency"]}]}, "experience_required": {"duration": ["at least 10 years", "minimum of 6 years"], "field": ["managerial", "management", "investment", "financial"]}}, {"job_id": "100003009053604", "location_code": "hk", "company": "Thales Transport & Security (Hong Kong) Limited", "job_title": "Project Cost Control Officer", "description": "Responsibilities\n\nUnderstand the revenue recognition plan at project start and the billing plan (invoice and progress payments), manage and proceed the revenue recognition and billing with Projects Manager and Business Control Manager\nUpdate revenue recognition plan as required\nCheck, control and monitor movements in Actual and Committed Costs on a monthly basis\nManage and forecast cash movements monthly. Track cash-in overdue status; give alert to Project Managers and Business Control Manager.\nProvide all necessary support to Project Managers on financial matters\nEnsure that project data reporting is in line with approved Project reviews\nCoordinate with the project team to ensure consistent accounting (revenue & margin recognition) and reporting across the project.\nDevelop strong relationships and continuous communication flows with project team\nEnsure that all financial processes & instructions and internal controls, including delegation of authorities, are implemented\u00a0 and compliant\nSupport budget, forecasts and monthly closing\n\nRequirements\n\nBachelor degree in Accounting/Finance or related discipline\nAt least 5 years\u2019 experience of project accounting & controlling\nExperience long-term contract management, a plus\nKnowledge of SAP, Excel\nProficiency in both written and spoken English.\nHighly articulate, confident team player able to communicate and work under pressure\nExperience in complex international environment", "employment_types": ["Full Time", "Permanent"], "selling_points": ["5+ years of project cost control experience", "Stable working hours", "Hong Kong region focused"], "locations": ["Mong Kok"], "categories": ["Accounting", "Finance / Accounting Manager", "Financial Controller", "Others"], "post_time": "2022-01-17T07:13:24Z", "salary": {"currency": null, "max": null, "min": null, "period": "monthly", "term": null}, "salary_visible": false, "title_keywords": ["officer"], "responsibilities": ["reporting", "control", "data", "invoice", "budget", "monitor", "coordinate with", "develop", "communication", "payments", "plan", "forecast", "costs"], "requirements": {"degrees": ["degree", "bachelor"], "majors": ["finance", "accounting"], "languages": ["english"], "language_level": ["proficiency"], "hard_skills": ["excel", "plus", "sap"], "soft_skills": ["confident", "articulate", "team player", "work under pressure"], "languages_combined": [{"language": "english", "language_level": ["proficiency"]}]}, "experience_required": {"duration": ["at least 5 years"], "field": ["management", "accounting"]}}, {"job_id": "100003009043077", "location_code": "hk", "company": "Headsearch21 Consultancy Ltd", "job_title": "Chief Financial Controller, CFO (5 days, good package, Retail Company, Sizable Company)", "description": "To expand the business, our client is seeking for high caliber candidate to fill up the following position:\n\n\nResponsibilities:\u00a0\u00a0\n\nManage finance related activities both internally and externally for the company\nResponsible for providing business advice and support to top management for business planning, expansion, strategic decision, budget forecasting and allocation, taxation, corporate governance etc.\nTo provide professional advice to the senior management team on strategic business development\nTo ensure high standards of financial controls and reporting\nMaintain and ensure relevant statutory/regulatory requirements\nProvide assistance on board management, and prepare relevant materials, resolutions, minutes, annual report and other documents\nAdvise the Board of corporate governance requirements and ensure compliance with the Listing Rules and other regulatory requirements\n\nRequirements:\u00a0\u00a0\n\nBachelor's Degree in Finance, Accounting, Business or related disciplines and professional accounting qualification,\u00a0such as ACCA and /or HKICPA\nAt least 15 years related experience\u00a0\nExperience in listed Company and Sizable Company is a must\nExperience in Retail Company\nStrategic, good business acumen and communication skills\nProficiency in spoken and written English and Putonghua\nMature, able to work independently and under pressure, resourceful and self-driven with a strong sense of commitment;\nGood interpersonal and organizational skills;\n\nInterested parties, please click the \"Apply Now\" or send\u00a0 your updated resume with\u00a0Current\u00a0and\u00a0Expected salary\u00a0in MS word format to cv @headsearch21.com\u00a0\n\nAll information collected will be treated in strict confidence and be used for recruitment purpose only\n\nRef#:\u00a0CA01007\n\nCompany Web-Site:\u00a0www.headsearch21.com\u00a0\n\nHotline: (852) 3188 3586", "employment_types": ["Full Time", "Permanent"], "selling_points": ["Exp in Listed Company", "5 Days ,Good Salary,Good package", "Must Exp in Sizable company"], "locations": ["Not Specified"], "categories": ["Accounting", "Financial Analyst", "Financial Controller", "Others"], "post_time": "2022-01-12T09:44:00Z", "salary": {"currency": "HKD", "max": null, "min": 160000, "period": "monthly", "term": null}, "salary_visible": true, "title_keywords": ["cfo", "financial controller"], "responsibilities": ["taxation", "management", "reporting", "regulatory requirements", "budget", "provide assistance", "ensure compliance", "maintain", "report", "senior management", "forecasting", "listing", "planning"], "requirements": {"degrees": ["degree", "bachelor"], "majors": ["business", "finance", "related disciplines", "accounting"], "languages": ["putonghua", "english"], "language_level": ["proficiency"], "hard_skills": ["acca", "acumen", "hkicpa"], "soft_skills": ["communication skills", "work independently", "organizational skills", "under pressure", "resourceful", "mature", "business acumen", "interpersonal", "driven"], "languages_combined": [{"language": "putonghua", "language_level": ["proficiency"]}, {"language": "english", "language_level": ["proficiency"]}]}, "experience_required": {"duration": ["at least 15 years"], "field": ["related", "retail"]}}, {"job_id": "100003009050161", "location_code": "hk", "company": "Magic Search Limited", "job_title": "Regional Cost Controller (Luxury Brand)", "description": "Our client is a global leading luxury Brand It is now looking for a Regional Finance Manager to join their team.\n\nKey Responsibilities\n\nPrepare and consolidated costing report with comparison against Budget and Forecast with comment\nWork closely with other functional team to ensure alignment and to reconcile any discrepancy\nPrepare other regular cost reporting or ad hoc analysis for management review of business performance\u00a0\nDevelop and replicate excel\u00a0budget/forecast\u00a0templates for\u00a0Asia\u00a0market\u00a0and\u00a0validation\u00a0\u00a0\nAssist\u00a0with the\u00a0budget & forecast\u00a0consolidation and review\u00a0process\nValidate system input and co-ordinate necessary follow-up with market\u00a0finance team\nAssist with analysis during budget and forecast process\nCost Management and Budget follow-up\nAssist in establishing/improving means of regional\u00a0cost\u00a0tracking\u00a0and budget follow-up\u00a0process\nRecommend and develop relevant reports and analysis\nAssist with SAP & Planning and Consolidation tool co-ordination, vendor master data creation and maintenance, and other ad hoc projects\n\nRequirements\n\nBachelor degree in Finance, Accounting or other related subjects\n6-7 years relevant retail working experience\nAbility to extract, organise, analyse and report data\nGood communication skills\nGood command in English and Chinese\u00a0", "employment_types": ["Full Time", "Permanent"], "selling_points": ["6-7 years experience", "luxury brand", "audit experience is a plus"], "locations": ["Not Specified"], "categories": ["Accounting", "Credit Control", "Financial Analyst", "Financial Controller"], "post_time": "2022-01-14T09:53:47Z", "salary": {"currency": null, "max": null, "min": null, "period": "monthly", "term": null}, "salary_visible": false, "title_keywords": [], "responsibilities": ["data", "budget", "system input", "management review", "relevant reports", "ad hoc", "develop", "finance team", "forecast", "report", "reporting", "cost", "management", "review", "tracking", "maintenance", "forecast process", "analysis", "ad hoc projects", "planning"], "requirements": {"degrees": ["degree", "bachelor"], "majors": ["finance", "accounting"], "languages": ["english", "chinese"], "language_level": ["good command"], "hard_skills": [], "soft_skills": ["communication skills"], "languages_combined": [{"language": "english", "language_level": ["good command"]}, {"language": "chinese", "language_level": ["good command"]}]}, "experience_required": {"duration": ["6-7 years"], "field": ["retail"]}}, {"job_id": "100003009033617", "location_code": "hk", "company": "", "job_title": "Financial Controller", "description": "We are a market leader in Hong Kong, China and ASEAN road transportation services. With very aggressive business growth agenda in developing new product lines, the company has set up own office and facility network in different continents to serve at customer convenience.\n\n\nJob Responsibilities:\nBudgeting, forecasting and analysis for region, reviewing business strategy and finances\nMonitor daily accounting functions, reporting and working closely with the Regional Finance Function\nManagement of tax planning process, compliance, and transfer pricing\nSupport various internal stakeholders in matters relating to internal controls, tax, and project implementations\nAd hoc assignments and projects\nRequirements:\nACCA, Degree or above in Accounting, Finance, or related disciplines\nAt least 15 years in an all-rounded accounting function, experience with financial reporting and accounting\nPrevious experience working in an audit firm is a plus, team leading experience preferred\nQualified Accountant is required, excellent business acumen and able to work with overseas staff\nExposure to Logistics or FMCG industry preferred\nAble to be based in Hong Kong, with occasional travel to Asian\nFluency in English and Chinese (Cantonese & Mandarin)\nCandidate with less experience will be considered as Senior Finance Manager\nWe offer excellent career development and attractive remuneration package to the right candidate.\n\nInformation supplied will be treated in strict confidence and used in accordance with the Personal Data (Privacy) Ordinance. Applicants not invited for interview within 2 months may consider their applications unsuccessful.\n\nInterested individuals please call +852 2473 2828 for more information. Only suitable candidates will be contacted.\n", "employment_types": ["Full Time", "Permanent"], "selling_points": ["Budgeting, forecasting and analysis for region", "Qualified Accountant with 15ys exp. is required", "Support various internal stakeholders"], "locations": ["Tsuen Wan Area"], "categories": ["Accounting", "Chief Accountant", "Financial Analyst", "Financial Controller"], "post_time": "2022-01-10T01:22:17Z", "salary": {"currency": null, "max": null, "min": null, "period": "monthly", "term": null}, "salary_visible": false, "title_keywords": ["financial controller"], "responsibilities": ["tax", "reporting", "management", "budgeting", "analysis", "planning process", "monitor", "compliance", "ad hoc assignments", "daily accounting", "forecasting"], "requirements": {"degrees": ["degree or above"], "majors": ["related disciplines", "finance", "accounting"], "languages": ["cantonese", "english", "chinese", "mandarin"], "language_level": ["fluency"], "hard_skills": ["acca", "fmcg industry", "acumen", "plus"], "soft_skills": ["business acumen"], "languages_combined": [{"language": "cantonese", "language_level": []}, {"language": "english", "language_level": ["fluency"]}, {"language": "chinese", "language_level": ["fluency"]}, {"language": "mandarin", "language_level": []}]}, "experience_required": {"duration": ["at least 15 years"], "field": ["financial", "finance manager", "audit", "accounting", "team"]}}, {"job_id": "100003009042770", "location_code": "hk", "company": "Michael Page", "job_title": "Financial Controller - Global E-Commerce Start Up 100K - 150K", "description": "Perfect opportunity for any FC level candidates who had experiences with start up companies and like to take on the role of an FC position, targeting to act also as an IR Director in a reputable global size E-commerce & Logistic Group. This role offers a great exposure and opportunity to join a very exciting corporation\n\nClient Details\n\nOur client is headquartered in Asia with an extremely sizable team. This Group currently operating in more than 30+ countries and currently still expanding. They are offering a fantastic opportunity for a Senior FC + IR candidate to assist the company expansion plan, targeting the global market and investors.\n\nDescription\n\nFinancial Modelling, Corporate Operational and Financial Analyses\nLeading a team of 5 reviewing daily and monthly accounting matters\nOrganize investors and financing conferences. Fund raising presentation\nResponsible of corporate financing project as well as giving advice to multiple external parties\nContinue research on E-comm development to support IR pitching\n\nProfile\n\nAt least 5 years of IR experiences, start up company background will be a plus\nSensitive to numbers and analytical with strong communication skills\nFluent in both written and spoken in English and Chinese\nEducational background in Finance or related field\n\nJob Offer\n\nGroup Position\nMedical & Dental insurance\n% bonus from raised fund\nOther attractive benefits\n\nTo apply online please click the 'Apply' button below. For a confidential discussion about this role please contact Sunny Chan on +852 3602 2466.", "employment_types": ["Full Time", "Permanent"], "selling_points": ["Expanding Business", "Global Position", "Investor Relations"], "locations": ["Not Specified"], "categories": ["Accounting", "Financial Controller", "Banking / Finance", "Corporate Finance", "Management", "Top Executives (CEO, CFO, CTO, GM, MD etc.)"], "post_time": "2022-01-12T08:45:37Z", "salary": {"currency": null, "max": null, "min": null, "period": "monthly", "term": null}, "salary_visible": false, "title_keywords": ["financial controller"], "responsibilities": ["external parties", "communication", "conferences", "plan", "insurance"], "requirements": {"degrees": [], "majors": [], "languages": ["english", "chinese"], "language_level": ["fluent"], "hard_skills": ["plus", "e-commerce"], "soft_skills": ["communication skills", "sensitive to numbers", "presentation", "responsible"], "languages_combined": [{"language": "english", "language_level": ["fluent"]}, {"language": "chinese", "language_level": ["fluent"]}]}, "experience_required": {"duration": ["at least 5 years"], "field": ["e-commerce"]}}, {"job_id": "100003009049785", "location_code": "hk", "company": "Michael Page", "job_title": "Finance Manager, 55k, PRC Firm", "description": "Our client is a reputable property company. They are now looking for a talent Finance Manager to join their finance team.\n\nClient Details\n\nOur client is a reputable property company. They are now looking for a talent Finance Manager to join their finance team.\n\nDescription\n\nReporting to the GM Finance, you will be responsible for\n\nPreparing for the Main Board IPO listing for the company\nHandling company secretarial matters after IPO\nPreparing annual and interim reports\nStrengthening internal controls, corporate governance and streamline accounting procedures to comply with the Hong Kong Listing Rules / standards\nProviding recommendations to enhance financial performance and business opportunities\nLiaising with CPA firm for audit and tax related matters\n\nProfile\n\nPRC University is highly preferred\n\nExcellent communication skills (English and Mandarin)\n\nDegree Holder in Business/Accounting/Finance\n\nJob Offer\n\nMain Board IPO Experience\nCompetitive Remuneration\n\nTo apply online please click the 'Apply' button below.\nFor a confidential discussion about this role please contact Nicole Hui on +852 3412 4832.", "employment_types": ["Full Time", "Permanent"], "selling_points": ["CPA is a must", "PRC", "13 Months Guaranteed with Bonus"], "locations": ["Not Specified"], "categories": ["Accounting", "Chief Accountant", "Finance / Accounting Manager", "Financial Controller"], "post_time": "2022-01-14T09:14:04Z", "salary": {"currency": null, "max": null, "min": null, "period": "monthly", "term": null}, "salary_visible": false, "title_keywords": ["finance manager"], "responsibilities": ["tax", "reporting", "business opportunities", "procedures", "liaising with", "audit", "communication", "reports", "finance team", "contact", "listing"], "requirements": {"degrees": ["degree holder"], "majors": ["finance", "business", "accounting"], "languages": ["english", "mandarin"], "language_level": ["excellent"], "hard_skills": ["cpa", "gm"], "soft_skills": ["communication skills", "responsible"], "languages_combined": [{"language": "english", "language_level": ["excellent"]}, {"language": "mandarin", "language_level": ["excellent"]}]}, "experience_required": {"duration": [], "field": []}}, {"job_id": "100003009043873", "location_code": "hk", "company": "Ambition", "job_title": "FP&A Director (M&A exp needed)", "description": "Our client is a renowned MNC with solid presence across the globe. To facilitate their company growth and increasing number of projects, they are looking for a high calibre FP&A Director to join their team and take care of the FP&A, finance projects and corporate finance duties across the region.\n\nReport to the Board of Director, your responsibilities will include:\n\n\nLeading FP&A functions and reporting to C-suites\nHandle finance projects globally and responsible for the strategic planning to facilitate business decisions\nAdvise and propose new business strategies/ investment initiatives/ M&A projects to Senior stakeholders\nStrong stakeholder management and influencing skills, responsible for presentation to global stakeholders\nOverseeing all finance, accounting, due diligence and compliance issues\nEnsure proper financial management and reporting\nPreparing financial modelling, investment analysis, scenario studies to support the group's investment decisions and finance projects\nEnsure compliance of relevant regulations, policies and guidelines and monitor the regular updating of policies and accounting standards\nReview daily business operation and formulate management reports\nTo assist in ad hoc corporate projects and strategic Planning\n\nTo qualify, the candidate must process:\n\n\nQualified accountant with ACCA, HKICPA or equivalent qualification\nAt least 8-15 years of working experience, ideally in MNC with solid people management experiences\nConsumer-sector background is a plus, not a must\nCandidates with consulting plus in-house background is preferred\nExcellent communication and business partnering experiences\nExcellent analytical and leadership skills\nFluent English and Mandarin\n\nPlease contact Kady Wu through calls or whatsapp at (852) 3103 4314 or Email directly to kady.wu@ambition.com.hk or click APPLY NOW.\n\nFor more information please visit http://www.ambition.com.hk/\n\nData provided is for recruitment purposes only.\n\n\nIf this job isn't quite right for you, but you know someone who would be great at this role, why not take advantage of our referral scheme? We offer HKD1000 in Apple gift cards for every referred candidate who we place in a role. Terms & Conditions Apply. https://www.ambition.com.hk/refer-a-friend", "employment_types": ["Full Time", "Permanent"], "selling_points": ["Solid FP&A + Corporate Fin exp.", "Consulting + in house background preferred", "Fast-paced, consumer sector"], "locations": ["Not Specified"], "categories": ["Accounting", "Financial Controller"], "post_time": "2022-01-13T02:15:55Z", "salary": {"currency": "HKD", "max": 159999, "min": 70000, "period": "monthly", "term": null}, "salary_visible": true, "title_keywords": ["director"], "responsibilities": ["regulations", "consulting", "data", "communication", "due diligence", "ad hoc", "compliance", "monitor", "report", "reporting", "management", "strategic planning", "investment analysis", "review", "contact", "business operation", "guidelines", "policies", "finance duties", "ensure compliance", "management reports", "recruitment"], "requirements": {"degrees": [], "majors": [], "languages": ["english", "mandarin"], "language_level": ["fluent"], "hard_skills": ["acca", "plus", "analysis", "scheme", "management reports", "c", "whatsapp", "hkicpa"], "soft_skills": ["communication", "leadership skills", "presentation", "responsible"], "languages_combined": [{"language": "english", "language_level": ["fluent"]}, {"language": "mandarin", "language_level": ["fluent"]}]}, "experience_required": {"duration": ["at least 8-15 years"], "field": ["people management", "business"]}}, {"job_id": "100003009039279", "location_code": "hk", "company": "Top Asia Holdings Limited", "job_title": "General Manager - Accounting Department", "description": "The incumbent will lead the accounting departments in Hong Kong and in China, to ensure the financial reports and management accounts are compiled on a timely and accurate basis, and to oversee and plan for the financial needs of the business units/projects.\n\nREQUIREMENTS:\n\n- Degree in Accounting with professional qualification\n\n- Possess over 10 years senior management experience as obtained from large audit firms and in commercial sector \u00a0\n\n- Solid experience in listed company financial reporting, budget planning and control, financing and tax planning\n\n- Excellent command of both spoken and written English and Chinese\n\nInterested parties please send resume with availability & past/expected salary to the HR Manager.\n\nAll data collected will be used for recruitment purposes only.", "employment_types": ["Full Time"], "selling_points": [], "locations": ["Central"], "categories": ["Accounting", "Financial Controller", "Taxation", "Others"], "post_time": "2022-01-11T16:01:49Z", "salary": {"currency": null, "max": null, "min": null, "period": "monthly", "term": null}, "salary_visible": false, "title_keywords": ["general manager", "accounting"], "responsibilities": ["tax", "financial reports", "management", "budget planning", "control", "audit", "financial reporting", "plan", "senior management", "planning"], "requirements": {"degrees": ["degree"], "majors": ["accounting"], "languages": ["english", "chinese"], "language_level": ["excellent"], "hard_skills": [], "soft_skills": ["timely", "accurate"], "languages_combined": [{"language": "english", "language_level": ["excellent"]}, {"language": "chinese", "language_level": ["excellent"]}]}, "experience_required": {"duration": ["10 years"], "field": ["management", "financing", "financial", "audit", "commercial", "planning"]}}, {"job_id": "100003009052550", "location_code": "hk", "company": "The Luxe Manor", "job_title": "Financial Controller / Assistant Financial Controller", "description": "Responsibilities:\nOversee the finance and accounting functions\n\nHandle all aspects of financial controls, reviews and planning\n\nCompile financial budget and perform operational and costing analysis\n\nHighlight and investigate significant issues of operating units, make recommendations on corrective measures\n\nConduct independent review and evaluations of operating units\u2019 financial / operational policies and procedures for the purpose of improving the efficiency and effectiveness\n\nEnforce internal control systems to ensure that the assets, revenues and costs are under effective control\n\nImplement cost effective control policies and procedures, ensure that the internal control systems operate properly and comply with Group and Company policies\n\nRequirements:\nDegree holder in Accounting / Finance or equivalent and with a recognized accounting qualification, preferable ACCA/HKICPA/AICPA\n\nMinimum 10 years\u2019 managerial experience in financial control function in sizable organization and accounting experience in HK listed or multinational corporations\n\nStrong business sense, proven management, analytical and leadership skills\n\nExcellent interpersonal and communication skills and ability to collaborate with all departments in an organization\n\nGood understanding of HK & China accounting rules and regulations\n\nFamiliar with HK & China operations in finance, taxation and audit\n\nSolid hotel experience\n\nInterested parties please send your detailed resume with current and expected salary by clicking Apply Now.\n\nAll applications will be handled in the strictest confidence and personal data collected will be used for recruitment purposes only. Applicants not invited for an interview within 6 weeks may consider their applications unsuccessful. Applicant contact details will be held for 6 months, from the date of application.", "employment_types": ["Full Time"], "selling_points": ["Compile financial budget", "Enforce internal control systems", "Minimum 10 years\u2019 relevant experience"], "locations": ["Not Specified"], "categories": ["Accounting", "Finance / Accounting Manager", "Financial Controller"], "post_time": "2022-01-17T03:24:03Z", "salary": {"currency": null, "max": null, "min": null, "period": "monthly", "term": null}, "salary_visible": false, "title_keywords": ["assistant financial controller", "financial controller"], "responsibilities": ["make recommendations", "control", "cost", "policies", "review", "budget", "procedures", "systems", "costing analysis", "internal control", "costs", "planning"], "requirements": {"degrees": ["degree holder"], "majors": ["finance", "accounting"], "languages": [], "language_level": [], "hard_skills": ["acca", "hkicpa"], "soft_skills": ["communication skills", "leadership skills", "interpersonal", "business sense"], "languages_combined": []}, "experience_required": {"duration": ["minimum 10 years"], "field": ["sizable organization", "managerial", "accounting experience", "financial"]}}, {"job_id": "100003009054922", "location_code": "hk", "company": "Sun Hung Kai Properties Ltd", "job_title": "FINANCIAL CONTROLLER \u2013 HOTEL DIVISION", "description": "Requirements:\n\n\nBachelor\u2019s degree holder, with CPA or other professional qualification in accounting. Prior working experience in audit preferred\nAt least 15 years\u2019 working experience, including relevant experience as Director of Finance in sizable hotels with extensive F&B and other facilites\nSolid working experience for hotels in Hong Kong and mainland China\nStrong analytical skills, good business acumen and ownership perspective\nBe resilient and able to cope with high work pressure and demanding deadlines\nHighly motivated, detail-minded and result oriented with multi-tasking skills\nProactive and a good team player\nGood communication and interpersonal skills\nProficient in both spoken and written English and Chinese\n\nResponsibilities:\n\n\nResponsible for the overall accounting and financial review matters, including reporting and analysis of the portfolio hotels in Hong Kong and mainland China\nWorking closely with headquarter corporate offices and finance teams of portfolio hotels\nProvide consolidated management reports and analysis with value-added views on business and good interpretation of financial data\nPerform regular reviews on financial controls\n\nGood remuneration and attractive fringe benefits will be offered to the successful applicant. Interested parties please apply with full resume, present and expected salary, available date by clicking \u201cApply Now\u201d.\n\nFor further information, please visit our company website: http://www.shkp.com/.\n\nWe are an equal opportunity employer and welcome applications from all qualified candidates. All personal data collected will be used for recruitment purpose only.\u00a0 Applicants not hearing from us within 3 months may consider their applications unsuccessful.\u00a0 All personal data collected will be destroyed within 24 months.", "employment_types": ["Full Time", "Permanent"], "selling_points": ["Bachelor degree with CPA qualification", "Exp as Director of Finance in sizable hotels", "Accounting & financial review of HK & PRC hotels"], "locations": ["Wan Chai"], "categories": ["Accounting", "Finance / Accounting Manager", "Financial Analyst", "Financial Controller"], "post_time": "2022-01-17T14:01:55Z", "salary": {"currency": null, "max": null, "min": null, "period": null, "term": null}, "salary_visible": false, "title_keywords": ["financial controller"], "responsibilities": ["reporting", "data", "analysis", "review", "teams", "management reports"], "requirements": {"degrees": ["bachelor", "degree holder"], "majors": ["accounting"], "languages": ["english", "chinese"], "language_level": ["proficient"], "hard_skills": ["cpa", "acumen", "analytical skills"], "soft_skills": ["detail-minded", "good team player", "multi-tasking skills", "analytical skills", "result oriented", "motivated", "communication and interpersonal skills", "business acumen", "proactive", "extensive"], "languages_combined": [{"language": "english", "language_level": ["proficient"]}, {"language": "chinese", "language_level": ["proficient"]}]}, "experience_required": {"duration": ["at least 15 years"], "field": ["finance", "audit", "f&b", "relevant experience", "hotels"]}}, {"job_id": "100003009047593", "location_code": "hk", "company": "Hong Huan Group Limited", "job_title": "Financial Controller", "description": "Responsibilities\n\nDevelop and oversee the finance & accounting functions in collaboration with Business Units and head office\nProviding accounting and financial insights to improve operational efficiency\nReporting to CFO, involve in strategic planning with top management related with all accounting and finance functions\nDevise the finance related policies complying to all applicable laws and regulations for the group\nOffer financial advice to management in corporate finance exercises such as M&A, investments etc.\nOn-going review of portfolio companies financial planning, reporting, forecast and budgeting activities\nEnsure timely and accurate preparation and submission of monthly financial and management reports for management review and for group consolidation and reporting purpose\nProvide business advice for process improvement, taxation and corporate governance\n\nRequirements\nQualified accountant with a degree or above in Accounting or Finance or related discipline\nMinimum of 15 years working experience includes proven track record at a senior management level\nAbility to consult and advise operating and corporate leaders on issues related to accounting, financial reporting, internal control and regulatory issues\nStrong leadership skills with high level of self-motivation and initiative\nProven analytical, organizational and problem-solving skills\nStrong interpersonal and communication skills, both verbal and written in English, Cantonese and Mandarin\nSuperior organizational skills and the ability to prioritize in a dynamic working environment\nPossess good communication, interpersonal and stakeholder management skills\nDemonstrate strong business acumen\nInterested parties please send full resume with current and expected salary by clicking the \"APPLY NOW\" button below.\nAll information provided by applicants will be treated in strict confidence and used only for recruitment purposes. Applicants may be considered for other suitable positions by our Company & the subsidiaries over not more than 6 months, after which their personal data will be destroyed.", "employment_types": ["Full Time", "Permanent"], "selling_points": [], "locations": ["Ngau Tau Kok"], "categories": ["Accounting", "Chief Accountant", "Financial Analyst", "Financial Controller"], "post_time": "2022-01-14T03:32:00Z", "salary": {"currency": null, "max": null, "min": null, "period": "monthly", "term": null}, "salary_visible": false, "title_keywords": ["financial controller"], "responsibilities": ["regulations", "reporting", "management", "taxation", "strategic planning", "policies", "budgeting", "review", "develop", "management reports", "forecast", "management review", "planning"], "requirements": {"degrees": ["degree or above"], "majors": ["finance", "accounting"], "languages": ["cantonese", "english", "mandarin"], "language_level": [], "hard_skills": ["problem-solving skills", "dynamic", "acumen", "internal control"], "soft_skills": ["communication skills", "organizational skills", "organizational", "leadership skills", "prioritize", "communication", "self-motivation", "dynamic", "business acumen", "problem-solving skills", "interpersonal", "initiative", "superior"], "languages_combined": [{"language": "cantonese", "language_level": []}, {"language": "english", "language_level": []}, {"language": "mandarin", "language_level": []}]}, "experience_required": {"duration": ["minimum of 15 years"], "field": ["management"]}}, {"job_id": "100003009050044", "location_code": "hk", "company": "Summergate Limited", "job_title": "Finance Manager / Assistant Controller", "description": "Reporting to Financial Controller, you will lead a finance team to cover all financial functions in HK and MC, and you\u2019ll also need to work collaboratively with people across the business at all levels.\n\nKEY RESPONSIBILITIES\n\nOverseeing all finance, accounting, tax, treasury, and company secretarial matters for Summergate HK and MC entities.\nFull responsibility for balance sheet control and reconciliations to ensure integrity of financial and accounting information.\nEnsure timely and accurate closing and reporting to head quarter.\nLead the relations with auditors, tax agents, and other external parties to manage statutory obligations for the entities.\nLead the finance team to manage day-to-day operations and finance administrative issues.\nDrive and deliver continuous improvement initiatives across end-to-end business processes, systems and reporting to align head quarter guidance and controls.\nAssist in yearly budget process for HKMC entities, and coordinate with the FP&A team in head quarter to provide business analysis to local business partners.\nMonitor and manage cash flow projections for HKMC entities, and ensure controls over fund transfers and cash management.\nLead, train, and coach the team members to build and maintain a sustainable team to support the local business.\nPerform other ad-hoc projects/assignments as required.\n\nKEY COMPETENCIES / EXPERIENCE\u00a0\n\nMinimum 8 years+ in finance accounting , with above 2-3 years\u2019 experience in managing full-scope finance functions in MNC or sizable local corporations;\nCA/CPA qualification preferred.\nExperience with JDE or Dynamic 365 highly advantageous;\nExperience in a big-4 or other accounting firm desirable;\nStrong leadership with the ability to drive and execute improvements;\nStrong inter-personal and communication skills with good command in written and spoken English. Chinese not essential but advantageous.\nCan-do attitude with strong sense of ownership.\nSelf-motivated and able to work under pressure;\nAbility to be hands on where necessary;", "employment_types": ["Full Time", "Permanent"], "selling_points": [], "locations": ["Lai Chi Kok"], "categories": ["Accounting", "Finance / Accounting Manager", "Financial Controller"], "post_time": "2022-01-14T09:41:00Z", "salary": {"currency": null, "max": null, "min": null, "period": "monthly", "term": null}, "salary_visible": false, "title_keywords": ["finance manager", "assistant"], "responsibilities": ["external parties", "day-to-day operations", "budget", "communication", "maintain", "ad-hoc projects", "work under pressure", "control", "monitor", "finance team", "balance sheet", "reporting", "guidance", "management", "coordinate with", "reconciliations", "cash flow", "tax", "systems", "business analysis"], "requirements": {"degrees": [], "majors": [], "languages": ["english", "chinese"], "language_level": ["good command"], "hard_skills": ["cpa", "analysis", "dynamic"], "soft_skills": ["communication skills", "self-motivated", "inter-personal", "can-do attitude", "timely", "integrity", "dynamic", "hands on", "accurate", "leadership", "work under pressure"], "languages_combined": [{"language": "english", "language_level": ["good command"]}, {"language": "chinese", "language_level": []}]}, "experience_required": {"duration": ["2-3 years"], "field": ["finance", "accounting"]}}, {"job_id": "100003009049547", "location_code": "hk", "company": "Thornstone Professional Services Limited", "job_title": "Financial Controller - Listed Company", "description": "Our Client is a listed food company in Hong Kong, to cope with their fast expansion, they are currently seeking a Financial Controller cum Company Secretary to join their team.\n\n\n\nResponsibilities:\n\nOversee and manage the whole finance, accounting and taxation functions\u00a0in HK\nEnsure all accounting procedures comply with the internal policy and legal compliance\nAdvise the Board on appropriate financial policies and strategies in order to achieve the organization\u2019s mission and objectives.\nPrepare monthly financial reports and consolidated management reports\nPrepare budget & forecast, raise out any potential variances\nLiaise with auditors and other professionals in annual audit, tax and company\u00a0secretarial filing\nImproving efficiencies and reducing costs across the business\nAd hoc projects and assignments\n\n\u00a0Requirements:\n\nDegree holder in Accounting, Finance or a related discipline\nQualified Accountant and memberof HKICPA, ACCA, CPAA\nAt least 10 years of accounting experience in listed companies with all rounded and hands on operation accounting background preferably with company secretary knowledge\nGood knowledge of Hong Kong listing rules, Hong Kong tax regulations policies and accounting system\nFMCG, manufacturing or food industry experience is preferable\nStrong command of languages (English, Cantonese and Mandarin)\nAdaptable, demonstrate strong leadership and able to communicate well with different level of colleagues", "employment_types": ["Full Time"], "selling_points": ["Listed Company", "Excellent Exposure", "Stable Environment"], "locations": ["Not Specified"], "categories": ["Accounting", "Finance / Accounting Manager", "Financial Controller", "Professional Services", "Company Secretary"], "post_time": "2022-01-14T08:51:55Z", "salary": {"currency": null, "max": null, "min": null, "period": "monthly", "term": null}, "salary_visible": false, "title_keywords": ["financial controller"], "responsibilities": ["tax", "taxation", "financial reports", "annual audit", "financial policies", "compliance", "procedures", "budget", "management reports", "ad hoc projects", "forecast", "liaise with", "costs"], "requirements": {"degrees": ["degree holder"], "majors": ["finance", "accounting"], "languages": ["cantonese", "english", "mandarin"], "language_level": [], "hard_skills": ["acca", "accounting system", "hkicpa"], "soft_skills": ["adaptable", "hands on", "leadership"], "languages_combined": [{"language": "cantonese", "language_level": []}, {"language": "english", "language_level": []}, {"language": "mandarin", "language_level": []}]}, "experience_required": {"duration": ["at least 10 years"], "field": ["manufacturing", "fmcg", "accounting experience", "food industry", "operation", "accounting"]}}, {"job_id": "100003009053700", "location_code": "hk", "company": "PwC", "job_title": "Manager - Finance Practice Support - PwC Tax - Hong Kong", "description": "Duties\n\nAssist in preparing and reviewing financial management and statistics reports\nPerform analytical review on financial results\nPerform data quality review on Tax systems\nCarry out monthly actions to improve financial management\nAssist in financial projects and ad-hoc assignments\nAssist in financial reports automation\nManage database / systems\nCo-ordinate with departments, e.g., GTS, Central FIN, Client First team, etc. on Tax finance matters\n\n\u00a0Requirements\n\nBachelor degree in any discipline\nMinimum 5 years\u2019 experience in Finance in MNC or professional services firm is preferred\nGood logical and analytical skill\nGood coordination, interpersonal and problem-solving skills\nGood project management skill\nAble to manage multiple tasks under deadlines while maintaining quality of work delivered\nAble to communicate with impact to peer groups, leaders and stakeholders\nAble to maintain good relationship with teammates and users\nDemonstrate creativity and able to contribute new ideas and knowledge where appropriate\nOpen minded, agile with change and practical\nCommitted to self-development and coaching of others for growth\nProficient in MS Office, especially in MS Excel & PowerPoint.\u00a0 Experience in using Outlook and technology tools such as Alteryx and Power BI, is a desirable\nGood in both spoken and written English and Chinese", "employment_types": ["Full Time", "Permanent"], "selling_points": ["Financial Management for Tax Practice", "ex-Professional Staff welcome", "Urgent Hire"], "locations": ["Central"], "categories": ["Accounting", "Finance / Accounting Manager", "Financial Controller"], "post_time": "2022-01-17T07:22:26Z", "salary": {"currency": null, "max": null, "min": null, "period": "monthly", "term": null}, "salary_visible": false, "title_keywords": ["manager"], "responsibilities": ["tax", "management", "financial reports", "data", "co-ordinate with", "ad-hoc assignments", "review", "quality", "systems", "reports", "database"], "requirements": {"degrees": ["degree", "bachelor"], "majors": [], "languages": ["english", "chinese"], "language_level": ["good"], "hard_skills": ["analytical skill", "bi", "agile", "powerpoint", "project management", "ms excel", "outlook", "alteryx", "problem-solving skills", "ms office"], "soft_skills": ["analytical skill", "agile", "multiple tasks", "committed", "open minded", "coordination", "project management skill", "problem-solving skills", "interpersonal"], "languages_combined": [{"language": "english", "language_level": ["good"]}, {"language": "chinese", "language_level": ["good"]}]}, "experience_required": {"duration": ["minimum 5 years"], "field": ["finance"]}}, {"job_id": "100003009048137", "location_code": "hk", "company": "Amazin Consultants Limited", "job_title": "Financial Controller and Company Secretary (Circa$800K p.a)", "description": "Our client is a reputable listed company with business in food retail, manufacturing and trading.\u00a0 They are inviting an experienced financial controller to lead the finance team.\n\n\n\nResponsibilities:\n\nOversee and manage the whole finance, accounting\u00a0and taxation functions\u00a0in Hong Kong.\nEnsure all accounting procedures comply with the internal policy and legal compliance\nAdvise Board on appropriate financial policies and strategies in order to achieve the organization\u2019s mission and objectives.\nHandle company secretarial duties and liaise with 3rd parties such as lawyer, SFC authorities, bankers etc. as necessary.\nPrepare monthly financial reports and consolidated management reports.\nPrepare budget & forecast, raise out any potential variances.\nLiaise with auditors and other professionals in annual audit, tax and company\u00a0secretarial filing.\nImproving efficiencies and reducing costs across the business.\u00a0\n\nRequirements:\n\nDegree holder in Accounting, Finance\u00a0or a related discipline\nQualified Accountant\u00a0and member\u00a0of HKICPA, ACCA, CPAA.\nAssociate member of ACS, ACIS preferred but not a must.\nAt least 5 years of accounting experience\u00a0in listed companies\u00a0with all rounded and hands-on operation accounting background.\nGood knowledge of Hong Kong listing rules, Hong Kong tax regulations policies and accounting system\nFMCG, manufacturing\u00a0or trading industry experience is an advantage.\nProficient in Cantonese, Mandarin and English.\nImmediate available is an advantage.\n\n\u00a0For interested parties, please send your full resume\u00a0 to\u00a0resume@ amazinhr.com\n\nPersonal information is collected and used for the purposes of recruitment only. We use your personal information to contact you for the position you apply and/or for the vacancy that matches with your profile.", "employment_types": ["Full Time", "Permanent"], "selling_points": ["Expanding listed company with established brand", "Finance and named company secretary role", "Work-life balance environment"], "locations": ["Others"], "categories": ["Accounting", "Finance / Accounting Manager", "Financial Controller"], "post_time": "2022-01-14T05:12:14Z", "salary": {"currency": "HKD", "max": 69999, "min": 55000, "period": "monthly", "term": null}, "salary_visible": true, "title_keywords": ["company secretary", "financial controller"], "responsibilities": ["tax", "taxation", "financial reports", "annual audit", "financial policies", "compliance", "procedures", "budget", "management reports", "forecast", "liaise with", "costs"], "requirements": {"degrees": ["degree holder"], "majors": ["finance", "accounting"], "languages": ["cantonese", "english", "mandarin"], "language_level": ["proficient"], "hard_skills": ["acca", "accounting system", "hkicpa"], "soft_skills": ["hands-on"], "languages_combined": [{"language": "cantonese", "language_level": ["proficient"]}, {"language": "english", "language_level": ["proficient"]}, {"language": "mandarin", "language_level": ["proficient"]}]}, "experience_required": {"duration": ["at least 5 years"], "field": ["manufacturing", "fmcg", "accounting experience", "operation", "accounting", "trading"]}}, {"job_id": "100003009050240", "location_code": "hk", "company": "Robert Walters (HK)", "job_title": "Finance Manager/ Financial Controller (Open to Big4 M level)", "description": "It is a HK main board listed company. This role reports to the chairman directly.\n\nJob Responsibilities:\n\nEnsure proper and consistent consolidated financial reporting standard compile with listing rules requirement\nReview the monthly consolidated management account package and commentary for Board reference Oversee and coordinate the annual budget process of the group\nOversee and coordinate the group annual audit, tax and company secretarial filling\nReview and liaise legal advice and support on major contracts at corporate level\nLiaise with banks on investment financing\nMange the cashflow and investment portfolios\n\nJob Requirements:\n\nQualified Accountant and degree holder in accounting or related discipline\nBig 4 trained candidate with minimum 8 years of working experience\nFamiliar with listing rules\nGood command of written and spoken in English, Mandarin and Cantonese", "employment_types": ["Full Time", "Permanent"], "selling_points": ["Main board listed", "Stable working environment", "Familiar with listing rules"], "locations": ["Not Specified"], "categories": ["Accounting", "Financial Controller"], "post_time": "2022-01-14T10:00:04Z", "salary": {"currency": null, "max": null, "min": null, "period": "monthly", "term": null}, "salary_visible": false, "title_keywords": ["finance manager", "financial controller"], "responsibilities": ["tax", "liaise", "management", "annual audit", "contracts", "review", "budget", "investment portfolios", "coordinate", "financial reporting", "liaise with", "listing"], "requirements": {"degrees": ["degree holder"], "majors": ["accounting"], "languages": ["cantonese", "english", "mandarin"], "language_level": ["good command"], "hard_skills": [], "soft_skills": [], "languages_combined": [{"language": "cantonese", "language_level": ["good command"]}, {"language": "english", "language_level": ["good command"]}, {"language": "mandarin", "language_level": ["good command"]}]}, "experience_required": {"duration": ["minimum 8 years"], "field": ["big 4"]}}, {"job_id": "100003009054564", "location_code": "hk", "company": "Foodgears Industrial International Limited", "job_title": "Management Accounting Manager", "description": "Responsibilities:\n\nDrive the financial planning of the company by analyzing its performance and risks\nSet targets for and supervise all accounting and finance personnel (management accountants, internal auditors etc.)\nOversee all audit and internal control operations\nPrepare timely and detailed reports on financial performance on a quarterly and annual basis\nConduct analysis to make forecasts and report to upper executives\nEnsure adherence to financial laws and guidelines\n\n\u00a0\nRequirements:\n\nProven experience as director of finance or similar role\nIn-depth knowledge of corporate finance and accounting principles, laws and best practices\nSolid knowledge of financial analysis and forecasting\nProficient in the use of MS Office and financial management software\nAn analytical mind with a strategic ability\nExcellent organizational and leadership skills\nOutstanding communication and interpersonal abilities\nCPA or other relevant qualification and China Accounting experience is a plus\n\n\n\nWe offer attractive remuneration package to the right candidate.\u00a0 Interested parties please send full resume with present & expected salary and available date by clicking \"Apply Now\".\n\n\nAll Personal data collected will be used for recruitment purposes only.\n", "employment_types": ["Permanent"], "selling_points": [], "locations": ["Wong Tai Sin Area"], "categories": ["Accounting", "Finance / Accounting Manager", "Financial Analyst", "Financial Controller"], "post_time": "2022-01-17T10:00:39Z", "salary": {"currency": null, "max": null, "min": null, "period": "monthly", "term": null}, "salary_visible": false, "title_keywords": ["accounting manager"], "responsibilities": ["management", "guidelines", "operations", "analysis", "ensure adherence", "audit", "planning", "reports", "report", "internal control"], "requirements": {"degrees": [], "majors": [], "languages": [], "language_level": [], "hard_skills": ["financial analysis", "cpa", "plus", "ms office"], "soft_skills": ["organizational", "leadership skills", "communication", "analytical mind", "interpersonal"], "languages_combined": []}, "experience_required": {"duration": [], "field": ["finance", "accounting experience"]}}, {"job_id": "100003009054928", "location_code": "hk", "company": "Pure Search International Limited", "job_title": "Senior Accounting Manager / Accounting Manager", "description": "Our Client\nA renowned Multi-National Corporation (MNC) with an industry-leading portfolio of consumer brands. With innovative go-to market strategies and after sales services in their distributor business model, they are continuing their expansion plans across Asia Pacific (APAC) and Hong Kong.\u00a0 They are now seeking for a Senior Accounting Manager / Accounting Manager to join its Finance team in Hong Kong.\n\nJob Description\nReporting to the Financial Controller, you will be managing an outsourced accounting service provider, take ownership of reporting, full set of accounts, such as Account Receivable, Accounts Payables, General Ledger etc. You will ensure books are closed properly and prepare meaningful reports to senior management for decision making. You will manage cashflow and ensure cash position of the company is maintained at a good level. You will work closely with the team and advise them on any new accounting standards, its implications to the business and any compliance issues. You will also be involved in ad hoc projects when needed.\n\nJob Requirements\nYou should have at least 10 years Accounting & Finance experience gained in sizable Multi National Corporations (MNCs). Prior experience working in Big 4 CPA firm or 2nd Tier CPA firm is a must. You should have strong communication and influencing skills, and be able to manage a sizeable team. Comfortable to day to day English Communication & Presentation is a must. Proficiency in English and Chinese is essential. Can-do Attitude is highly preferred.\n\n", "employment_types": ["Full Time"], "selling_points": ["HK$55,000 - 68,000 per month", "Renowned Consumer Business", "MNC culture"], "locations": ["Not Specified"], "categories": ["Accounting", "Chief Accountant", "Finance / Accounting Manager", "Financial Controller"], "post_time": "2022-01-17T14:11:21Z", "salary": {"currency": null, "max": null, "min": null, "period": "monthly", "term": null}, "salary_visible": false, "title_keywords": ["accounting manager"], "responsibilities": ["reporting", "general ledger", "full set of accounts", "compliance", "reports", "ad hoc projects", "accounting service", "senior management"], "requirements": {"degrees": [], "majors": [], "languages": ["english", "chinese"], "language_level": ["proficiency"], "hard_skills": ["cpa"], "soft_skills": ["communication", "presentation", "can-do attitude"], "languages_combined": [{"language": "english", "language_level": ["proficiency"]}, {"language": "chinese", "language_level": ["proficiency"]}]}, "experience_required": {"duration": ["at least 10 years"], "field": ["finance", "accounting", "cpa firm", "big 4"]}}, {"job_id": "100003009043137", "location_code": "hk", "company": "Ever Good Industries (International) Limited", "job_title": "Financial Controller and Company Secretary", "description": "Job Duties:\n\nReporting to CEO and directors, involve in strategic planning with top management related with all accounting and finance functions\nOn-going review of portfolio companies financial planning, reporting, forecast and budgeting activities\nResponsible for information disclosure of a Hong Kong main board listed company, including draft or review announcements, circulars, financial statements, interim and annual reports etc;\nMaintain effective interfaces with external parties including auditors, lawyers, government authorities, banks, and regulators such as SEHK and SFC\nAssist on the Company internal and external audit and ad hoc assignments as well as execute follow-up actions on audit findings including any irregularities or incidents\nManage cashflow and investment portfolio\nManage the budgeting and forecasting;\nActing as the named company secretary\n\nRequirements\uff1a\n\nA qualified accountant (HKICPA/ACCA) with a degree in Accounting, Finance or related discipline\nAt least 10 years of accounting experience\u00a0in listed companies\u00a0with all rounded and hands on operation accounting background preferably with company secretary knowledge\nCompany secretarial experiences in HK listed companies is essential\nA proactive and responsible candidate with excellent ethical standards\nConfidence and proven ability to present financial information and influence decision making\nProficiency in Hong Kong accounting standards, taxation and listing rules\u00a0\nKnowledge in China accounting, taxation, laws and regulations\n\u00a0Fluent in English, Cantonese and Mandarin\nImmediate availability preferred\n\nInterested parties, please send a detailed resume including the cover letter, the latest and expected salary and date of availability to the Human Resources Department by clicking \"APPLY NOW\".\n\n(Personal information collected\u00a0for recruitment purpose only)", "employment_types": ["Full Time"], "selling_points": [], "locations": ["Hung Hom"], "categories": ["Accounting", "Financial Controller"], "post_time": "2022-01-12T10:12:00Z", "salary": {"currency": null, "max": null, "min": null, "period": "monthly", "term": null}, "salary_visible": false, "title_keywords": ["company secretary", "financial controller"], "responsibilities": ["reporting", "management", "irregularities", "strategic planning", "budgeting", "review", "external parties", "audit", "financial statements", "maintain", "reports", "ad hoc assignments", "forecast", "forecasting", "planning"], "requirements": {"degrees": ["degree"], "majors": ["finance", "accounting"], "languages": ["cantonese", "english", "mandarin"], "language_level": ["fluent"], "hard_skills": ["acca", "hkicpa"], "soft_skills": ["confidence", "responsible", "hands on", "ethical", "proactive", "decision making"], "languages_combined": [{"language": "cantonese", "language_level": ["fluent"]}, {"language": "english", "language_level": ["fluent"]}, {"language": "mandarin", "language_level": ["fluent"]}]}, "experience_required": {"duration": ["at least 10 years"], "field": ["accounting experience", "operation", "accounting", "secretarial"]}}, {"job_id": "100003009043736", "location_code": "hk", "company": "KeeReal Consulting Limited", "job_title": "Finance Manager / Financial Controller (Private Equity & Venture Capital | Attractive Package)", "description": "Our client is a fast glowing private equity & venture capital company with regional offices. They are currently looking for a Finance Manager / Financial Controller (Private Equity & Venture Capital | Attractive Package) in the Hong Kong office to join their Finance dynamic team.\n\nResponsibilities:\nPrepare and review NAV, reconciliation on daily basis and monitor cash activity of the funds\nManage full set of fund accounting, reconciliation, and compliance duties\nPrepare and review internal and external reports for the funds' investors and other stakeholders\nResponsible for capital calls and review waterfall calculation\nPlan, implement and review the financial strategies of the corporation including budgeting, financing, taxation handling and compliance\nPrepare cash flow projection and forecasting for\u00a0 the corporation\nCoordinate SFC regulated activities for the licensed corporation and associated entities\nSupport management in key strategic initiatives and business improvement projects\nAny other ad hoc assignments assigned by the management team\nRequirements:\n\nDegree holder or above\u00a0in Accounting or Finance is required\nCPA qualified holder\nStrong understanding of regulations especially SFO\nAt least 5 years of experience in Fund Accounting\nStrong oral and written communication skills in English and Chinese", "employment_types": ["Full Time", "Permanent"], "selling_points": ["8 years of FI experience", "Attractive remuneration package", "Private Equity & Venture Capital"], "locations": ["Not Specified"], "categories": ["Accounting", "Financial Controller", "Banking / Finance", "Financial Services", "Fund Management"], "post_time": "2022-01-13T01:43:40Z", "salary": {"currency": null, "max": null, "min": null, "period": "monthly", "term": null}, "salary_visible": false, "title_keywords": ["finance manager", "financial controller"], "responsibilities": ["taxation", "management", "management team", "budgeting", "compliance", "review", "monitor", "coordinate", "cash flow", "reports", "ad hoc assignments", "plan", "forecasting"], "requirements": {"degrees": ["degree holder"], "majors": ["finance", "accounting"], "languages": ["english", "chinese"], "language_level": [], "hard_skills": ["cpa", "sfo"], "soft_skills": ["communication skills", "oral"], "languages_combined": [{"language": "english", "language_level": []}, {"language": "chinese", "language_level": []}]}, "experience_required": {"duration": ["at least 5 years"], "field": ["accounting"]}}, {"job_id": "100003009046429", "location_code": "hk", "company": "Michael Page", "job_title": "Financial Controller - HK Listed Co", "description": "Financial leadership opportunity\nCorporate Finance and Strategy focused\n\nClient Details\n\nOur client is a listed retail company with strong presence in PRC. In contributing to the market growth and business strategy, they are looking for a high calibre candidate to join their management as a Financial Controller.\n\nDescription\n\nDevelop and oversee the finance & accounting functions in collaboration with regional and head offices\nProvide supervision over the finance and accounting team\nDevise the finance related policies complying to all applicable laws and regulations for the group\nDemonstrate leadership and drive the upgrade of the current reporting work flow, processes and procedures, and any other matters to optimise the operational effectiveness and efficiency\nConstantly review the designed process, system and procedures to avoid any possible business and financial risks\nAct as a key business partner with the senior management and executive in offering strategic and financial insights and recommendations for business management and decision\nOffer financial advice to management in corporate finance exercises such as M&A, investments etc.\n\nProfile\n\nQualified accountant with a degree or above in Accounting or Finance or related discipline\nMinimum of 15 years working experience includes proven track record at a senior management level\nMandatory BIG 4 training with experience at corporate level with HK listed companies\nStrong knowledge with listing compliance and statutory requirements\nPossess good communication, interpersonal and stakeholder management skills\nDemonstrate strong business acumen\nGood command of spoken and written English, Cantonese and Mandarin\n\nJob Offer\n\nAttractive remuneration package\nstable work environment\nOffice location: Central\nSenior leadership position\nRenowned and long standing brand - market leader\n\nTo apply online please click the 'Apply' button below. For a confidential discussion about this role please contact Yamen Cheung on +852 2848 9575.", "employment_types": ["Full Time", "Permanent"], "selling_points": ["Business partnering and startegy focused", "Senior position in the leadership team", "Regional exposure"], "locations": ["Not Specified"], "categories": ["Accounting", "Finance / Accounting Manager", "Financial Controller", "Treasurer"], "post_time": "2022-01-13T11:05:52Z", "salary": {"currency": null, "max": null, "min": null, "period": "monthly", "term": null}, "salary_visible": false, "title_keywords": ["financial controller"], "responsibilities": ["regulations", "reporting", "management", "policies", "review", "procedures", "compliance", "provide supervision", "develop", "communication", "statutory requirements", "contact", "senior management", "listing"], "requirements": {"degrees": ["degree or above"], "majors": ["finance", "accounting"], "languages": ["cantonese", "english", "mandarin"], "language_level": ["good command"], "hard_skills": ["business management", "acumen"], "soft_skills": ["focused", "communication", "business acumen", "stable", "leadership", "interpersonal"], "languages_combined": [{"language": "cantonese", "language_level": ["good command"]}, {"language": "english", "language_level": ["good command"]}, {"language": "mandarin", "language_level": ["good command"]}]}, "experience_required": {"duration": ["minimum of 15 years"], "field": ["management", "training", "big 4"]}}, {"job_id": "100003009050202", "location_code": "hk", "company": "Robert Walters (HK)", "job_title": "Regional Finance Controller (FMCG/ retail/ F&B)", "description": "My client is an US based FMCG company. They are looking for a Regional Finance Controller for their new business line due to expansion. It is a new headcount reports to the US headquarter directly.\n\nJob Responsibilities:\n\nAs part of the start-up team, the role will serve as the bridge between the local Asia offices in Asia and the headquarter in US\nReview and consolidate the financial packs submitted by local finance teams\nEnsure the monthly reporting in the Group system is submitted timely and accurately\nConsistently improve and monitor the financial processes and internal control procedures are put in place and comply with group requirements\nEnsure that Group financial policies are put in place and implemented across all APAC countries\nManage statutory accounting, reporting and submission process for all legal entities in the region and ensure timely, accurate and correct submission\nProvide support and coaching to country finance team members\nParticipate in and drive global finance projects and initiatives\n\nJob Requirements:\n\nBachelor degree holder in accounting or related discipline, qualified accountant\nMinimum 8 years of relevant working experience with regional exposure, ideally with big4 background\nRelevant experience in retail/ FMCG/ F&B industry will be added advantage\nTechnically strong in IFRS, ideal to have knowledge in US GAAP\nExerience in system implementation/ process improvements is highly preferred\nStrong communication skills and able to work under multi-tasking environment\nDetail-minded and self-driven with strong project management skill", "employment_types": ["Full Time", "Permanent"], "selling_points": ["New headcount, part of the setup team", "Finance controllership role for Asia", "MNC working environment- energetic and fun"], "locations": ["Not Specified"], "categories": ["Accounting", "Finance / Accounting Manager", "Financial Controller"], "post_time": "2022-01-14T09:56:03Z", "salary": {"currency": null, "max": null, "min": null, "period": "monthly", "term": null}, "salary_visible": false, "title_keywords": [], "responsibilities": ["reporting", "provide support", "review", "monitor", "teams", "procedures", "financial policies", "finance team", "internal control"], "requirements": {"degrees": ["bachelor degree holder"], "majors": ["accounting"], "languages": [], "language_level": [], "hard_skills": ["system implementation", "project management", "ifrs"], "soft_skills": ["detail-minded", "communication skills", "multi-tasking", "project management skill", "driven", "ideal"], "languages_combined": []}, "experience_required": {"duration": ["minimum 8 years"], "field": ["fmcg", "relevant working experience", "f&b", "relevant experience", "retail"]}}, {"job_id": "100003009048910", "location_code": "hk", "company": "Kingsway Personnel Ltd", "job_title": "\u65e5\u672c\u8a9e\u30cd\u30a4\u30c6\u30a3\u30d6\u7d4c\u7406\u8ca1\u52d9\u30de\u30cd\u30fc\u30b8\u30e3\u30fc ~$45K\uff08\u7d4c\u9a13\u306b\u3088\u308b\uff09", "description": "Reference No.: NR09559\nNature of Business: Medical Services co.\nLocation: T.S.T\nWorking Days: 5 Days\n\nBenefits:\n- Medical Insurance\n- \u4ea4\u901a\u8cbb\u652f\u7d66\n- \u6709\u7d66\u521d\u5e74\u5ea610\u65e5\n\nResponsibilities:\n- \u7d4c\u7406\u8ca1\u52d9\u696d\u52d9\u5168\u822c\n- \u30b9\u30bf\u30c3\u30d5\u7ba1\u7406\n- \u5404\u7a2e\u30ec\u30dd\u30fc\u30c8\u4f5c\u6210\n- \u6d77\u5916\u652f\u5e97\u306e\u8ca1\u52d9\u7ba1\u7406\u3068\u30ea\u30b9\u30af\u7ba1\u7406\n\nRequirement:\n- \u8ca1\u52d9\u30fb\u4f1a\u8a08\u7d4c\u9a1310\u5e74\u4ee5\u4e0a\n- \u65e5\u672c\u8a9e\u30cd\u30a4\u30c6\u30a3\u30d6\u30ec\u30d9\u30eb\u3001\u30d3\u30b8\u30cd\u30b9\u30ec\u30d9\u30eb\u4ee5\u4e0a\u306e\u82f1\u8a9e\n- \u00a0Peachtree\u306a\u3069\u4f1a\u8a08\u30b7\u30b9\u30c6\u30e0\u4f7f\u7528\u7d4c\u9a13\u306e\u6709\u308b\u65b9\u6b53\u8fce\n- \u6771\u5357\u30a2\u30b8\u30a2\u3084\u5317\u7c73\u306e\u8ca1\u52d9\u4f1a\u8a08\u77e5\u8b58\u304c\u3042\u308c\u3070\u5c1a\u826f\u3044\n- \u7d4c\u9a13\u306b\u5fdc\u3058\u3066VISA\u5bfe\u5fdc\u53ef\u80fd\n\n\n\nInterested in the above vacancy?\u00a0 Send your resume to us NOW!\nOnly short-listed candidates will be notified. Personal data collected will be used for recruitment purpose only", "employment_types": ["Full Time", "Permanent"], "selling_points": ["\u65e5\u672c\u8a9e\u30cd\u30a4\u30c6\u30a3\u30d6\u8ca1\u52d9\u7d4c\u7406", "Full set of account", "5days, TST, stable company"], "locations": ["Tsim Sha Tsui"], "categories": ["Accounting", "Accountant", "Finance / Accounting Manager", "Financial Controller"], "post_time": "2022-01-16T21:50:22Z", "salary": {"currency": null, "max": null, "min": null, "period": "monthly", "term": null}, "salary_visible": false, "title_keywords": [], "responsibilities": [], "requirements": {"degrees": [], "majors": [], "languages": [], "language_level": [], "hard_skills": [], "soft_skills": [], "languages_combined": []}, "experience_required": {"duration": [], "field": []}}, {"job_id": "100003009043788", "location_code": "hk", "company": "ConnectedGroup Limited", "job_title": "Financial Controller & Company Secretary (HK Listed)", "description": "Financial Controller & Company Secretary (HK Listed)\n\nOur client is a HK main board listed manufacturing company with global presence. They are now looking for a Financial Controller & Company Secretary to head their global Finance team.\n\nPosition Responsibilities\n\nReport directly to the Chairman and lead a team of 2\nOversee finance & accounting, corporate communication, treasury, tax filing, budgeting, internal control, corporate governance, corporate communication and business analysis\nPerform all company secretarial duties, business and compliance advisories\nResponsible for announcements, press release, circulars, annual and interim report\nEnsure compliance with Listing Rules, companies' ordinances, statutory requirements etc.\nMaintain effective interfaces with external parties including auditors, lawyers, government authorities, banks, and regulators such as SEHK and SFC\nAssist on the Company internal audit and ad hoc audit as well as execute follow-up actions on audit findings including any irregularities or incidents\nBuilds strong relationships and fosters teamwork among department and staff to maximize team performance\nManage cashflow and investment portfolio\nDrive and improve efficiencies and reduce costs across the business\nHandle personal investment portfolio of the Chairman and participate in ad hoc projects as assigned\n\nPosition Requirements\n\nA qualified accountant with a degree in Accounting, Finance or related discipline\nBig 4 Accounting background with HK listed companies' experiences is a MUST\nAt least 8 years all-rounded Finance & Accounting experiences in which over 4 years gained from HK listed companies\nCompany secretarial experiences in HK listed companies is essential\nA proactive and responsible candidate with excellent ethical standards\nConfidence and proven ability to present financial information and influence decision making\nAbility to relate well with people at all levels with strong sense of responsibility\nFluency in Cantonese, Mandarin and English is a must\n\nInterested individuals can apply now and send CV to Vivian Wong, or call +852 3972 5831 for more information. Only relevant candidates will be contacted.\n\nFor a more comprehensive list of our vacancies, please visit: www.connectedgroup.com", "employment_types": ["Full Time", "Permanent"], "selling_points": ["One of the market leading players in the industry", "Key senior management in the business", "Attractive package with promising career prospect"], "locations": ["Not Specified"], "categories": ["Accounting", "Finance / Accounting Manager", "Financial Controller", "Others"], "post_time": "2022-01-13T01:56:54Z", "salary": {"currency": null, "max": null, "min": null, "period": "monthly", "term": null}, "salary_visible": false, "title_keywords": ["company secretary", "financial controller"], "responsibilities": ["internal audit", "budgeting", "external parties", "audit", "communication", "statutory requirements", "maintain", "listing", "costs", "internal control", "ad hoc", "tax filing", "compliance", "report", "irregularities", "ensure compliance", "lead a team", "ad hoc projects", "business analysis"], "requirements": {"degrees": ["degree"], "majors": ["finance", "accounting"], "languages": ["cantonese", "english", "mandarin"], "language_level": ["fluency"], "hard_skills": [], "soft_skills": ["confidence", "responsible", "sense of responsibility", "comprehensive", "ethical", "proactive", "decision making"], "languages_combined": [{"language": "cantonese", "language_level": ["fluency"]}, {"language": "english", "language_level": ["fluency"]}, {"language": "mandarin", "language_level": ["fluency"]}]}, "experience_required": {"duration": ["at least 8 years", "4 years"], "field": ["finance", "secretarial", "accounting", "big 4"]}}, {"job_id": "100003009029275", "location_code": "hk", "company": "", "job_title": "Financial Controller", "description": "Responsibilities:\n\n\u00a0\u00a0\u00a0\u00a0\u00a0\u00a0\u00a0\u00a0\u00a0\u00a0\u00a0\u00a0\u00a0 Report to CFO;\n\u00a0\u00a0\u00a0\u00a0\u00a0\u00a0\u00a0\u00a0\u00a0\u00a0\u00a0\u00a0\u00a0 Managing internal and external financial reporting requirements including consolidation, compliance and controlling activities;\n\u00a0\u00a0\u00a0\u00a0\u00a0\u00a0\u00a0\u00a0\u00a0\u00a0\u00a0\u00a0\u00a0 Managing parties including external auditors, tax authorities and internal business units;\n\u00a0\u00a0\u00a0\u00a0\u00a0\u00a0\u00a0\u00a0\u00a0\u00a0\u00a0\u00a0\u00a0 Leading cash and liquidity management and credit risk management;\n\u00a0\u00a0\u00a0\u00a0\u00a0\u00a0\u00a0\u00a0\u00a0\u00a0\u00a0\u00a0\u00a0 Leading forecasting and budgeting;\n\u00a0\u00a0\u00a0\u00a0\u00a0\u00a0\u00a0\u00a0\u00a0\u00a0\u00a0\u00a0\u00a0 Setting departmental KPIs for performance tracking;\n\u00a0\u00a0\u00a0\u00a0\u00a0\u00a0\u00a0\u00a0\u00a0\u00a0\u00a0\u00a0\u00a0 Coordinating company secretarial matters for the Group;\n\u00a0\u00a0\u00a0\u00a0\u00a0\u00a0\u00a0\u00a0\u00a0\u00a0\u00a0\u00a0\u00a0 Support various internal stakeholders in matters relating to internal controls, tax, and project implementations\n\u00a0\u00a0\u00a0\u00a0\u00a0\u00a0\u00a0\u00a0\u00a0\u00a0\u00a0\u00a0\u00a0 To perform additional duties and other ad hoc assignments as requested\n\nRequirements:\n\n\u00a0\u00a0\u00a0\u00a0\u00a0\u00a0\u00a0\u00a0\u00a0\u00a0\u00a0\u00a0\u00a0 Degree holder in Accounting, Finance, Business Administration or related discipline, qualified accountant of HKICPA/ACCA\n\u00a0\u00a0\u00a0\u00a0\u00a0\u00a0\u00a0\u00a0\u00a0\u00a0\u00a0\u00a0\u00a0 At least 10-15 years in an all-rounded accounting function, experience with financial reporting and accounting with 5 years\u2019 experience in managerial level\n\u00a0\u00a0\u00a0\u00a0\u00a0\u00a0\u00a0\u00a0\u00a0\u00a0\u00a0\u00a0\u00a0 Strong analytical ability and forecasting skills with strong attention to detail\n\u00a0\u00a0\u00a0\u00a0\u00a0\u00a0\u00a0\u00a0\u00a0\u00a0\u00a0\u00a0\u00a0 Knowledge in China accounting, laws and regulations\n\u00a0\u00a0\u00a0\u00a0\u00a0\u00a0\u00a0\u00a0\u00a0\u00a0\u00a0\u00a0\u00a0 Experience in Big4 or financial institutions is a plus\n\u00a0\u00a0\u00a0\u00a0\u00a0\u00a0\u00a0\u00a0\u00a0\u00a0\u00a0\u00a0\u00a0 Experience in medical related industry is a plus\n\u00a0\u00a0\u00a0\u00a0\u00a0\u00a0\u00a0\u00a0\u00a0\u00a0\u00a0\u00a0\u00a0 Proficient in both written and spoken English & Chinese\n\u00a0\u00a0\u00a0\u00a0\u00a0\u00a0\u00a0\u00a0\u00a0\u00a0\u00a0\u00a0\u00a0 Good time management skill and able to work under pressure\n\u00a0\u00a0\u00a0\u00a0\u00a0\u00a0\u00a0\u00a0\u00a0\u00a0\u00a0\u00a0\u00a0 Strong communication skills and connect proactively across various levels in the Business Units\n\u00a0\u00a0\u00a0\u00a0\u00a0\u00a0\u00a0\u00a0\u00a0\u00a0\u00a0\u00a0\u00a0 Proficient user in Excel\nInterest parties please click \"apply now\" or please contact\u00a03427 9018 for more information.", "employment_types": ["Full Time"], "selling_points": [], "locations": ["Central"], "categories": ["Accounting", "Financial Controller"], "post_time": "2022-01-09T16:25:46Z", "salary": {"currency": null, "max": null, "min": null, "period": "monthly", "term": null}, "salary_visible": false, "title_keywords": ["financial controller"], "responsibilities": ["tax", "management", "tracking", "budgeting", "additional duties", "compliance", "financial reporting", "ad hoc assignments", "kpis", "report", "forecasting", "external auditors"], "requirements": {"degrees": ["degree holder"], "majors": ["finance", "accounting", "business administration"], "languages": ["english", "chinese"], "language_level": ["proficient"], "hard_skills": ["excel", "acca", "plus", "hkicpa"], "soft_skills": ["communication skills", "time management skill", "attention to detail", "work under pressure"], "languages_combined": [{"language": "english", "language_level": ["proficient"]}, {"language": "chinese", "language_level": ["proficient"]}]}, "experience_required": {"duration": ["5 years", "at least 10-15 years"], "field": ["managerial", "financial", "related", "financial institutions", "accounting", "medical"]}}, {"job_id": "100003009037754", "location_code": "hk", "company": "PrimeLink Executive Recruitment Consultants Ltd", "job_title": "Finance & Administration Manager", "description": "Hong Kong Food & Beverage Trading Company\n\n\nOur client, an established food and beverage trading company in Hong Kong, is seeking a high calibre Finance professional to join the management team.\n\nReporting to the Managing Director, you will provide leadership and management to a finance team and adopt full responsibility for all accounting processes, cashflow planning, costing, sales analysis, budgeting, forecasting, financial reporting and treasury.\u00a0 You will also liaise with external professional parties for statutory reporting and taxation issues, as well as oversee other operations including IT, human resources and general administration.\u00a0 The continuous improvement of internal and financial controls, and the streamlining of policies and procedures are imperative to ensuring maximum efficiency to support the business. \u00a0\u00a0\u00a0\n\nThe successful candidate will be a qualified accountant and have over 15 years\u2019 experience, ideally within the food trading or FMCG sector.\u00a0 Strong interpersonal skills with a hands-on, proactive, independent and energetic approach are essential.\u00a0 Fluency in English and Chinese are required.\n\nTo apply, please send your detailed resume in MS-Word by e-mail to Cynthia Au-Yeung by APPLY NOW\n", "employment_types": ["Full Time", "Permanent"], "selling_points": ["Provide leadership & management to a finance team", "Experience within the food trading or FMCG sector", "A qualified accountant"], "locations": ["Not Specified"], "categories": ["Accounting", "Finance / Accounting Manager", "Financial Controller", "Hospitality / F & B", "Food & Beverage"], "post_time": "2022-01-12T23:26:09Z", "salary": {"currency": null, "max": null, "min": null, "period": "monthly", "term": null}, "salary_visible": false, "title_keywords": ["finance & administration manager"], "responsibilities": ["administration", "management team", "management", "reporting", "taxation", "budgeting", "analysis", "operations", "policies", "procedures", "finance team", "financial reporting", "liaise with", "forecasting", "planning"], "requirements": {"degrees": [], "majors": [], "languages": ["english", "chinese"], "language_level": ["fluency"], "hard_skills": ["ms-word", "analysis"], "soft_skills": ["independent", "hands-on", "energetic", "interpersonal skills", "proactive", "leadership", "detailed"], "languages_combined": [{"language": "english", "language_level": ["fluency"]}, {"language": "chinese", "language_level": ["fluency"]}]}, "experience_required": {"duration": ["15 years"], "field": ["food", "fmcg", "trading"]}}, {"job_id": "100003009038686", "location_code": "hk", "company": "Midland Holdings Limited", "job_title": "Financial Controller", "description": "Responsibilities:\n\nOverseas finance and accounting functions of the Group in HK\nLead HK accounting team & be in charge of overall financial planning, consolidation & reporting, budgeting & forecasting, cost control, treasury management and taxation matters\nProvide strategic advice and suggestions on top management decisions based on financial analysis\nDevelop strategies, review business performance and assess opportunities which will support the group\u2019s continued expansion\nIdentify opportunities for process improvement and key cost driver for cost effectiveness\nFormulate internal control system, and establish/ optimize workflow for operational effectiveness and efficiency\nLiaise with external parties, such as auditors and bankers\n\nRequirements:\n\nQualified Accountant with a degree or above in Accounting or Finance or other related discipline\nAt least 10 years' of financial management experience with a minimum of 6 years at senior managerial level in listed / investment company\nMature, self-motivated, independent combined with good interpersonal and communication skills\nProficiency in both spoken and written English and Chinese\n\nCompetitive Salary will be offered to the right candidate. \u00a0For application, please update your resume by clicking \"APPLY NOW\" or complete the online application form which is available at\u00a0https://www.midland.com.hk/joinus/\u00a0and sent to the corresponding email address together with your full resume, present & expected salary.\n\nAll personal data collected will be used for recruitment purpose only. \u00a0Applicants not hearing from us within 2 months may consider their applications unsuccessful. \u00a0All personal data supplied will be kept for a reasonable period in accordance with the legal requirements.\n\nAs an Equal Opportunities Employer, we are committed to eliminating discrimination in employment. Our vacancy is open to all applicants meeting the basic entry requirement irrespective of their disability, sex, marital status, pregnancy, age, family status, sexual orientation and race.", "employment_types": ["Full Time", "Permanent"], "selling_points": ["Min 6yr at SENIOR managerial level in listed firm", "Develop strategies, review business performance", "Group FP&A,consolidation,cost control,treasury"], "locations": ["Cheung Sha Wan"], "categories": ["Accounting", "Consulting", "Financial Analyst", "Financial Controller"], "post_time": "2022-01-12T03:12:42Z", "salary": {"currency": null, "max": null, "min": null, "period": "monthly", "term": null}, "salary_visible": false, "title_keywords": ["financial controller"], "responsibilities": ["reporting", "management", "taxation", "develop strategies", "cost", "budgeting", "review", "external parties", "financial analysis", "cost control", "liaise with", "forecasting", "internal control", "planning"], "requirements": {"degrees": ["degree or above"], "majors": ["finance", "accounting"], "languages": ["english", "chinese"], "language_level": ["proficiency"], "hard_skills": ["basic"], "soft_skills": ["communication skills", "self-motivated", "independent", "mature", "committed", "interpersonal"], "languages_combined": [{"language": "english", "language_level": ["proficiency"]}, {"language": "chinese", "language_level": ["proficiency"]}]}, "experience_required": {"duration": ["at least 10 years", "minimum of 6 years"], "field": ["managerial", "management", "investment", "financial"]}}, {"job_id": "100003009053604", "location_code": "hk", "company": "Thales Transport & Security (Hong Kong) Limited", "job_title": "Project Cost Control Officer", "description": "Responsibilities\n\nUnderstand the revenue recognition plan at project start and the billing plan (invoice and progress payments), manage and proceed the revenue recognition and billing with Projects Manager and Business Control Manager\nUpdate revenue recognition plan as required\nCheck, control and monitor movements in Actual and Committed Costs on a monthly basis\nManage and forecast cash movements monthly. Track cash-in overdue status; give alert to Project Managers and Business Control Manager.\nProvide all necessary support to Project Managers on financial matters\nEnsure that project data reporting is in line with approved Project reviews\nCoordinate with the project team to ensure consistent accounting (revenue & margin recognition) and reporting across the project.\nDevelop strong relationships and continuous communication flows with project team\nEnsure that all financial processes & instructions and internal controls, including delegation of authorities, are implemented\u00a0 and compliant\nSupport budget, forecasts and monthly closing\n\nRequirements\n\nBachelor degree in Accounting/Finance or related discipline\nAt least 5 years\u2019 experience of project accounting & controlling\nExperience long-term contract management, a plus\nKnowledge of SAP, Excel\nProficiency in both written and spoken English.\nHighly articulate, confident team player able to communicate and work under pressure\nExperience in complex international environment", "employment_types": ["Full Time", "Permanent"], "selling_points": ["5+ years of project cost control experience", "Stable working hours", "Hong Kong region focused"], "locations": ["Mong Kok"], "categories": ["Accounting", "Finance / Accounting Manager", "Financial Controller", "Others"], "post_time": "2022-01-17T07:13:24Z", "salary": {"currency": null, "max": null, "min": null, "period": "monthly", "term": null}, "salary_visible": false, "title_keywords": ["officer"], "responsibilities": ["reporting", "control", "data", "invoice", "budget", "monitor", "coordinate with", "develop", "communication", "payments", "plan", "forecast", "costs"], "requirements": {"degrees": ["degree", "bachelor"], "majors": ["finance", "accounting"], "languages": ["english"], "language_level": ["proficiency"], "hard_skills": ["excel", "plus", "sap"], "soft_skills": ["confident", "articulate", "team player", "work under pressure"], "languages_combined": [{"language": "english", "language_level": ["proficiency"]}]}, "experience_required": {"duration": ["at least 5 years"], "field": ["management", "accounting"]}}, {"job_id": "100003009043077", "location_code": "hk", "company": "Headsearch21 Consultancy Ltd", "job_title": "Chief Financial Controller, CFO (5 days, good package, Retail Company, Sizable Company)", "description": "To expand the business, our client is seeking for high caliber candidate to fill up the following position:\n\n\nResponsibilities:\u00a0\u00a0\n\nManage finance related activities both internally and externally for the company\nResponsible for providing business advice and support to top management for business planning, expansion, strategic decision, budget forecasting and allocation, taxation, corporate governance etc.\nTo provide professional advice to the senior management team on strategic business development\nTo ensure high standards of financial controls and reporting\nMaintain and ensure relevant statutory/regulatory requirements\nProvide assistance on board management, and prepare relevant materials, resolutions, minutes, annual report and other documents\nAdvise the Board of corporate governance requirements and ensure compliance with the Listing Rules and other regulatory requirements\n\nRequirements:\u00a0\u00a0\n\nBachelor's Degree in Finance, Accounting, Business or related disciplines and professional accounting qualification,\u00a0such as ACCA and /or HKICPA\nAt least 15 years related experience\u00a0\nExperience in listed Company and Sizable Company is a must\nExperience in Retail Company\nStrategic, good business acumen and communication skills\nProficiency in spoken and written English and Putonghua\nMature, able to work independently and under pressure, resourceful and self-driven with a strong sense of commitment;\nGood interpersonal and organizational skills;\n\nInterested parties, please click the \"Apply Now\" or send\u00a0 your updated resume with\u00a0Current\u00a0and\u00a0Expected salary\u00a0in MS word format to cv @headsearch21.com\u00a0\n\nAll information collected will be treated in strict confidence and be used for recruitment purpose only\n\nRef#:\u00a0CA01007\n\nCompany Web-Site:\u00a0www.headsearch21.com\u00a0\n\nHotline: (852) 3188 3586", "employment_types": ["Full Time", "Permanent"], "selling_points": ["Exp in Listed Company", "5 Days ,Good Salary,Good package", "Must Exp in Sizable company"], "locations": ["Not Specified"], "categories": ["Accounting", "Financial Analyst", "Financial Controller", "Others"], "post_time": "2022-01-12T09:44:00Z", "salary": {"currency": "HKD", "max": null, "min": 160000, "period": "monthly", "term": null}, "salary_visible": true, "title_keywords": ["cfo", "financial controller"], "responsibilities": ["taxation", "management", "reporting", "regulatory requirements", "budget", "provide assistance", "ensure compliance", "maintain", "report", "senior management", "forecasting", "listing", "planning"], "requirements": {"degrees": ["degree", "bachelor"], "majors": ["business", "finance", "related disciplines", "accounting"], "languages": ["putonghua", "english"], "language_level": ["proficiency"], "hard_skills": ["acca", "acumen", "hkicpa"], "soft_skills": ["communication skills", "work independently", "organizational skills", "under pressure", "resourceful", "mature", "business acumen", "interpersonal", "driven"], "languages_combined": [{"language": "putonghua", "language_level": ["proficiency"]}, {"language": "english", "language_level": ["proficiency"]}]}, "experience_required": {"duration": ["at least 15 years"], "field": ["related", "retail"]}}, {"job_id": "100003009050161", "location_code": "hk", "company": "Magic Search Limited", "job_title": "Regional Cost Controller (Luxury Brand)", "description": "Our client is a global leading luxury Brand It is now looking for a Regional Finance Manager to join their team.\n\nKey Responsibilities\n\nPrepare and consolidated costing report with comparison against Budget and Forecast with comment\nWork closely with other functional team to ensure alignment and to reconcile any discrepancy\nPrepare other regular cost reporting or ad hoc analysis for management review of business performance\u00a0\nDevelop and replicate excel\u00a0budget/forecast\u00a0templates for\u00a0Asia\u00a0market\u00a0and\u00a0validation\u00a0\u00a0\nAssist\u00a0with the\u00a0budget & forecast\u00a0consolidation and review\u00a0process\nValidate system input and co-ordinate necessary follow-up with market\u00a0finance team\nAssist with analysis during budget and forecast process\nCost Management and Budget follow-up\nAssist in establishing/improving means of regional\u00a0cost\u00a0tracking\u00a0and budget follow-up\u00a0process\nRecommend and develop relevant reports and analysis\nAssist with SAP & Planning and Consolidation tool co-ordination, vendor master data creation and maintenance, and other ad hoc projects\n\nRequirements\n\nBachelor degree in Finance, Accounting or other related subjects\n6-7 years relevant retail working experience\nAbility to extract, organise, analyse and report data\nGood communication skills\nGood command in English and Chinese\u00a0", "employment_types": ["Full Time", "Permanent"], "selling_points": ["6-7 years experience", "luxury brand", "audit experience is a plus"], "locations": ["Not Specified"], "categories": ["Accounting", "Credit Control", "Financial Analyst", "Financial Controller"], "post_time": "2022-01-14T09:53:47Z", "salary": {"currency": null, "max": null, "min": null, "period": "monthly", "term": null}, "salary_visible": false, "title_keywords": [], "responsibilities": ["data", "budget", "system input", "management review", "relevant reports", "ad hoc", "develop", "finance team", "forecast", "report", "reporting", "cost", "management", "review", "tracking", "maintenance", "forecast process", "analysis", "ad hoc projects", "planning"], "requirements": {"degrees": ["degree", "bachelor"], "majors": ["finance", "accounting"], "languages": ["english", "chinese"], "language_level": ["good command"], "hard_skills": [], "soft_skills": ["communication skills"], "languages_combined": [{"language": "english", "language_level": ["good command"]}, {"language": "chinese", "language_level": ["good command"]}]}, "experience_required": {"duration": ["6-7 years"], "field": ["retail"]}}, {"job_id": "100003009033617", "location_code": "hk", "company": "", "job_title": "Financial Controller", "description": "We are a market leader in Hong Kong, China and ASEAN road transportation services. With very aggressive business growth agenda in developing new product lines, the company has set up own office and facility network in different continents to serve at customer convenience.\n\n\nJob Responsibilities:\nBudgeting, forecasting and analysis for region, reviewing business strategy and finances\nMonitor daily accounting functions, reporting and working closely with the Regional Finance Function\nManagement of tax planning process, compliance, and transfer pricing\nSupport various internal stakeholders in matters relating to internal controls, tax, and project implementations\nAd hoc assignments and projects\nRequirements:\nACCA, Degree or above in Accounting, Finance, or related disciplines\nAt least 15 years in an all-rounded accounting function, experience with financial reporting and accounting\nPrevious experience working in an audit firm is a plus, team leading experience preferred\nQualified Accountant is required, excellent business acumen and able to work with overseas staff\nExposure to Logistics or FMCG industry preferred\nAble to be based in Hong Kong, with occasional travel to Asian\nFluency in English and Chinese (Cantonese & Mandarin)\nCandidate with less experience will be considered as Senior Finance Manager\nWe offer excellent career development and attractive remuneration package to the right candidate.\n\nInformation supplied will be treated in strict confidence and used in accordance with the Personal Data (Privacy) Ordinance. Applicants not invited for interview within 2 months may consider their applications unsuccessful.\n\nInterested individuals please call +852 2473 2828 for more information. Only suitable candidates will be contacted.\n", "employment_types": ["Full Time", "Permanent"], "selling_points": ["Budgeting, forecasting and analysis for region", "Qualified Accountant with 15ys exp. is required", "Support various internal stakeholders"], "locations": ["Tsuen Wan Area"], "categories": ["Accounting", "Chief Accountant", "Financial Analyst", "Financial Controller"], "post_time": "2022-01-10T01:22:17Z", "salary": {"currency": null, "max": null, "min": null, "period": "monthly", "term": null}, "salary_visible": false, "title_keywords": ["financial controller"], "responsibilities": ["tax", "reporting", "management", "budgeting", "analysis", "planning process", "monitor", "compliance", "ad hoc assignments", "daily accounting", "forecasting"], "requirements": {"degrees": ["degree or above"], "majors": ["related disciplines", "finance", "accounting"], "languages": ["cantonese", "english", "chinese", "mandarin"], "language_level": ["fluency"], "hard_skills": ["acca", "fmcg industry", "acumen", "plus"], "soft_skills": ["business acumen"], "languages_combined": [{"language": "cantonese", "language_level": []}, {"language": "english", "language_level": ["fluency"]}, {"language": "chinese", "language_level": ["fluency"]}, {"language": "mandarin", "language_level": []}]}, "experience_required": {"duration": ["at least 15 years"], "field": ["financial", "finance manager", "audit", "accounting", "team"]}}, {"job_id": "100003009042770", "location_code": "hk", "company": "Michael Page", "job_title": "Financial Controller - Global E-Commerce Start Up 100K - 150K", "description": "Perfect opportunity for any FC level candidates who had experiences with start up companies and like to take on the role of an FC position, targeting to act also as an IR Director in a reputable global size E-commerce & Logistic Group. This role offers a great exposure and opportunity to join a very exciting corporation\n\nClient Details\n\nOur client is headquartered in Asia with an extremely sizable team. This Group currently operating in more than 30+ countries and currently still expanding. They are offering a fantastic opportunity for a Senior FC + IR candidate to assist the company expansion plan, targeting the global market and investors.\n\nDescription\n\nFinancial Modelling, Corporate Operational and Financial Analyses\nLeading a team of 5 reviewing daily and monthly accounting matters\nOrganize investors and financing conferences. Fund raising presentation\nResponsible of corporate financing project as well as giving advice to multiple external parties\nContinue research on E-comm development to support IR pitching\n\nProfile\n\nAt least 5 years of IR experiences, start up company background will be a plus\nSensitive to numbers and analytical with strong communication skills\nFluent in both written and spoken in English and Chinese\nEducational background in Finance or related field\n\nJob Offer\n\nGroup Position\nMedical & Dental insurance\n% bonus from raised fund\nOther attractive benefits\n\nTo apply online please click the 'Apply' button below. For a confidential discussion about this role please contact Sunny Chan on +852 3602 2466.", "employment_types": ["Full Time", "Permanent"], "selling_points": ["Expanding Business", "Global Position", "Investor Relations"], "locations": ["Not Specified"], "categories": ["Accounting", "Financial Controller", "Banking / Finance", "Corporate Finance", "Management", "Top Executives (CEO, CFO, CTO, GM, MD etc.)"], "post_time": "2022-01-12T08:45:37Z", "salary": {"currency": null, "max": null, "min": null, "period": "monthly", "term": null}, "salary_visible": false, "title_keywords": ["financial controller"], "responsibilities": ["external parties", "communication", "conferences", "plan", "insurance"], "requirements": {"degrees": [], "majors": [], "languages": ["english", "chinese"], "language_level": ["fluent"], "hard_skills": ["plus", "e-commerce"], "soft_skills": ["communication skills", "sensitive to numbers", "presentation", "responsible"], "languages_combined": [{"language": "english", "language_level": ["fluent"]}, {"language": "chinese", "language_level": ["fluent"]}]}, "experience_required": {"duration": ["at least 5 years"], "field": ["e-commerce"]}}, {"job_id": "100003009049785", "location_code": "hk", "company": "Michael Page", "job_title": "Finance Manager, 55k, PRC Firm", "description": "Our client is a reputable property company. They are now looking for a talent Finance Manager to join their finance team.\n\nClient Details\n\nOur client is a reputable property company. They are now looking for a talent Finance Manager to join their finance team.\n\nDescription\n\nReporting to the GM Finance, you will be responsible for\n\nPreparing for the Main Board IPO listing for the company\nHandling company secretarial matters after IPO\nPreparing annual and interim reports\nStrengthening internal controls, corporate governance and streamline accounting procedures to comply with the Hong Kong Listing Rules / standards\nProviding recommendations to enhance financial performance and business opportunities\nLiaising with CPA firm for audit and tax related matters\n\nProfile\n\nPRC University is highly preferred\n\nExcellent communication skills (English and Mandarin)\n\nDegree Holder in Business/Accounting/Finance\n\nJob Offer\n\nMain Board IPO Experience\nCompetitive Remuneration\n\nTo apply online please click the 'Apply' button below.\nFor a confidential discussion about this role please contact Nicole Hui on +852 3412 4832.", "employment_types": ["Full Time", "Permanent"], "selling_points": ["CPA is a must", "PRC", "13 Months Guaranteed with Bonus"], "locations": ["Not Specified"], "categories": ["Accounting", "Chief Accountant", "Finance / Accounting Manager", "Financial Controller"], "post_time": "2022-01-14T09:14:04Z", "salary": {"currency": null, "max": null, "min": null, "period": "monthly", "term": null}, "salary_visible": false, "title_keywords": ["finance manager"], "responsibilities": ["tax", "reporting", "business opportunities", "procedures", "liaising with", "audit", "communication", "reports", "finance team", "contact", "listing"], "requirements": {"degrees": ["degree holder"], "majors": ["finance", "business", "accounting"], "languages": ["english", "mandarin"], "language_level": ["excellent"], "hard_skills": ["cpa", "gm"], "soft_skills": ["communication skills", "responsible"], "languages_combined": [{"language": "english", "language_level": ["excellent"]}, {"language": "mandarin", "language_level": ["excellent"]}]}, "experience_required": {"duration": [], "field": []}}, {"job_id": "100003009043873", "location_code": "hk", "company": "Ambition", "job_title": "FP&A Director (M&A exp needed)", "description": "Our client is a renowned MNC with solid presence across the globe. To facilitate their company growth and increasing number of projects, they are looking for a high calibre FP&A Director to join their team and take care of the FP&A, finance projects and corporate finance duties across the region.\n\nReport to the Board of Director, your responsibilities will include:\n\n\nLeading FP&A functions and reporting to C-suites\nHandle finance projects globally and responsible for the strategic planning to facilitate business decisions\nAdvise and propose new business strategies/ investment initiatives/ M&A projects to Senior stakeholders\nStrong stakeholder management and influencing skills, responsible for presentation to global stakeholders\nOverseeing all finance, accounting, due diligence and compliance issues\nEnsure proper financial management and reporting\nPreparing financial modelling, investment analysis, scenario studies to support the group's investment decisions and finance projects\nEnsure compliance of relevant regulations, policies and guidelines and monitor the regular updating of policies and accounting standards\nReview daily business operation and formulate management reports\nTo assist in ad hoc corporate projects and strategic Planning\n\nTo qualify, the candidate must process:\n\n\nQualified accountant with ACCA, HKICPA or equivalent qualification\nAt least 8-15 years of working experience, ideally in MNC with solid people management experiences\nConsumer-sector background is a plus, not a must\nCandidates with consulting plus in-house background is preferred\nExcellent communication and business partnering experiences\nExcellent analytical and leadership skills\nFluent English and Mandarin\n\nPlease contact Kady Wu through calls or whatsapp at (852) 3103 4314 or Email directly to kady.wu@ambition.com.hk or click APPLY NOW.\n\nFor more information please visit http://www.ambition.com.hk/\n\nData provided is for recruitment purposes only.\n\n\nIf this job isn't quite right for you, but you know someone who would be great at this role, why not take advantage of our referral scheme? We offer HKD1000 in Apple gift cards for every referred candidate who we place in a role. Terms & Conditions Apply. https://www.ambition.com.hk/refer-a-friend", "employment_types": ["Full Time", "Permanent"], "selling_points": ["Solid FP&A + Corporate Fin exp.", "Consulting + in house background preferred", "Fast-paced, consumer sector"], "locations": ["Not Specified"], "categories": ["Accounting", "Financial Controller"], "post_time": "2022-01-13T02:15:55Z", "salary": {"currency": "HKD", "max": 159999, "min": 70000, "period": "monthly", "term": null}, "salary_visible": true, "title_keywords": ["director"], "responsibilities": ["regulations", "consulting", "data", "communication", "due diligence", "ad hoc", "compliance", "monitor", "report", "reporting", "management", "strategic planning", "investment analysis", "review", "contact", "business operation", "guidelines", "policies", "finance duties", "ensure compliance", "management reports", "recruitment"], "requirements": {"degrees": [], "majors": [], "languages": ["english", "mandarin"], "language_level": ["fluent"], "hard_skills": ["acca", "plus", "analysis", "scheme", "management reports", "c", "whatsapp", "hkicpa"], "soft_skills": ["communication", "leadership skills", "presentation", "responsible"], "languages_combined": [{"language": "english", "language_level": ["fluent"]}, {"language": "mandarin", "language_level": ["fluent"]}]}, "experience_required": {"duration": ["at least 8-15 years"], "field": ["people management", "business"]}}, {"job_id": "100003009039279", "location_code": "hk", "company": "Top Asia Holdings Limited", "job_title": "General Manager - Accounting Department", "description": "The incumbent will lead the accounting departments in Hong Kong and in China, to ensure the financial reports and management accounts are compiled on a timely and accurate basis, and to oversee and plan for the financial needs of the business units/projects.\n\nREQUIREMENTS:\n\n- Degree in Accounting with professional qualification\n\n- Possess over 10 years senior management experience as obtained from large audit firms and in commercial sector \u00a0\n\n- Solid experience in listed company financial reporting, budget planning and control, financing and tax planning\n\n- Excellent command of both spoken and written English and Chinese\n\nInterested parties please send resume with availability & past/expected salary to the HR Manager.\n\nAll data collected will be used for recruitment purposes only.", "employment_types": ["Full Time"], "selling_points": [], "locations": ["Central"], "categories": ["Accounting", "Financial Controller", "Taxation", "Others"], "post_time": "2022-01-11T16:01:49Z", "salary": {"currency": null, "max": null, "min": null, "period": "monthly", "term": null}, "salary_visible": false, "title_keywords": ["general manager", "accounting"], "responsibilities": ["tax", "financial reports", "management", "budget planning", "control", "audit", "financial reporting", "plan", "senior management", "planning"], "requirements": {"degrees": ["degree"], "majors": ["accounting"], "languages": ["english", "chinese"], "language_level": ["excellent"], "hard_skills": [], "soft_skills": ["timely", "accurate"], "languages_combined": [{"language": "english", "language_level": ["excellent"]}, {"language": "chinese", "language_level": ["excellent"]}]}, "experience_required": {"duration": ["10 years"], "field": ["management", "financing", "financial", "audit", "commercial", "planning"]}}, {"job_id": "100003009048247", "location_code": "hk", "company": "Belton Group", "job_title": "Finance Manager / Senior Finance Manager", "description": "Job Responsibilities:\n\nLead a team and oversee the financial and management reporting, consolidation, and company secretarial functions\nLead the process re-engineering, including system and work-flow improvement project to drive consistency, efficiency and accuracy of the finance functions\nSupervise the budgetary control and forecasting process\nAct as the key contact point to external parties for all audit, legal, company secretarial and tax matters\nProvide financial analysis to management with value added comments\nSupport IPO, M&A activities, Group restructuring and Tax planning exercise\nPerform other ad hoc projects as assigned\nReport to the VP - Finance\n\n\u00a0Job Requirements:\n\nBachelor Degree in Finance/Accounting or Equivalent with professional accountancy qualification\nMinimum of 8 years financial reporting and relevant experience gained from sizable organization and Big 4 audit firm an advantage\nFamiliar with HK, Thailand and PRC accounting, taxation and company secretarial regulations\nKnowledge in Oracle\u00a0is preferred\nProficiency in MS Office/Excel\nAble to perform under pressure independently with strong sense of commitment and be self-motivated\nFluency in English, Mandarin and Cantonese\n\nWe offer 5-day work week, 13th month salary, performance bonus, medical insurance scheme and long-term career prospect to the right candidate. For interested parties, please send your detailed resume with current and expected salary via jobs.DB.\n\nFor more information about us, please visit our website at: http://www.beltontechnology.com.\n\nCandidates not invited for interview within 8 weeks may consider their applications unsuccessful. Applications will be treated in strict confidence. Personal data collected will be used for recruitment purpose only.", "employment_types": ["Full Time"], "selling_points": ["Double Pay and Performance Bonus", "Bachelor Degree in Finance/Accounting", "Minimum of 8 years financial reporting experience"], "locations": ["Tsing Yi"], "categories": ["Accounting", "Finance / Accounting Manager", "Financial Controller"], "post_time": "2022-01-14T06:53:05Z", "salary": {"currency": null, "max": null, "min": null, "period": "monthly", "term": null}, "salary_visible": false, "title_keywords": ["senior finance manager", "finance manager"], "responsibilities": ["tax", "control", "management", "external parties", "comments", "audit", "financial analysis", "lead a team", "ad hoc projects", "management reporting", "contact", "report", "forecasting", "tax matters", "re-engineering", "planning"], "requirements": {"degrees": ["degree", "bachelor"], "majors": ["finance", "accounting", "accountancy"], "languages": ["cantonese", "english", "mandarin"], "language_level": ["fluency"], "hard_skills": ["excel", "oracle", "ms office", "prc accounting"], "soft_skills": ["self-motivated", "independently", "under pressure"], "languages_combined": [{"language": "cantonese", "language_level": ["fluency"]}, {"language": "english", "language_level": ["fluency"]}, {"language": "mandarin", "language_level": ["fluency"]}]}, "experience_required": {"duration": ["minimum of 8 years"], "field": ["sizable organization", "big 4", "audit", "relevant experience", "financial"]}}, {"job_id": "100003009048912", "location_code": "hk", "company": "Hays", "job_title": "Finance Manager - Top U.S Private Equity (AUM USD 2B+)", "description": "Job Scope:\n\nLead and coordinate the development and delivery of financial policies, procedures, guidelines, and protocols to ensure the company complies with compliances, group regulations and good financial practice\nReview the monthly flash results, operating statement, quarterly forecast, annual budget and any other financial reporting as requested by stakeholders\nMonitor cashflow and implement proper control procedures to safeguard all cash inflows including daily sales and cash reconciliation for retail shops, disposal events on a timely basis\nManage the internal control procedures to ensure the organization is not exposed to undue risks and to safeguard company assets. Make sure proper authorization for business activities are imposed in the company\nEnsure the accuracy of inventory records. Coordinate and in charge of cycle count/bi-annual stocktaking and to reconcile physical quantities with book records\nUndertake strategic and tactical financial analysis, modeling, and evaluation to support management and operation leaders in their decision making\nIdentify and communicate the strategy and business plan needed to implement with other internal stakeholders e.g. inventory management, pricing decision, GP monitoring, promotion discount. Anticipate coming challenges and opportunities to achieve business goals and continuous improvement on business performance\nLead Admin, IT and PRC HR team. Coordinate the development/adoption and implementation of relevant policies within these functions\nTake initiative in reviewing and enhancing the company\u2019s ERP systems and implement the changes so as to improve operational efficiency and cost effectiveness\nReview annual profits tax returns\nReview annual accounts and liaise with auditors for the annual audit\n\nRequirements:\n\nBachelor\u2019s degree or above in accounting or finance or related discipline with professional qualification in accounting\nMinimum 15 years financial management experience including 5 years at management level\nFellow/member of professional bodies in accounting (e.g. HKICPA/ACCA)\nGood knowledge of computerised accounting systems, Microsoft Office applications and other PC software\nExperience in leading admin and HR function at management level\nAbility to develop financial strategy to achieve cost reduction and/or revenue generation\nAbility to solicit supports, to manage and implement business solution\nProficient presentation and communication skills to interact with all level of staff\nAbility to lead, motivate and develop staff\nExcellent command in both spoken and written English and Chinese\nWe are an equal opportunity employer. All applications received will be used exclusively for selection purpose and handled confidentially by authorized personnel only. Your application may also be considered for other suitable positions within the Swire group. (Please indicate clearly on your application if you would not like to be considered for other suitable positions within the group.)\u00a0Unsuccessful applications will be destroyed after an appropriate time.", "employment_types": ["Full Time", "Permanent"], "selling_points": ["Top-tier private Equity firm", "Competitive Package", "Great development opportunities"], "locations": ["Not Specified"], "categories": ["Accounting", "Accountant", "Finance / Accounting Manager", "Financial Controller"], "post_time": "2022-01-14T07:41:01Z", "salary": {"currency": null, "max": null, "min": null, "period": "monthly", "term": null}, "salary_visible": false, "title_keywords": ["finance manager"], "responsibilities": ["regulations", "business goals", "inventory", "financial policies", "budget", "inventory management", "communication", "evaluation", "liaise with", "internal control", "control", "monitor", "implementation", "develop", "forecast", "business plan", "business activities", "management", "cost", "annual audit", "review", "procedures", "monitoring", "cycle count", "pc software", "tax", "guidelines", "policies", "hr", "systems", "coordinate", "financial analysis", "financial reporting"], "requirements": {"degrees": ["degree or above", "bachelor"], "majors": ["finance", "accounting"], "languages": ["english", "chinese"], "language_level": ["excellent"], "hard_skills": ["erp systems", "acca", "bi", "microsoft office", "financial analysis", "make", "hkicpa", "flash", "accounting systems", "pc", "internal control"], "soft_skills": ["communication skills", "timely", "initiative", "presentation", "decision making"], "languages_combined": [{"language": "english", "language_level": ["excellent"]}, {"language": "chinese", "language_level": ["excellent"]}]}, "experience_required": {"duration": ["5 years", "minimum 15 years"], "field": ["hr", "management", "admin", "financial"]}}, {"job_id": "100003009042563", "location_code": "hk", "company": "mReferral Corporation (HK) Ltd   \u7d93\u7d61\u96c6\u5718(\u9999\u6e2f)\u6709\u9650\u516c\u53f8", "job_title": "Senior Manager (Finance & HR)", "description": "\nYour new company\nYour new company is a top-tier private equity firm with a growing presence in Asia.\n\nYour new role\nIn your new role, you will be responsible for a wide variety of finance functions. You will report into the local CFO and be responsible for :\n\n\nFund Accounting\nCorporate accounting\nRegulatory Reporting to the SFC - FRR (4, 9)\nMonth-end reporting for SPVs\nAudit co-ordination for Funds and SPVs\nDeal Support\n\n\nWhat you'll need to succeed\nTo succeed, you will need 5+years of finance experience within Private Equity and speak fluent English\n\nWhat you need to do now\nIf you are interested in This Position or other Accounting positions in the Asset Management (Private Equity, Hedge Fund, etc) / Investment Banking industry please send your Resume to jason.tsang@hays.com.hk or contact me directly at +852 2230 7901.", "employment_types": ["Full Time", "Permanent"], "selling_points": ["Qualified CPA and Chartered Secretary", "Min 10 years experience in Finance and Account", "Min 3 years in managerial capacity"], "locations": ["Wan Chai"], "categories": ["Accounting", "Chief Accountant", "Finance / Accounting Manager", "Financial Controller"], "post_time": "2022-01-12T07:59:08Z", "salary": {"currency": null, "max": null, "min": null, "period": "monthly", "term": null}, "salary_visible": false, "title_keywords": ["senior manager", "hr"], "responsibilities": ["reporting", "month-end", "audit", "contact", "banking", "report", "asset management"], "requirements": {"degrees": [], "majors": [], "languages": ["english"], "language_level": ["fluent"], "hard_skills": ["private equity", "frr"], "soft_skills": ["interested in", "responsible"], "languages_combined": [{"language": "english", "language_level": ["fluent"]}]}, "experience_required": {"duration": [], "field": ["finance"]}}, {"job_id": "100003009032593", "location_code": "hk", "company": "Sun Cupid Technology (HK) Ltd", "job_title": "Financial Controller", "description": "Responsibilities:\n\nLead the Finance Department over financial control and accounting functions, including management accounts reporting, forecast & budgeting, tax compliance and company secretarial matters handling\nIdentify performance drivers for both revenue and expenses and highlight any business risks and opportunities\nSupport management in key strategic initiatives and business improvement projects\nLead and supervise the HR and Administration team\nOversee full spectrum of HR function, including manpower planning and budgeting, talent acquisition, compensations and benefits, performance management, learning and development, employee relations\nReview and ensure HR policies and procedures are in alignment with operation needs and in compliance with labour regulations\nMonitor all spectrum of administration support to office, including maintenance, clean procurement of office supplies and other administration related matters\n\nRequirement:\n\nDegree holder in Finance or Accounting, qualified CPA and Chartered Secretary\nAt least 10 years' experience in finance and accounting with minimum 3 years' in managerial capacity\nExcellent business acumen with good analytical skills\nProactive, meticulous and able to work independently\nExcellent communication and effective people management skills\n\nWe offer attractive compensation package & career prospects to the right candidates. Interested parties please send your full resume with\u00a0availability,\u00a0present & expected salary to HR Department by clicking \"Apply Now\".\n\nPersonal data collected will be used for recruitment purpose only.", "employment_types": ["Full Time", "Permanent"], "selling_points": ["Degree in Accounting/Finance or related fields", "Minimum of 5-8 years of working experience", "Willing to travel overseas"], "locations": ["Lai Chi Kok"], "categories": ["Accounting", "Finance / Accounting Manager", "Financial Controller", "Others"], "post_time": "2022-01-07T11:44:59Z", "salary": {"currency": null, "max": null, "min": null, "period": "monthly", "term": null}, "salary_visible": false, "title_keywords": ["financial controller"], "responsibilities": ["tax", "regulations", "control", "management", "maintenance", "office supplies", "budgeting", "hr", "compliance", "expenses", "review", "accounts reporting", "policies", "procedures", "monitor", "planning", "forecast", "administration"], "requirements": {"degrees": ["degree holder"], "majors": ["finance", "accounting"], "languages": [], "language_level": [], "hard_skills": ["cpa", "analytical skills", "acumen"], "soft_skills": ["meticulous", "work independently", "analytical skills", "communication", "business acumen", "proactive"], "languages_combined": []}, "experience_required": {"duration": ["at least 10 years", "minimum 3 years"], "field": ["finance", "accounting", "managerial"]}}, {"job_id": "100003009049345", "location_code": "hk", "company": "Shanghai Commercial Bank Ltd", "job_title": "Officer, Finance", "description": "Responsibilities:\n\nSupport the implementation of system revamp and involve in the system building stage\n\nParticipate in each of the test phases e.g. getting user requirements, data migration process, validation of accounting treatments and accounting entries, and UAT test arrangement and workflow\nPerform reconciliation and checking on the accounting entries generated, interfaces and reports generated after the system go live\nEnsure the tasks and issues are in line with business action plans\nEscalate the issues and risks to the designated task force\nAct as a main contact point between vendor and Finance Division\nAssist to prepare documentation related to the project \u00a0\u00a0\nHandle clean up or ad-hoc request to the end of the project\nPerform BAU tasks as required\n\nRequirements:\n\nDegree holder with accounting professional qualifications\n\nMinimum 1 year of relevant experience, preferably in banking or accounting industry\nSolid technical background with understanding or hands-on experience in software development and web technologies\nGood written and verbal communication skills\nSolid organizational skills including attention to details and multi-tasking skills\n\nAttractive remuneration package will be offered to the right candidates. Interested parties please click \"Apply Now\" to submit your full resume with current and expected salary to the Human Resources Division.\n\nPlease visit us at www.shacombank.com.hk for more information about our Bank.\n\nAll personal data collected will be used for recruitment related purposes strictly in accordance with the Bank's personal data policies, a copy of which will be provided immediately upon request by contacting our Personal Data Compliance Officer. Applicants who are not contacted within two months may consider their applications unsuccessful and the personal data collected from the applicants will be retained for no longer than two years from the date of rejection during which the applicants may be considered for other suitable positions within the Bank.\u00a0", "employment_types": ["Full Time", "Permanent"], "selling_points": ["Exercise effective control on the operations", "UAT test arrangement and workflow", "Project Management"], "locations": ["North Point"], "categories": ["Accounting", "Financial Controller", "Others", "Banking / Finance", "Others"], "post_time": "2022-01-15T03:50:19Z", "salary": {"currency": null, "max": null, "min": null, "period": "monthly", "term": null}, "salary_visible": false, "title_keywords": ["officer"], "responsibilities": ["ad-hoc", "revamp", "uat", "data", "implementation", "checking", "reports", "contact", "documentation", "plans", "migration"], "requirements": {"degrees": ["degree holder"], "majors": ["accounting"], "languages": [], "language_level": [], "hard_skills": ["web technologies", "professional qualifications"], "soft_skills": ["communication skills", "organizational skills", "hands-on", "attention to details", "multi-tasking skills"], "languages_combined": []}, "experience_required": {"duration": ["minimum 1 year"], "field": ["software development", "accounting", "relevant experience", "banking"]}}, {"job_id": "100003009038844", "location_code": "hk", "company": "Darmax Limited", "job_title": "CFO - listed company - logistics", "description": "Responsibilities\n\nProviding accounting and financial insights to improve operational efficiency\nReporting to CEO, involve in strategic planning with top management related with all accounting and finance functions\nLead financial due diligence and process improvement projects\nCarry out financial management, work with foreign operational managers to implement financial priorities, like U.S, U.K.\nOn-going review of portfolio companies financial planning, reporting, forecast and budgeting activities\nEnsure timely and accurate preparation and submission of monthly financial and management reports for management review and for group consolidation and reporting purpose\nProvide business advice for process improvement, taxation and corporate governance\nBuilds strong relationships and fosters teamwork among department and staff to maximize team performance\n\n\u00a0Requirements\n\nCandidates with advance business or accounting degree preferred, such as CPA or MBA\nMinimum of 5-8 years of working experience is required\nDirect experience and strong track record in foreign countries\nAbility to consult and advise operating and corporate leaders on issues related to accounting, financial reporting, internal control and regulatory issues\nStrong leadership skills with high level of self-motivation and initiative\nProven analytical, organizational and problem-solving skills\nStrong interpersonal and communication skills, both verbal and written in English, Cantonese and Mandarin\nSuperior organizational skills and the ability to prioritize in a dynamic working environment\nGood interpersonal skills with the ability to deal with all levels of internal and external clients\nWill travel to overseas when required (United States of America)", "employment_types": ["Full Time", "Permanent"], "selling_points": ["CFO", "New and strategic role", "HK listco"], "locations": ["Not Specified"], "categories": ["Accounting", "Financial Controller"], "post_time": "2022-01-11T07:56:02Z", "salary": {"currency": null, "max": null, "min": null, "period": "monthly", "term": null}, "salary_visible": false, "title_keywords": ["logistics", "cfo"], "responsibilities": ["reporting", "management", "due diligence", "taxation", "strategic planning", "budgeting", "review", "management reports", "forecast", "management review", "planning"], "requirements": {"degrees": ["degree"], "majors": ["business", "accounting"], "languages": ["cantonese", "english", "mandarin"], "language_level": [], "hard_skills": ["problem-solving skills", "cpa", "dynamic", "internal control"], "soft_skills": ["communication skills", "organizational skills", "organizational", "leadership skills", "prioritize", "self-motivation", "dynamic", "interpersonal skills", "problem-solving skills", "interpersonal", "initiative", "superior"], "languages_combined": [{"language": "cantonese", "language_level": []}, {"language": "english", "language_level": []}, {"language": "mandarin", "language_level": []}]}, "experience_required": {"duration": ["minimum of 5-8 years"], "field": []}}, {"job_id": "100003009041539", "location_code": "hk", "company": "ConnectedGroup Limited", "job_title": "Finance Project Director, Asia (FMCG)", "description": "A HK-listed company subsidiary is current seeking a CFO. This is a newly created headcount for an upcoming logistics business.\n\nYou will be responsible for not just the day to day financial management of the company but also be involved in setting up department workflows, controls and advised on key projects such as financing and investments.\n\nYou should have:\n\n15+ years of working experience at a director level\nCPA qualification\nKnowledge in the logistics industry would be beneficial\nStrong knowledge of financial or tax regulations in HK and PRC", "employment_types": ["Full Time", "Permanent"], "selling_points": ["One of the market leading players in the industry", "International working environment", "Large-scale and high-impact project exposure"], "locations": ["Not Specified"], "categories": ["Accounting", "Financial Controller", "Others"], "post_time": "2022-01-12T04:00:42Z", "salary": {"currency": null, "max": null, "min": null, "period": "monthly", "term": null}, "salary_visible": false, "title_keywords": ["director"], "responsibilities": ["tax", "management", "logistics", "regulations"], "requirements": {"degrees": [], "majors": [], "languages": [], "language_level": [], "hard_skills": ["cpa"], "soft_skills": ["responsible"], "languages_combined": []}, "experience_required": {"duration": ["15+ years"], "field": []}}, {"job_id": "100003009053132", "location_code": "hk", "company": "Sinopec Chemical Commercial Holding (Hong Kong) Company Limited", "job_title": "Assistant Accountant / Accountant", "description": "Finance Project Director, Asia (FMCG)\n\nOur client is a world's leading FMCG Company with more than 70 products in over 50 countries. We are seeking a talented individual to join them as a Contract Finance Project Director to lead the Regional Finance Transformation Program.\n\nPosition Responsibilities\n\nBeing the overall program management lead for the entire Asia Finance Transformation Project - ensuring strong solutioning and deployment for cross-segment shared service, cluster and local business partnership and control\nIdentifying the project hurdles, surfacing them to the right stakeholders and ensuring closure and following through to ensure delivery of the project on time\nTracking and monitoring cost and benefits for the entire region\nDeveloping dashboard, reporting status, tracking risks and issues, following up on actions and escalating issues to region/global levels\nStablishing a detailed process to assess, map and document all local process and key activities as they are performed\nApplying project management skills and methodologies including but not limited to project plans, risk mitigation, issue tracking and communication plans etc.\nPartnering with the change leader to be a change sponsor at Market level, helping facilitate change and comms interventions as required\n\nPosition Requirements\n\nBachelor's Degree in Accounting, Business or related discipline\nProven track record in program leadership, experienced in navigating through complex transformational programs (e.g. business integration, outsourcing, new operating model, etc.)\nAt least 10+ years of full-set financial controlling experiences\nSolid Regional or Global large-scaled finance transformation project management experiences\nAbility to drive a complex agenda and influence at all levels, getting results through others\nGood understanding / perspective of Finance operating model\nAbility to interact and develop relationships with all levels of associates, including senior management, to influence desired outcomes\nStrong conflict management and influencing without authority skills\nStrong communication, written and interpersonal skill\nAbility to speak fluent English is a MUST; Fluency in Chinese is preferred\n\nInterested individuals can apply now and send CV to Vivian Wong, or call +852 3972 5831 for more information. Only relevant candidates will be contacted\n\nFor a more comprehensive list of our vacancies, please visit: www.connectedgroup.com", "employment_types": ["Full Time", "Permanent"], "selling_points": [], "locations": ["Wan Chai"], "categories": ["Accounting", "Financial Controller"], "post_time": "2022-01-17T06:02:29Z", "salary": {"currency": null, "max": null, "min": null, "period": "monthly", "term": null}, "salary_visible": false, "title_keywords": ["accountant", "assistant accountant"], "responsibilities": ["management", "business partnership", "control"], "requirements": {"degrees": [], "majors": [], "languages": [], "language_level": [], "hard_skills": [], "soft_skills": [], "languages_combined": []}, "experience_required": {"duration": [], "field": []}}, {"job_id": "100003009044909", "location_code": "hk", "company": "Bread Elements", "job_title": "Financial Analyst - Cost Controller", "description": "Main Job Duties:\n\nMainly responsible for preparing month-end reports to HQ in Beijing on a strictly timely basis\nAssist in the implementation of internal control (finance-related)\nCommunicate with inter-companies in China frequently\nPrepare budget and forecasts reports\nPrepare management reports and financial analysis on a timely basis\nAssist in maintaining and implementing financial systems;\nOther ad hoc tasks as assigned\n\nRequirements:\n\n2-5 years relevant experience\nBachelor's degree in Accounting, Finance, Economics or equivalent, CPA or ACCA is preferred.\nExcellent interpersonal, communication, analytical, and problem-solving skills\nWilling to learn, able to work independently, and work under pressure to meet tight deadlines\nPositive attitude, detail-minded, self-motivated\nProficiency in English and Chinese (Mandarin is a must)\nProficiency in MS Excel and Word", "employment_types": ["Full Time", "Permanent"], "selling_points": ["Finance, Cost Control, Reporting, Analysis", "Management Reporting & PnL", "Setting KPIs, Strategy & Recommendations"], "locations": ["Chai Wan"], "categories": ["Accounting", "Financial Analyst", "Financial Controller", "Others"], "post_time": "2022-01-13T06:40:13Z", "salary": {"currency": null, "max": null, "min": null, "period": "monthly", "term": null}, "salary_visible": false, "title_keywords": ["financial analyst"], "responsibilities": ["communicate with", "maintaining", "budget", "systems", "implementation", "month-end", "ad hoc tasks", "financial analysis", "management reports", "reports", "internal control"], "requirements": {"degrees": ["degree", "bachelor"], "majors": ["finance", "accounting", "economics"], "languages": ["english", "chinese", "mandarin"], "language_level": ["proficiency"], "hard_skills": ["acca", "word", "cpa", "ms excel", "problem-solving skills"], "soft_skills": ["detail-minded", "work independently", "meet tight deadlines", "self-motivated", "willing to learn", "communication", "positive attitude", "problem-solving skills", "interpersonal", "work under pressure"], "languages_combined": [{"language": "english", "language_level": ["proficiency"]}, {"language": "chinese", "language_level": ["proficiency"]}, {"language": "mandarin", "language_level": []}]}, "experience_required": {"duration": ["2-5 years"], "field": ["relevant experience"]}}, {"job_id": "100003009044675", "location_code": "hk", "company": "Aaron Shum Jewelry Limited", "job_title": "Chief Accountant", "description": "Job Highlights\n\nCover the Cost Control & report to Group Finance Director\n2 Business Units: Central Kitchen & Retail, 150 employees, fast expansion \u00a0\u00a0\nPrepare regular management reporting and PnL variance analysis\nProvide insightful recommendations on businesses to the top management\nMonitor budget and forecast for strategic and operational decisions\nSetting KPIs and conducting financial analysis for each business units & liaise with the related team\n\nResponsibilities:\n\nPrepare regular reports (incl. weekly/monthly cost control report & PnL report)\nCalculate weekly F&B internal transfer between legal entities\nPrepare for recipe costing of menu items and assist on the costing audits (retail and factory sides: control real/theoretical consumption)\nPerform forecasting & analysis, budgetary control, cash flow management, tax reporting & ops review\nReview management accounts & assist to prepare reports for top management\nCoordinate with different departments in preparation of the annual budget and forecast \u2013 direct responsibility for overall accountability for delivering consolidated budget/forecast, covering the P&L, cash flow and balance sheet\u00a0\nMonitor cash position, cash flow forecast and banking facilities for investment projects\nMonthly financial close including analytical review of balance sheet, P&L accounts for the business\nTake initiatives on driving changes and system development\nMonitor ongoing performance of the business and find ways to reduce risks\nAct as a key business partner with the senior management in offering strategic and financial insights and recommendations for business management and decision\n\nRequirements:\u00a0\n\nMin. 3 years work experience in Cost Control\nDegree or above in Accounting or Finance or related discipline\nExperience in Big4 is a plus\nStrong analysis & leadership skills\nSolid experience in group level consolidation and financial reporting\nGood command in both English & Cantonese\nProficient in PC skills, such as MS applications, ERP systems, Business Intelligence software (Tableau)\nGood interpersonal and communication skills\nSelf-motivated, curious, analytic, pinpoint, accurate, capable to work under pressure and meet deadline\nImmediately available is highly preferred\n\nBenefits:\u00a0\n\nMedical & Dental Insurance\nStaff discount on ALL Bakehouse shops & products\nGreat working environment with trendy Pantry\nFamily-Friendly Good Employer Certification\n\nWe offer great working environment, attractive salary and benefits package to the right candidate. Interested applicants please send us your resume with availability and expected salary.\n\nWe are an equal opportunity employer. Personal data collected will be treated in strictly confidential and for recruitment purpose only.", "employment_types": ["Full Time", "Permanent"], "selling_points": ["Accounting", "Qualified Accountant", "Finance"], "locations": ["Hung Hom"], "categories": ["Accounting", "Accountant", "Chief Accountant", "Financial Controller"], "post_time": "2022-01-13T05:19:07Z", "salary": {"currency": null, "max": null, "min": null, "period": "monthly", "term": null}, "salary_visible": false, "title_keywords": ["accountant"], "responsibilities": ["budget", "senior management", "control", "monitor", "p&l", "reports", "forecast", "banking", "forecasting", "balance sheet", "report", "reporting", "management", "review", "coordinate with", "cash flow", "audits", "tax", "analysis", "cost control", "prepare reports"], "requirements": {"degrees": ["degree or above"], "majors": ["finance", "accounting"], "languages": ["cantonese", "english"], "language_level": ["good command"], "hard_skills": ["erp systems", "plus", "ms applications", "analysis", "tableau", "pc skills", "business intelligence"], "soft_skills": ["communication skills", "self-motivated", "capable", "leadership skills", "accurate", "interpersonal", "work under pressure"], "languages_combined": [{"language": "cantonese", "language_level": ["good command"]}, {"language": "english", "language_level": ["good command"]}]}, "experience_required": {"duration": ["3 years"], "field": ["consolidation", "financial"]}}, {"job_id": "100003009037838", "location_code": "hk", "company": "ConnectedGroup Limited", "job_title": "Financial Controller (Manufacturing MNC)", "description": "Job Description\n\nROLE\n\nThe position is responsible for performance analysis and assisting in budget preparation for the key financials KPIs, such as Sales, Inventory, Capex, Margin, Marketing and Communication expenses, Store Expenses. It is also required to act as a Business Partner with various units for the Controlling function.\n\nESSENTIAL DUTIES AND RESPONSIBILITIES\n\nCalculate the monthly stock provision and consol margin adjustment\nWeekly sales report submission\nWork with the Marketing and Communication Teams, reconcile the expenses tracking file\nPerform In-depth analysis on margin\nRolling-forecast on inventory, to ensure the current stock landing\nProvide a comprehensive monthly overview of the Store Performance: profitability, productivity, occupancy ratio, distribution network, etc\nAnalyze the capex of the opening or renovation projects\nLiaise with Shared-Service Finance Department for HFM reporting\nMaintain the Agreements register\nAd hoc assignment, can be projects or various analysis\n\nREQUIREMENTS\n\nBachelor\u2019s degree, major in Finance & Accounting\n3+ years relevant professional experience, preferably acquired in retail\nExcellent written and spoken English\nProficient in Excel and PPT skills\nBusiness Intelligence tool and Hyperion knowledge\nProactive, strong in communication and analytics skills\n\nHOW TO APPLY\n\nInterested parties please send your\u00a0full resume, stating your availability, latest and expected salary\u00a0by clicking the APPLY NOW button.\n\nData collected will be for recruitment purpose only.\n\u00a0\n\nWHY WORK FOR US?\n\nUnique opportunity to be working in Hong Kong under the headquarter office, and to strategically be a fashion-forwarder with new ideas and initiatives to be implemented globally.\n\nTalent development is a managerial principle, promoting entrepreneurial spirit for highly empowered teams. We want to cultivate a \u201cstartup\u201d mindset where business agility is key to our fast paced development, and where every employee can reach their full potential in a stimulating and fulfilling workplace environment.\n\nJob Type\n\nRegular\n\nSchedule\n\nFull time\n\nOrganization\n\nQEELIN LTD", "employment_types": ["Full Time", "Permanent"], "selling_points": ["Key member of the business", "International working environment", "Attractive package with promising career prospect"], "locations": ["Not Specified"], "categories": ["Accounting", "Finance / Accounting Manager", "Financial Controller", "Others"], "post_time": "2022-01-11T04:01:28Z", "salary": {"currency": null, "max": null, "min": null, "period": "monthly", "term": null}, "salary_visible": false, "title_keywords": ["financial controller"], "responsibilities": ["reporting", "sales report", "analysis", "budget", "capex", "inventory", "expenses", "teams", "communication", "renovation", "ad hoc assignment", "maintain", "forecast", "liaise with", "kpis", "tracking"], "requirements": {"degrees": ["degree", "bachelor"], "majors": ["finance", "accounting"], "languages": ["english"], "language_level": ["excellent"], "hard_skills": ["excel", "business intelligence"], "soft_skills": ["communication", "proactive"], "languages_combined": [{"language": "english", "language_level": ["excellent"]}]}, "experience_required": {"duration": ["3+ years"], "field": ["retail"]}}, {"job_id": "100003009043527", "location_code": "hk", "company": "Randstad Hong Kong Limited", "job_title": "Finance Director | Investment Group (SFC Type 1, 2, 4, 6, 9)", "description": "Qualified Accountant and Bachelor\u2019s Degree major in Accounting / Finance.\nAt least 10 years experiences, strong in financial reporting, regulatory reporting, cost accounting, cash flow management and familiar with taxation of both HK and the PRC.\nExperience in Manufacturing industries is required and knowledge in Jewelry field is an advantage.\nResponsible for full set of accounts including consolidation, financial management reporting, preparing account analysis and accounts reconciliation and month end closing.\nExperience in financial audits, budgeting and forecasting.\nCoordinate audit related activities and liaise with auditors during the auditing process.\nSupport as needed with input and reconciliation in group portfolio management accounting software.\nMonitoring the preparation and submission of financial and management reports, and handling ad-hoc assignments as required.\nReview and monitor accounting and taxation related issues.", "employment_types": ["Full Time", "Permanent"], "selling_points": ["Leading SFC licensed financial services", "Supervise reporting team", "FRR, client money, financial control & reporting"], "locations": ["Not Specified"], "categories": ["Accounting", "Financial Controller", "Banking / Finance", "Financial Services", "Equities / Capital Markets"], "post_time": "2022-01-12T16:07:42Z", "salary": {"currency": "HKD", "max": 119999, "min": 90000, "period": "monthly", "term": null}, "salary_visible": true, "title_keywords": ["director"], "responsibilities": ["software", "budgeting", "audit", "liaise with", "month end closing", "full set of accounts", "monitor", "forecasting", "reporting", "cost", "management", "monitoring", "review", "cash flow", "management reporting", "audits", "taxation", "ad-hoc assignments", "analysis", "coordinate", "management reports", "financial reporting", "auditing"], "requirements": {"degrees": ["degree", "bachelor"], "majors": ["finance", "accounting"], "languages": [], "language_level": [], "hard_skills": ["accounting software", "analysis", "management reports"], "soft_skills": ["responsible"], "languages_combined": []}, "experience_required": {"duration": ["at least 10 years"], "field": ["management", "accounting", "manufacturing", "financial"]}}, {"job_id": "100003009046419", "location_code": "hk", "company": "ConnectedGroup Limited", "job_title": "Finance Manager, Family Office, 40-60k", "description": "about the company.\n\nOur client is a highly respected SFC licensed investment company with substantial growth in Asia Pacific. They offer wide range of services including securities and future trading, asset management, investment advisory etc. Currently, they are hiring a Finance Director to manage their Financial Reporting team in Hong Kong.\nabout the team.\nThe company offers a friendly work culture. Work life balance, stable Finance team. You will work with a strong leadership team with a forward looking vision. Reporting to the Head of Finance, you will manage a team of 4-5 in Hong Kong.\nabout the job.\nReporting directly to the CFO, you will:\nLead and manage a team on financial control and reporting activities under Type 1, 2, 4, 6, 9\nReview reporting packs prepared by team members including Head Office reporting, annual and statutory reports\nReview and prepare group consolidation of HK listed investment entities\nCheck and ensure quality submission of FRR returns and regulatory reports according to Client Money Rules\nEnhance existing accounting processes for structured products, equities, derivatives etc.\nDrive initiatives to streamline work-flow through automation and process improvement projects\nKey point of contact with internal and external auditors\nskills & experiences required.\nDegree holder in Accounting, Finance or related discipline\nQualified member of HKICPA, ACCA or CPA Aus\nMinimum 15 years or above in Financial Control, Financial Reporting gained from SFC licensed corporations\nPrior experience in HK listed financial institution is a definite advantage\nGood product knowledge in equities, derivatives, structured products etc\nKnowledgeable in SFC regulatory requirements including FRR, Client Money Rules\nExcellent presentation and interpersonal skills, able to effectively lead a medium sized team\nGood command of English, Mandarin and Cantonese\nhow to apply.\n\nTo apply online, please click on the link below. Alternatively, for a confidential discussion please contact Mimi Chak on + 852 2232 3420 or email: mimi.chak@randstad.com.hk", "employment_types": ["Full Time", "Permanent"], "selling_points": ["Managerial Position", "Stable Working Environment", "Growing platform"], "locations": ["Not Specified"], "categories": ["Accounting", "Finance / Accounting Manager", "Financial Analyst", "Financial Controller"], "post_time": "2022-01-13T10:57:51Z", "salary": {"currency": null, "max": null, "min": null, "period": "monthly", "term": null}, "salary_visible": false, "title_keywords": ["finance manager"], "responsibilities": ["reporting", "control", "regulatory requirements", "review", "quality", "external auditors", "reports", "finance team", "financial reporting", "contact", "asset management"], "requirements": {"degrees": ["degree holder"], "majors": ["finance", "accounting"], "languages": ["cantonese", "english", "mandarin"], "language_level": ["good command"], "hard_skills": ["cpa", "acca", "frr", "hkicpa"], "soft_skills": ["friendly", "interpersonal skills", "stable", "structured", "leadership", "presentation"], "languages_combined": [{"language": "cantonese", "language_level": ["good command"]}, {"language": "english", "language_level": ["good command"]}, {"language": "mandarin", "language_level": ["good command"]}]}, "experience_required": {"duration": [], "field": ["financial"]}}, {"job_id": "100003009036428", "location_code": "hk", "company": "Ambition", "job_title": "Financial Controller + Company Secretary", "description": "Career Highlights:\u00a0\n\nMonthly salary range from HK$20,000 (Officer) to HK$65,000 (Senior\u00a0Manager), depend on Experience and Ability;\nSenior Manager is require to manage a Team of Company Secretarial within the Company Secretarial Division;\nLong terms career development in a Multinational Company;\n5 days work with 20 days annual leave for the Senior Manager.\n\nKey Responsibilities:\u00a0\u00a0\u00a0\u00a0\n\nAttending to ongoing compliance requirements for listed and non-listed, local and offshore companies;\nAttending to ad hoc corporate transactions and providing relevant advice;\nKeeping abreast of, monitoring, and analyzing developing trends and changes in regulatory compliance laws, rules and regulations, and advising clients of the operational impact and corporate governance matters.\u00a0\n\nKey Requirements:\u00a0\n\nBachelor degree holder or above ;\nRegistered Student or Member of HKICS;\nAt least 8 years\u2019 working experience in handling company secretarial matters of Hong Kong-listed companies, preferably with sizable\u00a0professional firms or listed companies for the Senior Manager;\nAt least 3 years working experience in handling company secretarial matters for the Officer Grade;\nBasic knowledge of Hong Kong listing rules and other relevant regulatory requirements for both listed and non-listed companies \u2013 essential;\nSelf-motivated, well-organized and detail-oriented;\nExcellent command of spoken and written English with fluent spoken Mandarin;\nComputer literate; experience with ViewPoint 7.4 preferred.\nCandidates with Less Experience will be consider as Manager / Supervisor / Officer / Fresh Graduated Trainee position.\n\n\n\nAttractive remuneration package commensurate with qualifications and experience will be offered to the right candidate. Interested parties please use the following \"APPLY NOW\" function to apply for the job. A full resume stating date of availability, current & expected salary are required.\n\nOr email the Full Resume to dave @ talentcl.com\n\nFor any further inquiries about the job, please feel free to send message by WhatsApp at 9282 3326 (No telephone call will be answer).\n\n\nAll personal data collected will be used for recruitment purpose only. \u00a0Applicants not hearing from us within 3 weeks may consider their applications unsuccessful.", "employment_types": ["Full Time", "Permanent"], "selling_points": ["Listed company, consumer sector", "Finance head role, leading small team", "Hands-on, all-rounded role"], "locations": ["Not Specified"], "categories": ["Accounting", "Financial Controller"], "post_time": "2022-01-10T10:24:15Z", "salary": {"currency": "HKD", "max": 89999, "min": 55000, "period": "monthly", "term": null}, "salary_visible": true, "title_keywords": ["company secretary", "financial controller"], "responsibilities": ["regulations", "ad hoc", "monitoring", "compliance", "developing", "transactions"], "requirements": {"degrees": ["bachelor degree holder"], "majors": [], "languages": ["english", "mandarin"], "language_level": ["excellent", "fluent"], "hard_skills": ["basic"], "soft_skills": ["self-motivated", "well-organized", "detail-oriented"], "languages_combined": [{"language": "english", "language_level": ["excellent"]}, {"language": "mandarin", "language_level": ["fluent", "excellent"]}]}, "experience_required": {"duration": ["at least 8 years", "at least 3 years"], "field": ["secretarial"]}}, {"job_id": "100003009039769", "location_code": "hk", "company": "Michael Page", "job_title": "CFO, Family Office, Negotiable", "description": "Finance Manager, Family Office, 40-60k\n\nManagerial Position\nStable Working Environment\nGrowing platform\n\nMy client is an international asset management firm. They are now looking for a Finance Manager for their group finance team in Hong Kong.\n\nReport to the CFO, you will be responsible for:\n\nHandling full set month end closing.\nHandling FRR (Type1, 4, 9).\nHandling private equity fund accounting.\nSupporting the external audit process.\nHandling ad hoc projects.\n\nRequirements:\n\nUniversity graduated in Finance, Business Administration or relevant disciplines.\nAt least 8 years relevant experience gained from financial services/ asset management environment.\nOpen minded and willing to take up new challenges.\nHands on and detail orientated.\nStrong problem-solving skills.\nFluency in written and spoken English and Chinese (includes Putonghua).\n\nTo Apply\n\nThis is an excellent opportunity to join a leading asset management firm that offer long term career growth, guidance, and development.\n\nInterested individuals can apply now. Please send your CV in WORD format with your current and expected salary.", "employment_types": ["Full Time", "Permanent"], "selling_points": ["Must be existing CFO at Large Corp", "Prefer stable candidates", "Well-established family office"], "locations": ["Not Specified"], "categories": ["Accounting", "Chief Accountant", "Financial Controller", "Treasurer"], "post_time": "2022-01-11T11:04:29Z", "salary": {"currency": null, "max": null, "min": null, "period": "monthly", "term": null}, "salary_visible": false, "title_keywords": ["cfo"], "responsibilities": ["administration", "guidance", "month end closing", "audit", "asset management", "ad hoc projects", "finance team", "report"], "requirements": {"degrees": [], "majors": [], "languages": ["putonghua", "english", "chinese"], "language_level": ["fluency"], "hard_skills": ["problem-solving skills", "word", "private equity", "frr"], "soft_skills": ["responsible", "hands on", "detail orientated", "open minded", "problem-solving skills", "stable"], "languages_combined": [{"language": "putonghua", "language_level": ["fluency"]}, {"language": "english", "language_level": ["fluency"]}, {"language": "chinese", "language_level": ["fluency"]}]}, "experience_required": {"duration": ["at least 8 years"], "field": ["financial services", "relevant experience", "asset management"]}}, {"job_id": "100003009036166", "location_code": "hk", "company": "Robert Walters (HK)", "job_title": "Financial Controller (Open to big4 candidates)", "description": "Our client is a fast growing and well established listed company in Hong Kong. The Group has strong presence in Hong Kong and China. They are looking for a high calibre Finance Director to lead the Finance team in Hong Kong.\n\nReporting to the Board of Directors, your responsibilities will include:\n\nLeading the whole finance function in the Hong Kong, China and regional subsidiaries\nEnforce Standard of Operation for Finance and Accounting\nSupervising all Regional financial management reporting as the Group level\nEnsure financial accounting and management reports in accordance with IFRS and corporate requirements\nReview and streamline the internal control process to ensure operational efficiency and effectiveness\nFoster initiatives to drive group planning, budgeting and forecasting activities\nLook after the group treasury, tax, cash flow, capex and potential M&A and investment projects\nBusiness partnership with internal and external parties\n\nTo qualify, individuals must possess:\n\nDegree holder in Accounting/ Finance or other related disciplines. Member of recognized accounting bodies (HKICPA, CIA or ACCA) preferred;\nAt least 10-15 years relevant experience in Chinese company and in managerial or supervisory roles\nSolid training from Big 4 is a plus\nRelevant experiences in manufacturing, trading and distribution industries would be an advantage. Solid experiences in Hong Kong listed companies are needed\nSelf-initiative, well-organized, strong sense of responsibility and leadership skills;\nStrong analytical and strategic mindset, problem solving skills\nExcellent communication and business partnership skills\nFamiliar with MS Office (Word, Excel, Outlook and Chinese Word Processing);\nGood command in written English &amp; Chinese and Putonghua;\n\nPlease contact Kady Wu at (852) 3103 4314 OR Email to kady.wu@ambition.com.hk OR click APPLY NOW.\n\nFor more information please visit http://www.ambition.com.hk/\n\nData provided is for recruitment purposes only.\n\nIf this job isn't quite right for you, but you know someone who would be great at this role, why not take advantage of our referral scheme? We offer HKD1000 in Apple gift cards for every referred candidate who we place in a role. Terms & Conditions Apply. https://www.ambition.com.hk/refer-a-friend", "employment_types": ["Full Time", "Permanent"], "selling_points": ["Main board listed", "Stable working environment", "Familiar with listing rules"], "locations": ["Not Specified"], "categories": ["Accounting", "Financial Controller"], "post_time": "2022-01-10T09:32:16Z", "salary": {"currency": null, "max": null, "min": null, "period": "monthly", "term": null}, "salary_visible": false, "title_keywords": ["financial controller"], "responsibilities": ["supervising", "data", "budgeting", "internal and external parties", "capex", "communication", "business partnership", "internal control", "finance team", "reporting", "review", "cash flow", "forecasting activities", "management reporting", "contact", "tax", "management reports", "recruitment", "planning"], "requirements": {"degrees": ["degree holder"], "majors": ["related disciplines", "finance", "accounting"], "languages": ["putonghua", "english", "chinese"], "language_level": ["good command"], "hard_skills": ["ms office", "acca", "ifrs", "plus", "excel", "chinese word processing", "word", "scheme", "management reports", "outlook", "problem solving skills", "internal control", "hkicpa"], "soft_skills": ["sense of responsibility", "leadership skills", "well-organized", "communication", "self-initiative", "problem solving skills"], "languages_combined": [{"language": "putonghua", "language_level": []}, {"language": "english", "language_level": ["good command"]}, {"language": "chinese", "language_level": []}]}, "experience_required": {"duration": ["at least 10-15 years"], "field": ["managerial", "supervisory", "manufacturing", "relevant experience", "trading"]}}, {"job_id": "100003009039141", "location_code": "hk", "company": "Links International", "job_title": "Head of Finance - Business Partnering, Aggressive Career!", "description": "Our client is a reputable family office. They are now looking for a CFO to join their team.\n\nClient Details\n\nOur client is a reputable family office. They are now looking for a CFO to join their team.\n\nDescription\n\nReporting to the Family Member, you will be\n\nlooking after the family office and the finance function\npreparing management reporting and performing various analyses and planning\nperforming compliance and tax issues\nperforming other adhoc tasks when necessary\n\nProfile\n\nDegree Holder in Business/Accounting/Finance\nCPA qualification is a must\nExisting CFO at a reputable company is a must\nExcellent communication skills (English and Mandarin)\n\nJob Offer\n\nCompetitive remuneration\nFast and dynamic business growth\nReputable company\n\nTo apply online please click the 'Apply' button below.\nFor a confidential discussion about this role please contact Nicole Hui on +852 3412 4832.", "employment_types": ["Full Time", "Permanent"], "selling_points": ["Excellent career progression", "Fast track career path", "Stock options"], "locations": ["Not Specified"], "categories": ["Accounting", "Chief Accountant", "Financial Controller", "Others"], "post_time": "2022-01-11T08:49:27Z", "salary": {"currency": null, "max": null, "min": null, "period": "monthly", "term": null}, "salary_visible": false, "title_keywords": ["head of finance"], "responsibilities": ["tax", "reporting", "compliance", "communication", "management reporting", "contact", "planning"], "requirements": {"degrees": ["degree holder"], "majors": ["finance", "business", "accounting"], "languages": ["english", "mandarin"], "language_level": ["excellent"], "hard_skills": ["cpa", "dynamic"], "soft_skills": ["communication skills", "dynamic"], "languages_combined": [{"language": "english", "language_level": ["excellent"]}, {"language": "mandarin", "language_level": ["excellent"]}]}, "experience_required": {"duration": [], "field": []}}, {"job_id": "100003009046351", "location_code": "hk", "company": "Links International", "job_title": "Finance Manager (Leading Conglomerate ,PRC GAAP)", "description": "It is a HK gem board listed company. This role reports to the chairman directly.\n\nJob Responsibilities:\n\nEnsure proper and consistent consolidated financial reporting standard compile with listing rules requirement\nReview the monthly consolidated management account package and commentary for Board reference Oversee and coordinate the annual budget process of the group\nOversee and coordinate the group annual audit, tax and company secretarial filling\nReview and liaise legal advice and support on major contracts at corporate level\nLiaise with banks on investment financing\nMange the cashflow and investment portfolios\n\nJob Requirements:\n\nQualified Accountant and degree holder in accounting or related discipline\nBig 4 trained candidate with minimum 8 years of working experience\nFamiliar with listing rules\nGood command of written and spoken in English, Mandarin and Cantonese", "employment_types": ["Full Time", "Permanent"], "selling_points": ["Leading Conglomerate", "Greater China  Exposure", "PRC GAAP"], "locations": ["Central & Western Area"], "categories": ["Accounting", "Finance / Accounting Manager", "Financial Analyst", "Financial Controller"], "post_time": "2022-01-13T10:38:55Z", "salary": {"currency": "HKD", "max": 69999, "min": 55000, "period": "monthly", "term": null}, "salary_visible": true, "title_keywords": ["finance manager"], "responsibilities": ["tax", "liaise", "management", "annual audit", "contracts", "review", "budget", "investment portfolios", "coordinate", "financial reporting", "liaise with", "listing"], "requirements": {"degrees": ["degree holder"], "majors": ["accounting"], "languages": ["cantonese", "english", "mandarin"], "language_level": ["good command"], "hard_skills": [], "soft_skills": [], "languages_combined": [{"language": "cantonese", "language_level": ["good command"]}, {"language": "english", "language_level": ["good command"]}, {"language": "mandarin", "language_level": ["good command"]}]}, "experience_required": {"duration": ["minimum 8 years"], "field": ["big 4"]}}, {"job_id": "100003009030968", "location_code": "hk", "company": "Tsui Wah Restaurant", "job_title": "Financial controller", "description": "Responsibilities:\n\nWork with senior management team and contribute to strategic planning and decision-making of the Group\nDevelop and implement finance and controlling systems & processes that align with the organization's overall vision and its business objectives\nEnsure that all financial and control disciplines in relations to transactions, policies, systems, and procedures meet the organization's short and long-term business objectives and comply with regulations, accounting principles and standards\nReview legal contracts and provide financial, accounting and tax advice to drive business initiatives forward\nOptimize the tax structure of the Group\nManage treasury activities and drive financing transactions of the Group\nProvide cost effective and innovative IT solutions and infrastructure to support the requirements of business growth and productivity improvement\nLead and coach the team to support the businesses and safeguard the Group's financial integrity\n\nRequirements:\n\nAn experienced financial executive with at least 10+ years of successful track record in a commercial environment\nBachelor degree in Accounting, Finance or related discipline\nQualified Accountant with HKICPA/ACCA or equivalent\nIn-depth knowledge of PRC GAAP and IFRS and solid big 4 background is required\nFluency in Cantonese, English and Mandarin is required\nA high degree of flexibility in adapting to a rapidly changing environment\nAbility to manage stakeholders across geographies, businesses and seniorities\nProficient in strategic and tactical thinking about the business, developing actionable business plans and demonstrating to team members how to achieve those plans", "employment_types": ["Full Time"], "selling_points": ["Oversee various accounting operations", "Manage the budgeting and forecasting", "Produce financial statements as requsted"], "locations": ["Kwai Hing"], "categories": ["Accounting", "Finance / Accounting Manager", "Financial Analyst", "Financial Controller"], "post_time": "2022-01-07T08:43:36Z", "salary": {"currency": null, "max": null, "min": null, "period": "monthly", "term": null}, "salary_visible": false, "title_keywords": ["financial controller"], "responsibilities": ["regulations", "tax", "control", "business initiatives", "cost", "strategic planning", "policies", "contracts", "systems", "procedures", "review", "transactions", "develop", "infrastructure", "senior management"], "requirements": {"degrees": ["degree", "bachelor"], "majors": ["finance", "accounting"], "languages": ["cantonese", "english", "mandarin"], "language_level": ["fluency"], "hard_skills": ["acca", "ifrs", "hkicpa"], "soft_skills": [], "languages_combined": [{"language": "cantonese", "language_level": ["fluency"]}, {"language": "english", "language_level": ["fluency"]}, {"language": "mandarin", "language_level": ["fluency"]}]}, "experience_required": {"duration": [], "field": []}}, {"job_id": "100003009039282", "location_code": "hk", "company": "KOS International Limited", "job_title": "Financial Controller/ Finance Manager - China Based", "description": "Responsibilities:\n\nOversee various accounting operations;\nManage Billing, Accounts Receivables, Accounts Payables, Cost Accounting, Inventory Accounting and Revenue Recognition;\nIdentify accounting and financial issues and suggest timely solutions;\nSupport month-end and year-end close process;\nManage quality control over financial transactions and reporting;\nManage the budgeting and forecasting;\nProduce financial statements as requsted;\nCoordinate the preparation of regulatory reporting;\nManage and comply with local, state, and federal government reporting requirements and tax filings;\nDevelop and adhere to policies and procedures.\nRequirements:\n\nDegree holder in Finance or Accounting, qualified CPA and associate member of HKICS / ICSA;\nIPO / listed company experience is a must;\nStrong analytical mind, good communication skill and business sense\nStrong Microsoft Office application and Chinese word processing;\nGood command of both written and spoken in English and Chinese, fluency in Putonghua is highly preferred.\nWe offer an attractive remuneration package to the right candidates. Interested parties please apply in full resume including current salary, expected salary and earliest availability by clicking\u00a0APPLY NOW.\u00a0\n\nApplications without\u00a0expected salary will not be considered.\nPersonal data collected will be used for recruitment purpose only.\n", "employment_types": ["Full Time", "Permanent"], "selling_points": ["Well-established Manufacturing Service Provider", "All-rounded Role; Base in Dongguan", "10 Years+ Work Experience; Up to 60K"], "locations": ["Others - China"], "categories": ["Accounting", "Finance / Accounting Manager", "Financial Controller"], "post_time": "2022-01-11T09:17:30Z", "salary": {"currency": null, "max": null, "min": null, "period": "monthly", "term": null}, "salary_visible": false, "title_keywords": ["finance manager", "financial controller"], "responsibilities": ["tax", "year-end", "cost", "reporting", "operations", "inventory", "budgeting", "policies", "month-end", "transactions", "financial statements", "coordinate", "develop", "procedures", "quality control", "forecasting"], "requirements": {"degrees": ["degree holder"], "majors": ["finance", "accounting"], "languages": ["putonghua", "english", "chinese"], "language_level": ["fluency", "good command"], "hard_skills": ["cpa", "chinese word processing", "microsoft office"], "soft_skills": ["communication skill", "analytical mind", "business sense"], "languages_combined": [{"language": "putonghua", "language_level": ["fluency", "good command"]}, {"language": "english", "language_level": ["good command"]}, {"language": "chinese", "language_level": ["good command"]}]}, "experience_required": {"duration": [], "field": []}}, {"job_id": "100003009044477", "location_code": "hk", "company": "Trend Expo Limited", "job_title": "Accounting Manager / Finance Manager (F&B)", "description": "GoGoChart is a fast expanding start-up company, we are seeking different talent and expert in various division to join our dynamic and energetic team.\n\nWe willing to offer a competitive package and fringe benefits if you are the ideal candidate.\n\nWe believe our employees are the essential assets to lead the company to successful.\n\nResponsibilities:\n\nResponsible for managing all-rounded financial operations and internal control for our business in HK, China and other APAC regions\nWork closely with CEO and stakeholders in the running of finance, accounting and operational functions in compliance with policies and statutory requirements\nConduct review and delivery of monthly reporting package and consolidation with value added analysis, commentary and action plans for management decision making\nPrepare budget & forecast with continuous business performance tracking\nDevelop and implement various financial requirements to drive business improvement. Strengthen control issues and identify opportunity for process improvement\nSupport the development of existing and new business by reviewing and updating financial performance\nHandle audits, tax and statutory filing requirements\nSupporting on-going and ad-hoc projects both locally and regionally\nPerform budget control over all expenses\nRequirement:\n\nQualified accountant with ACCA, HKICPA or equivalent qualification\nAt least 5 years of relevant working experience with a minimum of 2 years in supervisory role\nCommercial and Big 4 experiences are preferably\nStrong business acumen and excellent analytical, reporting and business control skills\nIndependent, self-motivated, articulate and good interpersonal and influence skills to work with and manage internal and external stakeholders\nAble to work under pressure and in a fast paced environment\nGood command of both spoken and written English and Chinese", "employment_types": ["Full Time", "Permanent"], "selling_points": [], "locations": ["Wan Chai"], "categories": ["Accounting", "Finance / Accounting Manager", "Financial Controller"], "post_time": "2022-01-13T04:15:30Z", "salary": {"currency": null, "max": null, "min": null, "period": "monthly", "term": null}, "salary_visible": false, "title_keywords": ["accounting manager", "finance manager"], "responsibilities": [], "requirements": {"degrees": [], "majors": [], "languages": [], "language_level": [], "hard_skills": [], "soft_skills": [], "languages_combined": []}, "experience_required": {"duration": [], "field": []}}, {"job_id": "100003009035086", "location_code": "hk", "company": "ConnectedGroup Limited", "job_title": "Financial Controller & Company Secretary (HK Listed)", "description": "Financial Controller/ Finance Manager - China Based\n\nAbout the Client\n\nOur client is a well-established manufacturing services provider. To cope with their business needs, they are looking for a Financial Controller to base in Dongguan and oversee full spectrum of accounting and finance functions for the China operation.\n\nAbout the Role\n\nReport to the Vice President Finance\nLead a sizable team to manage accounting operation\nResponsible for financial and management reporting\nEnsure accounting processes align with group's standard\nInvolve in tax filings\nStrengthen internal control\nSupport annual audit\nTake up any ad-hoc tasks as assigned\n\nThe Successful Applicant\n\nBachelor Degree in Accounting, Finance or relevant\nHKICPA/ ACCA/ CPA Australia Chartered\n10 years+ relevant work experience\nExperience in the manufacturing sector and stationing in China is required\nExperience from professional service firms is an advantage\nStrong communication and interpersonal skills\nUser experience in sizable accounting systems e.g. Oracle, SAP\nFluent in Cantonese, Mandarin and English\nStation in Dongguan\n\nClick \"Apply Now\" to apply for this position or call Alec Yeung at +852 3180 4915 for a confidential discussion. All information collected will be kept in strict confidence and will be used for recruitment purpose only.", "employment_types": ["Full Time", "Permanent"], "selling_points": ["One of the market leading players in the industry", "Key senior management in the business", "Attractive package with promising career prospect"], "locations": ["Not Specified"], "categories": ["Accounting", "Finance / Accounting Manager", "Financial Controller", "Others"], "post_time": "2022-01-10T05:55:18Z", "salary": {"currency": null, "max": null, "min": null, "period": "monthly", "term": null}, "salary_visible": false, "title_keywords": ["company secretary", "financial controller"], "responsibilities": ["tax", "annual audit", "ad-hoc tasks", "systems", "user experience", "communication", "recruitment", "management reporting", "report", "internal control"], "requirements": {"degrees": ["degree", "bachelor"], "majors": ["finance", "accounting"], "languages": ["cantonese", "english", "mandarin"], "language_level": ["fluent"], "hard_skills": ["acca", "oracle", "sap", "cpa", "accounting systems", "internal control", "hkicpa"], "soft_skills": ["communication and interpersonal skills", "confidence", "responsible"], "languages_combined": [{"language": "cantonese", "language_level": ["fluent"]}, {"language": "english", "language_level": ["fluent"]}, {"language": "mandarin", "language_level": ["fluent"]}]}, "experience_required": {"duration": [], "field": ["manufacturing", "accounting"]}}, {"job_id": "100003009046946", "location_code": "hk", "company": "South China Holdings Company Limited", "job_title": "Internal Audit Manager", "description": "About Us\n\nWe are one of the F&B Business in Hong Kong. We are now looking for\u00a0Accounting Manager / Finance Manager\u00a0\n\nJob Description\n\nLeading the finance team and be responsible for the full spectrum of finance and accounting function.\n\n\u2022 Preparation of reports daily, weekly and monthly which include but are not limited to sales analysis, food and beverages cost reports, monthly management accounts.\n\n\u2022 Prepare ad-hoc report is required\n\n\u2022 Prepare weekly and monthly cash flow forecast\n\n\u2022 Preparation of annual budgets and monthly target per business unit\n\n\u2022 Preparation and Submission of a monthly report summarizing the performance of the businesses under your control, which includes a P&L, variance analysis against budget and Target, balance sheet and cash flow, focus areas for the next month, control weaknesses and corrective actions.\n\n\u2022Preparation of annual budgets per business unit with quarterly updated rolling forecasts.\n\n\u2022 Handling external audit and liaison with external auditors\n\nRequirements:\n\n- Degree in Accounting / Finance or equivalent\n\n- Experience in Food & Beverage outlets is highly recommended\n\n- 5 - 8 years relevant experience\n\n- Detailed oriented and strong analytical and communication skills\n\n- immediately available is preferred", "employment_types": ["Full Time", "Permanent"], "selling_points": ["Internal Audit", "5 years\u2019 internal audit/compliance experience", "Willing to travel to Mainland China"], "locations": ["Central"], "categories": ["Accounting", "Audit", "Financial Controller", "Management", "General Management"], "post_time": "2022-01-14T01:50:00Z", "salary": {"currency": null, "max": null, "min": null, "period": "monthly", "term": null}, "salary_visible": false, "title_keywords": ["manager"], "responsibilities": ["ad-hoc", "budgets", "cost", "management", "control", "balance sheet", "analysis", "budget", "audit", "p&l", "external auditors", "variance analysis", "monthly cash flow forecast", "cash flow", "reports", "finance team", "monthly report", "report"], "requirements": {"degrees": ["degree"], "majors": ["finance", "accounting"], "languages": [], "language_level": [], "hard_skills": [], "soft_skills": ["communication skills", "detailed oriented"], "languages_combined": []}, "experience_required": {"duration": ["5 - 8 years"], "field": ["food", "relevant experience"]}}, {"job_id": "100003009043307", "location_code": "hk", "company": "Ambition", "job_title": "SVP - Finance Project & Change Portfolio Management", "description": "This position will be responsible for carrying out\u00a0internal\u00a0audit\u00a0and ad-hoc\u00a0assignments across\u00a0the South China\u00a0Group\u00a0and reports directly to the senior management.\n\nKey Responsibilities:\n\nProviding objective assurance and\u00a0performing advisory\u00a0reviews\u00a0of\u00a0the adequacy and effectiveness of the\u00a0Group\u2019s\u00a0risk management and internal control systems.\nPerforming\u00a0data\u00a0analysis, including investigating\u00a0the roots causes;\u00a0and identifying anomalies.\nCommunicating audit results\u00a0and making\u00a0recommendations\u00a0to the\u00a0senior\u00a0management for improvements in operations and internal control.\nPreparing and reviewing audit deliverables \u2013 audit plans and audit reports.\nTracking the progress of corrective actions on audit issues.\nWorking\u00a0independently under general direction including exercising initiative\u00a0and\u00a0independent judgment.\n\nRequirements:\n\nAccounting qualification such as CPA or equivalent\u00a0is a must.\nOther professional qualifications\u00a0such as CIA\u00a0and CISA are highly\u00a0preferred.\nMinimum\u00a05\u00a0years\u2019\u00a0internal\u00a0audit/compliance\u00a0experience in\u00a0international\u00a0audit firms\u00a0or in-house roles in\u00a0listed companies of property and manufacturing industry.\nExperience in financial services carrying out regulated activities of Types 1, 2, 4, 6 and 9 under the Securities and Futures Ordinance is highly preferable.\nAble to adapt to\u00a0a dynamic and changing environment, striving to exceed expectations.\nHigh level of ethical standards; excellent reporting\u00a0skills\u00a0and proficient in using MS Word and Excel.\nCompetent in both written English and Chinese, and spoken Mandarin is highly preferred.\nWilling to travel\u00a0to Mainland China.\n\nAttractive remuneration package to the right candidate will be offered.\u00a0 Interested parties please send your full resume\u00a0with current and expected salary by clicking the below \"APPLY NOW\"", "employment_types": ["Full Time", "Permanent"], "selling_points": ["Established Name in the Financial Industry", "Strong Change Management Experience", "Group Level Business Initiatives"], "locations": ["Not Specified"], "categories": ["Accounting", "Financial Controller", "Banking / Finance", "Project Finance", "Others"], "post_time": "2022-01-12T10:36:41Z", "salary": {"currency": null, "max": null, "min": null, "period": "monthly", "term": null}, "salary_visible": false, "title_keywords": [], "responsibilities": ["management", "tracking", "operations", "systems", "audit", "data analysis", "reports", "plans", "senior management", "internal control"], "requirements": {"degrees": [], "majors": [], "languages": ["english", "chinese", "mandarin"], "language_level": [], "hard_skills": ["excel", "professional qualifications", "securities and futures ordinance", "cpa", "dynamic", "ms word"], "soft_skills": ["dynamic", "ethical", "competent"], "languages_combined": [{"language": "english", "language_level": []}, {"language": "chinese", "language_level": []}, {"language": "mandarin", "language_level": []}]}, "experience_required": {"duration": ["minimum 5 years"], "field": ["compliance", "audit", "financial services", "securities", "manufacturing industry"]}}, {"job_id": "100003009048327", "location_code": "hk", "company": "Links International", "job_title": "Finance Manager (PRC Leading Asset Management ,Type 4,9 )", "description": "Reporting to the Controller, Finance and Accounts, the job-holder will lead a small team of accountants in carrying out the accounting and finance works.\nResponsibilities:\nPrepare and review monthly reports \u2013 actual, budgets and forecasts, providing commentary on key variances and driving any actions required\nHandle full set of accounts, group consolidation and tax compliance of overseas operations; deal with internal and external auditors; and perform additional ad hoc assignments\nPrepare statutory accounts in compliance with the disclosure requirements, accounting standards and local tax laws\nOversee and prepare timely cash flow forecast to optimise the cash and treasury management\nFormulate and implement internal control policies and procedures, update financial guidelines, and issue instructions on accounting matters\nImprove internal work processes and service levels\nHandle financial management functions including asset and liability management, monitoring of investment performance and review of investment guidelines and compliance, maintenance of banking relations\nRequirements:\nDegree holder in accounting, finance or related discipline\nQualified accountant with qualifications from recognised accounting bodies e.g. HKICPA, or equivalent\nAt least 8 years\u2019 solid experience of which 3 years at managerial level\nRelevant work experience in sizeable organisations, public organisations and/or Big4 will be an advantage\nA \u201chands on\u201d leader and be responsible for all finance related matters including accounting management, financial reporting, project management, audit, tax, forecast, budget, treasury etc.\nFamiliar with Hong Kong and mainland accounting policies and regulations. \u00a0Overseas experience an advantage\nA self-motivator and team player to handle multiple projects within tight schedules and meet deadlines\nWell-organised with strong analytical and interpersonal skills\nGood command of written and spoken English and Chinese\nProficient in computer skills and sound knowledge of ERP system\nRemuneration and Benefits:\nThe successful candidate will be offered a two-year contract with prospects for renewal upon expiry. Salary will be commensurate with qualifications and experience, plus an appropriate contract-end gratuity. Medical benefits and annual leave will be offered.\nApplication Procedure:\nIf you want to join our team, please complete the application form on our website at http://www.hktdc.com/careers.html.\u00a0 Those who do not hear from us within EIGHT WEEKS after the closing date may assume their applications were unsuccessful.\nAll information provided by applicants will be treated in strict confidence and used only for recruitment purposes. Applicants may be considered for other suitable positions within the Council. \u00a0Their personal data will be destroyed six months after the selection is finalised.", "employment_types": ["Full Time", "Permanent"], "selling_points": ["PRC Leading Asset Management", "Type 4,9", "Excellent Career Progression Path"], "locations": ["Central & Western Area"], "categories": ["Accounting", "Finance / Accounting Manager", "Financial Controller", "Banking / Finance", "Financial Services"], "post_time": "2022-01-14T06:17:04Z", "salary": {"currency": "HKD", "max": 54999, "min": 45000, "period": "monthly", "term": null}, "salary_visible": true, "title_keywords": ["finance manager", "asset management"], "responsibilities": ["monthly reports", "operations", "internal control", "full set of accounts", "compliance", "forecast", "banking", "management", "review", "procedures", "monitoring", "cash flow", "tax", "budgets", "maintenance", "guidelines", "policies", "ad hoc assignments", "external auditors"], "requirements": {"degrees": ["degree holder"], "majors": ["finance", "accounting"], "languages": ["english", "chinese"], "language_level": ["good command"], "hard_skills": ["project management", "erp system", "computer skills", "hkicpa"], "soft_skills": ["responsible", "project management", "hands on", "interpersonal skills", "well-organised", "team player", "meet deadlines"], "languages_combined": [{"language": "english", "language_level": ["good command"]}, {"language": "chinese", "language_level": ["good command"]}]}, "experience_required": {"duration": ["at least 8 years", "3 years"], "field": ["managerial"]}}, {"job_id": "100003009040044", "location_code": "hk", "company": "ConnectedGroup Limited", "job_title": "Senior Manager, Finance Operations & Internal Control", "description": "Established name in the Financial Industry\nManagement Reporting and Project Control Skills\nStrong Change Management Experience\n\n\nOur client is an established financial services body in Hong Kong with strong governance platform in the industry. As part of their continuous improvement and growth, our client is looking for an experience Finance professional to join their team as Senior VP.\n\nSupporting the Global Markets business, you will be responsible for driving financial and operational efficiencies, as well as, running financial controls on key projects ran by the business. You will be involved in the planning and budgeting of different initiatives and analyse financial implications on the Group's project portfolio. This role requires an individual with excellent cost and internal control skills, budgeting, ability to multi-task with strong problem solving and stakeholder management skills in a high pressure environment.\n\nTo qualify, individuals must possess:\n\nBachelor's degree and internationally recognised CPA qualification\nSix Sigma or PMP certification highly sought after\n15+ years' relevant management reporting, and project management & control experience in a sizeable financial institution or MNC business\nMinimum 5 years' people leadership experience\nExcellent communication skills in English is a must. Cantonese and /or Mandarin a plus\nStrong project portfolio management skills, and can adapt to changing environment\nMust already be based in Hong Kong\n\n\nInterested parties, please send your resume to Rhoda.Rivera@ambition.com.hk quoting RR253716 or click APPLY NOW.\n\nOnly shortlisted candidates will be notified.\n\n#LI-RR1\n#BuildingBetterFutures\n\nIf this job isn't quite right for you, but you know someone who would be great at this role, why not take advantage of our referral scheme? We offer HKD1000 in Apple gift cards for every referred candidate who we place in a role. Terms & Conditions Apply. https://www.ambition.com.hk/refer-a-friend", "employment_types": ["Full Time", "Permanent"], "selling_points": ["Key member of the business", "Historical and sizable conglomerate business", "Attractive package with promising career prospect"], "locations": ["Not Specified"], "categories": ["Accounting", "Audit", "Financial Controller", "Others"], "post_time": "2022-01-12T01:00:42Z", "salary": {"currency": null, "max": null, "min": null, "period": "monthly", "term": null}, "salary_visible": false, "title_keywords": ["senior manager", "operations"], "responsibilities": ["control", "cost", "change management", "management", "budgeting", "communication", "project management", "management reporting", "analyse", "internal control", "planning"], "requirements": {"degrees": ["degree", "bachelor"], "majors": [], "languages": ["cantonese", "english", "mandarin"], "language_level": ["excellent"], "hard_skills": ["plus", "problem solving", "cpa", "six sigma", "project management", "pmp", "internal control"], "soft_skills": ["communication skills", "multi-task", "responsible", "problem solving", "project management", "leadership"], "languages_combined": [{"language": "cantonese", "language_level": []}, {"language": "english", "language_level": ["excellent"]}, {"language": "mandarin", "language_level": []}]}, "experience_required": {"duration": ["15+ years", "minimum 5 years"], "field": ["management", "finance", "project management", "business", "team", "financial"]}}, {"job_id": "100003009050160", "location_code": "hk", "company": "Magic Search Limited", "job_title": "Assistant Finance Manager (Luxury Brand)", "description": "About the client\n\nOur client is a leading PRC Asset Management focus on PE fund,Property fund with strong presence across APAC.To cope with their rapid expansion in Hk ,they are currently looking for a Finance Manager to join their Finance Team.\n\nJob Description:\n\nHandle the overall accounting operation\nPrepare financial statements and FRR\nOversee management report, annual budget and quarterly financial analysis, forecast\nLiaise with auditors for interim and annual financial reports\nOverview of daily treasury function\n\n\n\nRequirements\n\nUniversity graduated in Finance, Business Administration or relevant disciplines with CPA Qualification\nAt least 5 years of relevant experience\nFamiliar with FRR reporting\nExcellent communication skills in both English and Chinese.\nDynamic personality with an analytical mindset", "employment_types": ["Full Time", "Permanent"], "selling_points": ["6-7 years experience", "luxury brand", "audit experience is a plus"], "locations": ["Not Specified"], "categories": ["Accounting", "Audit", "Financial Analyst", "Financial Controller"], "post_time": "2022-01-14T09:53:26Z", "salary": {"currency": null, "max": null, "min": null, "period": "monthly", "term": null}, "salary_visible": false, "title_keywords": ["assistant finance manager"], "responsibilities": ["financial reports", "budget", "financial statements", "financial analysis", "forecast", "liaise with", "management report"], "requirements": {"degrees": [], "majors": [], "languages": ["english", "chinese"], "language_level": ["excellent"], "hard_skills": ["cpa", "dynamic", "frr"], "soft_skills": ["communication skills", "dynamic"], "languages_combined": [{"language": "english", "language_level": ["excellent"]}, {"language": "chinese", "language_level": ["excellent"]}]}, "experience_required": {"duration": ["at least 5 years"], "field": ["relevant experience"]}}, {"job_id": "100003009036590", "location_code": "hk", "company": "China Resources Ng Fung Limited", "job_title": "\u7d9c\u5408\u8ca1\u52d9\u5c08\u54e1 Integrated Financial Officer", "description": "Senior Manager, Finance Operations & Internal Control\n\nOur client is a sizable company with diverse businesses across the globe. We are seeking a talented individual to join them as a Senior Finance Manager that focused on Finance Operations & Internal Control to work closely with the growing team.\n\nPosition Responsibilities\n\nReport to a Finance Director and lead a team of Finance professionals\nLead finance daily operation on Accounts Receivables, Accounts Payables and General Ledgers\nImplement and streamline operational and finance policies through process re-engineering and continuous improvement\nSet SOP on daily operation process and procedure\nSet up internal control system, policies and procedures for the company\nLead the implementation, review and monitor internal control and risk management policies according to the statutory guidelines and business requirements\nProvide training and guidance on risk management, internal control and compliance related issues and projects\nAssist on the Company internal audit and ad hoc audit as well as execute follow-up actions on audit findings including any irregularities or incidents\n\nPosition Requirements\n\nA qualified accountant with a degree in Accounting, Finance or related discipline\nAt least 10+ years working experiences preferably with Big 4 background\nIn-depth experiences in finance operations from international sizable company\nExtensive experiences in internal control, policy and procedures\nFamiliar with setting up internal control and risk management policies is a definite advantage\nHave a self-motivated attitude to always strive for solutions\nGood command of spoken and written English and Chinese (Putonghua and Cantonese)\nDetail-oriented, self-motivated & discipline, good communication and analytical skills\n\nInterested individuals can apply now and send CV to Vivian Wong, or call +852 3972 5831 for more information. Only relevant candidates will be contacted.\n\nFor a more comprehensive list of our vacancies, please visit: www.connectedgroup.com", "employment_types": ["Full Time", "Permanent"], "selling_points": ["Business Partner", "Development Opportunities", "Financial Analysis"], "locations": ["Sham Shui Po"], "categories": ["Accounting", "Financial Analyst", "Financial Controller"], "post_time": "2022-01-10T11:14:28Z", "salary": {"currency": null, "max": null, "min": null, "period": "monthly", "term": null}, "salary_visible": false, "title_keywords": ["officer"], "responsibilities": ["provide training", "internal audit", "audit", "internal control", "ad hoc", "compliance", "monitor", "implementation", "re-engineering", "report", "guidance", "management", "review", "procedures", "irregularities", "guidelines", "policies", "daily operation", "lead a team"], "requirements": {"degrees": ["degree"], "majors": ["finance", "accounting"], "languages": ["cantonese", "putonghua", "english", "chinese"], "language_level": ["good command"], "hard_skills": ["analytical skills", "internal control"], "soft_skills": ["self-motivated", "analytical skills", "communication", "detail-oriented", "comprehensive", "extensive"], "languages_combined": [{"language": "cantonese", "language_level": ["good command"]}, {"language": "putonghua", "language_level": ["good command"]}, {"language": "english", "language_level": ["good command"]}, {"language": "chinese", "language_level": ["good command"]}]}, "experience_required": {"duration": ["at least 10+ years"], "field": ["finance", "big 4"]}}, {"job_id": "100003009034032", "location_code": "hk", "company": "Joint Billion Holdings Limited", "job_title": "Senior Manager, Group Finance Reporting", "description": "Our client is a global leading luxury Brand It is now looking for an Assistant Finance Manager to join their team.\n\n\n\nKey Responsibilities\n\nPrepare and consolidated Sales monthly sales report with comparison against Budget and Forecast with comment\nWork closely with other functional team to ensure alignment and to reconcile any discrepancy\nPrepare other regular sales reporting or ad hoc analysis for management review of business performance\u00a0\nDevelop and replicate excel\u00a0budget/forecast\u00a0templates for\u00a0Asia\u00a0market\u00a0and\u00a0validation\u00a0\u00a0\nAssist\u00a0with the\u00a0budget & forecast\u00a0consolidation and review\u00a0process\nValidate system input and co-ordinate necessary follow-up with market\u00a0finance team\nAssist with analysis during budget and forecast process\nCost Management and Budget follow-up\nAssist in establishing/improving means of regional\u00a0cost\u00a0tracking\u00a0and budget follow-up\u00a0process\nRecommend and develop relevant reports and analysis\nAssist in developing of business performance reports\u00a0\nPlanning and Consolidation tool co-ordination, vendor master data creation and maintenance, and other ad hoc projects\n\nRequirements\n\nBachelor degree in Finance, Accounting or other related subjects\n6-7 years relevant retail working experience\nAbility to extract, organise, analyse and report data\nGood communication skills\nGood command in English and Chinese\u00a0", "employment_types": ["Full Time", "Permanent"], "selling_points": ["Group Finance exposure based in Global HQ", "8-10 years of finance reporting experience", "HKICPA/ ACCA or equivalent qualified"], "locations": ["Tung Chung"], "categories": ["Accounting", "Audit", "Finance / Accounting Manager", "Financial Controller"], "post_time": "2022-01-10T02:28:32Z", "salary": {"currency": null, "max": null, "min": null, "period": "monthly", "term": null}, "salary_visible": false, "title_keywords": ["senior manager"], "responsibilities": ["performance reports", "data", "budget", "system input", "monthly sales report", "management review", "relevant reports", "ad hoc", "developing", "develop", "finance team", "forecast", "reporting", "cost", "management", "review", "tracking", "maintenance", "forecast process", "analysis", "ad hoc projects", "planning"], "requirements": {"degrees": ["degree", "bachelor"], "majors": ["finance", "accounting"], "languages": ["english", "chinese"], "language_level": ["good command"], "hard_skills": [], "soft_skills": ["communication skills"], "languages_combined": [{"language": "english", "language_level": ["good command"]}, {"language": "chinese", "language_level": ["good command"]}]}, "experience_required": {"duration": ["6-7 years"], "field": ["retail"]}}, {"job_id": "100003009046368", "location_code": "hk", "company": "Vanke Holdings (Hong Kong) Company Limited", "job_title": "Assistant Manager/ Manager (Finance - Property Developer)", "description": "\u5de5\u4f5c\u8077\u8cac\n1) \u8ca0\u8cac\u8cc7\u91d1\u8a08\u5283\u7684\u7de8\u5236\u53ca\u57f7\u884c\u76e3\u63a7\n2) \u6839\u64da\u7ba1\u7406\u9700\u8981\uff0c\u5229\u7528\u6838\u7b97\u63d0\u4f9b\u7684\u5206\u6790\u5831\u544a\uff0c\u958b\u5c55\u8ca1\u52d9\u5206\u6790\uff0c\u63d0\u4f9b\u6c7a\u7b56\u652f\u6301\n3) \u6839\u64da\u696d\u52d9\u9700\u8981\u5c55\u958b\u5206\u6790\uff0c\u70ba\u696d\u52d9\u4e00\u7dda\u63d0\u4f9b\u8ca1\u52d9\u652f\u6301\n4) \u8ca0\u8cac\u9810\u7b97\u7de8\u5236\u53ca\u7ba1\u7406\u53ca\u63a7\u5236\u5de5\u4f5c\n5) \u6839\u64da\u8ca1\u52d9\u5831\u8868\u6578\u64da\u9032\u884c\u696d\u7e3e\u8003\u8a55\uff0c\u4e26\u63d0\u4f9b\u7d50\u679c\n6) \u6309\u516c\u53f8\u8981\u6c42\u9032\u884c\u8ca1\u52d9\u5167\u63a7\u7ba1\u7406\n7) \u5176\u4ed6\u5206\u914d\u7684\u8ca1\u52d9\u5de5\u4f5c\n\n\u4efb\u8077\u8981\u6c42\n1) \u5927\u5b78\u5b78\u58eb\u5b78\u4f4d\u53ca\u4ee5\u4e0a\u8ca1\u52d9\u7ba1\u7406\u7b49\u76f8\u95dc\u5c08\u696d\n2) 1\u5e74\u53ca\u4ee5\u4e0a\u76f8\u95dc\u5de5\u4f5c\u7d93\u9a57\u512a\u5148\uff0c\u61c9\u5c46\u7562\u696d\u751f\u4ea6\u53ef\u7372\u8003\u616e\n3) \u6703\u8a08\u5c08\u696d\u8cc7\u683c\u5df2\u53d6\u5f97\u6216\u8003\u53d6\u4e2d\uff08\u5982AAT\uff0cCAT\uff0cACCA\uff0cHKSA\u7b49\uff09\n4) \u719f\u7df4\u4f7f\u7528office\u8edf\u4ef6\uff0cExcel\uff0cPowerPoint\uff0cWord\u7b49\n5) \u64c5\u9577\u6578\u64da\u5206\u6790\u5de5\u5177\u53ca\u7de8\u7a0b\u8a9e\u8a00\u512a\u5148\n6) \u6d41\u5229\u5ee3\u6771\u8a71\u53ca\u666e\u901a\u8a71\u512a\u5148\n\n\u6211\u5011\u63d0\u4f9b\n\n\u91ab\u7642\u4fdd\u96aa\n\u7bc0\u65e5\u798f\u5229\n12\u5929\u5e74\u5047\n\u54e1\u5de5\u8cfc\u7269\u512a\u60e0\n\u8077\u696d\u767c\u5c55\u901a\u9053\n......\n\n\nApply\n\nPlease send your application with updated CV by clicking \u201cApply Now\u201d .\n\n*Personal data collected will be used for recruitment purpose only.", "employment_types": ["Full Time", "Permanent"], "selling_points": ["Finance, tax & compliance for property development", "Financial analysis/ modelling, forecast, DD of M&A", "CPA,5 years commercial in real estate & Big 4 exp."], "locations": ["Central"], "categories": ["Accounting", "Financial Analyst", "Financial Controller", "Banking / Finance", "Corporate Finance"], "post_time": "2022-01-13T10:45:54Z", "salary": {"currency": null, "max": null, "min": null, "period": "monthly", "term": null}, "salary_visible": false, "title_keywords": ["developer", "assistant manager", "manager"], "responsibilities": ["personal data", "recruitment"], "requirements": {"degrees": [], "majors": [], "languages": [], "language_level": [], "hard_skills": [], "soft_skills": [], "languages_combined": []}, "experience_required": {"duration": [], "field": []}}, {"job_id": "100003009043061", "location_code": "hk", "company": "China Resources Property Management Limited", "job_title": "\u534e\u6da6\u7269\u4e1a\u8d22\u52a1\u4e13\u4e1a\u603b\u76d1", "description": "About the Company\n\nHello! Welcome to Plaza Premium Group, we're people passionate about \"Making Travel Better\". We are a global company with team members from all walks of life, together we are #PPGFamily, together we are building a legacy. You don't need to be from this industry, you do need to be passionate.\n\nOur promise to you:\n\nWe will respect and value your background and perspectives\nWe will work together with integrity\nWe will share our incredible pride for job, company and industry\nWhat we ask of you: bring passion to all that you do\nListen, move fast and think innovatively\nSpeak up, have ideas and share them\nBelieve in customer service, and treating every person with kindness\n\n\nAs industry leaders in innovating global airport hospitality you will work with colleagues from all parts of the world for a truly global experience. You will help and craft services and facilities in over 200 locations in more than 60 international airports across the world.\n\nWho we are\n\nWe were established in HK in 1998 by someone who understood the value of an airport lounge and felt that the experience shouldn't just be limited to a closed-circuit group of travelers. Through the years we have worked incredibly hard to create an experience which is both accessible and quality. Almost 25 years later we now span four core business segments: airport lounges, airport terminal hotels, airport meet & greet services, and a range of airport dining concepts.\n\nIn addition to our own brands, PPG provides airport hospitality solutions to leading airlines, alliances and corporates around the world. Here are a few names you might recognize: Cathay Pacific Airways, Singapore Airlines, Lufthansa etc.\n\nWith the future of travel always in sight, we created Smart Traveler, a mobile-app rewards program underpinned by in-house technology. We are fast-moving and always evolving to drive our purpose of making travel better.\n\nJoin our family today.\nTogether, we'll make travel better.\n\nWhat you'll be doing\n\nThis position is a key member in delivering consolidated financial reporting for the group as well as Head Office legal entities, including group reporting package from all oversea entities. Exercising Head Office Finance & Accounting leadership, this position will work closely with teams across the group to strengthen the integrity of financial records, determine / implement finance policies, extend technical guidance & support, review adequacy of financial recording processes etc., and maintaining overall finance controls discipline for the group.\n\nIn charge of statutory finance reporting for Head Office legal entities and group: Group Consolidated Financial Statement, Annual Reports, other ad-hoc finance reports\nAssists in the set up/improvement of internal control/accounting systems\nLiaise with subsidiaries\u2019 finance teams and business unit to obtain, analyze and consolidate financial report and information\nSupport Group Financial Controller in liaising with external audit & accounting consultants\nOversee all audit and internal control functions/operation\nManage and comply with government reporting requirements and tax filing\nStrengthen financial controls within the group : ensure integrity of financial records ; design, review and implement financial recording processes, provide training, etc.\nSupport group expansion for finance perspective\nAny ad hoc duties as assigned\n\nAbout You\n\nThe ideal candidate will have the ability to work in a diversified, fast-paced and collaborative environment with excellent interpersonal and good time management skills\n\nBachelor\u2019s degree in accounting with HKICPA / ACCA or equivalent professional qualifications\nMinimum 8 to 10 years relevant experience in which 3 years of supervisory experience\nTechnically sound, well versed with latest IFRS and Tax regulations\nAnalytical, with excellent report writing skills\nMatured, self-initiated, independently, with good interpersonal skills dealing with different levels of management\nA proven ability to interact in a positive, proactive, customer-service manner with internal and external customers\nAbility to multitask, move quickly in a fast moving and dynamic environment\nChange management and managerial skills\nTravelling may be required but low frequency.\nFluency in written and spoken English, Cantonese", "employment_types": ["Full Time", "Permanent"], "selling_points": [], "locations": ["Not Specified"], "categories": ["Accounting", "Accountant", "Financial Analyst", "Financial Controller"], "post_time": "2022-01-12T09:41:14Z", "salary": {"currency": null, "max": null, "min": null, "period": "monthly", "term": null}, "salary_visible": false, "title_keywords": [], "responsibilities": ["customer service", "ideas"], "requirements": {"degrees": [], "majors": [], "languages": [], "language_level": [], "hard_skills": ["airports"], "soft_skills": ["passionate", "customer service", "integrity", "passionate about"], "languages_combined": []}, "experience_required": {"duration": [], "field": []}}, {"job_id": "100003009050677", "location_code": "hk", "company": "Geox Asia Pacific Limited", "job_title": "Junior Financial Analyst", "description": "Responsibilities:\n\nManage finance, tax and internal control related matters for property development/ investment projects\nBe responsible for consolidating various Hong Kong project entities and preparing of monthly management reporting for the submission to the head office\nPerform financial analysis/modelling and forecasting the financial performance and cash flows of property\u00a0development/investment projects\n\nCoordinate with external tax representatives in preparing and executing tax planning proposals; reviewing tax submissions and ensuring tax compliance of offshore and Hong Kong entities\nParticipate in the due diligence work of Merger and Acquisition transactions\nPerform regular inspection on internal control procedures and compliance matters\nHandle other ad hoc assignments\nRequirements:\n\nQualified CPA with 5-year commercial experience in property developer; prior experience in Big 4 CPA firm background is also an advantage\nSelf-motivated, proactive and diligent\nExcellent interpersonal, communication and negotiation skills\nProficiency in PC skills, particularly on MS Words, Excel and PowerPoint\nFluent in English and Chinese (Cantonese and Mandarin)\nMore experience will be considered as Manager\nWe offer an attractive remuneration package. Interested parties please send your resume stating your present and expected salaries, together with your cover letter by clicking \"APPLY NOW\".\u00a0\n\nPlease read carefully the following Privacy Statement before applying: \"The personal data of unsuccessful candidates collected\u00a0for this\u00a0recruitment exercise will be kept no more than 2 years from its completion for future recruitment use and therefore destroyed.\u00a0 Information provided will be used for recruitment and appointment related purpose only.\u00a0 The Company will handle all personal data confidentially in accordance with the Personal Data (Privacy) Ordinance.\"\u00a0\u00a0\u00a0\n\nCandidates have a\u00a0right to make a data access, correction or destroy request concerning\u00a0the personal data by applying to the Human\u00a0Resources Department.\u00a0\u00a0", "employment_types": ["Full Time", "Permanent"], "selling_points": ["Financial Planning & Analysis in Retail & WHS", "Direct Report to Business Controller", "5-Day Work Week, MNC Working Environment"], "locations": ["Wan Chai"], "categories": ["Accounting", "Accounting Clerk / Supervisor", "Financial Analyst", "Financial Controller"], "post_time": "2022-01-15T03:51:13Z", "salary": {"currency": null, "max": null, "min": null, "period": "monthly", "term": null}, "salary_visible": false, "title_keywords": ["financial analyst", "junior"], "responsibilities": ["tax", "due diligence", "regular inspection", "compliance", "coordinate with", "procedures", "transactions", "financial analysis", "planning", "executing", "management reporting", "ad hoc assignments", "forecasting", "internal control"], "requirements": {"degrees": [], "majors": [], "languages": ["cantonese", "english", "chinese", "mandarin"], "language_level": ["fluent"], "hard_skills": ["excel", "ms words", "powerpoint", "cpa", "pc skills"], "soft_skills": ["self-motivated", "diligent", "communication", "negotiation skills", "proactive", "interpersonal"], "languages_combined": [{"language": "cantonese", "language_level": []}, {"language": "english", "language_level": ["fluent"]}, {"language": "chinese", "language_level": ["fluent"]}, {"language": "mandarin", "language_level": []}]}, "experience_required": {"duration": ["5-year"], "field": ["developer", "commercial", "cpa firm", "big 4"]}}, {"job_id": "100003009035672", "location_code": "hk", "company": "Sky Harvest Development Limited", "job_title": "Finance Manager - Retail Industry", "description": "\u5c97\u4f4d\u804c\u8d23\uff1a\n\n\u7efc\u5408\u7ba1\u7406\uff1a\u534f\u52a9\u8d22\u52a1\u603b\u76d1\u5f00\u5c55\u90e8\u95e8\u65e5\u5e38\u7ba1\u7406\uff0c\u53c2\u4e0e\u90e8\u95e8\u7ba1\u7406\u4f53\u7cfb\u5efa\u8bbe\u548c\u4eba\u624d\u57f9\u517b\uff0c\u6307\u5bfc\u5e76\u89c4\u8303\u5404\u4e0b\u5c5e\u5355\u4f4d\u7684\u8d22\u52a1\u7ba1\u7406\n\u4e1a\u52a1\u7ba1\u7406\uff1a\u6309\u7167\u96c6\u56e2\u53ca\u516c\u53f8\u8d22\u52a1\u7ba1\u7406\u8981\u6c42\uff0c\u63a8\u52a8\u90e8\u95e8\u9884\u7b97\u7ba1\u7406\u3001\u62a5\u8868\u7ba1\u7406\u3001\u8fd0\u8425\u5206\u6790\u3001\u6210\u672c\u7ba1\u7406\u3001\u98ce\u9669\u7ba1\u7406\u7b49\u5de5\u4f5c\u5f00\u5c55\n\u7ec4\u7ec7\u7f16\u5236\u516c\u53f8\u5e74\u5ea6\u8d22\u52a1\u9884\u7b97\u548c\u8d44\u91d1\u8ba1\u5212\uff0c\u5b9a\u671f\u8ddf\u8fdb\u9884\u7b97\u548c\u8d44\u91d1\u4f7f\u7528\u60c5\u51b5\n\u5b8c\u6210\u5404\u7c7b\u8d22\u52a1\u62a5\u8868\u53ca\u5206\u6790\u5de5\u4f5c\uff0c\u5305\u62ec\u4f46\u4e0d\u9650\u4e8e\u5404\u7c7b\u6cd5\u5b9a\u62a5\u8868\u3001\u7ba1\u7406\u62a5\u8868\u7b49\uff0c\u786e\u4fdd\u4f1a\u8ba1\u4fe1\u606f\u8d28\u91cf\n\u6bcf\u6708\u8ddf\u8fdb\u516c\u53f8\u8d22\u52a1\u6536\u5165\u53ca\u652f\u51fa\u6838\u7b97\uff0c\u5b8c\u6210\u5404\u7c7b\u8fd0\u8425\u6307\u6807\u5206\u6790\uff0c\u5e76\u5411\u516c\u53f8\u7ba1\u7406\u5c42\u62a5\u544a\uff1b\u6839\u636e\u4e1a\u52a1\u9700\u6c42\uff0c\u5b8c\u6210\u4e13\u9879\u8d22\u52a1\u5206\u6790\uff0c\u5305\u62ec\u6708\u5ea6\u7ba1\u7406\u62a5\u544a\u3001\u91cd\u70b9\u9879\u76ee\u8fdb\u5ea6\u62a5\u544a\u3001\u73b0\u91d1\u5206\u6790\u62a5\u544a\u3001\u5b58\u91cf\u53ca\u589e\u91cf\u8d44\u4ea7\u4ef7\u503c\u68c0\u8ba8\u62a5\u544a\u7b49\uff0c\u5b9e\u73b0\u4ef7\u503c\u521b\u9020\n\u5408\u7406\u5b89\u6392\u516c\u53f8\u8d44\u91d1\u4f7f\u7528\uff1b\u4f9d\u6cd5\u4f9d\u89c4\u5f00\u5c55\u9999\u6e2f\u53ca\u4e2d\u56fd\u5185\u5730\u516c\u53f8\u7684\u7a0e\u52a1\u7b79\u5212\uff0c\u964d\u4f4e\u7a0e\u8d1f\n\u5f3a\u5316\u5185\u90e8\u63a7\u5236\uff0c\u4e25\u683c\u6267\u884c\u516c\u53f8\u5236\u5ea6\uff0c\u6839\u636e\u9884\u7b97\u53ca\u5ba1\u6279\u6743\u9650\uff0c\u786e\u4fdd\u516c\u53f8\u65e5\u5e38\u91c7\u8d2d\u3001\u5404\u7c7b\u652f\u51fa\u7ba1\u7406\u5408\u89c4\n\u53c2\u4e0e\u7ecf\u8425\u51b3\u7b56\uff1a\u6839\u636e\u51b3\u7b56\u6743\u9650\uff0c\u5ba1\u6279\u516c\u53f8\u5404\u7c7b\u8d22\u52a1\u4e8b\u9879\uff1b\u53c2\u4e0e\u516c\u53f8\u91cd\u5927\u9879\u76ee\u7684\u53ef\u884c\u6027\u7814\u7a76\uff0c\u63d0\u4f9b\u51b3\u7b56\u652f\u6301\n\u5176\u4ed6\uff1a\u5b8c\u6210\u4e0a\u7ea7\u4ea4\u529e\u7684\u5404\u9879\u5de5\u4f5c\n\n\u5c97\u4f4d\u8981\u6c42\uff1a\n\n\u672c\u79d1\u53ca\u4ee5\u4e0a\u5b66\u5386\uff0c\u8d22\u52a1\u7ba1\u7406\u76f8\u5173\u4e13\u4e1a\uff0c\u719f\u6089\u9999\u6e2f\u53ca\u4e2d\u56fd\u5185\u5730\u7684\u8d22\u52a1\u7ba1\u7406\u77e5\u8bc6\uff0c\u6709CPA\u6216CFA\u7b49\u4e13\u4e1a\u8d44\u683c\u4f18\u5148\n\u5177\u59078\u5e74\u4ee5\u4e0a\u7684\u8d22\u52a1\u5de5\u4f5c\u7ecf\u9a8c\uff0c3\u5e74\u4ee5\u4e0a\u7ba1\u7406\u5c97\u4f4d\u5de5\u4f5c\u7ecf\u9a8c\uff0c\u5177\u5907\u4e2d\u8d44\u4f01\u4e1a\u80cc\u666f\u8005\u4f18\u5148\n\u79ef\u6781\u4e3b\u52a8\uff0c\u8e0f\u5b9e\u80af\u5e72\uff0c\u8ba1\u5212\u5206\u6790\u80fd\u529b\u3001\u6267\u884c\u529b\u5f3a\uff0c\u80fd\u591f\u5728\u8f83\u5927\u538b\u529b\u4e0b\u72ec\u7acb\u5b8c\u6210\u5de5\u4f5c\uff0c\u6709\u826f\u597d\u7684\u56e2\u961f\u5408\u4f5c\u7cbe\u795e\u548c\u6c9f\u901a\u80fd\u529b\n\u719f\u7ec3\u4f7f\u7528Powerpoint\u3001Excel\u53caWord\u7b49\uff0c\u6709\u8f83\u5f3a\u7684\u6587\u5b57\u8868\u8fbe\u80fd\u529b\n\u719f\u7ec3\u638c\u63e1\u5e7f\u4e1c\u8bdd\u3001\u666e\u901a\u8bdd\u548c\u82f1\u6587\uff0c\u5177\u5907\u4e2d\u6587\u62a5\u544a\u64b0\u5199\u80fd\u529b\n\u89c6\u5e94\u8058\u8005\u5b9e\u9645\u7ecf\u9a8c\uff0c\u53ef\u8003\u8651\u7ed9\u4e88\u66f4\u9ad8\u804c\u4f4d", "employment_types": ["Full Time"], "selling_points": ["5 day work week", "Working Experience in Retail Industry", "Acquired with Hong Kong and PRC accounting"], "locations": ["Cheung Sha Wan"], "categories": ["Accounting", "Finance / Accounting Manager", "Financial Controller"], "post_time": "2022-01-10T08:06:37Z", "salary": {"currency": null, "max": null, "min": null, "period": "monthly", "term": null}, "salary_visible": false, "title_keywords": ["finance manager"], "responsibilities": [], "requirements": {"degrees": [], "majors": [], "languages": [], "language_level": [], "hard_skills": [], "soft_skills": [], "languages_combined": []}, "experience_required": {"duration": [], "field": []}}, {"job_id": "100003009037413", "location_code": "hk", "company": "Aussco Hong Kong Limited", "job_title": "Finance Manager (Fintech background)", "description": "Main Responsibilities\nSupport the annual financial planning process (budgeting and forecasting)\nAssist the Business Controller in preparing financial statements and reporting\nAssist with analysis and stores performances by collecting, analyzing and reporting financial and statistical data\nMonitor sales, costs, margins and inventory and carry out all analysis required to identify variance\u2019s causes\nSupport on shop KPI targets settings and monthly controls activities\nAnalyze trends, formulate projections for retail and wholesale business\nWork closely with other Functions to ensure data quality and integrity\nCompletes ad hoc projects and duties assigned by the line manager from time to time\nJob Requirements\nBachelor Degree in\u00a0Accountancy / Economics / Finance or any related discipline\nMinimum 1 year relevant experience in budgeting / forecasting / financial analysis / audit in multinational company (retail Industry preferred)\nProactive, detail-minded and good team player\nGood communication skill and strong analytical skill\nGood command of spoken and written English and Chinese\nStrong MS Excel skills; knowledge of SQL, MS Powerpoint, SAP, Oracle Essbase is a plus\nCandidates with more experience will be considered as Senior Financial Analyst\nWe offer attractive remuneration and fringe benefits to the right candidate. Please submit your application in WORD format (quoting job title) together with a detailed resume, stating current and expected salary by\u00a0\"Apply Now\"\u00a0button.\u00a0\n\n\n(All personal data provided by job applicants are used only for recruitment purpose and will be treated strictly confidential. Unsuccessful applications will be properly disposed within 3 months.)", "employment_types": ["Full Time", "Permanent"], "selling_points": ["Fintech savvy", "Finance system improvement", "5 days work and competitive package"], "locations": ["Kwun Tong"], "categories": ["Accounting", "Finance / Accounting Manager", "Financial Controller", "Information Technology (IT)", "Others"], "post_time": "2022-01-11T02:44:41Z", "salary": {"currency": null, "max": null, "min": null, "period": "monthly", "term": null}, "salary_visible": false, "title_keywords": ["finance manager"], "responsibilities": ["reporting", "data", "budgeting", "analysis", "planning process", "monitor", "inventory", "financial statements", "quality", "ad hoc projects", "forecasting", "costs"], "requirements": {"degrees": ["degree", "bachelor"], "majors": ["finance", "economics", "accountancy"], "languages": ["english", "chinese"], "language_level": ["good command"], "hard_skills": ["analytical skill", "plus", "sap", "financial analysis", "sql", "ms excel", "ms powerpoint", "oracle"], "soft_skills": ["detail-minded", "good team player", "analytical skill", "communication skill", "proactive"], "languages_combined": [{"language": "english", "language_level": ["good command"]}, {"language": "chinese", "language_level": ["good command"]}]}, "experience_required": {"duration": ["minimum 1 year"], "field": ["retail industry", "multinational company", "audit", "relevant experience", "financial"]}}, {"job_id": "100003009035938", "location_code": "hk", "company": "Profit Hero Corporation Limited", "job_title": "Assistant Financial Controller (Station in S.E. Asian Country)", "description": "Full responsible to manage accounting team in Hong Kong, China and Overseas Group Companies (including but not limited to Singapore, European Countries) by streaming and enhancing the operational effectiveness and efficiency;\nBe responsible for financial planning, tax planning, cost accounting, budgeting and forecasting, cash flow management, statutory & financial management report and internal control for the company;\nReview, formulate and implement the internal control procedures and policies of the company operations;\nLiaise with external auditors, legal and tax advisers;\nNegotiate with banker for bank facilities;.\nManage Trade Mark Registration;\nMake the recommendations on risk management and corporate governance issues to top management.\n\nREQUIREMENTS\n\nDegree holder in Accounting or related discipline;\nOver 10 years financial exposure with more than\u00a03 years working experience in in retail industry;\nWell acquired with Hong Kong and PRC accounting and tax systems;\nPleasant personality, problem solving skills, good interpersonal skills, well-organized with high commitment, proactive, strategic thinking and analytical mind.\nFlexible in working hours and ability to work under pressure in a demanding and fast pace environment;\nProficient in computer applications.\nProficient in English and Chinese, fluent in Putonghua.\nImmediate availability is preferred.\n\nWe offer 5-day work week and attractive remuneration package with birthday leave,\u00a0 medical medical insurance, and discretionary bonus to the right candidate.\n\nInterested parties please send your full resume with the date of availability and expected salary by email via clicking \"Apply Now\". Only shortlisted candidates will be notified. Personal data collected will be used for recruitment purposes only.", "employment_types": ["Full Time", "Permanent"], "selling_points": ["10+ yrs exp.& 5yrs in Manufacturing environment", "Familiar with HK & PRC Acc rules & tax regulations", "Degree in Finance/Acc with Prof. Qualification"], "locations": ["Overseas"], "categories": ["Accounting", "Finance / Accounting Manager", "Financial Controller", "Manufacturing", "Manufacturing Management"], "post_time": "2022-01-10T08:52:34Z", "salary": {"currency": null, "max": null, "min": null, "period": "monthly", "term": null}, "salary_visible": false, "title_keywords": ["assistant financial controller"], "responsibilities": ["budgeting", "operations", "planning", "liaise with", "work under pressure", "internal control", "computer applications", "forecasting", "management report", "cost", "management", "review", "procedures", "cash flow", "tax", "policies", "systems", "insurance", "external auditors"], "requirements": {"degrees": ["degree holder"], "majors": ["accounting"], "languages": ["putonghua", "english", "chinese"], "language_level": ["fluent", "proficient"], "hard_skills": ["prc accounting", "make", "problem solving skills", "internal control"], "soft_skills": ["flexible", "responsible", "strategic thinking", "well-organized", "pleasant", "analytical mind", "interpersonal skills", "problem solving skills", "proactive", "work under pressure"], "languages_combined": [{"language": "putonghua", "language_level": ["fluent"]}, {"language": "english", "language_level": ["proficient", "fluent"]}, {"language": "chinese", "language_level": ["proficient", "fluent"]}]}, "experience_required": {"duration": ["3 years", "10 years"], "field": ["retail industry", "financial"]}}, {"job_id": "100003009041911", "location_code": "hk", "company": "CLP Power Hong Kong Limited", "job_title": "Accounting Assistant (2-Year Contract)  [Ref. CLPP-CD-FIN-AA]", "description": "Job Highlights\n\nManage all aspects of cash and digital asset for the Group\nProvide finance and treasury assistance with new business initiatives, recommendations to enhance financial performance and business opportunities\nParticipate in generating growth strategy for derivative products like crypto exchange or financial products roll out\nBuild cohesion and connectivity between the business team, engineering team and compliance team\nGood understanding and knowledge of TECHFin, eWallet, ERP Solution, e-commerce module,\u00a0etc.\n\nRequirement\n\nBachelor degree holder in related discipline\n5-year work experiences or above at a financial institution, VC-funded tech start-up or a high-growth technology company is preferred\nAbility to manage and execute multiple work streams and have an owner\u2019s mindset \u201croll up your sleeves\u201d\nExperience with financial system implementation in a similar role (gathering user requirements, enhancement requests, working on systems implementations, training) will be an advantage\nExcellent spoken and written English is essential\nStrong inter-personal and people management skills, with ability to work well with others as a team\n\nInterested applicants please provide your detailed resume stating your current and expected salary to us\u00a0by clicking \u2018Apply Now\u2019\n\nPersonal data collected would be used for recruitment purpose only\u00a0and we reserve the rights to consider the applications for other positions in our Group.", "employment_types": ["Full Time"], "selling_points": [], "locations": ["Sham Shui Po"], "categories": ["Accounting", "Accountant", "Financial Controller"], "post_time": "2022-01-13T18:54:32Z", "salary": {"currency": null, "max": null, "min": null, "period": "monthly", "term": null}, "salary_visible": false, "title_keywords": ["accounting assistant"], "responsibilities": ["management", "financial system", "business initiatives", "business opportunities", "compliance", "systems", "implementation", "recruitment", "personal data"], "requirements": {"degrees": ["bachelor degree holder"], "majors": [], "languages": ["english"], "language_level": ["excellent"], "hard_skills": ["crypto", "vc", "e-commerce", "erp", "system implementation", "exchange"], "soft_skills": ["detailed", "inter-personal"], "languages_combined": [{"language": "english", "language_level": ["excellent"]}]}, "experience_required": {"duration": ["5-year"], "field": ["tech", "training", "financial"]}}, {"job_id": "100003009040133", "location_code": "hk", "company": "Texco Hook & Eye Tape Ltd.", "job_title": "Finance Operations & Internal Control Manager / Assistant Manager (Station in Vietnam and China)", "description": "Required Skills & Experience:\u00a0\n\nDegree holder in Finance or Accounting with professional qualification or equivalent\nMinimum 10 years\u2019 experience with at least 5 years in manufacturing environment\nFamiliar with Hong Kong/PRC accounting rules and tax regulations policies\nExperienced in EMS industry and ERP system implementation is an advantage\nGood command of written and spoken Cantonese, Mandarin and English\nProactive and able to work in dynamic environment\nPrior PRC/Overseas exposure is a must\nImmediate available is preferable\n\nWe offer 5 day work week, attractive remuneration and fast promotion opportunities to the right talents. Interested parties please submit your full resume with qualifications, career history, availability, current and expected salary by kicking \"APPLY NOW\"", "employment_types": ["Full Time"], "selling_points": [], "locations": ["Not Specified"], "categories": ["Accounting", "Finance / Accounting Manager", "Financial Controller"], "post_time": "2022-01-12T01:38:34Z", "salary": {"currency": null, "max": null, "min": null, "period": "monthly", "term": null}, "salary_visible": false, "title_keywords": ["operations", "manager", "assistant manager"], "responsibilities": ["tax", "regulations", "policies", "ems", "implementation"], "requirements": {"degrees": ["degree holder"], "majors": ["finance", "accounting"], "languages": ["cantonese", "english", "mandarin"], "language_level": ["good command"], "hard_skills": ["ems", "erp system", "dynamic", "prc accounting"], "soft_skills": ["dynamic environment", "proactive"], "languages_combined": [{"language": "cantonese", "language_level": ["good command"]}, {"language": "english", "language_level": ["good command"]}, {"language": "mandarin", "language_level": ["good command"]}]}, "experience_required": {"duration": ["at least 5 years", "minimum 10 years"], "field": ["manufacturing"]}}, {"job_id": "100003009042324", "location_code": "hk", "company": "JH Partners (Asia) Company Limited", "job_title": "Fluent Japanese Speaking  Accounting Manager (Japanese Insurance company)", "description": "We are looking for an energetic, innovative & highly motivated professional to join the Financial Planning & Control Team of the Finance Department in Corporate Development. Reporting to the Manager - Financial Planning & Control, the appointee will be responsible for the following: -\n\nCompile the capital expenditure budget and ensure that it is financially justified for management approval and is subsequently monitored effectively with forecast updated periodically\nPerform period end closing activities such as accruals, adjustments and reports preparation\nProvide professional advice and support to user departments in relation to financial or control related matters\nSupport decision making by directly involving in quantitative and qualitative analysis\nImplement control procedures; report and review their effectiveness\nProvide day-to-day office and administration support\nConduct ad-hoc projects\n\nRequirements:\n\nA recognized university degree in relevant discipline, preferably a member of a recognized accountancy body\nA minimum of three years of relevant working experience\nStrong problem solving and interpersonal skills\nProficient in Microsoft Office applications; familiar with SAP would be an advantage\nA good team player, proactive, able to work under pressure and meet tight schedules\n\nPlease apply by clicking the \"Apply now\" button\u00a0giving a detailed C.V., including academic qualification, career history, current and expected salary, major achievements and personal attributes on or before 21 January 2022.\n\nImportant: To facilitate our easy tracking please use a unique file name for all attachments and your email subject box in this format: FIN_AA_Last Name_First Name_Other Names (if applicable)\n\nApplicants not invited for interview within 6 weeks from the closing date may assume their applications unsuccessful.\n\nInformation provided will be for recruitment purpose within the CLP Group and only short-listed candidates will be contacted. We comply with all applicable laws and regulations of HKSAR in handling applications. For details of the Personal Information Collection Statement, please visit our website: https://clp.to/engPICS\n\nFor further information on our company, please visit our website:\nhttps://www.clpgroup.com/\n\nDate Exhibited: 14.01.2022\n\nDate Withdrawn: 21.01.2022\n\nInformation Classification: PROPRIETARY\n\n(\u672c\u9805\u8077\u4f4d\u7a7a\u7f3a\u53ea\u5099\u82f1\u6587\u7248\u672c)", "employment_types": ["Full Time"], "selling_points": ["Fluent Japanese", "At least 10 years experiences in Accounting feild", "Management Experience is required"], "locations": ["Tsim Sha Tsui"], "categories": ["Accounting", "Chief Accountant", "Finance / Accounting Manager", "Financial Controller"], "post_time": "2022-01-12T07:02:43Z", "salary": {"currency": null, "max": null, "min": null, "period": "monthly", "term": null}, "salary_visible": false, "title_keywords": ["accounting manager"], "responsibilities": ["regulations", "schedules", "budget", "website", "ad-hoc projects", "administration", "work under pressure", "control", "reports", "forecast", "report", "reporting", "management", "review", "procedures", "tracking", "analysis", "recruitment", "planning"], "requirements": {"degrees": ["university degree"], "majors": ["accountancy"], "languages": [], "language_level": [], "hard_skills": ["sap", "microsoft office", "analysis", "problem solving", "c"], "soft_skills": ["meet tight schedules", "good team player", "proactive", "responsible", "work under pressure", "detailed", "innovative", "problem solving", "unique", "motivated", "interpersonal skills", "energetic", "decision making"], "languages_combined": []}, "experience_required": {"duration": ["minimum of three years"], "field": ["relevant working experience"]}}, {"job_id": "100003009036911", "location_code": "hk", "company": "ConnectedGroup Limited", "job_title": "Senior Finance Manager, Global Controllership (MNC)", "description": "Position Responsibilities\n\n\nReport to Director of Finance professionals\nImplement and streamline operational and finance policies through process re-engineering and continuous improvement\nSet SOP on daily operation process and procedure\nSet up internal control system, policies and procedures for the company\nLead the implementation, review and monitor internal control and risk management policies according to the statutory guidelines and business requirements\nEngaging remediation of identified issues through follow-up\nProvide training and guidance on risk management, internal control and compliance related issues and projects\nImplement the Company internal audit and ad hoc audit as well as execute follow-up actions on audit findings including any irregularities or incidents\nCosting Analysis, Monitor and Control suggestion\nPosition Requirements\n\n\nA degree in Accounting, Finance or related discipline\nAt least 7+ years working experiences preferably with Manufacturing background\nExtensive experiences in internal control, policy and procedures\nFamiliar with setting up internal control and risk management policies is a definite advantage\nHave a self-motivated attitude to always strive for solutions\nGood command of spoken and written English and Chinese, know Vietnamese is advantage\nDetail-oriented, self-motivated & discipline, good communication and analytical skills\nInterested parties please e-mail full resume with expected salary to Apply Now\n(All information collected for recruitment purpose only)", "employment_types": ["Full Time", "Permanent"], "selling_points": ["One of the market leading players in the industry", "Global scope exposure", "Attractive package with promising career prospect"], "locations": ["Not Specified"], "categories": ["Accounting", "Finance / Accounting Manager", "Financial Controller", "Others"], "post_time": "2022-01-11T00:00:22Z", "salary": {"currency": null, "max": null, "min": null, "period": "monthly", "term": null}, "salary_visible": false, "title_keywords": ["senior finance manager"], "responsibilities": ["provide training", "internal audit", "audit", "internal control", "control", "ad hoc", "compliance", "monitor", "implementation", "re-engineering", "report", "guidance", "management", "review", "procedures", "costing analysis", "irregularities", "guidelines", "policies", "daily operation"], "requirements": {"degrees": ["degree"], "majors": ["finance", "accounting"], "languages": ["vietnamese", "english", "chinese"], "language_level": ["advantage", "good command"], "hard_skills": ["analytical skills", "internal control"], "soft_skills": ["self-motivated", "analytical skills", "communication", "detail-oriented", "extensive"], "languages_combined": [{"language": "vietnamese", "language_level": ["advantage", "good command"]}, {"language": "english", "language_level": ["advantage", "good command"]}, {"language": "chinese", "language_level": ["advantage", "good command"]}]}, "experience_required": {"duration": ["at least 7+ years"], "field": ["manufacturing"]}}, {"job_id": "100003009048174", "location_code": "hk", "company": "Louis Vuitton Pacific Limited", "job_title": "Assistant Manager - Financial Control", "description": "Our Client (Japanese Insurance company\u00a0) is looking for Fluent Japanese Speaking\u00a0 Accounting Manager.\n\nResponsibilities\n\n\n\n\u30fbManagement of accounting and finance members including subsidiaries\n\u30fb Monthly and yearly closing management\n\u30fb Cash flow management\n\u30fb Create management report\n\n\n\nRequirements\n\n\u3010Must\u3011\nFluent Japanese and\u00a0 Business level of English\nAt least 10 years experiences in Accounting and Finance feild\nManagement Experience\n\n\u3010Welcome\u3011\nExperience to manage branch of China and Asean regions\u00a0\nWorking experience in Japan or Japanese Company\n\n\n1) Expected salary\n2) Current salary\n3) Reason for leaving current and past employments\n\nPersonal data collected will be used for employment-related purpose only.\u00a0We\u00a0regret to inform that only shortlisted candidates will be notified, thank you.", "employment_types": ["Full Time", "Permanent"], "selling_points": ["Career Opportunity with Louis Vuitton", "Finance/ Treasury operations - APAC exposure", "5 day work week, competitive remuneration"], "locations": ["Quarry Bay"], "categories": ["Accounting", "Financial Controller", "Banking / Finance", "Corporate Finance", "Treasury"], "post_time": "2022-01-14T05:39:26Z", "salary": {"currency": null, "max": null, "min": null, "period": "monthly", "term": null}, "salary_visible": false, "title_keywords": ["assistant manager"], "responsibilities": ["management", "management report", "cash flow"], "requirements": {"degrees": [], "majors": [], "languages": ["japanese", "english"], "language_level": ["fluent"], "hard_skills": ["inform", "reason"], "soft_skills": [], "languages_combined": [{"language": "japanese", "language_level": ["fluent", "fluent"]}, {"language": "english", "language_level": ["fluent"]}]}, "experience_required": {"duration": ["at least 10 years"], "field": ["finance", "management", "accounting"]}}, {"job_id": "100003009031718", "location_code": "hk", "company": "", "job_title": "Financial Controller/Senior Finance Manager", "description": "Senior Finance Manager, Global Controllership (MNC)\n\nOur client is a renowned international services company. They have developed a worldwide network across the globe. We are now seeking a senior professional to join them as a Senior Finance Manager for their Global Controllership team to work closely with the growing business.\n\nPosition Responsibilities\n\nLead the enhancement and standardization of financial controls, processes & reporting globally to achieve better quality and accuracy in financial reporting\nImplement and streamline operational and finance policies through process re-engineering and continuous improvement\nProactively manage and continuously improve the overall quality of the Group's financial reporting and internal control environment\nEstablish the internal control system, policies and procedures, for the group\nLead the implementation, review and monitor internal control and risk management policies according to the statutory guidelines and business requirements\nSupport key process and control owners by providing training and guidance on risk management, internal control and compliance related issues and projects\nCollaborate and provide guidance to Finance teams across the world on the application of Group accounting policies and IFRS reporting as required\nIdentify existing process deficiencies and inconsistencies and provide recommendations on improvement plans\n\nPosition Requirements\n\nDegree holder in Finance, Accounting or related discipline with CPA qualification\nBig 4 accounting firms training background is a MUST\nMinimum 10 years working experience, ideally with exposure to group consolidation in global headquarter environment\nSolid former Regional or Global exposure is essential\nExperienced in automating and simplifying process and control improvements\nAbility to deal with ambiguities and work within ill-defined boundaries and challenge status quo\nAble to work independently, but at the same time also a good team player with excellent stakeholder management and communication skills as well\nStrong interpersonal capabilities and ability to work cross - functionally with international teams and management on all levels\nExperienced in HFM and SAP\nGood command of spoken and written English and Chinese (Putonghua and Cantonese)\nDetail-oriented, self-motivated & discipline, good communication and analytical skills\n\nInterested individuals can apply now and send CV to Vivian Wong, or call +852 3972 5831 for more information. Only relevant candidates will be contacted\n\nFor a more comprehensive list of our vacancies, please visit: www.connectedgroup.com", "employment_types": ["Full Time", "Permanent"], "selling_points": [], "locations": ["Central"], "categories": ["Accounting", "Chief Accountant", "Finance / Accounting Manager", "Financial Controller"], "post_time": "2022-01-07T09:45:26Z", "salary": {"currency": null, "max": null, "min": null, "period": "monthly", "term": null}, "salary_visible": false, "title_keywords": ["senior finance manager", "financial controller"], "responsibilities": ["quality", "accounting policies", "plans", "internal control", "collaborate", "control", "compliance", "monitor", "implementation", "teams", "re-engineering", "reporting", "management", "guidance", "review", "procedures", "provide recommendations", "provide guidance", "guidelines", "policies", "financial reporting"], "requirements": {"degrees": ["degree holder"], "majors": ["finance", "accounting"], "languages": ["cantonese", "putonghua", "english", "chinese"], "language_level": ["good command"], "hard_skills": ["cpa", "sap", "analytical skills"], "soft_skills": ["communication skills", "good team player", "work independently", "self-motivated", "detail-oriented", "communication", "analytical skills", "comprehensive", "interpersonal"], "languages_combined": [{"language": "cantonese", "language_level": ["good command"]}, {"language": "putonghua", "language_level": ["good command"]}, {"language": "english", "language_level": ["good command"]}, {"language": "chinese", "language_level": ["good command"]}]}, "experience_required": {"duration": ["minimum 10 years"], "field": ["consolidation"]}}, {"job_id": "100003009034009", "location_code": "hk", "company": "Links International", "job_title": "(Senior) Finance Manager - Group Financial Reporting", "description": "Responsibilities:\n\nReport to CFO;\nManaging internal and external financial reporting requirements including consolidation, compliance and controlling activities;\nManaging parties including external auditors, tax authorities and internal business units;\nLeading cash and liquidity management and credit risk management;\nLeading forecasting and budgeting;\nSetting departmental KPIs for performance tracking;\nCoordinating company secretarial matters for the Group;\nSupport various internal stakeholders in matters relating to internal controls, tax, and project implementations\nTo perform additional duties and other ad hoc assignments as requested\n\n\u00a0Requirements:\n\nDegree holder in Accounting, Finance, Business Administration or related discipline, qualified accountant of HKICPA/ACCA\nAt least 10-15 years in an all-rounded accounting function, experience with financial reporting and accounting with 5 years\u2019 experience in managerial level\nStrong analytical ability and forecasting skills with strong attention to detail\nKnowledge in China accounting, laws and regulations\nExperience in Big4 or financial institutions is a plus\nExperience in medical related industry is a plus\nProficient in both written and spoken English & Chinese\nGood time management skill and able to work under pressure\nStrong communication skills and connect proactively across various levels in the Business Units\nProficient user in Excel\nCandidate with less experience will be considered as Senior Finance Manager\n\n(Personal data will be used for recruitment purpose only.\u00a0\u00a0All information received will remain confidential and will be destroyed after 6 months.)\n\nInterested candidates, please contact us at 34279018 for company details before applying.", "employment_types": ["Full Time", "Permanent"], "selling_points": ["Guaranteed 13 months salary", "Fast track career path", "All rounded and dynamic role"], "locations": ["Not Specified"], "categories": ["Accounting", "Chief Accountant", "Finance / Accounting Manager", "Financial Controller"], "post_time": "2022-01-10T02:23:14Z", "salary": {"currency": "HKD", "max": 69999, "min": 45000, "period": "monthly", "term": null}, "salary_visible": true, "title_keywords": ["finance manager"], "responsibilities": ["tax", "management", "tracking", "budgeting", "additional duties", "compliance", "financial reporting", "ad hoc assignments", "kpis", "report", "forecasting", "external auditors"], "requirements": {"degrees": ["degree holder"], "majors": ["finance", "accounting", "business administration"], "languages": ["english", "chinese"], "language_level": ["proficient"], "hard_skills": ["excel", "acca", "plus", "hkicpa"], "soft_skills": ["communication skills", "time management skill", "attention to detail", "work under pressure"], "languages_combined": [{"language": "english", "language_level": ["proficient"]}, {"language": "chinese", "language_level": ["proficient"]}]}, "experience_required": {"duration": ["5 years", "at least 10-15 years"], "field": ["managerial", "financial", "related", "finance manager", "financial institutions", "accounting", "medical"]}}, {"job_id": "100003009046396", "location_code": "hk", "company": "Wheelock Properties (Hong Kong) Ltd", "job_title": "Business Analyst", "description": "Our client is a well established living product store in Greater China.\u00a0\u00a0 They are looking for a potential candidate to their Finance team.\n\nJob Responsibilities :\n\nReported to Head of Finance and lead a team of General Accounting\nResponsible to prepare financial statements for the CS Group companies in Hong Kong with reference to a set of accounting policies and procedures\nAdvising line managers in the process of developing policies or procedures for their business operations ensuring compliance with the accounting policies and guidelines\nWork with IT for system and equipment development and testing in new store opening projects\nProvide financial advise on the tenant and consignment contract renewal application for management decision making\nLead and provide continuous coaching to a team of staff in carrying out the accounting operations and reporting\nTransfer pricing and review intercompany transaction flows\n\nJob Requirements :\n\nDegree holder in Finance & Accounting or equivalent\nQualified Accountant with 7 years relevant experiences in which at least 5 years in supervisory level in retail / F&B business\nHands on SAP experience\nPresentable, strong business acumen, leadership, interpersonal and communication skills\nGood command of both spoken and written English & Mandarin\nAnalytical, detail-minded, result-oriented , able to meet tight deadline\n\n\u00a0Our client will offer competitive remuneration package and good career prospects to the potential candidate, interested parties please quote the ref. no.\u00a0ACC-vh-111-JDB\u00a0and submit your resume to\u00a0Ms. Vida Hung\u00a0by our email address.\n\nAll profiles are handled with strictest confidentiality. Shortlisted candidates would be notified", "employment_types": ["Full Time", "Permanent"], "selling_points": [], "locations": ["Central"], "categories": ["Accounting", "Financial Analyst", "Financial Controller", "Banking / Finance", "Corporate Finance"], "post_time": "2022-01-13T18:55:19Z", "salary": {"currency": null, "max": null, "min": null, "period": null, "term": null}, "salary_visible": false, "title_keywords": ["business analyst"], "responsibilities": ["reporting", "management", "guidelines", "policies", "operations", "compliance", "procedures", "developing", "financial statements", "testing", "review", "lead a team", "accounting policies"], "requirements": {"degrees": ["degree holder"], "majors": ["finance", "accounting"], "languages": ["english", "mandarin"], "language_level": ["good command"], "hard_skills": ["sap", "acumen"], "soft_skills": ["detail-minded", "communication skills", "result-oriented", "presentable", "hands on", "meet tight deadline", "business acumen", "leadership", "interpersonal"], "languages_combined": [{"language": "english", "language_level": ["good command"]}, {"language": "mandarin", "language_level": ["good command"]}]}, "experience_required": {"duration": ["7 years", "at least 5 years"], "field": ["business", "supervisory level", "f&b", "retail"]}}, {"job_id": "100003009035079", "location_code": "hk", "company": "Michael Page", "job_title": "Finance Manager, 50k, PRC Education Preferred", "description": "Responsibilities:\n\nLead and manage a sizable team\nTimely preparation of monthly group consolidation, interim and annual report and other financial reporting functions\nAnalyze the group financial results in details and make assurance of the accuracy and quality of the financial reports\nOversee the reporting from overseas business units and ensure group accounting policies are consistently applied by business units and advise business units on compliance with the Hong Kong Listing Rules requirements\nLiaise with external auditors and professional advisors\nTake initiative to enhance internal controls, drive process improvement and operational efficiency\nAssist in system migration and implementation\nOrganize work schedules and setting priorities in order to meet critical deadlines\nAddress ad-hoc reporting requests work and participate in projects and assignments\n\nRequirements:\n\nDegree holder in Accounting, Finance or a related discipline and member of the HKICPA or a reputable accounting association\nMinimum 5 years' relevant experience gained in listed/ sizeable companies and also with professional experience in an international accounting firm is a must\nSound knowledge in HKFRS, Hong Kong Listing Rules and other financial reporting requirements relevant for a sizeable Hong Kong listed company\nProficiency in Excel, Word and PowerPoint\nFamiliar with SAP applications will be an added advantage\nExcellent command in written and spoken English and Chinese\nProactive, dynamic, good at multi-tasking and able to work independently and meet tight deadlines\nGood communication, interpersonal and analytical skills", "employment_types": ["Full Time", "Permanent"], "selling_points": ["CPA is a must", "PRC Education Preferred - 211 or 958", "13 Months Guaranteed with Bonus"], "locations": ["Not Specified"], "categories": ["Accounting", "Chief Accountant", "Finance / Accounting Manager", "Financial Controller"], "post_time": "2022-01-10T05:51:17Z", "salary": {"currency": null, "max": null, "min": null, "period": "monthly", "term": null}, "salary_visible": false, "title_keywords": ["finance manager"], "responsibilities": ["ad-hoc", "reporting", "financial reports", "schedules", "compliance", "quality", "implementation", "external auditors", "accounting policies", "financial reporting", "liaise with", "migration", "listing", "report"], "requirements": {"degrees": ["degree holder"], "majors": ["finance", "accounting"], "languages": ["english", "chinese"], "language_level": ["excellent"], "hard_skills": ["excel", "hkfrs", "sap", "word", "powerpoint", "analytical skills", "dynamic", "hkicpa"], "soft_skills": ["work independently", "meet tight deadlines", "analytical skills", "communication", "multi-tasking", "dynamic", "proactive", "interpersonal"], "languages_combined": [{"language": "english", "language_level": ["excellent"]}, {"language": "chinese", "language_level": ["excellent"]}]}, "experience_required": {"duration": ["minimum 5 years"], "field": ["accounting", "relevant experience"]}}, {"job_id": "100003009033591", "location_code": "hk", "company": "SinoMab BioScience Ltd", "job_title": "Assistant Internal Audit Manager/Senior Internal Auditor", "description": "Responsibilities:\n\n\nAssist Department Manager in corporate financial management and control in Company\u2019s financial activities\nConduct in-depth analysis and market research on peers / property market performance / tracking / benchmarking etc.\nProvide insights on funding forecast and budgetary control, perform variance analysis, review and monitor costs inherent that have dual accountability to both finance and business nature\nWork closely with other departments in the provision of management information and financial analysis management reporting package\nReview workflows and propose area of improvement / streamline\nParticipate ad hoc projects or presentations as assigned\nRequirements:\nBachelor degree or above in Accounting, Finance, Economics or other relevant disciplines\nWith at least 8 years' relevant experience in management accounting, market research or in similar position preferred\nCPA is preferred, but not a must\nExperience in listed company highly desired and exposure of property industry and advantage\nCreative & resourceful with good analytical mindset and communication skills\nExcellent command of English and Cantonese including Mandarin\nHighly proficient in MS office applications including Excel & PowerPoint\n\nWe offer ample opportunities for career development and attractive salary package commensurate with experience and qualifications. \u00a0Interested parties please apply with full resume via\u00a0\u201cAPPLY NOW\u201d.\u00a0\n\nFor further information on Wheelock Properties (Hong Kong) Limited, please visit our website:\u00a0www.wheelockpropertieshk.com.\n\nWe are an equal opportunities employer and invite applications from all qualified candidates. Personal data collected will be treated in strict confidence and handled by authorized persons for recruitment-related purposes only within The Wheelock & Wharf Group. Applicants not hearing from us within 2 months may consider their applications unsuccessful.\u00a0", "employment_types": ["Full Time"], "selling_points": ["Group level audit function", "Attractive Remuneration Package", "5-day work week, 13-month pay, medical benefits"], "locations": ["Shatin Area"], "categories": ["Accounting", "Audit", "Financial Controller", "Banking / Finance", "Risk Management"], "post_time": "2022-01-10T01:14:02Z", "salary": {"currency": null, "max": null, "min": null, "period": "monthly", "term": null}, "salary_visible": false, "title_keywords": ["manager", "internal auditor", "assistant"], "responsibilities": ["provide insights", "management", "control", "analysis", "review", "monitor", "market research", "presentations", "work closely with other departments", "financial analysis", "variance analysis", "ad hoc projects", "management reporting", "forecast", "costs", "tracking"], "requirements": {"degrees": ["degree or above", "bachelor"], "majors": ["finance", "accounting", "economics"], "languages": ["cantonese", "english", "mandarin"], "language_level": ["excellent"], "hard_skills": ["powerpoint", "cpa", "excel", "ms office"], "soft_skills": ["communication skills", "creative", "resourceful"], "languages_combined": [{"language": "cantonese", "language_level": ["excellent"]}, {"language": "english", "language_level": ["excellent"]}, {"language": "mandarin", "language_level": ["excellent"]}]}, "experience_required": {"duration": ["at least 8 years"], "field": ["management accounting", "relevant experience", "market research"]}}, {"job_id": "100003009043858", "location_code": "hk", "company": "Gravitas Recruitment Group", "job_title": "Financial Reporting M/AM- Reputable Insurer", "description": "Our client is a reputable property company. They are now looking for a talent Finance Manager to join their finance team.\n\nClient Details\n\nOur client is a reputable property company. They are now looking for a talent Finance Manager to join their finance team.\n\nDescription\n\nReporting to the GM Finance, you will be responsible for\n\nPreparing for the Main Board IPO listing for the company\nHandling company secretarial matters after IPO\nPreparing annual and interim reports\nStrengthening internal controls, corporate governance and streamline accounting procedures to comply with the Hong Kong Listing Rules / standards\nProviding recommendations to enhance financial performance and business opportunities\nLiaising with CPA firm for audit and tax related matters\n\nProfile\n\nPRC University is highly preferred\n\nExcellent communication skills (English and Mandarin)\n\nDegree Holder in Business/Accounting/Finance\n\nJob Offer\n\nMain Board IPO Experience\nCompetitive Remuneration\n\nTo apply online please click the 'Apply' button below.\nFor a confidential discussion about this role please contact Nicole Hui on +852 3412 4832.", "employment_types": ["Full Time", "Permanent"], "selling_points": ["Top-tier Insurance firms", "Financial Reporting", "Open to Big 4"], "locations": ["Not Specified"], "categories": ["Accounting", "Accountant", "Audit", "Financial Controller"], "post_time": "2022-01-13T02:11:50Z", "salary": {"currency": "HKD", "max": 69999, "min": 45000, "period": "monthly", "term": null}, "salary_visible": true, "title_keywords": [], "responsibilities": ["tax", "reporting", "business opportunities", "procedures", "liaising with", "audit", "communication", "reports", "finance team", "contact", "listing"], "requirements": {"degrees": ["degree holder"], "majors": ["finance", "business", "accounting"], "languages": ["english", "mandarin"], "language_level": ["excellent"], "hard_skills": ["cpa", "gm"], "soft_skills": ["communication skills", "responsible"], "languages_combined": [{"language": "english", "language_level": ["excellent"]}, {"language": "mandarin", "language_level": ["excellent"]}]}, "experience_required": {"duration": [], "field": []}}]