[{"job_id": "100003009044521", "location_code": "hk", "company": "r-pac Hong Kong Ltd", "job_title": "Financial Analyst", "description": "Job Responsibilities:\n\n\u00a0\u00a0\u00a0\u00a0\u00a0\u00a0\u00a0\u00a0 Participate in month end closing and conduct timely financial analysis\n\u00a0\u00a0\u00a0\u00a0\u00a0\u00a0\u00a0\u00a0 Preparation of presentation material for monthly operation review\n\u00a0\u00a0\u00a0\u00a0\u00a0\u00a0\u00a0\u00a0 Work collaboratively with various parties to collect and summarize information\n\u00a0\u00a0\u00a0\u00a0\u00a0\u00a0\u00a0\u00a0 Assist in preparation of annual budget and periodic forecasts\n\u00a0\u00a0\u00a0\u00a0\u00a0\u00a0\u00a0\u00a0 Other ad hoc tasks as assigned\n\n\u00a0Job Requirements:\n\n\u00a0\u00a0\u00a0\u00a0\u00a0\u00a0\u00a0\u00a0 Bachelor\u2019s Degree in Finance, Accounting or other related discipline\n\u00a0\u00a0\u00a0\u00a0\u00a0\u00a0\u00a0\u00a0 Student member of HKICPA or other related professional bodies\n\u00a0\u00a0\u00a0\u00a0\u00a0\u00a0\u00a0\u00a0 3-7 years relevant work experience\n\u00a0\u00a0\u00a0\u00a0\u00a0\u00a0\u00a0\u00a0 High Excel analytical ability and hands on skill set is essential\n\u00a0\u00a0\u00a0\u00a0\u00a0\u00a0\u00a0\u00a0 Understanding of financial statements and high degree of business acumen\n\u00a0\u00a0\u00a0\u00a0\u00a0\u00a0\u00a0\u00a0 Proficiency in the use of Microsoft Office Suite: Excel, PPT, Access\n\u00a0\u00a0\u00a0\u00a0\u00a0\u00a0\u00a0\u00a0 Good command of written and spoken English, Mandarin & Cantonese\n\u00a0\u00a0\u00a0\u00a0\u00a0\u00a0\u00a0\u00a0 Good communication, interpersonal & presentation skills\n\u00a0\u00a0\u00a0\u00a0\u00a0\u00a0\u00a0\u00a0 Knowledge of Flex system, SAP & ERP\n\u00a0\u00a0\u00a0\u00a0\u00a0\u00a0\u00a0\u00a0 Familiarity with PRC accounting standards and taxation regulations will be an advantage\n\u00a0\u00a0\u00a0\u00a0\u00a0\u00a0\u00a0\u00a0 Able to work under pressure and might tight deadlines\n\nWe offer excellent career development opportunities with a highly competitive salary supported by a benefits program including 5-days work, medical, MPF and discretionary bonus. Interested parties please click \"APPLY NOW\" for application information.\u00a0\n\n\u00a0**All information submitted will be treated as confidential and used **", "employment_types": ["Full Time"], "selling_points": ["Familiar in financial analysis", "Student member of HKICPA", "3-7 years relevant experiences"], "locations": ["Kwai Hing"], "categories": ["Accounting", "Financial Analyst"], "post_time": "2022-01-13T04:26:45Z", "salary": {"currency": null, "max": null, "min": null, "period": "monthly", "term": null}, "salary_visible": false, "title_keywords": ["financial analyst"], "responsibilities": ["month end closing", "review", "budget", "ad hoc tasks", "financial analysis"], "requirements": {"degrees": ["degree", "bachelor"], "majors": ["business", "finance", "accounting"], "languages": ["cantonese", "english", "mandarin"], "language_level": ["good command"], "hard_skills": ["excel", "sap", "erp", "microsoft office suite", "hkicpa", "flex system", "prc accounting", "acumen"], "soft_skills": ["communication", "presentation skills", "hands on", "business acumen", "interpersonal", "work under pressure"], "languages_combined": [{"language": "cantonese", "language_level": ["good command"]}, {"language": "english", "language_level": ["good command"]}, {"language": "mandarin", "language_level": ["good command"]}]}, "experience_required": {"duration": ["3-7 years"], "field": []}}, {"job_id": "100003009052924", "location_code": "hk", "company": "Brink's Asia Pacific Limited", "job_title": "Finance Analyst", "description": "Responsibilities:\n\nPrepare different types of financial reports such as budget, cash flow forecasts, business modeling, financial projections etc.\u00a0\u00a0\nPerform financial analysis of various data and being able to discern areas of importance.\nAssist in business development with emphasis on data collection, data comparison, budget preparation and financial analysis.\nAssist the supervisor on any ad-hoc assignments\n\nRequirements:\n\nDegree holder in finance/accounting with professional qualifications.\u00a0\u00a0\nMinimum 6 years of work experience, with a major focus on financial planning & analysis.\u00a0\u00a0\nExposure in Big 4 is preferred.\u00a0\u00a0\nWith comprehensive knowledge of IFRS and other regulatory requirements.\nExperience with Business Object and Hyperion financial management tool is an added advantage\nGood interpersonal skills and ability to clearly communicate with others.\u00a0\nHigh level of motivation, able to meet tight timelines, work independently and under pressure.\nInitiative with good analytical and communication skills.\nGood computer literacy in particular advanced skills in using Excel and PowerPoint.\n\nWe offer attractive remuneration package fringe benefits including\u00a0Banking Holiday,\u00a0Annual Leaves,\u00a0Discretionary Bonus\u00a0&\u00a0Additional Pension Contribution from Company\u00a0&\u00a0Medical Insurance. If you have the desire to join us, please send us your resume immediately with your present & expected salary by clicking Apply Now.\n\n(The information provided will be used for employment related\u00a0purpose only. All information of unsuccessful applicants will be destroyed within six months.)", "employment_types": ["Full Time", "Permanent"], "selling_points": ["Exposure in professional services", "With in-house experience preferred", "Good language skills"], "locations": ["Kwai Fong"], "categories": ["Accounting", "Financial Analyst", "Banking / Finance", "Analyst"], "post_time": "2022-01-17T04:34:12Z", "salary": {"currency": null, "max": null, "min": null, "period": "monthly", "term": null}, "salary_visible": false, "title_keywords": ["analyst"], "responsibilities": ["financial reports", "data", "ad-hoc assignments", "budget", "financial analysis", "cash flow", "data collection"], "requirements": {"degrees": ["degree holder"], "majors": ["finance", "accounting"], "languages": [], "language_level": [], "hard_skills": ["excel", "ifrs", "professional qualifications", "analysis", "powerpoint", "focus"], "soft_skills": ["communication skills", "work independently", "under pressure", "advanced", "computer literacy", "comprehensive", "interpersonal skills", "focus", "initiative"], "languages_combined": []}, "experience_required": {"duration": ["minimum 6 years"], "field": ["business", "management", "planning", "financial"]}}, {"job_id": "100003009051854", "location_code": "hk", "company": "The Great Eagle Group of Companies", "job_title": "Financial Analyst", "description": "Responsibilities:\nConduct analysis on current and past financial data and performance\nPreparing reports and projections with the analysis findings for management\nIdentifying trends in financial performance and providing recommendations for improvement\nReview financial information and forecasts\nDevelop initiatives and policies on improving financial growth\nHandle ad hoc works as assigned by management\n\nRequirements:\n\nDegree holder in Accounting, Finance, Information Technology or other related disciplines\nCertificate in Data Analytics will be an advantage\nMinimum 5 years\u2019 experience in multinational companies/enterprises\nExperience in real estate is an advantage\nStrong analytical and problem solving skills\nGood communication, presentation and interpersonal skills\nResponsible, well-organized, detail-minded, independent and able to work under pressure\nProficiency in MS Office Applications\nGood command of both spoken and written\u00a0English\u00a0and Chinese (including Putonghua)\n\nSalary and benefits will be commensurate with qualifications and experience.\u00a0 Interested parties, please send a full resume with present and expected salary, and date available to\u00a0The Human Resources Department, 32/F., Great Eagle Centre, 23 Harbour Road, Wanchai, Hong Kong\u00a0or\u00a0e-mail to us.\u00a0(Please quote the reference no. on the envelope and the covering letter.)\n\nTo know more about us, please visit our websites at\u00a0http://www.greateagle.com.hk\n\nWe are an equal opportunity employer and welcome applications from all qualified candidates.\n\nPersonal data collected will be treated in strict confidence and used only for recruitment-related purpose. Applicants who have not heard from us within four weeks may consider their applications unsuccessful. All personal data will be destroyed after 12 months.", "employment_types": ["Full Time", "Permanent"], "selling_points": ["Financial research and analysis", "Market trends in financial performance", "Certificate in Data Analytics will be an advantage"], "locations": ["Wan Chai"], "categories": ["Accounting", "Financial Analyst", "Banking / Finance", "Corporate Finance", "Equities / Capital Markets"], "post_time": "2022-01-17T01:23:09Z", "salary": {"currency": null, "max": null, "min": null, "period": "monthly", "term": null}, "salary_visible": false, "title_keywords": ["financial analyst"], "responsibilities": ["management", "ad hoc", "data", "policies", "analysis", "review", "develop", "preparing reports"], "requirements": {"degrees": ["certificate", "degree holder"], "majors": ["related disciplines", "finance", "accounting", "information technology"], "languages": ["putonghua", "english", "chinese"], "language_level": ["good command"], "hard_skills": ["data analytics", "problem solving skills", "ms office"], "soft_skills": ["detail-minded", "independent", "responsible", "well-organized", "communication", "analytical and problem solving skills", "interpersonal skills", "presentation", "work under pressure"], "languages_combined": [{"language": "putonghua", "language_level": ["good command"]}, {"language": "english", "language_level": ["good command"]}, {"language": "chinese", "language_level": ["good command"]}]}, "experience_required": {"duration": ["minimum 5 years"], "field": []}}, {"job_id": "100003009052097", "location_code": "hk", "company": "AVISTA Valuation Advisory Limited", "job_title": "Analyst / Senior Analyst", "description": "Service: Business Valuation\n\nLocation: Hong Kong\n\nJob Description and Responsibilities:\n\nPerform valuations for deal transaction and financial reporting purposes (such as purchase price allocation) under HKFRS, IFRS and US GAAP\nEngage in M&A advisory, financial modeling and other business consulting projects\nProduce and analyze financial model and business information\nConduct data collection and market research\nAssist in preparing proposal and presentation materials for potential valuation leads\n\nRequirements:\n\nUniversity graduates;\nProfessional qualification in Accounting (e.g. HKICPA / ACCA) or CFA would be an advantage;\n1 to 2 years relevant experience in M&A, audit or valuation related position. Experience in international valuation firm would be a plus.\nGood team player with the ability to work independently;\nProficiency in both verbal and written English and Mandarin is essential;\nGood understanding in valuation-related accounting standards (such as intangible assets and purchase price allocation issues) and valuation of financial instruments will be a plus;\nSound technical knowledge and the capability to apply up-to-date valuation methodologies;\nExcellent research, financial modelling and financial analytical skills;\nExcellent interpersonal and communication skills;\nShort business trip to PRC may be required.\nBenefit: We offer attractive remuneration package including a 5-day work week, medical insurance, study leave and good career prospect to the suitable candidate.\n\n\nApplication Procedure: Please send CV with expected salary by clicking \"Apply Now\".\n\nPersonal data will be used for recruitment purpose only.", "employment_types": ["Full Time", "Permanent"], "selling_points": ["Business valuation & financial reporting", "M&A advisory, financial modeling, IPO", "HKICPA/ACCA/CFA will be a plus"], "locations": ["Wan Chai"], "categories": ["Accounting", "Financial Analyst", "Banking / Finance", "Analyst", "Financial Services"], "post_time": "2022-01-17T02:05:31Z", "salary": {"currency": null, "max": null, "min": null, "period": "monthly", "term": null}, "salary_visible": false, "title_keywords": ["analyst", "senior analyst"], "responsibilities": ["valuation", "consulting", "financial modeling", "market research", "purchase", "financial reporting", "data collection"], "requirements": {"degrees": [], "majors": [], "languages": ["english", "mandarin"], "language_level": ["proficiency"], "hard_skills": ["acca", "plus", "cfa", "financial analytical skills", "hkicpa"], "soft_skills": ["communication skills", "good team player", "work independently", "analytical skills", "interpersonal"], "languages_combined": [{"language": "english", "language_level": ["proficiency"]}, {"language": "mandarin", "language_level": ["proficiency"]}]}, "experience_required": {"duration": ["1 to 2 years"], "field": ["related", "relevant experience", "audit"]}}, {"job_id": "100003009052195", "location_code": "hk", "company": "IPSOS Asia Limited", "job_title": "Accountant / Business Analyst", "description": "Role Objective / Purpose\n\n\nThe role of Business Analyst is responsible for all accounting and finance functions of IPSOS HK and to ensure proper accounting records are kept for internal and statutory audits.\n\nRole & Responsibilities:\n\nResponsible for monitoring the operational and accounting system\nMonitor and review the budget and actual spending of projects to ensure data integrity\nOversee the daily accounting functions to ensure accounting records are kept in compliance with the group accounting policies.\nMonitor and supervise the month end closing to ensure all management reports are submitted on time and accurate.\nPrepare monthly financial charts/reports for all IPSOS HK divisions.\nCompile various periodic analytical reports (e.g. Contribution Report, Job Summary Report etc.) and hold discussion meeting with divisional heads regularly so as to make them aware of their updated divisional performance.\nCommunicate with Research Departments regularly to understand and provide necessary support to them\nAssist the statutory audit of IPSOS HK to ensure audit deadline is met.\nParticipate in the group internal audits to make sure proper control procedures are in place.\nReview the existing internal control system and make recommendations on the existing work procedures so as to improve the efficiency.\nAssist in the annual budget process to understand the budget components of each division.\nAssist in the set-up of new accounting software to ensure it meets our business requirement.\nProvide support to Chief Financial Officer for ad hoc reporting so as to meet the tight reporting deadlines.\n\n\nPerson specification\n\nQualification\uff1a\n\nBachelor Degree in Accounting or equivalent with minimum 5 years of audit or accounting experience\n\nKnowledge (including general and IPSOS specific knowledge)\uff1a\n\nKnowledge in SAP system is a definite advantage\nAccounting standards and principles.\nRecent computing development especially in accounting software packages.\nKnowledge in market research products e.g. methodology, product type and client type etc. is preferred.\n\nSkill (including technical and people skill)\uff1a\n\nGood communication and interpersonal skills and able to communicate with people from different background and with different seniority.\nGood language skill both verbal and writing.\nBasic grasp of the market research industry.\nGood computer skill especially in Microsoft Excel, Word, and PowerPoint\nGood presentation skill.\n\nOther Requirements\n\nResponsible and able to work independently.\nDedication and good determination to meet deadlines.\n\nWe offer an attractive remuneration package with 5-day work week to the right candidates. Interested parties please send\u00a0resume with current and expected salary to us. All information collected will be used for recruitment purpose only.", "employment_types": ["Full Time", "Permanent"], "selling_points": ["Accountant", "Financial Analyst", "Audit or Accounting"], "locations": ["Hung Hom"], "categories": ["Accounting", "Accountant", "Financial Analyst", "Others"], "post_time": "2022-01-17T02:26:10Z", "salary": {"currency": null, "max": null, "min": null, "period": "monthly", "term": null}, "salary_visible": false, "title_keywords": ["accountant", "business analyst"], "responsibilities": ["software", "data", "budget", "audit", "communication", "accounting policies", "internal control", "make recommendations", "month end closing", "control", "ad hoc", "compliance", "monitor", "reports", "report", "reporting", "provide support", "review", "monitoring", "procedures", "audits", "communicate with", "market research", "management reports", "daily accounting"], "requirements": {"degrees": [], "majors": [], "languages": [], "language_level": [], "hard_skills": [], "soft_skills": ["work independently", "meet deadlines", "responsible"], "languages_combined": []}, "experience_required": {"duration": [], "field": []}}, {"job_id": "100003009052099", "location_code": "hk", "company": "AVISTA Valuation Advisory Limited", "job_title": "Analyst (2021 / 2022 Graduate Position)", "description": "Service: Business Valuation\nLocation: Hong Kong\n\nScope:\n\nWe are looking for fresh graduates to join our expanding business valuation team of our Hong Kong office. Our analysts will have the opportunities to have a wide range of exposure to various industries of our listed and unlisted clients for different valuation needs. Our business valuation services include:\n\nPerforming valuations for financial reporting purposes, such as equity investments, tangible & intangible assets and financial instruments valuations)\nProviding valuations for transaction purposes such as potential acquisitions and disposals of businesses\nAdvising companies and stakeholders in relation to valuation related matters\n\nResponsibilities:\n\nAnalysts will work as a team in general, with our director, managers and other senior analysts. You are expected to:\n\nAnalyze historical and forecasted financial information provided by clients\nConduct research on comparable financial data and other project-related business and industry information\nProvide assistance to senior colleagues in constructing valuation models and compiling valuation reports\nPrepare valuation analysis and supporting information for discussions and negotiations with clients and other stakeholders involved\nAssist in preparing proposals and presentation materials for potential valuation and consulting leads\nBuild relationships and conduct direct contacts with existing and prospective clients as well as other professional teams (such as sponsors, auditors, financial advisors, lawyers, etc.)\n\nRequirements:\n\nUniversity graduates in all disciplines, preferable with finance and/or accounting degree\nSelf-motivated team player with the ability to work independently in a fast-paced environment\nProficiency in both verbal and written English, Cantonese and Mandarin is essential\nDemonstrate interest in business valuation\nStrong research, financial modeling and financial analytical skills\nExcellent interpersonal and communication skills\nExperience in valuation related fields is a plus\nShort business trips to PRC may be required\n\nBenefits: We offer attractive remuneration package including a 5-day work week, medical insurance and good career prospect to the suitable candidate.\n\nApplication Procedure: Please send your CV with expected salary by clicking \"Apply Now\".\n\nPersonal data will be used for recruitment purpose only.", "employment_types": ["Full Time", "Permanent"], "selling_points": ["Valuations for financial reporting and transaction", "Analyze historical and forecasted financial info", "Fresh graduates are welcome"], "locations": ["Wan Chai"], "categories": ["Accounting", "Financial Analyst", "Banking / Finance", "Analyst", "Financial Services"], "post_time": "2022-01-17T02:05:32Z", "salary": {"currency": null, "max": null, "min": null, "period": "monthly", "term": null}, "salary_visible": false, "title_keywords": ["analyst"], "responsibilities": ["valuation", "consulting", "data", "analysis", "teams", "reports", "provide assistance", "conduct research"], "requirements": {"degrees": ["degree"], "majors": ["finance", "accounting"], "languages": ["cantonese", "english", "mandarin"], "language_level": ["proficiency"], "hard_skills": ["plus", "financial analytical skills"], "soft_skills": ["communication skills", "self-motivated", "work independently", "fast-paced environment", "analytical skills", "team player", "interpersonal"], "languages_combined": [{"language": "cantonese", "language_level": ["proficiency"]}, {"language": "english", "language_level": ["proficiency"]}, {"language": "mandarin", "language_level": ["proficiency"]}]}, "experience_required": {"duration": [], "field": ["related"]}}, {"job_id": "100003009051702", "location_code": "hk", "company": "ASM Technology Hong Kong Limited", "job_title": "SAP System Analyst (Finance Team)", "description": "Job description\nConduct Annual Planning and Quarterly Forecasting\nPartner with Global Costing teams on supporting standard costing process\nTranslate business objectives and requirements into system design that can be supported by SAP\nFacilitate functional teams for new SAP implementation and on-going application update and enhancement globally\nWork closely with internal teams and external vendors to ensure project tasks are delivered on time and are of satisfactory quality with proper documentation\nDesign a test plan and testing standards to monitor system activities\nFormulate SAP user guideline and provide user training\nProvide support on SAP process development and enhancement requests\nProvide ad-hoc support maintenance service and trouble-shooting to end-users\nJob requirements\nDegree holder in IT, Finance/Accounting, or related disciplines.\nMinimum 5 years of experience in SAP FICO module with at least 3 project implementation cycles\nSolid and strong business and technical skills in SAP FICO modules\nStrong interpersonal, communication and analytical skills\nA good team player, initiative and detail-minded\nGood command of written and spoken English, Chinese and Putonghua\nQuarterly travel to Asia Pacific may be required, depending on COVID situation\n\nAttractive salary and fringe benefits package will be offered to the right candidates.\n\nInterested parties please submit your application with cover letter, resume, certificate and transcripts.\n\nData collected will be used for recruitment purpose only. Suitable candidates may be referred to other vacancies within our company.", "employment_types": ["Full Time", "Permanent"], "selling_points": ["Minimum 5 years of experience in SAP FICO module", "Degree holder in IT, Finance/Accounting", "Conduct Annual Planning and Quarterly Forecasting"], "locations": ["Tsing Yi"], "categories": ["Accounting", "Financial Analyst", "Banking / Finance", "Analyst", "Information Technology (IT)", "Others"], "post_time": "2022-01-16T21:50:55Z", "salary": {"currency": null, "max": null, "min": null, "period": "monthly", "term": null}, "salary_visible": false, "title_keywords": ["system analyst"], "responsibilities": ["ad-hoc", "provide support", "maintenance", "teams", "implementation", "quality", "design", "testing", "monitor", "system design", "plan", "documentation", "forecasting", "planning"], "requirements": {"degrees": ["degree holder"], "majors": ["related disciplines", "finance", "it", "accounting"], "languages": ["putonghua", "english", "chinese"], "language_level": ["good command"], "hard_skills": ["sap", "analytical skills"], "soft_skills": ["detail-minded", "good team player", "analytical skills", "communication", "technical skills", "initiative", "interpersonal"], "languages_combined": [{"language": "putonghua", "language_level": ["good command"]}, {"language": "english", "language_level": ["good command"]}, {"language": "chinese", "language_level": ["good command"]}]}, "experience_required": {"duration": ["minimum 5 years"], "field": []}}, {"job_id": "100003009051724", "location_code": "hk", "company": "", "job_title": "Senior Regional FP&A Analyst", "description": "Job Responsibilities\n\nWork closely with senior management provide valuable financial and business insights for APAC region\nSet up and drive monthly and quarterly budgeting, forecasting. Explain variance and reports in presentations\nPerform trend and business analysis and share insights with senior management\nFeasibility studies and conduct financial modelling on new emerging markets and investments\nStandardization and delivery of financial and management reports, business partnership with shared services\nAd hoc projects within the region\n\nRequirements\n\nDegree in Finance and Accounting or relevant subject\nAt least 5-15 years of experience in an analytical position, CPA qualified accountant preferred.\nPrevious experience in a sizable audit firm will be a plus. All rounded finance professionals in reporting and FP&A will also be considered\nStrong analytical and interpersonal skills.\nFluency in English and willingness to be based in Hong Kong\nInterested candidates, please contact us at 800931404 for company details before applying.", "employment_types": ["Full Time", "Permanent"], "selling_points": ["Financial Planning & Analysis projects", "5 yrs FP&A / Management Accounting exp", "Attractive package + industry exposure"], "locations": ["Tsing Yi"], "categories": ["Accounting", "Financial Analyst"], "post_time": "2022-01-16T21:51:10Z", "salary": {"currency": "HKD", "max": 44999, "min": 35000, "period": "monthly", "term": null}, "salary_visible": true, "title_keywords": ["analyst"], "responsibilities": ["budgeting", "presentations", "management reports", "business partnership", "reports", "ad hoc projects", "business analysis", "senior management", "forecasting"], "requirements": {"degrees": ["degree"], "majors": ["finance", "accounting"], "languages": ["english"], "language_level": ["fluency"], "hard_skills": ["cpa", "plus"], "soft_skills": ["interpersonal skills"], "languages_combined": [{"language": "english", "language_level": ["fluency"]}]}, "experience_required": {"duration": ["at least 5-15 years"], "field": ["audit", "analytical"]}}, {"job_id": "100003009050677", "location_code": "hk", "company": "Geox Asia Pacific Limited", "job_title": "Junior Financial Analyst", "description": "Main Responsibilities\nSupport the annual financial planning process (budgeting and forecasting)\nAssist the Business Controller in preparing financial statements and reporting\nAssist with analysis and stores performances by collecting, analyzing and reporting financial and statistical data\nMonitor sales, costs, margins and inventory and carry out all analysis required to identify variance\u2019s causes\nSupport on shop KPI targets settings and monthly controls activities\nAnalyze trends, formulate projections for retail and wholesale business\nWork closely with other Functions to ensure data quality and integrity\nCompletes ad hoc projects and duties assigned by the line manager from time to time\nJob Requirements\nBachelor Degree in\u00a0Accountancy / Economics / Finance or any related discipline\nMinimum 1 year relevant experience in budgeting / forecasting / financial analysis / audit in multinational company (retail Industry preferred)\nProactive, detail-minded and good team player\nGood communication skill and strong analytical skill\nGood command of spoken and written English and Chinese\nStrong MS Excel skills; knowledge of SQL, MS Powerpoint, SAP, Oracle Essbase is a plus\nCandidates with more experience will be considered as Senior Financial Analyst\nWe offer attractive remuneration and fringe benefits to the right candidate. Please submit your application in WORD format (quoting job title) together with a detailed resume, stating current and expected salary by\u00a0\"Apply Now\"\u00a0button.\u00a0\n\n\n(All personal data provided by job applicants are used only for recruitment purpose and will be treated strictly confidential. Unsuccessful applications will be properly disposed within 3 months.)", "employment_types": ["Full Time", "Permanent"], "selling_points": ["Financial Planning & Analysis in Retail & WHS", "Direct Report to Business Controller", "5-Day Work Week, MNC Working Environment"], "locations": ["Wan Chai"], "categories": ["Accounting", "Accounting Clerk / Supervisor", "Financial Analyst", "Financial Controller"], "post_time": "2022-01-15T03:51:13Z", "salary": {"currency": null, "max": null, "min": null, "period": "monthly", "term": null}, "salary_visible": false, "title_keywords": ["financial analyst", "junior"], "responsibilities": ["reporting", "data", "budgeting", "analysis", "planning process", "monitor", "inventory", "financial statements", "quality", "ad hoc projects", "forecasting", "costs"], "requirements": {"degrees": ["degree", "bachelor"], "majors": ["finance", "economics", "accountancy"], "languages": ["english", "chinese"], "language_level": ["good command"], "hard_skills": ["analytical skill", "plus", "sap", "financial analysis", "sql", "ms excel", "ms powerpoint", "oracle"], "soft_skills": ["detail-minded", "good team player", "analytical skill", "communication skill", "proactive"], "languages_combined": [{"language": "english", "language_level": ["good command"]}, {"language": "chinese", "language_level": ["good command"]}]}, "experience_required": {"duration": ["minimum 1 year"], "field": ["retail industry", "multinational company", "audit", "relevant experience", "financial"]}}, {"job_id": "100003009051583", "location_code": "hk", "company": "Amazin Consultants Limited", "job_title": "FP&A Manager (Branded FMCG)", "description": "Responsibilities:\n\nPrepare full set of monthly management accounts and month-end closing independently\nPrepare statutory financial statements and liaise with external auditors\nAnalytical review on management reports to explain business performance\nHandle budgeting and forecasting\nAssist in group consolidation and prepare financials for results announcement\nHandle ad hoc tasks and assignments as required\n\nRequirements:\n\nDegree holder in Accountancy, Finance or other related disciplines\nMember of recognized accounting bodies (HKICPA, ACCA or equivalent) is preferred\n3 \u2013 5 years relevant experience, preferably gained in listed companies or sized CPA firms\nExperience in real estate or hospitality industry is an advantage\nKnowledge of IFRS / HKFRS\nProficient in MS Office Application\nSelf-motivated, detail-oriented, proactive and able to work independently\nGood communication and interpersonal skills\nGood command of both written and spoken English and Chinese\n\nSalary and benefits will be commensurate with qualifications and experience.\u00a0 Interested parties, please send a full resume with present and expected salary, and date available to The Human Resources Department, 32/F., Great Eagle Centre, 23 Harbour Road, Wanchai, Hong Kong or e-mail to us.\u00a0(Please quote the reference no. on the envelope and the covering letter.)\n\nTo know more about us, please visit our website at http://www.greateagle.com.hk.\n\nWe are an equal opportunity employer and welcome applications from all qualified candidates.\n\nPersonal data collected will be treated in strict confidence and used only for recruitment-related purpose. Applicants who have not heard from us within four weeks may consider their applications unsuccessful. All personal data will be destroyed after 12 months.", "employment_types": ["Full Time", "Permanent"], "selling_points": ["Provide analysis and insights on fin planning", "Collect figures from BU heads for bus analysis", "Stable working environment with attractive package"], "locations": ["Others"], "categories": ["Accounting", "Finance / Accounting Manager", "Financial Analyst"], "post_time": "2022-01-16T12:31:21Z", "salary": {"currency": null, "max": null, "min": null, "period": "monthly", "term": null}, "salary_visible": false, "title_keywords": ["manager"], "responsibilities": ["management", "budgeting", "review", "ad hoc tasks", "financial statements", "management reports", "month-end closing", "liaise with", "forecasting", "external auditors"], "requirements": {"degrees": ["degree holder"], "majors": ["related disciplines", "finance", "accountancy"], "languages": ["english", "chinese"], "language_level": ["good command"], "hard_skills": ["acca", "ifrs", "hkfrs", "cpa", "ms office", "hkicpa"], "soft_skills": ["self-motivated", "work independently", "detail-oriented", "communication and interpersonal skills", "proactive"], "languages_combined": [{"language": "english", "language_level": ["good command"]}, {"language": "chinese", "language_level": ["good command"]}]}, "experience_required": {"duration": ["5 years"], "field": ["hospitality industry", "relevant experience"]}}, {"job_id": "100003009051826", "location_code": "hk", "company": "The Great Eagle Group of Companies", "job_title": "Assistant Accountant / Accountant", "description": "The Company\nOne of the largest local leading conglomerates is hiring a FP&A candidate to focus on data analytics for their retail business.\n\nThe Role\n\n\nPerform budget and forecasting, revenue / cost / variance analysis, KPI and performance analysis\nConduct opex / capex analysis and project spending\n\u00a0Liaise with internal stakeholders in business cases, support feasibility study, and target / KPI evaluation\nEnsure company policies and compliance are aligned\nParticipate in ad-hoc projects\n\nYour Profile\n\n\nDegree holder in Finance / Statistics / Quantitative Analysis\nSolid experience in Data Science\nExperience from retail industry preferred\nExcellent communication skills\n\nApply Today\nTo apply online (Word attachment only), please click the 'Apply' button. Interested parties please apply with the most updated CV with expected salary and available date via JobsDB. Applicants who do not hear from us within 2 weeks may consider their applications unsuccessful.\n\nAbout Pathos\nWe are Pathos Consultancy Limited, a boutique recruitment firm based in Hong Kong strategically placing our candidates across all levels in permanent, temporary and contract roles.\u00a0 We specialize in IT and finance roles for banking, financial services and listed MNC sectors.", "employment_types": ["Full Time", "Permanent"], "selling_points": ["Monthly report & month-end closing", "Handle budgeting and forecasting", "HKICPA, ACCA or equivalent is preferred"], "locations": ["Wan Chai"], "categories": ["Accounting", "Accountant", "Accounting Clerk / Supervisor", "Financial Analyst"], "post_time": "2022-01-17T01:18:24Z", "salary": {"currency": null, "max": null, "min": null, "period": "monthly", "term": null}, "salary_visible": false, "title_keywords": ["accountant", "assistant accountant"], "responsibilities": ["cost", "data", "policies", "analysis", "budget", "capex", "compliance", "opex", "variance analysis", "communication", "evaluation", "liaise with", "ad-hoc projects", "forecasting"], "requirements": {"degrees": ["degree holder"], "majors": ["finance", "statistics"], "languages": [], "language_level": [], "hard_skills": ["data analytics", "focus", "analysis", "word"], "soft_skills": ["communication skills", "focus"], "languages_combined": []}, "experience_required": {"duration": [], "field": ["retail industry"]}}, {"job_id": "100003009050961", "location_code": "hk", "company": "DHL EXPRESS (HONG KONG) LIMITED", "job_title": "Financial Analyst, Aviation, Asia Pacific", "description": "Our client is one reputable consumer brand company. \u00a0They are currently looking for high caliber for their FP&A Manager.\n\nProvide analysis and insights on financial planning\nPartner with different business stakeholders and collect figures for business analysis\nStable working environment with attractive package\n\nJob Responsibilities:\n\nProvide analysis and insights on financial planning for management review and business planning\nPartner with different business stakeholders and collect different figures for business analysis\nLead mostly financial planning\u00a0& analysis projects such as sales controlling, cash flow forecast, strategic pricing, product mix analysis, KPI analysis etc for business review\n\nJob Requirement:\n\nBachelor degree with at least 6 years of experience\nTrack exposure in fast-paced environment / FMCG industry\nHighly analytical and detail-oriented with good business sense\nExcellent communication and interpersonal skills\nGood-command of written and verbal English and Chinese\u00a0", "employment_types": ["Full Time", "Permanent"], "selling_points": ["Degree in Finance/Accounting or related discipline", "1 to 3 years of work experience in accounting", "Handling and monitoring timely AP payments"], "locations": ["Lantau Island"], "categories": ["Accounting", "Finance / Accounting Manager", "Financial Analyst", "Others"], "post_time": "2022-01-14T12:07:28Z", "salary": {"currency": null, "max": null, "min": null, "period": null, "term": null}, "salary_visible": false, "title_keywords": ["financial analyst"], "responsibilities": ["analysis", "review", "cash flow", "forecast", "business analysis", "management review", "planning"], "requirements": {"degrees": ["degree", "bachelor"], "majors": [], "languages": ["english", "chinese"], "language_level": ["good"], "hard_skills": ["fmcg industry"], "soft_skills": ["fast-paced environment", "communication and interpersonal skills", "business sense", "detail-oriented"], "languages_combined": [{"language": "english", "language_level": ["good"]}, {"language": "chinese", "language_level": ["good"]}]}, "experience_required": {"duration": ["at least 6 years"], "field": []}}, {"job_id": "100003009054461", "location_code": "hk", "company": "Pathos Consultancy Limited", "job_title": "Business Analysis / Data Analytic Officer, 40K, Retail", "description": "Requirements:\n\nBachelor\u2019s degree in Finance, Business, Accounting or related disciplines. An MBA degree is an added advantage\nMinimum 5 years\u2019 relevant experience in business analysis\nStrong business acumen and numerical sense\nGood analytical and communication skills\nGood command of spoken and written English and Chinese\nFamiliar with PC software e.g. MS Word, Excel, PowerPoint\nResponsibilities:\n\nPerform financial analysis for business opportunities, including financial modelling, valuation analysis and scenario simulations\nConduct insightful operational analysis to investigate ongoing issue\nAssist the team with research to provide business insight and context for business recommendations\nSupport with putting together presentations for senior management\nSource and develop market intelligence available to the team, including monitoring of news and other sources of public information\nExecute relevant industry analysis against competitors\nParticipate in ad hoc projects to understand market development and identify opportunities for business units\nSupport the monitoring and reporting of business units and financial performance of business units\n(Candidates with less experience will be considered as Assistant Business Analyst.)\n\nGood remuneration and attractive fringe benefits will be offered to the successful applicant. Interested parties please apply with full resume, present and expected salary, available date by clicking \"Apply Now\".\n\nFor further information, please visit our company website: www.shkp.com.\n\nWe are an equal opportunity employer and welcome applications from all qualified candidates. All personal data collected will be used for recruitment purpose only.\u00a0 Applicants not hearing from us within 3 months may consider their applications unsuccessful.\u00a0 All personal data collected will be destroyed within 24 months.", "employment_types": ["Full Time", "Permanent"], "selling_points": ["Data Analytics / Business Analysis", "FP&A", "Retail background"], "locations": ["Central"], "categories": ["Accounting", "Consulting", "Finance / Accounting Manager", "Financial Analyst"], "post_time": "2022-01-17T09:39:13Z", "salary": {"currency": null, "max": null, "min": null, "period": "monthly", "term": null}, "salary_visible": false, "title_keywords": ["officer"], "responsibilities": ["valuation", "reporting", "business opportunities", "analysis", "monitoring", "presentations", "develop", "financial analysis", "ad hoc projects", "senior management"], "requirements": {"degrees": ["degree", "bachelor"], "majors": ["related disciplines", "finance", "business", "accounting"], "languages": ["english", "chinese"], "language_level": ["good command"], "hard_skills": ["excel", "analysis", "acumen", "powerpoint", "pc", "ms word"], "soft_skills": ["business acumen", "communication skills"], "languages_combined": [{"language": "english", "language_level": ["good command"]}, {"language": "chinese", "language_level": ["good command"]}]}, "experience_required": {"duration": ["minimum 5 years"], "field": ["business analysis", "relevant experience"]}}, {"job_id": "100003009049825", "location_code": "hk", "company": "Sun Hung Kai Properties Ltd", "job_title": "BUSINESS ANALYST / ASSISTANT BUSINESS ANALYST", "description": "Responsibilities\n\nConduct Financial modelling, Corporate Operational and Financial Analysis\nCollect real-time market information, help to conduct financial advisory to the management, including due diligence, valuation, deal structuring, transaction document negotiation & drafting and closing\nPrepare timely professional research reports / presentation materials upon market and industry movement on specific sectors and company focus\nWork with internal and external parties to optimize the operation flow\nPerform ad-hoc projects as required\n\nRequirement\n\nBachelor's Degree or above in Accounting, Finance or Law disciplines\nMinimum 2 years working experience and at least 1 year in asset management, PE\nExperience in investment banking, big 4\u00a0 is preferred\nStrong analysis, presentation(PPT) and modelling skills\nResult-oriented and willing to work under high pressure\nWith professional working attitude, willing to take on multiple functions\nExcellent command in spoken and written English and Chinese (including Putonghua)\n\nRemuneration and Benefits:\u00a0Salary will be commensurate with qualifications and experience. A competitive remuneration and benefits package, including annual leave, medical benefits, will be offered.", "employment_types": ["Full Time", "Permanent"], "selling_points": ["5 yrs' exp in business analysis (non-property)", "Financial analysis for business opportunities", "Operational analysis to investigate ongoing issue"], "locations": ["Wan Chai"], "categories": ["Accounting", "Financial Analyst", "Banking / Finance", "Analyst", "Professional Services", "Business Analysis / Data Analysis"], "post_time": "2022-01-14T09:17:27Z", "salary": {"currency": null, "max": null, "min": null, "period": null, "term": null}, "salary_visible": false, "title_keywords": ["business analyst", "assistant"], "responsibilities": ["due diligence", "management", "market information", "valuation", "internal and external parties", "financial analysis", "reports", "ad-hoc projects"], "requirements": {"degrees": ["degree or above", "bachelor"], "majors": ["finance", "accounting", "law"], "languages": ["putonghua", "english", "chinese"], "language_level": ["excellent"], "hard_skills": ["analysis", "pe"], "soft_skills": ["work under high pressure", "result-oriented"], "languages_combined": [{"language": "putonghua", "language_level": ["excellent"]}, {"language": "english", "language_level": ["excellent"]}, {"language": "chinese", "language_level": ["excellent"]}]}, "experience_required": {"duration": ["at least 1 year", "minimum 2 years"], "field": ["banking", "investment", "big 4", "asset management"]}}, {"job_id": "100003009052011", "location_code": "hk", "company": "Lucion International Financial Limited", "job_title": "Analyst/ Associate of PE Investment", "description": "Responsibilities:\n\nAssist in month-end closing work\nPrepare different kinds of business unit/project financial reports in a timely and accurate manner.\nConduct different kinds of analysis, such as but not limited to business case analysis, OPEX analysis, cost modeling, KPI monitoring, etc.\nPrepare presentations and visual aids to help illustrate data in appropriate ways\nEnsure accuracy of data within the reports and understand the content of supporting documentation, and proactively research issues that have a significant impact on financial results\nLiaise and coordinate with external auditors\nPerform ad-hoc tasks per request\n\nRequirements:\n\nBachelor Degree in Finance or Accounting or related discipline\n3-5 years experience in accounting and analysis functions\nKnowledge in tools or software like Power BI, Tableau, R, or other data & code manipulation methodologies for data analysis will be a big advantage.\nProficient in MS office application, especially in strong data applications, such as PowerPoint, Visio, Marco, function, etc.\u00a0\nExperience in handling SAP is a plus.\nAble to handle multi-tasks and meet tight deadlines\nMember of HKICPA/ACCA is a plus\nGood command of written and spoken English, Cantonese, and Mandarin\nImmediately available is an advantage\n\n\n\nWe offer attractive remuneration package and fringe benefits to the right candidates. Interested parties please submit your application to us. If you do not want to apply as JobsDB member, you may send your full resume with your availability, current and expected salaries to recruit01 at sf-express.com.\n\nYou are welcome to visit our website at\u00a0https://htm.sf-express.com/hk/tc/\u00a0for more information about us.\n\nCandidates who are not invited for interview within 1-month may consider their applications unsuccessful.\n\nAll personal data provided by job applicants will be used only for recruitment purpose and will be treated strictly confidential. Unsuccessful applications will be retained for a maximum period of 24-month.", "employment_types": ["Full Time", "Permanent"], "selling_points": ["CPA/ audit/ law", "big 4", "PE investment"], "locations": ["Central"], "categories": ["Accounting", "Financial Analyst", "Banking / Finance", "Equities / Capital Markets", "Asset Management"], "post_time": "2022-01-17T01:49:55Z", "salary": {"currency": null, "max": null, "min": null, "period": "monthly", "term": null}, "salary_visible": false, "title_keywords": ["analyst", "associate"], "responsibilities": ["liaise", "financial reports", "cost", "data", "analysis", "monitoring", "coordinate with", "ad-hoc tasks", "presentations", "opex", "month-end closing", "reports", "visual", "documentation", "external auditors"], "requirements": {"degrees": ["degree", "bachelor"], "majors": ["finance", "accounting"], "languages": ["cantonese", "english", "mandarin"], "language_level": ["good command"], "hard_skills": ["plus", "bi", "acca", "sap", "analysis", "code", "tableau", "powerpoint", "hkicpa", "marco", "r", "ms office"], "soft_skills": ["meet tight deadlines", "multi-tasks"], "languages_combined": [{"language": "cantonese", "language_level": ["good command"]}, {"language": "english", "language_level": ["good command"]}, {"language": "mandarin", "language_level": ["good command"]}]}, "experience_required": {"duration": ["3-5 years"], "field": ["accounting"]}}, {"job_id": "100003009043961", "location_code": "hk", "company": "S.F. Express (Hong Kong) Limited", "job_title": "Accountant (Financial Analyst)", "description": "Our client is a Global leading luxury brand. To cope with their business expansion, they are looking for a\u00a0Regional Assistant Financial Analyst to join the team.\n\nKey Responsibilities\n\nPrepare and consolidated Asia Sales monthly sales report with comparison against Budget and Forecast with comment\nWork closely with other functional team to ensure alignment and to reconcile any discrepancy\nPrepare other regular sales reporting or ad hoc analysis for management review of business performance\u00a0\nDevelop and replicate excel\u00a0budget/forecast\u00a0templates for\u00a0Asia\u00a0market\u00a0and\u00a0validation\u00a0\u00a0\nAssist\u00a0with the\u00a0budget & forecast\u00a0consolidation\u00a0(via excel platform)and review\u00a0process\nValidate system input and co-ordinate necessary follow-up with market\u00a0finance team\nAssist with analysis during budget and forecast process\nCost Management and Budget follow-up\n\nRequirements\n\nBachelor degree in Finance, Accounting or other related subject\n2 years relevant retail working experience\nAbility to extract, organise, analyse and report data\nGood communication skills\nGood command in English and Chinese\u00a0\n\nAll information provided will be treated in strict confidence and used solely for recruitment purposes. To apply, please quote current and expected salary and send your CV through \" APPLY NOW\"", "employment_types": ["Full Time", "Permanent"], "selling_points": ["Free shuttle bus coverage", "2 months or above performance bonus", "Attractive basic salary"], "locations": ["Tsing Yi"], "categories": ["Accounting", "Accountant", "Accounting Clerk / Supervisor", "Financial Analyst"], "post_time": "2022-01-13T02:36:40Z", "salary": {"currency": null, "max": null, "min": null, "period": "monthly", "term": null}, "salary_visible": false, "title_keywords": ["accountant", "financial analyst"], "responsibilities": ["reporting", "cost", "management", "ad hoc", "forecast process", "analysis", "budget", "review", "develop", "system input", "finance team", "forecast", "monthly sales report", "management review"], "requirements": {"degrees": ["degree", "bachelor"], "majors": ["finance", "accounting"], "languages": ["english", "chinese"], "language_level": ["good command"], "hard_skills": [], "soft_skills": ["communication skills", "confidence"], "languages_combined": [{"language": "english", "language_level": ["good command"]}, {"language": "chinese", "language_level": ["good command"]}]}, "experience_required": {"duration": ["2 years"], "field": ["retail"]}}, {"job_id": "100003009050155", "location_code": "hk", "company": "Magic Search Limited", "job_title": "Regional Assistant Financial Analyst (Luxury Brand)", "description": "Responsibilities:\n\n\nAssist Department Manager in corporate financial management and control in Company\u2019s financial activities\nConduct in-depth analysis and market research on peers / property market performance / tracking / benchmarking etc.\nProvide insights on funding forecast and budgetary control, perform variance analysis, review and monitor costs inherent that have dual accountability to both finance and business nature\nWork closely with other departments in the provision of management information and financial analysis management reporting package\nReview workflows and propose area of improvement / streamline\nParticipate ad hoc projects or presentations as assigned\nRequirements:\nBachelor degree or above in Accounting, Finance, Economics or other relevant disciplines\nWith at least 8 years' relevant experience in management accounting, market research or in similar position preferred\nCPA is preferred, but not a must\nExperience in listed company highly desired and exposure of property industry and advantage\nCreative & resourceful with good analytical mindset and communication skills\nExcellent command of English and Cantonese including Mandarin\nHighly proficient in MS office applications including Excel & PowerPoint\n\nWe offer ample opportunities for career development and attractive salary package commensurate with experience and qualifications. \u00a0Interested parties please apply with full resume via\u00a0\u201cAPPLY NOW\u201d.\u00a0\n\nFor further information on Wheelock Properties (Hong Kong) Limited, please visit our website:\u00a0www.wheelockpropertieshk.com.\n\nWe are an equal opportunities employer and invite applications from all qualified candidates. Personal data collected will be treated in strict confidence and handled by authorized persons for recruitment-related purposes only within The Wheelock & Wharf Group. Applicants not hearing from us within 2 months may consider their applications unsuccessful.\u00a0", "employment_types": ["Full Time", "Permanent"], "selling_points": ["2 years experience", "Luxury brand", "Regional explosure"], "locations": ["Not Specified"], "categories": ["Accounting", "Financial Analyst", "Financial Controller", "Banking / Finance", "Analyst"], "post_time": "2022-01-14T09:53:05Z", "salary": {"currency": null, "max": null, "min": null, "period": "monthly", "term": null}, "salary_visible": false, "title_keywords": ["assistant", "financial analyst"], "responsibilities": ["provide insights", "management", "control", "analysis", "review", "monitor", "market research", "presentations", "work closely with other departments", "financial analysis", "variance analysis", "ad hoc projects", "management reporting", "forecast", "costs", "tracking"], "requirements": {"degrees": ["degree or above", "bachelor"], "majors": ["finance", "accounting", "economics"], "languages": ["cantonese", "english", "mandarin"], "language_level": ["excellent"], "hard_skills": ["powerpoint", "cpa", "excel", "ms office"], "soft_skills": ["communication skills", "creative", "resourceful"], "languages_combined": [{"language": "cantonese", "language_level": ["excellent"]}, {"language": "english", "language_level": ["excellent"]}, {"language": "mandarin", "language_level": ["excellent"]}]}, "experience_required": {"duration": ["at least 8 years"], "field": ["management accounting", "relevant experience", "market research"]}}, {"job_id": "100003009046396", "location_code": "hk", "company": "Wheelock Properties (Hong Kong) Ltd", "job_title": "Business Analyst", "description": "Our client, HK listed company, is engaged in retailing and servicing business with rapid expansion plan across APAC region. Due to the continued expansion, they are looking for a strong caliber to join their finance team.\n\n\nResponsibilities\n\nReporting to the Board, the job holder is responsible for key finance functions\u00a0\nLead the Finance Department of 15 staffs\nManage annual audit processes\nPrepare periodic financial reports for fund investors and firm management\nManage and review the firm-wide budget and get involved in financial strategy planning and recommendation on firm performance\nPrepare routine management and regulatory reports to top management and regulators\nProvide advice to top management in relation to business finance with strategic\u00a0planning\nDelivering month/year-end reporting, budget & forecast analysis in order to\u00a0provide a better insight of business performance for Senior Management and\u00a0Board Committees\nProviding statutory reporting for the corporate entities including annual audit\u00a0process and liaising with external auditors\nOverseeing all tax related requirements for the corporate entities and liaise\u00a0with tax advisers\nEnhance productivity and ensure finance processes and documented procedures\u00a0are up-to-date\n\nRequirements\n\nCPA qualified with over 12 years of accounting and management experience\nRetail industry exposure is a must\nExperience in in-charge of company\u2019s overall financial reporting, management\u00a0reporting and treasury function\nPrior experience in M&A project will be an advantage\n\nIf you would like to apply for this role or find out more, please send your resume at info @ usgroupasia.com", "employment_types": ["Full Time", "Permanent"], "selling_points": [], "locations": ["Central"], "categories": ["Accounting", "Financial Analyst", "Financial Controller", "Banking / Finance", "Corporate Finance"], "post_time": "2022-01-13T18:55:19Z", "salary": {"currency": null, "max": null, "min": null, "period": null, "term": null}, "salary_visible": false, "title_keywords": ["business analyst"], "responsibilities": ["budget", "planning", "liaise with", "senior management", "liaising with", "reports", "forecast", "reporting", "management", "strategic planning", "annual audit", "review", "procedures", "fund investors", "tax", "year-end", "financial reports", "analysis", "provide advice", "external auditors"], "requirements": {"degrees": [], "majors": [], "languages": [], "language_level": [], "hard_skills": ["cpa"], "soft_skills": [], "languages_combined": []}, "experience_required": {"duration": ["12 years"], "field": ["management", "accounting", "financial"]}}, {"job_id": "100003009052239", "location_code": "hk", "company": "United Search Group (Asia) Limited", "job_title": "Chief Financial Officer-HK$150k-200k per month (HK listed retail company)", "description": "Key Responsibilities\n\nWork as business partners to support Brand Function to deliver their business goal; Ensure effective strategy implementation and monitoring performance\nExecute business performance analytics including implement modeling development and refinement to maximize customer retention and value, gather customer insights through data mining and analysis, identify up-sell & cross-sell opportunities to increase customer value\nWork closely with Brand Function to design customer journeys, conduct customer segmentation and best targeting tactics as well as effectiveness evaluation.\nProduce reporting analytics to enable identification of key trends or issues in the Business / Operating Unit that necessitate further analysis and discussion\nConnect with Headquarter Strategy Team on different aspect of the business e.g. analysis of internal financial information and external economic condition and its impact on business operations, future market outlook etc.\nSupport in Dashboards development including data modelling and design\nAny ad hoc activities arising\u00a0 \u00a0\n\nKey Stakeholders\n\nThis position\u2019s primary interfaces are (engagement, interaction, etc)\n\n\nLocal: Brand GM, Brand Marketing & Operation Team, Finance Operation Team, HR Team\nHQ: Strategy Team\n\nRequirements:\n\nDegree in Business, Statistics or Mathematics related field\n4-5 years working experience in business/data analysis or business intelligence preferably gained from Retail Industry\nStrong business acumen and analytical skillset\nEnjoy challenges and willing to push back & confront status quo when necessary\nExcellent communication, interpersonal & influencing skills\nAbility to work independently & effectively with all levels within an organization\nHigh proficient in SQL, MS Excel.\nExperience in statistical tool e.g. SPSS and BI tools e.g. Tableau is highly preferred.\u00a0 Knowledge in Salesforce Marketing Cloud will be a plus.\n\nCandidate with less experience will be considered as Business Analyst.\n\n\n\n\nWe offer opportunities for development in addition to a competitive remuneration and benefit package to the right candidate. Interested parties please click \"Apply Now\" for application.\n\nPersonal data provided by job applicants will be used strictly for recruitment purpose only.", "employment_types": ["Full Time", "Permanent"], "selling_points": ["Stable and autonomy working environment", "HK listed company in retail industry", "M&A experience and Energetic environment"], "locations": ["Wan Chai Area"], "categories": ["Accounting", "Chief Accountant", "Financial Analyst", "Financial Controller"], "post_time": "2022-01-17T02:31:50Z", "salary": {"currency": null, "max": null, "min": null, "period": "monthly", "term": null}, "salary_visible": false, "title_keywords": ["chief financial officer"], "responsibilities": ["reporting", "ad hoc", "data", "operations", "analysis", "monitoring", "customer insights", "implementation", "design", "hr", "evaluation", "data mining"], "requirements": {"degrees": ["degree"], "majors": ["mathematics", "business", "statistics"], "languages": [], "language_level": [], "hard_skills": ["plus", "bi", "salesforce", "analysis", "tableau", "sql", "ms excel", "business intelligence", "acumen"], "soft_skills": ["business acumen", "work independently", "interpersonal", "communication"], "languages_combined": []}, "experience_required": {"duration": ["4-5 years"], "field": ["data analysis", "business", "retail industry"]}}, {"job_id": "100003009054074", "location_code": "hk", "company": "Tianda Financial Limited", "job_title": "Finance Manager/ AM (SFC Type 1,4,9)", "description": "Responsibilities\uff1a\n\nHandle the accounting entries of the company and its subsidiaries and to develop and improve the accounting, financial, auditing and internal control management systems of the Company;\nSubmit FRR and annual audited financial statements to SFC;\nPrepare and monitor enforcement of annual budget,\u00a0monthly financial statements and consolidation financial statements;\nPrepare financial analysis, internal management reports and all financial analysis reports;\nHandle tax issues, accounts receivables and payables, client fund deposit and withdrawal, and annual auditing;\nResponsible for fund management, monitor liquid capital position;\nAssist with Investment services department to jointly monitor the credit status of margin clients.\nLiaise with tax authority, auditors, banks and SFC on finance related matters.\n\nRequirements:\n\nBachelor\u2019s Degree or above in accounting and finance, qualified accountant or members;\n3-4 years accounting and finance relevant experiences in investment banks or securities brokerage firms, familiar with accounting rules and regulations of securities business, familiar with accounting systems and back office system;\nHave a high level of responsibility and good communication\u00a0and coordination skills, strong sense of moral values, pay attention to details, have a good team spirit and professional attitude.\nWe offer 5-day work week and competitive remuneration package to qualified candidates. Interested parties please click \"Apply Now\" and submit your resume with current and expected salary .Please visit our company\u2019s website:\u00a0https://www.tiandafinancial.com\u00a0to know more about us.\n\nAll information provided by applicants will be treated in strict confidence and used for recruitment purpose only.\u00a0", "employment_types": ["Full Time", "Permanent"], "selling_points": [], "locations": ["Admiralty"], "categories": ["Accounting", "Finance / Accounting Manager", "Financial Analyst", "Banking / Finance", "Financial Services"], "post_time": "2022-01-17T08:19:00Z", "salary": {"currency": null, "max": null, "min": null, "period": "monthly", "term": null}, "salary_visible": false, "title_keywords": ["finance manager"], "responsibilities": ["tax", "management", "systems", "monitor", "budget", "financial statements", "develop", "monthly financial statements", "financial analysis", "management reports", "financial analysis reports", "liaise with", "auditing", "internal control"], "requirements": {"degrees": ["degree or above", "bachelor"], "majors": ["finance", "accounting"], "languages": [], "language_level": [], "hard_skills": ["accounting systems"], "soft_skills": ["team spirit", "coordination skills", "moral", "communication", "attention to details"], "languages_combined": []}, "experience_required": {"duration": ["3-4 years"], "field": ["securities brokerage", "investment banks", "finance", "business", "securities", "accounting"]}}, {"job_id": "100003009054019", "location_code": "hk", "company": "K. Wah International Holdings Ltd", "job_title": "AGM - Finance", "description": "Job Responsibilities\n\nHandle IR activities such as results announcements, investor briefings and meetings, roadshows, site visits, and conferences\nAssist in the preparation of annual reports, interim reports, and other relevant reports\nPrepare corporate presentations, Q&As, press releases for IR purposes\nMaintain good relationships with shareholders, analysts, commentators, columnists, and financial media\nDisseminate to the investment community of relevant information to generate publicity and coverage for the Company\nIdentify and follow up on any appropriate awards for best IR practices to enhance the Company\u2019s exposure in the investment community\nMonitor the economic situation, governments\u2019 fiscal and monetary policies, and conduct research and analysis on property market (Hong Kong and Mainland China)\nAssist in business development by participating in financial modeling and seeking potential investors\nSupport any ad hoc projects\n\n\u00a0Job Requirements\n\nDegree holder or above in Business Administration, Finance, Economics or related discipline\nA minimum of 10 years of work experience in listed companies or financial institutions\nSolid accounting background, with CFA qualification\nExcellent presentation, communication, and interpersonal skills with strong analytical skills and business sense\nKnowledgeable with regards to the financial and economic landscape of both Hong Kong and Mainland China\nExcellent command of written and spoken English and Chinese including Putonghua\nWell versed in computer applications especially in Excel and PowerPoint\n\nInterested parties please send resume with salary expectation and availability to\u00a0Human Resources Department, K. Wah International Holdings Limited, 29/F, K. Wah Centre, 191 Java Rd., North Point, H.K.\u00a0or by clicking\u00a0Apply Now\u00a0.\n\nAll Personal data collected will be used for recruitment purpose only. All applications will be retained for a maximum period of 2 years and may be considered for other suitable positions within the Group.", "employment_types": ["Full Time", "Permanent"], "selling_points": ["Investor Relations focus", "Qualified CFA", "Solid Accounting background"], "locations": ["North Point"], "categories": ["Accounting", "Finance / Accounting Manager", "Financial Analyst", "Banking / Finance", "Investment"], "post_time": "2022-01-17T08:07:18Z", "salary": {"currency": null, "max": null, "min": null, "period": "monthly", "term": null}, "salary_visible": false, "title_keywords": [], "responsibilities": ["relevant reports", "policies", "analysis", "financial modeling", "monitor", "presentations", "conferences", "maintain", "reports", "ad hoc projects", "conduct research"], "requirements": {"degrees": ["degree holder"], "majors": ["finance", "economics", "business administration"], "languages": ["putonghua", "english", "chinese"], "language_level": ["excellent"], "hard_skills": ["powerpoint", "cfa", "excel", "analytical skills"], "soft_skills": ["business sense", "analytical skills", "communication", "interpersonal skills", "presentation"], "languages_combined": [{"language": "putonghua", "language_level": ["excellent"]}, {"language": "english", "language_level": ["excellent"]}, {"language": "chinese", "language_level": ["excellent"]}]}, "experience_required": {"duration": ["minimum of 10 years"], "field": ["financial institutions"]}}, {"job_id": "100003009050735", "location_code": "hk", "company": "Hutchison Telecommunications (Hong Kong) Limited", "job_title": "Business Analyst - Investor Affairs", "description": "Responsibilities:\n\n\nCoordinate & prepare Interim/ Annual announcements & reports, Sustainability Committee Board papers & report\nCoordinate annual general meetings and webcast\nMonitor analyst coverage & market news, update consensus estimates, market views as well as industry and competitive analysis\nPrepare presentations and relevant written materials\nMaintain corporate website\nCollect, analyse & manage ESG data & KPIs from internal stakeholders and prepare regular sustainability reports/ presentations\nFormulate & maintain ESG policies & handle ESG-related matters\nConduct regular meetings, training, workshops & other activities with stakeholders on sustainability-related issues\n\nRequirements:\n\nUniversity graduate in Accounting, Finance, or related discipline\nThree or more years of working experience\nSelf-starter, project management skills, flexible in approach and methodology, and the ability to show initiatives and meet deadlines\nExcellent command in both written and spoken English and Chinese\nCandidates with less working experience will be considered as Assistant Business Analyst\n\nApart from competitive remuneration package and exciting opportunity for career development within the Group, we provide attractive employee benefits such as free company shuttle, free company SIM card and preferential SIM plan offers, comprehensive medical & insurance schemes, as well as full range of other employee well-being provisions.\n\nInterested parties, please apply with full resume, present and expected salary, by clicking \u201cAPPLY NOW\u201d. Please quote the reference number on the e-mail subject.\n\nWe are an equal opportunity employer and welcome applications from all qualified candidates. Personal data collected will be treated in the strictest confidence and handled confidentially by authorised personnel for recruitment-related purposes only within the CK Hutchison Group of companies. The personal data of unsuccessful applicants will be destroyed after the recruitment exercise pursuant to the requirements of the Personal Data (Privacy) Ordinance in Hong Kong.", "employment_types": ["Full Time", "Permanent"], "selling_points": [], "locations": ["Tsing Yi"], "categories": ["Accounting", "Financial Analyst", "Banking / Finance", "Corporate Finance", "Others"], "post_time": "2022-01-14T11:15:00Z", "salary": {"currency": null, "max": null, "min": null, "period": "monthly", "term": null}, "salary_visible": false, "title_keywords": ["business analyst"], "responsibilities": ["data", "policies", "analysis", "monitor", "website", "presentations", "coordinate", "maintain", "reports", "analyse", "kpis", "report"], "requirements": {"degrees": ["university graduate"], "majors": ["finance", "accounting"], "languages": ["english", "chinese"], "language_level": ["excellent"], "hard_skills": ["project management"], "soft_skills": ["flexible", "project management skills", "meet deadlines", "comprehensive"], "languages_combined": [{"language": "english", "language_level": ["excellent"]}, {"language": "chinese", "language_level": ["excellent"]}]}, "experience_required": {"duration": [], "field": ["business"]}}, {"job_id": "100003009054564", "location_code": "hk", "company": "Foodgears Industrial International Limited", "job_title": "Management Accounting Manager", "description": "Responsibilities:\n\nDrive the financial planning of the company by analyzing its performance and risks\nSet targets for and supervise all accounting and finance personnel (management accountants, internal auditors etc.)\nOversee all audit and internal control operations\nPrepare timely and detailed reports on financial performance on a quarterly and annual basis\nConduct analysis to make forecasts and report to upper executives\nEnsure adherence to financial laws and guidelines\n\n\u00a0\nRequirements:\n\nProven experience as director of finance or similar role\nIn-depth knowledge of corporate finance and accounting principles, laws and best practices\nSolid knowledge of financial analysis and forecasting\nProficient in the use of MS Office and financial management software\nAn analytical mind with a strategic ability\nExcellent organizational and leadership skills\nOutstanding communication and interpersonal abilities\nCPA or other relevant qualification and China Accounting experience is a plus\n\n\n\nWe offer attractive remuneration package to the right candidate.\u00a0 Interested parties please send full resume with present & expected salary and available date by clicking \"Apply Now\".\n\n\nAll Personal data collected will be used for recruitment purposes only.\n", "employment_types": ["Permanent"], "selling_points": [], "locations": ["Wong Tai Sin Area"], "categories": ["Accounting", "Finance / Accounting Manager", "Financial Analyst", "Financial Controller"], "post_time": "2022-01-17T10:00:39Z", "salary": {"currency": null, "max": null, "min": null, "period": "monthly", "term": null}, "salary_visible": false, "title_keywords": ["accounting manager"], "responsibilities": ["management", "guidelines", "operations", "analysis", "ensure adherence", "audit", "planning", "reports", "report", "internal control"], "requirements": {"degrees": [], "majors": [], "languages": [], "language_level": [], "hard_skills": ["financial analysis", "cpa", "plus", "ms office"], "soft_skills": ["organizational", "leadership skills", "communication", "analytical mind", "interpersonal"], "languages_combined": []}, "experience_required": {"duration": [], "field": ["finance", "accounting experience"]}}, {"job_id": "100003009054058", "location_code": "hk", "company": "Renesas Electronics Hong Kong Limited", "job_title": "Senior Specialist", "description": "\u00a0Responsibilities:\n\nReview and consolidate month-end finance closing reports from region\nHandle monthly management reports including expense monitoring & cash flow forecast, etc.\nResponsible for regional expense budget and forecast report\nLiaise and work closely with regional counterparts on all reporting and planning matters\nMonitor and maintain company\u2019s internal control and process\nCheck AP Non-Trade purchase request, staff trip report, etc.\n\n\u00a0Requirements:\n\nDegree in Accounting / Finance or equivalent\nMin. 3 years relevant experience in financial planning\nKnowledge of SAP & Power BI is an advantage\nGood command of spoken and written English, Mandarin and Cantonese\nProficiency in MS Office, include MS Word and Excel.\nIndependent, strong personal motivation and well disciplines.", "employment_types": ["Full Time", "Permanent"], "selling_points": ["Data consolidation, Financial analysis & reporting", "High Excel analytical ability", "Flexible working hours/ 5-day work week"], "locations": ["Kowloon Bay"], "categories": ["Accounting", "Accountant", "Accounting Clerk / Supervisor", "Financial Analyst"], "post_time": "2022-01-17T08:15:35Z", "salary": {"currency": null, "max": null, "min": null, "period": "monthly", "term": null}, "salary_visible": false, "title_keywords": ["senior specialist"], "responsibilities": ["liaise", "reporting", "ap", "review", "monitoring", "month-end", "budget", "monitor", "management reports", "cash flow", "reports", "planning", "forecast", "maintain", "purchase", "internal control", "report"], "requirements": {"degrees": ["degree"], "majors": ["finance", "accounting"], "languages": ["cantonese", "english", "mandarin"], "language_level": ["good command"], "hard_skills": ["excel", "bi", "sap", "ms office", "ms word"], "soft_skills": ["independent"], "languages_combined": [{"language": "cantonese", "language_level": ["good command"]}, {"language": "english", "language_level": ["good command"]}, {"language": "mandarin", "language_level": ["good command"]}]}, "experience_required": {"duration": ["3 years"], "field": ["planning", "relevant experience", "financial"]}}, {"job_id": "100003009044909", "location_code": "hk", "company": "Bread Elements", "job_title": "Financial Analyst - Cost Controller", "description": "Job Highlights\n\nCover the Cost Control & report to Group Finance Director\n2 Business Units: Central Kitchen & Retail, 150 employees, fast expansion \u00a0\u00a0\nPrepare regular management reporting and PnL variance analysis\nProvide insightful recommendations on businesses to the top management\nMonitor budget and forecast for strategic and operational decisions\nSetting KPIs and conducting financial analysis for each business units & liaise with the related team\n\nResponsibilities:\n\nPrepare regular reports (incl. weekly/monthly cost control report & PnL report)\nCalculate weekly F&B internal transfer between legal entities\nPrepare for recipe costing of menu items and assist on the costing audits (retail and factory sides: control real/theoretical consumption)\nPerform forecasting & analysis, budgetary control, cash flow management, tax reporting & ops review\nReview management accounts & assist to prepare reports for top management\nCoordinate with different departments in preparation of the annual budget and forecast \u2013 direct responsibility for overall accountability for delivering consolidated budget/forecast, covering the P&L, cash flow and balance sheet\u00a0\nMonitor cash position, cash flow forecast and banking facilities for investment projects\nMonthly financial close including analytical review of balance sheet, P&L accounts for the business\nTake initiatives on driving changes and system development\nMonitor ongoing performance of the business and find ways to reduce risks\nAct as a key business partner with the senior management in offering strategic and financial insights and recommendations for business management and decision\n\nRequirements:\u00a0\n\nMin. 3 years work experience in Cost Control\nDegree or above in Accounting or Finance or related discipline\nExperience in Big4 is a plus\nStrong analysis & leadership skills\nSolid experience in group level consolidation and financial reporting\nGood command in both English & Cantonese\nProficient in PC skills, such as MS applications, ERP systems, Business Intelligence software (Tableau)\nGood interpersonal and communication skills\nSelf-motivated, curious, analytic, pinpoint, accurate, capable to work under pressure and meet deadline\nImmediately available is highly preferred\n\nBenefits:\u00a0\n\nMedical & Dental Insurance\nStaff discount on ALL Bakehouse shops & products\nGreat working environment with trendy Pantry\nFamily-Friendly Good Employer Certification\n\nWe offer great working environment, attractive salary and benefits package to the right candidate. Interested applicants please send us your resume with availability and expected salary.\n\nWe are an equal opportunity employer. Personal data collected will be treated in strictly confidential and for recruitment purpose only.", "employment_types": ["Full Time", "Permanent"], "selling_points": ["Finance, Cost Control, Reporting, Analysis", "Management Reporting & PnL", "Setting KPIs, Strategy & Recommendations"], "locations": ["Chai Wan"], "categories": ["Accounting", "Financial Analyst", "Financial Controller", "Others"], "post_time": "2022-01-13T06:40:13Z", "salary": {"currency": null, "max": null, "min": null, "period": "monthly", "term": null}, "salary_visible": false, "title_keywords": ["financial analyst"], "responsibilities": ["budget", "senior management", "control", "monitor", "p&l", "reports", "forecast", "banking", "forecasting", "balance sheet", "report", "reporting", "management", "review", "coordinate with", "cash flow", "audits", "tax", "analysis", "cost control", "prepare reports"], "requirements": {"degrees": ["degree or above"], "majors": ["finance", "accounting"], "languages": ["cantonese", "english"], "language_level": ["good command"], "hard_skills": ["erp systems", "plus", "ms applications", "analysis", "tableau", "pc skills", "business intelligence"], "soft_skills": ["communication skills", "self-motivated", "capable", "leadership skills", "accurate", "interpersonal", "work under pressure"], "languages_combined": [{"language": "cantonese", "language_level": ["good command"]}, {"language": "english", "language_level": ["good command"]}]}, "experience_required": {"duration": ["3 years"], "field": ["consolidation", "financial"]}}, {"job_id": "100003009051810", "location_code": "hk", "company": "Panasonic Hong Kong Co., Limited", "job_title": "Senior Accountant (Japanese speaking)", "description": "Responsibilities:\n\nReview, formulate and implement financial and accounting policies, procedures and guidelines\u00a0\nIdentify areas for continuous improvement to eliminate risk and enhance internal control of operational activities and governance\nHandle tax issue, mainly for in-charging of BEPS, and communicate with related parties for planning and resolving\nHandle aggregation/ analysis and information sharing of whole entity and HK regional consolidated financial status\nConduct regular review of end-to-end processes\nProvide effective support to senior for resolving any task assigned\nHandle other ad-hoc duties as assigned\n\n\nRequirements:\n\nBachelor degree in Accounting or related discipline\n5 years or above relevant experience in accounting, tax and internal control\nGood command of spoken & written in English, Cantonese, Mandarin and Japanese\nProficiency in MS office applications, familiar with using accounting system is an advantage\nAble to work independently, good analytical and problem solving skills\nGood team player with strong interpersonal and communication skills\nResponsible, detail-oriented and proactive\nCandidate with more experience will be considered as Manager\n\nRemuneration will be commensurate with qualification and experience. Interested parties, please send your application with detailed resume indicating both existing & expected salary and date of availability to us.\n\nWe are an equal opportunity employer. All information provided by applicants will be treated in strict confidence and used for recruitment purpose only.", "employment_types": ["Full Time", "Permanent"], "selling_points": ["Bachelor degree in finance or accounting field", "5 yrs relevant exp. in AC, Tax & internal control", "Stable MNC in-house environment"], "locations": ["Tsim Sha Tsui"], "categories": ["Accounting", "Accounting Clerk / Supervisor", "Audit", "Financial Analyst"], "post_time": "2022-01-17T04:16:30Z", "salary": {"currency": null, "max": null, "min": null, "period": "monthly", "term": null}, "salary_visible": false, "title_keywords": ["senior accountant"], "responsibilities": ["tax", "communicate with", "guidelines", "analysis", "review", "procedures", "regular review", "accounting policies", "planning", "ad-hoc duties", "internal control"], "requirements": {"degrees": ["degree", "bachelor"], "majors": ["accounting"], "languages": ["cantonese", "japanese", "english", "mandarin"], "language_level": ["good command"], "hard_skills": ["problem solving skills", "ms office", "accounting system", "internal control"], "soft_skills": ["communication skills", "work independently", "good team player", "responsible", "detail-oriented", "analytical and problem solving skills", "proactive", "interpersonal"], "languages_combined": [{"language": "cantonese", "language_level": ["good command"]}, {"language": "japanese", "language_level": ["good command"]}, {"language": "english", "language_level": ["good command"]}, {"language": "mandarin", "language_level": ["good command"]}]}, "experience_required": {"duration": ["5 years"], "field": ["accounting", "relevant experience"]}}, {"job_id": "100003009053709", "location_code": "hk", "company": "Biel Crystal (HK) Manufactory Limited", "job_title": "Senior Accounting Clerk  -   Kwun Tong near MTR Station", "description": "We are the leading smart phone cover glass supplier in the world. \u00a0Our customers include all the well-known smart phone brands.\u00a0 Due to business needs, we are looking for talents to join our Finance team in Hong Kong.\n\n\u00a0Responsibilities:\n\nAssist in daily accounting duties including but not limited to data input, filing, preparing accounting journal entries, bank reconciliations, etc.\nPrepare monthly financial statements for overseas branch, schedules and analysis\nLiaise with China and overseas colleagues in monthly inter-company transactions reconciliation\nProcess data input in system and perform testing when implementation of new functions in system\nAssist in all ad-hoc assignments\n\nRequirements:\n\nReasonable level of accounting knowledge\n2 years accounting experience is preferred\nStrong communication and interpersonal skills to interact with people at different levels\nAble to work in a fast pace working environment\nProficient in MS Office (Word, Excel), Chinese Word processing\nGood command of both written and spoken English\nAbility to speak Chinese Putonghua is necessary\nRecent university graduate in business will also be considered\nImmediately available is preferred\n\nWork location is in Kwun Tong near MTR Station.\u00a0 We offer good career prospects with an attractive salary remuneration including double-pay,\u00a0discretionary bonus and\u00a0medical insurance\u00a0to the right candidate. \u00a0\n\n(Applicants not contacted within six weeks should consider their application unsuccessful. \u00a0Personal data provided by applicants will be strictly used for recruitment purpose only.)", "employment_types": ["Full Time", "Permanent"], "selling_points": [], "locations": ["Kwun Tong"], "categories": ["Accounting", "Accounting Clerk / Supervisor", "Financial Analyst"], "post_time": "2022-01-17T07:23:17Z", "salary": {"currency": null, "max": null, "min": null, "period": "monthly", "term": null}, "salary_visible": false, "title_keywords": ["accounting clerk"], "responsibilities": ["schedules", "ad-hoc assignments", "analysis", "data input", "bank reconciliations", "transactions", "testing", "implementation", "prepare monthly financial statements", "journal entries", "liaise with", "daily accounting"], "requirements": {"degrees": ["university graduate"], "majors": ["business"], "languages": ["putonghua", "english", "chinese"], "language_level": ["good command", "proficient"], "hard_skills": ["excel", "chinese word processing", "word", "ms office"], "soft_skills": ["communication and interpersonal skills"], "languages_combined": [{"language": "putonghua", "language_level": []}, {"language": "english", "language_level": ["good command"]}, {"language": "chinese", "language_level": ["proficient"]}]}, "experience_required": {"duration": ["2 years"], "field": ["accounting experience"]}}, {"job_id": "100003009054827", "location_code": "hk", "company": "The English Schools Foundation", "job_title": "HR and Finance Assistant - Quarry Bay School", "description": "Quarry Bay School is now looking for a HR & Fiance Assistant to join the team.\nResponsibilities:\n\nThe HR & Finance Assistant assists in HR & Accounting tasks under the supervision of the HR & Finance Officer.\nUndertake accounts payable functions\nUndertake petty cash records\nAssist with procurement and related matters\nAssist with Freelance Service Provider agreement process\nAssist with Fixed Asset records and perform annual count\nOther assigned HR and Finance related tasks\nPerform other duties as directed by the HR & Finance Officer/Principal\nCompetencies required:\nGood command of written and spoken English and Chinese\nProficient with MS Excel and Word\nReliability and detail-oriented\nRequirements\nBasic accounting knowledge\nRelevant experience\nApplicants must be a permanent Hong Kong resident or possess a valid visa to work in Hong Kong.\nClosing Date:\u00a016th January 2022\nFor enquiries, please contact Doris Wong at +852 25664242 via \"Apply Now\".\nApplications will be reviewed on a rolling basis and offers may be extended prior to the job closing date.\nBy applying for this position, your application may be considered for other opportunities within ESF.\nESF is an Equal Opportunities Employer\nPersonal data provided by job applicants will be used strictly in accordance with the ESF's Personal Data Policy, a copy of which will be provided upon request.\nAligned with the recommendations of the International Task Force on Child Protection, we hold ourselves to a high standard of effective recruiting practices with specific attention to child protection.\nsupportstaff\nsupportstaffhki", "employment_types": ["Full Time", "Permanent"], "selling_points": ["Undertake accounts payable functions", "Assist with procurement and related matters", "Basic accounting knowledge"], "locations": ["Not Specified"], "categories": ["Accounting", "Accounting Clerk / Supervisor", "Financial Analyst", "Admin & HR", "HR Supporting Staff"], "post_time": "2022-01-17T11:26:30Z", "salary": {"currency": null, "max": null, "min": null, "period": "monthly", "term": null}, "salary_visible": false, "title_keywords": ["hr", "finance assistant"], "responsibilities": ["hr", "perform other duties", "accounts payable"], "requirements": {"degrees": [], "majors": [], "languages": [], "language_level": [], "hard_skills": ["basic"], "soft_skills": [], "languages_combined": []}, "experience_required": {"duration": [], "field": ["relevant experience"]}}, {"job_id": "100003009054024", "location_code": "hk", "company": "CanAsia Consulting Group Hong Kong Co., Limited", "job_title": "Accountant / Senior / Manager (Big-4 audit preferred, match existing salary)", "description": "Working Location: Chek Lap Kok\n\nReporting to the Senior Manager, Accounting & Controlling, Aviation, Asia Pacific, this is a regional role responsible for optimizing cash flow, generating accurate and fair monthly aviation cost and revenue reports as well as produce trend analyses for Asia Pacific region as and when required.\n\nFinancial Accounting\n\nVerifying all invoices against contracts, closely communicate with vendors / suppliers on invoicing issues\nHandling and monitoring timely AP payments\nPreparing payment journals in SUN system\nPreparing monthly journals for dedicated air costs, accruing for incurred costs not invoiced accurately and timely\n\nFinancial Analysis and Reporting\n\nPreparing monthly reports and analyses on Air Capacity Sales revenue and kilos\nAnalyzing month to month variance on dedicated air costs\nProvide route cost performance analysis on AP network flights\nAd hoc trend analyses when required\n\nBudgeting and Forecasting\n\nSupporting budget planning and forecasting mainly on dedicated air costs\nAssisting the team to submit budget to Global Finance on time\n\nCompliance\n\nAssist the Senior Manager in monitoring internal control procedure in accordance with Company compliance policy\n\nAd-hoc Analytical Support (for Network Planning and Commercial)\n\nProvide analytical support to assist business decisions\n\nRequirements\n\nDegree in Finance/Accounting or related discipline\n1 to 3 years of work experience in accounting\nWork experience in Aviation industry or Express / Logistics industry will be an advantage\nStudent member / Qualified member of HKICPA or equivalent would be a plus\nGood knowledge of accounting standards\nGood communication skills in both English and Chinese (Cantonese and Mandarin)\nProficient in using MS Excel and PowerPoint\nBe independent, detailed and efficient\nAble to work under pressure and meet all deadlines assigned\nApplication:\nClick \"Apply Now\" or apply on line via the following link: https://dhlexpress.taleo.net/careersection/ex/jobdetail.ftl?job=210091Z&iniurl.src=CWS-10001&tz=GMT%2B08%3A00&tzname=Asia%2FShanghai\nPersonal Information Collection Statement pertaining to Recruitment\nDHL Express (Hong Kong) Limited / DHL Aviation (Hong Kong) Limited (\u201cDHL\u201d) is committed to protecting and respecting your privacy in accordance with the Personal Data (Privacy) Ordinance of Hong Kong (the \u201cOrdinance\u201d) and DHL\u2019s Personal Data Protection Policy (the \u201cPolicy\u201d) at https://www.dhl.com/hk-en/home/footer/local-privacy-notice.html\nBy proceeding to respond to this recruitment advertisement, you consent that we may use, retain, process, transfer or otherwise handle the personal data that we collect from you for recruitment,\u00a0 application processing, assessment and communication purposes (including any other purposes directly related thereto) in accordance with the Policy.\nAll personal data of unsuccessful applicants will be retained for future recruitment purposes for a period of not more than two (2) years after which such data will be destroyed.\nYou have the right at any time to make a data access or correction request concerning your personal data held by us. In addition, you may request us to delete your personal data that is no longer required for the relevant purposes which you have given consent. Should you wish to exercise such rights or have any question in relation to your personal data or the Policy, please contact our Human Resources Division in writing\u00a0", "employment_types": ["Full Time"], "selling_points": ["Fast learner, room for progress and growth", "Big-4 / Mid-tier audit background preferred", "Fresh grads are welcome"], "locations": ["Shatin Area"], "categories": ["Accounting", "Accountant", "Financial Analyst", "Professional Services", "Business Consultancy"], "post_time": "2022-01-17T08:07:21Z", "salary": {"currency": null, "max": null, "min": null, "period": "monthly", "term": null}, "salary_visible": false, "title_keywords": ["accountant", "manager"], "responsibilities": ["ad-hoc", "monthly reports", "data", "budgeting", "budget", "communication", "payment", "personal data", "costs", "internal control", "ap", "work under pressure", "budget planning", "ad hoc", "invoices", "contracts", "compliance", "reports", "logistics", "forecasting", "reporting", "cost", "monitoring", "cash flow", "contact", "communicate with", "analysis", "invoicing", "financial analysis", "payments", "recruitment", "planning"], "requirements": {"degrees": ["degree"], "majors": ["finance", "accounting"], "languages": ["cantonese", "english", "chinese", "mandarin"], "language_level": ["good"], "hard_skills": ["ap", "plus", "no", "analysis", "powerpoint", "html", "financial analysis", "make", "ms excel", "processing", "internal control", "hkicpa"], "soft_skills": ["efficient", "communication skills", "independent", "responsible", "work under pressure", "timely", "communication", "committed", "accurate", "detailed"], "languages_combined": [{"language": "cantonese", "language_level": ["good"]}, {"language": "english", "language_level": ["good"]}, {"language": "chinese", "language_level": ["good"]}, {"language": "mandarin", "language_level": ["good"]}]}, "experience_required": {"duration": ["1 to 3 years"], "field": ["logistics industry", "accounting"]}}, {"job_id": "100003009044521", "location_code": "hk", "company": "r-pac Hong Kong Ltd", "job_title": "Financial Analyst", "description": "Job Responsibilities:\n\n\u00a0\u00a0\u00a0\u00a0\u00a0\u00a0\u00a0\u00a0 Participate in month end closing and conduct timely financial analysis\n\u00a0\u00a0\u00a0\u00a0\u00a0\u00a0\u00a0\u00a0 Preparation of presentation material for monthly operation review\n\u00a0\u00a0\u00a0\u00a0\u00a0\u00a0\u00a0\u00a0 Work collaboratively with various parties to collect and summarize information\n\u00a0\u00a0\u00a0\u00a0\u00a0\u00a0\u00a0\u00a0 Assist in preparation of annual budget and periodic forecasts\n\u00a0\u00a0\u00a0\u00a0\u00a0\u00a0\u00a0\u00a0 Other ad hoc tasks as assigned\n\n\u00a0Job Requirements:\n\n\u00a0\u00a0\u00a0\u00a0\u00a0\u00a0\u00a0\u00a0 Bachelor\u2019s Degree in Finance, Accounting or other related discipline\n\u00a0\u00a0\u00a0\u00a0\u00a0\u00a0\u00a0\u00a0 Student member of HKICPA or other related professional bodies\n\u00a0\u00a0\u00a0\u00a0\u00a0\u00a0\u00a0\u00a0 3-7 years relevant work experience\n\u00a0\u00a0\u00a0\u00a0\u00a0\u00a0\u00a0\u00a0 High Excel analytical ability and hands on skill set is essential\n\u00a0\u00a0\u00a0\u00a0\u00a0\u00a0\u00a0\u00a0 Understanding of financial statements and high degree of business acumen\n\u00a0\u00a0\u00a0\u00a0\u00a0\u00a0\u00a0\u00a0 Proficiency in the use of Microsoft Office Suite: Excel, PPT, Access\n\u00a0\u00a0\u00a0\u00a0\u00a0\u00a0\u00a0\u00a0 Good command of written and spoken English, Mandarin & Cantonese\n\u00a0\u00a0\u00a0\u00a0\u00a0\u00a0\u00a0\u00a0 Good communication, interpersonal & presentation skills\n\u00a0\u00a0\u00a0\u00a0\u00a0\u00a0\u00a0\u00a0 Knowledge of Flex system, SAP & ERP\n\u00a0\u00a0\u00a0\u00a0\u00a0\u00a0\u00a0\u00a0 Familiarity with PRC accounting standards and taxation regulations will be an advantage\n\u00a0\u00a0\u00a0\u00a0\u00a0\u00a0\u00a0\u00a0 Able to work under pressure and might tight deadlines\n\nWe offer excellent career development opportunities with a highly competitive salary supported by a benefits program including 5-days work, medical, MPF and discretionary bonus. Interested parties please click \"APPLY NOW\" for application information.\u00a0\n\n\u00a0**All information submitted will be treated as confidential and used **", "employment_types": ["Full Time"], "selling_points": ["Familiar in financial analysis", "Student member of HKICPA", "3-7 years relevant experiences"], "locations": ["Kwai Hing"], "categories": ["Accounting", "Financial Analyst"], "post_time": "2022-01-13T04:26:45Z", "salary": {"currency": null, "max": null, "min": null, "period": "monthly", "term": null}, "salary_visible": false, "title_keywords": ["financial analyst"], "responsibilities": ["month end closing", "review", "budget", "ad hoc tasks", "financial analysis"], "requirements": {"degrees": ["degree", "bachelor"], "majors": ["business", "finance", "accounting"], "languages": ["cantonese", "english", "mandarin"], "language_level": ["good command"], "hard_skills": ["excel", "sap", "erp", "microsoft office suite", "hkicpa", "flex system", "prc accounting", "acumen"], "soft_skills": ["communication", "presentation skills", "hands on", "business acumen", "interpersonal", "work under pressure"], "languages_combined": [{"language": "cantonese", "language_level": ["good command"]}, {"language": "english", "language_level": ["good command"]}, {"language": "mandarin", "language_level": ["good command"]}]}, "experience_required": {"duration": ["3-7 years"], "field": []}}, {"job_id": "100003009052924", "location_code": "hk", "company": "Brink's Asia Pacific Limited", "job_title": "Finance Analyst", "description": "Responsibilities:\n\nPrepare different types of financial reports such as budget, cash flow forecasts, business modeling, financial projections etc.\u00a0\u00a0\nPerform financial analysis of various data and being able to discern areas of importance.\nAssist in business development with emphasis on data collection, data comparison, budget preparation and financial analysis.\nAssist the supervisor on any ad-hoc assignments\n\nRequirements:\n\nDegree holder in finance/accounting with professional qualifications.\u00a0\u00a0\nMinimum 6 years of work experience, with a major focus on financial planning & analysis.\u00a0\u00a0\nExposure in Big 4 is preferred.\u00a0\u00a0\nWith comprehensive knowledge of IFRS and other regulatory requirements.\nExperience with Business Object and Hyperion financial management tool is an added advantage\nGood interpersonal skills and ability to clearly communicate with others.\u00a0\nHigh level of motivation, able to meet tight timelines, work independently and under pressure.\nInitiative with good analytical and communication skills.\nGood computer literacy in particular advanced skills in using Excel and PowerPoint.\n\nWe offer attractive remuneration package fringe benefits including\u00a0Banking Holiday,\u00a0Annual Leaves,\u00a0Discretionary Bonus\u00a0&\u00a0Additional Pension Contribution from Company\u00a0&\u00a0Medical Insurance. If you have the desire to join us, please send us your resume immediately with your present & expected salary by clicking Apply Now.\n\n(The information provided will be used for employment related\u00a0purpose only. All information of unsuccessful applicants will be destroyed within six months.)", "employment_types": ["Full Time", "Permanent"], "selling_points": ["Exposure in professional services", "With in-house experience preferred", "Good language skills"], "locations": ["Kwai Fong"], "categories": ["Accounting", "Financial Analyst", "Banking / Finance", "Analyst"], "post_time": "2022-01-17T04:34:12Z", "salary": {"currency": null, "max": null, "min": null, "period": "monthly", "term": null}, "salary_visible": false, "title_keywords": ["analyst"], "responsibilities": ["financial reports", "data", "ad-hoc assignments", "budget", "financial analysis", "cash flow", "data collection"], "requirements": {"degrees": ["degree holder"], "majors": ["finance", "accounting"], "languages": [], "language_level": [], "hard_skills": ["excel", "ifrs", "professional qualifications", "analysis", "powerpoint", "focus"], "soft_skills": ["communication skills", "work independently", "under pressure", "advanced", "computer literacy", "comprehensive", "interpersonal skills", "focus", "initiative"], "languages_combined": []}, "experience_required": {"duration": ["minimum 6 years"], "field": ["business", "management", "planning", "financial"]}}, {"job_id": "100003009051854", "location_code": "hk", "company": "The Great Eagle Group of Companies", "job_title": "Financial Analyst", "description": "Responsibilities:\nConduct analysis on current and past financial data and performance\nPreparing reports and projections with the analysis findings for management\nIdentifying trends in financial performance and providing recommendations for improvement\nReview financial information and forecasts\nDevelop initiatives and policies on improving financial growth\nHandle ad hoc works as assigned by management\n\nRequirements:\n\nDegree holder in Accounting, Finance, Information Technology or other related disciplines\nCertificate in Data Analytics will be an advantage\nMinimum 5 years\u2019 experience in multinational companies/enterprises\nExperience in real estate is an advantage\nStrong analytical and problem solving skills\nGood communication, presentation and interpersonal skills\nResponsible, well-organized, detail-minded, independent and able to work under pressure\nProficiency in MS Office Applications\nGood command of both spoken and written\u00a0English\u00a0and Chinese (including Putonghua)\n\nSalary and benefits will be commensurate with qualifications and experience.\u00a0 Interested parties, please send a full resume with present and expected salary, and date available to\u00a0The Human Resources Department, 32/F., Great Eagle Centre, 23 Harbour Road, Wanchai, Hong Kong\u00a0or\u00a0e-mail to us.\u00a0(Please quote the reference no. on the envelope and the covering letter.)\n\nTo know more about us, please visit our websites at\u00a0http://www.greateagle.com.hk\n\nWe are an equal opportunity employer and welcome applications from all qualified candidates.\n\nPersonal data collected will be treated in strict confidence and used only for recruitment-related purpose. Applicants who have not heard from us within four weeks may consider their applications unsuccessful. All personal data will be destroyed after 12 months.", "employment_types": ["Full Time", "Permanent"], "selling_points": ["Financial research and analysis", "Market trends in financial performance", "Certificate in Data Analytics will be an advantage"], "locations": ["Wan Chai"], "categories": ["Accounting", "Financial Analyst", "Banking / Finance", "Corporate Finance", "Equities / Capital Markets"], "post_time": "2022-01-17T01:23:09Z", "salary": {"currency": null, "max": null, "min": null, "period": "monthly", "term": null}, "salary_visible": false, "title_keywords": ["financial analyst"], "responsibilities": ["management", "ad hoc", "data", "policies", "analysis", "review", "develop", "preparing reports"], "requirements": {"degrees": ["certificate", "degree holder"], "majors": ["related disciplines", "finance", "accounting", "information technology"], "languages": ["putonghua", "english", "chinese"], "language_level": ["good command"], "hard_skills": ["data analytics", "problem solving skills", "ms office"], "soft_skills": ["detail-minded", "independent", "responsible", "well-organized", "communication", "analytical and problem solving skills", "interpersonal skills", "presentation", "work under pressure"], "languages_combined": [{"language": "putonghua", "language_level": ["good command"]}, {"language": "english", "language_level": ["good command"]}, {"language": "chinese", "language_level": ["good command"]}]}, "experience_required": {"duration": ["minimum 5 years"], "field": []}}, {"job_id": "100003009052097", "location_code": "hk", "company": "AVISTA Valuation Advisory Limited", "job_title": "Analyst / Senior Analyst", "description": "Service: Business Valuation\n\nLocation: Hong Kong\n\nJob Description and Responsibilities:\n\nPerform valuations for deal transaction and financial reporting purposes (such as purchase price allocation) under HKFRS, IFRS and US GAAP\nEngage in M&A advisory, financial modeling and other business consulting projects\nProduce and analyze financial model and business information\nConduct data collection and market research\nAssist in preparing proposal and presentation materials for potential valuation leads\n\nRequirements:\n\nUniversity graduates;\nProfessional qualification in Accounting (e.g. HKICPA / ACCA) or CFA would be an advantage;\n1 to 2 years relevant experience in M&A, audit or valuation related position. Experience in international valuation firm would be a plus.\nGood team player with the ability to work independently;\nProficiency in both verbal and written English and Mandarin is essential;\nGood understanding in valuation-related accounting standards (such as intangible assets and purchase price allocation issues) and valuation of financial instruments will be a plus;\nSound technical knowledge and the capability to apply up-to-date valuation methodologies;\nExcellent research, financial modelling and financial analytical skills;\nExcellent interpersonal and communication skills;\nShort business trip to PRC may be required.\nBenefit: We offer attractive remuneration package including a 5-day work week, medical insurance, study leave and good career prospect to the suitable candidate.\n\n\nApplication Procedure: Please send CV with expected salary by clicking \"Apply Now\".\n\nPersonal data will be used for recruitment purpose only.", "employment_types": ["Full Time", "Permanent"], "selling_points": ["Business valuation & financial reporting", "M&A advisory, financial modeling, IPO", "HKICPA/ACCA/CFA will be a plus"], "locations": ["Wan Chai"], "categories": ["Accounting", "Financial Analyst", "Banking / Finance", "Analyst", "Financial Services"], "post_time": "2022-01-17T02:05:31Z", "salary": {"currency": null, "max": null, "min": null, "period": "monthly", "term": null}, "salary_visible": false, "title_keywords": ["analyst", "senior analyst"], "responsibilities": ["valuation", "consulting", "financial modeling", "market research", "purchase", "financial reporting", "data collection"], "requirements": {"degrees": [], "majors": [], "languages": ["english", "mandarin"], "language_level": ["proficiency"], "hard_skills": ["acca", "plus", "cfa", "financial analytical skills", "hkicpa"], "soft_skills": ["communication skills", "good team player", "work independently", "analytical skills", "interpersonal"], "languages_combined": [{"language": "english", "language_level": ["proficiency"]}, {"language": "mandarin", "language_level": ["proficiency"]}]}, "experience_required": {"duration": ["1 to 2 years"], "field": ["related", "relevant experience", "audit"]}}, {"job_id": "100003009052195", "location_code": "hk", "company": "IPSOS Asia Limited", "job_title": "Accountant / Business Analyst", "description": "Role Objective / Purpose\n\n\nThe role of Business Analyst is responsible for all accounting and finance functions of IPSOS HK and to ensure proper accounting records are kept for internal and statutory audits.\n\nRole & Responsibilities:\n\nResponsible for monitoring the operational and accounting system\nMonitor and review the budget and actual spending of projects to ensure data integrity\nOversee the daily accounting functions to ensure accounting records are kept in compliance with the group accounting policies.\nMonitor and supervise the month end closing to ensure all management reports are submitted on time and accurate.\nPrepare monthly financial charts/reports for all IPSOS HK divisions.\nCompile various periodic analytical reports (e.g. Contribution Report, Job Summary Report etc.) and hold discussion meeting with divisional heads regularly so as to make them aware of their updated divisional performance.\nCommunicate with Research Departments regularly to understand and provide necessary support to them\nAssist the statutory audit of IPSOS HK to ensure audit deadline is met.\nParticipate in the group internal audits to make sure proper control procedures are in place.\nReview the existing internal control system and make recommendations on the existing work procedures so as to improve the efficiency.\nAssist in the annual budget process to understand the budget components of each division.\nAssist in the set-up of new accounting software to ensure it meets our business requirement.\nProvide support to Chief Financial Officer for ad hoc reporting so as to meet the tight reporting deadlines.\n\n\nPerson specification\n\nQualification\uff1a\n\nBachelor Degree in Accounting or equivalent with minimum 5 years of audit or accounting experience\n\nKnowledge (including general and IPSOS specific knowledge)\uff1a\n\nKnowledge in SAP system is a definite advantage\nAccounting standards and principles.\nRecent computing development especially in accounting software packages.\nKnowledge in market research products e.g. methodology, product type and client type etc. is preferred.\n\nSkill (including technical and people skill)\uff1a\n\nGood communication and interpersonal skills and able to communicate with people from different background and with different seniority.\nGood language skill both verbal and writing.\nBasic grasp of the market research industry.\nGood computer skill especially in Microsoft Excel, Word, and PowerPoint\nGood presentation skill.\n\nOther Requirements\n\nResponsible and able to work independently.\nDedication and good determination to meet deadlines.\n\nWe offer an attractive remuneration package with 5-day work week to the right candidates. Interested parties please send\u00a0resume with current and expected salary to us. All information collected will be used for recruitment purpose only.", "employment_types": ["Full Time", "Permanent"], "selling_points": ["Accountant", "Financial Analyst", "Audit or Accounting"], "locations": ["Hung Hom"], "categories": ["Accounting", "Accountant", "Financial Analyst", "Others"], "post_time": "2022-01-17T02:26:10Z", "salary": {"currency": null, "max": null, "min": null, "period": "monthly", "term": null}, "salary_visible": false, "title_keywords": ["accountant", "business analyst"], "responsibilities": ["software", "data", "budget", "audit", "communication", "accounting policies", "internal control", "make recommendations", "month end closing", "control", "ad hoc", "compliance", "monitor", "reports", "report", "reporting", "provide support", "review", "monitoring", "procedures", "audits", "communicate with", "market research", "management reports", "daily accounting"], "requirements": {"degrees": [], "majors": [], "languages": [], "language_level": [], "hard_skills": [], "soft_skills": ["work independently", "meet deadlines", "responsible"], "languages_combined": []}, "experience_required": {"duration": [], "field": []}}, {"job_id": "100003009052099", "location_code": "hk", "company": "AVISTA Valuation Advisory Limited", "job_title": "Analyst (2021 / 2022 Graduate Position)", "description": "Service: Business Valuation\nLocation: Hong Kong\n\nScope:\n\nWe are looking for fresh graduates to join our expanding business valuation team of our Hong Kong office. Our analysts will have the opportunities to have a wide range of exposure to various industries of our listed and unlisted clients for different valuation needs. Our business valuation services include:\n\nPerforming valuations for financial reporting purposes, such as equity investments, tangible & intangible assets and financial instruments valuations)\nProviding valuations for transaction purposes such as potential acquisitions and disposals of businesses\nAdvising companies and stakeholders in relation to valuation related matters\n\nResponsibilities:\n\nAnalysts will work as a team in general, with our director, managers and other senior analysts. You are expected to:\n\nAnalyze historical and forecasted financial information provided by clients\nConduct research on comparable financial data and other project-related business and industry information\nProvide assistance to senior colleagues in constructing valuation models and compiling valuation reports\nPrepare valuation analysis and supporting information for discussions and negotiations with clients and other stakeholders involved\nAssist in preparing proposals and presentation materials for potential valuation and consulting leads\nBuild relationships and conduct direct contacts with existing and prospective clients as well as other professional teams (such as sponsors, auditors, financial advisors, lawyers, etc.)\n\nRequirements:\n\nUniversity graduates in all disciplines, preferable with finance and/or accounting degree\nSelf-motivated team player with the ability to work independently in a fast-paced environment\nProficiency in both verbal and written English, Cantonese and Mandarin is essential\nDemonstrate interest in business valuation\nStrong research, financial modeling and financial analytical skills\nExcellent interpersonal and communication skills\nExperience in valuation related fields is a plus\nShort business trips to PRC may be required\n\nBenefits: We offer attractive remuneration package including a 5-day work week, medical insurance and good career prospect to the suitable candidate.\n\nApplication Procedure: Please send your CV with expected salary by clicking \"Apply Now\".\n\nPersonal data will be used for recruitment purpose only.", "employment_types": ["Full Time", "Permanent"], "selling_points": ["Valuations for financial reporting and transaction", "Analyze historical and forecasted financial info", "Fresh graduates are welcome"], "locations": ["Wan Chai"], "categories": ["Accounting", "Financial Analyst", "Banking / Finance", "Analyst", "Financial Services"], "post_time": "2022-01-17T02:05:32Z", "salary": {"currency": null, "max": null, "min": null, "period": "monthly", "term": null}, "salary_visible": false, "title_keywords": ["analyst"], "responsibilities": ["valuation", "consulting", "data", "analysis", "teams", "reports", "provide assistance", "conduct research"], "requirements": {"degrees": ["degree"], "majors": ["finance", "accounting"], "languages": ["cantonese", "english", "mandarin"], "language_level": ["proficiency"], "hard_skills": ["plus", "financial analytical skills"], "soft_skills": ["communication skills", "self-motivated", "work independently", "fast-paced environment", "analytical skills", "team player", "interpersonal"], "languages_combined": [{"language": "cantonese", "language_level": ["proficiency"]}, {"language": "english", "language_level": ["proficiency"]}, {"language": "mandarin", "language_level": ["proficiency"]}]}, "experience_required": {"duration": [], "field": ["related"]}}, {"job_id": "100003009051702", "location_code": "hk", "company": "ASM Technology Hong Kong Limited", "job_title": "SAP System Analyst (Finance Team)", "description": "Job description\nConduct Annual Planning and Quarterly Forecasting\nPartner with Global Costing teams on supporting standard costing process\nTranslate business objectives and requirements into system design that can be supported by SAP\nFacilitate functional teams for new SAP implementation and on-going application update and enhancement globally\nWork closely with internal teams and external vendors to ensure project tasks are delivered on time and are of satisfactory quality with proper documentation\nDesign a test plan and testing standards to monitor system activities\nFormulate SAP user guideline and provide user training\nProvide support on SAP process development and enhancement requests\nProvide ad-hoc support maintenance service and trouble-shooting to end-users\nJob requirements\nDegree holder in IT, Finance/Accounting, or related disciplines.\nMinimum 5 years of experience in SAP FICO module with at least 3 project implementation cycles\nSolid and strong business and technical skills in SAP FICO modules\nStrong interpersonal, communication and analytical skills\nA good team player, initiative and detail-minded\nGood command of written and spoken English, Chinese and Putonghua\nQuarterly travel to Asia Pacific may be required, depending on COVID situation\n\nAttractive salary and fringe benefits package will be offered to the right candidates.\n\nInterested parties please submit your application with cover letter, resume, certificate and transcripts.\n\nData collected will be used for recruitment purpose only. Suitable candidates may be referred to other vacancies within our company.", "employment_types": ["Full Time", "Permanent"], "selling_points": ["Minimum 5 years of experience in SAP FICO module", "Degree holder in IT, Finance/Accounting", "Conduct Annual Planning and Quarterly Forecasting"], "locations": ["Tsing Yi"], "categories": ["Accounting", "Financial Analyst", "Banking / Finance", "Analyst", "Information Technology (IT)", "Others"], "post_time": "2022-01-16T21:50:55Z", "salary": {"currency": null, "max": null, "min": null, "period": "monthly", "term": null}, "salary_visible": false, "title_keywords": ["system analyst"], "responsibilities": ["ad-hoc", "provide support", "maintenance", "teams", "implementation", "quality", "design", "testing", "monitor", "system design", "plan", "documentation", "forecasting", "planning"], "requirements": {"degrees": ["degree holder"], "majors": ["related disciplines", "finance", "it", "accounting"], "languages": ["putonghua", "english", "chinese"], "language_level": ["good command"], "hard_skills": ["sap", "analytical skills"], "soft_skills": ["detail-minded", "good team player", "analytical skills", "communication", "technical skills", "initiative", "interpersonal"], "languages_combined": [{"language": "putonghua", "language_level": ["good command"]}, {"language": "english", "language_level": ["good command"]}, {"language": "chinese", "language_level": ["good command"]}]}, "experience_required": {"duration": ["minimum 5 years"], "field": []}}, {"job_id": "100003009051724", "location_code": "hk", "company": "", "job_title": "Senior Regional FP&A Analyst", "description": "Job Responsibilities\n\nWork closely with senior management provide valuable financial and business insights for APAC region\nSet up and drive monthly and quarterly budgeting, forecasting. Explain variance and reports in presentations\nPerform trend and business analysis and share insights with senior management\nFeasibility studies and conduct financial modelling on new emerging markets and investments\nStandardization and delivery of financial and management reports, business partnership with shared services\nAd hoc projects within the region\n\nRequirements\n\nDegree in Finance and Accounting or relevant subject\nAt least 5-15 years of experience in an analytical position, CPA qualified accountant preferred.\nPrevious experience in a sizable audit firm will be a plus. All rounded finance professionals in reporting and FP&A will also be considered\nStrong analytical and interpersonal skills.\nFluency in English and willingness to be based in Hong Kong\nInterested candidates, please contact us at 800931404 for company details before applying.", "employment_types": ["Full Time", "Permanent"], "selling_points": ["Financial Planning & Analysis projects", "5 yrs FP&A / Management Accounting exp", "Attractive package + industry exposure"], "locations": ["Tsing Yi"], "categories": ["Accounting", "Financial Analyst"], "post_time": "2022-01-16T21:51:10Z", "salary": {"currency": "HKD", "max": 44999, "min": 35000, "period": "monthly", "term": null}, "salary_visible": true, "title_keywords": ["analyst"], "responsibilities": ["budgeting", "presentations", "management reports", "business partnership", "reports", "ad hoc projects", "business analysis", "senior management", "forecasting"], "requirements": {"degrees": ["degree"], "majors": ["finance", "accounting"], "languages": ["english"], "language_level": ["fluency"], "hard_skills": ["cpa", "plus"], "soft_skills": ["interpersonal skills"], "languages_combined": [{"language": "english", "language_level": ["fluency"]}]}, "experience_required": {"duration": ["at least 5-15 years"], "field": ["audit", "analytical"]}}, {"job_id": "100003009050677", "location_code": "hk", "company": "Geox Asia Pacific Limited", "job_title": "Junior Financial Analyst", "description": "Main Responsibilities\nSupport the annual financial planning process (budgeting and forecasting)\nAssist the Business Controller in preparing financial statements and reporting\nAssist with analysis and stores performances by collecting, analyzing and reporting financial and statistical data\nMonitor sales, costs, margins and inventory and carry out all analysis required to identify variance\u2019s causes\nSupport on shop KPI targets settings and monthly controls activities\nAnalyze trends, formulate projections for retail and wholesale business\nWork closely with other Functions to ensure data quality and integrity\nCompletes ad hoc projects and duties assigned by the line manager from time to time\nJob Requirements\nBachelor Degree in\u00a0Accountancy / Economics / Finance or any related discipline\nMinimum 1 year relevant experience in budgeting / forecasting / financial analysis / audit in multinational company (retail Industry preferred)\nProactive, detail-minded and good team player\nGood communication skill and strong analytical skill\nGood command of spoken and written English and Chinese\nStrong MS Excel skills; knowledge of SQL, MS Powerpoint, SAP, Oracle Essbase is a plus\nCandidates with more experience will be considered as Senior Financial Analyst\nWe offer attractive remuneration and fringe benefits to the right candidate. Please submit your application in WORD format (quoting job title) together with a detailed resume, stating current and expected salary by\u00a0\"Apply Now\"\u00a0button.\u00a0\n\n\n(All personal data provided by job applicants are used only for recruitment purpose and will be treated strictly confidential. Unsuccessful applications will be properly disposed within 3 months.)", "employment_types": ["Full Time", "Permanent"], "selling_points": ["Financial Planning & Analysis in Retail & WHS", "Direct Report to Business Controller", "5-Day Work Week, MNC Working Environment"], "locations": ["Wan Chai"], "categories": ["Accounting", "Accounting Clerk / Supervisor", "Financial Analyst", "Financial Controller"], "post_time": "2022-01-15T03:51:13Z", "salary": {"currency": null, "max": null, "min": null, "period": "monthly", "term": null}, "salary_visible": false, "title_keywords": ["financial analyst", "junior"], "responsibilities": ["reporting", "data", "budgeting", "analysis", "planning process", "monitor", "inventory", "financial statements", "quality", "ad hoc projects", "forecasting", "costs"], "requirements": {"degrees": ["degree", "bachelor"], "majors": ["finance", "economics", "accountancy"], "languages": ["english", "chinese"], "language_level": ["good command"], "hard_skills": ["analytical skill", "plus", "sap", "financial analysis", "sql", "ms excel", "ms powerpoint", "oracle"], "soft_skills": ["detail-minded", "good team player", "analytical skill", "communication skill", "proactive"], "languages_combined": [{"language": "english", "language_level": ["good command"]}, {"language": "chinese", "language_level": ["good command"]}]}, "experience_required": {"duration": ["minimum 1 year"], "field": ["retail industry", "multinational company", "audit", "relevant experience", "financial"]}}, {"job_id": "100003009051826", "location_code": "hk", "company": "The Great Eagle Group of Companies", "job_title": "Assistant Accountant / Accountant", "description": "Responsibilities:\n\nPrepare full set of monthly management accounts and month-end closing independently\nPrepare statutory financial statements and liaise with external auditors\nAnalytical review on management reports to explain business performance\nHandle budgeting and forecasting\nAssist in group consolidation and prepare financials for results announcement\nHandle ad hoc tasks and assignments as required\n\nRequirements:\n\nDegree holder in Accountancy, Finance or other related disciplines\nMember of recognized accounting bodies (HKICPA, ACCA or equivalent) is preferred\n3 \u2013 5 years relevant experience, preferably gained in listed companies or sized CPA firms\nExperience in real estate or hospitality industry is an advantage\nKnowledge of IFRS / HKFRS\nProficient in MS Office Application\nSelf-motivated, detail-oriented, proactive and able to work independently\nGood communication and interpersonal skills\nGood command of both written and spoken English and Chinese\n\nSalary and benefits will be commensurate with qualifications and experience.\u00a0 Interested parties, please send a full resume with present and expected salary, and date available to The Human Resources Department, 32/F., Great Eagle Centre, 23 Harbour Road, Wanchai, Hong Kong or e-mail to us.\u00a0(Please quote the reference no. on the envelope and the covering letter.)\n\nTo know more about us, please visit our website at http://www.greateagle.com.hk.\n\nWe are an equal opportunity employer and welcome applications from all qualified candidates.\n\nPersonal data collected will be treated in strict confidence and used only for recruitment-related purpose. Applicants who have not heard from us within four weeks may consider their applications unsuccessful. All personal data will be destroyed after 12 months.", "employment_types": ["Full Time", "Permanent"], "selling_points": ["Monthly report & month-end closing", "Handle budgeting and forecasting", "HKICPA, ACCA or equivalent is preferred"], "locations": ["Wan Chai"], "categories": ["Accounting", "Accountant", "Accounting Clerk / Supervisor", "Financial Analyst"], "post_time": "2022-01-17T01:18:24Z", "salary": {"currency": null, "max": null, "min": null, "period": "monthly", "term": null}, "salary_visible": false, "title_keywords": ["accountant", "assistant accountant"], "responsibilities": ["management", "budgeting", "review", "ad hoc tasks", "financial statements", "management reports", "month-end closing", "liaise with", "forecasting", "external auditors"], "requirements": {"degrees": ["degree holder"], "majors": ["related disciplines", "finance", "accountancy"], "languages": ["english", "chinese"], "language_level": ["good command"], "hard_skills": ["acca", "ifrs", "hkfrs", "cpa", "ms office", "hkicpa"], "soft_skills": ["self-motivated", "work independently", "detail-oriented", "communication and interpersonal skills", "proactive"], "languages_combined": [{"language": "english", "language_level": ["good command"]}, {"language": "chinese", "language_level": ["good command"]}]}, "experience_required": {"duration": ["5 years"], "field": ["hospitality industry", "relevant experience"]}}, {"job_id": "100003009051583", "location_code": "hk", "company": "Amazin Consultants Limited", "job_title": "FP&A Manager (Branded FMCG)", "description": "Our client is one reputable consumer brand company. \u00a0They are currently looking for high caliber for their FP&A Manager.\n\nProvide analysis and insights on financial planning\nPartner with different business stakeholders and collect figures for business analysis\nStable working environment with attractive package\n\nJob Responsibilities:\n\nProvide analysis and insights on financial planning for management review and business planning\nPartner with different business stakeholders and collect different figures for business analysis\nLead mostly financial planning\u00a0& analysis projects such as sales controlling, cash flow forecast, strategic pricing, product mix analysis, KPI analysis etc for business review\n\nJob Requirement:\n\nBachelor degree with at least 6 years of experience\nTrack exposure in fast-paced environment / FMCG industry\nHighly analytical and detail-oriented with good business sense\nExcellent communication and interpersonal skills\nGood-command of written and verbal English and Chinese\u00a0", "employment_types": ["Full Time", "Permanent"], "selling_points": ["Provide analysis and insights on fin planning", "Collect figures from BU heads for bus analysis", "Stable working environment with attractive package"], "locations": ["Others"], "categories": ["Accounting", "Finance / Accounting Manager", "Financial Analyst"], "post_time": "2022-01-16T12:31:21Z", "salary": {"currency": null, "max": null, "min": null, "period": "monthly", "term": null}, "salary_visible": false, "title_keywords": ["manager"], "responsibilities": ["analysis", "review", "cash flow", "forecast", "business analysis", "management review", "planning"], "requirements": {"degrees": ["degree", "bachelor"], "majors": [], "languages": ["english", "chinese"], "language_level": ["good"], "hard_skills": ["fmcg industry"], "soft_skills": ["fast-paced environment", "communication and interpersonal skills", "business sense", "detail-oriented"], "languages_combined": [{"language": "english", "language_level": ["good"]}, {"language": "chinese", "language_level": ["good"]}]}, "experience_required": {"duration": ["at least 6 years"], "field": []}}, {"job_id": "100003009049825", "location_code": "hk", "company": "Sun Hung Kai Properties Ltd", "job_title": "BUSINESS ANALYST / ASSISTANT BUSINESS ANALYST", "description": "Requirements:\n\nBachelor\u2019s degree in Finance, Business, Accounting or related disciplines. An MBA degree is an added advantage\nMinimum 5 years\u2019 relevant experience in business analysis\nStrong business acumen and numerical sense\nGood analytical and communication skills\nGood command of spoken and written English and Chinese\nFamiliar with PC software e.g. MS Word, Excel, PowerPoint\nResponsibilities:\n\nPerform financial analysis for business opportunities, including financial modelling, valuation analysis and scenario simulations\nConduct insightful operational analysis to investigate ongoing issue\nAssist the team with research to provide business insight and context for business recommendations\nSupport with putting together presentations for senior management\nSource and develop market intelligence available to the team, including monitoring of news and other sources of public information\nExecute relevant industry analysis against competitors\nParticipate in ad hoc projects to understand market development and identify opportunities for business units\nSupport the monitoring and reporting of business units and financial performance of business units\n(Candidates with less experience will be considered as Assistant Business Analyst.)\n\nGood remuneration and attractive fringe benefits will be offered to the successful applicant. Interested parties please apply with full resume, present and expected salary, available date by clicking \"Apply Now\".\n\nFor further information, please visit our company website: www.shkp.com.\n\nWe are an equal opportunity employer and welcome applications from all qualified candidates. All personal data collected will be used for recruitment purpose only.\u00a0 Applicants not hearing from us within 3 months may consider their applications unsuccessful.\u00a0 All personal data collected will be destroyed within 24 months.", "employment_types": ["Full Time", "Permanent"], "selling_points": ["5 yrs' exp in business analysis (non-property)", "Financial analysis for business opportunities", "Operational analysis to investigate ongoing issue"], "locations": ["Wan Chai"], "categories": ["Accounting", "Financial Analyst", "Banking / Finance", "Analyst", "Professional Services", "Business Analysis / Data Analysis"], "post_time": "2022-01-14T09:17:27Z", "salary": {"currency": null, "max": null, "min": null, "period": null, "term": null}, "salary_visible": false, "title_keywords": ["business analyst", "assistant"], "responsibilities": ["valuation", "reporting", "business opportunities", "analysis", "monitoring", "presentations", "develop", "financial analysis", "ad hoc projects", "senior management"], "requirements": {"degrees": ["degree", "bachelor"], "majors": ["related disciplines", "finance", "business", "accounting"], "languages": ["english", "chinese"], "language_level": ["good command"], "hard_skills": ["excel", "analysis", "acumen", "powerpoint", "pc", "ms word"], "soft_skills": ["business acumen", "communication skills"], "languages_combined": [{"language": "english", "language_level": ["good command"]}, {"language": "chinese", "language_level": ["good command"]}]}, "experience_required": {"duration": ["minimum 5 years"], "field": ["business analysis", "relevant experience"]}}, {"job_id": "100003009043961", "location_code": "hk", "company": "S.F. Express (Hong Kong) Limited", "job_title": "Accountant (Financial Analyst)", "description": "Responsibilities:\n\nAssist in month-end closing work\nPrepare different kinds of business unit/project financial reports in a timely and accurate manner.\nConduct different kinds of analysis, such as but not limited to business case analysis, OPEX analysis, cost modeling, KPI monitoring, etc.\nPrepare presentations and visual aids to help illustrate data in appropriate ways\nEnsure accuracy of data within the reports and understand the content of supporting documentation, and proactively research issues that have a significant impact on financial results\nLiaise and coordinate with external auditors\nPerform ad-hoc tasks per request\n\nRequirements:\n\nBachelor Degree in Finance or Accounting or related discipline\n3-5 years experience in accounting and analysis functions\nKnowledge in tools or software like Power BI, Tableau, R, or other data & code manipulation methodologies for data analysis will be a big advantage.\nProficient in MS office application, especially in strong data applications, such as PowerPoint, Visio, Marco, function, etc.\u00a0\nExperience in handling SAP is a plus.\nAble to handle multi-tasks and meet tight deadlines\nMember of HKICPA/ACCA is a plus\nGood command of written and spoken English, Cantonese, and Mandarin\nImmediately available is an advantage\n\n\n\nWe offer attractive remuneration package and fringe benefits to the right candidates. Interested parties please submit your application to us. If you do not want to apply as JobsDB member, you may send your full resume with your availability, current and expected salaries to recruit01 at sf-express.com.\n\nYou are welcome to visit our website at\u00a0https://htm.sf-express.com/hk/tc/\u00a0for more information about us.\n\nCandidates who are not invited for interview within 1-month may consider their applications unsuccessful.\n\nAll personal data provided by job applicants will be used only for recruitment purpose and will be treated strictly confidential. Unsuccessful applications will be retained for a maximum period of 24-month.", "employment_types": ["Full Time", "Permanent"], "selling_points": ["Free shuttle bus coverage", "2 months or above performance bonus", "Attractive basic salary"], "locations": ["Tsing Yi"], "categories": ["Accounting", "Accountant", "Accounting Clerk / Supervisor", "Financial Analyst"], "post_time": "2022-01-13T02:36:40Z", "salary": {"currency": null, "max": null, "min": null, "period": "monthly", "term": null}, "salary_visible": false, "title_keywords": ["accountant", "financial analyst"], "responsibilities": ["liaise", "financial reports", "cost", "data", "analysis", "monitoring", "coordinate with", "ad-hoc tasks", "presentations", "opex", "month-end closing", "reports", "visual", "documentation", "external auditors"], "requirements": {"degrees": ["degree", "bachelor"], "majors": ["finance", "accounting"], "languages": ["cantonese", "english", "mandarin"], "language_level": ["good command"], "hard_skills": ["plus", "bi", "acca", "sap", "analysis", "code", "tableau", "powerpoint", "hkicpa", "marco", "r", "ms office"], "soft_skills": ["meet tight deadlines", "multi-tasks"], "languages_combined": [{"language": "cantonese", "language_level": ["good command"]}, {"language": "english", "language_level": ["good command"]}, {"language": "mandarin", "language_level": ["good command"]}]}, "experience_required": {"duration": ["3-5 years"], "field": ["accounting"]}}, {"job_id": "100003009050155", "location_code": "hk", "company": "Magic Search Limited", "job_title": "Regional Assistant Financial Analyst (Luxury Brand)", "description": "Our client is a Global leading luxury brand. To cope with their business expansion, they are looking for a\u00a0Regional Assistant Financial Analyst to join the team.\n\nKey Responsibilities\n\nPrepare and consolidated Asia Sales monthly sales report with comparison against Budget and Forecast with comment\nWork closely with other functional team to ensure alignment and to reconcile any discrepancy\nPrepare other regular sales reporting or ad hoc analysis for management review of business performance\u00a0\nDevelop and replicate excel\u00a0budget/forecast\u00a0templates for\u00a0Asia\u00a0market\u00a0and\u00a0validation\u00a0\u00a0\nAssist\u00a0with the\u00a0budget & forecast\u00a0consolidation\u00a0(via excel platform)and review\u00a0process\nValidate system input and co-ordinate necessary follow-up with market\u00a0finance team\nAssist with analysis during budget and forecast process\nCost Management and Budget follow-up\n\nRequirements\n\nBachelor degree in Finance, Accounting or other related subject\n2 years relevant retail working experience\nAbility to extract, organise, analyse and report data\nGood communication skills\nGood command in English and Chinese\u00a0\n\nAll information provided will be treated in strict confidence and used solely for recruitment purposes. To apply, please quote current and expected salary and send your CV through \" APPLY NOW\"", "employment_types": ["Full Time", "Permanent"], "selling_points": ["2 years experience", "Luxury brand", "Regional explosure"], "locations": ["Not Specified"], "categories": ["Accounting", "Financial Analyst", "Financial Controller", "Banking / Finance", "Analyst"], "post_time": "2022-01-14T09:53:05Z", "salary": {"currency": null, "max": null, "min": null, "period": "monthly", "term": null}, "salary_visible": false, "title_keywords": ["assistant", "financial analyst"], "responsibilities": ["reporting", "cost", "management", "ad hoc", "forecast process", "analysis", "budget", "review", "develop", "system input", "finance team", "forecast", "monthly sales report", "management review"], "requirements": {"degrees": ["degree", "bachelor"], "majors": ["finance", "accounting"], "languages": ["english", "chinese"], "language_level": ["good command"], "hard_skills": [], "soft_skills": ["communication skills", "confidence"], "languages_combined": [{"language": "english", "language_level": ["good command"]}, {"language": "chinese", "language_level": ["good command"]}]}, "experience_required": {"duration": ["2 years"], "field": ["retail"]}}, {"job_id": "100003009046396", "location_code": "hk", "company": "Wheelock Properties (Hong Kong) Ltd", "job_title": "Business Analyst", "description": "Responsibilities:\n\n\nAssist Department Manager in corporate financial management and control in Company\u2019s financial activities\nConduct in-depth analysis and market research on peers / property market performance / tracking / benchmarking etc.\nProvide insights on funding forecast and budgetary control, perform variance analysis, review and monitor costs inherent that have dual accountability to both finance and business nature\nWork closely with other departments in the provision of management information and financial analysis management reporting package\nReview workflows and propose area of improvement / streamline\nParticipate ad hoc projects or presentations as assigned\nRequirements:\nBachelor degree or above in Accounting, Finance, Economics or other relevant disciplines\nWith at least 8 years' relevant experience in management accounting, market research or in similar position preferred\nCPA is preferred, but not a must\nExperience in listed company highly desired and exposure of property industry and advantage\nCreative & resourceful with good analytical mindset and communication skills\nExcellent command of English and Cantonese including Mandarin\nHighly proficient in MS office applications including Excel & PowerPoint\n\nWe offer ample opportunities for career development and attractive salary package commensurate with experience and qualifications. \u00a0Interested parties please apply with full resume via\u00a0\u201cAPPLY NOW\u201d.\u00a0\n\nFor further information on Wheelock Properties (Hong Kong) Limited, please visit our website:\u00a0www.wheelockpropertieshk.com.\n\nWe are an equal opportunities employer and invite applications from all qualified candidates. Personal data collected will be treated in strict confidence and handled by authorized persons for recruitment-related purposes only within The Wheelock & Wharf Group. Applicants not hearing from us within 2 months may consider their applications unsuccessful.\u00a0", "employment_types": ["Full Time", "Permanent"], "selling_points": [], "locations": ["Central"], "categories": ["Accounting", "Financial Analyst", "Financial Controller", "Banking / Finance", "Corporate Finance"], "post_time": "2022-01-13T18:55:19Z", "salary": {"currency": null, "max": null, "min": null, "period": null, "term": null}, "salary_visible": false, "title_keywords": ["business analyst"], "responsibilities": ["provide insights", "management", "control", "analysis", "review", "monitor", "market research", "presentations", "work closely with other departments", "financial analysis", "variance analysis", "ad hoc projects", "management reporting", "forecast", "costs", "tracking"], "requirements": {"degrees": ["degree or above", "bachelor"], "majors": ["finance", "accounting", "economics"], "languages": ["cantonese", "english", "mandarin"], "language_level": ["excellent"], "hard_skills": ["powerpoint", "cpa", "excel", "ms office"], "soft_skills": ["communication skills", "creative", "resourceful"], "languages_combined": [{"language": "cantonese", "language_level": ["excellent"]}, {"language": "english", "language_level": ["excellent"]}, {"language": "mandarin", "language_level": ["excellent"]}]}, "experience_required": {"duration": ["at least 8 years"], "field": ["management accounting", "relevant experience", "market research"]}}, {"job_id": "100003009052239", "location_code": "hk", "company": "United Search Group (Asia) Limited", "job_title": "Chief Financial Officer-HK$150k-200k per month (HK listed retail company)", "description": "Our client, HK listed company, is engaged in retailing and servicing business with rapid expansion plan across APAC region. Due to the continued expansion, they are looking for a strong caliber to join their finance team.\n\n\nResponsibilities\n\nReporting to the Board, the job holder is responsible for key finance functions\u00a0\nLead the Finance Department of 15 staffs\nManage annual audit processes\nPrepare periodic financial reports for fund investors and firm management\nManage and review the firm-wide budget and get involved in financial strategy planning and recommendation on firm performance\nPrepare routine management and regulatory reports to top management and regulators\nProvide advice to top management in relation to business finance with strategic\u00a0planning\nDelivering month/year-end reporting, budget & forecast analysis in order to\u00a0provide a better insight of business performance for Senior Management and\u00a0Board Committees\nProviding statutory reporting for the corporate entities including annual audit\u00a0process and liaising with external auditors\nOverseeing all tax related requirements for the corporate entities and liaise\u00a0with tax advisers\nEnhance productivity and ensure finance processes and documented procedures\u00a0are up-to-date\n\nRequirements\n\nCPA qualified with over 12 years of accounting and management experience\nRetail industry exposure is a must\nExperience in in-charge of company\u2019s overall financial reporting, management\u00a0reporting and treasury function\nPrior experience in M&A project will be an advantage\n\nIf you would like to apply for this role or find out more, please send your resume at info @ usgroupasia.com", "employment_types": ["Full Time", "Permanent"], "selling_points": ["Stable and autonomy working environment", "HK listed company in retail industry", "M&A experience and Energetic environment"], "locations": ["Wan Chai Area"], "categories": ["Accounting", "Chief Accountant", "Financial Analyst", "Financial Controller"], "post_time": "2022-01-17T02:31:50Z", "salary": {"currency": null, "max": null, "min": null, "period": "monthly", "term": null}, "salary_visible": false, "title_keywords": ["chief financial officer"], "responsibilities": ["budget", "planning", "liaise with", "senior management", "liaising with", "reports", "forecast", "reporting", "management", "strategic planning", "annual audit", "review", "procedures", "fund investors", "tax", "year-end", "financial reports", "analysis", "provide advice", "external auditors"], "requirements": {"degrees": [], "majors": [], "languages": [], "language_level": [], "hard_skills": ["cpa"], "soft_skills": [], "languages_combined": []}, "experience_required": {"duration": ["12 years"], "field": ["management", "accounting", "financial"]}}, {"job_id": "100003009043999", "location_code": "hk", "company": "Amorepacific Hong Kong Co Ltd", "job_title": "Senior Business Analyst", "description": "Key Responsibilities\n\nWork as business partners to support Brand Function to deliver their business goal; Ensure effective strategy implementation and monitoring performance\nExecute business performance analytics including implement modeling development and refinement to maximize customer retention and value, gather customer insights through data mining and analysis, identify up-sell & cross-sell opportunities to increase customer value\nWork closely with Brand Function to design customer journeys, conduct customer segmentation and best targeting tactics as well as effectiveness evaluation.\nProduce reporting analytics to enable identification of key trends or issues in the Business / Operating Unit that necessitate further analysis and discussion\nConnect with Headquarter Strategy Team on different aspect of the business e.g. analysis of internal financial information and external economic condition and its impact on business operations, future market outlook etc.\nSupport in Dashboards development including data modelling and design\nAny ad hoc activities arising\u00a0 \u00a0\n\nKey Stakeholders\n\nThis position\u2019s primary interfaces are (engagement, interaction, etc)\n\n\nLocal: Brand GM, Brand Marketing & Operation Team, Finance Operation Team, HR Team\nHQ: Strategy Team\n\nRequirements:\n\nDegree in Business, Statistics or Mathematics related field\n4-5 years working experience in business/data analysis or business intelligence preferably gained from Retail Industry\nStrong business acumen and analytical skillset\nEnjoy challenges and willing to push back & confront status quo when necessary\nExcellent communication, interpersonal & influencing skills\nAbility to work independently & effectively with all levels within an organization\nHigh proficient in SQL, MS Excel.\nExperience in statistical tool e.g. SPSS and BI tools e.g. Tableau is highly preferred.\u00a0 Knowledge in Salesforce Marketing Cloud will be a plus.\n\nCandidate with less experience will be considered as Business Analyst.\n\n\n\n\nWe offer opportunities for development in addition to a competitive remuneration and benefit package to the right candidate. Interested parties please click \"Apply Now\" for application.\n\nPersonal data provided by job applicants will be used strictly for recruitment purpose only.", "employment_types": ["Full Time", "Permanent"], "selling_points": ["Work closely with Brand to design customer journey", "Execute business performance analytics", "4-5 years working experience in business analysis"], "locations": ["Wan Chai"], "categories": ["Accounting", "Financial Analyst", "Professional Services", "Business Analysis / Data Analysis", "Marketing / Public Relations", "Marketing - Market Research"], "post_time": "2022-01-13T02:44:45Z", "salary": {"currency": null, "max": null, "min": null, "period": "monthly", "term": null}, "salary_visible": false, "title_keywords": ["senior business analyst"], "responsibilities": ["reporting", "ad hoc", "data", "operations", "analysis", "monitoring", "customer insights", "implementation", "design", "hr", "evaluation", "data mining"], "requirements": {"degrees": ["degree"], "majors": ["mathematics", "business", "statistics"], "languages": [], "language_level": [], "hard_skills": ["plus", "bi", "salesforce", "analysis", "tableau", "sql", "ms excel", "business intelligence", "acumen"], "soft_skills": ["business acumen", "work independently", "interpersonal", "communication"], "languages_combined": []}, "experience_required": {"duration": ["4-5 years"], "field": ["data analysis", "business", "retail industry"]}}, {"job_id": "100003009054922", "location_code": "hk", "company": "Sun Hung Kai Properties Ltd", "job_title": "FINANCIAL CONTROLLER \u2013 HOTEL DIVISION", "description": "Requirements:\n\n\nBachelor\u2019s degree holder, with CPA or other professional qualification in accounting. Prior working experience in audit preferred\nAt least 15 years\u2019 working experience, including relevant experience as Director of Finance in sizable hotels with extensive F&B and other facilites\nSolid working experience for hotels in Hong Kong and mainland China\nStrong analytical skills, good business acumen and ownership perspective\nBe resilient and able to cope with high work pressure and demanding deadlines\nHighly motivated, detail-minded and result oriented with multi-tasking skills\nProactive and a good team player\nGood communication and interpersonal skills\nProficient in both spoken and written English and Chinese\n\nResponsibilities:\n\n\nResponsible for the overall accounting and financial review matters, including reporting and analysis of the portfolio hotels in Hong Kong and mainland China\nWorking closely with headquarter corporate offices and finance teams of portfolio hotels\nProvide consolidated management reports and analysis with value-added views on business and good interpretation of financial data\nPerform regular reviews on financial controls\n\nGood remuneration and attractive fringe benefits will be offered to the successful applicant. Interested parties please apply with full resume, present and expected salary, available date by clicking \u201cApply Now\u201d.\n\nFor further information, please visit our company website: http://www.shkp.com/.\n\nWe are an equal opportunity employer and welcome applications from all qualified candidates. All personal data collected will be used for recruitment purpose only.\u00a0 Applicants not hearing from us within 3 months may consider their applications unsuccessful.\u00a0 All personal data collected will be destroyed within 24 months.", "employment_types": ["Full Time", "Permanent"], "selling_points": ["Bachelor degree with CPA qualification", "Exp as Director of Finance in sizable hotels", "Accounting & financial review of HK & PRC hotels"], "locations": ["Wan Chai"], "categories": ["Accounting", "Finance / Accounting Manager", "Financial Analyst", "Financial Controller"], "post_time": "2022-01-17T14:01:55Z", "salary": {"currency": null, "max": null, "min": null, "period": null, "term": null}, "salary_visible": false, "title_keywords": ["financial controller"], "responsibilities": ["reporting", "data", "analysis", "review", "teams", "management reports"], "requirements": {"degrees": ["bachelor", "degree holder"], "majors": ["accounting"], "languages": ["english", "chinese"], "language_level": ["proficient"], "hard_skills": ["cpa", "acumen", "analytical skills"], "soft_skills": ["detail-minded", "good team player", "multi-tasking skills", "analytical skills", "result oriented", "motivated", "communication and interpersonal skills", "business acumen", "proactive", "extensive"], "languages_combined": [{"language": "english", "language_level": ["proficient"]}, {"language": "chinese", "language_level": ["proficient"]}]}, "experience_required": {"duration": ["at least 15 years"], "field": ["finance", "audit", "f&b", "relevant experience", "hotels"]}}, {"job_id": "100003009054074", "location_code": "hk", "company": "Tianda Financial Limited", "job_title": "Finance Manager/ AM (SFC Type 1,4,9)", "description": "Responsibilities\uff1a\n\nHandle the accounting entries of the company and its subsidiaries and to develop and improve the accounting, financial, auditing and internal control management systems of the Company;\nSubmit FRR and annual audited financial statements to SFC;\nPrepare and monitor enforcement of annual budget,\u00a0monthly financial statements and consolidation financial statements;\nPrepare financial analysis, internal management reports and all financial analysis reports;\nHandle tax issues, accounts receivables and payables, client fund deposit and withdrawal, and annual auditing;\nResponsible for fund management, monitor liquid capital position;\nAssist with Investment services department to jointly monitor the credit status of margin clients.\nLiaise with tax authority, auditors, banks and SFC on finance related matters.\n\nRequirements:\n\nBachelor\u2019s Degree or above in accounting and finance, qualified accountant or members;\n3-4 years accounting and finance relevant experiences in investment banks or securities brokerage firms, familiar with accounting rules and regulations of securities business, familiar with accounting systems and back office system;\nHave a high level of responsibility and good communication\u00a0and coordination skills, strong sense of moral values, pay attention to details, have a good team spirit and professional attitude.\nWe offer 5-day work week and competitive remuneration package to qualified candidates. Interested parties please click \"Apply Now\" and submit your resume with current and expected salary .Please visit our company\u2019s website:\u00a0https://www.tiandafinancial.com\u00a0to know more about us.\n\nAll information provided by applicants will be treated in strict confidence and used for recruitment purpose only.\u00a0", "employment_types": ["Full Time", "Permanent"], "selling_points": [], "locations": ["Admiralty"], "categories": ["Accounting", "Finance / Accounting Manager", "Financial Analyst", "Banking / Finance", "Financial Services"], "post_time": "2022-01-17T08:19:00Z", "salary": {"currency": null, "max": null, "min": null, "period": "monthly", "term": null}, "salary_visible": false, "title_keywords": ["finance manager"], "responsibilities": ["tax", "management", "systems", "monitor", "budget", "financial statements", "develop", "monthly financial statements", "financial analysis", "management reports", "financial analysis reports", "liaise with", "auditing", "internal control"], "requirements": {"degrees": ["degree or above", "bachelor"], "majors": ["finance", "accounting"], "languages": [], "language_level": [], "hard_skills": ["accounting systems"], "soft_skills": ["team spirit", "coordination skills", "moral", "communication", "attention to details"], "languages_combined": []}, "experience_required": {"duration": ["3-4 years"], "field": ["securities brokerage", "investment banks", "finance", "business", "securities", "accounting"]}}, {"job_id": "100003009054019", "location_code": "hk", "company": "K. Wah International Holdings Ltd", "job_title": "AGM - Finance", "description": "Job Responsibilities\n\nHandle IR activities such as results announcements, investor briefings and meetings, roadshows, site visits, and conferences\nAssist in the preparation of annual reports, interim reports, and other relevant reports\nPrepare corporate presentations, Q&As, press releases for IR purposes\nMaintain good relationships with shareholders, analysts, commentators, columnists, and financial media\nDisseminate to the investment community of relevant information to generate publicity and coverage for the Company\nIdentify and follow up on any appropriate awards for best IR practices to enhance the Company\u2019s exposure in the investment community\nMonitor the economic situation, governments\u2019 fiscal and monetary policies, and conduct research and analysis on property market (Hong Kong and Mainland China)\nAssist in business development by participating in financial modeling and seeking potential investors\nSupport any ad hoc projects\n\n\u00a0Job Requirements\n\nDegree holder or above in Business Administration, Finance, Economics or related discipline\nA minimum of 10 years of work experience in listed companies or financial institutions\nSolid accounting background, with CFA qualification\nExcellent presentation, communication, and interpersonal skills with strong analytical skills and business sense\nKnowledgeable with regards to the financial and economic landscape of both Hong Kong and Mainland China\nExcellent command of written and spoken English and Chinese including Putonghua\nWell versed in computer applications especially in Excel and PowerPoint\n\nInterested parties please send resume with salary expectation and availability to\u00a0Human Resources Department, K. Wah International Holdings Limited, 29/F, K. Wah Centre, 191 Java Rd., North Point, H.K.\u00a0or by clicking\u00a0Apply Now\u00a0.\n\nAll Personal data collected will be used for recruitment purpose only. All applications will be retained for a maximum period of 2 years and may be considered for other suitable positions within the Group.", "employment_types": ["Full Time", "Permanent"], "selling_points": ["Investor Relations focus", "Qualified CFA", "Solid Accounting background"], "locations": ["North Point"], "categories": ["Accounting", "Finance / Accounting Manager", "Financial Analyst", "Banking / Finance", "Investment"], "post_time": "2022-01-17T08:07:18Z", "salary": {"currency": null, "max": null, "min": null, "period": "monthly", "term": null}, "salary_visible": false, "title_keywords": [], "responsibilities": ["relevant reports", "policies", "analysis", "financial modeling", "monitor", "presentations", "conferences", "maintain", "reports", "ad hoc projects", "conduct research"], "requirements": {"degrees": ["degree holder"], "majors": ["finance", "economics", "business administration"], "languages": ["putonghua", "english", "chinese"], "language_level": ["excellent"], "hard_skills": ["powerpoint", "cfa", "excel", "analytical skills"], "soft_skills": ["business sense", "analytical skills", "communication", "interpersonal skills", "presentation"], "languages_combined": [{"language": "putonghua", "language_level": ["excellent"]}, {"language": "english", "language_level": ["excellent"]}, {"language": "chinese", "language_level": ["excellent"]}]}, "experience_required": {"duration": ["minimum of 10 years"], "field": ["financial institutions"]}}, {"job_id": "100003009050735", "location_code": "hk", "company": "Hutchison Telecommunications (Hong Kong) Limited", "job_title": "Business Analyst - Investor Affairs", "description": "Responsibilities:\n\n\nCoordinate & prepare Interim/ Annual announcements & reports, Sustainability Committee Board papers & report\nCoordinate annual general meetings and webcast\nMonitor analyst coverage & market news, update consensus estimates, market views as well as industry and competitive analysis\nPrepare presentations and relevant written materials\nMaintain corporate website\nCollect, analyse & manage ESG data & KPIs from internal stakeholders and prepare regular sustainability reports/ presentations\nFormulate & maintain ESG policies & handle ESG-related matters\nConduct regular meetings, training, workshops & other activities with stakeholders on sustainability-related issues\n\nRequirements:\n\nUniversity graduate in Accounting, Finance, or related discipline\nThree or more years of working experience\nSelf-starter, project management skills, flexible in approach and methodology, and the ability to show initiatives and meet deadlines\nExcellent command in both written and spoken English and Chinese\nCandidates with less working experience will be considered as Assistant Business Analyst\n\nApart from competitive remuneration package and exciting opportunity for career development within the Group, we provide attractive employee benefits such as free company shuttle, free company SIM card and preferential SIM plan offers, comprehensive medical & insurance schemes, as well as full range of other employee well-being provisions.\n\nInterested parties, please apply with full resume, present and expected salary, by clicking \u201cAPPLY NOW\u201d. Please quote the reference number on the e-mail subject.\n\nWe are an equal opportunity employer and welcome applications from all qualified candidates. Personal data collected will be treated in the strictest confidence and handled confidentially by authorised personnel for recruitment-related purposes only within the CK Hutchison Group of companies. The personal data of unsuccessful applicants will be destroyed after the recruitment exercise pursuant to the requirements of the Personal Data (Privacy) Ordinance in Hong Kong.", "employment_types": ["Full Time", "Permanent"], "selling_points": [], "locations": ["Tsing Yi"], "categories": ["Accounting", "Financial Analyst", "Banking / Finance", "Corporate Finance", "Others"], "post_time": "2022-01-14T11:15:00Z", "salary": {"currency": null, "max": null, "min": null, "period": "monthly", "term": null}, "salary_visible": false, "title_keywords": ["business analyst"], "responsibilities": ["data", "policies", "analysis", "monitor", "website", "presentations", "coordinate", "maintain", "reports", "analyse", "kpis", "report"], "requirements": {"degrees": ["university graduate"], "majors": ["finance", "accounting"], "languages": ["english", "chinese"], "language_level": ["excellent"], "hard_skills": ["project management"], "soft_skills": ["flexible", "project management skills", "meet deadlines", "comprehensive"], "languages_combined": [{"language": "english", "language_level": ["excellent"]}, {"language": "chinese", "language_level": ["excellent"]}]}, "experience_required": {"duration": [], "field": ["business"]}}, {"job_id": "100003009054564", "location_code": "hk", "company": "Foodgears Industrial International Limited", "job_title": "Management Accounting Manager", "description": "Responsibilities:\n\nDrive the financial planning of the company by analyzing its performance and risks\nSet targets for and supervise all accounting and finance personnel (management accountants, internal auditors etc.)\nOversee all audit and internal control operations\nPrepare timely and detailed reports on financial performance on a quarterly and annual basis\nConduct analysis to make forecasts and report to upper executives\nEnsure adherence to financial laws and guidelines\n\n\u00a0\nRequirements:\n\nProven experience as director of finance or similar role\nIn-depth knowledge of corporate finance and accounting principles, laws and best practices\nSolid knowledge of financial analysis and forecasting\nProficient in the use of MS Office and financial management software\nAn analytical mind with a strategic ability\nExcellent organizational and leadership skills\nOutstanding communication and interpersonal abilities\nCPA or other relevant qualification and China Accounting experience is a plus\n\n\n\nWe offer attractive remuneration package to the right candidate.\u00a0 Interested parties please send full resume with present & expected salary and available date by clicking \"Apply Now\".\n\n\nAll Personal data collected will be used for recruitment purposes only.\n", "employment_types": ["Permanent"], "selling_points": [], "locations": ["Wong Tai Sin Area"], "categories": ["Accounting", "Finance / Accounting Manager", "Financial Analyst", "Financial Controller"], "post_time": "2022-01-17T10:00:39Z", "salary": {"currency": null, "max": null, "min": null, "period": "monthly", "term": null}, "salary_visible": false, "title_keywords": ["accounting manager"], "responsibilities": ["management", "guidelines", "operations", "analysis", "ensure adherence", "audit", "planning", "reports", "report", "internal control"], "requirements": {"degrees": [], "majors": [], "languages": [], "language_level": [], "hard_skills": ["financial analysis", "cpa", "plus", "ms office"], "soft_skills": ["organizational", "leadership skills", "communication", "analytical mind", "interpersonal"], "languages_combined": []}, "experience_required": {"duration": [], "field": ["finance", "accounting experience"]}}, {"job_id": "100003009044909", "location_code": "hk", "company": "Bread Elements", "job_title": "Financial Analyst - Cost Controller", "description": "Job Highlights\n\nCover the Cost Control & report to Group Finance Director\n2 Business Units: Central Kitchen & Retail, 150 employees, fast expansion \u00a0\u00a0\nPrepare regular management reporting and PnL variance analysis\nProvide insightful recommendations on businesses to the top management\nMonitor budget and forecast for strategic and operational decisions\nSetting KPIs and conducting financial analysis for each business units & liaise with the related team\n\nResponsibilities:\n\nPrepare regular reports (incl. weekly/monthly cost control report & PnL report)\nCalculate weekly F&B internal transfer between legal entities\nPrepare for recipe costing of menu items and assist on the costing audits (retail and factory sides: control real/theoretical consumption)\nPerform forecasting & analysis, budgetary control, cash flow management, tax reporting & ops review\nReview management accounts & assist to prepare reports for top management\nCoordinate with different departments in preparation of the annual budget and forecast \u2013 direct responsibility for overall accountability for delivering consolidated budget/forecast, covering the P&L, cash flow and balance sheet\u00a0\nMonitor cash position, cash flow forecast and banking facilities for investment projects\nMonthly financial close including analytical review of balance sheet, P&L accounts for the business\nTake initiatives on driving changes and system development\nMonitor ongoing performance of the business and find ways to reduce risks\nAct as a key business partner with the senior management in offering strategic and financial insights and recommendations for business management and decision\n\nRequirements:\u00a0\n\nMin. 3 years work experience in Cost Control\nDegree or above in Accounting or Finance or related discipline\nExperience in Big4 is a plus\nStrong analysis & leadership skills\nSolid experience in group level consolidation and financial reporting\nGood command in both English & Cantonese\nProficient in PC skills, such as MS applications, ERP systems, Business Intelligence software (Tableau)\nGood interpersonal and communication skills\nSelf-motivated, curious, analytic, pinpoint, accurate, capable to work under pressure and meet deadline\nImmediately available is highly preferred\n\nBenefits:\u00a0\n\nMedical & Dental Insurance\nStaff discount on ALL Bakehouse shops & products\nGreat working environment with trendy Pantry\nFamily-Friendly Good Employer Certification\n\nWe offer great working environment, attractive salary and benefits package to the right candidate. Interested applicants please send us your resume with availability and expected salary.\n\nWe are an equal opportunity employer. Personal data collected will be treated in strictly confidential and for recruitment purpose only.", "employment_types": ["Full Time", "Permanent"], "selling_points": ["Finance, Cost Control, Reporting, Analysis", "Management Reporting & PnL", "Setting KPIs, Strategy & Recommendations"], "locations": ["Chai Wan"], "categories": ["Accounting", "Financial Analyst", "Financial Controller", "Others"], "post_time": "2022-01-13T06:40:13Z", "salary": {"currency": null, "max": null, "min": null, "period": "monthly", "term": null}, "salary_visible": false, "title_keywords": ["financial analyst"], "responsibilities": ["budget", "senior management", "control", "monitor", "p&l", "reports", "forecast", "banking", "forecasting", "balance sheet", "report", "reporting", "management", "review", "coordinate with", "cash flow", "audits", "tax", "analysis", "cost control", "prepare reports"], "requirements": {"degrees": ["degree or above"], "majors": ["finance", "accounting"], "languages": ["cantonese", "english"], "language_level": ["good command"], "hard_skills": ["erp systems", "plus", "ms applications", "analysis", "tableau", "pc skills", "business intelligence"], "soft_skills": ["communication skills", "self-motivated", "capable", "leadership skills", "accurate", "interpersonal", "work under pressure"], "languages_combined": [{"language": "cantonese", "language_level": ["good command"]}, {"language": "english", "language_level": ["good command"]}]}, "experience_required": {"duration": ["3 years"], "field": ["consolidation", "financial"]}}, {"job_id": "100003009051810", "location_code": "hk", "company": "Panasonic Hong Kong Co., Limited", "job_title": "Senior Accountant (Japanese speaking)", "description": "Responsibilities:\n\nReview, formulate and implement financial and accounting policies, procedures and guidelines\u00a0\nIdentify areas for continuous improvement to eliminate risk and enhance internal control of operational activities and governance\nHandle tax issue, mainly for in-charging of BEPS, and communicate with related parties for planning and resolving\nHandle aggregation/ analysis and information sharing of whole entity and HK regional consolidated financial status\nConduct regular review of end-to-end processes\nProvide effective support to senior for resolving any task assigned\nHandle other ad-hoc duties as assigned\n\n\nRequirements:\n\nBachelor degree in Accounting or related discipline\n5 years or above relevant experience in accounting, tax and internal control\nGood command of spoken & written in English, Cantonese, Mandarin and Japanese\nProficiency in MS office applications, familiar with using accounting system is an advantage\nAble to work independently, good analytical and problem solving skills\nGood team player with strong interpersonal and communication skills\nResponsible, detail-oriented and proactive\nCandidate with more experience will be considered as Manager\n\nRemuneration will be commensurate with qualification and experience. Interested parties, please send your application with detailed resume indicating both existing & expected salary and date of availability to us.\n\nWe are an equal opportunity employer. All information provided by applicants will be treated in strict confidence and used for recruitment purpose only.", "employment_types": ["Full Time", "Permanent"], "selling_points": ["Bachelor degree in finance or accounting field", "5 yrs relevant exp. in AC, Tax & internal control", "Stable MNC in-house environment"], "locations": ["Tsim Sha Tsui"], "categories": ["Accounting", "Accounting Clerk / Supervisor", "Audit", "Financial Analyst"], "post_time": "2022-01-17T04:16:30Z", "salary": {"currency": null, "max": null, "min": null, "period": "monthly", "term": null}, "salary_visible": false, "title_keywords": ["senior accountant"], "responsibilities": ["tax", "communicate with", "guidelines", "analysis", "review", "procedures", "regular review", "accounting policies", "planning", "ad-hoc duties", "internal control"], "requirements": {"degrees": ["degree", "bachelor"], "majors": ["accounting"], "languages": ["cantonese", "japanese", "english", "mandarin"], "language_level": ["good command"], "hard_skills": ["problem solving skills", "ms office", "accounting system", "internal control"], "soft_skills": ["communication skills", "work independently", "good team player", "responsible", "detail-oriented", "analytical and problem solving skills", "proactive", "interpersonal"], "languages_combined": [{"language": "cantonese", "language_level": ["good command"]}, {"language": "japanese", "language_level": ["good command"]}, {"language": "english", "language_level": ["good command"]}, {"language": "mandarin", "language_level": ["good command"]}]}, "experience_required": {"duration": ["5 years"], "field": ["accounting", "relevant experience"]}}, {"job_id": "100003009053709", "location_code": "hk", "company": "Biel Crystal (HK) Manufactory Limited", "job_title": "Senior Accounting Clerk  -   Kwun Tong near MTR Station", "description": "We are the leading smart phone cover glass supplier in the world. \u00a0Our customers include all the well-known smart phone brands.\u00a0 Due to business needs, we are looking for talents to join our Finance team in Hong Kong.\n\n\u00a0Responsibilities:\n\nAssist in daily accounting duties including but not limited to data input, filing, preparing accounting journal entries, bank reconciliations, etc.\nPrepare monthly financial statements for overseas branch, schedules and analysis\nLiaise with China and overseas colleagues in monthly inter-company transactions reconciliation\nProcess data input in system and perform testing when implementation of new functions in system\nAssist in all ad-hoc assignments\n\nRequirements:\n\nReasonable level of accounting knowledge\n2 years accounting experience is preferred\nStrong communication and interpersonal skills to interact with people at different levels\nAble to work in a fast pace working environment\nProficient in MS Office (Word, Excel), Chinese Word processing\nGood command of both written and spoken English\nAbility to speak Chinese Putonghua is necessary\nRecent university graduate in business will also be considered\nImmediately available is preferred\n\nWork location is in Kwun Tong near MTR Station.\u00a0 We offer good career prospects with an attractive salary remuneration including double-pay,\u00a0discretionary bonus and\u00a0medical insurance\u00a0to the right candidate. \u00a0\n\n(Applicants not contacted within six weeks should consider their application unsuccessful. \u00a0Personal data provided by applicants will be strictly used for recruitment purpose only.)", "employment_types": ["Full Time", "Permanent"], "selling_points": [], "locations": ["Kwun Tong"], "categories": ["Accounting", "Accounting Clerk / Supervisor", "Financial Analyst"], "post_time": "2022-01-17T07:23:17Z", "salary": {"currency": null, "max": null, "min": null, "period": "monthly", "term": null}, "salary_visible": false, "title_keywords": ["accounting clerk"], "responsibilities": ["schedules", "ad-hoc assignments", "analysis", "data input", "bank reconciliations", "transactions", "testing", "implementation", "prepare monthly financial statements", "journal entries", "liaise with", "daily accounting"], "requirements": {"degrees": ["university graduate"], "majors": ["business"], "languages": ["putonghua", "english", "chinese"], "language_level": ["good command", "proficient"], "hard_skills": ["excel", "chinese word processing", "word", "ms office"], "soft_skills": ["communication and interpersonal skills"], "languages_combined": [{"language": "putonghua", "language_level": []}, {"language": "english", "language_level": ["good command"]}, {"language": "chinese", "language_level": ["proficient"]}]}, "experience_required": {"duration": ["2 years"], "field": ["accounting experience"]}}, {"job_id": "100003009054827", "location_code": "hk", "company": "The English Schools Foundation", "job_title": "HR and Finance Assistant - Quarry Bay School", "description": "Quarry Bay School is now looking for a HR & Fiance Assistant to join the team.\nResponsibilities:\n\nThe HR & Finance Assistant assists in HR & Accounting tasks under the supervision of the HR & Finance Officer.\nUndertake accounts payable functions\nUndertake petty cash records\nAssist with procurement and related matters\nAssist with Freelance Service Provider agreement process\nAssist with Fixed Asset records and perform annual count\nOther assigned HR and Finance related tasks\nPerform other duties as directed by the HR & Finance Officer/Principal\nCompetencies required:\nGood command of written and spoken English and Chinese\nProficient with MS Excel and Word\nReliability and detail-oriented\nRequirements\nBasic accounting knowledge\nRelevant experience\nApplicants must be a permanent Hong Kong resident or possess a valid visa to work in Hong Kong.\nClosing Date:\u00a016th January 2022\nFor enquiries, please contact Doris Wong at +852 25664242 via \"Apply Now\".\nApplications will be reviewed on a rolling basis and offers may be extended prior to the job closing date.\nBy applying for this position, your application may be considered for other opportunities within ESF.\nESF is an Equal Opportunities Employer\nPersonal data provided by job applicants will be used strictly in accordance with the ESF's Personal Data Policy, a copy of which will be provided upon request.\nAligned with the recommendations of the International Task Force on Child Protection, we hold ourselves to a high standard of effective recruiting practices with specific attention to child protection.\nsupportstaff\nsupportstaffhki", "employment_types": ["Full Time", "Permanent"], "selling_points": ["Undertake accounts payable functions", "Assist with procurement and related matters", "Basic accounting knowledge"], "locations": ["Not Specified"], "categories": ["Accounting", "Accounting Clerk / Supervisor", "Financial Analyst", "Admin & HR", "HR Supporting Staff"], "post_time": "2022-01-17T11:26:30Z", "salary": {"currency": null, "max": null, "min": null, "period": "monthly", "term": null}, "salary_visible": false, "title_keywords": ["hr", "finance assistant"], "responsibilities": ["hr", "perform other duties", "accounts payable"], "requirements": {"degrees": [], "majors": [], "languages": [], "language_level": [], "hard_skills": ["basic"], "soft_skills": [], "languages_combined": []}, "experience_required": {"duration": [], "field": ["relevant experience"]}}, {"job_id": "100003009050961", "location_code": "hk", "company": "DHL EXPRESS (HONG KONG) LIMITED", "job_title": "Financial Analyst, Aviation, Asia Pacific", "description": "Working Location: Chek Lap Kok\n\nReporting to the Senior Manager, Accounting & Controlling, Aviation, Asia Pacific, this is a regional role responsible for optimizing cash flow, generating accurate and fair monthly aviation cost and revenue reports as well as produce trend analyses for Asia Pacific region as and when required.\n\nFinancial Accounting\n\nVerifying all invoices against contracts, closely communicate with vendors / suppliers on invoicing issues\nHandling and monitoring timely AP payments\nPreparing payment journals in SUN system\nPreparing monthly journals for dedicated air costs, accruing for incurred costs not invoiced accurately and timely\n\nFinancial Analysis and Reporting\n\nPreparing monthly reports and analyses on Air Capacity Sales revenue and kilos\nAnalyzing month to month variance on dedicated air costs\nProvide route cost performance analysis on AP network flights\nAd hoc trend analyses when required\n\nBudgeting and Forecasting\n\nSupporting budget planning and forecasting mainly on dedicated air costs\nAssisting the team to submit budget to Global Finance on time\n\nCompliance\n\nAssist the Senior Manager in monitoring internal control procedure in accordance with Company compliance policy\n\nAd-hoc Analytical Support (for Network Planning and Commercial)\n\nProvide analytical support to assist business decisions\n\nRequirements\n\nDegree in Finance/Accounting or related discipline\n1 to 3 years of work experience in accounting\nWork experience in Aviation industry or Express / Logistics industry will be an advantage\nStudent member / Qualified member of HKICPA or equivalent would be a plus\nGood knowledge of accounting standards\nGood communication skills in both English and Chinese (Cantonese and Mandarin)\nProficient in using MS Excel and PowerPoint\nBe independent, detailed and efficient\nAble to work under pressure and meet all deadlines assigned\nApplication:\nClick \"Apply Now\" or apply on line via the following link: https://dhlexpress.taleo.net/careersection/ex/jobdetail.ftl?job=210091Z&iniurl.src=CWS-10001&tz=GMT%2B08%3A00&tzname=Asia%2FShanghai\nPersonal Information Collection Statement pertaining to Recruitment\nDHL Express (Hong Kong) Limited / DHL Aviation (Hong Kong) Limited (\u201cDHL\u201d) is committed to protecting and respecting your privacy in accordance with the Personal Data (Privacy) Ordinance of Hong Kong (the \u201cOrdinance\u201d) and DHL\u2019s Personal Data Protection Policy (the \u201cPolicy\u201d) at https://www.dhl.com/hk-en/home/footer/local-privacy-notice.html\nBy proceeding to respond to this recruitment advertisement, you consent that we may use, retain, process, transfer or otherwise handle the personal data that we collect from you for recruitment,\u00a0 application processing, assessment and communication purposes (including any other purposes directly related thereto) in accordance with the Policy.\nAll personal data of unsuccessful applicants will be retained for future recruitment purposes for a period of not more than two (2) years after which such data will be destroyed.\nYou have the right at any time to make a data access or correction request concerning your personal data held by us. In addition, you may request us to delete your personal data that is no longer required for the relevant purposes which you have given consent. Should you wish to exercise such rights or have any question in relation to your personal data or the Policy, please contact our Human Resources Division in writing\u00a0", "employment_types": ["Full Time", "Permanent"], "selling_points": ["Degree in Finance/Accounting or related discipline", "1 to 3 years of work experience in accounting", "Handling and monitoring timely AP payments"], "locations": ["Lantau Island"], "categories": ["Accounting", "Finance / Accounting Manager", "Financial Analyst", "Others"], "post_time": "2022-01-14T12:07:28Z", "salary": {"currency": null, "max": null, "min": null, "period": null, "term": null}, "salary_visible": false, "title_keywords": ["financial analyst"], "responsibilities": ["ad-hoc", "monthly reports", "data", "budgeting", "budget", "communication", "payment", "personal data", "costs", "internal control", "ap", "work under pressure", "budget planning", "ad hoc", "invoices", "contracts", "compliance", "reports", "logistics", "forecasting", "reporting", "cost", "monitoring", "cash flow", "contact", "communicate with", "analysis", "invoicing", "financial analysis", "payments", "recruitment", "planning"], "requirements": {"degrees": ["degree"], "majors": ["finance", "accounting"], "languages": ["cantonese", "english", "chinese", "mandarin"], "language_level": ["good"], "hard_skills": ["ap", "plus", "no", "analysis", "powerpoint", "html", "financial analysis", "make", "ms excel", "processing", "internal control", "hkicpa"], "soft_skills": ["efficient", "communication skills", "independent", "responsible", "work under pressure", "timely", "communication", "committed", "accurate", "detailed"], "languages_combined": [{"language": "cantonese", "language_level": ["good"]}, {"language": "english", "language_level": ["good"]}, {"language": "chinese", "language_level": ["good"]}, {"language": "mandarin", "language_level": ["good"]}]}, "experience_required": {"duration": ["1 to 3 years"], "field": ["logistics industry", "accounting"]}}, {"job_id": "100003009054503", "location_code": "hk", "company": "Pathos Consultancy Limited", "job_title": "Assistant Accountant / Accountant, 23-27K, 2-year contract", "description": "Job Responsibilities:-\n\n\nPrepare companies for fund raising and/or IPO by analyzing their financial information, preparing financial projections and assisting them in preparing financial and management accounts;\nConduct financial due diligence potential acquisition targets by collecting detailed information and conducting interviews; collate, analyze the information and prepare a detailed due diligence report;\nBe the acting CFO of a client; prepare and review monthly/quarterly consolidated financial information; manage cash position, cashflow projection; analyze and compare company forecasts and budgets;\nWork with a team of professionals, auditors, financial advisors, valuers and lawyers to perform consulting/advisory projects; and\nAssist in compliance including company secretarial matters for private companies in Hong Kong; cross-border company setup and transactions in Hong Kong & China.\n\u00a0\n\nJob Requirements: -\n\nBachelor degree or above in Accounting or Finance, (HKICPA, CIA or ACCA preferred);\nAt least 2-years relevant working experience;\nGood grasp of Microsoft Office applications such as excel and powerpoint;\nGood communication and presentation skills and sense of servicing awareness;\nGood command in English and Mandarin (listening, oral, reading and writing)\u00a0is a must; good communication and presentation skills in English and Mandarin.\nExperience in using Xero, CRM applications (such as ZOHO) is a plus.\nApplicants with international background preferred;\nEntrepreneurial\u00a0mindset, intellectual curiosity, structured thinking, innovative, and\u00a0embraces change and disruption;\nHonest, reliable, responsible, focus on teamwork, open minded, willing to learn;", "employment_types": ["Full Time", "Contract"], "selling_points": ["3-5 years accounting experience", "SAP", "Accountant"], "locations": ["Central"], "categories": ["Accounting", "Accountant", "Accounting Clerk / Supervisor", "Financial Analyst"], "post_time": "2022-01-17T09:49:03Z", "salary": {"currency": null, "max": null, "min": null, "period": "monthly", "term": null}, "salary_visible": false, "title_keywords": ["accountant", "assistant accountant"], "responsibilities": ["due diligence", "management", "budgets", "consulting", "review", "compliance", "transactions", "conducting interviews", "setup", "report"], "requirements": {"degrees": ["degree or above", "bachelor"], "majors": ["finance", "accounting"], "languages": ["english", "mandarin"], "language_level": ["good command", "good"], "hard_skills": ["excel", "acca", "plus", "microsoft office", "xero", "powerpoint", "focus", "hkicpa"], "soft_skills": ["oral", "responsible", "teamwork", "willing to learn", "communication", "presentation skills", "reliable", "honest", "structured", "open minded", "focus", "innovative"], "languages_combined": [{"language": "english", "language_level": ["good command", "good", "good"]}, {"language": "mandarin", "language_level": ["good command", "good", "good"]}]}, "experience_required": {"duration": [], "field": ["relevant working experience"]}}, {"job_id": "100003009054839", "location_code": "hk", "company": "Hong Kong Parkview", "job_title": "Accountant - Hong Kong Parkview Group", "description": "The Company\nA multinational technology company is hiring an Assistant Accountant / Accountant, fresh graduate will be considered as an Accounting Assistant.\u00a0\n\nThe Role\n\n\nReport to Finance Manager\nRegional role, support month-end closing for regional office\nAssist in financial analysis, such as costing analysis and budgeting\nParticipate in ad hoc projects\u00a0\n\nYour Profile\n\n\nHigher holder\n3-5 years accounting experience\nSAP is an advantage\u00a0\n\nApply Today\nTo apply online (Word attachment only), please click the 'Apply' button. Interested parties please apply with the most updated CV with expected salary and available date via JobsDB. Applicants who do not hear from us within 2 weeks may consider their applications unsuccessful.\u00a0\n\nAbout Pathos\nWe are Pathos Consultancy Limited, a boutique recruitment firm based in Hong Kong strategically placing our candidates across all levels in permanent, temporary and contract roles.\u00a0 We specialize in IT and finance roles for banking, financial services and listed MNC sectors.", "employment_types": ["Full Time", "Permanent"], "selling_points": ["Conduct basic accounting system maintenance", "Support in ad-hoc duties", "At least 4 years audit / accounting experience"], "locations": ["Wan Chai Area"], "categories": ["Accounting", "Accountant", "Audit", "Financial Analyst"], "post_time": "2022-01-17T11:37:40Z", "salary": {"currency": null, "max": null, "min": null, "period": "monthly", "term": null}, "salary_visible": false, "title_keywords": ["accountant"], "responsibilities": ["budgeting", "financial analysis", "month-end closing", "ad hoc projects", "costing analysis", "report"], "requirements": {"degrees": ["fresh graduate"], "majors": ["accounting"], "languages": [], "language_level": [], "hard_skills": ["financial analysis", "analysis", "word", "sap"], "soft_skills": [], "languages_combined": []}, "experience_required": {"duration": ["3-5 years"], "field": ["accounting experience"]}}, {"job_id": "100003009049515", "location_code": "hk", "company": "Getz Bros. & Co. (Hong Kong) Limited", "job_title": "Financial Analyst/Accountant (New Position)", "description": "Duties and Responsibilities\nResponsibilities:\nAssist in daily accounting operations for the Hong Kong Parkview Group.\nHandle full set of accounts, financial analysis and management reports.\nConduct basic accounting system maintenance.\nSupport in ad-hoc duties.\nRequirements:\nHigher Diploma or Degree holder in Accounting or related discipline; member of HKICPA or equivalent is preferrable\nAt least 4 years audit / accounting experience.\nWell versed with MS Excel.\nGood command of spoken and written English, Cantonese and Putonghua.\nWe offer competitive remuneration package including 5-day work week, family medical plan, duty meal and free shuttle bus (to and from Central, Admiralty, and Aberdeen; to Causeway Bay and Wanchai) and excellent career opportunities to the right candidate. \u00a0\nPlease send full resume, expected salary and contact telephone number to\nHong Kong Parkview\nHuman Resources Department\n88 Tai Tam Reservoir Road, Hong Kong\nConfidential Fax No. 28123490\nEmail via \"Apply Now\"\n\n(All data collected will be used for recruitment purpose only)", "employment_types": ["Full Time", "Permanent"], "selling_points": ["5-day work, Competitive Pay and Benefits", "3-5 years auditing/accounting experiences", "Immediate availability is highly preferred"], "locations": ["Kwai Tsing Area"], "categories": ["Accounting", "Accountant", "Audit", "Financial Analyst"], "post_time": "2022-01-14T08:47:35Z", "salary": {"currency": null, "max": null, "min": null, "period": "monthly", "term": null}, "salary_visible": false, "title_keywords": ["accountant", "financial analyst"], "responsibilities": ["maintenance", "full set of accounts", "daily accounting operations", "financial analysis", "management reports", "ad-hoc duties"], "requirements": {"degrees": ["diploma", "degree holder"], "majors": ["accounting"], "languages": ["cantonese", "putonghua", "english"], "language_level": ["good command"], "hard_skills": ["no", "ms excel", "hkicpa"], "soft_skills": [], "languages_combined": [{"language": "cantonese", "language_level": ["good command"]}, {"language": "putonghua", "language_level": ["good command"]}, {"language": "english", "language_level": ["good command"]}]}, "experience_required": {"duration": ["at least 4 years"], "field": ["accounting experience", "audit"]}}, {"job_id": "100003009054697", "location_code": "hk", "company": "Lane Crawford (Hong Kong) Limited", "job_title": "Accounting Officer", "description": "Responsibilities:\u00a0\u00a0\u00a0\n\nProduce the monthly and quarterly Group financial reporting, management reporting and financial analysis;\nPerform daily accounting function;\nParticipate in annual budget preparation, financial analysis and forecasting;\nLiaise with external auditors, professional parties;\nAssist Finance Manager/Financial Controller to perform ad hoc projects\n\n\u00a0Requirements:\n\nDegree in Accountancy or related disciplines;\n3-5 years\u00a0auditing/accounting experiences;\nFamiliar with computerized accounting system and software, eg. ERP or POS;\nSuperior knowledge of MS Excel;\nDetail-minded, proactive, independent, under pressure and meet tight deadline;\nGood command of both spoken and written in Cantonese, English and Mandarin;\nImmediate availability is highly preferred\n\nWe are equal opportunity employer with good work environment. We offer attractive salary, training opportunity, and staff purchase discount. Please send your application with resume and expected salary to HR Department, Office Tower 8/F, 807-811, Hutchison Logistics Centre, 18 Container Port Road South, Kwai Chung or send your application by clicking \u201cApply Now\u201d.\n\n\nAll applications will be treated in strict confidence and all personal data collected will be used for recruitment purposes only.", "employment_types": ["Permanent"], "selling_points": ["Accounts Payable experience in Retail", "Strong communication and collaboration", "immediately available is preferred"], "locations": ["Southern Area"], "categories": ["Accounting", "Accounting Clerk / Supervisor", "Financial Analyst", "Others"], "post_time": "2022-01-17T10:37:23Z", "salary": {"currency": null, "max": null, "min": null, "period": null, "term": null}, "salary_visible": false, "title_keywords": ["accounting officer"], "responsibilities": ["annual budget preparation", "financial analysis", "ad hoc projects", "management reporting", "financial reporting", "liaise with", "daily accounting", "forecasting", "external auditors"], "requirements": {"degrees": ["degree"], "majors": ["related disciplines", "accountancy"], "languages": ["cantonese", "english", "mandarin"], "language_level": ["good command"], "hard_skills": ["pos", "ms excel", "accounting system", "erp"], "soft_skills": ["detail-minded", "independent", "under pressure", "meet tight deadline", "proactive", "superior"], "languages_combined": [{"language": "cantonese", "language_level": ["good command"]}, {"language": "english", "language_level": ["good command"]}, {"language": "mandarin", "language_level": ["good command"]}]}, "experience_required": {"duration": ["3-5 years"], "field": ["accounting"]}}, {"job_id": "100003009053248", "location_code": "hk", "company": "APEC Group International Limited", "job_title": "Management Trainee (Fresh graduates are welcomed)", "description": "Job Purpose:\u00a0\n\n\u201cTo coordinate and perform administrative support duties to the Enterprise and Product team.\u201d\n\nKey Accountabilities:\n\nIn addition to following Lane Crawford\u2019s policies and procedures, key accountabilities include, but are not limited to:\n\nAccount Management (30%)\n\nFunction as key contact to Product team seeking to onboard a new supplier\nResponsible for vendor account creation through supplier portal and oracle systems\nFollow through with vendors on required documentations including trademark registration\nCoordinate with the Legal team to walkthrough and solicit suppliers to accept portal for Essential terms\n\nCommunication (40%)\n\nLead as the central point of contact for suppliers in communicating policies and guidelines on :\nLegal \u00a0\u00a0\u00a0\u00a0\u00a0\u00a0\u00a0\u00a0\u00a0\u00a0\u00a0\u00a0\u00a0\u00a0\u00a0\u00a0\u00a0 \u00a0\u00a0\u00a0\u00a0\u00a0\u00a0\u00a0\u00a0\u00a0\u00a0\u00a0\u00a0\u00a0 (Essential business terms)\nLogistics \u00a0\u00a0\u00a0\u00a0\u00a0\u00a0\u00a0\u00a0\u00a0\u00a0 \u00a0\u00a0\u00a0\u00a0\u00a0\u00a0\u00a0\u00a0\u00a0\u00a0\u00a0\u00a0\u00a0 (Shipping reference and Invoice guide, China Customs)\nAccount Payable\u00a0\u00a0\u00a0\u00a0\u00a0\u00a0\u00a0\u00a0\u00a0\u00a0 (Invoice and payment procedures)\nSupport in answering enquiries from suppliers\nCoordinate with other teams to ensure timely and quality responses to enquiries\nWork with Account Payable to manage invoicing, timely payments, resolve discrepancies and issues,\u00a0 correspond with vendors and respond to payment-related inquiries\n\n\u00a0Process Management\n\nDevelop procedures, guidelines and tools to achieve efficiency\nPlan and develop special project and system enhancement to support service quality standards\nEnsure compliance with Policies and Procedures\n\nRequirements:\n\n\n*Candidates with immediate availability is required*\nAt least 3 years of Accounts Payable working experience in Retail industry\nGood understanding of Trade invoices payment process\nStrong communication skills as need to deal with buying team and multiple vendors\nGood coordination skills and team player\nFamiliar with Oracle Accounting System is not essential but a plus\nBachelor's Degree or any equivalent qualification in Finance or Accounting\n", "employment_types": ["Full Time", "Permanent"], "selling_points": ["Higher Diploma or above in Accounting", "Fresh graduates are welcomed", "Flexible working pattern"], "locations": ["Sheung Wan"], "categories": ["Accounting", "Accountant", "Consulting", "Financial Analyst"], "post_time": "2022-01-17T06:31:43Z", "salary": {"currency": null, "max": null, "min": null, "period": "monthly", "term": null}, "salary_visible": false, "title_keywords": ["management trainee"], "responsibilities": ["shipping", "quality", "communication", "payment", "plan", "invoices", "teams", "develop", "logistics", "management", "administrative support", "invoice", "procedures", "coordinate with", "contact", "guidelines", "policies", "systems", "ensure compliance", "coordinate", "invoicing", "payments", "payment process", "coordination", "accounts payable"], "requirements": {"degrees": ["degree", "bachelor"], "majors": ["finance", "accounting"], "languages": [], "language_level": [], "hard_skills": ["plus", "vendor", "accounting system", "documentations", "oracle"], "soft_skills": ["communication skills", "coordination skills", "responsible", "timely", "communication", "team player"], "languages_combined": []}, "experience_required": {"duration": ["at least 3 years"], "field": ["retail industry"]}}, {"job_id": "100003009054003", "location_code": "hk", "company": "Hang Lung Properties Limited", "job_title": "Accountant (China Reporting)", "description": "Job Highlights:\n\n\u00a05-day work week\n\u00a0Flexible working pattern\n\u00a0Excellent career path to management level\n\n\u00a0Description:\n\nThe trainee will be provided a professional training program including one-to-one coaching and mentoring for financial consultation service including: -\u00a0\n\nRisk Management\nFinancial Advisory Services\nFinancial Management\nI.T. Services and Solutions\nCloud Financial Services\n\nIn order to be trained as one of the most talented professional in the financial sector, the trainees will be undergoing a rotation to explore the mentioned sector in both theoretical and practical way.\n\n\u00a0Requirements:\n\nHigher Diploma or above in Accounting or related disciplines;\nFresh graduates are welcomed\n0 to 1 year of accounting or audit experience in any field is an advance;\nProficient in MS Word & Excel experience is highly preferred;\nBe responsible, communicate well with people at all levels;\nHard working & willing to learn;\nStrong desire to take challenges and make success on career life;\nGood command of both written and spoken English and Chinese; and\nImmediately available is preferred.\n\nWhat we offered?\n\n5-day work week\nImportant festivals early leave\nOvertime meal allowance\nDiscretionary bonus\nFull-paid sick leave\nStudy & Exam leave\nGraduation leave\nWedding leave\nCompassionate leave\nMedical Insurance Scheme\nTraining reimbursement\nInterested parties please send your full resume with your\u00a0working experience, academic and professional qualification, expected salary, and date of availability\u00a0to HR Department.\nPersonal data collected will be used for recruitment purpose only.", "employment_types": ["Full Time", "Permanent"], "selling_points": ["Knowledges of Mainland Accounting & Taxation", "Experience in Big Four CPA firm", "Familiar with Oracle and Yonyou"], "locations": ["Mong Kok"], "categories": ["Accounting", "Accountant", "Financial Analyst"], "post_time": "2022-01-17T08:39:09Z", "salary": {"currency": null, "max": null, "min": null, "period": null, "term": null}, "salary_visible": false, "title_keywords": ["accountant"], "responsibilities": ["management"], "requirements": {"degrees": ["higher diploma or above"], "majors": ["related disciplines", "accounting"], "languages": ["english", "chinese"], "language_level": ["good command"], "hard_skills": ["excel", "make", "ms word"], "soft_skills": ["hard working", "willing to learn", "responsible"], "languages_combined": [{"language": "english", "language_level": ["good command"]}, {"language": "chinese", "language_level": ["good command"]}]}, "experience_required": {"duration": ["0 to 1 year"], "field": ["audit experience", "accounting"]}}, {"job_id": "100003009045406", "location_code": "hk", "company": "Charterhouse Limited", "job_title": "Regional Financial Analyst", "description": "Responsibilities\u00a0\u00a0\n\nDeliver the monthly management and analysis reports of the Group\nEngage in budgeting and long term financial planning\nPromote standardization of the Group accounting and financial policies/ procedures\nSupport resolving financial and accounting issues of the Group companies in Mainland China\nSupport annual audit/interim review and results announcements\nWork on ad-hoc assignments as required\n\n\u00a0Requirements\n\nDegree in Accounting, Finance or related discipline and member of HKICPA or equivalent\nAt least 5 years of solid experience in listed sizable organization\nCandidate with experience in Big Four CPA firm is definitely an advantage\nSound knowledge of Mainland China accounting, taxation and regulations are essential\nAnalytical mind with ability to work in fast paced environment\nStrong communication and interpersonal skills\nGood command of spoken and written English and Chinese; proficiency in Mandarin is a must\nFamiliar with Oracle and Yonyou is highly preferred", "employment_types": ["Full Time", "Permanent"], "selling_points": ["Dynamic working environment", "Excellent remuneration package", "MNC Culture"], "locations": ["Not Specified"], "categories": ["Accounting", "Financial Analyst"], "post_time": "2022-01-13T07:47:31Z", "salary": {"currency": null, "max": null, "min": null, "period": "monthly", "term": null}, "salary_visible": false, "title_keywords": ["regional financial analyst"], "responsibilities": ["management", "annual audit", "analysis reports", "budgeting", "ad-hoc assignments", "financial policies", "procedures", "review", "planning"], "requirements": {"degrees": ["degree"], "majors": ["finance", "accounting"], "languages": ["english", "chinese", "mandarin"], "language_level": ["proficiency", "good command"], "hard_skills": ["cpa", "oracle", "hkicpa"], "soft_skills": ["analytical mind", "communication and interpersonal skills"], "languages_combined": [{"language": "english", "language_level": ["good command"]}, {"language": "chinese", "language_level": ["good command"]}, {"language": "mandarin", "language_level": ["proficiency"]}]}, "experience_required": {"duration": ["at least 5 years"], "field": ["sizable organization", "cpa firm", "big four"]}}, {"job_id": "100003009054459", "location_code": "hk", "company": "Zext intelligence Limited", "job_title": "Portfolio Management Trainee/ Manager (Fresh Grad, 18K-30K+)", "description": "Our client is a Listed group,\u00a0 Current they are looking for potential candidate to join their Finance team in Hong Kong.\n\nResponsibilities;\n\nReport to Head of Finance (General Account & Finance Analysis);\nTo\u00a0Lead a small team of Finance Operation Team in Hong Kong;\n\nHandle full set of account including operaton /finance analysis/ management account etc;\nTo perform and lead the accounting process and procedure, ensuring compliance with the accounting policies and guidelines;\nLead and coaching to a small team to manage accounting reporting & reporting;\nGood communcation with English and Chinese is must.\nRequirements:\n\nDegree or Above in Accounting or related discipline;\n\nHolder of CPA professional qualification and experience in 4A CPA Firm is a plus;\nAbout 8+\u00a0 years working experience in Full set of accounting and Management Accounting;\nExperience in Multi-national group is preferred;\nSolid Experience in Asia Pacific Trading Business is preferred;\nGood experience in dealing with various country business user;\nUsing software with MS Office (Execl, Word, Powerpoint) and Oracle Finance is a plus;\nExcellent spoken and written communication skill in English;\nWork independently and good team leadership.\nOur client will offer competitive remuneration package and good career prospects to the potential candidate, interested parties please quote ref.no.FM-0117-sh-JDB and submit your resume to Ms Fung by our email or enquiry with Tel:3428-6121.\n\n\nAll profiles are handled with strictest confidentiality. Shortlisted candidates would be notified", "employment_types": ["Full Time", "Permanent"], "selling_points": ["on the job training, continuous studying subsidy", "Double pay, Performance Bonus and incentives", "Trained to be part of the management in 2 years"], "locations": ["Quarry Bay"], "categories": ["Accounting", "Financial Analyst", "Management", "Management Trainee", "Banking / Finance", "Asset Management"], "post_time": "2022-01-17T09:38:09Z", "salary": {"currency": null, "max": null, "min": null, "period": "monthly", "term": null}, "salary_visible": false, "title_keywords": ["management trainee", "manager"], "responsibilities": ["reporting", "management", "guidelines", "analysis", "compliance", "lead a small team", "accounting policies", "report"], "requirements": {"degrees": ["degree or above"], "majors": ["accounting"], "languages": ["english"], "language_level": ["excellent"], "hard_skills": ["plus", "oracle", "word", "powerpoint", "cpa", "ms office"], "soft_skills": ["work independently", "communication skill", "leadership"], "languages_combined": [{"language": "english", "language_level": ["excellent"]}]}, "experience_required": {"duration": [], "field": ["management accounting", "cpa firm", "business", "accounting", "trading"]}}, {"job_id": "100003009043869", "location_code": "hk", "company": "S.F. Express (Hong Kong) Limited", "job_title": "Financial Analyst", "description": "The Employer:\n\nOur client is one of the major financial institution in Hong Kong. They are aggressive and innovative, and fast growing.\u00a0 They would like to expand the market share by investing their resources on the right talents.\n\nPortfolio Management Trainee Program\n\nThe employer looks for young talented individuals to join their Portfolio Manegement trainee program. The program is designed to prepare candidates to for further advancement in investment teams including fundamental research, investment consultation, and trading funds. Experienced candidates will be considered as the Portfolio Manager.\n\nThrough the program, trainee will be given various projects such as premium financing, refinancing or investment analysis. He/she will work closely with mentor from portfolio managers to business managers in each project. He/she will also participate in day to day portfolio management and have early access to global financial market.\n\nThe Role and Responsibilities:\n\nComprehensive on-the-job training regarding professional investment and asset management expertise.\nPreparing investment portfolio and global market analysis.\nTo develop investment strategies to achieve client\u2019s short-term and long-term financial objectives.\nOn going manage client\u2019s portfolios according to client\u2019s financial goals.\nPreparing different scheme of investment proposal and portfolio review report.\nIdentify client objectives and offer appropriate financial consultancy.\n\nRequirements:\n\nBachelor degree holder or above in all disciplines\nInitiative, sincere and a good team player\nProficiency in Chinese and English\nGood communication and interpersonal skills\nArticulate and detail oriented, ability to multitask in a fast paced environment.\u00a0\n\n\n\nWe offer a competitive salary and benefits package and the professional advantages of a dynamic environment that supports your development and recognizes your achievements.\n\nInterested individuals please send your detailed resume and expected salary by clicking\u00a0\"Apply Now\". Only candidates who are authorized to work in Hong Kong will be considered.\n\nAll personal data provided will only be used for recruitment purpose only.\nInformation of candidates not selected will be destroyed in 3 months.", "employment_types": ["Full Time", "Permanent"], "selling_points": ["Free shuttle bus coverage", "2 months or above performance bonus", "Attractive basic salary"], "locations": ["Tsing Yi"], "categories": ["Accounting", "Accountant", "Accounting Clerk / Supervisor", "Financial Analyst"], "post_time": "2022-01-13T02:15:15Z", "salary": {"currency": null, "max": null, "min": null, "period": "monthly", "term": null}, "salary_visible": false, "title_keywords": ["financial analyst"], "responsibilities": ["investment strategies", "preparing investment portfolio", "global market analysis", "develop", "investment proposal", "portfolio review report", "manage client\u2019s portfolios", "asset management"], "requirements": {"degrees": ["bachelor degree holder"], "majors": [], "languages": ["english", "chinese"], "language_level": ["proficiency"], "hard_skills": ["dynamic"], "soft_skills": ["good team player", "dynamic environment", "sincere", "detail oriented", "communication and interpersonal skills", "articulate", "ability to multitask", "initiative", "detailed"], "languages_combined": [{"language": "english", "language_level": ["proficiency"]}, {"language": "chinese", "language_level": ["proficiency"]}]}, "experience_required": {"duration": [], "field": []}}, {"job_id": "100003009050153", "location_code": "hk", "company": "Magic Search Limited", "job_title": "Accountant (Luxury Brand) (3 Months Contract)", "description": "This position will focus primarily on reporting and analysis for the organization. The ideal candidate is very motivated and willing to take on challenges, multi-task to succeed, and can work independently and with minimal oversight. This role will be responsible for financial analysis, developing reports, designing forecast templates, and analyzing data. Act as a liaison to multiple internal workgroups and other business units.\n\nResponsibilities\n\nAssist in the annual budget\nPrepare monthly rolling P&L forecast and variance analysis. Follow up on the achievement of P&L targets.\nDevelop a product costing model, product margin analysis, OPEX analysis, KPI monitoring\nWork with IT to improve reporting processes and develops effective\u00a0reporting tools for users.\nPrepare presentations and visual aids to help illustrate data in ways that are appropriate to the audience. Present information in an easy-to-understand communication approach including oral presentations and written communications.\nAssist Finance Manager/Finance Director in the preparation of ad-hoc analysis and management report\n\nRequirements:\n\nBachelor Degree in Finance or Accounting or related discipline\nMinimum 5 years\u2019 experience in finance and accounting functions, preferably in management accounting\nAble to work in a fast-paced, dynamic environment\nExperience in Logistic company is a plus\nResponsible, detail-minded, strong analytical, work with a team on tight deadlines\nGood command of written and spoken English, Cantonese, and Mandarin\nProficiency in MS Excel and PowerPoint, experience in handling SAP is a plus\nCandidate with less experience will be considered as Assistant Financial Analyst\n\nWe offer attractive remuneration package and fringe benefits to the right candidates. Interested parties please submit your application to us. If you do not want to apply as JobsDB member, you may send your full resume with your availability, current and expected salaries to recruit01 at sf-express.com.\n\nYou are welcome to visit our website at\u00a0https://htm.sf-express.com/hk/tc/\u00a0for more information about us.\n\nCandidates who are not invited for interview within 1-month may consider their applications unsuccessful.\n\nAll personal data provided by job applicants will be used only for recruitment purpose and will be treated strictly confidential. Unsuccessful applications will be retained for a maximum period of 24-month.", "employment_types": ["Temporary", "Contract"], "selling_points": ["Accountant", "4 years relevant working experience", "3 Months Contract"], "locations": ["Not Specified"], "categories": ["Accounting", "Accountant", "Finance / Accounting Manager", "Financial Analyst"], "post_time": "2022-01-14T09:53:04Z", "salary": {"currency": null, "max": null, "min": null, "period": "monthly", "term": null}, "salary_visible": false, "title_keywords": ["accountant"], "responsibilities": ["ad-hoc", "reporting", "data", "analysis", "budget", "monitoring", "p&l", "develop", "opex", "variance analysis", "presentations", "communication", "forecast", "visual", "management report"], "requirements": {"degrees": ["degree", "bachelor"], "majors": ["finance", "accounting"], "languages": ["cantonese", "english", "mandarin"], "language_level": ["good command"], "hard_skills": ["plus", "sap", "powerpoint", "ms excel", "dynamic"], "soft_skills": ["detail-minded", "dynamic environment", "responsible"], "languages_combined": [{"language": "cantonese", "language_level": ["good command"]}, {"language": "english", "language_level": ["good command"]}, {"language": "mandarin", "language_level": ["good command"]}]}, "experience_required": {"duration": ["minimum 5 years"], "field": ["management accounting", "finance", "accounting", "financial"]}}, {"job_id": "100003009050272", "location_code": "hk", "company": "Hawley and Hazel Asia Investment Company Limited", "job_title": "Assistant Finance Manager", "description": "Our client is a luxury brands distributor that carry wide range of products and expand their business rapidly . Their shops locate in prestigious business area. To cope with their business expansion, they are looking for an\u00a0Accountant to join the team.\n\nKey Responsibilities:\n\nResponsible for month-end closing, accounts reconciliation and journal entries.\nPerform financial management accounting\nPrepare and review management regular & ad-hoc reports and analysis.\nSet out standard procedures and develop internal control guidelines and procedures for improving existing work practices and enhancing the control mechanism.\nPrepare and review tax computation and audit schedules.\nAssist in other daily accounting duties and other ad hoc assignment as required.\n\nRequirements:\n\nDegree holder\u00a0in accountancy or similar discipline, LCC Higher Certificate or partly qualified HKICPA / ACCA.\nMinimum 4 years experience in accounting, retail industry is preferrable.\nGood communication skills, pro-active with strong financial judgment and problem-solving ability.\nAble to perform multi-tasks with prioritization skills, to work under pressure in meeting deadlines and attentive to details.\nPreferably in SAP and proficiency in MS applications (conversant with application of Excel formulas is definite an advantage).\nFluent in both written and spoken English and Chinese\n\nAll information provided will be treated in strict confidence and used solely for recruitment purposes. To apply, please quote current and expected salary and send your CV through \" APPLY NOW\"", "employment_types": ["Full Time", "Permanent"], "selling_points": ["FP&A, Budget, Forcast, Reporting & Compliance", "6 years experience, Big 4 trained preferred", "Exp in FMCG industry, SAP is a plus"], "locations": ["Aberdeen"], "categories": ["Accounting", "Audit", "Finance / Accounting Manager", "Financial Analyst"], "post_time": "2022-01-14T10:03:23Z", "salary": {"currency": null, "max": null, "min": null, "period": "monthly", "term": null}, "salary_visible": false, "title_keywords": ["assistant finance manager"], "responsibilities": ["ad-hoc", "management", "control", "tax computation", "guidelines", "schedules", "analysis", "review", "procedures", "audit", "ad hoc assignment", "develop", "month-end closing", "journal entries", "reports", "daily accounting", "internal control"], "requirements": {"degrees": ["higher certificate", "degree holder"], "majors": ["accountancy"], "languages": ["english", "chinese"], "language_level": ["fluent"], "hard_skills": ["excel", "acca", "ms applications", "sap", "problem-solving", "lcc", "hkicpa"], "soft_skills": ["communication skills", "confidence", "multi-tasks", "attentive to details", "problem-solving", "pro-active", "work under pressure"], "languages_combined": [{"language": "english", "language_level": ["fluent"]}, {"language": "chinese", "language_level": ["fluent"]}]}, "experience_required": {"duration": ["minimum 4 years"], "field": ["retail industry", "accounting"]}}, {"job_id": "100003009047678", "location_code": "hk", "company": "Robert Walters (HK)", "job_title": "Senior/Financial Analyst", "description": "We are looking for an Assistant Finance Manager, Group Budgeting, Planning & Compliance to support the senior manager on driving financial planning and analysis, as well as compliance for the Group.\n\nKey Responsibilites:\n\nResponsible for Group reporting, budgeting and forecasting\nManage financial closing, consolidation and prepare management report packages\nCompile cash flow report and forecast\nPrepare financial analysis on business performance of subsidiaries to support senior management on formulation of corporate strategies and key investment decisions\nEnforce compliance of SOX, finance policies and other governance for the Group.\u00a0Conduct relevant compliance trainings and internal controls testing\nPlan and lead internal audits of subsidiaries and compile audit reports.\nCoordinate external audits for the Group and its subsidiaries in HK and provide feedback to auditor before finalization of audit reports\nManage regional finance projects including development and roll out of new reports, processes and systems\u00a0\nPerform ad-hoc assignments given by line manager\n\nRequirements\n\nBachelor\u2019s Degree in Accounting, Business or related fields\nQualified accountant with full membership in HK or international accounting bodies\nYoung talents with at least 6 years experience in financial planning and reporting, financial accounting\nExperience in\u00a0reputable audit firms and SOX compliance is a definite advantage\nExperience in FMCG industry and multinational companies is preferred\nProficient in\u00a0SAP, BW and Microsoft Office\n\nWork Location : Wong Chuk Hang, Aberdeen\n\n\nWe offer competitive remuneration package and career development opportunity to the right candidate.\u00a0 Interested candidates please submit your resume with present and expected salary and earliest availability to us by clicking the \"APPLY NOW\" button.\u00a0\n\nApplicants who would not be invited for interview within 6 weeks may assume their applications unsuccessful. All applications will be retained for a maximum period of 12 months. All information collected will be used for recruitment and selection purpose and treated confidential.", "employment_types": ["Full Time", "Contract"], "selling_points": ["3 years contract", "FP&A role", "IT PMO experience"], "locations": ["Not Specified"], "categories": ["Accounting", "Financial Analyst"], "post_time": "2022-01-14T03:43:00Z", "salary": {"currency": null, "max": null, "min": null, "period": "monthly", "term": null}, "salary_visible": false, "title_keywords": ["financial analyst"], "responsibilities": ["budgeting", "audit", "plan", "senior management", "compliance", "testing", "reports", "forecast", "forecasting", "management report", "report", "reporting", "cash flow", "audits", "policies", "ad-hoc assignments", "systems", "financial analysis", "coordinate"], "requirements": {"degrees": ["degree", "bachelor"], "majors": ["business", "accounting"], "languages": [], "language_level": [], "hard_skills": ["fmcg industry", "sap", "microsoft office"], "soft_skills": [], "languages_combined": []}, "experience_required": {"duration": ["at least 6 years"], "field": ["fmcg", "financial", "compliance", "audit", "accounting", "planning"]}}, {"job_id": "100003009044105", "location_code": "hk", "company": "WilliamSELECT", "job_title": "Assistant Financial Analyst (APAC) - Retail", "description": "\u00a0 \u00a0 \u00a0 \u00a0 \u00a0 \u00a0Responsibilities\u00a0 :\u00a0\n\nHandle full set of accounts.\nPrepare monthly management reports and comment on variances, if any.\nLiaise with external auditors and tax consultants for the aspects of the financial reporting, tax filing as well as reviewing the profit tax return and computation.\nPrepare budgeting, forecasting and financial analysis.\nAssist in the implementation of accounting system, internal control and policies.\nEvaluate product costing and internal transfer pricing.\nHandle any ad-hoc assignments when necessary\u00a0 \u00a0 \u00a0 \u00a0 \u00a0\n\u00a0 \u00a0 \u00a0 \u00a0 \u00a0 \u00a0Requirements :\u00a0\n\nBachelor\u2019s degree (or equivalent) in accounting, finance, business or related discipline. Obtainment, or current pursuit of, a professional certification\u00a0\nOver 5 year experience in accounting field in trading /manufacturer .\nDevelop and plan assigned audits and projects,\nReview, evaluate and document the maturity of internal controls by performing walk through and testing procedures.\u00a0\nGood speaking both of Cantonese & English,\nGood PC knowledge & Accounting system is an advantage,\nWilling travel to China or Overseas is also required", "employment_types": ["Full Time", "Permanent"], "selling_points": ["FP&A focus", "Budget & Forecast", "Fresh Graduate welcome"], "locations": ["Not Specified"], "categories": ["Accounting", "Accounting Clerk / Supervisor", "Financial Analyst", "Banking / Finance", "Analyst"], "post_time": "2022-01-13T03:04:48Z", "salary": {"currency": null, "max": null, "min": null, "period": "monthly", "term": null}, "salary_visible": false, "title_keywords": ["assistant", "financial analyst"], "responsibilities": ["tax", "budgeting", "policies", "full set of accounts", "tax filing", "implementation", "ad-hoc assignments", "financial analysis", "evaluate", "management reports", "financial reporting", "liaise with", "forecasting", "internal control", "external auditors"], "requirements": {"degrees": ["degree", "bachelor"], "majors": ["business", "finance", "accounting"], "languages": ["cantonese", "english"], "language_level": ["good"], "hard_skills": ["pc knowledge", "accounting system"], "soft_skills": [], "languages_combined": [{"language": "cantonese", "language_level": ["good"]}, {"language": "english", "language_level": ["good"]}]}, "experience_required": {"duration": ["5 year"], "field": ["accounting", "trading"]}}, {"job_id": "100003009022593", "location_code": "hk", "company": "Peak Vision Appraisals Limited", "job_title": "Financial Analyst - Valuation", "description": "My client is a well known retail brand. To expand their finance team, they are looking for an Assistant Financial Analyst to join their team.\n\nResponsibilties:\n\nPrepare annual and monthly management reports for APAC\nPrepare budget and forecast reports to identify risks and improve efficient\u00a0\nConduct P&L variance analysis\nGive analytical support for business decisions\nParticipate in system/process improvement project\nReport to FP&A Manager and assist on ad hoc duties\u00a0\n\nRequirements:\n\nBachelor Degree in Accounting/Finance\u00a0\n1 years relevant experience in accounting/financial analysis, preferably from retail industry\nStrong analytical mind, good communication skill and business sense\nProactive and self motivated\u00a0\nGood command of spoken and written English and Chinese", "employment_types": ["Full Time"], "selling_points": ["Good career prospect", "Degree holder in Accounting, Finance, Surveying", "Friendly working environment"], "locations": ["Wan Chai Area"], "categories": ["Accounting", "Financial Analyst", "Banking / Finance", "Analyst", "Professional Services", "Business Analysis / Data Analysis"], "post_time": "2022-01-12T23:26:05Z", "salary": {"currency": null, "max": null, "min": null, "period": "monthly", "term": null}, "salary_visible": false, "title_keywords": ["financial analyst"], "responsibilities": ["ad hoc duties", "budget", "p&l", "variance analysis", "management reports", "reports", "forecast", "report"], "requirements": {"degrees": ["degree", "bachelor"], "majors": ["finance", "accounting"], "languages": ["english", "chinese"], "language_level": ["good command"], "hard_skills": ["financial analysis"], "soft_skills": ["business sense", "communication skill", "self motivated", "analytical mind", "proactive"], "languages_combined": [{"language": "english", "language_level": ["good command"]}, {"language": "chinese", "language_level": ["good command"]}]}, "experience_required": {"duration": ["1 years"], "field": ["retail industry", "accounting", "relevant experience", "financial"]}}, {"job_id": "100003009053217", "location_code": "hk", "company": "CEMG Management Limited", "job_title": "Accountant", "description": "Financial Analyst - Valuation\u00a0\n\nLocation: Wanchai, Hong Kong\n\nJob Description and Responsibilities:\n\n\u00a0- Conduct company and industry research and analysis\n\u00a0- Assist in performing financial analysis and valuation including business and property valuations\n\u00a0- Draft valuation report\n\u00a0- Assist in organizing and monitoring project progress, liaise with internal and external parties\n\nRequirements:\n\n- Degree holder in Accounting, Finance, Surveying or related disciplines preferred\n- 1 to 2 years relevant experience in valuation or audit would be an advantage\n- Responsible, committed, details oriented, and willing to learn\n- Good computer skills (MS Office, Excel, PowerPoint)\n- Good command of both written and spoken English, Mandarin and Cantonese\n- Good team player with the ability to work independently\n- Able to work under pressure and meet deadline\n- Fresh graduates are welcome\n\nWhat we offer:\n\n- 5 working days per week\n- Attractive remuneration package\n- Good career prospect\n- Medical benefits\n- Friendly working environment\u00a0\n\nInterest parties, please send detailed resume with expected salary to us or by clicking \"Apply Now\"\n\nOur website : https://www.peakval.com\u00a0\n\n(Personal data collected would be used for recruitment purpose only)\n\nPeak Vision Appraisals Limited\n\nWe are a professional appraisal and advisory firm. We offer professional valuation services for M&A, IPO and accounting reference purposes, as well as advise on Environmental, Social and Governance (ESG) reporting. Our clients are mainly listed companies in Hong Kong.", "employment_types": ["Full Time"], "selling_points": ["5 days work and Medical Insurance", "Handle full set of accounts", "University graduate or Higher Accounting(LCC&I)"], "locations": ["Tin Hau"], "categories": ["Accounting", "Accountant", "Accounting Clerk / Supervisor", "Financial Analyst"], "post_time": "2022-01-17T06:27:44Z", "salary": {"currency": null, "max": null, "min": null, "period": "monthly", "term": null}, "salary_visible": false, "title_keywords": ["accountant"], "responsibilities": ["valuation", "analysis", "monitoring", "internal and external parties", "project progress", "financial analysis", "liaise with", "report"], "requirements": {"degrees": ["degree holder"], "majors": ["related disciplines", "finance", "accounting", "surveying"], "languages": ["cantonese", "english", "mandarin"], "language_level": ["good command"], "hard_skills": ["excel", "computer skills", "powerpoint", "ms office"], "soft_skills": ["good team player", "work independently", "responsible", "willing to learn", "committed", "work under pressure"], "languages_combined": [{"language": "cantonese", "language_level": ["good command"]}, {"language": "english", "language_level": ["good command"]}, {"language": "mandarin", "language_level": ["good command"]}]}, "experience_required": {"duration": ["1 to 2 years"], "field": ["relevant experience", "audit"]}}, {"job_id": "100003009047617", "location_code": "hk", "company": "Aurabeat Technology Limited", "job_title": "Financial Analyst - FP&A", "description": "Job Highlights\n\nOversee daily financial operations of the Group\nHandle full set of accounts\n5 days work and Medical Insurance\nUniversity graduate or Higher Accounting(LCC&I) or equivalent\n\nReporting to the Account Manager, you will be responsible for\n\nResponsibilities\n\nAssist in the preparation of accounts and financial reports, including general ledger accounting entries, account receivable, account payable, related party transactions;\nPrepare monthly management reports, budgeting and forecasting;\nPrepare monthly financial report package including profit and loss accounts, statement of financial positions, cash flow statements; analyze and provide commentary on the key accounts;\nPerform periodical physical stock count and variance reconciliation;\nPerform RPT reconciliation and bank reconciliation;\nMaintain proper documentation of financial record;\nPerform ad hoc assignments as required.\n\nRequirements:\n\nUniversity graduate or Higher Accounting (LCC&I) or equivalent\nAudit experience is highly referred\nFluent in Mandarin, Cantonese and English\nProficient in MS office (Excel, Word and Powerpoint)\nTeam player with excellent communication and interpersonal skills\nAble to work independently with a strong sense of\u00a0responsibility, self-motivation and able to meet tight schedules\nExperienced in ERP system implementation is an advantage\nWorking experience in healthcare service industry is an advantage\n\n\n\n\nWe offer a competitive remuneration package including excellent career prospects to the right candidate. Interested parties please click \"Quick Apply\" now.\n\nAll data collected will be used for recruitment purpose only.", "employment_types": ["Full Time", "Permanent"], "selling_points": ["Monthly financial & business performance report", "Annual budget & monthly forecast plan", "3 years experience in FP&A"], "locations": ["Tsuen Wan Area"], "categories": ["Accounting", "Finance / Accounting Manager", "Financial Analyst", "Others"], "post_time": "2022-01-14T03:35:23Z", "salary": {"currency": null, "max": null, "min": null, "period": "monthly", "term": null}, "salary_visible": false, "title_keywords": ["financial analyst"], "responsibilities": ["financial reports", "general ledger", "budgeting", "bank reconciliation", "transactions", "maintain proper documentation", "management reports", "cash flow", "financial report", "ad hoc assignments", "forecasting"], "requirements": {"degrees": ["university graduate"], "majors": ["accounting"], "languages": ["cantonese", "english", "mandarin"], "language_level": ["fluent"], "hard_skills": ["excel", "word", "powerpoint", "erp system", "ms office"], "soft_skills": ["work independently", "sense of responsibility", "communication and interpersonal skills", "self-motivation", "team player", "meet tight schedules"], "languages_combined": [{"language": "cantonese", "language_level": ["fluent"]}, {"language": "english", "language_level": ["fluent"]}, {"language": "mandarin", "language_level": ["fluent"]}]}, "experience_required": {"duration": [], "field": ["healthcare", "audit experience", "service industry"]}}, {"job_id": "100003009054067", "location_code": "hk", "company": "The Tien Chu (Hong Kong) Company Limited", "job_title": "Accounting Manager", "description": "Responsibilities\n\nProvide analytical, forecasting, reporting, and project support to senior management\nBuild and maintain annual and 5-year projections with full assumptions/KPIs\nProduce monthly reports, which include key metrics, financial results, and variance reporting\nSpearhead the annual and quarterly budgeting and forecasting processes\nIdentify opportunities for performance improvement across the organization\nDevelop models that help with decision-making\nAssist in add-hoc tasks\nRequirements\n\nBachelor's degree in Finance, Accounting, or related field; CPA or CFA a plus.\n2-3 years of relevant experience in corporate finance, financial planning & analysis, investment banking, or other related fields.\nStrong working knowledge of Excel and financial modelling\nExcellent analytical, decision-making, and problem-solving skills\nAttention to accuracy and detail required\nSelf-motivated at work, independent and a good team player\nGood command of spoken and written Cantonese, English, Mandarin\nProficient in Chinese word processing is an advantage\nWe offer 5-day work, an attractive remuneration package to the successful candidate. Salary will be commensurate with qualifications and experience. Interested parties please send a detailed resume to our\u00a0Human Resources Department\u00a0by clicking the\u00a0Apply Now\u00a0button.\n\n\n\nWe are an equal opportunity employer. All information collected will be considered strictly confidential and will be used for recruitment purposes only.", "employment_types": ["Full Time", "Permanent"], "selling_points": ["Accountant", "Manufacturing / Trading Company", "Double pay, bonus, free lunch, shuttle, medical"], "locations": ["Tsing Yi"], "categories": ["Accounting", "Audit", "Finance / Accounting Manager", "Financial Analyst"], "post_time": "2022-01-17T08:17:19Z", "salary": {"currency": null, "max": null, "min": null, "period": "monthly", "term": null}, "salary_visible": false, "title_keywords": ["accounting manager"], "responsibilities": ["reporting", "monthly reports", "budgeting", "develop", "maintain", "kpis", "senior management", "forecasting"], "requirements": {"degrees": ["degree", "bachelor"], "majors": ["finance", "accounting"], "languages": ["cantonese", "english", "chinese", "mandarin"], "language_level": ["advantage", "good command", "proficient"], "hard_skills": ["excel", "plus", "chinese word processing", "cfa", "analysis", "cpa", "problem-solving skills"], "soft_skills": ["problem-solving skills", "self-motivated", "independent", "good team player"], "languages_combined": [{"language": "cantonese", "language_level": ["good command"]}, {"language": "english", "language_level": ["good command"]}, {"language": "chinese", "language_level": ["advantage", "proficient"]}, {"language": "mandarin", "language_level": ["good command"]}]}, "experience_required": {"duration": ["2-3 years"], "field": ["financial", "corporate finance", "related", "relevant experience", "investment", "banking", "planning"]}}, {"job_id": "100003009045979", "location_code": "hk", "company": "Hillman Ross", "job_title": "Business Analyst/Senior Business Analyst(Regional)", "description": "Responsibilities :\n\n\n\nPrepare consolidated financial statements and handle monthly closing of group companies\nHandle annual and interim audit review. Liaise with external auditors\nEngage in the publication of interim and annual reports\nPrepare statutory accounts and tax filings\nPerform financial analysis\nAssist in ad-hoc tasks as assigned by management\n\nRequirements:\n\n\n\nDegree holder in Accounting or related disciplines\nQualified Accountant of HKICPA or other recognized professional accounting bodies is advantage\nMinimum of 5 years\u2019 working experience in Manufacturing / Trading Company fields;\nExperience in group consolidation, familiar with PRC accounting and tax practices is an added advantage\nDetail-oriented, well-organized, self-motivated with strong sense of responsibility\nHigh competence in written and spoken English and Chinese; proficiency in Putonghua is an advantage;\nAttention to details and accuracy with strong sense of urgency\n\n\n\nWe offer competitive package to right candidate, including but unlimited double pay, performance bonus, free lunch, shuttle bus, education allowance, housing allowance, Medical and other benefits.\n\nWorking hours : Monday to Friday 9:00am to 5:00pm & Saturday 9:00am to 12:00noon\n\nInterested parties please send full resume in Chinese and English in strict confidence with expected salary & earliest availability to us for interview.\n\nFor more details, please visit www.tienchu.com\n\n(Personal data collected is solely for recruitment related purpose\u00a0and will be treated in strict confidence.)", "employment_types": ["Full Time", "Permanent"], "selling_points": ["Leading Retailer", "Stable Working Environment", "Strong Excel skills"], "locations": ["Not Specified"], "categories": ["Accounting", "Financial Analyst", "Others"], "post_time": "2022-01-13T09:18:53Z", "salary": {"currency": null, "max": null, "min": null, "period": "monthly", "term": null}, "salary_visible": false, "title_keywords": ["business analyst"], "responsibilities": ["tax", "management", "ad-hoc tasks", "review", "audit", "financial statements", "financial analysis", "reports", "liaise with", "publication", "external auditors"], "requirements": {"degrees": ["degree holder"], "majors": ["related disciplines", "accounting"], "languages": ["putonghua", "english", "chinese"], "language_level": ["advantage", "proficiency"], "hard_skills": ["prc accounting", "hkicpa"], "soft_skills": ["self-motivated", "sense of responsibility", "urgency", "well-organized", "detail-oriented", "attention to details"], "languages_combined": [{"language": "putonghua", "language_level": ["proficiency", "advantage"]}, {"language": "english", "language_level": []}, {"language": "chinese", "language_level": []}]}, "experience_required": {"duration": ["minimum of 5 years"], "field": ["manufacturing", "trading", "consolidation", "accounting"]}}, {"job_id": "100003009042865", "location_code": "hk", "company": "Modern Terminals Ltd", "job_title": "Financial Analyst (Contract)", "description": "A renowned Global Retailer is seeking for a Business Analyst/Senior Business Analyst to join their Regional team in Hong Kong.\n\nWe are now seeking for a Business Analyst/Senior Business Analyst(Regional)\n\nRESPONSIBILITIES\n\nPrepare revenue, cost, profit performance, and KPI analysis in multi-dimensions\nResponsible for revenue, cost, profit forecast/ budget, and performance tracking\nPresent financial analysis report on sales, brands and P&L to management\nOther ad hoc analyses as assigned\n\nQUALIFICATIONS\n\nDegree holder in Finance and Accounting or related disciplines\nMin 5 years of relevant experiences in Retail/FMCG/Consumer Goods related companies\nExcellent skill in Excel, Access and PowerPoint\nKnowledge in VBA is highly preferred\nStrong analytical and communication skills\nProficiency in written and spoken English, Cantonese and Mandarin", "employment_types": ["Full Time", "Contract"], "selling_points": [], "locations": ["Kwai Tsing Area"], "categories": ["Accounting", "Audit", "Financial Analyst", "Banking / Finance", "Analyst"], "post_time": "2022-01-12T09:18:30Z", "salary": {"currency": null, "max": null, "min": null, "period": "monthly", "term": null}, "salary_visible": false, "title_keywords": ["financial analyst"], "responsibilities": ["cost", "management", "ad hoc", "analysis", "budget", "p&l", "financial analysis", "communication", "forecast", "report", "tracking"], "requirements": {"degrees": ["degree holder"], "majors": ["related disciplines", "finance", "accounting"], "languages": ["cantonese", "english", "mandarin"], "language_level": ["proficiency"], "hard_skills": ["excel", "vba", "analysis", "powerpoint", "financial analysis"], "soft_skills": ["communication skills", "responsible"], "languages_combined": [{"language": "cantonese", "language_level": ["proficiency"]}, {"language": "english", "language_level": ["proficiency"]}, {"language": "mandarin", "language_level": ["proficiency"]}]}, "experience_required": {"duration": ["min 5 years"], "field": ["related", "retail", "fmcg"]}}, {"job_id": "100003009045575", "location_code": "hk", "company": "Toppan Forms (Hong Kong) Limited", "job_title": "Assistant Finance Manager", "description": "Purpose\u00a0of the Role\n\nReporting into the team Manager or Director, to provide business analysis and decision support for the finance team and be part of a Global Commercial Finance team managing business performance with a focus on PNL reporting, consolidation and analytical review.\u00a0 You will assist the team to manage all financial planning and analysis activities for the business and improve the business insights of those analysis to drive business performance and sound decision making.\n\nResponsibilities\n\nFinancial Analysis\n\nIdentify and recommend efficiencies and cost saving opportunities across all global store locations.\nReview division month end financials and ensure all variances are adequately explained.\nHighlight any anomalies that require follow up actions by Accounting & Reporting team or divisions.\nCollaborate with business partners to evaluate the effectiveness of investments via financial and non-financial KPIs.\n\nBudget/Forecast Planning\n\nAnalyse sales, margin, KPI and profit results to identify business trends and opportunities and quantify the effects of business changes, initiatives and events.\u00a0\nConduct frequent trend analysis and consolidate store locations for management decision making.\nSupport the team in preparing budget, forecast scenario and monthly financial review by working closely with business partners and cross departments.\n\nReporting\n\nWork with related functions to streamline and automate reports where possible and enhance communication.\nDevelop and maintain reporting required to monitor results at global level.\nStandardize division PNL analysis, business case template and reporting tool.\n\nControl\n\nMonitor and control expenditure in actual, budget and forecast in close collaboration with corporate and divisional functional and all finance functional teams.\nDocument and refine SOP (Standard Operating Procedures) for cross departments; ensure the SOP is well communicated to corporate and divisional level, compliance to company policies, accounting treatments, systems and audit standards.\nPerform any other ad hoc duties requested by your manager.\n\nRequirements\n\nDegree holder in Finance, Accounting, Business Management or related field\nStrong Microsoft PC based applications \u2013 Word, Excel and Powerpoint required.\u00a0\nMicrosoft Strategy and Power BI knowledge a plus.\nExcellent command of the English language and excellent communication skills\nStrong quantitative skills and able to analyse a business both statistically and conceptually\nAbility to format analytical works into presentation forms.\u00a0\nHigh degree of integrity and confidentiality with a keen sense of business/financial acumen", "employment_types": ["Full Time", "Permanent"], "selling_points": [], "locations": ["Kowloon Bay"], "categories": ["Accounting", "Accountant", "Finance / Accounting Manager", "Financial Analyst"], "post_time": "2022-01-13T08:06:50Z", "salary": {"currency": null, "max": null, "min": null, "period": "monthly", "term": null}, "salary_visible": false, "title_keywords": ["assistant finance manager"], "responsibilities": ["collaborate with", "budget", "audit", "communication", "maintain", "planning", "ad hoc duties", "control", "compliance", "monitor", "teams", "develop", "reports", "forecast", "kpis", "reporting", "cost", "management", "review", "procedures", "support the team", "policies", "analysis", "systems", "financial analysis", "evaluate", "analyse"], "requirements": {"degrees": ["degree", "degree holder"], "majors": ["business", "finance", "accounting"], "languages": ["english"], "language_level": ["excellent"], "hard_skills": ["business management", "excel", "plus", "bi", "word", "powerpoint", "pc", "acumen"], "soft_skills": ["communication skills", "integrity", "presentation", "keen"], "languages_combined": [{"language": "english", "language_level": ["excellent"]}]}, "experience_required": {"duration": [], "field": []}}, {"job_id": "100003009054117", "location_code": "hk", "company": "BOCOM International Holdings Company Limited", "job_title": "Associate, Structure Financing (Project Investment)", "description": "Responsibilities:\n\n\nResponsible for supervision of accounts receivable team and enhancement of debtor management\u00a0\u00a0\nCoordinate with relevant stakeholders for formulation of list prices of products and services, analyzing product costs on production processes as well as product cost data verification and maintenance in ERP environment\nSupport to prepare management reporting, cost variance and return analysis for performance evaluation and highlighting issues/risks with potential development opportunities\nWork closely with internal parties and external parties including customers, auditors and solicitors for operational need\nAdvise colleagues and executive management on decisions related to the company\u2019s finance and assist to conduct regular assessment of effectiveness of internal procedures under governance\nPerform ad-hoc assignments as required\n\nRequirements:\n\n\nDegree holder in Accountancy, Finance or related disciplines with professional accounting qualification\nAt least 8 years relevant working experience, in which above 4 years in supervisory position under ERP environment, specializing in manufacturing industry would be an advantage\nSolid experience in debtor management as well as using Power Query and SAP system is highly preferable\nAttentive to details, well organized with excellent analytical skill, proactive, strong sense of responsibility and able to work under pressure to meet tight deadline\nA good team player with good interpersonal and communication skill\nGood command in both spoken and written English and Chinese (Cantonese and \u00a0\u00a0\u00a0Mandarin)\nImmediately available is strongly preferable\n\nWe offer excellent compensation package, promotion prospects and job satisfaction. Interested parties, please\u00a0email\u00a0your detailed resume with current and expected salary by click \u201cApply Now\u201d.\n\nWe are an Equal Opportunities Employer. Personal data collected will be\u00a0used strictly in accordance with the employer's personal data policy, a copy of which will be provided upon request.\u00a0Candidates who do not notified within 8 weeks after submitting your application may consider the application unsuccessful and the application will be retained up to 24 months.\n\nDisclaimer: The above position description has been designed to indicate the general nature and level of work performed by employees within this classification. It is not designed to contain or be interpreted as a comprehensive list of all duties, responsibilities, and qualifications required of employees assigned to the position.\n\nToppan Forms does not accept unsolicited referrals and/or resumes from employment businesses and/or employment agencies. Any resumes submitted in the absence of a signed agreement will become the property of Toppan Forms and no fee shall be due.\n\nFor the details of Company Information, please visit\u00a0www.toppanforms.com\u00a0", "employment_types": ["Full Time"], "selling_points": ["Candidates from Big Four Preferred", "Minimum 2 years practical experience", "Ability to multi-task"], "locations": ["Not Specified"], "categories": ["Accounting", "Financial Analyst", "Others", "Banking / Finance", "Project Finance"], "post_time": "2022-01-17T08:27:15Z", "salary": {"currency": null, "max": null, "min": null, "period": "monthly", "term": null}, "salary_visible": false, "title_keywords": ["associate"], "responsibilities": ["cost", "management", "data verification", "accounts receivable", "maintenance", "ad-hoc assignments", "analysis", "external parties", "coordinate with", "procedures", "regular assessment", "management reporting", "internal parties", "evaluation", "costs"], "requirements": {"degrees": ["degree holder"], "majors": ["related disciplines", "finance", "accounting", "accountancy"], "languages": ["cantonese", "english", "chinese", "mandarin"], "language_level": ["good command"], "hard_skills": ["analytical skill", "sap", "erp"], "soft_skills": ["analytical skill", "good team player", "attentive to details", "sense of responsibility", "communication skill", "well organized", "meet tight deadline", "proactive", "interpersonal", "work under pressure"], "languages_combined": [{"language": "cantonese", "language_level": ["good command"]}, {"language": "english", "language_level": ["good command"]}, {"language": "chinese", "language_level": ["good command"]}, {"language": "mandarin", "language_level": ["good command"]}]}, "experience_required": {"duration": ["at least 8 years", "4 years"], "field": ["supervisory", "manufacturing industry", "relevant working experience", "management"]}}, {"job_id": "100003009049540", "location_code": "hk", "company": "Hillman Ross", "job_title": "Assistant FP&A Manager(HK Listed Company)", "description": "Key Responsibilities\n\nAssist the deal team to conduct due diligence of underlying investment targets, including industry analysis, commercial analysis, financial analysis and any other necessary analysis for Fund investment projects\nLiaise with external agents when necessary to facilitate the negotiation and settlement of projects goal, terms, investment returns, etc.\nPrepare for investment memo presentation to the Investment Committee. Assist the deal team in the internal approval process\nPerform post-investment monitoring and follow up in terms of specific projects\n\nRequirements\n\nUniversity degree or above in Finance, Accounting, Business Administration or a related discipline\n2-3 years\u2019 experience in Financial Due Diligence and valuation, work experience in professional accountancy firm (deal transactions/ valuation) is a plus\nSolid knowledge of financial products and markets\nExperience of handling institutional clients/investors is an advantage\nSelf-motivated, able to work under pressure and meet tight deadline\nTeam player with excellent communication, interpersonal and presentation skills\nProficiency in written and spoken English and Chinese including Putonghua", "employment_types": ["Full Time", "Permanent"], "selling_points": ["Regional Exposure", "Stable Working Environment", "Qualified Accountant is preferable"], "locations": ["Not Specified"], "categories": ["Accounting", "Accountant", "Audit", "Financial Analyst"], "post_time": "2022-01-14T08:51:02Z", "salary": {"currency": null, "max": null, "min": null, "period": "monthly", "term": null}, "salary_visible": false, "title_keywords": ["assistant"], "responsibilities": ["due diligence", "memo", "analysis", "monitoring", "financial analysis", "liaise with", "investment returns"], "requirements": {"degrees": ["degree or above"], "majors": ["finance", "accounting", "business administration"], "languages": ["putonghua", "english", "chinese"], "language_level": ["proficiency"], "hard_skills": ["plus"], "soft_skills": ["self-motivated", "communication", "presentation skills", "meet tight deadline", "team player", "interpersonal", "work under pressure"], "languages_combined": [{"language": "putonghua", "language_level": ["proficiency"]}, {"language": "english", "language_level": ["proficiency"]}, {"language": "chinese", "language_level": ["proficiency"]}]}, "experience_required": {"duration": ["2-3 years"], "field": ["financial"]}}, {"job_id": "100003009046537", "location_code": "hk", "company": "Michael Page", "job_title": "Senior Financial Analyst (retail), 39k", "description": "A renowned HK Listed Corporation is seeking for an Assistant FP&A Manager to join their Global Head Office in Hong Kong.\n\nWe are now seeking for an Assistant FP&A Manager(HK Listed Company)\n\nRESPONSIBILITIES\n\nPreparing annual budget, quarterly rolling forecast and perform budgetary control\nPrepare presentation materials for monthly operation review, special projects and annual budget\nReview month end closing and conduct timely financial analysis\nWork collaboratively with various parties to collect and summarize information\nOther ad hoc tasks as assigned\n\nQUALIFICATIONS\n\nDegree holder in Finance and Accounting or related disciplines\nQualified accountant of HKICPA / ACCA / CPA Australia is preferred\nMin 8 years of relevant experiences in Sizable companies. HK Listed company background preferred\nExcellent skill in Excel, Access and PowerPoint\nStrong analytical and communication skills\nProficiency in written and spoken English, Cantonese and Mandarin", "employment_types": ["Full Time", "Permanent"], "selling_points": ["5 years of retail experiences", "Sizable company", "MNC working cultrue"], "locations": ["Not Specified"], "categories": ["Accounting", "Consulting", "Financial Analyst", "Others"], "post_time": "2022-01-13T13:32:55Z", "salary": {"currency": null, "max": null, "min": null, "period": "monthly", "term": null}, "salary_visible": false, "title_keywords": ["senior financial analyst"], "responsibilities": ["control", "month end closing", "rolling forecast", "review", "budget", "ad hoc tasks", "financial analysis", "communication"], "requirements": {"degrees": ["degree holder"], "majors": ["related disciplines", "finance", "accounting"], "languages": ["cantonese", "english", "mandarin"], "language_level": ["proficiency"], "hard_skills": ["excel", "acca", "sizable companies", "powerpoint", "financial analysis", "cpa", "hkicpa"], "soft_skills": ["communication skills", "timely", "presentation"], "languages_combined": [{"language": "cantonese", "language_level": ["proficiency"]}, {"language": "english", "language_level": ["proficiency"]}, {"language": "mandarin", "language_level": ["proficiency"]}]}, "experience_required": {"duration": ["min 8 years"], "field": []}}, {"job_id": "100003009042498", "location_code": "hk", "company": "Lenovo Group Limited", "job_title": "Senior Financial Analyst", "description": "My client is one of the leading luxury retail brand worldwide and provides variety of luxury brands to the public. They are now hiring a Senior Financial Analyst focusing the FP&A duties to join them.\n\nClient Details\n\nMy client is one of the leading luxury retail brand worldwide and provides variety of luxury brands to the public. They are now hiring a Senior Financial Analyst focusing the FP&A duties to join them.\n\nDescription\n\nResponsibilities:\n\npreparing budgeting reports including annual budget and budgetary control of the company\nhandling the business unit performance analysis and evaluation\npreparing cash flow projections\nconducting financial modelling to different business unit\ndeveloping the feasibility reports and providing business recommendation and analysis\nassisting in ad hoc assignments\n\nProfile\n\nRequirements:\n\nBachelor degree of Accounting or other Finance Discipline\nCPA qualification\nMinimum 5 years of retail working experiences on FP&A\nGood command of both spoken and written English and Chinese\nDetail-minded, proactive and good communication skills\nProficiency with Microsoft Office Excel and PowerPoint\n\nJob Offer\n\nWe will offer competitive package to successful candidates:\n\nExcellent career path and opportunities\nMedical insurance\n\nTo apply online please click the 'Apply' button below. For a confidential discussion about this role please contact Queenie Yu on +852 2848 9578", "employment_types": ["Full Time", "Permanent"], "selling_points": ["Financial Analyst / Analyst", "Prepare annual budget and monthly forecast", "Complete monthly analysis report"], "locations": ["Quarry Bay"], "categories": ["Accounting", "Finance / Accounting Manager", "Financial Analyst", "Others"], "post_time": "2022-01-12T07:48:24Z", "salary": {"currency": null, "max": null, "min": null, "period": "monthly", "term": null}, "salary_visible": false, "title_keywords": ["senior financial analyst"], "responsibilities": ["control", "budgeting", "analysis", "budget", "developing", "cash flow", "reports", "ad hoc assignments", "evaluation"], "requirements": {"degrees": ["degree", "bachelor"], "majors": ["finance", "accounting"], "languages": ["english", "chinese"], "language_level": ["good command"], "hard_skills": ["powerpoint", "cpa", "excel", "microsoft office"], "soft_skills": ["detail-minded", "communication skills", "proactive"], "languages_combined": [{"language": "english", "language_level": ["good command"]}, {"language": "chinese", "language_level": ["good command"]}]}, "experience_required": {"duration": ["minimum 5 years"], "field": ["retail"]}}, {"job_id": "100003009045014", "location_code": "hk", "company": "Dah Chong Hong, Limited", "job_title": "Assistant Finance Manager", "description": "Prepare annual budget and monthly forecast on respective Business Groups (PC / Data Center / Mobile)\nComplete monthly analysis report and review Business Unit (BU) and Geography (Geo) performance\nWork closely with management on ad-hoc strategic presentation materials (e.g. Lenovo Executive Committee, Senior Leadership Team workshops) & involve in Board of Director presentation preparations\nClose collaboration and coordination with cross-functional teams across the Company on deliverables/projects to management to drive Company value\nAd-hoc enhancement projects in driving business efficiency and cost saving, etc.\nKey criteria\nBachelor degree with professional accounting qualification\nMinimum 4 years of working experience, with at least 1 year post-qualification experience in a FP&A role. Preferably Big 4 experience plus commercial experience.\u00a0\nTeam player but capable to work independently with minimum supervision\nAble to work under pressure and tight deadline, highly ambitious and seek for continuous self-improvement\nStrong communication skills and ability to present to Senior Leadership\nProficient in Excel Modeling and PowerPoint, experience in SAP/BPC and PowerBI is an advantage\nFluent in English and Cantonese, and working-level proficiency in Mandarin", "employment_types": ["Full Time"], "selling_points": [], "locations": ["Kowloon Bay"], "categories": ["Accounting", "Accountant", "Finance / Accounting Manager", "Financial Analyst"], "post_time": "2022-01-13T06:53:59Z", "salary": {"currency": null, "max": null, "min": null, "period": "monthly", "term": null}, "salary_visible": false, "title_keywords": ["assistant finance manager"], "responsibilities": ["ad-hoc", "management", "cost", "data", "analysis report", "review", "budget", "coordination with", "communication", "forecast", "enhancement projects", "cross-functional teams", "work under pressure"], "requirements": {"degrees": ["degree", "bachelor"], "majors": ["accounting"], "languages": ["cantonese", "english", "mandarin"], "language_level": ["proficiency", "fluent"], "hard_skills": ["excel", "plus", "sap", "analysis", "powerpoint", "mobile", "workshops", "pc"], "soft_skills": ["communication skills", "work independently", "capable", "coordination", "team player", "leadership", "presentation", "work under pressure"], "languages_combined": [{"language": "cantonese", "language_level": ["fluent"]}, {"language": "english", "language_level": ["proficiency", "fluent"]}, {"language": "mandarin", "language_level": ["fluent"]}]}, "experience_required": {"duration": ["minimum 4 years", "at least 1 year"], "field": ["commercial", "post-qualification", "big 4"]}}, {"job_id": "100003009044220", "location_code": "hk", "company": "Dah Chong Hong, Limited", "job_title": "Financial Analyst", "description": "Responsibilities:\n\nPrepare and review full set of accounts in assigned business unit.\nPrepare monthly financial and management reports/analysis.\nPrepare annual budget, forecast, cash flow management and tax reporting.\u00a0\nLiaise with business unit heads and external parties for annual audits.\nComply with legal and Group compliance requirement.\nAssist management on ad-hoc reports and analysis.\n\n\u00a0Requirements:\n\nDegree\u00a0in Accounting, Finance or related disciplines\nQualified member of HKICPA, ACCA or equivalent is preferred\nAt least 5 - 6 years of accounting experience\nProficient in MS office applications\nGood command of English & Mandarin\nSelf-motivated with a strong sense of responsibilities, team player but able to work\u00a0independently and meet tight reporting deadline\nImmediate available is an advantage\n\nPlease send your application with resume and expected salary to The HR Manager, Dah Chong Hong Ltd, 8/F, DCH Building, 20 Kai Cheung Road, Kowloon Bay or submit your application online by clicking \"Apply Now\" or send your resume to the email address stated in our company description.\n\nInformation provided will be for the purpose of selection within the company and only shortlisted candidates will be contacted. All applications will be retained for a maximum period of 6 months.", "employment_types": ["Full Time", "Permanent"], "selling_points": [], "locations": ["Kowloon Bay"], "categories": ["Accounting", "Finance / Accounting Manager", "Financial Analyst"], "post_time": "2022-01-13T03:25:55Z", "salary": {"currency": null, "max": null, "min": null, "period": "monthly", "term": null}, "salary_visible": false, "title_keywords": ["financial analyst"], "responsibilities": ["tax", "reporting", "management", "ad-hoc", "analysis", "review", "budget", "full set of accounts", "external parties", "audits", "compliance", "management reports", "cash flow", "reports", "forecast", "liaise with"], "requirements": {"degrees": ["degree"], "majors": ["related disciplines", "finance", "accounting"], "languages": ["english", "mandarin"], "language_level": ["good command"], "hard_skills": ["acca", "ms office", "hkicpa"], "soft_skills": ["self-motivated", "team player", "work independently", "sense of responsibilities"], "languages_combined": [{"language": "english", "language_level": ["good command"]}, {"language": "mandarin", "language_level": ["good command"]}]}, "experience_required": {"duration": ["at least 5 - 6 years"], "field": ["accounting experience"]}}, {"job_id": "100003009051153", "location_code": "hk", "company": "Panasonic Life Solutions (Hong Kong) Co., Limited", "job_title": "Assistant Accounting Officer", "description": "Responsibilities:\n\nResponsible for handling monthly financial performance review\nAssist in business transformation project\nKeep tracking the best use of financial resources including working capital to enhance profitability\u00a0and growth. Identify and mitigate potential serious financial risk\nPrepare periodical forecast and budget report & perform financial analysis\nPrepare monthly rolling P&L forecast and variance analysis for management\u2019s decision and KPI monitoring and follow up the achievement of P&L targets\nPreform special investigation and ad hoc projects as from time to time required by the management\nRequirements:\n\nBachelor Degree in Finance or Accounting or related discipline\nAt least 5 years\u2019 relevant experience in sizable companies\nStrong skills in Excel spreadsheet.\u00a0Knowledge in Oracle and Hyperion is preferred\nMember of HKICPA/ACCA is a plus\nSelf-motivated, good communication and interpersonal skills as well as a team player\nAble to work independently and adhere to deadline\nExcellent communication of both written and spoken English and Chinese\nImmediately available is highly preferred\n\nPlease send your application with resume and expected salary to The HR Manager, Dah Chong Hong, Ltd, 8/F, DCH Building, 20 Kai Cheung Road, Kowloon Bay by post or email to click\u00a0\"Apply Now\".\n\n\u00a0We are equal opportunities employer. Applicants who are not invited within 2 months may consider their application unsuccessful. All applicants may be considered for other suitable positions with DCH Group / CITIC Pacific Group and will be deleted from our files after 6 months from the date of application.", "employment_types": ["Full Time", "Permanent"], "selling_points": [], "locations": ["Tsuen Wan Area"], "categories": ["Accounting", "Accountant", "Financial Analyst"], "post_time": "2022-01-15T03:43:34Z", "salary": {"currency": null, "max": null, "min": null, "period": "monthly", "term": null}, "salary_visible": false, "title_keywords": ["assistant accounting officer"], "responsibilities": ["tracking", "management", "review", "budget", "monitoring", "p&l", "investigation", "financial analysis", "variance analysis", "ad hoc projects", "forecast", "report"], "requirements": {"degrees": ["degree", "bachelor"], "majors": ["finance", "accounting"], "languages": ["english", "chinese"], "language_level": ["excellent"], "hard_skills": ["excel", "oracle", "acca", "plus", "sizable companies", "spreadsheet", "hkicpa"], "soft_skills": ["self-motivated", "work independently", "communication", "communication and interpersonal skills", "team player"], "languages_combined": [{"language": "english", "language_level": ["excellent"]}, {"language": "chinese", "language_level": ["excellent"]}]}, "experience_required": {"duration": ["at least 5 years"], "field": ["relevant experience"]}}, {"job_id": "100003009050160", "location_code": "hk", "company": "Magic Search Limited", "job_title": "Assistant Finance Manager (Luxury Brand)", "description": "Responsibilities:\n\n\nSupport in preparing periodic reports, forecasts, budgets and month-end closing\nAssist to perform financial analysis for management review\nLiaise with different departments for accurate inventory management\nEnsure internal control policies and procedures aligned with Corporate policy and SOX requirements\nHandle ad hoc projects as assigned\nRequirements:\n\nDegree in Finance or Accounting\nMinimum 4 years\u2019 experience in financial analysis or full set of accounting\nSolid experience in whole budget cycle of manufacturing company\nGood communication skills with proficiency in both written and spoken English & Chinese (including Mandarin)\nFlexible, detail-minded, sensitive to figures and able to work under tight time frame\nProficient in data consolidation with Excel and PowerPoint\nWith knowledge in Oracle system or SOX and compliance would be an advantage\n\nCandidate with more experiences will be considered as Officer.\u00a0\n\nWe offer competitive compensation package to the right candidate including birthday leave, medical benefits, medical checkup, double pay plus discretionary bonus, excellent training opportunities and career advancement.\u00a0 \u00a0\n\nInterested parties please apply with full resume stating current & expected salary, availability and send to HRA Department, Unit 1, 15/F., CDW Building, 388 Castle Peak Road, Tsuen Wan, N.T. or click \"Apply Now\" to submit your application. (Please quote the reference no. #MS/ACC/220114 with the application.)\n\nAll applications received will be kept in strictest confidence and for recruitment purpose only. Those not invited for interview within 4 weeks may consider their applications unsuccessful.", "employment_types": ["Full Time", "Permanent"], "selling_points": ["6-7 years experience", "luxury brand", "audit experience is a plus"], "locations": ["Not Specified"], "categories": ["Accounting", "Audit", "Financial Analyst", "Financial Controller"], "post_time": "2022-01-14T09:53:26Z", "salary": {"currency": null, "max": null, "min": null, "period": "monthly", "term": null}, "salary_visible": false, "title_keywords": ["assistant finance manager"], "responsibilities": ["budgets", "policies", "procedures", "financial analysis", "inventory management", "month-end closing", "reports", "ad hoc projects", "liaise with", "management review", "internal control"], "requirements": {"degrees": ["degree"], "majors": ["finance", "accounting"], "languages": ["english", "chinese", "mandarin"], "language_level": ["proficiency", "good"], "hard_skills": ["excel", "plus", "oracle system", "powerpoint", "financial analysis"], "soft_skills": ["flexible", "communication skills", "detail-minded", "sensitive to figures"], "languages_combined": [{"language": "english", "language_level": ["proficiency", "good"]}, {"language": "chinese", "language_level": ["proficiency", "good"]}, {"language": "mandarin", "language_level": ["proficiency", "good"]}]}, "experience_required": {"duration": ["minimum 4 years"], "field": ["manufacturing", "accounting", "financial"]}}, {"job_id": "100003009037039", "location_code": "hk", "company": "Tory Burch Far East Limited", "job_title": "Part Time Assistant Financial Analyst", "description": "Our client is a global leading luxury Brand It is now looking for an Assistant Finance Manager to join their team.\n\n\n\nKey Responsibilities\n\nPrepare and consolidated Sales monthly sales report with comparison against Budget and Forecast with comment\nWork closely with other functional team to ensure alignment and to reconcile any discrepancy\nPrepare other regular sales reporting or ad hoc analysis for management review of business performance\u00a0\nDevelop and replicate excel\u00a0budget/forecast\u00a0templates for\u00a0Asia\u00a0market\u00a0and\u00a0validation\u00a0\u00a0\nAssist\u00a0with the\u00a0budget & forecast\u00a0consolidation and review\u00a0process\nValidate system input and co-ordinate necessary follow-up with market\u00a0finance team\nAssist with analysis during budget and forecast process\nCost Management and Budget follow-up\nAssist in establishing/improving means of regional\u00a0cost\u00a0tracking\u00a0and budget follow-up\u00a0process\nRecommend and develop relevant reports and analysis\nAssist in developing of business performance reports\u00a0\nPlanning and Consolidation tool co-ordination, vendor master data creation and maintenance, and other ad hoc projects\n\nRequirements\n\nBachelor degree in Finance, Accounting or other related subjects\n6-7 years relevant retail working experience\nAbility to extract, organise, analyse and report data\nGood communication skills\nGood command in English and Chinese\u00a0", "employment_types": ["Part Time"], "selling_points": ["Provide Support to FP&A Team", "Prepare and Maintain Reports Accuracy", "Fresh Graduate Are Welcome"], "locations": ["Tsim Sha Tsui"], "categories": ["Accounting", "Accounting Clerk / Supervisor", "Financial Analyst", "Others"], "post_time": "2022-01-11T01:28:36Z", "salary": {"currency": null, "max": null, "min": null, "period": "hourly", "term": null}, "salary_visible": false, "title_keywords": ["assistant", "financial analyst"], "responsibilities": ["performance reports", "data", "budget", "system input", "monthly sales report", "management review", "relevant reports", "ad hoc", "developing", "develop", "finance team", "forecast", "reporting", "cost", "management", "review", "tracking", "maintenance", "forecast process", "analysis", "ad hoc projects", "planning"], "requirements": {"degrees": ["degree", "bachelor"], "majors": ["finance", "accounting"], "languages": ["english", "chinese"], "language_level": ["good command"], "hard_skills": [], "soft_skills": ["communication skills"], "languages_combined": [{"language": "english", "language_level": ["good command"]}, {"language": "chinese", "language_level": ["good command"]}]}, "experience_required": {"duration": ["6-7 years"], "field": ["retail"]}}, {"job_id": "100003009049761", "location_code": "hk", "company": "Page Personnel", "job_title": "Management Accountant - FMCG Company", "description": "Job\u00a0Descriptions:\nPrepare financial reports by collecting, formatting, analyzing, and explaining information\nLead mostly\u00a0project-based\u00a0financial planning\u00a0& analysis such as sales controlling, cash flow forecast, strategic pricing, product mix analysis, KPI analysis etc.\nConduct investment appraisals and feasibility analysis on P&L projections of new expansion projects while optimizing business opportunities\nSupporting in the preparation of monthly business review presentations to top management\nWork with business units on\u00a0Budget / Forecast\u00a0and track performance with variance analysis on a timely basis\n\u00a0Requirement:\nDegree holder with at least 5 years of FP&A Experience across fast-paced environment, qualified public accountant (CA or CPA) is preferred\nAttention to detail and accuracy with strong sense of urgency\nHighly analytical and detail-oriented with good business acumen\nExcellent information management, organizational, problem analysis, and problem solving skills\nAbility to manage multiple stakeholders (senior - junior) and ability to multi-task\nCandidate with less experience will consider as\u00a0Financial Planning & Analysis Manager\nImmediate available is preferred\n\n\n\nJob Offer:\n\n5-day work\nCompetitive Salary Package\n13 months' Guaranteed Salary\nGroup Medical Scheme\nBirthday Leave\nMarriage Leave\nProvide Free Lunch\nEnergetic & Dynamic Culture\n*All information collected will be used for recruitment-related purpose only.\n\n\n\n\nInterested parties, please send your detailed resume, availability and expected salary by clicking \u201cApply Now\u201d.", "employment_types": ["Full Time", "Permanent"], "selling_points": ["Young Team Culture", "Regional Exposure", "Salary up to HK$ 30, 000 per month"], "locations": ["Wan Chai Area"], "categories": ["Accounting", "Accountant", "Financial Analyst", "Others"], "post_time": "2022-01-14T09:12:04Z", "salary": {"currency": "HKD", "max": 29999, "min": 20000, "period": "monthly", "term": null}, "salary_visible": true, "title_keywords": ["accountant"], "responsibilities": ["financial reports", "management", "analysis", "business opportunities", "review", "budget", "p&l", "presentations", "variance analysis", "cash flow", "formatting", "forecast", "planning"], "requirements": {"degrees": ["degree holder"], "majors": [], "languages": [], "language_level": [], "hard_skills": ["analysis", "scheme", "cpa", "dynamic", "problem solving skills", "acumen"], "soft_skills": ["multi-task", "fast-paced environment", "urgency", "organizational", "detail-oriented", "dynamic", "attention to detail", "business acumen", "problem solving skills", "energetic"], "languages_combined": []}, "experience_required": {"duration": ["at least 5 years"], "field": ["planning", "financial"]}}, {"job_id": "100003009049782", "location_code": "hk", "company": "Find Asia Limited", "job_title": "Accounting Manager/ Assistant Manager", "description": "Excellent opportunity for a candidate who is looking for a management accounting role in FMCG industry. Our client offers attractive salary package and stable career growth for potential candidate who wants to explore new career opportunity.\n\nClient Details\n\nOur client is a Korea FMCG company who focus on food & beverage products. With 10 office around the world, and over 1000 employees in the company, they are now seeking for a management accountant to cope with business expansion in the future.\n\nDescription\n\nConduct regular financial and commercial analysis of the Company's brands in markets around the world, particularly to monitor and forecast the performance of the brands in each market against business plans, identify issues, and propose mitigating solutions.\nFacilitate Management's better understanding of business performance and forecasts through insightful analysis, liaison with finance teams in markets and other departments.\nPreparation of regular financial management reports, including those for the Board and Group Reporting submissions.\nAssist in the Company's annual business plans and budget, as well as their ongoing monitoring and latest estimates.\nSupport the Finance Manager in accounting and finance processes, for example month/year end financial statement close, audits and banking.\nPerform or support ad hoc projects or tasks, for example review of contracts, implementation/improvement of processes, etc.\n\nProfile\n\nBachelor's degree in Finance/Accounting or relevant discipline\nExcellent communication skills, with fluent oral and written English and Mandarin Chinese\nStrong business acumen and ability to develop appropriately detailed data models and reports for effective/efficient analysis\nProactive individual, with attention to detail and good judgement\nGood Excel, Word, PowerPoint and general IT skills\nQuick learner and team player, with ability to work within a multicultural team from varied backgrounds\nExperience in a relevant analysis role (e.g. FP&A, Analyst, Management Accounting) and/or FMCG company would be beneficial, but fresh graduates with demonstrably strong capabilities and attitude will also be considered\n\nJob Offer\n\nMedical and Dental coverage\nAnnual leave 18 days\nFlexible working hour\nWFH Policy\n5 days work week\n\nTo apply online please click the 'Apply' button below. For a confidential discussion about this role please contact Matthew Tong on +852 3602 2460", "employment_types": ["Full Time", "Permanent"], "selling_points": ["Accounting Manager", "Reporting, budgeting, analysis, consolidation", "5 days, TST"], "locations": ["Tsim Sha Tsui"], "categories": ["Accounting", "Chief Accountant", "Finance / Accounting Manager", "Financial Analyst"], "post_time": "2022-01-15T03:50:35Z", "salary": {"currency": null, "max": null, "min": null, "period": "monthly", "term": null}, "salary_visible": false, "title_keywords": ["assistant manager", "accounting manager"], "responsibilities": ["data", "budget", "business plans", "communication", "financial statement", "contracts", "monitor", "teams", "implementation", "develop", "reports", "forecast", "banking", "reporting", "management", "monitoring", "review", "contact", "audits", "analysis", "management reports", "ad hoc projects"], "requirements": {"degrees": ["degree", "bachelor"], "majors": ["finance", "accounting"], "languages": ["mandarin chinese", "english"], "language_level": ["excellent", "fluent"], "hard_skills": ["excel", "analysis", "fmcg industry", "word", "powerpoint", "management reports", "focus", "acumen"], "soft_skills": ["efficient", "communication skills", "oral", "focus", "flexible", "quick learner", "team player", "attention to detail", "business acumen", "stable", "proactive", "detailed"], "languages_combined": [{"language": "mandarin chinese", "language_level": ["excellent", "fluent"]}, {"language": "english", "language_level": ["excellent", "fluent"]}]}, "experience_required": {"duration": [], "field": []}}, {"job_id": "100003009044920", "location_code": "hk", "company": "Wharf Estates Limited", "job_title": "EXPENDITURE BUDGET UNIT OFFICER", "description": "Our client, an electronics manufacturing co. is looking for the candidate with the following details:\u00a0\n\n\u00a0Duties\n\nReview the Accounting operation, month-end closing, reporting and forecasting, budgeting and analysis report\nPrepare the regional consolidation and management reporting of the Group\u00a0\nPerform various analysis and provide commentaries to management\u00a0\nLiaise with internal dept. for budgeting, forecast and cost control\u00a0\nEnsure accounting policies and procedures in line with statutory requirement and tax affairs\nSystem implementation\u00a0\nAnalyze regional logistics situation and inventory control\u00a0\n\n\u00a0Requirement\u00a0\n\nGood command of English & Mandarin\nQualified accounting certificate/ CPA\n10 years experience in Accounting in trading or manufacturer\u00a0\nWith experience in consolidating, monitoring and reviewing overseas (e.g. Asian countries) accounting, inventory control and internal control\u00a0\nGood management skill and able to work independent\u00a0\nGood Excel skill, PowerPoint and Chinese Word Processing", "employment_types": ["Full Time"], "selling_points": ["Degree holder in Accounting or related disciplines", "CPA, CIA qualification will be an advantage", "Minimum 3 years\u2019 experience in budget control"], "locations": ["Tsim Sha Tsui"], "categories": ["Accounting", "Financial Analyst", "Others", "Property / Real Estate", "Property Management"], "post_time": "2022-01-15T03:49:24Z", "salary": {"currency": null, "max": null, "min": null, "period": null, "term": null}, "salary_visible": false, "title_keywords": ["officer"], "responsibilities": ["tax", "reporting", "management", "analysis report", "budgeting", "analysis", "review", "procedures", "implementation", "accounting policies", "month-end closing", "logistics", "management reporting", "forecast", "cost control", "liaise with", "inventory control", "forecasting"], "requirements": {"degrees": ["certificate"], "majors": ["accounting"], "languages": ["english", "chinese", "mandarin"], "language_level": ["good command", "good"], "hard_skills": ["excel", "chinese word processing", "powerpoint", "cpa", "internal control"], "soft_skills": ["independent"], "languages_combined": [{"language": "english", "language_level": ["good command", "good"]}, {"language": "chinese", "language_level": ["good"]}, {"language": "mandarin", "language_level": ["good command", "good"]}]}, "experience_required": {"duration": ["10 years"], "field": ["accounting", "trading"]}}, {"job_id": "100003009051307", "location_code": "hk", "company": "Miramar Hotel and Investment Company, Limited", "job_title": "Assistant Accountant (management accounting focus)", "description": "Responsibilities:\n\nMonitor the approved expenditure budget according to the budget control framework\nControl budget funds availability and prepare budget forecast\nHandle over-budget applications and budget limit readjustment\nPrepare expenditure & budget statements and financial analysis reports\nPerform other ad-hoc assignments as required\n\nRequirements:\n\nDegree holder in Accounting, Finance, Business Management or related disciplines\nCPA, CIA or equivalent qualification will be an advantage\nAt least 3 years\u2019 experience in budget control, preferably gained in professional firms or sizable organizations\nExcellent communication & interpersonal skills\nMeticulous, detail-oriented with good analytical and report writing skills and able to work under pressure and meet deadline\nProficiency in Microsoft Word and Excel\nGood command in both written and spoken English and Chinese (including Putonghua)", "employment_types": ["Full Time", "Permanent"], "selling_points": [], "locations": ["Tsim Sha Tsui"], "categories": ["Accounting", "Accounting Clerk / Supervisor", "Financial Analyst", "Hospitality / F & B", "Food & Beverage"], "post_time": "2022-01-15T07:54:33Z", "salary": {"currency": null, "max": null, "min": null, "period": "monthly", "term": null}, "salary_visible": false, "title_keywords": ["accounting", "assistant accountant"], "responsibilities": ["control", "ad-hoc assignments", "budget", "monitor", "financial analysis reports", "forecast", "budget control"], "requirements": {"degrees": ["degree holder"], "majors": ["business", "finance", "related disciplines", "accounting"], "languages": ["putonghua", "english", "chinese"], "language_level": ["good command"], "hard_skills": ["business management", "excel", "microsoft word", "writing skills", "cpa"], "soft_skills": ["meticulous", "writing skills", "detail-oriented", "communication", "interpersonal skills", "work under pressure"], "languages_combined": [{"language": "putonghua", "language_level": ["good command"]}, {"language": "english", "language_level": ["good command"]}, {"language": "chinese", "language_level": ["good command"]}]}, "experience_required": {"duration": ["at least 3 years"], "field": []}}, {"job_id": "100003009043003", "location_code": "hk", "company": "Randstad Hong Kong Limited", "job_title": "Financial Analyst - immediate hire", "description": "The Job\n\nPrepare monthly report e.g. financial and management report, rolling forecast, analysis, promotion event, meeting report etc.\nResponsible for annual budget and festive food project\nHandle joint promotion and e-Shop matters\nPrepare feasibility report for business development\nImprove workflow and enhance ERP system (including POS, eShop and others)\nLiaise with various departments for operation matters\nThe Requirement\n\nDegree in Accounting, Finance or related discipline\nAt least 3 years' finance/accounting experience\nGood analytical and management reporting skills\nAttention to detail, self-motivated and independent\nSolid experience in budget and forecast\nHigh proficiency in Microsoft software skills, e.g. excel, PowerPoint.\nHands-on experience in using ERP system such as POS, Procurement & Accounting\nProficiency in financial and business performance analysis especially in Food & Beverage industry is preferred\nAttractive remuneration would be offered to the right candidates.\n\nPlease send your application with expected salary to Human Resources Manager:\n\nBy WhatsApp: 6388-3034 or\nBy Fax: 2722-5555\n\nPersonal data collected will be used for recruitment purpose only. We are an equal opportunity employer.", "employment_types": ["Full Time", "Permanent"], "selling_points": ["A Global Professional Services Company", "Accounting & System Implementation", "Flexible Working Arrangement"], "locations": ["Not Specified"], "categories": ["Accounting", "Accountant", "Finance / Accounting Manager", "Financial Analyst"], "post_time": "2022-01-12T09:29:41Z", "salary": {"currency": "HKD", "max": 44999, "min": 35000, "period": "monthly", "term": null}, "salary_visible": true, "title_keywords": ["financial analyst"], "responsibilities": ["e-shop", "rolling forecast", "analysis", "budget", "liaise with various departments", "monthly report", "management report", "report"], "requirements": {"degrees": ["degree"], "majors": ["finance", "accounting"], "languages": [], "language_level": [], "hard_skills": ["excel", "pos", "analysis", "powerpoint", "erp system", "whatsapp"], "soft_skills": ["hands-on", "self-motivated", "independent", "attention to detail"], "languages_combined": []}, "experience_required": {"duration": ["at least 3 years"], "field": ["finance", "accounting experience", "erp system", "accounting", "procurement"]}}, {"job_id": "100003009051200", "location_code": "hk", "company": "Champion Group International Limited", "job_title": "Financial Accountant", "description": "\n\nWork closely with Finance team for the transition of routine accounting operations to share service center\nCommunicate and direct share service center for handling accounts payable, account receivable and general ledger\nLiaise with share service center to ensure consistent application of workflow in Hong Kong office\nPrepare daily manual works and provide support on general accounting matters\nPerform ad-hoc duties as required\nRequirements:\u00a0\n\nBachelor Degree in Accounting/ Finance/ Data Analytics or related discipline\nMinimum 1 year of relevant working experience\u00a0\nHigh proficiency in MS Excel skills. Experienced in VBA will be an advantage\nExperience with SAP is a must\nData modelling skills to analyze and summarize data\nStrong interpersonal and communication skills\nFast learner with independent manner\nAttention to details, well-organized, results driven\n\nPlease send the CV by clicking \"Apply Now\".\n\nPersonal data collected will be used for recruitment purpose only.", "employment_types": ["Full Time", "Permanent"], "selling_points": [], "locations": ["Yuen Long"], "categories": ["Accounting", "Accountant", "Financial Analyst"], "post_time": "2022-01-15T04:40:49Z", "salary": {"currency": null, "max": null, "min": null, "period": "monthly", "term": null}, "salary_visible": false, "title_keywords": ["accountant"], "responsibilities": ["provide support", "data", "general ledger", "operations", "communication", "recruitment", "finance team", "ad-hoc duties", "liaise with", "personal data", "accounts payable"], "requirements": {"degrees": ["degree", "bachelor"], "majors": ["finance", "accounting"], "languages": [], "language_level": [], "hard_skills": ["vba", "data analytics", "ms excel", "sap"], "soft_skills": ["communication skills", "independent", "well-organized", "driven", "attention to details", "ad-hoc duties", "fast learner", "interpersonal"], "languages_combined": []}, "experience_required": {"duration": ["minimum 1 year"], "field": ["relevant working experience"]}}, {"job_id": "100003009038515", "location_code": "hk", "company": "aimHigher Consultancy Limited", "job_title": "Senior Business Analyst / Assistant Manager, Business Planning", "description": "We are a Hong Kong based company professional hygiene solution suppliers and commercial dishwasher and hygiene commercial products manufacturer. To cope with our business expansion, we are now inviting dynamic professional to join our professional team.\n\nKey Responsibilities\n\nReport to the Finance Manager\uff1b\nOverseeing the daily operations especially accounts payable and inventory of the Finance department and month end process\uff1b\nAssist in monitoring financial system and database ;\nAssist in preparing financial statements.\n\n\u00a0The ideal candidate should process the following qualities:\n\nDegree holder in accounting discipline and a semi-qualified accountant\uff1b\nA least 4 years of working experience, of which 2 years are gained from audit firms\uff1b\nFamiliar with the accounting standards\uff1b\nFamiliar with ERP and database\uff1b\nGood analytical skills\uff1b\nExcellent command in spoken & written English, Mandarin and Cantonese\nAttractive remuneration package\n\nCompetitive salary, performance bonus, medical insurance, child subsidy and education subsidy\nInterested candidates, please apply with a cover letter and your updated CV with current and expected salary and availability by clicking\u00a0\u201cApply Now\u201d. The information provided will be treated in strict confidence and used solely for recruitment purpose. All applicants' information will be destroyed after 12 months.\n\nFor more information about us, please visit our website at\u00a0http://www.champion-chem.com/en/", "employment_types": ["Full Time"], "selling_points": ["Leading FMCG group in Asia", "Business partnering role", "Regional exposure"], "locations": ["Not Specified"], "categories": ["Accounting", "Finance / Accounting Manager", "Financial Analyst", "Others"], "post_time": "2022-01-11T07:12:17Z", "salary": {"currency": null, "max": null, "min": null, "period": "monthly", "term": null}, "salary_visible": false, "title_keywords": ["senior business analyst", "assistant manager,"], "responsibilities": ["financial system", "inventory", "monitoring", "audit", "financial statements", "hygiene", "daily operations", "database", "insurance", "accounts payable", "report"], "requirements": {"degrees": ["degree holder"], "majors": ["accounting"], "languages": ["cantonese", "english", "mandarin"], "language_level": ["excellent"], "hard_skills": ["dynamic", "erp", "analytical skills"], "soft_skills": ["dynamic", "analytical skills", "ideal"], "languages_combined": [{"language": "cantonese", "language_level": ["excellent"]}, {"language": "english", "language_level": ["excellent"]}, {"language": "mandarin", "language_level": ["excellent"]}]}, "experience_required": {"duration": ["least 4 years", "2 years"], "field": ["audit"]}}, {"job_id": "100003009047500", "location_code": "hk", "company": "eSun Holdings Limited", "job_title": "Senior Accountant", "description": "Responsibilities\n\nWork closely with consultants by conducting joint meeting with client to identify recruitment needs from clients\nSupport recruitment operations through researching, sourcing, and approaching of suitable candidates for different job mandates\nDay-to-day responsibilities including assisting consultants in research, generating names of potential candidates for specified search, developing appropriate target lists and maintaining a timely and accurate candidate database\nAssist consultants in the preparation of candidate and client reports\n\nRequirements\n\nExperience in search/recruitment or a related research-based environment is a plus\nExcellent communication and interpersonal skills\nSelf motivated and result oriented\nStrong telephone presence and confidence in interfacing with different level of people\nExcellent in both written and spoken English and Chinese\nFresh graduates are welcome to apply\nInterested parties please send your updated resume in WORD format with current and expected salaries (quoting Employer Ref:)", "employment_types": ["Full Time", "Permanent"], "selling_points": ["Prepare monthly financial & management reports", "Assist in group reporting, budgeting & forecast", "Maintain proper internal control"], "locations": ["Lai Chi Kok"], "categories": ["Accounting", "Accountant", "Audit", "Financial Analyst"], "post_time": "2022-01-14T03:20:32Z", "salary": {"currency": null, "max": null, "min": null, "period": "monthly", "term": null}, "salary_visible": false, "title_keywords": ["senior accountant"], "responsibilities": ["client reports", "maintaining", "operations", "developing", "recruitment", "database"], "requirements": {"degrees": [], "majors": [], "languages": ["english", "chinese"], "language_level": ["excellent"], "hard_skills": ["plus"], "soft_skills": ["self motivated", "result oriented", "communication and interpersonal skills", "confidence"], "languages_combined": [{"language": "english", "language_level": ["excellent"]}, {"language": "chinese", "language_level": ["excellent"]}]}, "experience_required": {"duration": [], "field": ["related", "research", "recruitment"]}}, {"job_id": "100003009046399", "location_code": "hk", "company": "Wheelock Properties (Hong Kong) Ltd", "job_title": "Investment Associate", "description": "Company Description\n\nOur client is a well-known F&B company. They are looking for a Senior Operations Manager to join their dynamic team to oversee multiple stores.\n\nResponsibilities\n\nOversee day to day operations and monitor performance of the stores to maximize sales\nResponsible to enhance operation efficiency\nTrain and motivate staff to provide excellent services\nProvide recommendations to management team in improving store operations and sales performance\n\nRequirements\n\nHigher Diploma or above in Catering Management/Business Administration or related discipline is preferred\nAt least 5 years' management experience in catering industry\nProactive with excellent interpersonal & management skills\nGood command of Cantonese & English, preferably with Mandarin\nInterested parties please send your updated resume in WORD format with current and expected salaries (quoting Employer Ref:)", "employment_types": ["Full Time", "Permanent"], "selling_points": [], "locations": ["Central"], "categories": ["Accounting", "Accountant", "Financial Analyst", "Banking / Finance", "Investment"], "post_time": "2022-01-13T18:55:20Z", "salary": {"currency": null, "max": null, "min": null, "period": null, "term": null}, "salary_visible": false, "title_keywords": ["investment associate"], "responsibilities": ["management team", "day to day operations", "monitor performance", "operations", "sales performance", "provide recommendations"], "requirements": {"degrees": ["higher diploma or above"], "majors": ["business administration"], "languages": ["cantonese", "english", "mandarin"], "language_level": ["good command"], "hard_skills": [], "soft_skills": ["proactive", "interpersonal"], "languages_combined": [{"language": "cantonese", "language_level": ["good command"]}, {"language": "english", "language_level": ["good command"]}, {"language": "mandarin", "language_level": ["good command"]}]}, "experience_required": {"duration": ["at least 5 years"], "field": ["management"]}}, {"job_id": "100003009047408", "location_code": "hk", "company": "Tai Hing Catering Group Limited", "job_title": "Accountant", "description": "Company Description\n\nOur client is a well-established and one of the leading Food and Beverage Company in Hong Kong. For business needs, they invited a good talent to join their Supply Chain Team as Logistic Manager.\n\nResponsibilities\n\nResponsible for managing the 3rd party logistic (3PL) sourced delivery team to ensure smooth operations\nMeet daily targets for Point of Distribution (POD), including on-time delivery rates, safety, customer complaints & incidents, productivity, total operating costs and order fulfillment rate\nMaintain all transport processes, procedures and schedules as well as transportation plan\nEnsure that transportation system is being utilized properly and fully integrated with day-to-day operations\nBuild and manage relations with 3PL to meet both quality and cost objectives\nManage the delivery costs against budgets\nParticipant in Transportation Management System (TMS) Implementation or upgrade projects\n\nRequirements\n\nBachelor's degree holder with at least 8 years\u2019 experience in Transportation operations or related discipline , demonstrating good knowledge in either fleet management or local distribution management\nBeing Flexible\nExcellent communications skills and people management skills\nAble to work under pressure and have ability to handle rapid growth of deliveries\nGood command of spoken and written English and Chinese\n\nInterested parties please send your updated resume in WORD format with current and expected salaries (quoting Employer Ref:)", "employment_types": ["Full Time", "Permanent"], "selling_points": [], "locations": ["Quarry Bay"], "categories": ["Accounting", "Accountant", "Financial Analyst", "Taxation"], "post_time": "2022-01-14T03:01:21Z", "salary": {"currency": null, "max": null, "min": null, "period": "monthly", "term": null}, "salary_visible": false, "title_keywords": ["accountant"], "responsibilities": ["budgets", "cost", "management", "customer complaints", "schedules", "procedures", "day-to-day operations", "quality", "implementation", "maintain", "order fulfillment", "ensure smooth operations", "plan", "costs"], "requirements": {"degrees": ["bachelor", "degree holder"], "majors": [], "languages": ["english", "chinese"], "language_level": ["good command"], "hard_skills": ["rapid"], "soft_skills": ["flexible", "work under pressure"], "languages_combined": [{"language": "english", "language_level": ["good command"]}, {"language": "chinese", "language_level": ["good command"]}]}, "experience_required": {"duration": ["at least 8 years"], "field": ["related", "management"]}}, {"job_id": "100003009036456", "location_code": "hk", "company": "Specsavers Procurement Asia Limited", "job_title": "Financial Analyst", "description": "Company Description\n\nOur client is one of the most sophisticated fine dining restaurants in Hong Kong. Due to business needs, they are looking for the restaurant manager to join their operation team.\n\nResponsibilities\n\nPlay a big part working together with floor operation team and kitchen team\nDuties including site handover, staff recruitment, training, SOPs, menu design, trial run and full P&L responsibilities\nAct as an ambassador to maintain a good relationship with the guest and provide recommendation for food & wine pairing.\n\nRequirements\n\nDiploma in Hospitality Management / Food and Beverages or a related discipline\nMinimum 10 years\u2019 relevant experience in fine dining restaurant\nWith Michelin work experience is an advantage\nStrong leadership and customer-oriented\nPeople management skills and problem-solving skills\nInterested parties please send your updated resume in WORD format with current and expected salaries (quoting Employer Ref:)", "employment_types": ["Full Time", "Permanent"], "selling_points": ["Five-day work week; 18 days AL; work-life balance", "Flexible and friendly working environment", "Quarterly bonus; medical & dental insurance"], "locations": ["Kwun Tong"], "categories": ["Accounting", "Accounting Clerk / Supervisor", "Financial Analyst", "Others"], "post_time": "2022-01-10T10:29:37Z", "salary": {"currency": null, "max": null, "min": null, "period": "monthly", "term": null}, "salary_visible": false, "title_keywords": ["financial analyst"], "responsibilities": ["p&l", "design", "good relationship", "provide recommendation", "maintain", "recruitment", "sops"], "requirements": {"degrees": ["diploma"], "majors": ["hospitality management"], "languages": [], "language_level": [], "hard_skills": ["problem-solving skills"], "soft_skills": ["problem-solving skills", "customer-oriented", "leadership"], "languages_combined": []}, "experience_required": {"duration": ["minimum 10 years"], "field": ["restaurant", "relevant experience"]}}, {"job_id": "100003009043274", "location_code": "hk", "company": "BDO Financial Services Limited", "job_title": "Finance Manager, FP&A (Entertainment Business)", "description": "Responsibilities\nHandle full set of accounts and related financial accounting duties\nProvide daily accounting support, including analysis, related accounting reports and management reports\nDevelop financial statements, financial budgeting, cost & expenses management and control system\nPerform assigned ad-hoc reports\nJob Requirements\nDiploma or equivalent qualification\n2 - 4 years of relevant working experience\nExperience in SAP is an advantage\nAble to work independently\nWell organized and highly motivated with a positive attitude\nGood communication and interpersonal skills\nCandidate with higher capability will be considered as Accountant\nPlease send your CV with your expected salary and availability, and by quoting reference number (FAAC001) in the subject via \"Apply Now\"\n\nCandidates who are not contacted within 8 weeks should consider their application as unsuccessful.", "employment_types": ["Full Time"], "selling_points": ["Fully in charge of FP&A", "Collaboration with HK and China Business", "Entertainment Business"], "locations": ["Not Specified"], "categories": ["Accounting", "Financial Analyst", "Banking / Finance", "Corporate Finance", "Professional Services", "Company Secretary"], "post_time": "2022-01-12T10:26:57Z", "salary": {"currency": null, "max": null, "min": null, "period": "monthly", "term": null}, "salary_visible": false, "title_keywords": ["finance manager"], "responsibilities": ["ad-hoc", "cost", "management", "control", "budgeting", "analysis", "full set of accounts", "expenses", "financial statements", "develop", "management reports", "reports", "daily accounting", "accounting duties"], "requirements": {"degrees": ["diploma"], "majors": [], "languages": [], "language_level": [], "hard_skills": ["sap"], "soft_skills": ["work independently", "well organized", "positive attitude", "motivated", "communication and interpersonal skills"], "languages_combined": []}, "experience_required": {"duration": ["2 - 4 years"], "field": ["relevant working experience"]}}, {"job_id": "100003009047886", "location_code": "hk", "company": "Lexis Group Consultancy Limited", "job_title": "Senior Accountant (Financial Analysis Focus)", "description": "Our client is a HK based entertainment company and has businesses across Hong Kong, China and overseas.\u00a0 This is a newly created position and they looking for a young and energetic Finance professional to support their FP&A functions.\n\nResponsibilities:\u00a0\n\nTo drive business performance through financial planning and analysis and support decision making of business development, particularly in revenue and cost analysis, working capital and capex control, cash flow analysis, tax and operational efficiency assessment\nProvide highly relevant analytics and insight to business and financial performance, identify areas for improvement, and assist in the development and execution of strategic and operating plans\nBuild collaboration and drive effective communication partnering with operational teams for HK and China business\nOptimize planning or controlling tools and processes to increase efficiency, identify risk and opportunities to drive actions to mitigate\nPerforming other responsibilities and duties per assigned\u00a0\n\nRequirements:\n\nA qualified accountant with a degree in Finance, Accounting, Business Administration or related disciplines are preferable\nAt least 6 - 8 years relevant experience in financial analysis in sizable company and audit training in CPA firm is an advantage\nEntertainment business exposure in HK and PRC is a plus\nProficiency in Excel\nGood interpersonal, communication and presentation skills, with solid business acumen in serving the business unit\nFluent in both English, Cantonese and Mandarin (spoken and written)\nAble to work under pressure, handle multi-task and meet tight deadlines\nSolid analytical & research ability, self-motivated, and attention to details and accuracy\n\nInterested parties please send your application with full career history, current and expected salary by clicking Apply Now button. Applications will be treated in strict confidence. Personal data collected will be used for recruitment purposes only.", "employment_types": ["Full Time"], "selling_points": ["Work life balance / No OT", "Western style with dynamic fun team", "5 day work in Central"], "locations": ["Central & Western Area"], "categories": ["Accounting", "Accountant", "Finance / Accounting Manager", "Financial Analyst"], "post_time": "2022-01-14T04:08:29Z", "salary": {"currency": null, "max": null, "min": null, "period": "monthly", "term": null}, "salary_visible": false, "title_keywords": ["senior accountant"], "responsibilities": ["tax", "control", "analysis", "capex", "teams", "communication", "cash flow", "plans", "cost analysis", "planning"], "requirements": {"degrees": ["degree"], "majors": ["related disciplines", "finance", "accounting", "business administration"], "languages": ["cantonese", "english", "mandarin"], "language_level": ["fluent"], "hard_skills": ["excel", "plus", "financial analysis", "cpa", "acumen"], "soft_skills": ["meet tight deadlines", "self-motivated", "multi-task", "communication", "presentation skills", "attention to details", "business acumen", "interpersonal", "work under pressure"], "languages_combined": [{"language": "cantonese", "language_level": ["fluent"]}, {"language": "english", "language_level": ["fluent"]}, {"language": "mandarin", "language_level": ["fluent"]}]}, "experience_required": {"duration": ["at least 6 - 8 years"], "field": ["training", "cpa firm", "audit", "relevant experience", "financial"]}}, {"job_id": "100003009047333", "location_code": "hk", "company": "Global Cosmetics (HK) Company Limited", "job_title": "Senior Costing Officer", "description": "Our client is an expanding software development company with offices around the globe. Due to expansion, they would like to hire an additional Accountant to join their group company. As a Senior Accountant, you will report to the Finance Manager in Hong Kong to oversee the intercompanies of the group.\u00a0\n\nYour core duties includes but not limited to assist in the monthly consolidation process and financial statement preparation, analyze financial data regarding the actual to budget variances, identify trends, prepare financial reports to Seniors to understand the variances, prepare annual budget, assist in annual audit and tax compliance preparation for the Group.\n\nIn return, you will immense in a very flexible and chillaxing work environment. The company offers excellent staff benefits including top tier health insurance, free snack bars, gym etc.\n\nTo qualify, you should be an Associate Member / Student Member of CPA. Solid audit background from reputable CPA firms. Prior in-house experience will be an advantage. Candidate with knowledge in Xero accounting software would be an advantag . Excellent analytical skills and able to explain data to management team. High attention to details. Excellent communication skills in both written and spoken English.", "employment_types": ["Full Time"], "selling_points": ["Exp. in Manufacturing/Product Cost Management", "Familiar with KingDee ERP system is a plus", "Fluent in Mandarin"], "locations": ["Tsim Sha Tsui"], "categories": ["Accounting", "Accounting Clerk / Supervisor", "Financial Analyst", "Others"], "post_time": "2022-01-14T02:50:50Z", "salary": {"currency": null, "max": null, "min": null, "period": "monthly", "term": null}, "salary_visible": false, "title_keywords": ["officer"], "responsibilities": ["tax", "financial reports", "software", "data", "annual audit", "budget", "compliance", "financial statement", "report"], "requirements": {"degrees": [], "majors": [], "languages": [], "language_level": [], "hard_skills": [], "soft_skills": ["flexible"], "languages_combined": []}, "experience_required": {"duration": [], "field": []}}, {"job_id": "100003009042909", "location_code": "hk", "company": "Tristate Holdings Limited", "job_title": "Assistant Finance Manager", "description": "Role: Senior Costing Officer\n\nWe are looking for an experience senior costing officer, who is eager to grow in the cosmetics manufacturing industry. This role will be high demanding as we are dealing with the biggest foreign beauty brands that will require role to be highly analytical and confident in providing cost control strategies to sourcing departments and full cost analysis to sales departments to develop an impenetrable cost negotiation to our clients. This role will be reporting directly to the Head of Costing and top management.\n\nJob Description:\n\nAble work independently and proactively providing costing strategies and analysis\nProvide cost analysis to and cost control measures to all cost driving departments to assure company stays competitive\nAble to set up quotation template, SOP, and provide suggestion to cost optimize\nWork on quotation base on briefs provided by Sales Department and Product Design Department\nCalculate and prepare budget constraints to Sourcing department to execute\nCalculate and prepare budget constraint to R&D Department to establish competitive formulation cost\nCommunicate and provide guidance to Sourcing Department and R&D Department to suggest alternatives in achieving target within cost constraint\nWork on cost comparison from historical database and provide external resources to ensure cost liableness\nSearch for RFQ on different components or from various vendors to optimize costing database\nAnalyze customer's target price and provide feedback on feasibility or adjustment strategy\nLead, supervise and coordinate with costing team to perform quotation process to meet customer's target price\nReview costing exercise from subordinate before release sales department\nPrepare & Review cost breakdowns, cost summaries and GP analysis\nProvide cost reduction strategies and options to Sales Department to achieve customer's target\nSeek higher management advice and approval for a particular quotation that cannot hit customers' target under company\u2019s GP standards\nPrepare sales summary report for top management\n\n\u00a0Requirements:\n\nDiploma or above in accounting disciplines or relevant qualifications in costing\nMinimum 5 years of experience in costing\nExperience with using Cost analysis software\nFamiliar with KingDee ERP system is an advantage\nExperience in OEM/ODM cosmetics and skincare industry is preferred\nWell knowledge in manufacturing processes and product developments\nProficient with Microsoft software and other Business Intelligence software\nFluent in Mandarin is a must\nStationed in Hong Kong but Willing to Travel to China when needed", "employment_types": ["Full Time", "Permanent"], "selling_points": ["CPA, Big 4 audit background", "Listed co, flexible hour, stable environment", "Strong in HKFRS and IFRS"], "locations": ["Kwai Tsing Area"], "categories": ["Accounting", "Audit", "Finance / Accounting Manager", "Financial Analyst"], "post_time": "2022-01-12T09:13:19Z", "salary": {"currency": null, "max": null, "min": null, "period": "monthly", "term": null}, "salary_visible": false, "title_keywords": ["assistant finance manager"], "responsibilities": ["cost", "management", "analysis", "quotation", "budget", "coordinate with", "review", "prepare sales", "product design", "cost control", "database", "cost analysis", "provide guidance", "report"], "requirements": {"degrees": ["diploma or above"], "majors": ["accounting"], "languages": ["mandarin"], "language_level": ["fluent"], "hard_skills": ["analysis", "erp system", "business intelligence"], "soft_skills": [], "languages_combined": [{"language": "mandarin", "language_level": ["fluent"]}]}, "experience_required": {"duration": ["minimum 5 years"], "field": []}}]