[{"job_id": "100003009051721", "location_code": "hk", "company": "Advance Thermo Control Ltd", "job_title": "Accounting Manager", "description": "Manage the Accounting Department in Hong Kong and China\nHandle full set of account and prepare financial statements\nHandle month end closing independently\nPrepare consolidated financial statements and P & L report\nEnsure implementation of proper internal control procedures\nPrepare budget planning and cash flow forecast\nCarry annual audits and tax computation\nLiaise with Wofie accounting consultation and monitor the Wofie account reporting to the local government\u00a0\nControl and monitor the cost spent in the Company and factory\n\nREQUIREMENT\nDegree in Accounting / Finance or related disciplines\nAt least 10 years relevant experience and require daily travel to the China factory\nQualified accountant preferred\nMaintain updated accounting and taxation standard in both Hong Kong and China\nCan work under tight deadlines and pressure.\nHighly organized, detail-oriented and analytical\nStrong in Excel\nFluent written and spoken English and Chinese and Mandarin", "employment_types": ["Full Time"], "selling_points": ["5 working days", "Medical insurance", "US base company"], "locations": ["Tsuen Wan Area"], "categories": ["Accounting", "Finance / Accounting Manager"], "post_time": "2022-01-16T21:51:07Z", "salary": {"currency": null, "max": null, "min": null, "period": "monthly", "term": null}, "salary_visible": false, "title_keywords": ["accounting manager"], "responsibilities": ["reporting", "month end closing", "budget planning", "control", "tax computation", "cost", "taxation", "procedures", "implementation", "financial statements", "monitor", "liaise with", "cash flow", "maintain", "forecast", "audits", "report", "internal control"], "requirements": {"degrees": ["degree"], "majors": ["related disciplines", "finance", "accounting"], "languages": ["english", "chinese", "mandarin"], "language_level": ["fluent"], "hard_skills": ["excel", "internal control"], "soft_skills": ["organized", "independently", "detail-oriented"], "languages_combined": [{"language": "english", "language_level": ["fluent"]}, {"language": "chinese", "language_level": ["fluent"]}, {"language": "mandarin", "language_level": ["fluent"]}]}, "experience_required": {"duration": ["at least 10 years"], "field": ["relevant experience"]}}, {"job_id": "100003009054067", "location_code": "hk", "company": "The Tien Chu (Hong Kong) Company Limited", "job_title": "Accounting Manager", "description": "Responsibilities :\n\n\n\nPrepare consolidated financial statements and handle monthly closing of group companies\nHandle annual and interim audit review. Liaise with external auditors\nEngage in the publication of interim and annual reports\nPrepare statutory accounts and tax filings\nPerform financial analysis\nAssist in ad-hoc tasks as assigned by management\n\nRequirements:\n\n\n\nDegree holder in Accounting or related disciplines\nQualified Accountant of HKICPA or other recognized professional accounting bodies is advantage\nMinimum of 5 years\u2019 working experience in Manufacturing / Trading Company fields;\nExperience in group consolidation, familiar with PRC accounting and tax practices is an added advantage\nDetail-oriented, well-organized, self-motivated with strong sense of responsibility\nHigh competence in written and spoken English and Chinese; proficiency in Putonghua is an advantage;\nAttention to details and accuracy with strong sense of urgency\n\n\n\nWe offer competitive package to right candidate, including but unlimited double pay, performance bonus, free lunch, shuttle bus, education allowance, housing allowance, Medical and other benefits.\n\nWorking hours : Monday to Friday 9:00am to 5:00pm & Saturday 9:00am to 12:00noon\n\nInterested parties please send full resume in Chinese and English in strict confidence with expected salary & earliest availability to us for interview.\n\nFor more details, please visit www.tienchu.com\n\n(Personal data collected is solely for recruitment related purpose\u00a0and will be treated in strict confidence.)", "employment_types": ["Full Time", "Permanent"], "selling_points": ["Accountant", "Manufacturing / Trading Company", "Double pay, bonus, free lunch, shuttle, medical"], "locations": ["Tsing Yi"], "categories": ["Accounting", "Audit", "Finance / Accounting Manager", "Financial Analyst"], "post_time": "2022-01-17T08:17:19Z", "salary": {"currency": null, "max": null, "min": null, "period": "monthly", "term": null}, "salary_visible": false, "title_keywords": ["accounting manager"], "responsibilities": ["tax", "management", "ad-hoc tasks", "review", "audit", "financial statements", "financial analysis", "reports", "liaise with", "publication", "external auditors"], "requirements": {"degrees": ["degree holder"], "majors": ["related disciplines", "accounting"], "languages": ["putonghua", "english", "chinese"], "language_level": ["advantage", "proficiency"], "hard_skills": ["prc accounting", "hkicpa"], "soft_skills": ["self-motivated", "sense of responsibility", "urgency", "well-organized", "detail-oriented", "attention to details"], "languages_combined": [{"language": "putonghua", "language_level": ["proficiency", "advantage"]}, {"language": "english", "language_level": []}, {"language": "chinese", "language_level": []}]}, "experience_required": {"duration": ["minimum of 5 years"], "field": ["manufacturing", "trading", "consolidation", "accounting"]}}, {"job_id": "100003009051656", "location_code": "hk", "company": "Art-Ko Far East Limited", "job_title": "FINANCE MANAGER", "description": "\u2022\u00a0\u00a0 Diploma or Degree Holder in Accounting or related discipline.\n\n\u2022\u00a0\u00a0 At least 5 years accounting experience with minimum 3 years at the managerial level.\n\n\u2022\u00a0\u00a0 Hands-on experience of PRC accounting and taxation; familiar with HK & PRC Laws,\n\n\u2022\u00a0\u00a0 Accounting and taxation matters.\n\n\u2022\u00a0\u00a0 Handle all HR, administration duties, management reporting, budgeting & forecasting,\n\n\u2022\u00a0\u00a0 Review business performance, and ad-hoc projects as assigned.\n\n\u2022\u00a0\u00a0 Liaise with external auditors, bankers & MPF provider.\n\n\u2022\u00a0\u00a0 Good command in spoken and written English & Mandarin\n\n\u2022\u00a0\u00a0 Detail-oriented, well-organized and hardworking with strong sense of responsibility\n\n\u2022\u00a0\u00a0 Immediate availability or short notice is a must.\n\nWe offer medical and bonus scheme. Interested parties please send your resume with expected\nsalary to Mr Tse by clicking \"Apply Now\",\n\nPersonal data collected will be used for recruitment purpose only.\n", "employment_types": ["Full Time", "Permanent"], "selling_points": [], "locations": ["Shatin Area"], "categories": ["Accounting", "Finance / Accounting Manager", "Taxation", "Others"], "post_time": "2022-01-16T21:50:31Z", "salary": {"currency": null, "max": null, "min": null, "period": "monthly", "term": null}, "salary_visible": false, "title_keywords": ["finance manager"], "responsibilities": ["taxation", "mpf", "budgeting", "hr", "review", "external auditors", "management reporting", "liaise with", "ad-hoc projects", "forecasting", "administration"], "requirements": {"degrees": ["diploma", "degree holder"], "majors": ["accounting"], "languages": ["english", "mandarin"], "language_level": ["good command"], "hard_skills": ["prc accounting"], "soft_skills": ["sense of responsibility", "well-organized", "detail-oriented", "hands-on", "hardworking"], "languages_combined": [{"language": "english", "language_level": ["good command"]}, {"language": "mandarin", "language_level": ["good command"]}]}, "experience_required": {"duration": ["at least 5 years", "minimum 3 years"], "field": ["managerial", "accounting experience", "accounting"]}}, {"job_id": "100003009052581", "location_code": "hk", "company": "Sunlight Jewelers Limited", "job_title": "Accounts Manager", "description": "Responsibilities & Requirements\u8077\u8cac\u53ca\u8981\u6c42\n\n\u00a0\u00a0\u00a0\u00a0\u00a0\u00a0\u00a0 Minimum 5 years relevant experience in Jewellery industry\n\u00a0\u00a0\u00a0\u00a0\u00a0\u00a0\u00a0 Able to handle full set of accounts\n\u00a0\u00a0\u00a0\u00a0\u00a0\u00a0\u00a0 Costing knowledge\n\u00a0\u00a0\u00a0\u00a0\u00a0\u00a0\u00a0 Willing to work under pressure\n\u00a0\u00a0\u00a0\u00a0\u00a0\u00a0\u00a0 Good interpersonal & communication skills, responsible and self-motivated\n\u00a0\u00a0\u00a0\u00a0\u00a0\u00a0\u00a0 Experience in MYOB & PJS is preferable\n\u00a0\u00a0\u00a0\u00a0\u00a0\u00a0\u00a0 Fluent in written and spoken English\n\nWe offer 5 \u00bd-day work, Medical Scheme & Bank holidays to the right candidate.\u00a0 Interested parties, please send FULL RESUME with expected salary to: \"Apply Now\".", "employment_types": ["Full Time"], "selling_points": [], "locations": ["Hung Hom"], "categories": ["Accounting", "Accountant", "Finance / Accounting Manager", "Others"], "post_time": "2022-01-17T03:28:06Z", "salary": {"currency": null, "max": null, "min": null, "period": "monthly", "term": null}, "salary_visible": false, "title_keywords": ["manager"], "responsibilities": [], "requirements": {"degrees": [], "majors": [], "languages": ["english"], "language_level": ["fluent"], "hard_skills": ["myob"], "soft_skills": ["communication skills", "self-motivated", "responsible", "interpersonal", "work under pressure"], "languages_combined": [{"language": "english", "language_level": ["fluent"]}]}, "experience_required": {"duration": ["minimum 5 years"], "field": ["relevant experience"]}}, {"job_id": "100003009034609", "location_code": "hk", "company": "Putien Restaurant (H.K.) Limited", "job_title": "Assistant Finance Manager", "description": "Responsibilities:\u00a0\n\nLeading a team to manage day-to-day accounting, treasury and tax functions of the company\n\nOversee the month-end closing, budgeting/forecasting and interim/audit processes\n\nResponsible for monthly/quarterly management reports and packages to shareholders\nResponsible for the preparation of statutory financial statements, periodic tax and statutory returns with the tax authorities and other regulatory bodies\nWork closely with division/department users and provide insightful suggestions to facilitate business performance review and decision-making\nPerform ad hoc assignments and projects as required\n\n\u00a0\u00a0Requirements:\u00a0\n\nBachelor degree in Accounting, Finance or other related disciplines (with an internationally recognised accounting qualification)\nAt least 5 years of professional experience in accounting or auditing\u00a0\nHave a strong commercial acumen, strong written reporting and communication skills\nAbility to work well under pressure, working accurately with attention to detail, and meeting deadlines\nGood command of both written and spoken English and Chinese\n\nWe offer 5-day work week, competitive remuneration packages and advancement opportunities to the right candidate. Interested parties please apply with detailed resume with expected salary and contact numbers to the H.R. Department by email.", "employment_types": ["Full Time"], "selling_points": [], "locations": ["Tsuen Wan Area"], "categories": ["Accounting", "Finance / Accounting Manager", "Others", "Hospitality / F & B", "Food & Beverage"], "post_time": "2022-01-17T04:38:55Z", "salary": {"currency": null, "max": null, "min": null, "period": "monthly", "term": null}, "salary_visible": false, "title_keywords": ["assistant finance manager"], "responsibilities": ["tax", "budgeting", "review", "audit", "financial statements", "management reports", "month-end closing", "ad hoc assignments", "forecasting"], "requirements": {"degrees": ["degree", "bachelor"], "majors": ["related disciplines", "finance", "accounting"], "languages": ["english", "chinese"], "language_level": ["good command"], "hard_skills": ["acumen"], "soft_skills": ["communication skills", "under pressure", "attention to detail"], "languages_combined": [{"language": "english", "language_level": ["good command"]}, {"language": "chinese", "language_level": ["good command"]}]}, "experience_required": {"duration": ["at least 5 years"], "field": ["accounting"]}}, {"job_id": "100003009054564", "location_code": "hk", "company": "Foodgears Industrial International Limited", "job_title": "Management Accounting Manager", "description": "Responsibilities:\n\nDrive the financial planning of the company by analyzing its performance and risks\nSet targets for and supervise all accounting and finance personnel (management accountants, internal auditors etc.)\nOversee all audit and internal control operations\nPrepare timely and detailed reports on financial performance on a quarterly and annual basis\nConduct analysis to make forecasts and report to upper executives\nEnsure adherence to financial laws and guidelines\n\n\u00a0\nRequirements:\n\nProven experience as director of finance or similar role\nIn-depth knowledge of corporate finance and accounting principles, laws and best practices\nSolid knowledge of financial analysis and forecasting\nProficient in the use of MS Office and financial management software\nAn analytical mind with a strategic ability\nExcellent organizational and leadership skills\nOutstanding communication and interpersonal abilities\nCPA or other relevant qualification and China Accounting experience is a plus\n\n\n\nWe offer attractive remuneration package to the right candidate.\u00a0 Interested parties please send full resume with present & expected salary and available date by clicking \"Apply Now\".\n\n\nAll Personal data collected will be used for recruitment purposes only.\n", "employment_types": ["Permanent"], "selling_points": [], "locations": ["Wong Tai Sin Area"], "categories": ["Accounting", "Finance / Accounting Manager", "Financial Analyst", "Financial Controller"], "post_time": "2022-01-17T10:00:39Z", "salary": {"currency": null, "max": null, "min": null, "period": "monthly", "term": null}, "salary_visible": false, "title_keywords": ["accounting manager"], "responsibilities": ["management", "guidelines", "operations", "analysis", "ensure adherence", "audit", "planning", "reports", "report", "internal control"], "requirements": {"degrees": [], "majors": [], "languages": [], "language_level": [], "hard_skills": ["financial analysis", "cpa", "plus", "ms office"], "soft_skills": ["organizational", "leadership skills", "communication", "analytical mind", "interpersonal"], "languages_combined": []}, "experience_required": {"duration": [], "field": ["finance", "accounting experience"]}}, {"job_id": "100003009052995", "location_code": "hk", "company": "LGMG International Limited", "job_title": "Accounting Manager/Assistant Accounting Manager", "description": "Responsibilities\n\u00a0\n\n\nLiaise with suppliers, customers and financial institutions regarding finance and trade matters\nResponsible for week, month and year-end accounting closures\nPrepare budget, forecast and costing analysis\nMaintaining proper record keeping/filings\nProvide full spectrum of accounting and trade matters reporting\nUndertake ad hoc duties and responsibilities as assigned by the Board\n\nRequirements\n\n\nDegree holder in Accounting/Finance or related disciplines\n3-5 years or above experiences in accounting/import and export trade or related disciplines\nWork independently with suppliers, well-organized and self-motivated\nStrong interpersonal, communication skills and able to multi-task\nProficiency in MS Office applications\nGood command of both written and spoken English, Cantonese and Mandarin\nCandidate with less experience will be considered as Assistant Accounting Manager\nOccasional travel is required\nImmediately available is highly preferred\n\n\n\nInterested parties please send application with full CV with your current and expected salary by clicking \"Apply Now\"\nAll Personal data collected will be used for recruitment purpose only.", "employment_types": ["Full Time"], "selling_points": [], "locations": ["Wan Chai"], "categories": ["Accounting", "Accounting Clerk / Supervisor", "Finance / Accounting Manager"], "post_time": "2022-01-17T06:08:12Z", "salary": {"currency": null, "max": null, "min": null, "period": "monthly", "term": null}, "salary_visible": false, "title_keywords": ["assistant accounting manager", "accounting manager"], "responsibilities": ["ad hoc duties", "year-end", "reporting", "maintaining", "budget", "forecast", "costing analysis", "liaise with suppliers"], "requirements": {"degrees": ["degree holder"], "majors": ["related disciplines", "finance", "accounting"], "languages": ["cantonese", "english", "mandarin"], "language_level": ["good command"], "hard_skills": ["import and export", "ms office"], "soft_skills": ["communication skills", "work independently", "self-motivated", "multi-task", "well-organized", "interpersonal"], "languages_combined": [{"language": "cantonese", "language_level": ["good command"]}, {"language": "english", "language_level": ["good command"]}, {"language": "mandarin", "language_level": ["good command"]}]}, "experience_required": {"duration": ["3-5 years"], "field": ["related", "accounting"]}}, {"job_id": "100003009054541", "location_code": "hk", "company": "China Eagle Management Limited", "job_title": "Accountant / Finance Manager (5-day work)", "description": "\u00a0Responsibilities:\n\n\u00a0Assist to Finance Manager to oversee finance and accounting functions of the group and ensure compliance with the Hong Kong Listing Rules, International Accounting Standards (\u201cIAS\u201d) and the Companies Ordinance\nPrepare monthly consolidated financial information for the Group and co-ordinate to issue notices, announcements and circulars for compliance with the Listing Rules and other statutory requirements\nPrepare annual, interim and quarterly financial reports and relevant disclosure notes and liaise with external auditors in all aspects of the financial reporting\nPrepare financial analysis, budgeting, forecast, cash flow projection, and management reports\nAssist in managing funds and liaison with banks\nAssist in reviewing, monitoring and enhancing internal controls of the Group\nAssist in tax planning, treasury functions and any ad hoc projects for the Group\n\nRequirements:\n\nDegree holder in Accounting and possess HKICPA/ACCA or other equivalent\n4-5 years of relevant work experienceof which at least 1-2 years in a Hong Kong listed company.\nStrong analytical and excellent interpersonal skills\nPositive attitude, good team work ethic , highly responsibility and able to work under pressure\nDriven, enthusiastic, highly self-motivated, and able to operate independently\nConversant in accounting principles; experience in tax issues and legal practice preferred\nExcellent communication skills, fluent in English, Cantonese and Mandarin\nCandidates with more working experience will be considered as senior position", "employment_types": ["Full Time"], "selling_points": ["oversee finance and accounting functions", "1-2 years in a Hong Kong listed company", "5-day work & medical insurance"], "locations": ["Central"], "categories": ["Accounting", "Accountant", "Finance / Accounting Manager", "Treasurer"], "post_time": "2022-01-17T09:56:44Z", "salary": {"currency": null, "max": null, "min": null, "period": "monthly", "term": null}, "salary_visible": false, "title_keywords": ["accountant", "finance manager"], "responsibilities": ["tax", "financial reports", "budgeting", "compliance", "monitoring", "ensure compliance", "financial analysis", "statutory requirements", "cash flow", "management reports", "planning", "financial reporting", "forecast", "ad hoc projects", "liaise with", "listing", "external auditors"], "requirements": {"degrees": ["degree holder"], "majors": ["accounting"], "languages": ["cantonese", "english", "mandarin"], "language_level": ["excellent", "fluent"], "hard_skills": ["acca", "hkicpa"], "soft_skills": ["good team work", "communication skills", "self-motivated", "independently", "positive attitude", "interpersonal skills", "enthusiastic", "driven", "work under pressure"], "languages_combined": [{"language": "cantonese", "language_level": ["excellent", "fluent"]}, {"language": "english", "language_level": ["excellent", "fluent"]}, {"language": "mandarin", "language_level": ["excellent", "fluent"]}]}, "experience_required": {"duration": [], "field": ["legal"]}}, {"job_id": "100003009053831", "location_code": "hk", "company": "Sime Darby Motor Services Limited", "job_title": "Assistant Manager - Finance  (JDB/SDMSL/AFM/20220117)", "description": "To cope with our business growth and expansion, we are currently looking for an individual with high caliber to join our team.\n\nJob Responsibilities:\n\nAssist in overseeing all aspects of finance and accounting operations of group companies in multi-franchise motor and motor insurance\u00a0businesses in HK\nPrepare hands-on financial reporting and analysis for business line / management review\nLead the finance team to troubleshoot all month-end closing matters and ensure timely completion of monthly / quarterly\u00a0group reporting submission\nPrepare the annual budget and rolling forecast\nCo-ordinate and support the operational units through ascertaining their needs and recommending solutions to business and financial problems\nMonitor and ensure compliance with corporate policies and guidelines and statutory requirements\nHandle statutory audit and prepare audited financial statements\nReview and drive the enhancement of internal control procedure as well as streamline the financial processes and participate in system enhancements\nLiaise and work closely with finance service center team in Kuala Lumpur, operational units, external auditors and relevant professionals\nParticipate in ad hoc projects as assigned\n\nRequirements:\u00a0\n\nDegree holder in Finance or Accounting discipline\nQualified HKICPA or equivalent internationally recognized accounting qualification\nMinimum 8 years of working experience in accounting field and auditing field\u00a0gained in sizable organization\u00a0with some managerial experience\nSubsidiary level reporting experience in matrix organization or experience in motor industry would be a definite advantage\nStrong financial analysis mindset with business sense\nWilling to work overtime (weekend/ public holiday overtime work for monthly closing with compensation leave)\nProactive, detail-oriented\u00a0with good analytical and problem-solving capabilities\nAbility to work independently with minimal supervision\nWilling to take challenges and able to multitask in a demanding and fast-paced environment and meet tight reporting timeline\nGood interpersonal skills and able to communicate effectively with all levels\nGood command of both spoken and written English and Chinese\nImmediately availability is highly preferred\nWork location: Tsuen Wan (near MTR)\n\nWe offer attractive remuneration package, 5-day work week, competitive fringe benefits and excellent career development opportunity to the right candidate. Interested parties please send your full resume quoting job reference number with present salary, expected salary and\u00a0available date via e-mail to\u00a0ghr-recruitment.sdms @simedarby.com.hk\u00a0\n\nFor more information about us, please visit our\u00a0Website.\nFollow us on\u00a0our\u00a0LinkedIn\u00a0and stay tuned!\n\nAll information provided by applicants will be treated in strict confidence and used for recruitment purpose only.", "employment_types": ["Full Time", "Permanent"], "selling_points": ["Bachelor Degree Holder with HKICPA / Equivalent", "Subsidiary level reporting experience", "Minimum of 8 years in sizable organizations"], "locations": ["Tsuen Wan Area"], "categories": ["Accounting", "Accountant", "Audit", "Finance / Accounting Manager"], "post_time": "2022-01-17T07:35:53Z", "salary": {"currency": null, "max": null, "min": null, "period": "monthly", "term": null}, "salary_visible": false, "title_keywords": ["assistant manager"], "responsibilities": ["liaise", "operations", "budget", "audit", "financial statements", "statutory requirements", "troubleshoot", "management review", "internal control", "monitor", "finance team", "reporting", "review", "rolling forecast", "guidelines", "policies", "analysis", "ensure compliance", "month-end closing", "ad hoc projects", "financial reporting", "insurance", "external auditors"], "requirements": {"degrees": ["degree holder"], "majors": ["finance", "accounting"], "languages": ["english", "chinese"], "language_level": ["good command"], "hard_skills": ["financial analysis", "problem-solving", "hkicpa"], "soft_skills": ["work overtime", "work independently", "business sense", "fast-paced environment", "problem-solving", "detail-oriented", "multitask", "overtime work", "interpersonal skills", "proactive"], "languages_combined": [{"language": "english", "language_level": ["good command"]}, {"language": "chinese", "language_level": ["good command"]}]}, "experience_required": {"duration": ["minimum 8 years"], "field": ["sizable organization", "managerial", "accounting"]}}, {"job_id": "100003009052550", "location_code": "hk", "company": "The Luxe Manor", "job_title": "Financial Controller / Assistant Financial Controller", "description": "Responsibilities:\nOversee the finance and accounting functions\n\nHandle all aspects of financial controls, reviews and planning\n\nCompile financial budget and perform operational and costing analysis\n\nHighlight and investigate significant issues of operating units, make recommendations on corrective measures\n\nConduct independent review and evaluations of operating units\u2019 financial / operational policies and procedures for the purpose of improving the efficiency and effectiveness\n\nEnforce internal control systems to ensure that the assets, revenues and costs are under effective control\n\nImplement cost effective control policies and procedures, ensure that the internal control systems operate properly and comply with Group and Company policies\n\nRequirements:\nDegree holder in Accounting / Finance or equivalent and with a recognized accounting qualification, preferable ACCA/HKICPA/AICPA\n\nMinimum 10 years\u2019 managerial experience in financial control function in sizable organization and accounting experience in HK listed or multinational corporations\n\nStrong business sense, proven management, analytical and leadership skills\n\nExcellent interpersonal and communication skills and ability to collaborate with all departments in an organization\n\nGood understanding of HK & China accounting rules and regulations\n\nFamiliar with HK & China operations in finance, taxation and audit\n\nSolid hotel experience\n\nInterested parties please send your detailed resume with current and expected salary by clicking Apply Now.\n\nAll applications will be handled in the strictest confidence and personal data collected will be used for recruitment purposes only. Applicants not invited for an interview within 6 weeks may consider their applications unsuccessful. Applicant contact details will be held for 6 months, from the date of application.", "employment_types": ["Full Time"], "selling_points": ["Compile financial budget", "Enforce internal control systems", "Minimum 10 years\u2019 relevant experience"], "locations": ["Not Specified"], "categories": ["Accounting", "Finance / Accounting Manager", "Financial Controller"], "post_time": "2022-01-17T03:24:03Z", "salary": {"currency": null, "max": null, "min": null, "period": "monthly", "term": null}, "salary_visible": false, "title_keywords": ["assistant financial controller", "financial controller"], "responsibilities": ["make recommendations", "control", "cost", "policies", "review", "budget", "procedures", "systems", "costing analysis", "internal control", "costs", "planning"], "requirements": {"degrees": ["degree holder"], "majors": ["finance", "accounting"], "languages": [], "language_level": [], "hard_skills": ["acca", "hkicpa"], "soft_skills": ["communication skills", "leadership skills", "interpersonal", "business sense"], "languages_combined": []}, "experience_required": {"duration": ["minimum 10 years"], "field": ["sizable organization", "managerial", "accounting experience", "financial"]}}, {"job_id": "100003009050044", "location_code": "hk", "company": "Summergate Limited", "job_title": "Finance Manager / Assistant Controller", "description": "Reporting to Financial Controller, you will lead a finance team to cover all financial functions in HK and MC, and you\u2019ll also need to work collaboratively with people across the business at all levels.\n\nKEY RESPONSIBILITIES\n\nOverseeing all finance, accounting, tax, treasury, and company secretarial matters for Summergate HK and MC entities.\nFull responsibility for balance sheet control and reconciliations to ensure integrity of financial and accounting information.\nEnsure timely and accurate closing and reporting to head quarter.\nLead the relations with auditors, tax agents, and other external parties to manage statutory obligations for the entities.\nLead the finance team to manage day-to-day operations and finance administrative issues.\nDrive and deliver continuous improvement initiatives across end-to-end business processes, systems and reporting to align head quarter guidance and controls.\nAssist in yearly budget process for HKMC entities, and coordinate with the FP&A team in head quarter to provide business analysis to local business partners.\nMonitor and manage cash flow projections for HKMC entities, and ensure controls over fund transfers and cash management.\nLead, train, and coach the team members to build and maintain a sustainable team to support the local business.\nPerform other ad-hoc projects/assignments as required.\n\nKEY COMPETENCIES / EXPERIENCE\u00a0\n\nMinimum 8 years+ in finance accounting , with above 2-3 years\u2019 experience in managing full-scope finance functions in MNC or sizable local corporations;\nCA/CPA qualification preferred.\nExperience with JDE or Dynamic 365 highly advantageous;\nExperience in a big-4 or other accounting firm desirable;\nStrong leadership with the ability to drive and execute improvements;\nStrong inter-personal and communication skills with good command in written and spoken English. Chinese not essential but advantageous.\nCan-do attitude with strong sense of ownership.\nSelf-motivated and able to work under pressure;\nAbility to be hands on where necessary;", "employment_types": ["Full Time", "Permanent"], "selling_points": [], "locations": ["Lai Chi Kok"], "categories": ["Accounting", "Finance / Accounting Manager", "Financial Controller"], "post_time": "2022-01-14T09:41:00Z", "salary": {"currency": null, "max": null, "min": null, "period": "monthly", "term": null}, "salary_visible": false, "title_keywords": ["finance manager", "assistant"], "responsibilities": ["external parties", "day-to-day operations", "budget", "communication", "maintain", "ad-hoc projects", "work under pressure", "control", "monitor", "finance team", "balance sheet", "reporting", "guidance", "management", "coordinate with", "reconciliations", "cash flow", "tax", "systems", "business analysis"], "requirements": {"degrees": [], "majors": [], "languages": ["english", "chinese"], "language_level": ["good command"], "hard_skills": ["cpa", "analysis", "dynamic"], "soft_skills": ["communication skills", "self-motivated", "inter-personal", "can-do attitude", "timely", "integrity", "dynamic", "hands on", "accurate", "leadership", "work under pressure"], "languages_combined": [{"language": "english", "language_level": ["good command"]}, {"language": "chinese", "language_level": []}]}, "experience_required": {"duration": ["2-3 years"], "field": ["finance", "accounting"]}}, {"job_id": "100003009054922", "location_code": "hk", "company": "Sun Hung Kai Properties Ltd", "job_title": "FINANCIAL CONTROLLER \u2013 HOTEL DIVISION", "description": "Requirements:\n\n\nBachelor\u2019s degree holder, with CPA or other professional qualification in accounting. Prior working experience in audit preferred\nAt least 15 years\u2019 working experience, including relevant experience as Director of Finance in sizable hotels with extensive F&B and other facilites\nSolid working experience for hotels in Hong Kong and mainland China\nStrong analytical skills, good business acumen and ownership perspective\nBe resilient and able to cope with high work pressure and demanding deadlines\nHighly motivated, detail-minded and result oriented with multi-tasking skills\nProactive and a good team player\nGood communication and interpersonal skills\nProficient in both spoken and written English and Chinese\n\nResponsibilities:\n\n\nResponsible for the overall accounting and financial review matters, including reporting and analysis of the portfolio hotels in Hong Kong and mainland China\nWorking closely with headquarter corporate offices and finance teams of portfolio hotels\nProvide consolidated management reports and analysis with value-added views on business and good interpretation of financial data\nPerform regular reviews on financial controls\n\nGood remuneration and attractive fringe benefits will be offered to the successful applicant. Interested parties please apply with full resume, present and expected salary, available date by clicking \u201cApply Now\u201d.\n\nFor further information, please visit our company website: http://www.shkp.com/.\n\nWe are an equal opportunity employer and welcome applications from all qualified candidates. All personal data collected will be used for recruitment purpose only.\u00a0 Applicants not hearing from us within 3 months may consider their applications unsuccessful.\u00a0 All personal data collected will be destroyed within 24 months.", "employment_types": ["Full Time", "Permanent"], "selling_points": ["Bachelor degree with CPA qualification", "Exp as Director of Finance in sizable hotels", "Accounting & financial review of HK & PRC hotels"], "locations": ["Wan Chai"], "categories": ["Accounting", "Finance / Accounting Manager", "Financial Analyst", "Financial Controller"], "post_time": "2022-01-17T14:01:55Z", "salary": {"currency": null, "max": null, "min": null, "period": null, "term": null}, "salary_visible": false, "title_keywords": ["financial controller"], "responsibilities": ["reporting", "data", "analysis", "review", "teams", "management reports"], "requirements": {"degrees": ["bachelor", "degree holder"], "majors": ["accounting"], "languages": ["english", "chinese"], "language_level": ["proficient"], "hard_skills": ["cpa", "acumen", "analytical skills"], "soft_skills": ["detail-minded", "good team player", "multi-tasking skills", "analytical skills", "result oriented", "motivated", "communication and interpersonal skills", "business acumen", "proactive", "extensive"], "languages_combined": [{"language": "english", "language_level": ["proficient"]}, {"language": "chinese", "language_level": ["proficient"]}]}, "experience_required": {"duration": ["at least 15 years"], "field": ["finance", "audit", "f&b", "relevant experience", "hotels"]}}, {"job_id": "100003009052940", "location_code": "hk", "company": "EB Services Limited", "job_title": "Assistant Manager (Treasury Operation)", "description": "To cope with the continuous business expansion of the Company, we invite talented and professional candidate to join our growing team:\n\nJob Descriptions\n\nThe candidate needs to coordinate directly and liaise with various Hong Kong and overseas departments to ensure all treasury banking services are provided to meet operation requirements in a timely cost-efficient manner.\n\nResponsibilities:\nLead a small team for daily operations of treasury functions, including but not limit to customer accounts & commission payments.\nMonitor and manage the funding requirements.\nSupport bank account opening & closing, authorized signatories updated, and ensure electronic banking is operated in a secured manner.\nLiaise with external banks, online payment/collection gateways and other financial services providers for system interface and daily banking transactions.\nRecommend and implement ideas and innovations to improve upon existing systems, work processes and procedures on commission verification, commission payments and refund process.\nAble to build good relationship with internal customers and external stakeholders.\nParticipate in the development & enhancement of cash management systems, treasury management systems, online banking linkage with ERP systems, straight-through-payment process systems, online collection/payment gateway systems, to improve treasury operation processes & control and manage risks exposure.\n\nRequirements:\n\nBachelor\u2019s degree in Accounting or Finance.\nOver 7 years\u2019 experience from multinational companies is preferred.\nExperience in retail / e-commerce / direct selling industry experience is an advantage.\nExcellent analytical, critical thinking and troubleshooting skills.\nAble to manage multiple items simultaneously and prioritize appropriately.\nDemonstrates initiative in anticipating and solving issues; self-motivated and naturally inquisitive.\nGood verbal / written communication skills in both Chinese and English.\nStrong PC skills, especially in Excel (e.g., Marco, VBA), Smart Sheet, database & etc.\nImmediate available is highly preferred.", "employment_types": ["Full Time", "Permanent"], "selling_points": ["5 Days work week", "Medical benefits, life insurance", "Flexible working hours"], "locations": ["Ngau Tau Kok"], "categories": ["Accounting", "Finance / Accounting Manager", "Others"], "post_time": "2022-01-17T04:37:25Z", "salary": {"currency": null, "max": null, "min": null, "period": "monthly", "term": null}, "salary_visible": false, "title_keywords": ["assistant manager"], "responsibilities": ["cost", "lead a small team", "coordinate", "daily operations", "payments", "banking", "liaise with"], "requirements": {"degrees": ["degree", "bachelor"], "majors": ["finance", "accounting"], "languages": ["english", "chinese"], "language_level": ["good"], "hard_skills": ["erp systems", "excel", "vba", "e-commerce", "account opening", "marco", "pc skills"], "soft_skills": ["communication skills", "self-motivated", "troubleshooting", "prioritize", "initiative"], "languages_combined": [{"language": "english", "language_level": ["good"]}, {"language": "chinese", "language_level": ["good"]}]}, "experience_required": {"duration": ["7 years"], "field": ["retail", "e-commerce"]}}, {"job_id": "100003009053700", "location_code": "hk", "company": "PwC", "job_title": "Manager - Finance Practice Support - PwC Tax - Hong Kong", "description": "Duties\n\nAssist in preparing and reviewing financial management and statistics reports\nPerform analytical review on financial results\nPerform data quality review on Tax systems\nCarry out monthly actions to improve financial management\nAssist in financial projects and ad-hoc assignments\nAssist in financial reports automation\nManage database / systems\nCo-ordinate with departments, e.g., GTS, Central FIN, Client First team, etc. on Tax finance matters\n\n\u00a0Requirements\n\nBachelor degree in any discipline\nMinimum 5 years\u2019 experience in Finance in MNC or professional services firm is preferred\nGood logical and analytical skill\nGood coordination, interpersonal and problem-solving skills\nGood project management skill\nAble to manage multiple tasks under deadlines while maintaining quality of work delivered\nAble to communicate with impact to peer groups, leaders and stakeholders\nAble to maintain good relationship with teammates and users\nDemonstrate creativity and able to contribute new ideas and knowledge where appropriate\nOpen minded, agile with change and practical\nCommitted to self-development and coaching of others for growth\nProficient in MS Office, especially in MS Excel & PowerPoint.\u00a0 Experience in using Outlook and technology tools such as Alteryx and Power BI, is a desirable\nGood in both spoken and written English and Chinese", "employment_types": ["Full Time", "Permanent"], "selling_points": ["Financial Management for Tax Practice", "ex-Professional Staff welcome", "Urgent Hire"], "locations": ["Central"], "categories": ["Accounting", "Finance / Accounting Manager", "Financial Controller"], "post_time": "2022-01-17T07:22:26Z", "salary": {"currency": null, "max": null, "min": null, "period": "monthly", "term": null}, "salary_visible": false, "title_keywords": ["manager"], "responsibilities": ["tax", "management", "financial reports", "data", "co-ordinate with", "ad-hoc assignments", "review", "quality", "systems", "reports", "database"], "requirements": {"degrees": ["degree", "bachelor"], "majors": [], "languages": ["english", "chinese"], "language_level": ["good"], "hard_skills": ["analytical skill", "bi", "agile", "powerpoint", "project management", "ms excel", "outlook", "alteryx", "problem-solving skills", "ms office"], "soft_skills": ["analytical skill", "agile", "multiple tasks", "committed", "open minded", "coordination", "project management skill", "problem-solving skills", "interpersonal"], "languages_combined": [{"language": "english", "language_level": ["good"]}, {"language": "chinese", "language_level": ["good"]}]}, "experience_required": {"duration": ["minimum 5 years"], "field": ["finance"]}}, {"job_id": "100003009051539", "location_code": "hk", "company": "Shaw Brothers Holdings Limited", "job_title": "Administrative & Finance Manager", "description": "Responsibilities:\nProvide full spectrum of administrative and human resources supports\nWork in our accounting team in Group Finance to provide professional accounting services to different business units and to ensure proper accounting control in place\nFully conversant in Hong Kong employment-related ordinances and rules & regulations\nReview and ensure policies and procedures are in alignment with operation needs and in compliance with labour regulations\nCompile various reports and analysis for management\u2019s review\nSupport budget and forecast exercise\nHandling Contract and Correspondence\nBe fully responsible and to be proactive for all aspects of Company operations, and to provide solutions and recommendations to management\u00a0\nBe responsible for audit, tax return and other statutory reports filings\nPerform Ad-Hoc duties as assigned\n\u00a0Requirements :\nDegree Holder in Business Administration / Language / Communications / Finance or related disciplines\nFamiliar with HK & PRC accounting standard and statutory requirements\nMinimum 4-6 years of experience in Administration & Finance\nExperience in PRC enterprise is an advantage\nPreferably in sizable company\nPreferred experience in Entertainment or Production Industry\nAbility to work independently , tactful and under pressure\nPositive attitude and have strong sense of responsibility\nExcellent command of spoken and written Chinese and English including Cantonese and Putonghua\nProficiency in MS Office application and Chinese word processing\nImmediate available is highly preferred\nCandidates with less experience and lower qualifications will be considered for the position of\u00a0 Assistant Manager (Admin & Finance)\nCandidates will have written test during the interview", "employment_types": ["Full Time"], "selling_points": ["Administration", "Tseung Kwan O Industrial Estate", "Finance"], "locations": ["Tseung Kwan O"], "categories": ["Accounting", "Finance / Accounting Manager", "Admin & HR", "Clerical / Admin Staff", "HR Supporting Staff"], "post_time": "2022-01-16T08:53:56Z", "salary": {"currency": null, "max": null, "min": null, "period": "monthly", "term": null}, "salary_visible": false, "title_keywords": ["administrative & finance manager"], "responsibilities": ["regulations", "tax", "control", "management", "policies", "analysis", "review", "procedures", "compliance", "budget", "operations", "provide solutions", "audit", "reports", "forecast", "ad-hoc duties"], "requirements": {"degrees": ["degree holder"], "majors": ["related disciplines", "finance", "business administration", "communications"], "languages": ["cantonese", "putonghua", "english", "chinese"], "language_level": ["excellent", "proficiency"], "hard_skills": ["chinese word processing", "ms office", "prc accounting"], "soft_skills": ["work independently", "under pressure", "sense of responsibility", "positive attitude", "tactful"], "languages_combined": [{"language": "cantonese", "language_level": ["excellent"]}, {"language": "putonghua", "language_level": ["excellent"]}, {"language": "english", "language_level": ["excellent"]}, {"language": "chinese", "language_level": ["excellent", "proficiency"]}]}, "experience_required": {"duration": ["minimum 4-6 years"], "field": ["finance", "admin", "administration"]}}, {"job_id": "100003009046691", "location_code": "hk", "company": "International Beverage Holdings Ltd", "job_title": "Finance Manager", "description": "Preparation of monthly consolidated management reports and analysis\nPreparation of annual consolidated budget and forecast\nHandle full set of accounts for a few Group companies\nReview subsidiaries\u2019 financial statements\nEnsure financial records are maintained in compliance with company policies and statutory requirements\nPrepare monthly reporting packages and management reports, including consolidated financial/management reports of HK and PRC\nPerform internal control procedure review\nAd-hoc support as required by management\nThe Successful Applicants:\nQualified Accountant with at least 8 years\u2019 experience in accounting field, preferably with MNC experience\nFamiliar with HK and PRC accounting, taxation requirements and relevant regulations\nSolid experience in handling investments in China, including but not limited to supervising team in China, reviewing the financial reports and monitoring the cashflow.\nProficient in MS Office (Excel, Word and Outlook)\nAbility to prioritize multiple tasks\nSelf-driven, proactive, good team player, good interpersonal and communication skills and a keen analytical mind\nProficient in both written and spoken English and Chinese, including Mandarin\nImmediate available preferred\nInterested parties please send your full resume with present and expected salary, date of availability by clicking \"Apply Now\"", "employment_types": ["Full Time"], "selling_points": ["Preparation of annual consolidated budget", "Preparation of Group management reports & analysis", "Review subsidiaries\u2019 financial statements"], "locations": ["Tsim Sha Tsui"], "categories": ["Accounting", "Finance / Accounting Manager"], "post_time": "2022-01-13T18:54:23Z", "salary": {"currency": null, "max": null, "min": null, "period": "monthly", "term": null}, "salary_visible": false, "title_keywords": ["finance manager"], "responsibilities": ["ad-hoc", "regulations", "supervising", "budget", "financial statements", "communication", "statutory requirements", "internal control", "full set of accounts", "compliance", "forecast", "reporting", "management", "review", "monitoring", "taxation", "financial reports", "policies", "analysis", "management reports"], "requirements": {"degrees": [], "majors": [], "languages": ["english", "chinese", "mandarin"], "language_level": ["proficient"], "hard_skills": ["excel", "analysis", "word", "management reports", "outlook", "prc accounting", "internal control", "ms office"], "soft_skills": ["communication skills", "good team player", "multiple tasks", "interpersonal", "keen", "prioritize", "analytical mind", "proactive", "driven"], "languages_combined": [{"language": "english", "language_level": ["proficient"]}, {"language": "chinese", "language_level": ["proficient"]}, {"language": "mandarin", "language_level": ["proficient"]}]}, "experience_required": {"duration": ["at least 8 years"], "field": ["accounting", "financial", "team"]}}, {"job_id": "100003009054074", "location_code": "hk", "company": "Tianda Financial Limited", "job_title": "Finance Manager/ AM (SFC Type 1,4,9)", "description": "Responsibilities\uff1a\n\nHandle the accounting entries of the company and its subsidiaries and to develop and improve the accounting, financial, auditing and internal control management systems of the Company;\nSubmit FRR and annual audited financial statements to SFC;\nPrepare and monitor enforcement of annual budget,\u00a0monthly financial statements and consolidation financial statements;\nPrepare financial analysis, internal management reports and all financial analysis reports;\nHandle tax issues, accounts receivables and payables, client fund deposit and withdrawal, and annual auditing;\nResponsible for fund management, monitor liquid capital position;\nAssist with Investment services department to jointly monitor the credit status of margin clients.\nLiaise with tax authority, auditors, banks and SFC on finance related matters.\n\nRequirements:\n\nBachelor\u2019s Degree or above in accounting and finance, qualified accountant or members;\n3-4 years accounting and finance relevant experiences in investment banks or securities brokerage firms, familiar with accounting rules and regulations of securities business, familiar with accounting systems and back office system;\nHave a high level of responsibility and good communication\u00a0and coordination skills, strong sense of moral values, pay attention to details, have a good team spirit and professional attitude.\nWe offer 5-day work week and competitive remuneration package to qualified candidates. Interested parties please click \"Apply Now\" and submit your resume with current and expected salary .Please visit our company\u2019s website:\u00a0https://www.tiandafinancial.com\u00a0to know more about us.\n\nAll information provided by applicants will be treated in strict confidence and used for recruitment purpose only.\u00a0", "employment_types": ["Full Time", "Permanent"], "selling_points": [], "locations": ["Admiralty"], "categories": ["Accounting", "Finance / Accounting Manager", "Financial Analyst", "Banking / Finance", "Financial Services"], "post_time": "2022-01-17T08:19:00Z", "salary": {"currency": null, "max": null, "min": null, "period": "monthly", "term": null}, "salary_visible": false, "title_keywords": ["finance manager"], "responsibilities": ["tax", "management", "systems", "monitor", "budget", "financial statements", "develop", "monthly financial statements", "financial analysis", "management reports", "financial analysis reports", "liaise with", "auditing", "internal control"], "requirements": {"degrees": ["degree or above", "bachelor"], "majors": ["finance", "accounting"], "languages": [], "language_level": [], "hard_skills": ["accounting systems"], "soft_skills": ["team spirit", "coordination skills", "moral", "communication", "attention to details"], "languages_combined": []}, "experience_required": {"duration": ["3-4 years"], "field": ["securities brokerage", "investment banks", "finance", "business", "securities", "accounting"]}}, {"job_id": "100003009053110", "location_code": "hk", "company": "Changjiang Securities International Financial Group Limited", "job_title": "Assistant Manager, Accounts Department", "description": "Responsibilities:\n\nPrepare and review monthly, quarterly and annual financial reporting package in compliance with accounting standards\nPrepare various regular reports including monthly and quarterly financial analysis and FRR reporting in a timely, accurate and efficient manner\nLiaise with external parties on audit, tax returns and other accounting and financial matters\nUpdate accounting standards and information in accordance to market standards and SFC requirements\nHandle daily routine work and tax-related task\nTreasury management, including daily liquidity monitoring\nReview client money segregation on a daily basis\nAny other ad hoc tasks assigned by management\n\n\u00a0Requirements:\n\nDegree holder or above in accounting, finance or other related business discipline\nQualified accountant with HKICPA or other recognized professional accounting bodies is preferable\n4 years relevant working experience in financial institution/sizable accounting firm\nStrong in financial reporting, regulatory reporting (FRR), management accounting, cash flow management and familiar with taxation of both HK and the PRC\nGood command of written and spoken English and Chinese\nMature, with stable working history, responsible, detail minded\nStrong problem solving, analytical, communication and presentation skills\nSelf-motivated, independent and be able to work with team\n\nWe offer 5-days work with good career prospect and remuneration package for the right candidate.\u00a0Salary will be commensurate with qualifications and experience.\u00a0Interested parties please apply with full resume (both Chinese and English versions) with current and expected salary by clicking 'Apply Now'.\n\u00a0\nAll personal data will be used for recruitment purpose only and treated in strict confidence.", "employment_types": ["Full Time", "Permanent"], "selling_points": [], "locations": ["Sheung Wan"], "categories": ["Accounting", "Finance / Accounting Manager"], "post_time": "2022-01-17T05:53:25Z", "salary": {"currency": null, "max": null, "min": null, "period": "monthly", "term": null}, "salary_visible": false, "title_keywords": ["assistant manager,"], "responsibilities": ["tax", "reporting", "management", "compliance", "review", "external parties", "audit", "monitoring", "financial analysis", "ad hoc tasks", "reports", "financial reporting", "liaise with"], "requirements": {"degrees": ["degree holder"], "majors": ["business", "finance", "accounting"], "languages": ["english", "chinese"], "language_level": ["good command"], "hard_skills": ["problem solving", "frr", "hkicpa"], "soft_skills": ["self-motivated", "independent", "responsible", "mature", "problem solving", "communication", "presentation skills", "stable"], "languages_combined": [{"language": "english", "language_level": ["good command"]}, {"language": "chinese", "language_level": ["good command"]}]}, "experience_required": {"duration": ["4 years"], "field": ["accounting", "relevant working experience", "financial"]}}, {"job_id": "100003009054888", "location_code": "hk", "company": "Liang Kai Technology Development Group Limited", "job_title": "Assistant Finance Manager (Finance - Property Developer)", "description": "Job Description\n\nResponsibilities:\n\nManage finance, tax and internal control related matters for property development/ investment projects\nBe responsible for consolidating various Hong Kong project entities and preparing of monthly management reporting for the submission to the head office\nPerform financial analysis/modelling and forecasting the financial performance and cash flows of property development/investment projects\nCoordinate with external tax representatives in preparing and executing tax planning proposals; reviewing tax submissions and ensuring tax compliance of offshore and Hong Kong entities\nParticipate in the due diligence work of Merger and Acquisition transactions.\u00a0Perform regular inspection on internal control procedures and compliance matters\n\nRequirements:\n\nQualified CPA with 3-year commercial experience in property developer; prior experience in Big 4 CPA firm background is also an advantage\nSelf-motivated, proactive and diligent\nExcellent interpersonal, communication and negotiation skills\nProficiency in PC skills, particularly on MS Words, Excel and PowerPoint\nFluent in English and Chinese (Cantonese and Mandarin)\nMore experience will be considered as Manager\n\nWe offer an attractive remuneration package. Interested parties please provide your resume stating your present and expected salaries.\n\nThe Company will handle all personal data confidentially in accordance with the Personal Data (Privacy) Ordinance.\"\u00a0\u00a0", "employment_types": ["Full Time", "Contract"], "selling_points": [], "locations": ["Tai Koo"], "categories": ["Accounting", "Finance / Accounting Manager", "Banking / Finance", "Corporate Banking", "Property / Real Estate", "Property Management"], "post_time": "2022-01-17T12:56:39Z", "salary": {"currency": null, "max": null, "min": null, "period": "monthly", "term": null}, "salary_visible": false, "title_keywords": ["developer", "assistant finance manager"], "responsibilities": ["tax", "due diligence", "regular inspection", "compliance", "coordinate with", "procedures", "transactions", "financial analysis", "planning", "executing", "management reporting", "forecasting", "internal control"], "requirements": {"degrees": [], "majors": [], "languages": ["cantonese", "english", "chinese", "mandarin"], "language_level": ["fluent"], "hard_skills": ["excel", "ms words", "powerpoint", "cpa", "pc skills"], "soft_skills": ["self-motivated", "diligent", "communication", "negotiation skills", "proactive", "interpersonal"], "languages_combined": [{"language": "cantonese", "language_level": []}, {"language": "english", "language_level": ["fluent"]}, {"language": "chinese", "language_level": ["fluent"]}, {"language": "mandarin", "language_level": []}]}, "experience_required": {"duration": ["3-year"], "field": ["developer", "commercial", "cpa firm", "big 4"]}}, {"job_id": "100003009052700", "location_code": "hk", "company": "TRI-Come Recruitment Search", "job_title": "Asst. Finance Manager/ Accounting Manager / Accountant/ SR. Accounts Clerk", "description": "\u00a0 \u00a0 \u00a0 \u00a0 \u00a0 \u00a0Responsibilities\u00a0 :\u00a0\n\nHandle full set of accounts.\nPrepare monthly management reports and comment on variances, if any.\nLiaise with external auditors and tax consultants for the aspects of the financial reporting, tax filing as well as reviewing the profit tax return and computation.\nPrepare budgeting, forecasting and financial analysis.\nAssist in the implementation of accounting system, internal control and policies.\nEvaluate product costing and internal transfer pricing.\nHandle any ad-hoc assignments when necessary\u00a0 \u00a0 \u00a0 \u00a0 \u00a0\n\u00a0 \u00a0 \u00a0 \u00a0 \u00a0 \u00a0Requirements :\u00a0\n\nBachelor\u2019s degree (or equivalent) in accounting, finance, business or related discipline. Obtainment, or current pursuit of, a professional certification\u00a0\nOver 5 year experience in accounting field in trading /manufacturer .\nDevelop and plan assigned audits and projects,\nReview, evaluate and document the maturity of internal controls by performing walk through and testing procedures.\u00a0\nGood speaking both of Cantonese & English,\nGood PC knowledge & Accounting system is an advantage,\nWilling travel to China or Overseas is also required", "employment_types": ["Permanent"], "selling_points": [], "locations": ["Not Specified"], "categories": ["Accounting", "Accounting Clerk / Supervisor", "Finance / Accounting Manager", "Financial Analyst"], "post_time": "2022-01-17T03:45:06Z", "salary": {"currency": null, "max": null, "min": null, "period": "monthly", "term": null}, "salary_visible": false, "title_keywords": ["accounts clerk", "accounting manager", "accountant", "finance manager"], "responsibilities": ["tax", "budgeting", "policies", "full set of accounts", "tax filing", "implementation", "ad-hoc assignments", "financial analysis", "evaluate", "management reports", "financial reporting", "liaise with", "forecasting", "internal control", "external auditors"], "requirements": {"degrees": ["degree", "bachelor"], "majors": ["business", "finance", "accounting"], "languages": ["cantonese", "english"], "language_level": ["good"], "hard_skills": ["pc knowledge", "accounting system"], "soft_skills": [], "languages_combined": [{"language": "cantonese", "language_level": ["good"]}, {"language": "english", "language_level": ["good"]}]}, "experience_required": {"duration": ["5 year"], "field": ["accounting", "trading"]}}, {"job_id": "100003009053749", "location_code": "hk", "company": "Drake International and Vertical Talent HK", "job_title": "Office Manager/ HR & Finance Manager - Financial Services, Up to 50K", "description": "Our Client\n\nOur client is a professional organization in the banking and finance sector. Due to expansion, they now invite high calibre candidate with banking or financial services experience to join and grow with the organisation.\u00a0\n\n\nThe Role\n\n\nPlan and strategize the staffing structure and talent development in order to support the continuous business needs\u00a0\nResponsible for staff recruitment, review, training and various other aspects of human resources administration.\nManage full set of accounts\u00a0\nManage a small team in handling the full spectrum of HR and admin duties\u00a0\nResponsible for budgeting, preparation of accounts and coordinating external auditing matters.\nAct as the secretariat for working groups of the company if necessary\u00a0\nOversee the IT and office administration functions.\n\nTo Qualify\n\nDegree Holder in Human Resources Management,\u00a0 Accounting & Finance, Business Management or related disciplines\nMinimum 8 years of relevant experience from financial/ banking industry\u00a0\nExcellent command of spoken and written English and Chinese (Cantonese and Mandarin)\nWell-versed with Employment Ordinance\nImmediately available preferred\n\nWhat's In It For You?\nThis is an exciting opportunity for a skilled individual with excellent language and interpersonal skills who has relevant finance and HR background. You will work with a high calibre, closed-knit team\u00a0 Highly competitive benefit package include medical insurance for the right individual.\n\nTo Apply\n\nIf you feel your experience and professionalism can make an impact with this firm, please click \"Apply now\".\u00a0\n\nDue to a high volume of applicants, only shortlisted candidates will be contacted.\n\nPersonal data provided by job applicants will be used strictly in accordance with the employer's personal data policies and for recruitment services purposes only.", "employment_types": ["Full Time", "Permanent"], "selling_points": ["Professional organization", "Excellent remuneration package", "Banking & Finance industry background"], "locations": ["Central"], "categories": ["Accounting", "Finance / Accounting Manager", "Admin & HR", "Administration / Operation Manager", "HR Director / Manager"], "post_time": "2022-01-17T07:27:20Z", "salary": {"currency": null, "max": null, "min": null, "period": "monthly", "term": null}, "salary_visible": false, "title_keywords": ["hr", "finance manager", "office manager"], "responsibilities": ["management", "budgeting", "hr", "review", "full set of accounts", "office administration", "policies", "recruitment", "plan", "banking", "personal data", "insurance", "auditing", "administration"], "requirements": {"degrees": ["degree holder"], "majors": ["business", "finance", "related disciplines", "accounting"], "languages": ["cantonese", "english", "chinese", "mandarin"], "language_level": ["excellent"], "hard_skills": ["small", "make", "business management"], "soft_skills": ["interpersonal skills", "organisation", "responsible"], "languages_combined": [{"language": "cantonese", "language_level": ["excellent"]}, {"language": "english", "language_level": ["excellent"]}, {"language": "chinese", "language_level": ["excellent"]}, {"language": "mandarin", "language_level": ["excellent"]}]}, "experience_required": {"duration": ["minimum 8 years"], "field": ["banking industry", "financial services", "relevant experience", "banking", "financial"]}}, {"job_id": "100003009052261", "location_code": "hk", "company": "China Mobile International Limited", "job_title": "Assistant Treasury Manager/ Senior Accountant, Revenue & Treasury (CMIJD-1111-RTFINHK)", "description": "Job Responsibilities:\n\nManage bank account opening/ closing/ signature updates for Hong Kong and overseas entities\nResponsible for online banking platforms setting\nHandle bank transactions including loans, LC, guarantees\nPlan and modernize treasury process and policy\nResponsible for liaison with internal and external auditors\nEnsure the compliance of Treasury policy and SOX\nAssist in formulating and implementing hedging plans and its execution\nHandle ad hoc projects assigned\n\nJob Requirements:\n\nDegree holder in Accounting, Finance or related disciplines\nQualified Accountant under ACCA/HKICPA\nAt least 5 years relevant treasury management experience, preferably from sizeable multinational corporations or financial institutions\nSolid experience in cash management and foreign exchange\nGood knowledge in hedging, risk management, financial products and derivatives Knowledge in accounting for derivatives and hedging preferred\nProficiency in excel VBA, Powerpoint, Word (Chinese & English),\nPositive, self-motivated, good analytical skills and communication skills\nGood interpersonal skills\nGood command of spoken and written Chinese and English, proficiency in Putonghua is a MUST\nCandidates with less experience would be considered as Senior Accountant\n\nInterested parties please send your full resume with current & expected salary\u00a0by clicking \"Apply Now\".\n\nAll personal data provided will be used for consideration of your job application only.\n\nManage bank account opening/closing/signature updates for Hong Kong and overseas entities", "employment_types": ["Full Time", "Permanent"], "selling_points": ["Plan & modernize treasury process and policy", "Manage HK & Overseas bank accounts & platforms", "Formulate & implement hedging plans & execution"], "locations": ["Kwai Hing"], "categories": ["Accounting", "Accountant", "Finance / Accounting Manager", "Treasurer"], "post_time": "2022-01-17T02:36:06Z", "salary": {"currency": null, "max": null, "min": null, "period": "monthly", "term": null}, "salary_visible": false, "title_keywords": ["manager", "senior accountant", "assistant"], "responsibilities": ["account opening", "compliance", "transactions", "ad hoc projects", "plan", "banking", "plans", "external auditors"], "requirements": {"degrees": ["degree holder"], "majors": ["related disciplines", "finance", "accounting"], "languages": ["putonghua", "english", "chinese"], "language_level": ["proficiency", "good command"], "hard_skills": ["excel", "acca", "vba", "word", "powerpoint", "analytical skills", "hkicpa", "exchange"], "soft_skills": ["communication skills", "self-motivated", "analytical skills", "interpersonal skills", "positive"], "languages_combined": [{"language": "putonghua", "language_level": ["proficiency", "good command"]}, {"language": "english", "language_level": ["good command"]}, {"language": "chinese", "language_level": ["proficiency", "good command"]}]}, "experience_required": {"duration": ["at least 5 years"], "field": ["management", "financial institutions", "senior accountant"]}}, {"job_id": "100003009050021", "location_code": "hk", "company": "Shun Tak Property Management Limited", "job_title": "Accounting Manager", "description": "Job Duties:\n\nTo supervise a team for managing all daily operations of accounting function in Hong Kong and Macau\nTo perform timely and accurate financial reporting\nTo ensure and review the compliance of the group financial policies and procedures\nTo review and enhance workflows for better and efficient financial operation and reporting\nTo support in ad hoc financial evaluation supporting for business planning / development projects\n\nRequirements:\n\nDegree holder in Accounting and processed Accountancy qualifications\nMember of HKICPA / ACCA or equivalent\nMinimum 8 years\u2019 working experiences, exposure in the industry of property management is an advantage\nMature, detail orientated, excellent time management and interpersonal skills\nBusiness acumen with logical presentations in report writing\nTravel occasionally to Macau\n\n\u00a0We will offer attractive compensation package to the right candidate. Please send application enclosing resume stating career and salary history, expected salary and date of availability to The HR Dept, Rooms 908-11, 9/F, West Tower, Shun Tak Centre, 200 Connaught Road Central, Hong Kong by email to pm_hr(at)shuntakgroup.com\u00a0 (in Word format).\u00a0\u00a0Please quote the reference of the position you apply for in all correspondences.\n\nThe information supplied by the applicants will be used in accordance with the Personal Data (Privacy) Policy of Shun Tak Group (a copy of which will be provided upon request). Only shortlisted candidates will be notified. www.shuntakgroup.com", "employment_types": ["Full Time", "Permanent"], "selling_points": ["Accountancy qualifications", "Member of HKICPA/ACCA or equivalent", "Min 8 years relevant working experience"], "locations": ["Sheung Wan"], "categories": ["Accounting", "Chief Accountant", "Finance / Accounting Manager", "Others", "Others"], "post_time": "2022-01-14T09:38:51Z", "salary": {"currency": null, "max": null, "min": null, "period": "monthly", "term": null}, "salary_visible": false, "title_keywords": ["accounting manager"], "responsibilities": ["reporting", "ad hoc", "financial policies", "compliance", "review", "procedures", "daily operations", "financial reporting", "evaluation", "planning"], "requirements": {"degrees": ["degree holder"], "majors": ["accounting", "accountancy"], "languages": [], "language_level": [], "hard_skills": ["acca", "word", "presentations", "hkicpa", "acumen"], "soft_skills": ["mature", "interpersonal skills", "detail orientated", "business acumen", "time management"], "languages_combined": []}, "experience_required": {"duration": ["minimum 8 years"], "field": ["management"]}}, {"job_id": "100003009044453", "location_code": "hk", "company": "Kin Yat Industrial Co Ltd", "job_title": "Assistant Accounting Manager", "description": "As a Assistant Accounting Manager, you will work closely with Financial Controller and lead a team of 5 in HK and coordinate with 5 in PRC.\u00a0\n\nWhat You Will Achieve\n\nResponsible for preparing monthly consolidated financial and management report for the business unit and segment\nResponsible for preparing financial schedules and monthly bank reconciliation, factoring & trade loan\nAssist with the Group audit, tax filing and tax reporting\nResponsible for cash flow and financial accounts review\nAssist in budgeting and cost control\nStrong team management experience to work with the team to develop, mentor and upskill their abilities\nHandle System Implementation\nParticipate in various projects and assignments\n\nWhat You Will Need\n\nDegree or above in Accountancy with professional qualifications\nHKICPA, ACCA or CPAA Member\nAt least 8 years accounting experience, highly preferred candidate with Manufacturing background with PRC factory exposure\nHands-on experience in business operational functions with functional knowledge of ERP system is preferred\nExcellent interpersonal skill with good command of both English & Mandarin\nMust have self-initiative and work independently; able to work under pressure and meet tight deadline\nImmediately available is an advantage\nCandidate with less experience will be considered as Assistant Account Manager\n\nWe are an equal opportunity employer and welcome applications from all qualified candidates. Any interest candidate, please send your resume with expected salary and availability by clicking\u00a0\u201cApply Now\u201d.\n\n(Data collected will be treated as strictly confidential and will be used for recruitment purpose only and will be destroyed after the recruitment exercise when no longer required.)\n\n\n", "employment_types": ["Full Time", "Permanent"], "selling_points": [], "locations": ["Wong Tai Sin Area"], "categories": ["Accounting", "Accountant", "Accounting Clerk / Supervisor", "Finance / Accounting Manager"], "post_time": "2022-01-15T03:49:17Z", "salary": {"currency": null, "max": null, "min": null, "period": "monthly", "term": null}, "salary_visible": false, "title_keywords": ["assistant accounting manager"], "responsibilities": ["data", "schedules", "budgeting", "bank reconciliation", "audit", "work under pressure", "tax filing", "implementation", "develop", "management report", "reporting", "management", "review", "coordinate with", "cash flow", "tax", "lead a team", "recruitment", "cost control"], "requirements": {"degrees": ["degree or above"], "majors": ["accountancy"], "languages": ["english", "mandarin"], "language_level": ["excellent", "good command"], "hard_skills": ["acca", "no", "professional qualifications", "erp system", "system implementation", "hkicpa"], "soft_skills": ["work independently", "responsible", "interpersonal skill", "hands-on", "self-initiative", "meet tight deadline", "work under pressure"], "languages_combined": [{"language": "english", "language_level": ["excellent", "good command"]}, {"language": "mandarin", "language_level": ["excellent", "good command"]}]}, "experience_required": {"duration": ["at least 8 years"], "field": ["management", "manufacturing", "accounting experience", "erp system", "business", "team"]}}, {"job_id": "100003009048247", "location_code": "hk", "company": "Belton Group", "job_title": "Finance Manager / Senior Finance Manager", "description": "Job Responsibilities:\n\nLead a team and oversee the financial and management reporting, consolidation, and company secretarial functions\nLead the process re-engineering, including system and work-flow improvement project to drive consistency, efficiency and accuracy of the finance functions\nSupervise the budgetary control and forecasting process\nAct as the key contact point to external parties for all audit, legal, company secretarial and tax matters\nProvide financial analysis to management with value added comments\nSupport IPO, M&A activities, Group restructuring and Tax planning exercise\nPerform other ad hoc projects as assigned\nReport to the VP - Finance\n\n\u00a0Job Requirements:\n\nBachelor Degree in Finance/Accounting or Equivalent with professional accountancy qualification\nMinimum of 8 years financial reporting and relevant experience gained from sizable organization and Big 4 audit firm an advantage\nFamiliar with HK, Thailand and PRC accounting, taxation and company secretarial regulations\nKnowledge in Oracle\u00a0is preferred\nProficiency in MS Office/Excel\nAble to perform under pressure independently with strong sense of commitment and be self-motivated\nFluency in English, Mandarin and Cantonese\n\nWe offer 5-day work week, 13th month salary, performance bonus, medical insurance scheme and long-term career prospect to the right candidate. For interested parties, please send your detailed resume with current and expected salary via jobs.DB.\n\nFor more information about us, please visit our website at: http://www.beltontechnology.com.\n\nCandidates not invited for interview within 8 weeks may consider their applications unsuccessful. Applications will be treated in strict confidence. Personal data collected will be used for recruitment purpose only.", "employment_types": ["Full Time"], "selling_points": ["Double Pay and Performance Bonus", "Bachelor Degree in Finance/Accounting", "Minimum of 8 years financial reporting experience"], "locations": ["Tsing Yi"], "categories": ["Accounting", "Finance / Accounting Manager", "Financial Controller"], "post_time": "2022-01-14T06:53:05Z", "salary": {"currency": null, "max": null, "min": null, "period": "monthly", "term": null}, "salary_visible": false, "title_keywords": ["senior finance manager", "finance manager"], "responsibilities": ["tax", "control", "management", "external parties", "comments", "audit", "financial analysis", "lead a team", "ad hoc projects", "management reporting", "contact", "report", "forecasting", "tax matters", "re-engineering", "planning"], "requirements": {"degrees": ["degree", "bachelor"], "majors": ["finance", "accounting", "accountancy"], "languages": ["cantonese", "english", "mandarin"], "language_level": ["fluency"], "hard_skills": ["excel", "oracle", "ms office", "prc accounting"], "soft_skills": ["self-motivated", "independently", "under pressure"], "languages_combined": [{"language": "cantonese", "language_level": ["fluency"]}, {"language": "english", "language_level": ["fluency"]}, {"language": "mandarin", "language_level": ["fluency"]}]}, "experience_required": {"duration": ["minimum of 8 years"], "field": ["sizable organization", "big 4", "audit", "relevant experience", "financial"]}}, {"job_id": "100003009051241", "location_code": "hk", "company": "Shun Hing Electric Works & Engineering Co Ltd", "job_title": "ASSISTANT MANAGER (ACC)", "description": "Responsibilities:\n\nOverall responsibility in the Company\u2019s accounting functions including:\n\nReview of journals including cheque payments prepared by subordinates\n\nReview of all reconciliation statements between sub-ledgers and general ledgers on a monthly basis\n\nReview monthly debtor and stock aged reports and scrutinize irregular items\n\nReview monthly management accounts for submission by supervisor\n\nPrepare quarterly group reporting packages for review by supervisor\n\nPrepare draft consolidates financial statements and schedules for annual audit\n\nPrepare tax computation and schedules\n\nAssist in the preparation of annual budgets and interim reviews\n\nRequirements:\n\nBachelor degree in Accounting or Finance or above\n\nMinimum\u00a03 years of accounting experience and possession of appropriate audit experience is a definite advantage\n\nTrack record of managing a small team of accounting staff\n\nStrong analytical and reporting skills\n\nAble to handle multi-task and work under pressure independently\n\nProficient in PC skills, Excel, PowerPoint and Word processing\n\nFluent in English and Chinese\n\nProactive, meticulous and well organized\n\nImmediate available is highly preferred", "employment_types": ["Full Time", "Permanent"], "selling_points": [], "locations": ["Tsim Sha Tsui"], "categories": ["Accounting", "Finance / Accounting Manager"], "post_time": "2022-01-15T05:44:21Z", "salary": {"currency": null, "max": null, "min": null, "period": "monthly", "term": null}, "salary_visible": false, "title_keywords": ["assistant manager"], "responsibilities": ["reporting", "management", "budgets", "tax computation", "annual audit", "schedules", "review", "financial statements", "payments", "reports"], "requirements": {"degrees": ["degree", "bachelor"], "majors": ["finance", "accounting"], "languages": ["english", "chinese"], "language_level": ["fluent"], "hard_skills": ["small", "excel", "word processing", "powerpoint", "pc skills"], "soft_skills": ["meticulous", "independently", "multi-task", "well organized", "proactive", "work under pressure"], "languages_combined": [{"language": "english", "language_level": ["fluent"]}, {"language": "chinese", "language_level": ["fluent"]}]}, "experience_required": {"duration": ["minimum 3 years"], "field": ["accounting experience", "audit experience"]}}, {"job_id": "100003009052218", "location_code": "hk", "company": "Aon Services Hong Kong Limited \u6021\u5b89\u670d\u52d9\u9999\u6e2f\u6709\u9650\u516c\u53f8", "job_title": "Controllership Assistant Manager (1-year contract)", "description": "We\u2019re hiring!\u00a0\n\nAon is currently recruiting a Controllership Assistant Manager (1-year contract) to join our team in Hong Kong.\u00a0\n\nAbout Aon\n\nHeadquartered in London, Aon Plc is a leading global professional services firm providing a broad range of risk, retirement and health solutions. Our 50,000 colleagues in 120 countries empower results for clients by using proprietary data and analytics to deliver insights that reduce volatility and improve performance.\u00a0\n\nAt Aon, you\u2019ll be part of a team which will support and inspire you and provide the opportunities and resources to develop your skills. It\u2019s an environment which encourages you to achieve your best - together we\u2019ll empower results.\u00a0\u00a0\n\nResponsibilities:\n\nTo act as a key member of the Controllership team and be responsible for the monthly financial closing procedures in Hong Kong with respect to:\no Recurring and ad hoc journal processing;\no Trintech reconciliation preparation; and\no Process improvement to drive standardization and simplification\nTo clearly document the monthly financial close activities, including the key controls, preparers and reviews involved\nTo ensure financial activities are aligned to the Aon standard operating practices and where process gaps are identified, make proposals to the Controllership Manager and agree follow up actions\nTo execute the transition of financial close activities as agreed with Aon and Genpact stakeholders to Genpact prior to the end of the one year fixed contract\nTo support the standardization and simplification of the preparation of annual financial statements and Tax Returns of Aon businesses in Hong Kong\n\nRequirements:\n\nAt least 5 years relevant accounting experience\nExcellent Excel and other related software skills\nGood communication skill\nGood team player\n\nHow to Apply\n\nYour opportunity to empower results could start right here. Make your mark and apply online today with a brief covering letter and your resume, sharing relevant achievements for this position.\u00a0\n\nWe Offer You\n\nA competitive total rewards package, continuing education & training, and tremendous potential with a growing worldwide organization.\u00a0\n\nOur Colleague Experience\n\nEvery day, our colleagues make a difference, work with the best, own their potential, and value one another. Together, we share this one purpose: to empower economic and human possibility around the world. This unifying goal is at the heart of our identity, and it lives in everything we do. To learn more about our colleague experience, visit Aon Colleague Experience.\n\nAon is an equal opportunities employer. We are committed to creating a winning and inclusive culture where everyone feels valued and has opportunities for growth and development.", "employment_types": ["Full Time", "Contract"], "selling_points": [], "locations": ["Quarry Bay"], "categories": ["Accounting", "Accountant", "Accounting Clerk / Supervisor", "Finance / Accounting Manager"], "post_time": "2022-01-17T02:30:36Z", "salary": {"currency": null, "max": null, "min": null, "period": "monthly", "term": null}, "salary_visible": false, "title_keywords": ["assistant manager"], "responsibilities": ["tax", "ad hoc", "procedures", "financial statements", "key controls"], "requirements": {"degrees": [], "majors": [], "languages": [], "language_level": [], "hard_skills": ["excel", "make"], "soft_skills": ["good team player", "communication skill"], "languages_combined": []}, "experience_required": {"duration": ["at least 5 years"], "field": ["accounting experience"]}}, {"job_id": "100003009049184", "location_code": "hk", "company": "Hong Kong Interbank Clearing Ltd", "job_title": "Manager (Finance)", "description": "Responsibilities\n\nPrepare and review financial statements, management accounting reports, operating budget, statutory reports, business and financial analyses etc.\nPerform analyses on the company\u2019s operating performance against budget estimates\nReview financial analyses to be provided to external auditors in the annual financial audit and assist the external auditors in the operations audit\nReview cash positions and assist in liquidity management of the company\nManage the whole set of general ledger and accounts payable and receivable functions\nOversee the enhancement of the computerized systems for accounting and management data and manage user acceptance tests of new projects to ensure proper changes to the billing and accounting systems\nInitiate improvement of relevant accounting and tax planning processes\nManage relationships with bankers, auditors and internal/external stakeholders\nSupervise the finance team in general accounting operations\nPerform ad-hoc duties as assigned by superiors\nRequirements\n\nUniversity degree in accounting with HKICPA or equivalent professional qualification\nOver 8 years\u2019 accounting experience preferably in financial institutions or sizable organizations\nExcellent command of spoken and written English and Chinese\nGood knowledge of computerized accounting systems and PC applications\nStrong logical thinking, sound analytical skills and able to present ideas in an organized manner\nGood supervisory skill, self-motivated, independent and able to work under pressure\nCandidates with less experience may be considered for the position of Deputy Manager (Finance)\nHow to Apply\nInterested parties please send your curriculum vitae stating your current and expected salaries, and the contact phone number to the Human Resources Division, Unit B, 25/F, MG Tower, 133 Hoi Bun Road, Kwun Tong, Kowloon\u00a0\u00a0by clicking the \"Apply Now\" button below.\nAll applications and personal information collected will be treated in strict confidence and only be used for the purpose of recruitment and selection.\u00a0 The information collected will be accessed by our authorized personnel only.\u00a0 Those applicants not contacted by the Human Resources Division within two months from their application date should consider their applications filed for future reference which will be retained for one year for possible future job matching, and will be destroyed after the expiry of one year.", "employment_types": ["Full Time", "Permanent"], "selling_points": [], "locations": ["Ngau Tau Kok"], "categories": ["Accounting", "Finance / Accounting Manager", "Banking / Finance", "Financial Services", "Others"], "post_time": "2022-01-14T08:14:00Z", "salary": {"currency": null, "max": null, "min": null, "period": null, "term": null}, "salary_visible": false, "title_keywords": ["manager"], "responsibilities": ["tax", "management", "data", "operations", "general ledger", "review", "budget", "audit", "financial statements", "systems", "planning", "reports", "ad-hoc duties", "supervise the finance team", "accounts payable", "external auditors"], "requirements": {"degrees": ["university degree"], "majors": ["accounting"], "languages": ["english", "chinese"], "language_level": ["excellent"], "hard_skills": ["accounting systems", "pc applications", "analytical skills", "hkicpa"], "soft_skills": ["organized", "self-motivated", "independent", "analytical skills", "work under pressure"], "languages_combined": [{"language": "english", "language_level": ["excellent"]}, {"language": "chinese", "language_level": ["excellent"]}]}, "experience_required": {"duration": ["8 years"], "field": ["finance", "accounting experience", "financial institutions"]}}, {"job_id": "100003009045849", "location_code": "hk", "company": "Min Xin Holdings Limited", "job_title": "Accounting Manager/Assistant Accounting Manager", "description": "Job Responsibilities:\n\n\nManage the preparation of regular management reports and analyses, forecast and budget reports;\nWork closely with the external advisers for the statutory reporting and ensure compliance with HK listing rules and other related requirements;\nSet up accounting report packages and internal policies and procedures;\nAssist Group Financial Controller in performing treasury functions and ad hoc projects or assignments;\nHandle tax computation matters, statutory and tax filings;\nManage and develop subordinates in a wide range of functions.\nJob Requirements:\n\n\nDegree holder or above in Accounting/Finance or related discipline;\nCPA or equivalent professional qualifications;\nMinimum10 years working experience in Hong Kong listed companies, and big 4 accounting firms background preferred;\nFamiliar with HK and PRC accounting and tax practices, solid experience in group consolidation and SEHK regulatory requirements\nGood communication and interpersonal skills, demonstrated performance in people leadership, able to motivate teams to perform effectively and efficiently and handle multi-tasks with tight deadlines;\nStrong analytical and business sense, strong report writing and presentation skills;\nGood command of written and spoken English and Chinese (Cantonese and Putonghua);\nImmediate available is highly preferred.\nCandidates with less experience will be considered as Assistant Accounting Manager.\n\nWe offer attractive package including 5-day work and fringe benefit to the right candidate. Interested candidates please apply with full resume stating present & expected salary and date available by e-mail.\n\n\n(Personal data collected will be used for recruitment purpose only.)", "employment_types": ["Full Time", "Permanent"], "selling_points": [], "locations": ["Admiralty"], "categories": ["Accounting", "Finance / Accounting Manager"], "post_time": "2022-01-13T18:55:10Z", "salary": {"currency": null, "max": null, "min": null, "period": "monthly", "term": null}, "salary_visible": false, "title_keywords": ["assistant accounting manager", "accounting manager"], "responsibilities": ["tax", "reporting", "budget reports", "tax computation", "policies", "procedures", "ensure compliance", "develop", "management reports", "ad hoc projects", "forecast", "listing", "report"], "requirements": {"degrees": ["degree holder"], "majors": ["finance", "accounting"], "languages": ["cantonese", "putonghua", "english", "chinese"], "language_level": ["good command"], "hard_skills": ["prc accounting", "cpa", "sehk", "professional qualifications"], "soft_skills": ["multi-tasks", "business sense", "presentation skills", "communication and interpersonal skills", "leadership"], "languages_combined": [{"language": "cantonese", "language_level": ["good command"]}, {"language": "putonghua", "language_level": ["good command"]}, {"language": "english", "language_level": ["good command"]}, {"language": "chinese", "language_level": ["good command"]}]}, "experience_required": {"duration": [], "field": ["consolidation", "accounting", "big 4"]}}, {"job_id": "100003009051721", "location_code": "hk", "company": "Advance Thermo Control Ltd", "job_title": "Accounting Manager", "description": "Manage the Accounting Department in Hong Kong and China\nHandle full set of account and prepare financial statements\nHandle month end closing independently\nPrepare consolidated financial statements and P & L report\nEnsure implementation of proper internal control procedures\nPrepare budget planning and cash flow forecast\nCarry annual audits and tax computation\nLiaise with Wofie accounting consultation and monitor the Wofie account reporting to the local government\u00a0\nControl and monitor the cost spent in the Company and factory\n\nREQUIREMENT\nDegree in Accounting / Finance or related disciplines\nAt least 10 years relevant experience and require daily travel to the China factory\nQualified accountant preferred\nMaintain updated accounting and taxation standard in both Hong Kong and China\nCan work under tight deadlines and pressure.\nHighly organized, detail-oriented and analytical\nStrong in Excel\nFluent written and spoken English and Chinese and Mandarin", "employment_types": ["Full Time"], "selling_points": ["5 working days", "Medical insurance", "US base company"], "locations": ["Tsuen Wan Area"], "categories": ["Accounting", "Finance / Accounting Manager"], "post_time": "2022-01-16T21:51:07Z", "salary": {"currency": null, "max": null, "min": null, "period": "monthly", "term": null}, "salary_visible": false, "title_keywords": ["accounting manager"], "responsibilities": ["reporting", "month end closing", "budget planning", "control", "tax computation", "cost", "taxation", "procedures", "implementation", "financial statements", "monitor", "liaise with", "cash flow", "maintain", "forecast", "audits", "report", "internal control"], "requirements": {"degrees": ["degree"], "majors": ["related disciplines", "finance", "accounting"], "languages": ["english", "chinese", "mandarin"], "language_level": ["fluent"], "hard_skills": ["excel", "internal control"], "soft_skills": ["organized", "independently", "detail-oriented"], "languages_combined": [{"language": "english", "language_level": ["fluent"]}, {"language": "chinese", "language_level": ["fluent"]}, {"language": "mandarin", "language_level": ["fluent"]}]}, "experience_required": {"duration": ["at least 10 years"], "field": ["relevant experience"]}}, {"job_id": "100003009054067", "location_code": "hk", "company": "The Tien Chu (Hong Kong) Company Limited", "job_title": "Accounting Manager", "description": "Responsibilities :\n\n\n\nPrepare consolidated financial statements and handle monthly closing of group companies\nHandle annual and interim audit review. Liaise with external auditors\nEngage in the publication of interim and annual reports\nPrepare statutory accounts and tax filings\nPerform financial analysis\nAssist in ad-hoc tasks as assigned by management\n\nRequirements:\n\n\n\nDegree holder in Accounting or related disciplines\nQualified Accountant of HKICPA or other recognized professional accounting bodies is advantage\nMinimum of 5 years\u2019 working experience in Manufacturing / Trading Company fields;\nExperience in group consolidation, familiar with PRC accounting and tax practices is an added advantage\nDetail-oriented, well-organized, self-motivated with strong sense of responsibility\nHigh competence in written and spoken English and Chinese; proficiency in Putonghua is an advantage;\nAttention to details and accuracy with strong sense of urgency\n\n\n\nWe offer competitive package to right candidate, including but unlimited double pay, performance bonus, free lunch, shuttle bus, education allowance, housing allowance, Medical and other benefits.\n\nWorking hours : Monday to Friday 9:00am to 5:00pm & Saturday 9:00am to 12:00noon\n\nInterested parties please send full resume in Chinese and English in strict confidence with expected salary & earliest availability to us for interview.\n\nFor more details, please visit www.tienchu.com\n\n(Personal data collected is solely for recruitment related purpose\u00a0and will be treated in strict confidence.)", "employment_types": ["Full Time", "Permanent"], "selling_points": ["Accountant", "Manufacturing / Trading Company", "Double pay, bonus, free lunch, shuttle, medical"], "locations": ["Tsing Yi"], "categories": ["Accounting", "Audit", "Finance / Accounting Manager", "Financial Analyst"], "post_time": "2022-01-17T08:17:19Z", "salary": {"currency": null, "max": null, "min": null, "period": "monthly", "term": null}, "salary_visible": false, "title_keywords": ["accounting manager"], "responsibilities": ["tax", "management", "ad-hoc tasks", "review", "audit", "financial statements", "financial analysis", "reports", "liaise with", "publication", "external auditors"], "requirements": {"degrees": ["degree holder"], "majors": ["related disciplines", "accounting"], "languages": ["putonghua", "english", "chinese"], "language_level": ["advantage", "proficiency"], "hard_skills": ["prc accounting", "hkicpa"], "soft_skills": ["self-motivated", "sense of responsibility", "urgency", "well-organized", "detail-oriented", "attention to details"], "languages_combined": [{"language": "putonghua", "language_level": ["proficiency", "advantage"]}, {"language": "english", "language_level": []}, {"language": "chinese", "language_level": []}]}, "experience_required": {"duration": ["minimum of 5 years"], "field": ["manufacturing", "trading", "consolidation", "accounting"]}}, {"job_id": "100003009052581", "location_code": "hk", "company": "Sunlight Jewelers Limited", "job_title": "Accounts Manager", "description": "Responsibilities & Requirements\u8077\u8cac\u53ca\u8981\u6c42\n\n\u00a0\u00a0\u00a0\u00a0\u00a0\u00a0\u00a0 Minimum 5 years relevant experience in Jewellery industry\n\u00a0\u00a0\u00a0\u00a0\u00a0\u00a0\u00a0 Able to handle full set of accounts\n\u00a0\u00a0\u00a0\u00a0\u00a0\u00a0\u00a0 Costing knowledge\n\u00a0\u00a0\u00a0\u00a0\u00a0\u00a0\u00a0 Willing to work under pressure\n\u00a0\u00a0\u00a0\u00a0\u00a0\u00a0\u00a0 Good interpersonal & communication skills, responsible and self-motivated\n\u00a0\u00a0\u00a0\u00a0\u00a0\u00a0\u00a0 Experience in MYOB & PJS is preferable\n\u00a0\u00a0\u00a0\u00a0\u00a0\u00a0\u00a0 Fluent in written and spoken English\n\nWe offer 5 \u00bd-day work, Medical Scheme & Bank holidays to the right candidate.\u00a0 Interested parties, please send FULL RESUME with expected salary to: \"Apply Now\".", "employment_types": ["Full Time"], "selling_points": [], "locations": ["Hung Hom"], "categories": ["Accounting", "Accountant", "Finance / Accounting Manager", "Others"], "post_time": "2022-01-17T03:28:06Z", "salary": {"currency": null, "max": null, "min": null, "period": "monthly", "term": null}, "salary_visible": false, "title_keywords": ["manager"], "responsibilities": [], "requirements": {"degrees": [], "majors": [], "languages": ["english"], "language_level": ["fluent"], "hard_skills": ["myob"], "soft_skills": ["communication skills", "self-motivated", "responsible", "interpersonal", "work under pressure"], "languages_combined": [{"language": "english", "language_level": ["fluent"]}]}, "experience_required": {"duration": ["minimum 5 years"], "field": ["relevant experience"]}}, {"job_id": "100003009034609", "location_code": "hk", "company": "Putien Restaurant (H.K.) Limited", "job_title": "Assistant Finance Manager", "description": "Responsibilities:\u00a0\n\nLeading a team to manage day-to-day accounting, treasury and tax functions of the company\n\nOversee the month-end closing, budgeting/forecasting and interim/audit processes\n\nResponsible for monthly/quarterly management reports and packages to shareholders\nResponsible for the preparation of statutory financial statements, periodic tax and statutory returns with the tax authorities and other regulatory bodies\nWork closely with division/department users and provide insightful suggestions to facilitate business performance review and decision-making\nPerform ad hoc assignments and projects as required\n\n\u00a0\u00a0Requirements:\u00a0\n\nBachelor degree in Accounting, Finance or other related disciplines (with an internationally recognised accounting qualification)\nAt least 5 years of professional experience in accounting or auditing\u00a0\nHave a strong commercial acumen, strong written reporting and communication skills\nAbility to work well under pressure, working accurately with attention to detail, and meeting deadlines\nGood command of both written and spoken English and Chinese\n\nWe offer 5-day work week, competitive remuneration packages and advancement opportunities to the right candidate. Interested parties please apply with detailed resume with expected salary and contact numbers to the H.R. Department by email.", "employment_types": ["Full Time"], "selling_points": [], "locations": ["Tsuen Wan Area"], "categories": ["Accounting", "Finance / Accounting Manager", "Others", "Hospitality / F & B", "Food & Beverage"], "post_time": "2022-01-17T04:38:55Z", "salary": {"currency": null, "max": null, "min": null, "period": "monthly", "term": null}, "salary_visible": false, "title_keywords": ["assistant finance manager"], "responsibilities": ["tax", "budgeting", "review", "audit", "financial statements", "management reports", "month-end closing", "ad hoc assignments", "forecasting"], "requirements": {"degrees": ["degree", "bachelor"], "majors": ["related disciplines", "finance", "accounting"], "languages": ["english", "chinese"], "language_level": ["good command"], "hard_skills": ["acumen"], "soft_skills": ["communication skills", "under pressure", "attention to detail"], "languages_combined": [{"language": "english", "language_level": ["good command"]}, {"language": "chinese", "language_level": ["good command"]}]}, "experience_required": {"duration": ["at least 5 years"], "field": ["accounting"]}}, {"job_id": "100003009054564", "location_code": "hk", "company": "Foodgears Industrial International Limited", "job_title": "Management Accounting Manager", "description": "Responsibilities:\n\nDrive the financial planning of the company by analyzing its performance and risks\nSet targets for and supervise all accounting and finance personnel (management accountants, internal auditors etc.)\nOversee all audit and internal control operations\nPrepare timely and detailed reports on financial performance on a quarterly and annual basis\nConduct analysis to make forecasts and report to upper executives\nEnsure adherence to financial laws and guidelines\n\n\u00a0\nRequirements:\n\nProven experience as director of finance or similar role\nIn-depth knowledge of corporate finance and accounting principles, laws and best practices\nSolid knowledge of financial analysis and forecasting\nProficient in the use of MS Office and financial management software\nAn analytical mind with a strategic ability\nExcellent organizational and leadership skills\nOutstanding communication and interpersonal abilities\nCPA or other relevant qualification and China Accounting experience is a plus\n\n\n\nWe offer attractive remuneration package to the right candidate.\u00a0 Interested parties please send full resume with present & expected salary and available date by clicking \"Apply Now\".\n\n\nAll Personal data collected will be used for recruitment purposes only.\n", "employment_types": ["Permanent"], "selling_points": [], "locations": ["Wong Tai Sin Area"], "categories": ["Accounting", "Finance / Accounting Manager", "Financial Analyst", "Financial Controller"], "post_time": "2022-01-17T10:00:39Z", "salary": {"currency": null, "max": null, "min": null, "period": "monthly", "term": null}, "salary_visible": false, "title_keywords": ["accounting manager"], "responsibilities": ["management", "guidelines", "operations", "analysis", "ensure adherence", "audit", "planning", "reports", "report", "internal control"], "requirements": {"degrees": [], "majors": [], "languages": [], "language_level": [], "hard_skills": ["financial analysis", "cpa", "plus", "ms office"], "soft_skills": ["organizational", "leadership skills", "communication", "analytical mind", "interpersonal"], "languages_combined": []}, "experience_required": {"duration": [], "field": ["finance", "accounting experience"]}}, {"job_id": "100003009052995", "location_code": "hk", "company": "LGMG International Limited", "job_title": "Accounting Manager/Assistant Accounting Manager", "description": "Responsibilities\n\u00a0\n\n\nLiaise with suppliers, customers and financial institutions regarding finance and trade matters\nResponsible for week, month and year-end accounting closures\nPrepare budget, forecast and costing analysis\nMaintaining proper record keeping/filings\nProvide full spectrum of accounting and trade matters reporting\nUndertake ad hoc duties and responsibilities as assigned by the Board\n\nRequirements\n\n\nDegree holder in Accounting/Finance or related disciplines\n3-5 years or above experiences in accounting/import and export trade or related disciplines\nWork independently with suppliers, well-organized and self-motivated\nStrong interpersonal, communication skills and able to multi-task\nProficiency in MS Office applications\nGood command of both written and spoken English, Cantonese and Mandarin\nCandidate with less experience will be considered as Assistant Accounting Manager\nOccasional travel is required\nImmediately available is highly preferred\n\n\n\nInterested parties please send application with full CV with your current and expected salary by clicking \"Apply Now\"\nAll Personal data collected will be used for recruitment purpose only.", "employment_types": ["Full Time"], "selling_points": [], "locations": ["Wan Chai"], "categories": ["Accounting", "Accounting Clerk / Supervisor", "Finance / Accounting Manager"], "post_time": "2022-01-17T06:08:12Z", "salary": {"currency": null, "max": null, "min": null, "period": "monthly", "term": null}, "salary_visible": false, "title_keywords": ["assistant accounting manager", "accounting manager"], "responsibilities": ["ad hoc duties", "year-end", "reporting", "maintaining", "budget", "forecast", "costing analysis", "liaise with suppliers"], "requirements": {"degrees": ["degree holder"], "majors": ["related disciplines", "finance", "accounting"], "languages": ["cantonese", "english", "mandarin"], "language_level": ["good command"], "hard_skills": ["import and export", "ms office"], "soft_skills": ["communication skills", "work independently", "self-motivated", "multi-task", "well-organized", "interpersonal"], "languages_combined": [{"language": "cantonese", "language_level": ["good command"]}, {"language": "english", "language_level": ["good command"]}, {"language": "mandarin", "language_level": ["good command"]}]}, "experience_required": {"duration": ["3-5 years"], "field": ["related", "accounting"]}}, {"job_id": "100003009054541", "location_code": "hk", "company": "China Eagle Management Limited", "job_title": "Accountant / Finance Manager (5-day work)", "description": "\u00a0Responsibilities:\n\n\u00a0Assist to Finance Manager to oversee finance and accounting functions of the group and ensure compliance with the Hong Kong Listing Rules, International Accounting Standards (\u201cIAS\u201d) and the Companies Ordinance\nPrepare monthly consolidated financial information for the Group and co-ordinate to issue notices, announcements and circulars for compliance with the Listing Rules and other statutory requirements\nPrepare annual, interim and quarterly financial reports and relevant disclosure notes and liaise with external auditors in all aspects of the financial reporting\nPrepare financial analysis, budgeting, forecast, cash flow projection, and management reports\nAssist in managing funds and liaison with banks\nAssist in reviewing, monitoring and enhancing internal controls of the Group\nAssist in tax planning, treasury functions and any ad hoc projects for the Group\n\nRequirements:\n\nDegree holder in Accounting and possess HKICPA/ACCA or other equivalent\n4-5 years of relevant work experienceof which at least 1-2 years in a Hong Kong listed company.\nStrong analytical and excellent interpersonal skills\nPositive attitude, good team work ethic , highly responsibility and able to work under pressure\nDriven, enthusiastic, highly self-motivated, and able to operate independently\nConversant in accounting principles; experience in tax issues and legal practice preferred\nExcellent communication skills, fluent in English, Cantonese and Mandarin\nCandidates with more working experience will be considered as senior position", "employment_types": ["Full Time"], "selling_points": ["oversee finance and accounting functions", "1-2 years in a Hong Kong listed company", "5-day work & medical insurance"], "locations": ["Central"], "categories": ["Accounting", "Accountant", "Finance / Accounting Manager", "Treasurer"], "post_time": "2022-01-17T09:56:44Z", "salary": {"currency": null, "max": null, "min": null, "period": "monthly", "term": null}, "salary_visible": false, "title_keywords": ["accountant", "finance manager"], "responsibilities": ["tax", "financial reports", "budgeting", "compliance", "monitoring", "ensure compliance", "financial analysis", "statutory requirements", "cash flow", "management reports", "planning", "financial reporting", "forecast", "ad hoc projects", "liaise with", "listing", "external auditors"], "requirements": {"degrees": ["degree holder"], "majors": ["accounting"], "languages": ["cantonese", "english", "mandarin"], "language_level": ["excellent", "fluent"], "hard_skills": ["acca", "hkicpa"], "soft_skills": ["good team work", "communication skills", "self-motivated", "independently", "positive attitude", "interpersonal skills", "enthusiastic", "driven", "work under pressure"], "languages_combined": [{"language": "cantonese", "language_level": ["excellent", "fluent"]}, {"language": "english", "language_level": ["excellent", "fluent"]}, {"language": "mandarin", "language_level": ["excellent", "fluent"]}]}, "experience_required": {"duration": [], "field": ["legal"]}}, {"job_id": "100003009052473", "location_code": "hk", "company": "Hong Kong Huafa Investment Holdings Limited", "job_title": "Treasury/ Finance Manager \u8cc7\u91d1\u7ba1\u7406\u7d93\u7406", "description": "Hong Kong Huafa Investment Holdings Ltd. is a key platform for Huafa Group to reach out to the overseas market. Representing Huafa Group, Hong Kong Huafa is responsible for overseas investments, cross-border lending and listings of core assets. To meet the demands of growing business, we are now seeking a high-caliber finance professional to join our Treasury Team, this position will support all treasury operation activities for the Hong Kong Huafa and subsidiaries of Huafa Group.\n\nJob Duties\n\nDevelop and maintain networks and collaborative partnerships with financial institutions\nExplore and identify potential business opportunities, including but not limited to, corporate lending, structured transactions, syndications, treasury, trade financing and other financial products\nPrepare and review documentation in relation to bank accounts management and financing activities\nManage cash flow and budgeting with accurate forecasting\nPerform ad hoc duties as assigned\nRequirements\n\nBachelor degree or above in Business Administration, Finance, Accounting or a related discipline\nAt least 3 years' experience in corporate lending\nProficient in both spoken and written English and Chinese, Putonghua is preferred\nAbility to work independently and be able to work under pressure, with good communication, interpersonal and analytical skills\nCandidate with more experience will be considered as Manager/ Senior Manager\n\u5de5\u4f5c\u8077\u8cac\n\n\u8207\u91d1\u878d\u6a5f\u69cb\u7dad\u6301\u826f\u597d\u7684\u5408\u4f5c\u95dc\u4fc2\n\u63a2\u7d22\u4f01\u696d\u8cb8\u6b3e\u3001\u7d50\u69cb\u6027\u4ea4\u6613\u3001\u8cc7\u91d1\u7ba1\u7406\u3001\u8cbf\u6613\u878d\u8cc7\u3001\u5176\u4ed6\u91d1\u878d\u7522\u54c1\u7b49\u7684\u5546\u696d\u6a5f\u6703\n\u6e96\u5099\u53ca\u8986\u6838\u9280\u884c\u53ca\u878d\u8cc7\u6d3b\u52d5\u76f8\u95dc\u6587\u4ef6\n\u5354\u52a9\u73fe\u91d1\u6d41\u91cf\u9810\u6e2c\u53ca\u8ca1\u52d9\u9810\u7b97\u7684\u7ba1\u7406\n\u5b8c\u6210\u4e0a\u53f8\u4ea4\u8fa6\u7684\u5176\u4ed6\u5de5\u4f5c\u53ca\u9805\u76ee\n\u4efb\u8077\u8981\u6c42\n\n\u5927\u5b78\u672c\u79d1\u6216\u4ee5\u4e0a\u5b78\u6b77\uff0c\u4fee\u8b80\u5de5\u5546\u7ba1\u7406\u3001\u91d1\u878d\u3001\u6703\u8a08\u6216\u76f8\u95dc\u5c08\u696d\u7562\u696d\n\u81f3\u5c113\u5e74\u7684\u516c\u53f8\u8cb8\u6b3e\u76f8\u95dc\u5de5\u4f5c\u7d93\u9a57\n\u7cbe\u901a\u4e2d\u82f1\u6587\u53e3\u8a9e\u548c\u66f8\u5beb\uff0c\u719f\u6089\u666e\u901a\u8a71\u8005\u5c07\u7372\u512a\u5148\u8003\u616e\n\u5177\u826f\u597d\u7684\u5206\u6790\u80fd\u529b\u3001\u7368\u7acb\u5de5\u4f5c\u80fd\u529b\u3001\u4eba\u969b\u6e9d\u901a\u80fd\u529b\uff0c\u80fd\u7368\u7acb\u5de5\u4f5c\uff0c\u4e26\u627f\u53d7\u58d3\u529b\n\u5177\u8f03\u9ad8\u8cc7\u6b77\u7684\u7533\u8acb\u4eba\u53ef\u7372\u8003\u616e\u8058\u7528\u70ba\u7d93\u7406\uff0f\u9ad8\u7d1a\u7d93\u7406\n\nWe offer attractive remuneration package to the right candidates, including year-end double pay, discretionary bonus, allowances, group medical insurance, annual health check, and etc. Interested parties please apply directly by clicking \"Apply Now\".", "employment_types": ["Full Time", "Permanent"], "selling_points": ["Candidates with strong treasury exposure preferred", "At least 3 years' experience in corporate lending", "Nurturing professional in treasury team"], "locations": ["Central"], "categories": ["Accounting", "Finance / Accounting Manager", "Banking / Finance", "Loan", "Treasury"], "post_time": "2022-01-17T03:07:22Z", "salary": {"currency": null, "max": null, "min": null, "period": "monthly", "term": null}, "salary_visible": false, "title_keywords": ["finance manager"], "responsibilities": ["ad hoc duties", "management", "budgeting", "business opportunities", "review", "transactions", "develop", "cash flow", "maintain", "documentation", "forecasting"], "requirements": {"degrees": ["degree or above", "bachelor"], "majors": ["finance", "accounting", "business administration"], "languages": ["putonghua", "english", "chinese"], "language_level": ["proficient"], "hard_skills": ["analytical skills"], "soft_skills": ["work independently", "analytical skills", "communication", "interpersonal", "work under pressure"], "languages_combined": [{"language": "putonghua", "language_level": ["proficient"]}, {"language": "english", "language_level": ["proficient"]}, {"language": "chinese", "language_level": ["proficient"]}]}, "experience_required": {"duration": ["at least 3 years"], "field": []}}, {"job_id": "100003009053831", "location_code": "hk", "company": "Sime Darby Motor Services Limited", "job_title": "Assistant Manager - Finance  (JDB/SDMSL/AFM/20220117)", "description": "To cope with our business growth and expansion, we are currently looking for an individual with high caliber to join our team.\n\nJob Responsibilities:\n\nAssist in overseeing all aspects of finance and accounting operations of group companies in multi-franchise motor and motor insurance\u00a0businesses in HK\nPrepare hands-on financial reporting and analysis for business line / management review\nLead the finance team to troubleshoot all month-end closing matters and ensure timely completion of monthly / quarterly\u00a0group reporting submission\nPrepare the annual budget and rolling forecast\nCo-ordinate and support the operational units through ascertaining their needs and recommending solutions to business and financial problems\nMonitor and ensure compliance with corporate policies and guidelines and statutory requirements\nHandle statutory audit and prepare audited financial statements\nReview and drive the enhancement of internal control procedure as well as streamline the financial processes and participate in system enhancements\nLiaise and work closely with finance service center team in Kuala Lumpur, operational units, external auditors and relevant professionals\nParticipate in ad hoc projects as assigned\n\nRequirements:\u00a0\n\nDegree holder in Finance or Accounting discipline\nQualified HKICPA or equivalent internationally recognized accounting qualification\nMinimum 8 years of working experience in accounting field and auditing field\u00a0gained in sizable organization\u00a0with some managerial experience\nSubsidiary level reporting experience in matrix organization or experience in motor industry would be a definite advantage\nStrong financial analysis mindset with business sense\nWilling to work overtime (weekend/ public holiday overtime work for monthly closing with compensation leave)\nProactive, detail-oriented\u00a0with good analytical and problem-solving capabilities\nAbility to work independently with minimal supervision\nWilling to take challenges and able to multitask in a demanding and fast-paced environment and meet tight reporting timeline\nGood interpersonal skills and able to communicate effectively with all levels\nGood command of both spoken and written English and Chinese\nImmediately availability is highly preferred\nWork location: Tsuen Wan (near MTR)\n\nWe offer attractive remuneration package, 5-day work week, competitive fringe benefits and excellent career development opportunity to the right candidate. Interested parties please send your full resume quoting job reference number with present salary, expected salary and\u00a0available date via e-mail to\u00a0ghr-recruitment.sdms @simedarby.com.hk\u00a0\n\nFor more information about us, please visit our\u00a0Website.\nFollow us on\u00a0our\u00a0LinkedIn\u00a0and stay tuned!\n\nAll information provided by applicants will be treated in strict confidence and used for recruitment purpose only.", "employment_types": ["Full Time", "Permanent"], "selling_points": ["Bachelor Degree Holder with HKICPA / Equivalent", "Subsidiary level reporting experience", "Minimum of 8 years in sizable organizations"], "locations": ["Tsuen Wan Area"], "categories": ["Accounting", "Accountant", "Audit", "Finance / Accounting Manager"], "post_time": "2022-01-17T07:35:53Z", "salary": {"currency": null, "max": null, "min": null, "period": "monthly", "term": null}, "salary_visible": false, "title_keywords": ["assistant manager"], "responsibilities": ["liaise", "operations", "budget", "audit", "financial statements", "statutory requirements", "troubleshoot", "management review", "internal control", "monitor", "finance team", "reporting", "review", "rolling forecast", "guidelines", "policies", "analysis", "ensure compliance", "month-end closing", "ad hoc projects", "financial reporting", "insurance", "external auditors"], "requirements": {"degrees": ["degree holder"], "majors": ["finance", "accounting"], "languages": ["english", "chinese"], "language_level": ["good command"], "hard_skills": ["financial analysis", "problem-solving", "hkicpa"], "soft_skills": ["work overtime", "work independently", "business sense", "fast-paced environment", "problem-solving", "detail-oriented", "multitask", "overtime work", "interpersonal skills", "proactive"], "languages_combined": [{"language": "english", "language_level": ["good command"]}, {"language": "chinese", "language_level": ["good command"]}]}, "experience_required": {"duration": ["minimum 8 years"], "field": ["sizable organization", "managerial", "accounting"]}}, {"job_id": "100003009052550", "location_code": "hk", "company": "The Luxe Manor", "job_title": "Financial Controller / Assistant Financial Controller", "description": "Responsibilities:\nOversee the finance and accounting functions\n\nHandle all aspects of financial controls, reviews and planning\n\nCompile financial budget and perform operational and costing analysis\n\nHighlight and investigate significant issues of operating units, make recommendations on corrective measures\n\nConduct independent review and evaluations of operating units\u2019 financial / operational policies and procedures for the purpose of improving the efficiency and effectiveness\n\nEnforce internal control systems to ensure that the assets, revenues and costs are under effective control\n\nImplement cost effective control policies and procedures, ensure that the internal control systems operate properly and comply with Group and Company policies\n\nRequirements:\nDegree holder in Accounting / Finance or equivalent and with a recognized accounting qualification, preferable ACCA/HKICPA/AICPA\n\nMinimum 10 years\u2019 managerial experience in financial control function in sizable organization and accounting experience in HK listed or multinational corporations\n\nStrong business sense, proven management, analytical and leadership skills\n\nExcellent interpersonal and communication skills and ability to collaborate with all departments in an organization\n\nGood understanding of HK & China accounting rules and regulations\n\nFamiliar with HK & China operations in finance, taxation and audit\n\nSolid hotel experience\n\nInterested parties please send your detailed resume with current and expected salary by clicking Apply Now.\n\nAll applications will be handled in the strictest confidence and personal data collected will be used for recruitment purposes only. Applicants not invited for an interview within 6 weeks may consider their applications unsuccessful. Applicant contact details will be held for 6 months, from the date of application.", "employment_types": ["Full Time"], "selling_points": ["Compile financial budget", "Enforce internal control systems", "Minimum 10 years\u2019 relevant experience"], "locations": ["Not Specified"], "categories": ["Accounting", "Finance / Accounting Manager", "Financial Controller"], "post_time": "2022-01-17T03:24:03Z", "salary": {"currency": null, "max": null, "min": null, "period": "monthly", "term": null}, "salary_visible": false, "title_keywords": ["assistant financial controller", "financial controller"], "responsibilities": ["make recommendations", "control", "cost", "policies", "review", "budget", "procedures", "systems", "costing analysis", "internal control", "costs", "planning"], "requirements": {"degrees": ["degree holder"], "majors": ["finance", "accounting"], "languages": [], "language_level": [], "hard_skills": ["acca", "hkicpa"], "soft_skills": ["communication skills", "leadership skills", "interpersonal", "business sense"], "languages_combined": []}, "experience_required": {"duration": ["minimum 10 years"], "field": ["sizable organization", "managerial", "accounting experience", "financial"]}}, {"job_id": "100003009050044", "location_code": "hk", "company": "Summergate Limited", "job_title": "Finance Manager / Assistant Controller", "description": "Reporting to Financial Controller, you will lead a finance team to cover all financial functions in HK and MC, and you\u2019ll also need to work collaboratively with people across the business at all levels.\n\nKEY RESPONSIBILITIES\n\nOverseeing all finance, accounting, tax, treasury, and company secretarial matters for Summergate HK and MC entities.\nFull responsibility for balance sheet control and reconciliations to ensure integrity of financial and accounting information.\nEnsure timely and accurate closing and reporting to head quarter.\nLead the relations with auditors, tax agents, and other external parties to manage statutory obligations for the entities.\nLead the finance team to manage day-to-day operations and finance administrative issues.\nDrive and deliver continuous improvement initiatives across end-to-end business processes, systems and reporting to align head quarter guidance and controls.\nAssist in yearly budget process for HKMC entities, and coordinate with the FP&A team in head quarter to provide business analysis to local business partners.\nMonitor and manage cash flow projections for HKMC entities, and ensure controls over fund transfers and cash management.\nLead, train, and coach the team members to build and maintain a sustainable team to support the local business.\nPerform other ad-hoc projects/assignments as required.\n\nKEY COMPETENCIES / EXPERIENCE\u00a0\n\nMinimum 8 years+ in finance accounting , with above 2-3 years\u2019 experience in managing full-scope finance functions in MNC or sizable local corporations;\nCA/CPA qualification preferred.\nExperience with JDE or Dynamic 365 highly advantageous;\nExperience in a big-4 or other accounting firm desirable;\nStrong leadership with the ability to drive and execute improvements;\nStrong inter-personal and communication skills with good command in written and spoken English. Chinese not essential but advantageous.\nCan-do attitude with strong sense of ownership.\nSelf-motivated and able to work under pressure;\nAbility to be hands on where necessary;", "employment_types": ["Full Time", "Permanent"], "selling_points": [], "locations": ["Lai Chi Kok"], "categories": ["Accounting", "Finance / Accounting Manager", "Financial Controller"], "post_time": "2022-01-14T09:41:00Z", "salary": {"currency": null, "max": null, "min": null, "period": "monthly", "term": null}, "salary_visible": false, "title_keywords": ["finance manager", "assistant"], "responsibilities": ["external parties", "day-to-day operations", "budget", "communication", "maintain", "ad-hoc projects", "work under pressure", "control", "monitor", "finance team", "balance sheet", "reporting", "guidance", "management", "coordinate with", "reconciliations", "cash flow", "tax", "systems", "business analysis"], "requirements": {"degrees": [], "majors": [], "languages": ["english", "chinese"], "language_level": ["good command"], "hard_skills": ["cpa", "analysis", "dynamic"], "soft_skills": ["communication skills", "self-motivated", "inter-personal", "can-do attitude", "timely", "integrity", "dynamic", "hands on", "accurate", "leadership", "work under pressure"], "languages_combined": [{"language": "english", "language_level": ["good command"]}, {"language": "chinese", "language_level": []}]}, "experience_required": {"duration": ["2-3 years"], "field": ["finance", "accounting"]}}, {"job_id": "100003009054922", "location_code": "hk", "company": "Sun Hung Kai Properties Ltd", "job_title": "FINANCIAL CONTROLLER \u2013 HOTEL DIVISION", "description": "Requirements:\n\n\nBachelor\u2019s degree holder, with CPA or other professional qualification in accounting. Prior working experience in audit preferred\nAt least 15 years\u2019 working experience, including relevant experience as Director of Finance in sizable hotels with extensive F&B and other facilites\nSolid working experience for hotels in Hong Kong and mainland China\nStrong analytical skills, good business acumen and ownership perspective\nBe resilient and able to cope with high work pressure and demanding deadlines\nHighly motivated, detail-minded and result oriented with multi-tasking skills\nProactive and a good team player\nGood communication and interpersonal skills\nProficient in both spoken and written English and Chinese\n\nResponsibilities:\n\n\nResponsible for the overall accounting and financial review matters, including reporting and analysis of the portfolio hotels in Hong Kong and mainland China\nWorking closely with headquarter corporate offices and finance teams of portfolio hotels\nProvide consolidated management reports and analysis with value-added views on business and good interpretation of financial data\nPerform regular reviews on financial controls\n\nGood remuneration and attractive fringe benefits will be offered to the successful applicant. Interested parties please apply with full resume, present and expected salary, available date by clicking \u201cApply Now\u201d.\n\nFor further information, please visit our company website: http://www.shkp.com/.\n\nWe are an equal opportunity employer and welcome applications from all qualified candidates. All personal data collected will be used for recruitment purpose only.\u00a0 Applicants not hearing from us within 3 months may consider their applications unsuccessful.\u00a0 All personal data collected will be destroyed within 24 months.", "employment_types": ["Full Time", "Permanent"], "selling_points": ["Bachelor degree with CPA qualification", "Exp as Director of Finance in sizable hotels", "Accounting & financial review of HK & PRC hotels"], "locations": ["Wan Chai"], "categories": ["Accounting", "Finance / Accounting Manager", "Financial Analyst", "Financial Controller"], "post_time": "2022-01-17T14:01:55Z", "salary": {"currency": null, "max": null, "min": null, "period": null, "term": null}, "salary_visible": false, "title_keywords": ["financial controller"], "responsibilities": ["reporting", "data", "analysis", "review", "teams", "management reports"], "requirements": {"degrees": ["bachelor", "degree holder"], "majors": ["accounting"], "languages": ["english", "chinese"], "language_level": ["proficient"], "hard_skills": ["cpa", "acumen", "analytical skills"], "soft_skills": ["detail-minded", "good team player", "multi-tasking skills", "analytical skills", "result oriented", "motivated", "communication and interpersonal skills", "business acumen", "proactive", "extensive"], "languages_combined": [{"language": "english", "language_level": ["proficient"]}, {"language": "chinese", "language_level": ["proficient"]}]}, "experience_required": {"duration": ["at least 15 years"], "field": ["finance", "audit", "f&b", "relevant experience", "hotels"]}}, {"job_id": "100003009052940", "location_code": "hk", "company": "EB Services Limited", "job_title": "Assistant Manager (Treasury Operation)", "description": "To cope with the continuous business expansion of the Company, we invite talented and professional candidate to join our growing team:\n\nJob Descriptions\n\nThe candidate needs to coordinate directly and liaise with various Hong Kong and overseas departments to ensure all treasury banking services are provided to meet operation requirements in a timely cost-efficient manner.\n\nResponsibilities:\nLead a small team for daily operations of treasury functions, including but not limit to customer accounts & commission payments.\nMonitor and manage the funding requirements.\nSupport bank account opening & closing, authorized signatories updated, and ensure electronic banking is operated in a secured manner.\nLiaise with external banks, online payment/collection gateways and other financial services providers for system interface and daily banking transactions.\nRecommend and implement ideas and innovations to improve upon existing systems, work processes and procedures on commission verification, commission payments and refund process.\nAble to build good relationship with internal customers and external stakeholders.\nParticipate in the development & enhancement of cash management systems, treasury management systems, online banking linkage with ERP systems, straight-through-payment process systems, online collection/payment gateway systems, to improve treasury operation processes & control and manage risks exposure.\n\nRequirements:\n\nBachelor\u2019s degree in Accounting or Finance.\nOver 7 years\u2019 experience from multinational companies is preferred.\nExperience in retail / e-commerce / direct selling industry experience is an advantage.\nExcellent analytical, critical thinking and troubleshooting skills.\nAble to manage multiple items simultaneously and prioritize appropriately.\nDemonstrates initiative in anticipating and solving issues; self-motivated and naturally inquisitive.\nGood verbal / written communication skills in both Chinese and English.\nStrong PC skills, especially in Excel (e.g., Marco, VBA), Smart Sheet, database & etc.\nImmediate available is highly preferred.", "employment_types": ["Full Time", "Permanent"], "selling_points": ["5 Days work week", "Medical benefits, life insurance", "Flexible working hours"], "locations": ["Ngau Tau Kok"], "categories": ["Accounting", "Finance / Accounting Manager", "Others"], "post_time": "2022-01-17T04:37:25Z", "salary": {"currency": null, "max": null, "min": null, "period": "monthly", "term": null}, "salary_visible": false, "title_keywords": ["assistant manager"], "responsibilities": ["cost", "lead a small team", "coordinate", "daily operations", "payments", "banking", "liaise with"], "requirements": {"degrees": ["degree", "bachelor"], "majors": ["finance", "accounting"], "languages": ["english", "chinese"], "language_level": ["good"], "hard_skills": ["erp systems", "excel", "vba", "e-commerce", "account opening", "marco", "pc skills"], "soft_skills": ["communication skills", "self-motivated", "troubleshooting", "prioritize", "initiative"], "languages_combined": [{"language": "english", "language_level": ["good"]}, {"language": "chinese", "language_level": ["good"]}]}, "experience_required": {"duration": ["7 years"], "field": ["retail", "e-commerce"]}}, {"job_id": "100003009053700", "location_code": "hk", "company": "PwC", "job_title": "Manager - Finance Practice Support - PwC Tax - Hong Kong", "description": "Duties\n\nAssist in preparing and reviewing financial management and statistics reports\nPerform analytical review on financial results\nPerform data quality review on Tax systems\nCarry out monthly actions to improve financial management\nAssist in financial projects and ad-hoc assignments\nAssist in financial reports automation\nManage database / systems\nCo-ordinate with departments, e.g., GTS, Central FIN, Client First team, etc. on Tax finance matters\n\n\u00a0Requirements\n\nBachelor degree in any discipline\nMinimum 5 years\u2019 experience in Finance in MNC or professional services firm is preferred\nGood logical and analytical skill\nGood coordination, interpersonal and problem-solving skills\nGood project management skill\nAble to manage multiple tasks under deadlines while maintaining quality of work delivered\nAble to communicate with impact to peer groups, leaders and stakeholders\nAble to maintain good relationship with teammates and users\nDemonstrate creativity and able to contribute new ideas and knowledge where appropriate\nOpen minded, agile with change and practical\nCommitted to self-development and coaching of others for growth\nProficient in MS Office, especially in MS Excel & PowerPoint.\u00a0 Experience in using Outlook and technology tools such as Alteryx and Power BI, is a desirable\nGood in both spoken and written English and Chinese", "employment_types": ["Full Time", "Permanent"], "selling_points": ["Financial Management for Tax Practice", "ex-Professional Staff welcome", "Urgent Hire"], "locations": ["Central"], "categories": ["Accounting", "Finance / Accounting Manager", "Financial Controller"], "post_time": "2022-01-17T07:22:26Z", "salary": {"currency": null, "max": null, "min": null, "period": "monthly", "term": null}, "salary_visible": false, "title_keywords": ["manager"], "responsibilities": ["tax", "management", "financial reports", "data", "co-ordinate with", "ad-hoc assignments", "review", "quality", "systems", "reports", "database"], "requirements": {"degrees": ["degree", "bachelor"], "majors": [], "languages": ["english", "chinese"], "language_level": ["good"], "hard_skills": ["analytical skill", "bi", "agile", "powerpoint", "project management", "ms excel", "outlook", "alteryx", "problem-solving skills", "ms office"], "soft_skills": ["analytical skill", "agile", "multiple tasks", "committed", "open minded", "coordination", "project management skill", "problem-solving skills", "interpersonal"], "languages_combined": [{"language": "english", "language_level": ["good"]}, {"language": "chinese", "language_level": ["good"]}]}, "experience_required": {"duration": ["minimum 5 years"], "field": ["finance"]}}, {"job_id": "100003009046691", "location_code": "hk", "company": "International Beverage Holdings Ltd", "job_title": "Finance Manager", "description": "Preparation of monthly consolidated management reports and analysis\nPreparation of annual consolidated budget and forecast\nHandle full set of accounts for a few Group companies\nReview subsidiaries\u2019 financial statements\nEnsure financial records are maintained in compliance with company policies and statutory requirements\nPrepare monthly reporting packages and management reports, including consolidated financial/management reports of HK and PRC\nPerform internal control procedure review\nAd-hoc support as required by management\nThe Successful Applicants:\nQualified Accountant with at least 8 years\u2019 experience in accounting field, preferably with MNC experience\nFamiliar with HK and PRC accounting, taxation requirements and relevant regulations\nSolid experience in handling investments in China, including but not limited to supervising team in China, reviewing the financial reports and monitoring the cashflow.\nProficient in MS Office (Excel, Word and Outlook)\nAbility to prioritize multiple tasks\nSelf-driven, proactive, good team player, good interpersonal and communication skills and a keen analytical mind\nProficient in both written and spoken English and Chinese, including Mandarin\nImmediate available preferred\nInterested parties please send your full resume with present and expected salary, date of availability by clicking \"Apply Now\"", "employment_types": ["Full Time"], "selling_points": ["Preparation of annual consolidated budget", "Preparation of Group management reports & analysis", "Review subsidiaries\u2019 financial statements"], "locations": ["Tsim Sha Tsui"], "categories": ["Accounting", "Finance / Accounting Manager"], "post_time": "2022-01-13T18:54:23Z", "salary": {"currency": null, "max": null, "min": null, "period": "monthly", "term": null}, "salary_visible": false, "title_keywords": ["finance manager"], "responsibilities": ["ad-hoc", "regulations", "supervising", "budget", "financial statements", "communication", "statutory requirements", "internal control", "full set of accounts", "compliance", "forecast", "reporting", "management", "review", "monitoring", "taxation", "financial reports", "policies", "analysis", "management reports"], "requirements": {"degrees": [], "majors": [], "languages": ["english", "chinese", "mandarin"], "language_level": ["proficient"], "hard_skills": ["excel", "analysis", "word", "management reports", "outlook", "prc accounting", "internal control", "ms office"], "soft_skills": ["communication skills", "good team player", "multiple tasks", "interpersonal", "keen", "prioritize", "analytical mind", "proactive", "driven"], "languages_combined": [{"language": "english", "language_level": ["proficient"]}, {"language": "chinese", "language_level": ["proficient"]}, {"language": "mandarin", "language_level": ["proficient"]}]}, "experience_required": {"duration": ["at least 8 years"], "field": ["accounting", "financial", "team"]}}, {"job_id": "100003009054074", "location_code": "hk", "company": "Tianda Financial Limited", "job_title": "Finance Manager/ AM (SFC Type 1,4,9)", "description": "Responsibilities\uff1a\n\nHandle the accounting entries of the company and its subsidiaries and to develop and improve the accounting, financial, auditing and internal control management systems of the Company;\nSubmit FRR and annual audited financial statements to SFC;\nPrepare and monitor enforcement of annual budget,\u00a0monthly financial statements and consolidation financial statements;\nPrepare financial analysis, internal management reports and all financial analysis reports;\nHandle tax issues, accounts receivables and payables, client fund deposit and withdrawal, and annual auditing;\nResponsible for fund management, monitor liquid capital position;\nAssist with Investment services department to jointly monitor the credit status of margin clients.\nLiaise with tax authority, auditors, banks and SFC on finance related matters.\n\nRequirements:\n\nBachelor\u2019s Degree or above in accounting and finance, qualified accountant or members;\n3-4 years accounting and finance relevant experiences in investment banks or securities brokerage firms, familiar with accounting rules and regulations of securities business, familiar with accounting systems and back office system;\nHave a high level of responsibility and good communication\u00a0and coordination skills, strong sense of moral values, pay attention to details, have a good team spirit and professional attitude.\nWe offer 5-day work week and competitive remuneration package to qualified candidates. Interested parties please click \"Apply Now\" and submit your resume with current and expected salary .Please visit our company\u2019s website:\u00a0https://www.tiandafinancial.com\u00a0to know more about us.\n\nAll information provided by applicants will be treated in strict confidence and used for recruitment purpose only.\u00a0", "employment_types": ["Full Time", "Permanent"], "selling_points": [], "locations": ["Admiralty"], "categories": ["Accounting", "Finance / Accounting Manager", "Financial Analyst", "Banking / Finance", "Financial Services"], "post_time": "2022-01-17T08:19:00Z", "salary": {"currency": null, "max": null, "min": null, "period": "monthly", "term": null}, "salary_visible": false, "title_keywords": ["finance manager"], "responsibilities": ["tax", "management", "systems", "monitor", "budget", "financial statements", "develop", "monthly financial statements", "financial analysis", "management reports", "financial analysis reports", "liaise with", "auditing", "internal control"], "requirements": {"degrees": ["degree or above", "bachelor"], "majors": ["finance", "accounting"], "languages": [], "language_level": [], "hard_skills": ["accounting systems"], "soft_skills": ["team spirit", "coordination skills", "moral", "communication", "attention to details"], "languages_combined": []}, "experience_required": {"duration": ["3-4 years"], "field": ["securities brokerage", "investment banks", "finance", "business", "securities", "accounting"]}}, {"job_id": "100003009053110", "location_code": "hk", "company": "Changjiang Securities International Financial Group Limited", "job_title": "Assistant Manager, Accounts Department", "description": "Responsibilities:\n\nPrepare and review monthly, quarterly and annual financial reporting package in compliance with accounting standards\nPrepare various regular reports including monthly and quarterly financial analysis and FRR reporting in a timely, accurate and efficient manner\nLiaise with external parties on audit, tax returns and other accounting and financial matters\nUpdate accounting standards and information in accordance to market standards and SFC requirements\nHandle daily routine work and tax-related task\nTreasury management, including daily liquidity monitoring\nReview client money segregation on a daily basis\nAny other ad hoc tasks assigned by management\n\n\u00a0Requirements:\n\nDegree holder or above in accounting, finance or other related business discipline\nQualified accountant with HKICPA or other recognized professional accounting bodies is preferable\n4 years relevant working experience in financial institution/sizable accounting firm\nStrong in financial reporting, regulatory reporting (FRR), management accounting, cash flow management and familiar with taxation of both HK and the PRC\nGood command of written and spoken English and Chinese\nMature, with stable working history, responsible, detail minded\nStrong problem solving, analytical, communication and presentation skills\nSelf-motivated, independent and be able to work with team\n\nWe offer 5-days work with good career prospect and remuneration package for the right candidate.\u00a0Salary will be commensurate with qualifications and experience.\u00a0Interested parties please apply with full resume (both Chinese and English versions) with current and expected salary by clicking 'Apply Now'.\n\u00a0\nAll personal data will be used for recruitment purpose only and treated in strict confidence.", "employment_types": ["Full Time", "Permanent"], "selling_points": [], "locations": ["Sheung Wan"], "categories": ["Accounting", "Finance / Accounting Manager"], "post_time": "2022-01-17T05:53:25Z", "salary": {"currency": null, "max": null, "min": null, "period": "monthly", "term": null}, "salary_visible": false, "title_keywords": ["assistant manager,"], "responsibilities": ["tax", "reporting", "management", "compliance", "review", "external parties", "audit", "monitoring", "financial analysis", "ad hoc tasks", "reports", "financial reporting", "liaise with"], "requirements": {"degrees": ["degree holder"], "majors": ["business", "finance", "accounting"], "languages": ["english", "chinese"], "language_level": ["good command"], "hard_skills": ["problem solving", "frr", "hkicpa"], "soft_skills": ["self-motivated", "independent", "responsible", "mature", "problem solving", "communication", "presentation skills", "stable"], "languages_combined": [{"language": "english", "language_level": ["good command"]}, {"language": "chinese", "language_level": ["good command"]}]}, "experience_required": {"duration": ["4 years"], "field": ["accounting", "relevant working experience", "financial"]}}, {"job_id": "100003009054888", "location_code": "hk", "company": "Liang Kai Technology Development Group Limited", "job_title": "Assistant Finance Manager (Finance - Property Developer)", "description": "Job Description\n\nResponsibilities:\n\nManage finance, tax and internal control related matters for property development/ investment projects\nBe responsible for consolidating various Hong Kong project entities and preparing of monthly management reporting for the submission to the head office\nPerform financial analysis/modelling and forecasting the financial performance and cash flows of property development/investment projects\nCoordinate with external tax representatives in preparing and executing tax planning proposals; reviewing tax submissions and ensuring tax compliance of offshore and Hong Kong entities\nParticipate in the due diligence work of Merger and Acquisition transactions.\u00a0Perform regular inspection on internal control procedures and compliance matters\n\nRequirements:\n\nQualified CPA with 3-year commercial experience in property developer; prior experience in Big 4 CPA firm background is also an advantage\nSelf-motivated, proactive and diligent\nExcellent interpersonal, communication and negotiation skills\nProficiency in PC skills, particularly on MS Words, Excel and PowerPoint\nFluent in English and Chinese (Cantonese and Mandarin)\nMore experience will be considered as Manager\n\nWe offer an attractive remuneration package. Interested parties please provide your resume stating your present and expected salaries.\n\nThe Company will handle all personal data confidentially in accordance with the Personal Data (Privacy) Ordinance.\"\u00a0\u00a0", "employment_types": ["Full Time", "Contract"], "selling_points": [], "locations": ["Tai Koo"], "categories": ["Accounting", "Finance / Accounting Manager", "Banking / Finance", "Corporate Banking", "Property / Real Estate", "Property Management"], "post_time": "2022-01-17T12:56:39Z", "salary": {"currency": null, "max": null, "min": null, "period": "monthly", "term": null}, "salary_visible": false, "title_keywords": ["developer", "assistant finance manager"], "responsibilities": ["tax", "due diligence", "regular inspection", "compliance", "coordinate with", "procedures", "transactions", "financial analysis", "planning", "executing", "management reporting", "forecasting", "internal control"], "requirements": {"degrees": [], "majors": [], "languages": ["cantonese", "english", "chinese", "mandarin"], "language_level": ["fluent"], "hard_skills": ["excel", "ms words", "powerpoint", "cpa", "pc skills"], "soft_skills": ["self-motivated", "diligent", "communication", "negotiation skills", "proactive", "interpersonal"], "languages_combined": [{"language": "cantonese", "language_level": []}, {"language": "english", "language_level": ["fluent"]}, {"language": "chinese", "language_level": ["fluent"]}, {"language": "mandarin", "language_level": []}]}, "experience_required": {"duration": ["3-year"], "field": ["developer", "commercial", "cpa firm", "big 4"]}}, {"job_id": "100003009052700", "location_code": "hk", "company": "TRI-Come Recruitment Search", "job_title": "Asst. Finance Manager/ Accounting Manager / Accountant/ SR. Accounts Clerk", "description": "\u00a0 \u00a0 \u00a0 \u00a0 \u00a0 \u00a0Responsibilities\u00a0 :\u00a0\n\nHandle full set of accounts.\nPrepare monthly management reports and comment on variances, if any.\nLiaise with external auditors and tax consultants for the aspects of the financial reporting, tax filing as well as reviewing the profit tax return and computation.\nPrepare budgeting, forecasting and financial analysis.\nAssist in the implementation of accounting system, internal control and policies.\nEvaluate product costing and internal transfer pricing.\nHandle any ad-hoc assignments when necessary\u00a0 \u00a0 \u00a0 \u00a0 \u00a0\n\u00a0 \u00a0 \u00a0 \u00a0 \u00a0 \u00a0Requirements :\u00a0\n\nBachelor\u2019s degree (or equivalent) in accounting, finance, business or related discipline. Obtainment, or current pursuit of, a professional certification\u00a0\nOver 5 year experience in accounting field in trading /manufacturer .\nDevelop and plan assigned audits and projects,\nReview, evaluate and document the maturity of internal controls by performing walk through and testing procedures.\u00a0\nGood speaking both of Cantonese & English,\nGood PC knowledge & Accounting system is an advantage,\nWilling travel to China or Overseas is also required", "employment_types": ["Permanent"], "selling_points": [], "locations": ["Not Specified"], "categories": ["Accounting", "Accounting Clerk / Supervisor", "Finance / Accounting Manager", "Financial Analyst"], "post_time": "2022-01-17T03:45:06Z", "salary": {"currency": null, "max": null, "min": null, "period": "monthly", "term": null}, "salary_visible": false, "title_keywords": ["accounts clerk", "accounting manager", "accountant", "finance manager"], "responsibilities": ["tax", "budgeting", "policies", "full set of accounts", "tax filing", "implementation", "ad-hoc assignments", "financial analysis", "evaluate", "management reports", "financial reporting", "liaise with", "forecasting", "internal control", "external auditors"], "requirements": {"degrees": ["degree", "bachelor"], "majors": ["business", "finance", "accounting"], "languages": ["cantonese", "english"], "language_level": ["good"], "hard_skills": ["pc knowledge", "accounting system"], "soft_skills": [], "languages_combined": [{"language": "cantonese", "language_level": ["good"]}, {"language": "english", "language_level": ["good"]}]}, "experience_required": {"duration": ["5 year"], "field": ["accounting", "trading"]}}, {"job_id": "100003009053749", "location_code": "hk", "company": "Drake International and Vertical Talent HK", "job_title": "Office Manager/ HR & Finance Manager - Financial Services, Up to 50K", "description": "Our Client\n\nOur client is a professional organization in the banking and finance sector. Due to expansion, they now invite high calibre candidate with banking or financial services experience to join and grow with the organisation.\u00a0\n\n\nThe Role\n\n\nPlan and strategize the staffing structure and talent development in order to support the continuous business needs\u00a0\nResponsible for staff recruitment, review, training and various other aspects of human resources administration.\nManage full set of accounts\u00a0\nManage a small team in handling the full spectrum of HR and admin duties\u00a0\nResponsible for budgeting, preparation of accounts and coordinating external auditing matters.\nAct as the secretariat for working groups of the company if necessary\u00a0\nOversee the IT and office administration functions.\n\nTo Qualify\n\nDegree Holder in Human Resources Management,\u00a0 Accounting & Finance, Business Management or related disciplines\nMinimum 8 years of relevant experience from financial/ banking industry\u00a0\nExcellent command of spoken and written English and Chinese (Cantonese and Mandarin)\nWell-versed with Employment Ordinance\nImmediately available preferred\n\nWhat's In It For You?\nThis is an exciting opportunity for a skilled individual with excellent language and interpersonal skills who has relevant finance and HR background. You will work with a high calibre, closed-knit team\u00a0 Highly competitive benefit package include medical insurance for the right individual.\n\nTo Apply\n\nIf you feel your experience and professionalism can make an impact with this firm, please click \"Apply now\".\u00a0\n\nDue to a high volume of applicants, only shortlisted candidates will be contacted.\n\nPersonal data provided by job applicants will be used strictly in accordance with the employer's personal data policies and for recruitment services purposes only.", "employment_types": ["Full Time", "Permanent"], "selling_points": ["Professional organization", "Excellent remuneration package", "Banking & Finance industry background"], "locations": ["Central"], "categories": ["Accounting", "Finance / Accounting Manager", "Admin & HR", "Administration / Operation Manager", "HR Director / Manager"], "post_time": "2022-01-17T07:27:20Z", "salary": {"currency": null, "max": null, "min": null, "period": "monthly", "term": null}, "salary_visible": false, "title_keywords": ["hr", "finance manager", "office manager"], "responsibilities": ["management", "budgeting", "hr", "review", "full set of accounts", "office administration", "policies", "recruitment", "plan", "banking", "personal data", "insurance", "auditing", "administration"], "requirements": {"degrees": ["degree holder"], "majors": ["business", "finance", "related disciplines", "accounting"], "languages": ["cantonese", "english", "chinese", "mandarin"], "language_level": ["excellent"], "hard_skills": ["small", "make", "business management"], "soft_skills": ["interpersonal skills", "organisation", "responsible"], "languages_combined": [{"language": "cantonese", "language_level": ["excellent"]}, {"language": "english", "language_level": ["excellent"]}, {"language": "chinese", "language_level": ["excellent"]}, {"language": "mandarin", "language_level": ["excellent"]}]}, "experience_required": {"duration": ["minimum 8 years"], "field": ["banking industry", "financial services", "relevant experience", "banking", "financial"]}}, {"job_id": "100003009052261", "location_code": "hk", "company": "China Mobile International Limited", "job_title": "Assistant Treasury Manager/ Senior Accountant, Revenue & Treasury (CMIJD-1111-RTFINHK)", "description": "Job Responsibilities:\n\nManage bank account opening/ closing/ signature updates for Hong Kong and overseas entities\nResponsible for online banking platforms setting\nHandle bank transactions including loans, LC, guarantees\nPlan and modernize treasury process and policy\nResponsible for liaison with internal and external auditors\nEnsure the compliance of Treasury policy and SOX\nAssist in formulating and implementing hedging plans and its execution\nHandle ad hoc projects assigned\n\nJob Requirements:\n\nDegree holder in Accounting, Finance or related disciplines\nQualified Accountant under ACCA/HKICPA\nAt least 5 years relevant treasury management experience, preferably from sizeable multinational corporations or financial institutions\nSolid experience in cash management and foreign exchange\nGood knowledge in hedging, risk management, financial products and derivatives Knowledge in accounting for derivatives and hedging preferred\nProficiency in excel VBA, Powerpoint, Word (Chinese & English),\nPositive, self-motivated, good analytical skills and communication skills\nGood interpersonal skills\nGood command of spoken and written Chinese and English, proficiency in Putonghua is a MUST\nCandidates with less experience would be considered as Senior Accountant\n\nInterested parties please send your full resume with current & expected salary\u00a0by clicking \"Apply Now\".\n\nAll personal data provided will be used for consideration of your job application only.\n\nManage bank account opening/closing/signature updates for Hong Kong and overseas entities", "employment_types": ["Full Time", "Permanent"], "selling_points": ["Plan & modernize treasury process and policy", "Manage HK & Overseas bank accounts & platforms", "Formulate & implement hedging plans & execution"], "locations": ["Kwai Hing"], "categories": ["Accounting", "Accountant", "Finance / Accounting Manager", "Treasurer"], "post_time": "2022-01-17T02:36:06Z", "salary": {"currency": null, "max": null, "min": null, "period": "monthly", "term": null}, "salary_visible": false, "title_keywords": ["manager", "senior accountant", "assistant"], "responsibilities": ["account opening", "compliance", "transactions", "ad hoc projects", "plan", "banking", "plans", "external auditors"], "requirements": {"degrees": ["degree holder"], "majors": ["related disciplines", "finance", "accounting"], "languages": ["putonghua", "english", "chinese"], "language_level": ["proficiency", "good command"], "hard_skills": ["excel", "acca", "vba", "word", "powerpoint", "analytical skills", "hkicpa", "exchange"], "soft_skills": ["communication skills", "self-motivated", "analytical skills", "interpersonal skills", "positive"], "languages_combined": [{"language": "putonghua", "language_level": ["proficiency", "good command"]}, {"language": "english", "language_level": ["good command"]}, {"language": "chinese", "language_level": ["proficiency", "good command"]}]}, "experience_required": {"duration": ["at least 5 years"], "field": ["management", "financial institutions", "senior accountant"]}}, {"job_id": "100003009050021", "location_code": "hk", "company": "Shun Tak Property Management Limited", "job_title": "Accounting Manager", "description": "Job Duties:\n\nTo supervise a team for managing all daily operations of accounting function in Hong Kong and Macau\nTo perform timely and accurate financial reporting\nTo ensure and review the compliance of the group financial policies and procedures\nTo review and enhance workflows for better and efficient financial operation and reporting\nTo support in ad hoc financial evaluation supporting for business planning / development projects\n\nRequirements:\n\nDegree holder in Accounting and processed Accountancy qualifications\nMember of HKICPA / ACCA or equivalent\nMinimum 8 years\u2019 working experiences, exposure in the industry of property management is an advantage\nMature, detail orientated, excellent time management and interpersonal skills\nBusiness acumen with logical presentations in report writing\nTravel occasionally to Macau\n\n\u00a0We will offer attractive compensation package to the right candidate. Please send application enclosing resume stating career and salary history, expected salary and date of availability to The HR Dept, Rooms 908-11, 9/F, West Tower, Shun Tak Centre, 200 Connaught Road Central, Hong Kong by email to pm_hr(at)shuntakgroup.com\u00a0 (in Word format).\u00a0\u00a0Please quote the reference of the position you apply for in all correspondences.\n\nThe information supplied by the applicants will be used in accordance with the Personal Data (Privacy) Policy of Shun Tak Group (a copy of which will be provided upon request). Only shortlisted candidates will be notified. www.shuntakgroup.com", "employment_types": ["Full Time", "Permanent"], "selling_points": ["Accountancy qualifications", "Member of HKICPA/ACCA or equivalent", "Min 8 years relevant working experience"], "locations": ["Sheung Wan"], "categories": ["Accounting", "Chief Accountant", "Finance / Accounting Manager", "Others", "Others"], "post_time": "2022-01-14T09:38:51Z", "salary": {"currency": null, "max": null, "min": null, "period": "monthly", "term": null}, "salary_visible": false, "title_keywords": ["accounting manager"], "responsibilities": ["reporting", "ad hoc", "financial policies", "compliance", "review", "procedures", "daily operations", "financial reporting", "evaluation", "planning"], "requirements": {"degrees": ["degree holder"], "majors": ["accounting", "accountancy"], "languages": [], "language_level": [], "hard_skills": ["acca", "word", "presentations", "hkicpa", "acumen"], "soft_skills": ["mature", "interpersonal skills", "detail orientated", "business acumen", "time management"], "languages_combined": []}, "experience_required": {"duration": ["minimum 8 years"], "field": ["management"]}}, {"job_id": "100003009044453", "location_code": "hk", "company": "Kin Yat Industrial Co Ltd", "job_title": "Assistant Accounting Manager", "description": "As a Assistant Accounting Manager, you will work closely with Financial Controller and lead a team of 5 in HK and coordinate with 5 in PRC.\u00a0\n\nWhat You Will Achieve\n\nResponsible for preparing monthly consolidated financial and management report for the business unit and segment\nResponsible for preparing financial schedules and monthly bank reconciliation, factoring & trade loan\nAssist with the Group audit, tax filing and tax reporting\nResponsible for cash flow and financial accounts review\nAssist in budgeting and cost control\nStrong team management experience to work with the team to develop, mentor and upskill their abilities\nHandle System Implementation\nParticipate in various projects and assignments\n\nWhat You Will Need\n\nDegree or above in Accountancy with professional qualifications\nHKICPA, ACCA or CPAA Member\nAt least 8 years accounting experience, highly preferred candidate with Manufacturing background with PRC factory exposure\nHands-on experience in business operational functions with functional knowledge of ERP system is preferred\nExcellent interpersonal skill with good command of both English & Mandarin\nMust have self-initiative and work independently; able to work under pressure and meet tight deadline\nImmediately available is an advantage\nCandidate with less experience will be considered as Assistant Account Manager\n\nWe are an equal opportunity employer and welcome applications from all qualified candidates. Any interest candidate, please send your resume with expected salary and availability by clicking\u00a0\u201cApply Now\u201d.\n\n(Data collected will be treated as strictly confidential and will be used for recruitment purpose only and will be destroyed after the recruitment exercise when no longer required.)\n\n\n", "employment_types": ["Full Time", "Permanent"], "selling_points": [], "locations": ["Wong Tai Sin Area"], "categories": ["Accounting", "Accountant", "Accounting Clerk / Supervisor", "Finance / Accounting Manager"], "post_time": "2022-01-15T03:49:17Z", "salary": {"currency": null, "max": null, "min": null, "period": "monthly", "term": null}, "salary_visible": false, "title_keywords": ["assistant accounting manager"], "responsibilities": ["data", "schedules", "budgeting", "bank reconciliation", "audit", "work under pressure", "tax filing", "implementation", "develop", "management report", "reporting", "management", "review", "coordinate with", "cash flow", "tax", "lead a team", "recruitment", "cost control"], "requirements": {"degrees": ["degree or above"], "majors": ["accountancy"], "languages": ["english", "mandarin"], "language_level": ["excellent", "good command"], "hard_skills": ["acca", "no", "professional qualifications", "erp system", "system implementation", "hkicpa"], "soft_skills": ["work independently", "responsible", "interpersonal skill", "hands-on", "self-initiative", "meet tight deadline", "work under pressure"], "languages_combined": [{"language": "english", "language_level": ["excellent", "good command"]}, {"language": "mandarin", "language_level": ["excellent", "good command"]}]}, "experience_required": {"duration": ["at least 8 years"], "field": ["management", "manufacturing", "accounting experience", "erp system", "business", "team"]}}, {"job_id": "100003009048247", "location_code": "hk", "company": "Belton Group", "job_title": "Finance Manager / Senior Finance Manager", "description": "Job Responsibilities:\n\nLead a team and oversee the financial and management reporting, consolidation, and company secretarial functions\nLead the process re-engineering, including system and work-flow improvement project to drive consistency, efficiency and accuracy of the finance functions\nSupervise the budgetary control and forecasting process\nAct as the key contact point to external parties for all audit, legal, company secretarial and tax matters\nProvide financial analysis to management with value added comments\nSupport IPO, M&A activities, Group restructuring and Tax planning exercise\nPerform other ad hoc projects as assigned\nReport to the VP - Finance\n\n\u00a0Job Requirements:\n\nBachelor Degree in Finance/Accounting or Equivalent with professional accountancy qualification\nMinimum of 8 years financial reporting and relevant experience gained from sizable organization and Big 4 audit firm an advantage\nFamiliar with HK, Thailand and PRC accounting, taxation and company secretarial regulations\nKnowledge in Oracle\u00a0is preferred\nProficiency in MS Office/Excel\nAble to perform under pressure independently with strong sense of commitment and be self-motivated\nFluency in English, Mandarin and Cantonese\n\nWe offer 5-day work week, 13th month salary, performance bonus, medical insurance scheme and long-term career prospect to the right candidate. For interested parties, please send your detailed resume with current and expected salary via jobs.DB.\n\nFor more information about us, please visit our website at: http://www.beltontechnology.com.\n\nCandidates not invited for interview within 8 weeks may consider their applications unsuccessful. Applications will be treated in strict confidence. Personal data collected will be used for recruitment purpose only.", "employment_types": ["Full Time"], "selling_points": ["Double Pay and Performance Bonus", "Bachelor Degree in Finance/Accounting", "Minimum of 8 years financial reporting experience"], "locations": ["Tsing Yi"], "categories": ["Accounting", "Finance / Accounting Manager", "Financial Controller"], "post_time": "2022-01-14T06:53:05Z", "salary": {"currency": null, "max": null, "min": null, "period": "monthly", "term": null}, "salary_visible": false, "title_keywords": ["senior finance manager", "finance manager"], "responsibilities": ["tax", "control", "management", "external parties", "comments", "audit", "financial analysis", "lead a team", "ad hoc projects", "management reporting", "contact", "report", "forecasting", "tax matters", "re-engineering", "planning"], "requirements": {"degrees": ["degree", "bachelor"], "majors": ["finance", "accounting", "accountancy"], "languages": ["cantonese", "english", "mandarin"], "language_level": ["fluency"], "hard_skills": ["excel", "oracle", "ms office", "prc accounting"], "soft_skills": ["self-motivated", "independently", "under pressure"], "languages_combined": [{"language": "cantonese", "language_level": ["fluency"]}, {"language": "english", "language_level": ["fluency"]}, {"language": "mandarin", "language_level": ["fluency"]}]}, "experience_required": {"duration": ["minimum of 8 years"], "field": ["sizable organization", "big 4", "audit", "relevant experience", "financial"]}}, {"job_id": "100003009051241", "location_code": "hk", "company": "Shun Hing Electric Works & Engineering Co Ltd", "job_title": "ASSISTANT MANAGER (ACC)", "description": "Responsibilities:\n\nOverall responsibility in the Company\u2019s accounting functions including:\n\nReview of journals including cheque payments prepared by subordinates\n\nReview of all reconciliation statements between sub-ledgers and general ledgers on a monthly basis\n\nReview monthly debtor and stock aged reports and scrutinize irregular items\n\nReview monthly management accounts for submission by supervisor\n\nPrepare quarterly group reporting packages for review by supervisor\n\nPrepare draft consolidates financial statements and schedules for annual audit\n\nPrepare tax computation and schedules\n\nAssist in the preparation of annual budgets and interim reviews\n\nRequirements:\n\nBachelor degree in Accounting or Finance or above\n\nMinimum\u00a03 years of accounting experience and possession of appropriate audit experience is a definite advantage\n\nTrack record of managing a small team of accounting staff\n\nStrong analytical and reporting skills\n\nAble to handle multi-task and work under pressure independently\n\nProficient in PC skills, Excel, PowerPoint and Word processing\n\nFluent in English and Chinese\n\nProactive, meticulous and well organized\n\nImmediate available is highly preferred", "employment_types": ["Full Time", "Permanent"], "selling_points": [], "locations": ["Tsim Sha Tsui"], "categories": ["Accounting", "Finance / Accounting Manager"], "post_time": "2022-01-15T05:44:21Z", "salary": {"currency": null, "max": null, "min": null, "period": "monthly", "term": null}, "salary_visible": false, "title_keywords": ["assistant manager"], "responsibilities": ["reporting", "management", "budgets", "tax computation", "annual audit", "schedules", "review", "financial statements", "payments", "reports"], "requirements": {"degrees": ["degree", "bachelor"], "majors": ["finance", "accounting"], "languages": ["english", "chinese"], "language_level": ["fluent"], "hard_skills": ["small", "excel", "word processing", "powerpoint", "pc skills"], "soft_skills": ["meticulous", "independently", "multi-task", "well organized", "proactive", "work under pressure"], "languages_combined": [{"language": "english", "language_level": ["fluent"]}, {"language": "chinese", "language_level": ["fluent"]}]}, "experience_required": {"duration": ["minimum 3 years"], "field": ["accounting experience", "audit experience"]}}, {"job_id": "100003009052218", "location_code": "hk", "company": "Aon Services Hong Kong Limited \u6021\u5b89\u670d\u52d9\u9999\u6e2f\u6709\u9650\u516c\u53f8", "job_title": "Controllership Assistant Manager (1-year contract)", "description": "We\u2019re hiring!\u00a0\n\nAon is currently recruiting a Controllership Assistant Manager (1-year contract) to join our team in Hong Kong.\u00a0\n\nAbout Aon\n\nHeadquartered in London, Aon Plc is a leading global professional services firm providing a broad range of risk, retirement and health solutions. Our 50,000 colleagues in 120 countries empower results for clients by using proprietary data and analytics to deliver insights that reduce volatility and improve performance.\u00a0\n\nAt Aon, you\u2019ll be part of a team which will support and inspire you and provide the opportunities and resources to develop your skills. It\u2019s an environment which encourages you to achieve your best - together we\u2019ll empower results.\u00a0\u00a0\n\nResponsibilities:\n\nTo act as a key member of the Controllership team and be responsible for the monthly financial closing procedures in Hong Kong with respect to:\no Recurring and ad hoc journal processing;\no Trintech reconciliation preparation; and\no Process improvement to drive standardization and simplification\nTo clearly document the monthly financial close activities, including the key controls, preparers and reviews involved\nTo ensure financial activities are aligned to the Aon standard operating practices and where process gaps are identified, make proposals to the Controllership Manager and agree follow up actions\nTo execute the transition of financial close activities as agreed with Aon and Genpact stakeholders to Genpact prior to the end of the one year fixed contract\nTo support the standardization and simplification of the preparation of annual financial statements and Tax Returns of Aon businesses in Hong Kong\n\nRequirements:\n\nAt least 5 years relevant accounting experience\nExcellent Excel and other related software skills\nGood communication skill\nGood team player\n\nHow to Apply\n\nYour opportunity to empower results could start right here. Make your mark and apply online today with a brief covering letter and your resume, sharing relevant achievements for this position.\u00a0\n\nWe Offer You\n\nA competitive total rewards package, continuing education & training, and tremendous potential with a growing worldwide organization.\u00a0\n\nOur Colleague Experience\n\nEvery day, our colleagues make a difference, work with the best, own their potential, and value one another. Together, we share this one purpose: to empower economic and human possibility around the world. This unifying goal is at the heart of our identity, and it lives in everything we do. To learn more about our colleague experience, visit Aon Colleague Experience.\n\nAon is an equal opportunities employer. We are committed to creating a winning and inclusive culture where everyone feels valued and has opportunities for growth and development.", "employment_types": ["Full Time", "Contract"], "selling_points": [], "locations": ["Quarry Bay"], "categories": ["Accounting", "Accountant", "Accounting Clerk / Supervisor", "Finance / Accounting Manager"], "post_time": "2022-01-17T02:30:36Z", "salary": {"currency": null, "max": null, "min": null, "period": "monthly", "term": null}, "salary_visible": false, "title_keywords": ["assistant manager"], "responsibilities": ["tax", "ad hoc", "procedures", "financial statements", "key controls"], "requirements": {"degrees": [], "majors": [], "languages": [], "language_level": [], "hard_skills": ["excel", "make"], "soft_skills": ["good team player", "communication skill"], "languages_combined": []}, "experience_required": {"duration": ["at least 5 years"], "field": ["accounting experience"]}}, {"job_id": "100003009049184", "location_code": "hk", "company": "Hong Kong Interbank Clearing Ltd", "job_title": "Manager (Finance)", "description": "Responsibilities\n\nPrepare and review financial statements, management accounting reports, operating budget, statutory reports, business and financial analyses etc.\nPerform analyses on the company\u2019s operating performance against budget estimates\nReview financial analyses to be provided to external auditors in the annual financial audit and assist the external auditors in the operations audit\nReview cash positions and assist in liquidity management of the company\nManage the whole set of general ledger and accounts payable and receivable functions\nOversee the enhancement of the computerized systems for accounting and management data and manage user acceptance tests of new projects to ensure proper changes to the billing and accounting systems\nInitiate improvement of relevant accounting and tax planning processes\nManage relationships with bankers, auditors and internal/external stakeholders\nSupervise the finance team in general accounting operations\nPerform ad-hoc duties as assigned by superiors\nRequirements\n\nUniversity degree in accounting with HKICPA or equivalent professional qualification\nOver 8 years\u2019 accounting experience preferably in financial institutions or sizable organizations\nExcellent command of spoken and written English and Chinese\nGood knowledge of computerized accounting systems and PC applications\nStrong logical thinking, sound analytical skills and able to present ideas in an organized manner\nGood supervisory skill, self-motivated, independent and able to work under pressure\nCandidates with less experience may be considered for the position of Deputy Manager (Finance)\nHow to Apply\nInterested parties please send your curriculum vitae stating your current and expected salaries, and the contact phone number to the Human Resources Division, Unit B, 25/F, MG Tower, 133 Hoi Bun Road, Kwun Tong, Kowloon\u00a0\u00a0by clicking the \"Apply Now\" button below.\nAll applications and personal information collected will be treated in strict confidence and only be used for the purpose of recruitment and selection.\u00a0 The information collected will be accessed by our authorized personnel only.\u00a0 Those applicants not contacted by the Human Resources Division within two months from their application date should consider their applications filed for future reference which will be retained for one year for possible future job matching, and will be destroyed after the expiry of one year.", "employment_types": ["Full Time", "Permanent"], "selling_points": [], "locations": ["Ngau Tau Kok"], "categories": ["Accounting", "Finance / Accounting Manager", "Banking / Finance", "Financial Services", "Others"], "post_time": "2022-01-14T08:14:00Z", "salary": {"currency": null, "max": null, "min": null, "period": null, "term": null}, "salary_visible": false, "title_keywords": ["manager"], "responsibilities": ["tax", "management", "data", "operations", "general ledger", "review", "budget", "audit", "financial statements", "systems", "planning", "reports", "ad-hoc duties", "supervise the finance team", "accounts payable", "external auditors"], "requirements": {"degrees": ["university degree"], "majors": ["accounting"], "languages": ["english", "chinese"], "language_level": ["excellent"], "hard_skills": ["accounting systems", "pc applications", "analytical skills", "hkicpa"], "soft_skills": ["organized", "self-motivated", "independent", "analytical skills", "work under pressure"], "languages_combined": [{"language": "english", "language_level": ["excellent"]}, {"language": "chinese", "language_level": ["excellent"]}]}, "experience_required": {"duration": ["8 years"], "field": ["finance", "accounting experience", "financial institutions"]}}, {"job_id": "100003009045849", "location_code": "hk", "company": "Min Xin Holdings Limited", "job_title": "Accounting Manager/Assistant Accounting Manager", "description": "Job Responsibilities:\n\n\nManage the preparation of regular management reports and analyses, forecast and budget reports;\nWork closely with the external advisers for the statutory reporting and ensure compliance with HK listing rules and other related requirements;\nSet up accounting report packages and internal policies and procedures;\nAssist Group Financial Controller in performing treasury functions and ad hoc projects or assignments;\nHandle tax computation matters, statutory and tax filings;\nManage and develop subordinates in a wide range of functions.\nJob Requirements:\n\n\nDegree holder or above in Accounting/Finance or related discipline;\nCPA or equivalent professional qualifications;\nMinimum10 years working experience in Hong Kong listed companies, and big 4 accounting firms background preferred;\nFamiliar with HK and PRC accounting and tax practices, solid experience in group consolidation and SEHK regulatory requirements\nGood communication and interpersonal skills, demonstrated performance in people leadership, able to motivate teams to perform effectively and efficiently and handle multi-tasks with tight deadlines;\nStrong analytical and business sense, strong report writing and presentation skills;\nGood command of written and spoken English and Chinese (Cantonese and Putonghua);\nImmediate available is highly preferred.\nCandidates with less experience will be considered as Assistant Accounting Manager.\n\nWe offer attractive package including 5-day work and fringe benefit to the right candidate. Interested candidates please apply with full resume stating present & expected salary and date available by e-mail.\n\n\n(Personal data collected will be used for recruitment purpose only.)", "employment_types": ["Full Time", "Permanent"], "selling_points": [], "locations": ["Admiralty"], "categories": ["Accounting", "Finance / Accounting Manager"], "post_time": "2022-01-13T18:55:10Z", "salary": {"currency": null, "max": null, "min": null, "period": "monthly", "term": null}, "salary_visible": false, "title_keywords": ["assistant accounting manager", "accounting manager"], "responsibilities": ["tax", "reporting", "budget reports", "tax computation", "policies", "procedures", "ensure compliance", "develop", "management reports", "ad hoc projects", "forecast", "listing", "report"], "requirements": {"degrees": ["degree holder"], "majors": ["finance", "accounting"], "languages": ["cantonese", "putonghua", "english", "chinese"], "language_level": ["good command"], "hard_skills": ["prc accounting", "cpa", "sehk", "professional qualifications"], "soft_skills": ["multi-tasks", "business sense", "presentation skills", "communication and interpersonal skills", "leadership"], "languages_combined": [{"language": "cantonese", "language_level": ["good command"]}, {"language": "putonghua", "language_level": ["good command"]}, {"language": "english", "language_level": ["good command"]}, {"language": "chinese", "language_level": ["good command"]}]}, "experience_required": {"duration": [], "field": ["consolidation", "accounting", "big 4"]}}, {"job_id": "100003009050070", "location_code": "hk", "company": "GoGoChart Technology Limited", "job_title": "Accounting Manager/ Assistant Manager", "description": "We are looking for an Assistant Finance Manager, Group Budgeting, Planning & Compliance to support the senior manager on driving financial planning and analysis, as well as compliance for the Group.\n\nKey Responsibilites:\n\nResponsible for Group reporting, budgeting and forecasting\nManage financial closing, consolidation and prepare management report packages\nCompile cash flow report and forecast\nPrepare financial analysis on business performance of subsidiaries to support senior management on formulation of corporate strategies and key investment decisions\nEnforce compliance of SOX, finance policies and other governance for the Group.\u00a0Conduct relevant compliance trainings and internal controls testing\nPlan and lead internal audits of subsidiaries and compile audit reports.\nCoordinate external audits for the Group and its subsidiaries in HK and provide feedback to auditor before finalization of audit reports\nManage regional finance projects including development and roll out of new reports, processes and systems\u00a0\nPerform ad-hoc assignments given by line manager\n\nRequirements\n\nBachelor\u2019s Degree in Accounting, Business or related fields\nQualified accountant with full membership in HK or international accounting bodies\nYoung talents with at least 6 years experience in financial planning and reporting, financial accounting\nExperience in\u00a0reputable audit firms and SOX compliance is a definite advantage\nExperience in FMCG industry and multinational companies is preferred\nProficient in\u00a0SAP, BW and Microsoft Office\n\nWork Location : Wong Chuk Hang, Aberdeen\n\n\nWe offer competitive remuneration package and career development opportunity to the right candidate.\u00a0 Interested candidates please submit your resume with present and expected salary and earliest availability to us by clicking the \"APPLY NOW\" button.\u00a0\n\nApplicants who would not be invited for interview within 6 weeks may assume their applications unsuccessful. All applications will be retained for a maximum period of 12 months. All information collected will be used for recruitment and selection purpose and treated confidential.", "employment_types": ["Full Time", "Permanent"], "selling_points": ["Competitive working environment and salary", "Global Exposure and ESOP provided", "ACCA, HKICPA is a must"], "locations": ["Lai Chi Kok"], "categories": ["Accounting", "Accountant", "Finance / Accounting Manager", "Financial Controller"], "post_time": "2022-01-14T09:43:41Z", "salary": {"currency": null, "max": null, "min": null, "period": "monthly", "term": null}, "salary_visible": false, "title_keywords": ["assistant manager", "accounting manager"], "responsibilities": ["budgeting", "audit", "plan", "senior management", "compliance", "testing", "reports", "forecast", "forecasting", "management report", "report", "reporting", "cash flow", "audits", "policies", "ad-hoc assignments", "systems", "financial analysis", "coordinate"], "requirements": {"degrees": ["degree", "bachelor"], "majors": ["business", "accounting"], "languages": [], "language_level": [], "hard_skills": ["fmcg industry", "sap", "microsoft office"], "soft_skills": [], "languages_combined": []}, "experience_required": {"duration": ["at least 6 years"], "field": ["fmcg", "financial", "compliance", "audit", "accounting", "planning"]}}, {"job_id": "100003009042967", "location_code": "hk", "company": "id.Novetex Textiles Limited", "job_title": "Assistant Finance Manager", "description": "Responsibilities:\n\nReport to Financial Controller and supervise the day to day operations of a team of accounting staff;\nManaging month-end closing, group consolidation, and financial analysis, statutory reporting, forecasting, management reporting;\nEnsuring internal controls and compliance with accounting and legislative requirements;\nAssist with tax computation annually; dealing with annual statutory audit, external and internal auditors;\nCoordinate with the subsidiaries and group companies in all financial matters;\nAssist in overseeing the internal control of the group;\nImplement and enforce finance policies and procedures, tight controls and reporting system;\nAd hoc projects from time to time.\n\nRequirements:\n\nDegree holder in Accounting or related disciplines;\n8 years experience in\u00a0finance and accounting;\nRelevant experience in listed company is required;\nIn-depth knowledge in HK & PRC compliance regulations in such areas as tax and the HK Stock Exchange Listing Rules.\nProfessional qualification of HKICPA, ACCA or equivalent;\nFluent/Native in Putonghua and is a MUST. ;\nSelf-initiative detail-minded, able to work under pressure and tight deadline.\nWe offer an attractive remuneration package to the right applicants. Interested parties, please send your full resume with current and expected salary and availability by clicking \u201cApply Now\u201d.\n\nPersonal data collected will be treated in strict confidential and used for recruitment purpose only.", "employment_types": ["Full Time"], "selling_points": [], "locations": ["Lai Chi Kok"], "categories": ["Accounting", "Accountant", "Audit", "Finance / Accounting Manager"], "post_time": "2022-01-13T01:45:26Z", "salary": {"currency": null, "max": null, "min": null, "period": "monthly", "term": null}, "salary_visible": false, "title_keywords": ["assistant finance manager"], "responsibilities": ["reporting", "annual statutory audit", "day to day operations", "tax computation", "policies", "compliance", "coordinate with", "procedures", "financial analysis", "month-end closing", "ad hoc projects", "management reporting", "forecasting", "internal control", "report"], "requirements": {"degrees": ["degree holder"], "majors": ["related disciplines", "accounting"], "languages": ["putonghua"], "language_level": ["native", "fluent"], "hard_skills": ["hkicpa", "acca", "exchange"], "soft_skills": ["detail-minded", "self-initiative", "work under pressure"], "languages_combined": [{"language": "putonghua", "language_level": ["fluent", "native"]}]}, "experience_required": {"duration": ["8 years"], "field": ["finance", "accounting", "relevant experience"]}}, {"job_id": "100003009045575", "location_code": "hk", "company": "Toppan Forms (Hong Kong) Limited", "job_title": "Assistant Finance Manager", "description": "\u00a0Responsibilities:\nResponsible for the financial management of the company and for directing all the financial functions of the business\nEstablish and refine financial policies and systems to improve management efficiency and effectiveness\nPerform financial planning and business analysis, budgetary control, cash flow management, tax reporting and operation review\nReview all management accounts and prepare reports for top management in a timely, accurate and efficient manner\nComply with Hong Kong listing rules compliance requirements and enforce internal control\nProvide and support feasibility study on new business and projects\nTreasury Management\n\nRequirements:\n\nBachelor Degree in Finance or Accounting with professional accreditation such as CPA/ACCA or at equivalent\nMinimum 8 years of working experience in accounting / auditing; listed company with 3 years in supervisory role is highly preferred\nProficiency in Hong Kong accounting standards, taxation, listing rules and other legal and compliance regulations.\nFamiliar with Hong Kong accounting, legal and tax systems\nProactive, meticulous and able to work independently, efficiently and under pressure in a demanding and fast pace environment\nExcellent business acumen with good analytical skills\nExcellent communication and effective people management skills is also essential\nSound knowledge of MS applications and ERP system. Exposure in Oracle JDE implementation is preferred\nImmediately available is highly preferred\nWe offer a competitive remuneration package, our benefits include:\nPerformance bonus\nEducation subsidy\nProfessional membership fee sponsorship\nLife & medical insurance\nMarriage Leave, Compassionate Leave, Examination Leave etc.\nPublic holidays\nStaff purchase discount\n\nInterested parties please send full resume with present and expected salary to Human Resources Department by clicking \"APPLY NOW\" or via email recruit @wangon.com.\n\n(Information provided will be treated in strict confidence and will only be used for recruitment-related purposes.)", "employment_types": ["Full Time", "Permanent"], "selling_points": [], "locations": ["Kowloon Bay"], "categories": ["Accounting", "Accountant", "Finance / Accounting Manager", "Financial Analyst"], "post_time": "2022-01-13T08:06:50Z", "salary": {"currency": null, "max": null, "min": null, "period": "monthly", "term": null}, "salary_visible": false, "title_keywords": ["assistant finance manager"], "responsibilities": ["tax", "reporting", "management", "control", "prepare reports", "financial policies", "systems", "review", "compliance", "internal control", "cash flow", "business analysis", "listing", "planning"], "requirements": {"degrees": ["degree", "bachelor"], "majors": ["finance", "accounting"], "languages": [], "language_level": [], "hard_skills": ["acca", "oracle", "ms applications", "analytical skills", "cpa", "erp system", "acumen"], "soft_skills": ["meticulous", "work independently", "under pressure", "analytical skills", "communication", "business acumen", "proactive"], "languages_combined": []}, "experience_required": {"duration": ["minimum 8 years"], "field": ["accounting"]}}, {"job_id": "100003009047032", "location_code": "hk", "company": "Mercedes-Benz Hong Kong Limited", "job_title": "Assistant Manager - Controlling", "description": "Responsibilities:\n\n\nResponsible for supervision of accounts receivable team and enhancement of debtor management\u00a0\u00a0\nCoordinate with relevant stakeholders for formulation of list prices of products and services, analyzing product costs on production processes as well as product cost data verification and maintenance in ERP environment\nSupport to prepare management reporting, cost variance and return analysis for performance evaluation and highlighting issues/risks with potential development opportunities\nWork closely with internal parties and external parties including customers, auditors and solicitors for operational need\nAdvise colleagues and executive management on decisions related to the company\u2019s finance and assist to conduct regular assessment of effectiveness of internal procedures under governance\nPerform ad-hoc assignments as required\n\nRequirements:\n\n\nDegree holder in Accountancy, Finance or related disciplines with professional accounting qualification\nAt least 8 years relevant working experience, in which above 4 years in supervisory position under ERP environment, specializing in manufacturing industry would be an advantage\nSolid experience in debtor management as well as using Power Query and SAP system is highly preferable\nAttentive to details, well organized with excellent analytical skill, proactive, strong sense of responsibility and able to work under pressure to meet tight deadline\nA good team player with good interpersonal and communication skill\nGood command in both spoken and written English and Chinese (Cantonese and \u00a0\u00a0\u00a0Mandarin)\nImmediately available is strongly preferable\n\nWe offer excellent compensation package, promotion prospects and job satisfaction. Interested parties, please\u00a0email\u00a0your detailed resume with current and expected salary by click \u201cApply Now\u201d.\n\nWe are an Equal Opportunities Employer. Personal data collected will be\u00a0used strictly in accordance with the employer's personal data policy, a copy of which will be provided upon request.\u00a0Candidates who do not notified within 8 weeks after submitting your application may consider the application unsuccessful and the application will be retained up to 24 months.\n\nDisclaimer: The above position description has been designed to indicate the general nature and level of work performed by employees within this classification. It is not designed to contain or be interpreted as a comprehensive list of all duties, responsibilities, and qualifications required of employees assigned to the position.\n\nToppan Forms does not accept unsolicited referrals and/or resumes from employment businesses and/or employment agencies. Any resumes submitted in the absence of a signed agreement will become the property of Toppan Forms and no fee shall be due.\n\nFor the details of Company Information, please visit\u00a0www.toppanforms.com\u00a0", "employment_types": ["Full Time", "Permanent"], "selling_points": ["7 yrs Finance exp., less exp will be considered", "MNC Environment, great teamwork", "5-day Work Week, Flexi Hours, Mobile Working"], "locations": ["Chai Wan"], "categories": ["Accounting", "Finance / Accounting Manager", "Financial Analyst", "Professional Services", "Business Analysis / Data Analysis"], "post_time": "2022-01-14T02:06:40Z", "salary": {"currency": null, "max": null, "min": null, "period": "monthly", "term": null}, "salary_visible": false, "title_keywords": ["assistant manager"], "responsibilities": ["cost", "management", "data verification", "accounts receivable", "maintenance", "ad-hoc assignments", "analysis", "external parties", "coordinate with", "procedures", "regular assessment", "management reporting", "internal parties", "evaluation", "costs"], "requirements": {"degrees": ["degree holder"], "majors": ["related disciplines", "finance", "accounting", "accountancy"], "languages": ["cantonese", "english", "chinese", "mandarin"], "language_level": ["good command"], "hard_skills": ["analytical skill", "sap", "erp"], "soft_skills": ["analytical skill", "good team player", "attentive to details", "sense of responsibility", "communication skill", "well organized", "meet tight deadline", "proactive", "interpersonal", "work under pressure"], "languages_combined": [{"language": "cantonese", "language_level": ["good command"]}, {"language": "english", "language_level": ["good command"]}, {"language": "chinese", "language_level": ["good command"]}, {"language": "mandarin", "language_level": ["good command"]}]}, "experience_required": {"duration": ["at least 8 years", "4 years"], "field": ["supervisory", "manufacturing industry", "relevant working experience", "management"]}}, {"job_id": "100003009051835", "location_code": "hk", "company": "PwC", "job_title": "Manager / Senior Manager - Private Client Services - PwC Tax - Hong Kong", "description": "Reference No.: NR09559\nNature of Business: Medical Services co.\nLocation: T.S.T\nWorking Days: 5 Days\n\nBenefits:\n- Medical Insurance\n- \u4ea4\u901a\u8cbb\u652f\u7d66\n- \u6709\u7d66\u521d\u5e74\u5ea610\u65e5\n\nResponsibilities:\n- \u7d4c\u7406\u8ca1\u52d9\u696d\u52d9\u5168\u822c\n- \u30b9\u30bf\u30c3\u30d5\u7ba1\u7406\n- \u5404\u7a2e\u30ec\u30dd\u30fc\u30c8\u4f5c\u6210\n- \u6d77\u5916\u652f\u5e97\u306e\u8ca1\u52d9\u7ba1\u7406\u3068\u30ea\u30b9\u30af\u7ba1\u7406\n\nRequirement:\n- \u8ca1\u52d9\u30fb\u4f1a\u8a08\u7d4c\u9a1310\u5e74\u4ee5\u4e0a\n- \u65e5\u672c\u8a9e\u30cd\u30a4\u30c6\u30a3\u30d6\u30ec\u30d9\u30eb\u3001\u30d3\u30b8\u30cd\u30b9\u30ec\u30d9\u30eb\u4ee5\u4e0a\u306e\u82f1\u8a9e\n- \u00a0Peachtree\u306a\u3069\u4f1a\u8a08\u30b7\u30b9\u30c6\u30e0\u4f7f\u7528\u7d4c\u9a13\u306e\u6709\u308b\u65b9\u6b53\u8fce\n- \u6771\u5357\u30a2\u30b8\u30a2\u3084\u5317\u7c73\u306e\u8ca1\u52d9\u4f1a\u8a08\u77e5\u8b58\u304c\u3042\u308c\u3070\u5c1a\u826f\u3044\n- \u7d4c\u9a13\u306b\u5fdc\u3058\u3066VISA\u5bfe\u5fdc\u53ef\u80fd\n\n\n\nInterested in the above vacancy?\u00a0 Send your resume to us NOW!\nOnly short-listed candidates will be notified. Personal data collected will be used for recruitment purpose only", "employment_types": ["Full Time"], "selling_points": [], "locations": ["Not Specified"], "categories": ["Accounting", "Finance / Accounting Manager", "Taxation", "Management", "General Management"], "post_time": "2022-01-17T01:19:31Z", "salary": {"currency": null, "max": null, "min": null, "period": "monthly", "term": null}, "salary_visible": false, "title_keywords": ["senior manager", "manager"], "responsibilities": [], "requirements": {"degrees": [], "majors": [], "languages": [], "language_level": [], "hard_skills": [], "soft_skills": [], "languages_combined": []}, "experience_required": {"duration": [], "field": []}}, {"job_id": "100003009048407", "location_code": "hk", "company": "Guangdong Investment Ltd", "job_title": "SENIOR ACCOUNTING MANAGER", "description": "Responsibilities\n\n\nPerform financial evaluation on the MB Cars' pricing proposals and make recommendation in order to obtain Local and HQ Management approval.\nDevelop the annual operative planning and quarterly forecast for financial items and co-ordinate with all other functional areas for planning submission.\nMonitor and closely track business performance and propose measures to improve or close gap against defined KPIs.\nPrepare month-end closing and management reports at Business Unit level with financial analysis on evaluating business performance.\nPrepare simulations based on business performance and dealer target agreement. Review and verify the target achievement result of the dealer and the performance bonus calculations to ensure the accuracy.\nPrepare and analyze the proposal for relevant sale schemes, contracts and ad hoc request.\nEstablish financial model or feasibility study for projects or business decision.\nRegular monitoring and execution of internal control activities for the responsible areas to ensure the compliance of the local and global reporting requirements.\n\nRequirements\n\nDegree in Business Administration, major in Accounting or related Finance degree\nAt least 7 years relevant experience in the area of Financial Planning and Controlling\nGood knowledge of SAP FICO module\nKnowledge and experience in Financial Planning & Controlling methods and building a financial modelling\nMindset of continuous improvement and able to propose enhancements for operational efficiencies and effectiveness\nHigh proficiency in both English and Chinese professional business writing\nHighly analytical and logical with structured and critical thinking\nSolid problem-solving skills\nSensitive to figures, attentive to details and high accuracy of work\nStrong intercultural, communication and interpersonal skills\nSelf-motivated, ability to work independently and be a team player\nAble to meet deadlines and work under pressure\nCandidates with less experience will also be considered as Senior Executive - Controlling\n\nFor the successful candidate, we offer a 5-day week in addition to a salary that commensurate with your experience and qualification.\n\nPotential candidates who meet our requirements, kindly apply with full resume and application letter indicating your present and expected salary via \"Apply Now\".\n\nWe are an equal opportunity employer. The information provided will be treated in strict confidence and only be used for recruitment related purposes. The Company may refer suitable applicants to other vacancies within the Group. All personal data of unsuccessful applicants will be destroyed within 12 months on completion of the recruitment exercise.", "employment_types": ["Full Time"], "selling_points": ["Review group financial reporting", "Evaluate business performance", "Participate in ad-hoc assignments"], "locations": ["Sheung Wan"], "categories": ["Accounting", "Finance / Accounting Manager"], "post_time": "2022-01-14T06:29:13Z", "salary": {"currency": null, "max": null, "min": null, "period": "monthly", "term": null}, "salary_visible": false, "title_keywords": ["accounting manager"], "responsibilities": ["co-ordinate with", "evaluation", "internal control", "ad hoc", "contracts", "compliance", "monitor", "develop", "forecast", "kpis", "reporting", "management", "make recommendation", "review", "monitoring", "financial analysis", "management reports", "month-end closing", "planning"], "requirements": {"degrees": ["degree"], "majors": ["finance", "accounting", "business administration"], "languages": ["english", "chinese"], "language_level": ["proficiency"], "hard_skills": ["problem-solving skills", "sap"], "soft_skills": ["self-motivated", "work independently", "attentive to details", "sensitive to figures", "communication and interpersonal skills", "problem-solving skills", "team player", "structured", "meet deadlines", "work under pressure"], "languages_combined": [{"language": "english", "language_level": ["proficiency"]}, {"language": "chinese", "language_level": ["proficiency"]}]}, "experience_required": {"duration": ["at least 7 years"], "field": ["planning", "relevant experience", "financial"]}}, {"job_id": "100003009054075", "location_code": "hk", "company": "Classy Wheeler Limited", "job_title": "Accountant (Retail Industry)", "description": "Job Description & Summary\n\nA career in our Tax Wealth Advisory practice, within Tax services, will provide you with the opportunity to help our clients meet and manage their tax obligations across unique but ever changing tax specialties. You\u2019ll advise clients on their local and overseas tax affairs, while acting as a strategic consultant related to business analysis, managing indirect taxes, dispute resolution, and global enterprise tax solutions.\n\nOur team offers clients a scalable solution to address the tax compliance needs of corporations, partnerships, and other business entities by managing compliance services to maximise a tax department\u2019s strengths and minimise the impact on our clients resources. You\u2019ll support clients by providing outsourcing services which includes the preparation and review of income and franchise returns along with responding to inquiries from federal, state and local taxing authorities for our clients.\n\nAssist in preparation of documentation in relation to and support superiors to handle family wealth planning projects\n\nAssist in the set-up of asset holding structure for family wealth planning purposes\n\nAssist in the formation of Hong Kong or offshore companies and the ongoing maintenance including the filing of the necessary returns with the registration authority\n\nAssist in the application and ongoing maintenance of immigration matters\n\nRequirements\n\nA degree holder preferably in Accounting/Law/Corporate Governance but not essential.\n\nStudent member of ICSA / HKICS/HKICPA will be an advantage.\n\nFive years of company secretarial or personal tax experience preferable\n\nProficient in English and Chinese. Putonghua is essential.\n\nChinese writing and reading skill is essential.\n\nA team player with strong initiative and able to work under pressure.\n\n\n\n\u6709\u610f\u7533\u8acb\u8005\u8acb \u6309 APPLY NOW\u7533\u8acb\n\n", "employment_types": ["Full Time", "Permanent"], "selling_points": ["Luxury Italian shoes brand", "5 years of accounting experience in retail sector", "Competitive remuneration package and benefit"], "locations": ["Not Specified"], "categories": ["Accounting", "Accountant", "Accounting Clerk / Supervisor", "Finance / Accounting Manager"], "post_time": "2022-01-17T08:19:20Z", "salary": {"currency": null, "max": null, "min": null, "period": "monthly", "term": null}, "salary_visible": false, "title_keywords": ["accountant"], "responsibilities": ["tax", "documentation", "maintenance", "compliance", "review", "resolution", "support clients", "business analysis", "planning"], "requirements": {"degrees": ["degree holder"], "majors": ["accounting", "law"], "languages": ["putonghua", "english", "chinese"], "language_level": ["proficient"], "hard_skills": ["hkicpa"], "soft_skills": ["team player", "initiative", "work under pressure"], "languages_combined": [{"language": "putonghua", "language_level": []}, {"language": "english", "language_level": ["proficient"]}, {"language": "chinese", "language_level": ["proficient"]}]}, "experience_required": {"duration": ["five years"], "field": ["secretarial"]}}, {"job_id": "100003009052935", "location_code": "hk", "company": "Grand Alliance Asset Management Ltd", "job_title": "Graduate Trainee - Operations", "description": "Responsibilities\n\nReview group financial reporting and monthly consolidation\nEvaluate business performance\nPrepare and implement budgetary control\nParticipate in ad-hoc assignments, such as M&A transactions\nEnhance and maintain internal controls\n\nRequirements\n\nDegree holder in Accounting, Finance or related disciplines\nQualified accountant with a minimum of 12 years' of relevant working experience, of which at least 4 years managerial role in listed companies of related industries, preferably with transaction or auditing experience\nExcellent knowledge of Hong Kong accounting standards and listing rules\nSolid experience in reviewing sizeable consolidation\nGood leadership, interpersonal and strong problem solving skills\nAble to work under pressure and handle multiple tasks\nExcellent analytical, report writing, presentation and communication skills\nFluent in both spoken and written English and Chinese (Cantonese & Mandarin)\nKnowledge in Oracle Hyperion and E-Business Suite will be a definite advantage\nCandidates with less experience will be considered for the post of Accounting Manager.\n\nAttractive and competitive remuneration package will be offered to the right candidate.\u00a0 Application with full resume, current and expected salary, and date of availability should be sent through email. For details of the Company, please visit our website: www.gdi.com.hk.\n\nInformation provided will be for recruitment purpose and only short-listed candidates will be contacted. We comply with all applicable laws and regulations of HKSAR in handling applications.", "employment_types": ["Full Time", "Permanent"], "selling_points": [], "locations": ["Central"], "categories": ["Accounting", "Finance / Accounting Manager", "Information Technology (IT)", "Application Specialist - Software", "Banking / Finance", "Risk Management"], "post_time": "2022-01-17T04:45:22Z", "salary": {"currency": null, "max": null, "min": null, "period": "monthly", "term": null}, "salary_visible": false, "title_keywords": ["operations", "graduate trainee"], "responsibilities": ["control", "ad-hoc assignments", "review", "transactions", "evaluate", "maintain", "financial reporting"], "requirements": {"degrees": ["degree holder"], "majors": ["related disciplines", "finance", "accounting"], "languages": ["cantonese", "english", "chinese", "mandarin"], "language_level": ["fluent"], "hard_skills": ["problem solving skills", "oracle"], "soft_skills": ["communication skills", "presentation", "handle multiple tasks", "problem solving skills", "leadership", "interpersonal", "work under pressure"], "languages_combined": [{"language": "cantonese", "language_level": []}, {"language": "english", "language_level": ["fluent"]}, {"language": "chinese", "language_level": ["fluent"]}, {"language": "mandarin", "language_level": []}]}, "experience_required": {"duration": ["at least 4 years", "minimum of 12 years"], "field": ["managerial", "related", "consolidation", "relevant working experience", "accounting"]}}, {"job_id": "100003009045658", "location_code": "hk", "company": "ImagineX Management Co Ltd", "job_title": "Assistant Accounting Manager", "description": "Our Client\n\nOur client, an Italian luxury shoes brand, is looking for an Accountant to join their professional team in Hong Kong and support Hong Kong accounting team\n\nJob Responsibilities\n\nReport to Financial Controller\nProvide finance support to Hong Kong sales & operations team\nHandle full set of accounts and bookkeeping for local business\nArrange payment for local business and ensure compliance with brand payment procedures\nPrepare weekly cash flow forecast and project cash flow plans\nConsolidate sales statements and overall control on local invoices and issuing\nSupport annual filings as required by local tax bureau\nCoordinate for transfer price documentation, if any\nMaintain Fixed Asset Registrar and perform regular physical check of fixed asset\nComplete the bookkeeping and financial reporting\nProvide necessary financial training and coaching to local sales staff, or any other concerned employees\nSupport internal / external audit as necessary\nAny other tasks or projects assigned by Financial Controller\n\nJob Requirements\n\nBachelor degree in Accounting\nOver 5 years\u2019 of work experience in retail finance role, and hands-on experience in different finance aspects could be a plus\nWell organized and attention to details\nGood command of both spoken and written English and Chinese\nExcellent interpersonal and communication skills\nGood team spirit\n\nInterested applicants, please send your detailed resume quoting position title, reference number, current and expected salary.\n\nPersonal data provided by job applicants will be used\u00a0strictly in accordance with the employer's personal data policies and for recruitment purposes only.", "employment_types": ["Full Time", "Permanent"], "selling_points": ["Accounting & Auditing", "5 years' solid working experience", "Experience in retail industry"], "locations": ["Southern Area"], "categories": ["Accounting", "Accountant", "Accounting Clerk / Supervisor", "Finance / Accounting Manager"], "post_time": "2022-01-13T08:17:22Z", "salary": {"currency": null, "max": null, "min": null, "period": "monthly", "term": null}, "salary_visible": false, "title_keywords": ["assistant accounting manager"], "responsibilities": ["tax", "control", "invoices", "operations", "full set of accounts", "procedures", "audit", "ensure compliance", "coordinate", "other tasks", "payment", "cash flow", "maintain", "financial reporting", "forecast", "documentation", "plans", "report"], "requirements": {"degrees": ["degree", "bachelor"], "majors": ["accounting"], "languages": ["english", "chinese"], "language_level": ["good command"], "hard_skills": ["plus"], "soft_skills": ["communication skills", "team spirit", "well organized", "hands-on", "attention to details", "interpersonal", "detailed"], "languages_combined": [{"language": "english", "language_level": ["good command"]}, {"language": "chinese", "language_level": ["good command"]}]}, "experience_required": {"duration": ["5 years"], "field": ["finance", "retail"]}}, {"job_id": "100003009050893", "location_code": "hk", "company": "S.F. Express (Hong Kong) Limited", "job_title": "Assistant Finance Manager (SF REIT Asset Management Limited)", "description": "We aim to nurture bright, young finance talents by helping them to lay the foundation for a rewarding and challenging career in the asset management industry.\u00a0\n\nResponsibilities\n\nAssist in handling legal & compliance (incl. KYC/AML/CTF/PI/CRS/FATCA/SOW) matters and client service duties\nAssist in company accounting, fund accounting, reconciliation, risk management and fund operations\u00a0\n\nRequirements\n\nBachelor\u2019s degree in Business Administration, Accounting, Finance, Law, English Literature, Statistics or related disciplines. We also welcome candidates from other disciplines\nCPA, completion of certain core HKICPA modules, FRM, a certificate in legal studies, HKSI\u2019s Paper 1 exam and/or other relevant professional qualification is a plus\nLess than 2 years\u2019 prior work experience in legal & compliance, client services, investor relations, operations support, financial accounting, audit, taxation, risk management and/or data management is preferred\nStrong written and verbal communication skills with excellent command of English\nDetail-minded and well-organized\nStrong communication and interpersonal skills\nKnowledge in IT or any of the programming languages is a plus\nA team player and a self-starter, with a strong sense of responsibility and the ability to work well under pressure\u00a0\n\nCompetitive compensation, culture of growth and career development. Located in Central (Hong Kong), annual leave, public holidays, MPF, group life insurance & medical benefits\u00a0\n\nPlease e-mail cover letter & CV with expected salary\u00a0by clicking APPLY NOW.\n", "employment_types": ["Full Time"], "selling_points": ["Free shuttle bus coverage", "Attractive performance bonus", "Finance Functions"], "locations": ["Tsing Yi"], "categories": ["Accounting", "Finance / Accounting Manager", "Taxation", "Banking / Finance", "Others"], "post_time": "2022-01-14T11:40:37Z", "salary": {"currency": null, "max": null, "min": null, "period": "monthly", "term": null}, "salary_visible": false, "title_keywords": ["assistant finance manager", "asset management"], "responsibilities": ["management", "aml", "operations", "compliance", "kyc"], "requirements": {"degrees": ["certificate", "degree", "bachelor"], "majors": ["business administration", "law", "finance", "statistics", "related disciplines", "accounting"], "languages": ["english"], "language_level": ["excellent"], "hard_skills": ["plus", "data management", "hksi", "cpa", "programming", "frm", "hkicpa"], "soft_skills": ["detail-minded", "communication skills", "under pressure", "sense of responsibility", "well-organized", "communication and interpersonal skills", "team player"], "languages_combined": [{"language": "english", "language_level": ["excellent"]}]}, "experience_required": {"duration": ["2 years"], "field": ["risk management", "management", "legal", "compliance", "audit", "accounting", "financial"]}}, {"job_id": "100003009042563", "location_code": "hk", "company": "mReferral Corporation (HK) Ltd   \u7d93\u7d61\u96c6\u5718(\u9999\u6e2f)\u6709\u9650\u516c\u53f8", "job_title": "Senior Manager (Finance & HR)", "description": "Are you a passionate and yet creative talent who can think out of the box to driving the people agenda with a new approach? ImagineX Group is a premier retail, brand management and distribution company. We build luxury, designer and premium contemporary fashion, beauty and lifestyle businesses with an entrepreneurial approach and the passion and flair of a brand owner.\n\nWe are now inviting a creative, self-motivated, energetic and talented Assistant Accounting Manager\u00a0to join us.\n\nAssistant Accounting Manager\n\n\nWHAT YOU WILL BE DOING?\n\nPerform timely and accurate monthly and quarterly financial reporting, budget and forecast\nProvide analytical review and reporting on the company's performance\u00a0\nEnsure compliance with internal policies and regulations\nManage annual audit and assist in all tax related matters\nParticipate in ad-hoc projects\n\nYOU\u00a0NEED TO BE...\n\nUniversity graduate with a degree in Accounting and an internationally recognized\u00a0accounting qualification\nMinimum 5 years of solid financial accounting and auditing experience\nPrevious work experience in retail business is preferred\nPrior experience in Flex accounting system is an advantage\u00a0\nStrong interpersonal, communication, problem solving and supervisory skills\nMature, self-motivated, detail oriented and able to work under pressure\nGood command of spoken and written English, Chinese and Mandarin\n\nWE OFFER YOU...\n\nAnnual Leave & Birthday Leave\nPublic Holidays\n5-day Marriage Leave\nMedical Insurance\nDental Care\nProfessional Corporate Training\nAnnual Performance Bonus\nFree Shuttle Bus\nStaff Purchase Discount\nMonthly MPF Contribution up to 10% of Salary\n\nInterested parties please send your Full resume with current & expected salary to us by clicking Apply Now.\n\nInformation provided will be treated in strict confidence and only be used for recruitment purpose. The Company may refer suitable applicants to other vacancies within the associated Group of companies.\n\nFor more information of ImagineX Group, please visit our web site at\u00a0http://www.imaginex.com", "employment_types": ["Full Time", "Permanent"], "selling_points": ["Qualified CPA and Chartered Secretary", "Min 10 years experience in Finance and Account", "Min 3 years in managerial capacity"], "locations": ["Wan Chai"], "categories": ["Accounting", "Chief Accountant", "Finance / Accounting Manager", "Financial Controller"], "post_time": "2022-01-12T07:59:08Z", "salary": {"currency": null, "max": null, "min": null, "period": "monthly", "term": null}, "salary_visible": false, "title_keywords": ["senior manager", "hr"], "responsibilities": ["regulations", "reporting", "management", "tax", "annual audit", "policies", "review", "budget", "ensure compliance", "communication", "financial reporting", "forecast", "ad-hoc projects", "auditing", "work under pressure"], "requirements": {"degrees": ["university graduate", "degree"], "majors": ["accounting"], "languages": ["english", "chinese", "mandarin"], "language_level": ["good command"], "hard_skills": ["problem solving", "flex accounting"], "soft_skills": ["passionate", "self-motivated", "accurate", "timely", "detail oriented", "mature", "communication", "problem solving", "energetic", "creative", "interpersonal", "work under pressure"], "languages_combined": [{"language": "english", "language_level": ["good command"]}, {"language": "chinese", "language_level": ["good command"]}, {"language": "mandarin", "language_level": ["good command"]}]}, "experience_required": {"duration": ["minimum 5 years"], "field": ["business", "accounting", "retail", "financial"]}}, {"job_id": "100003009046863", "location_code": "hk", "company": "Cloud Light Technology Limited", "job_title": "Accounting Manager (Job Ref. No. Apply-HK-2108-AM)", "description": "Responsibilities\n\n\nAssist in financial statements review and analysis\nAssist in cash flow management\nAssist in annual audit and interim review\nAssist in budget preparation and monitoring\nAssist in filing tax returns\nAssist in internal control procedures\nAssist in system implementation and maintenance\nAssist in business support and acquisition from financial perspective\nAssist in other tasks as assigned\n\nRequirements\n\n\n\nDegree holder in Finance/Accounting or related disciplines\nAround 5 years\u2019 relevant experience, package will be commensurate with experience\nProactive, detail-minded, well-organized and result-oriented with excellent interpersonal skills, analytical mind and sense of responsibility\nFluent in English, Mandarin and Cantonese\n\n\n\nWe offer attractive remuneration package and fringe benefits to the suitable candidates. Interested parties, please submit your application to us.\u00a0\n\nYou are welcome to visit our website at\u00a0https://htm.sf-express.com/hk/tc/\u00a0for more information about us.\n\nCandidates who are not invited for an interview within 1-month may consider their applications unsuccessful.\n\nAll personal data provided by job applicants will be used only for recruitment purposes and will be treated strictly confidential. Unsuccessful applications will be retained for a maximum period of 24-month.", "employment_types": ["Full Time"], "selling_points": ["High-growth technology company", "2 years with Big 4 / Large Audit Firm", "Statutory Audited Accounts, Tax Planning"], "locations": ["Shatin Area"], "categories": ["Accounting", "Finance / Accounting Manager"], "post_time": "2022-01-14T01:29:31Z", "salary": {"currency": null, "max": null, "min": null, "period": "monthly", "term": null}, "salary_visible": false, "title_keywords": ["accounting manager"], "responsibilities": ["tax", "management", "maintenance", "annual audit", "analysis", "review", "budget", "monitoring", "financial statements", "procedures", "implementation", "other tasks", "cash flow", "internal control"], "requirements": {"degrees": ["degree holder"], "majors": ["related disciplines", "finance", "accounting"], "languages": ["cantonese", "english", "mandarin"], "language_level": ["fluent"], "hard_skills": [], "soft_skills": ["detail-minded", "sense of responsibility", "well-organized", "analytical mind", "interpersonal skills", "proactive", "result-oriented"], "languages_combined": [{"language": "cantonese", "language_level": ["fluent"]}, {"language": "english", "language_level": ["fluent"]}, {"language": "mandarin", "language_level": ["fluent"]}]}, "experience_required": {"duration": ["5 years"], "field": ["relevant experience"]}}, {"job_id": "100003009043725", "location_code": "hk", "company": "Airstar Bank Limited", "job_title": "Finance Manager", "description": "Responsibilities:\n\nLead the Finance Department over financial control and accounting functions, including management accounts reporting, forecast & budgeting, tax compliance and company secretarial matters handling\nIdentify performance drivers for both revenue and expenses and highlight any business risks and opportunities\nSupport management in key strategic initiatives and business improvement projects\nLead and supervise the HR and Administration team\nOversee full spectrum of HR function, including manpower planning and budgeting, talent acquisition, compensations and benefits, performance management, learning and development, employee relations\nReview and ensure HR policies and procedures are in alignment with operation needs and in compliance with labour regulations\nMonitor all spectrum of administration support to office, including maintenance, clean procurement of office supplies and other administration related matters\n\nRequirement:\n\nDegree holder in Finance or Accounting, qualified CPA and Chartered Secretary\nAt least 10 years' experience in finance and accounting with minimum 3 years' in managerial capacity\nExcellent business acumen with good analytical skills\nProactive, meticulous and able to work independently\nExcellent communication and effective people management skills\n\nWe offer attractive compensation package & career prospects to the right candidates. Interested parties please send your full resume with\u00a0availability,\u00a0present & expected salary to HR Department by clicking \"Apply Now\".\n\nPersonal data collected will be used for recruitment purpose only.", "employment_types": ["Full Time", "Permanent"], "selling_points": [], "locations": ["Tsim Sha Tsui"], "categories": ["Accounting", "Finance / Accounting Manager"], "post_time": "2022-01-13T01:40:44Z", "salary": {"currency": null, "max": null, "min": null, "period": "monthly", "term": null}, "salary_visible": false, "title_keywords": ["finance manager"], "responsibilities": ["tax", "regulations", "control", "management", "maintenance", "office supplies", "budgeting", "hr", "compliance", "expenses", "review", "accounts reporting", "policies", "procedures", "monitor", "planning", "forecast", "administration"], "requirements": {"degrees": ["degree holder"], "majors": ["finance", "accounting"], "languages": [], "language_level": [], "hard_skills": ["cpa", "analytical skills", "acumen"], "soft_skills": ["meticulous", "work independently", "analytical skills", "communication", "business acumen", "proactive"], "languages_combined": []}, "experience_required": {"duration": ["at least 10 years", "minimum 3 years"], "field": ["finance", "accounting", "managerial"]}}, {"job_id": "100003009042396", "location_code": "hk", "company": "Wang On Group", "job_title": "Assistant Finance Manager", "description": "\u00a0Job Responsibilities\n\nResponsible for the accurate production of month end financial number and data integrity of the financial ledger, including accrual of expense, depreciation of fixed asset, expense and procurement policies.\nResponsible for the timely maintenance of the ledger and respective systems, including raise and test Hi-sun/SAP system enhancement to ensure correct accounting flow in the financial general ledger system\nProvide accounting input on the new product and system implementation\nPerform other financial governance control related activities, including but not limited to risk assessment, BCP\nInvolve in the routine review and finetune of various financial governance and accounting policies\nAssist financial controller in providing info for auditor or other authority submission, eg. Tax filing submission\n\n\u00a0Job Requirements\n\n1. Knowledge, Skills & Attributes\n\nHave knowledge on financial, in particular on month end closing and technical accounting.\nGood sense of financial governance concept.\nStrong interpersonal communication skill with all level of people\nAbility to work under pressure, plan personal workload effectively\n2. Academic and Professional Qualification\n\nBachelor\u2019s degree in accounting or Finance\nMember of Accounting Professional Bodies\n\u00a03.\u00a0Training and Relevant Experiences\nAt least have 8 years or more experience, of which contains 3 to 5 years of banking industry covering Finance function\n\nWe offer competitive package to the right candidates. Interested parties please send your resume with current and expected salary by clicking the\u00a0\u201cApply Now\u201d\u00a0button.\u00a0\u00a0\n\n\u00a0All information provided by applicants will be treated in strict confidence and handled confidentially for recruitment purposes only. Applicants who are not contacted within 8 weeks may consider their application unsuccessful and their data will be destroyed within 12 months.", "employment_types": ["Full Time", "Permanent"], "selling_points": [], "locations": ["Kowloon Bay"], "categories": ["Accounting", "Audit", "Finance / Accounting Manager"], "post_time": "2022-01-12T07:18:25Z", "salary": {"currency": null, "max": null, "min": null, "period": "monthly", "term": null}, "salary_visible": false, "title_keywords": ["assistant finance manager"], "responsibilities": ["control", "maintenance", "data", "general ledger", "systems", "review", "implementation", "tax filing", "accounting policies", "procurement policies", "accrual"], "requirements": {"degrees": ["degree", "bachelor"], "majors": ["finance", "accounting"], "languages": [], "language_level": [], "hard_skills": [], "soft_skills": ["communication skill", "interpersonal", "work under pressure"], "languages_combined": []}, "experience_required": {"duration": ["3 to 5 years", "8 years"], "field": ["finance", "banking industry", "training"]}}, {"job_id": "100003009047131", "location_code": "hk", "company": "", "job_title": "Financial Manager - Chairman Office", "description": "Job Description\n\nAssists the Accounting Manager to over view the daily accounting operations and assist in any communication between internal departments in an absence of the Manager.\n\nThe Assistant Accounting Manager will report directly to the Accounting Manager.\u00a0 Candidate with less experience will also be considered for the position of Accountant.\n\nJob title of subordinates\n\nAccountant, Accounts Executive and Accounts Clerk\n\nArea of Responsibility\n\nResponsible to ensure all matter regarding full spectrum of accounting (internally and externally) is keeping proper record and comply with Hong Kong Accounting Standard.\n\nResponsibilities\n\nPrepare monthly statements, invoices, handling all enquiries and payment issues related\u00a0 to club members, school, suppliers and business associates\nPrepare regular and ad-hoc accounting reports for management and directors' review\nResponsible for managing the cash flow at adequate level e.g. cash receivable and payable, time deposit\nHandle claims for petty cash, prepare cheques, arrange T/T payments and all accounts payable duties with proper proof and record\nPayroll administration for part-time and casual staff\u00a0\nMaintain and check proper record on Club merchandise and in the Club accounting system\u00a0\nMake sure the internal or external audits are conducted smoothly by providing relevant and sufficient information to auditors\nAssist in setting up of accounting policies and IT system\nCoordinate with other club administrators for booking keeping issues\nResponsible to obtain accounting related reports from different sections or departments", "employment_types": ["Full Time"], "selling_points": ["Medical insurance", "Dental insurance", "Five-day work"], "locations": ["Wan Chai"], "categories": ["Accounting", "Finance / Accounting Manager", "Banking / Finance", "Corporate Finance"], "post_time": "2022-01-14T02:30:39Z", "salary": {"currency": null, "max": null, "min": null, "period": "monthly", "term": null}, "salary_visible": false, "title_keywords": ["financial manager"], "responsibilities": ["ad-hoc", "communication", "payment", "cheques", "maintain", "accounting policies", "administration", "invoices", "daily accounting operations", "reports", "report", "management", "review", "coordinate with", "cash flow", "booking", "audits", "payroll", "payments", "accounts payable"], "requirements": {"degrees": [], "majors": [], "languages": [], "language_level": [], "hard_skills": ["make", "accounting system"], "soft_skills": ["communication", "responsible"], "languages_combined": []}, "experience_required": {"duration": [], "field": []}}, {"job_id": "100003009052994", "location_code": "hk", "company": "Ruike Consultancy Asia Limited", "job_title": "(1-3 years ONLY! ) Accounting Officer (top tier financial services firm)", "description": "\u00a0Responsibilities:\nResponsible for the financial management of the company and for directing all the financial functions of the business\nEstablish and refine financial policies and systems to improve management efficiency and effectiveness\nPerform financial planning and business analysis, budgetary control, cash flow management, tax reporting and operation review\nPrepare and review full sets of accounts and day-to-day management of all accounting activities\nPrepare and review all management accounts and prepare reports for top management in a timely, accurate and efficient manner\nComply with legal requirements, enforce internal control and Group compliance requirements\nProvide and support feasibility study on new business and projects\n\nRequirements:\n\nBachelor Degree in Finance or Accounting with professional accreditation such as CPA/ACCA or at equivalent\nMinimum 5 years of working experience in accounting / auditing / property developer & listed company with 2 years in supervisory role is highly preferred\nProficiency in Hong Kong accounting standards, taxation, listing rules and other legal and compliance regulations.\nFamiliar with Hong Kong accounting, legal and tax systems\nProactive, meticulous and able to work independently, efficiently and under pressure in a demanding and fast pace environment\nExcellent business acumen with good analytical skills\nExcellent communication and effective people management skills is also essential\nSound knowledge of MS applications and ERP system. Exposure in Oracle implementation is preferred\n\nWe offer competitive remuneration package, our benefits include:\n\nPerformance bonus\nEducation subsidy\nProfessional membership fee sponsorship\nLife & medical insurance\nMarriage Leave, Compassionate Leave, Examination Leave etc.\nPublic holidays\nStaff purchase discount\n\nInterested parties please send\u00a0full resume\u00a0with present and expected salary\u00a0to Human Resources Department by clicking\u00a0\"APPLY NOW\" or e-mail to recruit @wangon.com\n\n(Information provided will be treated in strict confidence and will only be used for recruitment-related purposes.)", "employment_types": ["Full Time"], "selling_points": [], "locations": ["Central"], "categories": ["Accounting", "Accountant", "Accounting Clerk / Supervisor", "Finance / Accounting Manager"], "post_time": "2022-01-17T04:53:33Z", "salary": {"currency": null, "max": null, "min": null, "period": "monthly", "term": null}, "salary_visible": false, "title_keywords": ["accounting officer"], "responsibilities": ["tax", "reporting", "management", "control", "prepare reports", "financial policies", "systems", "review", "compliance", "day-to-day management", "cash flow", "business analysis", "internal control", "planning"], "requirements": {"degrees": ["degree", "bachelor"], "majors": ["finance", "accounting"], "languages": [], "language_level": [], "hard_skills": ["acca", "oracle", "ms applications", "analytical skills", "cpa", "erp system", "acumen"], "soft_skills": ["meticulous", "work independently", "under pressure", "analytical skills", "communication", "business acumen", "proactive"], "languages_combined": []}, "experience_required": {"duration": ["2 years", "minimum 5 years"], "field": ["developer", "supervisory", "accounting"]}}, {"job_id": "100003009045606", "location_code": "hk", "company": "Babel Capital Limited", "job_title": "Finance Associate/ Manager", "description": "Position Responsibilities:\n\nAssisting CEO with corporate strategic planning activities\nLiaise with, negotiate, and implement investment opportunities, bank financing, fund raising, corporate finance and capital market transactions for the group's business operation worldwide\nSupport lead evaluation, due diligence, management and execution of corporate finance transactions including investment / M&A, restructuring and both onshore and offshore debt & equity fund-raising activities\nBusiness forecast monitoring\nEnsure due compliance with Company\u2019s policies and procedures in carrying out responsibilities and executing transactions.\nDevelop and maintain investor relations, deal with related issues, assist with provision of \u00a0important corporate information, and engage strategic investors, etc.\u00a0\n\nPosition Requirements\n\nUniversity graduate in Finance, Accounting or Business\nAt least 10 years solid experiences in corporate finance gained from both advisory firms and commercial companies preferably with sizable Chinese enterprises investment banking or financial institutions experience is a MUST\nRecognised professional accountancy qualifications (CPA/CFA)\nWith strong strategic planning / investment assessment\nStrong in financial modelling, analytical and presentation skills\nDemonstrated success in M&A and corporate finance transactions\nSolid understanding of business operations, finance and accounting\nFluent in English and Mandarin with excellent presentation and communication skills\nSelf-starter with a strong drive to complete tasks effectively and accurately within tight deadline\nSelf-motivated to take ownership of job responsibilities\nFlexible working hours/times.", "employment_types": ["Full Time"], "selling_points": ["fintech startup", "financial services, accounting", "financial report and accounting"], "locations": ["Central"], "categories": ["Accounting", "Finance / Accounting Manager", "Treasurer", "Banking / Finance", "Financial Services"], "post_time": "2022-01-13T08:11:24Z", "salary": {"currency": null, "max": null, "min": null, "period": "monthly", "term": null}, "salary_visible": false, "title_keywords": ["associate", "manager"], "responsibilities": ["business operation", "due diligence", "management", "strategic planning", "policies", "monitoring", "compliance", "procedures", "transactions", "develop", "maintain", "executing", "forecast", "evaluation", "liaise with"], "requirements": {"degrees": ["university graduate"], "majors": ["business", "finance", "accounting"], "languages": ["english", "chinese", "mandarin"], "language_level": ["excellent", "fluent"], "hard_skills": ["cfa", "cpa"], "soft_skills": ["flexible", "communication skills", "self-motivated", "presentation skills", "presentation"], "languages_combined": [{"language": "english", "language_level": ["fluent", "excellent"]}, {"language": "chinese", "language_level": []}, {"language": "mandarin", "language_level": ["fluent", "excellent"]}]}, "experience_required": {"duration": ["at least 10 years"], "field": ["corporate finance", "commercial", "investment", "banking", "financial institutions"]}}, {"job_id": "100003009047619", "location_code": "hk", "company": "World Universal (International) Limited", "job_title": "Internal Audit Manager", "description": "Our client is a leading financial services company in Hong Kong.\u00a0\n\n\n\nResponsibilities:\n\nHandling daily accounting operations including AR/AP, general journal entries, bills and payments, bank reconciliation;\nHandle full set of accounts including bank reconciliation, general ledger, fixed assets register, prepayment, accruals and month-end closing and etc;\nPrepare monthly management accounts with accounting schedules and reconciliations on timely basis, including trust reconciliation against client assets;\nLiaise with external auditor and tax representatives for the preparation of statutory financial reports and tax filing.\nPerform ad-hoc assignments as required\n\nRequirements:\n\nDegree holder in Accounting, Finance or related discipline;\nAround 1-3 years accounting experience for the financial services sector;\nHighly independent, self-motivated, enthusiastic, capable to meet deadline and work under pressure\nGood command of written and spoken Chinese, English and Mandarin;\nGood interpersonal and communications skills;\nSelf-motivated, detail oriented, strong sense of responsibility and multi-tasked\n\nPlease feel free to send your updated profile together with your salary information to resume(at)ruikezixun.com to have a further discussion.\u00a0", "employment_types": ["Full Time", "Permanent"], "selling_points": [], "locations": ["Ngau Tau Kok"], "categories": ["Accounting", "Audit", "Finance / Accounting Manager", "Financial Analyst"], "post_time": "2022-01-15T03:49:45Z", "salary": {"currency": null, "max": null, "min": null, "period": "monthly", "term": null}, "salary_visible": false, "title_keywords": ["manager"], "responsibilities": ["ap", "tax", "management", "financial reports", "ar", "schedules", "general ledger", "ad-hoc assignments", "full set of accounts", "tax filing", "daily accounting operations", "bank reconciliation", "reconciliations", "month-end closing", "payments", "journal entries", "liaise with"], "requirements": {"degrees": ["degree holder"], "majors": ["finance", "accounting"], "languages": ["english", "chinese", "mandarin"], "language_level": ["good command"], "hard_skills": [], "soft_skills": ["highly independent", "self-motivated", "capable", "sense of responsibility", "detail oriented", "multi-tasked", "enthusiastic", "interpersonal", "work under pressure"], "languages_combined": [{"language": "english", "language_level": ["good command"]}, {"language": "chinese", "language_level": ["good command"]}, {"language": "mandarin", "language_level": ["good command"]}]}, "experience_required": {"duration": ["1-3 years"], "field": ["accounting experience", "financial services"]}}, {"job_id": "100003009045014", "location_code": "hk", "company": "Dah Chong Hong, Limited", "job_title": "Assistant Finance Manager", "description": "Babel Finance, a reputable digital assets/ crypto services provider, has the following opening in Hong Kong for application:\n\n\n\u00a0\u00a0\u00a0\u00a0\u00a0\u00a0 The role reports to Senior Finance Manager\n\u00a0\u00a0\u00a0\u00a0\u00a0\u00a0 To assist the finance team for efficient monthly closing, high quality financial reporting, financial operations, process and approvals, management reporting, and forecasting.\n\nIdeal candidate:\n\n\u00a0\u00a0\u00a0\u00a0\u00a0\u00a0 Degree holder or above in Accounting, or CPA equivalent qualification\n\u00a0\u00a0\u00a0\u00a0\u00a0\u00a0 4- 6 years internal financial management experience in banks or financial institutions.\u00a0 More experienced candidate will be considered the position of Finance Manager\n\u00a0\u00a0\u00a0\u00a0\u00a0\u00a0 Has good knowledge in lending/ borrowing, options, trading, investment products/ funds\n\u00a0\u00a0\u00a0\u00a0\u00a0\u00a0 Experience in configuring financial system, dealing with external services providers and banks is a plus.\u00a0\n\u00a0\u00a0\u00a0\u00a0\u00a0\u00a0 Energetic, ready to go, with fire in heart; has interest and passion in cryptos, proactive in style for areas of improvement, has drives to get things done.\n\u00a0\u00a0\u00a0\u00a0\u00a0\u00a0 Be able and be willing to work rather independently.\n\nIn return, we offer:\n\n\u00a0\u00a0\u00a0\u00a0\u00a0\u00a0 Competitive package, nice working environment, new industry with great development, rewarding experience, and wide career growth potential", "employment_types": ["Full Time"], "selling_points": [], "locations": ["Kowloon Bay"], "categories": ["Accounting", "Accountant", "Finance / Accounting Manager", "Financial Analyst"], "post_time": "2022-01-13T06:53:59Z", "salary": {"currency": null, "max": null, "min": null, "period": "monthly", "term": null}, "salary_visible": false, "title_keywords": ["assistant finance manager"], "responsibilities": ["management", "financial system", "operations", "quality", "configuring", "reports", "financial reporting", "finance team", "management reporting", "forecasting"], "requirements": {"degrees": ["degree holder"], "majors": ["accounting"], "languages": [], "language_level": [], "hard_skills": ["plus", "crypto", "investment products", "cpa", "go"], "soft_skills": ["efficient", "proactive", "independently", "passion in", "energetic", "ideal"], "languages_combined": []}, "experience_required": {"duration": ["4- 6 years"], "field": ["management", "financial institutions", "financial"]}}, {"job_id": "100003009051819", "location_code": "hk", "company": "RGF HR Agent Hong Kong Limited", "job_title": "Japanese Speaking Accounting, HR & Admin Manager - Japanese Company (Up to 35K/San Po Kong)", "description": "Responsibilities:\n\nResponsible for assigned internal audit/internal control project within the designated audit portfolio\nPerform compliance duties to monitor business operations in compliance with internal policies and controls\nExecute risk control measures business operation\nPrepare reports and analyses for providing sound financial and business recommendations to support business decisions\nResponsible for internal audit projects and initiatives to achieve the company's KPIs and strategic plan\nEnhance audit proficiencies, and continually improve audit workflows and practices\nAssist in business planning and budgeting\nRequirements:\n\nQualified Accountant with Degree in Accounting/Finance or related discipline\nAt least 5 years of experience in internal audit roles or related positions in a medium to large sized organization\nBig4 or 2nd tier Audit experience is a MUST\nTax Knowledge is advantage\nExperience in risk assessment, internal control, operational audit function is an advantage\nExcellent inter-personal skills, and effective communication abilities in both English and Chinese\nGood computer literacy in using Excel, Access, PowerPoint and Word\n\nInterested parties please send full resume with current and expected salary by clicking the \"APPLY NOW\" button below.\nAll information provided by applicants will be treated in strict confidence and used only for recruitment purposes. Applicants may be considered for other suitable positions by our Company & the subsidiaries over not more than 6 months, after which their personal data will be destroyed.\u00a0", "employment_types": ["Full Time", "Permanent"], "selling_points": ["Japanese Automobile Company/JLPT N2 or above", "10 yrs exp in Accounting/ACCA/HKIAAT Member", "Up to 35K/San Po Kong/ Stable job!"], "locations": ["Wong Tai Sin Area"], "categories": ["Accounting", "Finance / Accounting Manager", "Admin & HR", "Administration / Operation Manager", "HR Director / Manager"], "post_time": "2022-01-17T01:16:48Z", "salary": {"currency": null, "max": null, "min": null, "period": "monthly", "term": null}, "salary_visible": false, "title_keywords": ["admin", "hr", "accounting", "manager"], "responsibilities": ["business operation", "control", "internal audit", "operations", "policies", "compliance", "monitor", "audit", "support business decisions", "budgeting", "planning", "plan", "prepare reports", "kpis", "internal control"], "requirements": {"degrees": ["degree"], "majors": ["finance", "accounting"], "languages": ["english", "chinese"], "language_level": ["excellent"], "hard_skills": ["excel", "word", "powerpoint", "internal control"], "soft_skills": ["communication", "computer literacy", "inter-personal skills"], "languages_combined": [{"language": "english", "language_level": ["excellent"]}, {"language": "chinese", "language_level": ["excellent"]}]}, "experience_required": {"duration": ["at least 5 years"], "field": ["related", "audit experience", "audit"]}}, {"job_id": "100003009050401", "location_code": "hk", "company": "Premier Q Securities Limited", "job_title": "Assistant/Finance & Account Manager", "description": "Responsibilities:\n\nPrepare and review full set of accounts in assigned business unit.\nPrepare monthly financial and management reports/analysis.\nPrepare annual budget, forecast, cash flow management and tax reporting.\u00a0\nLiaise with business unit heads and external parties for annual audits.\nComply with legal and Group compliance requirement.\nAssist management on ad-hoc reports and analysis.\n\n\u00a0Requirements:\n\nDegree\u00a0in Accounting, Finance or related disciplines\nQualified member of HKICPA, ACCA or equivalent is preferred\nAt least 5 - 6 years of accounting experience\nProficient in MS office applications\nGood command of English & Mandarin\nSelf-motivated with a strong sense of responsibilities, team player but able to work\u00a0independently and meet tight reporting deadline\nImmediate available is an advantage\n\nPlease send your application with resume and expected salary to The HR Manager, Dah Chong Hong Ltd, 8/F, DCH Building, 20 Kai Cheung Road, Kowloon Bay or submit your application online by clicking \"Apply Now\" or send your resume to the email address stated in our company description.\n\nInformation provided will be for the purpose of selection within the company and only shortlisted candidates will be contacted. All applications will be retained for a maximum period of 6 months.", "employment_types": ["Full Time", "Permanent"], "selling_points": [], "locations": ["Wan Chai"], "categories": ["Accounting", "Accountant", "Finance / Accounting Manager", "Taxation"], "post_time": "2022-01-14T10:19:58Z", "salary": {"currency": null, "max": null, "min": null, "period": "monthly", "term": null}, "salary_visible": false, "title_keywords": ["account manager", "assistant"], "responsibilities": ["tax", "reporting", "management", "ad-hoc", "analysis", "review", "budget", "full set of accounts", "external parties", "audits", "compliance", "management reports", "cash flow", "reports", "forecast", "liaise with"], "requirements": {"degrees": ["degree"], "majors": ["related disciplines", "finance", "accounting"], "languages": ["english", "mandarin"], "language_level": ["good command"], "hard_skills": ["acca", "ms office", "hkicpa"], "soft_skills": ["self-motivated", "team player", "work independently", "sense of responsibilities"], "languages_combined": [{"language": "english", "language_level": ["good command"]}, {"language": "mandarin", "language_level": ["good command"]}]}, "experience_required": {"duration": ["at least 5 - 6 years"], "field": ["accounting experience"]}}, {"job_id": "100003009043616", "location_code": "hk", "company": "Cosco Shipping Ports Limited", "job_title": "Finance Manager / Assistant Finance Manager", "description": "Our client, a Japanese automobile company is looking for an Accounting, HR & Admin Manager to join their team as follows:\n\nJob Duties:\n\u2022 Handle the full set of accounting\n\u2022 Prepare month-end consolidation\n\u2022 Manage statutory audit, J-SOX, and tax filing\n\u2022 Prepare reports according to the templates provided by the HQ in Japan\n\u2022 Oversee the HR and Admin department\n\u2022 Liaise with the HQ in Japan\n\u2022 Other ad-hoc duties as assigned\n\nRequirement:\n\u2022 Bachelor's degree or higher\n\u2022 At least 10 years of relevant experience\n\u2022 Fluent in Japanese(JLT N2 or higher), English, and Chinese\n\u2022 ACCA/ HKIAAT student member or equivalent\n\u2022 Work experience in a Japanese company is a must\n\nPackage:\n- Discretionary bonus\n- Medical insurance\n\nInterested parties please send us your resume in MS Word/PDF format in English. All information received will be kept in strict confidential and only for recruitment purpose.\n\n", "employment_types": ["Full Time", "Permanent"], "selling_points": ["Five-day Work Week, Double Pay & Performance Bonus", "Medical, Dental & Life Insurance", "Education, Meal & Festive Allowance"], "locations": ["Sheung Wan"], "categories": ["Accounting", "Finance / Accounting Manager", "Financial Analyst", "Banking / Finance", "Corporate Finance"], "post_time": "2022-01-13T00:46:27Z", "salary": {"currency": null, "max": null, "min": null, "period": "monthly", "term": null}, "salary_visible": false, "title_keywords": ["assistant finance manager", "finance manager"], "responsibilities": ["hr", "tax filing", "month-end", "audit", "full set of accounting", "liaise with", "ad-hoc duties", "prepare reports"], "requirements": {"degrees": ["degree", "bachelor"], "majors": [], "languages": ["japanese", "english", "chinese"], "language_level": ["fluent"], "hard_skills": ["acca"], "soft_skills": [], "languages_combined": [{"language": "japanese", "language_level": ["fluent"]}, {"language": "english", "language_level": ["fluent"]}, {"language": "chinese", "language_level": ["fluent"]}]}, "experience_required": {"duration": ["at least 10 years"], "field": ["relevant experience"]}}, {"job_id": "100003009038166", "location_code": "hk", "company": "East Asia Professional Photofinishing Laboratory Ltd", "job_title": "Accounting Manager", "description": "Job Descriptions:\n\nResponsible for full set of account and financial reports inTypes1, 2, 4, 9 regulated activities\nPerform accounting duties such as daily cash flow, client money, segregation, bank reconciliations in compliance with the SFC/AML timely and accurately\nPrepare financial and management reports and regulatory reports in compliance with the SFC\nPerform daily monitoring and reporting of the liquid capital according to the FRR\nLiaise with external auditor and tax advisor for annual audit and tax issues\n\nJob Requirements:\n\n\nBachelor degree or above in account, finance or related disciplines\nHolder of professional qualification of CPA/ACCA\nMinimum 5 years\u2019 experience in securities firms with sound knowledge of SFC regulations and FRR\nWell-versed in Companies Ordinance, familiar with the SFC & HKEX rules and regulations\nFamiliar with Hong Kong accounting and tax regulations\nResponsible, independent, highly self-motivated, and detail minded\n\nGood command in Cantonese, English and Mandarin\n\n\u00a0\nWe offer attractive salary and fringe benefit package to the right candidate. Interested parties please send full resume to us. Personal data provided in your application will be kept in the strictest confidence. It will be used for employment-related purposes.", "employment_types": ["Full Time"], "selling_points": [], "locations": ["Chai Wan"], "categories": ["Accounting", "Finance / Accounting Manager"], "post_time": "2022-01-11T05:44:47Z", "salary": {"currency": null, "max": null, "min": null, "period": "monthly", "term": null}, "salary_visible": false, "title_keywords": ["accounting manager"], "responsibilities": ["tax", "reporting", "financial reports", "aml", "annual audit", "compliance", "bank reconciliations", "cash flow", "management reports", "reports", "liaise with", "accounting duties", "daily monitoring"], "requirements": {"degrees": ["degree or above", "bachelor"], "majors": ["related disciplines", "finance"], "languages": ["cantonese", "english", "mandarin"], "language_level": ["good command"], "hard_skills": ["cpa", "acca", "companies ordinance", "frr"], "soft_skills": ["self-motivated", "independent", "responsible"], "languages_combined": [{"language": "cantonese", "language_level": ["good command"]}, {"language": "english", "language_level": ["good command"]}, {"language": "mandarin", "language_level": ["good command"]}]}, "experience_required": {"duration": ["minimum 5 years"], "field": ["securities firms"]}}, {"job_id": "100003009046924", "location_code": "hk", "company": "St. James' Settlement", "job_title": "Assistant Accounting Manager (Contract)\u3008Ref: AC/05922\u3009", "description": "Responsibilities:\n\n\nInvolve in a wide range of international corporate finance transactions (including M&A, restructuring);\nFully participate in the financial and tax due diligence and the execution processes;\nPlay a key role in the investment project team;\nAssist in preparation of accounting schedules for year-end audit;\nPerform analytical and business analysis for management;\nHandle ad hoc financial reports and projects\n\n\u00a0Requirements:\n\nBachelor Degree in Accounting / Finance or an internationally recognized accounting qualification;\nMinimum 4 years\u2019 relevant experience, including 3 years experience gained in Big 4 / sizable listed companies;\nSolid corporate finance experience in M&A transactions would be advantageous;\nWorking knowledge in the HK Listing Rules is required;\nExcellent understanding of the PRC accounting rules and regulation;\nStrong analytical, reporting and problem solving skills;\nResult oriented and able to work under tight deadlines;\nSelf-motivated, responsible, a good team player and willing to travel;\nProficiency in computer application software;\nFluent communication skills in English, Cantonese and Mandarin;\nImmediate available is preferred.\n\n*Candidates with less experience will be considered as Assistant Finance Manager.\n\nWe offer 5-day work, attractive salary package and other fringe benefits to the right candidate.\u00a0\n\nInterested parties please send your detailed resume in MS Word format with your present and expected salary to us.\u00a0\n\nAll information received will be kept in strict confidence and will be treated only for employment related purpose.", "employment_types": ["Full Time", "Contract"], "selling_points": ["A university degree in Accounting / Finance", "With 6 years of relevant experience", "Professional accounting qualification ACCA/HKICPA"], "locations": ["Wan Chai"], "categories": ["Accounting", "Finance / Accounting Manager", "Public / Civil", "Social Services - Community / Non-profit Organization"], "post_time": "2022-01-14T01:45:06Z", "salary": {"currency": null, "max": null, "min": null, "period": "monthly", "term": null}, "salary_visible": false, "title_keywords": ["assistant accounting manager"], "responsibilities": ["tax", "due diligence", "year-end", "management", "ad hoc", "financial reports", "schedules", "audit", "transactions", "business analysis"], "requirements": {"degrees": ["degree", "bachelor"], "majors": ["finance", "accounting"], "languages": ["cantonese", "english", "mandarin"], "language_level": ["fluent"], "hard_skills": ["problem solving skills", "prc accounting"], "soft_skills": ["communication skills", "good team player", "self-motivated", "responsible", "result oriented", "problem solving skills"], "languages_combined": [{"language": "cantonese", "language_level": ["fluent"]}, {"language": "english", "language_level": ["fluent"]}, {"language": "mandarin", "language_level": ["fluent"]}]}, "experience_required": {"duration": ["minimum 4 years", "3 years"], "field": ["finance manager", "relevant experience", "big 4", "corporate finance"]}}, {"job_id": "100003009041068", "location_code": "hk", "company": "Litu Holdings Limited", "job_title": "Assistant Finance Manager", "description": "Responsibilities\n\nl\u00a0 Handle full set of accounts such as cash flow statements, P & L, balance sheet\n\nl\u00a0 Prepare moth-end closing journals, reconciliations, and schedules\n\nl\u00a0 Key responsible to liaise with internal and external auditors\n\nl\u00a0 Ensure proper implementation of internal controls\n\nl\u00a0 Assist in other internal control issues\n\nl\u00a0 Perform ad hoc assignments as require\n\nRequirements\n\nl\u00a0 High Diploma or Degree in Accountancy\n\nl\u00a0 At least 5 years relevant work experience\n\nl\u00a0 Experience in Manufacturing accounting is highly preferred\n\nl\u00a0 Experience in ERP system is an advantage\n\nl\u00a0 Self-motivated, independent and with strong sense of responsibility\n\nl\u00a0 Good command in Mandarin, Cantonese, and English\n\nl\u00a0 Immediately available is highly preferred", "employment_types": ["Full Time"], "selling_points": ["Minimum 3 years Experience", "Accounting Degree holder", "HK Listed Company"], "locations": ["Fanling"], "categories": ["Accounting", "Accountant", "Accounting Clerk / Supervisor", "Finance / Accounting Manager"], "post_time": "2022-01-12T04:37:13Z", "salary": {"currency": "HKD", "max": 34999, "min": 25000, "period": "monthly", "term": null}, "salary_visible": true, "title_keywords": ["assistant finance manager"], "responsibilities": ["schedules", "full set of accounts", "implementation", "external auditors", "reconciliations", "cash flow", "ad hoc assignments", "liaise with", "internal control", "balance sheet"], "requirements": {"degrees": ["high diploma", "degree"], "majors": ["accountancy"], "languages": ["cantonese", "english", "mandarin"], "language_level": ["good command"], "hard_skills": ["erp system"], "soft_skills": ["self-motivated", "independent", "sense of responsibility"], "languages_combined": [{"language": "cantonese", "language_level": ["good command"]}, {"language": "english", "language_level": ["good command"]}, {"language": "mandarin", "language_level": ["good command"]}]}, "experience_required": {"duration": ["at least 5 years"], "field": ["erp system", "manufacturing", "accounting"]}}, {"job_id": "100003009038224", "location_code": "hk", "company": "Sejong Consulting Limited", "job_title": "Manager / Assistant Manager - Client Accounting", "description": "Requirement:\n\nA university degree in Accounting / Finance or related discipline\nWith 6 years of relevant experience, of which 3 years will be in a supervisory role\nProficiency in Microsoft Office, experience in Crystal report applications is preferred\nProfessional accounting qualification ACCA/HKICPA or equivalent\nStrong communication, interpersonal, analytical and problem solving skills\nProven experience in IT system development and/or internal audit is an advantage\nJob Duties:\n\nProvide support and advice on accounting related matters to service units to meet the deadlines of month end and year end closings and to meet the requirements from funders\nReview journals and reports submitted by service units\nReview accounting-related operations in service units\nAssist in annual budget exercise, year-end closing and audit for the agency\nAssist in system development\nProvide training to service units\nProvide effective and accurate reports to seniors on all finance relevant issues\nAd-hoc analyses and tasks as required\n\nInterested persons please apply with full resume via \u201cAPPLY NOW\u201d on or before 21/01/2022.", "employment_types": ["Full Time"], "selling_points": [], "locations": ["Tsim Sha Tsui"], "categories": ["Accounting", "Accountant", "Finance / Accounting Manager", "Others"], "post_time": "2022-01-12T23:26:11Z", "salary": {"currency": null, "max": null, "min": null, "period": "monthly", "term": null}, "salary_visible": false, "title_keywords": ["assistant manager", "manager", "client accounting"], "responsibilities": ["provide training", "ad-hoc", "provide support", "operations", "review", "budget", "audit", "reports", "year-end closing"], "requirements": {"degrees": ["university degree"], "majors": ["finance", "accounting"], "languages": [], "language_level": [], "hard_skills": ["hkicpa", "acca", "problem solving skills", "microsoft office"], "soft_skills": ["communication", "analytical and problem solving skills", "interpersonal"], "languages_combined": []}, "experience_required": {"duration": ["6 years", "3 years"], "field": ["supervisory", "it system development", "relevant experience", "audit"]}}, {"job_id": "100003009036764", "location_code": "hk", "company": "Flexxon Global Limited", "job_title": "Finance Manager", "description": "The candidate will be in charge of completing various assignments either independently or as a team while reporting to the director in areas such as audit, accountancy and tax compliance including but not limited to the preparation of financial statements and tax computation, filing of profits and personal tax returns, and responding to IRD enquiries.\n\nRequirements\n\nDegree/diploma in Accounting or related discipline;\nStudent member/member of HKICPA or other recognisable professional accounting bodies;\nAbility to work independently and deal with competing deadlines;\nExcellent analytical, interpersonal and communication skills;\nAt least 5 years working experience;\nExperience in dealing with foreign clients is an advantage;\nKnowledge of accounting software (especially MYOB and Xero) will be advantageous;\nProficient in MS Word, Excel and Chinese Word Processing;\nGood command in written and spoken English and Chinese. Fluency in Putonghua is a plus.\n\nWe invite high-caliber candidates who are looking for advancement in his/her professional career to apply. We offer the successful candidate an attractive remuneration package including annual leave, examination leave, study leave and double pay. Our company works 5 days per week.\n\nPlease apply by sending e-mail to recruit@ sejong.com.hk.\nPlease contact 2970 7500 for inquiries.\n\nPersonal data collected will be used for recruitment purpose only.", "employment_types": ["Full Time", "Permanent"], "selling_points": ["Passionate , Energetic and Innovative work culture", "Flexible Work Arrangement, Performance Bonus", "Outstanding Career Growth and Development Opportun"], "locations": ["Shatin Area"], "categories": ["Accounting", "Finance / Accounting Manager"], "post_time": "2022-01-10T13:43:01Z", "salary": {"currency": null, "max": null, "min": null, "period": "monthly", "term": null}, "salary_visible": false, "title_keywords": ["finance manager"], "responsibilities": ["tax", "reporting", "tax computation", "software", "compliance", "audit", "financial statements", "communication"], "requirements": {"degrees": ["diploma", "degree"], "majors": ["accounting"], "languages": ["putonghua", "english", "chinese"], "language_level": ["fluency", "good command", "proficient"], "hard_skills": ["excel", "plus", "chinese word processing", "accounting software", "xero", "hkicpa", "myob", "ms word"], "soft_skills": ["communication skills", "work independently", "independently", "interpersonal"], "languages_combined": [{"language": "putonghua", "language_level": ["fluency"]}, {"language": "english", "language_level": ["good command"]}, {"language": "chinese", "language_level": ["good command", "proficient"]}]}, "experience_required": {"duration": ["at least 5 years"], "field": []}}, {"job_id": "100003009042741", "location_code": "hk", "company": "Sun Logistics Holdings Limited", "job_title": "Project Manager/ Assistant Finance Manager", "description": "We are hiring a Finance manager (system implementation and projects), a six-month contract role (renewable), to be based in Hong Kong to look after the system implementation and take up special projects for the region.\n\nThe Finance Manager will report to the Finance Director, APAC.\n\nResponsibilities\n\nBe the project manager to support SAP Hana s4 system implementation and other ad-hoc projects for the region.\nSupport daily operations and month end closing, where necessary\nProvide business finance support, including financial reports/analysis & forecast.\nHave chance to work with affiliates and shared services team\n\nEducation and Experience\n\nDegree in Accounting or related disciplines\nSolid experience on Finance System Implementation for SAP\nExperience in financial planning & reporting experience gained from MNC\n\nKey Competencies\n\nProficiency in SAP & ERP implementation experience is a MUST\nKnowledge in Hyperion Essbase\nStrong in Excel and PowerPoint\nMature and work independently and good project management skills\nResponsible, committed, detail-oriented, proactive and customer-oriented\nGood command of both written and spoken English and Chinese and Mandarin\nStrong communication and interpersonal skills", "employment_types": ["Full Time", "Permanent"], "selling_points": [], "locations": ["Admiralty"], "categories": ["Accounting", "Finance / Accounting Manager"], "post_time": "2022-01-12T08:37:18Z", "salary": {"currency": null, "max": null, "min": null, "period": "monthly", "term": null}, "salary_visible": false, "title_keywords": ["project manager", "assistant finance manager"], "responsibilities": ["reporting", "month end closing", "financial reports", "analysis", "implementation", "communication", "project management", "daily operations", "planning", "forecast", "ad-hoc projects", "report"], "requirements": {"degrees": ["degree"], "majors": ["related disciplines", "accounting"], "languages": ["english", "chinese", "mandarin"], "language_level": ["good command"], "hard_skills": ["excel", "sap", "analysis", "erp", "powerpoint", "project management", "system implementation"], "soft_skills": ["work independently", "responsible", "project management skills", "mature", "detail-oriented", "committed", "customer-oriented", "communication and interpersonal skills", "proactive"], "languages_combined": [{"language": "english", "language_level": ["good command"]}, {"language": "chinese", "language_level": ["good command"]}, {"language": "mandarin", "language_level": ["good command"]}]}, "experience_required": {"duration": [], "field": ["finance", "planning", "financial", "education"]}}, {"job_id": "100003009044477", "location_code": "hk", "company": "Trend Expo Limited", "job_title": "Accounting Manager / Finance Manager (F&B)", "description": "About Us\n\nWe are one of the F&B Business in Hong Kong. We are now looking for\u00a0Accounting Manager / Finance Manager\u00a0\n\nJob Description\n\nLeading the finance team and be responsible for the full spectrum of finance and accounting function.\n\n\u2022 Preparation of reports daily, weekly and monthly which include but are not limited to sales analysis, food and beverages cost reports, monthly management accounts.\n\n\u2022 Prepare ad-hoc report is required\n\n\u2022 Prepare weekly and monthly cash flow forecast\n\n\u2022 Preparation of annual budgets and monthly target per business unit\n\n\u2022 Preparation and Submission of a monthly report summarizing the performance of the businesses under your control, which includes a P&L, variance analysis against budget and Target, balance sheet and cash flow, focus areas for the next month, control weaknesses and corrective actions.\n\n\u2022Preparation of annual budgets per business unit with quarterly updated rolling forecasts.\n\n\u2022 Handling external audit and liaison with external auditors\n\nRequirements:\n\n- Degree in Accounting / Finance or equivalent\n\n- Experience in Food & Beverage outlets is highly recommended\n\n- 5 - 8 years relevant experience\n\n- Detailed oriented and strong analytical and communication skills\n\n- immediately available is preferred", "employment_types": ["Full Time", "Permanent"], "selling_points": [], "locations": ["Wan Chai"], "categories": ["Accounting", "Finance / Accounting Manager", "Financial Controller"], "post_time": "2022-01-13T04:15:30Z", "salary": {"currency": null, "max": null, "min": null, "period": "monthly", "term": null}, "salary_visible": false, "title_keywords": ["accounting manager", "finance manager"], "responsibilities": ["ad-hoc", "budgets", "cost", "management", "control", "balance sheet", "analysis", "budget", "audit", "p&l", "external auditors", "variance analysis", "monthly cash flow forecast", "cash flow", "reports", "finance team", "monthly report", "report"], "requirements": {"degrees": ["degree"], "majors": ["finance", "accounting"], "languages": [], "language_level": [], "hard_skills": [], "soft_skills": ["communication skills", "detailed oriented"], "languages_combined": []}, "experience_required": {"duration": ["5 - 8 years"], "field": ["food", "relevant experience"]}}, {"job_id": "100003009041938", "location_code": "hk", "company": "Moncler Asia Pacific Limited", "job_title": "Finance Manager, Rest of APAC", "description": "Aim\n\nReport to the Finance Director of APAC and General Manager of Rest of APAC, the key objectives of this role is to supervise the finance and accounting functions for Rest of APAC companies (Hong Kong, Macau, Taiwan, Singapore, Australia and New Zealand)\n\nResponsibilities\n\n\u00a0Supervise staff to manage work activities including daily accounting operations (AP, AR & GL), month-end closing and financial reporting, tax computation and assist in tax planning, audit preparation\n\u00a0Supervising and performing financial analyses/reports with interpretation and timely recommendation on further course of action\n\u00a0Improve and streamline policies, procedures on an on-going basis and ensure proper documentation and implementation to cope with the objectives of the Company\n\u00a0Liaison with professional parties including bankers, auditors, accounting firms, financial advisors and insurance broker\n\u00a0Monitor and analyze department work to develop efficient and cost-effective procedures\n\u00a0Work with various internal parties to facilitates process efficiency and effectiveness\n\u00a0Lead and develop existing and newly hired subordinates\n\u00a0Provides supports to operation and business related to financial aspects\n\u00a0Participates in ad hoc and special projects if required\n\nSkills & knowledge\n\n\u00a0University graduate in Accounting / Finance / Economics with minimum 10 years of progressive accounting experience gained from Retail industries\n\u00a0Certified member of HKICPA / ACCA or equivalent qualification\n\u00a0Excellent relationship building and senior stakeholder management skill\n\u00a0Self-starter, ability to identify issues, hold self and other accountable to achieve goals and resolve problems\n\u00a0Strong analytical and problem-solving skills, with attention to detail and able to work under pressure\n\u00a0Advanced user of SAP\nGood command of written and spoken in English, Cantonese and Mandarin", "employment_types": ["Full Time", "Permanent"], "selling_points": ["Finance", "Accounting", "Luxury"], "locations": ["Central"], "categories": ["Accounting", "Finance / Accounting Manager"], "post_time": "2022-01-12T04:43:21Z", "salary": {"currency": null, "max": null, "min": null, "period": "monthly", "term": null}, "salary_visible": false, "title_keywords": ["finance manager"], "responsibilities": ["supervising", "audit", "work under pressure", "ap", "ad hoc", "monitor", "daily accounting operations", "implementation", "develop", "reports", "report", "cost", "management", "ar", "tax computation", "procedures", "documentation", "tax", "policies", "month-end closing", "financial reporting", "insurance", "internal parties", "planning"], "requirements": {"degrees": ["university graduate"], "majors": ["finance", "accounting", "economics"], "languages": ["cantonese", "english", "mandarin"], "language_level": ["good command"], "hard_skills": ["ap", "acca", "ar", "sap", "documentation", "problem-solving skills", "hkicpa"], "soft_skills": ["efficient", "advanced", "timely", "accountable", "attention to detail", "progressive", "problem-solving skills", "work under pressure"], "languages_combined": [{"language": "cantonese", "language_level": ["good command"]}, {"language": "english", "language_level": ["good command"]}, {"language": "mandarin", "language_level": ["good command"]}]}, "experience_required": {"duration": ["minimum 10 years"], "field": ["finance", "accounting experience", "accounting", "retail"]}}, {"job_id": "100003009042310", "location_code": "hk", "company": "FANCL (Fantastic Natural Cosmetics Limited)", "job_title": "Assistant Accounting Manager", "description": "Our Finance Department has a team of professionals that strive\u00a0to create value\u00a0and automation within our company. \u00a0We encourage the use of \u201cbest practice\u201d at work, strike a balance between \u201ccontrol\u201d and \u201cefficiency\u201d.\n\nReporting to Senior Finance Manager, the incumbent will oversee and manage the full spectrum of finance operations for FANCL China market and our F&B business in Hong Kong.\u00a0\n\nResponsibilities:\n\nEnsure accuracy of monthly closing within a tight deadline\nPrepare monthly management report and business analysis\nEnsure all financial operations and procedures are complied with audit and tax requirements and internal corporate governance guidelines\nMaintain good internal control on AR, AP, fixed assets and inventory\nPrepare yearly budget and forecast, and update cash flow forecast from time to time\nHandle different treasury functions e.g. cash management, fixed deposits, loan and forex transactions etc.\nAssist in process improvement and system automation projects\nRequirements:\n\nUniversity graduate in Accounting, Finance or any related discipline\nHKICPA or equivalent qualification would be definitely an advantage\nAt least 5 years\u2019 relevant accounting experience preferably from F&B, Hospitality or Retail industry\nPreparation of consolidated financial statements in accordance with HKFRS and good knowledge of HK and China\u00a0tax regulations\nGood internal control mind set and good corporate governance practice\nDetail-minded, determined, strong problem solving skills with good business acumen\nGood command of both written and spoken English and Chinese (Cantonese and Mandarin)\nApplicant with more experience will be considered for the position of Deputy Accounting Manager.\n\nWhat We Offer\nA 5-day work week\nCompetitive Salary Package\nGuaranteed 13 Months\u2019 Pay & Year End Discretionary Bonus\nOn the Job Training & Training Sponsorship\nFull Paid Sick Leave, Annual Leave, Maternity Leave, Paternity Leave\nStaff Benefits e.g. Staff Purchase Discounts, Free Product, Sponsor of Gym Membership, Comprehensive Medical Benefits Coverage, etc.\nStaff Activities & Events e.g. Mid-Autumn Festival Gathering, New Joiner Gathering, Annual Dinner, Christmas Parties, Health Talks, Sports Activities, Interests Classes etc.\u00a0\u00a0\nInterested applicants please click 'Apply Now'\u00a0and send your r\u00e9sum\u00e9 with expected salary to us.\u00a0For internal reference purpose, please also state your public examination results on your attached r\u00e9sum\u00e9.\nPersonal data collected will be used for recruitment purposes only.", "employment_types": ["Full Time", "Permanent"], "selling_points": ["Monthly Closing, Management Report & Analysis", "Internal Control, Audit, Tax Planning, Budget", "5-day work,13 mth pay and year end bonus"], "locations": ["Tsim Sha Tsui"], "categories": ["Accounting", "Accountant", "Finance / Accounting Manager", "Financial Analyst"], "post_time": "2022-01-12T06:57:14Z", "salary": {"currency": null, "max": null, "min": null, "period": "monthly", "term": null}, "salary_visible": false, "title_keywords": ["assistant accounting manager"], "responsibilities": ["tax", "ap", "management", "ar", "guidelines", "operations", "inventory", "monthly management report", "procedures", "audit", "budget", "transactions", "cash flow", "maintain", "forecast", "business analysis", "internal control"], "requirements": {"degrees": ["university graduate"], "majors": ["finance", "accounting"], "languages": ["cantonese", "english", "chinese", "mandarin"], "language_level": ["good command"], "hard_skills": ["hkfrs", "acumen", "hkicpa", "problem solving skills", "internal control"], "soft_skills": ["detail-minded", "business acumen", "problem solving skills", "determined"], "languages_combined": [{"language": "cantonese", "language_level": ["good command"]}, {"language": "english", "language_level": ["good command"]}, {"language": "chinese", "language_level": ["good command"]}, {"language": "mandarin", "language_level": ["good command"]}]}, "experience_required": {"duration": ["at least 5 years"], "field": ["retail industry", "accounting experience", "f&b", "accounting"]}}, {"job_id": "100003009046290", "location_code": "hk", "company": "Prenetics Limited", "job_title": "Group Finance Manager", "description": "Founded in 2014, Prenetics is a major global diagnostics and genetic testing company with the mission to bring health closer to millions of people globally and decentralize healthcare by making the three pillars \u2014 Prevention, Diagnostics and Personalized Care \u2014 comprehensive and accessible to anyone, at anytime and anywhere. Prenetics is led by visionary entrepreneur, Danny Yeung, with a team of over 800 employees and operations across 9 locations, including United Kingdom, Hong Kong, India, South Africa, and Southeast Asia. Prenetics develops consumer genetic testing and early colorectal cancer screening; provides COVID-19 testing, rapid point of care and at-home diagnostic testing and medical genetic testing.\nMost recently, Prenetics made international headlines to become the first Unicorn in Hong Kong to publicly list on the Nasdaq via merger with 2021 Adrian Cheng's Artisan Acquisition Corp, valuing Prenetics at approximately US $1.7b.\n\nWe are currently seeking an experienced, self-motivated Group Finance Manager\u00a0who will be a key player in supporting Prenetics' group financial reporting and reporting processes and providing analytical support to help drive the Company's continued growth and global expansion.\n\nThis position will be responsible for performing group financial reporting and digital transformation project to support our growth. You will be a well-rounded top performer with the desire to contribute and add innovative ideas to the expanding team.\n\nYou don't mind working hard, are keen to take on responsibilities, and like the fast paced startup environment.\n\nResponsibilities\n\nLocal Reporting\n\n\nReport to the VP of Finance;\nResponsible for the Hong Kong entity\u2019s reporting and group level\u2019s consolidation reporting\nCoordinate with local finance team on solving internal accounting issues, set up Accounting SOP and month end check list\nAct as the key driver to plan the timeline across the group to deliver the financial reports within the reporting deadlines\nDrive the finance team to deliver the monthly financials reporting pack to the senior management to facilitate decision making\nPreparation of financial statements and ensure the reports comply with PCAOB standards and have sound knowledge of Sarbanes\u2013Oxley Act;\nEnsure the system of internal controls is properly maintained and followed;\nAct as the key person for the digital transformation project in the finance department; work closely with IT team for the project development & implementation (i.e. ERP) while provide financial solution to the business for new initiatives, and work closely with cross functional teams\nManage audit and tax matters;\n\nGroup Reporting\u00a0\n\nCollecting, interpreting and reviewing financial information\nHandling intercompany transaction\u2019s reconciliation to ensure the group level correctly eliminate requisite transactions at consolidation level\nHandle complex accounting issue and liaise with both internal parties and external professionals to finalize valuation reports for audit purpose.\nDrafting of annual/interim report, disclosure notes, and work closely with external auditor on external reporting\nAlignment of COA cross all the subsidiaries and management report\u2019s layout\nPreparation of year end reporting template to facilitate & consolidate notes disclosures for year-end reporting compliance\nReview procedures to safeguard company assets and ensure proper authorization for business activities\nSupport the Group Finance to review management reporting from subsidiary levels and facilitate in special projects, and work for process improvements;\n\nSystem Implementation\n\nAssist in the implementation and monitor activities of financial system projects\nParticipate in the group\u2019s system implementation project and coordinate system changes.\nPrepare project documentation including business requirements, business flow diagram and user manuals\nAssist in provide technical support and training to users of financial systems in subsidiaries level\n\nRequirement\n\n\n\nBachelor\u2019s degree in Accounting and /or Finance;\nProfessional accounting qualification (HKICPA or CPA or equivalent)\nMinimum 5 years of relevant experience in financial and managerial reporting, in which 2 years at managerial level, experience in listed company reporting is highly preferred\nComprehensive knowledge of accounting standards and other regulatory requirements\nStrong technical knowledge in international accounting standards and taxation regulations, good working knowledge on consolidation accounting, financial control management and planning\nIndependent with strong analytical skills and problems solving abilities; hands-on experience on SAP & NetSuite & Oracle related\nPossess a team player with good interpersonal skill\nExcellent time management skills and ability to multi-task and prioritize work in order to meet tight deadlines\nAbility to set a high bar for yourself and your team\u2019s skill sets\nBelieve in honest and trustworthy behaviors\n\nOur DNA is\u00a0P-R-E-N-E-T-I-C-S.\u00a0See what each word of our company name means:\n\nPassion\n\nYou love what you do and accomplish amazing result\nYou spread positivity, bring enthusiasm to work and inspire team members\nYou drive team toward specific goals, even when they seem unlikely or difficult\n\nResilience\n\nYou embrace changes and be able to drive through uncertainty, ambiguity and uncomfortable situations\nYou bounce back quickly from setbacks and challenges\nYou are persistent and determined to achieve the desired outcome\n\nEmpowerment\n\nYou trust others to play their positions well like an elite sports team\nYou foster a strong team spirit while encouraging others to take initiatives and risks\nYou create a space to allow team to grow and hold each other accountable\n\niNtegrity\n\nYou are trustworthy and lead by example\nYou are consistent in your message and action all the times\nYou deliver what you have promised\n\nEpic\n\nYou challenge your own comfort zone and always outperform yourself\nYou make meaningful and amazing impact to the world\nYou dare to take risks and you move fast\n\nTransparency\n\nYou are completely honest and committed to giving candid feedbacks, no matter how challenging it might be\nYou share ideas, knowledge and skills that empower others and create access to information with the wider team\nYou share wins and failures openly\n\nIngenuity\n\nYou make sound judgement and come up with solutions that are creative and smart. Copy when feasible\nYou challenge the status quo and question things that could be done differently for better. Modify the wheel if you can\u2019t change it\nYou think outside of the box and make value-based innovation\n\nCommunications\n\nYou articulate your thoughts and ideas effectively and respectfully\nYou know your audience and talk in a way they want to be told\nYou make sure communications happens, no matter where you are\n\nSelflessness\n\nYou put the needs of others before one's own and find ways in helping other to succeed\nYou focus on team wins than personal wins and share credits\nYou act in the company's best interest\n\nWe are Prenetics, our people make us who we are.", "employment_types": ["Full Time", "Permanent"], "selling_points": ["Sound knowledge of Sarbanes\u2013Oxley Act", "Responsible for entities and group reporting", "CPA with listed company /listco clients experience"], "locations": ["Quarry Bay"], "categories": ["Accounting", "Audit", "Finance / Accounting Manager", "Taxation"], "post_time": "2022-01-13T10:18:26Z", "salary": {"currency": null, "max": null, "min": null, "period": "monthly", "term": null}, "salary_visible": false, "title_keywords": ["finance manager"], "responsibilities": ["audit", "financial statements", "transactions", "plan", "liaise with", "senior management", "tax matters", "project documentation", "compliance", "teams", "implementation", "monitor", "reports", "finance team", "management report", "business activities", "report", "reporting", "valuation", "financial system", "review", "coordinate with", "procedures", "management reporting", "system changes", "year-end", "financial reports", "technical support", "systems", "coordinate", "internal parties"], "requirements": {"degrees": ["degree", "bachelor"], "majors": ["finance", "accounting"], "languages": [], "language_level": [], "hard_skills": ["no", "sap", "word", "analytical skills", "cpa", "hkicpa", "c", "make", "r", "focus", "oracle"], "soft_skills": ["meet tight deadlines", "team spirit", "trustworthy", "persistent", "comprehensive", "articulate", "team player", "focus", "independent", "determined", "integrity", "committed", "honest", "creative", "prioritize", "analytical skills", "interpersonal skill", "multi-task", "time management skills", "accountable", "hands-on"], "languages_combined": []}, "experience_required": {"duration": ["2 years", "minimum 5 years"], "field": ["related", "managerial", "relevant experience", "financial"]}}, {"job_id": "100003009043838", "location_code": "hk", "company": "", "job_title": "Assistant Accounting Manager", "description": "Responsibilities:\n\n- Responsible for financial reporting on a regular or ad-hoc basis\n- Advise the senior management from time to time on any internal control measures\n- Cash management to ensure a good liquidity while minimizing the finance expenses\n- Work closely with the senior management to develop business strategies in order to contribute to the rapid growth of the Group\n- Assist in dealing with the external auditor and other professional parties\n- Participate in ad hoc assignments or other projects\n\nKnowledge and Skill Requirements:\n\n- University graduate with degree major in Accounting\n- At least 8 years of financial and accounting experience, exposure in manufacturing environment is an advantage\n- Hands-on experience in profit analysis, inventory controls and internal audit\n- Able to work independently with good self-initiative\n- Solid knowledge in PRC accounting, tax, custom practice and regulations\n- Solid experience in daily operation of FLEX accounting system is an advantage\n- Fluency in Mandarin and English is necessary\n- Thorough attention to details\n- Travel to Shenzhen, Huizhou and Indonesia is required\n\nInterested candidates, please contact us at 28595011 for company details before applying.\n\u00a0\nPersonal data collected will be used for recruitment purpose only.", "employment_types": ["Full Time", "Permanent"], "selling_points": [], "locations": ["Others"], "categories": ["Accounting", "Finance / Accounting Manager"], "post_time": "2022-01-13T02:08:02Z", "salary": {"currency": null, "max": null, "min": null, "period": "monthly", "term": null}, "salary_visible": false, "title_keywords": ["assistant accounting manager"], "responsibilities": ["ad-hoc", "management", "expenses", "develop", "financial reporting", "ad hoc assignments", "senior management", "internal control"], "requirements": {"degrees": ["university graduate", "degree"], "majors": ["accounting"], "languages": ["english", "mandarin"], "language_level": ["fluency"], "hard_skills": ["analysis", "flex accounting", "prc accounting"], "soft_skills": ["work independently", "hands-on", "self-initiative", "thorough", "attention to details"], "languages_combined": [{"language": "english", "language_level": ["fluency"]}, {"language": "mandarin", "language_level": ["fluency"]}]}, "experience_required": {"duration": ["at least 8 years"], "field": ["manufacturing", "accounting experience", "audit", "operation", "accounting", "financial"]}}, {"job_id": "100003009051519", "location_code": "hk", "company": "Hong Kong Investment Funds Association", "job_title": "Assistant", "description": "Assistant\n\nThe Hong Kong Investment Funds Association (\u201cHKIFA\u201d) is a non-profit-making organization that represents the fund management industry in Hong Kong.\u00a0 www.hkifa.org.hk.\u00a0 We aim to recruit a high caliber candidate who will play a key role in the following areas.\n\nResponsibilities:\n\nThe main responsibilities include, amongst others:\n\nl\u00a0\u00a0Provide support to meetings (including planning, preparing agendas/papers, managing meeting logistics, taking minutes/notes, and following up to implement the decisions reached at meetings);\n\nl\u00a0\u00a0Perform desk-top research related to specific topics, and prepare papers/reports accordingly;\n\nl\u00a0\u00a0Liaise with member firms to solicit and collate inputs to prepare consultation responses and prepare reports/white papers for submission to the authorities/regulators or other stakeholder groups;\n\nl\u00a0\u00a0Assist in website/social media maintenance, and prepare materials for posting; and\n\nl\u00a0\u00a0Assist in administrative/ad hoc tasks as required.\n\nAttributes and qualities:\n\nl\u00a0\u00a0University graduate;\n\nl\u00a0Experience in capital markets and ESG a plus; \u00a0\n\nl\u00a0\u00a0Strong writing skills \u2013 both English and Chinese;\n\nl\u00a0\u00a0Proactive, detail-oriented and be able to take on multi-tasks; and\n\nl\u00a0\u00a0Have excellent PC skills.\n\nInterested parties please email to Hong Kong Investment Funds Association", "employment_types": ["Full Time"], "selling_points": ["excellent writing skills - Eng/Chin", "multi-tasks, detail-oriented", "excellent PC skills"], "locations": ["Central"], "categories": ["Accounting", "Accounting Clerk / Supervisor", "Finance / Accounting Manager", "Marketing / Public Relations", "Marketing - Marketing Communication"], "post_time": "2022-01-16T21:50:28Z", "salary": {"currency": null, "max": null, "min": null, "period": "monthly", "term": null}, "salary_visible": false, "title_keywords": ["assistant"], "responsibilities": ["social media", "management", "provide support", "prepare reports", "maintenance", "ad hoc tasks", "website", "logistics", "reports", "liaise with", "planning"], "requirements": {"degrees": ["university graduate"], "majors": [], "languages": ["english", "chinese"], "language_level": [], "hard_skills": ["plus", "pc skills", "maintenance", "writing skills"], "soft_skills": ["multi-tasks", "proactive", "writing skills", "detail-oriented"], "languages_combined": [{"language": "english", "language_level": []}, {"language": "chinese", "language_level": []}]}, "experience_required": {"duration": [], "field": ["capital markets"]}}, {"job_id": "100003009054510", "location_code": "hk", "company": "PERSOLKELLY Hong Kong Limited", "job_title": "Senior Fund Accounting Manager (up to 60k p/m + bonus)", "description": "Snapshot\n\nAn exciting opportunity to join a sizeable MPF Group as a Senior Fund Accounting Manager, to be responsible for evaluating NAV, fund administration work while leading the team.\n\nCompany Profile\n\nOur client, a sizeable MPF Group, is looking for a Senior Fund Accounting Manager to join the team\n\nExciting new role for you\n\nResponsible for computing NAV daily and related fund accounting duties\nMonitor and supervise the preparation of valuation reports\nEnsure operation and workflow are comply with both internal and external regulations\nEngage in UAT testing\n\nRequirements\n\nDegree holder in Business, Accounting, Finance or related discipline\nAt least 8 years in fund administration, less experienced candidate will be considered as Manager\nTeam player with experience in management\nGood command of English and Chinese\n\nRewards\n\nSizeable platform with stable career growth and attractive remuneration package", "employment_types": ["Full Time", "Permanent"], "selling_points": ["Banking MPF Group, Manager - Senior Manager wanted", "Fund Accounting and Administration", "Team management experience preferred"], "locations": ["Central & Western Area"], "categories": ["Accounting", "Finance / Accounting Manager", "Others", "Banking / Finance", "Fund Management"], "post_time": "2022-01-17T09:49:32Z", "salary": {"currency": null, "max": null, "min": null, "period": "monthly", "term": null}, "salary_visible": false, "title_keywords": ["accounting manager"], "responsibilities": ["regulations", "valuation", "management", "mpf", "monitor", "uat testing", "reports", "accounting duties", "administration"], "requirements": {"degrees": ["degree holder"], "majors": ["finance", "business", "accounting"], "languages": ["english", "chinese"], "language_level": ["good command"], "hard_skills": [], "soft_skills": ["team player", "stable", "responsible"], "languages_combined": [{"language": "english", "language_level": ["good command"]}, {"language": "chinese", "language_level": ["good command"]}]}, "experience_required": {"duration": [], "field": ["management", "team"]}}, {"job_id": "100003009047218", "location_code": "hk", "company": "Seamatch Asia Limited", "job_title": "Accounting Manager (Retail)", "description": "Responsibilities\n\nResponsible for finance and accounting function\nPrepare full set of monthly management accounts and month-end closing independently\nPrepare group consolidation and financial statement\nManage budget and monitor the group\u2019s cash flow\nProvide assistance and professional advice to senior management of the Company on accounting and financial matters\nCooperate with internal and external audit to complete annual audit reporting\nFollow up on the implementation progress of audit recommendations\n\u00a0Annual tax filing and external reporting requirement\nRequirements\n\nBachelor\u2019s degree holder in Accounting, Finance or Business\nQualified member of HKICPA/ACCA\u00a0\nAt least 8+ years of relevant work experience,\u00a0PRC / audit experience is preferred\nStrong interpersonal and communication skills\nProficient in MS Excel, MS Word & Chinese Word Processing", "employment_types": ["Full Time", "Permanent"], "selling_points": ["8+ years exp in finance and accounting function", "HKICPA/ACCA member with PRC/Audit experience", "Strong interpersonal and communication skills"], "locations": ["Cheung Sha Wan"], "categories": ["Accounting", "Accountant", "Audit", "Finance / Accounting Manager"], "post_time": "2022-01-14T02:37:54Z", "salary": {"currency": null, "max": null, "min": null, "period": "monthly", "term": null}, "salary_visible": false, "title_keywords": ["accounting manager"], "responsibilities": ["reporting", "management", "complete annual audit", "budget", "monitor", "audit", "implementation", "tax filing", "cash flow", "month-end closing", "financial statement", "senior management", "provide assistance", "cooperate with"], "requirements": {"degrees": ["bachelor", "degree holder"], "majors": ["business", "finance", "accounting"], "languages": ["chinese"], "language_level": ["proficient"], "hard_skills": ["acca", "chinese word processing", "hkicpa", "ms excel", "ms word"], "soft_skills": ["communication skills", "interpersonal"], "languages_combined": [{"language": "chinese", "language_level": ["proficient"]}]}, "experience_required": {"duration": ["at least 8+ years"], "field": ["audit experience"]}}, {"job_id": "100003009041826", "location_code": "hk", "company": "", "job_title": "Financial Manager (Catering industry)", "description": "Responsibilities:\n\nPrepare month-end closing, financial reporting, and consolidation\nDeliver management Profit and Loss accounts at company consolidation, brand and store levels on regular basis with variance analysis and commentaries\nSupport in building a monthly forecast, annual budget and long-range plan\nResponsible for store sales incentive targets settings, distribution and incentive achievement reporting\nParticipate in the financial aspect of store development such as feasibility studies and scenario analysis of capital investments and provide ROI performance appraisal of investments\nDevelop analytical and forecast model to support store and brand performance measurement and review\nDeliver weekly sales reports with sound commentaries\nAnalyse store productivity, costing and profitability analysis of various business models and brands\nSupport preparation of the financial presentation in PowerPoint\nProvide ad hoc operational financial support and reporting, and project management\nRequirements:\n\nDegree in Finance, Accounting, Economics, Statistics or Actuarial, with HKICPA, ACCA or equivalent professional accountancy qualifications\nOver 8 years experience in\u00a0handling massive, complex, and detailed financial data analysis in a well-organized and accurate manner\nProven abilities in developing robust analytical models and planning models\nAbility to work cross-functionally and engage business partnership\nStrong communication and presentation skills, flexible and confidence in a fast-paced environment\nFamiliar with EPR systems, such as Kingdee, is an advantage\nProficiency in financial and business performance analysis especially in Food & Beverage, Retail & FMCG industry is a MUST\nImmediately available is preferred\n\nBenefits:\n\nCompetitive salary package\nVarious caring leave types\nGreat learning and career development platform\nExcellent working environment\n\nInterested parties please send email with current and expected package, as well as date of availability to us for selection. All information collected would be used for recruitment purpose only. Process may take 2 to 3 weeks; candidates would not be considered, should there be no contact within 6 weeks.\nInterested candidates, please contact us at 35860105 for company details before applying.", "employment_types": ["Full Time", "Permanent"], "selling_points": ["Financial Manager in Catering industry", "Strong presentation, analytical skill; fast-paced", "Attractive Package"], "locations": ["Kowloon Bay"], "categories": ["Accounting", "Finance / Accounting Manager"], "post_time": "2022-01-12T06:03:13Z", "salary": {"currency": null, "max": null, "min": null, "period": "monthly", "term": null}, "salary_visible": false, "title_keywords": ["financial manager"], "responsibilities": ["reporting", "management", "ad hoc", "sales reports", "analysis", "budget", "measurement", "review", "develop", "variance analysis", "project management", "month-end closing", "financial reporting", "forecast", "plan", "analyse"], "requirements": {"degrees": ["degree"], "majors": ["finance", "economics", "statistics", "accountancy", "accounting"], "languages": [], "language_level": [], "hard_skills": ["acca", "analysis", "fmcg industry", "hkicpa"], "soft_skills": ["flexible", "confidence", "fast-paced environment", "well-organized", "robust", "communication", "presentation skills", "accurate", "detailed"], "languages_combined": []}, "experience_required": {"duration": ["8 years"], "field": ["data analysis", "financial"]}}, {"job_id": "100003009042909", "location_code": "hk", "company": "Tristate Holdings Limited", "job_title": "Assistant Finance Manager", "description": "Job Responsibilities :\u00a0\n\n\nWork in our accounting team in Group Finance to provide professional accounting services to different business units and to ensure proper accounting control in place\nReview and analyse the monthly financial and management accounts of the Group\u2019s subsidiaries\nPrepare month-end and year-end closing management reports, as well as book consolidation for the Group\nSupport budget and forecast exercise, evaluate business proposal\u00a0\nAble to provide valuable input in terms of accounting impact on assessment of new business\u00a0\nBe responsible for audit and announcements and statutory reports\u00a0 \u00a0 \u00a0\u00a0\nEvaluate business proposal and support on ad hoc assignments\n\nRequirements :\u00a0\n\n\nDegree holder in Accounting, Finance or related disciplines\nCPA and member of major professional accounting bodies\nAt least 3-5 years\u2019 experience in accounting profession\nBig 4 audit training is preferred\nDetail-minded, efficient, motivated by results and able to work independently\nStrong in technical skills on HKFRS and IFRS\nExcellent communication, leadership, problem-solving, and analytical skills\nGood command of written and spoken English and Chinese (Cantonese and Mandarin)\nGood computer skills including Excel and PowerPoint\n\n\nWe offer competitive\u00a0remuneration package includes\u00a05-day work week,\u00a0bank holidays, flexible working hours, meal allowance, medical benefits, annual leave, marriage leave\u00a0to the right candidate.\u00a0 If you are interested, please send in your full resume listing your present, expected salary to Human Resources Department\u00a0:\u00a05/F, 66-72 Lei Muk Road, Kwai Chung, N.T. or by clicking \"Apply Now\"\u00a0\n\n\nFor more company information, please visit our web-site at http://www.tristateww.com\n\n( All applications will be treated in strict confidential and we regret that only shortlisted candidates will be contacted )", "employment_types": ["Full Time", "Permanent"], "selling_points": ["CPA, Big 4 audit background", "Listed co, flexible hour, stable environment", "Strong in HKFRS and IFRS"], "locations": ["Kwai Tsing Area"], "categories": ["Accounting", "Audit", "Finance / Accounting Manager", "Financial Analyst"], "post_time": "2022-01-12T09:13:19Z", "salary": {"currency": null, "max": null, "min": null, "period": "monthly", "term": null}, "salary_visible": false, "title_keywords": ["assistant finance manager"], "responsibilities": ["control", "month-end and year-end closing", "management", "review", "budget", "audit", "evaluate", "management reports", "reports", "ad hoc assignments", "forecast", "analyse"], "requirements": {"degrees": ["degree holder"], "majors": ["related disciplines", "finance", "accounting"], "languages": ["cantonese", "english", "chinese", "mandarin"], "language_level": ["good command"], "hard_skills": ["excel", "ifrs", "hkfrs", "web", "problem-solving", "powerpoint", "analytical skills", "cpa", "computer skills"], "soft_skills": ["detail-minded", "efficient", "motivated by results", "work independently", "flexible", "problem-solving", "analytical skills", "communication", "technical skills", "leadership"], "languages_combined": [{"language": "cantonese", "language_level": ["good command"]}, {"language": "english", "language_level": ["good command"]}, {"language": "chinese", "language_level": ["good command"]}, {"language": "mandarin", "language_level": ["good command"]}]}, "experience_required": {"duration": ["at least 3-5 years"], "field": ["accounting"]}}, {"job_id": "100003009047044", "location_code": "hk", "company": "Kingsway Personnel Ltd", "job_title": "Japanese Speaking Senior Accountant/Accounting Manager ~40K", "description": "Employment Ref.: MA09563\nNature of Business: Well-known Japanese trading company\nWorking Days: 5 Days\nWorking Location: KLN Area\n\nBenefits:\n- Double pay\n- Discretionary Bonus\n- Medical insurance\n- Flexible working hours\n\nResponsibilities:\n- Review, formulate and implement financial and accounting policies, procedures and guidelines\n- Identify areas for continuous improvement to avoid risk and enhance internal control of operational activities and governance\n- Handle tax issue, mainly for in-charging of BEPS, and communicate with related parties for planning and resolving\n- Handle aggregation/ analysis and information sharing of whole entity and HK regional consolidated financial status\n- Conduct regular review of end-to-end processes\n\nRequirements:\n- Degree in Accounting or related discipline\n- Min. 5yrs exp. full set accounting, tax and internal control\n- Good command of Japanese (N3 or above), English and Mandarin\u00a0\n\nInterested in the above vacancy?\u00a0 Send your resume to us NOW!\nOnly short-listed candidates will be notified. Personal data collected will be used for recruitment purpose only", "employment_types": ["Full Time", "Permanent"], "selling_points": ["Min. 5yrs full set acct, tax, internal control", "Good at Japanese, English and Mandarin", "~40K, 13mths and bonus, Flexible working"], "locations": ["Not Specified"], "categories": ["Accounting", "Accountant", "Finance / Accounting Manager", "Taxation"], "post_time": "2022-01-15T19:11:32Z", "salary": {"currency": null, "max": null, "min": null, "period": "monthly", "term": null}, "salary_visible": false, "title_keywords": ["accounting manager", "senior accountant"], "responsibilities": [], "requirements": {"degrees": [], "majors": [], "languages": [], "language_level": [], "hard_skills": [], "soft_skills": [], "languages_combined": []}, "experience_required": {"duration": [], "field": []}}, {"job_id": "100003009036901", "location_code": "hk", "company": "Mindcluster Limited", "job_title": "Senior Accountant", "description": "Want to work in a venture studio with boundless opportunities and future-crafting projects? Join Us!\n\nHere we have a cluster of passionate and goal-oriented talents who strive for the acceleration of economies in the decentralized future.\u00a0With extensive business networks, profound market insights and comprehensive capabilities in Digital Assets, Blockchain, Fintech and AI, we are inviting you to join our ambitious team to embark your bespoke venture journey and make a real impact with your expertise.\n\nWho will love this job? Someone who:\n\nIs interested in the Venture Capital or Venture Studio industry\nIs interested in Financial Planning and Analysis for startups and work with venture team on corporate fundraising\nIs willing to challenge themselves in a fast-paced environment\nHappy to work in a flexible and dynamic team with strong bonding\nIs not afraid of failure, and love to explore different possibilities\nWants to lead finance and accounting team\n\nYour responsibilities\n\nLead and scale our finance team to keep up with our growth including keeping accounts and developing our financial infrastructure\nKnow the day-to-day work of finance and engagement for internal and external teams\nHave general knowledge in tax and payroll including monthly accounts payable and receivable, audit, insurance and equity planning\nGood at managing relationships with clients, vendors, banks, financial institutions and payment processors\nImplementation of high efficiency and accuracy of the monthly, quarterly and annual reporting process via both automation and control\nJob requirements\nA bachelor degree in accounting finance/ economics/ business or other related disciplines\nHave experience in finance functions, and are able to work in a dynamic environment with high growth and high efficiency\nCommercial acumen and the ability to think innovatively and have problem solving skills\nAttention to detail with the ability to work on complex accounting queries\nAbility to understand financial records for external stakeholders\n\nIf you are interested, please apply at\u00a0https://careers.mindcluster.io\u00a0or email us~", "employment_types": ["Full Time"], "selling_points": ["Step ahead and work on future-crafting projects", "Boundless opportunities & Fast-tracked career path", "Grow with us & Embark your bespoke venture journey"], "locations": ["Kwun Tong"], "categories": ["Accounting", "Finance / Accounting Manager"], "post_time": "2022-01-14T10:07:13Z", "salary": {"currency": null, "max": null, "min": null, "period": "monthly", "term": null}, "salary_visible": false, "title_keywords": ["senior accountant"], "responsibilities": ["tax", "control", "infrastructure", "teams", "developing", "audit", "implementation", "annual reporting", "payment", "finance team", "insurance", "payroll", "accounts payable", "planning"], "requirements": {"degrees": ["degree", "bachelor"], "majors": ["finance", "economics", "related disciplines", "business", "accounting"], "languages": [], "language_level": [], "hard_skills": ["problem solving skills", "dynamic", "io", "acumen"], "soft_skills": ["dynamic environment", "attention to detail", "problem solving skills"], "languages_combined": []}, "experience_required": {"duration": [], "field": ["finance"]}}, {"job_id": "100003009042100", "location_code": "hk", "company": "Tricor Services Limited", "job_title": "Accounting Senior Associate / Assistant Manager", "description": "Business Services Division offers tailor-made solutions encompassing financial, accounting, human resource and advisory services to our clients from small and medium-sized enterprises to multinationals, in diverse industry sectors. Partnering with our professionals, what you gain will be the best in the field.\n\nWe are looking for high caliber professionals to join our Business Services Division as \u00a0Senior Associate / Assistant Manager\u00a0to cope with our fast growing practice.\n\nWhat the job role is:\n\n\nResponsible for full sets of accounts and bookkeeping for clients\nPrepare various reports to fulfill clients\u2019 business objective\nProvide monthly payroll service to clients\nAssist in treasury & payment administration\nAssist in setup of accounting system for new clients\nMaintain good relationship with clients\nSatisfy any other specific requirements of clients\n\nWho we are looking for:\n\nDegree holder or above\nRegistered Student or Member of HKICPA or equivalent\nSolid experience in audit and/or accounting;\u00a0relevant experience with\u00a0a professional firm is an asset\nGood interpersonal skills and able to multi-task\nIndependent, self-motivated, proactive\nWell versed in MS applications(PowerPoint, Excel, Word); proficient in various accounting software is an advantage\nGood command of written and spoken English and Chinese; fluency in Mandarin is an advantage\nCandidates will be considered for a position commensurate with experience\n\nWe are an Authorized Employer of the Hong Kong Institute of Certified Public Accountants (HKICPA), Recognized Employer of CPA Australia (CPAA) and Approved Employer of the Association of Chartered Certified Accountants (ACCA).\n\nRemarks: We offer successful candidates 15-day annual leave, 5-day work, study/examination leave, qualifying premium upon completion of recognized professional examinations, excellent job exposure and career prospects.\n\nApplicants should send their full C.V. and expected salary to Human Resources Department by clicking \u201cApply Now\u201d. Please quote ref. \"Accounting Senior Associate / Assistant Manager\u201d on your application.\n\nPersonal data provided by job applicants will be used strictly in accordance with the employer's personal data policies, a copy of which will be provided immediately upon request.", "employment_types": ["Full Time", "Permanent"], "selling_points": ["Accounting", "Authorized Employer of the HKICPA, CPAA & ACCA", "Solid experience in payroll services"], "locations": ["Ngau Tau Kok"], "categories": ["Accounting", "Accountant", "Finance / Accounting Manager", "Taxation"], "post_time": "2022-01-12T06:07:49Z", "salary": {"currency": null, "max": null, "min": null, "period": null, "term": null}, "salary_visible": false, "title_keywords": ["senior associate", "accounting", "assistant manager"], "responsibilities": ["software", "policies", "audit", "maintain good relationship", "payment", "reports", "personal data", "payroll", "setup", "administration"], "requirements": {"degrees": ["degree holder"], "majors": [], "languages": ["english", "chinese", "mandarin"], "language_level": ["fluency", "advantage", "good command"], "hard_skills": ["small", "excel", "acca", "accounting software", "hong kong institute of certified public accountants", "association of chartered certified accountants", "word", "cpa", "c", "accounting system", "hkicpa"], "soft_skills": ["self-motivated", "independent", "multi-task", "responsible", "diverse", "interpersonal skills", "proactive"], "languages_combined": [{"language": "english", "language_level": ["good command"]}, {"language": "chinese", "language_level": ["good command"]}, {"language": "mandarin", "language_level": ["fluency", "advantage"]}]}, "experience_required": {"duration": [], "field": ["accounting", "relevant experience", "audit"]}}, {"job_id": "100003009036782", "location_code": "hk", "company": "Wilson Communications Limited", "job_title": "Accounting Manager / Assistant Accounting Manager", "description": "Your new role\n\nIn charge of management reporting, budgeting, and forecasting within China Business\nWork closely with Business and Operations to support organizational change and business growth\nAct as Finance representative to support leaders of China Business in handling daily financial issues\nInfluence and drive the business partners for cost-saving and productivity improvement\nDevelop financial models for assessing new business initiatives\nLiaise with professional parties for statutory requirements\n\nWhat you'll need to succeed\n\nDegree holder with professional qualification\nAt least 8 years of solid experience in in management reporting, preferably big 4 trained and with solid commercial experience in China operation\nHands on, attention to detail and strong analytical skills\nExcellent command of English, Cantonese and Mandarin\nOpen to occasional travel\n\nWhat you need to do now\nIf you're interested in this role, click 'apply now' or for further information and a confidential discussion on this role or to find out about more opportunities in Accounting/ Finance, contact Lorraine Shan at Hays at +852 2230 7924 or email your CV to lorraine.shan@hays.com.hk", "employment_types": ["Full Time", "Permanent"], "selling_points": ["Kwai Fong, 5-day, free shuttle bus", "Qualified member of ACCA, HKICPA or equivalent", "exp. in tele-communications or retail industry"], "locations": ["Kwai Fong"], "categories": ["Accounting", "Finance / Accounting Manager", "Financial Controller"], "post_time": "2022-01-10T14:21:26Z", "salary": {"currency": null, "max": null, "min": null, "period": "monthly", "term": null}, "salary_visible": false, "title_keywords": ["assistant accounting manager", "accounting manager"], "responsibilities": ["cost", "business initiatives", "budgeting", "operations", "financial models", "develop", "statutory requirements", "management reporting", "contact", "liaise with", "forecasting"], "requirements": {"degrees": ["degree holder"], "majors": [], "languages": ["cantonese", "english", "mandarin"], "language_level": ["excellent"], "hard_skills": ["analytical skills"], "soft_skills": ["organizational", "interested in", "analytical skills", "hands on", "attention to detail"], "languages_combined": [{"language": "cantonese", "language_level": ["excellent"]}, {"language": "english", "language_level": ["excellent"]}, {"language": "mandarin", "language_level": ["excellent"]}]}, "experience_required": {"duration": ["at least 8 years"], "field": ["commercial", "management", "operation", "big 4"]}}, {"job_id": "100003009048626", "location_code": "hk", "company": "Hays", "job_title": "Finance Manager (Listco | China Operation | Up to 60k )", "description": "Job Description\nMonitor business performance with reporting and analysis\nPartner with various Business Units and Supporting Divisions to perform financial projections\nTake part in budgeting, forecasting, and strategic planning\nControl expenses between actual versus budget trends and actions taken by the managers\nCAPEX control and cashflow forecast\nReview financial statements and schedules to ensure due diligence and compile a commentary\nPerform daily, weekly, and monthly reporting for management to review\n\n\n\nJob Requirements:\n\nBachelor Degree holder or above in Finance, Business, Economics or Statistical related discipline\nAt least 3 years account experience in sizable firms\nRetail, F&B background would be a definite advantage\nHigh proficiency in MS Office with strong excel skills\nIndependent, able to work in a fast-paced environment and meet tight reporting timelines.\nDemonstrate good communication, interpersonal and analytical skills.\nGood command of both spoken and written English and Chinese\n\nWe\u00a0Offer:\n\n5 day work week\nCompetitive Salary Package\n13 months' Guaranteed Salary\nPerformance Incentives\nGroup Medical Scheme\nBirthday Leave\nFree Lunch\nEnergetic & Dynamic Culture\n\nInterested parties, please send your detailed resume, availability, present and expected salary to Human Resources Department by clicking \u201cApply Now\u201d.\n\nWe are an equal opportunity employer. Applications from all qualified candidates are welcome.", "employment_types": ["Full Time", "Permanent"], "selling_points": ["Reputable company", "All rounded role", "New headcount"], "locations": ["Not Specified"], "categories": ["Accounting", "Finance / Accounting Manager"], "post_time": "2022-01-14T06:55:02Z", "salary": {"currency": "HKD", "max": 54999, "min": 45000, "period": "monthly", "term": null}, "salary_visible": true, "title_keywords": ["finance manager"], "responsibilities": ["reporting", "control", "due diligence", "management", "strategic planning", "schedules", "budgeting", "analysis", "expenses", "monitor", "budget", "capex", "review", "financial statements", "forecast", "forecasting"], "requirements": {"degrees": ["bachelor degree holder"], "majors": ["finance", "business", "economics"], "languages": ["english", "chinese"], "language_level": ["good command"], "hard_skills": ["excel", "analytical skills", "ms office"], "soft_skills": ["independent", "fast-paced environment", "analytical skills", "communication", "interpersonal"], "languages_combined": [{"language": "english", "language_level": ["good command"]}, {"language": "chinese", "language_level": ["good command"]}]}, "experience_required": {"duration": ["at least 3 years"], "field": []}}]