[{"job_id": "100003009052880", "location_code": "hk", "company": "YCA Partners CPA Limited", "job_title": "Audit Staff (Junior / Senior) - 5 day work", "description": "Requirements:\n\nDiploma / Degree holder with major in accounting, finance or business related disciplines;\n0-3 year(s) relevant working experience, fresh graduate is welcome;\nGood command in spoken and written English, Cantonese and Putonghua; and\nInitiative, hardworking and able to work under pressure;\n\nBenefits\n\nFive-day work week\nFlexible working hours\nDiscretionary bonus\nBirthday leave\nMedical allowance\u00a0\nExamination leave\nStudy leave\nOvertime compensation leave\n\nCompetitive package will be offered to the right candidate(s), including 5-day work, annual discretionary bonuses, training, examination and study leaves. Interested parties please send in full resume with current & expected salary to our HR Department via \"Apply Now\".\n\nPlease visit\u00a0www.yca.com.hk\u00a0for more information.\n\nPersonal data will be used for recruitment purpose only.", "employment_types": ["Full Time"], "selling_points": ["Five-day work week / Flexible working hours", "Discretionary bonus / Medical allowance", "Birthday leave / Examination leave / Study leave"], "locations": ["Kwun Tong"], "categories": ["Accounting", "Accountant", "Audit", "Others"], "post_time": "2022-01-17T04:24:02Z", "salary": {"currency": null, "max": null, "min": null, "period": "monthly", "term": null}, "salary_visible": false, "title_keywords": ["audit staff", "junior"], "responsibilities": ["work under pressure"], "requirements": {"degrees": ["diploma", "fresh graduate", "degree holder"], "majors": ["business", "finance", "related disciplines", "accounting"], "languages": ["cantonese", "putonghua", "english"], "language_level": ["good command"], "hard_skills": [], "soft_skills": ["initiative", "hardworking", "work under pressure"], "languages_combined": [{"language": "cantonese", "language_level": ["good command"]}, {"language": "putonghua", "language_level": ["good command"]}, {"language": "english", "language_level": ["good command"]}]}, "experience_required": {"duration": [], "field": ["relevant working experience"]}}, {"job_id": "100003009052149", "location_code": "hk", "company": "BDO", "job_title": "Group Assistant (Full time / Part time) - Assurance (Ref : AUD / JDB)", "description": "Main responsibilities:\n\nAssist in performing simple data processing and transforming\nHandle various documentation and administrative processes, such as document archiving\n\nRequirements:\n\nPreferably at post-secondary level. Graduates from any disciplines of studies are welcomed.\nWork experience is not required as on-the-job training will be provided.\nWell-versed in Excel and other Microsoft Office applications.\nBasic accounting and/or IT-related knowledge is/are a definite asset(s), but not a prerequisite.\nKnowledge in database management is preferable, but not a must.\n\nWe are an equal opportunity employer, and offer excellent prospects and career development for the right candidate.\u00a0 Interested parties please send your application\u00a0with full career history, current and expected salary by clicking\u00a0Apply Now.\n\nApplications will be treated in strict confidence. Personal data collected will be used for recruitment purposes only.", "employment_types": ["Full Time", "Part Time", "Temporary", "Contract"], "selling_points": ["Assist in data processing and transformation", "Provide clerical support", "Full time / Part time"], "locations": ["Sheung Wan"], "categories": ["Accounting", "Others", "Admin & HR", "Clerical / Admin Staff", "Information Technology (IT)", "Others"], "post_time": "2022-01-17T02:16:29Z", "salary": {"currency": null, "max": null, "min": null, "period": "monthly", "term": null}, "salary_visible": false, "title_keywords": ["assistant"], "responsibilities": ["documentation", "administrative processes", "data processing"], "requirements": {"degrees": [], "majors": [], "languages": [], "language_level": [], "hard_skills": ["excel", "basic", "microsoft office"], "soft_skills": [], "languages_combined": []}, "experience_required": {"duration": [], "field": ["training"]}}, {"job_id": "100003009053528", "location_code": "hk", "company": "Inno Consultants Services Limited", "job_title": "Accounts Clerk", "description": "\nProfessional Business Consultancy Company\nResponsibilities:\n\u2022 Bookkeeping\n\u2022 Data entry\n\u2022 Document processing\n\u2022 Liaison with clients\nRequirements:\nF.5 (or equivalent) or above\n\u2022 Min 1 year working experience\n\u2022 Proficiency in Cantonese, English and Mandarin\nProficiency in MS (particularly Words, Excel)\n\u2022 Office located in Kowloon Bay\n\u5de5\u4f5c\u7bc4\u570d\uff1a\n\u2022 \u7c3f\u8a18\n\u2022 \u8f38\u5165\u8cc7\u6599\n\u2022 \u6587\u4ef6\u8655\u7406\n\u2022 \u8207\u5ba2\u6236\u806f\u7cfb\n\u5c65\u6b77\uff1a\n\u2022 \u4e2d\u4e94\u6216\u4ee5\u4e0a\n\u2022 \u4e00\u5e74\u5de5\u4f5c\u7d93\u9a57\n\u2022 \u61c2\u8aaa\u5beb\u7cb5\u8a9e\u3001\u82f1\u8a9e\u548c\u666e\u901a\u8a71\n\u61c2\u5fae\u8edf\u7cfb\u7d71 (Words, Excel)\n\u2022 \u4e0a\u73ed\u5730\u9ede: \u4e5d\u9f8d\u7063\nApply please email to [via\u00a0 Apply Now ]\n\n", "employment_types": ["Full Time"], "selling_points": [], "locations": ["Kwun Tong Area"], "categories": ["Accounting", "Accounting Clerk / Supervisor", "Others", "Admin & HR", "Others"], "post_time": "2022-01-17T07:06:30Z", "salary": {"currency": null, "max": null, "min": null, "period": "monthly", "term": null}, "salary_visible": false, "title_keywords": ["accounts clerk"], "responsibilities": ["data entry"], "requirements": {"degrees": [], "majors": [], "languages": ["cantonese", "english", "mandarin"], "language_level": ["proficiency"], "hard_skills": ["excel", "words"], "soft_skills": [], "languages_combined": [{"language": "cantonese", "language_level": ["proficiency"]}, {"language": "english", "language_level": ["proficiency"]}, {"language": "mandarin", "language_level": ["proficiency"]}]}, "experience_required": {"duration": ["min 1 year"], "field": []}}, {"job_id": "100003009052880", "location_code": "hk", "company": "YCA Partners CPA Limited", "job_title": "Audit Staff (Junior / Senior) - 5 day work", "description": "Requirements:\n\nDiploma / Degree holder with major in accounting, finance or business related disciplines;\n0-3 year(s) relevant working experience, fresh graduate is welcome;\nGood command in spoken and written English, Cantonese and Putonghua; and\nInitiative, hardworking and able to work under pressure;\n\nBenefits\n\nFive-day work week\nFlexible working hours\nDiscretionary bonus\nBirthday leave\nMedical allowance\u00a0\nExamination leave\nStudy leave\nOvertime compensation leave\n\nCompetitive package will be offered to the right candidate(s), including 5-day work, annual discretionary bonuses, training, examination and study leaves. Interested parties please send in full resume with current & expected salary to our HR Department via \"Apply Now\".\n\nPlease visit\u00a0www.yca.com.hk\u00a0for more information.\n\nPersonal data will be used for recruitment purpose only.", "employment_types": ["Full Time"], "selling_points": ["Five-day work week / Flexible working hours", "Discretionary bonus / Medical allowance", "Birthday leave / Examination leave / Study leave"], "locations": ["Kwun Tong"], "categories": ["Accounting", "Accountant", "Audit", "Others"], "post_time": "2022-01-17T04:24:02Z", "salary": {"currency": null, "max": null, "min": null, "period": "monthly", "term": null}, "salary_visible": false, "title_keywords": ["audit staff", "junior"], "responsibilities": ["work under pressure"], "requirements": {"degrees": ["diploma", "fresh graduate", "degree holder"], "majors": ["business", "finance", "related disciplines", "accounting"], "languages": ["cantonese", "putonghua", "english"], "language_level": ["good command"], "hard_skills": [], "soft_skills": ["initiative", "hardworking", "work under pressure"], "languages_combined": [{"language": "cantonese", "language_level": ["good command"]}, {"language": "putonghua", "language_level": ["good command"]}, {"language": "english", "language_level": ["good command"]}]}, "experience_required": {"duration": [], "field": ["relevant working experience"]}}, {"job_id": "100003009052149", "location_code": "hk", "company": "BDO", "job_title": "Group Assistant (Full time / Part time) - Assurance (Ref : AUD / JDB)", "description": "Main responsibilities:\n\nAssist in performing simple data processing and transforming\nHandle various documentation and administrative processes, such as document archiving\n\nRequirements:\n\nPreferably at post-secondary level. Graduates from any disciplines of studies are welcomed.\nWork experience is not required as on-the-job training will be provided.\nWell-versed in Excel and other Microsoft Office applications.\nBasic accounting and/or IT-related knowledge is/are a definite asset(s), but not a prerequisite.\nKnowledge in database management is preferable, but not a must.\n\nWe are an equal opportunity employer, and offer excellent prospects and career development for the right candidate.\u00a0 Interested parties please send your application\u00a0with full career history, current and expected salary by clicking\u00a0Apply Now.\n\nApplications will be treated in strict confidence. Personal data collected will be used for recruitment purposes only.", "employment_types": ["Full Time", "Part Time", "Temporary", "Contract"], "selling_points": ["Assist in data processing and transformation", "Provide clerical support", "Full time / Part time"], "locations": ["Sheung Wan"], "categories": ["Accounting", "Others", "Admin & HR", "Clerical / Admin Staff", "Information Technology (IT)", "Others"], "post_time": "2022-01-17T02:16:29Z", "salary": {"currency": null, "max": null, "min": null, "period": "monthly", "term": null}, "salary_visible": false, "title_keywords": ["assistant"], "responsibilities": ["documentation", "administrative processes", "data processing"], "requirements": {"degrees": [], "majors": [], "languages": [], "language_level": [], "hard_skills": ["excel", "basic", "microsoft office"], "soft_skills": [], "languages_combined": []}, "experience_required": {"duration": [], "field": ["training"]}}, {"job_id": "100003009053528", "location_code": "hk", "company": "Inno Consultants Services Limited", "job_title": "Accounts Clerk", "description": "\nProfessional Business Consultancy Company\nResponsibilities:\n\u2022 Bookkeeping\n\u2022 Data entry\n\u2022 Document processing\n\u2022 Liaison with clients\nRequirements:\nF.5 (or equivalent) or above\n\u2022 Min 1 year working experience\n\u2022 Proficiency in Cantonese, English and Mandarin\nProficiency in MS (particularly Words, Excel)\n\u2022 Office located in Kowloon Bay\n\u5de5\u4f5c\u7bc4\u570d\uff1a\n\u2022 \u7c3f\u8a18\n\u2022 \u8f38\u5165\u8cc7\u6599\n\u2022 \u6587\u4ef6\u8655\u7406\n\u2022 \u8207\u5ba2\u6236\u806f\u7cfb\n\u5c65\u6b77\uff1a\n\u2022 \u4e2d\u4e94\u6216\u4ee5\u4e0a\n\u2022 \u4e00\u5e74\u5de5\u4f5c\u7d93\u9a57\n\u2022 \u61c2\u8aaa\u5beb\u7cb5\u8a9e\u3001\u82f1\u8a9e\u548c\u666e\u901a\u8a71\n\u61c2\u5fae\u8edf\u7cfb\u7d71 (Words, Excel)\n\u2022 \u4e0a\u73ed\u5730\u9ede: \u4e5d\u9f8d\u7063\nApply please email to [via\u00a0 Apply Now ]\n\n", "employment_types": ["Full Time"], "selling_points": [], "locations": ["Kwun Tong Area"], "categories": ["Accounting", "Accounting Clerk / Supervisor", "Others", "Admin & HR", "Others"], "post_time": "2022-01-17T07:06:30Z", "salary": {"currency": null, "max": null, "min": null, "period": "monthly", "term": null}, "salary_visible": false, "title_keywords": ["accounts clerk"], "responsibilities": ["data entry"], "requirements": {"degrees": [], "majors": [], "languages": ["cantonese", "english", "mandarin"], "language_level": ["proficiency"], "hard_skills": ["excel", "words"], "soft_skills": [], "languages_combined": [{"language": "cantonese", "language_level": ["proficiency"]}, {"language": "english", "language_level": ["proficiency"]}, {"language": "mandarin", "language_level": ["proficiency"]}]}, "experience_required": {"duration": ["min 1 year"], "field": []}}, {"job_id": "100003009052232", "location_code": "hk", "company": "Kai Fu Property Services Co Ltd", "job_title": "Accounting Assistant/ Assistant Accounting Officer", "description": "Job duties:\n\nPerform daily accounting operations including daily bank operation (arrange cheque deposit, cheque payment, bank transfer and authorised signatures) filing, book keeping etc.\nProvide clerical support to the Department\nResponsible for outdoor working\nAssist in ad-hoc assignment\n\nRequirements:\n\nHolder of a Associate Degree/Higher Diploma\u00a0or above\u00a0\n\nHolding LCC Elementary or above\n1 year relevant experience\u00a0or above\nWell organized, self-motivated, hardworking and willing to learn\nWilling to work under pressure and meet tight deadline\nGood organization, analytical and Excel skills\nFresh graduates will also be considered\nImmediate available is preferred\n\n**Salary and position will commensurate with\u00a0qualifications and\u00a0relevant working experiences.", "employment_types": ["Full Time", "Permanent"], "selling_points": [], "locations": ["Kowloon Bay"], "categories": ["Accounting", "Accountant", "Accounting Clerk / Supervisor", "Others"], "post_time": "2022-01-17T02:31:28Z", "salary": {"currency": null, "max": null, "min": null, "period": "monthly", "term": null}, "salary_visible": false, "title_keywords": ["accounting assistant", "assistant accounting officer"], "responsibilities": ["provide clerical support", "ad-hoc", "payment", "daily accounting operations"], "requirements": {"degrees": ["associate degree", "higher diploma or above"], "majors": [], "languages": [], "language_level": [], "hard_skills": ["excel", "lcc"], "soft_skills": ["self-motivated", "willing to learn", "well organized", "meet tight deadline", "hardworking", "work under pressure"], "languages_combined": []}, "experience_required": {"duration": ["1 year"], "field": ["relevant experience"]}}, {"job_id": "100003009054610", "location_code": "hk", "company": "DFS Hong Kong Limited", "job_title": "Assistant Planning Manager, Watches & Jewellry", "description": "We are seeking a self-motivated and meticulous Assistant Planning Manager to join our well-established team. With guidance from the Planning Manager, you will work on stock forecast, ordering and allocation for one category of product. You will closely monitor the inventory flow to achieve the worldwide gross margin plans, and to maximize sales and profitability in your assigned location.\n\nResponsibilities\n\nSeasonal Sales Planning\n\n\nDevelop worldwide seasonal sales, margin and mix plans for one segment of a category based on strategic direction and financial guidelines\nDevelop location-specific sales ratify with region plans; tie to location profiles and assist plans\nDevelop monthly financial plans at department level for one segment of a category\n\nOrder Placement and Replenishment\n\n\nProvide analysis necessary for the development of the monthly Open-to-Buy based on planning variances to the financial plans\nRecommend quantities to place for fashion orders based on stock projection\nReview and update replenishment forecasts as required based on stock projection\nMonitor Open-To-Buy weekly and make recommendations as appropriate\nCommunicate and follow up with vendors to support merchandise flow requirements\n\nInventory Management\n\n\nSupply the SKU Team with appropriate initialization information to activate distribution\nWork with Distributors to ensure on-order needs matches with location sales needs\nIdentify fast and slow sellers and develop action plan with team\nProvide monthly analysis to report and implement discontinued SKU action plans\nDevelop and recommend markdown strategy and manage markdown budgets\n\nKey Requirements\n\n\nBachelor\u2019s Degree or above\n1-2 years\u2019 experience in merchandising and/or planning with a major retailer\nExperience in the luxury market and international business preferred\nAble to create and maintain sophisticated Excel spreadsheets\nNegotiation experience required\nStrong interpersonal skills and be able to deliver high-level presentations\nProficient in both written and spoken English", "employment_types": ["Full Time", "Permanent"], "selling_points": ["World's Leading Luxury Travel Retailer", "Work Life Balance, Five-day Work Week", "International & Dynamic Working Environment"], "locations": ["Quarry Bay"], "categories": ["Accounting", "Others", "Merchandising & Purchasing", "Handbag", "Watch"], "post_time": "2022-01-17T10:14:11Z", "salary": {"currency": null, "max": null, "min": null, "period": "monthly", "term": null}, "salary_visible": false, "title_keywords": ["manager", "assistant"], "responsibilities": ["make recommendations", "budgets", "open-to-buy", "markdown strategy", "guidelines", "analysis", "review", "monitor", "replenishment", "develop", "inventory management", "report", "plan", "plans", "financial plans", "planning"], "requirements": {"degrees": ["degree or above", "bachelor"], "majors": [], "languages": ["english"], "language_level": ["proficient"], "hard_skills": ["excel", "presentations"], "soft_skills": ["sophisticated", "interpersonal skills", "negotiation"], "languages_combined": [{"language": "english", "language_level": ["proficient"]}]}, "experience_required": {"duration": ["1-2 years"], "field": ["business", "merchandising", "planning"]}}, {"job_id": "100003009052196", "location_code": "hk", "company": "IPSOS Asia Limited", "job_title": "Temporary Accounts Clerk \u2013 Accounts Receivable (1 year renewable contract)", "description": "The role of Accounts Clerk \u2013 Accounts Receivable is to assist the Accountant in handling account receivable function, monthly schedule & reconciliation and performing the financial accounting jobs for month end.\n\nRole & Responsibilities:\n\nIssue invoice to customers.\nPerform settlement received from customers and follow up on outstanding balances on a timely manner.\nPrepare management reports relating to accounts receivable.\nPrepare balance sheet and monthly schedules relating to accounts receivable and follow up on outstanding items.\nSupport ad-hoc assignments.\n\nQualification\uff1a\n\nDiploma or above in Accountancy or Finance\nLCCI Inter-mediate level or above with 1-2 years of accounting experience is preferred\n\nKnowledge\uff1a\n\nBasic accounting knowledge\nKnowledge in accounting system is a definite advantage\nProficient in MS Word & Excel\n\nSkill (including technical and people skill):\n\nGood English language skill both verbal and writing\nGood computer skill especially in Microsoft Excel, Word, and PowerPoint\n\nOther Requirements\n\nResponsible and able to work overtime to meet tight report deadlines\nImmediate available is preferred\n\nWe offer an attractive remuneration package with a 5-day workweek to the right candidates. Interested parties please send a resume to us. All information collected will be used for recruitment purposes only. The Company may retain applications for future openings or other appropriate positions within the Company. Resumes received will be destroyed within 12 months.", "employment_types": ["Full Time", "Part Time", "Permanent", "Temporary", "Contract", "Freelance"], "selling_points": ["Accounts Receivable", "Handling monthly schedule", "Preparing expense analysis and reporting"], "locations": ["Hung Hom"], "categories": ["Accounting", "Accountant", "Accounting Clerk / Supervisor", "Others"], "post_time": "2022-01-17T02:26:10Z", "salary": {"currency": null, "max": null, "min": null, "period": "monthly", "term": null}, "salary_visible": false, "title_keywords": ["accounts clerk"], "responsibilities": ["accounts receivable", "invoice", "schedules", "ad-hoc assignments", "a timely manner", "management reports", "balance sheet"], "requirements": {"degrees": [], "majors": [], "languages": [], "language_level": [], "hard_skills": [], "soft_skills": ["work overtime", "responsible"], "languages_combined": []}, "experience_required": {"duration": [], "field": []}}, {"job_id": "100003008990729", "location_code": "hk", "company": "HLB Hodgson Impey Cheng Limited", "job_title": "Audit Accountant I/ Audit Accountant II", "description": "Requirements\n\nBachelor degree holder (Major in Accounting is preferred)\nGood command of both written and spoken in English and Chinese\nFresh graduates will also be considered\n\nWe offer 5 days work. Interested parties please send your resume with expected salary and availability to the\u00a0Human Resources Department\u00a0(AAD 1), HLB Hodgson Impey Cheng Limited, 31/F Gloucester Tower, The Landmark, 11 Pedder Street, Central, Hong Kong or via email to AHon\uff20hic.com.hk\n\nPersonal data collected will be used for recruitment purposes only.", "employment_types": ["Full Time", "Permanent"], "selling_points": ["5-days work, Medical insurance, Exam/ Study Leave", "Degree holder (Fresh Graduates also welcome)", "Opportunity to gain audit experience in listed co."], "locations": ["Central & Western Area"], "categories": ["Accounting", "Accountant", "Audit", "Others"], "post_time": "2022-01-16T21:50:06Z", "salary": {"currency": null, "max": null, "min": null, "period": "monthly", "term": null}, "salary_visible": false, "title_keywords": ["accountant"], "responsibilities": [], "requirements": {"degrees": ["bachelor degree holder"], "majors": ["accounting"], "languages": ["english", "chinese"], "language_level": ["good command"], "hard_skills": [], "soft_skills": [], "languages_combined": [{"language": "english", "language_level": ["good command"]}, {"language": "chinese", "language_level": ["good command"]}]}, "experience_required": {"duration": [], "field": []}}, {"job_id": "100003009051712", "location_code": "hk", "company": "ASM Technology Hong Kong Limited", "job_title": "Contract General Accountant", "description": "Job description\nSupport daily data processing and voucher postings\nPerform month-end closing tasks and financial reporting packages\nAssist in preparation of annual accounts\nConduct analytical review of the financial data\nHandle other ad hoc duties as required\nJob requirements\nDegree in Accounting, Finance or relevant disciplines\nAt least 3 years working experience in accounting\nExperience in using SAP will be an advantage\nProficient in MS office application\nSelf-motivated and committed to continuous improvement\nAble to work independently and be a team player\nImmediately available is highly preferred\n\nWorking location: Tsing Yi, Hong Kong\n\nAttractive salary and fringe benefits package will be offered to the right candidates.\n\nInterested parties please submit your application with cover letter, resume, certificate and transcripts.\n\nData collected will be used for recruitment purpose only. Suitable candidates may be referred to other vacancies within our company.", "employment_types": ["Full Time", "Contract"], "selling_points": ["Degree in Accounting, Finance", "At least 3 years working experience", "Support daily data processing and voucher postings"], "locations": ["Tsing Yi"], "categories": ["Accounting", "Accountant", "Accounting Clerk / Supervisor", "Others"], "post_time": "2022-01-16T21:51:02Z", "salary": {"currency": null, "max": null, "min": null, "period": "monthly", "term": null}, "salary_visible": false, "title_keywords": ["accountant"], "responsibilities": ["ad hoc duties", "data", "review", "data processing", "month-end closing", "financial reporting"], "requirements": {"degrees": ["degree"], "majors": ["finance", "accounting"], "languages": [], "language_level": [], "hard_skills": ["sap", "ms office"], "soft_skills": ["committed", "self-motivated", "team player", "work independently"], "languages_combined": []}, "experience_required": {"duration": ["at least 3 years"], "field": ["accounting"]}}, {"job_id": "100003009052730", "location_code": "hk", "company": "South Horizons Management Limited", "job_title": "SENIOR ACCOUNTS CLERK / ACCOUNTS CLERK [Ref. SH-SAC/AC]", "description": "5 passes in HKCEE / HKDSE including English or equivalent\nHolder of LCC Intermediate level in\u00a0accounting\nMinimum 2 years' relevant working experience\nTo maintain accounting system and daily operation\nTo Handle full sets of book-keeping for management fund accounts\nTo generate debit notes / reminders / receipts from billing system\nTo handle daily cheque register and deposit arrangement\nTo prepare petty cash vouchers and reimbursement arrangement\nTo handle enquiries\nAd-hoc tasks as assigned by immediate supervisor\nProficient in MS Office with knowledge in Oracle system is an added advantage\nFluent in written and spoken English and Chinese\nDetail-oriented, self-motivated and able to work independently\nCandidate with less experience will be considered as Accounts Clerk\n\nWe offer salary and benefits commensurate with qualifications and experience. Please send a full resume with contact telephone number and expected salary to\u00a0General Manager - Human Resources & Administration, South Horizons Management Limited, 3/F., One Harbourfront, 18 Tak Fung Street, Hunghom, Kowloon\u00a0(Please quote reference on envelope)\u00a0or by clicking \"Apply Now\".\n\nWe are an equal opportunity employer and welcome applications from all qualified candidates. The information provided will be treated in strict confidence and be used only for consideration of your application for relevant/similar post(s).\n\nApplicants not hearing from us within six weeks from the date of advertisement may consider their applications unsuccessful. All personal data of unsuccessful applicants will be destroyed after the recruitment exercise when no longer required.", "employment_types": ["Full Time", "Permanent"], "selling_points": ["5 passes in HKCEE / HKDSE including English", "2 years' relevant working experience", "LCC Intermediate level in accounting"], "locations": ["Aberdeen"], "categories": ["Accounting", "Accounting Clerk / Supervisor", "Others", "Property / Real Estate", "Property Management"], "post_time": "2022-01-17T06:30:00Z", "salary": {"currency": null, "max": null, "min": null, "period": null, "term": null}, "salary_visible": false, "title_keywords": ["accounts clerk", "senior accounts clerk"], "responsibilities": ["management", "receipts", "ad-hoc tasks", "daily operation", "handle enquiries", "maintain", "book-keeping"], "requirements": {"degrees": ["hkdse"], "majors": [], "languages": ["english", "chinese"], "language_level": ["fluent"], "hard_skills": ["oracle system", "billing system", "lcc", "accounting system", "ms office"], "soft_skills": ["self-motivated", "work independently", "detail-oriented"], "languages_combined": [{"language": "english", "language_level": ["fluent"]}, {"language": "chinese", "language_level": ["fluent"]}]}, "experience_required": {"duration": ["minimum 2 years"], "field": ["relevant working experience"]}}, {"job_id": "100003009053372", "location_code": "hk", "company": "Rotam Agrochemical Company Limited", "job_title": "Executive, Company Secretarial", "description": "Responsibilities\u00a0\n\n\nAssist in handling company secretarial matters relating to associated companies of the Group under various jurisdictions;\nMaintain up-to-date records such as annual return and general meeting papers and attending to local filings;\nAssist in preparing relevant minutes and various information for public disclosures, compliance issues and corporate exercises of the Group;\nPerform ad hoc assignments as required.\nRequirements\n\n\nA degree holder with a student member of HKCGI;\nMinimum 2 years\u2019 experience in company secretarial field;\nExperience in handling offshore companies is an advantage;\nProficiency in MS Office applications, Chinese Word Processing and CSA;\nExcellent written and spoken English and Chinese. Mandarin is essential;\nGood interpersonal and organization skills;\nMeticulous, self-motivated, responsible and independent;\nImmediately available is highly preferred.\nCandidates with more experience will be considered as Senior Executive, Company Secretarial.\n\n\nWe provide competitive remuneration with career prospect to the right candidate. Interested parties please send your detailed resume with current & expected salary, contact number, availability with reference no.RA-CSE-2021 on subject line.\n\nCorporate Office Address: 26/F, E-Trade Plaza, 24 Lee Chung Street, Chai Wan, Hong Kong (5 minutes' walking distance to MTR station)\u00a0\u00a0\n\nFor more company information, please feel free to visit: www.rotam.com\u00a0\n\n(Personal data collected will be used for recruitment purpose only.)\u00a0", "employment_types": ["Full Time", "Permanent"], "selling_points": ["Co Sec matters for various jurisdictions& offshore", "Assist in preparing minutes and info for the Group", "Min 2 yrs exp., exp in handling offshore companies"], "locations": ["Chai Wan"], "categories": ["Accounting", "Others", "Professional Services", "Company Secretary", "Legal & Compliance"], "post_time": "2022-01-17T06:52:23Z", "salary": {"currency": null, "max": null, "min": null, "period": "monthly", "term": null}, "salary_visible": false, "title_keywords": ["executive"], "responsibilities": ["compliance", "maintain", "ad hoc assignments"], "requirements": {"degrees": ["degree holder"], "majors": [], "languages": ["english", "chinese", "mandarin"], "language_level": ["proficiency", "excellent"], "hard_skills": ["chinese word processing", "ms office"], "soft_skills": ["meticulous", "self-motivated", "independent", "responsible", "organization skills", "interpersonal"], "languages_combined": [{"language": "english", "language_level": ["excellent"]}, {"language": "chinese", "language_level": ["proficiency", "excellent"]}, {"language": "mandarin", "language_level": []}]}, "experience_required": {"duration": ["minimum 2 years"], "field": ["secretarial"]}}, {"job_id": "100003009052296", "location_code": "hk", "company": "Chef's Garden Limited", "job_title": "Accountant", "description": "Responsibilities:\n\nPrepare annual audit schedules, accounts reconciliation, provide appropriate follow-up actions, and manage the audit process;\nHandle and assist any ad-hoc tasks as assigned\nRequirements:\n\nDiploma/ Certificate in Accounting\n3 years accounting/ audit experience\nPrevious experience in restaurant/ retail business, Peachtree, Xero is an advantage\nProficiency in Excel and other MS office applications\nStable, self-motivated, hardworking, well-organized, detail-minded with strong sense of responsibilities, good interpersonal and communication skills;\nImmediately available\n\nWe\u00a0offer five-day work and Free meals\n\nInterested parties please apply by sending full resume with current and expected salary by clicking \"Apply Now\".\u00a0\n\n(All information and personal data collected relating to employment applications will be kept confidential and will be used \u00a0for recruitment purpose only.)", "employment_types": ["Full Time"], "selling_points": ["exp. in retail/catering business is a plus", "immediate available is preferable", "Be able to handle full set of accounts"], "locations": ["Sai Ying Pun"], "categories": ["Accounting", "Accountant", "Others", "Hospitality / F & B", "Food & Beverage"], "post_time": "2022-01-17T03:58:31Z", "salary": {"currency": null, "max": null, "min": null, "period": "monthly", "term": null}, "salary_visible": false, "title_keywords": ["accountant"], "responsibilities": ["schedules", "ad-hoc tasks", "audit", "annual audit"], "requirements": {"degrees": ["certificate", "diploma"], "majors": ["accounting"], "languages": [], "language_level": [], "hard_skills": ["excel", "peachtree", "xero", "ms office"], "soft_skills": ["detail-minded", "communication skills", "self-motivated", "well-organized", "stable", "interpersonal", "hardworking", "sense of responsibilities"], "languages_combined": []}, "experience_required": {"duration": ["3 years"], "field": ["restaurant", "business", "audit experience", "accounting", "retail"]}}, {"job_id": "100003009052940", "location_code": "hk", "company": "EB Services Limited", "job_title": "Assistant Manager (Treasury Operation)", "description": "To cope with the continuous business expansion of the Company, we invite talented and professional candidate to join our growing team:\n\nJob Descriptions\n\nThe candidate needs to coordinate directly and liaise with various Hong Kong and overseas departments to ensure all treasury banking services are provided to meet operation requirements in a timely cost-efficient manner.\n\nResponsibilities:\nLead a small team for daily operations of treasury functions, including but not limit to customer accounts & commission payments.\nMonitor and manage the funding requirements.\nSupport bank account opening & closing, authorized signatories updated, and ensure electronic banking is operated in a secured manner.\nLiaise with external banks, online payment/collection gateways and other financial services providers for system interface and daily banking transactions.\nRecommend and implement ideas and innovations to improve upon existing systems, work processes and procedures on commission verification, commission payments and refund process.\nAble to build good relationship with internal customers and external stakeholders.\nParticipate in the development & enhancement of cash management systems, treasury management systems, online banking linkage with ERP systems, straight-through-payment process systems, online collection/payment gateway systems, to improve treasury operation processes & control and manage risks exposure.\n\nRequirements:\n\nBachelor\u2019s degree in Accounting or Finance.\nOver 7 years\u2019 experience from multinational companies is preferred.\nExperience in retail / e-commerce / direct selling industry experience is an advantage.\nExcellent analytical, critical thinking and troubleshooting skills.\nAble to manage multiple items simultaneously and prioritize appropriately.\nDemonstrates initiative in anticipating and solving issues; self-motivated and naturally inquisitive.\nGood verbal / written communication skills in both Chinese and English.\nStrong PC skills, especially in Excel (e.g., Marco, VBA), Smart Sheet, database & etc.\nImmediate available is highly preferred.", "employment_types": ["Full Time", "Permanent"], "selling_points": ["5 Days work week", "Medical benefits, life insurance", "Flexible working hours"], "locations": ["Ngau Tau Kok"], "categories": ["Accounting", "Finance / Accounting Manager", "Others"], "post_time": "2022-01-17T04:37:25Z", "salary": {"currency": null, "max": null, "min": null, "period": "monthly", "term": null}, "salary_visible": false, "title_keywords": ["assistant manager"], "responsibilities": ["cost", "lead a small team", "coordinate", "daily operations", "payments", "banking", "liaise with"], "requirements": {"degrees": ["degree", "bachelor"], "majors": ["finance", "accounting"], "languages": ["english", "chinese"], "language_level": ["good"], "hard_skills": ["erp systems", "excel", "vba", "e-commerce", "account opening", "marco", "pc skills"], "soft_skills": ["communication skills", "self-motivated", "troubleshooting", "prioritize", "initiative"], "languages_combined": [{"language": "english", "language_level": ["good"]}, {"language": "chinese", "language_level": ["good"]}]}, "experience_required": {"duration": ["7 years"], "field": ["retail", "e-commerce"]}}, {"job_id": "100003009054674", "location_code": "hk", "company": "Moore Associates Limited", "job_title": "MNC in Hong Kong \u2013 Assistant Finance Manager/ Finance Manager", "description": "The company is a well-established lifestyle brand in Europe and now looking to grow and expand in Asia with the right candidate in the Asia Office.\n\nJob Responsibilities\n\nReport to the Head of the regional office for Asia to oversee and manage the finance and accounting function of the region (Station in Hong Kong)\nResponsible for daily accounting operation including treasury, A/P, A/R, costing, GL, invoicing, bank reconciliations\nPrepare regular reporting package such as monthly full-set accounting, financial reporting, management reporting, cashflow statements, group reporting, segment report, using the in-house finance module ERP system\nWork with and report to the GM directly on annual budget and forecast\nIdentify accounting and financial issues, communicate potential impact and recommendations to the GM.\nLiaise with external firm to handle annual audit, tax filing and assist in reviewing finance and accounting work\nReview internal controls and improve overall efficiency of finance functions\nFollow up with customers on overdue payment status\nAd-hoc jobs related to accounting\n\nSuccessful Applicant\n\nUniversity graduate, preferably in finance and accounting, with professional accounting qualification\nAt least 5 years of relevant experience in handling full sets of accounting, budget and forecast, analyst, financial reporting, group reporting with commercial experience\nExperience in retail / fashion wholesale industry is advantageous, but not a must\nProficiency in MS applications, such as Word, Excel and PowerPoint with hands-on experience in finance module ERP system is an advantage\nA good team player who is pro-active and able to work independently\nStrong analytical, communication and interpersonal skills\nExcellent command of English, Cantonese and Mandarin\n\nWe offer a 5-day working week, a competitive remuneration package and generous fringe benefits.\u00a0\n\nInterested candidates please send the full resume with current and expected salary\u00a0by clicking the \"Apply Now\" button\n\nFor more information, please visit our website www.carhartt-wip.com.", "employment_types": ["Full Time", "Permanent"], "selling_points": ["Lifestyle brand in Europe", "Manage the finance and accounting function", "Prepare regular reporting package"], "locations": ["Tsim Sha Tsui"], "categories": ["Accounting", "Accountant", "Chief Accountant", "Others"], "post_time": "2022-01-17T10:30:32Z", "salary": {"currency": null, "max": null, "min": null, "period": "monthly", "term": null}, "salary_visible": false, "title_keywords": ["assistant finance manager", "finance manager"], "responsibilities": ["ad-hoc", "reporting", "annual audit", "budget", "tax filing", "bank reconciliations", "review", "invoicing", "communication", "payment", "financial reporting", "management reporting", "forecast", "liaise with", "daily accounting", "report"], "requirements": {"degrees": ["university graduate"], "majors": ["finance", "accounting"], "languages": ["cantonese", "english", "mandarin"], "language_level": ["excellent"], "hard_skills": ["excel", "ms applications", "word", "powerpoint", "erp system", "gm", "r"], "soft_skills": ["good team player", "work independently", "responsible", "hands-on", "communication and interpersonal skills", "pro-active"], "languages_combined": [{"language": "cantonese", "language_level": ["excellent"]}, {"language": "english", "language_level": ["excellent"]}, {"language": "mandarin", "language_level": ["excellent"]}]}, "experience_required": {"duration": ["at least 5 years"], "field": ["finance", "commercial", "erp system", "relevant experience", "accounting", "retail", "financial"]}}, {"job_id": "100003009054403", "location_code": "hk", "company": "The Garden Company Limited", "job_title": "Senior Accounts Officer", "description": "Responsibilities:\n\nResponsible for accounts receivable, handling customer\u2019s settlement and scanning sales invoices.\nPerform routine accounting functions including data entry and document filing.\nOther clerical support to the Department and ad hoc assignments.\n\nRequirements:\n\nAccounting related education or qualification (LCC Diploma or above);\n2 years\u00a0or above experience\u00a0in accounting, experiences in credit control, SAP and FMCG/Retail industry is advantage\nIndependent, well organized and self-motivated\nGood command of both spoken and written English and Chinese\nProficient\u00a0in MS Excel & Word\nCandidates with less experience will be considered as Accounts Officer / Senior Accounts Clerk\n\nWorking Location: Sham Tseng (Free Shuttle Bus Service running along different locations in Yuen Long, Tuen Mun, Tsuen Wan and Shamshuipo to / from office are provided)\n\n\n\n\nInterested parties please\u00a0click\u00a0\u201cApply Now\u201d\u00a0\u00a0or send application\u00a0with detailed resume, date available and expected salary to\u00a0Human Resources Department, The Garden Company Limited, 1-11 Sham Tsz Street, Sham Tseng, New Territories, Hong Kong.\n\nAll applications will be treated in strict confidence and retained for 6 months for recruitment purposes only.", "employment_types": ["Full Time"], "selling_points": ["Accounts receivable", "Handling customer\u2019s settlement", "LCC Diploma or above"], "locations": ["Tsuen Wan Area"], "categories": ["Accounting", "Accounting Clerk / Supervisor", "Others"], "post_time": "2022-01-17T09:23:26Z", "salary": {"currency": null, "max": null, "min": null, "period": "monthly", "term": null}, "salary_visible": false, "title_keywords": ["accounts officer"], "responsibilities": ["scanning", "document filing", "invoices", "accounts receivable", "data entry", "clerical support", "ad hoc assignments"], "requirements": {"degrees": ["diploma or above"], "majors": ["accounting"], "languages": ["english", "chinese"], "language_level": ["good command"], "hard_skills": ["sap", "word", "ms excel", "lcc", "wan"], "soft_skills": ["self-motivated", "independent", "well organized"], "languages_combined": [{"language": "english", "language_level": ["good command"]}, {"language": "chinese", "language_level": ["good command"]}]}, "experience_required": {"duration": ["2 years"], "field": ["retail industry", "accounting", "fmcg"]}}, {"job_id": "100003009052570", "location_code": "hk", "company": "Mitsui & Co (HK) Ltd", "job_title": "Administrative Officer (Finance & Accounting)", "description": "We are now inviting candidate of high calibre to join us in the following capacity in our Finance & Accounting Division.\n\nJob Duties:\n\nHandling various accounting input and reports with the support of supervisor (monthly biz reports, forex reports, reports to HQ, etc.)\nSupport for import & export transaction processing and checking\nPrepare report of market risk for marketable products, such as LME transaction\n\nRequirements:\n\n\nAt least 2 \u2013 3 years\u2019 relevant working experience\nUtilization on SAP (ECC) system is preferable\nPossess Basic financial and accounting concept is preferable\nGood command of English and Mandarin\nGood command of Microsoft Office Tools (e.g. Word, Excel, etc.)\nInterested parties please apply with your full resume stating present and expected salary.\n\n\n\nAll information will be kept confidential and used for recruitment purpose only. Although we endeavour to respond to every applicant, this may not always be possible so if you receive no response within 60 days, please consider your application for this specific vacancy to be unsuccessful.\n\n", "employment_types": ["Full Time", "Permanent"], "selling_points": [], "locations": ["Admiralty"], "categories": ["Accounting", "Accounting Clerk / Supervisor", "Others", "Banking / Finance", "Order Processing & Operation / Settlement"], "post_time": "2022-01-17T03:26:35Z", "salary": {"currency": null, "max": null, "min": null, "period": "monthly", "term": null}, "salary_visible": false, "title_keywords": ["administrative officer", "accounting"], "responsibilities": ["prepare report", "reports", "checking", "transaction processing"], "requirements": {"degrees": [], "majors": [], "languages": ["english", "mandarin"], "language_level": ["good command"], "hard_skills": ["excel", "basic", "sap", "microsoft office", "ecc", "word"], "soft_skills": [], "languages_combined": [{"language": "english", "language_level": ["good command"]}, {"language": "mandarin", "language_level": ["good command"]}]}, "experience_required": {"duration": ["3 years"], "field": ["relevant working experience"]}}, {"job_id": "100003009049015", "location_code": "hk", "company": "PHM Contracting Co. Limited", "job_title": "Accounting Assistant", "description": "Responsibilities:\n\nResponsible for general accounting duties such as A/P, A/R, journal, and bank reconciliation\nTo prepare payment and receipt vouchers\nTo issue invoices, cheques, and receipts\nData input of accounting entries\nEnsure data input in a timely and accurate manner\nAssist in preparing accounting schedule and daily worker payroll\nPerform other ad hoc duties when required\n\nRequirements:\n\nl\u00a0\u00a0 Diploma or above in Accounting\n\nl\u00a0\u00a0 Holder of LCCI Intermediate or above\n\nl\u00a0\u00a0 Minimum 2 years\u2019 accounting experience\n\nl\u00a0\u00a0 Able to work independently, and Initiative-taking\n\nl\u00a0\u00a0 Experience in Peachtree is preferred\n\nl\u00a0\u00a0 Familiar with MS Word and Excel\n\n\nInterested candidates please send your full resume with expected salary by clicking 'Apply Now'\n\n(Personal data collected will be used for recruitment purpose only.)", "employment_types": ["Full Time"], "selling_points": ["Responsible for full set of accounts", "Able to work independently, Initiative-taking", "Experience in construction field is an advantage"], "locations": ["Kwun Tong"], "categories": ["Accounting", "Accountant", "Accounting Clerk / Supervisor", "Others"], "post_time": "2022-01-17T03:55:33Z", "salary": {"currency": null, "max": null, "min": null, "period": "monthly", "term": null}, "salary_visible": false, "title_keywords": ["accounting assistant"], "responsibilities": ["ad hoc duties", "invoices", "receipts", "bank reconciliation", "data input", "payment", "cheques", "general accounting duties", "schedule", "payroll"], "requirements": {"degrees": ["diploma or above"], "majors": ["accounting"], "languages": [], "language_level": [], "hard_skills": ["excel", "peachtree", "ms word"], "soft_skills": ["work independently", "initiative"], "languages_combined": []}, "experience_required": {"duration": ["minimum 2 years"], "field": ["accounting experience"]}}, {"job_id": "100003009053863", "location_code": "hk", "company": "iAsia Online Systems Limited", "job_title": "Accounting Assistant (Fresh Graduate will also be considered)", "description": "Primary Responsibilities\n\n\u00a0 \u00a0 \u00a0 \u00a0\u00a0 Perform daily accounting duties including invoicing, AP, AR,\u00a0 \u00a0 \u00a0 \u00a0 \u00a0 \u00a0 \u00a0GL, petty cash and data entry\n\u00a0 \u00a0 \u00a0 \u00a0 \u00a0Prepare\u00a0monthly bank reconciliation\n\u00a0\u00a0\u00a0\u00a0\u00a0\u00a0\u00a0\u00a0 Assist in month-end closing and audit\n\u00a0\u00a0\u00a0\u00a0\u00a0\u00a0\u00a0\u00a0 Prepare ledger breakdown\n\u00a0\u00a0\u00a0\u00a0\u00a0\u00a0\u00a0\u00a0 Perform ad hoc tasks as required\n\nRequirements\n\n\u00a0\u00a0\u00a0\u00a0\u00a0\u00a0\u00a0\u00a0 HKDSE or above with LCCI level II certificate\n\u00a0\u00a0\u00a0\u00a0\u00a0\u00a0\u00a0\u00a0 2 years working experience in Accounting function\n\u00a0\u00a0\u00a0\u00a0\u00a0\u00a0\u00a0\u00a0 Proficiency in MS Office (Excel, Word)\n\u00a0\u00a0\u00a0\u00a0\u00a0\u00a0\u00a0\u00a0 Proficiency in Peachtree is an advantage\n\u00a0\u00a0\u00a0\u00a0\u00a0\u00a0\u00a0\u00a0 Strong sense of responsibility and well-organized\n\n\u00a0We Offer\n\nCareer advancement opportunities\nAttractive remuneration package\n5-day work week and bank holiday\u00a0\nCompany medical insurance, life insurance and dental insurance\nYear End Discretionary Bonus\nOn job training and training allowance\nEducation sponsorship\nFriendly working environment\nStaff Activities & Events e.g. Happy Friday Gathering, Annual Dinner, Festival Gift, Christmas Party, etc\n\nInterested parties please apply by clicking \"Apply Now\" to send full resume with current & expected salary.\n\nFor more information of our company, please visit our website address:\u00a0http://www.iasia.com.hk\n\n(Data collected would be used for recruitment purpose only)", "employment_types": ["Permanent"], "selling_points": ["Perform daily accounting duties", "1-2 years working experience in Accounting", "Attractive remuneration package"], "locations": ["Yau Tsim Mong Area"], "categories": ["Accounting", "Accounting Clerk / Supervisor", "Others", "Admin & HR", "Clerical / Admin Staff"], "post_time": "2022-01-17T07:38:49Z", "salary": {"currency": null, "max": null, "min": null, "period": "monthly", "term": null}, "salary_visible": false, "title_keywords": ["accounting assistant"], "responsibilities": ["ap", "ar", "data entry", "ad hoc tasks", "bank reconciliation", "audit", "invoicing", "month-end closing", "daily accounting"], "requirements": {"degrees": ["certificate", "hkdse"], "majors": [], "languages": [], "language_level": [], "hard_skills": ["peachtree", "excel", "word", "ms office"], "soft_skills": ["well-organized", "sense of responsibility"], "languages_combined": []}, "experience_required": {"duration": ["2 years"], "field": ["accounting"]}}, {"job_id": "100003009051808", "location_code": "hk", "company": "Purapharm Corporation Limited", "job_title": "Accounts Clerk", "description": "Job Responsibilities\n\nDaily accounting entries, month-end closing and assist in handling full set of accounts of subsidiaries;\nPerform general daily accounting functions such as A/P, A/R, journal, bank reconciliation, Intercompany reconciliation and etc.;\nAssist in preparing monthly financial statement, costing and related month ended schedules;\nPrepare Sales report;\nParticipate in ad hoc projects and tasks as assigned by Department Head.\n\nRequirements\n\nLCC & I Level 2 or above, Higher Certificate in Accounting is preferred;\n3-5 years of accounting experience preferably in group companies;\nProficient in MS Office;\nExperience in U8+ and Microsoft Dynamic 365 accounting system would be advantage;\nAble to work under pressure;\nStrong communication skills;\nImmediate availabile is preferred.\n\nWorking Location: Hong Kong Science Park, Tai Po, N.T.\n\nWe offer 5-day working week and an attractive remuneration package. Interested party please submit your resume with current and expected salary by clicking \u201cAPPLY NOW\u201d. For company details, please visit www.purapharm.com.\n\nOur company is an equal opportunity employer. All personal data collected will be used for recruitment purpose only, while the personal data of the unsuccessful applicants will be destroyed within 6 months after the recruitment process.", "employment_types": ["Full Time", "Permanent"], "selling_points": ["Listed Company", "Full Set of Accounts", "3-5 Years of Accounting Experience"], "locations": ["Tai Po Area"], "categories": ["Accounting", "Accounting Clerk / Supervisor", "Others"], "post_time": "2022-01-17T01:14:32Z", "salary": {"currency": null, "max": null, "min": null, "period": "monthly", "term": null}, "salary_visible": false, "title_keywords": ["accounts clerk"], "responsibilities": ["schedules", "full set of accounts", "prepare sales", "bank reconciliation", "month-end closing", "ad hoc projects", "financial statement", "daily accounting", "report"], "requirements": {"degrees": ["higher certificate"], "majors": ["accounting"], "languages": [], "language_level": [], "hard_skills": ["dynamic", "lcc", "accounting system", "ms office"], "soft_skills": ["communication skills", "dynamic", "work under pressure"], "languages_combined": []}, "experience_required": {"duration": ["3-5 years"], "field": ["accounting experience", "accounting"]}}, {"job_id": "100003009053275", "location_code": "hk", "company": "BDO", "job_title": "Senior Associate / Associate - Payroll & HR Outsourcing", "description": "Trading Company in Kwai Chung invites candidates for the following post:\n\n\u00a0Accounts Clerk\n\n\u00a0Job Responsibilities:\n\nPerform daily accounting duties, including prepare payment, receipt and journal vouchers, documents filing and full spectrum of book-keeping and accounting work;\nPrepare monthly accounting schedules, bank reconciliations and reconcile intercompany balance and transactions;\nAssist in month/year-end financial reporting, stocktaking and etc.; and\nAd hoc assignments as required.\n\nRequirements:\n\n\nForm 5 or above with LCC&I 3rd Level or above with min. 3 years relevant working experience;\nProficient in MS Office, advanced Excel skills would be an advantage and experience in using ERP;\nGood command of spoken/written English and Chinese;\nMature, pro-active, strong sense of responsibility, analytical & detail-minded, able to work independently and good team player;\nImmediate available is highly preferred.\n\nInterested parties, please send your full resume stating career history, qualifications, current and expected salary, and availability to us by click \u201cApply Now\u201d to submit your application.", "employment_types": ["Full Time", "Permanent"], "selling_points": ["Provide payroll outsourcing services to clients", "1 year of experience in payroll outsourcing", "Degree in Accounting, HR or business studies"], "locations": ["Sheung Wan"], "categories": ["Accounting", "Others", "Admin & HR", "Compensation & Benefits"], "post_time": "2022-01-17T06:38:31Z", "salary": {"currency": null, "max": null, "min": null, "period": "monthly", "term": null}, "salary_visible": false, "title_keywords": ["hr", "senior associate", "associate"], "responsibilities": ["journal vouchers", "documents filing", "year-end", "schedules", "bank reconciliations", "transactions", "payment", "book-keeping", "financial reporting", "ad hoc assignments", "daily accounting"], "requirements": {"degrees": ["form 5 or above"], "majors": [], "languages": ["english", "chinese"], "language_level": ["good command"], "hard_skills": ["excel", "erp", "ms office"], "soft_skills": ["detail-minded", "work independently", "good team player", "advanced", "sense of responsibility", "mature", "pro-active"], "languages_combined": [{"language": "english", "language_level": ["good command"]}, {"language": "chinese", "language_level": ["good command"]}]}, "experience_required": {"duration": ["3 years"], "field": ["relevant working experience"]}}, {"job_id": "100003009052193", "location_code": "hk", "company": "Fed-Supremetech Limited", "job_title": "Assistant Accountant", "description": "Responsibilities:\n\nPerform and manage payroll calculation for clients\nCompile monthly payroll & MPF reports and employer\u2019s tax compliance\n\nRequirements:\n\nDegree holder,\u00a0preferably major in accounting, human resources management, business studies or equivalent\n1 year of relevant experience in\u00a0payroll outsourcing\u00a0\nKnowledge and experience in Hong Kong payroll, HK Employment Ordinance, MPF and relevant taxation legislations\nAction-orientated, detail minded and organized\nApplicants with more experience will be considered as Senior Associate\n\nWe are an equal opportunity employer, and offer excellent prospects and career development for the right candidate.\u00a0 Interested parties please send your application\u00a0with full career history, current and expected salary by\u00a0clicking\u00a0Apply Now\u00a0button below.\n\nApplications will be treated in strict confidence. Personal data collected will be used for recruitment purposes only.", "employment_types": ["Full Time"], "selling_points": [], "locations": ["Shatin Area"], "categories": ["Accounting", "Accountant", "Accounting Clerk / Supervisor", "Others"], "post_time": "2022-01-17T02:26:00Z", "salary": {"currency": null, "max": null, "min": null, "period": "monthly", "term": null}, "salary_visible": false, "title_keywords": ["assistant accountant"], "responsibilities": ["tax", "mpf", "compliance", "reports", "payroll"], "requirements": {"degrees": ["degree holder"], "majors": ["business", "accounting"], "languages": [], "language_level": [], "hard_skills": [], "soft_skills": ["organized"], "languages_combined": []}, "experience_required": {"duration": ["1 year"], "field": ["payroll", "relevant experience", "mpf"]}}, {"job_id": "100003009054800", "location_code": "hk", "company": "Public Finance Limited", "job_title": "Audit Executive", "description": "Electrical Engineering firm in Shatin invites candidates for the following vacancy :-\n\nASSISTANT ACCOUNTANT\n\nJob Responsibilities\n- To handle full set of books and accounts\n- To prepare vouchers and cheques.\u00a0 To handle relevant accounting entry, monitoring payment schedule\n- Keep track of bank balance and cash flow forecast\n- Handle month-end closing, remittance and reports\n- Assist in preparing annual financial budget\n\n\u00a0Requirements\n\n-Holder of LCC Higher Certificate of Accounting or equivalent\n-At least 5 years relevant working experience\n-Good communication skills; fluent Cantonese and English, Mandarin is essential\n-Proficient PC skills in MS office\n\n\nWe offer attractive package, including public holidays, alternate Saturday, double pay, Bonus, 14days annual leave,etc.\u00a0to suitable candidates. Interested\u00a0candidates please send application with full resume, availability and expected salary by email\u00a0\n\nPersonal data collected will be used for recruitment purpose only.\n\n\n\n", "employment_types": ["Full Time", "Permanent"], "selling_points": [], "locations": ["Not Specified"], "categories": ["Accounting", "Accounting Clerk / Supervisor", "Audit", "Others"], "post_time": "2022-01-17T11:08:55Z", "salary": {"currency": null, "max": null, "min": null, "period": "monthly", "term": null}, "salary_visible": false, "title_keywords": ["executive"], "responsibilities": ["monitoring", "budget", "payment", "cheques", "cash flow", "schedule", "forecast", "month-end closing", "reports"], "requirements": {"degrees": ["higher certificate"], "majors": ["accounting"], "languages": ["cantonese", "english", "mandarin"], "language_level": ["fluent"], "hard_skills": ["pc skills", "lcc", "ms office"], "soft_skills": ["communication skills"], "languages_combined": [{"language": "cantonese", "language_level": ["fluent"]}, {"language": "english", "language_level": ["fluent"]}, {"language": "mandarin", "language_level": []}]}, "experience_required": {"duration": ["least 5 years"], "field": ["relevant working experience"]}}, {"job_id": "100003009054237", "location_code": "hk", "company": "SinoPac Securities (Asia) Limited", "job_title": "Assistant Audit Manager (Ref: AAM)", "description": "\n\u8077\u8cac :\n\u2022 \u9910\u5ef3\u5168\u76e4\u6703\u8a08, \u6536\u7d0d\u5e33\u76ee, \u6708\u5ea6/\u5e74\u5ea6\u6703\u8a08\u5e33\u76ee, \u6bcf\u6708\u85aa\u91d1\u53ca\u5f37\u7a4d\u91d1\u8a08\u7b97; \u7cfb\u7d71\u8cc7\u6599\u66f4\u65b0; \u4e0a\u53f8\u6307\u6d3e\u5de5\u4f5c\u7b49\n\n\u8cc7\u6b77 :\n\u2022 \u5c08\u4e0a\u6559\u80b2\uff1a\u6587\u6191/\u8b49\u66f8; 5\u5e74\u7d93\u9a57; \u826f\u597d\u7cb5\u8a9e\u512a\u5148; \u4e00\u822c\u82f1\u8a9e; \u61c2\u8b80\u5beb\u4e2d\u6587; \u61c2\u8b80\u5beb\u82f1\u6587; \u61c2QuickBooks; \u61c2\u5168\u76e4\u6703\u8a08; \u61c2\u4e2d\u6587\u6253\u5b57; Self-motivated, responsible, able to work independently, Immediate availability is preferred\n\n\u5f85\u9047 :\n\u6bcf\u6708$18,000 - $22,000, \u6709\u96d9\u7ce7, \u5e74\u504710\u5929, \u9280\u884c\u5047\u671f, \u91ab\u7642\u798f\u5229\u53ca\u5e74\u7d42\u734e\u91d1, \u661f\u671f\u4e00\u81f3\u4e94: \u4e0a\u53489\u6642\u81f3\u4e0b\u53486\u6642, \u6bcf\u9031\u5de5\u4f5c5\u5929, \u6bcf\u5929\u5de5\u4f5c 9 \u5c0f\u6642\n\n\u7533\u8acb\u9808\u77e5 :\n\u6709\u610f\u8005\u8acb\u9023\u540c\u5c65\u6b77\u8868\u6309Apply Now\u7533\u8acb \u7d66EL CONCEPTO LTD.\u3002\u5982\u8981\u7d22\u53d6\u6536\u96c6\u500b\u4eba\u8cc7\u6599\u8072\u660e, \u8acb\u8207\u96f7\u5148\u751f(Email)\u806f\u7d61\u3002\n\n", "employment_types": ["Full Time", "Permanent"], "selling_points": ["5-day work", "Degree holder", "1\u20132 year audit experience"], "locations": ["Causeway Bay"], "categories": ["Accounting", "Audit", "Others"], "post_time": "2022-01-17T08:52:50Z", "salary": {"currency": null, "max": null, "min": null, "period": "monthly", "term": null}, "salary_visible": false, "title_keywords": ["manager", "assistant"], "responsibilities": [], "requirements": {"degrees": [], "majors": [], "languages": [], "language_level": [], "hard_skills": [], "soft_skills": ["self-motivated", "work independently", "responsible"], "languages_combined": []}, "experience_required": {"duration": [], "field": []}}, {"job_id": "100003009054697", "location_code": "hk", "company": "Lane Crawford (Hong Kong) Limited", "job_title": "Accounting Officer", "description": "RESPONSIBILITIES\nTo assist in carrying out independent and objective audit function\nReview and evaluate the system of management controls and assess their adequacy and effectiveness\nDraft potential recommendations for improvements\nConduct in accordance with HKFRS, SFC regulations and internal SOPs\nREQUIREMENTS\n\nDegree holder, preferably in law, finance, accounting, statistics, computer information systems or related disciplines\n1\u20132-year audit experience, securities audited experience\nKnowledge in banking ordinance, SFC regulations & guidelines, financial services and products is preferred but not essential\nFamiliar with EXCEL advanced functions\nGood interpersonal , communication, analytical and writing skills\nSelf-motivated and able to work both independently and as a team member\nGood command of written English and Chinese; Chinese typing skills and proficiency in Mandarin are required\n\n\u00a0A competitive remuneration package will be offered. Please send your detailed resume, including present and expected salary as well as availability date, to Human Resources Department, SinoPac Securities (Asia) Limited, 7/F., Lee Garden Three, 1 Sunning Road, Causeway Bay, Hong Kong or\u00a0 \u00a0by clicking \"Apply Now\".\n\nAll personal data collected will be used for recruitment purpose only and will be kept strictly confidential. Only short-listed candidates will be notified.", "employment_types": ["Permanent"], "selling_points": ["Accounts Payable experience in Retail", "Strong communication and collaboration", "immediately available is preferred"], "locations": ["Southern Area"], "categories": ["Accounting", "Accounting Clerk / Supervisor", "Financial Analyst", "Others"], "post_time": "2022-01-17T10:37:23Z", "salary": {"currency": null, "max": null, "min": null, "period": null, "term": null}, "salary_visible": false, "title_keywords": ["accounting officer"], "responsibilities": ["regulations", "management", "review", "audit", "evaluate", "sops"], "requirements": {"degrees": ["degree holder"], "majors": ["law", "finance", "statistics", "related disciplines", "accounting"], "languages": ["english", "chinese", "mandarin"], "language_level": ["proficiency", "good command"], "hard_skills": ["excel", "typing", "writing skills"], "soft_skills": ["self-motivated", "independently", "advanced", "writing skills", "communication", "team member", "interpersonal", "detailed"], "languages_combined": [{"language": "english", "language_level": ["good command"]}, {"language": "chinese", "language_level": ["proficiency", "good command"]}, {"language": "mandarin", "language_level": ["proficiency"]}]}, "experience_required": {"duration": [], "field": ["audit experience", "securities"]}}, {"job_id": "100003009049730", "location_code": "hk", "company": "Vicki Lam & Co.", "job_title": "\u521d\u7d1a\u6838\u6578\u54e1", "description": "Job Purpose:\u00a0\n\n\u201cTo coordinate and perform administrative support duties to the Enterprise and Product team.\u201d\n\nKey Accountabilities:\n\nIn addition to following Lane Crawford\u2019s policies and procedures, key accountabilities include, but are not limited to:\n\nAccount Management (30%)\n\nFunction as key contact to Product team seeking to onboard a new supplier\nResponsible for vendor account creation through supplier portal and oracle systems\nFollow through with vendors on required documentations including trademark registration\nCoordinate with the Legal team to walkthrough and solicit suppliers to accept portal for Essential terms\n\nCommunication (40%)\n\nLead as the central point of contact for suppliers in communicating policies and guidelines on :\nLegal \u00a0\u00a0\u00a0\u00a0\u00a0\u00a0\u00a0\u00a0\u00a0\u00a0\u00a0\u00a0\u00a0\u00a0\u00a0\u00a0\u00a0 \u00a0\u00a0\u00a0\u00a0\u00a0\u00a0\u00a0\u00a0\u00a0\u00a0\u00a0\u00a0\u00a0 (Essential business terms)\nLogistics \u00a0\u00a0\u00a0\u00a0\u00a0\u00a0\u00a0\u00a0\u00a0\u00a0 \u00a0\u00a0\u00a0\u00a0\u00a0\u00a0\u00a0\u00a0\u00a0\u00a0\u00a0\u00a0\u00a0 (Shipping reference and Invoice guide, China Customs)\nAccount Payable\u00a0\u00a0\u00a0\u00a0\u00a0\u00a0\u00a0\u00a0\u00a0\u00a0 (Invoice and payment procedures)\nSupport in answering enquiries from suppliers\nCoordinate with other teams to ensure timely and quality responses to enquiries\nWork with Account Payable to manage invoicing, timely payments, resolve discrepancies and issues,\u00a0 correspond with vendors and respond to payment-related inquiries\n\n\u00a0Process Management\n\nDevelop procedures, guidelines and tools to achieve efficiency\nPlan and develop special project and system enhancement to support service quality standards\nEnsure compliance with Policies and Procedures\n\nRequirements:\n\n\n*Candidates with immediate availability is required*\nAt least 3 years of Accounts Payable working experience in Retail industry\nGood understanding of Trade invoices payment process\nStrong communication skills as need to deal with buying team and multiple vendors\nGood coordination skills and team player\nFamiliar with Oracle Accounting System is not essential but a plus\nBachelor's Degree or any equivalent qualification in Finance or Accounting\n", "employment_types": ["Full Time"], "selling_points": [], "locations": ["Wan Chai"], "categories": ["Accounting", "Others"], "post_time": "2022-01-14T09:10:38Z", "salary": {"currency": null, "max": null, "min": null, "period": "monthly", "term": null}, "salary_visible": false, "title_keywords": [], "responsibilities": ["shipping", "quality", "communication", "payment", "plan", "invoices", "teams", "develop", "logistics", "management", "administrative support", "invoice", "procedures", "coordinate with", "contact", "guidelines", "policies", "systems", "ensure compliance", "coordinate", "invoicing", "payments", "payment process", "coordination", "accounts payable"], "requirements": {"degrees": ["degree", "bachelor"], "majors": ["finance", "accounting"], "languages": [], "language_level": [], "hard_skills": ["plus", "vendor", "accounting system", "documentations", "oracle"], "soft_skills": ["communication skills", "coordination skills", "responsible", "timely", "communication", "team player"], "languages_combined": []}, "experience_required": {"duration": ["at least 3 years"], "field": ["retail industry"]}}, {"job_id": "100003009052083", "location_code": "hk", "company": "Simatelex Manufactory Co., Ltd.", "job_title": "Assistant Accountant (Shenzhen Stationed)", "description": "\n\u8077\u8cac :\u8ca0\u8cac\u516c\u53f8\u7c3f\u8a18\uff0c\u5be9\u8a08\u6838\u6578\u53ca\u7de8\u5236\u8ca1\u52d9\u5831\u8868\uff0c\u8655\u7406\u7a05\u52d9\u4e8b\u9805\n\n\u8cc7\u6b77 :\u5c08\u4e0a\u6559\u80b2\uff1a\u6587\u6191/\u8b49\u66f8; \u4e00\u822c\u7cb5\u8a9e; \u4e00\u822c\u666e\u901a\u8a71; \u4e00\u822c\u82f1\u8a9e; \u61c2\u8b80\u5beb\u4e2d\u6587; \u61c2\u8b80\u5beb\u82f1\u6587; \u61c2MYOB; \u6301\u6709LCC\u4e2d\u7d1a\u8b49\u66f8; \u5177\u6709\u4e00\u822c\u6703\u8a08\u77e5\u8b58\n\n\u5f85\u9047 :\u6bcf\u6708$12,000 - $16,000, \u6709\u96d9\u7ce7, \u5e74\u504710\u5929 \u53ca\u6bcf\u6708\u5176\u4ed6\u6d25\u8cbc/\u798f\u5229$1000, \u661f\u671f\u4e00\u81f3\u4e94: \u4e0a\u53489\u6642\u81f3\u4e0b\u53486\u6642, \u6bcf\u9031\u5de5\u4f5c5\u5929, \u6bcf\u5929\u5de5\u4f5c 8 \u5c0f\u6642\n\n\u7533\u8acb\u9808\u77e5 :\u6c42\u8077\u8005\u53ef\u96fb\u90f5(Apply Now)\u5c65\u6b77\u8868\u7d66\u6797\u6dd1\u6e05\u6703\u8a08\u5e2b\u4e8b\u52d9\u6240\u3002\u5982\u8981\u7d22\u53d6\u6536\u96c6\u500b\u4eba\u8cc7\u6599\u8072\u660e, \u8acb\u8207\u9ece\u5c0f\u59d0(Email)\u806f\u7d61\u3002\n\n", "employment_types": ["Full Time", "Permanent"], "selling_points": [], "locations": ["Others - China"], "categories": ["Accounting", "Accounting Clerk / Supervisor", "Others"], "post_time": "2022-01-17T02:03:33Z", "salary": {"currency": null, "max": null, "min": null, "period": null, "term": null}, "salary_visible": false, "title_keywords": ["assistant accountant"], "responsibilities": [], "requirements": {"degrees": [], "majors": [], "languages": [], "language_level": [], "hard_skills": [], "soft_skills": [], "languages_combined": []}, "experience_required": {"duration": [], "field": []}}, {"job_id": "100003009053979", "location_code": "hk", "company": "Compass Offices", "job_title": "Junior Assistant Accountant", "description": "Responsible for handling full set of accounts, reconciliations, taxation and ad hoc assignments of our PRC plant.\n\nDiploma or above in Accounting or related disciplines\nAt least 2 years in manufacturing industry\nKnowledge in computerized accounting system and PRC taxation is an advantage\nGood command of English & Chinese\nMature, independent and with good analytical mind\nCandidates with less experience or fresh graduates will be considered as Accounting\u00a0Assistant\u00a0(Shenzhen Stationed)\n\nWe offer attractive remuneration package including 5-day work, bank holidays, group medical insurance etc to the right candidates. Interested parties please send your full resume including expected salary and date available to\u00a0Human Resources Department by clicking \"Apply Now\" button.\n\nFor more details, please visit our web-site at\u00a0www.simatelex.com.hk", "employment_types": ["Full Time"], "selling_points": ["Top leading Serviced Office provider in HK", "Good exposure for gaining in-house experience", "Dynamic working environment"], "locations": ["Sheung Wan"], "categories": ["Accounting", "Accounting Clerk / Supervisor", "Others", "Banking / Finance", "Corporate Finance"], "post_time": "2022-01-17T07:54:16Z", "salary": {"currency": null, "max": null, "min": null, "period": "monthly", "term": null}, "salary_visible": false, "title_keywords": ["assistant accountant", "junior"], "responsibilities": ["reconciliations", "full set of accounts", "ad hoc assignments", "taxation"], "requirements": {"degrees": ["diploma or above"], "majors": ["related disciplines", "accounting"], "languages": ["english", "chinese"], "language_level": ["good command"], "hard_skills": ["accounting system"], "soft_skills": ["mature", "analytical mind", "independent", "responsible"], "languages_combined": [{"language": "english", "language_level": ["good command"]}, {"language": "chinese", "language_level": ["good command"]}]}, "experience_required": {"duration": [], "field": ["accounting"]}}, {"job_id": "100003009054609", "location_code": "hk", "company": "A.S. Watson Retail (HK) Limited", "job_title": "Assistant Accountant - Financial Accounting (Group Finance)", "description": "Responsibilities:\n\nProcess invoices and prepare payments\nRecords financial transactions\nPerform filing and general administrative tasks\nReconciliations of the bank accounts and general ledger accounts\nLiaise with internal/external parties for enquiries\n\nRequirements:\n\nBachelor degree holder in Accountancy/Finance/Banking or related disciplines\nMinimum 1 year of relevant work experience is required\nProficiency in Microsoft offices (Excel, Word and Outlook)\nIndependent, well-organized, self-motivated with good interpersonal skills, able to work well under pressure and with minimum supervision\u00a0\nKnowledge in MS Dynamics AX is an advantage\nPresentable with good command of written and spoken English and Chinese\n\nPlease submit your resume with current and expected salary. All applications will be treated strictly confidential for recruitment purpose only.", "employment_types": ["Full Time", "Permanent"], "selling_points": ["Handling full set of books and month end closing", "Perform analytical review on cost centre", "Handle intercompany transactions"], "locations": ["Shatin Area"], "categories": ["Accounting", "Accountant", "Accounting Clerk / Supervisor", "Others"], "post_time": "2022-01-17T10:14:03Z", "salary": {"currency": null, "max": null, "min": null, "period": "monthly", "term": null}, "salary_visible": false, "title_keywords": ["accounting", "assistant accountant"], "responsibilities": ["invoices", "general ledger", "external parties", "transactions", "reconciliations", "liaise with", "payments", "administrative tasks"], "requirements": {"degrees": ["bachelor degree holder"], "majors": ["related disciplines", "finance", "accountancy"], "languages": ["english", "chinese"], "language_level": ["good command"], "hard_skills": ["excel", "outlook", "word"], "soft_skills": ["self-motivated", "under pressure", "independent", "well-organized", "presentable", "interpersonal skills"], "languages_combined": [{"language": "english", "language_level": ["good command"]}, {"language": "chinese", "language_level": ["good command"]}]}, "experience_required": {"duration": ["minimum 1 year"], "field": []}}, {"job_id": "100003009047651", "location_code": "hk", "company": "Moore Associates Limited", "job_title": "Audit Manager", "description": "Come and join a Winning Team\n\nWe are Awesome!\n\nWhy Should You Join Us?\n\nAt ASW, we believe in our people, in teamwork and the importance of your personal growth.\u00a0If you are looking for the opportunity to join our award-winning international family with 15,000+ stores across 25 markets in Asia and Europe, the ASW family welcomes you\u2026\u00a0 #BePartofMORE\n\nYou can enjoy:\n\nCompetitive compensation and benefits!\nComprehensive Medical and Life insurance coverage, including your spouse and children!\nFive-day work, plus casual wear every Friday, TGIF!\nProfessional training and career advancement opportunities!\nAttractive ACCA and CPA Australia Recognized Employer Partnership for F&A talents!\nExclusive company pension schemes for our people!\nMarriage, Maternity and Paternity Leave!\nConvenient office location, less than 5 min. walk from MTR!\nExclusive shopping discount!\nContemporary workplace, free drinks and chill out areas!\nWell-equipped Gym inside our office building!\nFitness and interest class packages!\nOnsite Clinic and Lactation Room!\nFree round-trip lunchtime shuttle bus services to Shatin!\nExclusive Bazaar Sales for our people only!\n\n\u00a0Role Purpose:\n\nThe Assistant Accountant will be responsible for\u00a0handling full set of books and month end closing for holding companies, handle intercompany transactions, overall review of and other financial reports.\n\nA typical day in this Role:\u00a0\n\nHandle full set of accounts and month end closing for holding companies\nOversee monthly results and perform analytical review of corporate cost centers\nHandle intercompany transactions and reconciliation\nHandle accounting for CAPEX\nPrepare financial and management reports, cash flow and ad hoc assignment\n\n\u00a0\u00a0This job is a good fit for You if:\n\nYou are keen to join retail industry\u00a0\nYou have high level of ownership on your assigned scope of work\nYou are motivated and enjoy teamwork.\n\n\u00a0\u00a0What we look for:\n\nHigher Diploma or above in Accountancy or Finance related disciplines\nMinimum 3 years of accounting experience preferably from Retail and FMCG background\nHigh proficiency in computer applications, Oracle accounting system preferred but not a must\nSelf-motivated, detailed-oriented, able to work independently and cope with deadlines\nGood command of both spoken and written in English and Chinese\n\nWhat is holding you back?\u00a0\n\nDon\u2019t miss out on this great chance to shape Your life!\u00a0\n\nApply now!\n\nInterested parties please e-mail your full resume in WORD FORMAT with expected salary to our company email (shown in our Company Profile).\n\n\nWe are an equal opportunity employer and welcome applications from all qualified candidates. The information provided will be treated in strict confidence and be used only for consideration of your application for relevant / similar posts within the A.S. Watson Group.\n\n\nApplicants not hearing from us within 6 weeks from the date of advertisement may consider their applications unsuccessful. All personal data of unsuccessful applicants will be destroyed within 12 months from the date of application.\u00a0", "employment_types": ["Full Time", "Permanent"], "selling_points": ["Audit assignments from a variety of industries", "Take a leader role in particular projects", "At least 6 years relevant experience"], "locations": ["Tsim Sha Tsui"], "categories": ["Accounting", "Audit", "Others"], "post_time": "2022-01-15T03:49:47Z", "salary": {"currency": null, "max": null, "min": null, "period": "monthly", "term": null}, "salary_visible": false, "title_keywords": ["manager"], "responsibilities": [], "requirements": {"degrees": [], "majors": [], "languages": [], "language_level": [], "hard_skills": [], "soft_skills": ["teamwork"], "languages_combined": []}, "experience_required": {"duration": [], "field": []}}, {"job_id": "100003009050391", "location_code": "hk", "company": "SGS Hong Kong Limited", "job_title": "Accounts Supervisor", "description": "Responsibilities:\n\nWork on audit assignments for clients from a variety of industries, covering Hong Kong and China, especially listed companies\nInvolve in projects such as due diligence and IPO\u00a0\nTake a leader role in particular projects\n\nRequirements: \u00a0\n\nDegree holder majoring in Accountancy / Finance\nAt least 6 years relevant experience, preferably gained with another international accounting and consulting association\nGood written and spoken English and Chinese\nGood communication / interpersonal skills\nHigh level of independence and strong motivation\nStrong technical ability and keen to develop a career in the audit profession\n\nCompetitive package will be offered to the right candidate(s), including 5 day work week, paid examination & study leave, birthday leave & medical insurance coverage. Interested parties please send full resume with working experience, academic and professional qualifications, including present & expected salary by clicking the \"Apply Now\" button.\u00a0 Personal data collected will be used for recruitment purposes only.\n\nSimply click the \u201cApply Now\u201d button.\n\nPlease visit our website at\u00a0www.moore.hk\u00a0to know more about us.", "employment_types": ["Full Time", "Permanent"], "selling_points": ["Yuen Long Area (Shuttle Bus Provided)", "Full set of accounts", "Monthly accrual and account reconciliation"], "locations": ["Yuen Long"], "categories": ["Accounting", "Accounting Clerk / Supervisor", "Others"], "post_time": "2022-01-15T03:51:05Z", "salary": {"currency": null, "max": null, "min": null, "period": "monthly", "term": null}, "salary_visible": false, "title_keywords": ["accounts supervisor"], "responsibilities": ["due diligence", "audit"], "requirements": {"degrees": ["degree holder"], "majors": ["finance", "accountancy"], "languages": ["english", "chinese"], "language_level": ["good"], "hard_skills": [], "soft_skills": ["communication", "keen", "interpersonal skills"], "languages_combined": [{"language": "english", "language_level": ["good"]}, {"language": "chinese", "language_level": ["good"]}]}, "experience_required": {"duration": ["at least 6 years"], "field": ["accounting", "relevant experience", "consulting"]}}, {"job_id": "100003009051628", "location_code": "hk", "company": "China Telecom Global Limited", "job_title": "Senior Finance and Accounting Officer", "description": "To cope with our continuous business growth, we are looking for passionate and competent candidates to join us.\n\nJob Responsibilities\n\nHandle full set of accounts, month-end closing and daily accounting entries.\nPerform general accounting functions such as voucher and cheque preparation, cashflow management, bank account reconciliation, accounts receivables and payables.\nPrepare financial management reports, analysis, budget and forecast.\nLiaise with external auditors, bankers and vendors.\nParticipate in ad hoc projects and tasks as assigned by Department Head.\n\n\u00a0Job Requirements\n\nDegree holder or above in Accounting or Finance or equivalent.\nMinimum 5 years\u2019 relevant experience in consolidation and financial accounting, preferably in HK Listed Company.\nMember of HKICPA / ACCA or equivalent professional accounting bodies.\nGood knowledge in accounting standards and taxation.\nSelf-motivated, detail-minded and able to work under pressure.\nStrong analytical and communication skills.\nGood command in English, Cantonese and Mandarin.\nCandidate with PRC / audit experience is preferred.\nPRC travel may be required.\nCandidate with more experience will be considered as Senior Accountant.\u00a0\n\nWe offer a\u00a05-day work week\u00a0with\u00a0attractive remuneration package to the right candidate. Interested parties\u00a0please apply with full resume, contact number, date available and expected salary by\u00a0clicking \"Apply Now\".\u00a0\n\nTo learn more about us, please visit our website\u00a0Liu Chong Hing Investment Ltd.\n\u00a0\nPersonal data provided by job applicants will be used for recruitment purpose only.", "employment_types": ["Full Time", "Permanent"], "selling_points": ["Exp. of accounting & financial reporting", "Exp. in telecom industry will be a plus", "Competitive salary package"], "locations": ["Wan Chai"], "categories": ["Accounting", "Accountant", "Others"], "post_time": "2022-01-16T15:32:24Z", "salary": {"currency": null, "max": null, "min": null, "period": "monthly", "term": null}, "salary_visible": false, "title_keywords": ["accounting officer"], "responsibilities": ["management", "analysis", "full set of accounts", "budget", "management reports", "month-end closing", "ad hoc projects", "forecast", "liaise with", "daily accounting", "external auditors"], "requirements": {"degrees": ["degree holder"], "majors": ["finance", "accounting"], "languages": ["cantonese", "english", "mandarin"], "language_level": ["good command"], "hard_skills": ["acca", "hkicpa"], "soft_skills": ["detail-minded", "communication skills", "self-motivated", "work under pressure"], "languages_combined": [{"language": "cantonese", "language_level": ["good command"]}, {"language": "english", "language_level": ["good command"]}, {"language": "mandarin", "language_level": ["good command"]}]}, "experience_required": {"duration": ["minimum 5 years"], "field": ["consolidation", "senior accountant", "relevant experience", "audit experience", "accounting", "financial"]}}, {"job_id": "100003009050391", "location_code": "hk", "company": "SGS Hong Kong Limited", "job_title": "Accounts Supervisor", "description": "\u00a0Key Responsibilities:\n\nHandle full set of accounts independently\nPrepare monthly accrual and account reconciliation\nPerform documents checking, data entries, payments, filing and bank reconciliation\nResponsible for preparation of financial and management report (e.g. AR/AP management reports, etc.)\nLiaise with Group companies to fulfil daily treasury operation and compliance work\nHandle ad hoc duties as assigned\n\n\u00a0Requirements/Qualifications\n\n\nLCCI or Higher Diploma or above in Accounting / Finance or equivalent qualification\nMinimum 3 years of accounting experience\nProficiency in MS Office and Chinese Word Processing\nFamiliar with Oracle Application is preferred\nMature, proactive, independent, detail-minded and strong sense of responsibility\nGood command of both written and spoken English and Chinese\nWilling to work under pressure, and able to meet tight deadline\nImmediate available is preferred\n\nInterested parties please send your full resume with\u00a0expected salary and date available by clicking \"Apply Now\".\n\n(Data received will be kept confidential and used for processing application only.)", "employment_types": ["Full Time", "Permanent"], "selling_points": ["Yuen Long Area (Shuttle Bus Provided)", "Full set of accounts", "Monthly accrual and account reconciliation"], "locations": ["Yuen Long"], "categories": ["Accounting", "Accounting Clerk / Supervisor", "Others"], "post_time": "2022-01-15T03:51:05Z", "salary": {"currency": null, "max": null, "min": null, "period": "monthly", "term": null}, "salary_visible": false, "title_keywords": ["accounts supervisor"], "responsibilities": ["ap", "ad hoc duties", "ar", "data", "full set of accounts", "compliance", "checking", "bank reconciliation", "management reports", "payments", "accrual", "liaise with", "management report"], "requirements": {"degrees": ["higher diploma or above"], "majors": ["finance", "accounting"], "languages": ["english", "chinese"], "language_level": ["proficiency", "good command"], "hard_skills": ["oracle", "chinese word processing", "ms office"], "soft_skills": ["detail-minded", "independent", "sense of responsibility", "mature", "meet tight deadline", "proactive", "work under pressure"], "languages_combined": [{"language": "english", "language_level": ["good command"]}, {"language": "chinese", "language_level": ["proficiency", "good command"]}]}, "experience_required": {"duration": ["minimum 3 years"], "field": ["accounting experience"]}}, {"job_id": "100003009051628", "location_code": "hk", "company": "China Telecom Global Limited", "job_title": "Senior Finance and Accounting Officer", "description": "Key Responsibilities\uff1a\n\nMaintain the strong knowledge of the latest accounting regulation development and corporate reporting requirements\nAssist the processing in the preparation of month end journal entries and produce reliable and auditable information for disclosure to external auditors and the parent company\nRegularly provide internal training, issue policy guidance and coordinate with regionals team among various jurisdictions\nParticipate in ad hoc corporate projects\n\nJob Requirements\uff1a\n\nDegree or above in Accounting, preferable HKICPA, ACCA, CICPA member or equivalent\nOver 3\u00a0years of relevant accounting experience,\u00a0 with relevant Chinese-funded overseas headquarter enterprise or auditing background in external audit firms is preferred\nWork experience\u00a0in telecom industry will be a plus\nFamiliar with Chinese Accounting Standards and International Accounting Standards will be a plus\nExcellent command of both written and spoken English and Chinese\nCandidate with much experience will be considered as senior position\u00a0\n\nWe offer 5 days work, competitive salary package and attractive career development opportunities to the right candidate.\u00a0\n\nInterested parties please email your full resume with your current & expected salary to us.\n\nApplicants not invited for interview within 3 months may assume their applications unsuccessful.\u00a0\n\nIf you are interested in other job opportunities, please check with below career website.\n\nPersonal data collected would be used for recruitment purpose only.\u00a0", "employment_types": ["Full Time", "Permanent"], "selling_points": ["Exp. of accounting & financial reporting", "Exp. in telecom industry will be a plus", "Competitive salary package"], "locations": ["Wan Chai"], "categories": ["Accounting", "Accountant", "Others"], "post_time": "2022-01-16T15:32:24Z", "salary": {"currency": null, "max": null, "min": null, "period": "monthly", "term": null}, "salary_visible": false, "title_keywords": ["accounting officer"], "responsibilities": ["guidance", "reporting", "ad hoc", "coordinate with", "maintain", "journal entries", "external auditors"], "requirements": {"degrees": ["degree or above"], "majors": ["accounting"], "languages": ["english", "chinese"], "language_level": ["excellent"], "hard_skills": ["acca", "plus", "hkicpa"], "soft_skills": [], "languages_combined": [{"language": "english", "language_level": ["excellent"]}, {"language": "chinese", "language_level": ["excellent"]}]}, "experience_required": {"duration": ["3 years"], "field": ["accounting experience", "audit"]}}, {"job_id": "100003009052585", "location_code": "hk", "company": "Forsters & Company", "job_title": "Accounting Officer", "description": "Requirements\n\nUniversity graduate of Accounting Studies\n2-3 years relevant experience in daily accounting support\nExperience in AP, AR, preferably in multinational corporations\nPrevious experience in handling vendor payment is preferable\nDetail-minded, adaptable, energetic and sense of responsibilities\nWell-versed in using Microsoft Office and accounting software\nGood command of English and fair in spoken Mandarin\nImmediate available is highly preferred\n\nResponsibilities\n\nPerform general accounting duties including payable and receivable\nHandle monthly bank reconciliation and arrange vendor payment\nResponsible for intercompany transactions and preparing monthly reports\nMaintain accurate accounting system and assist in month-end closing\n\nWe offer attractive remuneration package and promising career prospect to the right candidates. Interested parties please send full resume with expected/last salary and date of available by clicking \u2018Apply Now\u2019", "employment_types": ["Full Time", "Permanent"], "selling_points": [], "locations": ["Not Specified"], "categories": ["Accounting", "Accounting Clerk / Supervisor", "Others"], "post_time": "2022-01-17T06:15:51Z", "salary": {"currency": null, "max": null, "min": null, "period": "monthly", "term": null}, "salary_visible": false, "title_keywords": ["accounting officer"], "responsibilities": ["monthly reports", "bank reconciliation", "transactions", "payment", "maintain", "general accounting duties", "month-end closing"], "requirements": {"degrees": ["university graduate"], "majors": ["accounting"], "languages": ["english", "mandarin"], "language_level": ["good command"], "hard_skills": ["ap", "ar", "microsoft office", "accounting software", "vendor"], "soft_skills": ["detail-minded", "energetic", "adaptable", "sense of responsibilities"], "languages_combined": [{"language": "english", "language_level": ["good command"]}, {"language": "mandarin", "language_level": ["good command"]}]}, "experience_required": {"duration": ["2-3 years"], "field": ["accounting", "relevant experience"]}}, {"job_id": "100003009051526", "location_code": "hk", "company": "Ma Belle Jewellery Co Ltd", "job_title": "Assistant Accountant/ Accountant", "description": "Responsibilities:\n\nReconcile daily sales transactions\nHandle daily Accounts Payable/ Receivable operations\nPrepare daily sales reports & monthly stock take\nHelp to prepare month-end reports\nHandle accounting data entry and maintain good filing system\n\nRequirements:\n\nDiploma or above and at least LCC 2nd level\n3 years or above solid experience in accounting\nKnowledge in Flex System is an added advantage\nGood team player, Self-motivated, independent, well organized and good interpersonal skills\nGood command of English and Chinese\nImmediate available or short notice is preferred\n\nRecent graduates will be considered\n\nAttractive remuneration package will be offered to the right candidate. Please email full resume with current and expected salary to us\n\nPersonal data collected will be used for recruitment purposes only and will be treated in strict confidence.\u00a0 Applicants not invited for interview within 16 weeks may consider their applications unsuccessful and all information submitted will be destroyed.", "employment_types": ["Full Time", "Permanent"], "selling_points": ["Reconcile daily sales transactions, stock take", "Handle daily Accounts Payable/Receivable operation", "Prepare daily sales reports & month-end reports"], "locations": ["Tin Hau"], "categories": ["Accounting", "Accounting Clerk / Supervisor", "Treasurer", "Others"], "post_time": "2022-01-16T08:05:51Z", "salary": {"currency": null, "max": null, "min": null, "period": null, "term": null}, "salary_visible": false, "title_keywords": ["accountant", "assistant accountant"], "responsibilities": ["sales reports", "data entry", "operations", "month-end", "transactions", "stock take", "maintain", "reports", "accounts payable"], "requirements": {"degrees": ["diploma or above"], "majors": [], "languages": ["english", "chinese"], "language_level": ["good command"], "hard_skills": ["lcc", "flex system"], "soft_skills": ["good team player", "self-motivated", "independent", "confidence", "well organized", "interpersonal skills"], "languages_combined": [{"language": "english", "language_level": ["good command"]}, {"language": "chinese", "language_level": ["good command"]}]}, "experience_required": {"duration": ["3 years"], "field": ["accounting"]}}, {"job_id": "100003009053192", "location_code": "hk", "company": "The Lok Sin Tong Benevolent Society, Kowloon", "job_title": "Accounting Officer \u6703\u8a08\u4e3b\u4efb", "description": "Job Duty\uff1a\u00a0\nHandle full set of accounts and month end closing\nPrepare monthly statement and breakdown\nMaintain good accounting and operation control\nMonitor other staff\u00a0accounting duties\nAssist in annual audit\n\nRequirements:\n\nBachelor degree holder in Accounting\n3 years\u2019 relevant working experience\nProficient in MS applications both in English and Chinese (including Excel & Word)\nExperienced in accounting software such as Flex System\nAuditing experience will be an advantage\nHave initiative, detail-minded, responsible, integrity and good interpersonal skills\n\nApplications with full resume and expected salary should be\u00a0email to\u00a0us.\n\n(All applications will be treated in strict confidence and used solely for the purpose of recruitment)", "employment_types": ["Full Time"], "selling_points": [], "locations": ["Kowloon City"], "categories": ["Accounting", "Accountant", "Accounting Clerk / Supervisor", "Others"], "post_time": "2022-01-17T06:22:45Z", "salary": {"currency": null, "max": null, "min": null, "period": "monthly", "term": null}, "salary_visible": false, "title_keywords": ["accounting officer"], "responsibilities": ["month end closing", "control", "software", "annual audit", "full set of accounts", "monitor", "maintain", "recruitment", "accounting duties", "auditing"], "requirements": {"degrees": ["bachelor degree holder"], "majors": ["accounting"], "languages": ["english", "chinese"], "language_level": ["proficient"], "hard_skills": ["excel", "ms applications", "accounting software", "word", "flex system"], "soft_skills": ["detail-minded", "confidence", "responsible", "integrity", "interpersonal skills", "initiative"], "languages_combined": [{"language": "english", "language_level": ["proficient"]}, {"language": "chinese", "language_level": ["proficient"]}]}, "experience_required": {"duration": ["3 years"], "field": ["relevant working experience"]}}, {"job_id": "100003009051627", "location_code": "hk", "company": "Harvi Morrison Executive Search", "job_title": "Accountant / Assistant Accountant", "description": "My client is a\u00a0textile company and they are looking for an accountant to join their team.\n\nResponsibilities:\n\nAssistant financial manager for daily routine accounting duties\u00a0\nHandling full set of\u00a0account\nData entry to maintain accounting/inventory journals, ledgers and other records with\u00a0ERP system\nComplete and process sales invoices and reports\nHandling AR & AP\nPrepare bank reconciliation/receipts, reporting and balancing\nAssist in weekly wages, payroll, petty cash/expenses claim\nYear-end audit/taxation preparation\n\u00a0Assist in general administration duties if necessary\n\nRequirements:\n\nHigher diploma or above in accounting with LCCI higher certificate\nGood command in spoken and written of English and Chinese\nProactive, well organised, detail-minded, independence, hardworking, self-motivated\nExperience in payroll and balance sheet accounts has an advantage\nKnowledge and experience in handling China accounting is an advantage\nMicrosoft Dynamics NAV\u00a0operate skills\u00a0is highly preferred\nImmediate availability is highly preferred\nTo apply, please send your full resume and salary expectation to info @ harvimorrison.com or click \u2019\u2019APPLY NOW\". For further enquiries, please call (852)2907 2628. All information provided will be handled confidentially and be used for recruitment purpose only.\n", "employment_types": ["Full Time", "Permanent"], "selling_points": ["Minimum 4 years related accounting experience", "Good communication & interpersonal skill", "Good command of English & Chinese"], "locations": ["Central & Western Area"], "categories": ["Accounting", "Accountant", "Accounting Clerk / Supervisor", "Others"], "post_time": "2022-01-17T01:30:39Z", "salary": {"currency": null, "max": null, "min": null, "period": "monthly", "term": null}, "salary_visible": false, "title_keywords": ["accountant", "assistant accountant"], "responsibilities": ["ap", "reporting", "year-end", "taxation", "invoices", "ar", "data entry", "receipts", "inventory", "expenses", "bank reconciliation", "audit", "maintain", "reports", "accounting duties", "payroll", "administration"], "requirements": {"degrees": ["higher diploma or above", "higher certificate"], "majors": ["accounting"], "languages": ["english", "chinese"], "language_level": ["good command"], "hard_skills": [], "soft_skills": ["detail-minded", "self-motivated", "organised", "proactive", "hardworking"], "languages_combined": [{"language": "english", "language_level": ["good command"]}, {"language": "chinese", "language_level": ["good command"]}]}, "experience_required": {"duration": [], "field": ["payroll", "accounting"]}}, {"job_id": "100003009050676", "location_code": "hk", "company": "Citybase Property Management Limited", "job_title": "Accounting Officer / Assistant Accounting Officer", "description": "Job Description\n\nPrepare daily voucher\nPrepare monthly management financial statement, reports and analysis\nPrepare schedules and reconciliations and follow up outstanding items\n\n\u00a0Job Requirement\n\nDiploma holder in Accounting or above\n3-5 years working experience in accounting or auditing\nAble to handle full set of accounts\nWell-organized, responsible, detail-minded, self-motivated and hardworking\nProficiency in MS office and computerized systems is a must\nExperience in property management industry is an advantage\nImmediate available is preferable\nWorking location:\u00a0 Tin Shui Wai / Tai Kok Tsui\nWe will offer attractive compensation package to the right candidate. Please send application enclosing resume stating career and salary history, expected salary and date of availability to HR Manager, Citybase Property Management Limited, Unit No.1, 6/F, Hampton Loft, 11 Hoi Fan Road, Tai Kok Tsui, Kowloon by fax at 2717 4717 or by clicking ''Apply Now'' (in Word format). Please quote the reference of the position you apply for in all correspondences.\nWe are an equal opportunity employer and welcome applications from all qualified candidates. Personal data collected will be treated in strictest confidence and handled confidentially by authorized personnel for recruitment-related purposes within the Group. Applicants not hearing from us within six weeks from the date of advertisement may consider their applications unsuccessful.", "employment_types": ["Full Time", "Permanent"], "selling_points": ["Diploma holder", "3-5 years experience in accounting or auditing", "Strong analytical thinking"], "locations": ["Not Specified"], "categories": ["Accounting", "Accounting Clerk / Supervisor", "Others"], "post_time": "2022-01-14T11:10:16Z", "salary": {"currency": null, "max": null, "min": null, "period": "monthly", "term": null}, "salary_visible": false, "title_keywords": ["assistant accounting officer", "accounting officer"], "responsibilities": ["management", "analysis", "reconciliations", "reports", "financial statement", "prepare schedules"], "requirements": {"degrees": ["diploma holder"], "majors": ["accounting"], "languages": [], "language_level": [], "hard_skills": ["no", "word", "ms office"], "soft_skills": ["detail-minded", "self-motivated", "confidence", "responsible", "well-organized", "hardworking"], "languages_combined": []}, "experience_required": {"duration": ["3-5 years"], "field": ["management", "accounting"]}}, {"job_id": "100003009052264", "location_code": "hk", "company": "China Mobile International Limited", "job_title": "Accountant, Revenue & Treasury (6-month contract)", "description": "Job Responsibilities:\n\nPerform revenue & COS booking\nReview invoices and vouchers\nPerform month end closing by handling ERP system\nPerform analysis on revenue & COS and review for performance of each business/ product lines\nPerform the comparison analysis of actual vs provision\nOrganize quarterly reconciliation of related party transactions\nSupport financial reporting team for preparing interim and annual financial report\nAssist in driving new system set up and current system improvement\nAssist in ad hoc tasks\n\nJob Requirements:\n\nDegree holder in Accounting, Finance or related disciplines\nQualified Accountant under ACCA/HKICPA\nAt least 3 years relevant treasury management experience, preferably from sizeable multinational corporations or financial institutions\nSolid experience in cash management preferred\nProficiency in MS Excel, Word and PowerPoint. Experience in using Oracle ERP is a plus\nPositive, self-motivated, good analytical skills and communication skills\nGood interpersonal skills\nGood command of spoken and written Chinese and English, proficiency in Putonghua is a MUST\nCandidates with less experience would also be considered\n\nInterested parties please send your full resume with current & expected salary\u00a0by clicking \"Apply Now\".\n\nAll personal data provided will be used for consideration of your job application only.\n\n%MCEPASTEBIN%", "employment_types": ["Full Time", "Temporary"], "selling_points": ["Perform revenue & COS booking & analysis", "Review invoices and vouchers", "Perform Month end closing by handling ERP system"], "locations": ["Kwai Hing"], "categories": ["Accounting", "Accountant", "Accounting Clerk / Supervisor", "Others"], "post_time": "2022-01-17T02:36:30Z", "salary": {"currency": null, "max": null, "min": null, "period": "monthly", "term": null}, "salary_visible": false, "title_keywords": ["accountant"], "responsibilities": ["month end closing", "invoices", "analysis", "review", "ad hoc tasks", "transactions", "financial report", "booking", "financial reporting"], "requirements": {"degrees": ["degree holder"], "majors": ["related disciplines", "finance", "accounting"], "languages": ["putonghua", "english", "chinese"], "language_level": ["proficiency", "good command"], "hard_skills": ["acca", "plus", "word", "powerpoint", "oracle erp", "analytical skills", "ms excel", "hkicpa"], "soft_skills": ["communication skills", "self-motivated", "analytical skills", "interpersonal skills", "positive"], "languages_combined": [{"language": "putonghua", "language_level": ["proficiency", "good command"]}, {"language": "english", "language_level": ["good command"]}, {"language": "chinese", "language_level": ["proficiency", "good command"]}]}, "experience_required": {"duration": ["at least 3 years"], "field": ["management", "financial institutions"]}}, {"job_id": "100003009052745", "location_code": "hk", "company": "Sun Entertainment Group Limited", "job_title": "CHIEF OPERATING OFFICER", "description": "Responsibilities\n\n\nDevelop company\u2019s strategies / oversee implementation plans and monitor company\u2019s finances;\nEstablish, review, execute policies and procedures to continuously improve efficiencies in Finance and compliance with other functions of company, i.e. IT, Legal etc. to meet requirements and business needs;\nMaintain and monitor staffing, levels, knowledge-skills-attributes (KSA), expectations and motivation to fulfill organizational requirements;\nDriving performance measures for operations considering efficiency versus effectiveness in in set comprehensive polices and goals to enrich company\u2019s expansion in Macau or Australia\u2019s various projects, campaigns, concerts, etc.;\nDevelop initiatives and policies that improve company growth in Macau and participate in expansion activities (investments, acquisitions, corporate alliances etc.);\nConduct analysis reports to senior management and board of directors;\nEnsure smooth and effective collaboration with working partners and vendors in Macau / Australia;\nOther ad hoc tasks as assigned.\nRequirements\n\n\nBachelor degree or above preferably in Commerce, Accounting or related discipline;\nOver 10+ years of senior management experience with laws & regulations in Macau / Australia;\nAt least 5 years working experience in entertainment, event & marketing industry;\nProficiency in Macau accounting standards, taxation, and other legal and compliance regulations;\nQualified accountant of HKICPA / ACCA / CPA Australia is a MUST;\nSolid experience to prepare Conflict and Risk guidelines and procedures;\nGood team player with sound interpersonal and communication skills to work with various business partners;\nStrong analytical, managerial and leadership skills;\nProven problem-solving abilities and ability to work under tight deadlines;\nExcellent command of English & Chinese.", "employment_types": ["Full Time", "Permanent"], "selling_points": ["10+ years of senior management exp. in Macau/Aus.", "5 yrs entertainment, event & marketing industry", "Qualified accountant of CPA Austra"], "locations": ["Not Specified"], "categories": ["Accounting", "Others", "Management", "Top Executives (CEO, CFO, CTO, GM, MD etc.)", "E-commerce", "Others"], "post_time": "2022-01-17T03:54:02Z", "salary": {"currency": null, "max": null, "min": null, "period": "monthly", "term": null}, "salary_visible": false, "title_keywords": ["operating officer"], "responsibilities": ["policies", "review", "monitor", "implementation", "procedures", "develop", "compliance", "plans"], "requirements": {"degrees": ["degree or above", "bachelor"], "majors": ["accounting"], "languages": ["english", "chinese"], "language_level": ["excellent"], "hard_skills": ["acca", "problem-solving", "analysis", "cpa", "hkicpa"], "soft_skills": ["communication skills", "good team player", "organizational", "leadership skills", "problem-solving", "comprehensive", "smooth", "interpersonal"], "languages_combined": [{"language": "english", "language_level": ["excellent"]}, {"language": "chinese", "language_level": ["excellent"]}]}, "experience_required": {"duration": ["at least 5 years", "10+ years"], "field": ["management", "marketing"]}}, {"job_id": "100003009051730", "location_code": "hk", "company": "Whampoa Property Management Limited", "job_title": "ASSISTANT ACCOUNTANT [Ref. WPML-AA]", "description": "Degree holder in Accounting or Finance, student member of ACCA / HKICPA or equivalent\nMinimum 4 years' relevant working\u00a0experience, preferably in estate management companies or related industry\nHandle full sets of book-keeping for management fund accounts\nGenerate debit notes / reminders / receipts / autopay from billing system\nPrepare vouchers, cheques, bank balances and time deposits\nHandle overdue accounts and take follow-up actions\nDetail-oriented, self-motivated and able to\u00a0work independently\nGood interpersonal and communication skills\nProficient in MS Office with knowledge in\u00a0Oracle system an added advantage\nFluent in written and spoken English and\u00a0Chinese\nWe offer salary and benefits commensurate with qualifications and experience. Please send a full resume with contact telephone number and expected salary to\u00a0General Manager - Human Resources & Administration, Whampoa Property Management Limited, 3/F., One Harbourfront, 18 Tak Fung Street, Hunghom, Kowloon\u00a0\u00a0(Please quote reference on envelope) or by clicking \"Apply Now\".\n\nWe are an equal opportunity employer and welcome applications from all qualified candidates. The information provided will be treated in strict confidence and be used only for consideration of your application for relevant/similar post(s).\n\nApplicants not hearing from us within six weeks from the date of advertisement may consider their applications unsuccessful. All personal data of unsuccessful applicants will be destroyed after the recruitment exercise when no longer required.", "employment_types": ["Full Time", "Permanent"], "selling_points": ["Degree holder", "Minimum 4 years' relevant working experience", "Student member of ACCA / HKICPA"], "locations": ["Tsing Yi"], "categories": ["Accounting", "Accountant", "Accounting Clerk / Supervisor", "Others"], "post_time": "2022-01-16T21:51:14Z", "salary": {"currency": null, "max": null, "min": null, "period": null, "term": null}, "salary_visible": false, "title_keywords": ["assistant accountant"], "responsibilities": ["management", "receipts", "communication", "cheques", "book-keeping", "autopay"], "requirements": {"degrees": ["degree holder"], "majors": ["finance", "accounting"], "languages": ["english", "chinese"], "language_level": ["fluent"], "hard_skills": ["acca", "oracle system", "hkicpa", "billing system", "ms office"], "soft_skills": ["communication skills", "self-motivated", "work independently", "detail-oriented", "interpersonal"], "languages_combined": [{"language": "english", "language_level": ["fluent"]}, {"language": "chinese", "language_level": ["fluent"]}]}, "experience_required": {"duration": ["minimum 4 years"], "field": ["related", "management", "relevant working experience"]}}, {"job_id": "100003009037439", "location_code": "hk", "company": "City Super Ltd", "job_title": "Officer, General Accounting", "description": "Responsibilities:\n\nOversees accounts payable/ GL function of the Group\nEnsuring all vendor invoices are processed and recorded timely and accurately on a timely basis\nMonitor and follow up with the vendor accounts\nAssist in streamlining work flow. Develop and implement policies & procedures of the Group.\nManage and handle ad hoc projects\n\nRequirements:\n\nDegree/Diploma holder in Finance, Accounting and other related disciplines\nMember or student member of HKICPA or ACCA\nMinimum 3 years of relevant experience in sizable companies\nGood command of both spoken and written English and Chinese\nFamiliar with Microsoft Office, preferably with SAP experience.\nStrong business acumen, leadership, interpersonal and communication skills\nAnalytical and being a good team player, able to meet tight deadlines\nCandidate with more experience will be considered as Senior Officer\n\nWe offer competitive remuneration package and good prospects to the right candidates. Interested parties please send your full resume with expected salary to apply\n\n*Data collected will be kept confidential and used for recruitment purposes only.", "employment_types": ["Full Time", "Permanent"], "selling_points": ["Oversees accounts payable function of the Group", "Assist in streamlining work flow", "Manage and handle ad hoc projects"], "locations": ["Tsim Sha Tsui"], "categories": ["Accounting", "Accountant", "Others"], "post_time": "2022-01-11T02:50:39Z", "salary": {"currency": null, "max": null, "min": null, "period": "monthly", "term": null}, "salary_visible": false, "title_keywords": ["officer", "accounting"], "responsibilities": ["invoices", "policies", "monitor", "procedures", "develop", "ad hoc projects", "accounts payable"], "requirements": {"degrees": ["diploma holder", "degree"], "majors": ["related disciplines", "finance", "accounting"], "languages": ["english", "chinese"], "language_level": ["good command"], "hard_skills": ["acca", "sap", "microsoft office", "sizable companies", "acumen", "hkicpa"], "soft_skills": ["communication skills", "good team player", "meet tight deadlines", "business acumen", "leadership", "interpersonal"], "languages_combined": [{"language": "english", "language_level": ["good command"]}, {"language": "chinese", "language_level": ["good command"]}]}, "experience_required": {"duration": ["minimum 3 years"], "field": ["relevant experience"]}}, {"job_id": "100003009053604", "location_code": "hk", "company": "Thales Transport & Security (Hong Kong) Limited", "job_title": "Project Cost Control Officer", "description": "Responsibilities\n\nUnderstand the revenue recognition plan at project start and the billing plan (invoice and progress payments), manage and proceed the revenue recognition and billing with Projects Manager and Business Control Manager\nUpdate revenue recognition plan as required\nCheck, control and monitor movements in Actual and Committed Costs on a monthly basis\nManage and forecast cash movements monthly. Track cash-in overdue status; give alert to Project Managers and Business Control Manager.\nProvide all necessary support to Project Managers on financial matters\nEnsure that project data reporting is in line with approved Project reviews\nCoordinate with the project team to ensure consistent accounting (revenue & margin recognition) and reporting across the project.\nDevelop strong relationships and continuous communication flows with project team\nEnsure that all financial processes & instructions and internal controls, including delegation of authorities, are implemented\u00a0 and compliant\nSupport budget, forecasts and monthly closing\n\nRequirements\n\nBachelor degree in Accounting/Finance or related discipline\nAt least 5 years\u2019 experience of project accounting & controlling\nExperience long-term contract management, a plus\nKnowledge of SAP, Excel\nProficiency in both written and spoken English.\nHighly articulate, confident team player able to communicate and work under pressure\nExperience in complex international environment", "employment_types": ["Full Time", "Permanent"], "selling_points": ["5+ years of project cost control experience", "Stable working hours", "Hong Kong region focused"], "locations": ["Mong Kok"], "categories": ["Accounting", "Finance / Accounting Manager", "Financial Controller", "Others"], "post_time": "2022-01-17T07:13:24Z", "salary": {"currency": null, "max": null, "min": null, "period": "monthly", "term": null}, "salary_visible": false, "title_keywords": ["officer"], "responsibilities": ["reporting", "control", "data", "invoice", "budget", "monitor", "coordinate with", "develop", "communication", "payments", "plan", "forecast", "costs"], "requirements": {"degrees": ["degree", "bachelor"], "majors": ["finance", "accounting"], "languages": ["english"], "language_level": ["proficiency"], "hard_skills": ["excel", "plus", "sap"], "soft_skills": ["confident", "articulate", "team player", "work under pressure"], "languages_combined": [{"language": "english", "language_level": ["proficiency"]}]}, "experience_required": {"duration": ["at least 5 years"], "field": ["management", "accounting"]}}, {"job_id": "100003009051338", "location_code": "hk", "company": "EY", "job_title": "Tax - Customer Tax Operations Reporting - Manager - Hong Kong", "description": "In EY Tax, you\u2019ll have the opportunity to help the world\u2019s leading multinational organizations meet complex tax obligations around the world. You\u2019ll get a unique glimpse deep inside a company\u2019s business and become a trusted advisor, working collaboratively on a team that influences major business decisions.\u00a0Demand has made this a rapidly growing area, and the relationships we build here translate into big business in other areas, making this a true priority.\u00a0\nThe opportunity\nAs a Manager, you will be a part of our\u00a0Business Tax Services group on the Customer Tax Operations Reporting team.\u00a0This position offers excellent opportunities for learning and career advancement to the right candidate.\nYour key responsibilities\nAs a Manager, you will participate in and supervise multiple and challenging tax consulting engagements and to contribute to the delivery of innovative tax compliance support for our diverse clients.\u00a0\nLeading large and medium sized engagements.\nConducting and documenting tax research and legislation interpretation and advising on operational tax models, tax compliance strategies, and compliance issues.\nReviewing the work of junior staff for accuracy and completeness.\nBecome part of the tax engagement team in servicing the planning and compliance needs of clients and assisting clients with compliance audits.\nWorking closely with other members of our team on tax technical interpretation work for clients\nEstablish relationships with clients and gain a solid understanding of their business.\nDevelop technical skills by remaining up to date on trends, new developments and tax authority decisions, and apply them to moderately complex situations.\nIdentify opportunities for providing consulting and other special services.\nSupport the development and coaching of tax professionals and other junior tax staff members.\nParticipate in and contribute to the attainment of team objectives.\nTo qualify for the role you must have\nProfessional accounting designation or law degree\nMinimum of four years Hong Kong tax experience\nAbility to research and write utilizing electronic tax tools.\nStrong project management and organizational skills\nAbility to work with tight deadlines\nIdeally, you\u2019ll also have\nPrevious experience dealing with clients within the financial services sector is strongly preferred\nPrevious experience dealing with information exchange matters (FATCA, CRS) or information reporting and withholding matters\nMature, proactive, committed, highly motivated and driven team player\nWhat we look for\nWe\u2019re interested in strong team players who support their colleagues in reaching their goals while also considering their own workload and development. We\u2019re looking for people with a genuine passion for tax, and the future of tax, and are inspired to help the world\u2019s leading multinational organizations meet complex tax obligations around the world. If you have the confidence to speak up and influence a team that affects big businesses worldwide, this role is for you.\nWhat working at EY offers\nAt EY, our Total Rewards package supports our commitment to creating a leading people culture\u00a0-\u00a0built on high-performance teaming\u00a0-\u00a0where everyone can achieve their potential and contribute to building a better working world for our people, our clients and our communities. It's one of the many reasons we repeatedly win awards for being a great place to work.\nWe offer\u00a0a\u00a0competitive\u00a0compensation\u00a0package where you\u2019ll be rewarded based on your performance and recognized for the value you bring to our business. In addition, our Total Rewards package allows you decide which benefits are right for you and which ones help you create a solid foundation for your future. Our Total Rewards package includes a comprehensive medical, prescription drug and dental coverage, a defined contribution pension plan, a great vacation policy plus firm paid days that allow you to enjoy longer long weekends throughout the year, statutory holidays and paid personal days (based on province of residence), and a range of exciting programs and benefits designed to support your physical, financial and social well-being. Plus, we offer:\nSupport and coaching from some of the most engaging colleagues in the industry\nLearning opportunities to develop new skills and progress your career\nThe freedom and flexibility to handle your role in a way that\u2019s right for you\nAbout EY\nAs a global leader in assurance, tax, transaction and advisory services, we\u2019re using the finance products, expertise and systems we\u2019ve developed to build a better working world. That starts with a culture that believes in giving you the training, opportunities and creative freedom to make things better. Whenever you join, however long you stay, the exceptional EY experience lasts a lifetime.\nIf you can confidently demonstrate that you meet the criteria above, please contact us as soon as possible.\nMake your mark. Apply today.", "employment_types": ["Full Time", "Permanent"], "selling_points": ["FATCA/CRS/AEOI", "Conducting and documenting tax research", "Minimum of 4 years Hong Kong tax experience"], "locations": ["Not Specified"], "categories": ["Accounting", "Taxation", "Others", "Professional Services", "Legal & Compliance"], "post_time": "2022-01-15T09:41:14Z", "salary": {"currency": null, "max": null, "min": null, "period": "monthly", "term": null}, "salary_visible": false, "title_keywords": ["operations", "manager"], "responsibilities": ["tax", "reporting", "consulting", "operations", "compliance", "develop", "project management", "audits", "planning"], "requirements": {"degrees": ["degree"], "majors": ["accounting", "law"], "languages": [], "language_level": [], "hard_skills": ["crs", "project management", "fatca", "exchange"], "soft_skills": ["organizational skills", "proactive", "confidence", "passion for", "deep", "interested in", "unique", "mature", "genuine", "diverse", "project management", "learning", "committed", "motivated", "technical skills", "team player", "innovative", "driven"], "languages_combined": []}, "experience_required": {"duration": ["minimum of four years"], "field": ["financial services"]}}, {"job_id": "100003009045122", "location_code": "hk", "company": "Union Hospital", "job_title": "\u6536\u9280\u54e1 Clerk (Cashier) (Ref: JDB/130122/CAS_CC)", "description": "\u8077\u8cac\uff1a\n\n\u8ca0\u8cac\u65e5\u5e38\u6536\u6b3e\u3001\u958b\u55ae\u53ca\u57cb\u6578\u7a0b\u5e8f\n\u5354\u52a9\u8655\u7406\u4e00\u822c\u6587\u66f8\u5de5\u4f5c\u00a0\n\n\u5165\u8077\u8981\u6c42\uff1a\n\n\u4e2d\u4e94\u6216\u4ee5\u4e0a\u7a0b\u5ea6\uff0c\u9999\u6e2f\u4e2d\u5b78\u6703\u8003/\u9999\u6e2f\u4e2d\u5b78\u6587\u6191\u8003\u8a66\u4e4b\u82f1\u6587\u53ca\u6578\u5b78\u79d1\u5408\u683c\u512a\u5148\n\u51772\u5e74\u6216\u4ee5\u4e0a\u6536\u9280\u5de5\u4f5c\u7d93\u9a57\u512a\u5148\n\u61c2\u57fa\u672c\u96fb\u8166\u64cd\u4f5c\n\u9700\u8f2a\u73ed\u5de5\u4f5c\u6216\u56fa\u5b9a\u4e0b\u5348\u66f4\u00a0\n\n\u54e1\u5de5\u798f\u5229\uff1a\n\n\u6bcf\u661f\u671f\u5de5\u4f5c39\u5c0f\u6642\n\u6709\u85aa\u5e74\u504714\u5929\u8d77\n\u91ab\u7642\u798f\u5229\n\u91ab\u7642\u4fdd\u96aa\n\u5728\u8077\u57f9\u8a13\n\n\u54e1\u5de5\u53ef\u4eab\u6709\u6709\u85aa\u5e74\u5047\u3001\u9280\u884c\u5047\u671f\u3001\u5728\u8077\u57f9\u8a13\u3001\u4f4f\u9662\u4fdd\u96aa\u3001\u9580\u8a3a\u6d25\u8cbc\u3001\u6e21\u5047\u5c4b\u7b49\u798f\u5229\u3002\u00a0 \u00a0 \u00a0\n\n\u6c42\u8077\u8005\u53ef\u5728\u672c\u9662\u7db2\u7ad9 ( www.union.org ) \u4e0b\u8f09\u8077\u4f4d\u7533\u8acb\u8868 (\u8acb\u5beb\u4e0a\u8077\u4f4d\u7de8\u865f), \u4e26\u9023\u540c\u8b49\u660e\u6587\u4ef6\u7d93\u4ee5\u4e0b\u9014\u5f91\u905e\u4ea4:\u00a0\u00a0\u00a0\u00a0\u00a0\n\n\u90f5\u5bc4: \u65b0\u754c\u6c99\u7530\u5927\u570d\u5bcc\u5065\u8857\u5341\u516b\u865f\u4ec1\u5b89\u91ab\u9662\u4eba\u529b\u8cc7\u6e90\u90e8\u6536 \u6216 \u96fb\u90f5: Apply Now\u00a0\u6216 \u50b3\u771f: 2697 5028\u00a0\u00a0\u00a0\u00a0\u00a0\n\n\u8a3b\u4e00\uff1a\u6240\u6536\u96c6\u7684\u8cc7\u6599\u53ea\u4f5c\u62db\u8058\u7528\u9014\u3002\u00a0\u00a0\n\n\u8a3b\u4e8c\uff1a\u82e5\u7533\u8acb\u4eba\u65bc\u5169\u500b\u6708\u5167\u4ecd\u672a\u6536\u5230\u4efb\u4f55\u901a\u77e5\uff0c\u5247\u7576\u81ea\u52d5\u843d\u9078\uff1b\u534a\u5e74\u5167\u5df2\u905e\u4ea4\u540c\u4e00\u8077\u4f4d\u7533\u8acb\u4e4b\u4eba\u58eb\uff0c\u7121\u9808\u518d\u905e\u4ea4\u7533\u8acb\u8868\u3002\n\n\u8a3b\u4e09\uff1a\u56e0\u61c9\u300c\u6027\u7f6a\u884c\u5b9a\u7f6a\u7d00\u9304\u67e5\u6838\u300d\u6a5f\u5236\u5df2\u5be6\u65bd\uff0c\u672c\u9662\u5c07\u6703\u8981\u6c42\u6709\u95dc\u8077\u4f4d\u7684\u6e96\u50f1\u54e1\u9032\u884c\u6027\u7f6a\u884c\u5b9a\u7f6a\u7d00\u9304\u67e5\u6838\u3002\u00a0\u00a0\u00a0\u00a0", "employment_types": ["Full Time"], "selling_points": ["\u6709\u85aa\u5e74\u504714\u5929\u8d77, \u91ab\u7642\u798f\u5229, \u91ab\u7642\u4fdd\u96aa", "\u51772\u5e74\u6216\u4ee5\u4e0a\u6536\u9280\u5de5\u4f5c\u7d93\u9a57\u512a\u5148", "\u9700\u8f2a\u73ed\u5de5\u4f5c\u6216\u56fa\u5b9a\u4e0b\u5348\u66f4"], "locations": ["Shatin Area"], "categories": ["Accounting", "Others", "Admin & HR", "Clerical / Admin Staff", "Medical Services", "Others"], "post_time": "2022-01-13T07:45:04Z", "salary": {"currency": null, "max": null, "min": null, "period": "monthly", "term": null}, "salary_visible": false, "title_keywords": ["clerk"], "responsibilities": [], "requirements": {"degrees": [], "majors": [], "languages": [], "language_level": [], "hard_skills": [], "soft_skills": [], "languages_combined": []}, "experience_required": {"duration": [], "field": []}}, {"job_id": "100003009051068", "location_code": "hk", "company": "Commercial Investment Co., Ltd.", "job_title": "Accounts Assistant / Clerk", "description": "Responsibilities :\u00a0\nPerform daily accounting duties including data entries and filing, handling cheque payment approval and requisition, prepare vouchers\nResponsible for bank reconciliation, accounting schedule\nPrepare monthly and periodical management accounts\nAssist in other accounting duties as assigned\nRequirements :\nHKCEE or HKDSE with LCCI Accounting/Bookkeeping Level III / Diploma in accounting or equivalent\n3 years\u2019 relevant accounting experience, experience in handling taxation matters an advantage\nProficient in MS Office applications including Excel, knowledge of Flex accounting system is a definite advantage\nOrganized, detail-oriented, high accuracy, responsible, able to work independently and efficiently with minimum supervision\nCandidate with less experience will be considered as Accounts Clerk.", "employment_types": ["Permanent"], "selling_points": [], "locations": ["Central"], "categories": ["Accounting", "Accounting Clerk / Supervisor", "Others"], "post_time": "2022-01-15T19:11:49Z", "salary": {"currency": null, "max": null, "min": null, "period": null, "term": null}, "salary_visible": false, "title_keywords": ["clerk", "accounts assistant"], "responsibilities": ["management", "data", "bank reconciliation", "payment", "schedule", "daily accounting", "accounting duties"], "requirements": {"degrees": ["diploma", "hkdse"], "majors": ["accounting"], "languages": [], "language_level": [], "hard_skills": ["excel", "flex accounting", "ms office"], "soft_skills": ["organized", "work independently", "responsible", "detail-oriented"], "languages_combined": []}, "experience_required": {"duration": ["3 years"], "field": ["accounting experience"]}}, {"job_id": "100003009051052", "location_code": "hk", "company": "The Wharf Group", "job_title": "Internal Audit Assistant", "description": "Responsibilities :\n\nTo efficiently and effectively\u00a0assist the audit field-in-charge and/or manager to complete audit works relating to our\u00a0businesses in investment properties, development properties, hotels, etc.\u00a0 \u00a0\u00a0\n\nRequirements :\n\nUniversity graduate with 1 - 2 years\u00a0auditing experience\nExperience in MNCs and/or major international accounting firms most preferred but not essential\nStrong communications skill in spoken and written English and Chinese (Cantonese and Mandarin)\nProficient in Microsoft Office applications\nResponsible, analytical, independent, detail-oriented, and able to work under pressure\nOccasional travel to Mainland China is required\n\nWe work 5 days per week.\n\nInterested parties, please click \"APPLY NOW\" and attach with your application letter and full resume.\u00a0\n\nFor further information of the Wharf Group, please visit our website: www.wharfholdings.com", "employment_types": ["Full Time", "Permanent"], "selling_points": [], "locations": ["Tsim Sha Tsui"], "categories": ["Accounting", "Audit", "Others", "Property / Real Estate", "Others"], "post_time": "2022-01-15T19:11:48Z", "salary": {"currency": null, "max": null, "min": null, "period": null, "term": null}, "salary_visible": false, "title_keywords": ["assistant"], "responsibilities": ["audit"], "requirements": {"degrees": ["university graduate"], "majors": [], "languages": ["cantonese", "english", "chinese", "mandarin"], "language_level": [], "hard_skills": ["microsoft office"], "soft_skills": ["work under pressure", "independent", "responsible", "detail-oriented"], "languages_combined": [{"language": "cantonese", "language_level": []}, {"language": "english", "language_level": []}, {"language": "chinese", "language_level": []}, {"language": "mandarin", "language_level": []}]}, "experience_required": {"duration": ["1 - 2 years"], "field": ["accounting"]}}, {"job_id": "100003009045144", "location_code": "hk", "company": "Hong Kong Baptist Hospital", "job_title": "Clerk (Accounts)", "description": "Form 5 (HKCEE) / Form 6 (HKDSE) or above\nLCC&I Certificate Level 2 or equivalent\nMinimum 3 years of relevant experience\nPerform general accounting duties\nProficiency in MS Excel, Word\u00a0and Chinese word processing\nGood command of spoken and written English and Chinese\nAble to work under pressure and meet deadline\nHandle ad hoc duties as assigned\nWe offer attractive remuneration package and fringe benefits to the right candidates. Interested parties please apply with full resume and expected salary to Human Resources Department, Hong Kong Baptist Hospital, 18/F, Tower 2, Enterprise Square, 9 Sheung Yuet Road, Kowloon Bay, Kowloon, by email via \"Apply Now\" or by fax to 2339 5769 on or before 28 January 2022.\nThe information provided will only be used for recruitment related purposes. All personal information on unsuccessful candidates will be destroyed within 6 months.", "employment_types": ["Full Time", "Contract"], "selling_points": [], "locations": ["Kowloon Bay"], "categories": ["Accounting", "Accounting Clerk / Supervisor", "Others"], "post_time": "2022-01-13T18:54:38Z", "salary": {"currency": null, "max": null, "min": null, "period": "monthly", "term": null}, "salary_visible": false, "title_keywords": ["clerk"], "responsibilities": ["ad hoc duties", "general accounting duties", "work under pressure"], "requirements": {"degrees": ["certificate", "form 5", "hkdse"], "majors": [], "languages": ["english", "chinese"], "language_level": ["proficiency", "good command"], "hard_skills": ["ms excel", "chinese word processing", "word"], "soft_skills": ["work under pressure"], "languages_combined": [{"language": "english", "language_level": ["good command"]}, {"language": "chinese", "language_level": ["proficiency", "good command"]}]}, "experience_required": {"duration": ["minimum 3 years"], "field": ["relevant experience"]}}, {"job_id": "100003009054360", "location_code": "hk", "company": "ALS International Limited", "job_title": "Litigation & Audit Manager", "description": "Our client is a market leading boutique professional services firm, specialising in helping clients globally with their risk, litigation and forensic consulting cases. \u00a0With an established presence in both Europe and Asia, they are continuing to grow and expand further within the Asia region.\u00a0 As a result, they are now looking for an experienced Investigations Manager to lead the team within the region.\n\nReporting to the Head of Asia and supporting on high profile cases within the region, you will lead a small team as follows:\n\nProvide coaching and guidance to a small team, motivate and keep engaged throughout complex cases\nConduct research and in-depth investigations to uncover data and evidence to support findings on client cases\nUtilise e-discovery platforms, research databases, interviews and publicly available information to assimilate data and business intelligence\nReview, analyse and interpret financial statements, audit reports and documentary evidence to investigate irregularities, omissions, disputes and anomalies\nConduct investigative research and due diligence to verify background and reputation of corporations and individuals\nWork across multiple jurisdictions across Asia and China, liaising with local forensic accountants, solicitors, regulatory bodies or other third party professionals as required\nPrepare reports and presentations for management, lawyers and officials to escalate for higher level reviews\nProject manage multiple cases and engagements and be able to present updates and reviews on an ongoing basis\nPro-active in taking on ad hoc projects when required\n\nSuitable candidates should be able to demonstrate the following:\n\nA minimum of 5-10 years of experience in a similar audit, forensic, legal, e-discovery or research field\nIdeally be a qualified lawyer, or professional accountant and have experience of similar forensic or litigation processes\nSelf-sufficiency in leading and\u00a0 running multiple projects at different timelines, with an ability to prioritise to meet deadlines\nHave a natural curiosity and inquisitive mindset to constantly question and not just accept the status quo\nStrong organisational skills and eye for detail, having an ability to review documents and identify if something looks amiss\nHave a passion for problem solving and a willingness to go the extra mile to succeed\nProfessional gravitas to work with Partners and lawyers and senior level clients\nStrong communication skills in speaking, reading and writing in English and Chinese, fluency in Mandarin being a distinct advantage\nStrong team player and enjoy working in a collaborative environment to build cases and work towards deadlines\n\nOur client offers a collaborative team working environment and a compelling package to attract the best.\n\nCandidates that have the above attributes should send their resumes in English to Janice Ho, quoting\u00a0reference no:\u00a019451\u00a0to call +852 2920 9131 to discuss further.", "employment_types": ["Full Time"], "selling_points": [], "locations": ["Central"], "categories": ["Accounting", "Audit", "Others"], "post_time": "2022-01-17T09:16:31Z", "salary": {"currency": null, "max": null, "min": null, "period": "monthly", "term": null}, "salary_visible": false, "title_keywords": ["manager"], "responsibilities": ["consulting", "data", "audit", "financial statements", "communication", "conduct research", "due diligence", "liaising with", "presentations", "reports", "guidance", "reporting", "management", "review", "third party", "irregularities", "lead a small team", "ad hoc projects", "databases", "prepare reports", "multiple projects", "analyse"], "requirements": {"degrees": [], "majors": [], "languages": ["english", "chinese", "mandarin"], "language_level": ["fluency", "advantage"], "hard_skills": ["small", "no", "presentations", "problem solving", "databases", "go", "business intelligence"], "soft_skills": ["communication skills", "passion for", "enjoy working", "collaborative", "prioritise", "problem solving", "organisational skills", "team player", "eye for detail", "pro-active", "team working", "meet deadlines"], "languages_combined": [{"language": "english", "language_level": ["advantage", "fluency"]}, {"language": "chinese", "language_level": ["advantage", "fluency"]}, {"language": "mandarin", "language_level": ["advantage", "fluency"]}]}, "experience_required": {"duration": ["minimum of 5-10 years"], "field": ["research", "audit", "legal"]}}, {"job_id": "100003009052195", "location_code": "hk", "company": "IPSOS Asia Limited", "job_title": "Accountant / Business Analyst", "description": "Role Objective / Purpose\n\n\nThe role of Business Analyst is responsible for all accounting and finance functions of IPSOS HK and to ensure proper accounting records are kept for internal and statutory audits.\n\nRole & Responsibilities:\n\nResponsible for monitoring the operational and accounting system\nMonitor and review the budget and actual spending of projects to ensure data integrity\nOversee the daily accounting functions to ensure accounting records are kept in compliance with the group accounting policies.\nMonitor and supervise the month end closing to ensure all management reports are submitted on time and accurate.\nPrepare monthly financial charts/reports for all IPSOS HK divisions.\nCompile various periodic analytical reports (e.g. Contribution Report, Job Summary Report etc.) and hold discussion meeting with divisional heads regularly so as to make them aware of their updated divisional performance.\nCommunicate with Research Departments regularly to understand and provide necessary support to them\nAssist the statutory audit of IPSOS HK to ensure audit deadline is met.\nParticipate in the group internal audits to make sure proper control procedures are in place.\nReview the existing internal control system and make recommendations on the existing work procedures so as to improve the efficiency.\nAssist in the annual budget process to understand the budget components of each division.\nAssist in the set-up of new accounting software to ensure it meets our business requirement.\nProvide support to Chief Financial Officer for ad hoc reporting so as to meet the tight reporting deadlines.\n\n\nPerson specification\n\nQualification\uff1a\n\nBachelor Degree in Accounting or equivalent with minimum 5 years of audit or accounting experience\n\nKnowledge (including general and IPSOS specific knowledge)\uff1a\n\nKnowledge in SAP system is a definite advantage\nAccounting standards and principles.\nRecent computing development especially in accounting software packages.\nKnowledge in market research products e.g. methodology, product type and client type etc. is preferred.\n\nSkill (including technical and people skill)\uff1a\n\nGood communication and interpersonal skills and able to communicate with people from different background and with different seniority.\nGood language skill both verbal and writing.\nBasic grasp of the market research industry.\nGood computer skill especially in Microsoft Excel, Word, and PowerPoint\nGood presentation skill.\n\nOther Requirements\n\nResponsible and able to work independently.\nDedication and good determination to meet deadlines.\n\nWe offer an attractive remuneration package with 5-day work week to the right candidates. Interested parties please send\u00a0resume with current and expected salary to us. All information collected will be used for recruitment purpose only.", "employment_types": ["Full Time", "Permanent"], "selling_points": ["Accountant", "Financial Analyst", "Audit or Accounting"], "locations": ["Hung Hom"], "categories": ["Accounting", "Accountant", "Financial Analyst", "Others"], "post_time": "2022-01-17T02:26:10Z", "salary": {"currency": null, "max": null, "min": null, "period": "monthly", "term": null}, "salary_visible": false, "title_keywords": ["accountant", "business analyst"], "responsibilities": ["software", "data", "budget", "audit", "communication", "accounting policies", "internal control", "make recommendations", "month end closing", "control", "ad hoc", "compliance", "monitor", "reports", "report", "reporting", "provide support", "review", "monitoring", "procedures", "audits", "communicate with", "market research", "management reports", "daily accounting"], "requirements": {"degrees": [], "majors": [], "languages": [], "language_level": [], "hard_skills": [], "soft_skills": ["work independently", "meet deadlines", "responsible"], "languages_combined": []}, "experience_required": {"duration": [], "field": []}}, {"job_id": "100003009054540", "location_code": "hk", "company": "JAC Recruitment Hong Kong Co., Limited", "job_title": "Japanese Speaking Accountant / Accounting Supervisor (up to 28K)", "description": "Degree holder in Accounting and qualified member of ACCA / HKICPA or equivalent\nMinimum 3 years' relevant experience in financial and management accounting, preferably with consolidation experience\nAudit experience in sizable audit firm an advantage\nKnowledge in PRC to HK GAAP conversion\nReview full set of accounts, accounting schedule, budget, forecast, financial analysis and management reports\nReview monthly treasury reports of PRC and offshore companies\nPrepare and review audited accounts and management accounts\nHandle Hong Kong Profits Tax computation and CBCR reporting\nAnalytical, self-motivated, detail-oriented and able to meet tight deadlines\nProficient in Oracle and MS Office\nFluent in written and spoken English and Chinese, including Putonghua\n\nWe offer salary and benefits commensurate with qualifications and experience. Please send a full resume with contact number and expected salary to General Manager - Human Resources & Administration, Hutchison Property Management Company Limited, 3/F., One Harbourfront, 18 Tak Fung Street, Hunghom, Kowloon (Please quote reference on envelope) or by clicking \"Apply Now\".\n\nWe are an equal opportunity employer and welcome applications from all qualified candidates. The information provided will be treated in strict confidence and be used only for consideration of your application for relevant/similar post(s).\n\nApplicants not hearing from us within six weeks from the date of advertisement may consider their applications unsuccessful. All personal data of unsuccessful applicants will be destroyed after the recruitment exercise when no longer required.", "employment_types": ["Full Time", "Permanent"], "selling_points": ["JLPT N3 or above, 5yrs exp full set account", "Reporting, financial analysis, supervise jr staff", "5days, TST, gd career path, WORK-LIFE BALANCE"], "locations": ["Tsim Sha Tsui"], "categories": ["Accounting", "Accountant", "Accounting Clerk / Supervisor", "Others"], "post_time": "2022-01-17T09:55:08Z", "salary": {"currency": null, "max": null, "min": null, "period": "monthly", "term": null}, "salary_visible": false, "title_keywords": ["accountant", "accounting supervisor"], "responsibilities": ["reporting", "management", "tax computation", "review", "full set of accounts", "audit", "budget", "financial analysis", "management reports", "reports", "schedule", "forecast"], "requirements": {"degrees": ["degree holder"], "majors": ["accounting"], "languages": ["putonghua", "english", "chinese"], "language_level": ["fluent"], "hard_skills": ["acca", "financial analysis", "hkicpa", "management reports", "ms office", "oracle"], "soft_skills": ["self-motivated", "meet tight deadlines", "detail-oriented"], "languages_combined": [{"language": "putonghua", "language_level": ["fluent"]}, {"language": "english", "language_level": ["fluent"]}, {"language": "chinese", "language_level": ["fluent"]}]}, "experience_required": {"duration": ["minimum 3 years"], "field": ["management accounting", "consolidation", "audit", "relevant experience", "audit experience", "financial"]}}, {"job_id": "100003009054426", "location_code": "hk", "company": "HKR International Ltd", "job_title": "Assistant - Accounting / Assistant Accountant", "description": "The opportunity\n\nIn EY Tax, you\u2019ll have the opportunity to help the world\u2019s leading multinational organizations meet complex tax obligations around the world. You\u2019ll get a unique glimpse deep inside a company\u2019s business and become a trusted advisor, working collaboratively on a team that influences major business decisions.\u00a0Demand has made this a rapidly growing area, and the relationships we build here translate into big business in other areas, making this a true priority.\n\n\nYour key responsibilities\n\nJoin the fast-growing Asia Pacific Customer Tax Operations and Reporting Services practice to deliver complex AEOI engagements. As part of the team, you will work closely with team members across the Asia Pacific region while you are also required to interact with teams in other parts of the world, e.g. the US.\nTake part in various types of AEOI engagements which include advisory, compliance, reporting and transformation projects for financial institution clients from all sectors.\nUse the latest EY technologies in the engagement delivery.\nPartner with Tax Technology & Transformation to deliver innovative EY solutions which gives the unique value proposition.\nAssist clients in handling enquiries or inspections from tax authorities and other controversy matters.\nAssist in pursuits and the preparation of proposals.\n\nTo qualify for the role you must have\n\nBachelor or advanced degree in Accounting, Law, Finance or Economics, Business, IT or other relevant disciplines.\nExcellent command in both written & spoken English. High proficiency in Chinese and/or other language is preferable.\nEnergetic, hardworking, strong analytical, business savvy.\nTeam player with strong communication skills.\nStrong presentation, organization and management skills.\nGood at Microsoft Office. Appreciation of visualization / data analytics tools would be welcomed.\n\nIdeally, you\u2019ll also have\n\nPrevious experience dealing with clients within the financial services sector is strongly preferred\nPrevious experience dealing with information exchange matters (FATCA, CRS) or information reporting and withholding matters\nMature, proactive, committed, highly motivated and driven team player\n\nWhat we look for\n\nWe\u2019re interested in strong team players who support their colleagues in reaching their goals while also considering their own workload and development. We\u2019re looking for people with a genuine passion for tax, and the future of tax, and are inspired to help the world\u2019s leading multinational organizations meet complex tax obligations around the world. If you have the confidence to speak up and influence a team that affects big businesses worldwide, this role is for you.\n\nWhat working at EY offers\n\nAt EY, our Total Rewards package supports our commitment to creating a leading people culture\u00a0-\u00a0built on high-performance teaming\u00a0-\u00a0where everyone can achieve their potential and contribute to building a better working world for our people, our clients and our communities. It's one of the many reasons we repeatedly win awards for being a great place to work.\n\nWe offer\u00a0a\u00a0competitive\u00a0compensation\u00a0package where you\u2019ll be rewarded based on your performance and recognized for the value you bring to our business. In addition, our Total Rewards package allows you decide which benefits are right for you and which ones help you create a solid foundation for your future. Our Total Rewards package includes a comprehensive medical, prescription drug and dental coverage, a defined contribution pension plan, a great vacation policy plus firm paid days that allow you to enjoy longer long weekends throughout the year, statutory holidays and paid personal days (based on province of residence), and a range of exciting programs and benefits designed to support your physical, financial and social well-being. Plus, we offer:\n\nSupport and coaching from some of the most engaging colleagues in the industry\nLearning opportunities to develop new skills and progress your career\nThe freedom and flexibility to handle your role in a way that\u2019s right for you\n\nAbout EY\n\nAs a global leader in assurance, tax, transaction and advisory services, we\u2019re using the finance products, expertise and systems we\u2019ve developed to build a better working world. That starts with a culture that believes in giving you the training, opportunities and creative freedom to make things better. Whenever you join, however long you stay, the exceptional EY experience lasts a lifetime.\n\nIf you can confidently demonstrate that you meet the criteria above, please contact us as soon as possible.\n\nMake your mark.\n\nApply today.", "employment_types": ["Full Time", "Permanent"], "selling_points": ["Higher diploma or above in Accounting", "Fresh university graduates will also be considered", "Work in Tsuen Wan"], "locations": ["Tsuen Wan Area"], "categories": ["Accounting", "Accountant", "Accounting Clerk / Supervisor", "Others"], "post_time": "2022-01-17T09:30:17Z", "salary": {"currency": null, "max": null, "min": null, "period": null, "term": null}, "salary_visible": false, "title_keywords": ["accounting", "assistant accountant", "assistant"], "responsibilities": ["tax", "reporting", "management", "analytics tools", "visualization", "data", "operations", "compliance", "teams", "communication"], "requirements": {"degrees": ["degree", "bachelor"], "majors": ["law", "finance", "economics", "business", "it", "accounting"], "languages": ["english", "chinese"], "language_level": ["excellent", "proficiency"], "hard_skills": ["crs", "microsoft office", "data analytics", "fatca", "exchange"], "soft_skills": ["communication skills", "proactive", "confidence", "advanced", "passion for", "deep", "driven", "interested in", "unique", "innovative", "mature", "committed", "genuine", "motivated", "team player", "energetic", "presentation", "hardworking"], "languages_combined": [{"language": "english", "language_level": ["excellent"]}, {"language": "chinese", "language_level": ["proficiency"]}]}, "experience_required": {"duration": [], "field": ["financial services"]}}, {"job_id": "100003009048024", "location_code": "hk", "company": "OnePlatform Wealth Management Limited", "job_title": "Assistant Officer/ Officer, Accounting", "description": "Due to our business expansion, we are looking for high calibre candidates to share our vision and venture our success.\n\nThis role will support the Finance Team of our Platform Business.\n\nResponsibilities:\n\nHandle AR/AP operations and cross check the correctness of calculation of commission in system\nAssist in month-end closing\nPrepare payment advice on commission payment\nEnsure proper commission calculation\nCross checking of team structure and provider contract\nPerform ad hoc duties as assigned by management\nRequirement:\n\nHigher Diploma in Accountancy or LCCI Higher or equivalent related disciplines\n1 - 2 years relevant accounting experiences in financial or management accounting or external audit, preferably in insurance or insurance broker industry.\nActuarial experience in calculating commission will be a definite advantage\nSelf-motivated with passion, positive mindset with good communication skills\nMature, detail-oriented and able to work independently\nOpen-minded, flexible to adapt changes in work processes and/or work assignments\nGood command of both written and spoken English and Chinese\nProficient in PC skills, particularly in MS Excel, Word and PowerPoint\nFamiliar with Flex accounting system is a plus\nLess experience will be considered as Assistant Officer, Accounting.\nWe offer competitive remuneration including career prospects to the right candidate. Interested parties please send detailed resume with availability, current and expected salaries to\u00a0Human Resources Department, OnePlatform Wealth Management Limited, Trust Tower, 68 Johnston Road, Wan Chai, Hong Kong\u00a0or by clicking the\u00a0Apply Now\u00a0button and upload your CV and cover letter.\n\n(All applications will be treated in strict confidence and used for recruitment purpose within\u00a0OnePlatform Wealth Management Limited only. All applicants are kept on file 6 months from the date of the application.)", "employment_types": ["Full Time", "Permanent"], "selling_points": ["Responsible for AR/AP processing", "Commission calculation", "Preparing payment vouchers"], "locations": ["Wan Chai"], "categories": ["Accounting", "Accounting Clerk / Supervisor", "Others"], "post_time": "2022-01-14T04:32:31Z", "salary": {"currency": null, "max": null, "min": null, "period": "monthly", "term": null}, "salary_visible": false, "title_keywords": ["assistant officer", "officer", "accounting"], "responsibilities": ["ap", "ad hoc duties", "management", "ar", "operations", "checking", "payment", "month-end closing"], "requirements": {"degrees": ["diploma"], "majors": ["related disciplines", "accountancy"], "languages": ["english", "chinese"], "language_level": ["good command"], "hard_skills": ["plus", "word", "powerpoint", "ms excel", "flex accounting", "pc skills"], "soft_skills": ["flexible", "communication skills", "self-motivated", "work independently", "positive mindset", "open-minded", "mature", "detail-oriented"], "languages_combined": [{"language": "english", "language_level": ["good command"]}, {"language": "chinese", "language_level": ["good command"]}]}, "experience_required": {"duration": ["1 - 2 years"], "field": ["management accounting", "audit", "insurance", "accounting", "financial"]}}, {"job_id": "100003009044254", "location_code": "hk", "company": "Tang Tat Home For Elder Limited", "job_title": "\u6703\u8a08\u6587\u54e1 Accounts Clerk", "description": "\u8077\u8cac\uff1a\n\n\u8ca0\u8cac\u4e00\u822c\u6587\u66f8\u8655\u7406\u3001\u8ca1\u52d9\u5de5\u4f5c\u53ca\u5354\u52a9\u63a5\u5f85\u8655\u5de5\u4f5c\n\u8ca0\u8cac\u2f47\u5e38\u6703\u8a08\u8cec\u2f6c\uff0c\u5305\u62ec\u6aa2\u6838\u670d\u52d9\u55ae\u4f4d\u5448\u4ea4\u7684\u8ca1\u52d9\u6587\u4ef6\u3001\u767c\u51fa\u2f40\u7968\u3001\u6e96\u5099\u8a18\u5e33\u6191\u8b49\u3001\u9280\u2f8f\u5c0d\u5e33\u3001\u6587\u4ef6\u5b58\u6a94\n\n\u689d\u4ef6\uff1a\n\n\u6703\u8003\u4e2d\u4e94\u6216 DSE \u4e2d\u516d\u4ee5\u4e0a\u7a0b\u5ea6\uff0c\u5177\u5099\u6703\u8a08 LCC \u4e2d\u7d1a\u6216\u4ee5\u4e0a\u7a0b\u5ea6\n\u719f\u6089\u4e2d\u3001\u82f1\u6587\u96fb\u8166\u6587\u66f8\u64cd\u4f5c\n\u81f3\u5c11\u4e09\u5e74\u6709\u95dc\u5de5\u4f5c\u7d93\u9a57\uff0c\u512a\u5148\u8003\u616e\u6709\u793e\u6703\u670d\u52d9\u6a5f\u69cb\u2f2f\u4f5c\u7d93\u9a57\n\u4e3b\u52d5\u3001\u76e1\u8cac\u3001\u8655\u4e8b\u6709\u689d\u7406\u3001\u80fd\u7368\u7acb\u2f2f\u4f5c\n\n\u2f2f\u4f5c\u5730\u9ede\uff1a\u65fa\u89d2\u5340\ufe59\u4f9b\u5348\u81b3\ufe5a\n\u85aa\u91d1$18000 \u8d77\n\n\u96fb\u8a71\uff1a23801118\n\u96fb\u90f5\uff1a''Apply Now''", "employment_types": ["Full Time", "Permanent"], "selling_points": ["\u8ca0\u8cac\u4e00\u822c\u6587\u66f8\u8655\u7406\u3001\u8ca1\u52d9\u5de5\u4f5c\u53ca\u5354\u52a9\u63a5\u5f85\u8655\u5de5\u4f5c", "\u6703\u8003\u4e2d\u4e94\u6216 DSE \u4e2d\u516d\u4ee5\u4e0a\u7a0b\u5ea6\uff0c\u5177\u5099\u6703\u8a08 LCC \u4e2d\u7d1a\u6216\u4ee5\u4e0a\u7a0b\u5ea6", "\u81f3\u5c11\u4e09\u5e74\u6709\u95dc\u5de5\u4f5c\u7d93\u9a57\uff0c\u512a\u5148\u8003\u616e\u6709\u793e\u6703\u670d\u52d9\u6a5f\u69cb\u2f2f\u4f5c\u7d93\u9a57"], "locations": ["Mong Kok"], "categories": ["Accounting", "Accounting Clerk / Supervisor", "Others", "Admin & HR", "Receptionist"], "post_time": "2022-01-13T03:33:50Z", "salary": {"currency": null, "max": null, "min": null, "period": "monthly", "term": null}, "salary_visible": false, "title_keywords": ["accounts clerk"], "responsibilities": [], "requirements": {"degrees": ["dse"], "majors": [], "languages": [], "language_level": [], "hard_skills": ["lcc"], "soft_skills": [], "languages_combined": []}, "experience_required": {"duration": [], "field": []}}, {"job_id": "100003009048754", "location_code": "hk", "company": "Compass Group Hong Kong Ltd", "job_title": "F&B Costing Assistant (Fresh Graduate will be considered)", "description": "The incumbent will be responsible for:\n\nProviding clerical and administrative support to the costing team in an effective and timely manner\nAnalyzing costs on food production and process\nCoordinating with Operations regarding menu setting and food cost\nHandling administrative duties and responsible for ad hoc projects independently as required\n\nJob Requirements:\n\nRecent graduate in Hospitality/ Accounting/ Finance or related disciplines will be considered\nCandidate with more experience will be considered as F&B Costing Officer\nWith experience in F&B industry is an advantage\nProficient in both Windows and MS Excel\nAttentive to details, good numerical sense and organizational skills\nFast learner with positive working attitude\n\nWe offer an attractive remuneration package and excellent career prospects to the right candidate.\n\nPlease refer to our website www.compass-hk.com for more information about our company.\nWe are an equal opportunity employer and welcome applications from all qualified candidates.\nPersonal data collected would be used for recruitment purposes only", "employment_types": ["Full Time", "Permanent"], "selling_points": ["Administrative support for Costing Team", "Analyzing costs, coordinate with Operations", "Fresh Graduate will be considered"], "locations": ["Mong Kok"], "categories": ["Accounting", "Accounting Clerk / Supervisor", "Others", "Hospitality / F & B", "Food & Beverage"], "post_time": "2022-01-14T07:13:19Z", "salary": {"currency": null, "max": null, "min": null, "period": "monthly", "term": null}, "salary_visible": false, "title_keywords": ["assistant"], "responsibilities": ["cost", "administrative support", "operations", "administrative duties", "ad hoc projects", "costs"], "requirements": {"degrees": [], "majors": [], "languages": [], "language_level": [], "hard_skills": ["ms excel"], "soft_skills": ["organizational skills", "independently", "attentive to details", "responsible", "timely", "positive working attitude", "fast learner"], "languages_combined": []}, "experience_required": {"duration": [], "field": ["f&b"]}}, {"job_id": "100003009045930", "location_code": "hk", "company": "Patrick Chu, Conti Wong Lawyers LLP", "job_title": "Accounts Clerk (5-day work)", "description": "Job Responsibilities:\n\nHandle full set book keeping including handling billing, preparing vouchers, receipts, payments, ledgers, cheques, bank transfer, financial reports and expenses, etc\nResponsible for daily bank/accountings operation, bank reconciliation and transaction reports\nConduct month-end closing activities including bill settlement, profit & loss statement and expenses statement, etc\nAd-hoc tasks as required\n\nRequirements:\n\n3 years\u2019 relevant working experience, working experience gained from law firm is a plus\nProficient in Microsoft Applications (especially in Excel) and Chinese word processing\nKnowledge of Libra and Peachtree will be an advantage\nMature, Independent, well-organized and detail-minded\nImmediate availability is highly preferred\u00a0\n\nWe offer:\n\n5-day work\nFringe benefits include medical coverage\n\nInterested candidates, please submit your\u00a0full resume with current salary, expected\u00a0salary and date of availability\u00a0via:\n\n1)\u00a0 \u00a0\u00a0clicking \"APPLY NOW\" button \u00a0or\n2)\u00a0 \u00a0\u00a0\"BY POST\":\u00a0\u00a0Units 2804-07, 28/F, Man Yee Building, 68 Des Voeux Road Central, Central, Hong Kong\n\nFor company information, please visit our website:\u00a0http://www.pclawyers.com.hk/\n\nAll information received will be kept in strict confidence and will be used only for employment-related purpose. Applicants who are not contacted within\u00a06 months may consider their applications unsuccessful.", "employment_types": ["Full Time", "Permanent"], "selling_points": [], "locations": ["Central"], "categories": ["Accounting", "Accounting Clerk / Supervisor", "Others", "Professional Services", "Legal & Compliance"], "post_time": "2022-01-13T16:39:46Z", "salary": {"currency": null, "max": null, "min": null, "period": "monthly", "term": null}, "salary_visible": false, "title_keywords": ["accounts clerk"], "responsibilities": ["financial reports", "receipts", "preparing vouchers", "ad-hoc tasks", "expenses", "bank reconciliation", "cheques", "month-end closing", "payments", "reports"], "requirements": {"degrees": [], "majors": [], "languages": ["chinese"], "language_level": ["proficient"], "hard_skills": ["excel", "plus", "chinese word processing", "microsoft applications", "peachtree"], "soft_skills": ["detail-minded", "independent", "well-organized", "mature"], "languages_combined": [{"language": "chinese", "language_level": ["proficient"]}]}, "experience_required": {"duration": ["3 years"], "field": ["relevant working experience"]}}, {"job_id": "100003009051400", "location_code": "hk", "company": "Insurance Authority", "job_title": "Manager (Non-life Business)", "description": "Responsibilities:\n\nReport to Directors and Team Executives\nProvide comprehensive secretarial and administrative support\nSchedule, co-ordinate and organize meetings\nArrange travel and accommodation\nPrepare correspondences\nHandle and maintain records and documents\nAd-hoc tasks and other duties as assigned\n\nRequirements: \u00a0\n\nTertiary educated\nRelevant experience in professional services firm is preferred\nProficient in Microsoft office and Chinese word processing\nStrong language skills in English and Chinese\nFluent in Mandarin\nStrong organizational, interpersonal and communication skills\n\nCompetitive package will be offered to the right candidate(s), including 5 day work week, paid examination & study leave, birthday leave & medical insurance coverage. Interested parties please send full resume with working experience, academic and professional qualifications, including present & expected salary by clicking the \"Apply Now\" button.\u00a0 Personal data collected will be used for recruitment purposes only.\n\nSimply click the \u201cApply Now\u201d button\n\nPlease visit our website at\u00a0www.moore.hk\u00a0to know more about us.", "employment_types": ["Full Time", "Permanent"], "selling_points": [], "locations": ["Southern Area"], "categories": ["Accounting", "Others", "Insurance", "Others", "Public / Civil", "Others"], "post_time": "2022-01-15T14:24:49Z", "salary": {"currency": null, "max": null, "min": null, "period": "monthly", "term": null}, "salary_visible": false, "title_keywords": ["manager"], "responsibilities": ["other duties", "administrative support", "ad-hoc tasks", "maintain", "schedule", "report"], "requirements": {"degrees": [], "majors": [], "languages": ["english", "chinese", "mandarin"], "language_level": ["fluent", "proficient"], "hard_skills": ["chinese word processing", "microsoft office"], "soft_skills": ["communication skills", "organizational", "interpersonal"], "languages_combined": [{"language": "english", "language_level": []}, {"language": "chinese", "language_level": ["proficient"]}, {"language": "mandarin", "language_level": ["fluent"]}]}, "experience_required": {"duration": [], "field": ["relevant experience"]}}, {"job_id": "100003009047698", "location_code": "hk", "company": "Moore Associates Limited", "job_title": "Secretary", "description": "Responsibilities:\n\nResponsible for daily accounting operations including expenses, accounts payable, general ledger\nHandle staff expenses reimbursement\nAssist in month-end closing and year-end audit\nAssist in preparing HK tax computation for related entities\nUpdate accounting reports for management\u2019s review\nAssist in other accountings duties as assigned\n\nRequirements:\n\n\nDiploma Holder or LCCI Higher with 2 - 4 years\u2019 relevant accounting experience, preferably gained in property development sector\nBasic China accounting knowledge preferred and experience in group consolidation is a definite advantage\nProficient in MS Office applications, especially in Excel and experience in using Flex accounting system is an advantage\nResponsible, proactive, detail-oriented and able to work independently and efficiently with minimum supervision\nA team player with good communication skills\nProficient in spoken and written English and Chinese (Cantonese and Putonghua\nImmediate available is an advantage\n\nWe work 5 days per week.\n\nInterested parties, please click \"APPLY NOW\" and attach with your application letter and full resume.\u00a0\n\nFor further information of the Wharf Group, please visit our website:\u00a0www.wharfholdings.com", "employment_types": ["Full Time", "Permanent"], "selling_points": ["Secretarial and administrative support", "Tertiary educated", "Schedule, co-ordinate and organize meetings"], "locations": ["Tsim Sha Tsui"], "categories": ["Accounting", "Others", "Admin & HR", "Secretary"], "post_time": "2022-01-15T03:49:49Z", "salary": {"currency": null, "max": null, "min": null, "period": "monthly", "term": null}, "salary_visible": false, "title_keywords": ["secretary"], "responsibilities": ["year-end", "management", "tax computation", "general ledger", "expenses", "review", "daily accounting operations", "audit", "month-end closing", "reports", "accounts payable"], "requirements": {"degrees": ["diploma holder"], "majors": ["accounting"], "languages": ["cantonese", "putonghua", "english", "chinese"], "language_level": ["proficient"], "hard_skills": ["excel", "flex accounting", "basic", "ms office"], "soft_skills": ["communication skills", "work independently", "responsible", "detail-oriented", "team player", "proactive"], "languages_combined": [{"language": "cantonese", "language_level": ["proficient"]}, {"language": "putonghua", "language_level": ["proficient"]}, {"language": "english", "language_level": ["proficient"]}, {"language": "chinese", "language_level": ["proficient"]}]}, "experience_required": {"duration": ["2 - 4 years"], "field": ["development", "accounting experience", "accounting", "consolidation"]}}, {"job_id": "100003009049381", "location_code": "hk", "company": "Shanghai Commercial Bank Ltd", "job_title": "Officer, Internal Audit", "description": "Snapshot\n\nAn exciting opportunity to join a sizeable MPF Group as a Senior Fund Accounting Manager, to be responsible for evaluating NAV, fund administration work while leading the team.\n\nCompany Profile\n\nOur client, a sizeable MPF Group, is looking for a Senior Fund Accounting Manager to join the team\n\nExciting new role for you\n\nResponsible for computing NAV daily and related fund accounting duties\nMonitor and supervise the preparation of valuation reports\nEnsure operation and workflow are comply with both internal and external regulations\nEngage in UAT testing\n\nRequirements\n\nDegree holder in Business, Accounting, Finance or related discipline\nAt least 8 years in fund administration, less experienced candidate will be considered as Manager\nTeam player with experience in management\nGood command of English and Chinese\n\nRewards\n\nSizeable platform with stable career growth and attractive remuneration package", "employment_types": ["Full Time", "Permanent"], "selling_points": ["Perform audit assignments on banking products", "Propose solutions to mitigate potential risks", "Assist to prepare audit reports"], "locations": ["Kwun Tong"], "categories": ["Accounting", "Audit", "Others", "Banking / Finance", "Others"], "post_time": "2022-01-15T03:50:21Z", "salary": {"currency": null, "max": null, "min": null, "period": "monthly", "term": null}, "salary_visible": false, "title_keywords": ["officer"], "responsibilities": ["regulations", "valuation", "management", "mpf", "monitor", "uat testing", "reports", "accounting duties", "administration"], "requirements": {"degrees": ["degree holder"], "majors": ["finance", "business", "accounting"], "languages": ["english", "chinese"], "language_level": ["good command"], "hard_skills": [], "soft_skills": ["team player", "stable", "responsible"], "languages_combined": [{"language": "english", "language_level": ["good command"]}, {"language": "chinese", "language_level": ["good command"]}]}, "experience_required": {"duration": [], "field": ["management", "team"]}}, {"job_id": "100003009054510", "location_code": "hk", "company": "PERSOLKELLY Hong Kong Limited", "job_title": "Senior Fund Accounting Manager (up to 60k p/m + bonus)", "description": "We are a renowned hotel tableware company based in HK, with sales network worldwide, are looking for candidates with high calibre. Candidates interested in below post please send application letter and resume to us\u00a0for further consideration.\n\u00a0\nResponsibilities\n\nHandle full set of accounts\nGood team player, with strong sense of responsibilities\nPerform ad hoc assignments as required\n\n\u00a0Requirements\n\nDSE or F.5 with LCCI level 2 or above\nAt least 1 - 2 years of accounting experience\nFluent Cantonese, Fair Mandarin & English\nGood knowledge in excel, word, MYOB and ERP is preferable\nIndependent, proactive and work under pressure\nImmediately available is preferred", "employment_types": ["Full Time", "Permanent"], "selling_points": ["Banking MPF Group, Manager - Senior Manager wanted", "Fund Accounting and Administration", "Team management experience preferred"], "locations": ["Central & Western Area"], "categories": ["Accounting", "Finance / Accounting Manager", "Others", "Banking / Finance", "Fund Management"], "post_time": "2022-01-17T09:49:32Z", "salary": {"currency": null, "max": null, "min": null, "period": "monthly", "term": null}, "salary_visible": false, "title_keywords": ["accounting manager"], "responsibilities": ["full set of accounts", "ad hoc assignments"], "requirements": {"degrees": ["dse"], "majors": [], "languages": ["cantonese", "english", "mandarin"], "language_level": ["fluent"], "hard_skills": ["excel", "myob", "word", "erp"], "soft_skills": ["proactive", "independent", "work under pressure"], "languages_combined": [{"language": "cantonese", "language_level": ["fluent"]}, {"language": "english", "language_level": ["fluent"]}, {"language": "mandarin", "language_level": ["fluent"]}]}, "experience_required": {"duration": ["at least 1 - 2 years"], "field": ["accounting experience"]}}, {"job_id": "100003009046913", "location_code": "hk", "company": "Athena Tableware HK Limited", "job_title": "Account Clerk", "description": "Requirements\nAccounting graduate\nStudent member of HKICPA or equivalent\nGood command in written and spoken English and Chinese, fluency in Putonghua is an advantage\nKnowledge in using general computer software\nIndependent, self-motivated and be able to work under pressure and meet deadlines\nAt least 2-3 years audit experience\nWe offer\nAttractive salary and bonus scheme\n5-days work\nMedical benefits\nHigh quality training\nPlease apply with full resume together with current and expected salary to email via \"Apply Now\"\n\nPersonal data collected will be used for recruitment purpose only", "employment_types": ["Full Time", "Permanent"], "selling_points": ["DSE or F.5", "Knowledge of MYOB", "Proficient in MS Excel"], "locations": ["Kwun Tong"], "categories": ["Accounting", "Accounting Clerk / Supervisor", "Others", "Admin & HR", "Clerical / Admin Staff"], "post_time": "2022-01-14T01:45:32Z", "salary": {"currency": null, "max": null, "min": null, "period": "monthly", "term": null}, "salary_visible": false, "title_keywords": ["account clerk"], "responsibilities": ["software", "audit", "work under pressure"], "requirements": {"degrees": [], "majors": [], "languages": ["putonghua", "english", "chinese"], "language_level": ["fluency", "advantage", "good command"], "hard_skills": ["hkicpa"], "soft_skills": ["meet deadlines", "self-motivated", "independent", "work under pressure"], "languages_combined": [{"language": "putonghua", "language_level": ["fluency", "advantage", "good command"]}, {"language": "english", "language_level": ["fluency", "advantage", "good command"]}, {"language": "chinese", "language_level": ["fluency", "advantage", "good command"]}]}, "experience_required": {"duration": ["at least 2-3 years"], "field": ["audit experience"]}}, {"job_id": "100003009047440", "location_code": "hk", "company": "Wong Brothers CPA Limited", "job_title": "Assistant Accountant / Accountant in Audit Department", "description": "Responsibilities:\n\nHandle full set of accounts independently\nHandling accounts payable and receivable\nPreparing financial reports\nRequirements :\n\nSecondary 5\n5 Year(s) Experience Required\nKnowledge peachtree\nFluent Cantonese ; Fair Putonghua ; Fair English\nAble to read & write Chinese ; Able to read & write English\nEmployment Terms:\nDouble Pay\nMon to Fri: 9:30AM-6:00PM and Sat: 9:30AM-1:00PM, 5 - 5.5 working days per week, 8.5 working hours per day\nApplication Information:\n\nJob seekers may e-mail\u00a0resume to GLOBAL CAPITAL INTERNATIONAL TRADING LIMITED. To obtain a copy of Personal Information Collection Statement, please contact MISS MA by Email.", "employment_types": ["Full Time", "Permanent"], "selling_points": [], "locations": ["Not Specified"], "categories": ["Accounting", "Accountant", "Accounting Clerk / Supervisor", "Others"], "post_time": "2022-01-15T03:49:40Z", "salary": {"currency": null, "max": null, "min": null, "period": "monthly", "term": null}, "salary_visible": false, "title_keywords": ["accountant", "assistant accountant"], "responsibilities": ["financial reports", "full set of accounts", "accounts payable"], "requirements": {"degrees": [], "majors": [], "languages": ["cantonese", "putonghua", "english", "chinese"], "language_level": ["fluent"], "hard_skills": ["peachtree"], "soft_skills": [], "languages_combined": [{"language": "cantonese", "language_level": ["fluent"]}, {"language": "putonghua", "language_level": []}, {"language": "english", "language_level": []}, {"language": "chinese", "language_level": []}]}, "experience_required": {"duration": [], "field": []}}, {"job_id": "100003009048418", "location_code": "hk", "company": "Global Capital International Trading Limited", "job_title": "Account Clerk \u6703\u8a08\u6587\u54e1", "description": "Responsibilities:\n\nResponsible for credit control by following up delinquent accounts, monitoring irregularities, and enforcing payments by taking recovery actions\nSupervise billings and payment status of rental collection and prepare monthly account receivable reports\nHandle tenants\u2019 enquiries and complaints\nOther ad-hoc assignments as required\n\nRequirements:\n\nDegree holder in Accounting, Business Administration or related disciplines\nAt least 3 years\u2019 solid credit control experience preferably in billing and rental collection\nResponsible, attentive to details and self-motivated\nGood analytical and interpersonal skills\nProficiency in Microsoft Word and Excel\nGood command in both written and spoken English and Chinese\nLegal knowledge on delinquent accounts related to landlord and tenants will be an advantage\nCandidate with more experience will be considered as Senior Accounts Receivable Officer\n\nWe offer competitive remuneration package that commensurate with experience and qualifications.\u00a0 Interested parties are invited to send full resume stating contact telephone number, date available, present and expected salary to our recruitment email address.\n\n(Personal data provided will be used strictly in accordance with the Company's personal data policy which is available upon request.)", "employment_types": ["Full Time", "Permanent"], "selling_points": [], "locations": ["Cheung Sha Wan"], "categories": ["Accounting", "Accounting Clerk / Supervisor", "Audit", "Others"], "post_time": "2022-01-14T06:30:17Z", "salary": {"currency": null, "max": null, "min": null, "period": "monthly", "term": null}, "salary_visible": false, "title_keywords": ["account clerk"], "responsibilities": ["control", "irregularities", "ad-hoc assignments", "billings", "monitoring", "payment", "payments", "reports"], "requirements": {"degrees": ["degree holder"], "majors": ["related disciplines", "accounting", "business administration"], "languages": ["english", "chinese"], "language_level": ["good command"], "hard_skills": ["excel", "microsoft word"], "soft_skills": ["attentive to details", "interpersonal skills", "self-motivated", "responsible"], "languages_combined": [{"language": "english", "language_level": ["good command"]}, {"language": "chinese", "language_level": ["good command"]}]}, "experience_required": {"duration": ["at least 3 years"], "field": ["billing"]}}, {"job_id": "100003009044919", "location_code": "hk", "company": "Wharf Estates Limited", "job_title": "SENIOR ACCOUNTS RECEIVABLE OFFICER / ACCOUNTS RECEIVABLE OFFICER", "description": "Job Responsibilities:\n\nHandle daily accounting transactions, operations, data input and filing;\nFollow and monitor accounts payable transaction;\nPrepare payment vouchers, cheques and accounting records;\nAssist in Daily Worker Payroll;\nResponsible for outdoor assignments such as cheques bank-in, etc.\n\nRequirements:\n\nDiploma or equivalent in above in Accounting;\u00a0\nWith LCCI level II and 3 years experience and experience in construction industry is an advantage;\nDetail minded and good communication skills;\nAble to work independently, Self-motivated and responsible;\nGood command of MS office and accounting software;\nApplicant with less experience will be considered as Senior Account Clerk.\n\nInterested parties please apply with detailed resume stating expected salary and date of availability to Mr. Henry Fu via email by clicking \"Apply Now\"\u00a0or fax to 2635 0611.\u00a0\n\n[ Personal data collected will be used for recruitment-related purposes only. ]", "employment_types": ["Full Time", "Permanent"], "selling_points": ["Responsible for credit control", "Degree holder in Accounting", "At least 3 years\u2019 solid credit control experience"], "locations": ["Tsim Sha Tsui"], "categories": ["Accounting", "Accounting Clerk / Supervisor", "Credit Control", "Others"], "post_time": "2022-01-15T03:49:24Z", "salary": {"currency": null, "max": null, "min": null, "period": null, "term": null}, "salary_visible": false, "title_keywords": ["senior accounts receivable officer", "accounts receivable officer"], "responsibilities": ["operations", "monitor", "data input", "transactions", "payment", "cheques", "daily accounting", "payroll", "accounts payable"], "requirements": {"degrees": ["diploma"], "majors": ["accounting"], "languages": [], "language_level": [], "hard_skills": ["accounting software", "ms office"], "soft_skills": ["communication skills", "work independently", "self-motivated", "responsible"], "languages_combined": []}, "experience_required": {"duration": ["3 years"], "field": ["construction industry"]}}, {"job_id": "100003009046926", "location_code": "hk", "company": "Cheung Hing Lifting Components (Hong Kong) Limited", "job_title": "Accountant", "description": "\u4e2d\u4e94\u7a0b\u5ea6; 1\u5e74\u7d93\u9a57; \u826f\u597d\u7cb5\u8a9e; \u4e00\u822c\u666e\u901a\u8a71; \u4e00\u822c\u82f1\u8a9e; \u61c2\u8b80\u5beb\u4e2d\u6587; \u7565\u61c2\u8b80\u5beb\u82f1\u6587; \u61c2Microsoft Office; \u61c2MYOB; \u61c2MS Word; \u61c2MS Excel; \u61c2\u82f1\u6587\u6253\u5b57; \u61c2\u4e2d\u6587\u6253\u5b57; \u5177\u6709\u57fa\u672c\u96fb\u8166\u64cd\u4f5c\u77e5\u8b58; \u8655\u4e8b\u7d30\u5fc3\u3001\u6709\u689d\u7406\u53ca\u6709\u8cac\u4efb\u5fc3\n\n\u6bcf\u5c0f\u6642$60.00 - $70.00, \u661f\u671f\u4e00\u81f3\u4e94: \u4e0a\u53489\u6642\u81f3\u4e0b\u53486\u6642, \u6bcf\u9031\u5de5\u4f5c2\u5929\u81f35\u5929\n\n", "employment_types": ["Full Time", "Permanent"], "selling_points": ["Prepare vouchers and input accounting data", "Maintain records on corporate databases", "At least 3 year accounting experience"], "locations": ["Tsim Sha Tsui"], "categories": ["Accounting", "Accountant", "Others", "Admin & HR", "Clerical / Admin Staff"], "post_time": "2022-01-14T01:45:50Z", "salary": {"currency": null, "max": null, "min": null, "period": "monthly", "term": null}, "salary_visible": false, "title_keywords": ["accountant"], "responsibilities": [], "requirements": {"degrees": [], "majors": [], "languages": [], "language_level": [], "hard_skills": ["excel", "word"], "soft_skills": [], "languages_combined": []}, "experience_required": {"duration": [], "field": []}}, {"job_id": "100003009045893", "location_code": "hk", "company": "Man Lok Yuen Food Trading Limited", "job_title": "\u517c\u8077\u6703\u8a08/\u7c3f\u8a18\u6587\u54e1", "description": "Job Responsibilities:\n\nPerform daily accounting duties including data entry and basic accounts support\nHandle AR, AP, assist in payment process\nProvide clerical & administrative support, such as\u00a0answer telephone calls, order stationery,\u00a0filing & scanning\nPerform other ad hoc assignment as required\nRequirements:\n\n\nF.5 HKCEE 5 subjects passed including English\nLCCI Level 2 or above\nOver 1 year working experience in accounting work\nGood command of written and spoken in English, Mandarin and Cantonese\nPositive attitude, detailed minded with good interpersonal skill\nImmediately available is highly preferred\nHK permanent only", "employment_types": ["Part Time"], "selling_points": ["\u5b88\u6642", "\u6709\u8cac\u4efb\u5fc3", "\u8655\u4e8b\u7d30\u5fc3"], "locations": ["Shatin Area"], "categories": ["Accounting", "Others"], "post_time": "2022-01-13T09:02:53Z", "salary": {"currency": null, "max": null, "min": null, "period": "hourly", "term": null}, "salary_visible": false, "title_keywords": [], "responsibilities": ["ap", "scanning", "ar", "data entry", "administrative support", "ad hoc assignment", "stationery", "payment process", "daily accounting"], "requirements": {"degrees": [], "majors": [], "languages": ["cantonese", "english", "mandarin"], "language_level": ["good command"], "hard_skills": [], "soft_skills": ["positive attitude", "interpersonal skill", "detailed"], "languages_combined": [{"language": "cantonese", "language_level": ["good command"]}, {"language": "english", "language_level": ["good command"]}, {"language": "mandarin", "language_level": ["good command"]}]}, "experience_required": {"duration": ["1 year"], "field": ["accounting"]}}, {"job_id": "100003009051254", "location_code": "hk", "company": "Lynux Shipping Limited", "job_title": "Assistant Accountant (Double Pay + 14 days AL)", "description": "Job Offers\n\nDouble Pay\nDiscretionary performance bonus\nMarriage leave\nVolunteer leave\nGroup Medical & Life Insurance coverage including dependents\nTraining sponsorship\nFriendly working environment\nComplimentary Shuttle bus service from Tsing Yi station to office (5 minutes\u2019 drive way)\n\nKey Responsibilities:\n\nManage overheads and support in all issues related to accounts payable and receivable;\nManage the suppliers\u2019 invoices and payments;\nCarry out cost studies, cost planning and control and cost analysis;\nEnsure the agents account reconciliation are up to date and collection is done on time;\nReview services contract with global legal team and the client;\nAssist with Global Services Office operating cost control;\nOther ad hoc duties as assigned.\nJob Requirements:\nBachelor degree in Accounting/ Finance or above;\nMinimum 6 years\u2019 working experience in accounting field;\nExcellent skill in MS Office application;\nProficient in verbal and written English and Chinese;\nMature and with pleasant personality;\nDetail-oriented, able to handle multi-tasks and work under pressure.\n\nCandidate with less experience will be considered as Accountant.\n\nYou are invited to send in your full CV by email to [via Apply Now ].\n\nInformation provided will be treated strictly confidential and only be used for recruitment purposes.\n\nFor more information of Aramex, please visit us at aramex.com.", "employment_types": ["Full Time", "Permanent"], "selling_points": ["5-day work, Meal allowance", "13th Month Pay", "14 days Annual Leave"], "locations": ["Central"], "categories": ["Accounting", "Accounting Clerk / Supervisor", "Others", "Admin & HR", "Clerical / Admin Staff"], "post_time": "2022-01-15T06:22:10Z", "salary": {"currency": null, "max": null, "min": null, "period": "monthly", "term": null}, "salary_visible": false, "title_keywords": ["assistant accountant"], "responsibilities": ["ad hoc duties", "cost", "control", "invoices", "review", "cost planning", "payments", "cost control", "cost analysis", "accounts payable"], "requirements": {"degrees": ["degree", "bachelor"], "majors": ["finance", "accounting"], "languages": ["english", "chinese"], "language_level": ["proficient"], "hard_skills": ["ms office"], "soft_skills": ["multi-tasks", "mature", "detail-oriented", "pleasant", "work under pressure"], "languages_combined": [{"language": "english", "language_level": ["proficient"]}, {"language": "chinese", "language_level": ["proficient"]}]}, "experience_required": {"duration": ["minimum 6 years"], "field": ["accounting"]}}, {"job_id": "100003009051918", "location_code": "hk", "company": "Aramex Hong Kong Limited", "job_title": "Senior Accountant", "description": "Job Requirements:\n\nHolder of DSE Certificate or above ;\n1-2 years relevant experience ;\nGood computer skills, MS Office;\nIndependent, hard-working and mature;\n\n\n\nResponsibilities:\n\nHandling full sets of book-keeping\nAssist in accounts receivables, accounts payables and general ledger duties\nAssist in month end closing and prepare accounting schedules and breakdown\nAssist secretarial and administrative work\nAssist in ad-hoc assignments\n\n\n\nInterested candidates please send full resume with expected salary by clicking \"Apply Now\".\n\n\n(Data collected will be used for recruitment purpose only)", "employment_types": ["Full Time", "Permanent"], "selling_points": ["Multi-national working culture", "13 months' salary and discretionary bonus", "Minimum 6 years\u2019 working experience in accounting"], "locations": ["Tsing Yi"], "categories": ["Accounting", "Accountant", "Accounting Clerk / Supervisor", "Others"], "post_time": "2022-01-17T01:32:40Z", "salary": {"currency": null, "max": null, "min": null, "period": "monthly", "term": null}, "salary_visible": false, "title_keywords": ["senior accountant"], "responsibilities": ["month end closing", "administrative work", "schedules", "general ledger", "ad-hoc assignments", "book-keeping"], "requirements": {"degrees": ["certificate", "dse"], "majors": [], "languages": [], "language_level": [], "hard_skills": ["computer skills", "ms office"], "soft_skills": ["independent", "hard-working", "mature"], "languages_combined": []}, "experience_required": {"duration": ["1-2 years"], "field": ["relevant experience"]}}, {"job_id": "100003009047027", "location_code": "hk", "company": "LT Business Consultants Limited", "job_title": "Accounts Clerk", "description": "Responsibilities:-\n\n\n\nTo provide clerical support to our legal function.\nTo support the drafting of commercial agreements.\nTo coordinate meetings to deal with legal and contracting matters.\nTo manage billings from external legal counsels.\nTo handle\u00a0 other administrative duties of our legal function.\nTo support our corporate finance function when it is required.\n\nRequirements:-\n\nBachelor\u2019s degree in business administration or legal studies\nBasic understanding in business law\n2-3 years of experience in similar positions\nGood command of spoken and written English and Chinese (Cantonese & Mandarin)\nProficiency in MS Office applications\n\nWe offer an attractive basic salary, 5-day work, on-the-job training and career advancement opportunity to the right candidates.\u00a0 Please send full resume with availability, current and expected salary by clicking \"Apply Now\"\u00a0\n\n\u00a0Benefits\n\n\u00a0\u00a0\u00a0\u00a0\u00a0\u00a0\u00a0\u00a0 Five-day work\n\u00a0\u00a0\u00a0\u00a0\u00a0\u00a0\u00a0\u00a0 Bank Holidays\n\u00a0\u00a0\u00a0\u00a0\u00a0\u00a0\u00a0\u00a0 Medical Insurance\n\u00a0\u00a0\u00a0\u00a0\u00a0\u00a0\u00a0\u00a0 12+ Days Annual leave\n\u00a0\u00a0\u00a0\u00a0\u00a0\u00a0\u00a0\u00a0 Paid Marriage Leave\n\u00a0\u00a0\u00a0\u00a0\u00a0\u00a0\u00a0\u00a0 Birthday Leave\n\n\u00a0(Personal data collected will be used for recruitment purpose only.)", "employment_types": ["Full Time", "Permanent"], "selling_points": [], "locations": ["Central & Western Area"], "categories": ["Accounting", "Accounting Clerk / Supervisor", "Others"], "post_time": "2022-01-14T02:04:53Z", "salary": {"currency": null, "max": null, "min": null, "period": "monthly", "term": null}, "salary_visible": false, "title_keywords": ["accounts clerk"], "responsibilities": ["provide clerical support", "billings", "coordinate", "administrative duties", "contracting"], "requirements": {"degrees": ["degree", "bachelor"], "majors": ["business administration"], "languages": ["cantonese", "english", "chinese", "mandarin"], "language_level": ["good command"], "hard_skills": ["basic", "ms office"], "soft_skills": [], "languages_combined": [{"language": "cantonese", "language_level": ["good command"]}, {"language": "english", "language_level": ["good command"]}, {"language": "chinese", "language_level": ["good command"]}, {"language": "mandarin", "language_level": ["good command"]}]}, "experience_required": {"duration": ["2-3 years"], "field": []}}, {"job_id": "100003009044127", "location_code": "hk", "company": "Phase Scientific International Limited", "job_title": "Legal Assistant", "description": "Responsibilities:\n\nResponsible for the preparation of consolidation reports and\u00a0financial statements, the preparation of management & analysis reports and ad-hoc projects / assignments, and managing taxation affairs, etc.\nAssist in preparing quarter-end closing\nPerform ad-hoc assignments\n\nRequirements:\n\nDegree holder in accounting and finance with accounting qualification of ACCA/HKICPA or equivalent\nMinimum 3 years relevant experience in\u00a0sizable CPA firms\nFamiliar with accounting standards and statutory requirements\nStrong sense of responsibility, self-motivated, detailed-oriented and independent\nGood command of spoken and written English and Chinese\nComputer knowledge is required, preferably with knowledge of Chinese input\n\nInterested parties please send resume with day time contact telephone number and expected salary to Human Resources Department,\u00a07/F Three Pacific Place, 1 Queen\u2019s Road East, Hong Kong\u00a0or\u00a0fax to 2865 7517\u00a0or visit our\u00a0website\u00a0for email application.\n\nPlease visit our website (www.coli.com.hk) for more information about us.\n\nApplicants who are not invited within 2 months may consider their applications unsuccessful.\u00a0 All information provided by applicants will be treated in strict confidence and used only for recruitment purposes.\u00a0 Applicants may be considered for other suitable positions within the China Overseas Group and its related companies over a one-year period, after which their personal data will be destroyed.", "employment_types": ["Full Time", "Permanent"], "selling_points": ["Provide clerical support to our legal function", "Support the drafting of commercial agreements", "Support corporate finance function"], "locations": ["Kwun Tong"], "categories": ["Accounting", "Others", "Admin & HR", "Clerical / Admin Staff", "Professional Services", "Legal & Compliance"], "post_time": "2022-01-13T03:09:19Z", "salary": {"currency": null, "max": null, "min": null, "period": "monthly", "term": null}, "salary_visible": false, "title_keywords": ["legal assistant"], "responsibilities": ["taxation", "management", "analysis reports", "ad-hoc assignments", "financial statements", "reports", "ad-hoc projects"], "requirements": {"degrees": ["degree holder"], "majors": ["finance", "accounting"], "languages": ["english", "chinese"], "language_level": ["good command"], "hard_skills": ["chinese input", "cpa", "acca", "hkicpa"], "soft_skills": ["self-motivated", "independent", "detailed", "sense of responsibility"], "languages_combined": [{"language": "english", "language_level": ["good command"]}, {"language": "chinese", "language_level": ["good command"]}]}, "experience_required": {"duration": ["minimum 3 years"], "field": ["relevant experience"]}}, {"job_id": "100003009047349", "location_code": "hk", "company": "China Overseas Land & Investment Limited", "job_title": "Accountant", "description": "Requirements:\n\n- University graduate in Accountancy or Business Administration\n\n- Qualified Members or finalist of HKICPA or other relevant professional bodies\n\n-\u00a03-5\u00a0years\u00a0relevant experience from mid-tier CPA firms.\n\n- Experience on audit of listed or sizable multi-national companies would be an advantage\n\n- Fluency on both spoken and written\u00a0English and Chinese\n\n- Good time management\n\n- Good communication and interpersonal skills\u00a0\u00a0\u00a0\n\nWe offer an attractive remuneration package, excellent career prospects in a warm and friendly atmosphere. Our continuing expansion and growth offer numerous opportunities.\n\nIf you consider yourself the appropriate choice, please forward your CV and salary expectations with the application form\u00a0to the Human Resources Department, 2/F 625 King\u2019s Road, North Point, Hong Kong or by\u00a0clicking \u201cApply Now\u201d.\u00a0\u00a0\u00a0\n\nDownload Application Form\n\nSelected candidates will be notified by phone for interview arrangements within 6 weeks. Applications of unsuccessful candidates will be deleted immediately after screening.\n\nPersonal data provided by job applicants will be used strictly in accordance with the Employer's Personal Data Policies, a copy of which will be provided upon request.\n\nBaker Tilly Hong Kong\u00a0is a leading firm of certified public accountants and business advisers, specialising in providing clients with a range of integrated services. Our firm is driven by 300 directors and professional staff based in Hong Kong.", "employment_types": ["Full Time", "Permanent"], "selling_points": ["5-days work per week", "Sound career development", "Energetic team"], "locations": ["Admiralty"], "categories": ["Accounting", "Accountant", "Audit", "Others"], "post_time": "2022-01-14T02:52:57Z", "salary": {"currency": null, "max": null, "min": null, "period": "monthly", "term": null}, "salary_visible": false, "title_keywords": ["accountant"], "responsibilities": ["communication", "management", "audit", "administration"], "requirements": {"degrees": ["university graduate"], "majors": ["business administration", "accountancy"], "languages": ["english", "chinese"], "language_level": ["fluency"], "hard_skills": ["cpa", "hkicpa"], "soft_skills": ["time management", "communication and interpersonal skills"], "languages_combined": [{"language": "english", "language_level": ["fluency"]}, {"language": "chinese", "language_level": ["fluency"]}]}, "experience_required": {"duration": ["3-5 years"], "field": ["relevant experience", "audit"]}}, {"job_id": "100003009049256", "location_code": "hk", "company": "Baker Tilly Hong Kong", "job_title": "Audit Senior", "description": "Reporting to the Assistant Manager, Operations Support, you will be responsible for monitoring and supervision to service of Account Opening.\nResponsibilities:\nProcess the account opening applications compliant with internal policies and local regulatory requirements;\nConduct KYC (Know Your Client) /CDD (Customer Due Diligence) / AML (Anti-Money Laundering) review on new client relationships;\nPerform maker role for account opening customer system data input;\nAssist with ad hoc projects as assigned;\nPerform back-up function to Operations Support teams.\nTo meet the challenge, you should have the following qualifications and attributes:\nMatriculated, Degree holder in Banking / Business Administration / Finance is preferred\nAt least 5 years banking experience. Experience in Branch operations is an advantage\nAble to work independently and under pressure\nGood PC knowledge\nGood communication and interpersonal skills\nSelf-motivated with analytical mind\nCandidates with less experiences may be considered as Officer, Operations Support.\nPlease note that only shortlisted candidates will be notified.", "employment_types": ["Full Time", "Permanent"], "selling_points": ["3-5 years relevant experience from CPA firms", "University graduate in Accountancy", "Fluency on English and Chinese"], "locations": ["Quarry Bay"], "categories": ["Accounting", "Accountant", "Audit", "Others"], "post_time": "2022-01-14T08:19:54Z", "salary": {"currency": null, "max": null, "min": null, "period": "monthly", "term": null}, "salary_visible": false, "title_keywords": [], "responsibilities": ["reporting", "aml", "policies", "operations", "monitoring", "account opening", "regulatory requirements", "cdd", "review", "system data", "customer due diligence", "teams", "banking", "ad hoc projects", "communication", "kyc", "administration"], "requirements": {"degrees": ["degree holder"], "majors": ["finance", "business administration"], "languages": [], "language_level": [], "hard_skills": ["aml", "cdd", "account opening", "customer due diligence", "anti-money laundering", "kyc", "pc knowledge"], "soft_skills": ["work independently", "self-motivated", "under pressure", "responsible", "communication and interpersonal skills", "analytical mind"], "languages_combined": []}, "experience_required": {"duration": ["at least 5 years"], "field": ["banking experience"]}}, {"job_id": "100003009050642", "location_code": "hk", "company": "Dah Sing Financial Group", "job_title": "Senior Officer, Operations Support (Customer Due Diligence)", "description": "Job Description:\nReporting to the Main Board Director in charge of the function, the Manager - Cost Audit Department, preferably with procurement background,\u00a0will be leading the Cost Audit and Expenditure Budget Units covering HK or Mainland investment properties to ensure the operational expenditure meets business objectives and budget. The said Units shall conduct compliance check and to offer their opinion on the procurement requisitions according to Company\u2019s policies and procedures and control systems.\u00a0\nResponsibilities:\nLead and manage the Cost Audit Unit and Expenditure Budget Unit to review the transitional procurement requisitions and evaluate them against the approved budgets for budgetary control purpose.\nProvide necessary payment analysis to facilitate accounts payable control. Monitor performance of suppliers and tenderers versus their qualifications.\u00a0\nProvide timely and accurate expenditure information and status to Management for strategic planning and control purposes.\nRequirements:\nAt least 15 years of proven track record in sizable corporations on related experience.\nPractical execution experience in procurement activities and control is prerequisite.\u00a0\nBachelor\u2019s degree or professional qualification in procurement or engineering preferable.\nA team player and be able to communicate with all levels.\u00a0\nSwift and proactive to risk management issues with constructive opinion.\nWe offer competitive remuneration package that commensurate with experience and qualifications.\u00a0 Interested parties are invited to send full resume by clicking \"Apply Now\" stating contact telephone number, date available, present and expected salary to our recruitment email address.\n(Personal data provided will be used strictly in accordance with the Company\u2019s personal data policy which is available upon request.)", "employment_types": ["Full Time"], "selling_points": ["Assist with ad hoc projects as assigned", "Matriculated, Degree holder in Banking", "At least 5 years banking experience"], "locations": ["Not Specified"], "categories": ["Accounting", "Others", "Banking / Finance", "Corporate Banking", "Order Processing & Operation / Settlement"], "post_time": "2022-01-14T11:04:45Z", "salary": {"currency": null, "max": null, "min": null, "period": "monthly", "term": null}, "salary_visible": false, "title_keywords": ["senior officer", "operations"], "responsibilities": ["reporting", "cost", "control", "budgets", "management", "strategic planning", "policies", "analysis", "budget", "compliance", "audit", "procedures", "systems", "review", "evaluate", "payment", "accounts payable", "monitor performance"], "requirements": {"degrees": ["degree", "bachelor"], "majors": ["engineering"], "languages": [], "language_level": [], "hard_skills": ["swift"], "soft_skills": ["team player", "proactive", "constructive"], "languages_combined": []}, "experience_required": {"duration": ["at least 15 years"], "field": ["related", "procurement"]}}, {"job_id": "100003009049412", "location_code": "hk", "company": "Wharf Real Estate Investment Company Limited", "job_title": "Manager \u2013 Cost Audit Department", "description": "Responsibilities :\u00a0\n\n\nHandle full set of accounts for various group companies and related financial accounting duties\u00a0 \u00a0\nAssist in preparing monthly, quarterly, interim and final consolidated management accounts\nAssist in other accounting duties as assigned\n\nRequirements :\n\n\nDiploma Holder or LCCI Higher with 2 - 4 years\u2019 relevant accounting experience in handling full set of accounts\nExperience in group consolidation is a definite advantage\nProficient in MS Office applications, especially in Excel, and experience in using Flex accounting system preferred\nOrganized, detail-oriented and able to work independently and efficiently with minimum supervision\nA team player with good communication skills\nImmediate available is an advantage\nCandidates with less experience or lower qualification will be considered as Accounts Clerk.\n\n\nInterested parties, please click \"APPLY NOW\" and attach with your application letter and full resume.\u00a0\n\nFor further information of the Wharf Group, please visit our website: www.wharfholdings.com", "employment_types": ["Full Time", "Permanent"], "selling_points": ["Lead Cost Audit and Expenditure Budget Units", "At least 15 years of proven track record", "Bachelor\u2019s degree or professional qualification"], "locations": ["Tsim Sha Tsui"], "categories": ["Accounting", "Audit", "Others", "Merchandising & Purchasing", "Procurement / Purchasing / Sourcing"], "post_time": "2022-01-15T03:50:24Z", "salary": {"currency": null, "max": null, "min": null, "period": "monthly", "term": null}, "salary_visible": false, "title_keywords": ["manager"], "responsibilities": ["accounting duties", "full set of accounts", "management"], "requirements": {"degrees": ["diploma holder"], "majors": ["accounting"], "languages": [], "language_level": [], "hard_skills": ["excel", "flex accounting", "ms office"], "soft_skills": ["communication skills", "organized", "work independently", "detail-oriented", "team player"], "languages_combined": []}, "experience_required": {"duration": ["2 - 4 years"], "field": ["accounting experience", "accounting", "consolidation"]}}, {"job_id": "100003009051041", "location_code": "hk", "company": "The Wharf Group", "job_title": "Accounts Assistant", "description": "What You Will Do\u2026\n\nResponsible for accounts receivable and payable, including month end reporting and customer credit review\nPrepare bank reconciliation and month end closing\nHandle staff expenses claims\nHandle full set of accounts\nAssist in statutory audits\n\nParticipate in ad hoc projects and tasks\n\nWhat You Will Need\u2026\n\nDiploma in Accounting or Finance or related discipline\nOver 4 years relevant financial/accounting experience\nWell organized and possess good problem solving and analytical skills\nMature and good communication skill\nProficient in English and Mandarin\nImmediate available is preferred\n\nLead8 is an equal opportunity employer and welcomes applications from all qualified candidates\n\n(Excellent learning environment with the freedom to be creative)\n\nInterested parties please send portfolio, full resume giving details of qualifications, experience, expected salary and date available by clicking \"Apply Now\"", "employment_types": ["Full Time", "Permanent"], "selling_points": [], "locations": ["Tsim Sha Tsui"], "categories": ["Accounting", "Accounting Clerk / Supervisor", "Others", "Property / Real Estate", "Others"], "post_time": "2022-01-15T01:26:07Z", "salary": {"currency": null, "max": null, "min": null, "period": null, "term": null}, "salary_visible": false, "title_keywords": ["accounts assistant"], "responsibilities": ["reporting", "month end closing", "statutory audits", "accounts receivable", "review", "expenses", "bank reconciliation", "full set of accounts", "communication", "ad hoc projects"], "requirements": {"degrees": ["diploma"], "majors": ["finance", "accounting"], "languages": ["english", "mandarin"], "language_level": ["proficient"], "hard_skills": ["problem solving", "analytical skills"], "soft_skills": ["responsible", "communication skill", "well organized", "mature", "problem solving and analytical skills", "learning", "creative"], "languages_combined": [{"language": "english", "language_level": ["proficient"]}, {"language": "mandarin", "language_level": ["proficient"]}]}, "experience_required": {"duration": ["4 years"], "field": ["accounting experience", "financial"]}}, {"job_id": "100003009045058", "location_code": "hk", "company": "Harbour City Estates Ltd", "job_title": "ACCOUNTANT / ASSISTANT ACCOUNTANT", "description": "Career Level\nSenior\nQualification\nDegree\nYears of Experience\n8 years\nJob Type\nFull Time\nJob Functions\nAccounting, Others, Banking / Finance, Fund Management, Professional Services, Legal & Compliance", "employment_types": ["Full Time", "Permanent"], "selling_points": ["Degree holder in Accounting", "Qualified / finalist under HKICPA / ACCA", "Minimum 5 years\u2019 full set accounting experiences"], "locations": ["Tsim Sha Tsui"], "categories": ["Accounting", "Accounting Clerk / Supervisor", "Audit", "Others"], "post_time": "2022-01-15T03:49:27Z", "salary": {"currency": null, "max": null, "min": null, "period": null, "term": null}, "salary_visible": false, "title_keywords": ["accountant", "assistant accountant"], "responsibilities": ["management", "compliance", "banking"], "requirements": {"degrees": ["degree"], "majors": [], "languages": [], "language_level": [], "hard_skills": [], "soft_skills": [], "languages_combined": []}, "experience_required": {"duration": [], "field": []}}, {"job_id": "100003009050790", "location_code": "hk", "company": "Bank of Communications Hong Kong Branch", "job_title": "Section Head, Asset and Liability Management Compliance & Development", "description": "Job Responsibilities:\n\nHandle general accounting duties, with emphasis on A/R and G/L\nPrepare vouchers and accruals as assigned\nAssist in system implementation\nHandle data entries, filling and documentation\n\nSkills &\u00a0Requirements:\n\nF.5 or Diploma holder in Accountancy\nLCC Intermediate with 1 year working experience\nGood PC skill of MS Word, Excel & Chinese Word Processing\nResponsible and hard working\nFair in Mandarin /English\nImmediate available is highly preferred", "employment_types": ["Full Time"], "selling_points": [], "locations": ["Not Specified"], "categories": ["Accounting", "Others", "Banking / Finance", "Fund Management", "Professional Services", "Legal & Compliance"], "post_time": "2022-01-14T11:23:23Z", "salary": {"currency": null, "max": null, "min": null, "period": "monthly", "term": null}, "salary_visible": false, "title_keywords": ["section head"], "responsibilities": ["documentation", "general accounting duties", "implementation", "data"], "requirements": {"degrees": ["diploma holder"], "majors": ["accountancy"], "languages": ["english", "chinese", "mandarin"], "language_level": ["good"], "hard_skills": ["excel", "chinese word processing", "pc skill", "lcc", "ms word"], "soft_skills": ["hard working", "responsible"], "languages_combined": [{"language": "english", "language_level": []}, {"language": "chinese", "language_level": ["good"]}, {"language": "mandarin", "language_level": []}]}, "experience_required": {"duration": ["1 year"], "field": []}}, {"job_id": "100003009049551", "location_code": "hk", "company": "Tin Hang Technology Limited", "job_title": "Accounts Clerk", "description": "Major Responsibilities\n\nIs responsible for providing clerical services to finance, primarily on sorting, scanning, filing, and packing documents\n\nRequirements\n\nHKCEE preferable, with basic computer skills\nPossess filing principles with some experience in building up a filing system preferable\nAble to work neatly and orderly with 5S knowhow\nHighly responsible and willingness to accomplish\nWillingness to be involved labor work for box movement\nAble to work flexi-hours, 2 days a week\n\nInterested parties, please apply together with a detailed resume, stating current and expected salary, and send it via APPLY NOW.\u00a0 Attractive remuneration will be offered in commensurate with qualification and experience.\u00a0\n\nAll personal information received will be treated in strict confidence for employment purpose only.\u00a0 Your application can be considered as unsuccessful if you have no been reached within 3 months.\u00a0 On the other hand, it may be transferred to other companies of our group for job openings.\u00a0 Unsuccessful applications will be destroyed for a period not more than 12 months.\u00a0\n\nhttps://www.computime.com/\nhttps://salus-controls.com/", "employment_types": ["Full Time"], "selling_points": [], "locations": ["Sheung Wan"], "categories": ["Accounting", "Others", "Others", "Trading"], "post_time": "2022-01-14T08:57:59Z", "salary": {"currency": null, "max": null, "min": null, "period": "monthly", "term": null}, "salary_visible": false, "title_keywords": ["accounts clerk"], "responsibilities": ["scanning"], "requirements": {"degrees": [], "majors": [], "languages": [], "language_level": [], "hard_skills": ["computer skills", "basic"], "soft_skills": ["orderly", "responsible"], "languages_combined": []}, "experience_required": {"duration": [], "field": []}}, {"job_id": "100003009037399", "location_code": "hk", "company": "Computime Ltd", "job_title": "Part-time Filing Clerk", "description": "Institute of Professional Education And Knowledge (PEAK)\n\u53c3\u8003\u7de8\u865f : O/PEAK/TERM_OFF(Acc)/12/21\nThe Institute of Professional Education And Knowledge (PEAK) is a unit of Vocational Training Council responsible for the provision of in-service training and professional examination services. More than 200 major companies have utilized its corporate training services.\nMajor Duties:\n(a) To provide general accounting services in respect of:\n(i) financial planning and management;\n(ii) costing financial analysis and management reporting; and\n(iii) treasury / ledger accounting;\n(b) To help in the development and implementation of accounting policies, guidelines, procedures and computerized financial systems;\n(c) To conduct feasibility study on new initiatives; and\n(d) To lead and supervise a team of staff.\nRequirements:\n(a) A recognized relevant degree, or equivalent professional qualifications;\n(b) At least 2 years\u2019 relevant work experience preferably in sizeable organizations;\n(c) Good command of English and Chinese;\n(d) Good proficiency in Microsoft Office Software and computerized accounting / procurement systems;\n(e) Be proactive and able to work independently; and\n(f) Good problem solving, time management, interpersonal and communication skills.\nNotes:\n(1) Shortlisted applicants may be required to attend a written test.\n(2) The appointee(s) may be required to work irregular hours or outside normal office hours.\nApplication Procedures:\nA completed application form [VTC-1 (Rev. 1/2018)], together with a full curriculum vitae should be sent to the Recruitment Team, Institute of Professional Education and Knowledge, 9/F, VTC Tower, 27 Wood Road, Wanchai, Hong Kong or by email via \"Apply Now\". Please specify on the envelope or in the subject of the email, whichever is appropriate, the reference of the post being applied for.\nCandidates who would like to submit their applications through email are requested to take note of the following:\n(1) Completed application form (VTC-1) and detailed curriculum vitae (CV) should be provided in PDF format with total file size below 10MB.\n(2) Attachment(s) to the application by email should be saved with names as\n(a) VTC1- TERM OFF(Acc)-\u201cyour surname and given name\u201d, e.g. \u201cVTC1-TERM OFF(Acc)-CHAN Tai Man.pdf\u201d; and\n(b) CV- TERM OFF(Acc)-\u201cyour surname and given name\u201d, e.g. \u201cCV- TERM OFF(Acc)-CHAN Tai Man.pdf\u201d.\n(3) For the email subject, please cite \u201cApplication for the Post of TERM OFF(Acc) (Ref. No.: O/PEAK/TERM_OFF(Acc)/12/21)\u201d.\n(4) Original and copy of other supporting documents are to be provided as a later stage upon request.\nClosing date for application: 7 February 2022\nApplicants not invited for interview within 10 weeks from the closing date may consider their applications unsuccessful.\nThe Council reserves the right not to fill the post(s).\nPersonal data collected will be used for recruitment purposes only. Information on unsuccessful candidates will normally be destroyed 12 months after the completion of the recruitment exercise.", "employment_types": ["Part Time"], "selling_points": ["Free shuttle coach", "Provide clerical services to finance", "Able to work flexi-hours, 2 days a week"], "locations": ["Shatin Area"], "categories": ["Accounting", "Others", "Admin & HR", "Clerical / Admin Staff"], "post_time": "2022-01-11T02:43:16Z", "salary": {"currency": null, "max": null, "min": null, "period": "hourly", "term": null}, "salary_visible": false, "title_keywords": ["clerk"], "responsibilities": ["management", "guidelines", "systems", "procedures", "implementation", "financial analysis", "accounting policies", "management reporting", "planning"], "requirements": {"degrees": ["degree"], "majors": [], "languages": ["english", "chinese"], "language_level": ["good command"], "hard_skills": ["no", "professional qualifications", "problem solving", "c", "microsoft office software"], "soft_skills": ["communication skills", "work independently", "problem solving", "time management", "proactive", "interpersonal", "detailed"], "languages_combined": [{"language": "english", "language_level": ["good command"]}, {"language": "chinese", "language_level": ["good command"]}]}, "experience_required": {"duration": ["at least 2 years"], "field": []}}, {"job_id": "100003009047036", "location_code": "hk", "company": "Vocational Training Council", "job_title": "Term Officer (Accounting)", "description": "Job Description\n\n1) Assisting Accounting duties:\n\nHandling daily general accounting duties, data entry and filing\nHandling the month end closing and bank reconciliation\nCoordinating accounting functions for the inter-company transactions and reconciliation\n2) Assisting General Administrative and Receptionist duties:\u00a0\n\nBeing responsible for courier and mails arrangement\nBeing responsible for office & pantry supplies procurement and inventory control\nBeing responsible for office equipment repair and maintenance\n\n3) Performing ad-hoc duties assigned by Manager\n\n\nRequirements\n\nDiploma or above\n1-2 years of related experience is preferable (fresh graduates are also welcomed)\nGood command in both spoken and written English and Chinese\nGood typing skill and knowledge of PC (including WORD, EXCEL)\nIndependent with strong sense of responsibility and attention to details", "employment_types": ["Full Time"], "selling_points": ["To lead and supervise a team of staff", "A recognized relevant degree", "At least 2 years\u2019 relevant work experience"], "locations": ["Not Specified"], "categories": ["Accounting", "Accountant", "Others", "Admin & HR", "Others"], "post_time": "2022-01-14T02:07:11Z", "salary": {"currency": null, "max": null, "min": null, "period": "monthly", "term": null}, "salary_visible": false, "title_keywords": ["officer", "accounting"], "responsibilities": ["month end closing", "data entry and filing", "maintenance", "bank reconciliation", "transactions", "repair", "inventory control", "general accounting duties", "ad-hoc duties", "accounting duties"], "requirements": {"degrees": ["diploma or above"], "majors": [], "languages": ["english", "chinese"], "language_level": ["good command"], "hard_skills": ["pc", "excel", "typing", "word"], "soft_skills": ["independent", "attention to details", "sense of responsibility"], "languages_combined": [{"language": "english", "language_level": ["good command"]}, {"language": "chinese", "language_level": ["good command"]}]}, "experience_required": {"duration": ["1-2 years"], "field": ["related"]}}, {"job_id": "100003009050578", "location_code": "hk", "company": "Exact Medical Group Limited", "job_title": "Accounting & Admin. Assistant", "description": "Responsibilities:\n\nAudit of companies of various sizes and businesses\nPreparation of profits tax computation and returns\nCompilation of financial statements\nEngagements in other professional services such as financial due diligence\n\nRequirements:\n\nBachelor degree of any disciplines, preferably accounting or related major\nAssociate Degree or Diploma in accountancy or related discipline will also be considered\nRegistered students of HKICPA (or equivalent)\nFresh graduates to 2 years working experience gained in CPA firms\nProficient in English and Cantonese, fair in Putonghua\nGood communication / interpersonal skills\nKnowledge of PC software (i.e. MS Word, Excel)\nTeam player with strong initiative and sense of responsibility\n\n\nWe offer:\n\n5-day work week with casual wear Friday\nBirthday leave\nGraduation day leave\nAnnual leaves\nExam & study leaves\nCompetitive salaries\nPerformance bonus\nMedical insurance\nStructured training programs\n\n\u00a0(Personal data collected will be used for recruitment purposes only)", "employment_types": ["Full Time", "Permanent"], "selling_points": ["Accounting", "Admin", "Clerk"], "locations": ["Tsim Sha Tsui"], "categories": ["Accounting", "Others", "Admin & HR", "Clerical / Admin Staff", "Receptionist"], "post_time": "2022-01-14T10:48:54Z", "salary": {"currency": null, "max": null, "min": null, "period": "monthly", "term": null}, "salary_visible": false, "title_keywords": ["accounting & admin. assistant"], "responsibilities": ["due diligence", "tax computation", "audit", "financial statements"], "requirements": {"degrees": ["associate degree", "diploma", "degree", "bachelor"], "majors": ["accounting", "any disciplines", "accountancy"], "languages": ["cantonese", "putonghua", "english"], "language_level": ["proficient"], "hard_skills": ["excel", "cpa", "hkicpa", "pc", "ms word"], "soft_skills": ["sense of responsibility", "communication", "interpersonal skills", "team player", "initiative"], "languages_combined": [{"language": "cantonese", "language_level": ["proficient"]}, {"language": "putonghua", "language_level": ["proficient"]}, {"language": "english", "language_level": ["proficient"]}]}, "experience_required": {"duration": ["2 years"], "field": []}}, {"job_id": "100003009049221", "location_code": "hk", "company": "Nexia Charles Mar Fan Limited", "job_title": "Auditors", "description": "JOB RESPONSIBILITIES\n\n\u5354\u52a9\u5ba2\u6236\u6bcf\u6708\u6703\u8a08\u5165\u5e33\n\u5354\u52a9\u8655\u7406\u6587\u4ef6\u5de5\u4f5c\u3001\u7c3f\u8a18\n\u63d0\u4f9b\u4e00\u822c\u6587\u66f8\u53ca\u884c\u653f\u652f\u63f4\n\u5feb\u901f\u800c\u6e96\u78ba\u5730\u8f38\u5165\u6578\u64da\u53ca\u6838\u5c0d\n\nREQUIREMENT\n\n\u6709\u8655\u7406\u5168\u76e4\u6703\u8a08\u7d93\u9a57\n\u61c2\u96f2\u7aef\u6703\u8a08\u7cfb\u7d71\n5\u5929\u5de5\u4f5c, \u9280\u884c\u5047\u671f,\n\u6709\u7368\u7acb\u8655\u7406\u5de5\u4f5c\u80fd\u529b, \u80fd\u6309\u6642\u5b8c\u6210\u5de5\u4f5c\n\u6d41\u5229\u7cb5\u8a9e, \u61c2\u82f1\u6587\u666e\u901a\u8a71\n\u5373\u6642\u4e0a\u73ed\u8005\u512a\u5148\u8003\u616e\n\nIf interested, please submit resume with expected salary and availability by clicking the 'Apply' button below. \u6709\u610f\u8005\u8acb\u5c07\u500b\u4eba\u5c65\u6b77\uff08\u5217\u660e\u73fe\u6709\u53ca\u8981\u6c42\u85aa\u91d1\uff09\u900f\u904e\u672c\u7db2\u7ad9\u7533\u8acb\uff0c\u6709\u95dc\u8077\u4f4d\u8058\u8acb\u8a73\u7d30\u53ef\u81f4\u96fb3596 2046 (\u4eba\u529b\u8cc7\u6e90HR\u90e8\u9580) \u67e5\u8a62\u3002\n*All information received will be kept confidential and for recruitment purposes only.", "employment_types": ["Full Time", "Permanent"], "selling_points": [], "locations": ["Wan Chai"], "categories": ["Accounting", "Audit", "Others", "Others", "Student / Fresh Graduate / No Experience"], "post_time": "2022-01-14T08:17:25Z", "salary": {"currency": null, "max": null, "min": null, "period": "monthly", "term": null}, "salary_visible": false, "title_keywords": [], "responsibilities": [], "requirements": {"degrees": [], "majors": [], "languages": [], "language_level": [], "hard_skills": [], "soft_skills": [], "languages_combined": []}, "experience_required": {"duration": [], "field": []}}, {"job_id": "100003009041875", "location_code": "hk", "company": "E-commerce System Technology Limited", "job_title": "\u5168\u8077\u6703\u8a08\u7c3f\u8a18 (5\u5929\u5de5\u4f5c)", "description": "Responsibilities:\n\nResponsible for preparing schedules, reconciliation, statutory accounts and audit schedules of companies, and other ad hoc assignments\n\nRequirements:\n\nDegree or Higher Diploma holder in Accounting or relevant disciplines\nMinimum 2-3 years\u2019 relevant working experience in audit or accounting field, preferably gained from property management industry. Candidates with listed company background in different industries will also be considered\nExperience in handling full set of accounting is a must\nStudent member of HKICPA or other professional accounting bodies\nGood command of both written and spoken English and Chinese. Good PC skills and proficient in Flex accounting software\nAble to work independently, proactive and be a good team player\n\nWe offer competitive remuneration package that commensurate with experience and qualifications.\u00a0 Interested parties are invited to send full resume stating HKCEE / HKALE / HKDSE results, contact telephone number, date available, present and expected salary to our recruitment email address.\n\n(Personal data provided will be used strictly in accordance with the Company\u2019s personal data policy which is available upon request.)", "employment_types": ["Full Time"], "selling_points": [], "locations": ["Tsuen Wan Area"], "categories": ["Accounting", "Accounting Clerk / Supervisor", "Others", "Admin & HR", "Clerical / Admin Staff"], "post_time": "2022-01-12T04:35:03Z", "salary": {"currency": null, "max": null, "min": null, "period": "monthly", "term": null}, "salary_visible": false, "title_keywords": [], "responsibilities": ["schedules", "ad hoc assignments", "audit"], "requirements": {"degrees": ["degree", "higher diploma holder"], "majors": ["accounting"], "languages": ["english", "chinese"], "language_level": ["good command"], "hard_skills": ["flex accounting", "pc skills", "hkicpa"], "soft_skills": ["good team player", "work independently", "proactive"], "languages_combined": [{"language": "english", "language_level": ["good command"]}, {"language": "chinese", "language_level": ["good command"]}]}, "experience_required": {"duration": ["minimum 2-3 years"], "field": ["management", "accounting", "relevant working experience", "audit"]}}, {"job_id": "100003009045059", "location_code": "hk", "company": "Harbour City Estates Ltd", "job_title": "ACCOUNTS ASSISTANT", "description": "Responsibilities:\n\n\nResponsible for Accounts Payable daily operations including invoices and payments;\nEnsure payments are supported and approved in compliance with internal policies;\nMaintain proper and accurate records and supporting documents;\nLiaise with internal and external parties regarding queries and disputes with their accounts;\nAssist in financial closing in timely manner;\nAssist to prepare AP reports and reconciliation;\nHandle general filing and administration work;\nLiaise with external auditors for the annual audit and other ad hoc tasks.\n\n\u00a0Requirements - Qualification:\n\n\nHigher diploma or above in Accounting or equivalent;\nMinimum 2 to 3 years\u2019 relevant working experience.\n\nRequirements \u2013 Competences:\n\n\nGood problem solving and presentation skills;\nAble to work independently;\nDiligent and proactive;\nNumerical sensitive with analytical mindset and meticulous attention to detail.\u00a0\n\nWe look forward to receiving your application with detailed resume stating\u00a0working experience,\u00a0academic and language qualifications, existing and EXPECTED SALARY\u00a0as well as\u00a0availability.\u00a0All applications will be kept strictly confidential.\n\nWe offer promising professional career and exposure\u00a0to right candidate, together with attractive remuneration package including\u00a0discretionary bonus, continuing education allowance, medical and dental coverage.\n\nPersonal Data collected will be used for recruitment-related purposes only.", "employment_types": ["Full Time", "Permanent"], "selling_points": ["Minimum 2 years\u2019 relevant working experience", "Exp. in handling full set of accounting is a must", "Degree or Higher Diploma holder in Accounting"], "locations": ["Tsim Sha Tsui"], "categories": ["Accounting", "Accounting Clerk / Supervisor", "Audit", "Others"], "post_time": "2022-01-15T03:49:28Z", "salary": {"currency": null, "max": null, "min": null, "period": null, "term": null}, "salary_visible": false, "title_keywords": ["accounts assistant"], "responsibilities": ["ap", "invoices", "annual audit", "policies", "compliance", "internal and external parties", "ad hoc tasks", "external auditors", "daily operations", "maintain", "payments", "reports", "liaise with", "accounts payable", "administration"], "requirements": {"degrees": ["higher diploma or above"], "majors": ["accounting"], "languages": [], "language_level": [], "hard_skills": ["problem solving"], "soft_skills": ["meticulous", "work independently", "diligent", "problem solving", "presentation skills", "attention to detail", "sensitive", "proactive", "detailed"], "languages_combined": []}, "experience_required": {"duration": ["minimum 2 to 3 years"], "field": ["relevant working experience"]}}, {"job_id": "100003009048533", "location_code": "hk", "company": "Kum Shing Group", "job_title": "Senior Accounting Assistant / Accounting Assistant (AP \u2013 Subcontractor Payment)", "description": "Responsibilities:\n\nWork on audit assignments for clients from a variety of industries, covering Hong Kong and China\nInvolve in\u00a0audit of internal controls over financial reporting and ad-hoc projects such as due\u00a0diligence reviews, IPO exercises and merger and acquisition deals\nAssist in\u00a0planning, execution and delivery of assurance engagements\n\n\nRequirements:\u00a0\u00a0\n\nDegree holder majoring in Accountancy / Finance\nFresh graduates and candidates with practical audit experience will be considered, preferably gained with another international accounting network\nGood written and spoken English and Chinese\nGood communication / interpersonal skills\nHigh level of independence and strong motivation\nStrong technical ability and keen to\u00a0develop\u00a0a career in the audit profession\n\nCompetitive package will be offered to the right candidate(s), including 5 day work week, paid examination & study leave,\u00a0reimbursement for examination fees,\u00a0subsidy of examination revision course fees, birthday leave & medical insurance coverage. Interested parties please send full resume with working experience, academic and professional qualifications, including present & expected salary by clicking the \"Apply Now\" button.\u00a0 Personal data collected will be used for recruitment purposes only.\n\nSimply click the \u201cApply Now\u201d button\n\nPlease visit our website at\u00a0www.moore.hk\u00a0to know more about us.", "employment_types": ["Full Time", "Permanent"], "selling_points": ["Performance bonus, education subsidy, medical plan", "Excellent career path", "Minimum 2 to 3 years\u2019 relevant working experience"], "locations": ["To Kwa Wan"], "categories": ["Accounting", "Accountant", "Accounting Clerk / Supervisor", "Others"], "post_time": "2022-01-14T06:45:22Z", "salary": {"currency": null, "max": null, "min": null, "period": "monthly", "term": null}, "salary_visible": false, "title_keywords": ["accounting assistant"], "responsibilities": ["due diligence reviews", "audit", "financial reporting", "ad-hoc projects", "planning"], "requirements": {"degrees": ["degree holder"], "majors": ["finance", "accountancy"], "languages": ["english", "chinese"], "language_level": ["good"], "hard_skills": [], "soft_skills": ["communication", "keen", "interpersonal skills"], "languages_combined": [{"language": "english", "language_level": ["good"]}, {"language": "chinese", "language_level": ["good"]}]}, "experience_required": {"duration": [], "field": ["audit experience", "accounting"]}}, {"job_id": "100003009047650", "location_code": "hk", "company": "Moore Associates Limited", "job_title": "Audit Staff \u2013 Associates/Senior Associates", "description": "Job Description and Responsibilities:\n\nAssist in performing execution and delivery of audit assignments for listed and private clients from a variety of industries, covering Hong Kong and China\nInvolve in\u00a0assisting the audit of internal controls over financial reporting and ad-hoc projects such as due\u00a0diligence reviews, IPO exercises and merger and acquisition deals\u00a0\nPromoted to audit associate or more experienced position if performance is satisfactory\n\n\u00a0Requirements:\n\nDiploma holder majoring in Accountancy / Finance\nFresh graduates and candidates with practical audit experience will be considered, preferably gained with another international accounting network\nGood written and spoken English and Chinese\nGood communication / interpersonal skills\nHigh level of independence and strong motivation\nKeen to develop a career in the audit profession\n\n\n\nCompetitive package will be offered to the right candidate(s), including 5 day work week, paid examination & study leave,\u00a0reimbursement for examination fees,\u00a0subsidy of examination revision course fees, birthday leave & medical insurance coverage. Interested parties please send full resume with working experience, academic and professional qualifications, including present & expected salary by clicking the \"Apply Now\" button.\u00a0 Personal data collected will be used for recruitment purposes only.\n\nSimply click the \u201cApply Now\u201d button\n\nPlease visit our website at\u00a0www.moore.hk\u00a0to know more about us.", "employment_types": ["Full Time", "Permanent"], "selling_points": ["Apart from working on audit assignments", "Degree holder, majoring in accountancy/finance", "Fresh graduates will also be considered"], "locations": ["Tsim Sha Tsui"], "categories": ["Accounting", "Accountant", "Audit", "Others"], "post_time": "2022-01-15T03:49:47Z", "salary": {"currency": null, "max": null, "min": null, "period": "monthly", "term": null}, "salary_visible": false, "title_keywords": ["audit staff"], "responsibilities": ["financial reporting", "ad-hoc projects", "audit", "due diligence reviews"], "requirements": {"degrees": ["diploma holder"], "majors": ["finance", "accountancy"], "languages": ["english", "chinese"], "language_level": ["good"], "hard_skills": [], "soft_skills": ["communication", "keen", "interpersonal skills"], "languages_combined": [{"language": "english", "language_level": ["good"]}, {"language": "chinese", "language_level": ["good"]}]}, "experience_required": {"duration": [], "field": ["audit experience", "accounting"]}}, {"job_id": "100003009047652", "location_code": "hk", "company": "Moore Associates Limited", "job_title": "Audit Assistant", "description": "Requirements:\n\nBachelor Degree holder / High Diploma in Accounting / HKICPA / ACCA / HKIAAT student member / or equivalent\nKnowledge of QuickBooks / MYOB Accounting System is an added advantage\nMinimum 2 years of relevant working experience in handling full set of accounts independently\nGood communication and interpersonal skills with strong sense of responsibility, self-motivated and result-oriented\nGood command of written & spoken English and Mandarin\nProficient in Microsoft Office, such as Word, Excel, Chinese and English Word Processing, etc.\n\nWe offer 5 days work and bank holidays. Interested parties please apply with full CV quoting expected and last salary and availability emailing by clicking \"Apply Now\".\n\n[Personal data collected will be used for recruitment purpose only]", "employment_types": ["Full Time", "Permanent"], "selling_points": ["Audit assignments for listed and private clients", "Diploma holder majoring in Accountancy / Finance", "Fresh graduates will also be considered"], "locations": ["Tsim Sha Tsui"], "categories": ["Accounting", "Accountant", "Audit", "Others"], "post_time": "2022-01-15T03:49:48Z", "salary": {"currency": null, "max": null, "min": null, "period": "monthly", "term": null}, "salary_visible": false, "title_keywords": ["assistant"], "responsibilities": ["communication", "full set of accounts"], "requirements": {"degrees": ["high diploma", "bachelor degree holder"], "majors": ["accounting"], "languages": ["english", "chinese", "mandarin"], "language_level": ["good command", "proficient"], "hard_skills": ["excel", "acca", "microsoft office", "quickbooks", "chinese and english word processing", "word", "accounting system", "myob", "hkicpa"], "soft_skills": ["self-motivated", "independently", "sense of responsibility", "communication and interpersonal skills", "result-oriented"], "languages_combined": [{"language": "english", "language_level": ["good command", "proficient"]}, {"language": "chinese", "language_level": ["proficient"]}, {"language": "mandarin", "language_level": ["good command"]}]}, "experience_required": {"duration": ["minimum 2 years"], "field": ["relevant working experience"]}}, {"job_id": "100003009049428", "location_code": "hk", "company": "JCK & Associates Limited", "job_title": "ASSISTANT ACCOUNTANT / ACCOUNTANT   \u2013 5 days work in Wan Chai", "description": "Assist in handling routine clerical work\nHKDSE or above with 1 year\u00a0clerical working experience\nGood command of spoken and written English and Chinese\nProficient in MS Office and Chinese word processing\nImmediate available is preferable\nWorking location: Wanchai\n\nInterested parties please send application with last salary and expected salary by email to Human Resources Department, Room 3501, China Online Centre, 333 Lockhart Road, Wanchai, Hong Kong.", "employment_types": ["Full Time", "Permanent"], "selling_points": ["5 days work and bank holidays", "Minimum 2 years of relevant working experience", "Bachelor Degree holder / High Diploma"], "locations": ["Wan Chai"], "categories": ["Accounting", "Accountant", "Accounting Clerk / Supervisor", "Others"], "post_time": "2022-01-14T08:36:39Z", "salary": {"currency": null, "max": null, "min": null, "period": "monthly", "term": null}, "salary_visible": false, "title_keywords": ["accountant", "assistant accountant"], "responsibilities": [], "requirements": {"degrees": ["hkdse"], "majors": [], "languages": ["english", "chinese"], "language_level": ["good command", "proficient"], "hard_skills": ["chinese word processing", "ms office"], "soft_skills": [], "languages_combined": [{"language": "english", "language_level": ["good command"]}, {"language": "chinese", "language_level": ["good command", "proficient"]}]}, "experience_required": {"duration": ["1 year"], "field": ["clerical"]}}, {"job_id": "100003009043741", "location_code": "hk", "company": "Protech Property Management Ltd", "job_title": "Clerk", "description": "Ref. No.: JDB/HLD01/AC-C\n\nHKDSE or above with LCCI higher qualification\nMinimum 1 year's relevant experience\nProficiency in MS Office\nSelf-initiated, well-organized, responsible, detail-minded and hardworking\nAble to meet tight deadline\nFresh graduate will also be considered\n\n\nAttractive salary and fringe benefits will be offered to the successful candidates. Please apply with full resume by mail to\u00a0Human Resources Department, Henderson Land Development Co. Ltd., 71/F, Two International Finance Centre, 8 Finance Street, Central, Hong Kong\u00a0or by fax at\u00a02905 1855\u00a0or visit our homepage at\u00a0http://www.hld.com\u00a0or\u00a0by clicking \"Apply Now\".\n\n(Please quote the ref. no. on letter)\n\nPersonal data provided by job applicants will be used for recruitment purpose only.", "employment_types": ["Full Time", "Permanent"], "selling_points": [], "locations": ["Wan Chai Area"], "categories": ["Accounting", "Others", "Admin & HR", "Clerical / Admin Staff", "Property / Real Estate", "Property Management"], "post_time": "2022-01-13T01:45:05Z", "salary": {"currency": null, "max": null, "min": null, "period": "monthly", "term": null}, "salary_visible": false, "title_keywords": ["clerk"], "responsibilities": [], "requirements": {"degrees": ["hkdse", "fresh graduate"], "majors": [], "languages": [], "language_level": [], "hard_skills": ["no", "c", "ms office"], "soft_skills": ["detail-minded", "responsible", "well-organized", "meet tight deadline", "hardworking"], "languages_combined": []}, "experience_required": {"duration": ["minimum 1 year"], "field": ["relevant experience"]}}, {"job_id": "100003009048685", "location_code": "hk", "company": "Henderson Land Development Company Limited", "job_title": "ACCOUNTS CLERK", "description": "Responsibilities:\n\nMonitor the approved expenditure budget according to the budget control framework\nControl budget funds availability and prepare budget forecast\nHandle over-budget applications and budget limit readjustment\nPrepare expenditure & budget statements and financial analysis reports\nPerform other ad-hoc assignments as required\n\nRequirements:\n\nDegree holder in Accounting, Finance, Business Management or related disciplines\nCPA, CIA or equivalent qualification will be an advantage\nAt least 3 years\u2019 experience in budget control, preferably gained in professional firms or sizable organizations\nExcellent communication & interpersonal skills\nMeticulous, detail-oriented with good analytical and report writing skills and able to work under pressure and meet deadline\nProficiency in Microsoft Word and Excel\nGood command in both written and spoken English and Chinese (including Putonghua)", "employment_types": ["Full Time"], "selling_points": ["Medical Allowance", "Education Allowance", "Free Lunch"], "locations": ["Central"], "categories": ["Accounting", "Accounting Clerk / Supervisor", "Others", "Property / Real Estate", "Others"], "post_time": "2022-01-14T07:02:31Z", "salary": {"currency": null, "max": null, "min": null, "period": "monthly", "term": null}, "salary_visible": false, "title_keywords": ["accounts clerk"], "responsibilities": ["control", "ad-hoc assignments", "budget", "monitor", "financial analysis reports", "forecast", "budget control"], "requirements": {"degrees": ["degree holder"], "majors": ["business", "finance", "related disciplines", "accounting"], "languages": ["putonghua", "english", "chinese"], "language_level": ["good command"], "hard_skills": ["business management", "excel", "microsoft word", "writing skills", "cpa"], "soft_skills": ["meticulous", "writing skills", "detail-oriented", "communication", "interpersonal skills", "work under pressure"], "languages_combined": [{"language": "putonghua", "language_level": ["good command"]}, {"language": "english", "language_level": ["good command"]}, {"language": "chinese", "language_level": ["good command"]}]}, "experience_required": {"duration": ["at least 3 years"], "field": []}}, {"job_id": "100003009044920", "location_code": "hk", "company": "Wharf Estates Limited", "job_title": "EXPENDITURE BUDGET UNIT OFFICER", "description": "Requirements:\n\nDegree holder/ IVE graduate in Accountancy\n\nHKICPA/ ACCA/ HKAAT student member or equivalent\nExperience is preferred but not essential. Fresh Graduate is also considered\nCandidate who with good book-keeping/audit experience will be considered as Accountant, Semi-Senior or Senior\nGood command in written and spoken English, Cantonese and Mandarin\nProficient in MS Word and Excel\nIndependently and reliable capability\nImmediate available is preferred\n\n\n\nWe offer 5 days work per week (Mon to Fri : 9:30 am - 6:00 pm), study & examination leave, performance bonus and attractive remuneration package to the right candidate.\n\nInterested candidates please send your full resume with present and expected salary by clicking \"Apply Now\"\n\n\nPersonal data collected will be used for recruitment purpose only.\n\n", "employment_types": ["Full Time"], "selling_points": ["Degree holder in Accounting or related disciplines", "CPA, CIA qualification will be an advantage", "Minimum 3 years\u2019 experience in budget control"], "locations": ["Tsim Sha Tsui"], "categories": ["Accounting", "Financial Analyst", "Others", "Property / Real Estate", "Property Management"], "post_time": "2022-01-15T03:49:24Z", "salary": {"currency": null, "max": null, "min": null, "period": null, "term": null}, "salary_visible": false, "title_keywords": ["officer"], "responsibilities": ["book-keeping", "audit"], "requirements": {"degrees": ["fresh graduate", "degree holder"], "majors": ["accountancy"], "languages": ["cantonese", "english", "mandarin"], "language_level": ["good command"], "hard_skills": ["ms word", "excel", "acca", "hkicpa"], "soft_skills": ["independently", "reliable"], "languages_combined": [{"language": "cantonese", "language_level": ["good command"]}, {"language": "english", "language_level": ["good command"]}, {"language": "mandarin", "language_level": ["good command"]}]}, "experience_required": {"duration": [], "field": ["audit experience"]}}, {"job_id": "100003009053134", "location_code": "hk", "company": "Vision A. S. Limited", "job_title": "ASSISTANT ACCOUNTANT (ACCOUNTS DEPT) & AUDIT ASSISTANT, SEMI-SENIOR, SENIOR", "description": "We are looking for a suitable candidate to join our Regional Accounting Team based in Hong Kong.\n\nCore Responsibilities:\n\nResponsible for month end closing\nManage intercompany transactions with Asia Pacific operating companies\nAssist in quarterly forecast planning & budgeting\nProvide support for annual audit and tax related matters\nHandle ad-hoc assignments\n\nKey Requirements:\n\nDegree in Accounting\nFinalist/Qualified accountant with 3 years of accounting experience or above\nPreferable with audit experience\nKnowledge of SOX compliance is an advantage\nDetail-oriented, good analytical and communications skills\nProficient in Word, Excel and knowledge in computerized environment\nFluency in English and Chinese, both written and spoken\nAble to work under pressure and manage multiple assignments\nHardworking and willing to work overtime\nImmediate available is preferable\nLess experience will be considered as Accountant\n\nWe offer 5-day work with attractive salary, fringe benefits and good career prospects to the right candidates.\n\nAll information will be treated in the strictest confidence and used for recruitment purposes. Only short-listed candidates will be contacted for interview.", "employment_types": ["Full Time", "Permanent"], "selling_points": ["Degree holder/ IVE graduate in Accountancy", "HKICPA/ ACCA/ HKAAT student member or equivalent", "5 days work per week Mon to Fri : 9:30 am-6:00 pm"], "locations": ["Wan Chai"], "categories": ["Accounting", "Audit", "Others"], "post_time": "2022-01-17T06:02:55Z", "salary": {"currency": null, "max": null, "min": null, "period": "monthly", "term": null}, "salary_visible": false, "title_keywords": ["assistant accountant", "assistant"], "responsibilities": ["tax", "month end closing", "provide support", "annual audit", "budgeting", "ad-hoc assignments", "transactions", "forecast", "planning"], "requirements": {"degrees": ["degree"], "majors": ["accounting"], "languages": ["english", "chinese"], "language_level": ["fluency"], "hard_skills": ["excel", "word"], "soft_skills": ["work under pressure", "work overtime", "hardworking", "detail-oriented"], "languages_combined": [{"language": "english", "language_level": ["fluency"]}, {"language": "chinese", "language_level": ["fluency"]}]}, "experience_required": {"duration": ["3 years"], "field": ["accounting experience", "audit experience"]}}, {"job_id": "100003009054880", "location_code": "hk", "company": "Ogilvy & Mather (Hong Kong) Private Ltd", "job_title": "Regional Senior Accountant (MNC)", "description": "We are currently seeking a high calibre professional to join our District Team as\u00a0Senior Business Development Manager / Business Development Manager.\n\nJob Description:\n\nProvide professional service to corporate clients\u00a0\u00a0\nAnalyze and evaluate financial status\nProvide professional advice and after sales service to potential clients\nExpand and develop a professional agency force\nTeam Building and Management\n\nWe Offer:\n\nComprehensive training to be provided by professional trainers with excellent sales track records and qualifications\u00a0\nCommission + bonus + Monthly Salary\nExcellent career development and promotion opportunities\n5-day work plus 30-day Annual Leave\nGroup life , Insurance, travel allowance and mortgage loans.\n\n\nInterested parties, please\u00a0contact Mr. Cheung at\u00a053982493 for enquiry\u00a0\n\n", "employment_types": ["Full Time", "Permanent"], "selling_points": ["Degree in Accounting", "Finalist/Qualified accountant with 3 yrs acct. exp", "Knowledge of SOX compliance is an advantage"], "locations": ["Quarry Bay"], "categories": ["Accounting", "Accountant", "Accounting Clerk / Supervisor", "Others"], "post_time": "2022-01-17T12:23:10Z", "salary": {"currency": null, "max": null, "min": null, "period": "monthly", "term": null}, "salary_visible": false, "title_keywords": ["senior accountant"], "responsibilities": ["evaluate", "management", "develop"], "requirements": {"degrees": [], "majors": [], "languages": [], "language_level": [], "hard_skills": [], "soft_skills": [], "languages_combined": []}, "experience_required": {"duration": [], "field": []}}, {"job_id": "100003009046601", "location_code": "hk", "company": "", "job_title": "Senior Business Development Manager  /  Business Development Manager", "description": "\u548c\u9806\u5802\u4e2d\u91ab\u8a3a\u6240\n\u548c\u9806\u5802\u4e43\u77e5\u540d\u7684\u4e2d\u91ab\u8a3a\u6240\u9023\u9396\u96c6\u5718\uff0c\u5728\u5168\u6e2f\u5404\u5340\u8a3a\u6240\u6578\u76ee\u6b63\u9081\u541150\u9593\u3002\u9664\u4e86\u50b3\u7d71\u4e2d\u91ab\u85e5\u670d\u52d9\u5916\uff0c\u4e5f\u63d0\u4f9b\u9ad8\u54c1\u8cea\u4e2d\u91ab\u85e5\u5065\u5eb7\u7522\u54c1\uff0c\u4e26\u6b63\u7a4d\u6975\u62d3\u5c55\u7522\u54c1\u985e\u5225\u3002\u6211\u5011\u975e\u5e38\u6ce8\u91cd\u9867\u5ba2\u670d\u52d9\u6c34\u5e73\uff0c\u8b93\u9867\u5ba2\u4eab\u6709\u512a\u8cea\u6d88\u8cbb\u9ad4\u9a57\u3002\u672c\u516c\u53f8\u8a3a\u6240\u6578\u76ee\u6b63\u9ad8\u901f\u589e\u9577\uff0c\u73fe\u8aa0\u8058\u4e0b\u5217\u8077\u4f4d\uff1a\u00a0\n\n\nAccount Clerk\n\nJob Description:\n\n\n\nPerform daily accounting routines, including voucher preparation, journal inputs and payments, etc.\nResponsible for matters related to Accounts Payable\nAssist to month-end closing\nParticipate in other accounting related and ad hoc assignments\n\nUpdate bank book and bank reconciliation\n\nRequirements:\n\n\nForm 5 or above\nLCCI level 2 or above\nMinimum 3 years of accounting work experience for Accounts Payable, preferably in retail industry.\nExperience in using FLEXSYSTEM is preferred.\nDetailed-minded, well-organized, able to meet tight deadlines, positive working attitude with strong sense of responsibility\nBe proficient in MS Word, Excel and Chinese Word Processing\nCandidate with more experience will be considered as Senior Account Clerk\nImmediately available is highly preferred\n\nInterested parties please send your full resume with availability, current and expected salary by clicking \"Apply Now\".\u00a0\n\nAll Personal data collected will be used for recruitment purpose only.\nwebsite: https://wellsoon.hk\n", "employment_types": ["Full Time", "Permanent"], "selling_points": ["Analyze and evaluate financial status", "Provide professional service to corporate clients", "DIRECT ENTRY to management level"], "locations": ["Kwun Tong Area"], "categories": ["Accounting", "Others", "Banking / Finance", "Others", "Beauty Care / Health", "Others"], "post_time": "2022-01-13T16:01:55Z", "salary": {"currency": null, "max": null, "min": null, "period": "monthly", "term": null}, "salary_visible": false, "title_keywords": ["senior business development manager", "business development manager"], "responsibilities": ["voucher preparation", "bank reconciliation", "month-end closing", "payments", "ad hoc assignments", "daily accounting", "journal inputs", "accounts payable"], "requirements": {"degrees": ["form 5 or above"], "majors": [], "languages": ["chinese"], "language_level": ["proficient"], "hard_skills": ["excel", "chinese word processing", "flexsystem", "ms word"], "soft_skills": ["meet tight deadlines", "sense of responsibility", "well-organized", "positive working attitude", "detailed"], "languages_combined": [{"language": "chinese", "language_level": ["proficient"]}]}, "experience_required": {"duration": ["minimum 3 years"], "field": ["retail industry", "accounting"]}}, {"job_id": "100003009049699", "location_code": "hk", "company": "Wellsoon (International) Medicine Co., Limited.", "job_title": "Account Clerk", "description": "Job Responsibilities:\nSupport the AR Team on all collection works for Service Operation;\nHandle related reconciliation work on collection and receipts\nMaintain accounts receivable files and records\nDevelop professional relationship with external customers to ensure timely collection of accounts.\nAssist in ad-hoc tasks as required\nJob Requirements:\nDiploma or LCC Intermediate or above\n5 years of accounting experience in MNC\nHardworking, detailed attentive and good communication skills\nAble to work under pressure, overtime\u00a0work may be\u00a0required\u00a0to meet deadlines\nAdvanced skill in Excel such as V-lookup and Pivot table would be advantageous\nWe offer remuneration package including attractive salary, comprehensive fringe benefits and excellent opportunities for the right candidate.\u00a0(*** Employee Scholar Program\u00a0up to $160,000/ person for each degree***)\nWebsite:\u00a0http://www.otis.com/\u00a0\nInformation provided by applicants will be treated in strict confidence and will only be used for recruitment related purposes. All information on unsuccessful candidates will be deleted from our files within 24 months.", "employment_types": ["Full Time"], "selling_points": [], "locations": ["Kwun Tong"], "categories": ["Accounting", "Accounting Clerk / Supervisor", "Others"], "post_time": "2022-01-14T09:07:13Z", "salary": {"currency": null, "max": null, "min": null, "period": "monthly", "term": null}, "salary_visible": false, "title_keywords": ["account clerk"], "responsibilities": ["ar", "accounts receivable", "receipts", "ad-hoc tasks", "develop", "maintain"], "requirements": {"degrees": ["diploma"], "majors": [], "languages": [], "language_level": [], "hard_skills": ["excel", "pivot table", "lcc"], "soft_skills": ["attentive", "communication skills", "advanced", "detailed", "overtime work", "meet deadlines", "hardworking", "work under pressure"], "languages_combined": []}, "experience_required": {"duration": ["5 years"], "field": ["accounting experience"]}}, {"job_id": "100003009047498", "location_code": "hk", "company": "Otis Elevator Co (HK) Limited", "job_title": "Accounting Assistant", "description": "Job description and responsibilities:\n\nAble to handle full set of accounts independently by using accounting system;\nPreparing month end closings, consolidation, monthly financial reports and analysis of accounts\nAssist in audit, budget and management report analysis\nTo resolve daily accounting and operational issues;\nLiaise with auditor for annual audit and tax filing\nPerforming general administrative and clerical duties.\nPerform other ad hoc duties as assigned\n\n\u00a0Job requirements:\n\nDegree holder of the accounting\u00a0or related disciplines\nPreferably minimum 2 years of working experience in financial accounting\nFamiliar with Hong Kong and Mainland tax regulations is preferred\nGood knowledge of MS office (such as Word, Excel) and Chinese Word Processing\nGood interpersonal and communication skills, self-motivated and able to work well independently. Able to work under pressure and meet tight deadline\nGood command in both written and spoken English and Chinese\nApplicant with more experiences will be considered as Senior Accounting Officer or Assistant Accounting Manager.\n\nWe offer 13 months\u2019salary, annual leave, transportation allowance, paid sick leave, etc. to the right candidates\n\nInterested candidate please send your updated CV with expected salary by clicking \"Apply Now\".\n\nAll applications will be treated in strict confidence and used solely for recruitment purpose.", "employment_types": ["Full Time", "Permanent"], "selling_points": ["Work-Life harmony", "Exposure to MNC Environment", "Employee Scholar Program up to $160,000/ Degree"], "locations": ["Kowloon Bay"], "categories": ["Accounting", "Accountant", "Accounting Clerk / Supervisor", "Others"], "post_time": "2022-01-14T03:20:26Z", "salary": {"currency": null, "max": null, "min": null, "period": "monthly", "term": null}, "salary_visible": false, "title_keywords": ["accounting assistant"], "responsibilities": ["ad hoc duties", "financial reports", "annual audit", "analysis", "full set of accounts", "budget", "audit", "tax filing", "liaise with", "daily accounting", "management report"], "requirements": {"degrees": ["degree holder"], "majors": ["related disciplines", "accounting"], "languages": ["english", "chinese"], "language_level": ["good command", "good"], "hard_skills": ["excel", "chinese word processing", "word", "ms office"], "soft_skills": ["communication skills", "self-motivated", "independently", "meet tight deadline", "interpersonal", "work under pressure"], "languages_combined": [{"language": "english", "language_level": ["good command", "good"]}, {"language": "chinese", "language_level": ["good command", "good", "good"]}]}, "experience_required": {"duration": ["minimum 2 years"], "field": ["accounting", "financial"]}}, {"job_id": "100003009047078", "location_code": "hk", "company": "Jing Du Yang Sheng Tang Chinese Herbal Mfg Ltd", "job_title": "Accounting Officer", "description": "Meta Air Labs Limited is an Enterprise-Grade Blockchain as a Solutions (BaaS) Service Provider based in Hong Kong. We are looking for talented candidates to join us . If you are passionate in blockchain technology and want a new fresh start for your career path, SEND US YOUR LATEST CV!\n\nYour role:\n\nPerform daily settlement operations on crypto trading\nHandle day-end procedures and daily reconciliation\nPrepare daily and monthly settlement reports and statements\nRespond and resolve customer, requests, and concerns mainly using chat quickly and effectively\nEnsuring that our customers receive exceptional support from start-to-finish\nEscalate critical issues to the appropriate internal team\nIncrease customer satisfaction through providing friendly and professional customer support\nProvide feedbacks to the company to advocate for our customers\u00a0\n\nWe look for:\n\n1-3 years settlement or\u00a0client service experience in financial front o\ufb00ice, online payments, cryptocurrency, foreign exchange trading, etc is an advantage\nPassionate and committed professional with excellent interpersonal skills\nStrong work ethic and accountability\nService-oriented mind, pleasant\nMulti-tasker and quick learner\nPositive person who can turn challenges into opportunities\nAble to work under pressure with time constraint\nProficiency in Mandarin, Cantonese and English communication (verbal & writing)\nWilling to work on different shift\u00a0and public holidays\nOver-night shift is highly preferred, also welcome to apply for day shift\n\nWe offer:\n\nAttractive remuneration package with performance bonus\nShift and meal allowance for night shift staff\nPrivilege insurance plan for group medical (covers clinical, hospitalization with supplementary major medical) & dental\n5-day workweek, flexible work hours\nConvenient office location in Tsimshatsui\nWork with young and energetic team\nOpportunities to participate in blockchain projects\nFree snacks, coffee, and tea\u00a0\nFestival red packets and gifts\nEmployee referral bonus\nRegular staff activities\u00a0\n\nIf you are interested in this position and want to get a new exposure in Fintech industry, please don\u2019t hesitate to apply with your full resume, present/expected salary and availability by click on the 'Apply Now' button.\u00a0\n\nAll personal data collected will be\u00a0treated in strict confidence\u00a0and used for recruitment purpose only.\u00a0", "employment_types": ["Full Time", "Permanent"], "selling_points": [], "locations": ["Tsing Yi"], "categories": ["Accounting", "Accounting Clerk / Supervisor", "Others", "Admin & HR", "Clerical / Admin Staff"], "post_time": "2022-01-14T02:15:41Z", "salary": {"currency": null, "max": null, "min": null, "period": "monthly", "term": null}, "salary_visible": false, "title_keywords": ["accounting officer"], "responsibilities": ["operations", "procedures", "communication", "payments", "reports", "work under pressure"], "requirements": {"degrees": [], "majors": [], "languages": ["cantonese", "english", "mandarin"], "language_level": ["proficiency"], "hard_skills": ["blockchain", "crypto", "exchange", "cryptocurrency"], "soft_skills": ["passionate", "accountability", "service-oriented", "quick learner", "pleasant", "communication", "committed", "friendly", "interpersonal skills", "work ethic", "positive", "work under pressure"], "languages_combined": [{"language": "cantonese", "language_level": ["proficiency"]}, {"language": "english", "language_level": ["proficiency"]}, {"language": "mandarin", "language_level": ["proficiency"]}]}, "experience_required": {"duration": ["1-3 years"], "field": ["trading", "financial"]}}, {"job_id": "100003009050314", "location_code": "hk", "company": "Meta Air Labs Limited", "job_title": "Settlement & Customer Service Officer (Fintech, Over-Night Shift)", "description": "Reporting to the Senior Manager (Non-life Business), the incumbent will undertake the following:\n\nKey Responsibilities\n\nPerform prudential supervision of authorized non-life insurers\nParticipate in conducting inspection and monitoring non-life insurers' compliance with regulatory requirements\nSupport initiatives to promote the non-life insurance market of Hong Kong\nOther duties as assigned by senior management to facilitate the administration of the statutory functions of IA\u00a0\n\nRequirements\n\nA Bachelor\u2019s degree in accounting, finance, economics, statistics, actuarial science or related disciplines. Qualified CPA or actuary is recommended\nMinimum 5 years' solid work experience\nKnowledge of the local regulatory requirements, insurance products, industry practices and market dynamics relating to the insurance business.\nWork experience in a local or overseas insurance regulatory agency or non-life actuarial practices is preferred\nStrong problem-solving, analytical, interpersonal and communication skills, and able to work in a team in a collaborative environment\nAble to work independently and under pressure\nStrong command of both written and spoken English and Chinese. Proficiency in Putonghua will be an advantage\u00a0\n\nRemuneration Package\nA competitive remuneration package commensurate with the successful candidate\u2019s experience and qualifications will be offered.\n\nApplication\nReview of the applications will start as soon as possible and continue until the posts are filled. Interested applicants may send a letter of application quoting the reference number in the heading, together with a full resume stating public examination and university academic results as well as current and expected salaries by clicking \"Apply Now\".\n\nThe Insurance Authority is an equal opportunities employer. Applicants not invited for an interview within 2 months from the submission date may assume their applications unsuccessful. Applications may be considered for other suitable positions within IA. All applications will be handled in strict confidence and the information collected will only be used for recruitment purposes. All information on non-shortlisted applicants will be destroyed after 6 months from the submission of their applications.", "employment_types": ["Full Time"], "selling_points": ["Opportunity to learn settlement and blockchain", "Numeric sensitive, quick learner, can-do attitude", "Welcome to apply for day or overnight shift"], "locations": ["Tsim Sha Tsui"], "categories": ["Accounting", "Others", "Banking / Finance", "Others", "Sales, CS & Business Devpt", "Others"], "post_time": "2022-01-14T10:06:48Z", "salary": {"currency": null, "max": null, "min": null, "period": "monthly", "term": null}, "salary_visible": false, "title_keywords": ["customer service officer"], "responsibilities": ["other duties", "regulatory requirements", "compliance", "monitoring", "inspection", "senior management", "insurance", "administration"], "requirements": {"degrees": ["degree", "bachelor"], "majors": ["actuarial science", "finance", "economics", "statistics", "related disciplines", "accounting"], "languages": ["putonghua", "english", "chinese"], "language_level": ["advantage", "proficiency"], "hard_skills": ["cpa", "problem-solving"], "soft_skills": ["communication skills", "work independently", "confidence", "under pressure", "problem-solving", "collaborative", "interpersonal"], "languages_combined": [{"language": "putonghua", "language_level": ["proficiency", "advantage"]}, {"language": "english", "language_level": []}, {"language": "chinese", "language_level": []}]}, "experience_required": {"duration": ["minimum 5 years"], "field": ["agency", "insurance"]}}]