[{"job_id": "100003009054516", "location_code": "hk", "company": "China Mobile International Limited", "job_title": "Tax Accountant (Ref:CMIJD-0117-TATXFINHK)", "description": "Responsibilities:\u00a0\n\nPrepare and review tax compliance work in accordance to the relevant tax law and regulations\nSupport in half-year and year-end tax reporting preparation and review process\nSupport international tax and transfer pricing related issues\nWork closely with external tax advisor and colleagues in overseas to compute and analyze direct/indirect tax\nAssist in tax advisory for international business operations and expansion\nKeep abreast of the new tax laws & regulations and assess the impacts brought on different businesses\nCoordinate engagement and maintain productive working relationship with external tax advisor\nInvolve in preparation of tax proposals to senior management\nHandle ad-hoc projects as instructed by supervisor\n\nRequirements:\n\nDegree holder in Accounting/Finance or any other business related discipline and ideally with professional qualification (e.g. CPA, ACCA)\nAt least 4-5 years of corporate tax /indirect tax related working experience gained from Big 4 and/or MNCs is preferable; Candidate with less experience could be considered as Tax Officer\nKnowledge in regional/international tax, tax accounting is a plus\nExperiences from Telecom industry is definitely an advantage\nSelf-motivated with good tax accounting skill\nTeam player with strong interpersonal, research and presentation skills\nProficiency in MS Office applications and Chinese Word Processing\nGood command in both spoken Chinese & English; Putonghua is a MUST\nQuick learner and willing to work in dynamic environment\n\nInterested parties please send your full resume with current & expected salary\u00a0by clicking \"Apply Now\".\n\n\u00a0All personal data collected will be used for recruitment and employment related purpose only.", "employment_types": ["Full Time", "Permanent"], "selling_points": ["Prepare and review tax compliance tasks", "Exposure in global tax and transfer pricing issues", "Tax advisory for international business expansion"], "locations": ["Kwai Hing"], "categories": ["Accounting", "Accountant", "Taxation", "Others"], "post_time": "2022-01-17T09:51:07Z", "salary": {"currency": null, "max": null, "min": null, "period": "monthly", "term": null}, "salary_visible": false, "title_keywords": ["accountant"], "responsibilities": ["tax", "year-end", "regulations", "reporting", "ad-hoc projects", "operations", "compliance", "review", "coordinate", "maintain", "senior management"], "requirements": {"degrees": ["degree holder"], "majors": ["business", "finance", "accounting"], "languages": ["putonghua", "english", "chinese"], "language_level": ["proficiency", "good command"], "hard_skills": ["acca", "plus", "chinese word processing", "cpa", "dynamic", "ms office"], "soft_skills": ["self-motivated", "dynamic environment", "quick learner", "presentation skills", "team player", "interpersonal"], "languages_combined": [{"language": "putonghua", "language_level": []}, {"language": "english", "language_level": ["good command"]}, {"language": "chinese", "language_level": ["proficiency", "good command"]}]}, "experience_required": {"duration": ["at least 4-5 years"], "field": ["related", "big 4"]}}, {"job_id": "100003009052287", "location_code": "hk", "company": "PwC", "job_title": "Manager / Senior Associate - Tax Technology - PwC Tax - Hong Kong", "description": "About Tax\n\nTax and regulatory issues are on top of the mind for many companies operating around the world today. As a tax professional, you will help organisations and individuals maximise their tax efficiency and manage their tax risks. You achieve this through the advice you give your clients on how to conduct proper tax planning, and helping your clients to fully meet their tax compliance obligations.\n\nTaxation in a fast-paced business environment is exciting and intellectually stimulating. In order for you to face up to the challenges, you will need to constantly develop your tax knowledge and research skills. As you progress, you will likely become specialised in certain tax speciality area and particular industries.\n\nAbout Tax Technology Team\n\nThe Tax Technology team is responsible for all technology based business solutions for the Tax division in the China and Hong Kong region. Moreover, the team serves as a contact point and liaison for other territories within as well as outside the Asia-Pacific region in relation to tax technology. We work closely with both the tax professionals and IT specialists within the Firm to support the systems life cycle of concurrent tax technology projects so as to deliver best-in-class technology-based business solutions.\n\nJob description and responsibilities:\n\nUnderstand business and client needs and derive business requirements, functional design, and process design\nPerform systems and/or proposal comparisons, analysis, and evaluations with engagement team\nAssist in analysing business processes, identifying potential automation opportunities and creating Process Description Document, and Solution Design Document\nAssist in planning and tracking projects tasks and timeline\nPerform testing and handle related issues during development and implementation of software projects\nCollect feedback and monitor on software projects after launch\n\nRequirements:\n\nGreat written and verbal communications skills in both English and Chinese\nAbility to work well and communicate effectively with other professionals\nProficiency in ASP, .NET ,C# , JAVA or any kind of programming language\nFunctional knowledge of SQL and object-oriented programmingcoding methodologies\nDemonstrate understanding of different software development life-cycle methodologies\nStrong organizational and analytical skills to research, compile and clearly present information and data\nMust be proficient in Word, Excel and PowerPoint\nAbility to function well in a fast-paced, dynamic environment with competing priorities and tight deadlines\nHands-on experience with system design, implementation and quality assurance is a plus\nBSc / BEng in Computer Science, Math, Physics or Engineering is preferred\nJunior candidates will be considered as Associate", "employment_types": ["Full Time", "Permanent"], "selling_points": ["Technology Based Business Solutions for Tax", "Fast-paced and Intellectually Stimulating", "ASP NET C# JAVA"], "locations": ["Central"], "categories": ["Accounting", "Taxation", "Information Technology (IT)", "IT Project Management / Team Lead", "Software Development"], "post_time": "2022-01-17T02:39:03Z", "salary": {"currency": null, "max": null, "min": null, "period": "monthly", "term": null}, "salary_visible": false, "title_keywords": ["senior associate", "manager"], "responsibilities": ["software", "analysis", "systems", "monitor", "implementation", "design", "testing", "planning", "tracking"], "requirements": {"degrees": ["bsc"], "majors": ["math", "engineering", "computer science", "physics"], "languages": ["english", "chinese"], "language_level": [], "hard_skills": ["excel", "java", "plus", "word", "powerpoint", "analytical skills", "sql", "dynamic", "system design", "programming", "math", "c#"], "soft_skills": ["organizational", "dynamic environment", "hands-on", "analytical skills"], "languages_combined": [{"language": "english", "language_level": []}, {"language": "chinese", "language_level": []}]}, "experience_required": {"duration": [], "field": ["system design", "quality assurance"]}}, {"job_id": "100003009052950", "location_code": "hk", "company": "Fung, Yu & Co. CPA Limited", "job_title": "Internship - Audit Department/Accounting Services Department", "description": "If you want to\n\ngain valuable internship experience on audit work\nbuild up diversified concepts of doing audit for different business nature companies\nget the skill sets of presentation, interpersonal, communication to enrich your competitiveness in the future career\n\nOur internship program contains\n\nconcepts and practices of audit\nperforming audit work\naudit case study\npresentation\n\nIf you are\n\nwilling to learn\nenergetic and passionate\nHKID Holders\n\nWhat We Offer\n\nwork reference letter\non-job training\n\nWelcome to join us in this winter!\n\nPlease submit your application by clicking \u201cApply Now\u201d button.\n\nWelcome to visit our company website http://www.fungyucpa.com/\u00a0for more information.\n\nPersonal data collected will be used for recruitment purposes only.", "employment_types": ["Internship"], "selling_points": ["University degree holder majoring in accountancy", "Audit/Accounting", "Intern"], "locations": ["Central & Western Area"], "categories": ["Accounting", "Audit", "Consulting", "Taxation"], "post_time": "2022-01-17T04:39:36Z", "salary": {"currency": null, "max": null, "min": null, "period": "monthly", "term": null}, "salary_visible": false, "title_keywords": ["accounting", "internship"], "responsibilities": ["communication", "audit"], "requirements": {"degrees": [], "majors": [], "languages": [], "language_level": [], "hard_skills": [], "soft_skills": ["passionate", "presentation", "willing to learn", "communication", "energetic", "interpersonal"], "languages_combined": []}, "experience_required": {"duration": [], "field": ["audit"]}}, {"job_id": "100003009052314", "location_code": "hk", "company": "PwC", "job_title": "Manager - China Corporate Tax - PwC Tax - Hong Kong", "description": "Job Description & Responsibilities\n\nAssist clients in their China tax compliance obligations, including preparation of tax computations and returns, and handling correspondence with the Mainland Tax Bureau;\nProvide China tax advisory and consulting services to clients;\nDevelop and maintain client relationships;\nManage and develop a team of professional staffs; and\nPerform initial client needs analysis, determine the key areas of service that we want to pursue and develop value propositions and pitches for the client\nRequirements\n\nA recognised degree holder preferably in accounting or equivalent;\nQualified member of a professional accounting body;\nMinimum five to eight years of China tax experience;\nConfident with a strong business sense;\nAbility and aptitude in managing multiple stakeholders both internally and externally;\nSolid project management experience with strong analytical and organizational skills\nExcellent interpersonal and communication skills;\nProficient in both written and spoken English; and\nFluency in Putonghua.\nIn addition, candidates should illustrate the following personal attributes:\n\nDemonstrates courage and integrity\nAcquires and applies commercial and technical expertise by staying up to date in industry and with market trends\n\u00a0Manages projects and economics efficiently; planning and performing work in accordance with client requirements and professional standards\u00a0\nOpen minded, agile with change and practical\nCommitted to self develop and coaching of others for growth\nCommunicates with impact and empathy\nActively shares ideas and knowledge and is innovate\nLead and contribute to team success\nIs passionate about client service", "employment_types": ["Full Time", "Permanent"], "selling_points": ["Manage and develop a team of professional staffs", "Develop and maintain client relationships", "Qualified member of a professional accounting body"], "locations": ["Central"], "categories": ["Accounting", "Accountant", "Taxation"], "post_time": "2022-01-17T02:43:57Z", "salary": {"currency": null, "max": null, "min": null, "period": "monthly", "term": null}, "salary_visible": false, "title_keywords": ["manager"], "responsibilities": ["tax", "consulting", "analysis", "compliance", "develop", "maintain"], "requirements": {"degrees": ["degree holder"], "majors": ["accounting"], "languages": ["putonghua", "english"], "language_level": ["fluency", "proficient"], "hard_skills": ["project management", "agile"], "soft_skills": ["confident", "organizational skills", "communication skills", "agile", "business sense", "integrity", "project management", "committed", "open minded", "empathy", "interpersonal", "passionate about"], "languages_combined": [{"language": "putonghua", "language_level": ["fluency"]}, {"language": "english", "language_level": ["proficient"]}]}, "experience_required": {"duration": ["minimum five to eight years"], "field": ["project management", "analytical"]}}, {"job_id": "100003009051835", "location_code": "hk", "company": "PwC", "job_title": "Manager / Senior Manager - Private Client Services - PwC Tax - Hong Kong", "description": "Job Description & Summary\n\nA career in our Tax Wealth Advisory practice, within Tax services, will provide you with the opportunity to help our clients meet and manage their tax obligations across unique but ever changing tax specialties. You\u2019ll advise clients on their local and overseas tax affairs, while acting as a strategic consultant related to business analysis, managing indirect taxes, dispute resolution, and global enterprise tax solutions.\n\nOur team offers clients a scalable solution to address the tax compliance needs of corporations, partnerships, and other business entities by managing compliance services to maximise a tax department\u2019s strengths and minimise the impact on our clients resources. You\u2019ll support clients by providing outsourcing services which includes the preparation and review of income and franchise returns along with responding to inquiries from federal, state and local taxing authorities for our clients.\n\nAssist in preparation of documentation in relation to and support superiors to handle family wealth planning projects\n\nAssist in the set-up of asset holding structure for family wealth planning purposes\n\nAssist in the formation of Hong Kong or offshore companies and the ongoing maintenance including the filing of the necessary returns with the registration authority\n\nAssist in the application and ongoing maintenance of immigration matters\n\nRequirements\n\nA degree holder preferably in Accounting/Law/Corporate Governance but not essential.\n\nStudent member of ICSA / HKICS/HKICPA will be an advantage.\n\nFive years of company secretarial or personal tax experience preferable\n\nProficient in English and Chinese. Putonghua is essential.\n\nChinese writing and reading skill is essential.\n\nA team player with strong initiative and able to work under pressure.\n\n\n\n\u6709\u610f\u7533\u8acb\u8005\u8acb \u6309 APPLY NOW\u7533\u8acb\n\n", "employment_types": ["Full Time"], "selling_points": [], "locations": ["Not Specified"], "categories": ["Accounting", "Finance / Accounting Manager", "Taxation", "Management", "General Management"], "post_time": "2022-01-17T01:19:31Z", "salary": {"currency": null, "max": null, "min": null, "period": "monthly", "term": null}, "salary_visible": false, "title_keywords": ["senior manager", "manager"], "responsibilities": ["tax", "documentation", "maintenance", "compliance", "review", "resolution", "support clients", "business analysis", "planning"], "requirements": {"degrees": ["degree holder"], "majors": ["accounting", "law"], "languages": ["putonghua", "english", "chinese"], "language_level": ["proficient"], "hard_skills": ["hkicpa"], "soft_skills": ["team player", "initiative", "work under pressure"], "languages_combined": [{"language": "putonghua", "language_level": []}, {"language": "english", "language_level": ["proficient"]}, {"language": "chinese", "language_level": ["proficient"]}]}, "experience_required": {"duration": ["five years"], "field": ["secretarial"]}}, {"job_id": "100003009052349", "location_code": "hk", "company": "PwC", "job_title": "Manager, Integrated Tax and Business Consulting, Tax Services, Hong Kong", "description": "Job Description\n\nAbout PwC \u2013 Globally PwC firms help organizations and individuals create the value they\u2019re looking for. We're a network of firms in 158 countries with close to 169,000 people who are committed to delivering quality in assurance, tax and advisory services.\n\nPwC - Mainland China, Hong Kong and Macau\n\nPwC in Mainland China, Hong Kong and Macau work together on a collaborative basis, subject to local applicable laws. Collectively, we have around 500 partners and a strength of around 12,100 people.\n\nProviding organizations with the advice they need, wherever they may be located. Our highly qualified, experienced professionals listen to different points of view to help organizations solve their business issues and identify and maximize the opportunities they seek. Our industry specialization allows us to help co-create solutions with our clients for their sector of interest.\n\nWe are located in these cities: Beijing, Shanghai, Tianjin, Chongqing, Dalian, Xi'an, Qingdao, Nanjing, Suzhou, Hangzhou, Ningbo, Xiamen, Guangzhou, Shenzhen, Hong Kong and Macau.\n\nJob description\u00a0\n\nProvide HK tax compliance and consulting services to clients in one of the industries:- retail, financial services, trading, technology, manufacturing, transportation or logistics;\nLead cross-teams and regional tax advisory and consulting projects, such as company public listing, merger and acquisition, group restructuring, transfer pricing study, operations review and tax dispute resolutions; and\nOpportunities to develop specialty in a certain industry with international tax exposure\n\nRequirements\u00a0\n\nUniversity graduate or above;\nQualified member of a professional accounting body and/or tax body;\nMinimum 6 years of relevant experience in HK tax compliance and consultancy;\nGood command of written and spoken English and Chinese (Cantonese and Mandarin); and\nWilling to take on challenges.\n\n\n", "employment_types": ["Full Time", "Permanent"], "selling_points": ["Corporate Tax Advisory", "Supportive Team Environment", "Excellent Career Track"], "locations": ["Central"], "categories": ["Accounting", "Taxation"], "post_time": "2022-01-17T02:49:44Z", "salary": {"currency": null, "max": null, "min": null, "period": "monthly", "term": null}, "salary_visible": false, "title_keywords": ["manager"], "responsibilities": ["tax", "consulting", "operations", "compliance", "quality", "teams", "review", "develop", "logistics", "listing"], "requirements": {"degrees": ["university graduate or above"], "majors": [], "languages": ["cantonese", "english", "chinese", "mandarin"], "language_level": ["good command"], "hard_skills": [], "soft_skills": [], "languages_combined": [{"language": "cantonese", "language_level": ["good command"]}, {"language": "english", "language_level": ["good command"]}, {"language": "chinese", "language_level": ["good command"]}, {"language": "mandarin", "language_level": ["good command"]}]}, "experience_required": {"duration": ["minimum 6 years"], "field": ["compliance", "relevant experience"]}}, {"job_id": "100003009052286", "location_code": "hk", "company": "PwC", "job_title": "Associate / Senior Associate - Financial Services Tax -  PwC Tax", "description": "About Financial Services Tax Practice\n\nOur practice being the largest amongst professional accounting firms in Hong Kong, serves Hong Kong, mainland and international clients in the banking and capital markets, insurance and asset management industries.\u00a0 We provide tax compliance and consulting services to our clients.\u00a0\n\nJob Description\n\nProvide HK tax compliance and consulting services to clients in one of the industries:- retail, financial services, trading, technology, manufacturing, transportation or logistics;\nWork with a team of professionals on cross-teams and regional tax advisory and consulting projects, such as public listing, merger and acquisition, group restructuring, transfer pricing study, operations review and tax dispute resolutions; and\nStructured training will be provided equipping you to become a professional advisor\nRequirements\n\n\u00a0University graduate or above;\nQualified member of a professional accounting body is preferred;\nMinimum three years of relevant tax experience;\nGood command of both spoken and written English and Chinese; Mandarin is a plus", "employment_types": ["Full Time", "Part Time"], "selling_points": ["Services HK, mainland and international clients", "Largest practice in the Market", "Excellent Learning and Development Opportunity"], "locations": ["Central"], "categories": ["Accounting", "Taxation", "Banking / Finance", "Others"], "post_time": "2022-01-17T02:39:03Z", "salary": {"currency": null, "max": null, "min": null, "period": "monthly", "term": null}, "salary_visible": false, "title_keywords": ["senior associate", "associate"], "responsibilities": [], "requirements": {"degrees": [], "majors": [], "languages": [], "language_level": [], "hard_skills": [], "soft_skills": [], "languages_combined": []}, "experience_required": {"duration": [], "field": []}}, {"job_id": "100003009052161", "location_code": "hk", "company": "BDO", "job_title": "Associate - Tax (Graduate Recruitment - 2021 Intake)", "description": "Overview\n\nAs an associate of tax, you will provide tax services for a variety of clients. You have to ensure that all of their deliverables are completed on time and within budget for their senior and manager\n\nResponsibilities\n\nAssist the seniors and managers as part of a wider team to service their clients\nEnsure client files have all relevant documentation on the appropriate section\nTake responsibility for all client matters as directed by the senior and manager\nPrepare client tax returns required by the senior and manager\nActive adherence to budget and time pressures, bringing matters to the attention of the senior or manager\nPreparation of engagement letters and client acceptance documentation\nMust demonstrate strong team playing skills in all client and internal management dealings\nDevelop professional relationships with clients and within the firm\nProvide an efficient and pro-active service to clients and their internal management to ensure that their needs are fully met\nUndertake any training or development coordinated by the tax team\nWilling and open to take on tasks and challenges provided by their manager\nComplete additional ad-hoc duties or assignments as required\n\nRequirements\n\nBachelor degree in Accounting, Economics, Financial Services or equivalent subject\nAwareness of legal and economic environment of business and to related these to the clients\u2019 organizations and its activities and plans\nBe able to develop a clear understanding of relevant legislation\nSelf-motivated, able to work to tight deadlines\nWith an ability and interest in understanding clients\u2019 business\nGraduated in 2021\n\nWe are an equal opportunity employer, and offer excellent prospects and career development for the right candidate.\u00a0 Interested parties please send your application\u00a0with full career history, current and expected salary by clicking\u00a0Apply Now button below.\n\nApplications will be treated in strict confidence. Personal data collected will be used for recruitment purposes only.", "employment_types": ["Full Time", "Permanent"], "selling_points": ["Fresh graduate is welcomed", "Excellent career prospects", "Birthday Leave, Medical and Life Insurance, etc."], "locations": ["Sheung Wan"], "categories": ["Accounting", "Taxation", "Others", "Student / Fresh Graduate / No Experience"], "post_time": "2022-01-17T02:17:56Z", "salary": {"currency": null, "max": null, "min": null, "period": "monthly", "term": null}, "salary_visible": false, "title_keywords": ["associate"], "responsibilities": ["tax", "management", "budget", "letters", "develop", "ad-hoc duties", "documentation"], "requirements": {"degrees": ["degree", "bachelor"], "majors": ["economics", "accounting"], "languages": [], "language_level": [], "hard_skills": [], "soft_skills": ["clear", "self-motivated"], "languages_combined": []}, "experience_required": {"duration": [], "field": []}}, {"job_id": "100003009047053", "location_code": "hk", "company": "Belden Asia ( Hong Kong ) Limited", "job_title": "Tax Manager", "description": "PURPOSE OF POSITION:\n\nSupporting the Asia tax team in various tax planning, structuring and corporate income tax compliance initiatives. Managing tax accounting, formulate and implement regional tax strategy in line with global tax strategy, optimize the tax position, manage country tax compliance and enhance the access to capital for Asia Pacific.\n\nKEY ACCOUNTABILITIES:\n\nWe have establishments in China, Hong Kong, Singapore, India, Japan, Korea, Australia, Thailand, Indonesia, Malaysia, Philippines, Vietnam and Taiwan.\n\nAssist Tax Director in review the corporate income tax filings for establishments in Asia Pacific\u00a0\nAssist the US GAAP tax accounting for the Asia Pacific establishments\nSupport to implementing of the Belden Group's transfer pricing policies and preparation of proper documentation\nAssist the planning and implementation of tax projects in the Asia Pacific region\nAssist the provision of support from corporate income tax and transfer pricing perspectives to the different functional and business teams within the Belden Group\n\nREQUIREMENTS:\n\n7 years or above\u00a0tax and /or accounting working experience,\u00a0preferable in Big 4 accounting firms and/or multinational corporations\u00a0\nStrong research and technical skills\nExcellent written\u00a0and oral communication skills in English and Chinese\u00a0\nExperience in SAP (or other integrated accounting system) and Hyperion is an advantage", "employment_types": ["Permanent"], "selling_points": ["7 years or above of tax or accounting experience", "No commerical experience may also consider", "Excellent problem solving skills"], "locations": ["Shatin Area"], "categories": ["Accounting", "Taxation"], "post_time": "2022-01-14T02:16:36Z", "salary": {"currency": null, "max": null, "min": null, "period": "monthly", "term": null}, "salary_visible": false, "title_keywords": ["manager"], "responsibilities": ["tax", "policies", "review", "compliance", "implementation", "teams", "communication", "documentation", "planning"], "requirements": {"degrees": [], "majors": [], "languages": ["english", "chinese"], "language_level": ["excellent"], "hard_skills": ["documentation", "accounting system", "sap"], "soft_skills": ["technical skills", "communication skills", "oral"], "languages_combined": [{"language": "english", "language_level": ["excellent"]}, {"language": "chinese", "language_level": ["excellent"]}]}, "experience_required": {"duration": ["7 years"], "field": ["accounting", "big 4"]}}, {"job_id": "100003009051341", "location_code": "hk", "company": "EY", "job_title": "Tax - Customer Tax Operations & Reporting Services - Senior - Hong Kong", "description": "The opportunity\n\nIn EY Tax, you\u2019ll have the opportunity to help the world\u2019s leading multinational organizations meet complex tax obligations around the world. You\u2019ll get a unique glimpse deep inside a company\u2019s business and become a trusted advisor, working collaboratively on a team that influences major business decisions.\u00a0Demand has made this a rapidly growing area, and the relationships we build here translate into big business in other areas, making this a true priority.\n\n\nYour key responsibilities\n\nJoin the fast-growing Asia Pacific Customer Tax Operations and Reporting Services practice to deliver complex AEOI engagements. As part of the team, you will work closely with team members across the Asia Pacific region while you are also required to interact with teams in other parts of the world, e.g. the US.\nTake part in various types of AEOI engagements which include advisory, compliance, reporting and transformation projects for financial institution clients from all sectors.\nUse the latest EY technologies in the engagement delivery.\nPartner with Tax Technology & Transformation to deliver innovative EY solutions which gives the unique value proposition.\nAssist clients in handling enquiries or inspections from tax authorities and other controversy matters.\nAssist in pursuits and the preparation of proposals.\n\nTo qualify for the role you must have\n\nBachelor or advanced degree in Accounting, Law, Finance or Economics, Business, IT or other relevant disciplines.\nExcellent command in both written & spoken English. High proficiency in Chinese and/or other language is preferable.\nEnergetic, hardworking, strong analytical, business savvy.\nTeam player with strong communication skills.\nStrong presentation, organization and management skills.\nGood at Microsoft Office. Appreciation of visualization / data analytics tools would be welcomed.\n\nIdeally, you\u2019ll also have\n\nPrevious experience dealing with clients within the financial services sector is strongly preferred\nPrevious experience dealing with information exchange matters (FATCA, CRS) or information reporting and withholding matters\nMature, proactive, committed, highly motivated and driven team player\n\nWhat we look for\n\nWe\u2019re interested in strong team players who support their colleagues in reaching their goals while also considering their own workload and development. We\u2019re looking for people with a genuine passion for tax, and the future of tax, and are inspired to help the world\u2019s leading multinational organizations meet complex tax obligations around the world. If you have the confidence to speak up and influence a team that affects big businesses worldwide, this role is for you.\n\nWhat working at EY offers\n\nAt EY, our Total Rewards package supports our commitment to creating a leading people culture\u00a0-\u00a0built on high-performance teaming\u00a0-\u00a0where everyone can achieve their potential and contribute to building a better working world for our people, our clients and our communities. It's one of the many reasons we repeatedly win awards for being a great place to work.\n\nWe offer\u00a0a\u00a0competitive\u00a0compensation\u00a0package where you\u2019ll be rewarded based on your performance and recognized for the value you bring to our business. In addition, our Total Rewards package allows you decide which benefits are right for you and which ones help you create a solid foundation for your future. Our Total Rewards package includes a comprehensive medical, prescription drug and dental coverage, a defined contribution pension plan, a great vacation policy plus firm paid days that allow you to enjoy longer long weekends throughout the year, statutory holidays and paid personal days (based on province of residence), and a range of exciting programs and benefits designed to support your physical, financial and social well-being. Plus, we offer:\n\nSupport and coaching from some of the most engaging colleagues in the industry\nLearning opportunities to develop new skills and progress your career\nThe freedom and flexibility to handle your role in a way that\u2019s right for you\n\nAbout EY\n\nAs a global leader in assurance, tax, transaction and advisory services, we\u2019re using the finance products, expertise and systems we\u2019ve developed to build a better working world. That starts with a culture that believes in giving you the training, opportunities and creative freedom to make things better. Whenever you join, however long you stay, the exceptional EY experience lasts a lifetime.\n\nIf you can confidently demonstrate that you meet the criteria above, please contact us as soon as possible.\n\nMake your mark.\n\nApply today.", "employment_types": ["Full Time", "Permanent"], "selling_points": ["Asia Pacific Tax Services", "FATCA/CRS/AEOI", "Latest EY technologies in engagement delivery"], "locations": ["Not Specified"], "categories": ["Accounting", "Taxation", "Others", "Professional Services", "Legal & Compliance"], "post_time": "2022-01-15T09:53:39Z", "salary": {"currency": null, "max": null, "min": null, "period": "monthly", "term": null}, "salary_visible": false, "title_keywords": ["operations"], "responsibilities": ["tax", "reporting", "management", "analytics tools", "visualization", "data", "operations", "compliance", "teams", "communication"], "requirements": {"degrees": ["degree", "bachelor"], "majors": ["law", "finance", "economics", "business", "it", "accounting"], "languages": ["english", "chinese"], "language_level": ["excellent", "proficiency"], "hard_skills": ["crs", "microsoft office", "data analytics", "fatca", "exchange"], "soft_skills": ["communication skills", "proactive", "confidence", "advanced", "passion for", "deep", "driven", "interested in", "unique", "innovative", "mature", "committed", "genuine", "motivated", "team player", "energetic", "presentation", "hardworking"], "languages_combined": [{"language": "english", "language_level": ["excellent"]}, {"language": "chinese", "language_level": ["proficiency"]}]}, "experience_required": {"duration": [], "field": ["financial services"]}}, {"job_id": "100003009052339", "location_code": "hk", "company": "PwC", "job_title": "Senior Associate - Integrated Tax and Business Consulting - Tax", "description": "Job Description & Summary\n\n\n\nA career within Corporate Tax services, will provide you with the opportunity to help our clients meet their tax obligations while managing the impact tax has on their business. You\u2019ll advise clients on their local and overseas tax affairs, while acting as a strategic consultant related to business analysis, managing working capital, and profit sharing for partners. You\u2019ll also help organisations understand the pricing implications of goods and services between related parties, as well as providing advice on tax implications of deals.\n\nOur team helps our clients improve their tax function to control risk and facilitate better decision making. You\u2019ll focus on helping businesses with tax strategy, ensuring tax compliance, increasing post tax profits, and providing application support to achieve the best corporate tax practices.\n\nTo really stand out and make us fit for the future in a constantly changing world, each and every one of us at PwC needs to be a purpose-led and values-driven leader at every level. To help us achieve this we have the PwC Professional; our global leadership development framework. It gives us a single set of expectations across our lines, geographies and career paths, and provides transparency on the skills we need as individuals to be successful and progress in our careers, now and in the future.\n\nJob Description\u00a0\n\nAssisting clients in complying with their tax compliance obligations, including preparation of tax computations and returns, and handling correspondence with the Inland Revenue Department\nProviding tax advisory services to clients\nDeveloping and maintaining client relationships\nRequirements\n\nDegree holder in accounting or equivalent\nQualified member of a professional accounting body is preferred\nMinimum three years of relevant tax experience\nSound project management skills with strong business sense\nExcellent interpersonal and communication skills\nProficient in both written and spoken English and Chinese (Cantonese & Mandarin)\nFluent in Mandarin would be a definite advantage\nMore junior candidates will be considered as Associates", "employment_types": ["Full Time", "Permanent"], "selling_points": ["Leading Corporate Tax Practice", "Good Corporate Benefits", "Opportunity to Learn in a Team Environment"], "locations": ["Central"], "categories": ["Accounting", "Accountant", "Taxation"], "post_time": "2022-01-17T02:48:22Z", "salary": {"currency": null, "max": null, "min": null, "period": "monthly", "term": null}, "salary_visible": false, "title_keywords": ["senior associate"], "responsibilities": ["tax", "control", "maintaining", "compliance", "developing", "business analysis"], "requirements": {"degrees": ["degree holder"], "majors": ["accounting"], "languages": ["cantonese", "english", "chinese", "mandarin"], "language_level": ["advantage", "fluent", "proficient"], "hard_skills": ["project management"], "soft_skills": ["communication skills", "project management skills", "interpersonal", "business sense"], "languages_combined": [{"language": "cantonese", "language_level": []}, {"language": "english", "language_level": ["proficient"]}, {"language": "chinese", "language_level": ["proficient"]}, {"language": "mandarin", "language_level": ["fluent", "advantage"]}]}, "experience_required": {"duration": ["minimum three years"], "field": []}}, {"job_id": "100003008948269", "location_code": "hk", "company": "EY", "job_title": "Asia Pacific Tax Centre - Tax Accounting Risk Advisory Services - Manager/Senior Manager - Hong Kong", "description": "Trading\nJob Responsibilities:\n\nAccount Receivable, Account Payable\nPerform daily accounting functions including prepare voucher input and various payments\nAssist in projects and other ad hoc assignment\n\nJob Requirements :\n\nDiploma in Accounting\n2-4 year working experience in accounting field\u00a0\nFamiliar with Excel, Word and Chinese word processing\nInitiative, well-organised, hard working and willing to learn\n\nBenefit:\n\n5 days, bank holiday, medical scheme\n\n*Interested parties, please send full resume with current & expected salary & date available in MS WORD FORMAT ONLY to us\u00a0or fax to 3527 0634*\n\nWe are welcome applicants resend resumes to us even you have applied jobs in our company before.\n\nFor more jobs, please visit our website: www.hketernity.com\n\n(Personal data submitted are for recruitment purpose only.)", "employment_types": ["Full Time"], "selling_points": ["Asia Pacific Tax Center", "Income Tax, Bookkeeping & Tax Compliance - USGAAP", "International team and global exposures"], "locations": ["Quarry Bay"], "categories": ["Accounting", "Taxation", "Others", "Professional Services", "Business Consultancy"], "post_time": "2022-01-15T10:20:56Z", "salary": {"currency": null, "max": null, "min": null, "period": "monthly", "term": null}, "salary_visible": false, "title_keywords": ["senior manager", "accounting", "manager"], "responsibilities": ["daily accounting", "ad hoc assignment", "payments"], "requirements": {"degrees": ["diploma"], "majors": ["accounting"], "languages": ["chinese"], "language_level": [], "hard_skills": ["excel", "chinese word processing", "word"], "soft_skills": ["well-organised", "hard working", "willing to learn", "initiative"], "languages_combined": [{"language": "chinese", "language_level": []}]}, "experience_required": {"duration": ["2-4 year"], "field": ["accounting"]}}, {"job_id": "100003009044133", "location_code": "hk", "company": "Dah Chong Hong Holdings Limited", "job_title": "Tax Officer (Ref: GFN-Tax)", "description": "\nEY Asia-Pacific Tax Center (APTC) serves high-profile, multinational clients, providing a range of domestic and cross border tax services.\n\nThe opportunity\n\nOur Tax Accounting Risk Advisory Services (TARAS) practice operates within APTC, focus on helping clients effectively manage local statutory income tax reporting, bookkeeping and tax compliance obligations proactively and responsibly of our client\u2019s operations. TARAS professionals focus on details of income tax accounting, processes and internal controls over tax accounting and reporting. With engagements involving a few countries or many, you will have the opportunity to provide clients an integrated, consistent, quality service that unlocks the potential of the tax function across the entire record-to-report process.\n\nYour Key Responsibilities\n\nAs a Manager/Senior Manager in the services, you will spend your time transforming EY client\u2019s business. You will work with a variety of teams to understand their income tax processes and identify process and technology improvement opportunities across the record-to-report process. You may utilize a variety of tools and techniques to document current state and identify future state processes. You may design and configure automation tools, such as robotic process automation, data integration and workflow.\n\nFor key clients you will also help manage implementation of centrally managed global outsourcing/sourcing models that provide clients with greater control and visibility over global tax accounting compliance and reporting activities, access to global team members with finance expertise, and development of new operating models to address new markets. You will serve on audits of key clients including those requiring: HKAS 12, IAS 12 and US GAAP ASC 740 tax reporting requirements.\n\nSkills/Experience:\n\nFoundational accounting background including income tax accounting. Individuals from Assurance background in Financial Services strongly preferred.\nExperience in providing assurance services to listed clients including income tax accounts\nIdentify ways to automate manual tasks using existing financial or tax systems and emerging technologies\nExhibit competency in technology by maintaining complex sets of data, reviewing data analytics and analyzing trends including the collection of data as per agreed financial statement close timelines and other requirements\nExhibit critical thinking across EY methodologies/tools to enhance service delivery, challenge current procedures to find new approaches\nStrong spirit of entrepreneurship with colleagues and clients\nOpenness to collaborate with individuals from different backgrounds in an international environment\nFunction as Project Manager, team motivator, and oversee process guidance of workflow development\nTake ownership of tasks and make decisions and resolve issues including the escalation of client and internal partner issues while having a strong ability to work under pressure and strict deadlines\nAbility to think strategically to client centric solutions across: ESG reporting, Transactions, tax accounting process improvement, internal tax controls\nManaging, coaching and developing a team of staff and seniors, expectations to serve as counselors to junior resources\nBuild client relationships and demonstrate knowledge of client businesses\nScoping of new opportunities: develop proposals and participate in oral presentations provide high-quality services/work products build relationships with clients, understanding their unique needs to provide a tailored service\nTo qualify for the role you must have:\n\nA Bachelor's in Accounting or related field and a minimum of 7 years of related work experience\nStrong desire grow within EY as a TARAS specialist, team builder and client relationship management\nCertified Public Accountant or related designation being pursued\nAbility to lead a team, mentor counselees and manage client-serving business\nStrong organizational and time management skills, with exceptional client-serving consulting skills\nDemonstrated ability to capture and synthesize business requirements and entrepreneurship to operate in a new market and operate at a higher level\nWillingness to travel, expectations of 15%+ across APAC post Covid restrictions lifted\nIdeally, you\u2019ll also have\n\nBusiness Analyst background/experience\nExperience implementing robotic process automation\nMicrosoft Excel VBA development\nMicrosoft Power BI suite, including Power Pivot, Power Query, Power View and Power Map\nKnowledge and experience in the design and development of databases (specifically SQL Server)\nAlteryx\nERP experience, including SAP and/or Oracle\nWhat We Look For\n\nWe\u2019re interested in professionals who enjoy promoting the people agenda in organizations and change initiatives, bringing people issues and challenges to the forefront. You\u2019ll need the confidence to keep the people agenda front and centre, and the interpersonal skills and communications savvy to do this in a way that integrates well with executive priorities and objectives.\n\nWhat Working At EY Offers\n\nWe offer a competitive compensation package where you\u2019ll be rewarded based on your performance and recognized for the value you bring to services. In addition, our Total Rewards package includes medical and hospitalization benefits, group life and personal accident insurance, annual leave and Mandatory Provident Fund and a range of programs and benefits designed to support your physical and social well-being. Plus, we offer:\n\nSupport, coaching and feedback from some of the most engaging colleagues around\nOpportunities to develop new skills and progress your career\nThe freedom and flexibility to handle your role in a way that\u2019s right for you\nJoin us in building a better working world.\n\nApply now.", "employment_types": ["Full Time", "Permanent"], "selling_points": [], "locations": ["Kowloon Bay"], "categories": ["Accounting", "Financial Analyst", "Taxation", "Banking / Finance", "Corporate Finance"], "post_time": "2022-01-13T03:13:25Z", "salary": {"currency": null, "max": null, "min": null, "period": "monthly", "term": null}, "salary_visible": false, "title_keywords": ["officer"], "responsibilities": ["collaborate with", "consulting", "data", "operations", "quality", "design", "transactions", "financial statement", "work under pressure", "service delivery", "control", "maintaining", "compliance", "teams", "implementation", "developing", "develop", "presentations", "report", "reporting", "guidance", "management", "procedures", "audits", "tax", "power bi", "systems", "lead a team", "databases"], "requirements": {"degrees": ["bachelor"], "majors": ["accounting"], "languages": [], "language_level": [], "hard_skills": ["vba", "server", "bi", "sap", "data analytics", "presentations", "microsoft excel", "sql", "make", "erp", "databases", "alteryx", "integration", "focus", "oracle"], "soft_skills": ["oral", "confidence", "time management skills", "organizational", "interested in", "unique", "interpersonal skills", "think strategically", "focus", "work under pressure"], "languages_combined": []}, "experience_required": {"duration": ["minimum of 7 years"], "field": ["assurance", "related", "development", "design", "sql", "business", "accounting"]}}, {"job_id": "100003009052313", "location_code": "hk", "company": "PwC", "job_title": "Senior Associate - Tax Controversy Services, ITBC, Tax Services, Hong Kong", "description": "The position is responsible to assist on a range of Tax Planning and Compliance duties, and also provide administrative support to tax team and business partnering support.\n\nResponsibilities include:\n\nAssist and cooperate with various business units in handling Hong Kong Profits Tax compliance work\nProvide support in handling tax disputes of group companies in Hong Kong and the PRC with tax authorities\nAssist in implementing the Group\u2019s tax projects\nPrepare monthly reports and analysis, and provide support to facilitate other reporting requirements from headquarter\nAssist in handling ad hoc enquiries from group companies across HK, the PRC and Asia Pacific region\nPerform tax research and analysis on tax regulation changes\nPerform other related duties as assigned\n\nQualifications required:\n\nBachelor Degree in Finance, Accounting or related disciplines\n1-3 years of related experience in professional firm, the IRD or commercial field\nKnowledge and experience in HK, PRC and APAC taxes would be an advantage\nProficiency in Microsoft Excel, PowerPoint and reporting tools\nProficient in written and spoken English, Cantonese and Mandarin\nDetail-oriented, proactive and willing to work as a team\n\nWe offer competitive salary, discretionary bonus, medical insurance, life and personal accident insurance, annual leave and staff purchase discount. Interested candidates please send your resume with salary expectation by email or clicking\u00a0\"Apply Now\".\n\nWe are equal opportunities employer. Applicants who are not invited within 2 months may consider their application unsuccessful. All applicants may be considered for other suitable positions with DCH Group / CITIC Pacific Group and will be deleted from our files after 6 months from the date of application.", "employment_types": ["Full Time", "Permanent"], "selling_points": ["Resolving Tax Dispute, Tax Investigations", "3- 5 years Experience in Liaising with IRD", "Fluent in  English and Chinese"], "locations": ["Central"], "categories": ["Accounting", "Consulting", "Taxation"], "post_time": "2022-01-17T02:43:57Z", "salary": {"currency": null, "max": null, "min": null, "period": "monthly", "term": null}, "salary_visible": false, "title_keywords": ["senior associate"], "responsibilities": ["tax", "reporting", "provide support", "ad hoc", "monthly reports", "analysis", "compliance", "provide administrative support", "cooperate with", "planning"], "requirements": {"degrees": ["degree", "bachelor"], "majors": ["related disciplines", "finance", "accounting"], "languages": ["cantonese", "english", "mandarin"], "language_level": ["proficient"], "hard_skills": ["analysis", "powerpoint", "microsoft excel"], "soft_skills": ["work as a team", "proactive", "responsible", "detail-oriented"], "languages_combined": [{"language": "cantonese", "language_level": ["proficient"]}, {"language": "english", "language_level": ["proficient"]}, {"language": "mandarin", "language_level": ["proficient"]}]}, "experience_required": {"duration": ["1-3 years"], "field": ["related", "commercial"]}}, {"job_id": "100003009051327", "location_code": "hk", "company": "EY", "job_title": "Tax - Accounting Compliance and Reporting - Senior / Manager - Hong Kong", "description": "Job Descriptions and Responsibilities\n\nIn recent years, the Hong Kong Inland Revenue Department (\u201cIRD\u201d) has been deploying more resources on tax controversy and taking a more stringent approach in handling tax disputes with both corporate and individual taxpayers. Given the adoption of OECD\u2019s action plan on Base Erosion and Profit Shifting (\u201cBEPS\u201d) and the implementation of new tax regulations, taxpayers are facing more challenges and encountering with more tax controversy issues. To cope with the increasing market demand for tax controversy and dispute resolution services, our Tax Controversy Services (\u201cTCS\u201d) team is expanding and now recruiting experienced talents (preferably those who are familiar with the IRD\u2019s practices and/or with practical experience of dealing with the IRD) to join our TCS team.\n\nOur TCS team consists of ex-officers and tax specialists with strong expertise and experience in handling tax controversy. We are currently seeking high caliber tax professionals to join us and take part in:\n\nAssisting clients in resolving tax disputes, for example, tax audit and appeal cases, tax enquiries, challenges on the entitlement to treaty benefits;\nFormulation of settlement approaches for tax audit and investigation cases;\nNegotiation with the IRD\u2019s officers during the course of case resolving;\nHandling simple tax audit cases independently with direct partner supervision;\nPost-audit restructuring to rectify problems identified during tax audit;\nConducting tax health checks and defense file building;\nAssisting clients in obtaining treaty protection or treaty benefits, and defending against any challenges from the IRD;\nDeveloping and maintaining good client relationship at working level; and\nAssisting in the practice development for the TCS team and PwC.\n\nRequirements\n\nA recognized accounting or equivalent degree\nQualified member of a professional accounting body\nTotal 3- 5 years of experience in Hong Kong profits tax experience, preferably with experience of field audits / tax investigations or other areas of tax controversy\nWith IRD work experience is a plus, particularly experience in the Field Audit and Investigation Unit, Appeals Section or Treaty Section\nFluent in both written and spoken English, Cantonese and Putonghua\nExcellent interpersonal skills would be an advantage\nAnalytical-minded and solid in project management\nCandidates with more experience will be considered for Manager role\n\n\n\nThe PwC China (including Mainland China, Hong Kong, Macau) does not accept unsolicited resumes from search firm recruiters. Fees will not be paid in the event a candidate submitted by a recruiter without an agreement in place is hired; such resumes will be deemed the sole property of PwC China (including Mainland China, Hong Kong, Macau). PwC China (including Mainland China, Hong Kong, Macau) is an equal opportunity employer. All aspects of employment will be based on merit, competence, performance, and business needs. We do not discriminate on the basis of race, color, religion, marital status, age, national origin, ancestry, physical or medical condition, genetic information, gender, sexual orientation, gender identity or expression, veteran status, or any other status protected under the local law.", "employment_types": ["Full Time", "Permanent"], "selling_points": ["Participate in Accounting & Compliance Reporting", "Exposures in HKFRS/ IFRS/ USGAAP China GAAP", "Fast growing and dynamic team culture"], "locations": ["Not Specified"], "categories": ["Accounting", "Accountant", "Taxation", "Professional Services", "Legal & Compliance"], "post_time": "2022-01-15T08:57:58Z", "salary": {"currency": null, "max": null, "min": null, "period": "monthly", "term": null}, "salary_visible": false, "title_keywords": ["accounting", "manager"], "responsibilities": ["tax", "regulations", "implementation", "resolution", "plan"], "requirements": {"degrees": [], "majors": [], "languages": [], "language_level": [], "hard_skills": [], "soft_skills": [], "languages_combined": []}, "experience_required": {"duration": [], "field": []}}, {"job_id": "100003009051572", "location_code": "hk", "company": "Finest Industrial Co Ltd", "job_title": "Assistant Accountant / Accountant", "description": "The opportunity\u00a0\nEY Accounting Compliance & Reporting Services (\u201cACR\u201d) is one of the most fast-growing service lines under EY Tax Services. \u00a0In EY ACR, our services not only include accounting, statutory reporting and accounting compliance and support, but also extend to bringing values to EY clients by building proper data models to visualize and analyze the key performance measurements of client\u2019s business operations. \u00a0To create more values for EY\u00a0clients and further grow our businesses, we are looking for high caliber talents and professionals to join us.\nYour key responsibilities\u00a0\nParticipate in daily Bookkeeping, Accounting & Compliance Reporting engagements\nPrepare monthly financial report, vouchers and all the necessary schedules\nAssist the engagement team in data collection, data validation and data transformation\nAssist the engagement managers in building the right data model for further analysis in form of dashboard reporting\nDevelop and maintain effective working relationships with client personnel\nFollow through on client requests on a timely manner and manage expectations regarding the timing of deliverables and reports\nBuild strong internal relationships within the team and across other service lines\nUnderstand and follow EY workplace policies and procedures\nReceive direction from the Manager or above and execute procedures using the service delivery framework\nWork effectively as a team member, share responsibility, provide support, maintaining communication and update senior team members on engagement\u2019s progress\nArchive engagements\u2019 reports and correspondences on timely basis and EY policies\nRequirements:\n\nBachelor/Master's degree in Accounting, Finance, Business, IT, Engineering or related major\nGood knowledge of various accounting standards such as HKFRSs, IFRS, US GAAP, China GAAP etc\nWorking experience in asset management, PE Fund or investment companies is an advantage\nExcellent knowledge of business applications including MS Office, MS Excel, MS Word, PowerPoint etc\nKnowledge of data analytics and BI reporting tools such as MS Excel Power Query (M language), Power Pivot (DAX), Power BI, Tableau, Qlik View etc is preferred\nMastery of integrated ERP System (MS Navision, SAP, Dynamics, Oracle etc) is an advantage.\u00a0\nExperience and knowledge of cloud-based accounting and reporting software applications such as QuickBooks, Zero, Spotlight Reporting etc will be a bonus\nDemonstration of highly organized and disciplined working style, willingness to learn new skills, problem-solving skills under structured and unstructured working environments, multi-tasking and time-management skills, strong sense of responsibilities and ability to work under pressure\nStrong commitment to job, positive initiative, a good team player and with right attitude to work; and technically competent in handling day to day operations relating to accounting matters\nProficiency in written and spoken English, and good command of written Chinese. \u00a0Mandarin is an advantage\nIdeally, you\u2019ll also have\nEffective organization and time management skills with the ability to work under pressure and adhere to project deadlines \u00a0\nWhat we look for\nWe\u2019re interested in professionals who enjoy promoting the people agenda in organizations and change initiatives, bringing people issues and challenges to the forefront. You\u2019ll need the confidence to keep the people agenda front and center, and the interpersonal skills and communications savvy to do this in a way that integrates well with executive priorities and objectives. \u00a0\u00a0\nWhat working at EY offers\nWe offer a competitive compensation package where you\u2019ll be rewarded based on your performance and recognized for the value you bring to our services. In addition, our Total Rewards package includes medical and hospitalization benefits, group life and personal accident insurance, annual leave and Mandatory Provident Fund and a range of programs and benefits designed to support your physical and social well-being. Plus, we offer: \u00a0\nSupport, coaching and feedback from some of the most engaging colleagues around\nOpportunities to develop new skills and progress your career\nThe freedom and flexibility to handle your role in a way that\u2019s right for you\nIf you\u2019re looking for a role that\u2019ll challenge you, give you opportunities to grow and encourage you to own your career, this role is for you.\u00a0\nIf you can confidently demonstrate that you meet the criteria above, please contact us as soon as possible.\n\nMake your mark.\n", "employment_types": ["Full Time", "Permanent", "Contract"], "selling_points": [], "locations": ["Chai Wan"], "categories": ["Accounting", "Accountant", "Accounting Clerk / Supervisor", "Taxation"], "post_time": "2022-01-16T11:14:56Z", "salary": {"currency": null, "max": null, "min": null, "period": "monthly", "term": null}, "salary_visible": false, "title_keywords": ["accountant", "assistant accountant"], "responsibilities": ["service delivery", "reporting", "provide support", "maintaining", "data", "schedules", "policies", "analysis", "compliance", "a timely manner", "procedures", "develop", "communication", "maintain", "financial report", "reports", "data collection", "working relationships"], "requirements": {"degrees": ["degree", "bachelor", "master"], "majors": ["engineering", "finance", "business", "it", "accounting"], "languages": ["english", "chinese", "mandarin"], "language_level": ["advantage", "proficiency", "good command"], "hard_skills": ["ifrs", "bi", "oracle", "sap", "quickbooks", "data analytics", "accounting and reporting software", "powerpoint", "tableau", "ms excel", "erp system", "pe", "problem-solving skills", "ms office", "ms word"], "soft_skills": ["organized", "good team player", "confidence", "competent", "work under pressure", "time management skills", "interested in", "multi-tasking", "interpersonal skills", "problem-solving skills", "structured", "initiative", "positive", "sense of responsibilities"], "languages_combined": [{"language": "english", "language_level": ["proficiency", "good command"]}, {"language": "chinese", "language_level": ["good command"]}, {"language": "mandarin", "language_level": ["advantage"]}]}, "experience_required": {"duration": [], "field": ["accounting", "investment", "asset management"]}}, {"job_id": "100003009054600", "location_code": "hk", "company": "Procon CPA Limited", "job_title": "Junior/Senior Audit Officer(5-day work week)($17000-24000)", "description": "Job Description\nResponsible for full set of accounts independently\nHandle daily inter-company transaction / activities & general ledger\nAssist and monitor daily inventory/ import / export business & Custom EDI activities\nProcess A/P & A/R, credit control, P&L, payroll & various accounting matters of companies (HK & PRC)\nLiaise with Mainland China counterpart on accounting and taxation matters\nPrepare month-end closing schedules, costing analysis and related accounting reports\nAssist in other ad-hoc assignments\n\nRequirements\n\nDiploma holder or above or related discipline\n3-5 years working experience\nExperience in handling full-sets accounts\nProficient in MS Office, ERP and systematic documents processing\nGood command of both spoken and written Chinese and English\nWilling to travel overseas and mainland China in Post-Covid Period\nGood figure sense with proactive attitude and good communication skill\n\nYou will have an advantage if you are:\nHands-on experience in knowledge of financial / accounting / taxation regulation and policy in both HK & China\nDetails oriented, good communication and negotiation skills\nGood in problem solving, analytical and interpersonal skill\nSelf-motivated, committed and able to work under pressure, independently and support team works\nImmediate available\n\nWe offer attractive remuneration package with fringe benefits to right candidates\n\nLocation: walk 3 mins from Chai Wan MTR Station\n\nInterested parties please send email with current and expected salary and date of available by clicking \u201cApply Now\u201d\n\nPersonal Data collected will be used for recruitment purpose only.\n\nNo Recruitment Agency", "employment_types": ["Full Time", "Contract"], "selling_points": [], "locations": ["Lai Chi Kok"], "categories": ["Accounting", "Accountant", "Audit", "Taxation"], "post_time": "2022-01-17T10:12:11Z", "salary": {"currency": null, "max": null, "min": null, "period": "monthly", "term": null}, "salary_visible": false, "title_keywords": ["junior"], "responsibilities": ["taxation", "control", "schedules", "general ledger", "inventory", "full set of accounts", "monitor", "ad-hoc assignments", "p&l", "month-end closing", "costing analysis", "reports", "liaise with", "payroll"], "requirements": {"degrees": ["diploma holder"], "majors": [], "languages": ["english", "chinese"], "language_level": ["good command"], "hard_skills": ["problem solving", "processing", "erp", "ms office"], "soft_skills": ["self-motivated", "independently", "communication skill", "systematic", "interpersonal skill", "communication", "problem solving", "hands-on", "negotiation skills", "committed", "proactive", "work under pressure"], "languages_combined": [{"language": "english", "language_level": ["good command"]}, {"language": "chinese", "language_level": ["good command"]}]}, "experience_required": {"duration": ["3-5 years"], "field": ["accounting", "financial"]}}, {"job_id": "100003009051475", "location_code": "hk", "company": "BDO", "job_title": "Manager / Senior Associate - Transfer Pricing (Ref: TAX)", "description": "\u00a0Job responsibilities:\u00a0\n\nYou will be assigned to one of our audit teams of 3 \u2013 6 professionals stationing in Hong Kong.\nOur audit practice follows the standard APM issued by HKICPA.\nBook keeping accounting engagements are performed by separate accounting teams, not audit teams.\u00a0\n\nJob requirements:\u00a0\n\nGood command of written and oral English and Chinese\nProficiency in accounting double-entry system.\u00a0 Working experience in book keeping is not required.\nData processing and basic analysis in MS Excel\u00a0\n\nOur offers:\u00a0\n\nCompetitive package to attract talents starting from HK$17,000 \u2013 HK$24,000 per month\nOvertime work is not encouraged but, if incurred, will be compensated.\n5-day working week\nQP bonus of HK$3,000 per month\nAnnual leave: 12 days \u2013 14 days\nPaid exam leaves and study leaves for professional exams\nBirthday leave\nHardship allowance for working outside Hong Kong\nAnnual 3-day training camp in offsite hotel\u00a0\nFresh graduates are welcome\nShort-term contract staff will also be considered\n\nInterested parties can apply with detailed resume,\u00a0date of availability and expected salary\u00a0by email to Ms. Fanny Chau\n", "employment_types": ["Full Time", "Permanent"], "selling_points": ["Perform various TP and tax analysis", "2 to 6 years of relevant experience", "Excellent Career Prospect"], "locations": ["Sheung Wan"], "categories": ["Accounting", "Taxation", "Professional Services", "Business Consultancy"], "post_time": "2022-01-16T03:48:30Z", "salary": {"currency": null, "max": null, "min": null, "period": "monthly", "term": null}, "salary_visible": false, "title_keywords": ["senior associate", "manager"], "responsibilities": ["teams", "audit"], "requirements": {"degrees": [], "majors": [], "languages": ["english", "chinese"], "language_level": ["good command"], "hard_skills": ["analysis", "processing", "basic", "ms excel"], "soft_skills": ["overtime work", "oral"], "languages_combined": [{"language": "english", "language_level": ["good command"]}, {"language": "chinese", "language_level": ["good command"]}]}, "experience_required": {"duration": [], "field": []}}, {"job_id": "100003009051356", "location_code": "hk", "company": "EY", "job_title": "Tax - Payroll Operate Services - Staff /Senior Accountant - Hong Kong", "description": "Your Key Responsibilities\n\nAssist senior team members to perform various TP and tax analysis including TP planning/advisory, TP documentation, audit defense, advance pricing agreements and other related deliverables;\nAnalyze clients business activities, financial performance and intercompany transactions;\nParticipate in meetings or phone calls with senior business executives to identify functions, assets and risks;\nReview data sets, and perform financial analysis using a variety of economic, statistical and sector based models or techniques;\nEnsure timely delivery of work by managing project workflow, analyzing information, effective (internal and external) communication and managing and coaching more junior members of team;\nConduct industry and company research for clients in a range of sectors;\nClosely collaborate with TP or tax teams in HK or across the network;\nMonitoring OECD, global or local country TP or related tax developments.\n\nRequirements\n\n2 to 6 years of relevant experience in corporate tax or TP from other accounting firms and industry preferred\nCandidates with consulting, advisory, valuation, research, audit or related experience will also be strongly considered\nDegree holder, preferably major in economics, accounting, business, mathematics, finance or related disciplines\nExcellent command of both written and spoken English; proficiency in Mandarin is preferred\nExperience with common technology and TP database tools is important; experience with automation or efficiency solutions is an advantage.\n\nWhat We Look For\n\nApplicants who are dynamic, motivated and team-oriented.\nCritical thinkers with strong numerical and analytical skills\nProfessionals who are curious and fascinated by the inner working of business\nTeam player who can work effectively with others to achieve a common goal\nInterest and proficiency in new technologies\n\nRemark\n\nPosition offered will be commensurate with the experience of the right candidate", "employment_types": ["Full Time"], "selling_points": ["Global Payroll Services", "Payroll compliance and implementation methodology", "Minimum 2 years\u2019 experience in payroll/HR/C&B"], "locations": ["Quarry Bay"], "categories": ["Accounting", "Taxation", "Professional Services", "Business Consultancy", "Admin & HR", "Compensation & Benefits"], "post_time": "2022-01-15T10:49:30Z", "salary": {"currency": null, "max": null, "min": null, "period": "monthly", "term": null}, "salary_visible": false, "title_keywords": ["senior accountant", "staff"], "responsibilities": ["tax", "collaborate with", "data", "analysis", "review", "teams", "audit", "transactions", "monitoring", "financial analysis", "communication", "documentation", "phone calls", "business activities", "planning"], "requirements": {"degrees": ["degree holder"], "majors": ["mathematics", "finance", "economics", "related disciplines", "business", "accounting"], "languages": ["english", "mandarin"], "language_level": ["excellent", "proficiency"], "hard_skills": ["goal", "dynamic", "analytical skills"], "soft_skills": ["work effectively", "analytical skills", "motivated", "dynamic", "team player"], "languages_combined": [{"language": "english", "language_level": ["excellent"]}, {"language": "mandarin", "language_level": ["proficiency"]}]}, "experience_required": {"duration": ["2 to 6 years"], "field": ["research", "consulting", "related", "audit", "relevant experience", "database", "accounting"]}}, {"job_id": "100003009051481", "location_code": "hk", "company": "AXA International Limited", "job_title": "Accountant / Senior Accountant", "description": "Cheng & Cheng Limited is a Hong Kong based professional accounting firm with more than 25 years\u2019 experience in the financial sector. With the support of more than 250 professional staff, we aim to provide the best service to our clients.\u00a0\n\nWe provide a wide range of financial services, including, auditing, internal control and risk management, accounting, liquidation, taxation, pre-IPO and IPO services, etc.\n\nOur tax team provide comprehensive support from compliance to advisory services (e.g. preparing Profits Tax Returns and Profits Tax Computations, reply letters to the IRD, transfer pricing advisory and documentations, applications for certificates of resident status, Hong Kong and PRC tax advisory and tax planning for restructuring, tax investigation, etc.) to clients ranging from small and medium enterprises to listed companies and multinational companies in a professional and efficient manner.\u00a0\n\nThe successful candidates will join our tax team to help our clients to improve efficiencies, mitigate risk and improve opportunities within their tax functions by providing tax-related compliance assistance to them and their associated companies, analyzing tax opportunities and benefits that can be attained by them and assisting them in identifying and managing risks related to potential planning.\u00a0\n\nWe offer fabulous opportunities to develop your career through a broad range of engagements, mentoring as well as internal and external trainings.\u00a0\n\nWe invite high caliber individuals to join our team.\n\nTax Assistant Accountant (5-day work)\n\nWe invite high caliber fresh graduates t to join our team.\u00a0\n\nResponsibilities: -\n\n\u00a0Handle Hong Kong Profits Tax and Salaries Tax compliance and advisory engagements\n\nDraft reply letters to IRD queries\n\nPrepare applications for certificates of resident status\n\nParticipate in field audits and investigations, prepare analyses and other special jobs\n\nPerform ad hoc tasks\n\n\u00a0Requirements:-\n\nDegree or above\n\nStudent member/ member of HKICPA, ACCA or equivalent\n\nBasic PRC Tax knowledge is advantageous but not essential\n\nGood command of both spoken and written English and Chinese, Mandarin is preferred\n\nStrong self-motivation and ability to work under pressure\n\nGood communication, interpersonal and analytical skills\n\nApplicants with more than 2 years working experience and qualifications will be considered as Senior Tax Accountant\n\nWe offer 5-day work week with medical scheme, personal leave,study and exam leave. Interested parties please email your application letter and full resume stating\u00a0present & expected salary,availability and quoting job reference number by clicking \"Apply Now\".\u00a0For more information of the company,please visit www.chengcpa.com.hk.\n\n\nPersonal data collected will be used for recruitment purpose only.", "employment_types": ["Full Time"], "selling_points": [], "locations": ["Wan Chai"], "categories": ["Accounting", "Accountant", "Taxation"], "post_time": "2022-01-16T03:54:01Z", "salary": {"currency": null, "max": null, "min": null, "period": "monthly", "term": null}, "salary_visible": false, "title_keywords": ["accountant", "senior accountant"], "responsibilities": [], "requirements": {"degrees": [], "majors": [], "languages": [], "language_level": [], "hard_skills": [], "soft_skills": [], "languages_combined": []}, "experience_required": {"duration": [], "field": []}}, {"job_id": "100003009051338", "location_code": "hk", "company": "EY", "job_title": "Tax - Customer Tax Operations Reporting - Manager - Hong Kong", "description": "Responsibilities:\n\nReview full set of account, costing, taxation and ad hoc assignments of each office\nSupervise and monitor the daily accounting and finance operations of different companies\nPrepare monthly reports, financial statements, cash flow forecast and\u00a0management analysis reports\nConsolidate financial reports, review and prepare of budgeting and management reports to align with business objectives\nEnsure the accounting records and documentation in compliance with the local statutory requirement and company accounting policy\nDeal with both internal and external parties including auditor and tax agent etc.\nSupport year-end audit and taxation\nHandle ad hoc assignment\n\nRequirements:\n\nDegree holder major in accountancy\nStudent member or finalist of HKICPA or ACCA\nMinimum 5 years accounting experience with 3 years in manufacturing industry\nKnowledge in PRC taxation\nProficiency in Microsoft office and applications; well versed in Excel\nWilling to visit China and review financial operation when needed\nGood communication skills with foreign investment parties, able to work and interface well with personnel at various levels\nGood command of written English and Chinese\nFluent in spoken English, Mandarin and Cantonese\nStrong manufacturing analytical, presentation and report writing skills\nImmediately available or short notice will be an advantage", "employment_types": ["Full Time", "Permanent"], "selling_points": ["FATCA/CRS/AEOI", "Conducting and documenting tax research", "Minimum of 4 years Hong Kong tax experience"], "locations": ["Not Specified"], "categories": ["Accounting", "Taxation", "Others", "Professional Services", "Legal & Compliance"], "post_time": "2022-01-15T09:41:14Z", "salary": {"currency": null, "max": null, "min": null, "period": "monthly", "term": null}, "salary_visible": false, "title_keywords": ["operations", "manager"], "responsibilities": ["monthly reports", "analysis reports", "budgeting", "internal and external parties", "audit", "financial statements", "finance operations", "ad hoc assignment", "compliance", "monitor", "forecast", "management", "review", "cash flow", "documentation", "tax", "taxation", "financial reports", "year-end", "management reports", "ad hoc assignments", "daily accounting"], "requirements": {"degrees": ["degree holder"], "majors": ["accountancy"], "languages": ["cantonese", "english", "chinese", "mandarin"], "language_level": ["good command", "fluent"], "hard_skills": ["excel", "acca", "microsoft office", "writing skills", "hkicpa"], "soft_skills": ["communication skills", "presentation", "writing skills"], "languages_combined": [{"language": "cantonese", "language_level": ["fluent"]}, {"language": "english", "language_level": ["good command", "fluent"]}, {"language": "chinese", "language_level": ["good command"]}, {"language": "mandarin", "language_level": ["fluent"]}]}, "experience_required": {"duration": ["3 years", "minimum 5 years"], "field": ["accounting experience", "manufacturing industry"]}}, {"job_id": "100003009043940", "location_code": "hk", "company": "Hongkong Managers and Secretaries Limited", "job_title": "Tax Specialist (PRC Tax) / Senior Tax Consultant", "description": "Company Profile\u00a0\n\nOur client is an award-winning market leader with offices operating across the world. To cope with the expansion of the business, they are seeking for a brand new high-caliber individual to join their expanding team. The person will be expected to take lead in the APAC Tax function of the company's expanding Business Units.\u00a0\n\nExciting new role for you\u00a0\n\nDirectly report to Global Tax Director\nAct as team lead to manage the Group\u2019s tax function of the company and to groom subordinates\nAct as subject-matter-expert on taxation function and provide tax advisory to enhance overall efficiency and tackle potential matters of the business\u2019 manufacturing and R&D, supply chain, retail, to engineering activities\nInvolve in local and regional tax-related projects/transactions\nKey focal point between HK, HQ, APAC teams, and external tax advisors\nIn charge of local and cross-border tax compliance matters ranging from preparing & submitting tax returns, transfer pricing docs, to tax benefit applications, treaty-relief applications, other related tax activities\nAd-hoc tax projects and tax advisory for various business partners across APAC\n\nRequirements\u00a0\n\nBachelor\u2019s degree or above in Accounting or related discipline\n5+ years of solid experience in taxation/tax advisory or related areas with at least 1 years in commercial sector\nExperience with PRC taxation, transfer pricing and customs matters along with international and cross-border supply chain/tax jurisdiction matters preferred\nStrong interpersonal and stakeholder management; ability to deal with stakeholders across different levels across APAC-level\nStrong project management skills with the ability to juggle multiple projects\nSelf-motivated, work independently & with team, analytical, and communicate effectively in English\n\nRewards\u00a0\n\nYou will be working at a high performing energetic team with great career progression. Attractive remuneration and package. Opportunity to join a market leading group with a promising career path and potential internal transfer opportunities.\u00a0\n\n\nInterested parties please click apply or send your application via email to\u00a0jolly_wong@persolkelly.\u00a0 com\u00a0For any enquiries, please do not hesitate to contact me at\u00a0(852) 2281 0021.\n\nWe also have various job vacancies from our well-established clients in all kinds of fields, please feel free to contact us. We are always willing to give you support on your career development\n\nAll information received will be treated in strict confidence and used for recruitment purpose only. Only shortlisted candidate will be notified.", "employment_types": ["Full Time", "Permanent"], "selling_points": ["PRC Tax advisory services", "PRC corporate income tax and value-added tax", "5 days works, friendly working environment"], "locations": ["Causeway Bay"], "categories": ["Accounting", "Taxation"], "post_time": "2022-01-13T02:32:21Z", "salary": {"currency": "HKD", "max": 34999, "min": 30000, "period": "monthly", "term": null}, "salary_visible": true, "title_keywords": ["specialist", "consultant"], "responsibilities": ["tax", "taxation", "ad-hoc", "management", "compliance", "teams", "transactions", "project management", "multiple projects", "report"], "requirements": {"degrees": ["degree or above", "bachelor"], "majors": ["accounting"], "languages": ["english"], "language_level": [], "hard_skills": ["r&d", "project management", "focal"], "soft_skills": ["self-motivated", "work independently", "project management skills", "energetic", "interpersonal"], "languages_combined": [{"language": "english", "language_level": []}]}, "experience_required": {"duration": ["at least 1 years", "5+ years"], "field": ["related", "commercial", "supply chain"]}}, {"job_id": "100003009047044", "location_code": "hk", "company": "Kingsway Personnel Ltd", "job_title": "Japanese Speaking Senior Accountant/Accounting Manager ~40K", "description": "Our client is a global audit firm and looking for a new member to join the expanding team.\n\nResponsibilities:\n\nFor Tax Specialist (PRC Tax)\nProvide PRC tax advisory services (mainly PRC corporate income tax and value-added tax) to local and international clients\nPRC tax provision review\nCollaborate with our client's overseas member firms to work on various cross-border tax exercises, e.g. holding structures, group restructuring, M&A, other PRC tax planning projects\nConduct research on PRC tax issues\nSupport firm-wide and team-specific initiatives as well as other ad-hoc projects\nAssist in preparing\u00a0regional and local transfer pricing documentation and advisory reports\nRequirements:\n\nBachelor\u2019s degree in accountancy, finance, economics or related field\nMinimum 3years\u00a0of relevant experience in the PRC tax sector gained in a professional consulting environment\nPossess strong interpersonal, organizational and communications skills and computer literate\nProfessional qualification with\u00a0CCTAA or CICPA will be an advantage\nGood command of spoken and written English and Chinese (Proficiency in Mandarin would be an advantage)\nCandidates with less experience will be considered as Junior Tax Consultant\nImmediate availability is preferred\n\nFor Senior/Junior Tax Consultant (Hong Kong Tax, Transfer Pricing)\n\nPrepare regional and local transfer pricing documentation and advisory reports\nProvide Hong Kong tax advisory services to local and international clients from mainly a transfer pricing perspective\nCollaborate with our client's overseas member firms to work on various cross-border tax exercises, e.g. holding structures, group restructuring, M&A, other PRC tax planning projects\nWork effectively as a team member, support managerial personnel and lead teammates to achieve goals\nSupport firm-wide and team-specific initiatives as well as other ad-hoc projects\nImmediate availability is preferred\n\n\n\n\nInterested parties please submit your application to our mailbox by clicking Apply Now.\n\nPersonal data provided in the employment applications will be treated in strict confidence and used only for recruitment purpose.", "employment_types": ["Full Time", "Permanent"], "selling_points": ["Min. 5yrs full set acct, tax, internal control", "Good at Japanese, English and Mandarin", "~40K, 13mths and bonus, Flexible working"], "locations": ["Not Specified"], "categories": ["Accounting", "Accountant", "Finance / Accounting Manager", "Taxation"], "post_time": "2022-01-15T19:11:32Z", "salary": {"currency": null, "max": null, "min": null, "period": "monthly", "term": null}, "salary_visible": false, "title_keywords": ["accounting manager", "senior accountant"], "responsibilities": ["tax", "collaborate with", "review", "reports", "documentation", "ad-hoc projects", "conduct research", "planning"], "requirements": {"degrees": ["degree", "bachelor"], "majors": ["finance", "economics", "accountancy"], "languages": ["english", "chinese", "mandarin"], "language_level": ["advantage", "proficiency", "good command"], "hard_skills": ["documentation"], "soft_skills": ["work effectively", "organizational", "team member", "interpersonal"], "languages_combined": [{"language": "english", "language_level": ["proficiency", "advantage", "good command"]}, {"language": "chinese", "language_level": ["proficiency", "advantage", "good command"]}, {"language": "mandarin", "language_level": ["proficiency", "advantage", "good command"]}]}, "experience_required": {"duration": [], "field": ["relevant experience", "consulting"]}}, {"job_id": "100003009049284", "location_code": "hk", "company": "Baker Tilly Hong Kong", "job_title": "Senior - Tax Services (Elite program)", "description": "Employment Ref.: MA09563\nNature of Business: Well-known Japanese trading company\nWorking Days: 5 Days\nWorking Location: KLN Area\n\nBenefits:\n- Double pay\n- Discretionary Bonus\n- Medical insurance\n- Flexible working hours\n\nResponsibilities:\n- Review, formulate and implement financial and accounting policies, procedures and guidelines\n- Identify areas for continuous improvement to avoid risk and enhance internal control of operational activities and governance\n- Handle tax issue, mainly for in-charging of BEPS, and communicate with related parties for planning and resolving\n- Handle aggregation/ analysis and information sharing of whole entity and HK regional consolidated financial status\n- Conduct regular review of end-to-end processes\n\nRequirements:\n- Degree in Accounting or related discipline\n- Min. 5yrs exp. full set accounting, tax and internal control\n- Good command of Japanese (N3 or above), English and Mandarin\u00a0\n\nInterested in the above vacancy?\u00a0 Send your resume to us NOW!\nOnly short-listed candidates will be notified. Personal data collected will be used for recruitment purpose only", "employment_types": ["Full Time", "Permanent"], "selling_points": ["A qualified member of HKICPA", "3 years Hong Kong tax experience", "Fluency in spoken English, Cantonese and Putonghua"], "locations": ["Quarry Bay"], "categories": ["Accounting", "Consulting", "Taxation", "Professional Services", "Business Consultancy"], "post_time": "2022-01-14T08:22:41Z", "salary": {"currency": null, "max": null, "min": null, "period": "monthly", "term": null}, "salary_visible": false, "title_keywords": [], "responsibilities": [], "requirements": {"degrees": [], "majors": [], "languages": [], "language_level": [], "hard_skills": [], "soft_skills": [], "languages_combined": []}, "experience_required": {"duration": [], "field": []}}, {"job_id": "100003009046753", "location_code": "hk", "company": "BDO", "job_title": "Associate - Transfer Pricing (Ref: TAX)", "description": "Responsibilities\n\n\nParticipate in audit engagements for a variety of clients, including SME, companies listed on the Stock Exchange of Hong Kong, licensed corporations registered under Securities and Futures Commission (SFC), and investment funds\nPerform audit procedures and be responsible to manager / senior in charge for ensuring the work assigned is executed and completed as planned and in accordance to the firm\u2019s policies and procedures\n\nRequirements\n\n\nTertiary education (major in accounting or business related disciplines is preferred but not essential)\nFresh graduates will also be considered\nGood command of both written and spoken in English and Chinese, knowledge in Putonghua preferred\nGood interpersonal skill and able to work under pressure and tight deadlines\nWilling to travel on business needs\nCandidate with more experience will be considered in senior position\n\nWe are registered as Authorized Employer of the Hong Kong Institute of Certified Public Accountants (HKICPA). We offer fringe benefits to the right candidates, including medical scheme, hospitalization & surgical insurance, 5-day work week, study and examination leave.\n\nInterested parties please send your full resume with current and expected salary by post to our Human Resources Department, HLB Hodgson Impey Cheng Limited, 31/F Gloucester Tower, The Landmark, 11 Pedder Street, Central, Hong Kong or click Apply Now.\n", "employment_types": ["Full Time", "Permanent"], "selling_points": ["Participate in TP projects,  conduct research", "Excellent Career Prospects", "Fresh Graduates are welcomed"], "locations": ["Sheung Wan"], "categories": ["Accounting", "Taxation", "Others"], "post_time": "2022-01-14T00:45:22Z", "salary": {"currency": null, "max": null, "min": null, "period": "monthly", "term": null}, "salary_visible": false, "title_keywords": ["associate"], "responsibilities": ["sme", "policies", "procedures", "audit"], "requirements": {"degrees": [], "majors": [], "languages": ["putonghua", "english", "chinese"], "language_level": ["good command"], "hard_skills": ["hong kong institute of certified public accountants", "scheme", "hkicpa"], "soft_skills": ["work under pressure", "interpersonal skill"], "languages_combined": [{"language": "putonghua", "language_level": ["good command"]}, {"language": "english", "language_level": ["good command"]}, {"language": "chinese", "language_level": ["good command"]}]}, "experience_required": {"duration": [], "field": []}}, {"job_id": "100003009051080", "location_code": "hk", "company": "Wharf China Development Limited", "job_title": "Accounts Assistant", "description": "Your Key Responsibilities\n\nAssist senior team members to perform various TP and tax analysis including TP planning/advisory, TP documentation, audit defense, advance pricing agreements and other related deliverables;\nAnalyze clients business activities, financial performance and intercompany transactions;\nReview data sets, and perform financial analysis using a variety of economic, statistical and sector based models or techniques;\nConduct industry and company research for clients in a range of sectors;\nClosely collaborate with TP or tax teams in HK or across the network;\nKeep abreast of OECD, global or local country TP or related tax developments.\n\nRequirements\n\n\n1 year of relevant experience in corporate tax or TP from other accounting firms and industry preferred\nCandidates with consulting, advisory, valuation, research, audit or related experience will also be strongly considered\nDegree holder, preferably major in economics, accounting, business, mathematics, finance or related disciplines\nGood command of both written and spoken English; proficiency in Mandarin is preferred\nFresh graduate will also be considered\n\nWhat We Look For\n\n\nApplicants who are dynamic, motivated and team-oriented.\nPossess strong interpersonal, organizational and communications skills and computer literate.\nInterest and proficiency in new technologies", "employment_types": ["Full Time", "Permanent"], "selling_points": [], "locations": ["Tsim Sha Tsui"], "categories": ["Accounting", "Accounting Clerk / Supervisor", "Taxation", "Others"], "post_time": "2022-01-15T01:55:26Z", "salary": {"currency": null, "max": null, "min": null, "period": null, "term": null}, "salary_visible": false, "title_keywords": ["accounts assistant"], "responsibilities": ["tax", "collaborate with", "data", "analysis", "review", "teams", "audit", "transactions", "financial analysis", "documentation", "business activities", "planning"], "requirements": {"degrees": ["fresh graduate", "degree holder"], "majors": ["mathematics", "finance", "economics", "related disciplines", "business", "accounting"], "languages": ["english", "mandarin"], "language_level": ["proficiency", "good command"], "hard_skills": ["dynamic"], "soft_skills": ["motivated", "organizational", "dynamic", "interpersonal"], "languages_combined": [{"language": "english", "language_level": ["good command"]}, {"language": "mandarin", "language_level": ["proficiency"]}]}, "experience_required": {"duration": ["1 year"], "field": ["research", "consulting", "related", "audit", "relevant experience", "accounting"]}}, {"job_id": "100003009040489", "location_code": "hk", "company": "Link Asset Management Limited", "job_title": "Tax Manager - Finance (Ref. No.: L22/01-0285)", "description": "Responsibilities:\n\nResponsible for daily accounting operations including expenses, accounts payable, general ledger\nHandle staff expenses reimbursement\nAssist in month-end closing and year-end audit\nAssist in preparing HK tax computation for related entities\nUpdate accounting reports for management\u2019s review\nAssist in other accountings duties as assigned\n\nRequirements:\n\n\nDiploma Holder or LCCI Higher with 2 - 4 years\u2019 relevant accounting experience, preferably gained in property development sector\nBasic China accounting knowledge preferred and experience in group consolidation is a definite advantage\nProficient in MS Office applications, especially in Excel and experience in using Flex accounting system is an advantage\nResponsible, proactive, detail-oriented and able to work independently and efficiently with minimum supervision\nA team player with good communication skills\nProficient in spoken and written English and Chinese (Cantonese and Putonghua\nImmediate available is an advantage\n\nWe work 5 days per week.\n\nInterested parties, please click \"APPLY NOW\" and attach with your application letter and full resume.\u00a0\n\nFor further information of the Wharf Group, please visit our website:\u00a0www.wharfholdings.com", "employment_types": ["Full Time", "Permanent"], "selling_points": ["Perform analysis on tax data", "Bachelor\u2019s degree in Accountancy, Finance", "At least 5 years of relevant post-qualification"], "locations": ["Not Specified"], "categories": ["Accounting", "Accountant", "Taxation", "Others"], "post_time": "2022-01-12T02:44:35Z", "salary": {"currency": null, "max": null, "min": null, "period": "monthly", "term": null}, "salary_visible": false, "title_keywords": ["manager"], "responsibilities": ["year-end", "management", "tax computation", "general ledger", "expenses", "review", "daily accounting operations", "audit", "month-end closing", "reports", "accounts payable"], "requirements": {"degrees": ["diploma holder"], "majors": ["accounting"], "languages": ["cantonese", "putonghua", "english", "chinese"], "language_level": ["proficient"], "hard_skills": ["excel", "flex accounting", "basic", "ms office"], "soft_skills": ["communication skills", "work independently", "responsible", "detail-oriented", "team player", "proactive"], "languages_combined": [{"language": "cantonese", "language_level": ["proficient"]}, {"language": "putonghua", "language_level": ["proficient"]}, {"language": "english", "language_level": ["proficient"]}, {"language": "chinese", "language_level": ["proficient"]}]}, "experience_required": {"duration": ["2 - 4 years"], "field": ["development", "accounting experience", "accounting", "consolidation"]}}, {"job_id": "100003009052287", "location_code": "hk", "company": "PwC", "job_title": "Manager / Senior Associate - Tax Technology - PwC Tax - Hong Kong", "description": "About Tax\n\nTax and regulatory issues are on top of the mind for many companies operating around the world today. As a tax professional, you will help organisations and individuals maximise their tax efficiency and manage their tax risks. You achieve this through the advice you give your clients on how to conduct proper tax planning, and helping your clients to fully meet their tax compliance obligations.\n\nTaxation in a fast-paced business environment is exciting and intellectually stimulating. In order for you to face up to the challenges, you will need to constantly develop your tax knowledge and research skills. As you progress, you will likely become specialised in certain tax speciality area and particular industries.\n\nAbout Tax Technology Team\n\nThe Tax Technology team is responsible for all technology based business solutions for the Tax division in the China and Hong Kong region. Moreover, the team serves as a contact point and liaison for other territories within as well as outside the Asia-Pacific region in relation to tax technology. We work closely with both the tax professionals and IT specialists within the Firm to support the systems life cycle of concurrent tax technology projects so as to deliver best-in-class technology-based business solutions.\n\nJob description and responsibilities:\n\nUnderstand business and client needs and derive business requirements, functional design, and process design\nPerform systems and/or proposal comparisons, analysis, and evaluations with engagement team\nAssist in analysing business processes, identifying potential automation opportunities and creating Process Description Document, and Solution Design Document\nAssist in planning and tracking projects tasks and timeline\nPerform testing and handle related issues during development and implementation of software projects\nCollect feedback and monitor on software projects after launch\n\nRequirements:\n\nGreat written and verbal communications skills in both English and Chinese\nAbility to work well and communicate effectively with other professionals\nProficiency in ASP, .NET ,C# , JAVA or any kind of programming language\nFunctional knowledge of SQL and object-oriented programmingcoding methodologies\nDemonstrate understanding of different software development life-cycle methodologies\nStrong organizational and analytical skills to research, compile and clearly present information and data\nMust be proficient in Word, Excel and PowerPoint\nAbility to function well in a fast-paced, dynamic environment with competing priorities and tight deadlines\nHands-on experience with system design, implementation and quality assurance is a plus\nBSc / BEng in Computer Science, Math, Physics or Engineering is preferred\nJunior candidates will be considered as Associate", "employment_types": ["Full Time", "Permanent"], "selling_points": ["Technology Based Business Solutions for Tax", "Fast-paced and Intellectually Stimulating", "ASP NET C# JAVA"], "locations": ["Central"], "categories": ["Accounting", "Taxation", "Information Technology (IT)", "IT Project Management / Team Lead", "Software Development"], "post_time": "2022-01-17T02:39:03Z", "salary": {"currency": null, "max": null, "min": null, "period": "monthly", "term": null}, "salary_visible": false, "title_keywords": ["senior associate", "manager"], "responsibilities": ["software", "analysis", "systems", "monitor", "implementation", "design", "testing", "planning", "tracking"], "requirements": {"degrees": ["bsc"], "majors": ["math", "engineering", "computer science", "physics"], "languages": ["english", "chinese"], "language_level": [], "hard_skills": ["excel", "java", "plus", "word", "powerpoint", "analytical skills", "sql", "dynamic", "system design", "programming", "math", "c#"], "soft_skills": ["organizational", "dynamic environment", "hands-on", "analytical skills"], "languages_combined": [{"language": "english", "language_level": []}, {"language": "chinese", "language_level": []}]}, "experience_required": {"duration": [], "field": ["system design", "quality assurance"]}}, {"job_id": "100003009052950", "location_code": "hk", "company": "Fung, Yu & Co. CPA Limited", "job_title": "Internship - Audit Department/Accounting Services Department", "description": "If you want to\n\ngain valuable internship experience on audit work\nbuild up diversified concepts of doing audit for different business nature companies\nget the skill sets of presentation, interpersonal, communication to enrich your competitiveness in the future career\n\nOur internship program contains\n\nconcepts and practices of audit\nperforming audit work\naudit case study\npresentation\n\nIf you are\n\nwilling to learn\nenergetic and passionate\nHKID Holders\n\nWhat We Offer\n\nwork reference letter\non-job training\n\nWelcome to join us in this winter!\n\nPlease submit your application by clicking \u201cApply Now\u201d button.\n\nWelcome to visit our company website http://www.fungyucpa.com/\u00a0for more information.\n\nPersonal data collected will be used for recruitment purposes only.", "employment_types": ["Internship"], "selling_points": ["University degree holder majoring in accountancy", "Audit/Accounting", "Intern"], "locations": ["Central & Western Area"], "categories": ["Accounting", "Audit", "Consulting", "Taxation"], "post_time": "2022-01-17T04:39:36Z", "salary": {"currency": null, "max": null, "min": null, "period": "monthly", "term": null}, "salary_visible": false, "title_keywords": ["accounting", "internship"], "responsibilities": ["communication", "audit"], "requirements": {"degrees": [], "majors": [], "languages": [], "language_level": [], "hard_skills": [], "soft_skills": ["passionate", "presentation", "willing to learn", "communication", "energetic", "interpersonal"], "languages_combined": []}, "experience_required": {"duration": [], "field": ["audit"]}}, {"job_id": "100003009052314", "location_code": "hk", "company": "PwC", "job_title": "Manager - China Corporate Tax - PwC Tax - Hong Kong", "description": "Job Description & Responsibilities\n\nAssist clients in their China tax compliance obligations, including preparation of tax computations and returns, and handling correspondence with the Mainland Tax Bureau;\nProvide China tax advisory and consulting services to clients;\nDevelop and maintain client relationships;\nManage and develop a team of professional staffs; and\nPerform initial client needs analysis, determine the key areas of service that we want to pursue and develop value propositions and pitches for the client\nRequirements\n\nA recognised degree holder preferably in accounting or equivalent;\nQualified member of a professional accounting body;\nMinimum five to eight years of China tax experience;\nConfident with a strong business sense;\nAbility and aptitude in managing multiple stakeholders both internally and externally;\nSolid project management experience with strong analytical and organizational skills\nExcellent interpersonal and communication skills;\nProficient in both written and spoken English; and\nFluency in Putonghua.\nIn addition, candidates should illustrate the following personal attributes:\n\nDemonstrates courage and integrity\nAcquires and applies commercial and technical expertise by staying up to date in industry and with market trends\n\u00a0Manages projects and economics efficiently; planning and performing work in accordance with client requirements and professional standards\u00a0\nOpen minded, agile with change and practical\nCommitted to self develop and coaching of others for growth\nCommunicates with impact and empathy\nActively shares ideas and knowledge and is innovate\nLead and contribute to team success\nIs passionate about client service", "employment_types": ["Full Time", "Permanent"], "selling_points": ["Manage and develop a team of professional staffs", "Develop and maintain client relationships", "Qualified member of a professional accounting body"], "locations": ["Central"], "categories": ["Accounting", "Accountant", "Taxation"], "post_time": "2022-01-17T02:43:57Z", "salary": {"currency": null, "max": null, "min": null, "period": "monthly", "term": null}, "salary_visible": false, "title_keywords": ["manager"], "responsibilities": ["tax", "consulting", "analysis", "compliance", "develop", "maintain"], "requirements": {"degrees": ["degree holder"], "majors": ["accounting"], "languages": ["putonghua", "english"], "language_level": ["fluency", "proficient"], "hard_skills": ["project management", "agile"], "soft_skills": ["confident", "organizational skills", "communication skills", "agile", "business sense", "integrity", "project management", "committed", "open minded", "empathy", "interpersonal", "passionate about"], "languages_combined": [{"language": "putonghua", "language_level": ["fluency"]}, {"language": "english", "language_level": ["proficient"]}]}, "experience_required": {"duration": ["minimum five to eight years"], "field": ["project management", "analytical"]}}, {"job_id": "100003009051835", "location_code": "hk", "company": "PwC", "job_title": "Manager / Senior Manager - Private Client Services - PwC Tax - Hong Kong", "description": "Job Description & Summary\n\nA career in our Tax Wealth Advisory practice, within Tax services, will provide you with the opportunity to help our clients meet and manage their tax obligations across unique but ever changing tax specialties. You\u2019ll advise clients on their local and overseas tax affairs, while acting as a strategic consultant related to business analysis, managing indirect taxes, dispute resolution, and global enterprise tax solutions.\n\nOur team offers clients a scalable solution to address the tax compliance needs of corporations, partnerships, and other business entities by managing compliance services to maximise a tax department\u2019s strengths and minimise the impact on our clients resources. You\u2019ll support clients by providing outsourcing services which includes the preparation and review of income and franchise returns along with responding to inquiries from federal, state and local taxing authorities for our clients.\n\nAssist in preparation of documentation in relation to and support superiors to handle family wealth planning projects\n\nAssist in the set-up of asset holding structure for family wealth planning purposes\n\nAssist in the formation of Hong Kong or offshore companies and the ongoing maintenance including the filing of the necessary returns with the registration authority\n\nAssist in the application and ongoing maintenance of immigration matters\n\nRequirements\n\nA degree holder preferably in Accounting/Law/Corporate Governance but not essential.\n\nStudent member of ICSA / HKICS/HKICPA will be an advantage.\n\nFive years of company secretarial or personal tax experience preferable\n\nProficient in English and Chinese. Putonghua is essential.\n\nChinese writing and reading skill is essential.\n\nA team player with strong initiative and able to work under pressure.\n\n\n\n\u6709\u610f\u7533\u8acb\u8005\u8acb \u6309 APPLY NOW\u7533\u8acb\n\n", "employment_types": ["Full Time"], "selling_points": [], "locations": ["Not Specified"], "categories": ["Accounting", "Finance / Accounting Manager", "Taxation", "Management", "General Management"], "post_time": "2022-01-17T01:19:31Z", "salary": {"currency": null, "max": null, "min": null, "period": "monthly", "term": null}, "salary_visible": false, "title_keywords": ["senior manager", "manager"], "responsibilities": ["tax", "documentation", "maintenance", "compliance", "review", "resolution", "support clients", "business analysis", "planning"], "requirements": {"degrees": ["degree holder"], "majors": ["accounting", "law"], "languages": ["putonghua", "english", "chinese"], "language_level": ["proficient"], "hard_skills": ["hkicpa"], "soft_skills": ["team player", "initiative", "work under pressure"], "languages_combined": [{"language": "putonghua", "language_level": []}, {"language": "english", "language_level": ["proficient"]}, {"language": "chinese", "language_level": ["proficient"]}]}, "experience_required": {"duration": ["five years"], "field": ["secretarial"]}}, {"job_id": "100003009052349", "location_code": "hk", "company": "PwC", "job_title": "Manager, Integrated Tax and Business Consulting, Tax Services, Hong Kong", "description": "Job Description\n\nAbout PwC \u2013 Globally PwC firms help organizations and individuals create the value they\u2019re looking for. We're a network of firms in 158 countries with close to 169,000 people who are committed to delivering quality in assurance, tax and advisory services.\n\nPwC - Mainland China, Hong Kong and Macau\n\nPwC in Mainland China, Hong Kong and Macau work together on a collaborative basis, subject to local applicable laws. Collectively, we have around 500 partners and a strength of around 12,100 people.\n\nProviding organizations with the advice they need, wherever they may be located. Our highly qualified, experienced professionals listen to different points of view to help organizations solve their business issues and identify and maximize the opportunities they seek. Our industry specialization allows us to help co-create solutions with our clients for their sector of interest.\n\nWe are located in these cities: Beijing, Shanghai, Tianjin, Chongqing, Dalian, Xi'an, Qingdao, Nanjing, Suzhou, Hangzhou, Ningbo, Xiamen, Guangzhou, Shenzhen, Hong Kong and Macau.\n\nJob description\u00a0\n\nProvide HK tax compliance and consulting services to clients in one of the industries:- retail, financial services, trading, technology, manufacturing, transportation or logistics;\nLead cross-teams and regional tax advisory and consulting projects, such as company public listing, merger and acquisition, group restructuring, transfer pricing study, operations review and tax dispute resolutions; and\nOpportunities to develop specialty in a certain industry with international tax exposure\n\nRequirements\u00a0\n\nUniversity graduate or above;\nQualified member of a professional accounting body and/or tax body;\nMinimum 6 years of relevant experience in HK tax compliance and consultancy;\nGood command of written and spoken English and Chinese (Cantonese and Mandarin); and\nWilling to take on challenges.\n\n\n", "employment_types": ["Full Time", "Permanent"], "selling_points": ["Corporate Tax Advisory", "Supportive Team Environment", "Excellent Career Track"], "locations": ["Central"], "categories": ["Accounting", "Taxation"], "post_time": "2022-01-17T02:49:44Z", "salary": {"currency": null, "max": null, "min": null, "period": "monthly", "term": null}, "salary_visible": false, "title_keywords": ["manager"], "responsibilities": ["tax", "consulting", "operations", "compliance", "quality", "teams", "review", "develop", "logistics", "listing"], "requirements": {"degrees": ["university graduate or above"], "majors": [], "languages": ["cantonese", "english", "chinese", "mandarin"], "language_level": ["good command"], "hard_skills": [], "soft_skills": [], "languages_combined": [{"language": "cantonese", "language_level": ["good command"]}, {"language": "english", "language_level": ["good command"]}, {"language": "chinese", "language_level": ["good command"]}, {"language": "mandarin", "language_level": ["good command"]}]}, "experience_required": {"duration": ["minimum 6 years"], "field": ["compliance", "relevant experience"]}}, {"job_id": "100003009052286", "location_code": "hk", "company": "PwC", "job_title": "Associate / Senior Associate - Financial Services Tax -  PwC Tax", "description": "About Financial Services Tax Practice\n\nOur practice being the largest amongst professional accounting firms in Hong Kong, serves Hong Kong, mainland and international clients in the banking and capital markets, insurance and asset management industries.\u00a0 We provide tax compliance and consulting services to our clients.\u00a0\n\nJob Description\n\nProvide HK tax compliance and consulting services to clients in one of the industries:- retail, financial services, trading, technology, manufacturing, transportation or logistics;\nWork with a team of professionals on cross-teams and regional tax advisory and consulting projects, such as public listing, merger and acquisition, group restructuring, transfer pricing study, operations review and tax dispute resolutions; and\nStructured training will be provided equipping you to become a professional advisor\nRequirements\n\n\u00a0University graduate or above;\nQualified member of a professional accounting body is preferred;\nMinimum three years of relevant tax experience;\nGood command of both spoken and written English and Chinese; Mandarin is a plus", "employment_types": ["Full Time", "Part Time"], "selling_points": ["Services HK, mainland and international clients", "Largest practice in the Market", "Excellent Learning and Development Opportunity"], "locations": ["Central"], "categories": ["Accounting", "Taxation", "Banking / Finance", "Others"], "post_time": "2022-01-17T02:39:03Z", "salary": {"currency": null, "max": null, "min": null, "period": "monthly", "term": null}, "salary_visible": false, "title_keywords": ["senior associate", "associate"], "responsibilities": [], "requirements": {"degrees": [], "majors": [], "languages": [], "language_level": [], "hard_skills": [], "soft_skills": [], "languages_combined": []}, "experience_required": {"duration": [], "field": []}}, {"job_id": "100003009052161", "location_code": "hk", "company": "BDO", "job_title": "Associate - Tax (Graduate Recruitment - 2021 Intake)", "description": "Overview\n\nAs an associate of tax, you will provide tax services for a variety of clients. You have to ensure that all of their deliverables are completed on time and within budget for their senior and manager\n\nResponsibilities\n\nAssist the seniors and managers as part of a wider team to service their clients\nEnsure client files have all relevant documentation on the appropriate section\nTake responsibility for all client matters as directed by the senior and manager\nPrepare client tax returns required by the senior and manager\nActive adherence to budget and time pressures, bringing matters to the attention of the senior or manager\nPreparation of engagement letters and client acceptance documentation\nMust demonstrate strong team playing skills in all client and internal management dealings\nDevelop professional relationships with clients and within the firm\nProvide an efficient and pro-active service to clients and their internal management to ensure that their needs are fully met\nUndertake any training or development coordinated by the tax team\nWilling and open to take on tasks and challenges provided by their manager\nComplete additional ad-hoc duties or assignments as required\n\nRequirements\n\nBachelor degree in Accounting, Economics, Financial Services or equivalent subject\nAwareness of legal and economic environment of business and to related these to the clients\u2019 organizations and its activities and plans\nBe able to develop a clear understanding of relevant legislation\nSelf-motivated, able to work to tight deadlines\nWith an ability and interest in understanding clients\u2019 business\nGraduated in 2021\n\nWe are an equal opportunity employer, and offer excellent prospects and career development for the right candidate.\u00a0 Interested parties please send your application\u00a0with full career history, current and expected salary by clicking\u00a0Apply Now button below.\n\nApplications will be treated in strict confidence. Personal data collected will be used for recruitment purposes only.", "employment_types": ["Full Time", "Permanent"], "selling_points": ["Fresh graduate is welcomed", "Excellent career prospects", "Birthday Leave, Medical and Life Insurance, etc."], "locations": ["Sheung Wan"], "categories": ["Accounting", "Taxation", "Others", "Student / Fresh Graduate / No Experience"], "post_time": "2022-01-17T02:17:56Z", "salary": {"currency": null, "max": null, "min": null, "period": "monthly", "term": null}, "salary_visible": false, "title_keywords": ["associate"], "responsibilities": ["tax", "management", "budget", "letters", "develop", "ad-hoc duties", "documentation"], "requirements": {"degrees": ["degree", "bachelor"], "majors": ["economics", "accounting"], "languages": [], "language_level": [], "hard_skills": [], "soft_skills": ["clear", "self-motivated"], "languages_combined": []}, "experience_required": {"duration": [], "field": []}}, {"job_id": "100003009047053", "location_code": "hk", "company": "Belden Asia ( Hong Kong ) Limited", "job_title": "Tax Manager", "description": "PURPOSE OF POSITION:\n\nSupporting the Asia tax team in various tax planning, structuring and corporate income tax compliance initiatives. Managing tax accounting, formulate and implement regional tax strategy in line with global tax strategy, optimize the tax position, manage country tax compliance and enhance the access to capital for Asia Pacific.\n\nKEY ACCOUNTABILITIES:\n\nWe have establishments in China, Hong Kong, Singapore, India, Japan, Korea, Australia, Thailand, Indonesia, Malaysia, Philippines, Vietnam and Taiwan.\n\nAssist Tax Director in review the corporate income tax filings for establishments in Asia Pacific\u00a0\nAssist the US GAAP tax accounting for the Asia Pacific establishments\nSupport to implementing of the Belden Group's transfer pricing policies and preparation of proper documentation\nAssist the planning and implementation of tax projects in the Asia Pacific region\nAssist the provision of support from corporate income tax and transfer pricing perspectives to the different functional and business teams within the Belden Group\n\nREQUIREMENTS:\n\n7 years or above\u00a0tax and /or accounting working experience,\u00a0preferable in Big 4 accounting firms and/or multinational corporations\u00a0\nStrong research and technical skills\nExcellent written\u00a0and oral communication skills in English and Chinese\u00a0\nExperience in SAP (or other integrated accounting system) and Hyperion is an advantage", "employment_types": ["Permanent"], "selling_points": ["7 years or above of tax or accounting experience", "No commerical experience may also consider", "Excellent problem solving skills"], "locations": ["Shatin Area"], "categories": ["Accounting", "Taxation"], "post_time": "2022-01-14T02:16:36Z", "salary": {"currency": null, "max": null, "min": null, "period": "monthly", "term": null}, "salary_visible": false, "title_keywords": ["manager"], "responsibilities": ["tax", "policies", "review", "compliance", "implementation", "teams", "communication", "documentation", "planning"], "requirements": {"degrees": [], "majors": [], "languages": ["english", "chinese"], "language_level": ["excellent"], "hard_skills": ["documentation", "accounting system", "sap"], "soft_skills": ["technical skills", "communication skills", "oral"], "languages_combined": [{"language": "english", "language_level": ["excellent"]}, {"language": "chinese", "language_level": ["excellent"]}]}, "experience_required": {"duration": ["7 years"], "field": ["accounting", "big 4"]}}, {"job_id": "100003009051341", "location_code": "hk", "company": "EY", "job_title": "Tax - Customer Tax Operations & Reporting Services - Senior - Hong Kong", "description": "The opportunity\n\nIn EY Tax, you\u2019ll have the opportunity to help the world\u2019s leading multinational organizations meet complex tax obligations around the world. You\u2019ll get a unique glimpse deep inside a company\u2019s business and become a trusted advisor, working collaboratively on a team that influences major business decisions.\u00a0Demand has made this a rapidly growing area, and the relationships we build here translate into big business in other areas, making this a true priority.\n\n\nYour key responsibilities\n\nJoin the fast-growing Asia Pacific Customer Tax Operations and Reporting Services practice to deliver complex AEOI engagements. As part of the team, you will work closely with team members across the Asia Pacific region while you are also required to interact with teams in other parts of the world, e.g. the US.\nTake part in various types of AEOI engagements which include advisory, compliance, reporting and transformation projects for financial institution clients from all sectors.\nUse the latest EY technologies in the engagement delivery.\nPartner with Tax Technology & Transformation to deliver innovative EY solutions which gives the unique value proposition.\nAssist clients in handling enquiries or inspections from tax authorities and other controversy matters.\nAssist in pursuits and the preparation of proposals.\n\nTo qualify for the role you must have\n\nBachelor or advanced degree in Accounting, Law, Finance or Economics, Business, IT or other relevant disciplines.\nExcellent command in both written & spoken English. High proficiency in Chinese and/or other language is preferable.\nEnergetic, hardworking, strong analytical, business savvy.\nTeam player with strong communication skills.\nStrong presentation, organization and management skills.\nGood at Microsoft Office. Appreciation of visualization / data analytics tools would be welcomed.\n\nIdeally, you\u2019ll also have\n\nPrevious experience dealing with clients within the financial services sector is strongly preferred\nPrevious experience dealing with information exchange matters (FATCA, CRS) or information reporting and withholding matters\nMature, proactive, committed, highly motivated and driven team player\n\nWhat we look for\n\nWe\u2019re interested in strong team players who support their colleagues in reaching their goals while also considering their own workload and development. We\u2019re looking for people with a genuine passion for tax, and the future of tax, and are inspired to help the world\u2019s leading multinational organizations meet complex tax obligations around the world. If you have the confidence to speak up and influence a team that affects big businesses worldwide, this role is for you.\n\nWhat working at EY offers\n\nAt EY, our Total Rewards package supports our commitment to creating a leading people culture\u00a0-\u00a0built on high-performance teaming\u00a0-\u00a0where everyone can achieve their potential and contribute to building a better working world for our people, our clients and our communities. It's one of the many reasons we repeatedly win awards for being a great place to work.\n\nWe offer\u00a0a\u00a0competitive\u00a0compensation\u00a0package where you\u2019ll be rewarded based on your performance and recognized for the value you bring to our business. In addition, our Total Rewards package allows you decide which benefits are right for you and which ones help you create a solid foundation for your future. Our Total Rewards package includes a comprehensive medical, prescription drug and dental coverage, a defined contribution pension plan, a great vacation policy plus firm paid days that allow you to enjoy longer long weekends throughout the year, statutory holidays and paid personal days (based on province of residence), and a range of exciting programs and benefits designed to support your physical, financial and social well-being. Plus, we offer:\n\nSupport and coaching from some of the most engaging colleagues in the industry\nLearning opportunities to develop new skills and progress your career\nThe freedom and flexibility to handle your role in a way that\u2019s right for you\n\nAbout EY\n\nAs a global leader in assurance, tax, transaction and advisory services, we\u2019re using the finance products, expertise and systems we\u2019ve developed to build a better working world. That starts with a culture that believes in giving you the training, opportunities and creative freedom to make things better. Whenever you join, however long you stay, the exceptional EY experience lasts a lifetime.\n\nIf you can confidently demonstrate that you meet the criteria above, please contact us as soon as possible.\n\nMake your mark.\n\nApply today.", "employment_types": ["Full Time", "Permanent"], "selling_points": ["Asia Pacific Tax Services", "FATCA/CRS/AEOI", "Latest EY technologies in engagement delivery"], "locations": ["Not Specified"], "categories": ["Accounting", "Taxation", "Others", "Professional Services", "Legal & Compliance"], "post_time": "2022-01-15T09:53:39Z", "salary": {"currency": null, "max": null, "min": null, "period": "monthly", "term": null}, "salary_visible": false, "title_keywords": ["operations"], "responsibilities": ["tax", "reporting", "management", "analytics tools", "visualization", "data", "operations", "compliance", "teams", "communication"], "requirements": {"degrees": ["degree", "bachelor"], "majors": ["law", "finance", "economics", "business", "it", "accounting"], "languages": ["english", "chinese"], "language_level": ["excellent", "proficiency"], "hard_skills": ["crs", "microsoft office", "data analytics", "fatca", "exchange"], "soft_skills": ["communication skills", "proactive", "confidence", "advanced", "passion for", "deep", "driven", "interested in", "unique", "innovative", "mature", "committed", "genuine", "motivated", "team player", "energetic", "presentation", "hardworking"], "languages_combined": [{"language": "english", "language_level": ["excellent"]}, {"language": "chinese", "language_level": ["proficiency"]}]}, "experience_required": {"duration": [], "field": ["financial services"]}}, {"job_id": "100003009054921", "location_code": "hk", "company": "Eternity Consultants (HK) Ltd", "job_title": "Account Clerk / Senior Account Clerk - Trading (Fresh graduate will consider)", "description": "Trading\nJob Responsibilities:\n\nAccount Receivable, Account Payable\nPerform daily accounting functions including prepare voucher input and various payments\nAssist in projects and other ad hoc assignment\n\nJob Requirements :\n\nDiploma in Accounting\n2-4 year working experience in accounting field\u00a0\nFamiliar with Excel, Word and Chinese word processing\nInitiative, well-organised, hard working and willing to learn\n\nBenefit:\n\n5 days, bank holiday, medical scheme\n\n*Interested parties, please send full resume with current & expected salary & date available in MS WORD FORMAT ONLY to us\u00a0or fax to 3527 0634*\n\nWe are welcome applicants resend resumes to us even you have applied jobs in our company before.\n\nFor more jobs, please visit our website: www.hketernity.com\n\n(Personal data submitted are for recruitment purpose only.)", "employment_types": ["Full Time", "Permanent"], "selling_points": ["5 days, bank holiday, medical.", "F.7/+  w/ LCC Intermedicate/ Accounting Diploma", "2-4 year experience in accounting field"], "locations": ["Others"], "categories": ["Accounting", "Accounting Clerk / Supervisor", "Taxation", "Treasurer"], "post_time": "2022-01-17T13:57:23Z", "salary": {"currency": null, "max": null, "min": null, "period": "monthly", "term": null}, "salary_visible": false, "title_keywords": ["account clerk", "senior account clerk"], "responsibilities": ["daily accounting", "ad hoc assignment", "payments"], "requirements": {"degrees": ["diploma"], "majors": ["accounting"], "languages": ["chinese"], "language_level": [], "hard_skills": ["excel", "chinese word processing", "word"], "soft_skills": ["well-organised", "hard working", "willing to learn", "initiative"], "languages_combined": [{"language": "chinese", "language_level": []}]}, "experience_required": {"duration": ["2-4 year"], "field": ["accounting"]}}, {"job_id": "100003008948269", "location_code": "hk", "company": "EY", "job_title": "Asia Pacific Tax Centre - Tax Accounting Risk Advisory Services - Manager/Senior Manager - Hong Kong", "description": "\nEY Asia-Pacific Tax Center (APTC) serves high-profile, multinational clients, providing a range of domestic and cross border tax services.\n\nThe opportunity\n\nOur Tax Accounting Risk Advisory Services (TARAS) practice operates within APTC, focus on helping clients effectively manage local statutory income tax reporting, bookkeeping and tax compliance obligations proactively and responsibly of our client\u2019s operations. TARAS professionals focus on details of income tax accounting, processes and internal controls over tax accounting and reporting. With engagements involving a few countries or many, you will have the opportunity to provide clients an integrated, consistent, quality service that unlocks the potential of the tax function across the entire record-to-report process.\n\nYour Key Responsibilities\n\nAs a Manager/Senior Manager in the services, you will spend your time transforming EY client\u2019s business. You will work with a variety of teams to understand their income tax processes and identify process and technology improvement opportunities across the record-to-report process. You may utilize a variety of tools and techniques to document current state and identify future state processes. You may design and configure automation tools, such as robotic process automation, data integration and workflow.\n\nFor key clients you will also help manage implementation of centrally managed global outsourcing/sourcing models that provide clients with greater control and visibility over global tax accounting compliance and reporting activities, access to global team members with finance expertise, and development of new operating models to address new markets. You will serve on audits of key clients including those requiring: HKAS 12, IAS 12 and US GAAP ASC 740 tax reporting requirements.\n\nSkills/Experience:\n\nFoundational accounting background including income tax accounting. Individuals from Assurance background in Financial Services strongly preferred.\nExperience in providing assurance services to listed clients including income tax accounts\nIdentify ways to automate manual tasks using existing financial or tax systems and emerging technologies\nExhibit competency in technology by maintaining complex sets of data, reviewing data analytics and analyzing trends including the collection of data as per agreed financial statement close timelines and other requirements\nExhibit critical thinking across EY methodologies/tools to enhance service delivery, challenge current procedures to find new approaches\nStrong spirit of entrepreneurship with colleagues and clients\nOpenness to collaborate with individuals from different backgrounds in an international environment\nFunction as Project Manager, team motivator, and oversee process guidance of workflow development\nTake ownership of tasks and make decisions and resolve issues including the escalation of client and internal partner issues while having a strong ability to work under pressure and strict deadlines\nAbility to think strategically to client centric solutions across: ESG reporting, Transactions, tax accounting process improvement, internal tax controls\nManaging, coaching and developing a team of staff and seniors, expectations to serve as counselors to junior resources\nBuild client relationships and demonstrate knowledge of client businesses\nScoping of new opportunities: develop proposals and participate in oral presentations provide high-quality services/work products build relationships with clients, understanding their unique needs to provide a tailored service\nTo qualify for the role you must have:\n\nA Bachelor's in Accounting or related field and a minimum of 7 years of related work experience\nStrong desire grow within EY as a TARAS specialist, team builder and client relationship management\nCertified Public Accountant or related designation being pursued\nAbility to lead a team, mentor counselees and manage client-serving business\nStrong organizational and time management skills, with exceptional client-serving consulting skills\nDemonstrated ability to capture and synthesize business requirements and entrepreneurship to operate in a new market and operate at a higher level\nWillingness to travel, expectations of 15%+ across APAC post Covid restrictions lifted\nIdeally, you\u2019ll also have\n\nBusiness Analyst background/experience\nExperience implementing robotic process automation\nMicrosoft Excel VBA development\nMicrosoft Power BI suite, including Power Pivot, Power Query, Power View and Power Map\nKnowledge and experience in the design and development of databases (specifically SQL Server)\nAlteryx\nERP experience, including SAP and/or Oracle\nWhat We Look For\n\nWe\u2019re interested in professionals who enjoy promoting the people agenda in organizations and change initiatives, bringing people issues and challenges to the forefront. You\u2019ll need the confidence to keep the people agenda front and centre, and the interpersonal skills and communications savvy to do this in a way that integrates well with executive priorities and objectives.\n\nWhat Working At EY Offers\n\nWe offer a competitive compensation package where you\u2019ll be rewarded based on your performance and recognized for the value you bring to services. In addition, our Total Rewards package includes medical and hospitalization benefits, group life and personal accident insurance, annual leave and Mandatory Provident Fund and a range of programs and benefits designed to support your physical and social well-being. Plus, we offer:\n\nSupport, coaching and feedback from some of the most engaging colleagues around\nOpportunities to develop new skills and progress your career\nThe freedom and flexibility to handle your role in a way that\u2019s right for you\nJoin us in building a better working world.\n\nApply now.", "employment_types": ["Full Time"], "selling_points": ["Asia Pacific Tax Center", "Income Tax, Bookkeeping & Tax Compliance - USGAAP", "International team and global exposures"], "locations": ["Quarry Bay"], "categories": ["Accounting", "Taxation", "Others", "Professional Services", "Business Consultancy"], "post_time": "2022-01-15T10:20:56Z", "salary": {"currency": null, "max": null, "min": null, "period": "monthly", "term": null}, "salary_visible": false, "title_keywords": ["senior manager", "accounting", "manager"], "responsibilities": ["collaborate with", "consulting", "data", "operations", "quality", "design", "transactions", "financial statement", "work under pressure", "service delivery", "control", "maintaining", "compliance", "teams", "implementation", "developing", "develop", "presentations", "report", "reporting", "guidance", "management", "procedures", "audits", "tax", "power bi", "systems", "lead a team", "databases"], "requirements": {"degrees": ["bachelor"], "majors": ["accounting"], "languages": [], "language_level": [], "hard_skills": ["vba", "server", "bi", "sap", "data analytics", "presentations", "microsoft excel", "sql", "make", "erp", "databases", "alteryx", "integration", "focus", "oracle"], "soft_skills": ["oral", "confidence", "time management skills", "organizational", "interested in", "unique", "interpersonal skills", "think strategically", "focus", "work under pressure"], "languages_combined": []}, "experience_required": {"duration": ["minimum of 7 years"], "field": ["assurance", "related", "development", "design", "sql", "business", "accounting"]}}, {"job_id": "100003009044133", "location_code": "hk", "company": "Dah Chong Hong Holdings Limited", "job_title": "Tax Officer (Ref: GFN-Tax)", "description": "The position is responsible to assist on a range of Tax Planning and Compliance duties, and also provide administrative support to tax team and business partnering support.\n\nResponsibilities include:\n\nAssist and cooperate with various business units in handling Hong Kong Profits Tax compliance work\nProvide support in handling tax disputes of group companies in Hong Kong and the PRC with tax authorities\nAssist in implementing the Group\u2019s tax projects\nPrepare monthly reports and analysis, and provide support to facilitate other reporting requirements from headquarter\nAssist in handling ad hoc enquiries from group companies across HK, the PRC and Asia Pacific region\nPerform tax research and analysis on tax regulation changes\nPerform other related duties as assigned\n\nQualifications required:\n\nBachelor Degree in Finance, Accounting or related disciplines\n1-3 years of related experience in professional firm, the IRD or commercial field\nKnowledge and experience in HK, PRC and APAC taxes would be an advantage\nProficiency in Microsoft Excel, PowerPoint and reporting tools\nProficient in written and spoken English, Cantonese and Mandarin\nDetail-oriented, proactive and willing to work as a team\n\nWe offer competitive salary, discretionary bonus, medical insurance, life and personal accident insurance, annual leave and staff purchase discount. Interested candidates please send your resume with salary expectation by email or clicking\u00a0\"Apply Now\".\n\nWe are equal opportunities employer. Applicants who are not invited within 2 months may consider their application unsuccessful. All applicants may be considered for other suitable positions with DCH Group / CITIC Pacific Group and will be deleted from our files after 6 months from the date of application.", "employment_types": ["Full Time", "Permanent"], "selling_points": [], "locations": ["Kowloon Bay"], "categories": ["Accounting", "Financial Analyst", "Taxation", "Banking / Finance", "Corporate Finance"], "post_time": "2022-01-13T03:13:25Z", "salary": {"currency": null, "max": null, "min": null, "period": "monthly", "term": null}, "salary_visible": false, "title_keywords": ["officer"], "responsibilities": ["tax", "reporting", "provide support", "ad hoc", "monthly reports", "analysis", "compliance", "provide administrative support", "cooperate with", "planning"], "requirements": {"degrees": ["degree", "bachelor"], "majors": ["related disciplines", "finance", "accounting"], "languages": ["cantonese", "english", "mandarin"], "language_level": ["proficient"], "hard_skills": ["analysis", "powerpoint", "microsoft excel"], "soft_skills": ["work as a team", "proactive", "responsible", "detail-oriented"], "languages_combined": [{"language": "cantonese", "language_level": ["proficient"]}, {"language": "english", "language_level": ["proficient"]}, {"language": "mandarin", "language_level": ["proficient"]}]}, "experience_required": {"duration": ["1-3 years"], "field": ["related", "commercial"]}}, {"job_id": "100003009052313", "location_code": "hk", "company": "PwC", "job_title": "Senior Associate - Tax Controversy Services, ITBC, Tax Services, Hong Kong", "description": "Job Descriptions and Responsibilities\n\nIn recent years, the Hong Kong Inland Revenue Department (\u201cIRD\u201d) has been deploying more resources on tax controversy and taking a more stringent approach in handling tax disputes with both corporate and individual taxpayers. Given the adoption of OECD\u2019s action plan on Base Erosion and Profit Shifting (\u201cBEPS\u201d) and the implementation of new tax regulations, taxpayers are facing more challenges and encountering with more tax controversy issues. To cope with the increasing market demand for tax controversy and dispute resolution services, our Tax Controversy Services (\u201cTCS\u201d) team is expanding and now recruiting experienced talents (preferably those who are familiar with the IRD\u2019s practices and/or with practical experience of dealing with the IRD) to join our TCS team.\n\nOur TCS team consists of ex-officers and tax specialists with strong expertise and experience in handling tax controversy. We are currently seeking high caliber tax professionals to join us and take part in:\n\nAssisting clients in resolving tax disputes, for example, tax audit and appeal cases, tax enquiries, challenges on the entitlement to treaty benefits;\nFormulation of settlement approaches for tax audit and investigation cases;\nNegotiation with the IRD\u2019s officers during the course of case resolving;\nHandling simple tax audit cases independently with direct partner supervision;\nPost-audit restructuring to rectify problems identified during tax audit;\nConducting tax health checks and defense file building;\nAssisting clients in obtaining treaty protection or treaty benefits, and defending against any challenges from the IRD;\nDeveloping and maintaining good client relationship at working level; and\nAssisting in the practice development for the TCS team and PwC.\n\nRequirements\n\nA recognized accounting or equivalent degree\nQualified member of a professional accounting body\nTotal 3- 5 years of experience in Hong Kong profits tax experience, preferably with experience of field audits / tax investigations or other areas of tax controversy\nWith IRD work experience is a plus, particularly experience in the Field Audit and Investigation Unit, Appeals Section or Treaty Section\nFluent in both written and spoken English, Cantonese and Putonghua\nExcellent interpersonal skills would be an advantage\nAnalytical-minded and solid in project management\nCandidates with more experience will be considered for Manager role\n\n\n\nThe PwC China (including Mainland China, Hong Kong, Macau) does not accept unsolicited resumes from search firm recruiters. Fees will not be paid in the event a candidate submitted by a recruiter without an agreement in place is hired; such resumes will be deemed the sole property of PwC China (including Mainland China, Hong Kong, Macau). PwC China (including Mainland China, Hong Kong, Macau) is an equal opportunity employer. All aspects of employment will be based on merit, competence, performance, and business needs. We do not discriminate on the basis of race, color, religion, marital status, age, national origin, ancestry, physical or medical condition, genetic information, gender, sexual orientation, gender identity or expression, veteran status, or any other status protected under the local law.", "employment_types": ["Full Time", "Permanent"], "selling_points": ["Resolving Tax Dispute, Tax Investigations", "3- 5 years Experience in Liaising with IRD", "Fluent in  English and Chinese"], "locations": ["Central"], "categories": ["Accounting", "Consulting", "Taxation"], "post_time": "2022-01-17T02:43:57Z", "salary": {"currency": null, "max": null, "min": null, "period": "monthly", "term": null}, "salary_visible": false, "title_keywords": ["senior associate"], "responsibilities": ["tax", "regulations", "implementation", "resolution", "plan"], "requirements": {"degrees": [], "majors": [], "languages": [], "language_level": [], "hard_skills": [], "soft_skills": [], "languages_combined": []}, "experience_required": {"duration": [], "field": []}}, {"job_id": "100003009051572", "location_code": "hk", "company": "Finest Industrial Co Ltd", "job_title": "Assistant Accountant / Accountant", "description": "Job Description\nResponsible for full set of accounts independently\nHandle daily inter-company transaction / activities & general ledger\nAssist and monitor daily inventory/ import / export business & Custom EDI activities\nProcess A/P & A/R, credit control, P&L, payroll & various accounting matters of companies (HK & PRC)\nLiaise with Mainland China counterpart on accounting and taxation matters\nPrepare month-end closing schedules, costing analysis and related accounting reports\nAssist in other ad-hoc assignments\n\nRequirements\n\nDiploma holder or above or related discipline\n3-5 years working experience\nExperience in handling full-sets accounts\nProficient in MS Office, ERP and systematic documents processing\nGood command of both spoken and written Chinese and English\nWilling to travel overseas and mainland China in Post-Covid Period\nGood figure sense with proactive attitude and good communication skill\n\nYou will have an advantage if you are:\nHands-on experience in knowledge of financial / accounting / taxation regulation and policy in both HK & China\nDetails oriented, good communication and negotiation skills\nGood in problem solving, analytical and interpersonal skill\nSelf-motivated, committed and able to work under pressure, independently and support team works\nImmediate available\n\nWe offer attractive remuneration package with fringe benefits to right candidates\n\nLocation: walk 3 mins from Chai Wan MTR Station\n\nInterested parties please send email with current and expected salary and date of available by clicking \u201cApply Now\u201d\n\nPersonal Data collected will be used for recruitment purpose only.\n\nNo Recruitment Agency", "employment_types": ["Full Time", "Permanent", "Contract"], "selling_points": [], "locations": ["Chai Wan"], "categories": ["Accounting", "Accountant", "Accounting Clerk / Supervisor", "Taxation"], "post_time": "2022-01-16T11:14:56Z", "salary": {"currency": null, "max": null, "min": null, "period": "monthly", "term": null}, "salary_visible": false, "title_keywords": ["accountant", "assistant accountant"], "responsibilities": ["taxation", "control", "schedules", "general ledger", "inventory", "full set of accounts", "monitor", "ad-hoc assignments", "p&l", "month-end closing", "costing analysis", "reports", "liaise with", "payroll"], "requirements": {"degrees": ["diploma holder"], "majors": [], "languages": ["english", "chinese"], "language_level": ["good command"], "hard_skills": ["problem solving", "processing", "erp", "ms office"], "soft_skills": ["self-motivated", "independently", "communication skill", "systematic", "interpersonal skill", "communication", "problem solving", "hands-on", "negotiation skills", "committed", "proactive", "work under pressure"], "languages_combined": [{"language": "english", "language_level": ["good command"]}, {"language": "chinese", "language_level": ["good command"]}]}, "experience_required": {"duration": ["3-5 years"], "field": ["accounting", "financial"]}}, {"job_id": "100003009054600", "location_code": "hk", "company": "Procon CPA Limited", "job_title": "Junior/Senior Audit Officer(5-day work week)($17000-24000)", "description": "\u00a0Job responsibilities:\u00a0\n\nYou will be assigned to one of our audit teams of 3 \u2013 6 professionals stationing in Hong Kong.\nOur audit practice follows the standard APM issued by HKICPA.\nBook keeping accounting engagements are performed by separate accounting teams, not audit teams.\u00a0\n\nJob requirements:\u00a0\n\nGood command of written and oral English and Chinese\nProficiency in accounting double-entry system.\u00a0 Working experience in book keeping is not required.\nData processing and basic analysis in MS Excel\u00a0\n\nOur offers:\u00a0\n\nCompetitive package to attract talents starting from HK$17,000 \u2013 HK$24,000 per month\nOvertime work is not encouraged but, if incurred, will be compensated.\n5-day working week\nQP bonus of HK$3,000 per month\nAnnual leave: 12 days \u2013 14 days\nPaid exam leaves and study leaves for professional exams\nBirthday leave\nHardship allowance for working outside Hong Kong\nAnnual 3-day training camp in offsite hotel\u00a0\nFresh graduates are welcome\nShort-term contract staff will also be considered\n\nInterested parties can apply with detailed resume,\u00a0date of availability and expected salary\u00a0by email to Ms. Fanny Chau\n", "employment_types": ["Full Time", "Contract"], "selling_points": [], "locations": ["Lai Chi Kok"], "categories": ["Accounting", "Accountant", "Audit", "Taxation"], "post_time": "2022-01-17T10:12:11Z", "salary": {"currency": null, "max": null, "min": null, "period": "monthly", "term": null}, "salary_visible": false, "title_keywords": ["junior"], "responsibilities": ["teams", "audit"], "requirements": {"degrees": [], "majors": [], "languages": ["english", "chinese"], "language_level": ["good command"], "hard_skills": ["analysis", "processing", "basic", "ms excel"], "soft_skills": ["overtime work", "oral"], "languages_combined": [{"language": "english", "language_level": ["good command"]}, {"language": "chinese", "language_level": ["good command"]}]}, "experience_required": {"duration": [], "field": []}}, {"job_id": "100003009051475", "location_code": "hk", "company": "BDO", "job_title": "Manager / Senior Associate - Transfer Pricing (Ref: TAX)", "description": "Your Key Responsibilities\n\nAssist senior team members to perform various TP and tax analysis including TP planning/advisory, TP documentation, audit defense, advance pricing agreements and other related deliverables;\nAnalyze clients business activities, financial performance and intercompany transactions;\nParticipate in meetings or phone calls with senior business executives to identify functions, assets and risks;\nReview data sets, and perform financial analysis using a variety of economic, statistical and sector based models or techniques;\nEnsure timely delivery of work by managing project workflow, analyzing information, effective (internal and external) communication and managing and coaching more junior members of team;\nConduct industry and company research for clients in a range of sectors;\nClosely collaborate with TP or tax teams in HK or across the network;\nMonitoring OECD, global or local country TP or related tax developments.\n\nRequirements\n\n2 to 6 years of relevant experience in corporate tax or TP from other accounting firms and industry preferred\nCandidates with consulting, advisory, valuation, research, audit or related experience will also be strongly considered\nDegree holder, preferably major in economics, accounting, business, mathematics, finance or related disciplines\nExcellent command of both written and spoken English; proficiency in Mandarin is preferred\nExperience with common technology and TP database tools is important; experience with automation or efficiency solutions is an advantage.\n\nWhat We Look For\n\nApplicants who are dynamic, motivated and team-oriented.\nCritical thinkers with strong numerical and analytical skills\nProfessionals who are curious and fascinated by the inner working of business\nTeam player who can work effectively with others to achieve a common goal\nInterest and proficiency in new technologies\n\nRemark\n\nPosition offered will be commensurate with the experience of the right candidate", "employment_types": ["Full Time", "Permanent"], "selling_points": ["Perform various TP and tax analysis", "2 to 6 years of relevant experience", "Excellent Career Prospect"], "locations": ["Sheung Wan"], "categories": ["Accounting", "Taxation", "Professional Services", "Business Consultancy"], "post_time": "2022-01-16T03:48:30Z", "salary": {"currency": null, "max": null, "min": null, "period": "monthly", "term": null}, "salary_visible": false, "title_keywords": ["senior associate", "manager"], "responsibilities": ["tax", "collaborate with", "data", "analysis", "review", "teams", "audit", "transactions", "monitoring", "financial analysis", "communication", "documentation", "phone calls", "business activities", "planning"], "requirements": {"degrees": ["degree holder"], "majors": ["mathematics", "finance", "economics", "related disciplines", "business", "accounting"], "languages": ["english", "mandarin"], "language_level": ["excellent", "proficiency"], "hard_skills": ["goal", "dynamic", "analytical skills"], "soft_skills": ["work effectively", "analytical skills", "motivated", "dynamic", "team player"], "languages_combined": [{"language": "english", "language_level": ["excellent"]}, {"language": "mandarin", "language_level": ["proficiency"]}]}, "experience_required": {"duration": ["2 to 6 years"], "field": ["research", "consulting", "related", "audit", "relevant experience", "database", "accounting"]}}, {"job_id": "100003009051356", "location_code": "hk", "company": "EY", "job_title": "Tax - Payroll Operate Services - Staff /Senior Accountant - Hong Kong", "description": "EY\u2019s market-leading approach combines extensive local payroll service experience with a standard global payroll compliance and implementation methodology. You will have the opportunity to provide clients an integrated, consistent, quality service that unlocks the potential of the payroll function across the entire record-to-report process. The Payroll Operate Services practice is experiencing unprecedented growth, serving multinational clients. Our pipeline is robust, and we anticipate continued growth in the foreseeable future. We believe that by managing clients\u2019 accounting and payroll obligations we can make a critical difference and you\u2019ll be at the heart of this mission.\n\nThe opportunity\n\nWe are currently seeking high-potential Staff/Senior Accountant\u00a0to deliver exceptional client service and enable the continued growth of Payroll Operate Services practice. You will develop your career by teaming with other professionals to deliver on our promises to all of our stakeholders, and in so doing, you will play a critical role in building a better working world for our people, for our clients and for our communities.\n\nSound interesting? Well, this is just the beginning \u2014 because whenever you join, however long you stay, the exceptional EY experience lasts a lifetime.\u00a0\u00a0\n\nResponsibilities:\n\nCollect monthly payroll data, do data analysis, perform gross to net payroll calculation, and prepare payroll reports in a timely, accurate and complete manner.\nProvide support in setting up Mandatory Provident Fund (\u201cMPF\u201d) Schemes for clients and enrolment & termination of clients\u2019 employees from the clients\u2019 MPF Schemes in accordance with MPF Scheme rules and the clients\u2019 policy.\nPrepare Employer\u2019s annual returns and notifications in accordance with the relevant tax laws.\nAssist in on boarding new clients, system implementation and data migration.\nProvide support in administrative tasks, e.g. compliance procedures update, filing, printing, billing, etc.\nEnsure necessary payroll processes/procedure is always followed.\nDemonstrate professionalism through a positive and cooperative attitude and by maintaining the confidential and proprietary nature of client relationships and related work products and responding to queries from clients and internal stakeholders on a timely manner.\n\nTo qualify, you must meet the following requirements:\n\nUniversity graduates with minimum 2 years\u2019 experience in payroll outsourcing or HR/ C&B related work preferably from professional firms\nUnderstanding of payroll or other related finance activities\nDetail oriented with strong numeric skills and be capable to work independently in a fast pace operational environment\nExcellent knowledge of computer skill including MS Office and MS Excel\nGood command of written and spoken English and Chinese\nEffective organization and time management skills\nHave a strong ability to do multiple tasks, work under pressure and to strict deadlines\n\nIf you\u2019re looking for a role that\u2019ll challenge you, give you opportunities to grow and encourage you to own your career, this role is for you.\n\n\u00a0What we look for\u00a0\n\nWe\u2019re interested in professionals who enjoy promoting the people agenda in organizations and change initiatives, bringing people issues and challenges to the forefront.\u00a0You\u2019ll need the confidence to keep the people agenda front and center, and the interpersonal skills and communications savvy to do this in a way that integrates well with executive priorities and objectives.\u00a0\u00a0\n\nWhat working at EY offers\u00a0\n\nWe offer a competitive compensation package where you\u2019ll be rewarded based on your performance and recognized for the value you bring to our services. In addition, our Total Rewards package includes medical and hospitalization benefits, group life and personal accident insurance, annual leave and Mandatory Provident Fund and a range of programs and benefits designed to support your physical and social well-being. Plus, we offer:\u00a0\n\nSupport, coaching and feedback from some of the most engaging colleagues around\nOpportunities to develop new skills and progress your career\nThe freedom and flexibility to handle your role in a way that\u2019s right for you\n\nIf you can confidently demonstrate that you meet the criteria above, please contact us as soon as possible.\n\nJoin us in building a better working world.\n\nApply now.", "employment_types": ["Full Time"], "selling_points": ["Global Payroll Services", "Payroll compliance and implementation methodology", "Minimum 2 years\u2019 experience in payroll/HR/C&B"], "locations": ["Quarry Bay"], "categories": ["Accounting", "Taxation", "Professional Services", "Business Consultancy", "Admin & HR", "Compensation & Benefits"], "post_time": "2022-01-15T10:49:30Z", "salary": {"currency": null, "max": null, "min": null, "period": "monthly", "term": null}, "salary_visible": false, "title_keywords": ["senior accountant", "staff"], "responsibilities": ["data", "quality", "work under pressure", "maintaining", "compliance", "implementation", "develop", "reports", "migration", "report", "provide support", "management", "mpf", "procedures", "data analysis", "administrative tasks", "payroll", "tax", "hr", "a timely manner"], "requirements": {"degrees": [], "majors": [], "languages": ["english", "chinese"], "language_level": ["good command"], "hard_skills": ["analysis", "scheme", "make", "ms excel", "computer skill", "system implementation", "ms office"], "soft_skills": ["work independently", "unprecedented", "confidence", "capable", "multiple tasks", "time management skills", "timely", "cooperative", "detail oriented", "interested in", "robust", "interpersonal skills", "accurate", "extensive", "positive", "work under pressure"], "languages_combined": [{"language": "english", "language_level": ["good command"]}, {"language": "chinese", "language_level": ["good command"]}]}, "experience_required": {"duration": ["minimum 2 years"], "field": ["related", "compliance", "hr", "payroll"]}}, {"job_id": "100003009049043", "location_code": "hk", "company": "Cheng & Cheng Ltd", "job_title": "Tax Assistant Accountant (5-day work)", "description": "Cheng & Cheng Limited is a Hong Kong based professional accounting firm with more than 25 years\u2019 experience in the financial sector. With the support of more than 250 professional staff, we aim to provide the best service to our clients.\u00a0\n\nWe provide a wide range of financial services, including, auditing, internal control and risk management, accounting, liquidation, taxation, pre-IPO and IPO services, etc.\n\nOur tax team provide comprehensive support from compliance to advisory services (e.g. preparing Profits Tax Returns and Profits Tax Computations, reply letters to the IRD, transfer pricing advisory and documentations, applications for certificates of resident status, Hong Kong and PRC tax advisory and tax planning for restructuring, tax investigation, etc.) to clients ranging from small and medium enterprises to listed companies and multinational companies in a professional and efficient manner.\u00a0\n\nThe successful candidates will join our tax team to help our clients to improve efficiencies, mitigate risk and improve opportunities within their tax functions by providing tax-related compliance assistance to them and their associated companies, analyzing tax opportunities and benefits that can be attained by them and assisting them in identifying and managing risks related to potential planning.\u00a0\n\nWe offer fabulous opportunities to develop your career through a broad range of engagements, mentoring as well as internal and external trainings.\u00a0\n\nWe invite high caliber individuals to join our team.\n\nTax Assistant Accountant (5-day work)\n\nWe invite high caliber fresh graduates t to join our team.\u00a0\n\nResponsibilities: -\n\n\u00a0Handle Hong Kong Profits Tax and Salaries Tax compliance and advisory engagements\n\nDraft reply letters to IRD queries\n\nPrepare applications for certificates of resident status\n\nParticipate in field audits and investigations, prepare analyses and other special jobs\n\nPerform ad hoc tasks\n\n\u00a0Requirements:-\n\nDegree or above\n\nStudent member/ member of HKICPA, ACCA or equivalent\n\nBasic PRC Tax knowledge is advantageous but not essential\n\nGood command of both spoken and written English and Chinese, Mandarin is preferred\n\nStrong self-motivation and ability to work under pressure\n\nGood communication, interpersonal and analytical skills\n\nApplicants with more than 2 years working experience and qualifications will be considered as Senior Tax Accountant\n\nWe offer 5-day work week with medical scheme, personal leave,study and exam leave. Interested parties please email your application letter and full resume stating\u00a0present & expected salary,availability and quoting job reference number by clicking \"Apply Now\".\u00a0For more information of the company,please visit www.chengcpa.com.hk.\n\n\nPersonal data collected will be used for recruitment purpose only.", "employment_types": ["Full Time", "Permanent"], "selling_points": ["Taxation", "Draft reply letters to IRD queries", "Accountant"], "locations": ["Kowloon Bay"], "categories": ["Accounting", "Accountant", "Audit", "Taxation"], "post_time": "2022-01-14T07:58:04Z", "salary": {"currency": null, "max": null, "min": null, "period": "monthly", "term": null}, "salary_visible": false, "title_keywords": ["assistant accountant"], "responsibilities": [], "requirements": {"degrees": [], "majors": [], "languages": [], "language_level": [], "hard_skills": [], "soft_skills": [], "languages_combined": []}, "experience_required": {"duration": [], "field": []}}, {"job_id": "100003009051481", "location_code": "hk", "company": "AXA International Limited", "job_title": "Accountant / Senior Accountant", "description": "Responsibilities:\n\nReview full set of account, costing, taxation and ad hoc assignments of each office\nSupervise and monitor the daily accounting and finance operations of different companies\nPrepare monthly reports, financial statements, cash flow forecast and\u00a0management analysis reports\nConsolidate financial reports, review and prepare of budgeting and management reports to align with business objectives\nEnsure the accounting records and documentation in compliance with the local statutory requirement and company accounting policy\nDeal with both internal and external parties including auditor and tax agent etc.\nSupport year-end audit and taxation\nHandle ad hoc assignment\n\nRequirements:\n\nDegree holder major in accountancy\nStudent member or finalist of HKICPA or ACCA\nMinimum 5 years accounting experience with 3 years in manufacturing industry\nKnowledge in PRC taxation\nProficiency in Microsoft office and applications; well versed in Excel\nWilling to visit China and review financial operation when needed\nGood communication skills with foreign investment parties, able to work and interface well with personnel at various levels\nGood command of written English and Chinese\nFluent in spoken English, Mandarin and Cantonese\nStrong manufacturing analytical, presentation and report writing skills\nImmediately available or short notice will be an advantage", "employment_types": ["Full Time"], "selling_points": [], "locations": ["Wan Chai"], "categories": ["Accounting", "Accountant", "Taxation"], "post_time": "2022-01-16T03:54:01Z", "salary": {"currency": null, "max": null, "min": null, "period": "monthly", "term": null}, "salary_visible": false, "title_keywords": ["accountant", "senior accountant"], "responsibilities": ["monthly reports", "analysis reports", "budgeting", "internal and external parties", "audit", "financial statements", "finance operations", "ad hoc assignment", "compliance", "monitor", "forecast", "management", "review", "cash flow", "documentation", "tax", "taxation", "financial reports", "year-end", "management reports", "ad hoc assignments", "daily accounting"], "requirements": {"degrees": ["degree holder"], "majors": ["accountancy"], "languages": ["cantonese", "english", "chinese", "mandarin"], "language_level": ["good command", "fluent"], "hard_skills": ["excel", "acca", "microsoft office", "writing skills", "hkicpa"], "soft_skills": ["communication skills", "presentation", "writing skills"], "languages_combined": [{"language": "cantonese", "language_level": ["fluent"]}, {"language": "english", "language_level": ["good command", "fluent"]}, {"language": "chinese", "language_level": ["good command"]}, {"language": "mandarin", "language_level": ["fluent"]}]}, "experience_required": {"duration": ["3 years", "minimum 5 years"], "field": ["accounting experience", "manufacturing industry"]}}, {"job_id": "100003009051338", "location_code": "hk", "company": "EY", "job_title": "Tax - Customer Tax Operations Reporting - Manager - Hong Kong", "description": "In EY Tax, you\u2019ll have the opportunity to help the world\u2019s leading multinational organizations meet complex tax obligations around the world. You\u2019ll get a unique glimpse deep inside a company\u2019s business and become a trusted advisor, working collaboratively on a team that influences major business decisions.\u00a0Demand has made this a rapidly growing area, and the relationships we build here translate into big business in other areas, making this a true priority.\u00a0\nThe opportunity\nAs a Manager, you will be a part of our\u00a0Business Tax Services group on the Customer Tax Operations Reporting team.\u00a0This position offers excellent opportunities for learning and career advancement to the right candidate.\nYour key responsibilities\nAs a Manager, you will participate in and supervise multiple and challenging tax consulting engagements and to contribute to the delivery of innovative tax compliance support for our diverse clients.\u00a0\nLeading large and medium sized engagements.\nConducting and documenting tax research and legislation interpretation and advising on operational tax models, tax compliance strategies, and compliance issues.\nReviewing the work of junior staff for accuracy and completeness.\nBecome part of the tax engagement team in servicing the planning and compliance needs of clients and assisting clients with compliance audits.\nWorking closely with other members of our team on tax technical interpretation work for clients\nEstablish relationships with clients and gain a solid understanding of their business.\nDevelop technical skills by remaining up to date on trends, new developments and tax authority decisions, and apply them to moderately complex situations.\nIdentify opportunities for providing consulting and other special services.\nSupport the development and coaching of tax professionals and other junior tax staff members.\nParticipate in and contribute to the attainment of team objectives.\nTo qualify for the role you must have\nProfessional accounting designation or law degree\nMinimum of four years Hong Kong tax experience\nAbility to research and write utilizing electronic tax tools.\nStrong project management and organizational skills\nAbility to work with tight deadlines\nIdeally, you\u2019ll also have\nPrevious experience dealing with clients within the financial services sector is strongly preferred\nPrevious experience dealing with information exchange matters (FATCA, CRS) or information reporting and withholding matters\nMature, proactive, committed, highly motivated and driven team player\nWhat we look for\nWe\u2019re interested in strong team players who support their colleagues in reaching their goals while also considering their own workload and development. We\u2019re looking for people with a genuine passion for tax, and the future of tax, and are inspired to help the world\u2019s leading multinational organizations meet complex tax obligations around the world. If you have the confidence to speak up and influence a team that affects big businesses worldwide, this role is for you.\nWhat working at EY offers\nAt EY, our Total Rewards package supports our commitment to creating a leading people culture\u00a0-\u00a0built on high-performance teaming\u00a0-\u00a0where everyone can achieve their potential and contribute to building a better working world for our people, our clients and our communities. It's one of the many reasons we repeatedly win awards for being a great place to work.\nWe offer\u00a0a\u00a0competitive\u00a0compensation\u00a0package where you\u2019ll be rewarded based on your performance and recognized for the value you bring to our business. In addition, our Total Rewards package allows you decide which benefits are right for you and which ones help you create a solid foundation for your future. Our Total Rewards package includes a comprehensive medical, prescription drug and dental coverage, a defined contribution pension plan, a great vacation policy plus firm paid days that allow you to enjoy longer long weekends throughout the year, statutory holidays and paid personal days (based on province of residence), and a range of exciting programs and benefits designed to support your physical, financial and social well-being. Plus, we offer:\nSupport and coaching from some of the most engaging colleagues in the industry\nLearning opportunities to develop new skills and progress your career\nThe freedom and flexibility to handle your role in a way that\u2019s right for you\nAbout EY\nAs a global leader in assurance, tax, transaction and advisory services, we\u2019re using the finance products, expertise and systems we\u2019ve developed to build a better working world. That starts with a culture that believes in giving you the training, opportunities and creative freedom to make things better. Whenever you join, however long you stay, the exceptional EY experience lasts a lifetime.\nIf you can confidently demonstrate that you meet the criteria above, please contact us as soon as possible.\nMake your mark. Apply today.", "employment_types": ["Full Time", "Permanent"], "selling_points": ["FATCA/CRS/AEOI", "Conducting and documenting tax research", "Minimum of 4 years Hong Kong tax experience"], "locations": ["Not Specified"], "categories": ["Accounting", "Taxation", "Others", "Professional Services", "Legal & Compliance"], "post_time": "2022-01-15T09:41:14Z", "salary": {"currency": null, "max": null, "min": null, "period": "monthly", "term": null}, "salary_visible": false, "title_keywords": ["operations", "manager"], "responsibilities": ["tax", "reporting", "consulting", "operations", "compliance", "develop", "project management", "audits", "planning"], "requirements": {"degrees": ["degree"], "majors": ["accounting", "law"], "languages": [], "language_level": [], "hard_skills": ["crs", "project management", "fatca", "exchange"], "soft_skills": ["organizational skills", "proactive", "confidence", "passion for", "deep", "interested in", "unique", "mature", "genuine", "diverse", "project management", "learning", "committed", "motivated", "technical skills", "team player", "innovative", "driven"], "languages_combined": []}, "experience_required": {"duration": ["minimum of four years"], "field": ["financial services"]}}, {"job_id": "100003009046416", "location_code": "hk", "company": "PERSOLKELLY Hong Kong Limited", "job_title": "Regional Tax Manager (MNC, Double Pay, Good Bonus)", "description": "Company Profile\u00a0\n\nOur client is an award-winning market leader with offices operating across the world. To cope with the expansion of the business, they are seeking for a brand new high-caliber individual to join their expanding team. The person will be expected to take lead in the APAC Tax function of the company's expanding Business Units.\u00a0\n\nExciting new role for you\u00a0\n\nDirectly report to Global Tax Director\nAct as team lead to manage the Group\u2019s tax function of the company and to groom subordinates\nAct as subject-matter-expert on taxation function and provide tax advisory to enhance overall efficiency and tackle potential matters of the business\u2019 manufacturing and R&D, supply chain, retail, to engineering activities\nInvolve in local and regional tax-related projects/transactions\nKey focal point between HK, HQ, APAC teams, and external tax advisors\nIn charge of local and cross-border tax compliance matters ranging from preparing & submitting tax returns, transfer pricing docs, to tax benefit applications, treaty-relief applications, other related tax activities\nAd-hoc tax projects and tax advisory for various business partners across APAC\n\nRequirements\u00a0\n\nBachelor\u2019s degree or above in Accounting or related discipline\n5+ years of solid experience in taxation/tax advisory or related areas with at least 1 years in commercial sector\nExperience with PRC taxation, transfer pricing and customs matters along with international and cross-border supply chain/tax jurisdiction matters preferred\nStrong interpersonal and stakeholder management; ability to deal with stakeholders across different levels across APAC-level\nStrong project management skills with the ability to juggle multiple projects\nSelf-motivated, work independently & with team, analytical, and communicate effectively in English\n\nRewards\u00a0\n\nYou will be working at a high performing energetic team with great career progression. Attractive remuneration and package. Opportunity to join a market leading group with a promising career path and potential internal transfer opportunities.\u00a0\n\n\nInterested parties please click apply or send your application via email to\u00a0jolly_wong@persolkelly.\u00a0 com\u00a0For any enquiries, please do not hesitate to contact me at\u00a0(852) 2281 0021.\n\nWe also have various job vacancies from our well-established clients in all kinds of fields, please feel free to contact us. We are always willing to give you support on your career development\n\nAll information received will be treated in strict confidence and used for recruitment purpose only. Only shortlisted candidate will be notified.", "employment_types": ["Full Time", "Permanent"], "selling_points": ["MNC With Promising & Stable Career Path", "DOUBLE Pay, Bonus, 5-day, Full Medical, Awards", "CPA, Regional Exposure, Tax, Big 4 Background"], "locations": ["Not Specified"], "categories": ["Accounting", "Audit", "Finance / Accounting Manager", "Taxation"], "post_time": "2022-01-13T10:57:11Z", "salary": {"currency": null, "max": null, "min": null, "period": "monthly", "term": null}, "salary_visible": false, "title_keywords": ["manager"], "responsibilities": ["tax", "taxation", "ad-hoc", "management", "compliance", "teams", "transactions", "project management", "multiple projects", "report"], "requirements": {"degrees": ["degree or above", "bachelor"], "majors": ["accounting"], "languages": ["english"], "language_level": [], "hard_skills": ["r&d", "project management", "focal"], "soft_skills": ["self-motivated", "work independently", "project management skills", "energetic", "interpersonal"], "languages_combined": [{"language": "english", "language_level": []}]}, "experience_required": {"duration": ["at least 1 years", "5+ years"], "field": ["related", "commercial", "supply chain"]}}, {"job_id": "100003009043940", "location_code": "hk", "company": "Hongkong Managers and Secretaries Limited", "job_title": "Tax Specialist (PRC Tax) / Senior Tax Consultant", "description": "Our client is a global audit firm and looking for a new member to join the expanding team.\n\nResponsibilities:\n\nFor Tax Specialist (PRC Tax)\nProvide PRC tax advisory services (mainly PRC corporate income tax and value-added tax) to local and international clients\nPRC tax provision review\nCollaborate with our client's overseas member firms to work on various cross-border tax exercises, e.g. holding structures, group restructuring, M&A, other PRC tax planning projects\nConduct research on PRC tax issues\nSupport firm-wide and team-specific initiatives as well as other ad-hoc projects\nAssist in preparing\u00a0regional and local transfer pricing documentation and advisory reports\nRequirements:\n\nBachelor\u2019s degree in accountancy, finance, economics or related field\nMinimum 3years\u00a0of relevant experience in the PRC tax sector gained in a professional consulting environment\nPossess strong interpersonal, organizational and communications skills and computer literate\nProfessional qualification with\u00a0CCTAA or CICPA will be an advantage\nGood command of spoken and written English and Chinese (Proficiency in Mandarin would be an advantage)\nCandidates with less experience will be considered as Junior Tax Consultant\nImmediate availability is preferred\n\nFor Senior/Junior Tax Consultant (Hong Kong Tax, Transfer Pricing)\n\nPrepare regional and local transfer pricing documentation and advisory reports\nProvide Hong Kong tax advisory services to local and international clients from mainly a transfer pricing perspective\nCollaborate with our client's overseas member firms to work on various cross-border tax exercises, e.g. holding structures, group restructuring, M&A, other PRC tax planning projects\nWork effectively as a team member, support managerial personnel and lead teammates to achieve goals\nSupport firm-wide and team-specific initiatives as well as other ad-hoc projects\nImmediate availability is preferred\n\n\n\n\nInterested parties please submit your application to our mailbox by clicking Apply Now.\n\nPersonal data provided in the employment applications will be treated in strict confidence and used only for recruitment purpose.", "employment_types": ["Full Time", "Permanent"], "selling_points": ["PRC Tax advisory services", "PRC corporate income tax and value-added tax", "5 days works, friendly working environment"], "locations": ["Causeway Bay"], "categories": ["Accounting", "Taxation"], "post_time": "2022-01-13T02:32:21Z", "salary": {"currency": "HKD", "max": 34999, "min": 30000, "period": "monthly", "term": null}, "salary_visible": true, "title_keywords": ["specialist", "consultant"], "responsibilities": ["tax", "collaborate with", "review", "reports", "documentation", "ad-hoc projects", "conduct research", "planning"], "requirements": {"degrees": ["degree", "bachelor"], "majors": ["finance", "economics", "accountancy"], "languages": ["english", "chinese", "mandarin"], "language_level": ["advantage", "proficiency", "good command"], "hard_skills": ["documentation"], "soft_skills": ["work effectively", "organizational", "team member", "interpersonal"], "languages_combined": [{"language": "english", "language_level": ["proficiency", "advantage", "good command"]}, {"language": "chinese", "language_level": ["proficiency", "advantage", "good command"]}, {"language": "mandarin", "language_level": ["proficiency", "advantage", "good command"]}]}, "experience_required": {"duration": [], "field": ["relevant experience", "consulting"]}}, {"job_id": "100003009047044", "location_code": "hk", "company": "Kingsway Personnel Ltd", "job_title": "Japanese Speaking Senior Accountant/Accounting Manager ~40K", "description": "Employment Ref.: MA09563\nNature of Business: Well-known Japanese trading company\nWorking Days: 5 Days\nWorking Location: KLN Area\n\nBenefits:\n- Double pay\n- Discretionary Bonus\n- Medical insurance\n- Flexible working hours\n\nResponsibilities:\n- Review, formulate and implement financial and accounting policies, procedures and guidelines\n- Identify areas for continuous improvement to avoid risk and enhance internal control of operational activities and governance\n- Handle tax issue, mainly for in-charging of BEPS, and communicate with related parties for planning and resolving\n- Handle aggregation/ analysis and information sharing of whole entity and HK regional consolidated financial status\n- Conduct regular review of end-to-end processes\n\nRequirements:\n- Degree in Accounting or related discipline\n- Min. 5yrs exp. full set accounting, tax and internal control\n- Good command of Japanese (N3 or above), English and Mandarin\u00a0\n\nInterested in the above vacancy?\u00a0 Send your resume to us NOW!\nOnly short-listed candidates will be notified. Personal data collected will be used for recruitment purpose only", "employment_types": ["Full Time", "Permanent"], "selling_points": ["Min. 5yrs full set acct, tax, internal control", "Good at Japanese, English and Mandarin", "~40K, 13mths and bonus, Flexible working"], "locations": ["Not Specified"], "categories": ["Accounting", "Accountant", "Finance / Accounting Manager", "Taxation"], "post_time": "2022-01-15T19:11:32Z", "salary": {"currency": null, "max": null, "min": null, "period": "monthly", "term": null}, "salary_visible": false, "title_keywords": ["accounting manager", "senior accountant"], "responsibilities": [], "requirements": {"degrees": [], "majors": [], "languages": [], "language_level": [], "hard_skills": [], "soft_skills": [], "languages_combined": []}, "experience_required": {"duration": [], "field": []}}, {"job_id": "100003009049284", "location_code": "hk", "company": "Baker Tilly Hong Kong", "job_title": "Senior - Tax Services (Elite program)", "description": "Exposure to clients in a wide spectrum of industries on tax consulting assignments\nCompetitive remuneration package and benefits\nFast-track career path\n\nRequirements:\n\nGood honors degree in Accountancy, Business or related disciplines\nA qualified member of HKICPA\nExcellent writing and oral skills in English, with good grades in the public examinations\nCandidate with IELTs score of 8 or above will be considered favourably\nFluency in spoken English, Cantonese and Putonghua. Knowledge of other languages is a plus\nAn independent worker who excels under pressure\nAt least 3\u00a0years solid and relevant Hong Kong tax experience working\u00a0in a sizeable CPA firm in Hong Kong or the Hong Kong Inland Revenue\n\nWe offer an attractive remuneration package, interesting job exposure, excellent career growth prospects in a warm and friendly atmosphere. Our continuing expansion and growth offer numerous development opportunities to the incumbents.\u00a0\n\nIf you consider yourself the appropriate choice, please forward your CV and salary expectations with the application form\u00a0to the Human Resources Department, 2/F 625 King\u2019s Road, North Point, Hong Kong or by\u00a0clicking \u201cApply Now\u201d.\u00a0\u00a0\u00a0\n\nDownload Application Form\n\nSelected candidates will be notified by phone for interview arrangements within 6 weeks. Applications of unsuccessful candidates will be deleted immediately after screening.\n\nPersonal data provided by job applicants will be used strictly in accordance with the Employer's Personal Data Policies, a copy of which will be provided upon request.\n\nBaker Tilly Hong Kong\u00a0is a leading firm of certified public accountants and business advisers, specialising in providing clients with a range of integrated services. Our firm is driven by 300 directors and professional staff based in Hong Kong.", "employment_types": ["Full Time", "Permanent"], "selling_points": ["A qualified member of HKICPA", "3 years Hong Kong tax experience", "Fluency in spoken English, Cantonese and Putonghua"], "locations": ["Quarry Bay"], "categories": ["Accounting", "Consulting", "Taxation", "Professional Services", "Business Consultancy"], "post_time": "2022-01-14T08:22:41Z", "salary": {"currency": null, "max": null, "min": null, "period": "monthly", "term": null}, "salary_visible": false, "title_keywords": [], "responsibilities": ["tax", "consulting"], "requirements": {"degrees": [], "majors": [], "languages": [], "language_level": [], "hard_skills": [], "soft_skills": [], "languages_combined": []}, "experience_required": {"duration": [], "field": []}}, {"job_id": "100003008990992", "location_code": "hk", "company": "HLB Hodgson Impey Cheng Limited", "job_title": "Accountant / Senior Accountant \u2013 Audit & Assurance Services", "description": "Responsibilities\n\n\nParticipate in audit engagements for a variety of clients, including SME, companies listed on the Stock Exchange of Hong Kong, licensed corporations registered under Securities and Futures Commission (SFC), and investment funds\nPerform audit procedures and be responsible to manager / senior in charge for ensuring the work assigned is executed and completed as planned and in accordance to the firm\u2019s policies and procedures\n\nRequirements\n\n\nTertiary education (major in accounting or business related disciplines is preferred but not essential)\nFresh graduates will also be considered\nGood command of both written and spoken in English and Chinese, knowledge in Putonghua preferred\nGood interpersonal skill and able to work under pressure and tight deadlines\nWilling to travel on business needs\nCandidate with more experience will be considered in senior position\n\nWe are registered as Authorized Employer of the Hong Kong Institute of Certified Public Accountants (HKICPA). We offer fringe benefits to the right candidates, including medical scheme, hospitalization & surgical insurance, 5-day work week, study and examination leave.\n\nInterested parties please send your full resume with current and expected salary by post to our Human Resources Department, HLB Hodgson Impey Cheng Limited, 31/F Gloucester Tower, The Landmark, 11 Pedder Street, Central, Hong Kong or click Apply Now.\n", "employment_types": ["Full Time", "Permanent"], "selling_points": ["5-day work, medical insurance, study & exam leave", "Tertiary education, fresh graduates are welcome", "Major in acct/business preferred but not essential"], "locations": ["Central & Western Area"], "categories": ["Accounting", "Accountant", "Audit", "Taxation"], "post_time": "2022-01-13T18:54:40Z", "salary": {"currency": null, "max": null, "min": null, "period": "monthly", "term": null}, "salary_visible": false, "title_keywords": ["accountant", "senior accountant"], "responsibilities": ["sme", "policies", "procedures", "audit"], "requirements": {"degrees": [], "majors": [], "languages": ["putonghua", "english", "chinese"], "language_level": ["good command"], "hard_skills": ["hong kong institute of certified public accountants", "scheme", "hkicpa"], "soft_skills": ["work under pressure", "interpersonal skill"], "languages_combined": [{"language": "putonghua", "language_level": ["good command"]}, {"language": "english", "language_level": ["good command"]}, {"language": "chinese", "language_level": ["good command"]}]}, "experience_required": {"duration": [], "field": []}}, {"job_id": "100003009046753", "location_code": "hk", "company": "BDO", "job_title": "Associate - Transfer Pricing (Ref: TAX)", "description": "Your Key Responsibilities\n\nAssist senior team members to perform various TP and tax analysis including TP planning/advisory, TP documentation, audit defense, advance pricing agreements and other related deliverables;\nAnalyze clients business activities, financial performance and intercompany transactions;\nReview data sets, and perform financial analysis using a variety of economic, statistical and sector based models or techniques;\nConduct industry and company research for clients in a range of sectors;\nClosely collaborate with TP or tax teams in HK or across the network;\nKeep abreast of OECD, global or local country TP or related tax developments.\n\nRequirements\n\n\n1 year of relevant experience in corporate tax or TP from other accounting firms and industry preferred\nCandidates with consulting, advisory, valuation, research, audit or related experience will also be strongly considered\nDegree holder, preferably major in economics, accounting, business, mathematics, finance or related disciplines\nGood command of both written and spoken English; proficiency in Mandarin is preferred\nFresh graduate will also be considered\n\nWhat We Look For\n\n\nApplicants who are dynamic, motivated and team-oriented.\nPossess strong interpersonal, organizational and communications skills and computer literate.\nInterest and proficiency in new technologies", "employment_types": ["Full Time", "Permanent"], "selling_points": ["Participate in TP projects,  conduct research", "Excellent Career Prospects", "Fresh Graduates are welcomed"], "locations": ["Sheung Wan"], "categories": ["Accounting", "Taxation", "Others"], "post_time": "2022-01-14T00:45:22Z", "salary": {"currency": null, "max": null, "min": null, "period": "monthly", "term": null}, "salary_visible": false, "title_keywords": ["associate"], "responsibilities": ["tax", "collaborate with", "data", "analysis", "review", "teams", "audit", "transactions", "financial analysis", "documentation", "business activities", "planning"], "requirements": {"degrees": ["fresh graduate", "degree holder"], "majors": ["mathematics", "finance", "economics", "related disciplines", "business", "accounting"], "languages": ["english", "mandarin"], "language_level": ["proficiency", "good command"], "hard_skills": ["dynamic"], "soft_skills": ["motivated", "organizational", "dynamic", "interpersonal"], "languages_combined": [{"language": "english", "language_level": ["good command"]}, {"language": "mandarin", "language_level": ["proficiency"]}]}, "experience_required": {"duration": ["1 year"], "field": ["research", "consulting", "related", "audit", "relevant experience", "accounting"]}}, {"job_id": "100003009051080", "location_code": "hk", "company": "Wharf China Development Limited", "job_title": "Accounts Assistant", "description": "Responsibilities:\n\nResponsible for daily accounting operations including expenses, accounts payable, general ledger\nHandle staff expenses reimbursement\nAssist in month-end closing and year-end audit\nAssist in preparing HK tax computation for related entities\nUpdate accounting reports for management\u2019s review\nAssist in other accountings duties as assigned\n\nRequirements:\n\n\nDiploma Holder or LCCI Higher with 2 - 4 years\u2019 relevant accounting experience, preferably gained in property development sector\nBasic China accounting knowledge preferred and experience in group consolidation is a definite advantage\nProficient in MS Office applications, especially in Excel and experience in using Flex accounting system is an advantage\nResponsible, proactive, detail-oriented and able to work independently and efficiently with minimum supervision\nA team player with good communication skills\nProficient in spoken and written English and Chinese (Cantonese and Putonghua\nImmediate available is an advantage\n\nWe work 5 days per week.\n\nInterested parties, please click \"APPLY NOW\" and attach with your application letter and full resume.\u00a0\n\nFor further information of the Wharf Group, please visit our website:\u00a0www.wharfholdings.com", "employment_types": ["Full Time", "Permanent"], "selling_points": [], "locations": ["Tsim Sha Tsui"], "categories": ["Accounting", "Accounting Clerk / Supervisor", "Taxation", "Others"], "post_time": "2022-01-15T01:55:26Z", "salary": {"currency": null, "max": null, "min": null, "period": null, "term": null}, "salary_visible": false, "title_keywords": ["accounts assistant"], "responsibilities": ["year-end", "management", "tax computation", "general ledger", "expenses", "review", "daily accounting operations", "audit", "month-end closing", "reports", "accounts payable"], "requirements": {"degrees": ["diploma holder"], "majors": ["accounting"], "languages": ["cantonese", "putonghua", "english", "chinese"], "language_level": ["proficient"], "hard_skills": ["excel", "flex accounting", "basic", "ms office"], "soft_skills": ["communication skills", "work independently", "responsible", "detail-oriented", "team player", "proactive"], "languages_combined": [{"language": "cantonese", "language_level": ["proficient"]}, {"language": "putonghua", "language_level": ["proficient"]}, {"language": "english", "language_level": ["proficient"]}, {"language": "chinese", "language_level": ["proficient"]}]}, "experience_required": {"duration": ["2 - 4 years"], "field": ["development", "accounting experience", "accounting", "consolidation"]}}, {"job_id": "100003009045679", "location_code": "hk", "company": "Macleans Consulting International Limited", "job_title": "Senior Tax Manager - HK Compliance", "description": "Our Vision\nWe strive to be a world class real estate investor and manager serving and improving the lives of those around us.\u00a0 To support business expansion under Vision 2025, we are seeking a high caliber talent to join our dynamic team. To learn more about Vision 2025, please visit (https://www.linkreit.com/en/ourVision/).\n\nResponsibilities\n\nBe a core member of an expanding corporate tax team\nEnsure tax compliance in various jurisdictions including HK, Mainland China, Australia and the UK\u00a0\u00a0\nAdvise and support the tax aspects of acquisitions including tax due diligence and tax structuring\nAdvise and handle tax disputes or enquiries from tax authorities\nPerform analysis on tax data such as effective tax rates and schedules of tax provision\nManage international tax for BEPS, transfer pricing, CBCR and FATCA\nManage and liaise with external tax advisors for outsourced tax services\nKeep abreast the latest domestic and international tax developments\n\nRequirements\n\nBachelor\u2019s degree in Accountancy, Finance or related disciplines\nQualified accountant of HKICPA/ACCA, additional tax qualification is a plus\nAt least 5 years of relevant post-qualification experience at supervisory level, preferably from real estate industry, property management company or Big 4 accounting firms\nHigh proficiency in MS Office, including advanced Excel functions and PowerPoint\nExcellent command of written and spoken English and Chinese\nProactive and able to work independently in a fast-paced environment\nDemonstrate ability to interact and communicate effectively at all levels\n\nRemuneration\n\nWe offer a 5-day work week and an attractive remuneration package commensurate to the right candidates with qualifications and working experience. Fringe benefits for staff include annual leave, paternity leave, birthday leave, volunteering leave, medical scheme, life insurance, Employee Unit Purchase Plan and performance-based incentives.\n\nApplication\n\nIf you resonate with Link's vision and aspire to develop a rewarding career with us, please apply by clicking \"Apply Now\".\n\nWe are an equal opportunity employer. Personal data provided by job applicants will be treated in strict confidence and used strictly in accordance with our Privacy Policy Statement for recruitment purpose only. A copy of the Statement is available on our website (Linkreit.com). Applicants not hearing from us within 6 months may consider their applications unsuccessful.", "employment_types": ["Full Time"], "selling_points": ["Hong Kong Tax Compliance focused", "Positive working environment", "Promising career development opportunity"], "locations": ["Not Specified"], "categories": ["Accounting", "Taxation"], "post_time": "2022-01-13T08:20:12Z", "salary": {"currency": null, "max": null, "min": null, "period": "monthly", "term": null}, "salary_visible": false, "title_keywords": ["manager"], "responsibilities": ["tax", "due diligence", "data", "schedules", "analysis", "compliance", "liaise with"], "requirements": {"degrees": ["degree", "bachelor"], "majors": ["related disciplines", "finance", "accountancy"], "languages": ["english", "chinese"], "language_level": ["excellent"], "hard_skills": ["excel", "acca", "plus", "powerpoint", "hkicpa", "ms office"], "soft_skills": ["fast-paced environment", "work independently", "proactive", "advanced"], "languages_combined": [{"language": "english", "language_level": ["excellent"]}, {"language": "chinese", "language_level": ["excellent"]}]}, "experience_required": {"duration": ["at least 5 years"], "field": ["management", "post-qualification", "big 4", "supervisory level", "accounting"]}}, {"job_id": "100003009054568", "location_code": "hk", "company": "Liu & Wong Certified Public Accountants", "job_title": "Audit Juniors / Seniors \u2013 Multiple Headcounts", "description": "About our client:\n\nOur client is a listed\u00a0conglomerate with business and operations globally, they are now seeking a\u00a0Senior Tax Manager\u00a0to join their tax team in Hong Kong and will be directly reporting to the VP of Global Tax.\u00a0\n\nResponsibilities & Accountabilities\n\nTo be responsible for completion of HK corporate income tax returns, including all related preparation and analysis to ensure full compliance\nTo work closely with finance and accounting team to complete Group\u2019s interim and annual reporting\nTo prepare/review HK/overseas tax enquiries to both internal and external parties\nTo provide the insights and impact to the Group regarding latest HK tax development/regulations\nTo monitor tax assessments and tax payment trends to provide insights and improvement plans\nTo provide constructive comments on business transactions to comply with company policies and prevailing tax regulation\nQualification & Experience\n\nQualified accountant\nMinimum of 8 years of\u00a0experience\u00a0with prior experience from Big 4 firms (Manager grade preferred)\nSolid experience with Hong Kong tax compliance and knowledge of Singapore tax compliance would be a plus\nFluency\u00a0in both English and Mandarin\n\nTo apply, please\u00a0click on the \u2018Apply Now\u2019 button below or contact\u00a0Eddie Suen\u00a0at (852)\u00a02566-7343\u00a0for a confidential discussion. Alternatively, email your resume (with your notice period, current and expected salary) to\u00a0eddie.suen@macleansgroup\u00a0.com\n\nYour interest will be treated in strict confidence and only shortlisted candidates will be notified.", "employment_types": ["Full Time", "Permanent"], "selling_points": ["5-day work ! Good work-life balance !", "Study and examination leaves! On-the-job training!", "Near Central MTR Station !"], "locations": ["Central"], "categories": ["Accounting", "Audit", "Taxation"], "post_time": "2022-01-17T10:01:36Z", "salary": {"currency": null, "max": null, "min": null, "period": "monthly", "term": null}, "salary_visible": false, "title_keywords": [], "responsibilities": ["tax", "reporting", "regulations", "provide insights", "operations", "analysis", "compliance", "review", "internal and external parties", "monitor", "comments", "transactions", "policies", "payment", "contact", "plans", "interim and annual reporting"], "requirements": {"degrees": [], "majors": [], "languages": ["english", "mandarin"], "language_level": ["fluency"], "hard_skills": ["analysis", "plus"], "soft_skills": ["confidence", "constructive", "responsible"], "languages_combined": [{"language": "english", "language_level": ["fluency"]}, {"language": "mandarin", "language_level": ["fluency"]}]}, "experience_required": {"duration": ["minimum of 8 years"], "field": ["compliance", "big 4"]}}, {"job_id": "100003009051656", "location_code": "hk", "company": "Art-Ko Far East Limited", "job_title": "FINANCE MANAGER", "description": "Our client is a very well known and sizable Design & Creative company in Hong Kong and they are currently seeking for a Senior Tax Accountant with 3-8 years of US Tax experience to join their team to handle US tax matters . If you are a candidate who is hoping for a stable yet challenging career, here is your chance!\n\nClient Details\n\nOur client is one of largest creativity companies in Hong Kong . They are now seeking for a high potential US Tax candidate to join their team. They are looking for an international tax passionate individual. Candidates with CPA qualification or not are also welcomed\n\nDescription\n\nGroup Tax filing. Providing Tax advices to regional partners and stakeholders\nFamiliar with US tax or other APAC regional tax standard\nTax research and analysis, also updating the changes of all region's tax regulations\nUS Tax planning and implementation\n\nProfile\n\nDegree in Accounting, Finance or a related discipline\nBig 4 or 2nd tier CPA Trained. 3-8 years of experiences within Tax\nGood command of written and spoken English\nGood team player, detail-oriented and responsible\n\nJob Offer\n\nCareer development opportunities\nSizable company\nVery stable working environment\n\nTo apply online please click the 'Apply' button below. For a confidential discussion about this role please contact Sunny Chan on +852 3602 2466.", "employment_types": ["Full Time", "Permanent"], "selling_points": [], "locations": ["Shatin Area"], "categories": ["Accounting", "Finance / Accounting Manager", "Taxation", "Others"], "post_time": "2022-01-16T21:50:31Z", "salary": {"currency": null, "max": null, "min": null, "period": "monthly", "term": null}, "salary_visible": false, "title_keywords": ["finance manager"], "responsibilities": ["tax", "regulations", "analysis", "tax filing", "implementation", "design", "contact", "career development", "tax matters", "planning"], "requirements": {"degrees": ["degree"], "majors": ["finance", "accounting"], "languages": ["english"], "language_level": ["good command"], "hard_skills": ["cpa", "analysis"], "soft_skills": ["passionate", "good team player", "responsible", "detail-oriented", "stable", "creative"], "languages_combined": [{"language": "english", "language_level": ["good command"]}]}, "experience_required": {"duration": ["3-8 years"], "field": ["design", "team"]}}, {"job_id": "100003009052866", "location_code": "hk", "company": "Union Link CPA Limited", "job_title": "Audit Supervisor/ Senior/ Semi-Senior", "description": "\u2022\u00a0\u00a0 Diploma or Degree Holder in Accounting or related discipline.\n\n\u2022\u00a0\u00a0 At least 5 years accounting experience with minimum 3 years at the managerial level.\n\n\u2022\u00a0\u00a0 Hands-on experience of PRC accounting and taxation; familiar with HK & PRC Laws,\n\n\u2022\u00a0\u00a0 Accounting and taxation matters.\n\n\u2022\u00a0\u00a0 Handle all HR, administration duties, management reporting, budgeting & forecasting,\n\n\u2022\u00a0\u00a0 Review business performance, and ad-hoc projects as assigned.\n\n\u2022\u00a0\u00a0 Liaise with external auditors, bankers & MPF provider.\n\n\u2022\u00a0\u00a0 Good command in spoken and written English & Mandarin\n\n\u2022\u00a0\u00a0 Detail-oriented, well-organized and hardworking with strong sense of responsibility\n\n\u2022\u00a0\u00a0 Immediate availability or short notice is a must.\n\nWe offer medical and bonus scheme. Interested parties please send your resume with expected\nsalary to Mr Tse by clicking \"Apply Now\",\n\nPersonal data collected will be used for recruitment purpose only.\n", "employment_types": ["Full Time", "Permanent"], "selling_points": ["Work/ Life balance", "NO OT culture/ No overseas travelling", "5-day work (9:30 am to 6:00 pm)"], "locations": ["Wan Chai"], "categories": ["Accounting", "Audit", "Taxation"], "post_time": "2022-01-17T06:33:11Z", "salary": {"currency": null, "max": null, "min": null, "period": "monthly", "term": null}, "salary_visible": false, "title_keywords": ["audit supervisor"], "responsibilities": ["taxation", "mpf", "budgeting", "hr", "review", "external auditors", "management reporting", "liaise with", "ad-hoc projects", "forecasting", "administration"], "requirements": {"degrees": ["diploma", "degree holder"], "majors": ["accounting"], "languages": ["english", "mandarin"], "language_level": ["good command"], "hard_skills": ["prc accounting"], "soft_skills": ["sense of responsibility", "well-organized", "detail-oriented", "hands-on", "hardworking"], "languages_combined": [{"language": "english", "language_level": ["good command"]}, {"language": "mandarin", "language_level": ["good command"]}]}, "experience_required": {"duration": ["at least 5 years", "minimum 3 years"], "field": ["managerial", "accounting experience", "accounting"]}}, {"job_id": "100003009054121", "location_code": "hk", "company": "Vincent W M Lai & Co", "job_title": "Audit Junior / Intermediate (5-days work)", "description": "At least 3 year's audit experience\nMember/ Finalist of HKICPA/ACCA preferable\nGood organizational skills with the ability to handle multi-tasks and meet deadlines\nA high degree of independence, motivation and technical ability\nCandidate with less experience will be considered as Audit Semi-Senior\nWe offer the right candidates with a competitive remuneration package including study & examination leaves, birthday leave, 12-14 annual leaves, casual Friday and performance bonus.\n\n\nThe salary offered will commensurate with the experience and qualifications of the right candidates. Please send your full resume with expected salary to us by clicking \"APPLY NOW\".", "employment_types": ["Full Time", "Permanent"], "selling_points": [], "locations": ["Central"], "categories": ["Accounting", "Accountant", "Audit", "Taxation"], "post_time": "2022-01-17T08:28:24Z", "salary": {"currency": null, "max": null, "min": null, "period": "monthly", "term": null}, "salary_visible": false, "title_keywords": ["junior"], "responsibilities": ["audit"], "requirements": {"degrees": ["degree"], "majors": [], "languages": [], "language_level": [], "hard_skills": ["acca", "hkicpa"], "soft_skills": ["organizational skills", "meet deadlines", "multi-tasks"], "languages_combined": []}, "experience_required": {"duration": ["at least 3 year"], "field": ["audit experience", "audit"]}}, {"job_id": "100003009051578", "location_code": "hk", "company": "Vistra (Hong Kong) Limited", "job_title": "Senior Associate, Business Advisory", "description": "Requirements\n\nIVE / Diploma / Associate Degree / Degree holder in Accountancy\n1 year relevant\u00a0working experience in auditing / taxation / accounting\nCandidate with solid experience will be offered as Intermediate\nGood command of written English\nGood command of PC knowledge and MS Office\nHardworking, self-motivated and able to\u00a0work independently\n\nBenefits\n\n5-days week and medical claim\nProfessional training will be provided\nOffer Study & Exam Leaves for recognized professional exam\nOvertime pay\n\nInterested parties please email your full resume with expected salary by clicking \"Apply Now\"\u00a0 of Vincent W M Lai & Co.\n\nPersonal data collected will be used for recruitment purposes only", "employment_types": ["Full Time", "Permanent"], "selling_points": ["Provide business advisory service to fund clients", "FATCA / CRS knowledge & experience is required", "Opportunity to work in a professional service firm"], "locations": ["Causeway Bay"], "categories": ["Accounting", "Taxation", "Banking / Finance", "Financial Services", "Professional Services", "Legal & Compliance"], "post_time": "2022-01-16T11:50:59Z", "salary": {"currency": null, "max": null, "min": null, "period": "monthly", "term": null}, "salary_visible": false, "title_keywords": ["senior associate"], "responsibilities": ["taxation", "auditing"], "requirements": {"degrees": ["associate degree", "diploma", "degree holder"], "majors": ["accountancy"], "languages": ["english"], "language_level": ["good command"], "hard_skills": ["pc knowledge", "ms office"], "soft_skills": ["self-motivated", "work independently", "hardworking"], "languages_combined": [{"language": "english", "language_level": ["good command"]}]}, "experience_required": {"duration": ["1 year"], "field": ["accounting", "relevant working experience"]}}, {"job_id": "100003009046392", "location_code": "hk", "company": "Wheelock Properties (Hong Kong) Ltd", "job_title": "Accountant", "description": "Handle day-to-day FATCA/CRS work including registration and annual report for fund clients\nLiaise with external clients and other business units of the Group in relation to FATCA/CRS matters\u00a0\nOversee work completed by junior staff and provide guidance as needed\nKeep abreast of the statutory FATCA/CRS requirements and provide update within the group to the clients where appropriate\nBasic offshore fund advisory regulatory work\nPerform any ad hoc responsibilities as required\n\nRequirements:\n\nDegree in accounting, economics, law, or related disciplines\n2 years relevant working experiences in financial services industry\nKnowledge in FATCA/CRS regulations is a must\nExcellent in communications and interpersonal skills\nAbility to work independently, dedicated, and self-motivated\nAble to work under pressure in meeting deadlines\nFast learning and good research skills\nMicrosoft Office applications, especially with Word, Excel\nInternet applications e.g. Internet Explorer, Microsoft Outlook and Outlook Express, etc.\nProficiency level in Mandarin and English (Cantonese will be a plus)\nWe offer an attractive package with benefits for the right candidate and long term career prospect.\n\n\nPersonal data collected will be used for recruitment purpose only.\n\nOnly shortlisted candidates will be contacted and all applications will be treated in strict confidence.", "employment_types": ["Full Time", "Permanent"], "selling_points": [], "locations": ["Central"], "categories": ["Accounting", "Accountant", "Accounting Clerk / Supervisor", "Taxation"], "post_time": "2022-01-13T18:55:18Z", "salary": {"currency": null, "max": null, "min": null, "period": null, "term": null}, "salary_visible": false, "title_keywords": ["accountant"], "responsibilities": ["ad hoc responsibilities"], "requirements": {"degrees": ["degree"], "majors": ["related disciplines", "economics", "accounting", "law"], "languages": ["cantonese", "english", "mandarin"], "language_level": ["proficiency"], "hard_skills": ["crs", "excel", "plus", "microsoft office", "fatca", "word", "outlook"], "soft_skills": ["work independently", "self-motivated", "research skills", "learning", "interpersonal skills", "work under pressure"], "languages_combined": [{"language": "cantonese", "language_level": ["proficiency"]}, {"language": "english", "language_level": ["proficiency"]}, {"language": "mandarin", "language_level": ["proficiency"]}]}, "experience_required": {"duration": ["2 years"], "field": ["financial services industry"]}}, {"job_id": "100003009049966", "location_code": "hk", "company": "InfoTech Services (HK) Limited", "job_title": "Deputy Accountant / Accounts Officer", "description": "Responsibilities:\n\n\nSupervise a small team for providing comprehensive accounting services and support\nReview full set of accounts including accounts receivable, accounts payable, general ledger and month-end reports\nPrepare consolidated financial statements & management schedules, annual budget, regular forecasts and analysis reports\nPrepare cash flow projection\nHandle tax computation and related matters\nAssist in annual audit and tax computation\nHandle ad hoc tasks as assigned\nRequirements:\n\nDegree in Accounting/Finance or related disciplines\nQualified accountant with at least 6 years\u2019 relevant experience gained from international professional accounting firm or sizeable commercial organizations\nSound accounting and taxation knowledge, familiar with latest accounting standards\nCapable of handling full set of financial books and management reports independently\nExperience in property development industry will be an advantage\nCan work under tight deadlines and pressure\nEnjoy teamwork, highly organized, detail-oriented and with good analytical, interpersonal & communication skills\nStrong in Excel, Word and knowledge of Oracle or other ERP systems\nGood command of written English is essential\nWe offer ample opportunities for career development and attractive salary package commensurate with experience and qualifications. \u00a0Interested parties please apply with full resume via\u00a0\u201cAPPLY NOW\u201d.\u00a0\n\n\nFor further information on Wheelock Properties (Hong Kong) Limited, please visit our website:\u00a0www.wheelockpropertieshk.com.\n\nWe are an equal opportunities employer and invite applications from all qualified candidates. Personal data collected will be treated in strict confidence and handled by authorized persons for recruitment-related purposes only within The Wheelock & Wharf Group. Applicants not hearing from us within 2 months may consider their applications unsuccessful.\u00a0", "employment_types": ["Full Time", "Permanent"], "selling_points": ["Admiralty, 13 month salaries, performance bonus", "full set of books, PRC subsidiary consolidation", "book-keeping, payroll, PRC accounts, AR management"], "locations": ["Admiralty"], "categories": ["Accounting", "Accounting Clerk / Supervisor", "Audit", "Taxation"], "post_time": "2022-01-15T03:50:46Z", "salary": {"currency": null, "max": null, "min": null, "period": "monthly", "term": null}, "salary_visible": false, "title_keywords": ["accountant", "accounts officer"], "responsibilities": ["management", "tax computation", "accounts receivable", "annual audit", "schedules", "general ledger", "analysis reports", "review", "full set of accounts", "month-end", "financial statements", "budget", "ad hoc tasks", "cash flow", "reports", "accounts payable"], "requirements": {"degrees": ["degree"], "majors": ["related disciplines", "finance", "accounting"], "languages": ["english"], "language_level": ["good command"], "hard_skills": ["excel", "erp systems", "word", "management reports", "oracle"], "soft_skills": ["organized", "communication skills", "independently", "capable", "teamwork", "detail-oriented", "interpersonal"], "languages_combined": [{"language": "english", "language_level": ["good command"]}]}, "experience_required": {"duration": ["at least 6 years"], "field": ["commercial", "development", "accounting", "relevant experience"]}}, {"job_id": "100003009052823", "location_code": "hk", "company": "Morgan Half International (Hong Kong) Limited", "job_title": "Audit manager / Audit senior / Audit Junior (2nd Tiers and local CPA firms) - Multiple headcounts", "description": "Duties:\n\nHandle book-keeping for full set of books, payroll and MPF processing, leave register for hundreds of staff, accounts receivable and cash management, PRC accounts consolidation, financial and taxation reports, etc.\nEnsure period-end closing activities to be completed in a timely manner;\nParticipate in project accounts, forecast and management accounts assignments;\nPerform company secretarial tasks;\nPerform business correspondence, internal control and ad hoc assignments.\n\n\u00a0Requirements:\n\nBachelor/Higher Diploma or above in Accounting or related disciplines;\nAt least 2 years' work experience in commercial accounts or audit fields; more experienced with the right calibre may be considered as Deputy Accountant;\nGood command of written English; fast and accurate Chinese data-entry and Putonghua preferred;\nFamiliar with PRC accounting and taxation related regulations and practices is a distinctive advantage;\nGood at MS Office and Internet, etc. Habit of logically organizing Windows files and folders;\nMature, energetic and able to work independently.\u00a0\n\nWe offer competitive remuneration, self- and spouse group medical covering out-patient, in-patient, dental, Chinese medicine practitioner,\u00a0bank holidays,\u00a0decent Grade A work environment in Admiralty.", "employment_types": ["Full Time", "Temporary"], "selling_points": ["Multiple CPA firm headcounts", "Good package", "5 working days"], "locations": ["Not Specified"], "categories": ["Accounting", "Accountant", "Audit", "Taxation"], "post_time": "2022-01-17T04:10:47Z", "salary": {"currency": null, "max": null, "min": null, "period": "monthly", "term": null}, "salary_visible": false, "title_keywords": ["manager", "junior"], "responsibilities": ["taxation", "management", "mpf", "accounts receivable", "a timely manner", "book-keeping", "reports", "forecast", "ad hoc assignments", "payroll", "internal control"], "requirements": {"degrees": ["higher diploma or above", "bachelor"], "majors": ["related disciplines", "accounting"], "languages": ["putonghua", "english", "chinese"], "language_level": ["good command"], "hard_skills": ["ms office", "prc accounting"], "soft_skills": ["work independently", "accurate", "mature", "patient", "energetic"], "languages_combined": [{"language": "putonghua", "language_level": []}, {"language": "english", "language_level": ["good command"]}, {"language": "chinese", "language_level": []}]}, "experience_required": {"duration": ["at least 2 years"], "field": ["commercial", "audit"]}}, {"job_id": "100003009047408", "location_code": "hk", "company": "Tai Hing Catering Group Limited", "job_title": "Accountant", "description": "Multiple headcounts:\n\nWe are now helping multiple CPA firms (Including 2nd Tiers and local CPA firms) looking for audit and technical staffs. No matter you are looking for work life balance or listed company audit exposure or even financial institutions audit exposure, we have jobs referral to you. Currently, we have positions ranging from audit junior to audit senior manager position and technical manager positions. If you are looking forward to any job opportunities in CPA firms, please kindly submit your profile to us and we will get back to you ASAP.\u00a0\n\nRequirements:\n\nBachelor degree holder\nGood team player\nWelcome fresh graduate / experienced audit candidates\u00a0\n\nTo apply online, please press \"Apply Now\" button below. For any inquiries, please email info @morganhalf.com", "employment_types": ["Full Time", "Permanent"], "selling_points": [], "locations": ["Quarry Bay"], "categories": ["Accounting", "Accountant", "Financial Analyst", "Taxation"], "post_time": "2022-01-14T03:01:21Z", "salary": {"currency": null, "max": null, "min": null, "period": "monthly", "term": null}, "salary_visible": false, "title_keywords": ["accountant"], "responsibilities": ["audit"], "requirements": {"degrees": ["fresh graduate", "bachelor degree holder"], "majors": [], "languages": [], "language_level": [], "hard_skills": ["cpa", "no"], "soft_skills": ["good team player"], "languages_combined": []}, "experience_required": {"duration": [], "field": []}}, {"job_id": "100003009046393", "location_code": "hk", "company": "Wheelock Properties (Hong Kong) Ltd", "job_title": "Senior Accountant", "description": "Requirements:\n\nDiploma or Degree holder in Accountancy;\n0-3 years experience in audit firm\nGood communication skills in both English and Putonghua;\nExcellent organizational skills, high accuracy and able to meet tightening deadline and ad hoc assignment ;\nResponsible and independent;\nWilling to learn and hardworking;\u00a0and\nPunctual, neat and tidy\u00a0\n\nWe offer\u00a0competitive remuneration package and excellent career prospects to the right candidate including 5-day work.\n\nCandidates should send their application letter, full C.V. with current and expected salary and date of availability\u00a0to us by clicking \"APPLY NOW\u201d for arrangement of an interview. (Please state clearly the position you are applying for)", "employment_types": ["Full Time", "Permanent"], "selling_points": [], "locations": ["Central"], "categories": ["Accounting", "Accountant", "Accounting Clerk / Supervisor", "Taxation"], "post_time": "2022-01-13T18:55:18Z", "salary": {"currency": null, "max": null, "min": null, "period": null, "term": null}, "salary_visible": false, "title_keywords": ["senior accountant"], "responsibilities": ["communication", "ad hoc assignment", "audit"], "requirements": {"degrees": ["diploma", "degree holder"], "majors": ["accountancy"], "languages": ["putonghua", "english"], "language_level": ["good"], "hard_skills": [], "soft_skills": ["communication skills", "organizational skills", "independent", "responsible", "willing to learn", "hardworking"], "languages_combined": [{"language": "putonghua", "language_level": ["good"]}, {"language": "english", "language_level": ["good"]}]}, "experience_required": {"duration": ["0-3 years"], "field": ["audit"]}}, {"job_id": "100003009036579", "location_code": "hk", "company": "Puma Asia Pacific Limited", "job_title": "Manager, Tax APC", "description": "Responsibilities:\n\n\nSupervise a small team for providing comprehensive accounting services and support\nPrepare consolidated financial & management financial statements of a listed company, annual budget, regular forecast and relevant reports\nReview cash flow projection\nAssure tax compliance\nHandle ad hoc tasks as assigned\n\nRequirements:\n\n\nDegree in Accounting/Finance or related disciplines\nQualified accountant with at least 8 years\u2019 relevant experience gained from international professional accounting firm and sizeable commercial organizations\nSound accounting and taxation knowledge, familiar with latest accounting standards and Listing Rules\nCapable of handling full set of financial books and management reports independently\nCan work under tight deadlines and pressure\nEnjoy team work and with experience in supervising a small team\nHighly organized, detail-oriented and with good analytical, interpersonal & communication skills\nStrong in Excel, knowledge of Flex system\nHigh proficiency in written and spoken English and Chinese\n\nWe offer ample opportunities for career development and attractive salary package commensurate with experience and qualifications. \u00a0Interested parties please apply with full resume via\u00a0\u201cAPPLY NOW\u201d.\u00a0\n\nFor further information on Wheelock Properties (Hong Kong) Limited, please visit our website:\u00a0www.wheelockpropertieshk.com.\n\nWe are an equal opportunities employer and invite applications from all qualified candidates. Personal data collected will be treated in strict confidence and handled by authorized persons for recruitment-related purposes only within The Wheelock & Wharf Group. Applicants not hearing from us within 2 months may consider their applications unsuccessful.\u00a0", "employment_types": ["Full Time", "Permanent"], "selling_points": ["Support businesses in managing tax audits", "Manage and provide support to business projects", "Minimum 5 years of experience"], "locations": ["Not Specified"], "categories": ["Accounting", "Taxation", "Others"], "post_time": "2022-01-10T11:12:07Z", "salary": {"currency": null, "max": null, "min": null, "period": "monthly", "term": null}, "salary_visible": false, "title_keywords": ["manager"], "responsibilities": ["tax", "relevant reports", "management", "budget", "review", "compliance", "financial statements", "ad hoc tasks", "cash flow", "forecast"], "requirements": {"degrees": ["degree"], "majors": ["related disciplines", "finance", "accounting"], "languages": ["english", "chinese"], "language_level": ["proficiency"], "hard_skills": ["small", "excel", "management reports", "flex system"], "soft_skills": ["organized", "communication skills", "independently", "capable", "detail-oriented", "interpersonal"], "languages_combined": [{"language": "english", "language_level": ["proficiency"]}, {"language": "chinese", "language_level": ["proficiency"]}]}, "experience_required": {"duration": ["at least 8 years"], "field": ["commercial", "accounting", "relevant experience", "team"]}}, {"job_id": "100003009040825", "location_code": "hk", "company": "Emperor Group", "job_title": "Tax Manager", "description": "SPEED & SPIRIT is what we look for in our candidates, defined by some simple values that inspire us to BE DRIVEN in our performance, BE VIBRANT in our sporting legacy, BE TOGETHER in our team spirit, and BE YOU to let our individual talent and experience shine. Applying for a job at PUMA is easy and all genders are welcome. Simply click APPLY ONLINE and follow the steps to upload your application.\nSupport businesses in implementing and maintaining tax compliance controls\nPreparing and/or review local transfer pricing documentation\nSupport finance teams in preparing and/or reviewing tax provisions and corporate tax returns\nSupport businesses in managing tax audits\nManage and provide support to business projects from a tax perspective\nMinimum 5 years of experience in corporate tax and/or transfer pricing\nGood command of written and spoken English and Chinese (Mandarin and Cantonese)\nProficient in Microsoft Excel, PowerPoint and Word\nStrong analytic, communication and problem solving skills\nTaxation knowledge of multiple jurisdictions across APAC region is a plus\nProfessional qualification in accounting or taxation is a plus\nPUMA supports over 14,000 employees across 120+ countries. The PUMA Group owns the brand PUMA, Cobra Golf and stichd, and is headquartered in Herzogenaurach, Germany.\nPUMA provides equal opportunities for all job applicants, regardless of race, color, religion, national origin, sex, gender identity or expression, sexual orientation, age, or disability. Equality for all is one of the core principles at PUMA and we do not tolerate any form of harassment or discrimination.", "employment_types": ["Full Time", "Permanent"], "selling_points": ["Diverse industry exposure", "5 to 10 years of experience in tax", "Qualified member of a professional accounting body"], "locations": ["Wan Chai"], "categories": ["Accounting", "Taxation"], "post_time": "2022-01-12T03:07:10Z", "salary": {"currency": null, "max": null, "min": null, "period": null, "term": null}, "salary_visible": false, "title_keywords": ["manager"], "responsibilities": ["tax", "taxation", "provide support", "maintaining", "business projects", "review", "compliance", "teams", "audits", "communication", "documentation"], "requirements": {"degrees": [], "majors": [], "languages": ["cantonese", "english", "chinese", "mandarin"], "language_level": ["good command"], "hard_skills": ["simple", "plus", "cobra", "word", "powerpoint", "microsoft excel", "documentation", "problem solving skills"], "soft_skills": ["communication", "problem solving skills", "team spirit", "driven"], "languages_combined": [{"language": "cantonese", "language_level": ["good command"]}, {"language": "english", "language_level": ["good command"]}, {"language": "chinese", "language_level": ["good command"]}, {"language": "mandarin", "language_level": ["good command"]}]}, "experience_required": {"duration": ["minimum 5 years"], "field": ["team"]}}, {"job_id": "100003009035730", "location_code": "hk", "company": "RSM Hong Kong \u7f85\u7533\u7f8e\u6703\u8a08\u5e2b\u4e8b\u52d9\u6240", "job_title": "Manager / Seniors / Accountants, Tax Services", "description": "Responsibilities\nProvide tax advice and support to stakeholders for operational matters\nProvide tax support for M&A projects, including structuring and due diligence\nManage tax planning and implementation\nConduct tax research and analysis with reference to latest changes in tax regulations and provide an update to stakeholders\nRequirements\n\nUniversity graduate or above\nQualified member of a professional accounting body\n5 to 10 years of experience in tax\nWork experience from sizable companies is preferred\nGood command of written and spoken English and Chinese\n\nWe offer\u00a05-day work\u00a0week with competitive remuneration and benefit packages to the right candidate. Interested parties please send your application letter, resume, expected salary and availability to\u00a0Group\u00a0Human Resources Department, 28/F, Emperor Group Centre, 288 Hennessy Road, Wanchai, Hong Kong\u00a0or by fax 2835-6677\u00a0or by clicking the \"Apply Now\" button below.\n\nWe are an equal opportunity employer and welcome applications from all qualified candidates. The information provided will be treated in strict confidence and be used only for consideration of your application for relevant / similar posts within the Emperor Group. Applicants not hearing from us within four weeks from the date of advertisement may consider their applications unsuccessful. We retain the unsuccessful applications for a maximum period of 24 months.", "employment_types": ["Full Time", "Permanent"], "selling_points": [], "locations": ["Causeway Bay"], "categories": ["Accounting", "Accountant", "Audit", "Taxation"], "post_time": "2022-01-10T08:17:54Z", "salary": {"currency": null, "max": null, "min": null, "period": "monthly", "term": null}, "salary_visible": false, "title_keywords": ["manager"], "responsibilities": ["tax", "due diligence", "regulations", "analysis", "implementation", "operational matters", "planning"], "requirements": {"degrees": ["university graduate or above"], "majors": [], "languages": ["english", "chinese"], "language_level": ["good command"], "hard_skills": ["sizable companies"], "soft_skills": [], "languages_combined": [{"language": "english", "language_level": ["good command"]}, {"language": "chinese", "language_level": ["good command"]}]}, "experience_required": {"duration": ["5 to 10 years"], "field": []}}, {"job_id": "100003009046236", "location_code": "hk", "company": "BDO", "job_title": "Internship - Tax (Part-time)", "description": "Responsibilities:\u00a0\u00a0\n\nHandle Hong Kong and / or PRC tax planning and compliance engagements.\nHandle transfer pricing compliance and advisory projects or cross-border/international tax projects.\nConsistently deliver quality and timely services, and manage client portfolios.\nFacilitate open communication and assist in leading the team for supportive development and motivation.\nMaintain regular interaction with clients and manage expectations.\n\nRequirements:\u00a0\n\nHolder of recognized university bachelor degree with a minimum of 6 years of Tax experience with an international professional firm for the position of Manager. Less experienced candidates may be considered for the position of Seniors / Accountants.\nMember of HKICPA or equivalent for the position of Manager.\nStrong command of spoken and written English and Chinese (Cantonese and Mandarin).\nGood interpersonal skills and able to interact effectively with colleagues, clients and tax authorities.\nSelf-motivated with proven capabilities to meet with multiple deadlines and work under pressure.\nExcellent supervisory, analytical and presentation skills.\n\nRSM Hong Kong offers attractive rewards package to the right candidates. Applicants please send resume, quoting the\u00a0Ref. TAX,\u00a0with\u00a0full career details, availability and expected salary\u00a0to\u00a0The\u00a0Human Resources\u00a0Department, RSM Hong Kong, 29/F, Lee Garden Two, 28 Yun Ping Road, Causeway Bay, Hong Kong\u00a0or by clicking the\u00a0Apply Now\u00a0button and upload your CV.\u00a0\n\n(Data collected will be used for recruitment purpose only)", "employment_types": ["Part Time", "Temporary", "Internship"], "selling_points": ["Support preparation on tax assessments", "Able to work for 2-3 days per week", "Study Accounting, Economics related disciplines"], "locations": ["Sheung Wan"], "categories": ["Accounting", "Taxation", "Others", "Student / Fresh Graduate / No Experience"], "post_time": "2022-01-13T10:03:27Z", "salary": {"currency": null, "max": null, "min": null, "period": "hourly", "term": null}, "salary_visible": false, "title_keywords": ["internship"], "responsibilities": ["tax", "compliance", "quality", "communication", "maintain", "planning"], "requirements": {"degrees": ["degree", "bachelor"], "majors": [], "languages": ["cantonese", "english", "chinese", "mandarin"], "language_level": [], "hard_skills": ["hkicpa"], "soft_skills": ["self-motivated", "interpersonal skills", "presentation skills", "work under pressure"], "languages_combined": [{"language": "cantonese", "language_level": []}, {"language": "english", "language_level": []}, {"language": "chinese", "language_level": []}, {"language": "mandarin", "language_level": []}]}, "experience_required": {"duration": ["minimum of 6 years"], "field": []}}, {"job_id": "100003009050401", "location_code": "hk", "company": "Premier Q Securities Limited", "job_title": "Assistant/Finance & Account Manager", "description": "Job Description\n\nProvide assistance and support on the preparation and production of tax assessments, tax return and tax computation\nProvide professional services to clients and internal management\n\nSkills & Requirements\n\nUniversity student majoring in Accounting, Economics, Financial Services related disciplines\nGood interpersonal and communication skills\nImmediate available is highly preferred\nAble to work for 2-3 days per week\n\nWe are an equal opportunity employer, and offer excellent prospects and career development for the right candidate.\u00a0 Interested parties please send your application with full career history, current and expected salary by clicking Apply Now button below.\n\nApplications will be treated in strict confidence. Personal data collected will be used for recruitment purposes only.", "employment_types": ["Full Time", "Permanent"], "selling_points": [], "locations": ["Wan Chai"], "categories": ["Accounting", "Accountant", "Finance / Accounting Manager", "Taxation"], "post_time": "2022-01-14T10:19:58Z", "salary": {"currency": null, "max": null, "min": null, "period": "monthly", "term": null}, "salary_visible": false, "title_keywords": ["account manager", "assistant"], "responsibilities": ["tax", "management", "provide assistance", "tax computation"], "requirements": {"degrees": [], "majors": [], "languages": [], "language_level": [], "hard_skills": [], "soft_skills": ["communication skills", "interpersonal"], "languages_combined": []}, "experience_required": {"duration": [], "field": []}}, {"job_id": "100003009050463", "location_code": "hk", "company": "Faith Hill C.P.A. Limited", "job_title": "AUDIT STAFF - ASSOCIATES TO SENIORS  (5 days week)", "description": "Job Descriptions:\n\nResponsible for full set of account and financial reports inTypes1, 2, 4, 9 regulated activities\nPerform accounting duties such as daily cash flow, client money, segregation, bank reconciliations in compliance with the SFC/AML timely and accurately\nPrepare financial and management reports and regulatory reports in compliance with the SFC\nPerform daily monitoring and reporting of the liquid capital according to the FRR\nLiaise with external auditor and tax advisor for annual audit and tax issues\n\nJob Requirements:\n\n\nBachelor degree or above in account, finance or related disciplines\nHolder of professional qualification of CPA/ACCA\nMinimum 5 years\u2019 experience in securities firms with sound knowledge of SFC regulations and FRR\nWell-versed in Companies Ordinance, familiar with the SFC & HKEX rules and regulations\nFamiliar with Hong Kong accounting and tax regulations\nResponsible, independent, highly self-motivated, and detail minded\n\nGood command in Cantonese, English and Mandarin\n\n\u00a0\nWe offer attractive salary and fringe benefit package to the right candidate. Interested parties please send full resume to us. Personal data provided in your application will be kept in the strictest confidence. It will be used for employment-related purposes.", "employment_types": ["Full Time", "Permanent"], "selling_points": [], "locations": ["North Point"], "categories": ["Accounting", "Accountant", "Audit", "Taxation"], "post_time": "2022-01-15T03:51:07Z", "salary": {"currency": null, "max": null, "min": null, "period": "monthly", "term": null}, "salary_visible": false, "title_keywords": ["audit staff"], "responsibilities": ["tax", "reporting", "financial reports", "aml", "annual audit", "compliance", "bank reconciliations", "cash flow", "management reports", "reports", "liaise with", "accounting duties", "daily monitoring"], "requirements": {"degrees": ["degree or above", "bachelor"], "majors": ["related disciplines", "finance"], "languages": ["cantonese", "english", "mandarin"], "language_level": ["good command"], "hard_skills": ["cpa", "acca", "companies ordinance", "frr"], "soft_skills": ["self-motivated", "independent", "responsible"], "languages_combined": [{"language": "cantonese", "language_level": ["good command"]}, {"language": "english", "language_level": ["good command"]}, {"language": "mandarin", "language_level": ["good command"]}]}, "experience_required": {"duration": ["minimum 5 years"], "field": ["securities firms"]}}, {"job_id": "100003009039842", "location_code": "hk", "company": "Rise Associates Asia Limited", "job_title": "Accountant (Generalist, HK Property Developer)", "description": "Requirements:\nThree years' audit experience required for Senior to handle small to big companies' audit assisgnments / projects;\nFresh graduate / 1-2 years' audit experience for Associates;\nInitiative, team-work spirit and good inter-personal communication skill\n\nWe provide competitive salary to commensurate with audit experience.\u00a0 We also offer generous fringe benefits to the right candidates including study and examination leave etc.\n\nPlease send full resume and expected salary by email to info @fhcpa.com.hk\n\n** Office location - walking distance from MTR station **", "employment_types": ["Permanent"], "selling_points": ["Degree holder in Accountancy/Finance", "2+ yrs exp. (Big 4 experience preferred)", "Promising career prospect"], "locations": ["Not Specified"], "categories": ["Accounting", "Accountant", "Audit", "Taxation"], "post_time": "2022-01-12T11:53:43Z", "salary": {"currency": null, "max": null, "min": null, "period": "monthly", "term": null}, "salary_visible": false, "title_keywords": ["developer", "accountant"], "responsibilities": ["communication", "audit"], "requirements": {"degrees": ["fresh graduate"], "majors": [], "languages": [], "language_level": [], "hard_skills": ["small"], "soft_skills": ["communication skill", "initiative", "inter-personal"], "languages_combined": []}, "experience_required": {"duration": ["three years", "1-2 years"], "field": ["audit experience", "audit"]}}, {"job_id": "100003009046394", "location_code": "hk", "company": "Wheelock Properties (Hong Kong) Ltd", "job_title": "Accounting Manager", "description": "Our client is a well-established property developer in Hong Kong with a property portfolio consists of quality commercial and residential projects. They are now seeking a talented individual to join them as\u00a0Accountant.\u00a0\n\nJob Descriptions:\u00a0\n\nHandle daily accounting duties including data input, issue cheques, prepare bank reconciliation and vouchers\nPerform month-end closing and full set of financial statements\nPrepare auditing schedules and liaise with auditors in order to meet reporting deadlines\nManage expenses claims, organize daily schedules,\u00a0coordinate meetings, and maintain business records\u00a0\nAd-hoc projects as assigned\u00a0\n\u00a0Requirements:\u00a0\n\nDegree holder in Accountancy, Finance or related discipline\u00a0\nAt least 2 years experience\u00a0in accounting, big 4 experience preferred\nStudent member of HKICPA/ACCA\nGood communication skill, independent and proactive\nHighly sensitive to numbers, able to handle multiple tasks under a tight deadline with highly accuracy\nProficiency\u00a0in MS Office and knowledge of FlexSystem is a plus\nGood command in both written and spoken English and Chinese\nApplicants with more experience and qualifications may be considered as Senior Accountant", "employment_types": ["Full Time", "Permanent"], "selling_points": [], "locations": ["Central"], "categories": ["Accounting", "Finance / Accounting Manager", "Taxation", "Banking / Finance", "Investment"], "post_time": "2022-01-13T18:55:18Z", "salary": {"currency": null, "max": null, "min": null, "period": null, "term": null}, "salary_visible": false, "title_keywords": ["accounting manager"], "responsibilities": ["reporting", "schedules", "expenses", "data input", "bank reconciliation", "financial statements", "coordinate", "cheques", "month-end closing", "maintain", "liaise with", "daily accounting", "ad-hoc projects", "auditing"], "requirements": {"degrees": ["degree holder"], "majors": ["finance", "accountancy"], "languages": ["english", "chinese"], "language_level": ["good command"], "hard_skills": ["acca", "plus", "flexsystem", "hkicpa", "ms office"], "soft_skills": ["independent", "communication skill", "handle multiple tasks", "sensitive to numbers", "proactive"], "languages_combined": [{"language": "english", "language_level": ["good command"]}, {"language": "chinese", "language_level": ["good command"]}]}, "experience_required": {"duration": ["at least 2 years"], "field": ["accounting", "big 4", "senior accountant"]}}, {"job_id": "100003009039667", "location_code": "hk", "company": "Michael Page", "job_title": "Tax Manager, Family Office, 80k", "description": "Responsibilities\n\nOversee accounting functions of a group of property development companies to ensure statutory compliance\nSupervise a team in preparation of management and consolidated financial reports, cash flow forecast, budgeting and analysis etc\nProvide tax advisory and support to the business\nProvide support, bring insights and lead the team to work on the continuous process improvements, digitalization and automation initiatives\n\nRequirements:\n\nDegree in Accounting/Finance or related discipline\nQualified member of HKICPA/ACCA or related professional qualifications\nAt least 10 years\u2019 relevant experience with both commercial (preferably listed companies) and Big 4 professional firm experience \u00a0\nSolid experience in managing\u00a0consolidated accounts, financial analysis and management reporting\nGood knowledge in Accounting\u00a0and\u00a0Taxation\nStrong sense of responsibility, able to work under pressure and manage tight timeline\nStrong analytic\u00a0mind, well-organized and detail-oriented\nGood leadership and communication skills\nProficiency in MS Office, especially Excel; familiar with\u00a0ERP systems and automation tools\nHigh proficiency in written and spoken English and Chinese\n\nWe offer ample opportunities for career development and attractive salary package commensurate with experience and qualifications. \u00a0Interested parties please apply with full resume via\u00a0\u201cAPPLY NOW\u201d.\u00a0\u00a0\u00a0\u00a0\u00a0\n\nFor further information on Wheelock Properties (Hong Kong) Limited, please visit our website: www.wheelockpropertieshk.com\n\nWe are an equal opportunities employer and invite applications from all qualified candidates. Personal data collected will be treated in strict confidence and handled by authorized persons for recruitment-related purposes only within the Wheelock & Wharf Group. Applicants not hearing from us within two months may consider their applications unsuccessful.", "employment_types": ["Full Time", "Permanent"], "selling_points": ["Big 4 Tax/Tax candidates are welcome!", "Prefer stable candidates", "Well-established family office"], "locations": ["Not Specified"], "categories": ["Accounting", "Audit", "Taxation", "Others"], "post_time": "2022-01-11T10:25:26Z", "salary": {"currency": null, "max": null, "min": null, "period": "monthly", "term": null}, "salary_visible": false, "title_keywords": ["manager"], "responsibilities": ["tax", "management", "financial reports", "provide support", "statutory compliance", "budgeting", "analysis", "cash flow", "forecast"], "requirements": {"degrees": ["degree"], "majors": ["finance", "accounting"], "languages": ["english", "chinese"], "language_level": ["proficiency"], "hard_skills": ["excel", "acca", "erp systems", "professional qualifications", "financial analysis", "hkicpa", "ms office"], "soft_skills": ["communication skills", "sense of responsibility", "well-organized", "detail-oriented", "leadership", "work under pressure"], "languages_combined": [{"language": "english", "language_level": ["proficiency"]}, {"language": "chinese", "language_level": ["proficiency"]}]}, "experience_required": {"duration": ["at least 10 years"], "field": ["management", "big 4", "commercial", "relevant experience", "financial"]}}, {"job_id": "100003009038980", "location_code": "hk", "company": "SHINEWING Tax And Business Advisory Limited", "job_title": "Senior Accountant/ Staff Accountant - Tax Advisory Services", "description": "Our client is a reputable family office. They are now looking for a talent Tax Manager to join their team.\n\nClient Details\n\nOur client is a reputable family office. They are now looking for a talent Tax Manager to join their team.\n\nDescription\n\nReporting to the GM, you will be\n\nan individual contributor\npreparing management reporting and performing various analyses and planning\nperforming compliance and tax issues\nperforming other adhoc tasks when necessary\n\nProfile\n\nDegree Holder in Business/Accounting/Finance\n10 Years of Tax Experience is a must\nCPA qualification is a must\nExcellent communication skills (English and Mandarin)\n\nJob Offer\n\nCompetitive remuneration\nFast and dynamic business growth\nReputable company\n\nTo apply online please click the 'Apply' button below.\nFor a confidential discussion about this role please contact Nicole Hui on +852 3412 4832.", "employment_types": ["Full Time", "Permanent"], "selling_points": ["Assist in tax research, data analysis", "Strong communication & interpersonal skills", "Fresh graduate will be considered"], "locations": ["Causeway Bay"], "categories": ["Accounting", "Taxation"], "post_time": "2022-01-11T08:18:19Z", "salary": {"currency": null, "max": null, "min": null, "period": "monthly", "term": null}, "salary_visible": false, "title_keywords": ["staff accountant", "senior accountant"], "responsibilities": ["tax", "reporting", "compliance", "communication", "management reporting", "contact", "planning"], "requirements": {"degrees": ["degree holder"], "majors": ["finance", "business", "accounting"], "languages": ["english", "mandarin"], "language_level": ["excellent"], "hard_skills": ["cpa", "gm", "dynamic"], "soft_skills": ["communication skills", "dynamic"], "languages_combined": [{"language": "english", "language_level": ["excellent"]}, {"language": "mandarin", "language_level": ["excellent"]}]}, "experience_required": {"duration": ["10 years"], "field": []}}, {"job_id": "100003009040743", "location_code": "hk", "company": "ConnectedGroup Limited", "job_title": "Senior Tax Manager (Global Tax)", "description": "RESPONSIBILITIES:\n\n\nAssist in tax research, fact-finding, data analysis and organization\nAssist in preparing PRC, HK and multinational tax compliance and advisory work to clients\n\nREQUIREMENTS:\n\n\nBachelor degree in accounting or business related disciplines;\nExcellent command of spoken and written English and Chinese (Fluency in Mandarin will be an advantage);\nStrong communication & interpersonal skills; and\nAble to meet deadlines and under time pressure.\nCandidate with more experience will be considered as a senior position.\nFresh graduates are also welcome.\n\n\u00a0Personal data collected will be used for recruitment purpose only.\u00a0\n\n\u00a0www.shinewing.hk", "employment_types": ["Full Time", "Permanent"], "selling_points": ["Key member of the business", "A leading company in the industry", "Attractive package with promising career prospect"], "locations": ["Not Specified"], "categories": ["Accounting", "Audit", "Taxation", "Others"], "post_time": "2022-01-12T03:00:37Z", "salary": {"currency": null, "max": null, "min": null, "period": "monthly", "term": null}, "salary_visible": false, "title_keywords": ["manager"], "responsibilities": ["tax", "compliance", "data analysis"], "requirements": {"degrees": ["degree", "bachelor"], "majors": ["business", "related disciplines", "accounting"], "languages": ["english", "chinese", "mandarin"], "language_level": ["fluency", "advantage", "excellent"], "hard_skills": [], "soft_skills": ["communication", "meet deadlines", "interpersonal skills"], "languages_combined": [{"language": "english", "language_level": ["fluency", "advantage", "excellent"]}, {"language": "chinese", "language_level": ["fluency", "advantage", "excellent"]}, {"language": "mandarin", "language_level": ["fluency", "advantage", "excellent"]}]}, "experience_required": {"duration": [], "field": []}}, {"job_id": "100003009037829", "location_code": "hk", "company": "Gary Cheng CPA Limited", "job_title": "Manager/ Supervisor, Tax & Advisory", "description": "Senior Tax Manager (Global Tax)\n\nOur client is a conglomerate business with global operation. They are now looking for a talented and driven individual to join its growing Tax team.\n\nPosition Responsibilities\n\nLeading both the Tax Compliance and Tax Consulting and Planning of the team:\n\nTax Consulting and Planning\n\nProvide regular updates to the top management on the changes of tax regulations in the tax jurisdictions in which the group has presence\nProvide recommendations to the top management on any businesses which may have tax implication depending on the options chosen and propose mitigation plan/other options, if any\nProvide guidance to the top management on the priority of several of tax tasks and allocation of resources.\nProvide tax advices and supports to the commercial teams to effectively manage the tax expenses and disputes\nEnsure the Effective Tax Rate is carefully managed within a reasonable range\nSuggest and lead optimization projects to balance business and tax efficiency\nWork with the Treasury VP with tax exposure related to all the treasury transactions\n\nTax Compliance\n\nResponsible for completion of Hong Kong and international income tax returns including all related analysis and support\nOversee processing of economic transactions complying with company policies and prevailing tax regulations\nEnsure enough resources are being allocated and prioritize the resources to ensure all deadlines are met.\nManage the tax filing and reporting to minimize the occurrence of tax controversies\nEnsuring that appropriate internal controls are in place over accounting for income taxes.\nManage and oversee direct, indirect taxes (routine exposure assessment), other tax filings\nPrepare/review tax enquiries to both internal and external parties to ensure full compliance.\nMonitor tax assessments and tax payment trends\nPerform tax health-check exercises and lead improvement/optimization plans\n\nOther Tax-related duties:\n\nPropose strategies and be responsible and defend any audits of the companies' tax returns\nPrepare TP policy set and perform implementation\nManage tax work automation (e.g. Playstation / automate tax work paper using BW query)\n\nPosition Requirements\n\nBachelor's Degree in Qualified / Chartered Accountant or equivalent\nAt least 8 years of relevant tax experience in which at least 2 years at a manager level in Corporate Income Tax / Indirect Taxes, preferably gained in tax practices of Big 4 accounting firms, international law firms, Inland Revenue, consultant firms or commercial tax practices in large MNCs or local listed companies etc.\nExperiences in tax compliance and consulting of International Tax\nKnowledge of major Direct Tax of Asia Pacific countries (covering Japan)\nStrong project management, research, analytical and presentation skills\nGood written and spoken English and Chinese (Cantonese and Mandarin)\nProficiency in Microsoft Word, Excel and PowerPoint\n\nInterested individuals can apply now and send CV to Vivian Wong, or call +852 3972 5831 for more information. Only relevant candidates will be contacted\n\nFor a more comprehensive list of our vacancies, please visit: www.connectedgroup.com", "employment_types": ["Full Time", "Permanent"], "selling_points": ["Degree holder in Accounting or equivalent", "Work independently with project ownership mindset", "3 years+ experience, able to make recommendations"], "locations": ["Kwun Tong"], "categories": ["Accounting", "Audit", "Taxation", "Professional Services", "Business Consultancy"], "post_time": "2022-01-11T03:59:43Z", "salary": {"currency": null, "max": null, "min": null, "period": "monthly", "term": null}, "salary_visible": false, "title_keywords": ["manager", "supervisor"], "responsibilities": ["regulations", "consulting", "internal and external parties", "transactions", "payment", "plan", "plans", "compliance", "teams", "expenses", "tax filing", "monitor", "implementation", "reporting", "management", "review", "provide recommendations", "audits", "provide guidance", "tax", "policies", "analysis", "planning"], "requirements": {"degrees": ["degree", "bachelor"], "majors": [], "languages": ["cantonese", "english", "chinese", "mandarin"], "language_level": ["good"], "hard_skills": ["powerpoint", "project management", "microsoft word", "excel"], "soft_skills": ["project management", "presentation skills", "comprehensive"], "languages_combined": [{"language": "cantonese", "language_level": ["good"]}, {"language": "english", "language_level": ["good"]}, {"language": "chinese", "language_level": ["good"]}, {"language": "mandarin", "language_level": ["good"]}]}, "experience_required": {"duration": ["at least 8 years", "at least 2 years"], "field": ["consulting", "compliance", "big 4", "commercial", "accounting"]}}, {"job_id": "100003009043522", "location_code": "hk", "company": "Prestige CPA Limited", "job_title": "Senior Associate / Associate - Assurance", "description": "You will experience in:\n\nProvide HK Tax advisory services and compliance for variety of clients, including HK domestic and foreign corporations, partnerships and other business entities\nPrepare tax proposal to clients on Taxation advisory and compliance work\nInvolve in cross-border tax exercises, including holding structures, restructuring exercises, M&A and other tax-related projects.\nLiaise with IRD and assist clients to organize their business from a tax-efficient perspective.\nBuild client relationships and demonstrate understanding to client\u2019s business situation\n\nDesire skills and experience:\n\nDiploma / Degree holder in Accountancy or equivalent\nMinimum 3-5 years of experience from professional firm/ IRD/ commercial tax environment\nAble to make recommendation based on assessment, findings and information gathered\nStrong business awareness, good analytical skills and good interpersonal skills as a team player are essential\nIndependent to work under tight timeline or pressure with a strong sense of project ownership\nExcellent command of both verbal and written English, Chinese and Putonghua\nCandidate with less experience will be considered as Supervisor level\nRemuneration and benefits:\n\n5-days work\nCompetitive salary package\nDiscretionary year-end bonus and medical benefits\nAnnual Leave, Birthday Leave, Exam and Study Leave\nExcellent career development and training\n\nAt Gary Cheng Consultants Limited, we offer a supportive working environment where enables you to grow and succeed professionally.\u00a0\n\nInterested parties please send a full resume indicating with your present, expected salary package and earliest date available by clicking \"Apply Now\".\n\nThe information provided will be treated in strict confidence & be used only for consideration of your application. We may retain the unsuccessful applications for a maximum period of 24 months.", "employment_types": ["Full Time", "Permanent"], "selling_points": ["Accounting, auditing and tax", "5-day work; medical benefit; study and exam leave", "No overtime work and travelling is expected"], "locations": ["Tsim Sha Tsui"], "categories": ["Accounting", "Accounting Clerk / Supervisor", "Audit", "Taxation"], "post_time": "2022-01-12T15:55:45Z", "salary": {"currency": null, "max": null, "min": null, "period": "monthly", "term": null}, "salary_visible": false, "title_keywords": ["senior associate", "associate"], "responsibilities": ["tax", "taxation", "make recommendation", "compliance", "liaise with"], "requirements": {"degrees": ["diploma", "degree holder"], "majors": ["accountancy"], "languages": ["putonghua", "english", "chinese"], "language_level": ["excellent"], "hard_skills": ["make", "analytical skills"], "soft_skills": ["efficient", "independent", "analytical skills", "interpersonal skills", "team player"], "languages_combined": [{"language": "putonghua", "language_level": ["excellent"]}, {"language": "english", "language_level": ["excellent"]}, {"language": "chinese", "language_level": ["excellent"]}]}, "experience_required": {"duration": ["minimum 3-5 years"], "field": ["commercial"]}}, {"job_id": "100003009047949", "location_code": "hk", "company": "C. K. Lo & Company Certified Public Accountants", "job_title": "Audit senior / semi-senior / junior", "description": "Job Duty\n\n\nHandle full range of financial statement audit and taxation independently or with team;\nCommunicate with clients (local and foreign) to obtain information for performing the auditing duty; and\nAssist in performing accounting work and ad hoc assignments.\n\nRequirements\n\n\nDegree holder major in accountancy or related field;\nStudent member of HKICPA or ACCA;\nMinimum 3 years solid working experience for accounting and auditing in CPA firm is preferred. Fewer experience will also be considered as Junior Associate;\nKnowledge of financial reporting standards including HKFRSs, HKFRS for Private Entities and SME-FRS and auditing standards;\nExperience in handling the audit of MNC and consolidation is preferred;\nGood command in written and spoken English and Chinese (Cantonese and Mandarin);\nProficiency in Microsoft Office such as Word and Excel;\nStrong analytical and communication stills; and\nWilling to learn with positive working attitude.\n\nBenefit\n\n\n5-day work, no overtime work and travelling is expected;\n14-day annual leave;\nCompetitive remuneration package;\nMedical benefit;\nYear-end bonus; and\nStudy and exam leave.\n\nInterested parties please send full resume with contact details, date of availability, present and expected salary (application without stating these details may not be considered) to us for arrangement an interview.\n\nAll information provided by applicants will be treated confidential and used only for recruitment purpose.", "employment_types": ["Full Time", "Permanent"], "selling_points": [], "locations": ["Tsim Sha Tsui"], "categories": ["Accounting", "Accountant", "Audit", "Taxation"], "post_time": "2022-01-15T03:49:02Z", "salary": {"currency": null, "max": null, "min": null, "period": "monthly", "term": null}, "salary_visible": false, "title_keywords": ["junior"], "responsibilities": ["communicate with", "taxation", "audit", "communication", "ad hoc assignments", "financial reporting", "sme", "financial statement", "auditing"], "requirements": {"degrees": ["degree holder"], "majors": ["accountancy"], "languages": ["cantonese", "english", "chinese", "mandarin"], "language_level": ["good command"], "hard_skills": ["excel", "acca", "hkfrs", "microsoft office", "word", "cpa", "hkicpa"], "soft_skills": ["communication", "positive working attitude", "independently", "willing to learn"], "languages_combined": [{"language": "cantonese", "language_level": ["good command"]}, {"language": "english", "language_level": ["good command"]}, {"language": "chinese", "language_level": ["good command"]}, {"language": "mandarin", "language_level": ["good command"]}]}, "experience_required": {"duration": ["minimum 3 years"], "field": ["consolidation", "accounting", "cpa firm", "audit"]}}, {"job_id": "100003009035914", "location_code": "hk", "company": "Privatco CPA Limited", "job_title": "Auditor - Semi Senior/Senior", "description": "Audit senior / semi-senior / junior\n\nDegree holder major in accountancy or related field;\nStudent member / member of HKICPA or other professional bodies;\nApplicants with\u00a0no or\u00a0less experience\u00a0are\u00a0considered as Audit\u00a0Junior;\nHardworking, analytical and detail oriented;\nWilling to learn with positive working attitude;\nGood interpersonal and communication skills;\nStrong PC skills & proficiency in MS Word, Excel and Chinese word processing; and\nGood command of English, Chinese and Mandarin\n\nOffer competitive salary to suitable candidate.\u00a0\n\n\nWe offer 5-days work, medical allowance, study and exam leaves, good working condition and valuable experience. Travel is RARELY required.\n\nApply Method:\n\nInterested parties please email your full resume with current and expected salary to us.\n\n\n(data collected used for recruitment purpose only)", "employment_types": ["Full Time"], "selling_points": [], "locations": ["Kowloon Bay"], "categories": ["Accounting", "Accountant", "Audit", "Taxation"], "post_time": "2022-01-13T18:54:45Z", "salary": {"currency": null, "max": null, "min": null, "period": "monthly", "term": null}, "salary_visible": false, "title_keywords": [], "responsibilities": ["communication", "audit"], "requirements": {"degrees": ["degree holder"], "majors": ["accountancy"], "languages": ["english", "chinese", "mandarin"], "language_level": ["proficiency", "good command"], "hard_skills": ["excel", "no", "chinese word processing", "hkicpa", "pc skills", "ms word"], "soft_skills": ["communication skills", "detail oriented", "willing to learn", "positive working attitude", "interpersonal", "hardworking"], "languages_combined": [{"language": "english", "language_level": ["good command"]}, {"language": "chinese", "language_level": ["proficiency", "good command"]}, {"language": "mandarin", "language_level": ["good command"]}]}, "experience_required": {"duration": [], "field": ["audit"]}}, {"job_id": "100003009047534", "location_code": "hk", "company": "ConnectedGroup Limited", "job_title": "Manager, Regulatory Reporting, Bank", "description": "Job description:\n\nPerform audit assignments for clients from a variety of industries\nAssist in drafting the audited financial statements\nLead team members to perform the sizable audit assignment\nOther ad hoc tasks per request\u00a0\n\nRequirements:\n\nDiploma or accounting degree holder or HKICPA memberships\n2 - 4 years' solid experience in auditing and taxation assignments, less experienced candidates will be considered as\u00a0Semi Senior auditor level\nCPA firm experience will be an advantage\nGood in English written and speaking skills\nGood Bookkeeping knowledge will be an advantage\nGood PC knowledge including MS Excel, Word, MYOB, Peachtree & Chinese Word Processing\nGood communication skills and work independently\n\u00a0Hard-working, self-motivate, patient\n\u00a0Immediate available is preferred\n\nAt PRIVATCO CPA Limited, we offer a supportive working environment where enables you to grow and succeed professionally.\n\nInterested parties please send application letter and full resume with date of availability, current and expected salary by APPLY NOW. (Please mark the job title applied at the subject of the email).\n\n(Data collected will be used for recruitment purpose only.)", "employment_types": ["Full Time", "Permanent"], "selling_points": ["Leading international bank", "Friendly Working Environment", "Competitive remuneration package"], "locations": ["Not Specified"], "categories": ["Accounting", "Accountant", "Audit", "Taxation"], "post_time": "2022-01-14T03:23:58Z", "salary": {"currency": null, "max": null, "min": null, "period": "monthly", "term": null}, "salary_visible": false, "title_keywords": ["manager"], "responsibilities": ["ad hoc tasks", "audit", "financial statements"], "requirements": {"degrees": ["diploma", "degree holder"], "majors": ["accounting"], "languages": ["english", "chinese"], "language_level": ["good"], "hard_skills": ["chinese word processing", "word", "cpa", "ms excel", "peachtree", "pc knowledge", "myob", "hkicpa"], "soft_skills": ["communication skills", "work independently", "hard-working", "patient"], "languages_combined": [{"language": "english", "language_level": ["good"]}, {"language": "chinese", "language_level": ["good"]}]}, "experience_required": {"duration": ["2 - 4 years"], "field": ["cpa firm"]}}, {"job_id": "100003009050310", "location_code": "hk", "company": "Macy's Candies Limited", "job_title": "Assistant Accountant / Accountant", "description": "THE ROLE\n\nReporting into the team head, please find your responsibilities below -\n\nReview and prepare the regulatory report (HKMA) to ensure compliance with regulatory requirements;\nEnsure proper control checking and review procedures are in place;\nReview financial disclosure and audited financial statements in compliance with Banking Disclosure Rule;\nProvide support to maintain the local reporting system and database;\nParticipated in finance projects.\n\n\nTHE REQUIREMENTS\n\nUniversity graduated in Finance, Business Administration or relevant disciplines.\nAt least 5 years of working experience in Banks/ Big 4/ Financial Institution.\nSelf-motivated and can be a good team player.\nExcellent communication skills and problem solving skills.\nSelf-motivated with ability to deal with multiple commitments / deadlines.\nStrong analytical and organizing skills.\nCandidates with less experience will consider as the Assistant manager title.\n\n\nThis is an excellent opportunity to join one of the world's leading bank that offer long term career growth, guidance, and development.\n\nInterested individuals can apply now. Please send your CV in WORD format with your current and expected salary.\n\nVIEW OTHER LIVE VACANCIES HERE: http://www.connectedgroup.com/advancedsearch.aspx", "employment_types": ["Full Time"], "selling_points": [], "locations": ["Tai Po Area"], "categories": ["Accounting", "Accountant", "Taxation", "Banking / Finance", "Financial Services"], "post_time": "2022-01-14T10:05:52Z", "salary": {"currency": null, "max": null, "min": null, "period": "monthly", "term": null}, "salary_visible": false, "title_keywords": ["accountant", "assistant accountant"], "responsibilities": ["administration", "reporting", "control", "provide support", "guidance", "regulatory requirements", "review", "procedures", "checking", "financial statements", "ensure compliance", "compliance", "communication", "maintain", "database", "banking", "report"], "requirements": {"degrees": [], "majors": [], "languages": [], "language_level": [], "hard_skills": ["hkma", "problem solving skills", "word"], "soft_skills": ["communication skills", "good team player", "self-motivated", "problem solving skills"], "languages_combined": []}, "experience_required": {"duration": ["at least 5 years"], "field": ["big 4", "financial"]}}, {"job_id": "100003009044182", "location_code": "hk", "company": "W.Y. Lam & Co", "job_title": "AUDIT ASSISTANTS", "description": "Prepare and review loan documents for Commercial Facilities\nLiaise with legal counsels and marketing units to ensure proper and efficient operations of credit administration work\nReview loan operation procedures and streamlining workflow\nDegree holder or above in Finance or related disciplines\nMinimum 3 years\u2019 experience in loan documentation and credit administration\nExperience in commercial loans and syndicated loans will be an advantage\nIn-depth knowledge of loan documentation, procedures and relevant legal requirements\n\nCandidate with less experience will be considered as Deputy Manager, Documentation (Commercial)\n\n\u00a0\n\nThe above post requires proficiency in English, Cantonese and Putonghua.\n\nWe offer attractive remuneration package to the right candidates. Please send your full resume with expected salary to\u00a0The Human Resources Manager, Bank of Communications Co., Ltd., 10/F, Bank of\u00a0Communications\u00a0Tower,\u00a0231-235 Gloucester Road, Wan Chai,\u00a0Hong Kong, or fax to\u00a02838 9209, or e-mail to APPLY NOW.", "employment_types": ["Full Time", "Permanent"], "selling_points": [], "locations": ["Admiralty"], "categories": ["Accounting", "Audit", "Taxation"], "post_time": "2022-01-13T03:19:23Z", "salary": {"currency": null, "max": null, "min": null, "period": "monthly", "term": null}, "salary_visible": false, "title_keywords": [], "responsibilities": ["documentation", "operations", "review", "procedures", "liaise with", "administration"], "requirements": {"degrees": ["degree holder"], "majors": ["related disciplines", "finance"], "languages": ["cantonese", "putonghua", "english"], "language_level": ["proficiency"], "hard_skills": ["documentation"], "soft_skills": ["efficient"], "languages_combined": [{"language": "cantonese", "language_level": ["proficiency"]}, {"language": "putonghua", "language_level": ["proficiency"]}, {"language": "english", "language_level": ["proficiency"]}]}, "experience_required": {"duration": ["minimum 3 years"], "field": ["commercial", "administration"]}}, {"job_id": "100003009044058", "location_code": "hk", "company": "KLC Kennic Lui & Co. Limited", "job_title": "Senior Associate / Assistant Manager", "description": "Must be immediately available\nHKICPA / ACCA or other relevant professional bodies member or student member\n1 - 2 years experience in audit firm\nCandidates with more experience will be considered for the post of Audit Supervisor\nFluent in spoken and written English and Mandarin\nStrong analytical, communication and interpersonal skills\nStrong computer skill is preferred\n\nWe offer a 5 day week and attractive remuneration package including:\n\nMonthly incentive bonus\nYear end performance bonus\u00a0\nMedical insurance\nPaid sick leave\nStudy leave and examination leave\n\nPlease send your resume indicating the position you apply for and your expected and current salaries to\u00a0hroffice @ sino-cpa.com\n\n(Personal data collected will be used for recruitment purpose only.)", "employment_types": ["Full Time", "Permanent"], "selling_points": [], "locations": ["Central"], "categories": ["Accounting", "Audit", "Taxation"], "post_time": "2022-01-13T02:57:15Z", "salary": {"currency": null, "max": null, "min": null, "period": "monthly", "term": null}, "salary_visible": false, "title_keywords": ["senior associate", "assistant manager"], "responsibilities": ["communication", "audit"], "requirements": {"degrees": [], "majors": [], "languages": ["english", "mandarin"], "language_level": ["fluent"], "hard_skills": ["acca", "computer skill", "hkicpa"], "soft_skills": ["communication and interpersonal skills"], "languages_combined": [{"language": "english", "language_level": ["fluent"]}, {"language": "mandarin", "language_level": ["fluent"]}]}, "experience_required": {"duration": ["1 - 2 years"], "field": ["audit"]}}, {"job_id": "100003009042528", "location_code": "hk", "company": "SWC & Partners", "job_title": "Audit Juniors, Semi-Seniors & Seniors \u2013 Assurance", "description": "Requirements:\u00a0\u00a0\nAt\u00a0least\u00a03 years professional audit experience;\nProfessional qualifications including HKICPA, ACCA or equivalent;\nGood\u00a0command in written and spoken English, Cantonese and fluency in Putonghua;\nA\u00a0determined team leader with drive and initiative;\nExcellent communications and inter-personal skills; and\nStrong analytical and problem-solving skills.\n\nWe offer competitive remuneration packages and attractive staff fringe benefits to the right candidate.\u00a0\u00a0\n\nInterested applicants please submit your full resume, current and expected salary to our Human Resource Department at 5th Floor, Ho Lee Commercial Building, 38-44 D\u2019Aguilar Street, Central, Hong Kong or click \u201cApply Now\u201d.\u00a0 Personal data will be collected for recruitment purposes only.\u00a0\u00a0", "employment_types": ["Full Time", "Permanent"], "selling_points": ["Perform quality audit or tax procedure", "Handle full set of accounts", "Perform tax computation"], "locations": ["North Point"], "categories": ["Accounting", "Audit", "Taxation"], "post_time": "2022-01-12T23:26:15Z", "salary": {"currency": null, "max": null, "min": null, "period": "monthly", "term": null}, "salary_visible": false, "title_keywords": [], "responsibilities": ["audit"], "requirements": {"degrees": [], "majors": [], "languages": ["cantonese", "putonghua", "english"], "language_level": ["fluency", "good command"], "hard_skills": ["problem-solving skills", "hkicpa", "acca", "professional qualifications"], "soft_skills": ["problem-solving skills", "inter-personal skills", "initiative", "determined"], "languages_combined": [{"language": "cantonese", "language_level": ["good command"]}, {"language": "putonghua", "language_level": ["good command"]}, {"language": "english", "language_level": ["fluency", "good command"]}]}, "experience_required": {"duration": ["at least 3 years"], "field": ["audit experience"]}}, {"job_id": "100003009040281", "location_code": "hk", "company": "Lawrence Cheung C.P.A. Co Ltd", "job_title": "AUDIT INTERMEDIATE (Starting from HK$18,000 to HK$21,500)", "description": "Qualifications:\n\nDiploma/ Degree holders with major in accounting\nMembers or student members of HKICPA or equivalent are highly preferred\nPossess initiative, detail-oriented with strong analytical skills and good command of written and spoken English and Chinese including Mandarin\n\nResponsibilities across various disciplines:\n\nPerform quality audit or tax procedures\nHandle full set of accounts\nPerform tax computation\n\nBenefits:\n\nWe offer\u00a05-day working week, paid exam/study leaves\u00a0and medical,\u00a0attractive salary, comprehensive training, excellent career and promotion opportunities.\n\nInterested parties can click \u201cApply now\u201d or email their CVs & expected salary directly to:\n\nMs. Elaine Kwan\n\nSuite C, 21/F Lee & Man Commercial Center,\n\n169 Electric Road, North Point, Hong Kong\n\n\u00a0(Data collected will be used for recruiting purpose only)", "employment_types": ["Full Time", "Permanent"], "selling_points": ["12 days Annual leave & 12 days Study leave", "5 days work, Structure training program", "Fast promotion, half yearly appraisal"], "locations": ["Central"], "categories": ["Accounting", "Audit", "Taxation", "Others"], "post_time": "2022-01-12T02:07:14Z", "salary": {"currency": null, "max": null, "min": null, "period": "monthly", "term": null}, "salary_visible": false, "title_keywords": [], "responsibilities": ["tax", "tax computation", "full set of accounts", "quality", "audit", "procedures"], "requirements": {"degrees": ["diploma", "degree"], "majors": ["accounting"], "languages": ["english", "chinese", "mandarin"], "language_level": ["good command"], "hard_skills": ["analytical skills", "hkicpa"], "soft_skills": ["initiative", "analytical skills", "detail-oriented"], "languages_combined": [{"language": "english", "language_level": ["good command"]}, {"language": "chinese", "language_level": ["good command"]}, {"language": "mandarin", "language_level": ["good command"]}]}, "experience_required": {"duration": [], "field": []}}, {"job_id": "100003009039278", "location_code": "hk", "company": "Kwonnie Electrical Products Ltd", "job_title": "Finance Manager", "description": "We value our staff as team members and we are looking for staff who are serious in the profession.\n\nRequirements:-\n\nDiploma / Associate Degree/ Degree holder, Major in Accountancy\nStudent member of HKICPA/ACCA or equivalent\nAt least 1 year experience for Intermediate position / less than 1 year experience will be considered as Assistant\nGood command of both spoken and written English and Chinese, fluency in Putonghua is an advantage\nKnowledge in taxation and competent in using Excel is desirable\nQualified pay for completion of QP Final Examination\nGood promotion prospects and benefits\n\nWe offer attractive remuneration package with fast promotion prospect and salary increment with half-yearly appraisal, in-house training, 5 days work week, medical insurance, discretionary bonus, overtime pay or compensation leave and travel & meal allowance.\n\nPlease email us with your covering letter and resume giving full personal particulars, employment history and expected salary together with contact number.", "employment_types": ["Full Time", "Permanent"], "selling_points": [], "locations": ["Others - China"], "categories": ["Accounting", "Finance / Accounting Manager", "Financial Analyst", "Taxation"], "post_time": "2022-01-11T09:16:18Z", "salary": {"currency": null, "max": null, "min": null, "period": "monthly", "term": null}, "salary_visible": false, "title_keywords": ["finance manager"], "responsibilities": ["taxation"], "requirements": {"degrees": ["associate degree", "diploma", "degree holder"], "majors": ["accountancy"], "languages": ["putonghua", "english", "chinese"], "language_level": ["fluency", "advantage", "good command"], "hard_skills": ["excel", "acca", "hkicpa"], "soft_skills": ["competent"], "languages_combined": [{"language": "putonghua", "language_level": ["fluency", "advantage", "good command"]}, {"language": "english", "language_level": ["advantage", "good command"]}, {"language": "chinese", "language_level": ["advantage", "good command"]}]}, "experience_required": {"duration": ["at least 1 year", "1 year"], "field": []}}, {"job_id": "100003009037536", "location_code": "hk", "company": "Pinewood CPA Limited", "job_title": "Audit / CPA / Auditor Professionals \u2013 All levels", "description": "Job Description\nFull set of audit / accounting assignments including consolidation packages\nCorporate and individual tax compliance assignments\nSpecial engagements such as due diligence, M&A and pre-IPO reviews\nAd Hoc activities including IT projects like Clouds accounting\nRelevant company secretarial matters as well\nRequirements\nHKICPA qualified members or other related disciplines\nQP finalists/graduates/students\nDiploma/Higher Diploma/Associate Degree/Degree in Accounting or related discplines\nLess experience or fresh graduate will also be considered\nSound interpersonal and presentation skills and willing to communicate\nSelf-driven, results-oriented with strong problem-solving technique, detailed-minded and responsible\nWhat we provide\nWe are a HKICPA Authorized Employer\n5-day work week\nDiscretionary bonus\nAnnual leaves\nStudy and Examination leaves\nMedical allowances\nInterested parties please send full resume with earliest availability, current and expected salary by clicking \u201cAPPLY NOW\u201d", "employment_types": ["Full Time"], "selling_points": ["QP finalists/graduates/students", "fresh graduate will also be considered", "Wan Chai and Kwai Tsing Area"], "locations": ["Not Specified"], "categories": ["Accounting", "Accounting Clerk / Supervisor", "Audit", "Taxation"], "post_time": "2022-01-11T03:03:35Z", "salary": {"currency": null, "max": null, "min": null, "period": "monthly", "term": null}, "salary_visible": false, "title_keywords": [], "responsibilities": ["tax", "due diligence", "ad hoc", "compliance", "audit"], "requirements": {"degrees": ["associate degree", "diploma", "degree", "fresh graduate"], "majors": ["accounting"], "languages": [], "language_level": [], "hard_skills": ["problem-solving", "hkicpa"], "soft_skills": ["responsible", "problem-solving", "presentation skills", "interpersonal", "driven", "detailed"], "languages_combined": []}, "experience_required": {"duration": [], "field": []}}, {"job_id": "100003009040280", "location_code": "hk", "company": "Lawrence Cheung C.P.A. Co Ltd", "job_title": "AUDIT ASSISTANT (HKD17,000 to HK$18,000) \u2013 Fresh Graduates", "description": "Job Responsibilities\n\nResponsible for the financial and management reporting, budgeting, variance analysis, forecasting, assist in inventory control, VAT processing, and implement or create policies and procedures to control the business as well as proactively identifying and resolving finance and reporting issues;\nManage all aspect of the finance daily operation function in Thailand and PRC manufacturing plant;\nFormulate and implement financial policies and maintain effective internal control system for local regulations;\u00a0\nInvolve in analyzing, reviewing and establishing operational and internal system controls effectiveness and procedures;\nEvaluate control design and gap analysis; perform testing and evaluate operational effectiveness; identify and remediate deficiencies / weaknesses;\nPrepare cash-flow forecast and planning & tax planning;\nEnsure compliance with the statutory requirements of audit and tax filing\n\nJob Requirements\n\nProfessional qualified accountant with HKICPA or equivalent qualification;\nAt least 5 years\u2019 accounting/auditing experience and preferably in manufacturing industry;\nSolid experience in managing finance/accounting function in PRC;\nFamiliar with HK & WOFE accounting standards, taxation, regulations and operations;\nExperience in computerized accounting and ERP system;\nEnergetic, good interpersonal skills, disciplinary and task-oriented and able to work independently in dynamic environment;\nGood command of written and spoken English and Chinese, including Putonghua and Cantonese;\nExperience in setting up company in Thailand is highly preferred;\n\nInterested parties, please send your full resume stating your expected salary and date of availability to the Human Resources and Administration Department by email for application. We offer successful candidates an attractive remuneration packages (Basic salary + Bonus + Medical Scheme) and the opportunity to work in a dynamic and exciting environment. (Data collected will be used for recruitment purpose only)", "employment_types": ["Full Time", "Permanent"], "selling_points": ["5 days work, Structure training program", "12 days Annual leave & 12 days Study leaves", "Fast promotion, half yearly appraisal"], "locations": ["Not Specified"], "categories": ["Accounting", "Accounting Clerk / Supervisor", "Audit", "Taxation"], "post_time": "2022-01-12T02:07:14Z", "salary": {"currency": null, "max": null, "min": null, "period": "monthly", "term": null}, "salary_visible": false, "title_keywords": ["assistant"], "responsibilities": ["regulations", "budgeting", "financial policies", "audit", "design", "statutory requirements", "maintain", "internal control", "control", "tax filing", "testing", "forecast", "forecasting", "reporting", "procedures", "variance analysis", "inventory control", "management reporting", "tax", "policies", "analysis", "daily operation", "ensure compliance", "evaluate", "planning"], "requirements": {"degrees": [], "majors": [], "languages": ["cantonese", "putonghua", "english", "chinese"], "language_level": ["good command"], "hard_skills": ["erp system", "dynamic", "hkicpa"], "soft_skills": ["work independently", "energetic", "interpersonal skills", "dynamic environment"], "languages_combined": [{"language": "cantonese", "language_level": ["good command"]}, {"language": "putonghua", "language_level": ["good command"]}, {"language": "english", "language_level": ["good command"]}, {"language": "chinese", "language_level": ["good command"]}]}, "experience_required": {"duration": ["at least 5 years"], "field": ["finance", "erp system", "accounting", "manufacturing industry"]}}, {"job_id": "100003009041723", "location_code": "hk", "company": "Alfred H.K. Li & Co., CPA", "job_title": "AUDIT JUNIOR, SEMI-SENIOR, SENIOR AUDITORS AND SUPERVISORS", "description": "We value our staff as team members and we are looking for staff who are serious in the profession.\n\nResponsibilities:\nPerform general audit procedures such as transaction test, verification of assets and liabilities, reasonableness test on Profit & Loss items, prepare statutory accounts and profits tax computation etc.\n\nRequirements:-\n\n\nDiploma / Associate Degree/ Degree holder, Major in Accountancy\nStudent member of HKICPA/ACCA or equivalent is an advantage\nCandidate with audit working experience is an advantage\nGood command of both spoken and written English and Chinese, fluency in Putonghua is an advantage\nQualified pay for completion of QP Final Examination\nGood promotion prospects and benefits\n\nWe offer attractive remuneration package with fast promotion prospect and salary increment with half-yearly appraisal, in-house training, 5 days work week, medical insurance, discretionary bonus, overtime pay or compensation leave and travel & meal allowance.\n\nPlease email us with your covering letter and resume giving full personal particulars, employment history and expected salary together with contact number.", "employment_types": ["Full Time", "Permanent"], "selling_points": [], "locations": ["Kwun Tong"], "categories": ["Accounting", "Accounting Clerk / Supervisor", "Audit", "Taxation"], "post_time": "2022-01-12T04:16:06Z", "salary": {"currency": null, "max": null, "min": null, "period": "monthly", "term": null}, "salary_visible": false, "title_keywords": ["junior"], "responsibilities": ["tax computation", "procedures", "audit"], "requirements": {"degrees": ["associate degree", "diploma", "degree holder"], "majors": ["accountancy"], "languages": ["putonghua", "english", "chinese"], "language_level": ["fluency", "advantage", "good command"], "hard_skills": ["acca", "hkicpa"], "soft_skills": [], "languages_combined": [{"language": "putonghua", "language_level": ["fluency", "advantage", "good command"]}, {"language": "english", "language_level": ["advantage", "good command"]}, {"language": "chinese", "language_level": ["advantage", "good command"]}]}, "experience_required": {"duration": [], "field": ["audit"]}}, {"job_id": "100003009039227", "location_code": "hk", "company": "Roger Kam & Co", "job_title": "Audit Manager / Assistant Manager / Supervisor / Assistant Supervisor (5 DAYS WORK)", "description": "Alfred H.K. Li & Co., CPA is a fast-growing and highly dynamic CPA firm in Hong Kong.\n\nDue to continuous business expansion, we are looking for Audit junior, Semi-senior, Senior auditors and Supervisors who are conscientious, independent, responsible and hardworking.\n\nRequirements:\n\nDiploma/Associate Degree/Degree major in Accounting;\nStudent member of HKICPA/ACCA or equivalent preferred;\nGood command of both written and spoken English and Chinese is essential;\nWilling to travel to P.R.C. and fluent in Putonghua;\nOne to four years\u2019 audit experiences in audit firms preferred;\nGood command of knowledge in Microsoft Office and accounting software;\nGood interpersonal communication skill;\nAble to work under pressure and carry out multi-tasks independently;\nHardworking, honest, responsible and self\u2013motivated; and\nImmediate available is preferable.\n\nRemuneration will be commensurate with qualification and experiences.\u00a0\u00a0 We offer 5 days\u2019 work, discretionary performance bonus, 12 days annual leave, birthday leave, study and examination leaves and medical allowance.\n\nInterested candidates should forward your resume, expected and present salary and date of availability by clicking Apply Now.\n\nPersonal data collected will be used for recruitment purposes only.", "employment_types": ["Full Time", "Permanent"], "selling_points": ["5-day work, Sick Leave, Birthday Leave", "Study and exam leaves, training allowances, etc", "Performance bonus (two times every year)"], "locations": ["Tsim Sha Tsui"], "categories": ["Accounting", "Audit", "Taxation", "Others"], "post_time": "2022-01-11T09:05:41Z", "salary": {"currency": null, "max": null, "min": null, "period": "monthly", "term": null}, "salary_visible": false, "title_keywords": ["assistant manager", "manager", "supervisor", "assistant supervisor"], "responsibilities": ["communication", "audit", "software", "work under pressure"], "requirements": {"degrees": ["associate degree", "diploma", "degree"], "majors": ["accounting"], "languages": ["putonghua", "english", "chinese"], "language_level": ["good command", "fluent"], "hard_skills": ["acca", "microsoft office", "accounting software", "cpa", "dynamic", "c", "r", "hkicpa"], "soft_skills": ["independently", "independent", "responsible", "multi-tasks", "communication skill", "dynamic", "motivated", "honest", "conscientious", "interpersonal", "hardworking", "work under pressure"], "languages_combined": [{"language": "putonghua", "language_level": ["fluent"]}, {"language": "english", "language_level": ["good command"]}, {"language": "chinese", "language_level": ["good command"]}]}, "experience_required": {"duration": ["one to four years"], "field": ["audit"]}}, {"job_id": "100003009037782", "location_code": "hk", "company": "McMillan Woods (Hong Kong) CPA Limited", "job_title": "Audit Professionals of All Grades (Fresh Graduate is also welcomed)", "description": "Key duties:\n\nReport to Audit Partners\u00a0/ Audit Manager\nReview audit, assurance and special engagements as well as tax computation\u00a0\nSupervise / in-charge of special engagements\u00a0\nProvide technical support to audit teams\u00a0\nOversee client's portfolio\n\n\u00a0Requirements:\n\nProfessional qualification is preferred\u00a0\nExperience in handling listed companies, financial services companies are preferred\nAt least 5 years' audit experience is required\u00a0\n\n\u00a0We offer:\n\n5-day work\nAnnual leaves from 12 to 15 days according to length of services\u00a0\nPaid birthday holiday\nPaid marriage leave\u00a0\nPaid sick leave, medical insurance benefits\u00a0\nPaid study and examination leaves for attending professional exams \u00a0\nLocal meal allowances\nOvertime compensation benefit (covered non-office hours and non-working days)\nOverseas travel allowances\u00a0\nReimbursement of job-related seminars / course\u00a0\nPerformance bonus two times every year\u00a0\nReimbursement of professional qualification membership fee\u00a0\n\nSalary will commensurate with qualification and experience.\n\nInterested parties please send your application, full resume and present / expected salary by clicking \"Apply Now\".\u00a0\n\nPersonal data collected will be used for recruitment purpose only.", "employment_types": ["Full Time", "Permanent", "Internship"], "selling_points": ["All-grade audit professional", "5 days work", "Medical Scheme, Birthday Leave, Study & Exam Leave"], "locations": ["Wan Chai"], "categories": ["Accounting", "Audit", "Taxation"], "post_time": "2022-01-11T03:51:43Z", "salary": {"currency": null, "max": null, "min": null, "period": "monthly", "term": null}, "salary_visible": false, "title_keywords": [], "responsibilities": ["tax computation", "technical support", "review", "teams", "audit", "report"], "requirements": {"degrees": [], "majors": [], "languages": [], "language_level": [], "hard_skills": [], "soft_skills": [], "languages_combined": []}, "experience_required": {"duration": ["at least 5 years"], "field": ["audit experience", "financial services"]}}, {"job_id": "100003009039279", "location_code": "hk", "company": "Top Asia Holdings Limited", "job_title": "General Manager - Accounting Department", "description": "To carry out various audit, accounting and tax assignments under the supervision.\nAssisting in the preparation of audit proposals and presentations;and\nManaging a team or assisting engagement directors in carrying out quality audit and other assurance services to clients across various industries.\n\n\nJob Requirements:\n\nDegree or Diploma holder in Accounting, Business Administration, Finance or related disciplines.\nHKICPA, ACCA, CICPA or CPAA member or equivalent for Senior/Assistant Manager/Manager.\nRelevant working experience in audit/financial due diligence/IPO is highly preferred for Senior/Assistant Manager/Manager.\u00a0\u00a0\nStrong communication skills, team spirit and willingness to work under pressure.\nGood command of spoken and written English and Chinese (Cantonese and Mandarin); and\u00a0\nWilling to travel.", "employment_types": ["Full Time"], "selling_points": [], "locations": ["Central"], "categories": ["Accounting", "Financial Controller", "Taxation", "Others"], "post_time": "2022-01-11T16:01:49Z", "salary": {"currency": null, "max": null, "min": null, "period": "monthly", "term": null}, "salary_visible": false, "title_keywords": ["general manager", "accounting"], "responsibilities": ["tax", "due diligence", "work under pressure", "quality", "audit", "presentations", "communication", "managing a team", "administration"], "requirements": {"degrees": ["diploma holder", "degree"], "majors": ["related disciplines", "finance", "accounting", "business administration"], "languages": ["cantonese", "english", "chinese", "mandarin"], "language_level": ["good command"], "hard_skills": ["acca", "presentations", "hkicpa"], "soft_skills": ["communication skills", "team spirit", "under pressure", "willingness to work"], "languages_combined": [{"language": "cantonese", "language_level": ["good command"]}, {"language": "english", "language_level": ["good command"]}, {"language": "chinese", "language_level": ["good command"]}, {"language": "mandarin", "language_level": ["good command"]}]}, "experience_required": {"duration": [], "field": ["relevant working experience", "audit", "financial"]}}, {"job_id": "100003009036202", "location_code": "hk", "company": "Chan Li Law CPA Limited", "job_title": "Audit Trainee to Senior (Tsim Sha Tsui East)", "description": "The incumbent will lead the accounting departments in Hong Kong and in China, to ensure the financial reports and management accounts are compiled on a timely and accurate basis, and to oversee and plan for the financial needs of the business units/projects.\n\nREQUIREMENTS:\n\n- Degree in Accounting with professional qualification\n\n- Possess over 10 years senior management experience as obtained from large audit firms and in commercial sector \u00a0\n\n- Solid experience in listed company financial reporting, budget planning and control, financing and tax planning\n\n- Excellent command of both spoken and written English and Chinese\n\nInterested parties please send resume with availability & past/expected salary to the HR Manager.\n\nAll data collected will be used for recruitment purposes only.", "employment_types": ["Full Time", "Permanent"], "selling_points": ["fresh graduates", "5 days work", "authorised employer"], "locations": ["Tsim Sha Tsui"], "categories": ["Accounting", "Accountant", "Audit", "Taxation"], "post_time": "2022-01-10T09:38:44Z", "salary": {"currency": null, "max": null, "min": null, "period": "monthly", "term": null}, "salary_visible": false, "title_keywords": ["trainee"], "responsibilities": ["tax", "financial reports", "management", "budget planning", "control", "audit", "financial reporting", "plan", "senior management", "planning"], "requirements": {"degrees": ["degree"], "majors": ["accounting"], "languages": ["english", "chinese"], "language_level": ["excellent"], "hard_skills": [], "soft_skills": ["timely", "accurate"], "languages_combined": [{"language": "english", "language_level": ["excellent"]}, {"language": "chinese", "language_level": ["excellent"]}]}, "experience_required": {"duration": ["10 years"], "field": ["management", "financing", "financial", "audit", "commercial", "planning"]}}, {"job_id": "100003009015243", "location_code": "hk", "company": "CK Asset Holdings Limited", "job_title": "Tax Professional", "description": "We are currently recruiting for position of\u00a0Audit Trainee to Senior in our Tsim Sha Tsui East head office.\u00a0\u00a0\n\nWhat we require:\n\n0-4 years relevant working experience\nTertiary education (e.g. VTC, high diploma or above) in accounting or related disciplines\nFresh graduates in any discipline with no experience will also be considered as Audit Trainee\nGood command of written and spoken English\nStrong interpersonal and communication skills\n\nWhy CLL:\n\nEx-Big Four managerial level to ensure practice & training at professional standard\nJob exposure to a wide range of sectors, both local and overseas\nYoung and energetic team, led by coaches with \u201croll-up-the-sleeves mentality\u201d\nA culture of excel customer experience - on-the-job customer facing exposure\nFriendly working environment at convenience location\nAttractive remuneration plus annual increment\n5-day work week\nAnnual leave, study and examination leaves\nMedical allowance\nWe are an Authorised Employer of HKICPA\n\nInterested parties please send full resume with present and expected salary by clicking \u201cApply Now\u201d.\n\n(Personal data collected will be used for recruitment purposes only)", "employment_types": ["Full Time", "Permanent"], "selling_points": ["HK Listed Property Developer", "Qualified Accountant with at least 8 years tax exp", "Sound knowledge of international tax practices"], "locations": ["Central"], "categories": ["Accounting", "Audit", "Chief Accountant", "Taxation"], "post_time": "2022-01-04T16:20:09Z", "salary": {"currency": null, "max": null, "min": null, "period": null, "term": null}, "salary_visible": false, "title_keywords": [], "responsibilities": ["communication", "audit"], "requirements": {"degrees": ["high diploma or above"], "majors": ["related disciplines", "accounting"], "languages": ["english"], "language_level": ["good command"], "hard_skills": ["excel", "no", "hkicpa", "plus"], "soft_skills": ["communication skills", "energetic", "friendly", "interpersonal"], "languages_combined": [{"language": "english", "language_level": ["good command"]}]}, "experience_required": {"duration": ["0-4 years"], "field": ["relevant working experience", "audit"]}}, {"job_id": "100003009033870", "location_code": "hk", "company": "Bank of Communications Hong Kong Branch", "job_title": "Manager, Financial Accounting", "description": "University graduate with professional accounting qualification\nQualified Accountant with at least 8 years tax experience in big professional firm reaching managerial position\nSound knowledge of international tax practices\nIndependent,\u00a0self-motivated and result-oriented\nGood command of written and spoken English and Mandarin\n\n\nWe will offer attractive compensation package to the right candidate. Please send application enclosing resume stating career and salary history, expected salary and date of availability to The Senior Manager, Human Resources Department, CK Asset Holdings Limited, 7/F Cheung Kong Center, 2 Queen\u2019s Road Central, Hong Kong or by clicking \u201cApply Now\u201d (in Word format). Please quote the reference of the position you apply for in all correspondences.\n\nWe are an equal opportunity employer and welcome applications from all qualified candidates. Personal data collected will be treated in strictest confidence and handled confidentially by authorized personnel for recruitment-related purposes within the Group. Applicants not hearing from us within six weeks from the date of advertisement may consider their applications unsuccessful.", "employment_types": ["Full Time"], "selling_points": [], "locations": ["Not Specified"], "categories": ["Accounting", "Finance / Accounting Manager", "Taxation", "Banking / Finance", "Others"], "post_time": "2022-01-10T02:00:01Z", "salary": {"currency": null, "max": null, "min": null, "period": "monthly", "term": null}, "salary_visible": false, "title_keywords": ["manager", "accounting"], "responsibilities": ["tax", "personal data", "recruitment"], "requirements": {"degrees": ["university graduate"], "majors": ["accounting"], "languages": ["english", "mandarin"], "language_level": ["good command"], "hard_skills": ["word"], "soft_skills": ["self-motivated", "confidence", "independent", "result-oriented"], "languages_combined": [{"language": "english", "language_level": ["good command"]}, {"language": "mandarin", "language_level": ["good command"]}]}, "experience_required": {"duration": ["at least 8 years"], "field": ["managerial"]}}, {"job_id": "100003009034367", "location_code": "hk", "company": "Adventuras Limited", "job_title": "\u6703\u8a08\u53ca\u884c\u653f\u7d93\u7406", "description": "About Tax\n\nTax and regulatory issues are on top of the mind for many companies operating around the world today. As a tax professional, you will help organisations and individuals maximise their tax efficiency and manage their tax risks. You achieve this through the advice you give your clients on how to conduct proper tax planning, and helping your clients to fully meet their tax compliance obligations.\n\nTaxation in a fast-paced business environment is exciting and intellectually stimulating. In order for you to face up to the challenges, you will need to constantly develop your tax knowledge and research skills. As you progress, you will likely become specialised in certain tax speciality area and particular industries.\n\nAbout Tax Technology Team\n\nThe Tax Technology team is responsible for all technology based business solutions for the Tax division in the China and Hong Kong region. Moreover, the team serves as a contact point and liaison for other territories within as well as outside the Asia-Pacific region in relation to tax technology. We work closely with both the tax professionals and IT specialists within the Firm to support the systems life cycle of concurrent tax technology projects so as to deliver best-in-class technology-based business solutions.\n\nJob description and responsibilities:\n\nUnderstand business and client needs and derive business requirements, functional design, and process design\nPerform systems and/or proposal comparisons, analysis, and evaluations with engagement team\nAssist in analysing business processes, identifying potential automation opportunities and creating Process Description Document, and Solution Design Document\nAssist in planning and tracking projects tasks and timeline\nPerform testing and handle related issues during development and implementation of software projects\nCollect feedback and monitor on software projects after launch\n\nRequirements:\n\nGreat written and verbal communications skills in both English and Chinese\nAbility to work well and communicate effectively with other professionals\nProficiency in ASP, .NET ,C# , JAVA or any kind of programming language\nFunctional knowledge of SQL and object-oriented programmingcoding methodologies\nDemonstrate understanding of different software development life-cycle methodologies\nStrong organizational and analytical skills to research, compile and clearly present information and data\nMust be proficient in Word, Excel and PowerPoint\nAbility to function well in a fast-paced, dynamic environment with competing priorities and tight deadlines\nHands-on experience with system design, implementation and quality assurance is a plus\nBSc / BEng in Computer Science, Math, Physics or Engineering is preferred\nJunior candidates will be considered as Associate", "employment_types": ["Full Time"], "selling_points": [], "locations": ["Causeway Bay"], "categories": ["Accounting", "Accountant", "Accounting Clerk / Supervisor", "Taxation"], "post_time": "2022-01-10T03:15:37Z", "salary": {"currency": null, "max": null, "min": null, "period": "monthly", "term": null}, "salary_visible": false, "title_keywords": [], "responsibilities": ["software", "analysis", "systems", "monitor", "implementation", "design", "testing", "planning", "tracking"], "requirements": {"degrees": ["bsc"], "majors": ["math", "engineering", "computer science", "physics"], "languages": ["english", "chinese"], "language_level": [], "hard_skills": ["excel", "java", "plus", "word", "powerpoint", "analytical skills", "sql", "dynamic", "system design", "programming", "math", "c#"], "soft_skills": ["organizational", "dynamic environment", "hands-on", "analytical skills"], "languages_combined": [{"language": "english", "language_level": []}, {"language": "chinese", "language_level": []}]}, "experience_required": {"duration": [], "field": ["system design", "quality assurance"]}}, {"job_id": "100003008905455", "location_code": "hk", "company": "AnyDesk Software (Hong Kong) Limited", "job_title": "Finance Manager - Tech Unicorn Opportunity", "description": "\n\u8077\u8cac :\u9910\u5ef3\u5168\u76e4\u6703\u8a08, \u6536\u7d0d\u5e33\u76ee, \u6708\u5ea6/\u5e74\u5ea6\u6703\u8a08\u5e33\u76ee, \u6bcf\u6708\u85aa\u91d1\u53ca\u5f37\u7a4d\u91d1\u8a08\u7b97; \u7cfb\u7d71\u8cc7\u6599\u66f4\u65b0; \u4e0a\u53f8\u6307\u6d3e\u5de5\u4f5c\u7b49\n\n\u8cc7\u6b77 :\u5c08\u4e0a\u6559\u80b2\uff1a\u6587\u6191/\u8b49\u66f8; 5\u5e74\u7d93\u9a57; \u826f\u597d\u7cb5\u8a9e\u512a\u5148; \u4e00\u822c\u82f1\u8a9e; \u61c2\u8b80\u5beb\u4e2d\u6587; \u61c2\u8b80\u5beb\u82f1\u6587; \u61c2QuickBooks; \u61c2\u5168\u76e4\u6703\u8a08; \u61c2\u4e2d\u6587\u6253\u5b57; Self-motivated, responsible, able to work independently, Immediate availability is preferred\n\n\u5f85\u9047 :\u6bcf\u6708$18,000 - $22,000, \u6709\u96d9\u7ce7, \u5e74\u504710\u5929, \u9280\u884c\u5047\u671f, \u91ab\u7642\u798f\u5229\u53ca\u5e74\u7d42\u734e\u91d1, \u661f\u671f\u4e00\u81f3\u4e94: \u4e0a\u53489\u6642\u81f3\u4e0b\u53486\u6642, \u6bcf\u9031\u5de5\u4f5c5\u5929, \u6bcf\u5929\u5de5\u4f5c 9 \u5c0f\u6642\n\n\u7533\u8acb\u9808\u77e5 :\u6c42\u8077\u8005\u53ef\u96fb\u90f5(Apply Now)\u5c65\u6b77\u8868\u7d66EL CONCEPTO LTD.\u3002\u5982\u8981\u7d22\u53d6\u6536\u96c6\u500b\u4eba\u8cc7\u6599\u8072\u660e, \u8acb\u8207\u96f7\u5148\u751f(Email)\u806f\u7d61\u3002\n\n", "employment_types": ["Full Time", "Contract"], "selling_points": ["Qualified Accountant 5 years+ Experience", "High Growth Company - Great culture", "Growth opportunity: APAC Multi Entity Exposure"], "locations": ["Ngau Tau Kok"], "categories": ["Accounting", "Accountant", "Finance / Accounting Manager", "Taxation"], "post_time": "2022-01-07T10:40:36Z", "salary": {"currency": "HKD", "max": 44999, "min": 30000, "period": "monthly", "term": null}, "salary_visible": true, "title_keywords": ["finance manager"], "responsibilities": [], "requirements": {"degrees": [], "majors": [], "languages": [], "language_level": [], "hard_skills": [], "soft_skills": ["self-motivated", "work independently", "responsible"], "languages_combined": []}, "experience_required": {"duration": [], "field": []}}, {"job_id": "100003009022836", "location_code": "hk", "company": "Page Executive", "job_title": "Global Head of Tax, Insurance Start Up (role is based in Asia)", "description": "Job Description & Summary\n\n\n\nA career in our Corporate Transfer Pricing practice, within Transfer Pricing services, will provide you with the opportunity to help our clients develop compliant, tax efficient structures that help advance their business goals. You\u2019ll focus on all aspects of documentation planning, dispute resolution, and advance pricing agreements.\n\nOur team helps our clients with a range of transfer pricing solutions including compliance, advancing pricing agreements, and defence and dispute resolution. You\u2019ll focus on helping clients with business transformation that ultimately helps advance their business goals.\n\n\n\nJob Description &\u00a0\u00a0 Responsibilities\n\nProvide HK and China transfer pricing consulting services to clients in one of the industries:- retail, financial services, trading, technology, manufacturing, transportation or logistics;\nWork with a team of professionals on cross-teams and regional transfer pricing projects; and\nStructured training will be provided equipping you to become a professional advisor.\n\n\n\n\nRequirements\n\nBachelor degree in Accounting, Economics or Finance;\nMinimum 2 years of relevant experience in transfer pricing either in an accounting firm or industry;\nAbility to interpret and analyse financial statements and a general aptitude for quantitative analysis;\nGood command of both spoken and written English and Chinese; Mandarin is a plus\n\n\n\n\nThe PwC China (including Mainland China, Hong Kong, Macau) does not accept unsolicited resumes from search firm recruiters. Fees will not be paid in the event a candidate submitted by a recruiter without an agreement in place is hired; such resumes will be deemed the sole property of PwC China (including Mainland China, Hong Kong, Macau). PwC China (including Mainland China, Hong Kong, Macau) is an equal opportunity employer. All aspects of employment will be based on merit, competence, performance, and business needs. We do not discriminate on the basis of race, color, religion, marital status, age, national origin, ancestry, physical, medical condition, genetic information, gender, sexual orientation, gender identity or expression, veteran status, or any other status protected under the local law.\n\n\n\n", "employment_types": ["Full Time", "Permanent"], "selling_points": ["Join one of the largest Tech Startup in the world", "Entrepreneurial and fast-paced environment", "Excellent and flexible working culture"], "locations": ["Not Specified"], "categories": ["Accounting", "Taxation"], "post_time": "2022-01-05T06:40:02Z", "salary": {"currency": null, "max": null, "min": null, "period": "monthly", "term": null}, "salary_visible": false, "title_keywords": [], "responsibilities": ["tax", "business goals", "consulting", "compliance", "teams", "develop", "resolution", "logistics", "documentation", "planning"], "requirements": {"degrees": ["degree", "bachelor"], "majors": ["finance", "economics", "accounting"], "languages": ["english", "chinese", "mandarin"], "language_level": ["good command"], "hard_skills": ["analysis", "plus"], "soft_skills": [], "languages_combined": [{"language": "english", "language_level": ["good command"]}, {"language": "chinese", "language_level": ["good command"]}, {"language": "mandarin", "language_level": []}]}, "experience_required": {"duration": ["minimum 2 years"], "field": ["accounting", "relevant experience"]}}, {"job_id": "100003009025351", "location_code": "hk", "company": "Grand Alliance Asset Management Ltd", "job_title": "Compliance & Accounting Officer", "description": "We are currently seeking for a Global Head of Tax for one of our top-tier Insurance Clients. This role will provide you with the opportunity to take up the lead role for the Global Tax team, looking after multiple jurisdictions across the globe including Asia, US and Europe.\n\nClient Details\n\nOur client is one of the largest InsurTech in the world, serving customers across multiple markets in Asia, Europe and North America. They provide a digital platform to connect customers, insurers and intermediaries to provide better coverage, more effective communications and in-depth analysis of customer's needs.\n\nDescription\n\nReporting to the Global CFO, you are responsible for:\n\nProviding tax advice on M&A, Joint Ventures, partnerships and investments\nDriving global tax strategy and structuring advice\nMaking optimisation strategies and changes across multiple markets i.e. North America, Europe and Asia\nPartner with finance leaders to discuss about cross-border tax issues\nKeep updated on international tax developments and best practices\nWorking closely with tax authorities across various jurisdictions\nMonitoring tax reporting and compliance processes\n\nProfile\n\nWhat we are looking for:\n\nBig 4 trained tax accountant with over 10 plus years experience in a senior tax role\nQualified accountant\nGood knowledge in insurance, financial services and etc. will be advantageous\nAbility to work independent or in a small team environment\nMust be comfortable working in a start-up culture and environment\nProactively partner with leaders across the world\nExcellent communication skills\n\nJob Offer\n\nJoin one of the largest InsurTech in the world\nEntrepreneurial and fast-paced environment\nExcellent and flexible working culture\nAttractive salary packages i.e. equity\n\nTo apply online please click the 'Apply' button below. For a confidential discussion about this role please contact Jeremy Lam on +852 2848 4711.", "employment_types": ["Full Time", "Permanent"], "selling_points": [], "locations": ["Central"], "categories": ["Accounting", "Taxation", "Professional Services", "Legal & Compliance", "Banking / Finance", "Risk Management"], "post_time": "2022-01-06T04:12:47Z", "salary": {"currency": null, "max": null, "min": null, "period": "monthly", "term": null}, "salary_visible": false, "title_keywords": ["accounting officer"], "responsibilities": ["tax", "reporting", "analysis", "monitoring", "compliance", "digital platform", "communication", "contact", "insurance"], "requirements": {"degrees": [], "majors": [], "languages": [], "language_level": [], "hard_skills": ["small", "analysis", "plus"], "soft_skills": ["flexible", "communication skills", "independent", "responsible", "fast-paced environment"], "languages_combined": []}, "experience_required": {"duration": [], "field": ["big 4"]}}]