[{"job_id": "100003009051923", "location_code": "hk", "company": "Octopus Holdings Limited", "job_title": "Assistant Manager, Treasury", "description": "Job Responsibilities:\n\nMonitor daily cash-flow and daily transfer to group bank accounts\nAssist in cash-flow forecasting on a weekly/monthly basis\nEnsure the compliance of Treasury policy with regulatory requirement under SVF\nUpdate policies and procedures for Treasury function and review internal controls and risk management for Treasury\nPrepare regular treasury and financial analytic reports for management review\nSupport daily settlement to service providers\nSupport treasury related ad hoc projects and banking administrative work\n\nRequirements:\n\nA degree holder in Accounting, Finance or related discipline\nMinimum 5 years of work experience in cash-flow forecast, pooling and fixed income product management; experience in corporate treasury or cash management in banking industry is a plus\nQualified accountant\nKnowledgeable in Microsoft Office applications (Excel/Word/PowerPoint); experienced in Oracle Financials, Discoverer, Excel4Apps, or Oracle Treasury application is preferred\nFamiliar with settlement using e-banking systems; experience in system implementation is a plus\nGood communication and cooperation skills\nSelf-motivated, multi-tasking and is able to work under pressure\nCandidate with less experience will be considered as Treasury Analyst\nWe offer successful candidate an attractive remuneration package and excellent career prospects. Interested parties please send your resume, present and expected salary, contact details and quoting the reference number by clicking \"Apply Now\"Visit our web site:\u00a0http://www.octopus.com.hk/\n\nThe personal data collected will be used for recruitment purposes only. If you are not contacted by us within six weeks, you may consider your application unsuccessful. Personal data with an unsuccessful applicant will be destroyed 12 months after rejection of the application. During this retention period, you have the right to request for correction or destruction of your personal data at any time. Any request for the correction or destruction of personal data should be addressed in writing to our Human Resources & Administration Department.\n\nOctopus is an equal opportunity employer and all employment decisions and Human Resources policies are administered; especially those relating to recruitment & selection, compensation & benefits, promotion & transfer, training & development and termination & redundancy; without discrimination on the basis of age, race, colour, religion, sex, national origin, marital status, pregnancy, physical and mental disability and family status but on genuine occupational qualification, job performance, employees\u2019 ability and internal/ external relativities.", "employment_types": ["Full Time", "Permanent"], "selling_points": ["Monitor daily cash-flow and daily transfer", "Qualified accountant", "Minimum 5 years of work experience"], "locations": ["Kowloon Bay"], "categories": ["Accounting", "Treasurer"], "post_time": "2022-01-17T01:32:40Z", "salary": {"currency": null, "max": null, "min": null, "period": null, "term": null}, "salary_visible": false, "title_keywords": ["assistant manager,"], "responsibilities": ["management", "administrative work", "policies", "compliance", "monitor", "procedures", "review", "reports", "ad hoc projects", "banking", "forecasting", "management review"], "requirements": {"degrees": ["degree holder"], "majors": ["finance", "accounting"], "languages": [], "language_level": [], "hard_skills": ["excel", "plus", "microsoft office", "word", "powerpoint", "system implementation", "oracle"], "soft_skills": ["communication", "self-motivated", "multi-tasking", "work under pressure"], "languages_combined": []}, "experience_required": {"duration": ["minimum 5 years"], "field": ["product management", "banking industry", "management"]}}, {"job_id": "100003009053614", "location_code": "hk", "company": "\u601d\u8b00\u96c6\u5718\u6709\u9650\u516c\u53f8", "job_title": "Treasury clerk", "description": "Responsibilities1. Handle daily payment to the bank's accounts and affairs\n2. Prepare receipt, payment and journal vouchers, cheques and bank transfer and bank reconciliation\n3. Posting and reconciling Petty Cash\n4. Preparation of monthly budget cashflow\n5. Handle ad-hoc assignment as requiredRequirements1. Form 7 and with LCC Higher or similar qualification\n2. At least\u00a03\u00a0years experience in AP, AR\n3. Proficiency in MS Excel,\u00a0MS Word\n4. Good communication skill in English and\u00a0Chinese\n5. Strong sense of responsibility, high accuracy, well-organized, hard working and under pressure\n6. Immediate available is highly desired", "employment_types": ["Full Time"], "selling_points": ["Handle  payment to the bank's accounts and affairs", "Preparation of monthly budget cashflow", "Posting and reconciling Petty Cash"], "locations": ["Shatin Area"], "categories": ["Accounting", "Accountant", "Accounting Clerk / Supervisor", "Treasurer"], "post_time": "2022-01-17T07:14:34Z", "salary": {"currency": null, "max": null, "min": null, "period": "monthly", "term": null}, "salary_visible": false, "title_keywords": ["clerk"], "responsibilities": ["ad-hoc", "journal vouchers", "ap", "ar", "budget", "bank reconciliation", "communication", "payment", "cheques"], "requirements": {"degrees": [], "majors": [], "languages": ["english", "chinese"], "language_level": ["good"], "hard_skills": ["ap", "ar", "ms excel", "lcc", "ms word"], "soft_skills": ["under pressure", "sense of responsibility", "hard working", "communication skill", "well-organized"], "languages_combined": [{"language": "english", "language_level": ["good"]}, {"language": "chinese", "language_level": ["good"]}]}, "experience_required": {"duration": ["at least 3 years"], "field": []}}, {"job_id": "100003009054469", "location_code": "hk", "company": "Honor Information Technology Co., Limited", "job_title": "Treasury & Auditors - HK Finance dept.", "description": "Position Description:\n\nResponsible for the Hong Kong subsidiary's capital plan and budget forecast, to ensure the safety of the treasury, and timely feedback the capital budget forecast to the headquarters cash team;\nResponsible for financial support\uff1b\nResponsible for the Hong Kong subsidiary's budget review and budget model optimization, and formulate the FX control plan;\nResponsible for local accounting and audit support\u3002\n\nWork Experience Requirements:\n\nBachelor degree or above in accounting/finance/business or other related majors\nHands on experience and proven track record of cash and liquidity management\nExcellent analytical, interpersonal and presentation skills\nGood command of English/mandarin and communication skills\nGood problem solving capability, and coordination skills\nHave a thorough understanding of derivatives, hedging, investments, bank account management, and international funds flows.\nStrong local bank relationships\n\nPersonal Characteristics:\n\nGood communication skills, able to work under pressure.\n\nAdditional Information:\n\n\u00a0\u00a0\u00a0\u00a0\u00a0\u00a0\u00a0 Monday to Friday-office hour\n\u00a0\u00a0\u00a0\u00a0\u00a0\u00a0\u00a0 Work location: Tsim Sha Tsui\n\u00a0\u00a0\u00a0\u00a0\u00a0\u00a0\u00a0 Medical Insurance\n\u00a0\u00a0\u00a0\u00a0\u00a0\u00a0\u00a0 We offer attractive remuneration package and excellent career opportunities to the right candidates. Interested parties please send your full resume with available, current and expected salary to The Human Resources Department, Honor Information Technology Co., Limited\nExcellent conditions, salary can be negotiated face to face", "employment_types": ["Full Time", "Permanent"], "selling_points": ["Opportunity for career progression", "International exposure", "Stable working environment"], "locations": ["Tsim Sha Tsui"], "categories": ["Accounting", "Audit", "Treasurer"], "post_time": "2022-01-17T09:40:58Z", "salary": {"currency": null, "max": null, "min": null, "period": "monthly", "term": null}, "salary_visible": false, "title_keywords": [], "responsibilities": ["control", "management", "review", "budget", "audit", "communication", "forecast", "plan", "coordination", "work under pressure"], "requirements": {"degrees": ["degree or above", "bachelor"], "majors": ["business", "finance", "accounting"], "languages": ["english", "mandarin"], "language_level": ["good command"], "hard_skills": ["problem solving"], "soft_skills": ["communication skills", "coordination skills", "responsible", "timely", "problem solving", "presentation skills", "hands on", "thorough", "interpersonal", "work under pressure"], "languages_combined": [{"language": "english", "language_level": ["good command"]}, {"language": "mandarin", "language_level": ["good command"]}]}, "experience_required": {"duration": [], "field": ["management"]}}, {"job_id": "100003009054920", "location_code": "hk", "company": "Sun Hung Kai Properties Ltd", "job_title": "ASSISTANT TREASURY MANAGER", "description": "Requirements:\n\n\nBachelor\u2019s degree in banking, finance, accounting or related disciplines preferred\nMinimum 10 years\u2019 relevant experience in treasury or settlement in banking and/or sizable organizations.\nSensitive to numbers and with good interpersonal skills\nProven English proficiency, fluency in Putonghua preferred\nFamiliar with PC software e.g. MS Word, Excel, PowerPoint\n\nResponsibilities:\n\n\nTake charge of money market and assist in other treasury functions\nEnsure timely settlement of capital market transactions and liaison with treasury team for PRC operations\nCo-ordinate cashflow monitoring & follow-up on execution of syndicated loans, bilateral loans, bonds\nPrepare reports for management review\n\nGood remuneration and attractive fringe benefits will be offered to the successful applicant. Interested parties please apply with full resume, present and expected salary, available date by clicking \"Apply Now\".\n\nWe are an equal opportunity employer and welcome applications from all qualified candidates. All personal data collected will be used for recruitment purpose only.\u00a0 Applicants not hearing from us within 3 months may consider their applications unsuccessful.\u00a0 All personal data collected will be destroyed within 24 months.", "employment_types": ["Full Time", "Permanent"], "selling_points": ["10 yrs' exp in treasury or settlement in banking", "Take charge of money market", "Co-ordinate cashflow monitoring"], "locations": ["Wan Chai"], "categories": ["Accounting", "Treasurer", "Banking / Finance", "Corporate Finance", "Treasury"], "post_time": "2022-01-17T13:57:03Z", "salary": {"currency": null, "max": null, "min": null, "period": null, "term": null}, "salary_visible": false, "title_keywords": ["manager", "assistant"], "responsibilities": ["operations", "monitoring", "transactions", "management review", "prepare reports", "timely settlement"], "requirements": {"degrees": ["degree", "bachelor"], "majors": ["related disciplines", "finance", "accounting"], "languages": ["putonghua", "english"], "language_level": ["fluency", "proficiency"], "hard_skills": ["powerpoint", "pc", "excel", "ms word"], "soft_skills": ["sensitive to numbers", "interpersonal skills"], "languages_combined": [{"language": "putonghua", "language_level": ["fluency"]}, {"language": "english", "language_level": ["proficiency"]}]}, "experience_required": {"duration": ["minimum 10 years"], "field": ["relevant experience", "banking"]}}, {"job_id": "100003009052261", "location_code": "hk", "company": "China Mobile International Limited", "job_title": "Assistant Treasury Manager/ Senior Accountant, Revenue & Treasury (CMIJD-1111-RTFINHK)", "description": "Job Responsibilities:\n\nManage bank account opening/ closing/ signature updates for Hong Kong and overseas entities\nResponsible for online banking platforms setting\nHandle bank transactions including loans, LC, guarantees\nPlan and modernize treasury process and policy\nResponsible for liaison with internal and external auditors\nEnsure the compliance of Treasury policy and SOX\nAssist in formulating and implementing hedging plans and its execution\nHandle ad hoc projects assigned\n\nJob Requirements:\n\nDegree holder in Accounting, Finance or related disciplines\nQualified Accountant under ACCA/HKICPA\nAt least 5 years relevant treasury management experience, preferably from sizeable multinational corporations or financial institutions\nSolid experience in cash management and foreign exchange\nGood knowledge in hedging, risk management, financial products and derivatives Knowledge in accounting for derivatives and hedging preferred\nProficiency in excel VBA, Powerpoint, Word (Chinese & English),\nPositive, self-motivated, good analytical skills and communication skills\nGood interpersonal skills\nGood command of spoken and written Chinese and English, proficiency in Putonghua is a MUST\nCandidates with less experience would be considered as Senior Accountant\n\nInterested parties please send your full resume with current & expected salary\u00a0by clicking \"Apply Now\".\n\nAll personal data provided will be used for consideration of your job application only.\n\nManage bank account opening/closing/signature updates for Hong Kong and overseas entities", "employment_types": ["Full Time", "Permanent"], "selling_points": ["Plan & modernize treasury process and policy", "Manage HK & Overseas bank accounts & platforms", "Formulate & implement hedging plans & execution"], "locations": ["Kwai Hing"], "categories": ["Accounting", "Accountant", "Finance / Accounting Manager", "Treasurer"], "post_time": "2022-01-17T02:36:06Z", "salary": {"currency": null, "max": null, "min": null, "period": "monthly", "term": null}, "salary_visible": false, "title_keywords": ["manager", "senior accountant", "assistant"], "responsibilities": ["account opening", "compliance", "transactions", "ad hoc projects", "plan", "banking", "plans", "external auditors"], "requirements": {"degrees": ["degree holder"], "majors": ["related disciplines", "finance", "accounting"], "languages": ["putonghua", "english", "chinese"], "language_level": ["proficiency", "good command"], "hard_skills": ["excel", "acca", "vba", "word", "powerpoint", "analytical skills", "hkicpa", "exchange"], "soft_skills": ["communication skills", "self-motivated", "analytical skills", "interpersonal skills", "positive"], "languages_combined": [{"language": "putonghua", "language_level": ["proficiency", "good command"]}, {"language": "english", "language_level": ["good command"]}, {"language": "chinese", "language_level": ["proficiency", "good command"]}]}, "experience_required": {"duration": ["at least 5 years"], "field": ["management", "financial institutions", "senior accountant"]}}, {"job_id": "100003009050624", "location_code": "hk", "company": "Robert Walters (HK)", "job_title": "Treasury Manager", "description": "One of the sizable family offices in HK is looking for a Treasury Manager to join their high performing team.\n\nFamily office\nTreasury focus\nCPA qualified\n\n\nResponsibilities\n\nPrepare/review cash flow forecast in coordination with group treasurer for cash flow management and plan for funding requirements.\nArrange funding and banking facilities with HK and international banks to support the Group's fast growing investment activities\nMake recommendation to management in short term excess cash investments by analyzing various investments opportunities to maximize return at acceptable risk level.\nLiaise with banks, financial institutions, commodity counter-parties for financing arrangements including enquires of the group, negotiation, documentation, and execution of facility agreement, guarantees etc.\nManage general banking matters including bank accounts opening and signing pattern policy.\nAssist with overall treasury process improvement and implementation of treasury systems applications.\n\nRequirements:\n\nDegree in Finance, Accounting or related discipline\nAt least 10 years of treasury experience in sizable organizations\nCPA qualified, or equivalent qualifications\nFamiliar with treasury products, loan terms and structures, cash flow forecast and management reporting\nStrong analytical skills and sound business judgment for effective decision making\nSelf motivated team leader with excellent interpersonal and presentation skills\nFluency in both written and spoken English and Chinese (Putonghua and Cantonese)", "employment_types": ["Full Time", "Permanent"], "selling_points": ["HK sizable family office", "Treasury focus", "CPA qualified"], "locations": ["Not Specified"], "categories": ["Accounting", "Treasurer"], "post_time": "2022-01-14T11:00:04Z", "salary": {"currency": "HKD", "max": 69999, "min": 55000, "period": "monthly", "term": null}, "salary_visible": true, "title_keywords": ["manager"], "responsibilities": ["management", "documentation", "make recommendation", "coordination with", "review", "banking", "implementation", "systems", "cash flow", "forecast", "plan", "liaise with"], "requirements": {"degrees": ["degree"], "majors": ["finance", "accounting"], "languages": ["cantonese", "putonghua", "english", "chinese"], "language_level": ["fluency"], "hard_skills": ["cpa", "analytical skills"], "soft_skills": ["analytical skills", "self motivated", "presentation skills", "interpersonal", "decision making"], "languages_combined": [{"language": "cantonese", "language_level": []}, {"language": "putonghua", "language_level": []}, {"language": "english", "language_level": ["fluency"]}, {"language": "chinese", "language_level": ["fluency"]}]}, "experience_required": {"duration": ["at least 10 years"], "field": []}}, {"job_id": "100003009053384", "location_code": "hk", "company": "YOOV Internet Technology (HK) Limited", "job_title": "Assistant Accounting Officer (5-day work)", "description": "To cope with our business growth, we are currently looking for a high calibre candidate to join us as an Assistant Accounting Officer, assisting in Accounting & Admin Department.\n\nResponsibilities\n\nResponsible for daily accounting operations including AR/AP, general entries, bills and payments, bank reconciliation\nAssist in month end closing and preparation of financial report\nProcess payroll and tax affairs\nMaintain proper and systematic filing system\nPerform ad-hoc assignments when required\n\nRequirements\n\nDiploma or above, major in Accounting or related discipline\n1-2 years relevant working experience\nEnthusiastic, detail-minded, mature with positive attitude and a good team player\nGood command of both spoken & written English and Chinese\u00a0\nProficiency in MS Office applications including Excel, Work. Knowledge in Xero would be an advantage\nImmediately available is highly preferred\n\nInterested candidates please send your job application to our HR Department by \u201cAPPLY NOW\u201d. Please indicate the details of your working experience, current and expected salary, and your date of availability in your CV.\n\n(Only shortlisted candidates will be contacted)\u00a0\n\nPersonal Information Collection Statement (PICS)\n\nThe personal data collected will be used by our member(s) of the recruitment team for recruitment purpose only. It is our policy to retain the personal data of unsuccessful applicants for future recruitment purposes for a period of 3 months. When there are vacancies in our subsidiary or associate companies during that period, we may transfer the candidate\u2019s application to them for consideration of employment. And, all information will be kept confidential during that period and be destroyed after use.\n", "employment_types": ["Full Time", "Permanent"], "selling_points": ["Accounting Officer, Asst Acc Officer, Accounting", "Full set, Payroll, Tax", "Fast Growing Company with Good Prospect"], "locations": ["Kwun Tong"], "categories": ["Accounting", "Accounting Clerk / Supervisor", "Treasurer", "Others", "Student / Fresh Graduate / No Experience"], "post_time": "2022-01-17T06:54:08Z", "salary": {"currency": null, "max": null, "min": null, "period": "monthly", "term": null}, "salary_visible": false, "title_keywords": ["assistant accounting officer"], "responsibilities": ["ap", "tax", "month end closing", "ar", "ad-hoc assignments", "daily accounting operations", "bank reconciliation", "maintain", "payments", "financial report", "payroll"], "requirements": {"degrees": ["diploma or above"], "majors": ["accounting"], "languages": ["english", "chinese"], "language_level": ["good command"], "hard_skills": ["excel", "xero", "ms office"], "soft_skills": ["detail-minded", "good team player", "mature", "positive attitude", "enthusiastic"], "languages_combined": [{"language": "english", "language_level": ["good command"]}, {"language": "chinese", "language_level": ["good command"]}]}, "experience_required": {"duration": ["1-2 years"], "field": ["relevant working experience"]}}, {"job_id": "100003009051526", "location_code": "hk", "company": "Ma Belle Jewellery Co Ltd", "job_title": "Assistant Accountant/ Accountant", "description": "Responsibilities:\n\nReconcile daily sales transactions\nHandle daily Accounts Payable/ Receivable operations\nPrepare daily sales reports & monthly stock take\nHelp to prepare month-end reports\nHandle accounting data entry and maintain good filing system\n\nRequirements:\n\nDiploma or above and at least LCC 2nd level\n3 years or above solid experience in accounting\nKnowledge in Flex System is an added advantage\nGood team player, Self-motivated, independent, well organized and good interpersonal skills\nGood command of English and Chinese\nImmediate available or short notice is preferred\n\nRecent graduates will be considered\n\nAttractive remuneration package will be offered to the right candidate. Please email full resume with current and expected salary to us\n\nPersonal data collected will be used for recruitment purposes only and will be treated in strict confidence.\u00a0 Applicants not invited for interview within 16 weeks may consider their applications unsuccessful and all information submitted will be destroyed.", "employment_types": ["Full Time", "Permanent"], "selling_points": ["Reconcile daily sales transactions, stock take", "Handle daily Accounts Payable/Receivable operation", "Prepare daily sales reports & month-end reports"], "locations": ["Tin Hau"], "categories": ["Accounting", "Accounting Clerk / Supervisor", "Treasurer", "Others"], "post_time": "2022-01-16T08:05:51Z", "salary": {"currency": null, "max": null, "min": null, "period": null, "term": null}, "salary_visible": false, "title_keywords": ["accountant", "assistant accountant"], "responsibilities": ["sales reports", "data entry", "operations", "month-end", "transactions", "stock take", "maintain", "reports", "accounts payable"], "requirements": {"degrees": ["diploma or above"], "majors": [], "languages": ["english", "chinese"], "language_level": ["good command"], "hard_skills": ["lcc", "flex system"], "soft_skills": ["good team player", "self-motivated", "independent", "confidence", "well organized", "interpersonal skills"], "languages_combined": [{"language": "english", "language_level": ["good command"]}, {"language": "chinese", "language_level": ["good command"]}]}, "experience_required": {"duration": ["3 years"], "field": ["accounting"]}}, {"job_id": "100003009050446", "location_code": "hk", "company": "Chevalier Group - Corporate Office", "job_title": "Accountant - Treasury", "description": "Our\u00a0Accounts Department is now inviting high calibre persons to apply for this position :\n\n\n\nResponsibilities\n\nWorking in our Corporate Accounts Department, the incumbent will be responsible for\n\n\nHandle treasury related tasks including monitor daily cashflow, prepare cashflow projections, bank loan administration, bank account (HK/PRC) maintenance, etc.\nPrepare monthly treasury and investment reports\nPrepare bank instructions and assist in monitoring liquidity of the Group and execute short-term cash investment\nAssist in ad-hoc tasks when assigned\n\nRequirements\n\nDegree holder or above in Accounting / Finance or related disciplines\n3 - 5 years' working experience in accounting or treasury function, with knowledge in trade finance is preferred\nStrong interpersonal and multi-tasking skills\nProficient in MS Office such as Excel, PowerPoint and Chinese word processing\nGood command of written and spoken English, Chinese and Putonghua\n\nCandidate with less experience will be considered for the position of Assistant Accountant\n\n\n\nAttractive remuneration package will be offered to the right candidate. Interested parties, please send us your resume with current and expected salary by clicking \"Apply Now\" or mail to:\n\nThe Human Resources Manager, Chevalier Group, 22F, Chevalier\u00a0Commercial Centre,\u00a08\u00a0Wang Hoi\u00a0Road, Kowloon Bay, Hong Kong\n\nWe are an equal opportunity employer and welcome applications from all qualified candidates. Personal data collected would be used for recruitment purpose only.", "employment_types": ["Full Time", "Permanent"], "selling_points": ["Knowledge in trade finance", "Monitor daily cash flow, prepare cash flow project", "Degree holder or above in Accounting / Finance"], "locations": ["Kowloon Bay"], "categories": ["Accounting", "Accountant", "Treasurer", "Others"], "post_time": "2022-01-14T10:26:52Z", "salary": {"currency": null, "max": null, "min": null, "period": null, "term": null}, "salary_visible": false, "title_keywords": ["accountant"], "responsibilities": ["maintenance", "ad-hoc tasks", "monitoring", "monitor", "reports", "administration"], "requirements": {"degrees": ["degree holder"], "majors": ["related disciplines", "finance", "accounting"], "languages": ["putonghua", "english", "chinese"], "language_level": ["good command", "proficient"], "hard_skills": ["excel", "chinese word processing", "powerpoint", "ms office"], "soft_skills": ["multi-tasking skills", "interpersonal"], "languages_combined": [{"language": "putonghua", "language_level": ["good command"]}, {"language": "english", "language_level": ["good command"]}, {"language": "chinese", "language_level": ["good command", "proficient"]}]}, "experience_required": {"duration": ["3 - 5 years"], "field": ["finance", "accounting"]}}, {"job_id": "100003009051027", "location_code": "hk", "company": "The Wharf Group", "job_title": "Treasury (Banking) Manager", "description": "Responsibilities\u00a0:\n\nArranging bank loans and bonds issuance\nResponsible for banking liaison, agreement negotiation, and completing documentation for bank loan, bond, MTN program update and ISDA documents\nPreparing regular and ad hoc reports and analysis for management review\nAanlyzing market data and recommend solutions for risk management or cost saving\n\nRequirements :\n\nBachelor Degree in accounting, finance or related disciplines; CPA is preferred\nMinimum 7 years solid experience in corporate financing or banking\nProactive, analytical and detail-minded with good communication and interpersonal skills\nGood business sense and problem-solving skills\nAble to work under pressure and meet tight deadlines\nProficiency in MS Excel, Word and PowerPoint\nProficiency in English and Chinese\n\n\nWe work 5 days per week.\n\n\nInterested parties, please click \"APPLY NOW\" and attach with your application letter and full resume.\n\n\nFor further information of the Wharf Group, please visit our website: www.wharfholdings.com", "employment_types": ["Full Time", "Permanent"], "selling_points": [], "locations": ["Tsim Sha Tsui"], "categories": ["Accounting", "Treasurer", "Banking / Finance", "Corporate Finance", "Treasury"], "post_time": "2022-01-15T01:17:13Z", "salary": {"currency": null, "max": null, "min": null, "period": null, "term": null}, "salary_visible": false, "title_keywords": ["manager"], "responsibilities": ["management", "cost", "ad hoc", "analysis", "reports", "banking", "documentation", "market data", "management review"], "requirements": {"degrees": ["degree", "bachelor"], "majors": ["related disciplines", "finance", "accounting"], "languages": ["english", "chinese"], "language_level": ["proficiency"], "hard_skills": ["word", "powerpoint", "cpa", "ms excel", "problem-solving skills"], "soft_skills": ["detail-minded", "meet tight deadlines", "business sense", "communication and interpersonal skills", "problem-solving skills", "proactive", "work under pressure"], "languages_combined": [{"language": "english", "language_level": ["proficiency"]}, {"language": "chinese", "language_level": ["proficiency"]}]}, "experience_required": {"duration": ["minimum 7 years"], "field": ["financing", "banking"]}}, {"job_id": "100003009052341", "location_code": "hk", "company": "China Mobile Hong Kong \u4e2d\u570b\u79fb\u52d5\u9999\u6e2f", "job_title": "Accountant (Fixed Asset)", "description": "CHINA MOBILE HONG KONG COMPANY LIMITED\u00a0(\"CMHK\") is the wholly-owned subsidiary of China Mobile Limited (HKEx: 941) (NYSE: CHL), which ranks 65th on the Fortune Global 500.\n\nOur company strives to offer superior service experience and to become the preferable digital partner for customers. We are preserving an environment with trust, responsibility and caring. At CMHK, we commit to maximizing people\u2019s potential and paving the way toward success for every striver. We are now inviting high caliber professional to join us.\n\nDivision:\u00a0 Finance Division - Financial Accounting & Reporting Department\n\nIn this position, you will:\n\n\nAssist in month-end closing\nPrepare reports, reconciliations and schedules\nSupport daily operations on the fixed assets area\nCo-ordinate with business users on projects and accounting issues\nArrange and coordinate stocktaking and inspection of fixed assets\nOther ad hoc duties/projects assigned\nTo be successful in this position, you should meet the following requirements:\u00a0\n\nDegree in Accountancy or related disciplines\nOver 5 years relevant working experience, prior fixed asset management experience will be an advantage.\nProactive, independent, persistent and able to work under pressure to meet deadline\nGood knowledge in MS Excel/ Word, Macro / MS Access preferred\nExperience in using Oracle is an advantage\nGood command of both written and spoken English and Chinese (both Cantonese and Mandarin)\nImmediate Available is preferable\n\nWhen you work:\n\n\n5 days work\n8 hours/day\n\nWhat you enjoy:\n\nDouble pay\nDiscretionary Performance bonus\nLife insurance\nMedical insurance\nEducation subsidies\nBirthday gift\nMarriage leave\nBirthday leave\nStaff discount\n\nCMHK is committed to be an equal opportunity employer. We offer exceptional benefits package and the opportunity to work in a challenging environment. Personal data provided by applicants will be treated strictly in accordance with our personal data policy and for recruitment purposes only.\n\nPlease submit your application to us by clicking the APPLY NOW button and send your full resume with your availability, current and expected salary to us.", "employment_types": ["Full Time", "Permanent"], "selling_points": ["Double pay & Performance bonus", "Experience in using Oracle", "Good knowledge in MS Excel, Word and Access"], "locations": ["Kwai Hing"], "categories": ["Accounting", "Accountant", "Accounting Clerk / Supervisor", "Treasurer"], "post_time": "2022-01-17T02:57:40Z", "salary": {"currency": null, "max": null, "min": null, "period": null, "term": null}, "salary_visible": false, "title_keywords": ["accountant"], "responsibilities": ["ad hoc duties", "reporting", "schedules", "co-ordinate with", "work under pressure", "inspection", "coordinate", "reconciliations", "daily operations", "month-end closing", "prepare reports", "insurance", "asset management"], "requirements": {"degrees": ["degree"], "majors": ["related disciplines", "accountancy"], "languages": ["cantonese", "english", "chinese", "mandarin"], "language_level": ["good command"], "hard_skills": ["macro", "word", "mobile", "ms excel", "oracle"], "soft_skills": ["independent", "persistent", "committed", "proactive", "superior", "work under pressure"], "languages_combined": [{"language": "cantonese", "language_level": ["good command"]}, {"language": "english", "language_level": ["good command"]}, {"language": "chinese", "language_level": ["good command"]}, {"language": "mandarin", "language_level": ["good command"]}]}, "experience_required": {"duration": ["5 years"], "field": ["digital", "relevant working experience", "asset management"]}}, {"job_id": "100003009053487", "location_code": "hk", "company": "Global Life Immigration (HK) Limited", "job_title": "Accountant/ Assistant Accountant", "description": "Key Responsibilities\uff1a\n\n\u00a0Preparation of full set of accounts, financial report and management report\n\u00a0Responsible for daily accounting operation\n\u00a0Provide administrative and clerical support\n\u00a0Assist in ad hoc assignments\n\n\u00a0Requirements:\n\n\nF. 6 or above\n1-2 years accounting experience\nProficiency in MS Office application and Chinese Word Processing\nGood communication and presentation skill\nHardworking, good in team work, able to work under pressure\nGood in Chinese, English and Mandarin\nLess experience / Fresh graduate is also welcome\n\nWe offer\n\nWe offer attractive remuneration package, 5-day work, performance bonus, medical allowance, birthday leave and career prospects to successful candidates. \u00a0Interested parties please apply in full resume with your employment history, current\u00a0and expected salary, and click APPLY NOW.", "employment_types": ["Full Time", "Permanent"], "selling_points": ["F. 6 or above", "1-2 years accounting experience", "Attractive remuneration package"], "locations": ["Tsim Sha Tsui"], "categories": ["Accounting", "Accountant", "Accounting Clerk / Supervisor", "Treasurer"], "post_time": "2022-01-17T07:02:44Z", "salary": {"currency": null, "max": null, "min": null, "period": "monthly", "term": null}, "salary_visible": false, "title_keywords": ["accountant", "assistant accountant"], "responsibilities": ["full set of accounts", "financial report", "ad hoc assignments", "administrative and clerical support", "daily accounting", "management report"], "requirements": {"degrees": ["fresh graduate"], "majors": [], "languages": ["english", "chinese", "mandarin"], "language_level": ["proficiency", "good"], "hard_skills": ["presentation skill", "chinese word processing", "ms office"], "soft_skills": ["communication", "presentation skill", "hardworking", "work under pressure"], "languages_combined": [{"language": "english", "language_level": ["good"]}, {"language": "chinese", "language_level": ["proficiency", "good"]}, {"language": "mandarin", "language_level": ["good"]}]}, "experience_required": {"duration": ["1-2 years"], "field": ["accounting experience"]}}, {"job_id": "100003009047072", "location_code": "hk", "company": "Links International", "job_title": "Treasury Manager - FX & Hedging", "description": "Responsibilities:\n\nSupervise day-to-day treasury operation and cash management\nWorking closely with Finance team on project funding decisions and financial projections\nReview loan and funding documents\nManage foreign exchange and interest rate risk, and FX hedging across APAC\nPrepare and submit treasury reports for senior management review\nAdvise on tax issues regarding investments & M&A projects\nManage and liaise with banks for funding and investment decisions\nBeing a strong business partner with stakeholders across different regions\n\nRequirements:\n\nBachelor Degree in Accounting & Finance or related discipline\nAt least 5 years of experience in treasury, preferably in sizeable MNC and luxury retailer\nSolid experiences in Retail and FMCG related industries are highly preferred\nSmart, energetic person who is ambitious to strive for excellence\nExcellent command of both English and Cantonese\nExcellent communication and presentation\nDynamic personality with an analytical mindset", "employment_types": ["Full Time", "Permanent"], "selling_points": ["Guaranteed 13 months salary", "Work life balance", "Regional exposure"], "locations": ["Not Specified"], "categories": ["Accounting", "Chief Accountant", "Finance / Accounting Manager", "Treasurer"], "post_time": "2022-01-14T02:14:57Z", "salary": {"currency": "HKD", "max": 54999, "min": 45000, "period": "monthly", "term": null}, "salary_visible": true, "title_keywords": ["manager"], "responsibilities": ["tax", "management", "project funding", "review", "reports", "finance team", "liaise with", "senior management"], "requirements": {"degrees": ["degree", "bachelor"], "majors": ["finance", "accounting"], "languages": ["cantonese", "english"], "language_level": ["excellent"], "hard_skills": ["dynamic"], "soft_skills": ["communication", "energetic", "dynamic", "strive for excellence", "presentation"], "languages_combined": [{"language": "cantonese", "language_level": ["excellent"]}, {"language": "english", "language_level": ["excellent"]}]}, "experience_required": {"duration": ["at least 5 years"], "field": ["related", "retail", "fmcg"]}}, {"job_id": "100003009054921", "location_code": "hk", "company": "Eternity Consultants (HK) Ltd", "job_title": "Account Clerk / Senior Account Clerk - Trading (Fresh graduate will consider)", "description": "Trading\nJob Responsibilities:\n\nAccount Receivable, Account Payable\nPerform daily accounting functions including prepare voucher input and various payments\nAssist in projects and other ad hoc assignment\n\nJob Requirements :\n\nDiploma in Accounting\n2-4 year working experience in accounting field\u00a0\nFamiliar with Excel, Word and Chinese word processing\nInitiative, well-organised, hard working and willing to learn\n\nBenefit:\n\n5 days, bank holiday, medical scheme\n\n*Interested parties, please send full resume with current & expected salary & date available in MS WORD FORMAT ONLY to us\u00a0or fax to 3527 0634*\n\nWe are welcome applicants resend resumes to us even you have applied jobs in our company before.\n\nFor more jobs, please visit our website: www.hketernity.com\n\n(Personal data submitted are for recruitment purpose only.)", "employment_types": ["Full Time", "Permanent"], "selling_points": ["5 days, bank holiday, medical.", "F.7/+  w/ LCC Intermedicate/ Accounting Diploma", "2-4 year experience in accounting field"], "locations": ["Others"], "categories": ["Accounting", "Accounting Clerk / Supervisor", "Taxation", "Treasurer"], "post_time": "2022-01-17T13:57:23Z", "salary": {"currency": null, "max": null, "min": null, "period": "monthly", "term": null}, "salary_visible": false, "title_keywords": ["account clerk", "senior account clerk"], "responsibilities": ["daily accounting", "ad hoc assignment", "payments"], "requirements": {"degrees": ["diploma"], "majors": ["accounting"], "languages": ["chinese"], "language_level": [], "hard_skills": ["excel", "chinese word processing", "word"], "soft_skills": ["well-organised", "hard working", "willing to learn", "initiative"], "languages_combined": [{"language": "chinese", "language_level": []}]}, "experience_required": {"duration": ["2-4 year"], "field": ["accounting"]}}, {"job_id": "100003009044867", "location_code": "hk", "company": "China Mobile Hong Kong \u4e2d\u570b\u79fb\u52d5\u9999\u6e2f", "job_title": "Accounting Assistant (Revenue & Treasury)", "description": "CHINA MOBILE HONG KONG COMPANY LIMITED\u00a0(\"CMHK\") is the wholly-owned subsidiary of China Mobile Limited (HKEx: 941) (NYSE: CHL), which ranks 65th on the Fortune Global 500.\n\nOur company strives to offer superior service experience and to become the preferable digital partner for customers. We are preserving an environment with trust, responsibility and caring. At CMHK, we commit to maximizing people\u2019s potential and paving the way toward success for every striver. We are now inviting high caliber professional to join us.\n\nDivision:\u00a0 Finance Division -\u00a0Revenue & Treasury\n\nIn this position, you will:\n\n\nPrepare accounting entries of revenue, month end closing and reporting\nPrepare balance sheet and P&L schedules and reconciliations as well as follow up on any unusual items\nAssist in improving accounting process and leveraging technology to create efficiencies\nPerform other duties and ad hoc projects as required\nTo be successful in this position, you should meet the following requirements:\u00a0\n\n\nDegree in Accountancy/ Finance or business\u00a0related disciplines\n1 year relevant working experience with good knowledge of international accounting standards and practices preferred. Fresh graduate will also be considered.\nExperience in telecom industry and revenue accounting will be advantage\nProactive, independent, persistent and able to work under pressure to meet deadline\nGood knowledge in MS Excel/ Word, Macro / MS Access preferred\nAble to work on multiple priorities with accuracy and efficiency while keeping to deadlines\nGood command of both written and spoken English and Chinese (both Cantonese and Mandarin)\nImmediate Available is preferable\n\nWhen you work:\n\n\n5 days work\n8 hours/day\n\nWhat you enjoy:\n\nDouble pay\nDiscretionary Performance bonus\nLife insurance\nMedical insurance\nEducation subsidies\nBirthday gift\nMarriage leave\nBirthday leave\nStaff discount\n\nCMHK is committed to be an equal opportunity employer. We offer exceptional benefits package and the opportunity to work in a challenging environment. Personal data provided by applicants will be treated strictly in accordance with our personal data policy and for recruitment purposes only.\n\nPlease submit your application to us by clicking the APPLY NOW button and send your full resume with your availability, current and expected salary to us.", "employment_types": ["Full Time", "Permanent"], "selling_points": ["Double pay & Performance bonus", "Knowledge of international accounting standards", "Fresh graduate will also be considered"], "locations": ["Kwai Hing"], "categories": ["Accounting", "Accountant", "Accounting Clerk / Supervisor", "Treasurer"], "post_time": "2022-01-13T06:30:14Z", "salary": {"currency": null, "max": null, "min": null, "period": null, "term": null}, "salary_visible": false, "title_keywords": ["accounting assistant"], "responsibilities": ["reporting", "month end closing", "perform other duties", "schedules", "work under pressure", "p&l", "reconciliations", "ad hoc projects", "insurance", "balance sheet"], "requirements": {"degrees": ["degree", "fresh graduate"], "majors": ["related disciplines", "finance", "business", "accountancy"], "languages": ["cantonese", "english", "chinese", "mandarin"], "language_level": ["good command"], "hard_skills": ["mobile", "ms excel", "word", "macro"], "soft_skills": ["independent", "persistent", "committed", "proactive", "superior", "work under pressure"], "languages_combined": [{"language": "cantonese", "language_level": ["good command"]}, {"language": "english", "language_level": ["good command"]}, {"language": "chinese", "language_level": ["good command"]}, {"language": "mandarin", "language_level": ["good command"]}]}, "experience_required": {"duration": ["1 year"], "field": ["digital", "accounting", "relevant working experience"]}}, {"job_id": "100003009039715", "location_code": "hk", "company": "Michael Page", "job_title": "Treasury Manager - Listed Media Company 60K", "description": "Our client is a Hong Kong based Media company which has been established for over 50 years. They are now looking for a treasury Manager to take the lead in cash flow management and automation.\n\n\u5ba2\u6237\u7b80\u4ecb\n\nOur client is a Hong Kong based media company which has been established for over 50 years. They are now looking for a treasury Manager to take the lead in cash flow management and automation.\n\n\u5de5\u4f5c\u5185\u5bb9\n\nReporting to the Financial Controller, you are expected to:\n\n* Lead the team to handle cash management for the group\n\n* Prepare cash-flow forecasting on a weekly/ monthly basis and prepare regular treasury reports for management\n\n* Review and maintain internal control for the payment process\n\n* Assist finance transformation, system and process enhancement for cash management, cheque payment and treasury related matters\n\n* Assist in bank loans negotiation, loan documentation, loan drawdown and on-going loan compliance\n\n* Maintain good banking relationship\n\n\u7406\u60f3\u7684\u6c42\u804c\u8005\n\n* Bachelor's degree in accounting, finance or related disciplines\n\n* Professional accounting qualification is preferred\n\n* A minimum of 10 years of working experience in treasury function in sizable companies\n\n* Solid experience in finance/treasury system, e-payment platforms & automation improvement for the treasury function\n\n* Good command of spoken and written English and Cantonese\n\n\u798f\u5229\u5f85\u9047\n\nOur client offers a competitive package and an encouraging work environment focused on growth, excellence, and success with the company opportunities for career advancement.\n\nTo apply online please click the 'Apply' button below. For a confidential discussion about this role please contact Krystal Ho on +852 2848 9580.", "employment_types": ["Full Time", "Permanent"], "selling_points": ["Cash pooling and automation", "People management", "Min.10 years of treasury experience"], "locations": ["Not Specified"], "categories": ["Accounting", "Treasurer", "Others"], "post_time": "2022-01-11T10:38:27Z", "salary": {"currency": "HKD", "max": 69999, "min": 55000, "period": "monthly", "term": null}, "salary_visible": true, "title_keywords": ["manager"], "responsibilities": ["loan compliance", "reporting", "management", "review", "cash flow", "maintain", "reports", "payment", "payment process", "banking", "documentation", "contact", "forecasting", "internal control"], "requirements": {"degrees": ["degree", "bachelor"], "majors": ["related disciplines", "finance", "accounting"], "languages": ["cantonese", "english"], "language_level": ["good command"], "hard_skills": ["documentation", "sizable companies", "internal control"], "soft_skills": ["negotiation", "focused"], "languages_combined": [{"language": "cantonese", "language_level": ["good command"]}, {"language": "english", "language_level": ["good command"]}]}, "experience_required": {"duration": ["minimum of 10 years"], "field": ["finance"]}}, {"job_id": "100003009042521", "location_code": "hk", "company": "China Tonghai International Financial Limited", "job_title": "Treasury Officer", "description": "Job Responsibilities:\u00a0\n\nPrepare license corporation payment, cheques and online banking;\nAssist margin loan drawdown and repayment from various banks;\nAssist overall treasury function\n\nJob Requirements:\n\nDegree holder in Accountancy or equivalent;\nStudent member in HKICPA (or similar associations) is an advantage;\nMinimum 1 to 2 years' relevant working experience;\nExperience in treasury function is a plus;\nDiligent and proactive;\nNumerical sensitive with analytical mindset and meticulous attention to detail\u00a0\n\nWe offer attractive salary, benefits and 5-day workweek to the successful applicant.\u00a0 Please send your resume with\u00a0present\u00a0and\u00a0expected salary\u00a0to the Group Human Resources Manager. (Please quote the job reference number on the email subject line.)\u00a0\n\nPersonal Data collected will be used for recruitment purposes only.", "employment_types": ["Full Time", "Permanent"], "selling_points": ["5 days work week at Central", "Education allowance, medial, dental and insurance", "Financial services industry"], "locations": ["Central"], "categories": ["Accounting", "Accounting Clerk / Supervisor", "Treasurer", "Others"], "post_time": "2022-01-12T07:51:36Z", "salary": {"currency": null, "max": null, "min": null, "period": "monthly", "term": null}, "salary_visible": false, "title_keywords": ["officer"], "responsibilities": ["payment", "banking", "cheques"], "requirements": {"degrees": ["degree holder"], "majors": ["accountancy"], "languages": [], "language_level": [], "hard_skills": ["plus", "hkicpa"], "soft_skills": ["meticulous", "diligent", "attention to detail", "sensitive", "proactive"], "languages_combined": []}, "experience_required": {"duration": ["minimum 1 to 2 years"], "field": ["relevant working experience"]}}, {"job_id": "100003009039584", "location_code": "hk", "company": "KOS International Limited", "job_title": "Treasury, Senior Analyst", "description": "About the Client\n\nMy client is the top tier PE fund, they are looking for a Treasury talent to join their Accounting division.\n\nAbout the Role\n\nReporting to the Head of Finance, you will:\n\n\nHandle daily treasury transactions including deposit and loan administration, capital injection, cash pooling, fund transfer and intercompany loans\nPerform cash flow projection and liquidity positions analysis\nPrepare regular treasury reports to management\nAssist in updating Medium Term Note Programme and renewing Panda Bond Program, underlying issuances and fulfilling statutory reporting requirement\nMaintain banking relationships, assist in negotiating banking facilities and reviewing financing documents\n\nRequirements:\n\n\nBachelor Degree with major in Accounting, Finance or any related disciplines\nMinimum of 4 - 6 years' treasury experience in financial industry is preferred\nExcellent verbal and written communication skills - Mandarin and English\n\nClick \"Apply Now\" to apply for this position or call Becky Ng at +852 3180 4954 for a confidential discussion. All information collected will be kept in strict confidence and will be used for recruitment purpose only.", "employment_types": ["Full Time", "Permanent"], "selling_points": ["Handle daily treasury transactions", "Cash flow projection & liquidity positions", "Open to non FS candidates"], "locations": ["Not Specified"], "categories": ["Accounting", "Treasurer"], "post_time": "2022-01-11T10:09:39Z", "salary": {"currency": null, "max": null, "min": null, "period": "monthly", "term": null}, "salary_visible": false, "title_keywords": ["senior analyst"], "responsibilities": ["reporting", "management", "analysis", "transactions", "communication", "cash flow", "maintain", "reports", "recruitment", "banking", "administration"], "requirements": {"degrees": ["degree", "bachelor"], "majors": ["related disciplines", "finance", "accounting"], "languages": ["english", "mandarin"], "language_level": ["excellent"], "hard_skills": ["analysis", "pe"], "soft_skills": ["communication skills", "confidence"], "languages_combined": [{"language": "english", "language_level": ["excellent"]}, {"language": "mandarin", "language_level": ["excellent"]}]}, "experience_required": {"duration": ["minimum of 4 - 6 years"], "field": ["financial industry"]}}, {"job_id": "100003009045689", "location_code": "hk", "company": "Tung Wah College", "job_title": "Finance Manager, Finance Office  (TWC/22/009/FO/FM)", "description": "Duties\n\nThe appointee will be responsible for supporting the financial accounting function of the College.\u00a0 Main duties of the post will include:\n\nTo lead a team of staff and be responsible for providing a wide range of accounting services to the College including financial accounting and reporting, financial analysis, budgeting and forecasting;\nTo review current reporting practice and financial procedures to identify areas for continuous improvement;\nTo provide support and work closely with Schools and Units relating to financial accounting and reporting;\nTo implement internal controls relating to the accounting functions of the College and to ensure compliance with statutory requirements, accounting standards in Hong Kong, the College\u2019s policies, regulations and procedures;\nTo monitor the College\u2019s financial closing process, prepare a full set of financial statements, and work closely with external auditors for statutory audit;\nTo perform cash flow management and forecast planning;\nTo assist the implementation of system enhancement for new and existing systems of the Finance Office; and\nTo perform ad-hoc tasks as assigned by his/ her supervisors.\n\nRequirements\n\nApplicants should:\n\nPossess a recognized Bachelor\u2019s degree preferably in accounting or a related discipline and have recognized accounting professional qualifications;\nHave at least 8 years of relevant working experience in accounting, of which at least 3 years should be at supervisory level, preferably gained in tertiary education sector or self-financing institutions;\nHave a high level of proficiency in computer processing, preferably with knowledge in Accpac accounting software or SAP accounting system;\nHave a strong sense of responsibility and be able to work multi-task and independently to meet tight deadlines; and\nHave good communication, writing, interpersonal and problem-solving skills.\n\nSalary will be competitive and commensurate with qualifications and experience. Candidate with more experience may be considered for the post of Senior Manager or less experience may be considered for the post of Assistant Manager.\n\nTo apply, please submit your application letter, resume and a completed application form (available at http://www.twc.edu.hk/en/Administration_Units/hro/career/application_guideline) by mail to the Human Resources Office, Tung Wah College Cheung Kung Hai Memorial Building, 90A Shantung Street, Mongkok, Kowloon or email.\u00a0 Please quote the reference number of the post in the application letter and on the envelope.\u00a0 The College reserves the right to fill or not to fill the post.\u00a0 Applicants who are not contacted by the College 4 months after the application deadline may consider their applications unsuccessful.\n\nApplication Deadline: 27 January 2022 (Thursday)\n\nAll information and personal data collected will be used solely for recruitment related purposes. For more information about the College, please visit our website: http://www.twc.edu.hk.\n\nWE ARE AN EQUAL OPPORTUNITIES EMPLOYER", "employment_types": ["Full Time"], "selling_points": ["Lead a team", "financial accounting and reporting", "internal controls"], "locations": ["Mong Kok"], "categories": ["Accounting", "Accountant", "Finance / Accounting Manager", "Treasurer"], "post_time": "2022-01-13T08:21:45Z", "salary": {"currency": null, "max": null, "min": null, "period": "monthly", "term": null}, "salary_visible": false, "title_keywords": ["finance manager"], "responsibilities": ["regulations", "budgeting", "audit", "financial statements", "statutory requirements", "planning", "monitor", "implementation", "forecast", "forecasting", "reporting", "provide support", "management", "review", "procedures", "cash flow", "policies", "ad-hoc tasks", "systems", "ensure compliance", "financial analysis", "lead a team", "external auditors"], "requirements": {"degrees": ["degree", "bachelor"], "majors": ["accounting"], "languages": [], "language_level": [], "hard_skills": ["sap", "professional qualifications", "accounting software", "accounting system", "accpac", "problem-solving skills", "processing"], "soft_skills": ["meet tight deadlines", "independently", "multi-task", "sense of responsibility", "communication", "problem-solving skills", "interpersonal"], "languages_combined": []}, "experience_required": {"duration": ["at least 8 years", "at least 3 years"], "field": ["financing", "relevant working experience", "education", "supervisory level", "accounting"]}}, {"job_id": "100003009044625", "location_code": "hk", "company": "Maples Fund Services (Asia) Limited", "job_title": "Cash Operations Administrator", "description": "Position: Cash Operations Administrator\nLocation: Hong Kong\n\nThe Maples Group is a standard bearer in financial and legal services, trusted by many of the world\u2019s largest hedge fund managers, private equity firms and international corporations.\n\nOur distinction flows from our carefully curated team: 2,000+ professionals characterised by tenacity, ethics and exacting excellence.\u00a0We hire smart and sharpen smarter, arming talent with best-in-class resources and skills. \u00a0Operating in key financial centres across the Americas, Asia, Europe and the Middle East, our international presence offers a unique springboard for career development and cross-cultural immersion. \u00a0Our side-by-side financial and legal services are similarly ripe for interdisciplinary learning and growth.\u00a0\u00a0\n\nThe Maples Group looks to add a Hong Kong based Analyst to our team and invites eager and qualified candidates to apply. \u00a0We are committed to diversity, inclusion and equality of opportunity as we attract, retain and develop world-class talent.\n\nWho We Seek\n\nOur merit-based culture suits professionals in pursuit of boundless careers and lives.\u00a0Beyond their acumen, team members are collaborative and conscientious, bringing a healthy sense of drive and purpose to each interaction and to all aspects of their work.\n\nAbout the Role\n\nThe Cash Operations Administrator supports the Cash Operations team. Its tactical responsibilities feed one larger objective: provides back-office services to the global business in accordance with client agreements. Primary responsibilities include:\u00a0\n\nEntering all transactions into the banking system;\nWire transaction management;\nMonitoring a centralised inbox to ensure timely and accurate responses to employee and client queries;\nCompletion of audit confirmations;\nAdministration of online banking log-in details; and\nFiling, scanning, and preparation of daily bank reconciliations.\n\nWhat You Bring\n\nIn addition to indisputably high ethical standards and autonomy, the ideal candidate possesses the following:\n\nDegree preferred\nProficiency in Microsoft Word, Excel and Outlook is required;\nPrior experience in a similar role would be an asset, as well as knowledge of SWIFT, ABA, IBAN and sort codes, OFAC interest rates, time deposits, and foreign-currency transactions;\nThe ability to work overtime at short notice is critical;\nWill also be expected to demonstrate strong organisational and written/verbal communicationskills. A positive attitude, strong sense of teamwork, strong attention to detail, and excellentkeying accuracy and speed is essential;\nFluency in English and Chinese is required.\n\nBenefits & Rewards\n\nThe most enduring professional relationships are reciprocal relationships.\u00a0 The Maples Group prioritises employee health and wellbeing. Depending on your location, we offer a range of benefits, including:\n\nComprehensive health coverage (medical, dental and optical)\nCompetitive vacation packages\nEducational assistance and professional development programmes\nSavings or pension plan\nLife insurance\nTravel insurance\nGlobal mental wellness programme\nSocial events\n\nAbout the Maples Group\n\nOver five decades, the Maples Group has grown from modest beginnings into one of the world's preeminent professional services firms, offering specialised fiduciary, fund administration, regulatory and compliance, entity formation and management and legal services on the laws of the British Virgin Islands, the Cayman Islands, Ireland, Jersey and Luxembourg.\n\nYou can learn more about the Maples Group on our corporate website.\u00a0 Experience our culture and our people on our Careers Page or on LinkedIn.\n\nDisclaimer: All personal information collected during the application process will be used for recruitment-related purposes only. Please refer to our Job Applicant Privacy Notice at maples.com/privacy for details on how we handle personal information relating to job applicants.\n\n\u00a0Click here to apply", "employment_types": ["Full Time", "Permanent"], "selling_points": ["International financial services", "Treasury administrative position", "Great career prospects"], "locations": ["Wan Chai"], "categories": ["Accounting", "Treasurer", "Banking / Finance", "Financial Services"], "post_time": "2022-01-13T04:55:20Z", "salary": {"currency": null, "max": null, "min": null, "period": "monthly", "term": null}, "salary_visible": false, "title_keywords": ["operations", "administrator"], "responsibilities": ["scanning", "management", "operations", "monitoring", "audit", "transactions", "develop", "bank reconciliations", "career development", "banking", "administration"], "requirements": {"degrees": ["degree"], "majors": [], "languages": ["english", "chinese"], "language_level": ["fluency"], "hard_skills": ["excel", "microsoft word", "codes", "outlook", "swift", "private equity", "acumen"], "soft_skills": ["work overtime", "ideal", "timely", "teamwork", "collaborative", "unique", "positive attitude", "committed", "learning", "ethical", "attention to detail", "conscientious", "accurate", "world-class"], "languages_combined": [{"language": "english", "language_level": ["fluency"]}, {"language": "chinese", "language_level": ["fluency"]}]}, "experience_required": {"duration": [], "field": []}}, {"job_id": "100003009035120", "location_code": "hk", "company": "China Mobile Hong Kong \u4e2d\u570b\u79fb\u52d5\u9999\u6e2f", "job_title": "Assistant Accounting Officer (Revenue & Treasury)", "description": "CHINA MOBILE HONG KONG COMPANY LIMITED\u00a0(\"CMHK\") is the wholly-owned subsidiary of China Mobile Limited (HKEx: 941) (NYSE: CHL), which ranks 65th on the Fortune Global 500.\n\nOur company strives to offer superior service experience and to become the preferable digital partner for customers. We are preserving an environment with trust, responsibility and caring. At CMHK, we commit to maximizing people\u2019s potential and paving the way toward success for every striver. We are now inviting high caliber professional to join us.\n\nDivision:\u00a0 Finance Division -\u00a0Revenue & Treasury\n\nIn this position, you will:\n\n\nPrepare accounting entries of revenue, month end closing and reporting\nPrepare balance sheet and P&L schedules and reconciliations as well as follow up on any unusual items\nAssist in improving accounting process and leveraging technology to create efficiencies\nPerform other duties and ad hoc projects as required\nTo be successful in this position, you should meet the following requirements:\u00a0\n\n\nDegree in Accountancy/ Finance or business\u00a0related disciplines\n1 year relevant working experience with good knowledge of international accounting standards and practices preferred. Fresh graduate will also be considered.\nExperience in telecom industry and revenue accounting will be advantage\nProactive, independent, persistent and able to work under pressure to meet deadline\nGood knowledge in MS Excel/ Word, Macro / MS Access preferred\nAble to work on multiple priorities with accuracy and efficiency while keeping to deadlines\nGood command of both written and spoken English and Chinese (both Cantonese and Mandarin)\nImmediate Available is preferable\n\nWhen you work:\n\n\n5 days work\n8 hours/day\n\nWhat you enjoy:\n\nDouble pay\nDiscretionary Performance bonus\nLife insurance\nMedical insurance\nEducation subsidies\nBirthday gift\nMarriage leave\nBirthday leave\nStaff discount\n\nCMHK is committed to be an equal opportunity employer. We offer exceptional benefits package and the opportunity to work in a challenging environment. Personal data provided by applicants will be treated strictly in accordance with our personal data policy and for recruitment purposes only.\n\nPlease submit your application to us by clicking the APPLY NOW button and send your full resume with your availability, current and expected salary to us.", "employment_types": ["Full Time", "Permanent"], "selling_points": ["Double pay & Performance bonus", "Knowledge of international accounting standards", "Fresh graduate will also be considered"], "locations": ["Kwai Hing"], "categories": ["Accounting", "Accountant", "Accounting Clerk / Supervisor", "Treasurer"], "post_time": "2022-01-10T06:03:11Z", "salary": {"currency": null, "max": null, "min": null, "period": null, "term": null}, "salary_visible": false, "title_keywords": ["assistant accounting officer"], "responsibilities": ["reporting", "month end closing", "perform other duties", "schedules", "work under pressure", "p&l", "reconciliations", "ad hoc projects", "insurance", "balance sheet"], "requirements": {"degrees": ["degree", "fresh graduate"], "majors": ["related disciplines", "finance", "business", "accountancy"], "languages": ["cantonese", "english", "chinese", "mandarin"], "language_level": ["good command"], "hard_skills": ["mobile", "ms excel", "word", "macro"], "soft_skills": ["independent", "persistent", "committed", "proactive", "superior", "work under pressure"], "languages_combined": [{"language": "cantonese", "language_level": ["good command"]}, {"language": "english", "language_level": ["good command"]}, {"language": "chinese", "language_level": ["good command"]}, {"language": "mandarin", "language_level": ["good command"]}]}, "experience_required": {"duration": ["1 year"], "field": ["digital", "accounting", "relevant working experience"]}}, {"job_id": "100003009047663", "location_code": "hk", "company": "Robert Walters (HK)", "job_title": "Internal Control Manager", "description": "A global logistic company is looking for an Internal Control Manager to join their expanding team in Hong Kong. Report to CFO and lead a small team to handle the internal control and treasury functions.\n\nResponsibilities:\n\nLead a small team to manage Internal Control and Treasury functions\n70% on internal control/audit (internal & external) and 30% on treasury\nEnsure compliance with Group's policy and local requirement at all times\nEnhance process efficiency, internal control, risk management, corporate governance and cost saving\nManage account payable, fixed asset and treasury functions\nReview daily payment and treasury work performed by subordinates and shared service centre\nCollaborate and communicate with internal stakeholders to implement corporate initiatives and projects\n\n\nRequirements:\n\nDegree holder in Accounting or related discipline\nQualified accountant with minimum 6 years experience in internal/external audit and internal control\nFamiliar with accounting standards, taxation laws and Companies Ordinance\nExcellent communication, interpersonal,influence and leadership skills\nProficient in written and spoken English and Chinese\nProficient PC skills, knowledge in SAP is an advantage", "employment_types": ["Full Time", "Permanent"], "selling_points": ["Leadership role", "Fast growing industry", "Excellent communication skill"], "locations": ["Not Specified"], "categories": ["Accounting", "Audit", "Credit Control", "Treasurer"], "post_time": "2022-01-14T03:41:00Z", "salary": {"currency": null, "max": null, "min": null, "period": "monthly", "term": null}, "salary_visible": false, "title_keywords": ["manager"], "responsibilities": ["collaborate", "communicate with", "management", "cost", "lead a small team", "review", "audit", "ensure compliance", "payment", "internal control"], "requirements": {"degrees": ["degree holder"], "majors": ["accounting"], "languages": ["english", "chinese"], "language_level": ["proficient"], "hard_skills": ["companies ordinance", "pc skills", "sap", "internal control"], "soft_skills": ["communication", "leadership skills", "interpersonal"], "languages_combined": [{"language": "english", "language_level": ["proficient"]}, {"language": "chinese", "language_level": ["proficient"]}]}, "experience_required": {"duration": ["minimum 6 years"], "field": ["audit"]}}, {"job_id": "100003009042648", "location_code": "hk", "company": "CUHK Medical Centre Limited", "job_title": "Shroff Service Officer", "description": "Key Responsibilities\n\nPerform cashier counter duties and day-end procedures;\nHandle patients and next-of-kin enquiries;\nHandle patient billing issues and ensure accuracy of all chargeable items when issuing invoice;\nFollow up payment with patients and corporates;\nPerform general clerical duties, including filing, data entry and record keeping; and\nPerform any other duties as assigned by supervisor(s) from time to time.\n\nJob Requirements\n\nCompletion of Secondary Education\nAt least 2 years\u2019 relevant work experience\nExperience in hospital, hotel, airline or insurance company and area of billing and cashier is preferred\nCustomer-oriented with excellent communication and interpersonal skills\nShift duty (night shift) is required\nTeam player and able to work independently and under pressure\nGood command of written and spoken English and Chinese\nProficient in MS Office applications\n\nCompensation and Employment Terms\n\nWe provide a unique employment experience for people seeking careers in hospital and healthcare industry; and offer competitive remuneration packages to the successful candidates. Appointment will be made on a 3-year contract with contract-end gratuity, renewable subject to good performance and mutual agreement.\n\nApplication Closing Date\n\n25 January 2022\n\n\n\nPersonal Information Collection Statement\n\nData collected will only be used for job application processing. Applicants not contacted by CUHK Medical Centre Limited within eight weeks from the application closing date may assume their applications unsuccessful. All personal data collected will be kept for a period of 12 months from the application closing date, and will be destroyed thereafter.", "employment_types": ["Full Time", "Contract"], "selling_points": ["2 years\u2019 relevant work experience", "Hospital, hotel, airline or insurance co. exp", "Shift duty (night shift) is required"], "locations": ["Shatin Area"], "categories": ["Accounting", "Treasurer", "Banking / Finance", "Credit Collection", "Hospitality / F & B", "Hospitality / Hotel Services"], "post_time": "2022-01-12T08:15:56Z", "salary": {"currency": null, "max": null, "min": null, "period": "monthly", "term": null}, "salary_visible": false, "title_keywords": ["officer"], "responsibilities": ["any other duties", "data entry", "invoice", "procedures", "payment"], "requirements": {"degrees": ["secondary education"], "majors": [], "languages": ["english", "chinese"], "language_level": ["good command"], "hard_skills": ["airline", "ms office"], "soft_skills": ["work independently", "under pressure", "customer-oriented", "communication and interpersonal skills", "team player"], "languages_combined": [{"language": "english", "language_level": ["good command"]}, {"language": "chinese", "language_level": ["good command"]}]}, "experience_required": {"duration": ["at least 2 years"], "field": ["billing", "insurance"]}}, {"job_id": "100003009053292", "location_code": "hk", "company": "Sinochem Hong Kong (Group) Company Limited", "job_title": "Corporate Finance \u2013 Treasury specialist \u8cc7\u91d1\u5c08\u54e1", "description": "Responsibilities:\n\n\u00a0Cash operation planning, payment processing and closing balance analysis\n\u00a0Perform Daily analysis of cash pool operation results, and solicit new customers to\u00a0 \u00a0join cash pool, and meet the savings target\n\u00a0Handle various ad hoc projects.\nRequirements:\n\n\u00a0Degree holder in Finance / Accounting or related disciplines\n\u00a0At least 3 years of finance experience\n\u00a0Strong analytical and co-ordination skills\n\u00a0Proficient in MS Excel, MS Word and MS PowerPoint\n\u00a0Good command of spoken and written English, Chinese and Mandarin\n\u00a0Good knowledge of corporate treasury function and cash pooling\n\u00a0Independent, outgoing, well-organized, detail and result-oriented person\nSalary:\n\n\n20k~28k with double pay, bonus\n\nBenefits & Others:\n5 days work week\nMedical Insurance coverage\nO.T. allowance", "employment_types": ["Full Time"], "selling_points": [], "locations": ["Wan Chai"], "categories": ["Accounting", "Treasurer", "Banking / Finance", "Corporate Finance", "Treasury"], "post_time": "2022-01-17T07:24:52Z", "salary": {"currency": null, "max": null, "min": null, "period": "monthly", "term": null}, "salary_visible": false, "title_keywords": ["specialist", "corporate finance"], "responsibilities": ["payment", "analysis", "ad hoc projects", "planning"], "requirements": {"degrees": ["degree holder"], "majors": ["related disciplines", "finance", "accounting"], "languages": ["english", "chinese", "mandarin"], "language_level": ["good command"], "hard_skills": ["ms powerpoint", "ms excel", "ms word"], "soft_skills": ["outgoing", "result-oriented", "independent", "well-organized"], "languages_combined": [{"language": "english", "language_level": ["good command"]}, {"language": "chinese", "language_level": ["good command"]}, {"language": "mandarin", "language_level": ["good command"]}]}, "experience_required": {"duration": ["at least 3 years"], "field": ["finance"]}}, {"job_id": "100003009053198", "location_code": "hk", "company": "DHL EXPRESS (HONG KONG) LIMITED", "job_title": "Controller - Accounting (Internal Control Manager)", "description": "Reporting to Senior Manager, Accounting and Tax, you will lead a small team to manage Internal Control and Treasury functions, coordinate internal and external audits and to ensure proper internal controls are in place.\n\nResponsibilities:\n\nInternal Control\n\nReview internal control self-assessments to ensure compliance with Group\u2019s policy and local requirement at all times\nPerform operational and financial review to identify areas of improvement\nProvide feasible recommendation and initiate new measures to enhance process efficiency, internal control, risk management, corporate governance and cost saving\nHandle external audit, internal audit and other compliance activities\n\nTreasury\n\nManage account payable, fixed asset and treasury functions\nReview daily payment and treasury work performed by subordinates and shared service centre\nCollaborate with various Departments to implement corporate initiatives and projects\n\nRequirements:\n\nQualified accountant with at least 3-year post qualification working experience\nMinimum 6 years\u2019 solid experience in external audit, internal audit, internal control or related areas, with at least 2 years in commercial sector\nExposure in payment and treasury is an advantage but not mandatory\nFamiliar with accounting standards, taxation laws and Companies Ordinance\nStrong leadership with excellent influencing, communication and presentation skills\nExcellent analytical and problem solving skills with strong business acumen\nExcellent command of spoken and written English and Chinese\nProficient PC skills, knowledge in SAP is an advantage\n\nPersonal Information Collection Statement pertaining to Recruitment\n\nDHL Express (Hong Kong) Limited / DHL Aviation (Hong Kong) Limited (\u201cDHL\u201d) is committed to protecting and respecting your privacy in accordance with the Personal Data (Privacy) Ordinance of Hong Kong (the \u201cOrdinance\u201d) and DHL\u2019s Personal Data Protection Policy (the \u201cPolicy\u201d) at\u00a0https://www.dhl.com/hk-en/home/footer/local-privacy-notice.html\n\nBy proceeding to respond to this recruitment advertisement, you consent that we may use, retain, process, transfer or otherwise handle the personal data that we collect from you for recruitment,\u00a0 application processing, assessment and communication purposes (including any other purposes directly related thereto) in accordance with the Policy.\n\nAll personal data of unsuccessful applicants will be retained for future recruitment purposes for a period of not more than two (2) years after which such data will be destroyed.\n\nYou have the right at any time to make a data access or correction request concerning your personal data held by us. In addition, you may request us to delete your personal data that is no longer required for the relevant purposes which you have given consent. Should you wish to exercise such rights or have any question in relation to your personal data or the Policy, please contact our Human Resources Division in writing.", "employment_types": ["Full Time"], "selling_points": ["Review internal control self-assessments", "Perform operational and financial review", "Minimum 6 years\u2019 solid experience"], "locations": ["Ngau Tau Kok"], "categories": ["Accounting", "Accountant", "Audit", "Treasurer"], "post_time": "2022-01-17T06:24:53Z", "salary": {"currency": null, "max": null, "min": null, "period": "monthly", "term": null}, "salary_visible": false, "title_keywords": ["accounting", "manager"], "responsibilities": ["collaborate with", "management", "cost", "internal audit", "review", "compliance", "audit", "ensure compliance", "payment", "internal control"], "requirements": {"degrees": [], "majors": [], "languages": ["english", "chinese"], "language_level": ["excellent"], "hard_skills": ["no", "sap", "processing", "html", "make", "companies ordinance", "problem solving skills", "pc skills", "internal control", "acumen"], "soft_skills": ["communication", "analytical and problem solving skills", "presentation skills", "committed", "business acumen", "leadership"], "languages_combined": [{"language": "english", "language_level": ["excellent"]}, {"language": "chinese", "language_level": ["excellent"]}]}, "experience_required": {"duration": ["at least 2 years", "at least 3-year", "minimum 6 years"], "field": ["related", "commercial", "audit"]}}, {"job_id": "100003009054541", "location_code": "hk", "company": "China Eagle Management Limited", "job_title": "Accountant / Finance Manager (5-day work)", "description": "\u00a0Responsibilities:\n\n\u00a0Assist to Finance Manager to oversee finance and accounting functions of the group and ensure compliance with the Hong Kong Listing Rules, International Accounting Standards (\u201cIAS\u201d) and the Companies Ordinance\nPrepare monthly consolidated financial information for the Group and co-ordinate to issue notices, announcements and circulars for compliance with the Listing Rules and other statutory requirements\nPrepare annual, interim and quarterly financial reports and relevant disclosure notes and liaise with external auditors in all aspects of the financial reporting\nPrepare financial analysis, budgeting, forecast, cash flow projection, and management reports\nAssist in managing funds and liaison with banks\nAssist in reviewing, monitoring and enhancing internal controls of the Group\nAssist in tax planning, treasury functions and any ad hoc projects for the Group\n\nRequirements:\n\nDegree holder in Accounting and possess HKICPA/ACCA or other equivalent\n4-5 years of relevant work experienceof which at least 1-2 years in a Hong Kong listed company.\nStrong analytical and excellent interpersonal skills\nPositive attitude, good team work ethic , highly responsibility and able to work under pressure\nDriven, enthusiastic, highly self-motivated, and able to operate independently\nConversant in accounting principles; experience in tax issues and legal practice preferred\nExcellent communication skills, fluent in English, Cantonese and Mandarin\nCandidates with more working experience will be considered as senior position", "employment_types": ["Full Time"], "selling_points": ["oversee finance and accounting functions", "1-2 years in a Hong Kong listed company", "5-day work & medical insurance"], "locations": ["Central"], "categories": ["Accounting", "Accountant", "Finance / Accounting Manager", "Treasurer"], "post_time": "2022-01-17T09:56:44Z", "salary": {"currency": null, "max": null, "min": null, "period": "monthly", "term": null}, "salary_visible": false, "title_keywords": ["accountant", "finance manager"], "responsibilities": ["tax", "financial reports", "budgeting", "compliance", "monitoring", "ensure compliance", "financial analysis", "statutory requirements", "cash flow", "management reports", "planning", "financial reporting", "forecast", "ad hoc projects", "liaise with", "listing", "external auditors"], "requirements": {"degrees": ["degree holder"], "majors": ["accounting"], "languages": ["cantonese", "english", "mandarin"], "language_level": ["excellent", "fluent"], "hard_skills": ["acca", "hkicpa"], "soft_skills": ["good team work", "communication skills", "self-motivated", "independently", "positive attitude", "interpersonal skills", "enthusiastic", "driven", "work under pressure"], "languages_combined": [{"language": "cantonese", "language_level": ["excellent", "fluent"]}, {"language": "english", "language_level": ["excellent", "fluent"]}, {"language": "mandarin", "language_level": ["excellent", "fluent"]}]}, "experience_required": {"duration": [], "field": ["legal"]}}, {"job_id": "100003009046602", "location_code": "hk", "company": "Links International", "job_title": "Treasury Manager - New Headcount with US Listed MNC", "description": "Key Responsibilities:\n* Cash flow management, which includes estimates; calculations of net cash position, analysis of\ncash flow activities and assessments of investing/borrowing activities\n* Develop hedging recommendations\n* Implementing and administering currency and interest rates to the hedging program\n* Administer bank accounts globally and maintain cash, debt, and interest schedules in accordance\nwith accounting standards\n* Support the VP, Finance & Operations in identifying improvement opportunities\n* Managing the delivery of all Treasury initiatives and projects\n* Assist HQ to manage banking and lending relationships\n* Provide technical and other support for mergers, acquisitions and other projects as needed\n\nExperience, Education and Designations:\n* 5 to 7 years' experience in a similar role\n* Undergraduate degree in finance or accounting, a CTP designation is a plus, or CPA, CMA, CGA\n* Experience with multiple currencies and international operations strongly preferred in a\nmanufacturing environment\n* Experience preparing cash forecasts and cash flow analyses\n* Experience working in private equity ownership environment\n* Experience in building complex financial models to evaluate various financial plans\n\n", "employment_types": ["Full Time", "Permanent"], "selling_points": ["APAC job scope", "Stable working hours (9-5pm)", "International working environment"], "locations": ["Central & Western Area"], "categories": ["Accounting", "Finance / Accounting Manager", "Treasurer", "Banking / Finance", "Treasury"], "post_time": "2022-01-13T16:12:54Z", "salary": {"currency": null, "max": null, "min": null, "period": "monthly", "term": null}, "salary_visible": false, "title_keywords": ["manager"], "responsibilities": ["management", "schedules", "operations", "analysis", "financial models", "develop", "evaluate", "cash flow", "maintain", "banking", "financial plans"], "requirements": {"degrees": ["degree"], "majors": ["finance", "accounting"], "languages": [], "language_level": [], "hard_skills": ["cpa", "analysis", "private equity", "plus"], "soft_skills": [], "languages_combined": []}, "experience_required": {"duration": ["5 to 7 years"], "field": ["financial", "education"]}}, {"job_id": "100003009044510", "location_code": "hk", "company": "Links International", "job_title": "Treasury Manager - Luxury Retail", "description": "Responsibilities:\n\nSupervise day-to-day treasury operation and cash management\nWorking closely with Finance team on project funding decisions and financial projections\nReview loan and funding documents\nManage foreign exchange and interest rate risk, and FX hedging across APAC\nPrepare and submit treasury reports for senior management review\nAdvise on tax issues regarding investments & M&A projects\nManage and liaise with banks for funding and investment decisions\nBeing a strong business partner with stakeholders across different regions\n\nRequirements:\n\nBachelor Degree in Accounting & Finance or related discipline\nAt least 5 years of experience in treasury, preferably in sizeable MNC and luxury retailer\nSolid experiences in Retail and FMCG related industries are highly preferred\nSmart, energetic person who is ambitious to strive for excellence\nExcellent command of both English and Cantonese\nExcellent communication and presentation\nDynamic personality with an analytical mindset", "employment_types": ["Full Time", "Permanent"], "selling_points": ["Guaranteed 13 months salary", "Work life balance", "Regional exposure"], "locations": ["Not Specified"], "categories": ["Accounting", "Chief Accountant", "Finance / Accounting Manager", "Treasurer"], "post_time": "2022-01-13T04:23:52Z", "salary": {"currency": "HKD", "max": 54999, "min": 45000, "period": "monthly", "term": null}, "salary_visible": true, "title_keywords": ["manager"], "responsibilities": ["tax", "management", "project funding", "review", "reports", "finance team", "liaise with", "senior management"], "requirements": {"degrees": ["degree", "bachelor"], "majors": ["finance", "accounting"], "languages": ["cantonese", "english"], "language_level": ["excellent"], "hard_skills": ["dynamic"], "soft_skills": ["communication", "energetic", "dynamic", "strive for excellence", "presentation"], "languages_combined": [{"language": "cantonese", "language_level": ["excellent"]}, {"language": "english", "language_level": ["excellent"]}]}, "experience_required": {"duration": ["at least 5 years"], "field": ["related", "retail", "fmcg"]}}, {"job_id": "100003009039251", "location_code": "hk", "company": "Cosco Shipping Investment Holdings Co., Limited", "job_title": "Treasury Officer (\u8d44\u91d1\u7ba1\u7406\u90e8\u4e3b\u4efb\uff09", "description": "\u00a0Job Description\nResponsible for opening/closing/maintenance of the on-shore and off-shore bank accounts.\nResponsible for routine matters related to internet-banking system, including user and cash pool management.\nResponsible for maintaining the statistics of bank account information.\nAssisting in treasury-management matters, including FX Spot transactions, application for banking facilities, reviewing finance documents, post-lending matters.\nAssisting in maintaining statistics of cash flows and interest-bearing debts.\n\u8d1f\u8d23\u516c\u53f8\u94f6\u884c\u5728\u5cb8/\u79bb\u5cb8\u8d26\u6237\u7ba1\u7406\u5de5\u4f5c\uff0c\u5305\u62ec\u8d26\u6237\u5f00\u7acb\u3001\u53d8\u66f4\u4e0e\u6ce8\u9500\uff1b\n\u8d1f\u8d23\u7f51\u4e0a\u94f6\u884c\u7cfb\u7edf\u7ba1\u7406\u5de5\u4f5c\uff0c\u5305\u62ec\u7f51\u4e0a\u94f6\u884c\u7528\u6237\u7ba1\u7406\u4e0e\u8d44\u91d1\u6c60\u7ef4\u62a4\uff1b\n\u8d1f\u8d23\u8d26\u6237\u4fe1\u606f\u7684\u7edf\u8ba1\u5de5\u4f5c\uff1b\n\u534f\u52a9\u8d44\u91d1\u7ba1\u7406\u5de5\u4f5c\uff0c\u5305\u62ec\u5916\u6c47\u5373\u671f\u4ea4\u6613\u3001\u7533\u8bf7\u94f6\u884c\u6388\u4fe1\u3001\u5408\u540c\u5ba1\u9605\u3001\u8d37\u540e\u4e8b\u9879\u7b49\uff1b\n\u534f\u52a9\u8d44\u91d1\u4e0e\u5e26\u606f\u8d1f\u503a\u7684\u7edf\u8ba1\u5de5\u4f5c\u3002\u00a0 \u00a0\u00a0\nRequirements\n\nEducational Requirements: Bachelor\u2019s degree or above in Economics, Finance, accounting or other related majors.\nWork Experience: 3 to 5 years work experiences in financial service industries are preferred.\nLanguage Requirements: Proficient speaker of Cantonese, Mandarin and English.\nOther Requirements: Proficient user of Ms Office software; personalities of prudence and earnestness, a great sense of responsibility and teamwork; compliance with rules and regulations; obedience to other work assignments from superiors.\n\u5b66\u5386\u8981\u6c42\uff1a\u7ecf\u6d4e\u3001\u91d1\u878d\u3001\u4f1a\u8ba1\u6216\u5176\u4ed6\u76f8\u5173\u4e13\u4e1a\u672c\u79d1\u6bd5\u4e1a\u6216\u4ee5\u4e0a\uff1b\n\u5de5\u4f5c\u7ecf\u9a8c\uff1a3\u81f35\u5e74\uff0c\u91d1\u878d\u884c\u4e1a\u80cc\u666f\u4f18\u5148\uff1b\n\u8bed\u8a00\u8981\u6c42\uff1a\u719f\u7ec3\u4f7f\u7528\u5e7f\u4e1c\u8bdd\u3001\u666e\u901a\u8bdd\u4e0e\u82f1\u8bed\uff1b\n\u5176\u4ed6\u8981\u6c42\uff1a\u719f\u7ec3\u4f7f\u7528Ms Office\u529e\u516c\u8f6f\u4ef6\uff1b\u5de5\u4f5c\u8e0f\u5b9e\u8ba4\u771f\uff0c\u5177\u6709\u8d23\u4efb\u5fc3\u4e0e\u56e2\u961f\u610f\u8bc6\uff1b\u9075\u5b88\u516c\u53f8\u5404\u9879\u89c4\u7ae0\u5236\u5ea6\uff0c\u670d\u4ece\u4e0a\u53f8\u5de5\u4f5c\u5b89\u6392\u3002", "employment_types": ["Full Time"], "selling_points": ["Bachelor\u2019s degree or above in Finance", "3 to 5 years work experiences in financial", "Proficient user of Ms Office software"], "locations": ["Sheung Wan"], "categories": ["Accounting", "Accounting Clerk / Supervisor", "Treasurer", "Banking / Finance", "Treasury"], "post_time": "2022-01-11T09:17:47Z", "salary": {"currency": null, "max": null, "min": null, "period": "monthly", "term": null}, "salary_visible": false, "title_keywords": ["officer"], "responsibilities": ["management", "maintaining", "maintenance", "transactions", "banking"], "requirements": {"degrees": ["degree or above", "bachelor"], "majors": ["finance", "economics", "accounting"], "languages": ["cantonese", "english", "mandarin"], "language_level": ["proficient"], "hard_skills": ["ms office"], "soft_skills": ["teamwork", "sense of responsibility"], "languages_combined": [{"language": "cantonese", "language_level": ["proficient"]}, {"language": "english", "language_level": ["proficient"]}, {"language": "mandarin", "language_level": ["proficient"]}]}, "experience_required": {"duration": ["3 to 5 years"], "field": ["financial"]}}, {"job_id": "100003009034830", "location_code": "hk", "company": "Hong Kong Hengfeng Oil Trade Co., Limited", "job_title": "Treasury Executive \u8d44\u91d1\u4e3b\u4efb\u5c97\u4f4d", "description": "Responsibilities:\n\nProcess inward/outward remittance, time deposit, fund transfer, foreign exchange, account maintenance, etc.\u00a0\nSupport the Group and oversea divisions preparing Letter of Credit (\u201cL/C\u201d) and other trade finance related bank facility documents\nPerform treasury functions including cash and liquidity management\nCoordinate with finance division to perform accounts reconciliations, data entry and documents filing etc.\u00a0\nAssist to develop and maintain a positive long-term professional relationship with global and PRC financial intuitions\nHandle ad-hot task assigned by management.\n\nJob requirements:\n\nBachelor Degree holder with major in Finance/ Accounting or related disciplines\nMinimum 1 year working experience, fresh graduate welcome also\nExperiences in L/C issuance, trade finance and treasury are highly preferable\nHands on knowledge of MS Office and Chinese Word processing\nFamiliar with Accounting System SAP will be an advantage\nGood command of both spoken and written English and Chinese, Mandarin is required\nExposure to PRC and international trading business is highly preferred\nAble to work independently and attention to details\nImmediate available is highly preferred.\nInterested parties, please send your resume with CURRENT & EXPECTED salary and DATE AVAILABLE by clicking 'Apply Now'.\u00a0\n\n(Data collected would be used for recruitment purpose only)\n\n\n\nWe Offer\n\nDouble pay\u00a0 Five-day work week\u00a0 Medical insurance\u00a0 Dental insurance\nPerformance bonus \u00a0On-the-job training oversea", "employment_types": ["Full Time"], "selling_points": ["Degree holder", "Double pay", "Five-day work week"], "locations": ["Wan Chai"], "categories": ["Accounting", "Treasurer"], "post_time": "2022-01-10T04:22:39Z", "salary": {"currency": null, "max": null, "min": null, "period": "monthly", "term": null}, "salary_visible": false, "title_keywords": ["executive"], "responsibilities": ["management", "documents filing", "data entry", "coordinate with", "develop", "reconciliations", "maintain", "account maintenance"], "requirements": {"degrees": ["fresh graduate", "bachelor degree holder"], "majors": ["related disciplines", "finance", "accounting"], "languages": ["english", "chinese", "mandarin"], "language_level": ["good command"], "hard_skills": ["chinese word processing", "sap", "c", "accounting system", "ms office"], "soft_skills": ["work independently", "hands on", "attention to details"], "languages_combined": [{"language": "english", "language_level": ["good command"]}, {"language": "chinese", "language_level": ["good command"]}, {"language": "mandarin", "language_level": ["good command"]}]}, "experience_required": {"duration": ["minimum 1 year"], "field": ["finance"]}}, {"job_id": "100003009045606", "location_code": "hk", "company": "Babel Capital Limited", "job_title": "Finance Associate/ Manager", "description": "Babel Finance, a reputable digital assets/ crypto services provider, has the following opening in Hong Kong for application:\n\n\n\u00a0\u00a0\u00a0\u00a0\u00a0\u00a0 The role reports to Senior Finance Manager\n\u00a0\u00a0\u00a0\u00a0\u00a0\u00a0 To assist the finance team for efficient monthly closing, high quality financial reporting, financial operations, process and approvals, management reporting, and forecasting.\n\nIdeal candidate:\n\n\u00a0\u00a0\u00a0\u00a0\u00a0\u00a0 Degree holder or above in Accounting, or CPA equivalent qualification\n\u00a0\u00a0\u00a0\u00a0\u00a0\u00a0 4- 6 years internal financial management experience in banks or financial institutions.\u00a0 More experienced candidate will be considered the position of Finance Manager\n\u00a0\u00a0\u00a0\u00a0\u00a0\u00a0 Has good knowledge in lending/ borrowing, options, trading, investment products/ funds\n\u00a0\u00a0\u00a0\u00a0\u00a0\u00a0 Experience in configuring financial system, dealing with external services providers and banks is a plus.\u00a0\n\u00a0\u00a0\u00a0\u00a0\u00a0\u00a0 Energetic, ready to go, with fire in heart; has interest and passion in cryptos, proactive in style for areas of improvement, has drives to get things done.\n\u00a0\u00a0\u00a0\u00a0\u00a0\u00a0 Be able and be willing to work rather independently.\n\nIn return, we offer:\n\n\u00a0\u00a0\u00a0\u00a0\u00a0\u00a0 Competitive package, nice working environment, new industry with great development, rewarding experience, and wide career growth potential", "employment_types": ["Full Time"], "selling_points": ["fintech startup", "financial services, accounting", "financial report and accounting"], "locations": ["Central"], "categories": ["Accounting", "Finance / Accounting Manager", "Treasurer", "Banking / Finance", "Financial Services"], "post_time": "2022-01-13T08:11:24Z", "salary": {"currency": null, "max": null, "min": null, "period": "monthly", "term": null}, "salary_visible": false, "title_keywords": ["associate", "manager"], "responsibilities": ["management", "financial system", "operations", "quality", "configuring", "reports", "financial reporting", "finance team", "management reporting", "forecasting"], "requirements": {"degrees": ["degree holder"], "majors": ["accounting"], "languages": [], "language_level": [], "hard_skills": ["plus", "crypto", "investment products", "cpa", "go"], "soft_skills": ["efficient", "proactive", "independently", "passion in", "energetic", "ideal"], "languages_combined": []}, "experience_required": {"duration": ["4- 6 years"], "field": ["management", "financial institutions", "financial"]}}, {"job_id": "100003009029784", "location_code": "hk", "company": "Hays", "job_title": "Treasury (Senior) Manager - HK listed Comp. | 70k", "description": "A reputable HK listed company is looking for a treasury expert to bring impacts to the company\n\nYour new role\n\nLead the team to handle cash management for the group\nPrepare regular treasury reporting package for management review\nLead in cash-flow forecasting on a weekly/ monthly basis\nLead projects for business process re-engineering & system enhancement\nReview and maintain sound internal control throughout the payment process\nParticipate in finance transformation and financial process enhancement\nDeveloped/ update policies and procedures for Treasury function\nLead/ assist in bank loans negotiation, loan documentation, loan drawdown and on-going loan compliance\n\n\nWhat you'll need to succeed\n\nBachelor's degree in accounting, finance or related disciplines\nProfessional accounting qualification is preferred\nAt least 8 years of working experience in treasury function in sizable corporates\nIn-depth knowledge and understanding of financial management and treasury operations\nSolid experience in finance system, e-payment platforms & system implementation\nHost to Host payment experience in treasury is a MUST\nGood command of spoken and written English and Cantonese\n\n\nWhat you need to do now\nIf you're interested in this role, click 'apply now' or for further information and a confidential discussion on this role or to find out about more opportunities in Accounting/ Finance, contact Harvey Kwong at Hays at +852 2230 7442 or email your CV to harvey.kwong@hays.com.hk", "employment_types": ["Full Time", "Permanent"], "selling_points": ["Very stable", "Lucrative Package", "Team leading exposure"], "locations": ["Not Specified"], "categories": ["Accounting", "Treasurer"], "post_time": "2022-01-07T06:09:44Z", "salary": {"currency": null, "max": null, "min": null, "period": "monthly", "term": null}, "salary_visible": false, "title_keywords": ["manager"], "responsibilities": ["loan compliance", "reporting", "management", "policies", "operations", "review", "procedures", "implementation", "business process re-engineering", "payment", "maintain", "contact", "payment process", "documentation", "forecasting", "management review", "internal control"], "requirements": {"degrees": ["degree", "bachelor"], "majors": ["related disciplines", "finance", "accounting"], "languages": ["cantonese", "english"], "language_level": ["good command"], "hard_skills": ["documentation", "system implementation", "internal control"], "soft_skills": ["interested in", "negotiation"], "languages_combined": [{"language": "cantonese", "language_level": ["good command"]}, {"language": "english", "language_level": ["good command"]}]}, "experience_required": {"duration": ["at least 8 years"], "field": ["finance"]}}, {"job_id": "100003009038616", "location_code": "hk", "company": "New Hope Group", "job_title": "Senior Financial Accountant", "description": "Roles and Responsibilities \u00b7\n\n\u00a0Preparation of detailed monthly reports within tight deadlines\u00a0\n\u00a0Overseeing the financial processes for all day-to-day operations \u00b7\n\u00a0Monthly accounts management \u00b7\u00a0\u00a0\n\u00a0Cash flow budgets including monthly reviews and re-forecasting \u00b7\n\u00a0Cost management and analysis \u00b7\u00a0\u00a0\u00a0\n\u00a0Taxation requirements and reporting \u00b7\u00a0\n\u00a0Creating KPI reports \u00b7\u00a0\u00a0\n\u00a0Assisting with the preparation of year-end accounts and statutory accounts \u00b7\n\u00a0Assist with building financial models and budgets each fiscal year \u00b7\u00a0\u00a0\u00a0\u00a0\u00a0\u00a0\n\u00a0Responding to financial inquiries by gathering and interpreting data \u00b7\n\u00a0Complete bank reconciliations \u00b7\n\u00a0Examining financial records to check for accuracy \u00b7\u00a0\nCashflow management and update cashflow/ budget on a weekly basis \u00b7\nManage and perform the accounts payable functions including approvals and reconciliations\nQualifications and requirements\u00a0\n\nDegree qualified in finance/accounting \u00b7\nCA/CPA qualified or equivalent\u00a0\nIntermediate to highly skilled with software applications experience \u00b7\u00a0\n3-5 years\u2019 experience in similar role of accountant or senior accountant \u00b7\nBig four auditing firm experience preferred \u00b7\nFull working rights within HK, Hong Kong citizenship \u00b7\u00a0\nMandarin speaking preferred\u00a0\u00a0\n\u00a0Market Salary Range, depending on individual working experience and capabilities\n", "employment_types": ["Full Time"], "selling_points": ["5 days work", "3-5 years\u2019 experience", "CA/CPA qualified"], "locations": ["Wan Chai"], "categories": ["Accounting", "Accountant", "Finance / Accounting Manager", "Treasurer"], "post_time": "2022-01-11T07:45:42Z", "salary": {"currency": null, "max": null, "min": null, "period": "monthly", "term": null}, "salary_visible": false, "title_keywords": ["accountant"], "responsibilities": ["budgets", "management", "cost", "monthly reports", "analysis", "day-to-day operations", "cash flow", "forecasting"], "requirements": {"degrees": ["degree"], "majors": ["finance", "accounting"], "languages": ["mandarin"], "language_level": [], "hard_skills": ["cpa"], "soft_skills": [], "languages_combined": [{"language": "mandarin", "language_level": []}]}, "experience_required": {"duration": ["3-5 years"], "field": ["senior accountant", "big four"]}}, {"job_id": "100003009038798", "location_code": "hk", "company": "UMP Healthcare Group", "job_title": "Accounting Executive (Payment)", "description": "ABOUT UMP\nAt UMP, we are dedicated to cultivating a performance culture of ever improving and innovative and \u201casking why\". Culture is the foundation of everything we believe at UMP. Our built-in career ladder and employee performance academy empower our UMPeople to stay ahead in this changing healthcare industry. We offer continuous training and career development opportunities at both the professional and personal levels. No matter what goals our team set for themselves, we want to help them grow.\n\nAbout the UMP team\nUMPeople share and live up to the same values. We strive to have a diverse and inclusive work culture where people feel needed and valued for their own intelligence and experience. UMPeople is a proud team, embark on a new career where you can find your purpose and meaning at work today.\n\n\nWhat You'll Do:\n\nMainly focus on Account Payable functions\nResponsible for preparing vouchers, payments and reimbursement, and maintain an accurate record in a professional manner\nHandle month-end closing and reconciliation\u00a0\nWork in documents filing and other data entry duties\nAbout You and What Type of Skills You'll Need:\n\nHigher diploma in Accounting, Finance or related disciplines\n2 years of accounting experience, especially in account payable functions\nProficiency in Microsoft Excel\nExperience in using SunSystem is a plus\nProactive and keen to learn, positive to work under fast-paced environment\nGood command of English and Chinese, including Mandarin\nImmediate available is highly\u00a0preferred\n\n\u200bUMP Healthcare Group is an Equal Opportunity Employer. All qualified candidates will receive consideration for employment regardless of age, disability, protected veteran status, race, color, religious creed, national origin, citizenship, marital status, sex and sexual orientation or gender identity.\n\nPlease visit our website at:\u00a0http://www.ump.com.hk\u00a0for more information about us. All information obtained will be kept in strict confidence and used for recruitment and employment related purpose only.", "employment_types": ["Full Time", "Permanent"], "selling_points": ["2 years in account payable function", "Independent and organized, good time management", "Good company culture with career ladder"], "locations": ["Central"], "categories": ["Accounting", "Accountant", "Accounting Clerk / Supervisor", "Treasurer"], "post_time": "2022-01-11T07:50:08Z", "salary": {"currency": null, "max": null, "min": null, "period": "monthly", "term": null}, "salary_visible": false, "title_keywords": ["accounting executive"], "responsibilities": [], "requirements": {"degrees": [], "majors": [], "languages": [], "language_level": [], "hard_skills": ["ladder"], "soft_skills": ["innovative"], "languages_combined": []}, "experience_required": {"duration": [], "field": []}}, {"job_id": "100003009038593", "location_code": "hk", "company": "China Mobile Hong Kong \u4e2d\u570b\u79fb\u52d5\u9999\u6e2f", "job_title": "Assistant Accountant (Fixed Asset)", "description": "CHINA MOBILE HONG KONG COMPANY LIMITED\u00a0(\"CMHK\") is the wholly-owned subsidiary of China Mobile Limited (HKEx: 941) (NYSE: CHL), which ranks 65th on the Fortune Global 500.\n\nOur company strives to offer superior service experience and to become the preferable digital partner for customers. We are preserving an environment with trust, responsibility and caring. At CMHK, we commit to maximizing people\u2019s potential and paving the way toward success for every striver. We are now inviting high caliber professional to join us.\n\nDivision:\u00a0 Finance Division - Financial Accounting & Reporting Department\n\nIn this position, you will:\n\n\nAssist in month-end closing\nPrepare reports, reconciliations and schedules\nSupport daily operations on the fixed assets area\nCo-ordinate with business users on projects and accounting issues\nArrange and coordinate stocktaking and inspection of fixed assets\nOther ad hoc duties/projects assigned\nTo be successful in this position, you should meet the following requirements:\u00a0\n\nDegree in Accountancy or related disciplines\nOver 5 years relevant working experience, prior fixed asset management experience will be an advantage.\nProactive, independent, persistent and able to work under pressure to meet deadline\nGood knowledge in MS Excel/ Word, Macro / MS Access preferred\nExperience in using Oracle is an advantage\nGood command of both written and spoken English and Chinese (both Cantonese and Mandarin)\nImmediate Available is preferable\n\nWhen you work:\n\n\n5 days work\n8 hours/day\n\nWhat you enjoy:\n\nDouble pay\nDiscretionary Performance bonus\nLife insurance\nMedical insurance\nEducation subsidies\nBirthday gift\nMarriage leave\nBirthday leave\nStaff discount\n\nCMHK is committed to be an equal opportunity employer. We offer exceptional benefits package and the opportunity to work in a challenging environment. Personal data provided by applicants will be treated strictly in accordance with our personal data policy and for recruitment purposes only.\n\nPlease submit your application to us by clicking the APPLY NOW button and send your full resume with your availability, current and expected salary to us.", "employment_types": ["Full Time", "Permanent"], "selling_points": ["Double pay & Performance bonus", "Experience in using Oracle", "Good knowledge in MS Excel, Word and Access"], "locations": ["Kwai Hing"], "categories": ["Accounting", "Accountant", "Accounting Clerk / Supervisor", "Treasurer"], "post_time": "2022-01-11T07:29:22Z", "salary": {"currency": null, "max": null, "min": null, "period": null, "term": null}, "salary_visible": false, "title_keywords": ["assistant accountant"], "responsibilities": ["ad hoc duties", "reporting", "schedules", "co-ordinate with", "work under pressure", "inspection", "coordinate", "reconciliations", "daily operations", "month-end closing", "prepare reports", "insurance", "asset management"], "requirements": {"degrees": ["degree"], "majors": ["related disciplines", "accountancy"], "languages": ["cantonese", "english", "chinese", "mandarin"], "language_level": ["good command"], "hard_skills": ["macro", "word", "mobile", "ms excel", "oracle"], "soft_skills": ["independent", "persistent", "committed", "proactive", "superior", "work under pressure"], "languages_combined": [{"language": "cantonese", "language_level": ["good command"]}, {"language": "english", "language_level": ["good command"]}, {"language": "chinese", "language_level": ["good command"]}, {"language": "mandarin", "language_level": ["good command"]}]}, "experience_required": {"duration": ["5 years"], "field": ["digital", "relevant working experience", "asset management"]}}, {"job_id": "100003009046429", "location_code": "hk", "company": "Michael Page", "job_title": "Financial Controller - HK Listed Co", "description": "Financial leadership opportunity\nCorporate Finance and Strategy focused\n\nClient Details\n\nOur client is a listed retail company with strong presence in PRC. In contributing to the market growth and business strategy, they are looking for a high calibre candidate to join their management as a Financial Controller.\n\nDescription\n\nDevelop and oversee the finance & accounting functions in collaboration with regional and head offices\nProvide supervision over the finance and accounting team\nDevise the finance related policies complying to all applicable laws and regulations for the group\nDemonstrate leadership and drive the upgrade of the current reporting work flow, processes and procedures, and any other matters to optimise the operational effectiveness and efficiency\nConstantly review the designed process, system and procedures to avoid any possible business and financial risks\nAct as a key business partner with the senior management and executive in offering strategic and financial insights and recommendations for business management and decision\nOffer financial advice to management in corporate finance exercises such as M&A, investments etc.\n\nProfile\n\nQualified accountant with a degree or above in Accounting or Finance or related discipline\nMinimum of 15 years working experience includes proven track record at a senior management level\nMandatory BIG 4 training with experience at corporate level with HK listed companies\nStrong knowledge with listing compliance and statutory requirements\nPossess good communication, interpersonal and stakeholder management skills\nDemonstrate strong business acumen\nGood command of spoken and written English, Cantonese and Mandarin\n\nJob Offer\n\nAttractive remuneration package\nstable work environment\nOffice location: Central\nSenior leadership position\nRenowned and long standing brand - market leader\n\nTo apply online please click the 'Apply' button below. For a confidential discussion about this role please contact Yamen Cheung on +852 2848 9575.", "employment_types": ["Full Time", "Permanent"], "selling_points": ["Business partnering and startegy focused", "Senior position in the leadership team", "Regional exposure"], "locations": ["Not Specified"], "categories": ["Accounting", "Finance / Accounting Manager", "Financial Controller", "Treasurer"], "post_time": "2022-01-13T11:05:52Z", "salary": {"currency": null, "max": null, "min": null, "period": "monthly", "term": null}, "salary_visible": false, "title_keywords": ["financial controller"], "responsibilities": ["regulations", "reporting", "management", "policies", "review", "procedures", "compliance", "provide supervision", "develop", "communication", "statutory requirements", "contact", "senior management", "listing"], "requirements": {"degrees": ["degree or above"], "majors": ["finance", "accounting"], "languages": ["cantonese", "english", "mandarin"], "language_level": ["good command"], "hard_skills": ["business management", "acumen"], "soft_skills": ["focused", "communication", "business acumen", "stable", "leadership", "interpersonal"], "languages_combined": [{"language": "cantonese", "language_level": ["good command"]}, {"language": "english", "language_level": ["good command"]}, {"language": "mandarin", "language_level": ["good command"]}]}, "experience_required": {"duration": ["minimum of 15 years"], "field": ["management", "training", "big 4"]}}, {"job_id": "100003009037174", "location_code": "hk", "company": "Peoplus Recruitment", "job_title": "Internal Control Manager RM220111-01", "description": "Our client is a MNC Supply Chain Solution group in worldwide\u00a0is now seeking a candidate for their openings\n\nResponsibilities:\n\nReporting to Senior Manager and responsible to lead a small team to manage Internal Control and Treasury functions, and also coordinate internal and external audits\nResponsible to review internal control self-assessments to ensure compliance with Group\u2019s policy and local requirement\nReview operational and financial to identify areas of improvement\nWork with senior manager and responsible to provide recommendation and initiate new measures to improve process efficiency, internal control, risk management, corporate governance and cost saving\nHandle external audit, internal audit and other compliance activities\nWork as supervisor to manage account payable, fixed asset and treasury functions\nReview subordinates and shared service centre daily payment and treasury work\nWork closely with different departments to implement corporate initiatives and projects\n\nRequirements:\n\nQualified accountant with at least 3-year post qualification working experiences with at least 6 years\u2019 solid experience in external audit, internal audit, internal control or related areas, with at least 2 years in commercial sector\nFamiliar with accounting standards, taxation laws and Companies Ordinance\nStrong leadership with excellent influencing, communication and presentation skills\nExcellent analytical and problem solving skills with strong business acumen\nExcellent command of spoken and written English and Chinese\nProficient PC skills, knowledge in SAP is an advantage\n\nInterested parties please send full resume with followings to ryan\u00a0@peoplus.com.hk\n\n\n\n1. Current & Expected Salary\n2. Date of Availability\u00a0\n3. Quoting the Emp. Ref. No. : RM220111-01\n4. Date of Achievement : Academic Result\n\nFor a confidential discussion about this role please contact\u00a0Ryan at 3998 4490\n\nAll personal data provided by job applicants will be used for recruitment purpose only.", "employment_types": ["Full Time", "Permanent"], "selling_points": ["Perform operational and financial review", "Review internal control self-assessments", "Min. 6 related exp. & lead a small team"], "locations": ["Kwun Tong Area"], "categories": ["Accounting", "Accountant", "Credit Control", "Treasurer"], "post_time": "2022-01-11T01:58:46Z", "salary": {"currency": null, "max": null, "min": null, "period": "monthly", "term": null}, "salary_visible": false, "title_keywords": ["manager"], "responsibilities": ["reporting", "management", "cost", "internal audit", "lead a small team", "internal and external audits", "review", "audit", "compliance", "ensure compliance", "coordinate", "provide recommendation", "payment", "internal control"], "requirements": {"degrees": [], "majors": [], "languages": ["english", "chinese"], "language_level": ["excellent"], "hard_skills": ["sap", "companies ordinance", "problem solving skills", "pc skills", "internal control", "acumen"], "soft_skills": ["communication", "analytical and problem solving skills", "presentation skills", "business acumen", "leadership"], "languages_combined": [{"language": "english", "language_level": ["excellent"]}, {"language": "chinese", "language_level": ["excellent"]}]}, "experience_required": {"duration": ["at least 6 years", "at least 3-year", "at least 2 years"], "field": ["related", "commercial", "audit"]}}, {"job_id": "100003009034415", "location_code": "hk", "company": "UMP Healthcare Holdings Limited", "job_title": "Accounting Executive", "description": "UMP Vision:\u00a0To give everyone access to trusted and affordable care, so that everyone can freely pursue their dreams without worrying about their health.\nFounded in 1990, UMP Healthcare Holdings Limited is a listed company on the main board of the Hong Kong Stock Exchange (stock code: 722.HK) and one of the leading medical and healthcare platforms in Hong Kong and Macau.\nJob Descriptions;\nAssist in daily accounting operations, mainly focus on AP/AR functions\nAssist in preparing month-end closing, ensure to submit in a timely manner\nPerform commission computation and related accounts maintenance\n\u00a0About You and What Type of Skills You'll Need:\nHigher Diploma in Finance, Accounting or related disciplines\nAt least 2 years of accounting experience\nProficiency in Microsoft Excel\nExperience in SunSystem is a plus\nKeen to learn, detail-minded, positive to chase deadlines\nGood command of English and Chinese\nImmediate available is highly\u00a0preferred\n\n\n\nWhat we offer:\n\nenergetic working environment\nconvenient working location, 5 mins from MTR station\n5-day work week\n12 days+ annual leave\nDiscretionary bonus\nComprehensive medical benefits\u00a0\nMarriage leave\nExam leave\nUMP Healthcare Group is an Equal Opportunity Employer. All qualified candidates will receive consideration for employment regardless of age, disability, protected veteran status, race, color, religious creed, national origin, citizenship, marital status, sex and sexual orientation or gender identity.\n\nPlease visit our website at:\u00a0http://www.ump.com.hk\u00a0for more information about us.\u00a0All information obtained will be kept in strict confidence and used for recruitment and employment related purpose only.", "employment_types": ["Full Time", "Permanent"], "selling_points": ["Responsible for daily accounting operations", "Great opportunity to work in medical industry", "Fast growth medical group in Hong Kong"], "locations": ["Central"], "categories": ["Accounting", "Accountant", "Accounting Clerk / Supervisor", "Treasurer"], "post_time": "2022-01-10T03:21:13Z", "salary": {"currency": null, "max": null, "min": null, "period": "monthly", "term": null}, "salary_visible": false, "title_keywords": ["accounting executive"], "responsibilities": ["ap", "ar", "maintenance", "a timely manner", "daily accounting operations", "month-end closing"], "requirements": {"degrees": ["diploma"], "majors": ["related disciplines", "finance", "accounting"], "languages": ["english", "chinese"], "language_level": ["good command"], "hard_skills": ["ap", "plus", "ar", "maintenance", "microsoft excel", "code", "focus", "exchange"], "soft_skills": ["detail-minded", "keen", "timely", "focus", "positive"], "languages_combined": [{"language": "english", "language_level": ["good command"]}, {"language": "chinese", "language_level": ["good command"]}]}, "experience_required": {"duration": ["at least 2 years"], "field": ["accounting experience"]}}, {"job_id": "100003009032404", "location_code": "hk", "company": "China State Construction Engineering (Hong Kong) Limited", "job_title": "Assistant Accounting Officer/ Senior Accounting Clerk \u2013 Treasury Section", "description": "Responsibilities:\nCarry out daily treasury operations including handling daily payment, cash pooling and executing internet banking transactions.\nPrepare bank accounts opening and closing issues.\nPrepare periodic treasury reports, treasury-related accounting entries and other financial reports.\nHandle a full set of import/export documents\nAssist in month end closing, audit related assignment\nPerform other duties or ad hoc task as assigned\nRequirements:\nDiploma or above with treasury related working experience, preferable from sizable companies.\nStrong analytical and self-motivated with good problem-solving skills\nIndependent, be able to meet tight deadlines\nMore experience will be considered as \"Assistant Accounting Officer\"\n\n\nWe offer attractive remuneration package with comprehensive fringe benefits to the right candidates. Interested parties please send resume with\u00a0day-time contact number, expected salary and quoting Ref. No.\u00a0to Human Resources Manager, 29/F., China Overseas Building, 139 Hennessy Road, Wanchai, Hong Kong or e-mail or fax to 2528 2840.\nInterested parties are invited to visit our website (www.cscechk.com/en) for more information.\nApplicants who are not invited within 2 months may consider their applications unsuccessful. All information provided by applicants will be treated in strict confidence and used only for recruitment purposes. Applicants may be considered for other suitable positions within the China Overseas Group and its related companies for one-year period, thereafter which their personal data will be destroyed.\nServing The Community\u00a0\u3002\u00a0Prospering Hong Kong", "employment_types": ["Full Time", "Permanent"], "selling_points": ["Diploma or above with treasury related experience", "Carry out daily treasury operations", "Double pay, bonus, attractive benefit package"], "locations": ["Wan Chai"], "categories": ["Accounting", "Accounting Clerk / Supervisor", "Treasurer"], "post_time": "2022-01-07T11:03:00Z", "salary": {"currency": null, "max": null, "min": null, "period": "monthly", "term": null}, "salary_visible": false, "title_keywords": ["accounting clerk", "assistant accounting officer"], "responsibilities": ["financial reports", "month end closing", "perform other duties", "ad hoc", "operations", "audit", "transactions", "payment", "executing", "reports", "banking"], "requirements": {"degrees": ["diploma or above"], "majors": [], "languages": [], "language_level": [], "hard_skills": ["problem-solving skills", "sizable companies"], "soft_skills": ["problem-solving skills", "self-motivated", "independent", "meet tight deadlines"], "languages_combined": []}, "experience_required": {"duration": [], "field": ["related", "accounting"]}}, {"job_id": "100003009024338", "location_code": "hk", "company": "Atom International Technology Limited", "job_title": "Treasury Analyst", "description": "Job Description\nJOB DUTY\n\nAssist to perform treasury functions and post-trade operations\nManage & maintain asset funding, money gap limit control, settlement control & all transactions relating to customer loans, deposits and their positions\nCheck dealing tickets / position of crypto transactions and ensure the transactions are complied with company policy\nAssist to prepare reports on asset and liability, liquidity checks, revenue monitor, settlement records etc.\nProactively to communicate platform information / instant market impacts to department head and business departments\n\n\nREQUIREMENTS\n\nDegree holder, any discipline is welcome to apply\nWork experience in financial institutions, preferably in settlements and operations\nExperience in treasury business including back office and middle office would be considered\nA good team player with excellent communication, presentation and interpersonal skills\nStrong spreadsheet skills, knowledge of database coding is an advantage\nProficient in English, multi-lingual is required\nAssist to perform treasury functions and post-trade operations\nManage & maintain asset funding, money gap limit control, settlement control & all transactions relating to customer loans, deposits and their positions\nCheck dealing tickets / position of crypto transactions and ensure the transactions are complied with company policy\nAssist to prepare reports on asset and liability, liquidity checks, revenue monitor, settlement records etc.\nProactively to communicate platform information / instant market impacts to department head and business departments", "employment_types": ["Full Time"], "selling_points": ["Treasury", "Settlements & Operations", "Post-trade reconciliation"], "locations": ["North Point"], "categories": ["Accounting", "Accountant", "Finance / Accounting Manager", "Treasurer"], "post_time": "2022-01-05T15:47:27Z", "salary": {"currency": null, "max": null, "min": null, "period": "monthly", "term": null}, "salary_visible": false, "title_keywords": ["analyst"], "responsibilities": ["control", "operations", "monitor", "transactions", "maintain", "prepare reports"], "requirements": {"degrees": ["degree holder"], "majors": [], "languages": ["english"], "language_level": ["proficient"], "hard_skills": ["crypto", "gap", "spreadsheet"], "soft_skills": ["communication", "good team player", "interpersonal skills", "presentation"], "languages_combined": [{"language": "english", "language_level": ["proficient"]}]}, "experience_required": {"duration": [], "field": ["financial institutions", "business"]}}, {"job_id": "100003009023588", "location_code": "hk", "company": "Pathos Consultancy Limited", "job_title": "Senior Treasury Analyst, 35-40K per month", "description": "The Company\nOur client is a multinational corporation with strong global presence, they are now hiring a Senior Treasury Analyst to join the team.\n\nThe Role\n\n\nReport to Treasury Manager to handle regional treasury functions\nPerform cash and working capital management\nMonitor cash flow and prepare forecasts and FX reports\nPerform accounts reconciliation related to accounts payable\nInvolve in internal control and process enhancement projects\n\n\n\nYour Profile\n\n\nDegree holder\n3-5 years treasury experience gained from sizeable MNCs\nFluent in English & Cantonese\nFast paced and can-do attitude\n\nApply Today\nTo apply online (Word attachment only), please click the 'Apply' button. Interested parties please apply with the most updated CV with expected salary and available date via JobsDB. Applicants who do not hear from us within 2 weeks may consider their applications unsuccessful.\u00a0\n\nAbout Pathos\nWe are Pathos Consultancy Limited, a boutique recruitment firm based in Hong Kong strategically placing our candidates across all levels in permanent, temporary and contract roles.\u00a0 We specialize in IT and finance roles for banking, financial services and listed MNC sectors.", "employment_types": ["Full Time", "Permanent"], "selling_points": ["Treasury Analyst", "FX", "Regional role"], "locations": ["Central"], "categories": ["Accounting", "Accounting Clerk / Supervisor", "Finance / Accounting Manager", "Treasurer"], "post_time": "2022-01-05T09:13:48Z", "salary": {"currency": null, "max": null, "min": null, "period": "monthly", "term": null}, "salary_visible": false, "title_keywords": ["analyst"], "responsibilities": ["management", "monitor", "cash flow", "reports", "enhancement projects", "internal control", "accounts payable", "report"], "requirements": {"degrees": ["degree holder"], "majors": [], "languages": ["cantonese", "english"], "language_level": ["fluent"], "hard_skills": ["word", "internal control"], "soft_skills": ["can-do attitude"], "languages_combined": [{"language": "cantonese", "language_level": ["fluent"]}, {"language": "english", "language_level": ["fluent"]}]}, "experience_required": {"duration": ["3-5 years"], "field": []}}, {"job_id": "100003009039769", "location_code": "hk", "company": "Michael Page", "job_title": "CFO, Family Office, Negotiable", "description": "Our client is a reputable family office. They are now looking for a CFO to join their team.\n\nClient Details\n\nOur client is a reputable family office. They are now looking for a CFO to join their team.\n\nDescription\n\nReporting to the Family Member, you will be\n\nlooking after the family office and the finance function\npreparing management reporting and performing various analyses and planning\nperforming compliance and tax issues\nperforming other adhoc tasks when necessary\n\nProfile\n\nDegree Holder in Business/Accounting/Finance\nCPA qualification is a must\nExisting CFO at a reputable company is a must\nExcellent communication skills (English and Mandarin)\n\nJob Offer\n\nCompetitive remuneration\nFast and dynamic business growth\nReputable company\n\nTo apply online please click the 'Apply' button below.\nFor a confidential discussion about this role please contact Nicole Hui on +852 3412 4832.", "employment_types": ["Full Time", "Permanent"], "selling_points": ["Must be existing CFO at Large Corp", "Prefer stable candidates", "Well-established family office"], "locations": ["Not Specified"], "categories": ["Accounting", "Chief Accountant", "Financial Controller", "Treasurer"], "post_time": "2022-01-11T11:04:29Z", "salary": {"currency": null, "max": null, "min": null, "period": "monthly", "term": null}, "salary_visible": false, "title_keywords": ["cfo"], "responsibilities": ["tax", "reporting", "compliance", "communication", "management reporting", "contact", "planning"], "requirements": {"degrees": ["degree holder"], "majors": ["finance", "business", "accounting"], "languages": ["english", "mandarin"], "language_level": ["excellent"], "hard_skills": ["cpa", "dynamic"], "soft_skills": ["communication skills", "dynamic"], "languages_combined": [{"language": "english", "language_level": ["excellent"]}, {"language": "mandarin", "language_level": ["excellent"]}]}, "experience_required": {"duration": [], "field": []}}, {"job_id": "100003009037196", "location_code": "hk", "company": "Michael Page", "job_title": "APAC Finance Manager - Technology (Unicorn Start Up)", "description": "Head of finance position\nInternational work environment\n\nClient Details\n\nOur client is a well-known unicorn start up. They are looking for candidate with strong leadership and drive to join them as APAC Finance Manager to head up the team.\n\nDescription\n\nDirect report to Global Head of Finance\nResponsible for the function of Finance and Risk in APAC\nControlling, planning and reporting: provide strong leadership in driving the financial exercises in this region\nWork closely with APAC accounting team and set up future direction\nResponsible for Cash and working capital management\n\nProfile\n\nQualified accountant with 7 years of experiences in corporate finance / accounting & finance\nExcellent command of English\nSelf starter, high flyer and capable do-er\nStrong leadership and able to tackle challenges\n\nJob Offer\n\nAttractive remuneration package with stock options\nCareer advance to be head of regional finance function\nRegional exposure in an up-and-coming industry\nPart of APAC management team\nHigh autonomy and space to prove yourself\n\nTo apply online please click the 'Apply' button below. For a confidential discussion about this role please contact Yamen Cheung on +852 2848 9575.", "employment_types": ["Full Time", "Permanent"], "selling_points": ["Highly Initiating - you build your own team", "Regional leadership position with high autonomy", "Energetic, aspiring and high flyer wanted"], "locations": ["Not Specified"], "categories": ["Accounting", "Finance / Accounting Manager", "Financial Controller", "Treasurer"], "post_time": "2022-01-11T02:02:22Z", "salary": {"currency": null, "max": null, "min": null, "period": "monthly", "term": null}, "salary_visible": false, "title_keywords": ["finance manager"], "responsibilities": ["reporting", "management", "management team", "contact", "report", "planning"], "requirements": {"degrees": [], "majors": [], "languages": ["english"], "language_level": ["excellent"], "hard_skills": [], "soft_skills": ["leadership", "capable", "responsible"], "languages_combined": [{"language": "english", "language_level": ["excellent"]}]}, "experience_required": {"duration": ["7 years"], "field": ["finance", "accounting", "corporate finance"]}}, {"job_id": "100003009030380", "location_code": "hk", "company": "Goldsland Holdings Co Ltd", "job_title": "\u8cc7\u91d1\u4e3b\u7ba1/\u8ca1\u52d9\u7d93\u7406", "description": "\u5d17\u4f4d\u8077\u8cac\uff1a\n1\u3001\u8ca0\u8cac\u65e5\u5e38\u6191\u8b49\u7684\u7de8\u88fd\u5de5\u4f5c\uff0c\u5c0d\u9280\u884c\u7d50\u9918\u3002\n2\u3001 \u73fe\u91d1\u652f\u4ed8\u53ca\u7ba1\u7406\uff0c\u65e5\u5e38\u5230\u9280\u884c\u6253\u7c3f\u53ca\u5165\u652f\u7968\u3001\u8f49\u8cec\u7b49\u9280\u884c\u696d\u52d9\u3002\n3\u3001 \u6bcf\u6708\u5c0d\u6240\u7ba1\u7406\u59a5\u5354\uff0c\u6838\u5c0d\u9280\u884c\u9918\u984d\uff0c\u8655\u7406\u6536\u652f\u55ae\u64da(\u5305\u62ec\u652f\u7968\u652f\u51fa)\uff0c\u5b9a\u88fd\u8cc7\u91d1\u65e5\u5831\u8868\u3002\n4\u3001 \u8cc7\u91d1\u6838\u7b97\uff0c\u8fa6\u7406\u6bcf\u5e74\u5404\u9280\u884c\u6388\u4fe1\u51fd\u7684\u8abf\u6574\u53ca\u66f4\u65b0\u4e8b\u5b9c(\u5305\u62ec\u5411\u96c6\u5718\u63d0\u4ea4\u7e8c\u7c3d\u8acb\u793a\u8aaa\u660e)\u3002\n5\u3001 \u8fa6\u7406\u9280\u884c\u501f\u6b3e\uff0c\u5354\u52a9\u9999\u6e2f\u5e74\u5be9\u3001\u570b\u5167\u5e74\u5be9\uff0c\u958b\u6236\u9280\u884c\u7684\u8fa6\u7406\u3002\n6\u3001 \u8ca0\u8cac\u8cbb\u7528\u5831\u92b7\u7968\u64da\u7684\u5be9\u6838\uff0c\u4fdd\u8a3c\u5831\u92b7\u624b\u7e8c\u53ca\u7968\u64da\u7684\u5408\u898f\u53ca\u6e96\u5099\u6027\u3002\n7\u3001 \u53ca\u6642\u5c0d\u6703\u8a08\u6191\u8b49\u8cec\u76ee\u3001\u5831\u8868\u7b49\u9032\u884c\u6536\u96c6\uff0c\u88dd\u8a02\u6b78\u6a94\u7b49\u3002\n8\u3001 \u5176\u4ed6\u76f8\u95dc\u51fa\u7d0d\u5de5\u4f5c\u3002\n\n\u5d17\u4f4d\u8981\u6c42\uff1a\n1\u3001\u526f\u5b78\u58eb\u53ca\u4ee5\u4e0a\u5b78\u6b77\uff0c\u9700\u6709\u8ca1\u52d9\u53ca\u6703\u8a08\u57fa\u790e\u3002\n2\u3001\u719f\u7df4\u4f7f\u7528office\u7b49\u8fa6\u516c\u8edf\u4ef6\uff0c\u91d1\u8776\u8edf\u4ef6\uff0c\u5177\u6709\u826f\u597d\u7684\u5b78\u7fd2\u3001\u6e9d\u901a\u3001\u5354\u8abf\u80fd\u529b\u3002\n3\u3001\u6709\u826f\u597d\u5718\u968a\u5408\u4f5c\u7cbe\u795e\uff0c\u5177\u6709\u9ad8\u5c1a\u7684\u8077\u696d\u7d20\u8cea\uff0c\u5c0d\u5de5\u4f5c\u8a8d\u771f\u3001\u8aa0\u5be6\u3001\u4e3b\u52d5\u3001\u7d30\u7dfb\u3001\u80fd\u627f\u53d7\u58d3\u529b\u3002\n4\u3001\u53ef\u7acb\u5373\u4e0a\u73ed\u512a\u5148\u3002", "employment_types": ["Full Time"], "selling_points": [], "locations": ["Tsim Sha Tsui"], "categories": ["Accounting", "Treasurer"], "post_time": "2022-01-07T07:22:06Z", "salary": {"currency": null, "max": null, "min": null, "period": "monthly", "term": null}, "salary_visible": false, "title_keywords": [], "responsibilities": [], "requirements": {"degrees": [], "majors": [], "languages": [], "language_level": [], "hard_skills": [], "soft_skills": [], "languages_combined": []}, "experience_required": {"duration": [], "field": []}}, {"job_id": "100003009028141", "location_code": "hk", "company": "Century City Holdings Limited", "job_title": "Administration Clerk", "description": "Responsibilities\uff1a\n\n-\u00a0\u00a0\u00a0\u00a0\u00a0\u00a0\u00a0\u00a0\u00a0 Execute clerical functions to the Treasury department\n\n-\u00a0\u00a0\u00a0\u00a0\u00a0\u00a0\u00a0\u00a0\u00a0 Prepare periodic reports, treasury-related accounting entries and other financial reports\n\n-\u00a0\u00a0\u00a0\u00a0\u00a0\u00a0\u00a0\u00a0\u00a0 Participate in other ad-hoc administrative departmental assignments\n\nRequirements:\n\n-\u00a0\u00a0\u00a0\u00a0\u00a0\u00a0\u00a0\u00a0\u00a0\u00a0\u00a0\u00a0\u00a0 Form 6 HKDSE graduate or higher\n\n-\u00a0\u00a0\u00a0\u00a0\u00a0\u00a0\u00a0\u00a0\u00a0\u00a0\u00a0\u00a0\u00a0 Clerical experience is preferred\n\n-\u00a0\u00a0\u00a0\u00a0\u00a0\u00a0\u00a0\u00a0\u00a0\u00a0\u00a0\u00a0\u00a0 Skill in using word processing and spreadsheet applications is an advantage\n\n-\u00a0\u00a0\u00a0\u00a0\u00a0\u00a0\u00a0\u00a0\u00a0\u00a0\u00a0\u00a0\u00a0 Knowledge in accounting is an advantage\n\n-\u00a0\u00a0\u00a0\u00a0\u00a0\u00a0\u00a0\u00a0\u00a0\u00a0\u00a0\u00a0\u00a0 Diligent, responsible and willing to learn\n\n-\u00a0\u00a0\u00a0\u00a0\u00a0\u00a0\u00a0\u00a0\u00a0\u00a0\u00a0\u00a0\u00a0 Fresh graduate will also be considered\n\n\n\nWe offer attractive remuneration package to the right candidate. Please click \u201cApply Now\u201d to submit your full resume with present and expected salaries.\n\nAll personal data / information provided by applicants to the Century City Group is used for recruitment and related purpose(s) only.\n\nWe are an Equal Opportunities Employer.", "employment_types": ["Full Time", "Permanent"], "selling_points": ["Fresh graduate will be considered", "Clerical position for Treasury Department", "Good work-life balance"], "locations": ["Causeway Bay"], "categories": ["Accounting", "Treasurer", "Others", "Admin & HR", "Clerical / Admin Staff"], "post_time": "2022-01-07T01:36:52Z", "salary": {"currency": null, "max": null, "min": null, "period": "monthly", "term": null}, "salary_visible": false, "title_keywords": ["clerk"], "responsibilities": ["ad-hoc", "financial reports", "reports"], "requirements": {"degrees": ["hkdse", "fresh graduate"], "majors": [], "languages": [], "language_level": [], "hard_skills": ["spreadsheet", "word processing"], "soft_skills": ["willing to learn", "diligent", "responsible"], "languages_combined": []}, "experience_required": {"duration": [], "field": ["clerical"]}}, {"job_id": "100003009027225", "location_code": "hk", "company": "DBS Bank Ltd", "job_title": "Vice President, Corporate Treasury, Finance", "description": "Business Function\n\nGroup Finance aims to deliver world-class standards in reporting, financial planning and finance processes. We provide insights and analyses that help the bank make sound business decisions \u2013 whether in the areas of product development or customer profitability. We also provide capital management, business planning, forecasting, and tax and accounting advisory services.\n\nResponsibilities\n\nHong Kong ALCO and Balance Sheet Management:\n\nAssist the Team Head and HK ALCO in formulating balance sheet strategies and presenting this in an effective manner to ALCO/senior management. Maintain close on-the-ground engagements with the business units to understand business drivers and execute balance sheet steers efficiently.\n\nFunds Transfer Pricing (FTP) Calibration:\n\nBe familiar with FTP policies and principles. Manage day-to-day FTP setting in line with the Hong Kong ALCO strategy. Interact with the business units for any FTP quotations and program discussions.\n\nBalance Sheet Analytics:\n\nProvide data-driven insights into balance sheet trends, risks, and mitigation strategies, which would lead to increased balance sheet efficiency (Net Interest Income, Net Interest Margin, Return on Equity, etc). Be familiar with analytics tools available.\n\nMarkets:\n\nSupport local execution of the HQLA duration rebalancing portfolio and contribute to market views. Manage HK wholesale funding requirements to maintain structural liquidity ratios.\n\nRegulatory & Others:\n\nEnsure all relevant regulatory liquidity ratios managed by CT are adhered to. Be familiar with Central Operations market risk limits and ensure adherence.\n\nAssist the Team Head in management reporting and provide CT support to strategic projects when required.\n\nRequirements\n\n5+ years in balance sheet management (Asset Liability Management, Funding & Liquidity, Market and Liquidity risk, Capital, etc.) functions. Business experience with close interaction with ALCO/ balance sheet management functions would be considered.\nHaving experience working in a dealing room environment will be an advantage.\nUniversity degree in finance/ accounting/ economics/ risk management/ engineering, preferably with CPA/CFA/FRM qualifications and/or Certified Treasury Management Professional under HKMA\u2019s Enhanced Competency Framework in Treasury Management (ECF-TM).\nA strong understanding of financial markets products \u2013 FX swaps, derivatives, MTNs, regulatory assets (HQLA), etc\nUnderstanding key drivers of balance sheet management \u2013 liquidity ratios, FTP, capital\nFamiliar with liquidity regulations in HK\nKeeping abreast of macro-economic environment and implications on funding markets/liquidity condition.\nStrong communication and interpersonal skills in stakeholders\u2019 management\nSelf-starter with ability to multi-task, strong desire to learn and to be a team player\nDemonstrated ability to deliver against tight deadlines\nMotivated to establish and drive projects within Finance team and with Group\nFamiliarity with market data systems (Reuters, Bloomberg) and Murex would be an advantage.\n\nApply Now\n\nWe offer a competitive salary and benefits package and the professional advantages of a dynamic environment that supports your development and recognises your achievements.\n\nWe regret only shortlisted candidates will be notified.", "employment_types": ["Full Time"], "selling_points": ["Pension Fund Scheme", "Medical Coverage for Family", "Career Development"], "locations": ["Central"], "categories": ["Accounting", "Treasurer", "Banking / Finance", "Corporate Banking", "Treasury"], "post_time": "2022-01-06T09:25:36Z", "salary": {"currency": null, "max": null, "min": null, "period": "monthly", "term": null}, "salary_visible": false, "title_keywords": ["vice president"], "responsibilities": [], "requirements": {"degrees": [], "majors": [], "languages": [], "language_level": [], "hard_skills": [], "soft_skills": [], "languages_combined": []}, "experience_required": {"duration": [], "field": []}}, {"job_id": "100003009020604", "location_code": "hk", "company": "China Telecom Global Limited", "job_title": "Treasury Officer", "description": "Key Responsibilities:\n\nResponsible for daily treasury operations\nManage bank accounts including preparing the related banking documentations\nPrepare bank account balance report\nMonitor the daily fund balance and arrange fund transfer or term deposit\nManage bank guarantee operations\nManage bank credit facilities and maintains bank relations\nHandle ad hoc assignments as requested by the supervisor\n\nJob Requirements:\n\nDegree holder in finance/accounting or related discipline, holder of professional qualification is an advantage\nAt least with 2 years of relevant MNC treasury experience\nProficiency in MS Excel, Word and PowerPoint\nStrong analytical and problem solving skills\nAble to work independently under pressure and tight deadlines\nGood command of both spoken and written English and Chinese including Cantonese and Mandarin\nImmediately available is preferred\n\nWe offer 5 days work, competitive salary package and attractive career development opportunities to the right candidate.\u00a0\n\nInterested parties please email your full resume with your current & expected salary to us.\n\nApplicants not invited for interview within 3 months may assume their applications unsuccessful.\u00a0\n\nIf you are interested in other job opportunities, please check with below career website.\n\nPersonal data collected would be used for recruitment purpose only.\u00a0", "employment_types": ["Full Time", "Permanent"], "selling_points": ["With MNC treasury experience", "Immediately available is preferred", "Competitive salary package"], "locations": ["Wan Chai"], "categories": ["Accounting", "Accountant", "Treasurer", "Others"], "post_time": "2022-01-04T16:29:01Z", "salary": {"currency": null, "max": null, "min": null, "period": "monthly", "term": null}, "salary_visible": false, "title_keywords": ["officer"], "responsibilities": ["operations", "monitor", "ad hoc assignments", "banking", "report"], "requirements": {"degrees": ["degree holder"], "majors": ["finance", "accounting"], "languages": ["cantonese", "english", "chinese", "mandarin"], "language_level": ["good command"], "hard_skills": ["ms excel", "problem solving skills", "word", "powerpoint"], "soft_skills": ["analytical and problem solving skills", "work independently", "under pressure"], "languages_combined": [{"language": "cantonese", "language_level": ["good command"]}, {"language": "english", "language_level": ["good command"]}, {"language": "chinese", "language_level": ["good command"]}, {"language": "mandarin", "language_level": ["good command"]}]}, "experience_required": {"duration": ["2 years"], "field": []}}, {"job_id": "100003009024232", "location_code": "hk", "company": "Under Armour Asia Limited", "job_title": "Assistant Manager, Accounts Payable, APAC", "description": "This individual will supervise a team to manage the APAC Accounts Payable function, execute best-practice processes and adherence to company policies, internal controls and local statutory requirements.\n\n\n\nESSENTIAL DUTIES & RESPONSIBILITIES:\n\n\nOversee month end close activities, including account reconciliations and AP aging analysis\nWorking capital monitoring, cash flow forecast and coordinate intercompany settlement\nCoach PTP teammates and work closely with US AP team and HK procurement team to ensure accurate and on time payments. Monitor completion of assigned tasks in line with expected timing and quality\nImprove and streamline procure to pay (PTP) processes for the whole APAC region, develop internal control checkpoints to ensure all processes are completed in compliance with group policy, internal control standards and local statutory requirements\nCreate and maintain Key Performance Indicators (KPI) to measure PTP team performance, drive continuous improvement and deliver defined PTP Service Level Agreement (SLA)\nPositively influence and educate business team on the Company\u2019s AP policies. Be a great business partner to APAC leadership team, provide timely response on any payments queries and expense analysis\nHandle ad-hoc treasury and account payable projects, including Ariba, Concur and SAP FMS enhancement\nPerform ad hoc tasks as assigned.\n\nQUALIFICATION & REQUIREMENTS:\n\n\nDegree in Accounting/Finance or related discipline\nQualified accountant from ACCA/ HKICPA or equivalent is preferred\nAt least 5 years' accounting experiences in sizeable multinational company with at least 3 years in supervisory role. Retail and shared services role experience is a plus.\nStrong customer service orientation with excellent oral and written communication skills\nAbility to multi-task and prioritize in a fast-paced environment\nProficiency in PC skills, Excel, PowerPoint and Word\nExperience with SAP FMS or Ariba is a plus\nExcellent verbal and written communication skills (strong English language skills)", "employment_types": ["Full Time", "Permanent"], "selling_points": ["Retail accounting / Accounts payable", "Process Improvement / Procure to pay", "SAP / ERP / FMS"], "locations": ["Kowloon Bay"], "categories": ["Accounting", "Accountant", "Accounting Clerk / Supervisor", "Treasurer"], "post_time": "2022-01-05T11:45:00Z", "salary": {"currency": null, "max": null, "min": null, "period": "monthly", "term": null}, "salary_visible": false, "title_keywords": ["assistant manager,"], "responsibilities": ["ap", "ad-hoc", "ad hoc tasks", "policies", "analysis", "monitoring", "monitor", "quality", "compliance", "develop", "coordinate", "reconciliations", "cash flow", "statutory requirements", "payments", "maintain", "forecast", "internal control"], "requirements": {"degrees": ["degree"], "majors": ["finance", "accounting"], "languages": ["english"], "language_level": ["excellent"], "hard_skills": ["excel", "acca", "plus", "sap", "fms", "word", "powerpoint", "pc skills", "hkicpa"], "soft_skills": ["communication skills", "oral", "multi-task", "fast-paced environment", "prioritize", "customer service"], "languages_combined": [{"language": "english", "language_level": ["excellent"]}]}, "experience_required": {"duration": ["at least 3 years", "at least 5 years"], "field": ["supervisory", "accounting", "multinational company", "retail"]}}, {"job_id": "100003009012618", "location_code": "hk", "company": "ConnectedGroup Limited", "job_title": "Regional Treasury Manager (48k - 50k)", "description": "Regional Treasury Manager (48k - 50k)\n\nOur client is a giant listed consumer business. They are looking for a talented and driven individual to join its growing Treasury team. The position offers excellent training, broad exposure and ample room to grow. This is an opportunity to build your career at a corporation with strong heritage and at the same time experience the excitement of business transformation.\n\nPosition Responsibilities\n\nHandle global treasury reporting against KPIs\nWork in a global team, drive improvement projects\nManage global interest expense forecasting and cash flow simulations\nRecommend optimum capital structure, perform simulations to senior management\nConduct working capital AR analysis and liaise with local teams\nCalculation of rating agencies' reports and manage KPIs\nHandle Relationship Management and negotiations of bank facilities\nAssist in MTN renewal and private placement/bond issuances\nPerform FX sensitivity analysis\nValidate closing figures reported by countries for cash, loans, bonds, FX MTM\nIdentify Group's FX exposure and determine hedging instruments\nPerform credit rating analysis of the Group and liaise with credit rating agency\n\nPosition Requirements\n\nUniversity graduate in Finance/ Accounting or relevant disciplines\nMinimum 6-8 years' experience in Treasury in Financial Services industry\nProficiency in both written and spoken English\nCPA or CFA qualification is a plus\nStrong analytical skills\nSelf-motivation/ High energy\nAble to work under pressure, result oriented, willing to accept challenge\nSolid Project Management experience\nStrong leadership and communication skills to foster an environment of collaboration and drive process improvements\n\nInterested individuals can apply now and send CV to Vivian Wong, or call +852 3972 5831 for more information. Only relevant candidates will be contacted\n\nFor a more comprehensive list of our vacancies, please visit: www.connectedgroup.com", "employment_types": ["Full Time", "Permanent"], "selling_points": ["One of the market leading players in the industry", "Team management exposure", "Attractive package with promising career prospect"], "locations": ["Not Specified"], "categories": ["Accounting", "Finance / Accounting Manager", "Treasurer", "Others"], "post_time": "2022-01-01T07:00:35Z", "salary": {"currency": null, "max": null, "min": null, "period": "monthly", "term": null}, "salary_visible": false, "title_keywords": ["manager"], "responsibilities": ["reporting", "management", "ar", "analysis", "teams", "cash flow", "reports", "liaise with", "kpis", "senior management", "forecasting"], "requirements": {"degrees": ["university graduate"], "majors": ["finance", "accounting"], "languages": ["english"], "language_level": ["proficiency"], "hard_skills": ["plus", "cfa", "analytical skills", "cpa", "project management"], "soft_skills": ["communication skills", "analytical skills", "project management", "result oriented", "self-motivation", "comprehensive", "leadership", "work under pressure"], "languages_combined": [{"language": "english", "language_level": ["proficiency"]}]}, "experience_required": {"duration": ["minimum 6-8 years"], "field": ["project management", "financial services industry"]}}, {"job_id": "100003009023007", "location_code": "hk", "company": "Eternity Consultants (HK) Ltd", "job_title": "Accounting and Administration Supervisor", "description": "1. \u8655\u7406\u5168\u5957\u5e33\u76ee\u3001\u8ca1\u52d9\u5831\u544a\u53ca\u9810\u7b97\u5831\u544a\n\n2. \u65e5\u5e38\u6703\u8a08\u8077\u80fd(\u5305\u62ec\uff1a\u7c3d\u767c\u652f\u7968\u3001\u9280\u884c\u5165\u5e33\u3001\u6578\u64da\u8f38\u5165\u3001\u9280\u884c\u5c0d\u5e33\u3001\u57f7\u884c\u7c3f\u8a18\u3001\u6e96\u5099\u5de5\u7a0b/\u9805\u76ee\u5831\u50f9\u3001\u767c\u7968\u53ca\u5c0d\u5e33\u7b49)\n\n3. \u8207\u6838\u6578\u5e2b\u6e9d\u901a\u9032\u884c\u5e74\u7d50\u53ca\u5be9\u6838\u5831\u544a\n\n4. \u8ddf\u9032\u903e\u671f\u672a\u4ed8\u6b3e\u9805\n\n5. \u6e96\u5099\u516c\u53f8\u5468\u5e74\u7533\u5831\u8868\u53ca\u905e\u4ea4\n\n6. \u6e96\u5099\u54e1\u5de5\u85aa\u4ff8\u7a05\u6587\u4ef6\u53ca\u905e\u4ea4\n\n7. \u70ba\u7ba1\u7406\u5c64\u3001\u71df\u696d\u90e8\u53ca\u5de5\u7a0b\u90e8\u63d0\u4f9b\u884c\u653f\u53ca\u696d\u52d9\u652f\u6301\n\n8. \u4fdd\u6301\u826f\u597d\u6703\u8a08\u53ca\u884c\u653f\u6b78\u6a94\u7cfb\u7d71\n\n9. \u6839\u64da\u9700\u8981\u57f7\u884c\u81e8\u6642\u4efb\u52d9\n\n10. \u958b\u767c\u55ae\u7d66\u9999\u6e2f\u53ca\u570b\u5167\u5ba2\u6236\n\n\u8cc7\u6b77\uff1a\n\n1. \u4e94\u5e74\u4ee5\u4e0a\u5168\u76e4\u6703\u8a08\u5e33\u76ee\u7d93\u9a57\n\n2. \u5c08\u4e0a\u6559\u80b2\n\n3. \u64c1\u6709\u4e2d\u570b\u6703\u8a08\u57fa\u672c\u77e5\u8b58\n\n4. \u826f\u597d\u4e2d\u82f1\u6587\u6e9d\u901a\u80fd\u529b\n\n5. \u61c2\u5f97\u9999\u6e2f\u52de\u5de5\u6cd5\u4f8b\n\n\u5f85\u9047\uff1a\n\n1. \u6bcf\u6708\u6e2f\u5e6320000-25000\n\n2. \u4e94\u5929\u5de5\u4f5c(\u4e0a\u534809:30-\u4e0b\u534818:00)\n\n4. \u5e74\u7d42\u96d9\u7ce7\n\n5. \u9280\u884c\u5047\u671f\n.\n\n*\u6709\u610f\u8005\u8acb\u5c07\u500b\u4eba\u5c65\u6b77, \u9023\u540c\u4eba\u5de5\u8981\u6c42, \u96fb\u90f5 MS WORD \u7248\u672c\u4e88\u6211\u53f8\u00a0 \u00a0 account@HKETERNITY. com \u00a0\u6216\u50b3\u771f\u5230 3527 0634.\n\n\u82e5\u6c42\u8077\u8005\u4ee5\u5f80\u66fe\u7d93\u905e\u4ea4\u500b\u4eba\u5c65\u6b77\u4e88\u6211\u53f8, \u6b61\u8fce\u518d\u6b21\u905e\u4ea4.\n\n\u66f4\u591a\u4e0d\u540c\u7684\u5de5\u4f5c:\u00a0www.hketernity.com\n\n\u00a0(\u6240\u6709\u500b\u4eba\u8cc7\u6599\u50c5\u4f9b\u62db\u8058\u7528\u9014)", "employment_types": ["Full Time", "Permanent"], "selling_points": ["\u8655\u7406\u5168\u5957\u5e33\u76ee\u3001\u8ca1\u52d9\u5831\u544a\u53ca\u9810\u7b97\u5831\u544a", "\u70ba\u7ba1\u7406\u5c64\u3001\u71df\u696d\u90e8\u53ca\u5de5\u7a0b\u90e8\u63d0\u4f9b\u884c\u653f\u53ca\u696d\u52d9\u652f\u6301", "\u64c1\u6709\u4e2d\u570b\u6703\u8a08\u57fa\u672c\u77e5\u8b58"], "locations": ["Not Specified"], "categories": ["Accounting", "Accounting Clerk / Supervisor", "Taxation", "Treasurer"], "post_time": "2022-01-05T07:11:26Z", "salary": {"currency": null, "max": null, "min": null, "period": "monthly", "term": null}, "salary_visible": false, "title_keywords": ["accounting", "supervisor"], "responsibilities": [], "requirements": {"degrees": [], "majors": [], "languages": [], "language_level": [], "hard_skills": ["ms word"], "soft_skills": [], "languages_combined": []}, "experience_required": {"duration": [], "field": []}}, {"job_id": "100003009018947", "location_code": "hk", "company": "DHL EXPRESS (HONG KONG) LIMITED", "job_title": "Controller - Accounting (Internal Control Manager)", "description": "Reporting to Senior Manager, Accounting and Tax, you will lead a small team to manage Internal Control and Treasury functions, coordinate internal and external audits and to ensure proper internal controls are in place.\n\nResponsibilities:\n\nInternal Control\n\nReview internal control self-assessments to ensure compliance with Group\u2019s policy and local requirement at all times\nPerform operational and financial review to identify areas of improvement\nProvide feasible recommendation and initiate new measures to enhance process efficiency, internal control, risk management, corporate governance and cost saving\nHandle external audit, internal audit and other compliance activities\n\nTreasury\n\nManage account payable, fixed asset and treasury functions\nReview daily payment and treasury work performed by subordinates and shared service centre\nCollaborate with various Departments to implement corporate initiatives and projects\n\nRequirements:\n\nQualified accountant with at least 3-year post qualification working experience\nMinimum 6 years\u2019 solid experience in external audit, internal audit, internal control or related areas, with at least 2 years in commercial sector\nExposure in payment and treasury is an advantage but not mandatory\nFamiliar with accounting standards, taxation laws and Companies Ordinance\nStrong leadership with excellent influencing, communication and presentation skills\nExcellent analytical and problem solving skills with strong business acumen\nExcellent command of spoken and written English and Chinese\nProficient PC skills, knowledge in SAP is an advantage\n\nPersonal Information Collection Statement pertaining to Recruitment\n\nDHL Express (Hong Kong) Limited / DHL Aviation (Hong Kong) Limited (\u201cDHL\u201d) is committed to protecting and respecting your privacy in accordance with the Personal Data (Privacy) Ordinance of Hong Kong (the \u201cOrdinance\u201d) and DHL\u2019s Personal Data Protection Policy (the \u201cPolicy\u201d) at\u00a0https://www.dhl.com/hk-en/home/footer/local-privacy-notice.html\n\nBy proceeding to respond to this recruitment advertisement, you consent that we may use, retain, process, transfer or otherwise handle the personal data that we collect from you for recruitment,\u00a0 application processing, assessment and communication purposes (including any other purposes directly related thereto) in accordance with the Policy.\n\nAll personal data of unsuccessful applicants will be retained for future recruitment purposes for a period of not more than two (2) years after which such data will be destroyed.\n\nYou have the right at any time to make a data access or correction request concerning your personal data held by us. In addition, you may request us to delete your personal data that is no longer required for the relevant purposes which you have given consent. Should you wish to exercise such rights or have any question in relation to your personal data or the Policy, please contact our Human Resources Division in writing.", "employment_types": ["Full Time"], "selling_points": ["Review internal control self-assessments", "Perform operational and financial review", "Minimum 6 years\u2019 solid experience"], "locations": ["Ngau Tau Kok"], "categories": ["Accounting", "Accountant", "Audit", "Treasurer"], "post_time": "2022-01-04T06:14:09Z", "salary": {"currency": null, "max": null, "min": null, "period": "monthly", "term": null}, "salary_visible": false, "title_keywords": ["accounting", "manager"], "responsibilities": ["collaborate with", "management", "cost", "internal audit", "review", "compliance", "audit", "ensure compliance", "payment", "internal control"], "requirements": {"degrees": [], "majors": [], "languages": ["english", "chinese"], "language_level": ["excellent"], "hard_skills": ["no", "sap", "processing", "html", "make", "companies ordinance", "problem solving skills", "pc skills", "internal control", "acumen"], "soft_skills": ["communication", "analytical and problem solving skills", "presentation skills", "committed", "business acumen", "leadership"], "languages_combined": [{"language": "english", "language_level": ["excellent"]}, {"language": "chinese", "language_level": ["excellent"]}]}, "experience_required": {"duration": ["at least 2 years", "at least 3-year", "minimum 6 years"], "field": ["related", "commercial", "audit"]}}, {"job_id": "100003009019247", "location_code": "hk", "company": "Green Monday", "job_title": "ACCOUNT CLERK / SENIOR ACCOUNT CLERK (F&B, Retail)", "description": "Responsibilities\n\nBe the AGENT to make change happen and make GREEN common!\nResponsible for accounts receivable especially on F&B, retail and FMCG industry;\nPerform daily routine accounting transactions including reconcile sales and receipts on different F&B platforms and e-commerce;\nAssist in A/P duties, staff expenses claims, cheque payments, preparing vouchers and general ledger entries;\nMaintain petty cash and bank reconciliation;\nParticipate in month end closing tasks;\nSupport yearly or quarterly stocktake;\nAssist in ad-hoc assignments.\n\nRequirements\n\n\nPassionate in promoting green lifestyle (knowledge in vegetarian / vegan product is a plus)\nDSE or above, LCC Intermediate or above in Accounting;\nMinimum 1 year experience in accounting, relevant experience in F&B, retail, FMCG industry is definitely an advantage;\nProficient in MS Office and well versed in Excel;\nKnowledge of Flex system or Oracle Netsuite is an advantage;\nFast learner and good team player;\nImmediately available is preferred;\nCandidate with more experience will be considered as Senior Account Clerk.\nWe offer a competitive and attractive remuneration package to the right candidate.\u00a0 Interested parties please apply with full resume stating availability, current and expected salaries by clicking \"APPLY NOW\" .\n\nWe are an equal opportunity employer and welcome applications from qualified candidates.\u00a0 All information provided will be treated in strict confidence by authorized personnel and will be used only for recruitment related purpose.\u00a0 Applicants who do not hear from us within 6 weeks may consider their application unsuccessful.\u00a0 All personal data of unsuccessful applications will be destroyed after 6 months.\u00a0\n", "employment_types": ["Full Time", "Permanent"], "selling_points": ["5-day work week, double pay", "Knowledge of Flex, Oracle Netsuite is an advantage", "F&B, Retail, FMCG industry, Immediate Available"], "locations": ["Kowloon Bay"], "categories": ["Accounting", "Accountant", "Accounting Clerk / Supervisor", "Treasurer"], "post_time": "2022-01-04T07:05:52Z", "salary": {"currency": null, "max": null, "min": null, "period": "monthly", "term": null}, "salary_visible": false, "title_keywords": ["account clerk", "senior account clerk"], "responsibilities": ["month end closing", "receipts", "accounts receivable", "preparing vouchers", "general ledger", "expenses", "ad-hoc assignments", "bank reconciliation", "transactions", "maintain", "payments"], "requirements": {"degrees": ["dse"], "majors": ["accounting"], "languages": [], "language_level": [], "hard_skills": ["excel", "plus", "oracle", "fmcg industry", "lcc", "flex system", "ms office"], "soft_skills": ["passionate", "good team player", "fast learner"], "languages_combined": []}, "experience_required": {"duration": ["minimum 1 year"], "field": ["fmcg", "f&b", "relevant experience", "accounting", "retail"]}}, {"job_id": "100003009024257", "location_code": "hk", "company": "PERSOLKELLY Hong Kong Limited", "job_title": "Accounting Manager / Internal Manager / Internal Control Manager  (MNC, Double Pay, Good Bonus)", "description": "Company Profile\u00a0\n\nOur client is an award-winning market leader with offices operating across the world. To cope with the expansion of the business, they are seeking for a brand new high-caliber individual to join their expanding team. The person will be expected to take lead in the Internal Control & Treasury function of the company's expanding Business Units. Less experienced candidate will be offered a Assistant Manager title.\u00a0\u00a0\n\nExciting new role for you\u00a0\n\nDirectly report to CFO\nAct as team lead to manage the Internal Control and Treasury functions of the company and to groom subordinates\nRegularly perform review on operation and financial process to proactively suggest areas of improvements\nAct as subject-matter-expert on IC and Treasury function and provide recommendations to enhance overall efficiency of internal control, risk management, corporate governance, etc\nIn charge of internal & external audit work and other related compliance activities\nManage AP, fixed asset, and treasury activities\nLiaise with various departments to run corporate projects as well as to review daily payment & treasury activities by subordinates/shared service center\n\nRequirements\u00a0\n\nBachelor\u2019s degree or above in HR or related discipline\n5+ years of solid experience in internal/external audit, internal control, or related areas with at least 2 years in commercial sector\nExposure in payment and treasury is an advantage but not mandatory\nFamiliar with accounting standards, taxation laws and Companies Ordinance\nStrong interpersonal and stakeholder management; ability to deal with stakeholders across different levels\nStrong project management skills with the ability to juggle multiple projects\nSelf-motivated, work independently & with team, analytical, and communicate effectively in English and Mandarin\nKnowledge in SAP system is an advantage\n\nRewards\u00a0\n\nYou will be working at a high performing energetic team with great career progression. Attractive remuneration and package. Opportunity to join a market leading group with a promising career path and potential internal transfer opportunities.\u00a0\n\n\n\nInterested parties please click apply or send your application via email to\u00a0jolly_wong@persolkelly. For any enquiries, please do not hesitate to contact me at\u00a0(852) 2281 0021.\n\nWe also have various job vacancies from our well-established clients in all kinds of fields, please feel free to contact us. We are always willing to give you support on your career development\n\nAll information received will be treated in strict confidence and used for recruitment purpose only. Only shortlisted candidate will be notified.", "employment_types": ["Full Time", "Permanent"], "selling_points": ["MNC With Promising & Stable Career Path", "DOUBLE Pay, Bonus, 5-day, Full Medical, Awards", "CPA, Int Control & Treasury, Audit, Function Head"], "locations": ["Not Specified"], "categories": ["Accounting", "Accountant", "Audit", "Treasurer"], "post_time": "2022-01-05T12:06:12Z", "salary": {"currency": null, "max": null, "min": null, "period": "monthly", "term": null}, "salary_visible": false, "title_keywords": ["accounting manager", "manager"], "responsibilities": ["ap", "taxation", "management", "hr", "review", "compliance", "audit", "liaise with various departments", "project management", "payment", "provide recommendations", "multiple projects", "internal control", "report"], "requirements": {"degrees": ["degree or above", "bachelor"], "majors": [], "languages": ["english", "mandarin"], "language_level": [], "hard_skills": ["ap", "sap", "project management", "companies ordinance", "internal control"], "soft_skills": ["self-motivated", "work independently", "project management skills", "energetic", "interpersonal"], "languages_combined": [{"language": "english", "language_level": []}, {"language": "mandarin", "language_level": []}]}, "experience_required": {"duration": ["at least 2 years", "5+ years"], "field": ["related", "commercial", "audit"]}}, {"job_id": "100003009017327", "location_code": "hk", "company": "Hong Kong Express Airways Limited", "job_title": "Officer, Accounting", "description": "DEAR TALENT, YOUR MOVE!\n\nBeing the new rising airline since 2013, we are the Hong Kong\u2019s only Low Cost Carrier (LCC) offering you safe and flexible service options to Hong Kong and beyond.\n\nWe\u2019re on a mission to inspire you to be different, to shake things up, to inspire the spirit of adventure by bringing you to fascinating destinations that few others serve.\n\nSpread your wings and fly with us!\n\n\nWhat will you do?\u00a0\u00a0\n\nResponsible for payment settlement including payment status and payment cancellation;\nWork closely with the Accounts Payable team to ensure the payments settled on time;\nEnsure payment vouchers and bank reconciliations are completed in a timely manner for month-end closing;\nAssist in daily treasury operations and prepare treasury-related accounting entries, e.g. inter-account transactions and cash pooling;\nSupport ad-hoc projects and tasks as assigned.\n\nWe are a perfect match, if you have:\n\nUniversity Graduate in Finance, Accounting, Business or related discipline;\n2 years of relevant work experience;\nExperience in using Netsuite System, Electronic banking system is a plus;\nExcellent command of spoken and written English and Chinese and proficient in Microsoft Office Suite;\nExcellent numerical and analytical skills, with strong attention to detail and accuracy;\nA quick learner with the ability to work independently and as a team;\nFresh graduate will\u00a0also be\u00a0considered.\n\nYour Future Work Life?\n\nWork flexibly with staggered working hours and flexible workplace\nDress Casual and Smart everyday\nWork in a newly-designed office with open seating, stylish breakout areas, game room, gym and free coffee\u2026\nWork with a group of energetic and multicultural professionals (up to 50 nationalities!)\nHave great fun in Snack Friday, New Year Market, Fly with your Kids Day, Basketball Team\u2026\nHave your voice heard through Townhalls, Crew forums, CEO live sessions etc.\n\nWhat will you enjoy?\n\nFly anywhere we fly for free plus taxes during leisure with your friends and family\nSpecial privileges to buy duty free products\nCareer Express\n\n\n\nYou will be inspired by our core values.\nYou will be inspired by our vibrant, efficient and entrepreneurial spirit. Join our fun, collaborative and reliable team to ignite your dream!\n\n\n\nInterested? It\u2019s time to have YOUR MOVE!\nIf you're ready to embark your adventure, start by clicking the \u2018Apply now\u2019 and get on the plane to fly with HK Express!\u00a0", "employment_types": ["Full Time"], "selling_points": ["Payment settlement and bank reconciliation", "Accounting experience preferred", "Flexible work arrangements"], "locations": ["Airport Area"], "categories": ["Accounting", "Accountant", "Accounting Clerk / Supervisor", "Treasurer"], "post_time": "2022-01-03T13:34:12Z", "salary": {"currency": null, "max": null, "min": null, "period": "monthly", "term": null}, "salary_visible": false, "title_keywords": ["officer", "accounting"], "responsibilities": ["cost", "operations", "a timely manner", "bank reconciliations", "transactions", "payment", "month-end closing", "payments", "banking", "ad-hoc projects", "accounts payable"], "requirements": {"degrees": ["university graduate", "fresh graduate"], "majors": ["business", "finance", "accounting"], "languages": ["english", "chinese"], "language_level": ["excellent", "proficient"], "hard_skills": ["plus", "fun", "airline", "netsuite system", "analytical skills", "microsoft office suite", "safe", "lcc"], "soft_skills": ["flexible", "efficient", "work independently", "responsible", "timely", "collaborative", "quick learner", "analytical skills", "reliable", "attention to detail", "energetic"], "languages_combined": [{"language": "english", "language_level": ["proficient", "excellent"]}, {"language": "chinese", "language_level": ["proficient", "excellent"]}]}, "experience_required": {"duration": ["2 years"], "field": ["banking"]}}, {"job_id": "100003009009973", "location_code": "hk", "company": "China Mobile Hong Kong \u4e2d\u570b\u79fb\u52d5\u9999\u6e2f", "job_title": "Accounting Assistant (Revenue & Treasury)", "description": "CHINA MOBILE HONG KONG COMPANY LIMITED\u00a0(\"CMHK\") is the wholly-owned subsidiary of China Mobile Limited (HKEx: 941) (NYSE: CHL), which ranks 65th on the Fortune Global 500.\n\nOur company strives to offer superior service experience and to become the preferable digital partner for customers. We are preserving an environment with trust, responsibility and caring. At CMHK, we commit to maximizing people\u2019s potential and paving the way toward success for every striver. We are now inviting high caliber professional to join us.\n\nDivision:\u00a0 Finance Division -\u00a0Revenue & Treasury\n\nIn this position, you will:\n\n\nPrepare accounting entries of revenue, month end closing and reporting\nPrepare balance sheet and P&L schedules and reconciliations as well as follow up on any unusual items\nAssist in improving accounting process and leveraging technology to create efficiencies\nPerform other duties and ad hoc projects as required\nTo be successful in this position, you should meet the following requirements:\u00a0\n\n\nDegree in Accountancy/ Finance or business\u00a0related disciplines\n1 year relevant working experience with good knowledge of international accounting standards and practices preferred. Fresh graduate will also be considered.\nExperience in telecom industry and revenue accounting will be advantage\nProactive, independent, persistent and able to work under pressure to meet deadline\nGood knowledge in MS Excel/ Word, Macro / MS Access preferred\nAble to work on multiple priorities with accuracy and efficiency while keeping to deadlines\nGood command of both written and spoken English and Chinese (both Cantonese and Mandarin)\nImmediate Available is preferable\n\nWhen you work:\n\n\n5 days work\n8 hours/day\n\nWhat you enjoy:\n\nDouble pay\nDiscretionary Performance bonus\nLife insurance\nMedical insurance\nEducation subsidies\nBirthday gift\nMarriage leave\nBirthday leave\nStaff discount\n\nCMHK is committed to be an equal opportunity employer. We offer exceptional benefits package and the opportunity to work in a challenging environment. Personal data provided by applicants will be treated strictly in accordance with our personal data policy and for recruitment purposes only.\n\nPlease submit your application to us by clicking the APPLY NOW button and send your full resume with your availability, current and expected salary to us.", "employment_types": ["Full Time", "Permanent"], "selling_points": ["Double pay & Performance bonus", "Knowledge of international accounting standards", "Fresh graduate will also be considered"], "locations": ["Kwai Hing"], "categories": ["Accounting", "Accountant", "Accounting Clerk / Supervisor", "Treasurer"], "post_time": "2021-12-31T02:41:29Z", "salary": {"currency": null, "max": null, "min": null, "period": null, "term": null}, "salary_visible": false, "title_keywords": ["accounting assistant"], "responsibilities": ["reporting", "month end closing", "perform other duties", "schedules", "work under pressure", "p&l", "reconciliations", "ad hoc projects", "insurance", "balance sheet"], "requirements": {"degrees": ["degree", "fresh graduate"], "majors": ["related disciplines", "finance", "business", "accountancy"], "languages": ["cantonese", "english", "chinese", "mandarin"], "language_level": ["good command"], "hard_skills": ["mobile", "ms excel", "word", "macro"], "soft_skills": ["independent", "persistent", "committed", "proactive", "superior", "work under pressure"], "languages_combined": [{"language": "cantonese", "language_level": ["good command"]}, {"language": "english", "language_level": ["good command"]}, {"language": "chinese", "language_level": ["good command"]}, {"language": "mandarin", "language_level": ["good command"]}]}, "experience_required": {"duration": ["1 year"], "field": ["digital", "accounting", "relevant working experience"]}}, {"job_id": "100003009007727", "location_code": "hk", "company": "Links International", "job_title": "Treasury Manager - Luxury Retail", "description": "Responsibilities:\n\nSupervise day-to-day treasury operation and cash management\nWorking closely with Finance team on project funding decisions and financial projections\nReview loan and funding documents\nManage foreign exchange and interest rate risk, and FX hedging across APAC\nPrepare and submit treasury reports for senior management review\nAdvise on tax issues regarding investments & M&A projects\nManage and liaise with banks for funding and investment decisions\nBeing a strong business partner with stakeholders across different regions\n\nRequirements:\n\nBachelor Degree in Accounting & Finance or related discipline\nAt least 5 years of experience in treasury, preferably in sizeable MNC and luxury retailer\nSolid experiences in Retail and FMCG related industries are highly preferred\nSmart, energetic person who is ambitious to strive for excellence\nExcellent command of both English and Cantonese\nExcellent communication and presentation\nDynamic personality with an analytical mindset", "employment_types": ["Full Time", "Permanent"], "selling_points": ["Guaranteed 13 months salary", "Work life balance", "Regional exposure"], "locations": ["Not Specified"], "categories": ["Accounting", "Chief Accountant", "Finance / Accounting Manager", "Treasurer"], "post_time": "2021-12-30T04:03:14Z", "salary": {"currency": "HKD", "max": 54999, "min": 35000, "period": "monthly", "term": null}, "salary_visible": true, "title_keywords": ["manager"], "responsibilities": ["tax", "management", "project funding", "review", "reports", "finance team", "liaise with", "senior management"], "requirements": {"degrees": ["degree", "bachelor"], "majors": ["finance", "accounting"], "languages": ["cantonese", "english"], "language_level": ["excellent"], "hard_skills": ["dynamic"], "soft_skills": ["communication", "energetic", "dynamic", "strive for excellence", "presentation"], "languages_combined": [{"language": "cantonese", "language_level": ["excellent"]}, {"language": "english", "language_level": ["excellent"]}]}, "experience_required": {"duration": ["at least 5 years"], "field": ["related", "retail", "fmcg"]}}, {"job_id": "100003009015368", "location_code": "hk", "company": "Specialist Mortagae Limited", "job_title": "Junior Accountant  \u2013 Australian Tax", "description": "Requirements:\nDegree in accounting from a recognized Australian university\nPreference will be given to those with knowledge on Australian taxation system\nSome relevant working experience will be considered although not necessary\nProficient in most Microsoft Office applications\nOrganized, meticulous and positive mind set\nGood written and spoken English is a prerequisite\nWe offer a great working environment, 5 day work week and a competitive remuneration package.\n\nQualified candidates are invited to email their resume by clicking \"Apply Now\"\n", "employment_types": ["Full Time", "Permanent"], "selling_points": ["5 day work week", "13-month salary", "Loyalty bonus"], "locations": ["Central"], "categories": ["Accounting", "Accountant", "Treasurer", "Professional Services", "Business Analysis / Data Analysis"], "post_time": "2022-01-03T06:42:07Z", "salary": {"currency": null, "max": null, "min": null, "period": "monthly", "term": null}, "salary_visible": false, "title_keywords": ["junior accountant"], "responsibilities": ["taxation"], "requirements": {"degrees": ["degree"], "majors": ["accounting"], "languages": ["english"], "language_level": ["good"], "hard_skills": ["microsoft office"], "soft_skills": ["organized", "meticulous", "positive"], "languages_combined": [{"language": "english", "language_level": ["good"]}]}, "experience_required": {"duration": [], "field": ["relevant working experience"]}}, {"job_id": "100003009011937", "location_code": "hk", "company": "LifeHealth Group Limited", "job_title": "Accountant", "description": "Responsibilities:\n\nResponsible for full set of accounts and month-end closing including daily accounting duties\nManage AP, AR & general accounting duties in related to management account reporting\nPrepare bank reconciliations and accounts analysis\nHandle expense claims, petty cash & banking activities\nCoordinate audit schedules and liaise with external auditors\nAssist in enhancement of internal control\nPerform ad hoc duties as required\n\nRequirements:\n\nHigher Diploma/Degree or about in Accountancy\nMinimum 5 years of working experiences in accounting\nGood comments in MS Office application, specially for MS Excel\nExperience in retails / medical company and flex system is an advantage\nSelf-motivated, hardworking and strong sense of responsibility\nImmediately available is preferred\nCandidate will less experience will be considered for position of Assistant Accountant\n\nWe offer 5 days work with excellent opportunities to the right candidate.\n\nInterested parties please send your resume with expected salary & availability.", "employment_types": ["Full Time"], "selling_points": [], "locations": ["Central"], "categories": ["Accounting", "Accountant", "Accounting Clerk / Supervisor", "Treasurer"], "post_time": "2021-12-31T08:32:19Z", "salary": {"currency": null, "max": null, "min": null, "period": "monthly", "term": null}, "salary_visible": false, "title_keywords": ["accountant"], "responsibilities": ["ap", "reporting", "management", "ad hoc duties", "ar", "schedules", "analysis", "full set of accounts", "bank reconciliations", "audit", "coordinate", "month-end closing", "general accounting duties", "banking", "liaise with", "daily accounting", "internal control", "external auditors"], "requirements": {"degrees": ["diploma", "degree"], "majors": ["accountancy"], "languages": [], "language_level": [], "hard_skills": ["ms excel", "flex system", "ms office"], "soft_skills": ["self-motivated", "hardworking", "sense of responsibility"], "languages_combined": []}, "experience_required": {"duration": ["minimum 5 years"], "field": ["accounting", "medical"]}}, {"job_id": "100003009007284", "location_code": "hk", "company": "South-East Asia Investment & Agency Co Ltd", "job_title": "Accountant", "description": "Responsibilities\n\n\nHandle full set of accounts and month-end closing;\nPrepare daily accounting vouchers, data entries and filing;\nPrepare monthly consolidation financial and management reports;\nPrepare accounts of subsidiaries of the Group (including overseas subsidiaries);\nCoordinate with internal stakeholder to support the year-end audit framework;\nHandle board papers, results announcement, interim / annual report and external reporting;\nCarry out ad-hoc assignments as required.\n\nRequirement\n\nHigher Diploma or above in Accounting or Finance or related disciplines;\nMinimum 3-5 years of related working experience;\nProficient in MS word and excel;\nGood command in both spoken and written English and Chinese;\nHands-on experience in Flex Account is preferred;\nInitiative, independent and strong sense of responsibility;\nLess experience will be considered for a junior position;\nImmediate available is preferred.\n\nA competitive package will be offered to the right candidate. Interested parties please send detailed resume with expected salary and availability by clicking \"Apply Now\" to submit your application.\n\n*Only shortlisted candidates will be notified. All personal data collected will be used for recruitment purposes only and will be treated strictly confidential.", "employment_types": ["Full Time", "Permanent"], "selling_points": ["Handle full set of accounts & month-end closing", "Prepare accounts of subsidiaries of the Group", "Hands-on experience in Flex Account"], "locations": ["Wan Chai"], "categories": ["Accounting", "Accountant", "Taxation", "Treasurer"], "post_time": "2021-12-30T02:16:39Z", "salary": {"currency": null, "max": null, "min": null, "period": null, "term": null}, "salary_visible": false, "title_keywords": ["accountant"], "responsibilities": ["year-end", "reporting", "data", "ad-hoc assignments", "full set of accounts", "coordinate with", "audit", "management reports", "month-end closing", "daily accounting", "report"], "requirements": {"degrees": ["higher diploma or above"], "majors": ["related disciplines", "finance", "accounting"], "languages": ["english", "chinese"], "language_level": ["good command"], "hard_skills": ["excel", "flex", "ms word"], "soft_skills": ["hands-on", "independent", "initiative", "sense of responsibility"], "languages_combined": [{"language": "english", "language_level": ["good command"]}, {"language": "chinese", "language_level": ["good command"]}]}, "experience_required": {"duration": ["minimum 3-5 years"], "field": ["related"]}}, {"job_id": "100003009009979", "location_code": "hk", "company": "China Mobile Hong Kong \u4e2d\u570b\u79fb\u52d5\u9999\u6e2f", "job_title": "Assistant Accountant (Fixed Asset)", "description": "CHINA MOBILE HONG KONG COMPANY LIMITED\u00a0(\"CMHK\") is the wholly-owned subsidiary of China Mobile Limited (HKEx: 941) (NYSE: CHL), which ranks 65th on the Fortune Global 500.\n\nOur company strives to offer superior service experience and to become the preferable digital partner for customers. We are preserving an environment with trust, responsibility and caring. At CMHK, we commit to maximizing people\u2019s potential and paving the way toward success for every striver. We are now inviting high caliber professional to join us.\n\nDivision:\u00a0 Finance Division - Financial Accounting & Reporting Department\n\nIn this position, you will:\n\n\nAssist in month-end closing\nPrepare reports, reconciliations and schedules\nSupport daily operations on the fixed assets area\nCo-ordinate with business users on projects and accounting issues\nArrange and coordinate stocktaking and inspection of fixed assets\nOther ad hoc duties/projects assigned\nTo be successful in this position, you should meet the following requirements:\u00a0\n\nDegree in Accountancy or related disciplines\nOver 5 years relevant working experience, prior fixed asset management experience will be an advantage.\nProactive, independent, persistent and able to work under pressure to meet deadline\nGood knowledge in MS Excel/ Word, Macro / MS Access preferred\nExperience in using Oracle is an advantage\nGood command of both written and spoken English and Chinese (both Cantonese and Mandarin)\nImmediate Available is preferable\n\nWhen you work:\n\n\n5 days work\n8 hours/day\n\nWhat you enjoy:\n\nDouble pay\nDiscretionary Performance bonus\nLife insurance\nMedical insurance\nEducation subsidies\nBirthday gift\nMarriage leave\nBirthday leave\nStaff discount\n\nCMHK is committed to be an equal opportunity employer. We offer exceptional benefits package and the opportunity to work in a challenging environment. Personal data provided by applicants will be treated strictly in accordance with our personal data policy and for recruitment purposes only.\n\nPlease submit your application to us by clicking the APPLY NOW button and send your full resume with your availability, current and expected salary to us.", "employment_types": ["Full Time", "Permanent"], "selling_points": ["Double pay & Performance bonus", "Experience in using Oracle", "Good knowledge in MS Excel, Word and Access"], "locations": ["Kwai Hing"], "categories": ["Accounting", "Accountant", "Accounting Clerk / Supervisor", "Treasurer"], "post_time": "2021-12-31T02:43:18Z", "salary": {"currency": null, "max": null, "min": null, "period": null, "term": null}, "salary_visible": false, "title_keywords": ["assistant accountant"], "responsibilities": ["ad hoc duties", "reporting", "schedules", "co-ordinate with", "work under pressure", "inspection", "coordinate", "reconciliations", "daily operations", "month-end closing", "prepare reports", "insurance", "asset management"], "requirements": {"degrees": ["degree"], "majors": ["related disciplines", "accountancy"], "languages": ["cantonese", "english", "chinese", "mandarin"], "language_level": ["good command"], "hard_skills": ["macro", "word", "mobile", "ms excel", "oracle"], "soft_skills": ["independent", "persistent", "committed", "proactive", "superior", "work under pressure"], "languages_combined": [{"language": "cantonese", "language_level": ["good command"]}, {"language": "english", "language_level": ["good command"]}, {"language": "chinese", "language_level": ["good command"]}, {"language": "mandarin", "language_level": ["good command"]}]}, "experience_required": {"duration": ["5 years"], "field": ["digital", "relevant working experience", "asset management"]}}, {"job_id": "100003008996638", "location_code": "hk", "company": "ConnectedGroup Limited", "job_title": "Treasury Manager/ Senior Treasury Manager", "description": "Treasury Manager/ Senior Treasury Manager\n\nOur client is a leading pharmaceutical company. They are looking for a CPA Qualified Treasury Manager with at least 8 years of solid experience to lead a small team and report to the Treasurer.\n\nResponsibilities:\n\nPrepare cash flow forecast to ensure there are sufficient funds to meet short and long-term cash requirements\nPrepare regular reports based on financial data showing incoming and outgoing figures, as well as other relevant information\nLiaise with various parties to manage treasury/financing matters of the Group's projects.\nLiaise with banks and investment companies to fulfill treasury and accounting needs\nPerform other ad hoc assignments and projects\nLoan administration and monitoring.\n\nRequirements:\n\nDegree in Accounting/Finance or other related disciplines\nQualified member of HKICPA / ACCA or equivalent professional accounting bodies\n8+ years of accounting experience with treasury focused experience in sizable corporations\nProven hands-on experience in handling financing and treasury activities.\nTeam player, able to work independently with high attention to detail and meet tight deadlines.\nGood command of spoken & written English and Cantonese\n\nInterested parties, please send your CV to Ivy Yeung Ivy.Yeung@connectedgroup.com for more details. For other available opportunities, please visit www.connectedgroup.com.", "employment_types": ["Full Time", "Permanent"], "selling_points": ["Big 4 & Commercial Background preferred", "Minimum 8 yrs of exp. in Treasury function", "Manage and execute treasury transactions"], "locations": ["Not Specified"], "categories": ["Accounting", "Finance / Accounting Manager", "Treasurer"], "post_time": "2021-12-23T08:00:54Z", "salary": {"currency": null, "max": null, "min": null, "period": "monthly", "term": null}, "salary_visible": false, "title_keywords": ["manager"], "responsibilities": ["data", "monitoring", "cash flow", "reports", "ad hoc assignments", "forecast", "liaise with", "administration"], "requirements": {"degrees": ["degree"], "majors": ["related disciplines", "finance", "accounting"], "languages": ["cantonese", "english"], "language_level": ["good command"], "hard_skills": ["acca", "hkicpa"], "soft_skills": ["work independently", "meet tight deadlines", "focused", "hands-on", "attention to detail", "team player"], "languages_combined": [{"language": "cantonese", "language_level": ["good command"]}, {"language": "english", "language_level": ["good command"]}]}, "experience_required": {"duration": ["8+ years"], "field": ["accounting experience", "financing"]}}, {"job_id": "100003008996715", "location_code": "hk", "company": "China CITIC Bank International Limited", "job_title": "Senior Officer/ Assistant Manager, Treasury Accounting", "description": "Job Purpose\nProvide timely and reliable information to serve internal and external reporting requirements\nKey Responsibilities\nResponsible for reconciliation assignment and monthly adjustment entries on treasury products\nPrepare daily and monthly treasury MIS schedules.\nIdentify discrepancies of treasury product balances in system against GL and report to senior management for necessary actions.\nSupport new product developments on accounting and reporting related rules development\nTake significant role in participating project development, user acceptance tests, system enhancement and implementation\nPrepare audit schedules and financial disclosure notes for interim and annual reports.\nAssist in preparing and updating the accounting guidelines and procedures manual.\nRequirements\nDegree holder in Accounting or related disciplines\nIn-depth knowledge of accounting principles, accounting policies and procedures and government regulations\nMinimum 3 \u2013 5 years\u2019 experience in banking or financial industry with knowledge in treasury related area.\nGood computer skills; proficiency in MS Office and Access.\nGood analytical and communication skills.\nGood command of English, Chinese and Putonghua.\nFor more details about career opportunities with the Bank, please visit our website http://www.cncbinternational.com/careers/en/index.jsp.\u00a0 Please apply with full resume stating current and expected salaries.\nPersonal data collected will be used for recruitment related purposes only. Applicants not invited for interview within 6 weeks may consider their applications unsuccessful. However, applicants may be considered for other suitable positions within the Group for a period of not more than 2 years. Personal data will be destroyed at any time after 3 months.\nChina CITIC Bank International is committed to being an equal opportunities employer and intends to provide a work environment free of unlawful discrimination or harassment.\u00a0 All employment decisions will be made in a non-discriminatory manner.", "employment_types": ["Full Time", "Permanent"], "selling_points": ["Reconciliation assignment on treasury products", "Knowledge of treasury product", "Internal and external reporting preparation"], "locations": ["Quarry Bay"], "categories": ["Accounting", "Accountant", "Treasurer", "Others"], "post_time": "2021-12-23T08:36:16Z", "salary": {"currency": null, "max": null, "min": null, "period": "monthly", "term": null}, "salary_visible": false, "title_keywords": ["senior officer", "assistant manager,", "accounting"], "responsibilities": ["reporting", "schedules", "guidelines", "implementation", "audit", "reports", "procedures manual", "senior management", "report"], "requirements": {"degrees": ["degree holder"], "majors": ["related disciplines", "accounting"], "languages": ["putonghua", "english", "chinese"], "language_level": ["good command"], "hard_skills": ["computer skills", "ms office"], "soft_skills": ["communication skills", "committed"], "languages_combined": [{"language": "putonghua", "language_level": ["good command"]}, {"language": "english", "language_level": ["good command"]}, {"language": "chinese", "language_level": ["good command"]}]}, "experience_required": {"duration": ["5 years"], "field": ["related", "financial industry", "banking"]}}, {"job_id": "100003008998613", "location_code": "hk", "company": "China Mobile Hong Kong \u4e2d\u570b\u79fb\u52d5\u9999\u6e2f", "job_title": "Assistant Accounting Officer (Revenue & Treasury)", "description": "CHINA MOBILE HONG KONG COMPANY LIMITED\u00a0(\"CMHK\") is the wholly-owned subsidiary of China Mobile Limited (HKEx: 941) (NYSE: CHL), which ranks 65th on the Fortune Global 500.\n\nOur company strives to offer superior service experience and to become the preferable digital partner for customers. We are preserving an environment with trust, responsibility and caring. At CMHK, we commit to maximizing people\u2019s potential and paving the way toward success for every striver. We are now inviting high caliber professional to join us.\n\nDivision:\u00a0 Finance Division -\u00a0Revenue & Treasury\n\nIn this position, you will:\n\n\nPrepare accounting entries of revenue, month end closing and reporting\nPrepare balance sheet and P&L schedules and reconciliations as well as follow up on any unusual items\nAssist in improving accounting process and leveraging technology to create efficiencies\nPerform other duties and ad hoc projects as required\nTo be successful in this position, you should meet the following requirements:\u00a0\n\n\nDegree in Accountancy/ Finance or business\u00a0related disciplines\n1 year relevant working experience with good knowledge of international accounting standards and practices preferred. Fresh graduate will also be considered.\nExperience in telecom industry and revenue accounting will be advantage\nProactive, independent, persistent and able to work under pressure to meet deadline\nGood knowledge in MS Excel/ Word, Macro / MS Access preferred\nAble to work on multiple priorities with accuracy and efficiency while keeping to deadlines\nGood command of both written and spoken English and Chinese (both Cantonese and Mandarin)\nImmediate Available is preferable\n\nWhen you work:\n\n\n5 days work\n8 hours/day\n\nWhat you enjoy:\n\nDouble pay\nDiscretionary Performance bonus\nLife insurance\nMedical insurance\nEducation subsidies\nBirthday gift\nMarriage leave\nBirthday leave\nStaff discount\n\nCMHK is committed to be an equal opportunity employer. We offer exceptional benefits package and the opportunity to work in a challenging environment. Personal data provided by applicants will be treated strictly in accordance with our personal data policy and for recruitment purposes only.\n\nPlease submit your application to us by clicking the APPLY NOW button and send your full resume with your availability, current and expected salary to us.", "employment_types": ["Full Time", "Permanent"], "selling_points": ["Double pay & Performance bonus", "Knowledge of international accounting standards", "Fresh graduate will also be considered"], "locations": ["Kwai Hing"], "categories": ["Accounting", "Accountant", "Accounting Clerk / Supervisor", "Treasurer"], "post_time": "2021-12-24T03:53:25Z", "salary": {"currency": null, "max": null, "min": null, "period": null, "term": null}, "salary_visible": false, "title_keywords": ["assistant accounting officer"], "responsibilities": ["reporting", "month end closing", "perform other duties", "schedules", "work under pressure", "p&l", "reconciliations", "ad hoc projects", "insurance", "balance sheet"], "requirements": {"degrees": ["degree", "fresh graduate"], "majors": ["related disciplines", "finance", "business", "accountancy"], "languages": ["cantonese", "english", "chinese", "mandarin"], "language_level": ["good command"], "hard_skills": ["mobile", "ms excel", "word", "macro"], "soft_skills": ["independent", "persistent", "committed", "proactive", "superior", "work under pressure"], "languages_combined": [{"language": "cantonese", "language_level": ["good command"]}, {"language": "english", "language_level": ["good command"]}, {"language": "chinese", "language_level": ["good command"]}, {"language": "mandarin", "language_level": ["good command"]}]}, "experience_required": {"duration": ["1 year"], "field": ["digital", "accounting", "relevant working experience"]}}, {"job_id": "100003008998076", "location_code": "hk", "company": "Sun Hung Kai Properties Ltd", "job_title": "ASSISTANT TREASURY MANAGER", "description": "Requirements:\n\n\nBachelor\u2019s degree in banking, finance, accounting or related disciplines preferred\nMinimum 10 years\u2019 relevant experience in treasury or settlement in banking and/or sizable organizations.\nSensitive to numbers and with good interpersonal skills\nProven English proficiency, fluency in Putonghua preferred\nFamiliar with PC software e.g. MS Word, Excel, PowerPoint\n\nResponsibilities:\n\n\nTake charge of money market and assist in other treasury functions\nEnsure timely settlement of capital market transactions and liaison with treasury team for PRC operations\nCo-ordinate cashflow monitoring & follow-up on execution of syndicated loans, bilateral loans, bonds\nPrepare reports for management review\n\nGood remuneration and attractive fringe benefits will be offered to the successful applicant. Interested parties please apply with full resume, present and expected salary, available date by clicking \"Apply Now\".\n\nWe are an equal opportunity employer and welcome applications from all qualified candidates. All personal data collected will be used for recruitment purpose only.\u00a0 Applicants not hearing from us within 3 months may consider their applications unsuccessful.\u00a0 All personal data collected will be destroyed within 24 months.", "employment_types": ["Full Time", "Permanent"], "selling_points": ["10 yrs' exp in treasury or settlement in banking", "Take charge of money market", "Co-ordinate cashflow monitoring"], "locations": ["Wan Chai"], "categories": ["Accounting", "Treasurer", "Banking / Finance", "Corporate Finance", "Treasury"], "post_time": "2021-12-24T02:31:51Z", "salary": {"currency": null, "max": null, "min": null, "period": null, "term": null}, "salary_visible": false, "title_keywords": ["manager", "assistant"], "responsibilities": ["operations", "monitoring", "transactions", "management review", "prepare reports", "timely settlement"], "requirements": {"degrees": ["degree", "bachelor"], "majors": ["related disciplines", "finance", "accounting"], "languages": ["putonghua", "english"], "language_level": ["fluency", "proficiency"], "hard_skills": ["powerpoint", "pc", "excel", "ms word"], "soft_skills": ["sensitive to numbers", "interpersonal skills"], "languages_combined": [{"language": "putonghua", "language_level": ["fluency"]}, {"language": "english", "language_level": ["proficiency"]}]}, "experience_required": {"duration": ["minimum 10 years"], "field": ["relevant experience", "banking"]}}, {"job_id": "100003008993570", "location_code": "hk", "company": "Sino Group", "job_title": "ASSISTANT MANAGER (GROUP TREASURY)(Ref: AM-GT/JDB)", "description": "The successful candidate will be responsible for managing the daily operation, ensuring the completion of the month-end closing timely, preparing cashflow reports, budgeting, financial reports, and performing other duties and ad hoc projects as required. He/she will assist Section Head to supervise subordinates, identify process improvement and provide advice and solutions to enhance efficiency on the operation, treasury, taxation, and reporting processes.\n\nRequirements:\n\nBachelor\u2019s degree holder or equivalent\nQualified member of ACCA, HKICPA, or equivalent\nMinimum 5 years' relevant experience with 3 years' auditing experience in a sizeable accounting firm\nFamiliar with accounting standards and statutory requirements\nStrong sense of responsibility, self-motivation, and independence\nDetail-oriented and be able to work under pressure\nProficient in spoken and written English and Chinese\nCandidate with less experience will be considered as a Senior Accountant\nWe offer attractive remuneration packages commensurate with experience and qualifications. If you aspire to an exciting and rewarding career, send your resume immediately, quoting your present and expected salaries by clicking the button \u201cApply Now\u201d.\nIf the applicant does not receive a response by 21\u00a0January 2022, the application will be considered unsuccessful. Before submitting your application, please read the Personal Data (Privacy) Policy and Personal Information Collection Statement at our Company website. Information provided by applicants will be treated in strict confidence and used for recruitment purposes only.", "employment_types": ["Full Time"], "selling_points": [], "locations": ["Not Specified"], "categories": ["Accounting", "Treasurer", "Banking / Finance", "Credit Analysis / Approval", "Loan"], "post_time": "2021-12-22T08:25:17Z", "salary": {"currency": null, "max": null, "min": null, "period": null, "term": null}, "salary_visible": false, "title_keywords": ["assistant manager"], "responsibilities": ["taxation", "financial reports", "reporting", "other duties", "budgeting", "daily operation", "statutory requirements", "month-end closing", "reports", "ad hoc projects", "provide advice", "auditing", "work under pressure"], "requirements": {"degrees": ["bachelor", "degree holder"], "majors": [], "languages": ["english", "chinese"], "language_level": ["proficient"], "hard_skills": ["acca", "hkicpa"], "soft_skills": ["responsible", "sense of responsibility", "timely", "detail-oriented", "self-motivation", "work under pressure"], "languages_combined": [{"language": "english", "language_level": ["proficient"]}, {"language": "chinese", "language_level": ["proficient"]}]}, "experience_required": {"duration": ["3 years", "minimum 5 years"], "field": ["accounting", "relevant experience", "senior accountant"]}}, {"job_id": "100003008994367", "location_code": "hk", "company": "S.F. Express (Hong Kong) Limited", "job_title": "Assistant Treasury Manager (SF REIT Asset Management Limited)", "description": "Responsibilities\n\n\nMaintain working relationship with banks\nCommunicate with banks to explore on suitable ways to obtain financing\nAnalyze products recommended by banks\nPerform fund sufficiency and loan repayment ability assessments\nHandle cash flow forecast and accuracy review\nProcess various agreements with banks and be familiar with such contents\nHandle compliance monitoring by banks\nAssist with regulatory requirement update\nAssist in other tasks as assigned\n\nRequirements\n\n\n\nDegree holder in Finance/Accounting or related disciplines\nAround 5 years\u2019 relevant experience, preferably from the banking/treasury sector\nProactive, detail-minded, well-organized and result-oriented with excellent interpersonal skills, analytical mind and sense of responsibility\nFluent in English, Mandarin and Cantonese\n\n\n\nWe offer attractive remuneration and fringe benefits to the right candidates. Please apply in WORD format (quoting Ref. No.) together with a detailed resume, stating current and expected salary to us.\n\nYou are welcome to visit our website at\u00a0www.sf-express.com/hk/tc\u00a0for more information about us.\n\nApplicants who are not invited for interview within 3 months may consider their applications unsuccessful.\n\n(All personal data provided by job applicants are used only for recruitment purpose and will be treated strictly confidential. Unsuccessful applications will be properly disposed within 3 months.)", "employment_types": ["Full Time"], "selling_points": ["Free shuttle bus coverage", "Attractive performance bonus", "Treasury Functions"], "locations": ["Tsing Yi"], "categories": ["Accounting", "Treasurer"], "post_time": "2021-12-23T01:04:25Z", "salary": {"currency": null, "max": null, "min": null, "period": "monthly", "term": null}, "salary_visible": false, "title_keywords": ["manager", "assistant", "asset management"], "responsibilities": ["communicate with", "review", "compliance", "monitoring", "cash flow", "maintain", "forecast", "contents"], "requirements": {"degrees": ["degree holder"], "majors": ["related disciplines", "finance", "accounting"], "languages": ["cantonese", "english", "mandarin"], "language_level": ["fluent"], "hard_skills": [], "soft_skills": ["detail-minded", "sense of responsibility", "well-organized", "analytical mind", "interpersonal skills", "proactive", "result-oriented"], "languages_combined": [{"language": "cantonese", "language_level": ["fluent"]}, {"language": "english", "language_level": ["fluent"]}, {"language": "mandarin", "language_level": ["fluent"]}]}, "experience_required": {"duration": ["5 years"], "field": ["relevant experience", "banking"]}}, {"job_id": "100003008997003", "location_code": "hk", "company": "Search Unlimited Company Limited", "job_title": "Vice President - Group Treasury", "description": "Vice President - Group Treasury\n\nOur client is a leading public-listed banking and financial services institution in Hong Kong with a strong reputation of serving the communities across the globe.\u00a0 The Group has provided a diverse range of financial and investment products and services, while focusing on innovation, leadership, performance and corporate governance.\n\n\nBased in Hong Kong, the incumbent will report directly to the Group Chief Financial Officer to carry out the following responsibilities:\n\nDevelop and review policies, guidelines and processes for the treasury function.\nManage short-and-long-term funding, including the bank financing.\nPerform financial risk management, including liquidity, FX, counterparty and interest, etc.\nAttend to cash forecasts and ensure that the high-quality liquidity forecasts are established.\nOversee cash management, including the existing cash pool.\nOversee investments and execute other financial activities.\nIn charge of trade finance and other treasury related activities.\nEstablish work relationships and cooperation with group finance, tax, legal and other departments.\nAssume ad hoc projects and all issues regarding treasury for the group.\n\nQualifications:\n\nBachelor of Business, Finance or Accounting with CPA/CFA qualifications.\nMinimum 15 years\u2019 relevant work experience from the banking and finance industry.\nExperience in mainboard public-listed corporate environment as a group treasurer.\nA proven ability in working with different departments to achieve the corporate goals.\nExperience in project management is an advantage.\nFluent in English and Chinese (Mandarin and Cantonese)\n\n\u00a0Personality traits:\n\nA self-starter with strong initiative.\nIndependent, responsive and hands-on.\nGood commercial and business acumen\nExcellent people and communication skills with ability to establish rapport with internal and external.\nAbility to work under pressure, deadlines and good at multi-tasking.", "employment_types": ["Full Time", "Permanent"], "selling_points": ["Public-listed banking & financial services", "Professional and passionate team environment", "Excellent career propsect"], "locations": ["Central & Western Area"], "categories": ["Accounting", "Treasurer"], "post_time": "2021-12-23T09:36:43Z", "salary": {"currency": null, "max": null, "min": null, "period": "monthly", "term": null}, "salary_visible": false, "title_keywords": ["vice president"], "responsibilities": ["tax", "management", "guidelines", "policies", "work under pressure", "review", "quality", "develop", "communication", "project management", "ad hoc projects", "banking", "report"], "requirements": {"degrees": ["bachelor"], "majors": ["finance", "business", "accounting"], "languages": ["cantonese", "english", "chinese", "mandarin"], "language_level": ["fluent"], "hard_skills": ["cfa", "investment products", "cpa", "project management", "acumen"], "soft_skills": ["communication skills", "independent", "work under pressure", "diverse", "project management", "hands-on", "multi-tasking", "business acumen", "leadership", "initiative", "responsive"], "languages_combined": [{"language": "cantonese", "language_level": []}, {"language": "english", "language_level": ["fluent"]}, {"language": "chinese", "language_level": ["fluent"]}, {"language": "mandarin", "language_level": []}]}, "experience_required": {"duration": ["minimum 15 years"], "field": ["project management", "finance industry", "banking"]}}]