[{"job_id": "100003009053102", "location_code": "hk", "company": "Lik Kai Engineering Company Limited", "job_title": "Senior Engineer / Engineer / Assistant Engineer (Electrical) (5-day work)", "description": "Job Responsibilities:\n\nAssist Project Manager in electrical project execution & tender estimation\nLiaise and communicate with client, architect, consultant, main contractor and others\nSupervise subcontractor performance\nPrepare tenders, job budget, drawing and equipment submission for new projects or A&A works\n\nJob Requirements:\n\nHolder of Degree / Higher Diploma in Building Services / Electrical Engineering or equivalent\nAt least 5 years' proven experience in project execution\nGood command of both written and spoken Chinese and English\n\nKnowledge in PowerPoint, MS Word, Excel, Chinese Word Processing and AutoCAD\n\nCandidates with less experience will be considered as Assistant Engineer.\n\nGood remuneration and attractive benefits will be offered to the right person. Interested parties please send full resume with expected salary via \"APPLY NOW\"\u00a0or by fax: 2611-4654 or by post to The Human Resources & Administration Department - Recruitment & Selection Section, Lik Kai Engineering Co., Ltd. 5th Floor, New East Sun Industrial Building, No. 18 Shing Yip Street, Kwun Tong, Kowloon.\n\nWe are an Equal Opportunity Employer. Personal data collected will be used for recruitment purpose only.", "employment_types": ["Full Time", "Permanent"], "selling_points": ["Holder of Degree / Higher Diploma", "5 years' proven experience in project execution", "Assist Project Manager in electrical project"], "locations": ["Not Specified"], "categories": ["Engineering", "Electrical / Electronics", "Engineering Project Management", "Mechanical"], "post_time": "2022-01-17T05:51:19Z", "salary": {"currency": null, "max": null, "min": null, "period": "monthly", "term": null}, "salary_visible": false, "title_keywords": ["senior engineer", "assistant engineer", "engineer"], "responsibilities": ["liaise", "communicate with client", "budget", "tender"], "requirements": {"degrees": ["diploma", "degree"], "majors": ["building services", "electrical engineering"], "languages": ["english", "chinese"], "language_level": ["good command"], "hard_skills": ["excel", "chinese word processing", "ms word", "powerpoint", "autocad"], "soft_skills": [], "languages_combined": [{"language": "english", "language_level": ["good command"]}, {"language": "chinese", "language_level": ["good command"]}]}, "experience_required": {"duration": ["at least 5 years"], "field": []}}, {"job_id": "100003009053240", "location_code": "hk", "company": "Schneider Electric (Hong Kong) Ltd", "job_title": "Technical Support Engineer", "description": "Job Description\n\nAP Infosense is seeking an experienced Electronic Engineer for development of prototype. The person hired for the position will have the opportunity to work with world-class design experts for advancement. He/she will perform duties including development of hardware and software for sensor evaluation/demo and conduct experimental data analysis, testing and documentation.\n\nThe candidate will have opportunity to work closely with system design team on Firmware / Software development of appliance products.\n- Manage projects on developing new sensor products\n- Prepare sensor specification & documentation\n- Perform sensor evaluation, characterization and qualification\n- Application support to customers\n\nSkills & Requirements\n\nProficiency in circuit design tools such as EDA, Arduino, etc.\nFamiliar with PADS Schematic Capture, PCB layout and AutoCAD skills\nExperience in C or C++MCU programming and MCU system application\nExperience in machine learning and AI algorithms, especially in 3D image recognition and/or related areas is preferred.\nBe proactive and have strong analytic and problem solving skill", "employment_types": ["Full Time"], "selling_points": ["Knowledge in ACB/ MCCB/ PLC/ BMS", "Customer-oriented", "Electrical Engineering / Electronic"], "locations": ["Quarry Bay"], "categories": ["Engineering", "Electrical / Electronics"], "post_time": "2022-01-17T06:30:51Z", "salary": {"currency": null, "max": null, "min": null, "period": "monthly", "term": null}, "salary_visible": false, "title_keywords": ["technical support engineer"], "responsibilities": ["ap", "software", "developing", "design", "testing", "data analysis", "hardware", "system design", "manage projects", "evaluation", "documentation"], "requirements": {"degrees": [], "majors": [], "languages": [], "language_level": [], "hard_skills": ["ai", "problem solving", "c", "programming", "autocad"], "soft_skills": ["problem solving skill", "learning", "proactive"], "languages_combined": []}, "experience_required": {"duration": [], "field": ["related", "programming"]}}, {"job_id": "100003009052686", "location_code": "hk", "company": "Super Electrical Contracting Limited", "job_title": "Electrical Engineer", "description": "Job description:\n\nAnalyzing, documenting and communicating to internal/external to meet customer technical expectations and ensure customer satisfaction\nManaging customer relationships to ensure early and open communication that meets customer expectations\nDeveloping and maintaining strong working relationships with Internal Groups such as Sales, Engineering, Service, Marketing, and other relevant company resources\nHotline support for technical enquiry\nHandle goods returns process\nUsing knowledge-bases to share information about known issues\n\nQualifications:\n\nHigher Diploma or above in Electrical Engineering / Electronic\u00a0or related discipline\n1 year of working experience is preferred. Fresh graduate will also be considered\nGood command in English, Cantonese & Mandarin\nDetail-minded and a good team player\nCustomer-oriented & self-motivated\nProduct knowledge of ACB, MCCB, PLC or BMS.\nGood communication and presentation skills\nGood PC skills including Word, Excel, Power Point\n\nWe offer attractive remuneration package to the successful candidates. Interested parties please 'Apply Now' with your full resume, contact number\u00a0and\u00a0expected salary.\n\n(Personal data collected will be used for recruitment purpose only)\u00a0\n\nApplications will be kept confidential and used for recruitment purpose only. The Company will retain the applications for a maximum period of six months and may refer suitable applicants to other vacancies within the Group.", "employment_types": ["Full Time"], "selling_points": [], "locations": ["Not Specified"], "categories": ["Engineering", "Electrical / Electronics", "Engineering Project Management"], "post_time": "2022-01-17T03:42:04Z", "salary": {"currency": null, "max": null, "min": null, "period": "monthly", "term": null}, "salary_visible": false, "title_keywords": ["electrical engineer"], "responsibilities": ["maintaining", "developing", "communication", "working relationships", "share information"], "requirements": {"degrees": ["higher diploma or above", "fresh graduate"], "majors": ["electrical engineering"], "languages": ["cantonese", "english", "mandarin"], "language_level": ["good command"], "hard_skills": ["excel", "plc", "word", "bms", "power point", "pc skills"], "soft_skills": ["detail-minded", "good team player", "self-motivated", "communication", "customer-oriented", "presentation skills"], "languages_combined": [{"language": "cantonese", "language_level": ["good command"]}, {"language": "english", "language_level": ["good command"]}, {"language": "mandarin", "language_level": ["good command"]}]}, "experience_required": {"duration": ["1 year"], "field": []}}, {"job_id": "100003009055036", "location_code": "hk", "company": "TUV Rheinland Hong Kong Limited", "job_title": "Assistant Engineer, Electrical - Safety Laboratory (Fresh graduates are welcome)", "description": "Job Duties:\n\nResponsible for project planning, design work, site supervision, commissioning,\n\noperation and project documentation preparation\n\nRequirements:\n\nHolding Diploma/IVE Graduate in Electrical Engineering\n\nWith 3-4 years experience of Electrical Installation in Building Services\n\nFamiliar with Auto CAD is preferred\u00a0\u00a0\n\nAble to work independently and handle with projects\n\nMonthly salary HK$ 25K \u2013 30K (Salary is negotiable depending on previous job experiences) Alternative Saturday off\n\nWe offer compensation for overtime work and performance based bonus.\n\nInterested candidates should send detailed resume with current and expected salary, available date to the HR Department, Block E, 3/F., Gemstar Tower, 23 Man Lok Street, Hung Hom, Kowloon.\u00a0\n\nOnly short-listed candidates will be notified. Personal data provided by applicants will be used for recruitment purposes only.", "employment_types": ["Full Time", "Permanent"], "selling_points": ["Electrical - Safety Laboratory", "Fresh graduates are welcome", "On-the-job training"], "locations": ["Tsuen Wan Area"], "categories": ["Engineering", "Electrical / Electronics", "Sciences, Lab, R&D", "Laboratory"], "post_time": "2022-01-18T00:34:54Z", "salary": {"currency": null, "max": null, "min": null, "period": null, "term": null}, "salary_visible": false, "title_keywords": ["assistant engineer"], "responsibilities": ["design work", "project planning", "commissioning", "site supervision", "project documentation"], "requirements": {"degrees": ["diploma"], "majors": ["electrical engineering"], "languages": [], "language_level": [], "hard_skills": ["auto cad"], "soft_skills": ["work independently"], "languages_combined": []}, "experience_required": {"duration": ["3-4 years"], "field": ["installation", "building services"]}}, {"job_id": "100003009054696", "location_code": "hk", "company": "Teammate Technology Engineering Limited", "job_title": "Assistant Engineer / Engineer Trainee", "description": "Duties:\n\nProvide technical support and on-site services to our clients\nPerform the equipment & software installation and maintenance.\nPreparing the documents and report.\nOpen field work and Shift Duty may be required.\nAble to work with main contractor.\n\n\n\nRequirements:\n\nCertificate or above in Electrical Engineering / Building Services Engineering or equivalent.\nMinimum 1 years' experience in field service and technical support\nGood team player, Self initiative, independent and able to work under pressure\nGood command of spoken and written English, Mandarin and Cantonese\nGood knowledge on computer & software applications\n\n\n\nInterested parties, please send full resume & expected remuneration \u00a0by clicking \u2018Apply Now\u2019 for interview. For more company details of Mun Hean, please visit our website: www.munhean.com\n\nPersonal data will be used for recruitment purpose only.", "employment_types": ["Full Time", "Permanent"], "selling_points": ["Co-ordinate and liaise with client, subcontractors", "Assist the project manager plan, execute projects", "Immediate available is highly preferred"], "locations": ["Lai Chi Kok"], "categories": ["Building & Construction", "Building / Construction / QS", "Engineering", "Electrical / Electronics", "Engineering Project Management"], "post_time": "2022-01-17T10:36:52Z", "salary": {"currency": null, "max": null, "min": null, "period": "monthly", "term": null}, "salary_visible": false, "title_keywords": ["assistant engineer", "engineer", "trainee"], "responsibilities": ["installation", "software", "maintenance", "technical support", "report"], "requirements": {"degrees": ["certificate"], "majors": ["building services", "electrical engineering", "engineering"], "languages": ["cantonese", "english", "mandarin"], "language_level": ["good command"], "hard_skills": [], "soft_skills": ["good team player", "independent", "initiative", "work under pressure"], "languages_combined": [{"language": "cantonese", "language_level": ["good command"]}, {"language": "english", "language_level": ["good command"]}, {"language": "mandarin", "language_level": ["good command"]}]}, "experience_required": {"duration": ["minimum 1 years"], "field": []}}, {"job_id": "100003009054985", "location_code": "hk", "company": "Pyrofoe Engineers Ltd", "job_title": "Assistant  Engineer", "description": "Job Responsibilities:\n\nPerform testing and related activities at the safety laboratory\nPerform maintenance and calibration of equipment in the laboratory\nConduct evaluation of laboratory measurement uncertainty according to the ISO guide to the expression of uncertainty\nPerform ad-hoc assignments as required\n\nJob Requirements:\n\nHigher Diploma\u00a0or above in Electrical and Electronic Engineering or related disciplines\nMinimum 1 year experience in safety laboratory\nSelf-motivated and independent\nAbility to work on tight deadlines\nGood command of spoken and written English and Chinese\n\nOther Benefits:\n\nPublic Holidays\nDouble Pay and Performance Bonus\nMedical, Dental and Life Insurance\nAnnual Leave, Maternity Leave, Paternity Leave, Marriage Leave, Compassionate Leave\nOn-the-job training as well as Training Sponsorship/ Subsidies\n\nApplications:\n\nInterested parties please send your full resume with expected salary and date available to the Human Resources Department by clicking \"Apply Now\".\n\nAll information received will be kept in strict confidence and used for employment purpose only. Applicants who are not invited for interview within\u00a05 weeks may assume their applications unsuccessful and their data will be retained for 6 months for other suitable vacancies in our organization and thereafter destroyed.", "employment_types": ["Full Time", "Permanent"], "selling_points": [], "locations": ["Not Specified"], "categories": ["Building & Construction", "Building / Construction / QS", "Engineering", "Electrical / Electronics", "Others"], "post_time": "2022-01-17T16:22:46Z", "salary": {"currency": null, "max": null, "min": null, "period": "monthly", "term": null}, "salary_visible": false, "title_keywords": ["engineer", "assistant"], "responsibilities": ["maintenance", "ad-hoc assignments", "measurement", "testing", "evaluation"], "requirements": {"degrees": ["higher diploma or above"], "majors": ["related disciplines", "engineering"], "languages": ["english", "chinese"], "language_level": ["good command"], "hard_skills": [], "soft_skills": ["self-motivated", "independent"], "languages_combined": [{"language": "english", "language_level": ["good command"]}, {"language": "chinese", "language_level": ["good command"]}]}, "experience_required": {"duration": ["minimum 1 year"], "field": ["laboratory"]}}, {"job_id": "100003009054986", "location_code": "hk", "company": "Pyrofoe Engineers Ltd", "job_title": "Engineer", "description": "Responsibilities\n\nProper training and guidance will be given to undertake the following responsibilities:\nCo-ordinate and liaise with client, subcontractors and authorities in the smooth and timely running of the project.\nAssist the project manager/project engineer to plan, execute and monitor the progress in meeting the target dates.\nAssist the project manager/project engineer to prepare and submit the project document e.g. Material Submission, Method Statement.\nAssist the project manager/project engineer in material procurement.\nCo-ordinate with subcontractors in construction site.\n\nRequirements\n\nDiploma or above in Electrical / Electronic / Computer Engineering / Information Engineering or related subject.\n1-2 years\u2019 experience in design, specification and implementation of ELV systems.\nFresh graduates are also welcomed.\nKnowledge on Auto CAD an advantage.\nSelf-motivated, responsible, good communication and interpersonal skills.\nGood command of both written and spoken English and Chinese.\nImmediate available and with construction work experience is highly preferred.\nCandidates with more experience will be considered as Assistant Engineer.\u00a0\n\nWe offer an attractive remuneration package, training and good career opportunities to the right candidate.\u00a0 Interested parties are invited to send your application enclosing full resume stating career and salary history (either in Word format or PDF format) to the HR Department by\u00a0Whatsapp to 9306-7864, or by\u00a0fax to 2370-2073 or click Apply Now.\n\nApplicants not invited for an interview within two months may consider their applications unsuccessful.\u00a0 All personal data collected will be used for recruitment purpose only.\n\n", "employment_types": ["Full Time", "Permanent"], "selling_points": [], "locations": ["Not Specified"], "categories": ["Building & Construction", "Building / Construction / QS", "Engineering", "Electrical / Electronics", "Others"], "post_time": "2022-01-17T16:22:46Z", "salary": {"currency": null, "max": null, "min": null, "period": "monthly", "term": null}, "salary_visible": false, "title_keywords": ["engineer"], "responsibilities": ["guidance", "co-ordinate with", "monitor", "liaise with client", "plan"], "requirements": {"degrees": ["diploma or above"], "majors": ["computer engineering", "engineering"], "languages": ["english", "chinese"], "language_level": ["good command"], "hard_skills": ["auto cad"], "soft_skills": ["self-motivated", "communication and interpersonal skills", "responsible"], "languages_combined": [{"language": "english", "language_level": ["good command"]}, {"language": "chinese", "language_level": ["good command"]}]}, "experience_required": {"duration": ["1-2 years"], "field": ["construction", "design"]}}, {"job_id": "100003009052228", "location_code": "hk", "company": "Nan Fung Group", "job_title": "SENIOR TECHNICAL OFFICER / TECHNICAL OFFICER", "description": "1-2 years experience min. in Fire Services Installation\nCan work independently\nGood at ACAD\nApplicant is required to send CV and expected salary to Pyrofoe Engineers Ltd (\u885b\u5b89\u5de5\u7a0b\u6709\u9650\u516c\u53f8) by fax 2385 2150 or email via \"Apply Now\" for interview arrangement.", "employment_types": ["Full Time", "Permanent"], "selling_points": ["Higher Diploma in Building Services Engineering", "5 years' experience in property maintenance", "Certificate of Registration of Electrical Worker"], "locations": ["Not Specified"], "categories": ["Engineering", "Electrical / Electronics", "Engineering Project Management", "Others"], "post_time": "2022-01-17T02:31:07Z", "salary": {"currency": null, "max": null, "min": null, "period": null, "term": null}, "salary_visible": false, "title_keywords": ["technical officer", "senior technical officer"], "responsibilities": ["installation", "interview arrangement"], "requirements": {"degrees": [], "majors": [], "languages": [], "language_level": [], "hard_skills": [], "soft_skills": ["work independently"], "languages_combined": []}, "experience_required": {"duration": ["1-2 years"], "field": []}}, {"job_id": "100003009053816", "location_code": "hk", "company": "Datatech enterprise limited", "job_title": "Building Services (Air conditioning and Electrical) Assistant Engineer /Project Engineer", "description": "Responsibilities:\n\n\nHandling data center infrastructure design & technical support for projects, in-house design co-ordination and administration;\nPreparation of tender documentation, system specification and drawings;\nParticipate in electrical system design & process;\nProvide on-site technical support and verification, T&C etc.;\nPrepare feasibility report, design proposal, budgetary estimation, electrical design calculation, and tender bidding document for E&M projects.\nOther relevant assignments as specified by managers.\n\n\u00a0Requirements:\n\n\nDiploma / Higher\u00a0Diploma / Degree or above in Electrical Engineering or related disciplines;\n3-5 years' solid experience in\u00a0consulting firm / electrical contracting company;\nExperience in infrastructure design, such as, HV, LV, ELV, Genset system, UPS system, discrimination study etc.\nProficient in MS Office, Sketchup, AutoCAD or BIM, luminaire calculation software knowledge is preferable;\nHolder of relevant electrical license and with knowledge of using BIM & CFD will be an advantage;\nAble to work with tight schedules;\nSelf-motivated, self-disciplined, organized, detail-oriented and responsible;\nGood communication, interpersonal and problem-solving skills;\nAn attractive remuneration package and fringe benefits will be offered to the right candidate. Interested parties, please send your resume stating with current and expected salary to the Human Resources Department by clicking Apply Now.\n\n\nFor more information, please visit the corporate website at\u00a0www.newtechapac.com\n\nAll information collected will be kept strictly confidential and for recruitment purpose only.", "employment_types": ["Full Time", "Permanent"], "selling_points": [], "locations": ["Shatin Area"], "categories": ["Engineering", "Electrical / Electronics", "Engineering Project Management", "Building & Construction", "Others"], "post_time": "2022-01-17T07:34:18Z", "salary": {"currency": "HKD", "max": 34999, "min": 14000, "period": "monthly", "term": null}, "salary_visible": true, "title_keywords": ["assistant engineer", "project engineer"], "responsibilities": ["data", "technical support", "infrastructure", "design", "drawings", "system design", "tender", "documentation", "report", "administration"], "requirements": {"degrees": ["diploma", "degree or above"], "majors": ["related disciplines", "electrical engineering"], "languages": [], "language_level": [], "hard_skills": ["sketchup", "bim", "problem-solving skills", "ms office", "autocad"], "soft_skills": ["organized", "self-motivated", "responsible", "detail-oriented", "communication", "problem-solving skills", "interpersonal"], "languages_combined": []}, "experience_required": {"duration": ["3-5 years"], "field": ["infrastructure", "consulting", "design"]}}, {"job_id": "100003009052860", "location_code": "hk", "company": "The Hongkong Electric Co., Ltd.", "job_title": "Technician (CI) (Ref: CS-CI-T-JD)", "description": "2 years experience min. in Fire Services Installation\nCan work independently\nRequire full-time on site\nGood at ACAD\nApplicant is required to send CV and expected salary to Pyrofoe Engineers Ltd (\u885b\u5b89\u5de5\u7a0b\u6709\u9650\u516c\u53f8) by fax 2385 2150 or email via \"Apply Now\" for interview arrangement.", "employment_types": ["Full Time", "Permanent"], "selling_points": ["Deliver low voltage metering work", "Diploma/ Cert in Electrical Eng or related", "A minimum of 3 years\u2019 relevant work experience"], "locations": ["North Point"], "categories": ["Engineering", "Draftsman", "Electrical / Electronics", "Building & Construction", "Others"], "post_time": "2022-01-17T04:18:25Z", "salary": {"currency": null, "max": null, "min": null, "period": "monthly", "term": null}, "salary_visible": false, "title_keywords": ["technician"], "responsibilities": ["installation", "interview arrangement"], "requirements": {"degrees": [], "majors": [], "languages": [], "language_level": [], "hard_skills": [], "soft_skills": ["work independently"], "languages_combined": []}, "experience_required": {"duration": ["2 years"], "field": []}}, {"job_id": "100003009051698", "location_code": "hk", "company": "ASM Technology Hong Kong Limited", "job_title": "Digital Electronic Engineer / Senior Digital Electronic Engineer", "description": "Responsibilities:\n\nPrepare tender and quotation for building service engineering\nPrepare shop drawing & CSD / site coordination & supervision\nLiaison with clients, architects, contractors for system design and installation design\nAttend project meeting\nOther relevant duties as assigned by manager\nRequirements:\n\nDegree / Associate Degree / Higher Diploma in Engineering (Building Services/ Mechanical Engineering/Engineering Disciplines)\nMin 3 years of relevant working experience in building services engineering for Project Engineer\n0~2-year relevant working experience in\u00a0building services assistant engineering for Assistant Engineering\nProficiency in PC knowledge including AutoCAD, MS Office Applications\nGood command in spoken and written English and Cantonese\nInitiative, independent, responsible and a good team player", "employment_types": ["Full Time", "Permanent"], "selling_points": ["Degree or higher in Electronic / Computer Engineer", "Fresh graduate is welcome", "Develop and support digital hardware platform"], "locations": ["Tsing Yi"], "categories": ["Engineering", "Electrical / Electronics", "Others"], "post_time": "2022-01-16T21:50:53Z", "salary": {"currency": null, "max": null, "min": null, "period": "monthly", "term": null}, "salary_visible": false, "title_keywords": ["electronic engineer"], "responsibilities": ["installation", "quotation", "design", "system design", "site coordination", "tender"], "requirements": {"degrees": ["associate degree", "diploma", "degree"], "majors": ["building services", "engineering", "mechanical engineering"], "languages": ["cantonese", "english"], "language_level": ["good command"], "hard_skills": ["pc knowledge", "ms office", "autocad"], "soft_skills": ["good team player", "independent", "initiative", "responsible"], "languages_combined": [{"language": "cantonese", "language_level": ["good command"]}, {"language": "english", "language_level": ["good command"]}]}, "experience_required": {"duration": ["min 3 years"], "field": ["building services", "relevant working experience", "engineering"]}}, {"job_id": "100003009052355", "location_code": "hk", "company": "Sheenway (Hong Kong) Limited", "job_title": "Project Engineer (5-day week)", "description": "\u00a0Requirement:\n\nProficient in C and/or assembly language\nDegree holder in Computer Science, Computer Engineering, I.T., Electronics Engineering\nFamiliar with embedded Linux product development environment\nSolid experience in sensor, thermostat and/or HVAC hardware design\n\nKnowledge in MSTP, networking, SIP protocol stack is a plus but not required\n\nProduct scope (A)\n\n\nnetworked sensors, wireless and wired room climatic control\nAWS\nPLC\n\nProduct scope (B)\n\n\nVoIP\nembedded Linux\n\n\nJob description:\n\nProduct development from prototyping, customizing user features, to debugging, field tests and production optimization.", "employment_types": ["Full Time", "Permanent"], "selling_points": [], "locations": ["Tsim Sha Tsui"], "categories": ["Engineering", "Electrical / Electronics", "Engineering Project Management", "Manufacturing", "Product Development / Management"], "post_time": "2022-01-17T02:50:45Z", "salary": {"currency": null, "max": null, "min": null, "period": "monthly", "term": null}, "salary_visible": false, "title_keywords": ["project engineer"], "responsibilities": [], "requirements": {"degrees": ["degree holder"], "majors": ["computer engineering", "computer science"], "languages": [], "language_level": [], "hard_skills": ["linux", "plus", "assembly language", "hvac", "plc", "aws", "hardware", "c"], "soft_skills": [], "languages_combined": []}, "experience_required": {"duration": [], "field": ["design"]}}, {"job_id": "100003009050233", "location_code": "hk", "company": "CLP Power Hong Kong Limited", "job_title": "System Administrator (2-Year Contract) [Ref: CLPP-PSBG-TSD-MB-SA]", "description": "Job description\nDevelop and support digital hardware platform for semi-conductor packaging machine.\nDesign and develop digital electronic circuits including microcontrollers, FPGAs\nDesign and develop digital system interface for variety sub-systems i.e sensors, motion controllers, PC\u2026.\nJob requirements\nDegree or higher in Electronic / Computer Engineering or relevant disciplines\nKnowledge in digital or analog circuit design\nKnowledge in FPGA related programming languages (e.g. Verilog, VHDL, C Language)\nFresh graduate with good potential will also be considered\nCandidate with suitable working experience will be considered as senior position\n\nAttractive salary and fringe benefits package will be offered to the right candidates.\n\nInterested parties please submit your application with cover letter, resume, certificate and transcripts.\n\nData collected will be used for recruitment purpose only. Suitable candidates may be referred to other vacancies within our company.", "employment_types": ["Full Time", "Contract"], "selling_points": [], "locations": ["Not Specified"], "categories": ["Engineering", "Electrical / Electronics", "Information Technology (IT)", "Support"], "post_time": "2022-01-17T16:20:56Z", "salary": {"currency": null, "max": null, "min": null, "period": "monthly", "term": null}, "salary_visible": false, "title_keywords": ["system administrator"], "responsibilities": ["hardware", "systems", "design and develop", "develop"], "requirements": {"degrees": ["degree", "fresh graduate"], "majors": ["computer engineering"], "languages": [], "language_level": [], "hard_skills": ["c language", "vhdl", "programming", "verilog"], "soft_skills": [], "languages_combined": []}, "experience_required": {"duration": [], "field": []}}, {"job_id": "100003009055061", "location_code": "hk", "company": "Ensec Solutions Hong Kong Limited", "job_title": "Technical Engineer / Junior Technician", "description": "About The Role:\n\nAssist in Project, Implementation, Test and Commissioning\nAssist in daily operation and monitor system performance\u00a0\n\n\nAbout You:\n\nBachelor's degree or above in Electronics or Electrical Engineering\n3 years or above relevant experience\nProficient in AutoCAD and Microsoft Office\nObtain HKSAR driving license category 1 and 2 is an advantage\nGood communication skill, able to handle pressure\u00a0\n\nWhat you can get from us\n\nOn-the-job training, learning and development\u00a0provided\nExecutive workshops, interest class, corporate purchase discount offered by SHKP\nCompetitive salary and annual leaves\nFlexible working opportunities\n\nInterested parties, please send full resume with expected salary and available date to Human Resources and Administration Department by e-mail or by fax 2111 9459.\n\n(Data collected will be used for recruitment purpose only.)", "employment_types": ["Full Time", "Permanent"], "selling_points": ["Security system installation", "Fresh graduate will be considered", "Double pay, bonus, medical insurance etc."], "locations": ["Kwun Tong"], "categories": ["Engineering", "Electrical / Electronics", "Engineering Project Management", "Others", "Technician"], "post_time": "2022-01-18T01:06:12Z", "salary": {"currency": null, "max": null, "min": null, "period": "monthly", "term": null}, "salary_visible": false, "title_keywords": ["junior technician", "technical engineer"], "responsibilities": ["commissioning", "daily operation", "monitor", "implementation", "communication", "purchase"], "requirements": {"degrees": ["degree or above", "bachelor"], "majors": ["electrical engineering"], "languages": [], "language_level": [], "hard_skills": ["microsoft office", "workshops", "autocad"], "soft_skills": ["flexible", "communication skill", "learning"], "languages_combined": []}, "experience_required": {"duration": ["3 years"], "field": ["relevant experience"]}}, {"job_id": "100003009052588", "location_code": "hk", "company": "CLP Power Hong Kong Limited", "job_title": "Engineer IIs [Ref: CLPP-GBG-GED-PMB-EII]", "description": "Major Responsibilities\n\nDevelop driving and sensing systems of the new generation of robotic devices\nWrite specifications and/or instructions & test plans\nDesign & develop robot prototyping and testing\nSimulate testing environments of systems\nPerform supplier sourcing, engagement, and management\nManage critical components, platform selection, qualification and BOM establishment\n\nRequirements\n\nBachelor degree or above in Computer, Electronics Engineering or related discipline\nMinimum 1 year\u2019s experience in robotics industry\nStrong technical competency and knowledge in motor driving and control systems\nDemonstrate abilities in translating non-technical objectives into design requirements\nExperience in camera modelling, characterization and calibration\nExperience in FE analysis and design for production\nSelf-driven and passionate to learn new things and encounter challenges\nGood collaboration and effective problem-solving skills\nWilling to learn and able to work under pressure\nGood command of spoken English and Chinese (including Putonghua)\n\nInterested parties, please apply together with a detailed resume, stating current and expected salary, and send it via APPLY NOW.\u00a0 Attractive remuneration will be offered in commensurate with qualification and experience.\u00a0\n\nAll personal information received will be treated in strict confidence for employment purpose only.\u00a0 Your application can be considered as unsuccessful if you have not been reached within 3 months.\u00a0 On the other hand, it may be transferred to other companies of our group for job openings.\u00a0 Unsuccessful applications will be destroyed for a period not more than 12 months.\u00a0\n\nhttps://www.computime.com/\nhttps://salus-controls.com/", "employment_types": ["Full Time", "Permanent"], "selling_points": [], "locations": ["Tuen Mun Area"], "categories": ["Engineering", "Electrical / Electronics"], "post_time": "2022-01-17T16:20:49Z", "salary": {"currency": null, "max": null, "min": null, "period": "monthly", "term": null}, "salary_visible": false, "title_keywords": ["engineer"], "responsibilities": ["management", "systems", "design", "develop", "testing", "specifications", "plans"], "requirements": {"degrees": ["degree or above", "bachelor"], "majors": ["engineering"], "languages": ["putonghua", "english", "chinese"], "language_level": ["good command"], "hard_skills": ["problem-solving skills", "analysis"], "soft_skills": ["passionate", "willing to learn", "problem-solving skills", "driven", "work under pressure"], "languages_combined": [{"language": "putonghua", "language_level": ["good command"]}, {"language": "english", "language_level": ["good command"]}, {"language": "chinese", "language_level": ["good command"]}]}, "experience_required": {"duration": ["minimum 1 year"], "field": ["design"]}}, {"job_id": "100003009053918", "location_code": "hk", "company": "Obrien Tech Limited", "job_title": "\u96fb\u6a5f\u5de5\u7a0b\u5e2b", "description": "Applications are invited for the above vacancy in Metering Branch of Technical Services Department. Reporting to the engineer, the appointee will be required to:\n\n\nManage work schedules to ensure timeliness of meter data collection for all CLP customers\nPerform daily operations on various meter reading management systems, e.g., Customer Care & Marketing System (CCMS), Meter Data Management System (MDMS), Strategic Metering Platform (SMP), Meter Reading Handheld System (MRHS), etc.\nHandle and resolve exceptions triggered from metering systems\nMaintain metering operation performance to ensure compliance with established service standards\nAnalyze data and initiate projects to improve operation efficiency\nDesign and conduct user acceptance tests for system upgrade\nDevelop and produce procedures, guidelines and training materials to support operations\nPerform any other duties assigned by supervisor as and when required.\n\nRequirements:\n\nHigher Certificate / Higher Diploma in Electronic / Electrical Engineering / Computer Science or Professional Diploma in Power Engineering or equivalent plus minimum 2 years\u2019 relevant experience\nKnowledge in data analytic and cyber security management is preferable\nKnowledge and experience in metering operations and SAP is an advantage\nGood verbal and written communication skills\nBe mindful and has good safety awareness\nGood team player and be flexible to work on ad-hoc tasks\nCandidates who do not fully meet the requirements but have demonstrated positive attitude and good potential for further development will be considered for junior position.\n\nPlease apply by clicking the button \u201cApply Now\u201d below for application on or before 25 January 2022.\n\nApplicants not invited for interview within 6 weeks from the closing date may assume their applications unsuccessful.\n\nInformation provided will be for recruitment purpose within the CLP Group and only short-listed candidates will be contacted. We comply with all applicable laws and regulations of HKSAR in handling applications. For details of the Personal Information Collection Statement, please visit our website: http://clp.to/engPICS\n\nFor further information on our company, please visit our website: https://www.clpgroup.com/", "employment_types": ["Full Time"], "selling_points": [], "locations": ["Tsim Sha Tsui"], "categories": ["Engineering", "Electrical / Electronics", "Engineering Project Management", "Others"], "post_time": "2022-01-17T07:46:09Z", "salary": {"currency": null, "max": null, "min": null, "period": "monthly", "term": null}, "salary_visible": false, "title_keywords": [], "responsibilities": ["regulations", "any other duties", "data", "schedules", "operations", "cyber security", "website", "design", "communication", "service standards", "maintain", "develop", "analyze data", "reporting", "management", "procedures", "daily operations", "data collection", "guidelines", "ad-hoc tasks", "systems", "ensure compliance", "recruitment"], "requirements": {"degrees": ["diploma", "higher certificate"], "majors": ["engineering", "electrical engineering", "computer science"], "languages": [], "language_level": [], "hard_skills": ["plus", "data management", "sap", "cyber security"], "soft_skills": ["flexible", "communication skills", "good team player", "mindful", "positive attitude"], "languages_combined": []}, "experience_required": {"duration": ["minimum 2 years"], "field": ["relevant experience", "engineering"]}}, {"job_id": "100003009054356", "location_code": "hk", "company": "Nice Property Management Limited", "job_title": "Assistant Maintenance Officer (Building Services) / Technical Assistant", "description": "As a senior engineer, you will support the project manager in leading the engineering team for design development and co-ordination, carrying out planning and procurement activities and ensuring the works are executed on site to a high safety and quality standard.\nRequirements:\nHigher Diploma or Degree in Electrical Engineering;\nAt least 8 years' relevant experience in facilities planning, installation and maintenance, testing and commissioning preferably with E&M contractors;\nDetail-oriented with strong safety awareness and problem solving skills;\nIndependent and able to work under pressure and tight schedule;\nProficiency in both written and spoken English and Chinese.\nCandidate with less experience will consider as Project Electrical Engineer.\nYou may apply to https://career.gammonconstruction.com/home/index?jobid=7db4917f-14a1-4b2f-a658-f9ae5ca32a32&source=003, providing your full resume, current and expected salary.\nFor more information about Gammon Construction Limited, please visit our company's website at http://www.gammonconstruction.com.\nWe are an equal opportunity employer and welcome applications from all qualified candidates.\u00a0 Information provided will be treated in strict confidence and only be used for consideration of your application for the relevant post within the Company.\u00a0 Applicants who are not invited for an interview within 6 weeks may consider their application unsuccessful.", "employment_types": ["Full Time"], "selling_points": [], "locations": ["Hung Hom"], "categories": ["Engineering", "Electrical / Electronics", "Mechanical", "Property / Real Estate", "Others"], "post_time": "2022-01-17T09:15:43Z", "salary": {"currency": null, "max": null, "min": null, "period": "monthly", "term": null}, "salary_visible": false, "title_keywords": ["maintenance officer", "assistant", "technical assistant"], "responsibilities": ["installation", "commissioning", "maintenance", "work under pressure", "quality", "website", "design", "testing", "schedule", "planning"], "requirements": {"degrees": ["diploma", "degree"], "majors": ["electrical engineering"], "languages": ["english", "chinese"], "language_level": ["proficiency"], "hard_skills": ["problem solving skills", "maintenance"], "soft_skills": ["confidence", "independent", "detail-oriented", "problem solving skills", "work under pressure"], "languages_combined": [{"language": "english", "language_level": ["proficiency"]}, {"language": "chinese", "language_level": ["proficiency"]}]}, "experience_required": {"duration": ["at least 8 years"], "field": ["installation", "maintenance", "testing", "relevant experience", "planning"]}}, {"job_id": "100003009022960", "location_code": "hk", "company": "Murata Power Solutions (Hong Kong) Limited", "job_title": "Engineering Supervisor, Electronic", "description": "Job Duties\n\nSecurity system installation, programming, testing and commissioning\nConduct on-site system training to customer\nSystem trouble shooting and problem solving\nAssist in project management\nAssisting and providing technical support to Sales Department\nProvide service support on delivery and collection of equipment or parts to the customers whenever necessary\nTo attend emergency call out service as requested by customer\n\nRequirements\n\nDiploma / Certificate in Electronic / Electrical Engineering or Computer Engineering or other related Engineering\u00a0discipline\nHolder of Security Personnel Permit (Cat. D) is an advantage\nAt least 1-year relevant working experience, experience in security systems is an advantage, such as CCTV, Access Control, Burglar Alarm, EAS system, etc.\nAble to work independently and under pressure\nProject management experience is an advantage\nFresh graduate is welcomed.\u00a0 Candidate with less experience will be considered as Junior Technician.\n\n\nRemuneration\n\nAttractive remuneration package include 13 months salary will be offered to the right candidate. (6 working days per week)\u00a0\n\n\n\nApply Method\n\nInterested candidates please send your resume in Word format with your availability, current and expected salary\u00a0by clicking \"Apply Now\".\n\nPersonal data collected will be used for recruitment purpose only.", "employment_types": ["Full Time"], "selling_points": ["Electronic Engineering", "Power Supply AC/DC and DC/DC", "Electronical"], "locations": ["Shatin Area"], "categories": ["Engineering", "Electrical / Electronics"], "post_time": "2022-01-17T16:20:52Z", "salary": {"currency": null, "max": null, "min": null, "period": "monthly", "term": null}, "salary_visible": false, "title_keywords": ["supervisor"], "responsibilities": ["installation", "commissioning", "technical support", "testing", "project management"], "requirements": {"degrees": ["certificate", "diploma", "fresh graduate"], "majors": ["computer engineering", "electrical engineering", "engineering"], "languages": [], "language_level": [], "hard_skills": ["project management", "cctv", "security personnel permit"], "soft_skills": ["project management", "work independently", "under pressure"], "languages_combined": []}, "experience_required": {"duration": ["at least 1-year"], "field": ["project management", "security", "relevant working experience"]}}, {"job_id": "100003009055047", "location_code": "hk", "company": "IBS Technology Int'l HK Limited", "job_title": "Electronics Engineer (QC)", "description": "We are looking for a professional, energetic and innovative engineer to join Generation Engineering Department of Generation Business Group (GBG). Reporting to Project Management Branch, the appointee will be an active member of a multi-project management team which develops and executes various engineering projects and Project Management Governance System in GBG.\u00a0 Major duties include:\n\nAssist Project Managers in the development, planning and execution of various plant upgrade and refurbishment projects;\nReview design submissions, construction schedules, techniques to ensure the technical integrity of project and the contractor\u2019s conformity with contract terms and specifications;\nConduct frequent site inspections to monitor progress, safety and quality of works, and collaborate with contractors to identify and implement continuous improvement initiatives to achieve world class safety, health, environmental and quality standards;\nLead engineering and construction of small-scale projects, supervise contractors\u2019 activities, and collaborate with relevant project stakeholders to achieve safe and cost-effective project delivery;\nAssist in managing expenditures and compilation of budgets;\n\nRequirements\n\nA recognized university degree in Mechanical / Electrical Engineering discipline or equivalent, plus at least 3 years relevant working experience; or higher diploma/certificate in a relevant discipline plus no less than 5 years relevant working experience;\nKnowledge of work planning and programming including works sequencing, manpower and equipment resourcing and cost estimating;\nGood understanding of basic engineering principles behind the various processes of power generation are preferred;\u00a0\u00a0\nPrevious exposures in safety, health and environmental requirements pertaining to project works in the generation industry is advantageous;\nHands-on contractual & commercial knowledge associated with contract execution and contractor management;\nA pro-active, communicative, flexible and self-driven team player seeking to build a career in CLP;\nProficient in both written and spoken English and Chinese;\nComputer literacy in Word, Excel and PowerPoint.\n\nPlease apply by sending\u00a0a detailed C.V., including academic qualifications, career history, major achievements and personal attributes on or before 25\u00a0January 2022. To facilitate our easy tracking please use a unique file name for all attachments and your email subject box in this format: CLPP-GBG-GED-PMB-EIIs_Last Name_First Name_Other Names.\n\nApplicants not invited for interview within 6 weeks from the closing date may assume their applications unsuccessful.\n\nInformation provided will be for recruitment purpose within the CLP Group and only short-listed candidates will be contacted. We comply with all applicable laws and regulations of HKSAR in handling applications. For details of the Personal Information Collection Statement, please visit our website: https://clp.to/engPICS\n\nFor further information on our company, please visit our website:\nhttps://www.clpgroup.com/", "employment_types": ["Full Time"], "selling_points": ["5-day work, Quarterly Performance Bonus, Medical", "quality control", "electronics components"], "locations": ["Kwai Hing"], "categories": ["Engineering", "Electrical / Electronics"], "post_time": "2022-01-18T00:53:02Z", "salary": {"currency": null, "max": null, "min": null, "period": "monthly", "term": null}, "salary_visible": false, "title_keywords": ["electronics engineer"], "responsibilities": ["collaborate with", "budgets", "cost", "supervise contractors", "monitor progress", "schedules", "refurbishment projects", "quality", "review design submissions", "specifications", "site inspections", "planning"], "requirements": {"degrees": ["certificate", "university degree", "diploma"], "majors": ["electrical engineering"], "languages": ["english", "chinese"], "language_level": ["proficient"], "hard_skills": ["excel", "no", "plus", "basic", "word", "powerpoint", "c", "programming"], "soft_skills": ["flexible", "unique", "computer literacy", "hands-on", "pro-active", "team player", "driven", "detailed"], "languages_combined": [{"language": "english", "language_level": ["proficient"]}, {"language": "chinese", "language_level": ["proficient"]}]}, "experience_required": {"duration": ["5 years", "at least 3 years"], "field": ["relevant working experience", "engineering"]}}, {"job_id": "100003009052291", "location_code": "hk", "company": "Hong Kong Labware Company Limited", "job_title": "Field Service Engineer", "description": "Your role\n\nLead a team to manage the operation in Data Center to meet the ISO Quality and Security Standard\nManage and communicate with customers to meet the requirements\nAssist manager to formulate daily operation manual, event handling procedures and business continuity plan\nPrepare operation and incident reports to maintain service level and prevention of future incident\nSupport emergency duties and 7 x 24 shift duties in Data Center is required\n\nTo succeed in the role\n\nDegree holder in Information Technology / Computer Science / Communication Engineering with 3 years\u2019 working experience or Higher Diploma with 5 years\u2019 experience in Data Center\u00a0\nObtain CDCP certificate\nHolder of ITIL, AOS or VCP certificate is an advantage\nStrong leadership and interpersonal skills\nGood customer handling\u00a0skill\nProficient in spoken and written English and Chinese\n\nIf you have the desire for an exciting and rewarding career, please send us your resume, quoting the reference number, your present and expected salary by Whatsapp, email or post to the Human Resources Department.\n\n\u00a0Whatsapp:\u00a05410 6137\n\nPost: HR-ENGINEERING, 13/F, Lai Chi Kok Engineering Center, 4 Yuet Lun Street, Lai Chi Kok, Kowloon.on other job opportunities of PCCW, please visit our website at http://www.pccw.com/Careers/Job+Opportunities+%26+Application/Current+Opportunities?language=en_US", "employment_types": ["Full Time", "Permanent"], "selling_points": ["Perform installation of analytical instruments", "Provide on-site preventive maintenance", "Fresh graduates will also be considered"], "locations": ["Kwai Hing"], "categories": ["Engineering", "Electrical / Electronics", "Others"], "post_time": "2022-01-17T02:39:28Z", "salary": {"currency": null, "max": null, "min": null, "period": "monthly", "term": null}, "salary_visible": false, "title_keywords": ["service engineer"], "responsibilities": ["communicate with", "business continuity", "data", "hr", "daily operation", "quality", "procedures", "website", "communication", "lead a team", "maintain", "reports", "plan"], "requirements": {"degrees": ["certificate", "diploma", "degree holder"], "majors": ["engineering", "computer science", "information technology"], "languages": ["english", "chinese"], "language_level": ["proficient"], "hard_skills": ["itil", "whatsapp"], "soft_skills": ["communication", "leadership", "interpersonal skills"], "languages_combined": [{"language": "english", "language_level": ["proficient"]}, {"language": "chinese", "language_level": ["proficient"]}]}, "experience_required": {"duration": ["3 years", "5 years"], "field": ["engineering", "information technology"]}}, {"job_id": "100003009053108", "location_code": "hk", "company": "Lik Kai Engineering Company Limited", "job_title": "Maintenance Engineer - Electrical (5-day work)", "description": "\n\u8077\u8cac :\u4e00\u822c\u96fb\u6a5f\u5de5\u7a0b\u5e2b\u5de5\u4f5c, \u8ca0\u8cac\u65b0\u96fb\u529b\u8a2d\u5099\u4e4b\u8a2d\u8a08\u3001\u7b56\u5283\u3001\u7e6a\u5236\u5716\u5247\u3001\u76e3\u7ba1\u5de5\u4f5c\uff0c\u8207\u627f\u5efa\u5546\u53ca\u5ba2\u6236\u5354\u8abf\u53ca\u76e3\u7ba1\u9032\u5ea6\n\n\u8cc7\u6b77 :\u5c08\u4e0a\u6559\u80b2\uff1a\u6587\u6191/\u8b49\u66f8; \u4e00\u822c\u7cb5\u8a9e; \u4e00\u822c\u666e\u901a\u8a71; \u4e00\u822c\u82f1\u8a9e\u512a\u5148; \u61c2\u95b1\u8b80\u4e2d\u6587; \u61c2\u95b1\u8b80\u82f1\u6587\n\n\u5f85\u9047 :\u6bcf\u6708$13,000 - $15,000, \u6709\u9280\u884c\u5047\u671f \u53ca\u91ab\u7642\u4fdd\u96aa, \u661f\u671f\u4e00\u81f3\u4e94: \u4e0a\u53489\u6642\u81f3\u4e0b\u53486\u6642, \u6bcf\u9031\u5de5\u4f5c5\u5929, \u6bcf\u5929\u5de5\u4f5c 8 - 9 \u5c0f\u6642\n\n\u7533\u8acb\u9808\u77e5 :\u6c42\u8077\u8005\u53ef\u96fb\u90f5(Apply Now)\u5c65\u6b77\u8868\u7d66OBRIEN TECH LIMITED\u3002\u5982\u8981\u7d22\u53d6\u6536\u96c6\u500b\u4eba\u8cc7\u6599\u8072\u660e, \u8acb\u8207\u9673\u5148\u751f(Email)\u806f\u7d61\u3002\n\n", "employment_types": ["Full Time", "Permanent"], "selling_points": ["Holder of Degree / Higher Diploma", "5 years' relevant experience", "Assist in monitoring maintenance works"], "locations": ["Not Specified"], "categories": ["Engineering", "Electrical / Electronics", "Engineering Project Management", "Mechanical"], "post_time": "2022-01-17T05:52:57Z", "salary": {"currency": null, "max": null, "min": null, "period": "monthly", "term": null}, "salary_visible": false, "title_keywords": ["engineer"], "responsibilities": [], "requirements": {"degrees": [], "majors": [], "languages": [], "language_level": [], "hard_skills": [], "soft_skills": [], "languages_combined": []}, "experience_required": {"duration": [], "field": []}}, {"job_id": "100003009054234", "location_code": "hk", "company": "BAI Communications Limited", "job_title": "Radio Network Maintenance Engineer", "description": "Holder of Diploma or Higher Certificate in Electrical Engineering or Mechanical Engineering or Building Services Engineering from a Hong Kong polytechnic university / polytechnic, the Hong Kong Institute of Vocational Education (IVE) or a technical institute / technical college, or equivalent\n\n\nPlease send resume & expected salary to HR Dept., Nice Property Management Ltd., Room 2-4, 18/F, New Trend Centre, 704 Prince Edward Road East, Kowloon or fax to 21947804, or email\n\nPersonal data collected will be used for recruitment purpose only.", "employment_types": ["Full Time"], "selling_points": ["Radio Network Maintenance Engineer", "Cellar Network Maintenance", "Telecom Network Maintenance"], "locations": ["Kwun Tong Area"], "categories": ["Engineering", "Electrical / Electronics", "Telecommunication / Wireless / Radio", "Others"], "post_time": "2022-01-17T08:52:28Z", "salary": {"currency": null, "max": null, "min": null, "period": "monthly", "term": null}, "salary_visible": false, "title_keywords": ["engineer"], "responsibilities": ["hr", "recruitment", "management", "personal data"], "requirements": {"degrees": ["diploma", "higher certificate"], "majors": ["engineering", "building services", "electrical engineering", "mechanical engineering"], "languages": [], "language_level": [], "hard_skills": ["nice"], "soft_skills": [], "languages_combined": []}, "experience_required": {"duration": [], "field": []}}, {"job_id": "100003009054318", "location_code": "hk", "company": "Excelink Engineering Company Limited", "job_title": "Engineer \u2013 MVAC /  Electrical", "description": "Job Highlights\n-- 5-day normal office hours in office-warehouse environment\n-- inspection of electronics components\n-- Kwai Chung area (near Kwai Hing Station)\n\nResponsibilities:\n-- quality control inspection of electronics components.\n-- perform warehouse operations for incoming and outgoing shipments.\n-- data encoding in system database, data entry for QC records\n-- communicate with Sales and Buyers about quality issues\n\nRequirements:\n-- engineering graduate preferably major in electronics\n-- knowledgeable on electronics components such as semiconductor and passive components\n-- self-initiative and with good attention to details\n-- team player with good interpersonal & communication skills\n-- able to work under pressure and willing to work overtime\n\nApplicants must be a permanent HKID holder or dependent visa. Interested parties please send your full resume with availability status, present & expected salary\n", "employment_types": ["Full Time"], "selling_points": ["Hip Dip / Degree in Mechanical / Electrical / BS", "Double pay, Medical, 10 days AL", "Min. 3 yrs working exp. in E&M engineering field"], "locations": ["Shau Kei Wan"], "categories": ["Engineering", "Draftsman", "Electrical / Electronics", "Mechanical"], "post_time": "2022-01-17T09:08:49Z", "salary": {"currency": null, "max": null, "min": null, "period": "monthly", "term": null}, "salary_visible": false, "title_keywords": ["engineer"], "responsibilities": ["communicate with", "data", "data entry", "quality", "inspection", "database", "quality control", "warehouse operations"], "requirements": {"degrees": [], "majors": [], "languages": [], "language_level": [], "hard_skills": [], "soft_skills": ["communication skills", "work overtime", "self-initiative", "attention to details", "team player", "interpersonal", "work under pressure"], "languages_combined": []}, "experience_required": {"duration": [], "field": []}}, {"job_id": "100003009022947", "location_code": "hk", "company": "Murata Power Solutions (Hong Kong) Limited", "job_title": "Leading Engineer, Firmware", "description": "About The Role :\n\n\nAssist the supervisor to perform in-house or field testing\nPrepare testing records\nDeal with any other duties as may be assigned from time to time by the supervisor\nAbout You :\n\n\nForm 3 or above\nSolid computer knowledge\nProactive, innovative and willing to learn & work\nGood working attitude\nGreat interest in career development in E&M, Transportation and construction field\nSuccessful candidate will join the Apprenticeship Training Scheme\nWhat you can get from us\n\n\nOn-the-job training, learning and development\u00a0provided\nExecutive workshops, interest class, corporate purchase discount offered by SHKP\nCompetitive salary and annual leaves\nFlexible working opportunities\nInterested parties, please send full resume with expected salary and available date to Human Resources and Administration Department by e-mail or by fax 2111 9459.\n\n(Data collected will be used for recruitment purpose only)", "employment_types": ["Full Time"], "selling_points": ["Power Supply Firmware", "Software", "Development opportunities"], "locations": ["Shatin Area"], "categories": ["Engineering", "Electrical / Electronics", "Others"], "post_time": "2022-01-17T16:20:52Z", "salary": {"currency": null, "max": null, "min": null, "period": "monthly", "term": null}, "salary_visible": false, "title_keywords": ["engineer"], "responsibilities": ["any other duties", "purchase", "career development", "testing"], "requirements": {"degrees": [], "majors": [], "languages": [], "language_level": [], "hard_skills": ["workshops", "scheme"], "soft_skills": ["flexible", "good working attitude", "willing to learn", "innovative", "learning", "proactive"], "languages_combined": []}, "experience_required": {"duration": [], "field": []}}, {"job_id": "100003009051754", "location_code": "hk", "company": "POWERCO Electric (Far East) Company Limited", "job_title": "Assistant Engineer / Engineer", "description": "Your role\u00a0\n\nThe successful candidate will provide assistance in the planning and operation activities for HKT exchanges and data centers in either one of the two disciplines\n\nInfrastructure Planning and design - Data Center / Exchange Center\nLead a small team to design in accommodation planning, equipment layout, cable route and building facilities provision to support the telecom equipment infrastructure\nPerform the planning in Data Center, design equipment layout, implementation works and contractors\u2019 management\nKeep building facilities knowledge update to fulfill the telecom equipment growth\nDevelop the process automation to improve work efficiency\nDC Power Planning & Operations\nCollaborate with various parties on ISO quality audit and ensure works are meeting the standard requirement.\nSupervise the installation and upgrade works of DC power plant\nCarry out operation and maintenance work of DC power plant\nManage vendors to secure the supply of high quality and cost effective products\n\n\nTo succeed in the role\u00a0\n\u00a0\n\nDegree holder or Higher Diploma/Higher Certificate in Electrical, Information System, Computer Science, Communication Engineering or related disciplines with 3 years\u2019 relevant experiences in telecommunications or IT industry.\nWell organized, analytical, hardworking and good interpersonal skills\nHolder of registered electrical worker license A or above is preferable\nKnowledge in Data Center design, AutoCAD / BIM (Building Information Modeling) / software program and holding professional certificate of CDCP is an advantage\nProficient in spoken and written in both English and Chinese\nCandidate with less experience or lower qualifications will be considered as Senior Technical Officer\n\nIf you have the desire for an exciting and rewarding career, please send us your resume, quoting the reference number, your present and expected salary by Whatsapp, email or post to the Human Resources Department.\n\n\u00a0Whatsapp:\u00a05410 6137\n\nPost: HR-ENGINEERING, 13/F, Lai Chi Kok Engineering Center, 4 Yuet Lun Street, Lai Chi Kok, Kowloon.on other job opportunities of PCCW, please visit our website at http://www.pccw.com/Careers/Job+Opportunities+%26+Application/Current+Opportunities?language=en_US", "employment_types": ["Full Time", "Permanent"], "selling_points": ["Diploma / Degree in E&M Engineering", "1-2 years relevant working experience", "Knowledge in AutoCad and Microsoft Office"], "locations": ["Shatin Area"], "categories": ["Engineering", "Electrical / Electronics", "Mechanical", "Others"], "post_time": "2022-01-17T00:28:45Z", "salary": {"currency": null, "max": null, "min": null, "period": "monthly", "term": null}, "salary_visible": false, "title_keywords": ["assistant engineer", "engineer"], "responsibilities": ["collaborate with", "software", "data", "operations", "quality", "audit", "design", "website", "communication", "infrastructure", "implementation", "develop", "provide assistance", "installation", "management", "cost", "maintenance", "lead a small team", "hr", "planning"], "requirements": {"degrees": ["certificate", "diploma", "higher certificate", "degree holder"], "majors": ["engineering", "design", "related disciplines", "it", "computer science"], "languages": ["english", "chinese"], "language_level": ["proficient"], "hard_skills": ["small", "maintenance", "information system", "bim", "autocad", "whatsapp", "dc", "exchange"], "soft_skills": ["communication", "well organized", "hardworking", "interpersonal skills"], "languages_combined": [{"language": "english", "language_level": ["proficient"]}, {"language": "chinese", "language_level": ["proficient"]}]}, "experience_required": {"duration": ["3 years"], "field": ["related", "telecommunications", "it", "engineering"]}}, {"job_id": "100003009052181", "location_code": "hk", "company": "Jobslink Limited", "job_title": "Engineer (BSE/FS/ELL/ELV/ME)", "description": "Duties\n\nResponsible for test & commissioning and maintenance of telecommunications systems\n\nQualifications / Requirements\n\nHigher Diploma graduate with minimum 4 years solid experience in carrying out corrective and preventive maintenance of radio networks in railway environment.\u00a0 Candidates should be proficient in using radio test equipment and possess good communication skills, and also be prepared to work irregular hours, holder of driving license a definite advantage.\u00a0\n\nWe offer attractive salaries, fringe benefits and training with excellent opportunities for promotion and career development for the right candidates.\u00a0 Please immediately email to us your\u00a0full details including your academic qualification, working experiences, strengths in radio communication, and expected salary.", "employment_types": ["Permanent"], "selling_points": ["At least 1 years\u2019 working experience in BSE/FS/ELL", "BEng / H.Dip in BSE, EE, ME, FS, CIVIL, & ext.", "Overall project operations & co-ordination"], "locations": ["Not Specified"], "categories": ["Building & Construction", "Building / Construction / QS", "Engineering", "Electrical / Electronics", "Mechanical"], "post_time": "2022-01-17T02:21:48Z", "salary": {"currency": null, "max": null, "min": null, "period": "monthly", "term": null}, "salary_visible": false, "title_keywords": ["engineer"], "responsibilities": ["systems", "commissioning", "maintenance"], "requirements": {"degrees": ["diploma"], "majors": [], "languages": [], "language_level": [], "hard_skills": ["maintenance"], "soft_skills": ["communication skills"], "languages_combined": []}, "experience_required": {"duration": ["minimum 4 years"], "field": ["maintenance"]}}, {"job_id": "100003009054823", "location_code": "hk", "company": "HALO Energy Limited, HKSTP Acceleration Programme", "job_title": "System Testing Engineer (Compliance)", "description": "Senior Electronic Engineer\nRequirements:\u00a0\n- Degree or Diploma in Electronic Engineering or equivalent.\n- At least 5 years experiences in electronic manufacturing field is preferred.\n- Familiar with temperature control, proportional power control, motor control, MCU control circuit design is preferable.\n- Knowledgeable with EMC /CE /VDE /FCC/UL standards and familiar with approval process.\n- Good interpersonal skill and able to communicate with oversea customers\n- Good command of written and spoken English and Mandarin.\n- PRC station is required\n\n", "employment_types": ["Full Time"], "selling_points": ["At least 5 years relevant working experience", "System testing in an innovation way", "5 days per week working hours, performance bonus"], "locations": ["Shatin Area"], "categories": ["Engineering", "Electrical / Electronics", "Information Technology (IT)", "Testing / QA", "Others"], "post_time": "2022-01-17T11:27:30Z", "salary": {"currency": null, "max": null, "min": null, "period": "monthly", "term": null}, "salary_visible": false, "title_keywords": ["engineer"], "responsibilities": ["communicate with", "control", "design"], "requirements": {"degrees": ["diploma", "degree"], "majors": ["engineering"], "languages": ["english", "mandarin"], "language_level": ["good command"], "hard_skills": [], "soft_skills": ["interpersonal skill"], "languages_combined": [{"language": "english", "language_level": ["good command"]}, {"language": "mandarin", "language_level": ["good command"]}]}, "experience_required": {"duration": ["at least 5 years"], "field": ["manufacturing"]}}, {"job_id": "100003009054098", "location_code": "hk", "company": "AP Infosense Limited", "job_title": "Electronic Engineer", "description": "Job Description\n\nAP Infosense is seeking an experienced Electronic Engineer for development of prototype. The person hired for the position will have the opportunity to work with world-class design experts for advancement. He/she will perform duties including development of hardware and software for sensor evaluation/demo and conduct experimental data analysis, testing and documentation.\n\nThe candidate will have opportunity to work closely with system design team on Firmware / Software development of appliance products.\n- Manage projects on developing new sensor products\n- Prepare sensor specification & documentation\n- Perform sensor evaluation, characterization and qualification\n- Application support to customers\n\nSkills & Requirements\n\nProficiency in circuit design tools such as EDA, Arduino, etc.\nFamiliar with PADS Schematic Capture, PCB layout and AutoCAD skills\nExperience in C or C++MCU programming and MCU system application\nExperience in machine learning and AI algorithms, especially in 3D image recognition and/or related areas is preferred.\nBe proactive and have strong analytic and problem solving skill", "employment_types": ["Full Time", "Contract"], "selling_points": ["Higher Diploma or above in Engineering", "5 days work with performance bonus", "Fluent in English and Mandarin will be a plus"], "locations": ["Shatin Area"], "categories": ["Engineering", "Electrical / Electronics"], "post_time": "2022-01-18T02:52:41Z", "salary": {"currency": null, "max": null, "min": null, "period": "monthly", "term": null}, "salary_visible": false, "title_keywords": ["electronic engineer"], "responsibilities": ["ap", "software", "developing", "design", "testing", "data analysis", "hardware", "system design", "manage projects", "evaluation", "documentation"], "requirements": {"degrees": [], "majors": [], "languages": [], "language_level": [], "hard_skills": ["ai", "problem solving", "c", "programming", "autocad"], "soft_skills": ["problem solving skill", "learning", "proactive"], "languages_combined": []}, "experience_required": {"duration": [], "field": ["related", "programming"]}}, {"job_id": "100003009055242", "location_code": "hk", "company": "Mun Hean Electrical Engineering (H.K.) Co Ltd", "job_title": "Engineer / Assistant Engineer (5 days work)", "description": "Duties:\n\nProvide technical support and on-site services to our clients\nPerform the equipment & software installation and maintenance.\nPreparing the documents and report.\nOpen field work and Shift Duty may be required.\nAble to work with main contractor.\n\n\n\nRequirements:\n\nCertificate or above in Electrical Engineering / Building Services Engineering or equivalent.\nMinimum 1 years' experience in field service and technical support\nGood team player, Self initiative, independent and able to work under pressure\nGood command of spoken and written English, Mandarin and Cantonese\nGood knowledge on computer & software applications\n\n\n\nInterested parties, please send full resume & expected remuneration \u00a0by clicking \u2018Apply Now\u2019 for interview. For more company details of Mun Hean, please visit our website: www.munhean.com\n\nPersonal data will be used for recruitment purpose only.", "employment_types": ["Full Time", "Permanent"], "selling_points": ["Preparing the documents and report.", "Minimum 1 years' experience", "Certificate or above in Electrical Engineering"], "locations": ["Quarry Bay"], "categories": ["Engineering", "Electrical / Electronics", "Others", "Others", "Technician"], "post_time": "2022-01-18T01:54:55Z", "salary": {"currency": null, "max": null, "min": null, "period": "monthly", "term": null}, "salary_visible": false, "title_keywords": ["assistant engineer", "engineer"], "responsibilities": ["installation", "software", "maintenance", "technical support", "report"], "requirements": {"degrees": ["certificate"], "majors": ["building services", "electrical engineering", "engineering"], "languages": ["cantonese", "english", "mandarin"], "language_level": ["good command"], "hard_skills": [], "soft_skills": ["good team player", "independent", "initiative", "work under pressure"], "languages_combined": [{"language": "cantonese", "language_level": ["good command"]}, {"language": "english", "language_level": ["good command"]}, {"language": "mandarin", "language_level": ["good command"]}]}, "experience_required": {"duration": ["minimum 1 years"], "field": []}}, {"job_id": "100003009055081", "location_code": "hk", "company": "Newtech Management Services Ltd", "job_title": "Electrical Engineer (Electrical Design)", "description": "Responsibilities:\n\n\nHandling data center infrastructure design & technical support for projects, in-house design co-ordination and administration;\nPreparation of tender documentation, system specification and drawings;\nParticipate in electrical system design & process;\nProvide on-site technical support and verification, T&C etc.;\nPrepare feasibility report, design proposal, budgetary estimation, electrical design calculation, and tender bidding document for E&M projects.\nOther relevant assignments as specified by managers.\n\n\u00a0Requirements:\n\n\nDiploma / Higher\u00a0Diploma / Degree or above in Electrical Engineering or related disciplines;\n3-5 years' solid experience in\u00a0consulting firm / electrical contracting company;\nExperience in infrastructure design, such as, HV, LV, ELV, Genset system, UPS system, discrimination study etc.\nProficient in MS Office, Sketchup, AutoCAD or BIM, luminaire calculation software knowledge is preferable;\nHolder of relevant electrical license and with knowledge of using BIM & CFD will be an advantage;\nAble to work with tight schedules;\nSelf-motivated, self-disciplined, organized, detail-oriented and responsible;\nGood communication, interpersonal and problem-solving skills;\nAn attractive remuneration package and fringe benefits will be offered to the right candidate. Interested parties, please send your resume stating with current and expected salary to the Human Resources Department by clicking Apply Now.\n\n\nFor more information, please visit the corporate website at\u00a0www.newtechapac.com\n\nAll information collected will be kept strictly confidential and for recruitment purpose only.", "employment_types": ["Full Time"], "selling_points": [], "locations": ["Kowloon Bay"], "categories": ["Engineering", "Electrical / Electronics", "Engineering Project Management", "Others"], "post_time": "2022-01-18T01:11:43Z", "salary": {"currency": null, "max": null, "min": null, "period": "monthly", "term": null}, "salary_visible": false, "title_keywords": ["electrical engineer"], "responsibilities": ["data", "technical support", "infrastructure", "design", "drawings", "system design", "tender", "documentation", "report", "administration"], "requirements": {"degrees": ["diploma", "degree or above"], "majors": ["related disciplines", "electrical engineering"], "languages": [], "language_level": [], "hard_skills": ["sketchup", "bim", "problem-solving skills", "ms office", "autocad"], "soft_skills": ["organized", "self-motivated", "responsible", "detail-oriented", "communication", "problem-solving skills", "interpersonal"], "languages_combined": []}, "experience_required": {"duration": ["3-5 years"], "field": ["infrastructure", "consulting", "design"]}}, {"job_id": "100003009054822", "location_code": "hk", "company": "Avantec Manufacturing Ltd", "job_title": "Electronics Engineer(IoT)", "description": "\u00a0Requirement:\n\nProficient in C and/or assembly language\nDegree holder in Computer Science, Computer Engineering, I.T., Electronics Engineering\nFamiliar with embedded Linux product development environment\nSolid experience in sensor, thermostat and/or HVAC hardware design\n\nKnowledge in MSTP, networking, SIP protocol stack is a plus but not required\n\nProduct scope (A)\n\n\nnetworked sensors, wireless and wired room climatic control\nAWS\nPLC\n\nProduct scope (B)\n\n\nVoIP\nembedded Linux\n\n\nJob description:\n\nProduct development from prototyping, customizing user features, to debugging, field tests and production optimization.", "employment_types": ["Full Time"], "selling_points": [], "locations": ["Kwun Tong"], "categories": ["Engineering", "Electrical / Electronics", "Others"], "post_time": "2022-01-17T11:23:06Z", "salary": {"currency": null, "max": null, "min": null, "period": "monthly", "term": null}, "salary_visible": false, "title_keywords": [], "responsibilities": [], "requirements": {"degrees": ["degree holder"], "majors": ["computer engineering", "computer science"], "languages": [], "language_level": [], "hard_skills": ["linux", "plus", "assembly language", "hvac", "plc", "aws", "hardware", "c"], "soft_skills": [], "languages_combined": []}, "experience_required": {"duration": [], "field": ["design"]}}, {"job_id": "100003009055109", "location_code": "hk", "company": "Autotoll Limited", "job_title": "Engineer", "description": "About The Role:\n\nAssist in Project, Implementation, Test and Commissioning\nAssist in daily operation and monitor system performance\u00a0\n\n\nAbout You:\n\nBachelor's degree or above in Electronics or Electrical Engineering\n3 years or above relevant experience\nProficient in AutoCAD and Microsoft Office\nObtain HKSAR driving license category 1 and 2 is an advantage\nGood communication skill, able to handle pressure\u00a0\n\nWhat you can get from us\n\nOn-the-job training, learning and development\u00a0provided\nExecutive workshops, interest class, corporate purchase discount offered by SHKP\nCompetitive salary and annual leaves\nFlexible working opportunities\n\nInterested parties, please send full resume with expected salary and available date to Human Resources and Administration Department by e-mail or by fax 2111 9459.\n\n(Data collected will be used for recruitment purpose only.)", "employment_types": ["Full Time", "Permanent"], "selling_points": ["Daily operation and monitor system performance", "3 years or above relevant experience", "Proficient in AutoCAD and Microsoft Office"], "locations": ["Kowloon Bay"], "categories": ["Engineering", "Electrical / Electronics", "Mechanical", "Others"], "post_time": "2022-01-18T01:15:15Z", "salary": {"currency": null, "max": null, "min": null, "period": "monthly", "term": null}, "salary_visible": false, "title_keywords": ["engineer"], "responsibilities": ["commissioning", "daily operation", "monitor", "implementation", "communication", "purchase"], "requirements": {"degrees": ["degree or above", "bachelor"], "majors": ["electrical engineering"], "languages": [], "language_level": [], "hard_skills": ["microsoft office", "workshops", "autocad"], "soft_skills": ["flexible", "communication skill", "learning"], "languages_combined": []}, "experience_required": {"duration": ["3 years"], "field": ["relevant experience"]}}, {"job_id": "100003009055331", "location_code": "hk", "company": "Computime Ltd", "job_title": "Senior Engineer \u2013 Electronic (Robotics)", "description": "Major Responsibilities\n\nDevelop driving and sensing systems of the new generation of robotic devices\nWrite specifications and/or instructions & test plans\nDesign & develop robot prototyping and testing\nSimulate testing environments of systems\nPerform supplier sourcing, engagement, and management\nManage critical components, platform selection, qualification and BOM establishment\n\nRequirements\n\nBachelor degree or above in Computer, Electronics Engineering or related discipline\nMinimum 1 year\u2019s experience in robotics industry\nStrong technical competency and knowledge in motor driving and control systems\nDemonstrate abilities in translating non-technical objectives into design requirements\nExperience in camera modelling, characterization and calibration\nExperience in FE analysis and design for production\nSelf-driven and passionate to learn new things and encounter challenges\nGood collaboration and effective problem-solving skills\nWilling to learn and able to work under pressure\nGood command of spoken English and Chinese (including Putonghua)\n\nInterested parties, please apply together with a detailed resume, stating current and expected salary, and send it via APPLY NOW.\u00a0 Attractive remuneration will be offered in commensurate with qualification and experience.\u00a0\n\nAll personal information received will be treated in strict confidence for employment purpose only.\u00a0 Your application can be considered as unsuccessful if you have not been reached within 3 months.\u00a0 On the other hand, it may be transferred to other companies of our group for job openings.\u00a0 Unsuccessful applications will be destroyed for a period not more than 12 months.\u00a0\n\nhttps://www.computime.com/\nhttps://salus-controls.com/", "employment_types": ["Full Time", "Permanent"], "selling_points": ["5 days work, double pay, and free shuttle coach", "Design & develop robot prototyping and testing", "Experience in FE analysis"], "locations": ["Shatin Area"], "categories": ["Engineering", "Electrical / Electronics", "Information Technology (IT)", "Testing / QA", "Network & System"], "post_time": "2022-01-18T02:12:48Z", "salary": {"currency": null, "max": null, "min": null, "period": "monthly", "term": null}, "salary_visible": false, "title_keywords": ["senior engineer"], "responsibilities": ["management", "systems", "design", "develop", "testing", "specifications", "plans"], "requirements": {"degrees": ["degree or above", "bachelor"], "majors": ["engineering"], "languages": ["putonghua", "english", "chinese"], "language_level": ["good command"], "hard_skills": ["problem-solving skills", "analysis"], "soft_skills": ["passionate", "willing to learn", "problem-solving skills", "driven", "work under pressure"], "languages_combined": [{"language": "putonghua", "language_level": ["good command"]}, {"language": "english", "language_level": ["good command"]}, {"language": "chinese", "language_level": ["good command"]}]}, "experience_required": {"duration": ["minimum 1 year"], "field": ["design"]}}, {"job_id": "100003009055199", "location_code": "hk", "company": "Gammon Construction Ltd", "job_title": "Senior Electrical Engineer  HKG/90773/13910/210496", "description": "As a senior engineer, you will support the project manager in leading the engineering team for design development and co-ordination, carrying out planning and procurement activities and ensuring the works are executed on site to a high safety and quality standard.\nRequirements:\nHigher Diploma or Degree in Electrical Engineering;\nAt least 8 years' relevant experience in facilities planning, installation and maintenance, testing and commissioning preferably with E&M contractors;\nDetail-oriented with strong safety awareness and problem solving skills;\nIndependent and able to work under pressure and tight schedule;\nProficiency in both written and spoken English and Chinese.\nCandidate with less experience will consider as Project Electrical Engineer.\nYou may apply to https://career.gammonconstruction.com/home/index?jobid=7db4917f-14a1-4b2f-a658-f9ae5ca32a32&source=003, providing your full resume, current and expected salary.\nFor more information about Gammon Construction Limited, please visit our company's website at http://www.gammonconstruction.com.\nWe are an equal opportunity employer and welcome applications from all qualified candidates.\u00a0 Information provided will be treated in strict confidence and only be used for consideration of your application for the relevant post within the Company.\u00a0 Applicants who are not invited for an interview within 6 weeks may consider their application unsuccessful.", "employment_types": ["Full Time", "Permanent"], "selling_points": ["Electrical Engineering", "Experience in facilities planning, installation", "Strong safety awareness"], "locations": ["Not Specified"], "categories": ["Engineering", "Electrical / Electronics"], "post_time": "2022-01-18T01:44:49Z", "salary": {"currency": null, "max": null, "min": null, "period": null, "term": null}, "salary_visible": false, "title_keywords": ["electrical engineer"], "responsibilities": ["installation", "commissioning", "maintenance", "work under pressure", "quality", "website", "design", "testing", "schedule", "planning"], "requirements": {"degrees": ["diploma", "degree"], "majors": ["electrical engineering"], "languages": ["english", "chinese"], "language_level": ["proficiency"], "hard_skills": ["problem solving skills", "maintenance"], "soft_skills": ["confidence", "independent", "detail-oriented", "problem solving skills", "work under pressure"], "languages_combined": [{"language": "english", "language_level": ["proficiency"]}, {"language": "chinese", "language_level": ["proficiency"]}]}, "experience_required": {"duration": ["at least 8 years"], "field": ["installation", "maintenance", "testing", "relevant experience", "planning"]}}, {"job_id": "100003009055459", "location_code": "hk", "company": "HKT", "job_title": "Assistant Engineer, Networking Operations Center", "description": "Your role\n\nLead a team to manage the operation in Data Center to meet the ISO Quality and Security Standard\nManage and communicate with customers to meet the requirements\nAssist manager to formulate daily operation manual, event handling procedures and business continuity plan\nPrepare operation and incident reports to maintain service level and prevention of future incident\nSupport emergency duties and 7 x 24 shift duties in Data Center is required\n\nTo succeed in the role\n\nDegree holder in Information Technology / Computer Science / Communication Engineering with 3 years\u2019 working experience or Higher Diploma with 5 years\u2019 experience in Data Center\u00a0\nObtain CDCP certificate\nHolder of ITIL, AOS or VCP certificate is an advantage\nStrong leadership and interpersonal skills\nGood customer handling\u00a0skill\nProficient in spoken and written English and Chinese\n\nIf you have the desire for an exciting and rewarding career, please send us your resume, quoting the reference number, your present and expected salary by Whatsapp, email or post to the Human Resources Department.\n\n\u00a0Whatsapp:\u00a05410 6137\n\nPost: HR-ENGINEERING, 13/F, Lai Chi Kok Engineering Center, 4 Yuet Lun Street, Lai Chi Kok, Kowloon.on other job opportunities of PCCW, please visit our website at http://www.pccw.com/Careers/Job+Opportunities+%26+Application/Current+Opportunities?language=en_US", "employment_types": ["Full Time"], "selling_points": [], "locations": ["Lai Chi Kok"], "categories": ["Engineering", "Electrical / Electronics", "Telecommunication / Wireless / Radio"], "post_time": "2022-01-18T02:37:11Z", "salary": {"currency": null, "max": null, "min": null, "period": "monthly", "term": null}, "salary_visible": false, "title_keywords": ["operations", "assistant engineer"], "responsibilities": ["communicate with", "business continuity", "data", "hr", "daily operation", "quality", "procedures", "website", "communication", "lead a team", "maintain", "reports", "plan"], "requirements": {"degrees": ["certificate", "diploma", "degree holder"], "majors": ["engineering", "computer science", "information technology"], "languages": ["english", "chinese"], "language_level": ["proficient"], "hard_skills": ["itil", "whatsapp"], "soft_skills": ["communication", "leadership", "interpersonal skills"], "languages_combined": [{"language": "english", "language_level": ["proficient"]}, {"language": "chinese", "language_level": ["proficient"]}]}, "experience_required": {"duration": ["3 years", "5 years"], "field": ["engineering", "information technology"]}}, {"job_id": "100003009055120", "location_code": "hk", "company": "Autotoll Limited", "job_title": "Technician Apprentices", "description": "About The Role :\n\n\nAssist the supervisor to perform in-house or field testing\nPrepare testing records\nDeal with any other duties as may be assigned from time to time by the supervisor\nAbout You :\n\n\nForm 3 or above\nSolid computer knowledge\nProactive, innovative and willing to learn & work\nGood working attitude\nGreat interest in career development in E&M, Transportation and construction field\nSuccessful candidate will join the Apprenticeship Training Scheme\nWhat you can get from us\n\n\nOn-the-job training, learning and development\u00a0provided\nExecutive workshops, interest class, corporate purchase discount offered by SHKP\nCompetitive salary and annual leaves\nFlexible working opportunities\nInterested parties, please send full resume with expected salary and available date to Human Resources and Administration Department by e-mail or by fax 2111 9459.\n\n(Data collected will be used for recruitment purpose only)", "employment_types": ["Full Time", "Contract"], "selling_points": ["Assist to perform in-house or field testing", "Form 3 or above", "Join the Apprenticeship Training Scheme"], "locations": ["Not Specified"], "categories": ["Transportation & Logistics", "Others", "Engineering", "Electrical / Electronics", "Mechanical"], "post_time": "2022-01-18T01:15:53Z", "salary": {"currency": null, "max": null, "min": null, "period": "monthly", "term": null}, "salary_visible": false, "title_keywords": ["technician"], "responsibilities": ["any other duties", "purchase", "career development", "testing"], "requirements": {"degrees": [], "majors": [], "languages": [], "language_level": [], "hard_skills": ["workshops", "scheme"], "soft_skills": ["flexible", "good working attitude", "willing to learn", "innovative", "learning", "proactive"], "languages_combined": []}, "experience_required": {"duration": [], "field": []}}, {"job_id": "100003009055454", "location_code": "hk", "company": "HKT", "job_title": "Assistant Engineer, Exchange Infrastructure planning & design", "description": "Your role\u00a0\n\nThe successful candidate will provide assistance in the planning and operation activities for HKT exchanges and data centers in either one of the two disciplines\n\nInfrastructure Planning and design - Data Center / Exchange Center\nLead a small team to design in accommodation planning, equipment layout, cable route and building facilities provision to support the telecom equipment infrastructure\nPerform the planning in Data Center, design equipment layout, implementation works and contractors\u2019 management\nKeep building facilities knowledge update to fulfill the telecom equipment growth\nDevelop the process automation to improve work efficiency\nDC Power Planning & Operations\nCollaborate with various parties on ISO quality audit and ensure works are meeting the standard requirement.\nSupervise the installation and upgrade works of DC power plant\nCarry out operation and maintenance work of DC power plant\nManage vendors to secure the supply of high quality and cost effective products\n\n\nTo succeed in the role\u00a0\n\u00a0\n\nDegree holder or Higher Diploma/Higher Certificate in Electrical, Information System, Computer Science, Communication Engineering or related disciplines with 3 years\u2019 relevant experiences in telecommunications or IT industry.\nWell organized, analytical, hardworking and good interpersonal skills\nHolder of registered electrical worker license A or above is preferable\nKnowledge in Data Center design, AutoCAD / BIM (Building Information Modeling) / software program and holding professional certificate of CDCP is an advantage\nProficient in spoken and written in both English and Chinese\nCandidate with less experience or lower qualifications will be considered as Senior Technical Officer\n\nIf you have the desire for an exciting and rewarding career, please send us your resume, quoting the reference number, your present and expected salary by Whatsapp, email or post to the Human Resources Department.\n\n\u00a0Whatsapp:\u00a05410 6137\n\nPost: HR-ENGINEERING, 13/F, Lai Chi Kok Engineering Center, 4 Yuet Lun Street, Lai Chi Kok, Kowloon.on other job opportunities of PCCW, please visit our website at http://www.pccw.com/Careers/Job+Opportunities+%26+Application/Current+Opportunities?language=en_US", "employment_types": ["Full Time"], "selling_points": [], "locations": ["Lai Chi Kok"], "categories": ["Engineering", "Electrical / Electronics", "Telecommunication / Wireless / Radio"], "post_time": "2022-01-18T02:36:51Z", "salary": {"currency": null, "max": null, "min": null, "period": "monthly", "term": null}, "salary_visible": false, "title_keywords": ["assistant engineer"], "responsibilities": ["collaborate with", "software", "data", "operations", "quality", "audit", "design", "website", "communication", "infrastructure", "implementation", "develop", "provide assistance", "installation", "management", "cost", "maintenance", "lead a small team", "hr", "planning"], "requirements": {"degrees": ["certificate", "diploma", "higher certificate", "degree holder"], "majors": ["engineering", "design", "related disciplines", "it", "computer science"], "languages": ["english", "chinese"], "language_level": ["proficient"], "hard_skills": ["small", "maintenance", "information system", "bim", "autocad", "whatsapp", "dc", "exchange"], "soft_skills": ["communication", "well organized", "hardworking", "interpersonal skills"], "languages_combined": [{"language": "english", "language_level": ["proficient"]}, {"language": "chinese", "language_level": ["proficient"]}]}, "experience_required": {"duration": ["3 years"], "field": ["related", "telecommunications", "it", "engineering"]}}, {"job_id": "100003009051719", "location_code": "hk", "company": "Advance Thermo Control Ltd", "job_title": "Senior Electronic Engineer", "description": "Senior Electronic Engineer\nRequirements:\u00a0\n- Degree or Diploma in Electronic Engineering or equivalent.\n- At least 5 years experiences in electronic manufacturing field is preferred.\n- Familiar with temperature control, proportional power control, motor control, MCU control circuit design is preferable.\n- Knowledgeable with EMC /CE /VDE /FCC/UL standards and familiar with approval process.\n- Good interpersonal skill and able to communicate with oversea customers\n- Good command of written and spoken English and Mandarin.\n- PRC station is required\n\n", "employment_types": ["Full Time"], "selling_points": ["5 days work per week", "Medical insurance", "US management base"], "locations": ["Others - China"], "categories": ["Engineering", "Electrical / Electronics", "Manufacturing & Production"], "post_time": "2022-01-16T21:51:06Z", "salary": {"currency": null, "max": null, "min": null, "period": "monthly", "term": null}, "salary_visible": false, "title_keywords": ["senior electronic engineer"], "responsibilities": ["communicate with", "control", "design"], "requirements": {"degrees": ["diploma", "degree"], "majors": ["engineering"], "languages": ["english", "mandarin"], "language_level": ["good command"], "hard_skills": [], "soft_skills": ["interpersonal skill"], "languages_combined": [{"language": "english", "language_level": ["good command"]}, {"language": "mandarin", "language_level": ["good command"]}]}, "experience_required": {"duration": ["at least 5 years"], "field": ["manufacturing"]}}, {"job_id": "100003009051545", "location_code": "hk", "company": "VisionNav Robotics Limited", "job_title": "Project Application Engineer", "description": "Responsibility:\n1. AGF onsite deployment, debugging, troubleshooting and customer training in overseas project;\n2. AGF operational status tracking, recording and summarizing in overseas project onsite, and regularly reporting to project manager;\n3. Responsible for project documentations;\n4. After-sales repair and maintenance;\n5. Develop and follow up project schedule plan for overseas projects, communication and coordinate with customers for technical problems;\n6. Timely feedback customer requirement, constantly improve project management skills and improve customer service level;\n7. Complete other tasks assigned by the manager;\n\nRequirements:\n1. Associate degree or above, major in electrical engineering, automation, electronic engineering or related;\n2. Familiar with CAD, SolidWorks, Excel, Word, PPT and other office software;\n3. Good learning ability;\n4. Cantonese and Mandarin are main working languages, good communication skills is preferred\n5. Enthusiastic in work, strong adaptability and stress resistance, good teamwork spirit and customer service awareness, able to travel\n6. Having experience in electrical automation industry and FAE work experience is preferred;\n7. Having experience in AGV, AGF or forklift maintenance is preferred.", "employment_types": ["Full Time", "Contract"], "selling_points": [], "locations": ["Tai Po Area"], "categories": ["Engineering", "Electrical / Electronics"], "post_time": "2022-01-16T09:47:26Z", "salary": {"currency": "HKD", "max": 34999, "min": 17000, "period": "monthly", "term": null}, "salary_visible": true, "title_keywords": ["application engineer"], "responsibilities": ["reporting", "maintenance", "coordinate with", "troubleshooting", "develop", "communication", "project management", "repair", "customer service", "other tasks", "schedule", "plan", "tracking"], "requirements": {"degrees": ["degree or above"], "majors": ["engineering", "electrical engineering"], "languages": ["cantonese", "mandarin"], "language_level": ["good"], "hard_skills": ["excel", "maintenance", "cad", "word", "solidworks", "office software"], "soft_skills": ["communication skills", "learning ability", "customer service", "teamwork spirit", "adaptability", "enthusiastic"], "languages_combined": [{"language": "cantonese", "language_level": ["good"]}, {"language": "mandarin", "language_level": ["good"]}]}, "experience_required": {"duration": [], "field": ["maintenance"]}}, {"job_id": "100003009055645", "location_code": "hk", "company": "Links International", "job_title": "Building Services Engineer", "description": "Job Responsibilities:\n\nProvide support to the Project Manager in tender preparation, tender analysis, price negotiation and budget control\nCo-ordinate with clients, consultants, main-contractors and sub-contractors for project implementation\nHandle project administration\nResolve site matters and site coordination\nAd hoc duties as required\n\nJob Requirements:\n\nDegree Holder in Electrical / Mechanical / Building Services or equivalent\nAt lease 4 years' relevant experience in participation of E&M / Building Services Contracts, senior experience will be considering as Senior Engineer\nGood command of both written and spoken English and Chinese\nGood communication and interpersonal skills\nSelf motivated, Independent and able to work under pressure\nProficiency in AutoCAD and Microsoft Project", "employment_types": ["Full Time", "Permanent"], "selling_points": ["4+ years experience in E&M / building services", "Tender management experience", "Immediate available is preferred"], "locations": ["Not Specified"], "categories": ["Engineering", "Electrical / Electronics", "Engineering Project Management", "Others"], "post_time": "2022-01-18T02:49:42Z", "salary": {"currency": null, "max": null, "min": null, "period": "monthly", "term": null}, "salary_visible": false, "title_keywords": ["building services engineer"], "responsibilities": ["ad hoc duties", "provide support", "price negotiation", "handle project administration", "co-ordinate with clients", "implementation", "tender analysis", "site coordination", "tender preparation", "budget control"], "requirements": {"degrees": ["degree holder"], "majors": ["building services"], "languages": ["english", "chinese"], "language_level": ["good command"], "hard_skills": ["microsoft project", "autocad"], "soft_skills": ["self motivated", "communication and interpersonal skills", "independent", "work under pressure"], "languages_combined": [{"language": "english", "language_level": ["good command"]}, {"language": "chinese", "language_level": ["good command"]}]}, "experience_required": {"duration": ["4 years"], "field": ["building services", "relevant experience", "senior engineer"]}}, {"job_id": "100003009051701", "location_code": "hk", "company": "ASM Technology Hong Kong Limited", "job_title": "Process Engineer (Fresh Graduate / IANG Holder Is Welcome)", "description": "Job description\nDefine process flow, requirements and specifications and verify through Design of Experiment (DoE) to optimize current machinery performance\nDiscuss with customers about the conceptual process design of new product and the enhancement of existing products\u2019 process design\nSupport on-site process optimization and/or trouble-shooting through engineering evaluation to meet customer requirements\nDebug the machinery functions to ensure meeting customer requirements and conduct process analysis to study the parameter test results from DoE for process optimization\nSupport internal machinery optimization before buy-off\nTest the samples provided by customers for bonding\nJob requirements\nDegree or higher in Applied Physics / Applied Mathematics / Mechanical Engineering / Materials science / Chemical Engineering or relevant disciplines\nGood understanding of DoE, FMECA, statistics and instrumentation\nStrong in analytical methods\nDetail-oriented with a critical degree of accuracy regarding analysis\nWorking experience in micro-electronics is a plus\nOccasional business trip is required\n\nAttractive salary and fringe benefits package will be offered to the right candidates.\n\nInterested parties please submit your application with cover letter, resume, certificate and transcripts.\n\nData collected will be used for recruitment purpose only. Suitable candidates may be referred to other vacancies within our company.", "employment_types": ["Full Time", "Permanent"], "selling_points": ["Degree or higher in Applied Physics / Applied Math", "Good understanding of DoE, FMECA, statistics", "Strong in analytical methods"], "locations": ["Kwai Tsing Area"], "categories": ["Engineering", "Electrical / Electronics", "Mechanical", "Others"], "post_time": "2022-01-16T21:50:55Z", "salary": {"currency": null, "max": null, "min": null, "period": "monthly", "term": null}, "salary_visible": false, "title_keywords": ["process engineer"], "responsibilities": ["analysis", "specifications", "design", "evaluation"], "requirements": {"degrees": ["degree"], "majors": ["mechanical engineering", "physics", "applied mathematics", "chemical engineering", "materials science"], "languages": [], "language_level": [], "hard_skills": ["analysis", "plus"], "soft_skills": ["detail-oriented"], "languages_combined": []}, "experience_required": {"duration": [], "field": []}}, {"job_id": "100003009051704", "location_code": "hk", "company": "ASM Technology Hong Kong Limited", "job_title": "Senior System Engineer/ System Engineer (R&D)", "description": "Job description\nGather system requirements, prepare technical specification and provide system design and solution suggestion\u00a0\nWork closely with technical leaders to deliver electrical system solution of products\nParticipate in multiple projects simultaneously\nJob requirements\nDegree or higher in Computer / Electrical / Electronic / Mechanical / Industrial / System Engineering or relevant disciplines\nKeen interest and ability in system integration, workflow standardization and staying abreast of new technology\nBasic knowledge in assembly & packaging equipment for semiconductor is an advantage\nGood command of Mandarin and English preferred\nCandidate with minimum 3 years\u2019 working experience in system integration or industrial controls will be considered as senior position\n\nAttractive salary and fringe benefits package will be offered to the right candidates.\nInterested parties please submit your application with cover letter, resume, certificate and transcripts.\nData collected will be used for recruitment purpose only. Suitable candidates may be referred to other vacancies within our company.", "employment_types": ["Full Time", "Permanent"], "selling_points": ["Degree in Computer / Engineering or relevant", "Participate in multiple projects simultaneously", "Fresh graduate are welcome"], "locations": ["Tsing Yi"], "categories": ["Engineering", "Electrical / Electronics", "Manufacturing & Production", "Mechanical"], "post_time": "2022-01-16T21:50:56Z", "salary": {"currency": null, "max": null, "min": null, "period": "monthly", "term": null}, "salary_visible": false, "title_keywords": ["system engineer", "senior system engineer"], "responsibilities": ["multiple projects", "system design"], "requirements": {"degrees": ["degree"], "majors": ["system engineering"], "languages": ["english", "mandarin"], "language_level": ["good command"], "hard_skills": ["integration", "basic"], "soft_skills": ["keen"], "languages_combined": [{"language": "english", "language_level": ["good command"]}, {"language": "mandarin", "language_level": ["good command"]}]}, "experience_required": {"duration": ["minimum 3 years"], "field": []}}, {"job_id": "100003009054632", "location_code": "hk", "company": "RecruitPRO Consultancy Hong Kong Limited", "job_title": "Technician / \u51b7\u6c23\u7dad\u4fee\u6280\u5de5 - (HVAC/MVAC/Chiller/E&M/BMS/\u51b7\u6c23/\u96fb\u529b) - \u591a\u540d\u7a7a\u7f3a - \u53ef\u7c3dA\u724c", "description": "A leading contractor.\u00a0 They are now seeking for the candidates :\n\n\n\nFor Job Seekers directly apply use only:\u00a0\napplyppt @recruitpro662.com\n\nor please whatapps: 6718 7715\u00a0\n\n\n(Senior or Assistant) Technician / \u51b7\u6c23\u7dad\u4fee\u6280\u5de5 - (HVAC / MVAC / Chiller / E&M\u51b7\u6c23/\u96fb\u529b) - \u591a\u540d\u00a0\n\n\n\n*** \u4eba\u5de5\u8996\u4e4e\u5de5\u4f5c\u7d93\u9a57, \u5b78\u6b77\u53ca\u4e4b\u524d\u4eba\u5de5\u800c\u5b9a\u3002\n*** 5.5/6\u5929\u7dad\u4fee\u5de5\u4f5c, \u56e0\u60c5\u6cc1\u4e0d\u540c, \u53ef\u80fd\u9700\u8981\u65e9\u4e2d\u665a\u8f2a\u73ed \u53ca\u99d0\u5834\u5de5\u4f5c\u3002\n\n\u8ca0\u8cac\u7dad\u4fee, \u4fdd\u990a\u53ca\u6aa2\u67e5\u51b7\u6c23\u7cfb\u7d71/\u96fb\u529b\u7cfb\u7d71\u53ca\u8a2d\u5099\u3002(\u51b7\u6c23\u548c\u96fb\u529b\u662f\u4e0d\u540c\u7684\u7dad\u4fee\u7d44\u5225,\u6309\u4f60\u7d93\u9a57\u800c\u5206\u7d44\u3002)\n\u5de5\u4f5c\u5730\u9ede:\u9577\u99d0\u65bc\u5927\u578b\u5546\u5834, \u5927\u5b78, \u653f\u5e9c\u7269\u696d, \u5c4b\u82d1,\u570b\u969b\u5b78\u6821,\u5546\u696d\u5927\u5ec8,DATA CENTRE\u7b49\u7b49\n\u6709H/R/A \u724c\u66f4\u4f73, \u4f46\u4e0d\u662f\u5fc5\u9808\u7684\u3002\n\u6b61\u8fce\u65b0\u4eba\u5165\u884c, \u6709\u5728\u8077\u57f9\u8a13\u3002\u4f46\u6700\u597d\u6700\u5c11\u534a\u5e74 OR 1\u5e74\u4ee5\u4e0a\u76f8\u95dc\u7d93\u9a57\u3002\n\u9577\u5de5, \u6709\u512a\u539a\u798f\u5229\u53ca\u82b1\u7d051-2 \u500b\u6708\u3002\n\n\nhave more experience, will be consider as A/C operator OR\u00a0 BMS operator and work in Building control room\u00a0\n\n\n\u4eba\u5de5 : 16 - 26K - NEGO , plus OT pay\u00a0\n\u591a\u540d\u7a7a\u7f3a, \u8fd4\u5de5\u5730\u9ede\u5f48\u6027, \u6e2f\u4e5d\u65b0\u754c\u7686\u53ef\u3002\n\n\n\n\nFor Job Seekers, who prefer to directly sent your CV to us, our job seekers directly apply email address is posted in our company profile above.\n\nPlease kindly send your CV in WORD format ONLY\u00a0with:\n\nCURRENT and EXPECTED SALARY\nAVAILABILITY\nJOB TITLE in your EMAIL SUBJECT", "employment_types": ["Full Time", "Permanent"], "selling_points": [], "locations": ["Not Specified"], "categories": ["Building & Construction", "Building / Construction / QS", "Engineering", "Electrical / Electronics", "Mechanical"], "post_time": "2022-01-17T16:21:07Z", "salary": {"currency": null, "max": null, "min": null, "period": "monthly", "term": null}, "salary_visible": false, "title_keywords": ["technician"], "responsibilities": ["control room", "data"], "requirements": {"degrees": [], "majors": [], "languages": [], "language_level": [], "hard_skills": ["plus", "hvac", "word", "bms", "c", "r"], "soft_skills": [], "languages_combined": []}, "experience_required": {"duration": [], "field": []}}, {"job_id": "100003009054858", "location_code": "hk", "company": "Liu Chong Hing Property Management & Agency Ltd", "job_title": "Technical Supervisor (On-site Maintenance)", "description": "Job Responsibilities\n\nAssist the Maintenance Officer to oversee the on-site facilities management of a shopping mall.\nResponsible for supervision of technicians and contractors on on-site daily operation, facilities maintenance and repair works and building services systems.\nCentralize order requests and ensure fairness and appropriateness of job allocation for technicians.\nPrepare regular reports on daily repair and maintenance schedule, emergency call out activities and inventory level of equipment to the Maintenance Officer for a comprehensive control of on-site work and further analysis.\nHandle tenants\u2019 enquires, complains and requests in a professional manner.\nAttend 24-hour emergency calls on all facilities related issues.\nPrepare roster and carry out technician shift duty.\nParticipate in ad hoc projects and tasks as assigned by the superior.\nJob Requirements\n\nCertificate or above, in M&E, Building Services or related disciplines.\nMinimum 8 years\u2019 relevant experience with 3 years at supervisory level with sound knowledge of repair and maintenance of M&E services.\nHolder of Registered Electrical Worker Certificate Grade B or above and Safety Green Card.\nProficient in MS Office applications and Chinese Word Processing.\nGood interpersonal skills with strong sense of responsibility.\nImmediate available is preferred.\nCandidate with less experience at supervisory level may consider as Senior Technician.\nInterested parties\u00a0please apply with full resume, contact number, date available and expected salary by\u00a0clicking \"Apply Now\".\u00a0\n\nTo learn more about us, please visit our website\u00a0Liu Chong Hing Investment Ltd.\n\u00a0\nPersonal data provided by job applicants will be used for recruitment purpose only.", "employment_types": ["Full Time", "Permanent"], "selling_points": ["Maintenance and Repair of Shopping Mall", "On-site supervision of technicians", "Shift duty and emergency calls required"], "locations": ["Mong Kok"], "categories": ["Building & Construction", "Building / Construction / QS", "Engineering", "Electrical / Electronics", "Mechanical"], "post_time": "2022-01-17T11:55:42Z", "salary": {"currency": null, "max": null, "min": null, "period": "monthly", "term": null}, "salary_visible": false, "title_keywords": ["technical supervisor"], "responsibilities": ["management", "control", "maintenance", "inventory", "systems", "daily operation", "analysis", "professional manner", "repair", "reports", "schedule", "ad hoc projects"], "requirements": {"degrees": ["certificate"], "majors": ["related disciplines", "building services"], "languages": ["chinese"], "language_level": ["proficient"], "hard_skills": ["chinese word processing", "ms office", "maintenance", "green card"], "soft_skills": ["interpersonal skills", "sense of responsibility"], "languages_combined": [{"language": "chinese", "language_level": ["proficient"]}]}, "experience_required": {"duration": ["3 years", "minimum 8 years"], "field": ["supervisory level", "relevant experience", "maintenance"]}}, {"job_id": "100003009053676", "location_code": "hk", "company": "Able Engineering Company Limited", "job_title": "Resident Building Services Engineer", "description": "Corporate member of a professional institution recognized for corporate membership in the status of registered professional engineer (RPE) of the Hong Kong Institution of Engineers (HKIE) in the Building Services Engineering or Electrical Engineering or Mechanical Engineering Discipline, or equivalent;\nAt least 5 years relevant post qualification experience in building services engineering, electrical engineering or mechanical engineering;\nWork on construction site.\n\nWe offer competitive salary package and career development opportunity to the successful candidate. Interested parties may send your full resume, present and expected salary, available date and contact number by email by clicking \"Apply Now\".\n\n\nTo visit our website for more information: www.ableeng.com.hk\n\n(As an Equal Opportunities Employer, Able is committed to eliminating discrimination in employment. The vacancy advertised is open to all applicants meeting the basic entry requirement irrespective of their disability, sex, marital status, pregnancy, age, family status, sexual orientation or race etc. Applicants not hearing from us within 6 months may consider their applications unsuccessful. Personal data collected will be used for recruitment related purposes only.)", "employment_types": ["Full Time", "Permanent"], "selling_points": [], "locations": ["Not Specified"], "categories": ["Building & Construction", "Building / Construction / QS", "Engineering", "Electrical / Electronics", "Mechanical"], "post_time": "2022-01-17T07:20:04Z", "salary": {"currency": null, "max": null, "min": null, "period": "monthly", "term": null}, "salary_visible": false, "title_keywords": ["building services engineer"], "responsibilities": [], "requirements": {"degrees": [], "majors": [], "languages": [], "language_level": [], "hard_skills": ["the hong kong institution of engineers", "hkie"], "soft_skills": [], "languages_combined": []}, "experience_required": {"duration": ["at least 5 years"], "field": ["building services", "engineering"]}}, {"job_id": "100003009054206", "location_code": "hk", "company": "Auberge Hospitality Limited", "job_title": "And we are hiring \u2013 \u6280\u8853\u54e1, \u6109\u666f\u7063\u5eb7\u6a02\u6703", "description": "\u8077\u8cac\uff1a\n\n\u8ca0\u8cac\u6703\u6240\u6cb9\u6f06\u3001\u6728\u5de5\u3001\u6ce5\u6c34\u53ca\u4e00\u822c\u7dad\u4fee\u4fdd\u990a\u5de5\u4f5c\n\n\u8cc7\u6b77\uff1a\n\n\u6301\u6ce5\u6c34/\u6cb9\u6f06\u76f8\u95dc\u8b49\u66f8\u6216\u4e2d\u5de5\u724c\uff0c\u6301\u96fb\u5de5A\u724c\u8005\u512a\u5148\u8003\u616e\n\u5177\u4e09\u5e74\u4ee5\u4e0a\u76f8\u95dc\u5de5\u4f5c\u7d93\u9a57\uff0c\u6709\u6703\u6240\u6216\u9152\u5e97\u5de5\u4f5c\u7d93\u9a57\u8005\u512a\u5148\u8003\u616e\n\u80fd\u64cd\u6d41\u5229\u5ee3\u6771\u8a71\u53ca\u7c21\u55ae\u82f1\u8a9e\n\u9808\u8f2a\u73ed\u5de5\u4f5c (\u516c\u53f8\u63d0\u4f9b\u5bbf\u820d\u4e88\u6709\u9700\u8981\u4e4b\u54e1\u5de5)\n\u53ef\u5373\u6642\u4e0a\u73ed\u8005\u512a\u5148\u8003\u616e\n\nWe offer an attractive remuneration package and excellent career opportunities to the right candidate. Interested applicants please send your CV by email to Apply Now or by WhatsApp at 63173527.\n\nPersonal data provided by job applicants will be used strictly for recruitment purposes only.", "employment_types": ["Full Time", "Permanent"], "selling_points": ["\u8ca0\u8cac\u6703\u6240\u6cb9\u6f06\u3001\u6728\u5de5\u3001\u6ce5\u6c34\u53ca\u4e00\u822c\u7dad\u4fee\u4fdd\u990a\u5de5\u4f5c", "\u6301\u6ce5\u6c34/\u6cb9\u6f06\u76f8\u95dc\u8b49\u66f8\u6216\u4e2d\u5de5\u724c\uff0c\u6301\u96fb\u5de5A\u724c\u8005\u512a\u5148\u8003\u616e", "\u5177\u4e09\u5e74\u4ee5\u4e0a\u76f8\u95dc\u5de5\u4f5c\u7d93\u9a57\uff0c\u6709\u6703\u6240\u6216\u9152\u5e97\u5de5\u4f5c\u7d93\u9a57\u8005\u512a\u5148\u8003\u616e"], "locations": ["Lantau Island"], "categories": ["Engineering", "Electrical / Electronics", "Mechanical", "Others", "Technician"], "post_time": "2022-01-17T09:02:47Z", "salary": {"currency": null, "max": null, "min": null, "period": "monthly", "term": null}, "salary_visible": false, "title_keywords": ["\u6280\u8853\u54e1"], "responsibilities": [], "requirements": {"degrees": [], "majors": [], "languages": [], "language_level": [], "hard_skills": [], "soft_skills": [], "languages_combined": []}, "experience_required": {"duration": [], "field": []}}, {"job_id": "100003009051673", "location_code": "hk", "company": "Care For You Company Limited", "job_title": "Service Technician - Medical Equipment", "description": "Responsibilities:\u00a0\n\nProvide technical service support to hospitals, clinics and home patients, including equipment / system installation, repairing, regular preventive maintenance\nDiagnose problems and repair faulty devices\nOn-site trouble shooting, handle enquiries\nPromote products, services & sleep test for customers\n\n\u00a0Requirements:\u00a0\n\nDiploma in Electronics discipline or equivalent\nGood command in both written and spoken English/Cantonese\nSelf-motivated, good interpersonal skill\nOutgoing, pleasant & able to work independently", "employment_types": ["Full Time", "Permanent"], "selling_points": ["Technical support, repairing & promote products", "On-site trouble shooting & perform sleep test", "Self-motivated, pleasant & work independently"], "locations": ["Tsim Sha Tsui"], "categories": ["Engineering", "Electrical / Electronics", "Mechanical", "Medical Services", "Others"], "post_time": "2022-01-16T21:50:40Z", "salary": {"currency": null, "max": null, "min": null, "period": "monthly", "term": null}, "salary_visible": false, "title_keywords": ["technician"], "responsibilities": ["installation", "maintenance", "diagnose", "handle enquiries", "repair", "promote products"], "requirements": {"degrees": ["diploma"], "majors": [], "languages": ["cantonese", "english"], "language_level": ["good command"], "hard_skills": [], "soft_skills": ["outgoing", "self-motivated", "work independently", "pleasant", "interpersonal skill"], "languages_combined": [{"language": "cantonese", "language_level": ["good command"]}, {"language": "english", "language_level": ["good command"]}]}, "experience_required": {"duration": [], "field": []}}, {"job_id": "100003009055332", "location_code": "hk", "company": "Computime Ltd", "job_title": "Senior Engineer \u2013 Electronics", "description": "Major Responsibilities\n\nDesign and develop electronic and wireless products\nPrepare schematic drawing, review PCB layout, prepare test plan and specifications\nBuild prototype and hardware performance evaluation\nWork with software team for driver, firmware and apps development\nPerform engineering verification test and design verification test\nSupport production for sample build, pilot run and mass production\nWork with test lab to resolve EMC/EMI issues to meet international standards\nSupport sales and business team for RFI and RFQ\nWork at multi-sites with multi-cultural teams\n\nRequirements\n\nBachelor Degree in Electrical & Electronics Engineering\nMinimum 5 years of solid experience in electronic hardware system design and development\nKnowledge in 3-phase motor control\nExperience in Heat Pump and/or AC control an advantage\nSolid experience in circuit design and PCB layout\nHands-on experience in SoC design of electronics products\nFamiliar in using oscilloscope, multi meter, E-load, data logger, etc. to do design verification\nFamiliar with any of the following sub-systems a plus:\n- Radar, LTE, WiFi, BLE, Zigbee, NFC\n- AC/DC conversion, DC/DC conversion, battery charging, wireless charging\n- AC motor, DC motor, Brushless motor\n- Power electronics design\nKnowledgeable with EMC / CE / VDE / FCC/ UL Standards and familiar with approval process\nProblem solving skills, quick learner and a good team player\nGood command of spoken English and Chinese, including Putonghua\nLess experience considered as Engineer\n\nInterested parties, please apply together with a detailed resume, stating current and expected salary, and send it via APPLY NOW.\u00a0 Attractive remuneration will be offered in commensurate with qualification and experience.\u00a0\n\nAll personal information received will be treated in strict confidence for employment purpose only.\u00a0 Your application can be considered as unsuccessful if you have not been reached within 3 months.\u00a0 On the other hand, it may be transferred to other companies of our group for job openings.\u00a0 Unsuccessful applications will be destroyed for a period not more than 12 months.\u00a0\n\nhttps://www.computime.com/\nhttps://salus-controls.com/", "employment_types": ["Full Time", "Permanent"], "selling_points": ["5 days work, double pay, and free shuttle coach", "Prepare schematic drawing, review PCB layout", "SoC design of electronics products"], "locations": ["Shatin Area"], "categories": ["Engineering", "Electrical / Electronics", "Telecommunication / Wireless / Radio", "Information Technology (IT)", "Mobile / Wireless Communications"], "post_time": "2022-01-18T02:12:49Z", "salary": {"currency": null, "max": null, "min": null, "period": "monthly", "term": null}, "salary_visible": false, "title_keywords": ["senior engineer"], "responsibilities": ["software", "review", "design and develop", "teams", "design", "hardware", "specifications", "plan", "evaluation"], "requirements": {"degrees": ["degree", "bachelor"], "majors": ["engineering"], "languages": ["putonghua", "english", "chinese"], "language_level": ["good command"], "hard_skills": ["plus", "hardware", "system design", "dc", "problem solving skills"], "soft_skills": ["quick learner", "good team player", "hands-on", "problem solving skills"], "languages_combined": [{"language": "putonghua", "language_level": ["good command"]}, {"language": "english", "language_level": ["good command"]}, {"language": "chinese", "language_level": ["good command"]}]}, "experience_required": {"duration": ["minimum 5 years"], "field": ["development", "system design", "design"]}}, {"job_id": "100003009051900", "location_code": "hk", "company": "Hong Kong Applied Science and Technology Research Institute Company Limited (ASTRI)", "job_title": "Senior Engineer (PI) /Engineer (PI), Electronic Engineering", "description": "Reference #:2021/ART/333CP/a\n\u00a0\nJob Responsibilities\n\nAssist in ITF R&D project as assigned\nHands on PCB assemble and circuit function validation\nDesign and implement PCB schematic and layout design\nPrepare testing data for the deliverables, write reports documenting detail methods and results\nRequirements\n\nGraduate in EE-related discipline such as Electronic Engineering, Information Engineering or relevant discipline\nA bachelor\u2019s degree, master\u2019s degree or a doctoral degree\u2019s holder is welcome to apply\nFor bachelor\u2019s degree holder, they will be considered for the position of Engineering Associate (PI)\nExperiences in PCB schematic & layout design, mixed signal IC design, digital & analogue signal processing\nFamiliar with EDA software such as Altium/Cadence/Mentor/Synopsys, etc. EE equipment like oscilloscope, multimeter etc\nExperience in firmware development, MCU software development is a plus\nGood command of written and spoken English or Chinese\nApplication\n\nTo apply, by clicking 'APPLY NOW'\u00a0\u00a0with your resume, you must quote the\u00a0Job Ref\u00a0and include the following information:\n\nName of University\nDegree obtained/expecting and when\nHave you participated in ITF Research Talent Hub before? Yes/No\nIf you answer Yes in item 3, please state the period\nHave you been employed by ASTRI before? If yes, please state the period\n\nThe resume should\u00a0not\u00a0include any sensitive personal information such as HKID or passport number, photo, etc.\n\nThe application will be open until the position is filled. Only short-listed candidates will be notified. ASTRI reserves the right not to fill the position.\n\nASTRI is an Equal Opportunities Employer. Personal data provided by job applicants will be used\u00a0exclusively\u00a0for recruitment\u00a0only. For details, please refer to\u00a0Privacy - ASTRI - Hong Kong Applied Science and Technology Research Institute Company Limited,\u00a0in particular section 9.", "employment_types": ["Full Time", "Contract"], "selling_points": ["Five-Day Work Week, involve R&D projects", "Medical Insurance Provided", "Stable working environment"], "locations": ["Shatin Area"], "categories": ["Engineering", "Electrical / Electronics", "Sciences, Lab, R&D", "Research & Development (R&D)", "Others", "Student / Fresh Graduate / No Experience"], "post_time": "2022-01-17T01:28:35Z", "salary": {"currency": null, "max": null, "min": null, "period": "monthly", "term": null}, "salary_visible": false, "title_keywords": ["senior engineer", "engineer"], "responsibilities": ["data", "layout design", "design", "testing", "reports"], "requirements": {"degrees": ["degree holder", "degree", "bachelor", "master"], "majors": ["engineering"], "languages": ["english", "chinese"], "language_level": ["good command"], "hard_skills": ["no", "plus", "processing", "signal"], "soft_skills": ["sensitive"], "languages_combined": [{"language": "english", "language_level": ["good command"]}, {"language": "chinese", "language_level": ["good command"]}]}, "experience_required": {"duration": [], "field": ["digital", "development", "design", "software development"]}}, {"job_id": "100003009052027", "location_code": "hk", "company": "Concord Solutions (HK) Limited", "job_title": "\u7cfb\u7d71\u7ba1\u7406\u5de5\u7a0b\u5e2b System Engineer", "description": "\u4e3b\u8981\u8077\u8cac\uff1a\n\u8ca0\u8cac\u8fc5\u901f\u6709\u6548\u7387\u5730\u63a5\u807d\u6545\u969c\u5831\u544a\u71b1\u7dda\n\u53c3\u8207\u53ca\u5354\u8abf\u65e5\u5e38PM\u548cCM\u5de5\u4f5c\uff0c\u78ba\u4fdd\u5de5\u4f5c\u8cea\u91cf\u9054\u5230\u71df\u904b\u8981\u6c42\n\u73fe\u5834\u6545\u969c\u8655\u7406\u53ca\u6574\u6539\n\u8ca0\u8cac\u6280\u8853\u554f\u984c\u7684\u5206\u6790\u548c\u89e3\u6c7a\u5be6\u65bd\uff0c\u5be6\u6642\u638c\u63e1\u8a2d\u5099\u904b\u7528\u72c0\u614b\uff0c\u53ca\u6642\u89e3\u6c7a\u8a2d\u5099\u5b58\u5728\u7684\u554f\u984c\n\u4e3b\u7ba1\u6307\u6d3e\u7684\u5176\u4ed6\u81e8\u6642\u8077\u8cac\n7 x 24\u503c\u73ed\u5de5\u4f5c\n\n\u5165\u8077\u689d\u4ef6\uff1a\n\u9ad8\u7d1a\u6587\u6191\u3001\u5c08\u79d1\u53ca\u4ee5\u4e0a\u5b78\u6b77\uff0c\u901a\u4fe1\u3001\u96fb\u5b50\u3001\u8a08\u7b97\u6a5f\u3001\u81ea\u52d5\u5316\u63a7\u5236\u53ca\u76f8\u95dc\u5c08\u696d\u53ca\u76f8\u95dc\u5c08\u696d\uff1b\n\u5177\u67092\u5e74\u6216\u4ee5\u4e0a\u81ea\u52d5\u5316\u63a7\u5236, \u7cfb\u7d71\u5de5\u4f5c\u7d93\u9a57\uff1b\n\u719f\u6089PLC\u63a7\u5236\u539f\u7406\uff0cAllen Bradley-PLC \u7a0b\u5f0f\u8a9e\u8a00 Programming, Trouble-shooting and debugging\n\u719f\u6089\u96fb\u8166\u8a2d\u5099\u7dad\u8b77\u6280\u8853: Window Server, Linux, IT Networking\n\u00a0\u5177\u5099\u96fb\u5b50\u5143\u4ef6\u7dad\u4fee\u53ca\u6545\u969c\u8a3a\u65b7\u8655\u7406\u80fd\u529b;\n\u00a0\u5177\u5099\u4eba\u969b\u95dc\u4fc2\u8655\u7406\u80fd\u529b\u3001\u5354\u8abf\u80fd\u529b\u3001\u8cac\u4efb\u5fc3\u3001\u81ea\u767c\u6027\u53ca\u80fd\u7368\u7acb\u5de5\u4f5c\uff1b\n\u5177\u5099\u826f\u597d\u7684\u4e2d\u6587\u53ca\u82f1\u8a9e\u8b80\u3001\u5beb\u80fd\u529b\u3002\n\n\u7533\u8acb\u8005\u8acb\u628a\u5de5\u4f5c\u5c65\u6b77\uff0c\u73fe\u6642\u85aa\u91d1\u53ca\u8981\u6c42\u5f85\u9047\uff0c\u767c\u9001\u96fb\u90f5\u81f3 APPLY NOW \u6216\u50b3\u771f\u81f324792532\u3002", "employment_types": ["Full Time", "Permanent"], "selling_points": [], "locations": ["Tsim Sha Tsui"], "categories": ["Engineering", "Electrical / Electronics"], "post_time": "2022-01-17T01:52:27Z", "salary": {"currency": null, "max": null, "min": null, "period": "monthly", "term": null}, "salary_visible": false, "title_keywords": ["system engineer"], "responsibilities": [], "requirements": {"degrees": [], "majors": [], "languages": [], "language_level": [], "hard_skills": ["server", "linux", "plc", "programming"], "soft_skills": [], "languages_combined": []}, "experience_required": {"duration": [], "field": []}}, {"job_id": "100003009001298", "location_code": "hk", "company": "Lik On Security Limited", "job_title": "\u5730\u76e4\u7ba1\u5de5 Site Supervisor", "description": "\u00a0\u8077\u8cac\u7bc4\u7587\uff1a\n\n\n\u00a0\u00a0\u00a0\u00a0\u00a0\u00a0\u00a0\u00a0 \u76e3\u7763\u5404\u627f\u5224\u5546\u5b89\u88dd\u5f31\u96fb\u5de5\u7a0b\u9805\u76ee\n\u00a0\u00a0\u00a0\u00a0\u00a0\u00a0\u00a0\u00a0 \u8ca0\u8cac\u50b3\u905e\u826f\u597d\u5b89\u5168\u3001\u74b0\u4fdd\u548c\u8cea\u91cf\u63a7\u5236\n\u00a0\u00a0\u00a0\u00a0\u00a0\u00a0\u00a0\u00a0 \u8655\u7406\u65e5\u5e38\u5730\u76e4\u7ba1\u7406\u53ca\u5354\u8abf\u65bd\u5de5\n\u00a0\u00a0\u00a0\u00a0\u00a0\u00a0\u00a0\u00a0 \u5b9a\u671f\u51fa\u5e2d\u5de5\u7a0b\u9032\u5ea6\u53ca\u5b89\u5168\u6703\u8b70\uff0c\u4e26\u4f5c\u51fa\u76f8\u61c9\u5b89\u6392\u53ca\u5de5\u4f5c\u5206\u914d\n\u00a0\u00a0\u00a0\u00a0\u00a0\u00a0\u00a0\u00a0 \u76e3\u7763\u6e2c\u8a66\u53ca\u8abf\u8a66\u5de5\u4f5c\n\n\u5165\u8077\u8981\u6c42\uff1a\n\n\n\u00a0\u00a0\u00a0\u00a0\u00a0\u00a0\u00a0\u00a0 \u6700\u5c113\u5e74\u5f31\u96fb\u6216\u9805\u76ee\u5730\u76e4\u76e3\u7763\u7d93\u9a57\n\u00a0\u00a0\u00a0\u00a0\u00a0\u00a0\u00a0\u00a0 \u826f\u597d\u7684\u6e9d\u901a\u548c\u5730\u76e4\u7ba1\u7406\u80fd\u529b\n\u00a0\u00a0\u00a0\u00a0\u00a0\u00a0\u00a0\u00a0 \u6301\u6709\u6548\u96fb\u5de5\u724c\u548c\u5efa\u9020\u696d\u5de5\u4eba\u8a3b\u518a\u8b49\n\u00a0\u00a0\u00a0\u00a0\u00a0\u00a0\u00a0\u00a0 \u53ef\u5373\u6642\u4e0a\u73ed\u512a\u5148\u8003\u616e\n\n\u61c9\u5fb5\u8005\u8acb\u5c07\u5c65\u6b77\u8868\u53ca\u8981\u6c42\u85aa\u91d1\u96fb\u90f5(\u8acb\u6309\"APPLY NOW\") \u6216 \u90f5\u5bc4\u81f3:\u00a0\u529b\u5b89\u8b77\u885b\u6709\u9650\u516c\u53f8\u4e5d\u9f8d\u9577\u6c99\u7063\u9577\u7fa9\u885710\u865f\u660c\u9686\u5de5\u696d\u5927\u5ec88\u6a13\u884c\u653f\u90e8\u6536\u00a0\u6216\u81f4\u96fb\u00a02485-2485 \u884c\u653f\u90e8\u9810\u7d04\u9762\u8a66\u6642\u9593\u3002\n\n\u672c\u516c\u53f8\u662f\u5e73\u7b49\u6a5f\u6703\u50f1\u4e3b\uff0c\u6240\u6709\u6536\u96c6\u8cc7\u6599\u53ea\u6703\u7528\u4f5c\u62db\u8058\u7528\u9014\u3002", "employment_types": ["Full Time", "Permanent"], "selling_points": ["\u6700\u5c113\u5e74\u5f31\u96fb\u6216\u9805\u76ee\u5730\u76e4\u76e3\u7763\u7d93\u9a57", "\u6301\u6709\u6548\u96fb\u5de5\u724c\u548c\u5efa\u9020\u696d\u5de5\u4eba\u8a3b\u518a\u8b49", "\u76e3\u7763\u5404\u627f\u5224\u5546\u5b89\u88dd\u5f31\u96fb\u5de5\u7a0b\u9805\u76ee"], "locations": ["Not Specified"], "categories": ["Engineering", "Electrical / Electronics", "Telecommunication / Wireless / Radio", "Others", "Security / Safety Control"], "post_time": "2022-01-16T21:50:07Z", "salary": {"currency": null, "max": null, "min": null, "period": "monthly", "term": null}, "salary_visible": false, "title_keywords": ["site supervisor"], "responsibilities": [], "requirements": {"degrees": [], "majors": [], "languages": [], "language_level": [], "hard_skills": [], "soft_skills": [], "languages_combined": []}, "experience_required": {"duration": [], "field": []}}, {"job_id": "100003009054937", "location_code": "hk", "company": "Sun Hung Kai Properties Ltd", "job_title": "SENIOR TECHNICAL OFFICER / TECHNICAL OFFICER - RESIDENTIAL", "description": "Requirements:\n\n\nDegree or above in Building Surveying/Building Study or related discipline\nMinimum 6 years\u2019 relevant experience in property maintenance\nPractical hands-on experience in managing luxury residential properties will be an advantage\nConversant with statutory regulations and requirement in Hong Kong\nGood communication skill, independent and aggressive with all-rounded knowledge of repair and maintenance in A&A and builder\u2019s works, M&E\nGood command of both written and spoken English and Chinese\nRegistered Minor Works Contractor (Class III), Green Card holders and Safety Supervisors\nPossession of Grade B Certificate of Registration of Electrical Worker will be an advantage\nFlexible and able to work under pressure and meet tight deadlines\n\nResponsibilities:\n\n\nResponsible for interior renovation, repair and maintenance of residential rental properties\nProvide technical advices and recommendations on repair and improvement works\nPrepare specifications and tender documents for repair and maintenance works\nConduct study on cost control measures for building works\nMonitor contractors\u2019 performance\nAttend meetings as assigned\n\n(Candidates with less experience will be considered for Technical Officer.)\n\nGood remuneration and attractive fringe benefits will be offered to the successful applicant. Interested parties please apply with full resume, present and expected salary, available date by clicking \"Apply Now\".\n\nFor further information, please visit our company website: http://www.shkp.com/.\n\nWe are an equal opportunity employer and welcome applications from all qualified candidates. All personal data collected will be used for recruitment purpose only.\u00a0 Applicants not hearing from us within 3 months may consider their applications unsuccessful.\u00a0 All personal data collected will be destroyed within 24 months.", "employment_types": ["Full Time", "Permanent"], "selling_points": ["Repair and maintenance of residential properties", "Prepare tender documents", "Study on cost control measures for building works"], "locations": ["Wan Chai"], "categories": ["Building & Construction", "Building / Construction / QS", "Engineering", "Electrical / Electronics", "Property / Real Estate", "Property Management"], "post_time": "2022-01-17T14:28:33Z", "salary": {"currency": null, "max": null, "min": null, "period": null, "term": null}, "salary_visible": false, "title_keywords": ["technical officer", "senior technical officer"], "responsibilities": ["maintenance", "tender documents", "renovation", "monitor", "repair", "specifications", "cost control", "attend meetings", "repair and maintenance works"], "requirements": {"degrees": ["certificate", "degree or above"], "majors": ["building surveying"], "languages": ["english", "chinese"], "language_level": ["good command"], "hard_skills": ["certificate of registration of electrical worker", "maintenance", "green card"], "soft_skills": ["flexible", "meet tight deadlines", "independent", "communication skill", "hands-on", "work under pressure"], "languages_combined": [{"language": "english", "language_level": ["good command"]}, {"language": "chinese", "language_level": ["good command"]}]}, "experience_required": {"duration": ["minimum 6 years"], "field": ["relevant experience", "maintenance"]}}, {"job_id": "100003009047894", "location_code": "hk", "company": "The Arca", "job_title": "Duty Engineer \u503c\u73ed\u5de5\u7a0b\u5e2b", "description": "Job Responsibilities \u5de5\u4f5c\u5167\u5bb9:\n\nResponsible for hotel daily maintenance and equipment inspection, such as water, electricity, mechanical equipment, furniture, electronic devices, bathroom equipment and basic air-conditioning maintenance work\n\u8ca0\u8cac\u9152\u5e97\u65e5\u5e38\u7dad\u4fee\u548c\u8a2d\u5099\u6aa2\u67e5\uff0c\u4f8b\u5982\u6c34\u3001\u96fb\u3001\u6a5f\u68b0\u8a2d\u5099\u3001\u5bb6\u5177\u3001\u96fb\u5b50\u8a2d\u5099\u3001\u6d74\u5ba4\u8a2d\u5099\u53ca\u7a7a\u8abf\u7dad\u4fee\u4fdd\u990a\u5de5\u4f5c\nSupervise and control the preventive maintenance schedule\n\u76e3\u7763\u548c\u63a7\u5236\u9810\u9632\u6027\u7dad\u4fee\u8a08\u5283\n\nJob Requirements \u5de5\u4f5c\u8981\u6c42:\n\nHolder of Diploma/Certificate holders in Building Services/Mechanical/Electrical Engineering or other related disciplines\n\u6301\u6709\u5c4b\u5b87\u8a2d\u5099/\u6a5f\u68b0/\u96fb\u6c23\u5de5\u7a0b\u6216\u5176\u4ed6\u76f8\u95dc\u5b78\u79d1\u7684\u6587\u6191/\u8b49\u66f8\nGrade B Certificate of Registration of Electrical Worker is preferred\n\u6301\u6709B\u7d1a\u96fb\u696d\u5de5\u7a0b\u4eba\u54e1\u8a3b\u518a\u8b49\u66f8\u8005\u512a\u5148\nMinimum 4 years\u2019 working experience in repairs and maintenance\n\u81f3\u5c114\u5e74\u7dad\u4fee\u548c\u4fdd\u990a\u7684\u5de5\u4f5c\u7d93\u9a57\nGood command of both spoken and written English and Chinese\n\u826f\u597d\u7684\u4e2d\u6587\u548c\u82f1\u6587\n\nWe offer career opportunities and excellent remuneration package to the right candidate. Please email your full resume with current and expected salary to Human Resources Department or on Whatsapp 5976 5391.\n\nYulan Group Limited is an equal opportunity employer. Applicants not invited for interview within six weeks may consider their applications unsuccessful. All information will be used solely for recruitment purpose and will be destroyed when the recruitment process is finished.", "employment_types": ["Full Time", "Permanent"], "selling_points": ["\u8ca0\u8cac\u9152\u5e97\u65e5\u5e38\u7dad\u4fee\u548c\u8a2d\u5099\u6aa2\u67e5", "\u76e3\u7763\u548c\u63a7\u5236\u9810\u9632\u6027\u7dad\u4fee\u8a08\u5283", "4\u5e74\u7dad\u4fee\u548c\u4fdd\u990a\u7684\u5de5\u4f5c\u7d93\u9a57"], "locations": ["Southern Area"], "categories": ["Engineering", "Electrical / Electronics", "Engineering Project Management", "Mechanical"], "post_time": "2022-01-14T04:23:21Z", "salary": {"currency": null, "max": null, "min": null, "period": "monthly", "term": null}, "salary_visible": false, "title_keywords": ["engineer"], "responsibilities": ["control", "schedule", "maintenance", "inspection"], "requirements": {"degrees": ["certificate", "diploma"], "majors": ["related disciplines", "building services", "electrical engineering"], "languages": ["english", "chinese"], "language_level": ["good command"], "hard_skills": ["certificate of registration of electrical worker", "maintenance"], "soft_skills": [], "languages_combined": [{"language": "english", "language_level": ["good command"]}, {"language": "chinese", "language_level": ["good command"]}]}, "experience_required": {"duration": ["minimum 4 years"], "field": ["maintenance"]}}, {"job_id": "100003009052597", "location_code": "hk", "company": "Forward Construction Company Limited", "job_title": "BUILDING SERVICES COORDINATOR", "description": "Requirements\nHigher Diploma or above in Building Services / Electrical / Mechanical Engineering\nMinimum 5 years\u2019 experience relevant experience\nKnowledge of Building Services Installation and relevant statutory regulations\nProficient in PC skills (e.g. MS office, MS project & AutoCAD)\nGood interpersonal and communication skills\nHard working, self-motivated and able to work independently\nInterested candidates, please e-mail your full resume, expected salary and contact telephone number by clicking \"Apply Now\"", "employment_types": ["Full Time", "Permanent"], "selling_points": ["Higher Diploma or above in Building Services", "Minimum 5 years\u2019 experience relevant experience", "Knowledge of Building Services Installation"], "locations": ["Not Specified"], "categories": ["Building & Construction", "Building / Construction / QS", "Engineering", "Electrical / Electronics", "Others"], "post_time": "2022-01-17T03:30:01Z", "salary": {"currency": null, "max": null, "min": null, "period": "monthly", "term": null}, "salary_visible": false, "title_keywords": ["coordinator"], "responsibilities": ["regulations", "installation", "communication"], "requirements": {"degrees": ["higher diploma or above"], "majors": ["building services", "mechanical engineering"], "languages": [], "language_level": [], "hard_skills": ["pc skills", "autocad", "ms office"], "soft_skills": ["communication skills", "self-motivated", "work independently", "hard working", "interpersonal"], "languages_combined": []}, "experience_required": {"duration": ["minimum 5 years"], "field": ["relevant experience"]}}, {"job_id": "100003009051151", "location_code": "hk", "company": "Allworth Consultants Limited", "job_title": "HVAC Engineer / Electrical Engineer - all level  (Upto $600k annual)", "description": "Highe Diploma or above in Electrical, Mechanical, Building Services Engineering or related discipline.\nMinimum 3 years relevant working experience in any Electrical, HVAC or MVAC\nWorked in E&M Contractors is an advantage\nExperience in site coordination, supervision and submissions\nCandidate with less experience will be considered as Assistant Engineer\n\nFor application, please click \"APPLY NOW\" or WhatsApp CV to +852 3752\u00a08881\n\n\u00a0Please visit our website for more job openings\u00a0\nhttp://awclhk.com/job-opportunities/", "employment_types": ["Full Time"], "selling_points": ["5 days work", "E&M Contractor", "Residential, Hospital, Plant projects"], "locations": ["Not Specified"], "categories": ["Engineering", "Electrical / Electronics", "Mechanical"], "post_time": "2022-01-15T03:36:20Z", "salary": {"currency": "HKD", "max": 54999, "min": 35000, "period": "monthly", "term": null}, "salary_visible": true, "title_keywords": ["electrical engineer", "engineer"], "responsibilities": ["site coordination", "website"], "requirements": {"degrees": ["diploma or above"], "majors": ["building services", "engineering"], "languages": [], "language_level": [], "hard_skills": ["hvac", "whatsapp"], "soft_skills": ["coordination"], "languages_combined": []}, "experience_required": {"duration": ["minimum 3 years"], "field": ["relevant working experience"]}}, {"job_id": "100003009048270", "location_code": "hk", "company": "Media-Go Engineering Ltd", "job_title": "Customer Support Engineer", "description": "Job Responsibilities:\n\nProvide technical support to end users and sub-contractors\n\u5411\u7528\u6236\u53ca\u627f\u5224\u5546\u63d0\u4f9b\u6280\u8853\u652f\u63f4\nProvide onsite services including software and hardware installation and maintenance and on-site inspection\n\u63d0\u4f9b\u73fe\u5834\u5b89\u88dd\u8edf\u4ef6\u53ca\u786c\u4ef6\u3001\u7dad\u4fee\u53ca\u6aa2\u67e5\u670d\u52d9\nProvide repair services, follow up and testing the products\n\u63d0\u4f9b\u7dad\u4fee\u3001\u8ddf\u9032\u53ca\u7522\u54c1\u6e2c\u8a66\u670d\u52d9\n\nJob Requirements:\n\nCertificate or Diploma in Electronics / Electrical Engineering / Building Service Engineering or equivalent\n\u4fee\u8b80\u96fb\u6a5f / \u96fb\u6a5f\u5de5\u7a0b / \u5c4b\u5b87\u88dd\u5099\u5de5\u7a0b\u6216\u76f8\u95dc\u4e4b\u8b49\u66f8\u6216\u6587\u6191\nMin. 1 - 2 years of solid experience with sound on-site installation, coordination and T&C skills\n\u5177\u4e00\u81f3\u4e8c\u5e74\u6216\u4ee5\u4e0a\u76f8\u95dc\u7d93\u9a57\uff0c\u5305\u62ec\u73fe\u5834\u97f3\u97ff\u5b89\u88dd\u3001\u5354\u8abf\u3001\u6e2c\u8a66\u53ca\u8a66\u904b\u884c\nExperience in maintenance of automatic control system will be an advantage\n\u6709\u81ea\u52d5\u5316\u63a7\u5236\u7cfb\u7d71\u7dad\u4fee\u7d93\u9a57\u512a\u5148\u8003\u616e\nGreen Card holder and CIC worker. Registration of Electrical Worker (Grade A) will be an advantage\n\u9700\u6709\u5e73\u5b89\u54ad\uff0c\u5efa\u9020\u696d\u5de5\u4eba\u8a3b\u518a\u8a3c\u3002\u6301\u96fb\u5de5\u724c\u8005\u512a\u5148\u8003\u616e\nGood command of Cantonese, fair command of English in reading and writing\n\u64cd\u6d41\u5229\u5ee3\u6771\u8a71, \u80fd\u95b1\u8b80\u548c\u66f8\u5beb\u7c21\u55ae\u82f1\u6587\nTeam work spirit\n\u5718\u968a\u5408\u4f5c\u7cbe\u795e\nImmediate available preferred\n\u53ef\u5373\u6642\u4e0a\u73ed\u512a\u5148\u8003\u616e\n\nWe offer competitive remuneration package and good prospects to the right candidates. Interested parties please click\u00a0\"Apply Now\"\u00a0to send your full resume with current and expected salary to us. (Please quote the job title on the subject).\n\nFor more information, please visit our website:\u00a0www.mediago-group.com\n\nData collected will be kept confidential and used for recruitment purposes only.", "employment_types": ["Full Time"], "selling_points": [], "locations": ["Kwun Tong Area"], "categories": ["Engineering", "Electrical / Electronics", "Others"], "post_time": "2022-01-15T03:49:53Z", "salary": {"currency": null, "max": null, "min": null, "period": "monthly", "term": null}, "salary_visible": false, "title_keywords": ["support engineer"], "responsibilities": ["installation", "software", "maintenance", "technical support", "site inspection", "testing", "hardware", "repair"], "requirements": {"degrees": ["certificate", "diploma"], "majors": ["engineering", "electrical engineering"], "languages": ["cantonese", "english"], "language_level": ["good command"], "hard_skills": ["maintenance", "green card"], "soft_skills": ["coordination"], "languages_combined": [{"language": "cantonese", "language_level": ["good command"]}, {"language": "english", "language_level": ["good command"]}]}, "experience_required": {"duration": ["1 - 2 years"], "field": ["installation", "maintenance"]}}, {"job_id": "100003009051239", "location_code": "hk", "company": "iAdvantage Limited", "job_title": "Facility Engineer (Data Centre)", "description": "Responsibilities:\n\nSupervise and assign work orders to the technical team to carry out routine repair and maintenance work\nProvide technical guidance for E&M improvement works\nSchedule and implement planned maintenance works as assigned\nMonitor the progress of all contracted-out projects and tenants\u2019 fit-out works\nPrepare approval form to top management for the procurement of any goods/services\nAssist in testing and commissioning of tenants\u2019 fit-out works and handover of premises to new tenants\nMaintain ISO9001:2008 and ISO14001:2004 QEMS System for data centre operation\n\nRequirements:\n\nHigher Diploma in Electrical Engineering or Building Services Engineering or related disciplines\n5 years\u2019 relevant experience in Electrical and/or MVAC Operation and Maintenance, with Data Centre experience is highly preferred\nFamiliar with UPS, Gensets, chiller plant, LV switchboards and CRACs\nHolder of Electrical Worker License Grade A or Above\nGood remuneration and attractive fringe benefits will be offered to the successful applicant. Interested parties please apply with full resume, present & expected salary, available date by clicking \"Apply Now\". For further information, please visit our company website: http://www.iadvantage.net/\n\n\nWe are an equal opportunity employer and welcome applications from all qualified candidates. All personal data collected will be used for recruitment purpose only. Applicants not hearing from us within 3 months may consider their applications unsuccessful. All personal data collected will be destroyed within 12 months", "employment_types": ["Full Time", "Permanent"], "selling_points": ["Leading Data Centre in Hong Kong", "Foster Professional Business Partnerships", "Energetic and Flexible Working Environment"], "locations": ["Not Specified"], "categories": ["Engineering", "Electrical / Electronics", "Engineering Project Management"], "post_time": "2022-01-15T05:41:33Z", "salary": {"currency": null, "max": null, "min": null, "period": "monthly", "term": null}, "salary_visible": false, "title_keywords": ["facility engineer"], "responsibilities": ["guidance", "management", "commissioning", "maintenance", "data", "monitor", "testing", "repair", "maintain", "schedule"], "requirements": {"degrees": ["diploma"], "majors": ["related disciplines", "building services", "electrical engineering", "engineering"], "languages": [], "language_level": [], "hard_skills": ["maintenance"], "soft_skills": [], "languages_combined": []}, "experience_required": {"duration": ["5 years"], "field": ["operation", "relevant experience", "maintenance"]}}, {"job_id": "100003009055743", "location_code": "hk", "company": "KOS International Limited", "job_title": "Building Services Engineer (Main Contractor)", "description": "Job Description\n\nAbout our client\n\nOur client is a leading main contractor with a stable project pipeline in Hong Kong. To cope with its business growth, they are looking for a high caliber Building Services Engineer to join.\n\nAbout the role\n\nKeep track on design issuance with consultants according to agreed timeline\nIdentify design problem and liaise with consultants on alternatives\nCoordinate with sub-contractor on site progress and provide technical advice\nEstablish and monitor schedule for submission of CSD, CBW, drawings and material samples\nPerform site inspection and project meetings to monitor the quality and safety standard of the installation\n\n\nThe successful applicants\n\nDegree holder or above in Building Services / Mechanical / Electrical Engineering or related disciplines\n3 years of experience in Main Contractor or Consultant\nProfessional qualification (e.g. MHKIE, MCIBSE, MIMech or equivalent) is preferred", "employment_types": ["Full Time", "Permanent"], "selling_points": ["Degree holder in Building Services or equivalent", "Main Contractor", "Minimum 3 years of relevant experience"], "locations": ["Not Specified"], "categories": ["Engineering", "Electrical / Electronics", "Mechanical", "Others"], "post_time": "2022-01-18T02:54:47Z", "salary": {"currency": null, "max": null, "min": null, "period": "monthly", "term": null}, "salary_visible": false, "title_keywords": ["building services engineer"], "responsibilities": ["installation", "technical advice", "monitor", "coordinate with", "design", "drawings", "site inspection", "quality", "schedule", "liaise with consultants"], "requirements": {"degrees": ["degree holder"], "majors": ["related disciplines", "building services", "electrical engineering"], "languages": [], "language_level": [], "hard_skills": ["mhkie"], "soft_skills": ["stable"], "languages_combined": []}, "experience_required": {"duration": ["3 years"], "field": []}}, {"job_id": "100003009049814", "location_code": "hk", "company": "OMICRON electronics Asia Limited", "job_title": "Technical Support and Application Engineer (Electrical Engineer)", "description": "General Description\n\nOMICRON is a leading manufacturer of primary and secondary test equipment for electric power systems, with a headquarter in Austria. The role of Technical Support and Application Engineer (Electrical Engineer) will be responsible for supporting technical sales and providing technical support of OMICRON products\u00a0and their applications for our customers in the Asia region. The position is to be located in our OMICRON Service Center in Hong Kong and will be reporting to Application Engineer.\n\n\n\n\nYour tasks\n\nYou will take care of all technical requests of our customers in Asia \u2013 by telephone or e-mail\nYou will work independently or together with your colleagues on answering all application queries for our products\nYou will assist our clients in the practical application and integration of our test equipment\nYou support our regional sales team by actively conducting customer trainings and on-site product demos, and participating\nYou will actively participate in trade fairs, seminars, trade shows and workshops; and support our sales and marketing team with your technical knowledge\nYou will document and observe customer and market requirements to further develop our products\nYou will provide technical and application support to customers for OMICRON products and services, particularly for secondary testing equipment\nYou assist in developing, maintaining and improving customer relationships with help of Customer Relationship Management tools (CRM).\nYou will carry out customer engineering services, particularly related to secondary testing\nYou will support our regional application specialist and product management with your ideas to improve our innovative solutions; you will translate market requirements into technical specifications.\n\nYour profile\n\nYou have good knowledge of power system substations, generation, transmission and distribution of electric power\nHaving knowledge of protection, automation and control systems and experiences with electrical diagnostic tests of high voltage apparatus would be added advantages\nYou have a good knowledge of Mandarin and English; proficiency in more languages will help you in your work\nYou enjoy communicating and you like to organize your working day independently\nYou have a precise, reliable and autonomous working style\nYou want your enthusiasm for technology to connect with your job\nYou are flexible, and would enjoy travelling to other countries (20-50% travelling)\n\n\u00a0Education\n\nYou have a degree in Electrical engineering or relevant experience\n\nThis is not an exhaustive list of all duties and responsibilities. OMICRON reserves the right to amend and change responsibilities to meet business and organizational needs as necessary.\n\n\u00a0OMICRON distinguishes itself by:\n\nNot just offering a position, but an opportunity for growth and development in an international multi-cultural company.\nHaving fun while working as a part of a professional team.\nEncouraging personal initiative through flat hierarchies.\nOur extraordinary corporate culture and strong commitment to a healthy \"work-life-balance.\"\nOffering an attractive benefit package.\n\nOMICRON provides equal employment opportunities to all employees and applicants for employment without regard to race, color, religion, gender, sexual orientation, nationality or origin, age or disability.\n\nIf interested in becoming part of the OMICRON team, please submit your resume and cover letter with your expected salary to us. We look forward to hearing from you.", "employment_types": ["Full Time", "Permanent"], "selling_points": ["Experience in electrical/ power industry", "Degree in Electrical engineering", "MNC and Fun working environment"], "locations": ["Hung Hom"], "categories": ["Engineering", "Electrical / Electronics", "Engineering Project Management", "Others"], "post_time": "2022-01-14T09:16:29Z", "salary": {"currency": null, "max": null, "min": null, "period": "monthly", "term": null}, "salary_visible": false, "title_keywords": ["technical support", "application engineer", "electrical engineer"], "responsibilities": ["reporting", "management", "control", "ideas", "maintaining", "technical support", "systems", "developing", "develop", "testing", "specifications", "sales team"], "requirements": {"degrees": ["degree"], "majors": ["electrical engineering"], "languages": ["english", "mandarin"], "language_level": ["good"], "hard_skills": ["integration", "workshops", "fun"], "soft_skills": ["flexible", "exhaustive", "work independently", "independently", "responsible", "organizational", "interested in", "autonomous", "reliable", "precise", "innovative", "initiative"], "languages_combined": [{"language": "english", "language_level": ["good"]}, {"language": "mandarin", "language_level": ["good"]}]}, "experience_required": {"duration": [], "field": ["relevant experience", "engineering"]}}, {"job_id": "100003009055147", "location_code": "hk", "company": "Teltec Semiconductor Pacific Limited", "job_title": "Sales Engineer / Senior Engineer", "description": "Job Highlights:\n\n\nEver-expanding organization with extensive career development pathways and opportunities;\nApply your talent where it counts, working with a highly skilled technical team;\nGood remuneration and benefits.\n\nAbout Us\n\nTeltec Pacific is a multinational technical sales and service organisation serving the Semiconductor, Photonics and Optoelectronics Industry for over 37 years; with headquarters based in Central, Hong Kong and branches across the Asia Pacific region. We represent some of the Industry\u2019s world leading equipment and materials manufacturers in the region.\n\nAn exciting opportunity is now available, and we invite applications for Sales Engineer and Senior Engineer to join our organization. Successful candidates will be responsible for the company\u2019s represented equipment or materials in the high-tech electronics industry. You will work alongside with our collaborative technical sales and service engineering teams staying in various cities and countries in the Far East.\n\n\n\nJob Description\n\nDuties & Responsibilities\n\nSupport Sales and Services Managers;\nHandles Sales and Application jobs for Research Instrument\nSkills, Experience & Attributes\u00a0\n\nDegree holders, Science or Engineering majors highly regarded;\n0-3 years of solid experience in electronic industries preferred. Senior engineers post will be offered to those who have very related experience;\u00a0\nFluent in English and Mandarin;\u00a0\nMature and independent individuals with a high attention to detail and a proactive attitude;\n\nApplications\n\nWe are seeking highly engaged and motivated individuals to join our dynamic and growing organization, which highly recognises and rewards outstanding performances. Senior positions may be offered to potential candidates who can demonstrate long and direct working experience in the electronics market. Those successful will be offered 5-day work weeks, attractive remuneration and fringe benefits including medical allowance.\n\nIf this sounds like you, and you can demonstrate that you fill the requirements above, please submit your cover letter, full resume with expected salary to:\n\nHR Department\nTeltec Semiconductor Pacific Limited\n2802 Wing On House,\n71 Des Voeux Road Central,\nHong Kong\nTel: 852-25214213\nFax: 852-28106090\nWebsite: www.teltec.asia", "employment_types": ["Full Time", "Permanent"], "selling_points": ["Degree holders, Science or Engineering majors", "0\u20133 years experience in electronic industries", "Excellent development opportunities"], "locations": ["Central"], "categories": ["Engineering", "Electrical / Electronics", "Mechanical", "Sales, CS & Business Devpt", "Technical Sales / Sales Engineer"], "post_time": "2022-01-18T02:05:10Z", "salary": {"currency": null, "max": null, "min": null, "period": "monthly", "term": null}, "salary_visible": false, "title_keywords": ["senior engineer", "sales engineer"], "responsibilities": ["career development"], "requirements": {"degrees": [], "majors": [], "languages": [], "language_level": [], "hard_skills": [], "soft_skills": ["extensive"], "languages_combined": []}, "experience_required": {"duration": [], "field": []}}, {"job_id": "100003009053401", "location_code": "hk", "company": "Prudential Surveyors International Ltd", "job_title": "Assistant Building Surveyor / Technical Assistant", "description": "Jobs Highlight\n\n\n\nDiploma or Degree in Science or Engineering major\n1-3 years service experience in Instruments/Equipment\nOn-site lab equipment maintenance\n\nAbout Us\n\n\nTeltec Pacific is a multinational technical sales and service organisation serving the Semiconductor, Photonics and Optoelectronics Industry for over 36 years; with headquarters based in Central, Hong Kong and branches across the Asia Pacific region. We represent some of the Industry\u2019s world leading equipment and materials manufacturers in the region.\n\nAn exciting opportunity is now available, and we invite applications for\u00a0Technician / Service Engineer (Lab Equipment) to join our organization. Successful candidates will be responsible for the company\u2019s represented equipment or materials in the high-tech electronics industry. You will work alongside with our collaborative technical sales and service engineering teams staying in various cities and countries in the Far East.\n\n\n\nJob Description\n\nDuties & Responsibilities\n\nLab equipment service at customer site;\nManage and maintain a long-term relationship with new and existing customers;\nHandle sales enquirers and provide prompt and efficient business correspondences\n\nSkills, Experience & Attributes\u00a0\n\n\nDiploma or Degree holders in Science or Engineering majors highly regarded;\n1-3 years of solid experience\u00a0in Instruments/Equipment service. Engineers post will be\u00a0offered to those who have more experience;\u00a0\nFluent in English and Mandarin;\u00a0\nExcellent verbal and written communication skills with the ability to manage key stakeholder relationships at all levels;\nMature and independent individuals with a high attention to detail and a proactive attitude;\n\nApplications\n\nWe are seeking highly engaged and motivated individuals to join our dynamic and growing organization, which highly recognises and rewards outstanding performances. Senior positions may be offered to potential candidates who can demonstrate long and direct working experience in the electronics market. Those successful will be offered 5-day work weeks, attractive remuneration and fringe benefits including medical allowance.\n\nIf this sounds like you, and you can demonstrate that you fill the requirements above, please submit your cover letter, full resume with expected salary to:\n\nHR Department\nTeltec Semiconductor Pacific Limited\n2802 Wing On House,\n71 Des Voeux Road Central,\nHong Kong\nTel: 852-25214213\nFax: 852-28106090\nWebsite: www.teltec.asia", "employment_types": ["Full Time", "Permanent"], "selling_points": [], "locations": ["Sheung Wan"], "categories": ["Building & Construction", "Civil / Structural", "Engineering", "Electrical / Electronics", "Others"], "post_time": "2022-01-17T06:55:38Z", "salary": {"currency": null, "max": null, "min": null, "period": "monthly", "term": null}, "salary_visible": false, "title_keywords": ["surveyor", "assistant", "technical assistant"], "responsibilities": ["communication", "maintain", "teams", "maintenance"], "requirements": {"degrees": ["diploma", "degree"], "majors": ["science", "engineering"], "languages": ["english", "mandarin"], "language_level": ["fluent"], "hard_skills": ["dynamic", "maintenance"], "soft_skills": ["efficient", "communication skills", "independent", "responsible", "prompt", "collaborative", "mature", "motivated", "dynamic", "organisation", "attention to detail", "proactive"], "languages_combined": [{"language": "english", "language_level": ["fluent"]}, {"language": "mandarin", "language_level": ["fluent"]}]}, "experience_required": {"duration": ["1-3 years"], "field": []}}, {"job_id": "100003009051267", "location_code": "hk", "company": "China Mobile International Limited", "job_title": "(Assistant) Engineer, Mobile Service (Ref: CMIJD-0103-AENOMHK)", "description": "Responsibilities:\n\nDesign, plan and participate in project related to\u00a0development of\u00a0international network which consists of PoP sites, data centers, internet and internal IP backbones.\nTrack\u00a0network project progress\u00a0including\u00a0solution evaluation and selection, migration, expansion, feature development, software upgrade.\nProvide technical support relate to mobile service.\nProvide support in daily operation and emergency\u00a0services\u00a0\n\nRequirements:\n\nUniversity degree in Electrical/ Telecommunications or related disciplines, with definite advantage by processing relevant professional certification\nMinimum 3 years or above relevant experience in Mobile and IP network engineering\nExposure to\u00a0the design, planning,\u00a0implementation, maintenance and support of Mobile or IP network is an advantage\nProficiency in MS Office applications and Chinese Word Processing\nGood command of spoken and written Chinese and English, proficiency in Putonghua is an advantage\n\nInterested parties please send your full resume with current & expected salary by email to hr@ cmi.chinamobile.com.\u00a0Please indicate the reference number in the subject line.\n\nAll personal data provided will be used for consideration of your job application only.", "employment_types": ["Full Time", "Permanent"], "selling_points": ["Mobile network development", "Career growth opportunity", "Friendly working environment"], "locations": ["Kwai Hing"], "categories": ["Engineering", "Electrical / Electronics", "Telecommunication / Wireless / Radio", "Information Technology (IT)", "Mobile / Wireless Communications"], "post_time": "2022-01-15T06:58:56Z", "salary": {"currency": null, "max": null, "min": null, "period": "monthly", "term": null}, "salary_visible": false, "title_keywords": ["engineer", "assistant"], "responsibilities": ["provide support", "software", "data", "technical support", "daily operation", "project progress", "design", "plan", "evaluation", "migration"], "requirements": {"degrees": ["university degree"], "majors": ["related disciplines"], "languages": ["putonghua", "english", "chinese"], "language_level": ["advantage", "proficiency", "good command"], "hard_skills": ["chinese word processing", "maintenance", "mobile", "ip", "processing", "ms office"], "soft_skills": [], "languages_combined": [{"language": "putonghua", "language_level": ["proficiency", "advantage", "good command"]}, {"language": "english", "language_level": ["advantage", "good command"]}, {"language": "chinese", "language_level": ["proficiency", "advantage", "good command"]}]}, "experience_required": {"duration": ["minimum 3 years"], "field": ["relevant experience", "engineering"]}}, {"job_id": "100003009044969", "location_code": "hk", "company": "Harbour City Estates Ltd", "job_title": "\u5de5\u7a0b\u7763\u5c0e\u54e1 (\u96fb\u529b) TECHNICAL SUPERVISOR (5\u5929\u534a\u5de5\u4f5c)", "description": "\u8077\u8cac\uff1a\n\n\u8ca0\u8cac\u5546\u696d\u5927\u5ec8\u9ad8\u4f4e\u58d3\u96fb\u529b\u3001\u7e3d\u63a3\u6ac3\u53ca\u5927\u578b\u99ac\u9054\u63a7\u5236\u7dda\u8def\u3001\u5c4b\u5b87\u8a2d\u65bd\u7dad\u4fee\u4fdd\u990a\u53ca\u904b\u4f5c\u7b49\n\n\u5165\u8077\u8981\u6c42\uff1a\n\n\u9808\u5177\u6709\u6b63\u5f0f\u5b78\u5f92\u8a13\u7df4\uff0c\u6301\u6709\u5c4b\u5b87\u8a2d\u5099 / \u96fb\u6a5f\u5de5\u7a0b\u8b49\u66f8\u5c07\u7372\u512a\u5148\u8003\u616e\n\u4e09\u5e74\u4ee5\u4e0a\u96fb\u6a5f\u4fdd\u990a\u5de5\u4f5c\u7d93\u9a57\uff0c\u5176\u4e2d\u6700\u5c11\u4e00\u5e74\u70ba\u79d1\u6587\u6216\u7763\u5c0e\u7d1a\uff0c\u5177\u6709\u9ad8\u4f4e\u58d3\u96fb\u529b\u3001\u7e3d\u63a3\u6ac3\u53ca\u5927\u578b\u99ac\u9054\u63a7\u5236\u7dda\u8def\u7dad\u4fee\u4fdd\u990a\u7d93\u9a57\u5c07\u7372\u512a\u5148\u8003\u616e\n\u5fc5\u9808\u6301\u6709B\u7d1a\u96fb\u724c\u53ca\u5e73\u5b89\u54ad\uff0cH\u7d1a\u96fb\u724c\u6301\u6709\u8005\u5c07\u7372\u512a\u5148\u8003\u616e\n\n\u672c\u96c6\u5718\u63d0\u4f9b\u512a\u539a\u85aa\u916c\u3001\u826f\u597d\u6649\u5347\u6a5f\u6703\u3001\u5c08\u696d\u5728\u8077\u57f9\u8a13\u3001\u57f9\u8a13\u8cc7\u52a9\u3001\u9580\u8a3a\u53ca\u4f4f\u9662\u91ab\u7642\u8a08\u5283\u3001\u54e1\u5de5\u5eb7\u6a02\u6d3b\u52d5\u53ca\u5176\u4ed6\u798f\u5229\u3002\n\n\u6b61\u8fce\u6295\u5bc4\u500b\u4eba\u5c65\u6b77\uff08\u8acb\u5217\u660e\u7533\u8acb\u8077\u4f4d\uff09\uff1a\n\n\u50b3\u771f\u81f3 2118 8689 \u6216\u81f4\u96fb 2118 5350\u4eba\u4e8b\u90e8\u67e5\u8a62\n\n(\u7533\u8acb\u4eba\u63d0\u4f9b\u4e4b\u5168\u90e8\u8cc7\u6599\u7d55\u5c0d\u4fdd\u5bc6\u53ca\u53ea\u4f5c\u62db\u8058\u4e4b\u7528)", "employment_types": ["Full Time", "Permanent"], "selling_points": ["\u8ca0\u8cac\u5546\u696d\u5927\u5ec8\u9ad8\u4f4e\u58d3\u96fb\u529b\u3001\u7e3d\u63a3\u6ac3\u53ca\u5927\u578b\u99ac\u9054\u63a7\u5236\u7dda\u8def\u3001\u5c4b\u5b87\u8a2d\u65bd\u7dad\u4fee\u4fdd\u990a\u53ca\u904b\u4f5c\u7b49", "\u9808\u5177\u6709\u6b63\u5f0f\u5b78\u5f92\u8a13\u7df4\uff0c\u6301\u6709\u5c4b\u5b87\u8a2d\u5099 / \u96fb\u6a5f\u5de5\u7a0b\u8b49\u66f8\u5c07\u7372\u512a\u5148\u8003\u616e", "\u4e09\u5e74\u4ee5\u4e0a\u96fb\u6a5f\u4fdd\u990a\u5de5\u4f5c\u7d93\u9a57\uff0c\u5176\u4e2d\u6700\u5c11\u4e00\u5e74\u70ba\u79d1\u6587\u6216\u7763\u5c0e\u7d1a"], "locations": ["Tsim Sha Tsui"], "categories": ["Building & Construction", "Building / Construction / QS", "Engineering", "Electrical / Electronics", "Others", "Technician"], "post_time": "2022-01-15T03:49:25Z", "salary": {"currency": null, "max": null, "min": null, "period": null, "term": null}, "salary_visible": false, "title_keywords": ["technical supervisor"], "responsibilities": [], "requirements": {"degrees": [], "majors": [], "languages": [], "language_level": [], "hard_skills": [], "soft_skills": [], "languages_combined": []}, "experience_required": {"duration": [], "field": []}}, {"job_id": "100003009049918", "location_code": "hk", "company": "Fed-Supremetech Limited", "job_title": "ASSISTANT ELECTRICAL ENGINEER", "description": "\u00a0Fed-Supremetech Limited\n\nElectrical Engineering firm in Shatin invites candidates for the following vacancy :-\n\n\u00a0ASSISTANT ELECTRICAL PROJECT ENGINEER\n\nJob Responsibilities\n\n* To assist Project Manager / Project Engineer to handle design, quotation, project follows.\n*\u00a0Project schedule\u00a0, Site Status,\u00a0materials\u00a0updating\n* Check and review the drawing, production and delivery arrangement\n*\u00a0Co-ordination with Clients and other project management jobs\n* Basic knowledge in electrical power distribution system\n\n\u00a0Requirement\n\n* Degree Holder in Electrical Engineering or equivalent\u00a0\n* Fresh graduate to 2 years experience\n* Experience in electrical engineering is an advantage\n* Good command in written of English\n* Good Communication and interpersonal skills\n(experienced or higher education will consider to Project Engineer or Senior Project Engineer)\n\n\nWe offer attractive package, including double pay, Bonus, 14 days annual leave, etc.\u00a0to suitable candidates. Interested candidates please send application with full resume, availability and expected salary by email\n\nPersonal data collected would be used for recruitment purpose only.", "employment_types": ["Full Time"], "selling_points": [], "locations": ["Shatin Area"], "categories": ["Engineering", "Electrical / Electronics", "Engineering Project Management", "Manufacturing & Production"], "post_time": "2022-01-14T09:27:29Z", "salary": {"currency": null, "max": null, "min": null, "period": "monthly", "term": null}, "salary_visible": false, "title_keywords": ["electrical engineer", "assistant"], "responsibilities": ["review", "quotation", "design", "project management", "schedule"], "requirements": {"degrees": ["fresh graduate", "degree holder"], "majors": ["electrical engineering"], "languages": ["english"], "language_level": ["good command"], "hard_skills": [], "soft_skills": ["communication and interpersonal skills"], "languages_combined": [{"language": "english", "language_level": ["good command"]}]}, "experience_required": {"duration": ["2 years"], "field": ["engineering"]}}, {"job_id": "100003009055994", "location_code": "hk", "company": "Trinity Search Limited", "job_title": "Senior Engineer to Project Manager - HVAC (New Macau's project-based HK) Salary upto $75K", "description": "What you will do\u00a0\u00a0\n\nThe person will in charge of Quality Circle to ensure all project works are meeting the quality standards. Responsible for identifying problems and suggest possible solutions in eliminating incidents.\n\nHow you will do it\n\nRevise and streamline the process from time-to-time in meeting customers' satisfaction\nEnsure all the work done are carried out in accordance with the project specifications and clients' requirements\nConduct regular review meeting with clients to streamline process and reduce the nuisance\nAttend regular meetings with Project Manager and Contractors\n\nWhat we look for\n\nRequired\n\nHigher Certificate in Building Services Engineering / Mechanical Engineering / Electrical Engineering or equivalent\nOver\u00a010\u00a0years\u2019 relevant work experience in Water Supply and Fire Services Installations\nQualified QA Auditor with not less than 3 years' experience in Quality Management/Audit\nHolder of valid certificate for Quality Management Systems Auditor/Lead Auditor Training Course certified by the International Register of Certified Auditors (IRCA)\nRegistered Electrical Worker qualified for Grade A Category 2 Electrical Work\nCompleted Safety Training Course for Site Management Staff provided by CIC\n\nPreferred\n\nGood communications and organization skills\nAttention to detail\u00a0\n\nInterest parties please send your application letter & CV including current and expected salary, date of availability to us.\n\nOnly the shortlisted candidates will be notified. Data collected would be used for recruitment purposes only.", "employment_types": ["Full Time", "Permanent"], "selling_points": ["Senior Engineer to Project Manager (HVAC)", "Macau's project / based HK", "Good command in both English and Cantonese"], "locations": ["Not Specified"], "categories": ["Engineering", "Electrical / Electronics", "Mechanical"], "post_time": "2022-01-18T03:10:26Z", "salary": {"currency": null, "max": null, "min": null, "period": "monthly", "term": null}, "salary_visible": false, "title_keywords": ["senior engineer", "project manager"], "responsibilities": ["management", "data", "systems", "quality", "audit", "site management", "regular review", "specifications", "recruitment"], "requirements": {"degrees": ["certificate", "higher certificate"], "majors": ["electrical engineering", "engineering", "mechanical engineering", "building services", "quality management"], "languages": [], "language_level": [], "hard_skills": [], "soft_skills": ["organization skills", "attention to detail", "responsible"], "languages_combined": []}, "experience_required": {"duration": ["3 years", "10 years"], "field": ["quality management", "audit", "qa"]}}, {"job_id": "100003009048636", "location_code": "hk", "company": "CITIC Telecom International Holdings Limited", "job_title": "Engineer / Engineer Trainee - Network Operations", "description": "What you will do\u00a0\u00a0\n\nThe person will in charge of Quality Circle to ensure all project works are meeting the quality standards. Responsible for identifying problems and suggest possible solutions in eliminating incidents.\n\nHow you will do it\n\nRevise and streamline the process from time-to-time in meeting customers' satisfaction\nEnsure all the work done are carried out in accordance with the project specifications and clients' requirements\nConduct regular review meeting with clients to streamline process and reduce the nuisance\nAttend regular meetings with Project Manager and Contractors\n\nWhat we look for\n\nRequired\n\nHigher Certificate in Building Services Engineering / Mechanical Engineering / Electrical Engineering or equivalent\nOver\u00a010\u00a0years\u2019 relevant work experience in Water Supply and Fire Services Installations\nQualified QA Auditor with not less than 3 years' experience in Quality Management/Audit\nHolder of valid certificate for Quality Management Systems Auditor/Lead Auditor Training Course certified by the International Register of Certified Auditors (IRCA)\nRegistered Electrical Worker qualified for Grade A Category 2 Electrical Work\nCompleted Safety Training Course for Site Management Staff provided by CIC\n\nPreferred\n\nGood communications and organization skills\nAttention to detail\u00a0\n\nInterest parties please send your application letter & CV including current and expected salary, date of availability to us.\n\nOnly the shortlisted candidates will be notified. Data collected would be used for recruitment purposes only.", "employment_types": ["Full Time", "Permanent"], "selling_points": ["With double pay, discretionary bonus & 14 days AL", "Sizable and energetic team", "Fresh graduates are welcome"], "locations": ["Kwai Fong"], "categories": ["Engineering", "Electrical / Electronics", "Telecommunication / Wireless / Radio", "Others", "Student / Fresh Graduate / No Experience"], "post_time": "2022-01-14T06:56:22Z", "salary": {"currency": null, "max": null, "min": null, "period": "monthly", "term": null}, "salary_visible": false, "title_keywords": ["operations", "engineer", "trainee"], "responsibilities": ["management", "data", "systems", "quality", "audit", "site management", "regular review", "specifications", "recruitment"], "requirements": {"degrees": ["certificate", "higher certificate"], "majors": ["electrical engineering", "engineering", "mechanical engineering", "building services", "quality management"], "languages": [], "language_level": [], "hard_skills": [], "soft_skills": ["organization skills", "attention to detail", "responsible"], "languages_combined": []}, "experience_required": {"duration": ["3 years", "10 years"], "field": ["quality management", "audit", "qa"]}}, {"job_id": "100003009055898", "location_code": "hk", "company": "Hays", "job_title": "Project Manager, Smoke Detection/ E&M", "description": "What you will do\u00a0\u00a0\n\nThe team delivers innovative solutions to a wide customer base across all industry segments for\u00a0 BMS\u00a0systems. You will be part of a growing project team of BMS driving new projects or maintaining customer\u2019s facilities.\n\nHow you will do it\n\nAssist Manager in tender preparation, tender analysis and price negotiation\nCoordinate with clients, consultants and sub-contractors for project implementation\nHandle project administration\n\nWhat we look for\n\nRequired\n\nHigher Diploma or Degree in Building Service / Electrical / Mechanical Engineering or equivalent\n2 to10 years\u2019 relevant experiences\n\n\u00a0Preferred\n\nEffective interpersonal, presentation and project management skills\nGood problem solving techniques, organizing and planning ability\nGood spoken and written in English and Chinese\nIndependent and able to work under pressure & tight deadline\nWilling to work on site in various locations\u00a0", "employment_types": ["Full Time", "Permanent"], "selling_points": ["Stable environment", "Competitive Package", "Hong Kong largest construction project"], "locations": ["Not Specified"], "categories": ["Building & Construction", "Building / Construction / QS", "Engineering", "Electrical / Electronics", "Mechanical"], "post_time": "2022-01-18T03:03:53Z", "salary": {"currency": "HKD", "max": 44999, "min": 35000, "period": "monthly", "term": null}, "salary_visible": true, "title_keywords": ["project manager"], "responsibilities": ["price negotiation", "handle project administration", "maintaining", "work under pressure", "systems", "implementation", "tender analysis", "coordinate with clients", "project management", "tender preparation", "planning"], "requirements": {"degrees": ["diploma", "degree"], "majors": ["mechanical engineering"], "languages": ["english", "chinese"], "language_level": ["good"], "hard_skills": ["bms", "project management", "analysis", "problem solving"], "soft_skills": ["independent", "negotiation", "interpersonal", "project management skills", "problem solving", "innovative", "presentation", "work under pressure"], "languages_combined": [{"language": "english", "language_level": ["good"]}, {"language": "chinese", "language_level": ["good"]}]}, "experience_required": {"duration": ["2 to10 years"], "field": []}}, {"job_id": "100003009049361", "location_code": "hk", "company": "HGC Global Communications Limited", "job_title": "Technical Officer \u2013 E&M Facilities", "description": "What you will do:\n\nDynamic, high-energy, highly effective and engaging Sales and Business Development Leader with a strong foundation in sales management and deep industry experience and proven track record for selling large, complex outcome-based solutions as a service offering.\u00a0 The Sales Manager will support the Sales Director to drive customer solutions that lead to deal closure and the development of new products and offerings for Johnson Controls. We are seeking a high achieving, proactive leader who is self-directed, internally motivated and operates with personal integrity.\n\nHow you will do it:\n\n\nAdding customer equity by creating valued business partnerships with c-suite customers; proactively identifying business opportunities for the customer; conveying a firm understanding of the customer\u2019s business and political drivers.\nDeveloping strategic solutions for customers that appropriately consider available facts, constraints, competitive circumstances, strategic priorities, and probable consequences; clearly connecting solutions to business needs\nProvides significant industry expertise and client business acumen. Sells higher level services to the customer, enabling competitive advantage for them in the marketplace. Provides thought leadership and capitalizes on cumulative industry, product, and company-specific experiences. Captures best practices and advises and facilitates the management and movement of information.\nUsing one\u2019s knowledge of economic, financial, market, and industry trends to understand and improve customer results; using one\u2019s understanding of major business functions, industry trends, and own organization\u2019s position to contribute to effective business strategies and/or tactics.\nSells, with minimal supervision, the JCI offerings persuasively, persistently and confidently to building owners and owner representatives at the C-level while reaching optimal profit levels. Particularly focusing on selling performance contracting while ensuring that we achieve maximize share of customers business. \u00a0\nMeet or exceed secured volume target\nMeet or exceed pipeline target\nFocuses on demonstrating value at the executive level by providing solutions to business and financial challenges as well as working through gateways to achieve joint planning status. Sells, renews and expands renewable service agreements, including multi-year agreements, to both new and existing customer.\nBuilds partnering relationships with the economic buyer, owner or owner representatives responsible for the decision making process to drive the solution sales of JCI offerings. Manages ongoing sales process, develops relationship, responds to and anticipates customer needs. Actively listens, probes and identifies concerns. \u00a0\nUnderstands the customer's business and speaks their language. \u00a0\nDemonstrates financial and business acumen to develop credibility, loyalty, trust and commitment.\nSeeks out, targets and initiates contact with prospective customers. \u00a0\nDevelops network of contacts. Understands and leverages sales process checkpoints as well as demonstrates evidence of gaining small trial closes and commitments. \u00a0Qualifies and assesses potential customers. \u00a0Refers leads to other business segments.\nAddresses customer's financial, business, operational and environmental objectives, needs and requirements. \u00a0\nRecommends solutions that match the customer\u2019s business and financial challenges. Differentiates JCI services and products from competitors based on business benefits and knowledge of competitor\u2019s business strategies.\nMaximizes assigned Project Development Engineering resources effectively and efficiently. Ensures the customer and JCI receive maximum value from dedicated and assigned resources. \u00a0Engages appropriate sales support resources determined by the JCI sales and business process, including COE (construction management services), energy and operational engineering and technical support, financial and legal resources, etc.\nEffectively writes, presents and communicates proposals. \u00a0Secures major opportunities through the use of financial agreements. \u00a0\nNegotiates value, addresses resistance when demonstrated, and closes the sale.\nUtilizes applicable sales tools effectively (Salesforce, Account Management, Account Plan and TAS) to plan and document progress as well as increase business opportunity in accounts. \u00a0Leverages JCI sales process monthly checkpoints to gain progressive commitments from the customer.\nManages the sales process steps of the pipeline with a focus on completing the Opportunity Action plan and meeting the milestones in the customer\u2019s buying process.\nLeads the sales team by building and fostering team relationships to ensure customer satisfaction. \u00a0\nSolicits support from and communicates effectively with internal staff. \u00a0Develops relationship with Systems and Service sales organization to exceed customers' expectations.\nOwns and facilitates the customer relationship particularly when selling Performance Contracting initiatives.\nActs as the customer\u2019s advocate in interactions with the JCI organization to ensure the customer obtains the best value from the JCI offerings. \u00a0\nSets appropriate customer expectations on JCI product and service offerings. \u00a0Participates in final project inspection. \u00a0Ensures that the customer is trained and oriented to system operation or the value of services delivered.\nAssists in the development of the team or Area Office Solution sales and marketing plans and strategies. \u00a0Aides in the implementation of these strategies and action plans. \u00a0\nTargets new customers based on vertical market strategies.\nKeeps management informed of progress and account status. \u00a0\nKnows when to call for assistance from upper management to keep the sales process moving.\nAttends and presents at trade show. \u00a0Participates in professional organizations\n\nQualifications:\n\nDegree in Business, Sales, Marketing or Engineering\nKnowledge and experience:\n5+ years sales experience in complex sales in a matrixed environment\nExtensive experience selling to C-suite and negotiating large, financial and complex deal structures\nExperience in energy efficiency and sustainability\nExperience in commercial and industrial industries preferred\nExperience in innovative and sales of new offerings preferred\n\nCompetency Levels:\n\nCompany Specific\n\nBusiness Acumen\n\nKnows how to sell and understand the energy efficiency & sustainability industry\nKnowledgeable in current and possible future policies, practices, trends and information affecting his/her business and organization\nIs aware of how strategies and tactics work in the marketplace.\nCustomer Focus\nActs with customer and business success in mind\nEstablishes and maintains effective relationships with customers and team members and gains their trust and respect\nDrive for Results\nCan be accounted on to exceed goals successfully\nIs constantly and consistently one of the top performers\nAction oriented and timely in guidance and actions\nVery bottom-line oriented\nSteadfastly pushes self and others for results\nStrategic Agility\n\n\u00a0Sees ahead clearly\nCan anticipate future consequences and trends accurately\nHas broad knowledge and perspective\nIs future oriented\nCan articulately paint credible pictures and visions of possibilities and likelihoods\nCan create competitive and breakthrough strategies and plans\nManaging Vision and Purpose\nCommunicates a compelling and inspired vision or sense of core purpose\nTalks beyond today\nTalks about possibilities\nIs optimistic\nCreates mileposts and symbols to rally support behind the vision\nMakes the vision shareable by everyone\nCan inspire and motivate entire units or organisations\n\nJob specific:\n\nAction Oriented\n\nEnjoys working hard\nIs action oriented\nDrives for action and \u201ccloses the loop\u201d in discussions\n\nNegotiating\n\nKnows how to plan and execute negotiations and is skilled in facilitating teams to develop these strategies\nCan negotiate skill-fully in tough situations with both internal and external groups\nCan settle differences with minimum noise; can win concessions without damaging relationships\nCan be both direct and forceful as well as diplomatic\nGains trust quickly of other parties to the negotiations\nHas a good sense of timing\n\nOrganizational\u00a0agility\n\nKnowledgeable about how organisations work and their culture.\nKnows how to get things done both through formal channels and the informal network\nUnderstands the origin and reasoning behind key policies, practices and procedures.\n\nOrganizing\n\nCan co-ordinate resources (people, funding, material, support) to drive towards established goals and be able to establish goals for the business.\nCan orchestrate multiple activities at once to accomplish a goal.\nUses resources effectively and efficiently understanding the drivers of project management.\n\nPresentation Skills\n\nIs effective in a variety of formal presentation settings: one-on-one, small and large groups, with peers, direct reports and bosses.\nIs effective both inside and outside the organization, on both cool data and hot and controversial topics.\nCommands attention and can manage group process during the presentation\nCan change tactics midstream when something isn\u2019t\u00a0working\n\nWritten Communications\n\nIs able to write clearly and succinctly in a variety of communication settings and styles.\nCan get messages across that have the desired effect.\n\nInterest parties please send your application letter & CV including current and expected salary, date by clicking \"Apply Now\".\n\nOnly the shortlisted candidates will be notified. Data collected would be used for recruitment purposes only.", "employment_types": ["Full Time", "Permanent"], "selling_points": ["Certificate in Electrical or related discipline", "1-2 years relevant working experience", "Maintain routine maintenance of site facilities"], "locations": ["Tsing Yi"], "categories": ["Building & Construction", "Building / Construction / QS", "Engineering", "Electrical / Electronics", "Mechanical"], "post_time": "2022-01-14T08:31:42Z", "salary": {"currency": null, "max": null, "min": null, "period": "monthly", "term": null}, "salary_visible": false, "title_keywords": ["technical officer"], "responsibilities": ["management", "business opportunities", "developing", "develop", "contracting", "contact", "sales management", "planning"], "requirements": {"degrees": [], "majors": [], "languages": [], "language_level": [], "hard_skills": ["small", "c", "dynamic", "acumen"], "soft_skills": ["responsible", "deep", "integrity", "motivated", "dynamic", "business acumen", "proactive", "leadership", "decision making"], "languages_combined": []}, "experience_required": {"duration": [], "field": ["management", "business development"]}}, {"job_id": "100003009047417", "location_code": "hk", "company": "Shun Cheong Electrical Engineering Co Ltd", "job_title": "Assistant Engineer (BSE/FS/ELL/ELV/ME)", "description": "What you will do\n\nThis person will join the ACVS team in Hong Kong. He/she will\n\n\nMajority to develop sales opportunities for\u00a0Digital Solutions market segment from property developers, end users, E&M consultants and stakeholders operating in Hong Kong and Macau\nAct as the single point of contact for sales and support the growth for Digital Solutions market from property developers, end-users, E&M consultants and stakeholders\nManage the existing relationship with potential customers\nLine up internal resources from different business units to support growth of Digital Solutions revenue\nHow you will do it\n\nAssist business units in achieving growth targets\n\nCoordination of sales and follow up activities\nCreate cross sales activities to ensure both groups are working effectively to meet property developers, end-users, E&M consultants, key account customers and stakeholders expectations\nAssist the sharing of potential customers' local standards and ensure consistency in new works and service maintenance, where global team will keep Digital Solutions information updated\nWhat we look for\n\n\nRequired\n\nMinimum 2 years' sales experience in Building Solutions (BMS, HVAC, Energy, ELV)\nExperiences in customer account management will be an advantage\nGood oral, written and presentation skills with ability to present to senior executives\nCustomer focus and follow up activities oriented\nGood command of spoken and written English and Chinese\nPreferred\n\nExperience in operation from multi-national corporations\nGood connections with property developers, E&M consultants preferred\nIndependent and able to work under pressure\nExperience in facilities, energy savings, smart city preferred\nHands on computer knowledge of MS Office\nInterest parties please send your application letter & CV including current and expected salary, date of availability to us.\n\nOnly the shortlisted candidates will be notified. Data collected would be used for recruitment purposes only.", "employment_types": ["Full Time", "Permanent"], "selling_points": ["BEng / H.Dip in BSE, EE, ME, FS, CIVIL, & ext.", "Overall project operations & co-ordination", "Fresh graduates are welcomed"], "locations": ["Lai Chi Kok"], "categories": ["Engineering", "Electrical / Electronics", "Engineering Project Management", "Mechanical"], "post_time": "2022-01-14T03:01:56Z", "salary": {"currency": null, "max": null, "min": null, "period": "monthly", "term": null}, "salary_visible": false, "title_keywords": ["assistant engineer"], "responsibilities": ["sales activities", "management", "maintenance", "data", "develop", "recruitment", "contact", "coordination", "work under pressure"], "requirements": {"degrees": [], "majors": [], "languages": ["english", "chinese"], "language_level": ["good command"], "hard_skills": ["maintenance", "hvac", "bms", "focus", "ms office"], "soft_skills": ["oral", "independent", "presentation skills", "hands on", "coordination", "customer focus", "work under pressure"], "languages_combined": [{"language": "english", "language_level": ["good command"]}, {"language": "chinese", "language_level": ["good command"]}]}, "experience_required": {"duration": ["minimum 2 years"], "field": ["operation", "account management"]}}, {"job_id": "100003009055418", "location_code": "hk", "company": "Meinhardt (Hong Kong) Limited", "job_title": "Resident Building Services Inspectors (Ref: 21721T2)", "description": "We are seeking a professional, outcome and solution oriented, self-reliant and self-motivated individual with high experience in estimating and delivering complex and integrated security solutions to commercial customers to lead the ELV (IBMS, Fire & Security) and Networking Pre-sale design and estimation for Hong Kong.\n\nWhat you will do:\n\nHelp sales team win profitable deals by providing technical design and estimation expertise and leadership in complex security solutions. Responsible for providing direction for ELV (IBMS, Fire & Security) and Networking business sales support resources across Hong Kong assigned to his/her group, including the project planning, design, estimation and documentation of JCI projects. Maintains engineering integrity of all projects, ensures quality, on-time and standardized delivery of proposals. Collaborates with ELV Domain, IBMS, Fire, Security and Networking domain sales leaders across Hong Kong and come up with advanced solutions for the customers. Works with other CoE Managers to ensure timely and accurate completion of all CoE related functions.\n\nHow you will do it:\n\nPlans, implements and manages the activities of the CoE team responsible for the timely and profitable design and pricing of IBMS, Fire, Security and Networking solutions sales estimates.\nIn conjunction with the CoE leadership team, develops and maintains the long term sales support strategy.\nImplements standardized best practices and tools across HK IBMS, Fire, Security and Networking pre-sale design and estimation teams.\nWorks with JCI Sales Managers, Consultants, and Architects to come up with accurate pre-sale design solutions and estimation for the opportunity\nComplements sales force by developing value added engineering designs to varied applications of systems providing the best competitive solution\nEnsures consistency of field installation delivery through proper hand-off of design plans and other documents as required.\nEstablishes and maintains a high level of quality design functionality to customers for maximum retention.\nWorks with Training Manager and Products team to ensure CoE team capabilities and certification levels on the both JCI and Local offerings to match sales initiatives and goals.\nHiring and Staffing.\n\nWhat we look for:\n\nProven team leader capabilities and supervision experience in dealing with large integrated IBMS, Fire, Security and Networking projects and programs.\nExcellent OEM / Vendor local connect.\nCustomer focus and service oriented, Excellent people skills, persuasive and ability to make decisions individually and as part of a team\nExcellent oral, written and presentation skills with ability to present to senior level executives & Entrepreneurial attitude, leadership abilities and ability to be a team player at all levels.\nWork closely with the sales team, help them in attending customer meeting and increase the win rate.\nAbility to influence customers.\nExpertise in codes and standards\nMultiple language skills preferred (English and another)\nDemonstrated problem solving ability.\nUp to 50% Travel\n\nInterest parties please send your application letter & CV including current and expected salary, date of availability by clicking \"Apply Now\"\n\nOnly the shortlisted candidates will be notified. Data collected would be used for recruitment purposes only.", "employment_types": ["Full Time", "Contract"], "selling_points": [], "locations": ["Not Specified"], "categories": ["Building & Construction", "Building / Construction / QS", "Engineering", "Electrical / Electronics", "Mechanical"], "post_time": "2022-01-18T02:31:11Z", "salary": {"currency": null, "max": null, "min": null, "period": "monthly", "term": null}, "salary_visible": false, "title_keywords": [], "responsibilities": ["installation", "project planning", "documentation", "design solutions", "data", "systems", "quality", "teams", "design", "developing", "sales team", "recruitment", "providing direction", "plans"], "requirements": {"degrees": [], "majors": [], "languages": ["english"], "language_level": [], "hard_skills": ["sales support", "vendor", "problem solving", "make", "documentation", "focus", "codes"], "soft_skills": ["self-motivated", "oral", "persuasive", "advanced", "responsible", "timely", "integrity", "problem solving", "presentation skills", "customer focus", "team player", "accurate", "leadership"], "languages_combined": [{"language": "english", "language_level": []}]}, "experience_required": {"duration": [], "field": ["design", "commercial", "security", "sale", "team"]}}, {"job_id": "100003009048341", "location_code": "hk", "company": "ST Engineering Infa Systems Limited", "job_title": "System Engineer / Installation Engineer x 5", "description": "What you will do\n\nThis is an excellent opportunity to join the world class and high technology company in physical security industry.\n\nThis person will join the Security Products sales team in Hong Kong. He/she will cover North Asia region including Hong Kong, Macau, Taiwan, Japan, South Korea, and Mongolia.\n\nThis position reports directly to the Regional Sales Director of North Asia based in Hong Kong.\n\nHow you will do it\n\nAs the Technical Sales Specialist, he/she needs to have experience in technical account management. He/she will be the key technical point of contact for customers, provide technical advice and demonstrating our solutions. He/she will be responsible to identify the go-to-market strategies and to lead the corresponding stakeholders to meet the business objective.\n\nUnderstand the market trend and work with product management teams to come out with the appropriate technical solution/ planning for the market\nProduct / Solution testing before the official release to the markets, work with global R&D and engineering teams closely\nCreate demand through demonstration and engagement with end-users / consultants / architects\nProvide excellent customer service through engagement and dedication to customer satisfaction\n\nWhat we look for\n\nRequired\n\nBachelor\u2019s Degree preferably in engineering, networking, or IT\nMinimum 3 years of electronics / IT customer facing experience\nGood knowledge about the physical security market and technologies\nExcellent communication and presentation skills\nStrong IP networking knowledge\nFluent in English and Cantonese, and conversational Mandarin\nStrong personality, self-motivated, flexible to business demands and can work under pressure\nAble to travel overseas and work independently\nPassionate candidate with less experience will also be considered\nInterest parties please send your application letter & CV including current and expected salary, date of availability to\u00a0our email address on the top\u00a0or click \"APPLY NOW\".\n\n\nOnly the shortlisted candidates will be notified. Data collected would be used for recruitment purposes only.\u00a0", "employment_types": ["Full Time", "Permanent", "Contract"], "selling_points": [], "locations": ["North Point"], "categories": ["Engineering", "Electrical / Electronics", "Information Technology (IT)", "Testing / QA", "Others", "Student / Fresh Graduate / No Experience"], "post_time": "2022-01-14T06:29:00Z", "salary": {"currency": null, "max": null, "min": null, "period": "monthly", "term": null}, "salary_visible": false, "title_keywords": ["system engineer", "engineer"], "responsibilities": ["management teams", "management", "data", "work under pressure", "technical advice", "teams", "testing", "communication", "customer service", "sales team", "contact", "reports", "recruitment", "planning"], "requirements": {"degrees": ["degree", "bachelor"], "majors": ["it", "engineering"], "languages": ["cantonese", "english", "mandarin"], "language_level": ["conversational", "fluent"], "hard_skills": ["r&d", "ip", "go"], "soft_skills": ["flexible", "passionate", "self-motivated", "work independently", "responsible", "communication", "presentation skills", "customer service", "work under pressure"], "languages_combined": [{"language": "cantonese", "language_level": ["fluent"]}, {"language": "english", "language_level": ["conversational", "fluent"]}, {"language": "mandarin", "language_level": ["fluent"]}]}, "experience_required": {"duration": ["minimum 3 years"], "field": ["it", "account management"]}}, {"job_id": "100003009048055", "location_code": "hk", "company": "Edwin McAuley Electronics Ltd", "job_title": "Senior Electronic Engineer/ Electronic Engineer (Welcome Fresh graduates)", "description": "What you will do\n\nThe candidate will be managing the Service Business (including HVAC, BMS and Fire & Security services) of the company in HK and Macau. This role is expected to deliver superb maintenance and service solutions to a wide customer base across all industry segments.\n\n\u00a0How you will do it\n\nSet and execute strategies to grow HVAC, BMS and Fire & Security services businesses\nAchieve annual secured order, revenue and margin target in accordance with Company\u2019s objectives and direction\nManage service teams to provide preventive maintenance services and repair work for systems at customer sites; and testing and commissioning of systems installed by others\nCoordinate with Sales team to prepare maintenance and repair proposals and tenders\nDevelop and maintain key customer relationships with professional knowledge and excellent service quality\nHandle customer complaints and direct service managers to resolve issues\nManage subcontractors to achieve healthy partnership\nEnsure quality of work to the satisfaction of customer\nStrengthen relationships with customers to secure more orders\nEnsure teams adhering to the compliance of EHS, Ethics Code and Company policies in all work sites\n\nWhat we look for\n\nRequired\n\nDegree holder in Building Services or engineering-related disciplines\nMinimum 20 years\u2019 HVAC, BMS and Fire & Security services experience, of which at least 10 years at managerial level\nStrong technical knowledge and experience in HVAC, BMS and Fire & Security Systems\nExperience in tracking performance of service teams\nCompetency in project planning and have strong leadership skills\u00a0\n\nPreferred\n\nGood communication and interpersonal skills\nProficient in English and Chinese\nAbility to travel, learn and train up others\nGood problem-solving techniques, organizing and planning ability\nIndependent and able to work under pressure and tight deadline\nPrior experience with government maintenance contracts is a plus\n\n", "employment_types": ["Full Time", "Permanent"], "selling_points": ["Knowledge in electronic component applications", "Experience in embedded software or MCU system", "5-day work week, mid-year bonus & double pay"], "locations": ["North Point"], "categories": ["Engineering", "Electrical / Electronics", "Manufacturing & Production", "Manufacturing", "Product Development / Management"], "post_time": "2022-01-14T04:37:08Z", "salary": {"currency": null, "max": null, "min": null, "period": "monthly", "term": null}, "salary_visible": false, "title_keywords": ["senior electronic engineer", "electronic engineer"], "responsibilities": ["quality", "communication", "maintain", "work under pressure", "contracts", "compliance", "teams", "testing", "develop", "commissioning", "customer complaints", "coordinate with", "tracking", "project planning", "maintenance", "policies", "systems", "repair", "sales team", "maintenance services", "planning"], "requirements": {"degrees": ["degree holder"], "majors": ["related disciplines", "building services", "engineering"], "languages": ["english", "chinese"], "language_level": ["proficient"], "hard_skills": ["plus", "maintenance", "hvac", "problem-solving", "bms", "code"], "soft_skills": ["independent", "problem-solving", "leadership skills", "communication and interpersonal skills", "work under pressure"], "languages_combined": [{"language": "english", "language_level": ["proficient"]}, {"language": "chinese", "language_level": ["proficient"]}]}, "experience_required": {"duration": ["at least 10 years", "minimum 20 years"], "field": ["managerial", "security", "maintenance"]}}, {"job_id": "100003009049594", "location_code": "hk", "company": "Fortune Link Engineering Co Ltd.", "job_title": "Engineer / Assistant Engineer(s) (MVAC or Electrical)", "description": "What you will do\u00a0\u00a0\n\nThe team delivers innovative solutions to a wide customer base across all industry segments for HVAC, FS and BMS systems. You will be part of a growing project / service team of HVAC, FS and BMS driving new projects or maintaining customer\u2019s facilities.\n\nHow you will do it\n\nAssist Manager in tender preparation, tender analysis and price negotiation\nCoordinate with clients, consultants and sub-contractors for project implementation\nHandle project administration\n\nWhat we look for\n\nRequired\n\nHigher Diploma or Degree in Building Service / Electrical / Fire Services / Mechanical Engineering or equivalent\n2 to10 years\u2019 relevant experiences\n\n\u00a0Preferred\n\nEffective interpersonal, presentation and project management skills\nGood problem solving techniques, organizing and planning ability\nGood spoken and written in English and Chinese\nIndependent and able to work under pressure & tight deadline\nWilling to work on site in various locations\u00a0\n\nWhat we offer\n\nExcellent career growth opportunity\nAnnual Leave, Birthday Leave and Marriage Leave\nMedical, Dental and Life Insurance\nEducation Subsidy\nOn-job Training\nDiscretionary Bonus\n\nInterest parties please send your application letter & CV including current and expected salary, date of availability to us.\n\nOnly the shortlisted candidates will be notified. Data collected would be used for recruitment purposes only.", "employment_types": ["Full Time", "Permanent"], "selling_points": [], "locations": ["Not Specified"], "categories": ["Engineering", "Electrical / Electronics", "Engineering Project Management", "Others"], "post_time": "2022-01-14T08:55:02Z", "salary": {"currency": null, "max": null, "min": null, "period": "monthly", "term": null}, "salary_visible": false, "title_keywords": ["engineer", "assistant"], "responsibilities": ["price negotiation", "handle project administration", "maintaining", "work under pressure", "systems", "implementation", "tender analysis", "coordinate with clients", "project management", "tender preparation", "planning"], "requirements": {"degrees": ["diploma", "degree"], "majors": ["mechanical engineering"], "languages": ["english", "chinese"], "language_level": ["good"], "hard_skills": ["hvac", "analysis", "bms", "project management", "problem solving"], "soft_skills": ["independent", "negotiation", "interpersonal", "project management skills", "problem solving", "innovative", "presentation", "work under pressure"], "languages_combined": [{"language": "english", "language_level": ["good"]}, {"language": "chinese", "language_level": ["good"]}]}, "experience_required": {"duration": ["2 to10 years"], "field": []}}, {"job_id": "100003009050346", "location_code": "hk", "company": "Chicony Power Technology Hong Kong Limited", "job_title": "Senior Electronic Engineer", "description": "Responsibilities:\n\nConceptual design of power conversion circuit by calculation and simulation\nBuild and test sample to prove concept\nGenerate test report for Engineering verification\nCreate test plan for production\nSupport production and tackle manufacturing issues\n\nRequirements:\n\nHolder of Degree in Electronic Engineering or equivalent\n5+ years solid experience in Switched Mode Power Supply design & development\nExtensive knowhow of electronic components for power supply design\nInterested in doing power conversion research\nDigital power control experience is preferred\nGood communication skill with customers and internal team members\nProficient in English, Cantonese & Putonghua\nCandidate with less experience will be considered as Electronic Engineer\u00a0\n\nWe offer:\n\n5 days work, public holidays, medical benefit, double pay and performance bonus\n\nInterested parties please send detailed resume with present & expected salary by clicking\u00a0\"APPLY NOW\".", "employment_types": ["Full Time", "Permanent"], "selling_points": ["Degree in Electronic Engineering or equivalent", "5 days work, public holidays, double pay", "Switched Mode Power Supply"], "locations": ["Shatin Area"], "categories": ["Engineering", "Electrical / Electronics", "Others", "Sciences, Lab, R&D", "Research & Development (R&D)"], "post_time": "2022-01-14T10:30:29Z", "salary": {"currency": null, "max": null, "min": null, "period": "monthly", "term": null}, "salary_visible": false, "title_keywords": ["senior electronic engineer"], "responsibilities": ["plan", "design", "report"], "requirements": {"degrees": ["degree"], "majors": ["engineering"], "languages": ["cantonese", "putonghua", "english"], "language_level": ["proficient"], "hard_skills": [], "soft_skills": ["communication skill", "interested in", "extensive"], "languages_combined": [{"language": "cantonese", "language_level": ["proficient"]}, {"language": "putonghua", "language_level": ["proficient"]}, {"language": "english", "language_level": ["proficient"]}]}, "experience_required": {"duration": ["5+ years"], "field": ["development", "design", "digital"]}}, {"job_id": "100003009046171", "location_code": "hk", "company": "Pyrofoe Engineers Ltd", "job_title": "Assistant Engineer", "description": "1-2 years experience min. in Fire Services Installation\nCan work independently\nRequire full-time on site\nGood at ACAD\nHK$20,000-23,000\nApplicant is required to send CV and expected salary to Pyrofoe Engineers Ltd (\u885b\u5b89\u5de5\u7a0b\u6709\u9650\u516c\u53f8) by fax 2385 2150 or email via \"Apply Now\"\u00a0for interview arrangement.", "employment_types": ["Full Time", "Permanent"], "selling_points": [], "locations": ["Not Specified"], "categories": ["Building & Construction", "Building / Construction / QS", "Engineering", "Electrical / Electronics", "Others"], "post_time": "2022-01-13T10:23:07Z", "salary": {"currency": null, "max": null, "min": null, "period": "monthly", "term": null}, "salary_visible": false, "title_keywords": ["assistant engineer"], "responsibilities": ["installation", "interview arrangement"], "requirements": {"degrees": [], "majors": [], "languages": [], "language_level": [], "hard_skills": [], "soft_skills": ["work independently"], "languages_combined": []}, "experience_required": {"duration": ["1-2 years"], "field": []}}, {"job_id": "100003009049508", "location_code": "hk", "company": "Jones Lang LaSalle Ltd", "job_title": "Engineer", "description": "About JLL \u2013\u00a0\n\nWe\u2019re JLL. We\u2019re a professional services and investment management firm specializing in real estate. As a Fortune 500 company, we help real estate owners, occupiers and investors achieve their business ambitions.\u00a0\n\nIf you\u2019re looking to step up your career, JLL is the perfect professional home. With us, you\u2019ll have a chance to innovate with the world\u2019s leading businesses, put that expertise into action on landmark projects, and work on game-changing real estate initiatives. You\u2019ll also make long-lasting professional connections and be inspired by the best. We\u2019re focused on opportunity and want to help you make the most of yours. Achieve your ambitions - join us at JLL!\u00a0\n\nAbout the role:\u00a0\n\nCommitment to facility operations excellence\n\nDo you have superior technical know-how when it comes to maintaining a facility? Let\u2019s talk! We always welcome people who can carry our torch for superior quality service.\n\nIn this role, you\u2019ll be our go-to guy when it comes to managing our site\u2019s daily operations and technical issues, providing effective solutions whenever difficulties arise. Are you well-versed in workplace safety? As we\u2019ll rely on you to develop and carry out an elaborate preventative program for managing sites. You\u2019ll also make sure that all essential site activities\u2014including the maintenance of electrical, mechanical, chemical, fire protection systems and equipment\u2014are performed in a safe and efficient manner; complying with policies and requirements set out by the government, our client and our own management teams. Your expertise in critical environment procedures may also help you land this job.\n\nPerformance Excellence\n\nAre you driven by performance metrics? We find that the best working relationships are fostered by meeting (and exceeding) our service level agreements.\u00a0 This will also be part of your DNA!\u00a0 Working as part of a larger team, you will be involved in ensuring all key performance indicators are met, as set out in the management contract.\n\nChampioning Improvement\n\nDo you get excited by improvement works? As part of a larger team, you will be involved in launching various improvement and savings programmes that will benefit both us and our clients. For example, you will be involved in the implementation of energy management programmes to help cut utilities costs and eliminate wastages.\n\nThis will involve working closely with our vendors, coordinating with them on a variety of projects\u2014from beginning to end. You\u2019ll see to it that our vendors are managed accordingly, and that technical and safety audits and repairs are in sync with the projects\u2019 timeline.\n\nPutting best practices in place\n\nDo you like sharing ideas to improve the work process? As our facilities engineer, you\u2019ll contribute to the creation of engineering service delivery standards. You\u2019ll also help in the planning, implementation and review of site-specific processes and protocols.\n\nTeamwork should also be one of your strongest points, as you\u2019ll work with a team to ensure that all performance targets set out in the contract are being met. To do this, you\u2019ll develop tools that help measure the technical team\u2019s performance on a quarterly or annual basis.\n\nSound like you? To apply you will have:\n\nA technical hands on expert\n\nAn ideal candidate would have a university degree or professional qualification in engineering or facilities management, and over four years\u2019 experience in facilities operation. A strong background in troubleshooting processes is a big plus.\n\nGood communicator\n\nDo you have an excellent command of spoken and written English and Chinese language? Can you communicate technical issues to less able colleagues, clients and vendors? If you said yes to these, bring your ambition and explore our world of possibility.\n\nWhat you can expect from us\n\nWe\u2019re an entrepreneurial, inclusive culture. We succeed together - across the desk and around the globe. We believe the best inspire the best, so we invest in supporting each other, learning together and celebrating our success.\n\nOur Total Rewards program reflects our commitment to helping you achieve your ambitions in career, recognition, well-being, benefits and pay. We\u2019ll offer you a competitive salary and benefits package.\n\nWith us, you\u2019ll develop your strengths and enjoy a career full of varied experiences. We can\u2019t wait to see where your ambitions take you at JLL.\n\nApply today!", "employment_types": ["Full Time", "Permanent"], "selling_points": ["Building Services / Electrical / Mechanical", "Facilities Management", "Preventive Maintenance / Corrective Maintenance"], "locations": ["Mong Kok"], "categories": ["Building & Construction", "Building / Construction / QS", "Engineering", "Electrical / Electronics", "Property / Real Estate", "Property Management"], "post_time": "2022-01-14T08:46:27Z", "salary": {"currency": null, "max": null, "min": null, "period": "monthly", "term": null}, "salary_visible": false, "title_keywords": ["engineer"], "responsibilities": ["ideas", "site activities", "operations", "quality", "troubleshooting", "costs", "management teams", "service delivery", "maintaining", "implementation", "develop", "management", "review", "procedures", "daily operations", "audits", "maintenance", "policies", "systems", "performance metrics", "working relationships", "planning"], "requirements": {"degrees": ["university degree"], "majors": ["engineering"], "languages": ["english", "chinese"], "language_level": ["excellent"], "hard_skills": ["plus", "maintenance", "make", "safe", "facilities management", "go"], "soft_skills": ["efficient", "ideal", "focused", "teamwork", "troubleshooting", "hands on", "learning", "communicator", "driven", "superior"], "languages_combined": [{"language": "english", "language_level": ["excellent"]}, {"language": "chinese", "language_level": ["excellent"]}]}, "experience_required": {"duration": ["four years"], "field": ["management", "operation", "engineering"]}}, {"job_id": "100003009047859", "location_code": "hk", "company": "Bond West Consultants", "job_title": "Technical Sales Engineer/ Senior Key Account Sales Executive (Electronic Components)", "description": "(Ref Number: jobs@0114a_mc)\n\nOur client, a\u00a0PCB/ Electronic component mfg is now looking for high caliber candidates as follows:\n\nTechnical Sales Engineer (20-28K + Commission, depends on exp.) /\u00a0Senior Key Account Sales Executive\n\nResponsibilities:\n\nDevelop Electronic Component in Hong Kong and Southern China market\nIdentify the market trends and customer needs\nIdentify new business opportunities to achieve continuous growth\nDevelop with sales and market strategy\nBuild company reputation and brand in the region\nBe responsible for sales activities, including customer/ site visit\nMaintaining strong relationship with key suppliers\nReporting to District manager and working in all aspects of marketing events\nTravel to southern china if need\nRequirements:\n\nDiploma in Electronics/Electrical or other related\nAt least 1 year experience in Electronic Components, Sales exp. is a plus\nKnowledge of EMC Components/ Power Magnetics/ Capacitors/ passive components is a must\nExcellent verbal and written communication skills\nProficiency in English and Mandarin\nFresh gradutes also welcomed.\nPlease send in your full resume with last drawn, expected salary and availability\u00a0to Bond West Application Email Address\u00a0\"Click Here\"\u00a0or via\u00a0\"APPLY\" button.\n\n\nFor any query, please feel free to contact\u00a0Ms Chan at 2957 8251.\nFor more job opportunity, please visit our website:\u00a0www.bondwest.com.hk\n(Data collected is only for recruitment purpose)", "employment_types": ["Full Time"], "selling_points": ["PCB, Electronic component sales", "5 days job with performance bonus", "Electronics/ Electrical edu background is a must"], "locations": ["Wong Tai Sin Area"], "categories": ["Engineering", "Electrical / Electronics", "Engineering Project Management", "Sales, CS & Business Devpt", "Technical Sales / Sales Engineer"], "post_time": "2022-01-14T04:03:41Z", "salary": {"currency": null, "max": null, "min": null, "period": "monthly", "term": null}, "salary_visible": false, "title_keywords": ["sales executive", "sales engineer"], "responsibilities": ["sales activities", "reporting", "marketing events", "maintaining", "business opportunities", "develop"], "requirements": {"degrees": ["diploma"], "majors": [], "languages": ["english", "mandarin"], "language_level": ["proficiency"], "hard_skills": ["plus"], "soft_skills": ["communication skills"], "languages_combined": [{"language": "english", "language_level": ["proficiency"]}, {"language": "mandarin", "language_level": ["proficiency"]}]}, "experience_required": {"duration": ["at least 1 year"], "field": []}}, {"job_id": "100003009051175", "location_code": "hk", "company": "Aecom Asia Company Limited", "job_title": "Resident Building Services Engineer (RBSE)", "description": "Duties and Responsibilities List of the Resident Building Services Engineer Seconded from the Building Services Designer\n\nThe Building Services Designer shall second a full-time Resident Building Services Engineer (RBSE) \u00a0on site to provide supervision of the building services and electrical and mechanical works. The Resident Building Services Engineer shall be a Registered Professional Engineer in Hong Kong under the Engineers Registration Ordinance and a corporate member of the Hong Kong Institution of Engineers (HKIE) in the Building Services Engineering or Electrical Engineering or Mechanical Engineering Discipline, or other professional institution acceptable by the Client, with at least 5 years' relevant post-professional qualification experience (i.e. corporate member of the HKIE \u2013 Building Services Engineering or Electrical Engineering or Mechanical Engineering Discipline or other professional institution acceptable by the Client) in the supervision and coordination of construction projects. The RBSE should be full time on site starting from 6 months before the commencement of the superstructure works until the defects date.\n\n\n\nDuties and Responsibilities\n\nThe RBSE shall follow the instruction from the Project Manager (PM) or its delegates. The responsibilities of RBSE shall mainly focus on quality control and to resolve issues between design and site works of building services and E&M installations, and follow the accepted Site Supervision Plan of the Site Supervisory Team.\u00a0\u00a0 The duties and responsibilities of the RBSE shall include, but not limited to, the followings: -\n\nto oversee, inspect, test and examine the materials used, the workmanship, the installation method and procedure employed by the Contractor for all building services and E&M works (or named as BS works), including works manufactured / fabricated off site with the assistance of the site supervisory staff;\nto check and ensure the materials used and workmanship employed by the Contractor for all building services and E&M works are in compliance with the Client's Requirements (CR), specification, drawings, approved design and construction procedures and testing and commissioning procedures;\nto check and ensure only the approved design drawings and specification are used for installation / construction;\nto identify defective or substandard building services and E&M works, materials and workmanship which do not comply with the CR, specifications, drawings, accepted design construction procedures and testing and commissioning procedures, and to co-ordinate and witness the performance of appropriate tests and remedial works on the defective or substandard building services and E&M works;\nto communicate among the Designers, the Contractor, user departments, the Project Manager and its delegates the site technical staff, the Building Services Co-ordinator(s), the Testing and Commissioning Team and the BS Designer, etc on building services and E&M related matters, in connection with the Site Agent on builder's work and RSS on other disciplines;\nto resolve and report design or installation problems or site difficulties in building services and E&M works on site arising from unforeseen circumstances;\nto communicate and liaise with relevant parties to ensure the works are carried out in accordance with the accepted time schedule and drawings;\nto communicate with the representatives of the PM and to submit monthly report to the PM on progress and quality of building services works and E&M works;\nto report to the Project Manager and its delegates immediately any issues that affect time and quality of the works that need the special attention of the PM or the delegates of the PM together with any remedial solution proposed;\nto ensure the building services and E&M works to progress with minimum disruption, and in cases of action involving variations to design, consult the BS Designer and report to the Project Manager or its delegates;\nto oversee site records on building services and E&M works, and co-ordinate the checking of building services works with the assistance of site supervisory team;\nto monitor the progress of work, and to produce timely information in advance of construction / installation to avoid delay;\nto participate in resolving any dispute arising from utility companies, building services and E&M subcontractors, other contractors, user departments and other government departments on issues relating to building services and E&M;\nto review and fine tune the design drawings to match with the actual site condition;\nto forecast site supervision resources requirements for building services and E&M works and advise the PM on the appropriate planning and action plans to optimize utilization of the resources;\nto monitor, witness and check all the testing and commissioning works and to keep proper record with the assistance of site supervisory team;\nto monitor the co-ordination of building services and E&M works requirements in connection with builder's works, report on the consequential changes to the building services and E&M design, and produce sketch plans and working drawings and to resolve site problems with design solution;\nto check, supervise and inspect all Temporary Works, interfacing works, existing building services and utilities termination, decommissioning and diversion works as required in this contract;\nto attend regular and ad hoc meetings;\u00a0\nto assist the preparation of design, estimate and specification in collaboration with the allied disciplines;\nto assist the Project Manager or its delegates in the investigation, and prepare report on the acceptance or otherwise of the use of materials, installations and testing & commissioning works;\nto assist in the monitoring and reporting of the performance of the building services and E&M Specialist Subcontractors in relation to all aspects involved in Chapter 4 of the Contractor Management Handbook;\nto supervise and manage the site supervisory staff of the building services & E&M team;\nto provide input to the preparation of the Quality Plan, that is submitted by the Contractor to substantiate the fulfillment of Enhanced Quality Supervision and Assurance Plan for building services works, for site supervision and inspection;\nto check and ensure only accepted shop drawings and materials/equipment are used for construction;\nto participate in the regular site safety, health and environmental checking;\nto participate in the site environmental compliance checking;\nto undertake any other duties in connection with the site construction activities as and when required by the Project Manager and its delegates;\nto properly record and maintain all relevant correspondences for compliance of ISO 9001, ISO 14001, OHSAS 18001 per all ArchSD's internal manuals and other government audit standards; and\nto report any incidents/ reportable accidents on site to the PM as per ArchSD and DEVB's requirements\n\n\n", "employment_types": ["Full Time", "Contract"], "selling_points": ["At least 5 years' relevant experience", "RPE & MHKIE in relevant discipline", "On site to supervise BS & E&M works"], "locations": ["Chai Wan"], "categories": ["Engineering", "Electrical / Electronics", "Mechanical", "Building & Construction", "Others"], "post_time": "2022-01-15T04:05:19Z", "salary": {"currency": null, "max": null, "min": null, "period": "monthly", "term": null}, "salary_visible": false, "title_keywords": ["building services engineer"], "responsibilities": ["any other duties", "fulfillment", "quality", "audit", "design", "drawings", "maintain", "plan", "monthly report", "liaise with", "plans", "ad hoc", "compliance", "monitor", "bs", "testing", "schedule", "forecast", "report", "installation", "prepare report", "reporting", "commissioning", "management", "design drawings", "review", "procedures", "checking", "investigation", "monitoring", "inspection", "specifications", "quality plan", "communicate with", "site supervision", "provide supervision", "coordination", "quality control", "planning"], "requirements": {"degrees": [], "majors": [], "languages": [], "language_level": [], "hard_skills": ["focus", "the hong kong institution of engineers", "hkie"], "soft_skills": ["focus", "timely", "coordination"], "languages_combined": []}, "experience_required": {"duration": ["at least 5 years"], "field": ["building services", "engineering"]}}, {"job_id": "100003009051809", "location_code": "hk", "company": "Hong Kong Applied Science and Technology Research Institute Company Limited (ASTRI)", "job_title": "Senior Engineer (PI) /Engineer (PI), ASIC Design", "description": "Reference#:\u00a02021/ART/329CP/a-d\nJob Responsibilities\nAssist in ITF R&D project as assigned\nDevelop digital circuit hardware\nPrepare testing data for the deliverables\nRequirements\nGraduate in STEM-related discipline such as Computer Science, Electronic Engineering, Information Engineering and Mathematics or relevant discipline\nA bachelor\u2019s degree, master\u2019s degree or a doctoral degree\u2019s holder is welcome to apply\nFor bachelor\u2019s degree holder, they will be considered for the position of Engineering Associate (PI)\nExperience in digital circuit design and hardware description language will be an advantage\nExperience in cadence simulation tools Xcelium is a plus\nGood command of written and spoken English or Chinese\nApplication\n\nTo apply, by clicking 'APPLY NOW'\u00a0\u00a0with your resume, you must quote the\u00a0Job Ref\u00a0and include the following information:\n\nName of University\nDegree obtained/expecting and when\nHave you participated in ITF Research Talent Hub before? Yes/No\nIf you answer Yes in item 3, please state the period\nHave you been employed by ASTRI before? If yes, please state the period\n\nThe resume should\u00a0not\u00a0include any sensitive personal information such as HKID or passport number, photo, etc.\n\nThe application will be open until the position is filled. Only short-listed candidates will be notified. ASTRI reserves the right not to fill the position.\n\nASTRI is an Equal Opportunities Employer. Personal data provided by job applicants will be used\u00a0exclusively\u00a0for recruitment\u00a0only. For details, please refer to\u00a0Privacy - ASTRI - Hong Kong Applied Science and Technology Research Institute Company Limited,\u00a0in particular section 9.", "employment_types": ["Full Time", "Contract"], "selling_points": ["Five-Day Work Week, involve R&D projects", "Medical Insurance Provided", "Stable working environment"], "locations": ["Shatin Area"], "categories": ["Engineering", "Electrical / Electronics", "Sciences, Lab, R&D", "Research & Development (R&D)", "Others", "Student / Fresh Graduate / No Experience"], "post_time": "2022-01-17T01:14:31Z", "salary": {"currency": null, "max": null, "min": null, "period": "monthly", "term": null}, "salary_visible": false, "title_keywords": ["senior engineer", "engineer"], "responsibilities": ["hardware", "data", "testing", "develop"], "requirements": {"degrees": ["degree holder", "degree", "bachelor", "master"], "majors": ["engineering"], "languages": ["english", "chinese"], "language_level": ["good command"], "hard_skills": ["no", "hardware", "plus"], "soft_skills": ["sensitive"], "languages_combined": [{"language": "english", "language_level": ["good command"]}, {"language": "chinese", "language_level": ["good command"]}]}, "experience_required": {"duration": [], "field": ["digital", "design"]}}, {"job_id": "100003009045607", "location_code": "hk", "company": "RNB Engineering Hong Kong Limited", "job_title": "Senior Project Engineer/ Engineer / Assistant Engineer - MVAC", "description": "Responsibilities\u00a0\n\nResponsible for managing the maintenance and repair contract / works of Central Air-Conditioning Systems;\nDaily operation management of maintenance and repair projects and execute related processes;\nPrepare work schedule, equipment & material submission, shop drawing, service report, etc. for repair and renovation works;\nPrepare quotation, tender bidding, cost estimation and budget control;\nCoordinate all related projects / works with clients, suppliers, subcontractor, technical field staffs, and etc., and\nAttend site meeting\n\n\u00a0Requirements\n\nHigh Dip.\u00a0or above in MVAC/Building Services Engineering\u00a0or related disciplines;\nGood command of spoken and written Chinese & English;\nProficient in MS Excel, Word and Chinese word processing;\nGood communication skill with proactive and positive attitude;\nAble to work under pressure;\nAt least 1 years of relevant practical working experience on Central MVAC systems in commercial and public sectors", "employment_types": ["Full Time", "Permanent"], "selling_points": [], "locations": ["To Kwa Wan"], "categories": ["Engineering", "Electrical / Electronics", "Engineering Project Management", "Mechanical"], "post_time": "2022-01-13T08:11:26Z", "salary": {"currency": null, "max": null, "min": null, "period": "monthly", "term": null}, "salary_visible": false, "title_keywords": ["senior project engineer", "assistant engineer", "engineer"], "responsibilities": ["management", "cost estimation", "maintenance", "systems", "daily operation", "renovation", "quotation", "coordinate", "repair", "schedule", "tender", "budget control", "report"], "requirements": {"degrees": ["high dip"], "majors": [], "languages": ["english", "chinese"], "language_level": ["good command", "proficient"], "hard_skills": ["ms excel", "chinese word processing", "word"], "soft_skills": ["positive attitude", "communication skill", "proactive", "work under pressure"], "languages_combined": [{"language": "english", "language_level": ["good command"]}, {"language": "chinese", "language_level": ["good command", "proficient"]}]}, "experience_required": {"duration": ["at least 1 years"], "field": ["commercial"]}}, {"job_id": "100003009048830", "location_code": "hk", "company": "Hong Kong Air Cargo Terminals Ltd", "job_title": "Engineer \u2013 Building Services (E&M / Electronic)", "description": "Duties\nAdministrate either E&M or Electronic Section and carry out corresponding maintenance and project works\nPerform scheduled daily work and assignment for the maintenance, repair, minor alterations, improvement and replacement of equipment and system\nSet standard for routine maintenance work with consideration in resource deployment, productivity improvement and coordination with operations team\nLiaise with contractors and monitor their performance\nUndertake the acceptance procedures of new installation against specifications\nMaintain proper documentation on compliance of license requirement, warranty claims and feedback on follow up actions\nPlan the stock level and control the usage of spares, consumable materials and tools for equipment\nPrepare tender specifications and monitor tendering process, project set-up, installation work and schedule\nExercise full quality control of project work\nConduct user training for the Section / Department concerned before hand over of work\nProvide regular work reports and recommendations to supervisors\nLead and supervise staff to carry out their work safely, efficiently and legally\nPerform any other duties as assigned by the supervisor\nQualifications\n5 years\u2019 relevant experience, minimum 3 years\u2019 supervisory experience or contractor management experience\nEducation background in Building Services / Electrical / Electronic / Mechanical / Marine Engineering\nGood command of English and Chinese\nWilling to perform shift duties including overnight shift\nPackage including Chinese New Year bonus, discretionary bonus, transport subsidy, overtime allowance, annual safety bonus, quarterly special attendance bonus, employer topped-up MPF contributions, medical benefits (including family members), voluntary dental coverage (including family members), life insurance, birthday leave, extra annual leave, statutory and public holiday, marriage leave, maternity leave, paternity leave, newborn baby gift, sports centre and free shuttle bus.\n\nInterested parties please apply with full resume detailing experience, qualifications and expected salary by post, by e-mail or click \"Apply Now\".\nBy post: Human Resources, 6/F, North Office Block, SuperTerminal 1, Hong Kong International Airport, HK\n\n\nPlease quote the above reference in your application. To know more about our company, please visit our website\u00a0https://careers.hactl.com/.\n\n\nApplicants not invited for interview within four weeks should consider their applications unsuccessful. Applicants\u2019 personal data collected will only be used for the sole purpose of recruitment. The data of unsuccessful applicants will be destroyed within six months.", "employment_types": ["Full Time", "Permanent"], "selling_points": ["Maintenance & project works of E&M or Electronic", "Contractor management", "Competitive remuneration package"], "locations": ["Airport Area"], "categories": ["Building & Construction", "Building / Construction / QS", "Engineering", "Electrical / Electronics", "Mechanical"], "post_time": "2022-01-14T07:22:15Z", "salary": {"currency": null, "max": null, "min": null, "period": "monthly", "term": null}, "salary_visible": false, "title_keywords": ["engineer"], "responsibilities": ["any other duties", "operations", "coordination with", "maintain proper documentation", "tendering", "plan", "liaise with contractors", "control", "compliance", "monitor", "reports", "schedule", "tender", "installation", "management", "attendance", "mpf", "procedures", "specifications", "maintenance", "repair", "quality control", "insurance"], "requirements": {"degrees": [], "majors": [], "languages": ["english", "chinese"], "language_level": ["good command"], "hard_skills": ["documentation", "deployment", "maintenance"], "soft_skills": ["coordination"], "languages_combined": [{"language": "english", "language_level": ["good command"]}, {"language": "chinese", "language_level": ["good command"]}]}, "experience_required": {"duration": ["5 years", "minimum 3 years"], "field": ["management", "relevant experience", "supervisory experience"]}}, {"job_id": "100003009045748", "location_code": "hk", "company": "Pioneer Management Limited", "job_title": "Technical Assistant (Building Works)", "description": "The Job:\nMaintenance building Works in Housing Estate\n\nRequirements:\nTechnical Assistant (Building Works)\n\nat least in possession of a Diploma or Higher Certificate in Building Studies from a Hong Kong Polytechnic University / Polytechnic the Hong Kong Institute of Vocation Education (IVE) or a technical institute / technical college; or equivalent.\n\nPlease send full resume & salary expected by clicking \"Apply Now\".\n\n(Personal data collected will be used strictly for recruitment purpose only)", "employment_types": ["Full Time", "Permanent"], "selling_points": ["Maintenance building Works in Housing Estate", "Diploma or Higher Certificate in Building Studies", "Hong Kong Institute of Vocation Education (IVE)"], "locations": ["Wong Tai Sin Area"], "categories": ["Building & Construction", "Building / Construction / QS", "Engineering", "Electrical / Electronics", "Mechanical"], "post_time": "2022-01-13T08:33:26Z", "salary": {"currency": null, "max": null, "min": null, "period": "monthly", "term": null}, "salary_visible": false, "title_keywords": ["technical assistant"], "responsibilities": ["maintenance"], "requirements": {"degrees": ["diploma", "higher certificate"], "majors": ["building studies"], "languages": [], "language_level": [], "hard_skills": [], "soft_skills": [], "languages_combined": []}, "experience_required": {"duration": [], "field": []}}, {"job_id": "100003009048890", "location_code": "hk", "company": "Perfect World Company Limited", "job_title": "\u6280\u8853\u54e1 (\u96fb\u529b)", "description": "\u5927\u5ec8\u8a2d\u65bd\u6aa2\u67e5,\u4fdd\u990a\u53ca\u57f7\u884c\u8a2d\u5c0f\u578b\u7dad\u4fee,\u4e26\u8ddf\u9032\u5916\u5224\u627f\u8fa6\u5546\u5de5\u4f5c\n\u4e2d\u5b78\u7562\u696d\n\u826f\u597d\u7cb5\u8a9e; \u4e00\u822c\u82f1\u8a9e; \u61c2\u8b80\u5beb\u4e2d\u6587\n\u6301\u6709\u96fb\u5de5A\u724c; \u51772\u5e74\u6216\u4ee5\u4e0a\u6c34\u96fb\u6216\u51b7\u6c23\u7dad\u4fee\u4fdd\u990a\u7d93\u9a57\n\n\u6709\u610f\u7533\u8acb\u8005,\u53ef\u900f\u904e\u4ee5\u4e0b\u5176\u4e2d\u4e00\u7a2e\u9014\u5f91\u7533\u8acb:\n\n1) \u6309 \u201cAPPLY NOW\" \u5c07\u5c65\u6b77\u8868\u96fb\u90f5\u81f3\u672c\u516c\u53f8 \u6216\n\n2)\u00a0\u81f4\u96fb\u00a02864 4512\u00a0\u77f3\u5148\u751f\u00a0\u6216\n\n3)\u00a0WhatsApp 6462 0906\u00a0\u3002\n\nAll applications applied through our system will be delivered directly to the advertiser and privacy of personal data of the applicant will be ensured with security.", "employment_types": ["Full Time"], "selling_points": ["\u5927\u5ec8\u8a2d\u65bd\u6aa2\u67e5", "\u4e2d\u5b78\u7562\u696d", "\u51772\u5e74\u6216\u4ee5\u4e0a\u6c34\u96fb\u6216\u51b7\u6c23\u7dad\u4fee\u4fdd\u990a\u7d93\u9a57"], "locations": ["Causeway Bay"], "categories": ["Engineering", "Electrical / Electronics", "Others"], "post_time": "2022-01-14T07:36:29Z", "salary": {"currency": null, "max": null, "min": null, "period": "monthly", "term": null}, "salary_visible": false, "title_keywords": ["\u6280\u8853\u54e1"], "responsibilities": ["personal data"], "requirements": {"degrees": [], "majors": [], "languages": [], "language_level": [], "hard_skills": ["whatsapp"], "soft_skills": [], "languages_combined": []}, "experience_required": {"duration": [], "field": []}}, {"job_id": "100003009046353", "location_code": "hk", "company": "CSX World Terminals Hong Kong Limited", "job_title": "Shift Engineer", "description": "Responsibilities:\n\u2022\u00a0Perform routine maintenance and repairs for all crane equipment and workshop equipment\n\u2022\u00a0Assist in preparing and keeping maintenance and repair records\n\u2022\u00a0Attend all faults & emergency repair works and supervise the remedy as well as provide failures troubles shooting & technical diagnosis\n\u2022\u00a0Ensure all the cranes maintenance works carried out by the contractors meet with the Company\u2019s needs and reports to supervisor\n\u2022\u00a0Lead team members to carry out assigned jobs\n\nRequirements:\n\u2022\u00a0Higher Certificate/Diploma in electrical engineering or related discipline\n\u2022\u00a06 years relevant working experience in heavy electrical industrials with 3 years supervisory experience\n\u2022\u00a0Knowledge of AC/DC motor drives, PLC and cranes control is preferred\n\u2022\u00a0Holder of Electrical License B is preferred\n\u2022\u00a0Holder of Container Handling Industry Safety Card\n\u2022\u00a0Holder of driving license Class 1 & Class 2 is preferred\n\u2022\u00a0Willing to perform shift work\n\u2022\u00a0Good interpersonal and communication skills\n\n**Candidates with less experience will be considered as Assistant Engineer.\n\nBenefit:\n5 Shift Per Week / Night Shift Allowance / Annual Leave / General Holidays / Group Medical Insurance (Included dependent) & Life Insurance / Discretionary Bonus / Free Shuttle Bus Service\n\n(All information collected will be kept strictly confidential and for recruitment and employment-related purposes only)", "employment_types": ["Full Time", "Permanent"], "selling_points": [], "locations": ["Kwai Tsing Area"], "categories": ["Engineering", "Electrical / Electronics", "Mechanical", "Others"], "post_time": "2022-01-13T10:39:13Z", "salary": {"currency": null, "max": null, "min": null, "period": "monthly", "term": null}, "salary_visible": false, "title_keywords": ["engineer"], "responsibilities": ["workshop", "reports", "maintenance", "repair"], "requirements": {"degrees": ["diploma", "higher certificate"], "majors": ["electrical engineering"], "languages": [], "language_level": [], "hard_skills": ["dc", "plc", "container"], "soft_skills": ["communication skills", "interpersonal"], "languages_combined": []}, "experience_required": {"duration": ["6 years", "3 years"], "field": ["relevant working experience", "supervisory experience"]}}, {"job_id": "100003005585293", "location_code": "hk", "company": "Infracable Limited", "job_title": "Civil Implementation Assistant/Officer", "description": "Job Description:\n\nTo Monitor civil contractors to carry out site work according to set target drawing and company standard\n\nResponsible for site inspection, provide technical advice to contractors, handle and solve site problems and public complaints, it any\n\nAttend meetings with concerned parties about civil work issues\n\nResponsible for certification of as-built civil works and conduct site measurements\n\nRequirement:\n\nDiploma holder of Civil/Electrical/Electronic/Communications or related disciplines\n\nMature and independent with good communication skills\n\nGood command in verbal and written English and Chinese\n\nPossess 2 years experience in telecom civil works/construction field is an advantage\n\nFresh graduate will also be considered\n\n\u00a0Benefits: Medical & Dental Insurance, Five-day work week\n\nWe offer attractive remuneration package to the right candidate. To apply, please send a full resume with contact telephone number, date of availability, expected salary by clicking \"Apply Now\". (All information collected will be kept strictly confidential and be used for recruitment purpose only.)", "employment_types": ["Full Time", "Permanent"], "selling_points": [], "locations": ["Kwun Tong"], "categories": ["Engineering", "Electrical / Electronics", "Engineering Project Management", "Telecommunication / Wireless / Radio"], "post_time": "2022-01-14T06:25:50Z", "salary": {"currency": "HKD", "max": 19999, "min": 11000, "period": "monthly", "term": null}, "salary_visible": true, "title_keywords": ["officer", "assistant"], "responsibilities": ["attend meetings", "technical advice", "monitor", "site inspection"], "requirements": {"degrees": ["diploma holder", "fresh graduate"], "majors": ["related disciplines", "communications"], "languages": ["english", "chinese"], "language_level": ["good command"], "hard_skills": [], "soft_skills": ["communication skills", "independent", "mature"], "languages_combined": [{"language": "english", "language_level": ["good command"]}, {"language": "chinese", "language_level": ["good command"]}]}, "experience_required": {"duration": ["2 years"], "field": ["construction"]}}, {"job_id": "100003009049482", "location_code": "hk", "company": "Jones Lang LaSalle Ltd", "job_title": "Assistant Project Engineer", "description": "About JLL \u2013\u00a0\n\nWe\u2019re JLL. We\u2019re a professional services and investment management firm specializing in real estate. As a Fortune 500 company, we help real estate owners, occupiers and investors achieve their business ambitions.\u00a0\n\nIf you\u2019re looking to step up your career, JLL is the perfect professional home. With us, you\u2019ll have a chance to innovate with the world\u2019s leading businesses, put that expertise into action on landmark projects, and work on game-changing real estate initiatives. You\u2019ll also make long-lasting professional connections and be inspired by the best. We\u2019re focused on opportunity and want to help you make the most of yours. Achieve your ambitions - join us at JLL!\u00a0\n\nAbout the role:\u00a0\n\nWhat this job involves:\u00a0\n\nAssist the renovation, refurbishment & enhancement projects for sizeable composite development to ensure timely completion and within budgets\nAssist Senior Project Manager with the preparations of strategic plans, budgets and client reports\nSupport projects from project conception to project handover (including DLP)\nPreparate project specification, tender documentations, evaluation of tenders and preparation of contracts\nReview design submissions; and liaise with statutory bodies on approval of statutory submissions\nCo-ordinate with consultants\u00a0and contractors\u00a0to ensure projects are delivered accordingly project specifications, at high quality standard and compliance with statutory regulations / standards (e.g. fire, health and safety standards)\nSupervise the repair and maintenance works and assist in coordination of churn activities\nEnsure the implementation and management of Risk & Safety work practices during project implementation\nEnsure all safety procedures, including Crisis Management / Business Continuity and Emergency Procedures are maintained at all times\nCo-ordinate with Owners & the Business Units on Project issues\nPrepare & update Monthly\u00a0Management Report\n\nSound like you? To apply you will have:\n\nDegree or above in Building Surveying / Building Management / Building Services or related disciplines with minimum of 2 years\u2019 experience, preferably in project and construction management of retail shops, F&B\u00a0and offices space\nMembership of RICS, CIOB, HKICM, HKIE or equivalent is preferred\nKnowledge of HVAC, Fire Services System, Plumbing and Drainage system, ELV system, Electrical and Lighting system, AV system, Building and A&A works is preferred\nConversant with Construction Site Safety requirements, Hong Kong construction and building related legislations and submission process\nStrong interpersonal skills, mature, independent and strategic thinking with leadership skills\nFamiliar with MS applications and AutoCAD\nCandidates with more experience will be considered as Project Engineer\n\nWhat we can do for you:\u00a0\n\nAt JLL, we make sure that you become the best version of yourself by helping you realise your full potential in an entrepreneurial and inclusive work environment. We will empower your ambitions through our dedicated Total Rewards Program, competitive pay and benefits package.\u00a0\n\nApply today!\u00a0", "employment_types": ["Full Time", "Permanent"], "selling_points": ["Project Management / Construction Management", "Building Services / Building Surveying", "Good Career Development Opportunities"], "locations": ["Pok Fu Lam"], "categories": ["Building & Construction", "Building / Construction / QS", "Engineering", "Electrical / Electronics", "Engineering Project Management"], "post_time": "2022-01-14T08:44:15Z", "salary": {"currency": null, "max": null, "min": null, "period": "monthly", "term": null}, "salary_visible": false, "title_keywords": ["assistant project engineer"], "responsibilities": ["business continuity", "co-ordinate with", "quality", "compliance with statutory regulations", "building management", "review design submissions", "liaise with", "project conception", "support projects", "emergency procedures", "implementation", "churn activities", "project handover", "risk & safety work practices", "legislations", "crisis management", "client reports", "management", "construction management", "procedures", "tender documentations", "specifications", "approval of statutory submissions", "refurbishment & enhancement projects", "repair and maintenance works", "budgets", "strategic plans", "monthly management report", "assist the renovation", "preparation of contracts", "safety standards", "coordination", "preparate project specification", "evaluation of tenders"], "requirements": {"degrees": ["degree or above"], "majors": ["construction management", "related disciplines", "building management", "building services", "building surveying"], "languages": [], "language_level": [], "hard_skills": ["hong kong construction and building related legislations", "documentations", "hkie", "fire services system", "ms applications", "building and a&a works", "make", "plumbing and drainage system", "submission process", "knowledge of hvac", "electrical and lighting system", "ciob", "elv system", "hkicm", "maintenance", "rics", "av system", "construction site safety requirements", "autocad"], "soft_skills": ["independent", "focused", "strategic thinking", "timely", "leadership skills", "mature", "interpersonal skills", "coordination"], "languages_combined": []}, "experience_required": {"duration": ["minimum of 2 years"], "field": ["management", "related", "f&b", "building services", "building surveying", "retail", "construction"]}}, {"job_id": "100003009043577", "location_code": "hk", "company": "Sunland.AL (International) Co., Limited", "job_title": "Draftsman / Assistant Engineer (Mechanical / Electrical / P & D / Fire Services / BS Disciplines)", "description": "Higher Diploma\u00a0or above\nProficiency in AutoCAD, MS Office,\u00a0Microsoft Project\nLanguages: Cantonese & English\nAt least 2~3 years of experience in related field\nExperience with consultancy firm will be an advantage\nImmediate available is preferred\n\nBenefit\n\nFive-Days Work Week\nMedical Insurance\nPerformance Bonus\n\nPlease send your resume with availability, current and expected salary to Sunland.AL (International) Co., Limited at by clicking \"Apply Now\"\n\n*Personal data collected will be used for recruitment purpose only.", "employment_types": ["Full Time", "Permanent"], "selling_points": ["Five-Days Work Week", "Medical Insurance", "Performance Bonus"], "locations": ["Tsim Sha Tsui"], "categories": ["Building & Construction", "Building / Construction / QS", "Engineering", "Electrical / Electronics", "Mechanical"], "post_time": "2022-01-12T23:19:04Z", "salary": {"currency": "HKD", "max": 29999, "min": 14000, "period": "monthly", "term": null}, "salary_visible": true, "title_keywords": ["assistant engineer", "draftsman"], "responsibilities": [], "requirements": {"degrees": ["higher diploma or above"], "majors": [], "languages": ["cantonese", "english"], "language_level": [], "hard_skills": ["microsoft project", "ms office", "autocad"], "soft_skills": [], "languages_combined": [{"language": "cantonese", "language_level": []}, {"language": "english", "language_level": []}]}, "experience_required": {"duration": ["at least 2~3 years"], "field": ["related"]}}, {"job_id": "100003009050327", "location_code": "hk", "company": "Otis Elevator Co (HK) Limited", "job_title": "Project Engineer/ Assistant Project Engineer", "description": "With customers in more than 200 countries and territories, we are globally recognized for our quality, safety and reliability. You will find us in the world\u2019s most iconic structures, and we are the company that made the modern vertical city possible.\n\nJoin us in moving the world forward!\n\n\nResponsibilities\n\nAssist to lead and supervise Project / Modification\u00a0team in carrying out the project programmes\nEnsure completion on project schedule and resources, as well as compliance to contract requirement\nMonitor the progress and work with internal departments & external suppliers to ensure on-time delivery\nCoordinate and work closely with Government sectors such as EMSD to ensure all projects in accordance with regulatory requirements\nQuality, Safety and cost control are required\n\nRequirements\n\nDegree in Building Services\u00a0/ Mechanical / Electrical, Electronic\u00a0Engineering courses or equivalent\n4-5 years' project management experience in\u00a0lift/elevator industry\u00a0\nStrong sense of responsibility\nAble to work under pressure\nGood time management\nGood interpersonal and communication skill\nFluent in spoken & written English and Chinese\nCandidate with less experience would be considered as Assistant Engineer\nFresh graduate welcome\nWe offer remuneration package including attractive salary, comprehensive fringe benefits and excellent opportunities for the right candidate.\u00a0(*** Employee Scholar Program\u00a0up to $160,000/ person for each degree***)\n\nWebsite:\u00a0http://www.otis.com/\u00a0\nInformation provided by applicants will be treated in strict confidence and will only be used for recruitment related purposes. All information on unsuccessful candidates will be deleted from our files within 24 months.", "employment_types": ["Full Time", "Permanent"], "selling_points": ["Family-Friendly Employer", "Fortune 500 MNC", "Excellent Workplace for Development and Learning"], "locations": ["Kowloon Bay"], "categories": ["Engineering", "Electrical / Electronics", "Engineering Project Management", "Mechanical"], "post_time": "2022-01-14T10:07:21Z", "salary": {"currency": null, "max": null, "min": null, "period": "monthly", "term": null}, "salary_visible": false, "title_keywords": ["assistant project engineer", "project engineer"], "responsibilities": ["regulatory requirements", "compliance", "monitor", "quality", "coordinate", "schedule", "cost control"], "requirements": {"degrees": ["degree", "fresh graduate"], "majors": ["building services", "engineering"], "languages": ["english", "chinese"], "language_level": ["fluent"], "hard_skills": ["project management"], "soft_skills": ["sense of responsibility", "communication skill", "project management", "time management", "interpersonal", "work under pressure"], "languages_combined": [{"language": "english", "language_level": ["fluent"]}, {"language": "chinese", "language_level": ["fluent"]}]}, "experience_required": {"duration": ["4-5 years"], "field": ["project management"]}}, {"job_id": "100003009046040", "location_code": "hk", "company": "Maxgrand Limited", "job_title": "Assistant Project Engineer/Assistant Project Engineer Trainee(5 days work)", "description": "Requirements:\n\nDiploma/ High Diploma / Degree in electrical Engg./electronic Engg./IT/Building System/ or related discipline/experience.\nFresh Graduate will also be considered.\nGood command of English, Cantonese and Mandarin.\nGood computer skills on MS Word, Excel.\nKnowledge in AutoCAD is preferred.\nGood problem solving skills, able to work independently and Self-motivated.\nWilling to work outside for on-site support and coordination.\u00a0\u00a0\n\nResponsibilities:\n\nReport to sales manager;\nProvide advice and assistance to salesperson for project follow up;\nProvide technical support for customer;\n\nWe offer attractive\u00a0remuneration package\u00a0with\u00a0double pay,\u00a0bonus\u00a0and\u00a0medical \u00a0insurance\u00a0to the right candidate. Please send your CV with expected salary stated\u00a0by clicking APPLY NOW.\n", "employment_types": ["Full Time"], "selling_points": ["Fresh Graduate will also be considered.", "Diploma/ High Diploma / Degree in electrical Engg.", "Knowledge in AutoCAD is preferred."], "locations": ["Kwai Hing"], "categories": ["Engineering", "Electrical / Electronics", "Engineering Project Management"], "post_time": "2022-01-13T18:55:11Z", "salary": {"currency": null, "max": null, "min": null, "period": "monthly", "term": null}, "salary_visible": false, "title_keywords": ["assistant project engineer"], "responsibilities": ["technical support", "project follow up", "provide advice", "report"], "requirements": {"degrees": ["high diploma", "diploma", "degree", "fresh graduate"], "majors": [], "languages": ["cantonese", "english", "mandarin"], "language_level": ["good command"], "hard_skills": ["excel", "ms word", "computer skills", "problem solving skills", "autocad"], "soft_skills": ["problem solving skills", "coordination", "work independently", "self-motivated"], "languages_combined": [{"language": "cantonese", "language_level": ["good command"]}, {"language": "english", "language_level": ["good command"]}, {"language": "mandarin", "language_level": ["good command"]}]}, "experience_required": {"duration": [], "field": ["related", "it"]}}, {"job_id": "100003009047187", "location_code": "hk", "company": "GHK Hospital Limited", "job_title": "Technician", "description": "\u8077\u8cac :\u4e00\u822c\u6280\u8853\u54e1\u5de5\u4f5c (\u5c0d\u91ab\u9662\u7dad\u4fee\u6709\u71b1\u8aa0; \u5177\u5099\u51b7\u6c23\u53ca\u4e00\u822c\u4f9b\u6c34\u3001\u6392\u6c34\u7dad\u4fee\u5de5\u4f5c\u7d93\u9a57; \u5177\u5728\u91ab\u9662\u6216\u5927\u578b\u5546\u5834\u670d\u52d9\u7d93\u9a57\u512a\u5148)\n\u8cc7\u6b77 :\u5c0f\u4e09\u7a0b\u5ea6; 3\u5e74\u7d93\u9a57; \u826f\u597d\u7cb5\u8a9e; \u4e00\u822c\u666e\u901a\u8a71; \u4e00\u822c\u82f1\u8a9e; \u61c2\u8b80\u5beb\u4e2d\u6587; \u61c2\u8b80\u5beb\u82f1\u6587; \u6301\u6709\u96fb\u5de5A\u724c; 3\u5e74\u4ee5\u4e0a\u7dad\u4fee\u6216\u5b89\u88dd\u7d93\u9a57; \u6301\u6709\u6280\u5de5\u8b49\u66f8\n\u5f85\u9047 :\u6bcf\u6708$20,000 - $30,000, \u6709\u5e74\u504715\u5929, \u914c\u60c5\u6027\u82b1\u7d05, \u7259\u79d1\u798f\u5229, \u91ab\u7642\u798f\u5229 \u53ca\u7a7f\u68ad\u5df4\u58eb\u670d\u52d9, \u4e0a\u53488\u6642\u81f3\u4e0b\u53484\u6642\u6216\u4e0b\u53483\u6642\u81f3\u4e0b\u534811\u6642\u6216\u4e0b\u534811\u6642\u81f3\u4e0a\u53488\u6642, \u6bcf\u9031\u5de5\u4f5c5\u5929\u81f36\u5929,\u8f2a\u73ed,\u8f2a\u4f11, \u6bcf\u5929\u5de5\u4f5c 8 - 9 \u5c0f\u6642\n\u7533\u8acb\u9808\u77e5 :\u6c42\u8077\u8005\u53ef\u50b3\u771f(39033406)\u6216\u96fb\u90f5(APPLY NOW)\u5c65\u6b77\u8868\u7d66\u6e2f\u6021\u91ab\u9662\u3002\u5982\u8981\u7d22\u53d6\u6536\u96c6\u500b\u4eba\u8cc7\u6599\u8072\u660e, \u8acb\u8207\u6eab \u5c0f\u59d0(Email)\u806f\u7d61\u3002", "employment_types": ["Full Time"], "selling_points": ["3\u5e74\u4ee5\u4e0a\u7dad\u4fee\u6216\u5b89\u88dd\u7d93\u9a57", "\u6301\u6709\u96fb\u5de5A\u724c; \u6301\u6709\u6280\u5de5\u8b49\u66f8", "\u6709\u5e74\u504715\u5929, \u914c\u60c5\u6027\u82b1\u7d05, \u7259\u79d1\u798f\u5229, \u91ab\u7642\u798f\u5229 \u53ca\u7a7f\u68ad\u5df4\u58eb\u670d\u52d9"], "locations": ["Central & Western Area"], "categories": ["Engineering", "Electrical / Electronics", "Mechanical", "Others", "Technician"], "post_time": "2022-01-15T03:49:36Z", "salary": {"currency": null, "max": null, "min": null, "period": "monthly", "term": null}, "salary_visible": false, "title_keywords": ["technician"], "responsibilities": [], "requirements": {"degrees": [], "majors": [], "languages": [], "language_level": [], "hard_skills": [], "soft_skills": [], "languages_combined": []}, "experience_required": {"duration": [], "field": []}}, {"job_id": "100003009039480", "location_code": "hk", "company": "CLP Power Hong Kong Limited", "job_title": "Senior Technical Officer (2-Year Contract) [Ref. CLPP-PSBG-WER-OB-STO]", "description": "Applications are invited for the above vacancy in Operations Branch of East & West Region.\u00a0 Reporting to the Engineer I, the successful candidate will be responsible for the following duties:-\u00a0\n\nCarry out maintenance, diagnosis and repair of Distribution Automation (DA) facilities (CRTU, LRTU & ORTU)\nCarry out 11kV & LV plant or circuits fault repair, supervise and co-ordinate maintenance activities and handle temporary supply restorations\nMonitor performance and progress to ensure that work plans are completed according to schedule and in compliance with relevant specifications, procedures and standards\nEnsure smooth work by coordinating access, schedules, isolation etc. with relevant internal and external stakeholders\nDiagnose complex problems and faults, identify and formulate preventive and corrective action using a variety of instruments and methods and make recommendations on quality improvement\u00a0\u00a0\u00a0\nCarry out high voltage switching and issue safety documents according to CLPP Safety Rules\nPlan and control projects activities, including materials and resources utilization to ensure that the related costs are within budget\u00a0\nPerform site measurements and prepare records. Ensure timely and accurate input of data in company IT systems such as EWMS, EFMS, SPS, AM/FM, DMS, TCOM etc.\u00a0\u00a0\u00a0\nLead by example in assisting the department in implementing safety initiatives aiming to promote safety culture\nPerform\u00a0standby duty / emergency call out / repair work, shift work, and/or work under adverse weather condition as and when required\nCarry out other duties including participating in safety promotion activities, driving, record updating, reporting writing, and any other duties assigned by supervisors\n\nRequirements:\n\n\nHigher Certificate / Higher Diploma holder in Electrical Engineering or Professional Diploma in Power Engineering or equivalent plus 5 years\u2019 relevant experience OR\u00a0Ordinary Certificate / Ordinary Diploma holder in Electrical Engineering or Diploma in Power Engineering or equivalent plus 8 years\u2019 relevant experience with at least 3 years at Technical Officer II Level\nPossession of a valid Driving License (class 1, 2)\nSafety Supervisor or equivalent preferred\nFamiliar with CLP Power Safety Rules, engineering standards and codes of practice / management systems, occupational health and environment related legislations\nGood understanding of Safe Systems of Work, operational safety and manual handling standards/techniques\nDemonstration of safety awareness, teamwork, and customer orientation\nGood understanding of simplified electrical installation / control wiring / plant / substation drawings\nGood knowledge of customers\u2019 installations, protection equipment, alarms and trip indicators\nAbility to work independently and to communicate technical concepts in English and Chinese, both verbal and written, Mandarin preferred\nGood supervisory, problem solving & influencing skills\nGood budget planning and resource allocation abilities\nGood knowledge of functionalities of company IT systems, e.g. EWMS, EFMS, SPS, AM/FM, DMS, TCOM etc.\nAbility to use simple PC applications, e.g. MS outlook, word, excel etc.\nAbility to perform basic functionalities of smart / mobile technology, e.g. Electronic Site Inspection Report (eSir), etc.\nCandidates with less qualification and/or experience but demonstrate good potential for further development will be considered for a position at lower grade.\nPlease apply by clicking the button \u201cApply Now\u201d below for application on or before 21 January 2022.\n\nApplicants not invited for interview within 6 weeks from the closing date may assume their applications unsuccessful.\nThe level of appointment will be commensurate with qualification and experience. The entry pay, terms of appointment and conditions of service will be offered to the successful candidate which are subject to the provisions prevailing at the time the offer of appointment is made.\nInformation provided will be for recruitment purpose within the CLP Group and only short-listed candidates will be contacted. We comply with all applicable laws and regulations of HKSAR in handling applications. For details of the Personal Information Collection Statement, please visit our website: https://clp.to/engPICS\nFor further information on CLP, please visit our website: http://www.clpgroup.com/", "employment_types": ["Full Time", "Contract"], "selling_points": [], "locations": ["Not Specified"], "categories": ["Engineering", "Electrical / Electronics", "Others"], "post_time": "2022-01-13T18:54:47Z", "salary": {"currency": null, "max": null, "min": null, "period": "monthly", "term": null}, "salary_visible": false, "title_keywords": ["senior technical officer"], "responsibilities": ["regulations", "any other duties", "data", "schedules", "operations", "budget", "quality", "website", "drawings", "plan", "plans", "costs", "make recommendations", "control", "budget planning", "other duties", "monitor performance", "compliance", "diagnose", "site inspection", "schedule", "legislations", "report", "reporting", "management", "installation", "procedures", "specifications", "maintenance", "systems", "repair", "recruitment"], "requirements": {"degrees": ["diploma holder", "higher certificate", "certificate", "diploma", "higher diploma holder"], "majors": ["engineering", "electrical engineering"], "languages": ["english", "chinese", "mandarin"], "language_level": [], "hard_skills": ["sps", "simple", "plus", "excel", "basic", "maintenance", "word", "pc applications", "problem solving", "make", "safe", "mobile", "outlook", "codes"], "soft_skills": ["make recommendations", "work independently", "responsible", "timely", "teamwork", "problem solving", "smooth", "accurate"], "languages_combined": [{"language": "english", "language_level": []}, {"language": "chinese", "language_level": []}, {"language": "mandarin", "language_level": []}]}, "experience_required": {"duration": ["5 years", "at least 3 years", "8 years"], "field": ["development", "relevant experience", "engineering"]}}, {"job_id": "100003009050744", "location_code": "hk", "company": "Hutchison Telecommunications (Hong Kong) Limited", "job_title": "Engineer (Fault Investigation)", "description": "Responsibilities:\n\nSupporting Radio Network Configuration design and implementation\nSupporting Radio Network Events and Activities Management\nSupporting VIP Complaint analysis and Fault investigation\n\nRequirements:\n\n\nBachelor Degree in Electrical and Electronic Engineering or Computer Science or relevant discipline\nExperience in Engineering\u00a0background on EEE or CS is preferred\nSkill-set on machine learning language, data analytic tool is preferred\nGood command of both spoken and written English, Cantonese and Mandarin\n\nApart from competitive remuneration package and exciting opportunity for career development within the Group, we provide attractive employee benefits such as free company shuttle, free company SIM card and preferential SIM plan offers, comprehensive medical & insurance schemes, as well as full range of other employee well-being provisions.\n\n\nInterested parties, please apply with full resume, present and expected salary, by clicking \u201cAPPLY NOW\u201d. Please quote the reference number on the e-mail subject.\n\nWe are an equal opportunity employer and welcome applications from all qualified candidates. Personal data collected will be treated in the strictest confidence and handled confidentially by authorised personnel for recruitment-related purposes only within the CK Hutchison Group of companies. The personal data of unsuccessful applicants will be destroyed after the recruitment exercise pursuant to the requirements of the Personal Data (Privacy) Ordinance in Hong Kong.", "employment_types": ["Full Time", "Permanent"], "selling_points": [], "locations": ["Tsing Yi"], "categories": ["Engineering", "Electrical / Electronics", "Telecommunication / Wireless / Radio", "Others"], "post_time": "2022-01-14T11:15:04Z", "salary": {"currency": null, "max": null, "min": null, "period": "monthly", "term": null}, "salary_visible": false, "title_keywords": ["engineer"], "responsibilities": ["management", "configuration", "analysis", "implementation", "design", "investigation"], "requirements": {"degrees": ["degree", "bachelor"], "majors": ["engineering", "computer science"], "languages": ["cantonese", "english", "mandarin"], "language_level": ["good command"], "hard_skills": [], "soft_skills": ["comprehensive", "learning"], "languages_combined": [{"language": "cantonese", "language_level": ["good command"]}, {"language": "english", "language_level": ["good command"]}, {"language": "mandarin", "language_level": ["good command"]}]}, "experience_required": {"duration": [], "field": ["cs", "engineering"]}}, {"job_id": "100003009046860", "location_code": "hk", "company": "Cloud Light Technology Limited", "job_title": "Senior Electronic Engineer \u2013 Mixed-signal / RF Circuit Design  (Job Ref. Apply-HK-2014-SEE)", "description": "Job Responsibilities:\u00a0\n\nResponsible for RF and electronic sub-system design for high-speed fiber-optic transceiver and optical sensor products;\nHigh-speed PCB board layout and optimization;\nDesign validation and failure analysis\nPerform 3D electromagnetic simulation for new RF package designs;\nResearch latest high-speed packaging techniques for use in optoelectronic applications.\n\n\n\nRequirement:\n\n\nBachelor or above in Electronics engineering, Applied Physics or equivalent.\n4 years of relevant experience in mixed-signal /RF circuit design and implementation, with actual product development\u00a0\nExperience with mixed-signal / RF PCB design and ability to layout the circuit to meet expected performance and designed specification.\nFamiliar with EDA tools such as Altium Designer and Cadence Allegro\nFamiliar with simulation tools such as HFSS and ADS\nFamiliar with standard RF test & measurement tools such as oscilloscopes, network analysers & spectrum analysers.\nUnderstanding on the fundamental of optoelectronics is an advantage;\nGood communication skills with the ability to work in an international team\n\u00a0Ability to work independently and tackle tasks with minimal supervision.\n\u00a0Fresh graduates with solid circuit design knowledge will also be considered.\nCandidate with more relevant working experiences and solid circuit design experiences may also be considered for the ranking of senior engineer.\n\nRemunerations & Benefits:\n\nWork locations in Hong Kong and travel to the PRC may be required\nWork Hours from 9am to 6pm\n5-day work\nHong Kong Public Holidays\nChinese New Year Bonus\n\nApplication:\n\nTo apply, please email us\u00a0your resume, your availability to report duty and quote the Job Ref.\nOnly short-listed candidates will be notified. Personal data provided by applicants will be used for consideration of an application only.\n\nApplication Deadline:\n\nUntil this position is filled.\nResumes received will strictly be used for recruitment-related purpose", "employment_types": ["Full Time", "Permanent"], "selling_points": ["RF and electronic sub-system design", "PCB board layout and optimization", "Design validation and failure analysis"], "locations": ["Shatin Area"], "categories": ["Engineering", "Electrical / Electronics", "Manufacturing & Production", "Telecommunication / Wireless / Radio"], "post_time": "2022-01-14T01:29:30Z", "salary": {"currency": null, "max": null, "min": null, "period": "monthly", "term": null}, "salary_visible": false, "title_keywords": ["senior electronic engineer"], "responsibilities": ["analysis", "system design", "design"], "requirements": {"degrees": ["bachelor"], "majors": ["engineering", "physics"], "languages": [], "language_level": [], "hard_skills": ["signal"], "soft_skills": ["communication skills", "work independently"], "languages_combined": []}, "experience_required": {"duration": ["4 years"], "field": ["senior engineer", "product development", "relevant experience", "design"]}}, {"job_id": "100003009051860", "location_code": "hk", "company": "Hong Kong Applied Science and Technology Research Institute Company Limited (ASTRI)", "job_title": "Machine Learning - Senior Lead Engineer / Lead Engineer", "description": "Reference #:\u00a0CTO/IOTSEN/10\n\n\nJob Responsibilities\n\n\nPropose, review, and execute projects advancing the practical state-of-the-art in machine learning (ML) and deep learning (DL)\nResearch and implement ML and DL technologies both independently and as part of collaborative teams to solve industrial vision-related problems\nDevelop and prototype ML/DL algorithms and software\nWork with hardware engineers to integrate a software into a well-tested and robust system\nProvide excellent communication with customers, partners, and teammates\nTake business trips to other cities for onsite support occasionally\nPerform other related duties and responsibilities, on occasion, as assigned\nRequirements\nPhD holder or Master\u2019s degree in Computer Science, Electronic/Electrical Engineering, Information Engineering, Mathematics, Statistics, Physics or relevant disciplines with minimum 3 years of related experience. Candidates with less experience may also be considered.\nExposure to Python or C++ programming\nExperience with DL frameworks such as TensorFlow, PyTorch and others.\nExposure to C, C# or CUDA programming is a plus\nFamiliar with maintenance of workstations and clusters for ML/DL is a plus\nStrong teamwork and good analytical thinking skills\nGood verbal and written communication skills in English\nLive ASTRI values\nApplication\n\nThe appointment will be on renewable contract terms with a competitive salary and performance-linked variable pay. Fringe benefits include paid leave, medical and dental benefits, insurance coverage and contribution to MPF. The incumbent will normally work\u00a0a five-day week.\n\nInterested candidates, please send an application (quoting Ref. No.) with a detailed resume, current and expected salary to\u00a0Talent Acquisition by clicking \"APPLY NOW\".\u00a0The resume should\u00a0not\u00a0include any sensitive personal information such as HKID or passport number, photo, etc.\u00a0\n\nPosition offer is subject to the applicant\u2019s experience and academic qualification. The application will be open until the position is filled. Only short-listed candidates will be notified. ASTRI reserves the right not to fill the position.\n\nASTRI is an Equal Opportunities Employer. Personal data provided by job applicants will be used\u00a0exclusively\u00a0for recruitment\u00a0only. For details, please refer to\u00a0Privacy - ASTRI - Hong Kong Applied Science and Technology Research Institute Company Limited, in particular section 9.", "employment_types": ["Full Time", "Contract"], "selling_points": ["Deep learning", "Research and implement ML and DL technologies", "Develop and prototype ML/DL algorithms"], "locations": ["Shatin Area"], "categories": ["Engineering", "Electrical / Electronics", "Engineering Project Management", "Sciences, Lab, R&D", "Research & Development (R&D)"], "post_time": "2022-01-17T01:23:55Z", "salary": {"currency": null, "max": null, "min": null, "period": "monthly", "term": null}, "salary_visible": false, "title_keywords": ["engineer", "lead"], "responsibilities": ["software", "review", "teams", "develop", "communication", "hardware"], "requirements": {"degrees": ["degree", "master"], "majors": ["mathematics", "engineering", "electrical engineering", "statistics", "physics", "computer science"], "languages": ["english"], "language_level": ["good"], "hard_skills": ["plus", "c++", "maintenance", "cuda", "ml", "c", "programming", "python", "c#"], "soft_skills": ["communication skills", "teamwork"], "languages_combined": [{"language": "english", "language_level": ["good"]}]}, "experience_required": {"duration": ["minimum 3 years"], "field": ["related", "statistics", "engineering"]}}, {"job_id": "100003009047381", "location_code": "hk", "company": "CHI Instrumentation Limited", "job_title": "Technical Engineer", "description": "Requirements:\n- Higher certificate / Diploma or Degree holder in Electronic, Electrical, Building Service Eng. or equivalent;\n- 1-2 years experience (fresh graduate will also be considered)\n-\u00a0Good command of spoken/written English, Cantonese and Mandarin;\n- Independent, self-motivated and able to work under pressure;\n-\u00a0Excellent interpersonal and negotiation skills\n\nResponsibilities:\n-Preparation of tender and equipment submission;\n-Perform site meeting and provide technical support;\n-Coordinate with client, contractor, consultant;\n\n", "employment_types": ["Full Time"], "selling_points": ["Commission scheme", "Bonus", "Nice working environment"], "locations": ["Kwai Hing"], "categories": ["Engineering", "Electrical / Electronics", "Engineering Project Management"], "post_time": "2022-01-14T02:56:40Z", "salary": {"currency": "HKD", "max": 24999, "min": 17000, "period": "monthly", "term": null}, "salary_visible": true, "title_keywords": ["technical engineer"], "responsibilities": ["technical support", "tender"], "requirements": {"degrees": ["diploma", "higher certificate", "fresh graduate", "degree holder"], "majors": [], "languages": ["cantonese", "english", "mandarin"], "language_level": ["good command"], "hard_skills": [], "soft_skills": ["self-motivated", "independent", "negotiation skills", "interpersonal", "work under pressure"], "languages_combined": [{"language": "cantonese", "language_level": ["good command"]}, {"language": "english", "language_level": ["good command"]}, {"language": "mandarin", "language_level": ["good command"]}]}, "experience_required": {"duration": ["1-2 years"], "field": []}}, {"job_id": "100003009044355", "location_code": "hk", "company": "Nam Wah Intelligent Automation Limited", "job_title": "Project Engineer", "description": "Job Description\n\nReporting to Project Manager, the Project Engineer will have the following missions:\n- Responsible for overall control and manage industrial automation projects\n\n- Prepare documentations, system design, equipment and drawing submissions\n- PLC and SCADA system programming\n- Supervision of site installation and control panel fabrication\n- On site testing & commissioning\n\nRequirements\n- Degree/High Diploma/Diploma in Electronics / Electrical / Computer / Mechanical Engineering, Computer Science or related discipline\n- 1-2 years working experience, Fresh Graduates are welcomed\n- Good communication skill\n- Strong analytical ability and problem solving skills\n- Familiar with Industrial Automation Control is an advantage", "employment_types": ["Full Time"], "selling_points": ["PLC/SCADA", "Industrial Automation", "Allen Bradley/Siemens"], "locations": ["Lai Chi Kok"], "categories": ["Engineering", "Electrical / Electronics", "Engineering Project Management", "Information Technology (IT)", "Network & System"], "post_time": "2022-01-13T03:48:25Z", "salary": {"currency": null, "max": null, "min": null, "period": "monthly", "term": null}, "salary_visible": false, "title_keywords": ["project engineer"], "responsibilities": ["reporting", "control", "installation", "commissioning", "testing", "system design"], "requirements": {"degrees": ["high diploma", "diploma", "degree"], "majors": ["computer science", "mechanical engineering"], "languages": [], "language_level": [], "hard_skills": ["problem solving skills"], "soft_skills": ["problem solving skills", "communication skill"], "languages_combined": []}, "experience_required": {"duration": ["1-2 years"], "field": []}}, {"job_id": "100003009043808", "location_code": "hk", "company": "Citybase Property Management Limited", "job_title": "Technical Officer / Assistant Technical Officer", "description": "Responsibilities:\u00a0\n\nTo monitor\u00a0property maintenance, E & M services and builder's work\nTo prepare the tender document of R & M both E & M services and builder's work\n\nRequirements:\n\nDiploma holder in Building Services Engineering / Electrical Engineering or equivalent\nHolder of Registration of Electrical Worker (Grade:A/B)\nMinimum 3 years experience in maintenance of building service installations at residential property\nGood command of spoken English and Cantonese\nKnowledge in PC applications including MS Excel and Word\nResponsible, independent, self-motivated, willing to work under pressure, with good communication skill\u00a0\nCandidates with less experience will be considered as Assistant Technical Officer\n\nWe will offer attractive compensation package to the right candidate. Please send application enclosing resume stating career and salary history, expected salary and date of availability to HR Manager, Citybase Property Management Limited, Unit No.1, 6/F, Hampton Loft, 11 Hoi Fan Road, Tai Kok Tsui, Kowloon by fax at 2717 4717 or by clicking \"Apply Now\"\u00a0(in Word format). Please quote the reference of the position you apply for in all correspondences.\n\nWe are an equal opportunity employer and welcome applications from all qualified candidates. Personal data collected will be treated in strictest confidence and handled confidentially by authorized personnel for recruitment-related purposes within the Group. Applicants not hearing from us within six weeks from the date of advertisement may consider their applications unsuccessful.", "employment_types": ["Full Time", "Permanent"], "selling_points": ["Dip holder in BS Eng/Electrical Eng", "Minimum 3 yrs exp in R&M at residential property", "Certificate of Registration of Electrical Worker"], "locations": ["Tin Shui Wai"], "categories": ["Engineering", "Electrical / Electronics", "Engineering Project Management", "Others", "Technician"], "post_time": "2022-01-14T09:41:02Z", "salary": {"currency": null, "max": null, "min": null, "period": null, "term": null}, "salary_visible": false, "title_keywords": ["technical officer", "assistant technical officer"], "responsibilities": ["tender document", "monitor", "maintenance"], "requirements": {"degrees": ["diploma holder"], "majors": ["building services", "engineering", "electrical engineering"], "languages": ["cantonese", "english"], "language_level": ["good command"], "hard_skills": ["no", "maintenance", "word", "pc applications", "ms excel"], "soft_skills": ["self-motivated", "confidence", "independent", "responsible", "communication skill", "work under pressure"], "languages_combined": [{"language": "cantonese", "language_level": ["good command"]}, {"language": "english", "language_level": ["good command"]}]}, "experience_required": {"duration": ["minimum 3 years"], "field": ["maintenance"]}}, {"job_id": "100003009050743", "location_code": "hk", "company": "Hutchison Telecommunications (Hong Kong) Limited", "job_title": "Engineer (Technology Evolution & Network Development)", "description": "Responsibilities:\n\n\nSupporting data collection, analysis and report using existing radio network traffic data and\u00a0new platform (including 3rd party)\nPreparing detailed analysis and comprehensive reports\u00a0\nSupporting development of database, web portal and automation\n\nRequirements:\n\nBachelor degree or above in Electrical and Electronic Engineering or Computer Science or relevant discipline\nExperience in Engineering\u00a0background on EEE or CS is preferred\nSkill-set on machine learning language, data analytic tool is preferred\nGood command of both spoken and written English, Cantonese and Mandarin\n\nApart from competitive remuneration package and exciting opportunity for career development within the Group, we provide attractive employee benefits such as free company shuttle, free company SIM card and preferential SIM plan offers, comprehensive medical & insurance schemes, as well as full range of other employee well-being provisions.\n\n\nInterested parties, please apply with full resume, present and expected salary, by clicking \u201cAPPLY NOW\u201d. Please quote the reference number on the e-mail subject.\n\nWe are an equal opportunity employer and welcome applications from all qualified candidates. Personal data collected will be treated in the strictest confidence and handled confidentially by authorised personnel for recruitment-related purposes only within the CK Hutchison Group of companies. The personal data of unsuccessful applicants will be destroyed after the recruitment exercise pursuant to the requirements of the Personal Data (Privacy) Ordinance in Hong Kong.", "employment_types": ["Full Time", "Permanent"], "selling_points": [], "locations": ["Tsing Yi"], "categories": ["Engineering", "Electrical / Electronics", "Telecommunication / Wireless / Radio", "Others"], "post_time": "2022-01-14T11:15:03Z", "salary": {"currency": null, "max": null, "min": null, "period": "monthly", "term": null}, "salary_visible": false, "title_keywords": ["engineer"], "responsibilities": ["data", "analysis", "reports", "data collection", "database", "report"], "requirements": {"degrees": ["degree or above", "bachelor"], "majors": ["engineering", "computer science"], "languages": ["cantonese", "english", "mandarin"], "language_level": ["good command"], "hard_skills": [], "soft_skills": ["comprehensive", "learning"], "languages_combined": [{"language": "cantonese", "language_level": ["good command"]}, {"language": "english", "language_level": ["good command"]}, {"language": "mandarin", "language_level": ["good command"]}]}, "experience_required": {"duration": [], "field": ["cs", "engineering"]}}, {"job_id": "100003009046660", "location_code": "hk", "company": "Pyrofoe Engineers Ltd", "job_title": "Engineer", "description": "2 years experience min. in Fire Services Installation\nCan work independently\nRequire full-time on site\nGood at ACAD\nApplicant is required to send CV and expected salary to Pyrofoe Engineers Ltd (\u885b\u5b89\u5de5\u7a0b\u6709\u9650\u516c\u53f8) by fax 2385 2150 or email via \"Apply Now\" for interview arrangement.", "employment_types": ["Full Time", "Permanent"], "selling_points": [], "locations": ["Not Specified"], "categories": ["Building & Construction", "Building / Construction / QS", "Engineering", "Electrical / Electronics", "Others"], "post_time": "2022-01-13T18:54:08Z", "salary": {"currency": null, "max": null, "min": null, "period": "monthly", "term": null}, "salary_visible": false, "title_keywords": ["engineer"], "responsibilities": ["installation", "interview arrangement"], "requirements": {"degrees": [], "majors": [], "languages": [], "language_level": [], "hard_skills": [], "soft_skills": ["work independently"], "languages_combined": []}, "experience_required": {"duration": ["2 years"], "field": []}}, {"job_id": "100003009050242", "location_code": "hk", "company": "Trinity Search Limited", "job_title": "Assistant Building Services Engineer -  5 days (Fresh Graduate is welcome)", "description": "Our client is an International Group focusing in air purification business for road tunnel. They are currently looking for the following candidates to join them:\n\nAssistant Building Services Engineer\u00a0\n(Fresh Graduate is also welcome)\n\n5 days work\nAttractive bonus (3-4mths)\nworking location: Kowloon area\n\n\nResponsibilities:\n\nDrawing preparation in BIM and AutoCAD\nDrawing coordination with different parties\nPreparation of relevant method statement\n\nRequirements:\n\nHigher Diploma or above in Electrical / Mechanical /\u00a0Building Services Engineering\nFamiliar in Autocad, knowledge in BIM is a plus\nGood command in English, Mandarin and Cantonese", "employment_types": ["Full Time", "Permanent"], "selling_points": ["ABSE (Fresh Graduate is also welcome)", "5 days work, attractive package", "Air Purification System for road tunnel"], "locations": ["Not Specified"], "categories": ["Engineering", "Electrical / Electronics", "Engineering Project Management"], "post_time": "2022-01-14T10:00:15Z", "salary": {"currency": null, "max": null, "min": null, "period": "monthly", "term": null}, "salary_visible": false, "title_keywords": ["building services engineer", "assistant"], "responsibilities": ["coordination with"], "requirements": {"degrees": ["higher diploma or above"], "majors": ["building services", "engineering"], "languages": ["cantonese", "english", "mandarin"], "language_level": ["good command"], "hard_skills": ["bim", "plus", "autocad"], "soft_skills": [], "languages_combined": [{"language": "cantonese", "language_level": ["good command"]}, {"language": "english", "language_level": ["good command"]}, {"language": "mandarin", "language_level": ["good command"]}]}, "experience_required": {"duration": [], "field": []}}]