[{"job_id": "100003009053404", "location_code": "hk", "company": "Hing Yip Engineering (International) Company Limited", "job_title": "Assistant Project Coordinator (Interior Design)", "description": "Responsibilities:\n\nAssist project managers and designers to coordinate project matters, schedule and report problems.\nTo manage, control and monitor of daily project works, instructions and progress\nCoordinate and liaise with sub-contractors, suppliers, and third party companies\nPrepare weekly progress report for project team and client\u2019s record\nAssist in other ad-hoc assignment\n\nRequirements:\u00a0\n\nDegree / Diploma in Building Studies / Construction Management / Engineering\u00a0or related discipline is an advantage but not a must\nAble to handle multi-tasks under pressure and deadline\nWilling to learn and attention to details\nGood computer literate (AutoCAD, Microsoft Word, Excel)\u00a0is a plus\nCandidates with less experience / Fresh Graduates are also considered\n\nInterested candidates please send us the followings by email or click \"Apply Now'.\n\nFull resume\nPresent / expected salary\nAnything you would like to share with us\n\nWe offer attractive remuneration package, career advancement, various project opportunities to the right candidate.\n\nPlease visit our interior design brand BOKA Design facebook page for more information: www.facebook.com/bokadesignhk\n\n(Personal data collected will be used for recruitment purpose only.)\n", "employment_types": ["Full Time"], "selling_points": ["Manage project fields, work schedule, reporting", "Liaise with designers, contractors, suppliers", "Prepare weekly progress report to project team"], "locations": ["Kwun Tong"], "categories": ["Design", "Interior", "Building & Construction", "Building / Construction / QS", "Engineering", "Engineering Project Management"], "post_time": "2022-01-17T06:55:51Z", "salary": {"currency": null, "max": null, "min": null, "period": "monthly", "term": null}, "salary_visible": false, "title_keywords": ["assistant project coordinator"], "responsibilities": ["ad-hoc", "control", "monitor", "coordinate", "schedule", "liaise with", "third party", "report"], "requirements": {"degrees": ["diploma", "degree"], "majors": ["construction management", "building studies", "engineering"], "languages": [], "language_level": [], "hard_skills": ["excel", "plus", "microsoft word", "autocad"], "soft_skills": ["willing to learn", "under pressure", "attention to details", "multi-tasks"], "languages_combined": []}, "experience_required": {"duration": [], "field": []}}, {"job_id": "100003009054034", "location_code": "hk", "company": "NEC Hong Kong Limited", "job_title": "Project Engineer", "description": "Responsibilities:\u00a0\n\n\nAssist in project implementation, testing & commissioning, quality assurance and documentation;\u00a0\nProvide first line maintenance service to network and LED display panels;\nAssist in installation and configuration of network and computer systems;\nManage contractors\u2019 work progress to fulfill the project requirement; and\nHandle ad hoc tasks as assigned.\nRequirements:\n\nHigher Diploma or above in Electronic Engineering or IT-related\u00a0disciplines;\nAt least 3 years' relevant experiences in IT and or ELV equipment installation, maintenance and trouble shooting;\n\nKnowledge in network switches, PC/Server setup and configuration;\nHands-on knowledge of AutoCAD is highly preferable;\nSelf-motivated and able to work independently under tight deadline with minimum supervision;\nGood command of spoken English, Cantonese and Mandarin.\n\nPlease send your full detailed resume with expected salary and date available to The Human Resources Manager, NEC Hong Kong Limited, 25th Floor, The Metropolis Tower, 10 Metropolis Drive, Hunghom, Kowloon or by e-mail.\n\nPersonal data provided by job applicant will be used strictly in accordance with employer's personal data policy, a copy of which will be provided immediately upon request.", "employment_types": ["Full Time", "Permanent"], "selling_points": ["3 yrs in project implementation", "knowledge in network switches, server & PC setup", "experience in using AutoCAD preferred"], "locations": ["Not Specified"], "categories": ["Engineering", "Engineering Project Management", "Information Technology (IT)", "Support", "Network & System"], "post_time": "2022-01-17T08:08:53Z", "salary": {"currency": null, "max": null, "min": null, "period": "monthly", "term": null}, "salary_visible": false, "title_keywords": ["project engineer"], "responsibilities": ["installation", "commissioning", "maintenance", "configuration", "quality", "implementation", "computer systems", "testing", "ad hoc tasks", "documentation"], "requirements": {"degrees": ["higher diploma or above"], "majors": ["related disciplines", "it", "engineering"], "languages": ["cantonese", "english", "mandarin"], "language_level": ["good command"], "hard_skills": ["server", "pc", "maintenance", "autocad"], "soft_skills": ["hands-on", "work independently", "self-motivated", "detailed"], "languages_combined": [{"language": "cantonese", "language_level": ["good command"]}, {"language": "english", "language_level": ["good command"]}, {"language": "mandarin", "language_level": ["good command"]}]}, "experience_required": {"duration": ["at least 3 years"], "field": ["installation", "it", "maintenance"]}}, {"job_id": "100003009052355", "location_code": "hk", "company": "Sheenway (Hong Kong) Limited", "job_title": "Project Engineer (5-day week)", "description": "University degree, major\u00a0in Electrical & Electronic Engineering is preferred\n2 years or above experience in product development and project management of consumer electronic products\nCapability in understanding BOM, schematic diagram & 3D drawing will be an advantage\nSound communication & negotiation skills\nGood written and spoken English, Chinese & Mandarin\nProficiency in MS Office & other PC software\nResponsible, self-initiation, aggressive and work under pressure\nRequired to travel to China periodically\nImmediate available", "employment_types": ["Full Time", "Permanent"], "selling_points": [], "locations": ["Tsim Sha Tsui"], "categories": ["Engineering", "Electrical / Electronics", "Engineering Project Management", "Manufacturing", "Product Development / Management"], "post_time": "2022-01-17T02:50:45Z", "salary": {"currency": null, "max": null, "min": null, "period": "monthly", "term": null}, "salary_visible": false, "title_keywords": ["project engineer"], "responsibilities": ["communication", "project management", "work under pressure", "pc software"], "requirements": {"degrees": ["university degree"], "majors": ["engineering"], "languages": ["english", "chinese", "mandarin"], "language_level": ["good"], "hard_skills": ["pc", "project management", "ms office"], "soft_skills": ["responsible", "communication", "project management", "negotiation skills", "work under pressure"], "languages_combined": [{"language": "english", "language_level": ["good"]}, {"language": "chinese", "language_level": ["good"]}, {"language": "mandarin", "language_level": ["good"]}]}, "experience_required": {"duration": ["2 years"], "field": ["project management", "product development"]}}, {"job_id": "100003008605664", "location_code": "hk", "company": "Biocline Healthcare Services Ltd", "job_title": "Project Engineer/ Assistant Project Engineer", "description": "Reporting to Project Manager, you will work with a growing team of project engineers and direct labour responsible for the installation process to ensure that engineering design, procurement, project planning and coordination, site installation, testing and commissioning, inspection and handover to the clients are executed at a high safety and quality standard.\n\nProject opportunities include but not limited to:\n\nSupply & Installation of Modular Operating Theatres at Kwong Wah Hospital\u00a0\nDesign & Build Laboratory Projects at Hong Kong Science Park\u00a0\nDesign of Chinese Medicine Hospital's Laboratory Building\u00a0\nMedical Gas Pipeline System Installation of Kwai Chung Hospital & Tsuen Wan Adventist Hospital\u00a0\n\nRequirements:\n\nDegree or Higher Diploma in Building Services / Mechanical Engineering or relevant disciplines;\nElect / MVAC / MGPS installation experience, preferably with main contractors or E&M contractors\nRelevant work experience in Hospital/University/Laboratory projects is advantageous\u00a0\nDetail-oriented with strong safety awareness and problem solving skills;\nIndependent and able to work under pressure and tight schedule;\nProficiency in written and spoken English and Chinese;\nLess experience will be considered an assistant project engineer grade.", "employment_types": ["Full Time"], "selling_points": [], "locations": ["Not Specified"], "categories": ["Engineering", "Engineering Project Management", "Mechanical"], "post_time": "2022-01-17T09:10:25Z", "salary": {"currency": null, "max": null, "min": null, "period": "monthly", "term": null}, "salary_visible": false, "title_keywords": ["assistant project engineer", "project engineer"], "responsibilities": ["reporting", "project planning", "installation", "engineering design", "commissioning", "quality", "design", "testing", "inspection", "schedule", "coordination", "work under pressure"], "requirements": {"degrees": ["diploma", "degree"], "majors": ["building services", "mechanical engineering"], "languages": ["english", "chinese"], "language_level": ["proficiency"], "hard_skills": ["problem solving skills", "wan"], "soft_skills": ["independent", "responsible", "detail-oriented", "coordination", "problem solving skills", "work under pressure"], "languages_combined": [{"language": "english", "language_level": ["proficiency"]}, {"language": "chinese", "language_level": ["proficiency"]}]}, "experience_required": {"duration": [], "field": ["installation", "laboratory"]}}, {"job_id": "100003009055325", "location_code": "hk", "company": "Unistress Building Construction Limited", "job_title": "Assistant Project Coordinator / Assistant Engineer", "description": "Requirements:\n\nHigh Certificate / Higher Diploma / Degree in Building Studies or Structural Engineering\nRelevant 1 years site working experience in building projects with Main Contractor\nHard working and good interpersonal skill\nImmediate available preferred\u00a0\u00a0\n\n\nIf interested, please send full resume to the above E-mail or click \"APPLY NOW\".", "employment_types": ["Full Time", "Permanent"], "selling_points": ["High Cert / Higher Dip / Degree in BuildingStudies", "Relevant 2 years site working experience", "Hard working and good interpersonal skill"], "locations": ["Not Specified"], "categories": ["Building & Construction", "Building / Construction / QS", "Civil / Structural", "Engineering", "Engineering Project Management"], "post_time": "2022-01-18T02:11:33Z", "salary": {"currency": null, "max": null, "min": null, "period": "monthly", "term": null}, "salary_visible": false, "title_keywords": ["assistant project coordinator", "assistant engineer"], "responsibilities": [], "requirements": {"degrees": ["certificate", "diploma", "degree"], "majors": ["building studies", "structural engineering"], "languages": [], "language_level": [], "hard_skills": [], "soft_skills": ["hard working", "interpersonal skill"], "languages_combined": []}, "experience_required": {"duration": ["1 years"], "field": []}}, {"job_id": "100003009052645", "location_code": "hk", "company": "Kamui Group Development Limited", "job_title": "Assistant Project Manager/ Project Officer \u2013 Project Management", "description": "Responsibilities:\n\n\nParticipate in new development or alteration projects from planning, execution to completion\nAssist the Project Manager in overseeing and controlling the quality and progress of projects\nAssist the Project Manager for document checking\nConduct site visits and prepare project progress reports\nLiaison with clients, internal departments, external consultants and sub - contractors\nCompile and maintain documentation including specifications, tender document, time & cost control reports\n\nRequirements:\n\n\nDegree holder in building/ engineering/ construction studies\nGood command of written & spoken English & Mandarin\nMinimum 5 year\u2019s relevant working experience\nProactive, well-organized and self-motivated\nProficiency in PC applications including MS Office & Project applications\nFamiliar with Auto-CAD, Photoshop, Sketchup and other graphic presentation software\nCandidate with less experience will be considered as Project Officer", "employment_types": ["Full Time"], "selling_points": ["New development & renovation", "Project Management", "Logistic & Industrial Sector"], "locations": ["Shatin Area"], "categories": ["Building & Construction", "Building / Construction / QS", "Civil / Structural", "Engineering", "Engineering Project Management"], "post_time": "2022-01-17T03:38:15Z", "salary": {"currency": null, "max": null, "min": null, "period": "monthly", "term": null}, "salary_visible": false, "title_keywords": ["assistant project manager", "project officer"], "responsibilities": ["quality", "project progress", "checking", "specifications", "reports", "cost control", "maintain documentation", "tender document", "planning"], "requirements": {"degrees": ["degree holder"], "majors": ["engineering"], "languages": ["english", "mandarin"], "language_level": ["good command"], "hard_skills": ["cad", "pc applications", "photoshop", "ms office", "sketchup"], "soft_skills": ["self-motivated", "proactive", "well-organized", "presentation"], "languages_combined": [{"language": "english", "language_level": ["good command"]}, {"language": "mandarin", "language_level": ["good command"]}]}, "experience_required": {"duration": ["minimum 5 year"], "field": ["relevant working experience"]}}, {"job_id": "100003009053102", "location_code": "hk", "company": "Lik Kai Engineering Company Limited", "job_title": "Senior Engineer / Engineer / Assistant Engineer (Electrical) (5-day work)", "description": "This is a fixed-term contract position of minimum 2 years with possibility for renewal subject to organization need and individual performance.\n\nResponsibilities:\n\nProviding technical assistance in design and site supervision of the Airport Systems Works\nAssisting in leading design consultants and construction contractors to ensure the airport systems design, programme and budget requirements are met\nReviewing the design and proposals from consultants and contractors to ensure compliance with sound engineering principles and required standards in terms of quality and safety\nCoordinating design and construction interface issues and proactively resolve potential clashes\nProviding technical support to site supervision teams including responding to request for information and preparing design change documents\nSupervising the installation and commissioning of the systems, site acceptance tests and commissioning programmes in conjunction with project owners and users\n\nRequirements:\n\nDegree holder in Electronic or Electrical Engineering or related disciplines with at least 6 years of relevant experience, of which at least 3 years in project management role.\nProfessional qualification in Electronic/ Electrical Engineering or other related disciplines gained from recognized professional bodies is preferred\nSound technical knowledge in design and implementation of the airport, airfield and apron systems in particular on Access Control System, CCTV System, Public Address System, Trunk Mobile Radio System and E&M Control Systems.\nProven experience in management of system integration project of systems design, planning, construction works and site supervisory works.\nProactive mindset with strong communication, analytical and negotiation skills\nExcellent command of spoken and written English and Chinese with knowledge of Putonghua is an advantage.\nProficient in Microsoft Office application and project management software tools.\nHolder of a valid HK driving license (Class 1, 2) is preferred", "employment_types": ["Full Time", "Permanent"], "selling_points": ["Holder of Degree / Higher Diploma", "5 years' proven experience in project execution", "Assist Project Manager in electrical project"], "locations": ["Not Specified"], "categories": ["Engineering", "Electrical / Electronics", "Engineering Project Management", "Mechanical"], "post_time": "2022-01-17T05:51:19Z", "salary": {"currency": null, "max": null, "min": null, "period": "monthly", "term": null}, "salary_visible": false, "title_keywords": ["senior engineer", "assistant engineer", "engineer"], "responsibilities": ["installation", "supervising", "commissioning", "site supervision", "technical support", "systems", "budget", "quality", "design", "ensure compliance", "teams", "technical assistance"], "requirements": {"degrees": ["degree holder"], "majors": ["related disciplines", "project management", "electrical engineering"], "languages": ["putonghua", "english", "chinese"], "language_level": ["advantage", "excellent"], "hard_skills": ["microsoft office", "cctv", "project management", "mobile", "integration"], "soft_skills": ["communication", "project management", "negotiation skills", "proactive"], "languages_combined": [{"language": "putonghua", "language_level": ["advantage", "excellent"]}, {"language": "english", "language_level": ["advantage", "excellent"]}, {"language": "chinese", "language_level": ["advantage", "excellent"]}]}, "experience_required": {"duration": ["at least 6 years", "at least 3 years"], "field": ["management", "supervisory", "engineering", "related", "design", "project management", "relevant experience", "construction", "planning"]}}, {"job_id": "100003009054076", "location_code": "hk", "company": "Jetline Construction Co., Limited", "job_title": "Building Services Coordinator / Assistant Building Services Coordinator", "description": "Job Responsibilities:\n\nAssist Project Manager in electrical project execution & tender estimation\nLiaise and communicate with client, architect, consultant, main contractor and others\nSupervise subcontractor performance\nPrepare tenders, job budget, drawing and equipment submission for new projects or A&A works\n\nJob Requirements:\n\nHolder of Degree / Higher Diploma in Building Services / Electrical Engineering or equivalent\nAt least 5 years' proven experience in project execution\nGood command of both written and spoken Chinese and English\n\nKnowledge in PowerPoint, MS Word, Excel, Chinese Word Processing and AutoCAD\n\nCandidates with less experience will be considered as Assistant Engineer.\n\nGood remuneration and attractive benefits will be offered to the right person. Interested parties please send full resume with expected salary via \"APPLY NOW\"\u00a0or by fax: 2611-4654 or by post to The Human Resources & Administration Department - Recruitment & Selection Section, Lik Kai Engineering Co., Ltd. 5th Floor, New East Sun Industrial Building, No. 18 Shing Yip Street, Kwun Tong, Kowloon.\n\nWe are an Equal Opportunity Employer. Personal data collected will be used for recruitment purpose only.", "employment_types": ["Full Time", "Permanent"], "selling_points": ["Bonus twice a year", "11 days Annual Leave, 5.5 days, bank holiday", "Work life balance"], "locations": ["Not Specified"], "categories": ["Building & Construction", "Building / Construction / QS", "Civil / Structural", "Engineering", "Engineering Project Management"], "post_time": "2022-01-17T08:19:28Z", "salary": {"currency": null, "max": null, "min": null, "period": "monthly", "term": null}, "salary_visible": false, "title_keywords": ["coordinator", "assistant"], "responsibilities": ["liaise", "communicate with client", "budget", "tender"], "requirements": {"degrees": ["diploma", "degree"], "majors": ["building services", "electrical engineering"], "languages": ["english", "chinese"], "language_level": ["good command"], "hard_skills": ["excel", "chinese word processing", "ms word", "powerpoint", "autocad"], "soft_skills": [], "languages_combined": [{"language": "english", "language_level": ["good command"]}, {"language": "chinese", "language_level": ["good command"]}]}, "experience_required": {"duration": ["at least 5 years"], "field": []}}, {"job_id": "100003009054131", "location_code": "hk", "company": "Luen Hop Metal and Aluminium Engineering Company Limited", "job_title": "Senior PROJECT COORDINATOR", "description": "This is a fixed-term contract position of minimum 2 years with possibility for renewal subject to organization need and individual performance.\n\nThe incumbent is responsible for providing support to the Senior Project Engineer in civil and building works.\u00a0 This involves ensuring that the works are designed, specified and built to achieve the required level of service; to specified standards of materials and workmanship; and that they are completed safely, on time and within budget to the satisfaction of the Authority.\n\n\nResponsibilities:\n\nProviding technical assistance in the design and site supervision of the civil and viaduct\u00a0works;\nEnsuring that the consultants\u2019/contractors\u2019 proposals and works are technically sound and safe;\nUndertaking interface/coordination related to civil/viaduct\u00a0works;\nReview of design submissions and technical reports;\nMonitoring statutory submission of the consultants\u2019 design works;\nCarry out site supervision teams including responding to request for information and preparing design change documents; and\nCollaboratively working with the Contractors to ensure the works are completed on time and within budget to a high level of quality.\n\nRequirements:\n\nBachelor's degree in Civil / Structural Engineering or related disciplines with at least 6 years\u2019 relevant experience, of which minimum of 3 years should be in project management\nMember of HKIE or other equivalent professional bodies\nExperience in the management of pre-stressing R.C. viaduct; road and utlilities construction and site supervisory works\nExperience in construction supervision in operational areas and in the management of\u00a0statutory submission to Buildings Department and relevant authorities is preferred\nStrong communication, analytical and negotiation skills\nGood command of spoken and written English and Chinese. Knowledge of Putonghua is an advantage\nProficient in MS Office applications and project management software tools\nKnowledge of CADD software such as Microstation or AutoCAD is an advantage\nKnowledge of BIM software is preferred", "employment_types": ["Full Time"], "selling_points": ["Attend project coordination meeting w/ Consultant", "12 Days AL and bonus", "5 Year(s) or above Experience Required"], "locations": ["Shatin Area"], "categories": ["Building & Construction", "Building / Construction / QS", "Engineering", "Engineering Project Management", "Others"], "post_time": "2022-01-17T08:30:28Z", "salary": {"currency": "HKD", "max": 29999, "min": 20000, "period": "monthly", "term": null}, "salary_visible": true, "title_keywords": ["senior project coordinator"], "responsibilities": ["site supervision", "review", "monitoring", "teams", "design", "budget", "quality", "reports", "coordination", "technical assistance"], "requirements": {"degrees": ["degree", "bachelor"], "majors": ["related disciplines", "project management", "structural engineering"], "languages": ["putonghua", "english", "chinese"], "language_level": ["advantage", "good command"], "hard_skills": ["hkie", "project management", "bim", "c", "autocad", "r", "ms office"], "soft_skills": ["communication", "project management", "negotiation skills"], "languages_combined": [{"language": "putonghua", "language_level": ["advantage"]}, {"language": "english", "language_level": ["good command"]}, {"language": "chinese", "language_level": ["good command"]}]}, "experience_required": {"duration": ["at least 6 years", "minimum of 3 years"], "field": ["management", "engineering", "related", "structural", "project management", "relevant experience", "construction"]}}, {"job_id": "100003009054696", "location_code": "hk", "company": "Teammate Technology Engineering Limited", "job_title": "Assistant Engineer / Engineer Trainee", "description": "Responsibilities:\n\nCoordinate with E&M and work activities on sites as required.\nFollowing up project details and monitor project progress.\n\nRequirements:\n\nHigh Diploma or above in Building Services / Engineering / Electrical & Mechanical Engineering or related disciplines.\n3-10 years relevant experience, 0-3 years' will be considered as Assistant Building Services Coordinator.\n\nComputer knowledge for ACAD, MS Office, MS Project.\nWilling to learn and work hard.\nImmediate availability is highly preferable\u00a0.\n\nInterest parties, please send your detailed CV with expected salary by clicking \u201cApply Now\u201d.\u00a0\n\nAll Personal data collected will be used for recruitment purpose only.", "employment_types": ["Full Time", "Permanent"], "selling_points": ["Co-ordinate and liaise with client, subcontractors", "Assist the project manager plan, execute projects", "Immediate available is highly preferred"], "locations": ["Lai Chi Kok"], "categories": ["Building & Construction", "Building / Construction / QS", "Engineering", "Electrical / Electronics", "Engineering Project Management"], "post_time": "2022-01-17T10:36:52Z", "salary": {"currency": null, "max": null, "min": null, "period": "monthly", "term": null}, "salary_visible": false, "title_keywords": ["assistant engineer", "engineer", "trainee"], "responsibilities": ["monitor project progress", "coordinate with"], "requirements": {"degrees": ["high diploma or above"], "majors": ["related disciplines", "building services", "engineering", "mechanical engineering"], "languages": [], "language_level": [], "hard_skills": ["ms office"], "soft_skills": ["willing to learn", "detailed"], "languages_combined": []}, "experience_required": {"duration": ["0-3 years", "3-10 years"], "field": ["building services", "relevant experience"]}}, {"job_id": "100003009054971", "location_code": "hk", "company": "Mesan Fiberglass Engineering (International) Limited", "job_title": "Project Engineer", "description": "Requirement :\n\nDegree/High Diploma in Civil / Structural / Mechanical / Electrical Engineering or related disciplines\nMin 2 years\u2019 relevant experience in building projects / construction site\nFamiliar with HK Building Regulations\nGood team player with excellent communication and presentation skills. Good technical knowledge and analytical thinking.\nPleasant character, independent and responsible.\nFluent in spoken and written English; Mandarin would be an advantage.\nImmediate availability would be preferred\nJob Responsibilities:\n\nSite Coordination with the client\u2019s representatives, consultants, engineers and all related parties including supervision of sub-contractors to ensure installation to be completed on time.\nPreparation of drawings (CAD); required documents; correspondence; program and submissions.\nHand over the completed installation to clients including testing and commissioning; supervision of defects rectification or remedial works", "employment_types": ["Full Time"], "selling_points": ["We offer 5 days work", "Attractive remuneration and benefits package", "Min 2 years\u2019 relevant experience"], "locations": ["Wong Tai Sin Area"], "categories": ["Building & Construction", "Civil / Structural", "Engineering", "Engineering Project Management", "Manufacturing & Production"], "post_time": "2022-01-17T16:22:38Z", "salary": {"currency": null, "max": null, "min": null, "period": "monthly", "term": null}, "salary_visible": false, "title_keywords": ["project engineer"], "responsibilities": ["installation", "commissioning", "rectification", "testing", "drawings", "site coordination"], "requirements": {"degrees": ["high diploma", "degree"], "majors": ["related disciplines", "electrical engineering"], "languages": ["english", "mandarin"], "language_level": ["advantage", "fluent"], "hard_skills": [], "soft_skills": ["good team player", "independent", "responsible", "pleasant", "communication", "presentation skills"], "languages_combined": [{"language": "english", "language_level": ["fluent"]}, {"language": "mandarin", "language_level": ["advantage"]}]}, "experience_required": {"duration": ["min 2 years"], "field": ["relevant experience", "construction"]}}, {"job_id": "100003009055735", "location_code": "hk", "company": "Airport Authority Hong Kong", "job_title": "Project Engineer, Systems", "description": "This is a fixed-term contract position of minimum 2 years with possibility for renewal subject to organization need and individual performance.\n\nResponsibilities:\n\nProviding technical assistance in design and site supervision of the Airport Systems Works\nAssisting in leading design consultants and construction contractors to ensure the airport systems design, programme and budget requirements are met\nReviewing the design and proposals from consultants and contractors to ensure compliance with sound engineering principles and required standards in terms of quality and safety\nCoordinating design and construction interface issues and proactively resolve potential clashes\nProviding technical support to site supervision teams including responding to request for information and preparing design change documents\nSupervising the installation and commissioning of the systems, site acceptance tests and commissioning programmes in conjunction with project owners and users\n\nRequirements:\n\nDegree holder in Electronic or Electrical Engineering or related disciplines with at least 6 years of relevant experience, of which at least 3 years in project management role.\nProfessional qualification in Electronic/ Electrical Engineering or other related disciplines gained from recognized professional bodies is preferred\nSound technical knowledge in design and implementation of the airport, airfield and apron systems in particular on Access Control System, CCTV System, Public Address System, Trunk Mobile Radio System and E&M Control Systems.\nProven experience in management of system integration project of systems design, planning, construction works and site supervisory works.\nProactive mindset with strong communication, analytical and negotiation skills\nExcellent command of spoken and written English and Chinese with knowledge of Putonghua is an advantage.\nProficient in Microsoft Office application and project management software tools.\nHolder of a valid HK driving license (Class 1, 2) is preferred", "employment_types": ["Full Time"], "selling_points": ["Technical assistance in system design&supervision", "Review design&proposal from consultants&contractor", "Supervise installation and system commissioning"], "locations": ["Airport Area"], "categories": ["Engineering", "Electrical / Electronics", "Engineering Project Management"], "post_time": "2022-01-18T02:54:02Z", "salary": {"currency": null, "max": null, "min": null, "period": "monthly", "term": null}, "salary_visible": false, "title_keywords": ["project engineer"], "responsibilities": ["installation", "supervising", "commissioning", "site supervision", "technical support", "systems", "budget", "quality", "design", "ensure compliance", "teams", "technical assistance"], "requirements": {"degrees": ["degree holder"], "majors": ["related disciplines", "project management", "electrical engineering"], "languages": ["putonghua", "english", "chinese"], "language_level": ["advantage", "excellent"], "hard_skills": ["microsoft office", "cctv", "project management", "mobile", "integration"], "soft_skills": ["communication", "project management", "negotiation skills", "proactive"], "languages_combined": [{"language": "putonghua", "language_level": ["advantage", "excellent"]}, {"language": "english", "language_level": ["advantage", "excellent"]}, {"language": "chinese", "language_level": ["advantage", "excellent"]}]}, "experience_required": {"duration": ["at least 6 years", "at least 3 years"], "field": ["management", "supervisory", "engineering", "related", "design", "project management", "relevant experience", "construction", "planning"]}}, {"job_id": "100003009055731", "location_code": "hk", "company": "Airport Authority Hong Kong", "job_title": "Project Engineer (Viaduct)", "description": "This is a fixed-term contract position of minimum 2 years with possibility for renewal subject to organization need and individual performance.\n\nThe incumbent is responsible for providing support to the Senior Project Engineer in civil and building works.\u00a0 This involves ensuring that the works are designed, specified and built to achieve the required level of service; to specified standards of materials and workmanship; and that they are completed safely, on time and within budget to the satisfaction of the Authority.\n\n\nResponsibilities:\n\nProviding technical assistance in the design and site supervision of the civil and viaduct\u00a0works;\nEnsuring that the consultants\u2019/contractors\u2019 proposals and works are technically sound and safe;\nUndertaking interface/coordination related to civil/viaduct\u00a0works;\nReview of design submissions and technical reports;\nMonitoring statutory submission of the consultants\u2019 design works;\nCarry out site supervision teams including responding to request for information and preparing design change documents; and\nCollaboratively working with the Contractors to ensure the works are completed on time and within budget to a high level of quality.\n\nRequirements:\n\nBachelor's degree in Civil / Structural Engineering or related disciplines with at least 6 years\u2019 relevant experience, of which minimum of 3 years should be in project management\nMember of HKIE or other equivalent professional bodies\nExperience in the management of pre-stressing R.C. viaduct; road and utlilities construction and site supervisory works\nExperience in construction supervision in operational areas and in the management of\u00a0statutory submission to Buildings Department and relevant authorities is preferred\nStrong communication, analytical and negotiation skills\nGood command of spoken and written English and Chinese. Knowledge of Putonghua is an advantage\nProficient in MS Office applications and project management software tools\nKnowledge of CADD software such as Microstation or AutoCAD is an advantage\nKnowledge of BIM software is preferred", "employment_types": ["Full Time"], "selling_points": ["Bachelor degree in Civil / Structural Engineering", "6 years' relevant working experience", "Member of HKIE or other professional bodies"], "locations": ["Airport Area"], "categories": ["Engineering", "Engineering Project Management"], "post_time": "2022-01-18T02:53:52Z", "salary": {"currency": null, "max": null, "min": null, "period": "monthly", "term": null}, "salary_visible": false, "title_keywords": ["project engineer"], "responsibilities": ["site supervision", "review", "monitoring", "teams", "design", "budget", "quality", "reports", "coordination", "technical assistance"], "requirements": {"degrees": ["degree", "bachelor"], "majors": ["related disciplines", "project management", "structural engineering"], "languages": ["putonghua", "english", "chinese"], "language_level": ["advantage", "good command"], "hard_skills": ["hkie", "project management", "bim", "c", "autocad", "r", "ms office"], "soft_skills": ["communication", "project management", "negotiation skills"], "languages_combined": [{"language": "putonghua", "language_level": ["advantage"]}, {"language": "english", "language_level": ["good command"]}, {"language": "chinese", "language_level": ["good command"]}]}, "experience_required": {"duration": ["at least 6 years", "minimum of 3 years"], "field": ["management", "engineering", "related", "structural", "project management", "relevant experience", "construction"]}}, {"job_id": "100003009054684", "location_code": "hk", "company": "Teammate Technology Engineering Limited", "job_title": "Project Administrator / Assistant", "description": "Responsibilities\n\nAssist and support project manager in all aspects of project follow up such as material planning, site coordination, schedule planning, procurement etc.\nAssist in tendering and cost analysis\nProvide project administration and filing\nResponsible for general project coordination\n\nRequirements\n\nDiploma or above qualification\nAt least 2 years relevant experience on project administration\nCandidates with less experience will be considered as Project Assistant\nImmediate available is highly preferred\n\nWe offer an attractive remuneration package, training and good career opportunities to the right candidate.\u00a0 Interested parties are invited to send your application enclosing full resume stating career and salary history (either in Word format or PDF format) to the HR Department by\u00a0Whatsapp to 9306-7864, or by\u00a0fax to 2370-2073 or click Apply Now.\n\nApplicants not invited for an interview within two months may consider their applications unsuccessful.\u00a0 All personal data collected will be used for recruitment purpose only.\n\n", "employment_types": ["Full Time", "Permanent"], "selling_points": ["Support project manager in all aspects of project", "Assist in tendering and cost analysis", "Immediate available is highly preferred"], "locations": ["Lai Chi Kok"], "categories": ["Building & Construction", "Building / Construction / QS", "Engineering", "Electrical / Electronics", "Engineering Project Management"], "post_time": "2022-01-17T10:33:09Z", "salary": {"currency": null, "max": null, "min": null, "period": "monthly", "term": null}, "salary_visible": false, "title_keywords": ["assistant", "project administrator"], "responsibilities": ["project follow up", "project coordination", "tendering", "site coordination", "schedule", "project administration", "cost analysis", "planning"], "requirements": {"degrees": ["diploma or above"], "majors": [], "languages": [], "language_level": [], "hard_skills": [], "soft_skills": [], "languages_combined": []}, "experience_required": {"duration": ["at least 2 years"], "field": ["relevant experience", "administration"]}}, {"job_id": "100003009052228", "location_code": "hk", "company": "Nan Fung Group", "job_title": "SENIOR TECHNICAL OFFICER / TECHNICAL OFFICER", "description": "Requirement:\u00a0\n\nHigher Diploma in Building Services Engineering / Building Studies or related disciplines is preferred.\nHolder of Certificate of Registration of Electrical Worker in Grade A or above.\nMinimum 5 years' experience in property maintenance.\nFamiliar with related ordinances and professional maintenance practices.\nGood communication and interpersonal skills.\nResult-oriented, self-motivated and able to work under pressure.\nGood PC skills in MS Words, Excel and Chinese Word-processing etc.\nGood command of both written and spoken English and Chinese.\nCandidate with less experience will be considered as Assistant Technical Officer.\n\n\u00a0Key Responsibility:\u00a0\n\nAssist to carry out routine maintenance and operation works.\nPrepare specifications and tender documents for repair and maintenance works.\nHandle owner\u2019s / tenant\u2019s requests on technical aspects.\nMonitor the performance of building facilities.\nPrepare equipment and inventory lists.\nSupervise and carry out Testing and commissioning.\n\n\u00a0We provide generous compensation and fringe benefits to the right candidates. Please send your full resume with salary expected to The Human Resources Manager, 23/F., Nan Fung Tower, 88 Connaught Road C, Central, HK\u00a0or by E-mail: hr @ pm.nanfung.com or by\u00a0clicking\u00a0\"Apply Now\"\u00a0below\u00a0(We are an equal opportunity employer. All applications will be treated in strict confidence and only be used for selection purpose.)\n\nFor further information about Personal Information Collection Statement (\u201cPICS\u201d) Pertaining to Recruitment, please click the link below\u00a0www.nanfung.com/en/common/pics/.\n\n\u201cNan Fung Group\u201d and \u201cthe Group\u201d mean Nan Fung International Holdings Limited and its subsidiaries.", "employment_types": ["Full Time", "Permanent"], "selling_points": ["Higher Diploma in Building Services Engineering", "5 years' experience in property maintenance", "Certificate of Registration of Electrical Worker"], "locations": ["Not Specified"], "categories": ["Engineering", "Electrical / Electronics", "Engineering Project Management", "Others"], "post_time": "2022-01-17T02:31:07Z", "salary": {"currency": null, "max": null, "min": null, "period": null, "term": null}, "salary_visible": false, "title_keywords": ["technical officer", "senior technical officer"], "responsibilities": ["commissioning", "maintenance", "tender documents", "inventory", "testing", "specifications", "monitor the performance", "repair and maintenance works"], "requirements": {"degrees": ["certificate", "diploma"], "majors": ["related disciplines", "building studies", "building services", "engineering"], "languages": ["english", "chinese"], "language_level": ["good command", "good"], "hard_skills": ["excel", "chinese word-processing", "maintenance", "ms words", "certificate of registration of electrical worker", "pc skills"], "soft_skills": ["self-motivated", "communication and interpersonal skills", "result-oriented", "work under pressure"], "languages_combined": [{"language": "english", "language_level": ["good command", "good"]}, {"language": "chinese", "language_level": ["good command", "good", "good"]}]}, "experience_required": {"duration": ["minimum 5 years"], "field": ["maintenance"]}}, {"job_id": "100003009052926", "location_code": "hk", "company": "T W Design Consultants Limited", "job_title": "ASSOCIATE [Ref.TWD-A]", "description": "Degree holder in Electrical Engineering, Mechanical Engineering, Building Services Engineering or related disciplines\nMember of HKIE, Chartered Engineer of CIBSE or equivalent\nMinimum 12 years' experience, preferably with E&M consultants and/or developers\nTo prepare tender documents / drawings, tender analysis / report and systems design / vetting\nTo supervise testing and commissioning, approve drawing and material submissions and supervise statutory submission work\nFluent in written and spoken English and Chinese, including Putonghua\n\nWe offer salary and benefits commensurate with qualifications and experience. Please send a full resume with contact number and expected salary to General Manager - Human Resources & Administration, T W Design\u00a0Consultants Limited, 3/F., One Harbourfront, 18 Tak Fung Street, Hunghom, Kowloon (Please quote reference on envelope) or by clicking \"Apply Now\".\n\nWe are an equal opportunity employer and welcome applications from all qualified candidates. The information provided will be treated in strict confidence and be used only for consideration of your application for relevant/similar post(s).\n\nApplicants not hearing from us within six weeks from the date of advertisement may consider their applications unsuccessful. All personal data of unsuccessful applicants will be destroyed after the recruitment exercise when no longer required.", "employment_types": ["Full Time", "Permanent"], "selling_points": ["Degree holder in Engineering", "Member of HKIE, Chartered Engineer of CIBSE", "Minimum 12 years' relevant working experience"], "locations": ["Hung Hom"], "categories": ["Building & Construction", "Building / Construction / QS", "Engineering", "Engineering Project Management", "Mechanical"], "post_time": "2022-01-17T07:26:03Z", "salary": {"currency": null, "max": null, "min": null, "period": null, "term": null}, "salary_visible": false, "title_keywords": ["associate"], "responsibilities": ["commissioning", "prepare tender documents", "systems", "design", "drawings", "tender analysis", "testing", "report"], "requirements": {"degrees": ["degree holder"], "majors": ["engineering", "electrical engineering", "mechanical engineering", "related disciplines", "building services"], "languages": ["putonghua", "english", "chinese"], "language_level": ["fluent"], "hard_skills": ["analysis", "hkie"], "soft_skills": [], "languages_combined": [{"language": "putonghua", "language_level": ["fluent"]}, {"language": "english", "language_level": ["fluent"]}, {"language": "chinese", "language_level": ["fluent"]}]}, "experience_required": {"duration": ["minimum 12 years"], "field": []}}, {"job_id": "100003009052519", "location_code": "hk", "company": "Cayee Network Systems Limited", "job_title": "Sales and Project Engineer/ Coordinator", "description": "Assist in technical proposal preparation, tender preparation, price and cost estimation, design, and project implementation\nHandle enquiries, understand client requirements, identify possible solutions and create high customer satisfaction\nWork\u00a0with\u00a0application development\u00a0team\u00a0to\u00a0provide IoT\u00a0Solution\n(HMI/GUI/SCADA platform, industrial\u00a0ethernet networking devices,\u00a0wireless communication)\nSupport\u00a0project\u00a0initiation\u00a0including\u00a0gather\u00a0requirements\u00a0and\u00a0technical\u00a0details\u00a0to\u00a0conduct\u00a0feasibility\u00a0study\u00a0\nPrepare\u00a0and\u00a0submit\u00a0assurance\u00a0plan\u00a0result\u00a0for\u00a0management\u00a0review\nParticipate\u00a0in\u00a0in-house\u00a0IT\u00a0related\u00a0projects\u00a0and\u00a0other\u00a0adhoc\u00a0assigned\u00a0duties\n\nJob Requirements:\n\nResponsible,\u00a0initiative,\u00a0diligent,\u00a0responsible\u00a0and\u00a0with\u00a0strong\u00a0attention\u00a0to\u00a0details;\nInterested\u00a0in\u00a0Industrial\u00a0IoT\u00a0solution,\u00a0IT\u00a0systems\u00a0and\u00a0digital\u00a0project\u00a0development\nGood\u00a0command\u00a0of\u00a0spoken\u00a0and\u00a0written\u00a0Cantonese,\u00a0Putonghua\u00a0and\u00a0English;\nAny\u00a0relevant\u00a0digital\u00a0project\u00a0experience\u00a0would\u00a0be\u00a0an\u00a0advantage.\nTechnical\u00a0Development\u00a0School\u00a0or\u00a0above are\u00a0welcome\u00a0to\u00a0apply.\u00a0\n\nFeel free to visit our website www.cayee.com.hk for more information.\n\nApplicants please submit your full resume with present and expected salary to sales@ cayee.com.hk for an interview or click \"APPLY NOW\" to submit your application.\n(Data collected will be used for recruitment purpose only)", "employment_types": ["Full Time", "Part Time", "Permanent", "Temporary", "Contract", "Internship", "Freelance"], "selling_points": ["Fresh graduate and all fields are welcome to apply", "Industrial Networking, Automation, IoT solutions", "Self-motivated, flexible and passionate working"], "locations": ["Kwai Fong"], "categories": ["Engineering", "Engineering Project Management", "Information Technology (IT)", "Network & System", "Others", "Student / Fresh Graduate / No Experience"], "post_time": "2022-01-17T03:18:09Z", "salary": {"currency": null, "max": null, "min": null, "period": "monthly", "term": null}, "salary_visible": false, "title_keywords": ["coordinator", "sales", "project engineer"], "responsibilities": ["cost estimation", "data", "systems", "implementation", "design", "website", "communication", "handle enquiries", "recruitment", "tender preparation", "plan", "application development", "management review"], "requirements": {"degrees": [], "majors": [], "languages": ["cantonese", "putonghua", "english"], "language_level": ["good command"], "hard_skills": [], "soft_skills": ["responsible", "interested in", "diligent", "communication", "attention to details", "initiative"], "languages_combined": [{"language": "cantonese", "language_level": ["good command"]}, {"language": "putonghua", "language_level": ["good command"]}, {"language": "english", "language_level": ["good command"]}]}, "experience_required": {"duration": [], "field": ["digital"]}}, {"job_id": "100003009053678", "location_code": "hk", "company": "Yau Shing Engineering Company Limited", "job_title": "Assistant Engineer / Engineer  (HVAC)", "description": "Job Requirements :\u00a0\nHigher Diploma\u00a0 or above in Building Services\u00a0\nAssistant Engineer \u00a0at least 2-3 years working experiences\u00a0\u00a0and knowledge in HVAC systems\u00a0 / E&M systems and installation\u00a0\nGood technical knowledge and Drawings by Autocad .\nAble to work independently with good problem solving skills\n\n\u00a0 \u00a0 \u00a0 \u00a0 \u00a0 \u00a0 \u00a0 Job Duties :\n\nBuilding services\u00a0related works of government projects\nManagement of Building services\u2019 related works of government projects\u00a0(ASD Or EMSD)\nCoordinate with clients and Handle\u00a0\nAssistant Engineer able to work independently and as a term with all aspects of MVAC work including site co-ordination\u00a0\u00a0\n\nInterested parties pls email your full resumes and expected salary by clicking \"Apply Now\"\n\n\nPersonal data collected will be used for recruitment purpose only.", "employment_types": ["Full Time"], "selling_points": ["HVAC", "Building Services", "AC /BS ENGINEERING"], "locations": ["Not Specified"], "categories": ["Building & Construction", "Building / Construction / QS", "Engineering", "Engineering Project Management", "Mechanical"], "post_time": "2022-01-17T07:20:10Z", "salary": {"currency": null, "max": null, "min": null, "period": "monthly", "term": null}, "salary_visible": false, "title_keywords": ["assistant engineer", "engineer"], "responsibilities": ["coordinate with clients", "management", "site co-ordination"], "requirements": {"degrees": ["diploma"], "majors": ["building services"], "languages": [], "language_level": [], "hard_skills": ["hvac", "problem solving skills", "autocad"], "soft_skills": ["work independently", "problem solving skills"], "languages_combined": []}, "experience_required": {"duration": ["at least 2-3 years"], "field": ["installation"]}}, {"job_id": "100003009055593", "location_code": "hk", "company": "Robert Walters (HK)", "job_title": "Site Supervisor (ELV, 30K, 5-day, Client side)", "description": "We are searching for a Site Supervisor for our client, it's a client representative role for a newly awarded ELV project:\n\nResponsibilities:\n\nMonitor day-to-day site work progress and contractor workmanship to ensure project delivery quality\nSupervise contractor safety and work performance\nRepresent Enginneer or Engineer's representative to attend and witness system testing and commissioning\nSite coordination and resolve construction site issues to ensure timely delivery of project works\n\nRequirements:\n\nDiploma or above in Electronics Engineering / Electrical Engineering/ Computer and Information Engineering or equivalent\nAt least 3 years' relevant experience in site coordination and project implementation of telecommunications, electronic or information & communications technology project or equivalent\nPossess a valid Construction Industry Safety Training Certificate", "employment_types": ["Full Time", "Temporary"], "selling_points": ["Client side representative", "", ""], "locations": ["Not Specified"], "categories": ["Engineering", "Electrical / Electronics", "Engineering Project Management", "Telecommunication / Wireless / Radio"], "post_time": "2022-01-18T02:46:26Z", "salary": {"currency": null, "max": null, "min": null, "period": "monthly", "term": null}, "salary_visible": false, "title_keywords": ["site supervisor"], "responsibilities": ["commissioning", "quality", "monitor", "testing", "site coordination"], "requirements": {"degrees": ["certificate", "diploma or above"], "majors": ["engineering", "electrical engineering"], "languages": [], "language_level": [], "hard_skills": [], "soft_skills": ["coordination"], "languages_combined": []}, "experience_required": {"duration": ["at least 3 years"], "field": ["telecommunications", "relevant experience"]}}, {"job_id": "100003009052830", "location_code": "hk", "company": "The Hongkong Electric Co., Ltd.", "job_title": "Senior Meter Asset Management Engineer (Ref: CS-M-SMAME-JD)", "description": "Responsibilities:\n\nReporting to the Head of Metering, the appointee will mainly perform the following responsibilities:\n\n\nTo oversee the administration and operations of a team, prepare capital and revenue budgets and control expenditures, and formulate strategies to cope with the changing rules and legislations as well as technical advancement\nTo supervise the team to handle meter asset management works including planning, evaluation, inspection, testing, procurement, housekeeping and scrapping of the meters\nTo lead the team to develop, integrate, test and commission of various Advanced Metering Infrastructure (AMI) metering related systems, e.g. Field Area Network design, Head-End system, Meter Data Management (MDM) System and Network Management System (NMS)\nTo design, plan and manage metering installations in relation to Remote Meter Reading (RMR) / AMI communications\n\nRequirements:\n\n\nBachelor Degree in Electrical Engineering, Electronics Engineering or related disciplines with Corporate Membership of HKIE\nA minimum of 10 years\u2019 relevant work experience, of which with at least 4 years\u2019 in supervisory level\nFamiliar with local and international regulations related to tariff meters, metering principles, meter system design and meter technologies\nKnowledge of and experience in Advanced Metering Infrastructure, smart meter deployment, ISO Management Systems and 5S Good Housekeeping preferred\nGood command of English and Chinese languages, both spoken and written\nHolder of a valid driving license for Class 1 vehicle an advantage\n\nCandidate with qualification leading to Corporate Membership of HKIE or less relevant experience may also be considered for the position of Meter Asset Management Engineer I.\n\n\nWorking Location: North Point\n\n\nApplication:\n\nIf you are interested in this position, please send your resume\u00a0(in PDF format)\u00a0with details of qualification, experience, present and expected salary, and contact number to the Human Resources Division, The Hongkong Electric Co., Ltd. on or before 31 January 2022\u00a0and quote the reference number in your application. Please also visit our website to know more about our Company http://www.hkelectric.com.\n\nApplicants not invited for interview within\u00a0one month from the closing date may consider their applications unsuccessful. All unsuccessful applications will be kept for\u00a0six months after the date of this advertisement.\n\nWe are an equal opportunity employer.\u00a0 Personal data provided by job applicants will be treated in strictest confidence and used only for recruitment-related purposes in accordance with the laws and ordinance of the HKSAR.", "employment_types": ["Full Time", "Permanent"], "selling_points": ["To oversee the administration and operations", "Bachelor Degree in Electrical Engineering", "A minimum of 10 years\u2019 relevant work experience"], "locations": ["North Point"], "categories": ["Engineering", "Electrical / Electronics", "Engineering Project Management", "Others"], "post_time": "2022-01-17T04:13:15Z", "salary": {"currency": null, "max": null, "min": null, "period": "monthly", "term": null}, "salary_visible": false, "title_keywords": ["engineer", "asset management"], "responsibilities": ["data", "operations", "oversee the administration", "design", "plan", "evaluation", "control", "infrastructure", "testing", "develop", "legislations", "reporting", "management", "inspection", "budgets", "housekeeping", "systems", "asset management", "planning"], "requirements": {"degrees": ["degree", "bachelor"], "majors": ["related disciplines", "engineering", "electrical engineering"], "languages": ["english", "chinese"], "language_level": ["good command"], "hard_skills": ["system design", "hkie", "deployment"], "soft_skills": ["confidence", "interested in", "advanced"], "languages_combined": [{"language": "english", "language_level": ["good command"]}, {"language": "chinese", "language_level": ["good command"]}]}, "experience_required": {"duration": ["at least 4 years", "minimum of 10 years"], "field": ["management", "infrastructure", "relevant experience", "supervisory level", "human resources", "asset management"]}}, {"job_id": "100003009053460", "location_code": "hk", "company": "UPS Parcel Delivery Service Limited", "job_title": "Plant Engineering Assistant Manager", "description": "Responsibilities\n\nThe Plant Engineer Assistant Manager execute plant engineering function in Hong Kong and Taiwan. the successful candidate will:\n\nSupport the appropriation of project funds. Produce 2D AutoCAD layout drawings, assemble estimates, and create project schedules. Input, review and approve funding requests and PE related supporting documents in UPS internal appropriation database.\nManage bidding and contracting of projects. Define project scope through direct production of 2D AutoCAD layout drawings, and editing of UPS specifications for use in both bid documents and contracts. Liaise with professional services companies (consultants). Write contracts.\nSupervise on-site construction, Lease Hold Improvement works, and Material Handling system installation. Ensure safe work environment, adherence to UPS specification and requirements, and completion of contracted scope. Drive effective use of resources, adherence to schedule, adherence to budget and process payments. Coordinate cross-functionally to ensure effective commissioning and deployment of new assets.\nBe responsible for facility and equipment maintenance through the dispatch of vendors. Ensure work is done in safe and proper manner and contracted scope is completed.\nAudit conveyor contractor preventative maintenance procedures to ensure quality work.\nAudit Facility Safety to UPS standards and regulatory requirements. Correct deficiencies in order to ensure a safe work environment.\nAudit Environmental compliance. Oversee deficiency correction.\nProvide support in HK and TW through a combination of directly completing tasks, and/or reviewing and advising, and/or training UPS local country teams in order to execute tasks described above.\n\nQualifications\n\nBachelor Degree in Engineering (Civil, Electrical, Mechanical or similar)\nMinimum 5 years of experience required in any of the following field: construction project management, building maintenance and industrial equipment maintenance\nFluent in oral and written communication, in both English and Chinese (Mandarin, Cantonese)\nAble to draw a building layout on 2D CAD software\nCompetent in Microsoft office applications\nAbility to travel within Asia\nAbility to work cross-culturally with the staff in other countries\nExperience with a formal Continuous Improvement Process system is an asset", "employment_types": ["Full Time", "Permanent"], "selling_points": ["Construction project and building maintenance", "Engineering (Civil, Electrical, Mechanical)", "5 years or above working experience"], "locations": ["Lai Chi Kok"], "categories": ["Building & Construction", "Building / Construction / QS", "Engineering", "Engineering Project Management", "Mechanical"], "post_time": "2022-01-17T07:00:26Z", "salary": {"currency": null, "max": null, "min": null, "period": "monthly", "term": null}, "salary_visible": false, "title_keywords": ["assistant manager"], "responsibilities": ["software", "schedules", "regulatory requirements", "budget", "quality", "audit", "drawings", "communication", "database", "liaise with", "editing", "contracts", "compliance", "teams", "material handling system", "schedule", "installation", "provide support", "commissioning", "review", "procedures", "specifications", "maintenance", "coordinate", "project management", "payments", "contracting"], "requirements": {"degrees": ["degree", "bachelor"], "majors": ["engineering"], "languages": ["cantonese", "english", "chinese", "mandarin"], "language_level": ["fluent"], "hard_skills": ["maintenance", "microsoft office", "cad", "project management", "safe", "material handling system", "deployment", "pe", "autocad"], "soft_skills": ["oral", "responsible", "competent", "communication", "project management"], "languages_combined": [{"language": "cantonese", "language_level": ["fluent"]}, {"language": "english", "language_level": ["fluent"]}, {"language": "chinese", "language_level": ["fluent"]}, {"language": "mandarin", "language_level": ["fluent"]}]}, "experience_required": {"duration": ["minimum 5 years"], "field": ["project management", "construction", "maintenance"]}}, {"job_id": "100003009053892", "location_code": "hk", "company": "Hysan Development Co Ltd", "job_title": "Engineer", "description": "Job Purpose\n\n\nResponsible for managing operation, maintenance and improvement works for building services systems and handling technical issues.\n\nKey Responsibilities\n\n\nLead technical staff to carry out operation, maintenance and works for building services systems in an efficient, reliable and safe manner ensuring that the required quality standards are achieved.\nProvide technical support to Business Units, Property Management Department and other Departments with respect to building services including tenant fitting out / reinstatement, minor alteration and modification works and advising technical comments.\nCarry out regular audit of conditions of existing building services installations and recommend and implement works to maintain efficiency and reliability of the building services installations.\nAssist to perform regular review and recommendation of maintenance procedures to ensure that systems are being effectively maintained with optimum resource.\nAssist to compile and manage budget, tender document and manage the tendering process. Support Managers / Senior Manager to arrange procurement, manage contracts and projects / works and activities and issues under the portfolio of the Technical Services Department.\nHandle technical issues / works.\nAssist in implementing environmental management strategies and energy saving programme with energy consumption analysis and forecast.\n\n\nSkills, Qualifications and Experience Requirements\n\n\nDegree holder in building services engineering or related engineering disciplines\nMinimum 5 years relevant experience in plant operation and maintenance in property management or development company with 2 years at supervisory level\nStrong sense of responsibility Self-motivated and able to work under pressure\nGood PC skills\nGood command of spoken and written English and Chinese\n\nAn attractive remuneration package will be offered to the right candidate. Interested parties please press \"Apply now\".\n\n\nHysan is an equal opportunity employer.\u00a0 All information collected will be kept in strict confidence and used solely for recruitment related purposes within the Hysan Group Companies.\n\nYou may get to know more about us through www.hysan.com.hk", "employment_types": ["Full Time", "Permanent"], "selling_points": ["Manage operation, maintenance and BS systems", "Degree Holder with 5 years\u2019 relevant experience", "5-day work, 14-day AL, Dental, Double Pay + Bonus"], "locations": ["Causeway Bay"], "categories": ["Building & Construction", "Building / Construction / QS", "Engineering", "Engineering Project Management", "Property / Real Estate", "Others"], "post_time": "2022-01-17T07:42:36Z", "salary": {"currency": null, "max": null, "min": null, "period": "monthly", "term": null}, "salary_visible": false, "title_keywords": ["engineer"], "responsibilities": ["management", "maintenance", "technical support", "contracts", "analysis", "systems", "quality", "comments", "audit", "procedures", "regular review", "budget", "tendering", "maintain", "forecast", "tender document", "work under pressure"], "requirements": {"degrees": ["degree holder"], "majors": ["building services", "engineering"], "languages": ["english", "chinese"], "language_level": ["good command"], "hard_skills": ["pc skills", "safe", "analysis", "maintenance"], "soft_skills": ["efficient", "self-motivated", "responsible", "sense of responsibility", "reliable", "work under pressure"], "languages_combined": [{"language": "english", "language_level": ["good command"]}, {"language": "chinese", "language_level": ["good command"]}]}, "experience_required": {"duration": ["2 years", "minimum 5 years"], "field": ["management", "maintenance", "development", "operation", "relevant experience", "supervisory level"]}}, {"job_id": "100003009051775", "location_code": "hk", "company": "Wang Fu Project Management Limited", "job_title": "Project Manager", "description": "Responsibilities :\n\nCoordinate with clients and sub-contractors to facilitate site progress, safety and quality control\nCollaborate with engineers, architects etc. to determine the specifications of the project\nCommunicate, implement, and monitor company's policy to the project teams for the effective implementation of the policy\nEstablish the master program, monitor the progress and control the overall budget including manpower, equipment, materials, wastage and miscellaneous expenses etc\nEnsure all works being carried out according to the regulations and code of practice to obtain the relevant completion certificates\n\nRequirements :\n\nCorporate member of a building related professional institute\nMinimum 5 years post-qualification experience in the building construction field\nMinimum 7 years relevant experience with at least 2 years in building maintenance organization in the capacity of site management\nStrong in leadership / management and can work under pressure\nStrong problem solving and analytical ability\nHigh self-motivated and able to work independently\n\nWe offer a competitive remuneration package\uff1a\n\n16 Days Annual Leave\nBirthday Leave\nEducation Allowance\nPerformance Bonus\nMedical Insurance\n\nInterested parties please send your\u00a0full resume with current and expected salary and available date\u00a0by clicking \"Apply Now\".\u00a0\n\nPersonal data will be used for recruitment purpose only.", "employment_types": ["Full Time", "Permanent"], "selling_points": ["Corporate member of a building", "At least 5 years of post-qualification exp", "Lead project teams to complete the projects"], "locations": ["Kwun Tong"], "categories": ["Building & Construction", "Building / Construction / QS", "Engineering", "Engineering Project Management", "Others"], "post_time": "2022-01-17T01:04:02Z", "salary": {"currency": null, "max": null, "min": null, "period": "monthly", "term": null}, "salary_visible": false, "title_keywords": ["project manager"], "responsibilities": ["regulations", "control", "overall budget", "collaborate with engineers", "expenses", "monitor", "teams", "implementation", "coordinate with clients", "quality control", "determine the specifications"], "requirements": {"degrees": [], "majors": [], "languages": [], "language_level": [], "hard_skills": ["problem solving", "maintenance"], "soft_skills": ["self-motivated", "work independently", "problem solving", "leadership", "work under pressure"], "languages_combined": []}, "experience_required": {"duration": ["at least 2 years", "minimum 7 years", "minimum 5 years"], "field": ["management", "post-qualification", "maintenance", "relevant experience", "construction"]}}, {"job_id": "100003009053453", "location_code": "hk", "company": "PERSOL Hong Kong", "job_title": "(Urgent!!) Electrical Engineer", "description": "Our client, a reputable main contractor / sub-contractor in Hong Kong is seeking a number of high caliber Engineer(s) \u2013 E&M / HVAC / MVAC / P&D for their new projects.\n\nRequirements:\n\nH.D. in Electrical Engineering / Mechanical Engineering / Building Services Engineering or equivalent\n3 years\u2019 Electrical /\u00a0HVAC /\u00a0MVAC /\u00a0Plumbing and Drainage experience from subcontracting experience\nFamiliar with environmental assessment standards\nHands-on BIM software / applications experiences preferable\u00a0\nProficiency in MS Office (Word, Excel and PowerPoint)\nGood interpersonal, project management and site supervision skills\nGood spoken and written in English and Chinese\n\nCandidates with more experience will be considered for senior positions.\n\nPlease send your CV by clicking the button \u201cApply Now\u201d or email to\u202f corex_tang @persolkelly.com. For inquiries about this role or any other exciting opportunities, please call 2971-2525.\n\nAll information received will be treated in strict confidence and used for recruitment purpose only.", "employment_types": ["Full Time", "Contract"], "selling_points": ["Excellent salary package + bonus", "Good promotion / training opportunity", "3-yr exp in E&M/HVAC/MVAC/P&D"], "locations": ["Shatin Area"], "categories": ["Engineering", "Electrical / Electronics", "Engineering Project Management", "Telecommunication / Wireless / Radio"], "post_time": "2022-01-17T07:00:09Z", "salary": {"currency": "HKD", "max": 44999, "min": 35000, "period": "monthly", "term": null}, "salary_visible": true, "title_keywords": ["electrical engineer"], "responsibilities": ["project management", "site supervision", "recruitment", "software"], "requirements": {"degrees": [], "majors": [], "languages": ["english", "chinese"], "language_level": ["good"], "hard_skills": ["excel", "hvac", "word", "powerpoint", "project management", "bim", "ms office"], "soft_skills": ["project management", "hands-on", "confidence", "interpersonal"], "languages_combined": [{"language": "english", "language_level": ["good"]}, {"language": "chinese", "language_level": ["good"]}]}, "experience_required": {"duration": ["3 years"], "field": ["plumbing", "drainage"]}}, {"job_id": "100003009052682", "location_code": "hk", "company": "Kamui Group Development Limited", "job_title": "Site Engineer", "description": "Responsibilities:\n\nCommunicate and coordinate with the client, sub-contractors, suppliers, professional consultants and other counterparts as well as any on-site supervision staffs\nSupervise and monitor daily site progress and worker schedule\nTo prepare site progress report and attend site meeting\nTo prepare document and technical submission\nTo arrange and solve technical issues on site\nRequirements:\n\nHigher diploma or above in construction related disciplines\nMinimum 3 year\u2019s relevant working experience\nGood knowledge of building plans, design and construction & development processes\nEffective communication and negotiation skills\nProficiency in PC applications including AutoCAD and M.S. Project\nGood command of spoken & written English & Chinese", "employment_types": ["Full Time"], "selling_points": ["New development & Renovation", "Logistic & Industrial Sector", "Year end bonus"], "locations": ["Shatin Area"], "categories": ["Building & Construction", "Building / Construction / QS", "Engineering", "Engineering Project Management"], "post_time": "2022-01-17T03:41:41Z", "salary": {"currency": null, "max": null, "min": null, "period": "monthly", "term": null}, "salary_visible": false, "title_keywords": ["site engineer"], "responsibilities": ["coordinate with", "monitor", "on-site supervision", "schedule", "report"], "requirements": {"degrees": ["higher diploma or above"], "majors": ["related disciplines"], "languages": ["english", "chinese"], "language_level": ["good command"], "hard_skills": ["autocad", "pc applications"], "soft_skills": ["communication", "negotiation skills"], "languages_combined": [{"language": "english", "language_level": ["good command"]}, {"language": "chinese", "language_level": ["good command"]}]}, "experience_required": {"duration": ["minimum 3 year"], "field": ["relevant working experience"]}}, {"job_id": "100003009052961", "location_code": "hk", "company": "NexLen International Limited", "job_title": "Technician / Technical Support Engineer", "description": "Job Responsibilities\n\nTo provide hardware and software maintenance or remote support to solve the IT related problems\nTo provide the system setting and configuration\nTo handle customer technical enquiries and product / system demonstration\nTo assist in managing hardware and software inventory items\n\nRequirements\n\nCertificate / Diploma in IT or relevant discipline\nExperience in IT Industry or relevant experience is highly preferred\nFresh graduate will also be considered, will provide professional training to the right candidate\nGood communication skill, outgoing and self-motivated personality is required\nGood team player, willing to work under pressure and tight schedule\nGood command of both spoken and written English and Chinese\n\nWe offer attractive salary and fringe benefit package to the right candidate. Interested parties please send full resume to us.\n\nPersonal data provided in your application will be kept in the strictest confidence. It will be used for employment-related purposes. Applications not notified within 1 month will be considered as unsuccessful. Unsuccessful application may be kept for another 3 months for new openings before properly shredded.\n\nDBcampaignaviation\n", "employment_types": ["Full Time", "Permanent"], "selling_points": ["Experience in IT Industry or relevant experience", "Fresh graduate will also be considered", "Technician, Technical support engineer"], "locations": ["Kwun Tong"], "categories": ["Engineering", "Engineering Project Management", "Information Technology (IT)", "Hardware", "Support"], "post_time": "2022-01-17T04:42:31Z", "salary": {"currency": null, "max": null, "min": null, "period": "monthly", "term": null}, "salary_visible": false, "title_keywords": ["technician", "technical support engineer"], "responsibilities": ["software", "configuration", "inventory", "hardware", "hardware and software maintenance"], "requirements": {"degrees": ["certificate", "diploma", "fresh graduate"], "majors": ["it"], "languages": ["english", "chinese"], "language_level": ["good command"], "hard_skills": [], "soft_skills": ["outgoing", "good team player", "self-motivated", "communication skill", "work under pressure"], "languages_combined": [{"language": "english", "language_level": ["good command"]}, {"language": "chinese", "language_level": ["good command"]}]}, "experience_required": {"duration": [], "field": ["it", "relevant experience"]}}, {"job_id": "100003009055746", "location_code": "hk", "company": "PCCW Solutions", "job_title": "Tech Talent - Enginnering Associate", "description": "The Job\n\nAcquire engineering solutions knowledge and soft skills through on-the-job training in different projects in Hong Kong and Macau\nAttach to high-value engineering projects in the areas of sound and innovative technical solutions, solutions development and delivery, project management, engineering system operations, support and management\nDevelop a rewarding career in an advanced, fast-paced and multi cultural environment\n\nThe Person\n\nBachelor / Master degree in Electronic / Electrical / Information Engineering, Communication Engineering, IT or related disciplines with less than 2 years of full-time working experience\nGood presentation, interpersonal and communication skills\nA good team player with analytical and problem-solving skills and who relishes challenges\nGood command of spoken and written English and Chinese\n\n\u00b7\u00a0\u00a0\u00a0\u00a0\u00a0\u00a0\u00a0\u00a0\u00a0\n\n\u00b7\u00a0\u00a0\u00a0\u00a0\u00a0\u00a0\u00a0\u00a0\u00a0", "employment_types": ["Full Time"], "selling_points": [], "locations": ["Mong Kok"], "categories": ["Engineering", "Electrical / Electronics", "Engineering Project Management", "Telecommunication / Wireless / Radio"], "post_time": "2022-01-18T02:55:02Z", "salary": {"currency": null, "max": null, "min": null, "period": "monthly", "term": null}, "salary_visible": false, "title_keywords": ["associate"], "responsibilities": ["project management", "management", "operations", "develop"], "requirements": {"degrees": ["bachelor", "master degree"], "majors": ["related disciplines", "it", "engineering"], "languages": ["english", "chinese"], "language_level": ["good command"], "hard_skills": ["problem-solving skills"], "soft_skills": ["communication skills", "good team player", "presentation", "communication", "problem-solving skills", "interpersonal"], "languages_combined": [{"language": "english", "language_level": ["good command"]}, {"language": "chinese", "language_level": ["good command"]}]}, "experience_required": {"duration": ["2 years"], "field": ["related", "it", "engineering"]}}, {"job_id": "100003009055444", "location_code": "hk", "company": "Airport Authority Hong Kong", "job_title": "Project Engineer, Systems (APM)", "description": "This is a fixed-term contract position of minimum 2 years with possibility for renewal subject to organization need and individual performance.\n\u00a0\u00a0 \u00a0\nResponsibilities:\n\nProviding technical assistance in design, construction supervision and testing & commissioning of Automatic People Mover (APM) works;\nEnsuring that the contractors' proposals and works are technically safe and sound;\nUndertaking interface/ coordination related to APM works;\nReviewing contractors\u2019 submissions and technical reports;\nMonitoring statutory submissions of the contractors\u2019 and consultant\u2019s works; and\nProviding technical supports to site supervision teams including responding to request for information and preparation of design change documents.\n\nRequirements:\n\nBachelor\u2019s degree in Electrical /\u00a0Mechanical Engineering or other related disciplines\nMember of HKIE or other equivalent professional bodies is preferred\nAt least 6 years\u2019 relevant experience, of which minimum of 3 years should be in project management role\nSound technical knowledge in the design and implementation of APM System in particular on rolling stock & depot equipment / guideway system\u00a0and\u00a0system integration\u00a0\nProven experience in the management of system integration project for design, planning, construction, site supervisory and testing & commissioning works\nStrong communication, analytical and negotiation skills\nGood command of spoken and written English and Chinese\nKnowledge of Putonghua is an advantage\nProficient in MS Office applications and project management software tools", "employment_types": ["Full Time"], "selling_points": ["Project mgmt of Automatic People Mover (APM) works", "undertake interface / coordination works", "rolling stock & depot equipment/ guideway systems"], "locations": ["Airport Area"], "categories": ["Engineering", "Engineering Project Management"], "post_time": "2022-01-18T02:36:00Z", "salary": {"currency": null, "max": null, "min": null, "period": "monthly", "term": null}, "salary_visible": false, "title_keywords": ["project engineer"], "responsibilities": ["technical supports", "commissioning", "site supervision", "monitoring", "teams", "design", "testing", "reports", "coordination", "technical assistance"], "requirements": {"degrees": ["degree", "bachelor"], "majors": ["related disciplines", "mechanical engineering"], "languages": ["putonghua", "english", "chinese"], "language_level": ["advantage", "good command"], "hard_skills": ["integration", "project management", "hkie", "ms office"], "soft_skills": ["communication", "project management", "negotiation skills"], "languages_combined": [{"language": "putonghua", "language_level": ["advantage"]}, {"language": "english", "language_level": ["good command"]}, {"language": "chinese", "language_level": ["good command"]}]}, "experience_required": {"duration": ["at least 6 years", "minimum of 3 years"], "field": ["management", "supervisory", "design", "testing", "project management", "relevant experience", "construction", "planning"]}}, {"job_id": "100003009054545", "location_code": "hk", "company": "Tactful Building Co Ltd", "job_title": "Purchasing Officer/ Clerk", "description": "Practical experience in Construction industry;\nTo plan, source and negotiate with new/existing supplier, in order to reduce the total cost of inventory;\nSupply contract management and periodical review supplier performance;\nHighly motivated and quality driven;\nHigher Diploma in Logistic Management;\nLess experience will be considered as Purchasing Clerk.\u00a0\n\nWe offer attractive remuneration package. Interested parties, please send full resume with present and expected salary to HR & Admin Dept.\n\nAll information collected will be kept in strictly confidential and used for recruitment purpose only.", "employment_types": ["Full Time", "Permanent"], "selling_points": [], "locations": ["Kwun Tong"], "categories": ["Engineering", "Engineering Project Management", "Transportation & Logistics", "Supply Chain", "Building & Construction", "Others"], "post_time": "2022-01-17T09:57:20Z", "salary": {"currency": null, "max": null, "min": null, "period": "monthly", "term": null}, "salary_visible": false, "title_keywords": ["clerk", "purchasing officer"], "responsibilities": ["cost", "management", "inventory", "review", "quality", "contract management", "plan"], "requirements": {"degrees": ["diploma"], "majors": [], "languages": [], "language_level": [], "hard_skills": [], "soft_skills": ["motivated", "driven"], "languages_combined": []}, "experience_required": {"duration": [], "field": ["purchasing", "construction industry"]}}, {"job_id": "100003009044429", "location_code": "hk", "company": "Lingnan University", "job_title": "Project Engineer (Multiple positions) (Post Ref.: 21/328)", "description": "Lingnan University, a distinctive liberal arts institution in the Hong Kong Special Administrative Region, is committed to the provision of quality whole-person education by combining the best of Chinese and Western liberal arts traditions. It strives to pursue excellence in teaching, learning, scholarship and community engagement. With three academic Faculties, it offers a wide range of undergraduate degree programmes in arts, business and social sciences. Lingnan\u2019s liberal arts education is characterised by a broad-based interdisciplinary curriculum with specialised disciplinary studies; close student-staff relationship; a vibrant residential campus; ample global learning opportunities; active community engagement and multifarious workplace experience. The School of Graduate Studies also offers postgraduate programmes up to doctoral level in various disciplines and provides professional education for the wider society. \u00a0\u00a0Applications are now invited for the following posts:\n\nProject Engineer (Multiple positions)\nOffice of Service-Learning\n(Post Ref.: 21/328)\n\nThe Office of Service-Learning (OSL) is looking for Project Engineers with strong interest in designing exciting mechatronic products and nurturing future generations of innovators.\n\nThese positions offers opportunities for innovators to tackle unique challenges and develop novel products with a multinational team of engineers, social workers and scientists. The ideal candidates are interested in designing products that improves the living in urban and rural environment. Current design products range from ultra-violet disinfection robots, transparent filtration masks and intelligent wheelchairs. The appointees will also support the design and delivery of technology literacy programmes to undergraduate students. These positions will offer on-the-job training and are open to fresh university graduates.\n\nResponsibilities\nDesign innovative mechatronics products and humanitarian technologies for making real impact\nConduct research to evaluate and refine user experiences\nPrepare material for design competitions, marketing, and stakeholder engagement\nDesign and deliver integrated technology literacy programmes for students, faculty, and community members\nProvide mentorship to students engaged in design and technology-heavy competitions\nSupport entrepreneurship events and facilities (including student startups, coworking space operations, and programme promotions)\nPerform administrative duties (including report preparation, programme promotions and Service-Learning coordination)\n\nRequirements\nGraduate with a background in Science, Engineering, Technology or Social Sciences\nExperience in creating 2D drawings, 3D models and assemblies using CAD software such as SolidWorks, Fusion 360, Inventor, or Rhino\nExperience with basic microcontroller programming (Arduino, etc.) to aid in rapid prototyping\nPractical understanding of various manufacturing methods such as 3D printing, laser/waterjet cutting, CNC machining, injection moulding, and knowing which is appropriate for a given design\nHands-on experience with assembling and testing prototypes, using benchtop tools including multimeter, oscilloscopes\nGood knowledge in mechanical design and common components (including motors, fasteners, transmissions, bearing, etc.)\nExperience with technical programming languages such as MATLAB, C++, and Python\nSuccessful candidates will be working in a team with diverse expertise from science to engineering, and social science to marketing.\u00a0Preference will be given to candidates with passions in solving social problems with technology.\u00a0\nSalary and Fringe Benefits\nThe rank and commencing salary will be commensurate with qualifications and experience. Fringe benefits, where applicable, include annual leave, medical and dental benefits and mandatory provident fund.\n\nApplication Procedure\nPlease click \"Apply Now\" to submit your application with a 2-page design portfolio highlighting ONE outstanding project with pictures. Personal data collected will be used for recruitment purposes only.\n\nWe are an equal opportunities employer. Review of applications will start from January 2022 and continue until the post is filled. Qualified candidates are advised to submit their applications early for consideration.\n\nThe University reserves the right not to make an appointment for the post advertised, or to fill the post by invitation or by search. We regret that only shortlisted candidates will be notified.", "employment_types": ["Full Time"], "selling_points": ["Design innovative mechatronics products", "Conduct research to evaluate", "Prepare material for design competitions"], "locations": ["Tuen Mun Area"], "categories": ["Engineering", "Engineering Project Management", "Manufacturing & Production", "Others"], "post_time": "2022-01-17T01:01:22Z", "salary": {"currency": null, "max": null, "min": null, "period": "monthly", "term": null}, "salary_visible": false, "title_keywords": ["project engineer"], "responsibilities": ["operations", "design", "evaluate", "administrative duties", "coordination", "conduct research", "report"], "requirements": {"degrees": [], "majors": [], "languages": [], "language_level": [], "hard_skills": ["basic", "c++", "rhino", "cad", "python", "programming", "rapid", "matlab", "solidworks"], "soft_skills": ["diverse", "hands-on"], "languages_combined": []}, "experience_required": {"duration": [], "field": ["programming", "testing"]}}, {"job_id": "100003009051772", "location_code": "hk", "company": "Cheung Hing Construction Co., Ltd", "job_title": "Project Coordinator", "description": "Responsibilities:\n\nCoordinate with clients and sub-contractors to facilitate site progress, safety and quality control.\nAttend site visits and meetings.\nPrepare and regularly review short term program, master program, materials and shop drawings submission schedule.\nPlan, prepare, organize and maintain project documentations\nPerform ad hoc duties as assigned\n\nRequirements:\n\nDegree/ Diploma in Building Studies or equivalent\nMin. 5 years relevant working experience\n2 years in maintenance work in the capacity of site representative or working experience in the government maintenance work is an advantage\nGood command of both written and spoken English and Chinese\nKnowledge of AutoCad and MS office\nStrong communication and problem solving skill.\nImmediate available is an advantage\n\nCandidates with less experience will be considered as\n\n\u00a0\u201cAssistant Project Coordinator \".\n\n\u00a0We offer a competitive remuneration package\uff1a\n\n14 Days Annual Leave\nBirthday Leave\nEducation Allowance\nPerformance Bonus\nMedical Insurance\n\nInterested parties, please send full resume with\u00a0expected salary\u00a0and\u00a0available date by clicking \" Apply Now\"\n\n\n(Data collected will be used for recruitment purpose only.)\n", "employment_types": ["Full Time", "Permanent"], "selling_points": ["Degree/ Diploma in Building Studies", "Knowledge of AutoCad and MS office", "Liaise and co-ordinate with the employers"], "locations": ["Kwun Tong"], "categories": ["Building & Construction", "Building / Construction / QS", "Civil / Structural", "Engineering", "Engineering Project Management"], "post_time": "2022-01-17T01:01:52Z", "salary": {"currency": null, "max": null, "min": null, "period": "monthly", "term": null}, "salary_visible": false, "title_keywords": ["project coordinator"], "responsibilities": ["ad hoc duties", "review", "drawings", "coordinate with clients", "maintain", "schedule", "quality control", "plan"], "requirements": {"degrees": ["diploma", "degree"], "majors": ["building studies"], "languages": ["english", "chinese"], "language_level": ["good command"], "hard_skills": ["problem solving", "ms office", "maintenance", "autocad"], "soft_skills": ["communication", "problem solving skill"], "languages_combined": [{"language": "english", "language_level": ["good command"]}, {"language": "chinese", "language_level": ["good command"]}]}, "experience_required": {"duration": ["5 years", "2 years"], "field": ["relevant working experience", "maintenance"]}}, {"job_id": "100003009050008", "location_code": "hk", "company": "Projexasia Limited", "job_title": "Project Coordinator", "description": "Degree/ Higher Diploma/ Certificate in Building Studies or equivalent\n3-5 years\u00a0experience in Main Contractor Works\nMain Contractor experience in Alteration & Addition / Fit-out Works including architectural; design; administration; construction management and co-ordination of works\nFamiliarity with BD regulations preferable\nMust hold\u00a0a Safety Green Card\nA minimum of Technically Competent Person Grade 1 Level (TCP1)\nCorporate Membership of HKICM / CIOB / HKIE in building discipline or equivalent will be an advantage\nResponsible for clearly communicating, managing and supervising site supervisory staff, multiple subcontractor trades, and liaising with the client and consultant staff\nProficiency in both written and spoken English\nProficiency in PC application including AutoCAD and M.S. Project\u00a0is preferred\n\nWe offer a comprehensive remuneration package to the right candidate.\u00a0 Interested parties must possess the appropriate experience and qualifications.\u00a0 Please send your application with a detailed Curriculum Vitae to the Human Resources Manager by fax: (852) 2866 3804 or email\n\n\n(Personal data collected will be used for recruitment purposes only).", "employment_types": ["Full Time", "Permanent"], "selling_points": [], "locations": ["Airport Area"], "categories": ["Building & Construction", "Building / Construction / QS", "Civil / Structural", "Engineering", "Engineering Project Management"], "post_time": "2022-01-14T09:37:47Z", "salary": {"currency": null, "max": null, "min": null, "period": "monthly", "term": null}, "salary_visible": false, "title_keywords": ["project coordinator"], "responsibilities": ["regulations", "construction management", "supervising", "liaising with", "design", "administration"], "requirements": {"degrees": ["certificate", "diploma", "degree"], "majors": ["building studies"], "languages": ["english"], "language_level": ["proficiency"], "hard_skills": ["hkicm", "hkie", "green card", "ciob", "pc", "autocad"], "soft_skills": ["responsible", "competent"], "languages_combined": [{"language": "english", "language_level": ["proficiency"]}]}, "experience_required": {"duration": ["3-5 years"], "field": []}}, {"job_id": "100003009051670", "location_code": "hk", "company": "Sunland.AL (International) Co., Limited", "job_title": "Project Engineer (Plumbing & Drainage / Mechanical / Electrical / Fire Services / BS Disciplines)", "description": "Specialist knowledge and experience in the design of related disciplines\u00a0or equivalent\nHigher Diploma or Degree holder in Electrical Engineering, Building Services or equivalent.\nComputer software skill: MS Office, AutoCAD, Microsoft Project\nLanguages: Cantonese &\u00a0English (Mandarin an advantage)\nAt least 4~6 years\u2019 experience in related field.\nGood communication skills\nImmediate available is preferred\n\nBenefits:\n\nFive-Days Work Week\nMedical Insurance\nPerformance Bonus\n\nPlease send your resume with availability, current and expected salary to Sunland.AL (International) Co., Limited by \"Clicking Apply Now\"\n\n\nPersonal data will be used for recruitment purpose only.\n", "employment_types": ["Full Time", "Permanent"], "selling_points": ["Five-Days Work Week", "Medical Insurance", "Performance Bonus"], "locations": ["Tsim Sha Tsui"], "categories": ["Building & Construction", "Building / Construction / QS", "Engineering", "Electrical / Electronics", "Engineering Project Management"], "post_time": "2022-01-16T21:50:39Z", "salary": {"currency": null, "max": null, "min": null, "period": "monthly", "term": null}, "salary_visible": false, "title_keywords": ["project engineer"], "responsibilities": ["communication", "software", "design"], "requirements": {"degrees": ["diploma", "degree holder"], "majors": ["building services", "electrical engineering"], "languages": ["cantonese", "english", "mandarin"], "language_level": ["advantage"], "hard_skills": ["microsoft project", "autocad", "ms office"], "soft_skills": ["communication skills"], "languages_combined": [{"language": "cantonese", "language_level": []}, {"language": "english", "language_level": []}, {"language": "mandarin", "language_level": ["advantage"]}]}, "experience_required": {"duration": ["at least 4~6 years"], "field": ["related", "design"]}}, {"job_id": "100003009054355", "location_code": "hk", "company": "Shun Shing Contractors Limited", "job_title": "Project Coordinator II", "description": "Job\u00a0Responsibilities:\n\nAssistant to Qualified Building Surveyor / Qualified Construction Manager to inter alia :-\n\n\nPrepare master and interim programmes and update the programmes from time to time on a bi-weekly basis\nPrepare shop drawings for the approval of Architect and Consultants\nPrepare Notification of Delays (NODs)\nTogether with the in-house QS to prepare the VOs\nManage the ordering of materials, in particular those require long lead-time\nCarry out regular site inspection with Safety Officer\nInspect works to ensure good workmanship\nAttend site meeting and prepare the minutes of meeting accordingly\nRequirements:\n\nA good Non-cognate Degree (2nd upper honoured degree or above) recognised by the government of HKSAR\nA construction related Cognate Degree in Building Surveying or Construction Management would be an advantage\nconversant in using word, excel and powerpoint, knowledge of computer aided design (CAD) would be an advantage\nGood command of spoken and written Chinese and English\nSelf-motivated, energetic and composed team player\n\nWe will provide : (1) mentorship and guidance (through qualified professionals) to selected candidates so that they can learn through on-the-job training; and (2) subject to conditions, assistance to selected candidates to enrol for construction related part-time studies and we shall pay for the tuition fees involved.\u00a0\u00a0 In addition, we offer attractive remuneration package with medical benefits to the right candidate.\u00a0 The incumbent will become part of the in-house project management team which consists of authorized person, qualified quantity surveyor and other construction professionals.\n\n\n\n\nFor those who are holding higher qualifications and more experience mentioned hereinabove, we may consider them for the post of \u201cProject Coordinator I\u201d.", "employment_types": ["Full Time"], "selling_points": [], "locations": ["Kwun Tong"], "categories": ["Building & Construction", "Building / Construction / QS", "Civil / Structural", "Engineering", "Engineering Project Management"], "post_time": "2022-01-17T09:25:48Z", "salary": {"currency": null, "max": null, "min": null, "period": "monthly", "term": null}, "salary_visible": false, "title_keywords": ["project coordinator"], "responsibilities": ["site inspection", "drawings"], "requirements": {"degrees": ["degree or above", "degree"], "majors": ["building surveying", "construction management"], "languages": ["english", "chinese"], "language_level": ["good command"], "hard_skills": ["excel", "word", "powerpoint", "cad"], "soft_skills": ["self-motivated", "energetic", "team player"], "languages_combined": [{"language": "english", "language_level": ["good command"]}, {"language": "chinese", "language_level": ["good command"]}]}, "experience_required": {"duration": [], "field": []}}, {"job_id": "100003009051806", "location_code": "hk", "company": "Ensec Solutions Hong Kong Limited", "job_title": "Project Engineer", "description": "Responsible for design work, project planning, site supervision, commissioning and operation of ELV systems for Access Control , CCTV and Burglar Alarm System installations\nResponsible in project management\nSecurity system installation, programming, testing and commissioning\nConduct on-site system training to customer\nSystem trouble shooting and problem solving\nProviding technical support to Sales Department\nProvide service support on delivery and collection of equipment or parts to the customers whenever necessary\n\nRequirements\n\nDiploma / Certificate in Electronic / Electrical Engineering or Computer Engineering or other related Engineering discipline\nHolder of Security Personnel Permit (Cat. D) is an advantage\nAt least 2 years experience with security systems, such as CCTV, Access Control, Burglar Alarm, etc.\nProject management experience is an advantage\nGood knowledge of MS Office and AutoCAD\n\n\n\nRemuneration\n\nAttractive remuneration package includes 13 months salary will be offered to the right candidate. (5.5 working days per week)\n\nApply Method\n\nInterested? Please send your cover letter and resume in Word format with your availability, current and expected salary\u00a0by clicking \"Apply Now\".\n\nPersonal data collected will be used for recruitment purpose only.", "employment_types": ["Full Time", "Permanent"], "selling_points": ["Familiar with security system", "Project management", "Double pay, bonus, medical insurance etc."], "locations": ["Kwun Tong"], "categories": ["Engineering", "Electrical / Electronics", "Engineering Project Management", "Others"], "post_time": "2022-01-17T01:14:08Z", "salary": {"currency": null, "max": null, "min": null, "period": "monthly", "term": null}, "salary_visible": false, "title_keywords": ["project engineer"], "responsibilities": ["design work", "installation", "project planning", "commissioning", "site supervision", "technical support", "systems", "testing", "burglar alarm", "project management", "recruitment", "personal data", "access control"], "requirements": {"degrees": ["certificate", "diploma"], "majors": ["computer engineering", "electrical engineering", "engineering"], "languages": [], "language_level": [], "hard_skills": ["cctv", "security personnel permit", "word", "problem solving", "project management", "autocad", "programming", "ms office"], "soft_skills": ["problem solving", "project management", "responsible"], "languages_combined": []}, "experience_required": {"duration": ["at least 2 years"], "field": ["project management", "security"]}}, {"job_id": "100003009054274", "location_code": "hk", "company": "CHOW TAI FOOK JEWELLERY CO LTD", "job_title": "Project Officer/ Senior Project Officer, Engineering Department", "description": "What You Will Own\n\nConduct and supervise renovation & maintenance, installation and fitting-out works of branches, offices and facilities in HK, Macau and other countries\nTo\u00a0execute the whole project cycle, monitor & report work progress and manage workmanship on site to ensure project quality could meet in-house and \u00a0landlord\u2019s standards\nOversee renovation works and site development projects, co-ordinate with departments, consultants and contractors to ensure on time completion with specifications\u00a0and requirements compliance\nPrepare quotations, tenders and provide professional technical advices\nAssist in\u00a0other ad-hoc projects as assigned\nFrequent business travels to overseas are necessary\n\nWho Will Thrive\n\nDiploma or above in Electrical / Civil Engineering/ Building Services /\u00a0Building Studies / Construction / Project Management\u00a0or relevant disciplines with\u00a04 - 7\u00a0years' relevant hands-on technical and supervisory experience\nHolder of\u00a0Certificate of Registration of Electrical Worker (Grade A)\u00a0is an advantage\nIndependent, strong leadership and problem solving skills\nHardworking, well-organized with strong sense of responsibility and integrity\nGood communication and interpersonal skills\nGood command of written and spoken English, Cantonese and Mandarin\nKnowledge of\u00a0AutoCAD / PhotoShop / SketchUp 3D and MS Office is preferred\nCandidate with more experience will be considered as Senior Project Officer\n\nBenefits\n\n5-day work\nCompetitive salary, staff meal, medical and dental insurance, life insurance\nVarious types of leave, e.g. Family-friendly leave, self-development leave,\u00a0Examination leave, marriage leave, birthday leave, volunteer service leave, etc\n\nWe offer excellent career opportunities, attractive remuneration package & benefits to the right candidate.\u00a0Interested parties please apply by clicking \"Apply Now\" with a full resume stating the latest and expected salary.\n\nAll information collected will be used for recruitment purposes only.", "employment_types": ["Full Time", "Permanent"], "selling_points": ["Conduct and supervise renovation & maintenance", "Diploma in Building Services/Project Management", "Competitive salary, staff meal,medical insurance"], "locations": ["Kwai Hing"], "categories": ["Building & Construction", "Building / Construction / QS", "Engineering", "Electrical / Electronics", "Engineering Project Management"], "post_time": "2022-01-17T09:00:46Z", "salary": {"currency": null, "max": null, "min": null, "period": "monthly", "term": null}, "salary_visible": false, "title_keywords": ["project officer", "senior project officer"], "responsibilities": ["installation", "maintenance", "co-ordinate with", "renovation", "monitor", "quality", "compliance", "communication", "project management", "specifications", "ad-hoc projects", "report"], "requirements": {"degrees": ["certificate", "diploma or above"], "majors": ["project management", "building studies", "building services", "civil engineering"], "languages": ["cantonese", "english", "mandarin"], "language_level": ["good command"], "hard_skills": ["maintenance", "sketchup", "project management", "photoshop", "certificate of registration of electrical worker", "problem solving skills", "ms office", "autocad"], "soft_skills": ["independent", "sense of responsibility", "well-organized", "integrity", "project management", "hands-on", "communication and interpersonal skills", "problem solving skills", "leadership", "hardworking"], "languages_combined": [{"language": "cantonese", "language_level": ["good command"]}, {"language": "english", "language_level": ["good command"]}, {"language": "mandarin", "language_level": ["good command"]}]}, "experience_required": {"duration": ["4 - 7 years"], "field": ["engineering", "project management", "building services", "supervisory experience", "construction"]}}, {"job_id": "100003009055061", "location_code": "hk", "company": "Ensec Solutions Hong Kong Limited", "job_title": "Technical Engineer / Junior Technician", "description": "Job Duties\n\nSecurity system installation, programming, testing and commissioning\nConduct on-site system training to customer\nSystem trouble shooting and problem solving\nAssist in project management\nAssisting and providing technical support to Sales Department\nProvide service support on delivery and collection of equipment or parts to the customers whenever necessary\nTo attend emergency call out service as requested by customer\n\nRequirements\n\nDiploma / Certificate in Electronic / Electrical Engineering or Computer Engineering or other related Engineering\u00a0discipline\nHolder of Security Personnel Permit (Cat. D) is an advantage\nAt least 1-year relevant working experience, experience in security systems is an advantage, such as CCTV, Access Control, Burglar Alarm, EAS system, etc.\nAble to work independently and under pressure\nProject management experience is an advantage\nFresh graduate is welcomed.\u00a0 Candidate with less experience will be considered as Junior Technician.\n\n\nRemuneration\n\nAttractive remuneration package include 13 months salary will be offered to the right candidate. (6 working days per week)\u00a0\n\n\n\nApply Method\n\nInterested candidates please send your resume in Word format with your availability, current and expected salary\u00a0by clicking \"Apply Now\".\n\nPersonal data collected will be used for recruitment purpose only.", "employment_types": ["Full Time", "Permanent"], "selling_points": ["Security system installation", "Fresh graduate will be considered", "Double pay, bonus, medical insurance etc."], "locations": ["Kwun Tong"], "categories": ["Engineering", "Electrical / Electronics", "Engineering Project Management", "Others", "Technician"], "post_time": "2022-01-18T01:06:12Z", "salary": {"currency": null, "max": null, "min": null, "period": "monthly", "term": null}, "salary_visible": false, "title_keywords": ["junior technician", "technical engineer"], "responsibilities": ["installation", "commissioning", "technical support", "testing", "project management"], "requirements": {"degrees": ["certificate", "diploma", "fresh graduate"], "majors": ["computer engineering", "electrical engineering", "engineering"], "languages": [], "language_level": [], "hard_skills": ["project management", "cctv", "security personnel permit"], "soft_skills": ["project management", "work independently", "under pressure"], "languages_combined": []}, "experience_required": {"duration": ["at least 1-year"], "field": ["project management", "security", "relevant working experience"]}}, {"job_id": "100003009025335", "location_code": "hk", "company": "The Top Decoration Engineering Co Ltd", "job_title": "Project Administrator / Assistant Project Administrator", "description": "Responsible for coordination works on site, material delivery arrangement\nAssist Site Agents to coordinate project matters, schedule and report problems\nManage, control and monitor of daily project works, instructions and progress\nCoordinate and liaise with clients, sub-contractors and suppliers\nAssist in other ad-hoc assignment", "employment_types": ["Full Time"], "selling_points": [], "locations": ["Kwun Tong"], "categories": ["Engineering", "Engineering Project Management"], "post_time": "2022-01-16T21:50:24Z", "salary": {"currency": "HKD", "max": 19999, "min": 14000, "period": "monthly", "term": null}, "salary_visible": true, "title_keywords": ["assistant", "project administrator"], "responsibilities": ["liaise with clients", "ad-hoc", "control", "coordination works", "monitor", "coordinate", "schedule", "report"], "requirements": {"degrees": [], "majors": [], "languages": [], "language_level": [], "hard_skills": [], "soft_skills": ["coordination", "responsible"], "languages_combined": []}, "experience_required": {"duration": [], "field": []}}, {"job_id": "100003009053918", "location_code": "hk", "company": "Obrien Tech Limited", "job_title": "\u96fb\u6a5f\u5de5\u7a0b\u5e2b", "description": "\n\u8077\u8cac :\u4e00\u822c\u96fb\u6a5f\u5de5\u7a0b\u5e2b\u5de5\u4f5c, \u8ca0\u8cac\u65b0\u96fb\u529b\u8a2d\u5099\u4e4b\u8a2d\u8a08\u3001\u7b56\u5283\u3001\u7e6a\u5236\u5716\u5247\u3001\u76e3\u7ba1\u5de5\u4f5c\uff0c\u8207\u627f\u5efa\u5546\u53ca\u5ba2\u6236\u5354\u8abf\u53ca\u76e3\u7ba1\u9032\u5ea6\n\n\u8cc7\u6b77 :\u5c08\u4e0a\u6559\u80b2\uff1a\u6587\u6191/\u8b49\u66f8; \u4e00\u822c\u7cb5\u8a9e; \u4e00\u822c\u666e\u901a\u8a71; \u4e00\u822c\u82f1\u8a9e\u512a\u5148; \u61c2\u95b1\u8b80\u4e2d\u6587; \u61c2\u95b1\u8b80\u82f1\u6587\n\n\u5f85\u9047 :\u6bcf\u6708$13,000 - $15,000, \u6709\u9280\u884c\u5047\u671f \u53ca\u91ab\u7642\u4fdd\u96aa, \u661f\u671f\u4e00\u81f3\u4e94: \u4e0a\u53489\u6642\u81f3\u4e0b\u53486\u6642, \u6bcf\u9031\u5de5\u4f5c5\u5929, \u6bcf\u5929\u5de5\u4f5c 8 - 9 \u5c0f\u6642\n\n\u7533\u8acb\u9808\u77e5 :\u6c42\u8077\u8005\u53ef\u96fb\u90f5(Apply Now)\u5c65\u6b77\u8868\u7d66OBRIEN TECH LIMITED\u3002\u5982\u8981\u7d22\u53d6\u6536\u96c6\u500b\u4eba\u8cc7\u6599\u8072\u660e, \u8acb\u8207\u9673\u5148\u751f(Email)\u806f\u7d61\u3002\n\n", "employment_types": ["Full Time"], "selling_points": [], "locations": ["Tsim Sha Tsui"], "categories": ["Engineering", "Electrical / Electronics", "Engineering Project Management", "Others"], "post_time": "2022-01-17T07:46:09Z", "salary": {"currency": null, "max": null, "min": null, "period": "monthly", "term": null}, "salary_visible": false, "title_keywords": [], "responsibilities": [], "requirements": {"degrees": [], "majors": [], "languages": [], "language_level": [], "hard_skills": [], "soft_skills": [], "languages_combined": []}, "experience_required": {"duration": [], "field": []}}, {"job_id": "100003009026533", "location_code": "hk", "company": "TQM Consultants Co Ltd", "job_title": "Industrial and Manufacturing Engineering Graduate Trainee (Scheme A in MIS)", "description": "TQM Consultants Co. Limited, a well-established top-tier management consulting firm based in Hong Kong, provides a wide spectrum of consultancy services with extensive experience in various business and industrial sectors\n\nWe are the market leader of management systems in Hong Kong, sharing 70% of the HKSAR Government/ Public Sector\u2019s Management System Consultancy and Training assignments.\n\nhttp://www.tqm.com.hk\n\nJob Detail\n\nParticipate in process improvement, quality improvement and safety/environmental/energy management project\nPrepare work proposal and project documentation\nCoordinate with various teams in the company to achieve project goals\nRegularly and timely follow up with the customer needs and objectives\nHandle ad hoc projects as assigned\nEnsure high-quality customer services are provided at all times\n\nRequirements\u00a0\n\nGraduates\u00a0(years 2020\u00a0onwards)\u00a0with good honour Degree in\u00a0Manufacturing, Industrial and System Engineering Disciplines\nHolders\u00a0of Hong Kong identity card\nGood interpersonal, communication & presentation skills\nGood command of English and Chinese, both spoken and written\n\nWhy us?\n\nOfferthe\u00a0HKIE Graduate Training Scheme 'A'\u00a0in\u00a0Manufacturing, Industrial & Systems Discipline (MIS)\n\u00a02-year Scheme \u2018A\u2019 trainee + 2-year working to become a registered professional engineer! (6 YEARS for Non-scheme A)\nMarket-leading remuneration package (13-month pay with annual bonus and Medical, Telecom, and Training allowance)\nWork-life Balance (5-day workweek (09:00-17:30) and 2 weeks of paid ALs)\nRegular Team Building Activities\nProfessional advice and coaching regularly\n\nHow to apply? Learn more at https://www.tqm.com.hk/scheme-a", "employment_types": ["Full Time"], "selling_points": [], "locations": ["Wan Chai"], "categories": ["Engineering", "Engineering Project Management"], "post_time": "2022-01-17T06:05:55Z", "salary": {"currency": null, "max": null, "min": null, "period": "monthly", "term": null}, "salary_visible": false, "title_keywords": ["graduate trainee"], "responsibilities": ["management", "consulting", "systems", "quality", "coordinate with", "teams", "customer services", "communication", "ad hoc projects", "project documentation"], "requirements": {"degrees": ["degree"], "majors": ["system engineering", "manufacturing"], "languages": ["english", "chinese"], "language_level": ["good command"], "hard_skills": ["documentation", "hkie", "scheme"], "soft_skills": ["timely", "communication", "presentation skills", "extensive", "interpersonal"], "languages_combined": [{"language": "english", "language_level": ["good command"]}, {"language": "chinese", "language_level": ["good command"]}]}, "experience_required": {"duration": [], "field": ["management", "business", "consulting"]}}, {"job_id": "100003009026534", "location_code": "hk", "company": "TQM Consultants Co Ltd", "job_title": "Graduate Engineer (Fresh/Oversea Graduates are Welcome)", "description": "TQM Consultants Co. Limited, a well-established top-tier management consultancy firm based in Hong Kong, provides a wide spectrum of consultancy services with extensive experience in various business and industrial sectors.\n\nWe are the market leader of management systems in Hong Kong, sharing 70% of the HKSAR Government/ Public Sector\u2019s Management System Consultancy and Training assignments.\n\nhttp://www.tqm.com.hk\n\nJob Details\n\n\nParticipate in process improvement, quality improvement and safety/environmental/energy management project\nPrepare work proposal and project documentation\nCoordinate with various teams in the company to achieve project goals\nRegularly and timely follow up with the customer needs and objectives\nHandle ad hoc projects as assigned\nEnsure high quality customer services are provided at all times\n\nRequirements\n\n\nGraduates (years 2020 onwards) with good honour Degree in Engineering Discipline\nHolders of Hong Kong identity card\nGood interpersonal, communication & presentation skills\nGood command of English and Chinese, both spoken and written\n\nWhy us?\n\n\nMarket-leading remuneration package (13-month pay with annual bonus and Medical, Telecom, and Training allowance)\nWork-life Balance (5-day workweek (09:00-17:30) and 2 weeks of paid ALs)\nRegular Team Building Activities\nProfessional advice and coaching on a regular basis\n\nHow to apply? Learn more at https://www.tqm.com.hk/scheme-a %MCEPASTEBIN%", "employment_types": ["Full Time"], "selling_points": [], "locations": ["Wan Chai"], "categories": ["Engineering", "Engineering Project Management"], "post_time": "2022-01-17T06:04:35Z", "salary": {"currency": null, "max": null, "min": null, "period": "monthly", "term": null}, "salary_visible": false, "title_keywords": ["graduate engineer"], "responsibilities": ["management", "coordinate with", "quality", "teams", "customer services", "ad hoc projects", "project documentation"], "requirements": {"degrees": ["degree"], "majors": ["engineering"], "languages": ["english", "chinese"], "language_level": ["good command"], "hard_skills": ["scheme"], "soft_skills": ["communication", "presentation skills", "interpersonal"], "languages_combined": [{"language": "english", "language_level": ["good command"]}, {"language": "chinese", "language_level": ["good command"]}]}, "experience_required": {"duration": [], "field": []}}, {"job_id": "100003009051382", "location_code": "hk", "company": "Aecom Asia Company Limited", "job_title": "Engineer / Project Engineer / Senior Engineer, Transportation", "description": "Job Requirements\u00a0\n\n\nA recognized degree in Civil Engineering or equivalent\nA minimum 4 years of relevant work experience in the design or construction or project co-ordination of civil infrastructure projects such as railway, bridges, aviation, utilities, marine works.\nChartered Status to HKIE or equivalent.\nFluent in spoken and written Chinese (Cantonese and/or Putonghua) and English\nFor senior engineer, the professional maturity to mentor junior engineers.\nTeam player with excellent interpersonal and communication skills\nFamiliarity and understanding of Hong Kong design codes and standards is an advantage.\n\nJob Duties\n\n\nDesign of civil structures and/or project management for major infrastructure projects in Hong Kong\nParticipate in interdisciplinary co-ordination of project deliverables.\nPrepare study reports, design reports, technical notes and specific project deliverables.\nFor senior engineers, assist the project managers in the management of specific projects and liaison with clients.\u00a0\n\nAECOM is a place where you can put your innovative thinking and business skills into high gear and work alongside other highly intelligent and motivated people. It's a place where you can apply your skills to some of the world's most challenging, interesting, and meaningful projects worldwide. It's a place that values the diversity of our areas of practice and our people. It's what makes AECOM a great place to work and grow. AECOM is an Equal Opportunity Employer.\n\n\nFor more information on AECOM, please visit our website at www.aecom.com.\u00a0", "employment_types": ["Full Time", "Permanent"], "selling_points": ["A minimum 4 years of experience", "A recognized degree in Civil Engineer", "Chartered Status to HKIE or equivalent"], "locations": ["Shatin Area"], "categories": ["Building & Construction", "Building / Construction / QS", "Civil / Structural", "Engineering", "Engineering Project Management"], "post_time": "2022-01-15T13:16:41Z", "salary": {"currency": null, "max": null, "min": null, "period": "monthly", "term": null}, "salary_visible": false, "title_keywords": ["senior engineer", "engineer", "project engineer"], "responsibilities": ["management", "project deliverables", "infrastructure", "website", "design", "project management", "reports"], "requirements": {"degrees": ["degree"], "majors": ["civil engineering"], "languages": ["cantonese", "putonghua", "english", "chinese"], "language_level": ["fluent"], "hard_skills": ["hkie", "codes"], "soft_skills": ["communication skills", "team player", "interpersonal"], "languages_combined": [{"language": "cantonese", "language_level": ["fluent"]}, {"language": "putonghua", "language_level": ["fluent"]}, {"language": "english", "language_level": ["fluent"]}, {"language": "chinese", "language_level": ["fluent"]}]}, "experience_required": {"duration": ["minimum 4 years"], "field": ["infrastructure", "construction", "design"]}}, {"job_id": "100003009043878", "location_code": "hk", "company": "Citybase Property Management Limited", "job_title": "Engineer", "description": "Responsibilities:\u00a0\n\nTo monitor\u00a0property maintenance, building renovation and E & M work\nTo prepare the tender document of R & M work\n\nRequirements:\n\nHigh Diploma/Degree in Building Services Engineering/ Electrical Engineering or related disciplines.\nAt least 5 years experience in property & facilities maintenance of which 3 years at supervisory level/ experience at direct technical staff and outside contractors.\nGood knowledge in the operation of electrical installation, air-conditioning system and builder works.\nHands-on experience in preparing technical specifications for the works/tenders.\nRegistered Electrical Worker ( Grade B is preferable).\nAble to work independently and self-motivated.\nFamiliar with ISO9001, OSH18001 is preferable.\nCandidates with less experience or qualification\u00a0will be considered as Senior Technical Officer\n\nWe will offer attractive compensation package to the right candidate. Please send application enclosing resume stating career and salary history, expected salary and date of availability to HR Manager, Citybase Property Management Limited, Unit No.1, 6/F, Hampton Loft, 11 Hoi Fan Road, Tai Kok Tsui, Kowloon by fax at 2717 4717 or by clicking \"Apply Now\"\u00a0(in Word format). Please quote the reference of the position you apply for in all correspondences.\n\nWe are an equal opportunity employer and welcome applications from all qualified candidates. Personal data collected will be treated in strictest confidence and handled confidentially by authorized personnel for recruitment-related purposes within the Group. Applicants not hearing from us within six weeks from the date of advertisement may consider their applications unsuccessful.", "employment_types": ["Full Time", "Permanent"], "selling_points": ["Certificate of Diploma holder", "Minimum 5 years experience in maintenance", "Good command of spoken English and Cantonese"], "locations": ["Tin Shui Wai"], "categories": ["Building & Construction", "Building / Construction / QS", "Engineering", "Engineering Project Management", "Others", "Technician"], "post_time": "2022-01-17T09:51:26Z", "salary": {"currency": null, "max": null, "min": null, "period": null, "term": null}, "salary_visible": false, "title_keywords": ["engineer"], "responsibilities": ["tender document", "renovation", "monitor", "maintenance"], "requirements": {"degrees": ["high diploma", "degree"], "majors": ["related disciplines", "building services", "engineering", "electrical engineering"], "languages": [], "language_level": [], "hard_skills": ["no", "word", "maintenance"], "soft_skills": ["hands-on", "confidence", "work independently", "self-motivated"], "languages_combined": []}, "experience_required": {"duration": ["3 years", "at least 5 years"], "field": ["supervisory level", "maintenance"]}}, {"job_id": "100003009055726", "location_code": "hk", "company": "Airport Authority Hong Kong", "job_title": "Project Engineer (Quality)", "description": "This is a fixed-term contract position of minimum 2 years with possibility for renewal subject to organization need and individual performance.\n\u00a0\nThe incumbent is responsible for providing support to the Senior Project Engineer (Quality) for the effective and efficient project management of design and construction contracts to ensure that both the medium and long term development projects are planned and delivered to meet the Authority\u2019s quality standards.\n\n\nResponsibilities:\n\n\u2022\u00a0\u00a0 \u00a0Assist in supervision / management of Quality Assurance and Quality Control. Coordination with project team and contractor to ensure quality procedures are fully implemented;\n\u2022\u00a0\u00a0 \u00a0Assist in conducting and preparing Quality Audit Reports;\n\u2022\u00a0\u00a0 \u00a0Assist in conducting and preparing Internal Surveillance Checks on various contracts teams;\n\u2022\u00a0\u00a0 \u00a0Assist in preparing and updating audit schedules, table and summaries\n\u2022\u00a0\u00a0 \u00a0Co-ordination with project teams for monitoring and closing out of NCRs and Site Notices. Coordination with project teams in closing out audit observations and maintaining updated record of\u00a0materials test reports.\n\nRequirements:\n\u2022\u00a0\u00a0 \u00a0Bachelor's degree in Civil / Structural Engineering or related disciplines\n\u2022\u00a0\u00a0 \u00a0At least 6 years\u2019 relevant experience, of which minimum of 3 years should be in QA/QC\n\u2022\u00a0\u00a0 \u00a0Member of HKIE or other equivalent professional bodies\n\u2022\u00a0\u00a0 \u00a0Experience in the management of civil and building works construction and site supervision\n\u2022\u00a0\u00a0 \u00a0Auditing skills of contractor audit/internal audit is an advantage\n\u2022\u00a0\u00a0 \u00a0Proven practical experience in project quality management is an advantage\n\u2022\u00a0\u00a0 \u00a0Strong communication, analytical and negotiation skills\n\u2022\u00a0\u00a0 \u00a0Good command of spoken and written English and Chinese. Knowledge of Putonghua is an advantage\n\u2022\u00a0\u00a0 \u00a0Proficient in MS Office applications, project management software tools, Aconex and SnagR is an added advantage", "employment_types": ["Full Time"], "selling_points": ["Degree holder in Civil/Structural Engineering", "At least 6 years' relevant working experience", "3 years in quality control, auditing"], "locations": ["Airport Area"], "categories": ["Engineering", "Building & Construction", "Civil / Structural", "Engineering Project Management"], "post_time": "2022-01-18T02:53:42Z", "salary": {"currency": null, "max": null, "min": null, "period": "monthly", "term": null}, "salary_visible": false, "title_keywords": ["project engineer"], "responsibilities": ["management", "maintaining", "schedules", "contracts", "coordination with", "quality", "procedures", "audit", "teams", "monitoring", "reports", "quality control"], "requirements": {"degrees": ["degree", "bachelor"], "majors": ["related disciplines", "structural engineering"], "languages": ["putonghua", "english", "chinese"], "language_level": ["advantage", "good command"], "hard_skills": ["project management", "hkie", "ms office"], "soft_skills": ["communication", "project management", "negotiation skills"], "languages_combined": [{"language": "putonghua", "language_level": ["advantage"]}, {"language": "english", "language_level": ["good command"]}, {"language": "chinese", "language_level": ["good command"]}]}, "experience_required": {"duration": ["at least 6 years", "minimum of 3 years"], "field": ["management", "qa", "relevant experience", "quality management", "construction"]}}, {"job_id": "100003009055530", "location_code": "hk", "company": "China Mobile International Limited", "job_title": "Assistant Project Manager (CMIJD-0819-APMD&SDCHK)", "description": "Responsibilities:\n\nProject management for data business service delivery, including IEPL/IPLC, IDC, MPLS VPN, IP Transit and etc.\nManage and provide regular progress update during the project lifecycle for new circuit installation, upgrade, and relocation etc.\nCoordinate with domestic China Mobile Company and business partner/vendor to deliver the service on time.\nConduct risk management, procedure optimization and escalate all outstanding issue during provisioning stage.\nEstablish and maintain a good relationship with customers, internal teams.\nWork with overseas customers during non-office hour if necessary.\nCoordinate with internal parties to enhance the quality level if necessary.\nConsolidate, revise and update internal reports weekly and monthly.\nRequirements:\n\nBachelor's degree or above\nTechnical background such as CCNA, CCNP, IP networking skills will be an advantage\nMinimum 5 years of experience\nExcellent teamwork skills, hardworking, self-motived and able to work under pressure\nExcellent written and verbal communication skills in both English and Mandarin\n*Candidate with less experience will be considered as Senior Specialist\n\n\nInterested parties please apply in\u00a0full resume with current and expected salary\u00a0by e-mail to\u00a0hr\u00a0@\u00a0cmi.chinam obil e.com.\u00a0 Please indicate the reference in the subject line.\n\nAll personal data collected will be used for recruitment and employment related purpose only.", "employment_types": ["Full Time", "Permanent"], "selling_points": ["Manage global project delivery process", "Data service project management", "IP Transit, IEPL/UPLC, IDC, MPLS VPN"], "locations": ["Kwai Hing"], "categories": ["Engineering", "Engineering Project Management", "Telecommunication / Wireless / Radio", "Sales, CS & Business Devpt", "Technical Sales / Sales Engineer"], "post_time": "2022-01-18T02:40:53Z", "salary": {"currency": null, "max": null, "min": null, "period": "monthly", "term": null}, "salary_visible": false, "title_keywords": ["assistant project manager"], "responsibilities": ["service delivery", "installation", "management", "data", "coordinate with", "teams", "quality", "good relationship", "project management", "maintain", "reports", "internal parties"], "requirements": {"degrees": ["degree or above", "bachelor"], "majors": [], "languages": ["english", "mandarin"], "language_level": ["excellent"], "hard_skills": ["ip", "ccnp", "ccna"], "soft_skills": ["communication skills", "teamwork", "hardworking", "work under pressure"], "languages_combined": [{"language": "english", "language_level": ["excellent"]}, {"language": "mandarin", "language_level": ["excellent"]}]}, "experience_required": {"duration": ["minimum 5 years"], "field": []}}, {"job_id": "100003009026531", "location_code": "hk", "company": "TQM Consultants Co Ltd", "job_title": "Logistics and Transportation Graduate Trainee (Scheme A in LTE)", "description": "TQM Consultants Co. Limited, a well-established top-tier management consulting firm based in Hong Kong, provides a wide spectrum of consultancy services with extensive experience in various business and industrial sectors.\n\nWe are the market leader of management systems in Hong Kong, sharing 70% of the HKSAR Government/ Public Sector\u2019s Management System Consultancy and Training assignments.\n\nhttp://www.tqm.com.hk\n\nJob Detail\n\nParticipate in process improvement, quality improvement and safety/environmental/energy management project\nPrepare work proposal and project documentation\nCoordinate with various teams in the company to achieve project goals\nRegularly and timely follow up with the customer needs and objectives\nHandle ad hoc projects as assigned\nEnsure high-quality customer services are provided at all times\n\nRequirements\u00a0\n\nGraduates\u00a0(years 2020\u00a0onwards)\u00a0with good honour Degree in\u00a0Logistics and Transportation Engineering Discipline\nHolders\u00a0of Hong Kong identity card\nGood interpersonal, communication & presentation skills\nGood command of English and Chinese, both spoken and written\n\nWhy us?\n\nOfferthe\u00a0HKIE Graduate Training Scheme 'A'\u00a0in\u00a0Logistics and Transportation Discipline(LTE)\n2-year Scheme \u2018A\u2019 trainee + 2-year working to become a registered professional engineer! (6 YEARS for Non-scheme A)\nMarket-leading remuneration package (13-month pay with annual bonus and Medical, Telecom, and Training allowance)\nWork-life Balance (5-day workweek (09:00-17:30) and 2 weeks of paid ALs)\nRegular Team Building Activities\nProfessional advice and coaching regularly\n\nHow to apply? Learn more at https://www.tqm.com.hk/scheme-a", "employment_types": ["Full Time"], "selling_points": [], "locations": ["Wan Chai"], "categories": ["Engineering", "Engineering Project Management", "Transportation & Logistics", "Supply Chain"], "post_time": "2022-01-17T06:52:00Z", "salary": {"currency": null, "max": null, "min": null, "period": "monthly", "term": null}, "salary_visible": false, "title_keywords": ["logistics", "graduate trainee"], "responsibilities": ["management", "consulting", "systems", "quality", "coordinate with", "teams", "customer services", "communication", "ad hoc projects", "logistics", "project documentation"], "requirements": {"degrees": ["degree"], "majors": ["engineering"], "languages": ["english", "chinese"], "language_level": ["good command"], "hard_skills": ["documentation", "hkie", "scheme"], "soft_skills": ["timely", "communication", "presentation skills", "extensive", "interpersonal"], "languages_combined": [{"language": "english", "language_level": ["good command"]}, {"language": "chinese", "language_level": ["good command"]}]}, "experience_required": {"duration": [], "field": ["management", "business", "consulting"]}}, {"job_id": "100003009051960", "location_code": "hk", "company": "Kai Fu Property Services Co Ltd", "job_title": "Technical Assistant (Building Services/ Building Works)", "description": "Qualifications\u00a0:\n\nHolder of Higher Diploma /\u00a0Diploma / Higher Certificate\u00a0in Electrical, Building Services, Mechanical, Building Studies, Civil Engineering, Building Surveying, etc. from a HK polytechnic university / HKIVE or a technical\u00a0institute / technical college\nHolder of Certificate in Safety Supervisor Modular Course in (a) Basic Accident Prevention or (b) Basic Occupational Health or (c) Basic Safety Management or (d) Construction Safety conducted by Occupational Safety and Health Council will be an added advantage\nPossess valid Green Card\nWell versed in the application of Microsoft WORD, EXCEL,\u00a0AutoCAD\nWith positive working attitude and service-oriented mindset\nGraduates of\u00a0Year 2020/2021 will be considered\u00a0\n\nJob Duties:\n\nAssist supervisors\u00a0in\u00a0housing maintenance works, including making and recording site measurements and records;\nPrepare drawings, sketches, estimate works costs, etc.\u00a0;\nPerform ad hoc duties as assigned by superiors.\n\nWork Location : Kowloon East/ Ma On Shan\u00a0\n\n**Candidate with more than three years of relevant working experience will be considered as Maintenance Officer.\n\u00a0\n\n\nInterested parties please click the \"APPLY NOW\" to submit your application with\u00a0full resume including\u00a0contact phone\u00a0number,\u00a0date\u00a0available\u00a0in MS Word format to us.\u00a0\n\n\u00a0<Personal data collected will be treated in strictest confidence\u00a0for recruitment related purposes only>", "employment_types": ["Full Time", "Permanent"], "selling_points": [], "locations": ["Not Specified"], "categories": ["Building & Construction", "Building / Construction / QS", "Engineering", "Engineering Project Management", "Property / Real Estate", "Property Management"], "post_time": "2022-01-17T01:39:16Z", "salary": {"currency": null, "max": null, "min": null, "period": "monthly", "term": null}, "salary_visible": false, "title_keywords": ["technical assistant"], "responsibilities": ["ad hoc duties", "management", "maintenance", "sketches", "drawings", "costs"], "requirements": {"degrees": ["certificate", "diploma", "higher certificate"], "majors": ["building surveying", "building studies", "building services", "civil engineering"], "languages": [], "language_level": [], "hard_skills": ["excel", "microsoft word", "basic", "maintenance", "green card", "c", "autocad"], "soft_skills": ["positive working attitude", "service-oriented"], "languages_combined": []}, "experience_required": {"duration": [], "field": []}}, {"job_id": "100003009051686", "location_code": "hk", "company": "ASM Technology Hong Kong Limited", "job_title": "Project Engineer", "description": "ASM is a high-tech manufacturer involved in the development, manufacturing and marketing of semiconductor assembly equipment and materials. To cope with our strategic planning, we are looking for this incumbent to support on project management by ensuring the projects are executed within scope, on time, on budget, and with requirements met. In addition, the incumbent will assists project manager in the full spectrum of project lifecycle.\n\nJob Responsibilities\n\nAssist project management on maintain project plans and schedules, and ensures the project requirements are defined and meet the project\u2019s objectives\nEnsures all project milestones and deliverables are documented, approved, and stored for reusability, support, and audit purposes in designated project tools\nPrepare regular reports on project budgets, financial forecasts, and tracks actual costs and variance to the approved budget\nFinalizes projects by ensuring all necessary close-down and transition steps are taken and documented\nWorks with Management and other Project Managers to develop processes to maintain dependency tracking, and ensures project dependencies are identified and managed\nAssists in other areas of the department and company as necessary\nJob Requirements\u00a0\n\nBachelor\u2019s degree in Engineering discipline is preferred\n1-2 years of experience with engineering equipment development is preferrable\nFluent in spoken and written English, Chinese and Mandarin\nAnalytical and problem-solving ability\nDetail-oriented mindset\nStrong interpersonal skills, with the ability to build positive working relationships with diverse teams in a dynamic environment\n\n\n\nAttractive salary and fringe benefits package will be offered to the right candidates.\n\nInterested parties please submit your application with cover letter, resume, certificate and transcripts.\n\nData collected will be used for recruitment purpose only. Suitable candidates may be referred to other vacancies within our company.", "employment_types": ["Full Time", "Permanent"], "selling_points": ["Bachelor\u2019s degree in Engineering discipline", "1-2 years of experience", "Assist project management on maintain project plan"], "locations": ["Tsing Yi"], "categories": ["Engineering", "Engineering Project Management", "Others"], "post_time": "2022-01-16T21:50:47Z", "salary": {"currency": null, "max": null, "min": null, "period": "monthly", "term": null}, "salary_visible": false, "title_keywords": ["project engineer"], "responsibilities": ["project requirements", "budgets", "management", "schedules", "budget", "audit", "develop", "project management", "maintain", "reports", "plans", "costs", "tracking"], "requirements": {"degrees": ["degree", "bachelor"], "majors": ["engineering"], "languages": ["english", "chinese", "mandarin"], "language_level": ["fluent"], "hard_skills": ["problem-solving"], "soft_skills": ["problem-solving"], "languages_combined": [{"language": "english", "language_level": ["fluent"]}, {"language": "chinese", "language_level": ["fluent"]}, {"language": "mandarin", "language_level": ["fluent"]}]}, "experience_required": {"duration": ["1-2 years"], "field": ["development", "engineering"]}}, {"job_id": "100003009056010", "location_code": "hk", "company": "Robert Walters (HK)", "job_title": "AV Engineer/ ELV Engineer (5-day, client side, 32K)", "description": "We are searching for our client for a AV Engineer, it's a client representative role and below you may find the job details:\n\nResponsibilities:\n\nExecute Audiovisual projects professionally\nRepresent client and liaise with sub contractor in project coordination\nManage external resources and support teammates to complete project fully\n\nRequirements:\n\nDiploma or above in Electronic Engineering, Electrical Engineer or related disciplines\nMinimum 3 years relevant experiences\nCandidates with less experience will be considered as Assistant Engineer\nGood command of spoken and written English & Chinese", "employment_types": ["Full Time", "Temporary"], "selling_points": ["Client-side representative", "5-day work, attractive package", "Salary up to HKD 32, 000"], "locations": ["Not Specified"], "categories": ["Engineering", "Electrical / Electronics", "Engineering Project Management", "Telecommunication / Wireless / Radio"], "post_time": "2022-01-18T03:11:18Z", "salary": {"currency": null, "max": null, "min": null, "period": "monthly", "term": null}, "salary_visible": false, "title_keywords": ["engineer"], "responsibilities": ["liaise with", "project coordination"], "requirements": {"degrees": ["diploma or above"], "majors": ["related disciplines", "engineering"], "languages": ["english", "chinese"], "language_level": ["good command"], "hard_skills": [], "soft_skills": [], "languages_combined": [{"language": "english", "language_level": ["good command"]}, {"language": "chinese", "language_level": ["good command"]}]}, "experience_required": {"duration": ["minimum 3 years"], "field": []}}, {"job_id": "100003009051958", "location_code": "hk", "company": "BUDA Surveying Ltd", "job_title": "Assistant Engineer", "description": "To assist and follow up project progress\nTo coordinate with site staff, subcontractors and client's representative for field works arrangement\nIrregular field works maybe required\nDaily data entry\nGeneral support in document submission\nAny ad-hoc tasks assigned by immediate supervisor\n\nRequirements:\n\nHD or above in Civil/Building/Industrial Engineering/Environmental or related disciplines\nGood command of written and spoken both in Chinese and English\nKnowledge in AutoCAD\nProficient in the use of Microsoft Word and Excel\u00a0\nDriving License (Class 1, 2) is an advantage\nFresh Graduate is considerable\n\nWe offer internal & external training to right candidate.\u00a0 Interested parties please send detailed resume with your current and expected salary and date of availability.\nAll information provided will be treated in strict confidence and used solely for recruitment purposes.", "employment_types": ["Full Time"], "selling_points": [], "locations": ["Kwai Hing"], "categories": ["Engineering", "Engineering Project Management", "Public / Civil", "Utilities", "Building & Construction", "Others"], "post_time": "2022-01-17T01:38:31Z", "salary": {"currency": null, "max": null, "min": null, "period": "monthly", "term": null}, "salary_visible": false, "title_keywords": ["assistant engineer"], "responsibilities": ["data entry", "ad-hoc tasks", "coordinate with", "project progress", "general support"], "requirements": {"degrees": ["fresh graduate"], "majors": [], "languages": ["english", "chinese"], "language_level": ["good command"], "hard_skills": ["excel", "microsoft word", "autocad"], "soft_skills": [], "languages_combined": [{"language": "english", "language_level": ["good command"]}, {"language": "chinese", "language_level": ["good command"]}]}, "experience_required": {"duration": [], "field": []}}, {"job_id": "100003009054504", "location_code": "hk", "company": "Keio Engineering Co Ltd", "job_title": "Quantity Surveyor", "description": "To meet the rapid business expansion, we are looking for an additional new headcount of the QS talents to join our QS team. You will involve the entire tender management from evaluation to arrive the bid decisions and the cost management.\u00a0\u00a0\u00a0\n\nWhat we look for?\n\nExecute the cost estimation, cost control and analysis to reach the cost efficiency;\nPricing and estimate the cost of different material needed for the E&M projects;\nResponsible for the tender analysis & risk assessment and provide effective solution;\nPrepare and ensure tender documents and technical documentations are properly; complied with company policy and standard for tender document submission;\nLiaise with clients, or main contractors, or sub-contractors, or government regularly on tender documents, and attend tender meetings;\nDeliver the final account settlement;\nCoordinate and communicate with internal or external stakeholders.\n\nWhat you need to succeed?\n\nHigher Diploma/ Degree holder in Quantity Surveying, Engineering or Building Services Engineering;\nAt least\u00a04\u00a0years\u2019\u00a0relevant experience in E&M or Building Services industry;\nExperience in tendering, budgeting and cost control management is an advantage;\nStrong analytical mind, independent and a proactive team player;\nGood command of both written and spoken in Chinese and English.\n\nWhat we offer?\n\nStable and friendly work environment\nOpen office design\nAnnual leave\nMedical insurance\nEducation subsidy\nYear-end double pay\nDiscretionary bonus\nExcellent career development\nUnlimited beverages and snacks\nInternal and external training programme\nOn-job training\n\nInterested parties, please send your detailed resume with expected salary via \u201cApply Now\u201d for our consideration", "employment_types": ["Full Time", "Permanent"], "selling_points": ["E&M or Building Services industry", "Tendering, budgeting and cost control management", "Quantity Surveying"], "locations": ["Sai Wan"], "categories": ["Building & Construction", "Building / Construction / QS", "Engineering", "Engineering Project Management", "Mechanical"], "post_time": "2022-01-17T09:53:49Z", "salary": {"currency": null, "max": null, "min": null, "period": "monthly", "term": null}, "salary_visible": false, "title_keywords": ["quantity surveyor"], "responsibilities": ["liaise with clients", "communicate with", "cost", "management", "cost estimation", "tender documents", "budgeting", "analysis", "tendering", "tender analysis", "coordinate", "tender", "evaluation", "cost control", "tender document"], "requirements": {"degrees": ["diploma", "degree holder"], "majors": ["building services", "engineering", "surveying"], "languages": ["english", "chinese"], "language_level": ["good command"], "hard_skills": ["analysis", "documentations", "rapid"], "soft_skills": ["independent", "responsible", "analytical mind", "team player", "proactive"], "languages_combined": [{"language": "english", "language_level": ["good command"]}, {"language": "chinese", "language_level": ["good command"]}]}, "experience_required": {"duration": ["at least 4 years"], "field": ["building services", "management", "relevant experience"]}}, {"job_id": "100003009055081", "location_code": "hk", "company": "Newtech Management Services Ltd", "job_title": "Electrical Engineer (Electrical Design)", "description": "Responsibilities:\n\n\nHandling data center infrastructure design & technical support for projects, in-house design co-ordination and administration;\nPreparation of tender documentation, system specification and drawings;\nParticipate in electrical system design & process;\nProvide on-site technical support and verification, T&C etc.;\nPrepare feasibility report, design proposal, budgetary estimation, electrical design calculation, and tender bidding document for E&M projects.\nOther relevant assignments as specified by managers.\n\n\u00a0Requirements:\n\n\nDiploma / Higher\u00a0Diploma / Degree or above in Electrical Engineering or related disciplines;\n3-5 years' solid experience in\u00a0consulting firm / electrical contracting company;\nExperience in infrastructure design, such as, HV, LV, ELV, Genset system, UPS system, discrimination study etc.\nProficient in MS Office, Sketchup, AutoCAD or BIM, luminaire calculation software knowledge is preferable;\nHolder of relevant electrical license and with knowledge of using BIM & CFD will be an advantage;\nAble to work with tight schedules;\nSelf-motivated, self-disciplined, organized, detail-oriented and responsible;\nGood communication, interpersonal and problem-solving skills;\nAn attractive remuneration package and fringe benefits will be offered to the right candidate. Interested parties, please send your resume stating with current and expected salary to the Human Resources Department by clicking Apply Now.\n\n\nFor more information, please visit the corporate website at\u00a0www.newtechapac.com\n\nAll information collected will be kept strictly confidential and for recruitment purpose only.", "employment_types": ["Full Time"], "selling_points": [], "locations": ["Kowloon Bay"], "categories": ["Engineering", "Electrical / Electronics", "Engineering Project Management", "Others"], "post_time": "2022-01-18T01:11:43Z", "salary": {"currency": null, "max": null, "min": null, "period": "monthly", "term": null}, "salary_visible": false, "title_keywords": ["electrical engineer"], "responsibilities": ["data", "technical support", "infrastructure", "design", "drawings", "system design", "tender", "documentation", "report", "administration"], "requirements": {"degrees": ["diploma", "degree or above"], "majors": ["related disciplines", "electrical engineering"], "languages": [], "language_level": [], "hard_skills": ["sketchup", "bim", "problem-solving skills", "ms office", "autocad"], "soft_skills": ["organized", "self-motivated", "responsible", "detail-oriented", "communication", "problem-solving skills", "interpersonal"], "languages_combined": []}, "experience_required": {"duration": ["3-5 years"], "field": ["infrastructure", "consulting", "design"]}}, {"job_id": "100003009026532", "location_code": "hk", "company": "TQM Consultants Co Ltd", "job_title": "Engineering Management Trainee", "description": "TQM Consultants Co. Limited, a well-established top-tier management consulting firm based in Hong Kong, provides a wide spectrum of consultancy services with extensive experience in various business and industrial sectors\n\nWe are the market leader of management systems in Hong Kong, sharing 70% of the HKSAR Government/ Public Sector\u2019s Management System Consultancy and Training assignments.\n\nhttp://www.tqm.com.hk\n\nJob Detail\n\nParticipate in engineering management, process improvement, quality improvement and safety/environmental/energy management project\nPrepare work proposal and project documentation\nCoordinate with various teams in the company to achieve project goals\nRegularly and timely follow up with the customer needs and objectives\nHandle ad hoc projects as assigned\nEnsure high-quality customer services are provided at all times\n\nRequirements\u00a0\n\nGraduates\u00a0(years 2020\u00a0onwards)\u00a0with good honour Degree in\u00a0Engineering Discipline, preferably in Engineering Management\nHolders\u00a0of Hong Kong identity card\nGood interpersonal, communication & presentation skills\nGood command of English and Chinese, both spoken and written\n\nWhy us?\n\nMarket-leading remuneration package (13-month pay with annual bonus and Medical, Telecom, and Training allowance)\nWork-life Balance (5-day workweek (09:00-17:30) and 2 weeks of paid ALs)\nRegular Team Building Activities\nProfessional advice and coaching regularly", "employment_types": ["Full Time"], "selling_points": [], "locations": ["Wan Chai"], "categories": ["Engineering", "Engineering Project Management"], "post_time": "2022-01-17T06:09:49Z", "salary": {"currency": null, "max": null, "min": null, "period": "monthly", "term": null}, "salary_visible": false, "title_keywords": ["management trainee"], "responsibilities": ["management", "consulting", "systems", "quality", "coordinate with", "teams", "customer services", "communication", "ad hoc projects", "project documentation"], "requirements": {"degrees": ["degree"], "majors": ["engineering"], "languages": ["english", "chinese"], "language_level": ["good command"], "hard_skills": ["documentation"], "soft_skills": ["timely", "communication", "presentation skills", "extensive", "interpersonal"], "languages_combined": [{"language": "english", "language_level": ["good command"]}, {"language": "chinese", "language_level": ["good command"]}]}, "experience_required": {"duration": [], "field": ["management", "business", "consulting"]}}, {"job_id": "100003009051239", "location_code": "hk", "company": "iAdvantage Limited", "job_title": "Facility Engineer (Data Centre)", "description": "Responsibilities:\n\nSupervise and assign work orders to the technical team to carry out routine repair and maintenance work\nProvide technical guidance for E&M improvement works\nSchedule and implement planned maintenance works as assigned\nMonitor the progress of all contracted-out projects and tenants\u2019 fit-out works\nPrepare approval form to top management for the procurement of any goods/services\nAssist in testing and commissioning of tenants\u2019 fit-out works and handover of premises to new tenants\nMaintain ISO9001:2008 and ISO14001:2004 QEMS System for data centre operation\n\nRequirements:\n\nHigher Diploma in Electrical Engineering or Building Services Engineering or related disciplines\n5 years\u2019 relevant experience in Electrical and/or MVAC Operation and Maintenance, with Data Centre experience is highly preferred\nFamiliar with UPS, Gensets, chiller plant, LV switchboards and CRACs\nHolder of Electrical Worker License Grade A or Above\nGood remuneration and attractive fringe benefits will be offered to the successful applicant. Interested parties please apply with full resume, present & expected salary, available date by clicking \"Apply Now\". For further information, please visit our company website: http://www.iadvantage.net/\n\n\nWe are an equal opportunity employer and welcome applications from all qualified candidates. All personal data collected will be used for recruitment purpose only. Applicants not hearing from us within 3 months may consider their applications unsuccessful. All personal data collected will be destroyed within 12 months", "employment_types": ["Full Time", "Permanent"], "selling_points": ["Leading Data Centre in Hong Kong", "Foster Professional Business Partnerships", "Energetic and Flexible Working Environment"], "locations": ["Not Specified"], "categories": ["Engineering", "Electrical / Electronics", "Engineering Project Management"], "post_time": "2022-01-15T05:41:33Z", "salary": {"currency": null, "max": null, "min": null, "period": "monthly", "term": null}, "salary_visible": false, "title_keywords": ["facility engineer"], "responsibilities": ["guidance", "management", "commissioning", "maintenance", "data", "monitor", "testing", "repair", "maintain", "schedule"], "requirements": {"degrees": ["diploma"], "majors": ["related disciplines", "building services", "electrical engineering", "engineering"], "languages": [], "language_level": [], "hard_skills": ["maintenance"], "soft_skills": [], "languages_combined": []}, "experience_required": {"duration": ["5 years"], "field": ["operation", "relevant experience", "maintenance"]}}, {"job_id": "100003009053781", "location_code": "hk", "company": "Hysan Development Co Ltd", "job_title": "Manager, Technical Services (Building Maintenance)", "description": "Job Purpose\nResponsible for managing technical staff and works for operation and maintenance of building fabrics, providing technical supports and handling technical issues.\n\nKey Responsibilities\n\n\nManage building maintenance staff and works of the Technical Services Department and lead technical staff to deliver safe, reliable and cost effective operation and maintenance services in building maintenance aspects.\nEstablish operation and maintenance plans and manage the associated works to meet the above objectives.\nSupport Senior Manager, Technical Services to establish and implement plans for safety / health / environmental / sustainability issues to inline with company and departmental objectives.\nPerform staff management to meet organization and company needs.\nProvide technical support to Business Units, Property Management Department and other Departments with respect to general building issues including tenant fitting out / reinstatement, minor alteration and modification works and input on new developments.\nPlan and manage maintenance works with respect to building maintenance.\nPeriodically review and audit of building maintenance conditions for recommending and implementing works to maintain the required quality standards and conditions.\nPeriodically review and update of maintenance procedures and systems related to building maintenance.\nCompile and manage budget plans for works and O&M.\nManage procurement, contracts and projects / works under the portfolio of the Technical Services Department.\nManage and handle technical issues / works.\n\nSkills, Qualifications and Experience Requirements\n\nDegree holder in building studies, building surveying or construction related discipline\nMHKIS / MRICS or equivalent professional qualification is preferred\nMinimum 10 years relevant experience in building fabric and maintenance works with 5 years at supervisory level in a leading property developer / landlord\nGood management skills and strong sense of responsibility\nSelf-motivated and able to work under pressure\nGood PC skills\nGood interpersonal and communication skills\nGood command of spoken and written English and Chinese\n\nAn attractive remuneration package will be offered to the right candidate. Interested parties please press \"Apply now\".\n\nHysan is an equal opportunity employer.\u00a0 All information collected will be kept in strict confidence and used solely for recruitment related purposes within the Hysan Group Companies.\n\nYou may get to know more about us through www.hysan.com.hk", "employment_types": ["Full Time", "Permanent"], "selling_points": ["Manage building maintenance staff and works", "Degree holder with 10+ years relevant experience", "5-day work, 16-day AL, Dental, Double Pay + Bonus"], "locations": ["Causeway Bay"], "categories": ["Building & Construction", "Building / Construction / QS", "Engineering", "Engineering Project Management", "Mechanical"], "post_time": "2022-01-17T07:30:49Z", "salary": {"currency": null, "max": null, "min": null, "period": "monthly", "term": null}, "salary_visible": false, "title_keywords": ["manager"], "responsibilities": ["cost", "technical supports", "management", "maintenance", "technical support", "contracts", "review", "quality", "audit", "procedures", "systems", "budget", "communication", "maintain", "maintenance services", "plan", "plans", "work under pressure"], "requirements": {"degrees": ["degree holder"], "majors": ["building surveying", "building studies"], "languages": ["english", "chinese"], "language_level": ["good command"], "hard_skills": ["safe", "pc skills", "maintenance"], "soft_skills": ["communication skills", "self-motivated", "responsible", "sense of responsibility", "reliable", "interpersonal", "work under pressure"], "languages_combined": [{"language": "english", "language_level": ["good command"]}, {"language": "chinese", "language_level": ["good command"]}]}, "experience_required": {"duration": ["5 years", "minimum 10 years"], "field": ["developer", "supervisory level", "relevant experience", "maintenance"]}}, {"job_id": "100003009055768", "location_code": "hk", "company": "Hong Huan Group Limited", "job_title": "Assistant Manager (Business Development & ESG Development)", "description": "Responsibilities:\n\nAssist Director to evaluate market research data and develop integrate business analysis for Group Strategic business decision, ESG and sustainability initiatives;\nConduct research and identify market trends and potential investment / new business opportunities;\nManage analysis projects including planning, execution, reports and presentation to Directors Office;\nCommunicate with business partners to smoothen the research and analysis projects;\nKeep track of market trend and competitors\u2019 activities;\nProject document administration;\n\nRequirements:\n\nUniversity real estate / sustainability studies / Environmental Science or related discipline;\n2-5 years of market research experiences who should have strong analytical skills with experience in conducting reports and presentation.\nStrong project management skills and attention to detail;\n\nWe offer competitive remuneration package to the right candidates. Interested parties, please submit your resume (in both English and Chinese), with stating current and expected salary, availability, contact phone number by\u00a0APPLY NOW.\n\nAll applications and personal information collected will be treated in strict confidence and only be used for the purpose of recruitment and selection. The information collected will be accessed by our authorized personnel only. Unsuccessful applications will be retained for six months of possible future job matching, and will be destroyed after the expiry of six months.", "employment_types": ["Full Time", "Permanent"], "selling_points": [], "locations": ["Ngau Tau Kok"], "categories": ["Engineering", "Engineering Project Management", "Sciences, Lab, R&D", "Environmental Science / Waste Management", "Property / Real Estate", "Others"], "post_time": "2022-01-18T02:55:57Z", "salary": {"currency": null, "max": null, "min": null, "period": "monthly", "term": null}, "salary_visible": false, "title_keywords": ["assistant manager"], "responsibilities": ["communicate with", "administration", "data", "business opportunities", "analysis", "market research", "develop", "evaluate", "reports", "business analysis", "conduct research", "planning"], "requirements": {"degrees": [], "majors": [], "languages": [], "language_level": [], "hard_skills": ["project management", "analytical skills"], "soft_skills": ["project management skills", "presentation", "attention to detail", "analytical skills"], "languages_combined": []}, "experience_required": {"duration": ["2-5 years"], "field": ["market research", "analytical"]}}, {"job_id": "100003009052490", "location_code": "hk", "company": "Union Contractors Limited", "job_title": "Project Coordinator / Assistant Project Coordinator", "description": "Job Requirements:\nDiploma or above of building / civil related institute or equivalent\nAt least 3 years\u2019 experience in participating for projects with Large Scale A&A Works\nAble to liaise and co-ordinate with the employers, consultants, sub-contractors and suppliers for developing construction details, monitoring site progress and conducting site co-ordination works.\nFamiliar with Auto-CAD or Micro-Station or BIM and MS Project\nImmediate available is definitely an advantage\nCandidate with less experience and / or qualification will be considered as Assistant Project Co-ordinator.\n\n\nWe offer attractive remuneration package with competitive fringe benefits to the right candidates..\n\nInterested parties please send your full resume with current and expected salary via email by clicking \"Apply Now\".\nPersonal data will be used for recruitment purpose only", "employment_types": ["Full Time", "Permanent"], "selling_points": ["Familiar with Auto-CAD or Micro-Station", "At least 3 years\u2019 experience", "Liaise and co-ordinate with the employers"], "locations": ["Not Specified"], "categories": ["Building & Construction", "Building / Construction / QS", "Civil / Structural", "Engineering", "Engineering Project Management"], "post_time": "2022-01-17T03:10:33Z", "salary": {"currency": null, "max": null, "min": null, "period": "monthly", "term": null}, "salary_visible": false, "title_keywords": ["assistant project coordinator", "project coordinator"], "responsibilities": ["liaise", "co-ordinate with", "site co-ordination", "monitoring", "developing"], "requirements": {"degrees": ["diploma or above"], "majors": [], "languages": [], "language_level": [], "hard_skills": ["cad", "bim"], "soft_skills": [], "languages_combined": []}, "experience_required": {"duration": ["at least 3 years"], "field": ["co-ordinator"]}}, {"job_id": "100003009052908", "location_code": "hk", "company": "Haven of Hope Christian Service", "job_title": "Project Manager - Facility Management (Ref : SSO/FM/PM/JDB)", "description": "Responsibilities\n\nResponsible for the management of major capital projects, from inception to completion.\u00a0 End-user management, design control, cost/cashflow management, program control, quality supervision, etc. are duties to be involved.\nIn charge of minor capital projects (costing below $10Mn) of alteration / maintenance nature.\u00a0 Responsible for the implementation and discharge of projects to meet the specified requirements within the budget and time constraints.\nCarry out initial studies and prepare project proposals for senior management and funding body consideration.\nResponsible for the maintenance planning / budgeting and maintenance management for service units.\nAdvise senior management and end-users on issues concerning maintenance, works projects and facilities management.\nCarry out management and administration duties, including supervision of staff, for the facilities management functions.\n\nRequirements\n\nBachelor\u2019s degree in Architecture or Building Survey\nMember of HKIA/HKIS or equivalent\nMinimum 5 years of solid experience in building projects\nStrong in leadership, problem solving, and communication\nGood command of written English and Chinese\nAlign with the Vision, Mission and Core Values of the Haven of Hope Christian Service\nCandidates are strongly advised to submit their portfolio with not more than 10 pages together with the application.\nPlease send full resume with expected salary and reference no. quoted to Haven of Hope Christian Service, Staff Engagement Department, 7 Haven of Hope Road, Tseung Kwan O, New Territories or via email by clicking \"Apply Now\", or via Whatsapp no. 6507 8148 (with reference no. quoted at the caption) on or before 5 February 2022. Only short-listed candidates will be notified.\nEnquiry: 2703 3227 (Phone); 6507 8148 (Whatsapp).\nFor details about our organization, please visit www.hohcs.org.hk.\nProspective employees are requested to undergo/submit Sexual Conviction Record Check for work relating to children or mentally incapacitated persons before employment. Data collected will be used for recruitment purpose only.\nThis advertisement should not be reproduced, in whole or in part, to other recruitment websites without our prior written permission.", "employment_types": ["Full Time", "Permanent"], "selling_points": [], "locations": ["Tseung Kwan O"], "categories": ["Building & Construction", "Architectural Services", "Building / Construction / QS", "Engineering", "Engineering Project Management"], "post_time": "2022-01-17T04:30:08Z", "salary": {"currency": null, "max": null, "min": null, "period": "monthly", "term": null}, "salary_visible": false, "title_keywords": ["project manager"], "responsibilities": ["administration", "cost", "management", "control", "maintenance", "budgeting", "budget", "quality", "implementation", "design", "senior management", "planning"], "requirements": {"degrees": ["degree", "bachelor"], "majors": ["architecture"], "languages": ["english", "chinese"], "language_level": ["good command"], "hard_skills": ["hope", "no", "hkis", "problem solving", "whatsapp"], "soft_skills": ["problem solving", "leadership", "communication"], "languages_combined": [{"language": "english", "language_level": ["good command"]}, {"language": "chinese", "language_level": ["good command"]}]}, "experience_required": {"duration": ["minimum 5 years"], "field": []}}, {"job_id": "100003009052451", "location_code": "hk", "company": "Eternity Consultants (HK) Ltd", "job_title": "Assistant Project Manager / Project Manager - Toys", "description": "Job Duties:\n\nManage, monitor and enhance the efficiency and effectiveness of all aspects of engineering activities within an organization including sampling and product review\nEnsure all engineering projects, initiatives, and processes are in conformance with organization\u2019s established policies and objectives\nManage the daily operations of engineering team and deliver the KPI of company for engineering and technical functions\nTo lead the team member to drive the team structure and solve the problems in consistent way\nWork on product costing, budget and control repairing and maintenance costs\nTypically reports to top management\n\nJob Requirements:\n\nBachelor\u2019s degree in Industrial Engineering or equivalent\nMinimum 6 years plastic toys\n\nSolid experience in the manufacturing field with exposure in areas of production, quality, safety, logistics and maintenance\nGood understanding of production processes and manufacturing capabilities\nStrong knowledge of practices and procedures to effectively resolve workflow issues\nStrong ability to gather, analyze and interpret information and develop, recommend and implement solutions\nDemonstrate experience in leading, guiding, and mentoring teams and individuals; understand group dynamics and team development\nResult and quality focused; great attention to detail\nEffectively communicate, both verbally and written to all levels of the organization\nGood analytical and problem solving skills are essential\nFluency in both spoken and written English and Chinese (Mandarin & Cantonese)\nERP application experience is preferable\u00a0\n\n*Interested parties, please Email full resume with current & expected salary & date available in MS WORD FORMAT ONLY to us\u00a0\u00a0or fax to 3527 0634*\n\nWe are welcome applicants resend resumes to us even you have applied jobs in our company before.\n\nFor more jobs, please visit our website:\u00a0www.hketernity.com\n\n(Personal data submitted are for recruitment purpose only.)\u00a0\n\nFor more jobs, please visit our website:\u00a0www.hketernity.com\n\n\u00a0(Personal data submitted are for recruitment purpose only.)", "employment_types": ["Full Time", "Permanent"], "selling_points": ["5 days, 13 months+bonus, bank medical", "6-8 years in project follow up in toy, plastic", "project follow up"], "locations": ["Not Specified"], "categories": ["Engineering", "Engineering Project Management", "Manufacturing", "Manufacturing Management", "Product Development / Management"], "post_time": "2022-01-17T03:04:12Z", "salary": {"currency": null, "max": null, "min": null, "period": "monthly", "term": null}, "salary_visible": false, "title_keywords": ["assistant project manager", "project manager"], "responsibilities": ["control", "management", "maintenance", "policies", "review", "monitor", "budget", "daily operations", "reports", "costs"], "requirements": {"degrees": ["degree", "bachelor"], "majors": ["engineering"], "languages": ["cantonese", "english", "chinese", "mandarin"], "language_level": ["fluency"], "hard_skills": ["problem solving skills", "maintenance", "erp"], "soft_skills": ["analytical and problem solving skills", "attention to detail", "focused"], "languages_combined": [{"language": "cantonese", "language_level": []}, {"language": "english", "language_level": ["fluency"]}, {"language": "chinese", "language_level": ["fluency"]}, {"language": "mandarin", "language_level": []}]}, "experience_required": {"duration": [], "field": ["manufacturing", "logistics", "maintenance"]}}, {"job_id": "100003009048866", "location_code": "hk", "company": "Ebro Executive Search Limited", "job_title": "Facilities Engineer / Project Engineer - Data Center MEP", "description": "The Job\n\nClient: 1) E&M Contractor, 2) Asset Management Company\nPosition: Facilities Engineer / Project Engineer\nResponsibilities:\nFacilities Engineer: Carry out preventive and corrective maintenance to all E&M facilities in the data center. Routine inspections. Liaise with and manage works of contractors\nProject Engineer: Assist in project planning, site installation coordination & supervision, testing & commissioning\n$25-45K. Medical, Bonus.\n\nRequirements\n\nTertiary educated in Electrical / Mechanical / Building Services Engineering or related discipline\nMin. 3 years MEP installation / maintenance experience for data center projects\nFamiliar with UPS, CRAC, chiller, switchboards\nRegistered Electrical Worker, REW A(0) or above\nGood communication skills\nGood command of languages", "employment_types": ["Full Time", "Permanent"], "selling_points": ["E&M Contractor / Asset Management Company", "Min 3yrs project / maintenance exp for data center", "$25-45K. medical, bonus"], "locations": ["Not Specified"], "categories": ["Engineering", "Electrical / Electronics", "Engineering Project Management", "Mechanical"], "post_time": "2022-01-16T21:50:22Z", "salary": {"currency": null, "max": null, "min": null, "period": "monthly", "term": null}, "salary_visible": false, "title_keywords": ["mep", "engineer", "project engineer"], "responsibilities": ["installation", "project planning", "commissioning", "maintenance", "data", "testing", "coordination", "liaise with", "asset management"], "requirements": {"degrees": [], "majors": [], "languages": [], "language_level": [], "hard_skills": ["maintenance"], "soft_skills": ["communication skills"], "languages_combined": []}, "experience_required": {"duration": ["3 years"], "field": ["installation", "maintenance"]}}, {"job_id": "100003009049918", "location_code": "hk", "company": "Fed-Supremetech Limited", "job_title": "ASSISTANT ELECTRICAL ENGINEER", "description": "ASM is a high-tech manufacturer involved in the development, manufacturing and marketing of semiconductor assembly equipment and materials. To cope with our strategic planning, we are looking for this incumbent to lead technical, and/or enterprise level initiatives by providing direction, and executing project work-streams and follow-up to ensure projects are delivered within scope, on time, and within budget. The incumbent would drive collaboration through effective leadership to develop, manage, and implement portfolio and project management practices, ensuring they are understood, adopted, and flexible in meeting user needs.\n\nJob Responsibilities\n\nCreates and maintains project plans and schedules, and ensures the project requirements are defined and meet the project\u2019s objectives\nCollaborates with employees, management, clients, and other internal and external stakeholders\nImplement portfolio and project management practices\nDevelops, executes, and composes clear and effective communications, trainings, and post-delivery support plans\nDirects large scale, technical projects, and collaborates with employees, leadership, clients, and other internal and external stakeholders\nMentors team members in project management, processes, tools, and techniques\nManages clear and specific contractual terms for required project work with vendors\nEnsures projects have the appropriate governance and management controls and practices\n\nJob Requirements\u00a0\n\nBachelor\u2019s degree in Engineering discipline is preferred\nAt least 5+ years of experience with engineering equipment development\nProject Management Program certificate preferred\nFluent in spoken and written English, Chinese and Mandarin\nDetail-minded with strong numeric and business acumen\nExpert planning and tracking skills, capable of managing multiple projects, well organized, excellent time management with respect to priorities and self-management\nAbility to create structure in ambiguous situations and design effective processes\nStrong management and leadership skills, with the ability to lead cross-functional teams effectively in a dynamic environment\nCreative problem-solving skills for maintaining project timelines and developing alternative scenarios\n\nAttractive salary and fringe benefits package will be offered to the right candidates.\n\nInterested parties please submit your application with cover letter, resume, certificate and transcripts.\n\nData collected will be used for recruitment purpose only. Suitable candidates may be referred to other vacancies within our company.", "employment_types": ["Full Time"], "selling_points": [], "locations": ["Shatin Area"], "categories": ["Engineering", "Electrical / Electronics", "Engineering Project Management", "Manufacturing & Production"], "post_time": "2022-01-14T09:27:29Z", "salary": {"currency": null, "max": null, "min": null, "period": "monthly", "term": null}, "salary_visible": false, "title_keywords": ["electrical engineer", "assistant"], "responsibilities": ["project requirements", "management", "schedules", "project management", "plans"], "requirements": {"degrees": ["certificate", "degree", "bachelor"], "majors": ["project management", "engineering"], "languages": ["english", "chinese", "mandarin"], "language_level": ["fluent"], "hard_skills": ["problem-solving skills", "project management", "dynamic", "acumen"], "soft_skills": ["detail-minded", "dynamic environment", "capable", "creative", "leadership skills", "well organized", "project management", "business acumen", "problem-solving skills", "time management"], "languages_combined": [{"language": "english", "language_level": ["fluent"]}, {"language": "chinese", "language_level": ["fluent"]}, {"language": "mandarin", "language_level": ["fluent"]}]}, "experience_required": {"duration": ["at least 5+ years"], "field": ["development", "engineering"]}}, {"job_id": "100003009051874", "location_code": "hk", "company": "LAWSGROUP", "job_title": "Project Engineer (Redevelopment Project)", "description": "We are looking for a high caliber individual to join us.\u00a0Reporting to CLP supervisor directly, the appointee will be responsible for but not limited to the following:\n\nResponsibilities:\n\nTo assist Engineers on the daily works including, but not limited to : -\n-\u00a0 Develop project proposals for technology and supplier development, including cost benefit analysis and risk management plan\n-\u00a0 Source, evaluate and recommend technology application and supplier development\n-\u00a0 Plan and control project activities, administer/monitor contract performance and conduct post implementation review\n-\u00a0 Coordinate and work with contractors to carryout on-site inspection, installation, testing & commissioning works for pilot projects\nCarry out other duties, including driving, assigned by supervisor as and when required\nTo organize and expedite flow of documents for the branches and teams.\nTo schedule appointments for Engineers and co-ordinate arrangements for meetings, conferences and travel\nTo organize and maintain files of correspondence and records\nTo prepare standard and special reports in a variety of formats and to gather, summarise and present information using word processing and presentation graphics software.\nTo guide the tour to visit the Centre\n\n\n\nRequirements:\n\nForm 5 or equivalent. Ordinary Certificate with 3 years\u2019 working experience is preferable.\nThose candidates without the abovementioned qualifications but with extensive relevant working experience will also be considered case by case. Ex-CLP working experience is preferable.\nComputer literacy in Words, Power Point, Microsoft Project and Excel\nKnowledge of requirement of FIU relevant Code of Practice and relevant procedures\nPossession of Construction Industry Safety Training Certificate\u00a0 (Green Card)\nCertified Worker of Confined Space (preferable)\nProficient of both written and spoken English & Cantonese\nPossession of a valid driving license (preferable)\nPossession of Certificate of Registration of Electrical Worker Grade B & Grade H (preferable)\n\nWe offer successful candidates a remuneration package, comprehensive benefit package and excellent career prospects. Interested parties please send your resume in details with last/current and expected salary by clicking\u00a0\u201cApply Now\u201d.", "employment_types": ["Full Time", "Permanent"], "selling_points": ["At least  2 years' relevant exprience", "Degree holder in  Architecture / Building Survey", "Handle various redevelopment projects in HK"], "locations": ["Lai Chi Kok"], "categories": ["Engineering", "Engineering Project Management", "Others"], "post_time": "2022-01-17T01:25:50Z", "salary": {"currency": null, "max": null, "min": null, "period": "monthly", "term": null}, "salary_visible": false, "title_keywords": ["project engineer"], "responsibilities": ["software", "maintain", "plan", "graphics", "control", "other duties", "monitor", "implementation", "teams", "develop", "site inspection", "testing", "conferences", "reports", "schedule", "installation", "cost", "management", "commissioning", "review", "analysis", "evaluate", "coordinate"], "requirements": {"degrees": ["certificate", "form 5 or equivalent"], "majors": [], "languages": ["cantonese", "english"], "language_level": ["proficient"], "hard_skills": ["excel", "microsoft project", "words", "green card", "certificate of registration of electrical worker", "power point", "code"], "soft_skills": ["computer literacy", "extensive"], "languages_combined": [{"language": "cantonese", "language_level": ["proficient"]}, {"language": "english", "language_level": ["proficient"]}]}, "experience_required": {"duration": ["3 years"], "field": ["relevant working experience"]}}, {"job_id": "100003009053946", "location_code": "hk", "company": "Geek Plus International Company Limited", "job_title": "Assistant Manager, Customer Care (Overnight Shift Required)", "description": "We are looking for a high caliber individual to join us.\u00a0Reporting to CLP supervisor directly, the appointee will be responsible for but not limited to the following:\n\nResponsibilities:\n\nSafety data analysis and interpretation (including report & PPT preparation);\nGiving safety improvement suggestions for daily operation;\nMaintain and promote safety and health aspects to front-line staff;\nAttend related external and internal safety meetings.\n\n\u00a0Requirements:\n\nHolder of Higher Diploma /\u00a0Certificate / Associated Degree in Safety, Health and Environment or relevant engineering disciplines;\nConversant with local statutory safety, environmental requirements and best practices;\nRegistered as a Safety Officer with 5 years or less experience in relevant field / industry;\nProficient in both written and spoken English and Chinese;\nCustomer-oriented, self-motivated and able to work under pressure;\nBasic PC knowledge.\n\n\n\nWe offer successful candidates a remuneration package, comprehensive benefit package and excellent career prospects. Interested parties please send your resume in details with last/current and expected salary by clicking\u00a0\u201cApply Now\u201d.", "employment_types": ["Full Time", "Permanent"], "selling_points": ["Exp in technical support and customer services", "Strong communication, independently and flexible", "Overnight shift is required, with allowance"], "locations": ["Kwai Hing"], "categories": ["Sales, CS & Business Devpt", "Customer Service - Supervisor / Officer", "Engineering", "Engineering Project Management", "Information Technology (IT)", "Technical / Functional Consulting"], "post_time": "2022-01-17T07:48:56Z", "salary": {"currency": null, "max": null, "min": null, "period": "monthly", "term": null}, "salary_visible": false, "title_keywords": ["assistant manager,"], "responsibilities": ["data analysis", "maintain", "daily operation", "report"], "requirements": {"degrees": ["certificate", "diploma", "degree"], "majors": ["engineering"], "languages": ["english", "chinese"], "language_level": ["proficient"], "hard_skills": ["pc knowledge", "basic"], "soft_skills": ["customer-oriented", "self-motivated", "work under pressure"], "languages_combined": [{"language": "english", "language_level": ["proficient"]}, {"language": "chinese", "language_level": ["proficient"]}]}, "experience_required": {"duration": ["5 years"], "field": []}}, {"job_id": "100003009052595", "location_code": "hk", "company": "Forward Construction Company Limited", "job_title": "PROJECT COORDINATOR", "description": "We are looking for a high caliber individual to join us.\u00a0Reporting to MTR supervisor directly, the appointee will be responsible for but not limited to the following:\n\nResponsibilities:\n\nTo coordinate, monitor and supervise the contractor\u2019s works.\nTo prepare and submit progress report about the contractor\u2019s works.\nTo inspect and monitor the site work safety.\nTo attend the tenant\u2019s meeting, progress meeting and project meeting.\nTo carry out other duties assigned by the Corporation\u2019s Representative.\nTo report to the Corporation\u2019s Representative or his delegates from time to time the status of the work assigned.\nRequirements:\n\nMore than 10 years\u2019 experience in building construction and/or building repair of which 5 years are at supervisory level.\n\nPossessing higher certificate/ higher diploma in building studies/ civil or structural engineering from VTC-IVE/THEi. (Other equivalent qualification stated in Qualification Framework is acceptable).\nPossessing Technically Competent Person (TCP) Grade T3.\nCompleted Construction Safety Supervisor Course of CICTA.\n\nWe offer successful candidates a remuneration package, comprehensive benefit package and excellent career prospects. Interested parties please send your resume in details with last/current and expected salary by clicking\u00a0\u201cApply Now\u201d.", "employment_types": ["Full Time", "Permanent"], "selling_points": ["Degree / Diploma / Certificate or above", "Minimum 5 years experience", "Familiar with costing, contract, regulations"], "locations": ["Not Specified"], "categories": ["Building & Construction", "Building / Construction / QS", "Engineering", "Engineering Project Management", "Others"], "post_time": "2022-01-17T03:30:01Z", "salary": {"currency": null, "max": null, "min": null, "period": "monthly", "term": null}, "salary_visible": false, "title_keywords": ["project coordinator"], "responsibilities": ["coordinate", "monitor", "other duties", "report"], "requirements": {"degrees": ["diploma", "higher certificate"], "majors": ["building studies", "structural engineering"], "languages": [], "language_level": [], "hard_skills": ["tcp"], "soft_skills": ["competent"], "languages_combined": []}, "experience_required": {"duration": ["5 years", "10 years"], "field": ["supervisory level", "construction"]}}, {"job_id": "100003009055890", "location_code": "hk", "company": "Hays", "job_title": "Electrical Engineering Manager", "description": "We are looking for a high caliber individual to join us. Reporting to CLP supervisor directly, the appointee will be responsible for but not limited to the following:\n\nResponsibilities:\n\n\u00a0Responsible for data analysis;\n\u00a0understand AMI, innovative service to provide customer by using Smart meters' data;\n\u00a0Familiar with Power BI & excel (and other Microsoft application).\n\nRequirements:\n\nHolder of Higher Diploma or Higher Certificate with at least 3 years\u2019 relevant working experience. Or holder of Ordinary Certificate with at least 5 years\u2019 relevant working experience;\nThose candidates without the abovementioned qualifications but with extensive relevant working experience will also be considered case by case;\nComputer literacy in Words, Power Point, Microsoft Project and Excel;\nKnowledge of requirement of FIU relevant Code of Practice and relevant procedures;\nPossession of Construction Industry Safety Training Certificate (Green Card);\nCertified Worker of Confine Space (preferable);\nProficient of both written and spoken English & Cantonese;\nPossession of a valid driving license;\nPossession of Certificate of Registration of Electrical Worker Grade B & Grade H (preferable);\nPossession of CLP\u2019s certification of Competent Person (Electrical).\n\nWe offer successful candidates a remuneration package, comprehensive benefit package and excellent career prospects. Interested parties please send your resume in details with last/current and expected salary by clicking\u201cApply Now\u201d.", "employment_types": ["Full Time", "Permanent"], "selling_points": ["Chartered Engineer", "Competitive Package", "18AL"], "locations": ["Not Specified"], "categories": ["Building & Construction", "Building / Construction / QS", "Engineering", "Electrical / Electronics", "Engineering Project Management"], "post_time": "2022-01-18T03:03:23Z", "salary": {"currency": "HKD", "max": 69999, "min": 45000, "period": "monthly", "term": null}, "salary_visible": true, "title_keywords": ["engineering manager"], "responsibilities": ["data analysis", "power bi", "data"], "requirements": {"degrees": ["certificate", "diploma", "higher certificate"], "majors": [], "languages": ["cantonese", "english"], "language_level": ["proficient"], "hard_skills": ["excel", "microsoft project", "words", "green card", "certificate of registration of electrical worker", "power point", "code"], "soft_skills": ["computer literacy", "extensive", "competent"], "languages_combined": [{"language": "cantonese", "language_level": ["proficient"]}, {"language": "english", "language_level": ["proficient"]}]}, "experience_required": {"duration": ["at least 3 years", "at least 5 years"], "field": ["relevant working experience"]}}, {"job_id": "100003009055393", "location_code": "hk", "company": "Unistress Building Construction Limited", "job_title": "Graduate Engineer - Building or Civil Engineering", "description": "We are looking for a professional, energetic and experienced engineer to join.\u00a0 Reporting to the Senior Project Engineer/ Project Manager, the candidate will be an active member of a project management team which develops and executes a mega engineering project.\u00a0 Major duties will include:\n\nResponsibilities\n\nEnsure that Company Safety, Health, Environmental and Quality framework is incorporated in all aspects of the Project\u2019s development and implementation;\nPerform Electrical system quality inspection activities in accordance with the Project Quality Plan;\nKeep Construction Superintendent / Deputy Construction Superintendent updated with status of Electrical system quality issues and alert any potential quality problems in advance;\nPerform witness inspections and monitor production processes;\nMonitor the quality and workmanship of the E&M works to ensure compliance with the contract drawings, specifications and other standards;\nMonitor the work progress and proactively anticipate interface and construction problems to ensure timely delivery and completion;\nReview, evaluate and endorse Contractor's and Suppliers\u2019 completion files and records and ensure related accuracy and adequacy;\nWitness acceptance tests and perform final quality check against design requirement, specification and acceptance criteria prior to acceptance of E&M works, as appropriate;\nProvide expertise to site team to avoid/resolve quality problems;\nMonitor Suppliers\u2019 and Contractor\u2019s quality assurance and quality control activities.\n\nRequirements:\n\nHigher Diploma in Electrical related discipline or equivalent with at least 7 years of site construction experience; or a recognized degree in Electrical related discipline with at least 5 years relevant experience; plus 2 years minimum recent experience in E&M, Instrumentation & Control system hook-up, commissioning and start-up experience;\nHong Kong Registered Electrical Worker Grade H;\nPossession of Certificate for Construction Safety Supervisors would be an advantage;\nExperience related to project scope, or related offshore project inspection experience or minimum 2 years\u2019 recent experience in E&M inspection, equipment mechanical completion, Factory Acceptance Test, functional loop check would be an advantage;\nPossess knowledge of measurement instrumentation, Pneumatic/Hydraulic actuators, Distributed Control System/ Programmable Logic Controllers and Telecommunication system installation standard and testing requirement;\nBasic understanding on explosion proof equipment installation;\nGood communication and interpersonal skills to work with different stakeholders;\nAble to work independently and under pressure;\nWilling to work under the offshore marine condition and work under shifts;\nExcellent in the use of MS Office applications, including Word, Excel and PowerPoint. Experience in using company systems would be advantage;\nGood written and spoken English and/ or Chinese. Proficient in Mandarin would be preferable.\n\nWe offer successful candidates a remuneration package, comprehensive benefit package and excellent career prospects. Interested parties please send your resume in details with last/current and expected salary by clicking\u00a0\u201cApply Now\u201d.\n", "employment_types": ["Full Time", "Permanent"], "selling_points": ["Building or Civil Engineering Graduates required", "Academic qualification gained within 3 years", "Academic qualification recognized by HKIA..."], "locations": ["Not Specified"], "categories": ["Building & Construction", "Building / Construction / QS", "Civil / Structural", "Engineering", "Engineering Project Management"], "post_time": "2022-01-18T02:26:45Z", "salary": {"currency": null, "max": null, "min": null, "period": "monthly", "term": null}, "salary_visible": false, "title_keywords": ["graduate engineer"], "responsibilities": ["quality check", "review", "monitor", "quality", "implementation", "inspection", "ensure compliance", "drawings", "evaluate", "specifications", "design", "quality control", "quality plan"], "requirements": {"degrees": ["certificate", "diploma", "degree"], "majors": [], "languages": ["english", "chinese", "mandarin"], "language_level": ["proficient", "good"], "hard_skills": ["excel", "plus", "basic", "word", "powerpoint", "ms office"], "soft_skills": ["work independently", "communication and interpersonal skills", "under pressure"], "languages_combined": [{"language": "english", "language_level": ["good"]}, {"language": "chinese", "language_level": ["good"]}, {"language": "mandarin", "language_level": ["proficient"]}]}, "experience_required": {"duration": ["2 years", "at least 5 years", "at least 7 years", "minimum 2 years"], "field": ["related", "relevant experience", "construction"]}}, {"job_id": "100003009052756", "location_code": "hk", "company": "Rise Associates Asia Limited", "job_title": "Assistant Technical Manager (Building Surveying) - Client side", "description": "\nJob responsibilities:\n\nLead the team of maintenance technicians in dealing with property repair and maintenance works for portfolio of commercial buildings\nPrepare A&A and fit-out works\u00a0\u00a0\nPrepare reports and maintenance service contracts\nMonitor the performance and progress of project and maintenance work\nControl the inventory of spares parts and equipment\nManage repair and maintenance\u2019s budget, project management fee and expenses\nLiaise and co-ordinate with both internal and external stakeholders\u00a0\n\u00a0\nJob requirements:\n\nDegree holder in Building Surveying or related discipline\nProfessional qualification such as MHKIS/ MRICS would be an advantage\nMore than 7 years\u2019 experience in building maintenance work\nProficiency in both written Chinese and English\nStrong leadership and interpersonal skills\nAble to work under pressure", "employment_types": ["Permanent"], "selling_points": ["Client side", "Commercial portfolio", "Five working days"], "locations": ["Not Specified"], "categories": ["Building & Construction", "Building / Construction / QS", "Engineering", "Engineering Project Management", "Others"], "post_time": "2022-01-17T04:07:19Z", "salary": {"currency": null, "max": null, "min": null, "period": "monthly", "term": null}, "salary_visible": false, "title_keywords": ["assistant technical manager"], "responsibilities": ["liaise", "control", "service contracts", "maintenance", "co-ordinate with", "inventory", "budget", "expenses", "project management", "repair", "monitor the performance", "prepare reports", "repair and maintenance works"], "requirements": {"degrees": ["degree holder"], "majors": ["building surveying"], "languages": ["english", "chinese"], "language_level": ["proficiency"], "hard_skills": ["maintenance"], "soft_skills": ["leadership", "interpersonal skills", "work under pressure"], "languages_combined": [{"language": "english", "language_level": ["proficiency"]}, {"language": "chinese", "language_level": ["proficiency"]}]}, "experience_required": {"duration": ["7 years"], "field": ["maintenance"]}}, {"job_id": "100003009052351", "location_code": "hk", "company": "K. H. Foundations Ltd.", "job_title": "Assistant Engineer", "description": "Fresh Graduate &/or little working experience;\nHigher Diploma / Associate in Civil Engineering;\nResponsible for coordination, submission\u00a0and technical support;\nFast learner.\n\nWe offer attractive remuneration package. Interested parties please send resume with present and expected salary to Human Resources Department or Fax 23813111.\n\n\u00a0All information collected will be kept in strictly confidential and used for recruitment purpose only.", "employment_types": ["Full Time", "Permanent"], "selling_points": [], "locations": ["Not Specified"], "categories": ["Building & Construction", "Building / Construction / QS", "Civil / Structural", "Engineering", "Engineering Project Management"], "post_time": "2022-01-17T02:50:00Z", "salary": {"currency": null, "max": null, "min": null, "period": "monthly", "term": null}, "salary_visible": false, "title_keywords": ["assistant engineer"], "responsibilities": ["technical support", "coordination"], "requirements": {"degrees": ["diploma", "fresh graduate"], "majors": ["civil engineering"], "languages": [], "language_level": [], "hard_skills": [], "soft_skills": ["coordination", "fast learner", "responsible"], "languages_combined": []}, "experience_required": {"duration": [], "field": []}}, {"job_id": "100003009046259", "location_code": "hk", "company": "Jones Lang LaSalle Management Services Ltd", "job_title": "Technical Officer - New Territories & Kowloon Districts", "description": "Job Description\u00a0\n\nHigher Diploma/Certificate in Building Services Engineering or related disciplines\nAt least 4 years\u2019 experience in Property & Facilities Management\nMonitor daily repair and maintenance works\nSelf-motivated with good communication skills\nGood command of written and spoken English and Chinese\nHands-on knowledge of PC applications including MS Office, AutoCAD, Project Management Scheduling, etc.\nHolder of Registration of Electrical Worker in Grade A (0) is an advantage\nCandidates with less experience will be considered as Senior Technician/Technician\n\nPlease apply by clicking \"Apply Now\", or submit full resume and expected salary to the HR Department, Room 1402, 14/F, Dorset House, Taikoo Place, 979 King's Road, Quarry Bay, HK or fax to 2968-4177. (Please quote the reference number on the envelope/subject of email)\n\n\nApplicants not invited for interviews within 6 weeks may consider their applications unsuccessful. Information provided will be treated with strict confidential and be used for the purpose of employment only.", "employment_types": ["Full Time", "Permanent"], "selling_points": ["High Dip holder in Electrical/ related fields", "Min. 4 yrs of relevant experience", "Electrical Worker license A"], "locations": ["Not Specified"], "categories": ["Engineering", "Electrical / Electronics", "Engineering Project Management", "Others", "Technician"], "post_time": "2022-01-15T05:45:30Z", "salary": {"currency": null, "max": null, "min": null, "period": null, "term": null}, "salary_visible": false, "title_keywords": ["technical officer"], "responsibilities": ["management", "hr", "monitor", "communication", "project management", "scheduling", "repair and maintenance works"], "requirements": {"degrees": ["certificate", "diploma"], "majors": ["related disciplines", "building services", "engineering"], "languages": ["english", "chinese"], "language_level": ["good command"], "hard_skills": ["maintenance", "pc applications", "facilities management", "project management", "ms office", "autocad"], "soft_skills": ["communication skills", "self-motivated", "project management", "hands-on"], "languages_combined": [{"language": "english", "language_level": ["good command"]}, {"language": "chinese", "language_level": ["good command"]}]}, "experience_required": {"duration": ["at least 4 years"], "field": ["management"]}}, {"job_id": "100003009055736", "location_code": "hk", "company": "Airport Authority Hong Kong", "job_title": "Construction Superintendent, Civil & Structural", "description": "This is a fixed-term contract position of minimum 2 years with possibility for renewal subject to organization need and individual performance.\n\nResponsibilities:\n\nMonitoring the quality of works of contractors, ensuring materials on site meets with the specified requirements and works are completed on schedule\nHandling daily coordination works with internal and external parties to facilitate the conduction of site works and ensuring works are conducted in a safe and efficient manner\nMonitoring and educating the workforce to work safely\nMaintaining comprehensive daily work records and preparing progress reports\nPerform shift duties including overnight as needed\n\nRequirements:\n\nHigher Diploma/Higher Certificate or above in Civil / Structural/ Buildings/Facilities Management Engineering or other related disciplines with at least 8 years' relevant working experience in site supervision of large scale multi-disciplinary projects or building works\nDegree holder in related disciplines with 4 years' experience will also be considered\nCandidates without the above specified academic qualification but have 12 years' relevant working experience will also be considered\nCandidate with less experience would be considered for Assistant Construction Superintendent, C&S\nPossess sound knowledge and experience in transport related building/complex, alternation and addition projects and fit out/building works is preferred\nExperience in airport works under a live operation environment is an advantage\nGood command of spoken and written English and Chinese with knowledge of Putonghua is an advantage\nProficient in Microsoft Office applications Holder of a valid HK driving license (Class 1, 2) is preferred", "employment_types": ["Full Time"], "selling_points": ["Monitor the quality of contractor works", "Handle daily coordination works with diff parties", "Maintain comprehensive daily work records"], "locations": ["Airport Area"], "categories": ["Building & Construction", "Engineering", "Engineering Project Management"], "post_time": "2022-01-18T02:54:07Z", "salary": {"currency": null, "max": null, "min": null, "period": "monthly", "term": null}, "salary_visible": false, "title_keywords": [], "responsibilities": ["coordination works", "maintaining", "progress reports", "internal and external parties", "monitoring", "quality", "schedule"], "requirements": {"degrees": ["diploma", "higher certificate", "degree holder"], "majors": ["related disciplines", "engineering"], "languages": ["putonghua", "english", "chinese"], "language_level": ["advantage", "good command"], "hard_skills": ["facilities management", "microsoft office"], "soft_skills": [], "languages_combined": [{"language": "putonghua", "language_level": ["advantage", "good command"]}, {"language": "english", "language_level": ["advantage", "good command"]}, {"language": "chinese", "language_level": ["advantage", "good command"]}]}, "experience_required": {"duration": ["at least 8 years", "4 years", "12 years"], "field": ["management", "engineering", "related", "structural", "relevant working experience", "operation", "construction"]}}, {"job_id": "100003009045682", "location_code": "hk", "company": "RNB Engineering Hong Kong Limited", "job_title": "Project Manager / Assistant Project Manager (Maintenance Services)", "description": "Responsibilities\n\n\nCoordinate the installation, repair and maintenance works which included electrical, plumbing & drainage, air-conditioning and builder works for all kinds of building properties, including bidding and customer relationship\u00a0management and guiding subordinates to complete related engineering tasks.\nResponsible for bidding quotation, budgeting and settlement statistics.\nResponsible for daily operation management of maintenance and repair projects and execute related processes.\nMonitoring and control the work quality and safety as per client required.\nResponsible for coordinating all related projects with customers, suppliers, subcontractors and subordinates.\nResponsible for arranging, guiding and supervising subordinates and subcontractors to complete related maintenance and repair projects.\nParticipate in various types of project meetings\n\n\u00a0Requirements\n\nBachelor\u2019s degree or above in Mechanical / Building Services / Electrical Engineering or related discipline;\nMinimum 10 years' experience in E&M, relevant experience on\u00a0Maintenance Services projects is advantageous\nProficient in AutoCAD\nGood co-ordination and interpersonal skill\nGood command of written and spoken English and Chinese\n\n\u00a0Candidates with less experience will be consider as Assistant Project Manager.\n\nFor interested parties, please email your resume with expected salary to us.\u00a0\u00a0", "employment_types": ["Full Time", "Permanent"], "selling_points": [], "locations": ["To Kwa Wan"], "categories": ["Engineering", "Electrical / Electronics", "Engineering Project Management", "Mechanical"], "post_time": "2022-01-13T08:20:44Z", "salary": {"currency": null, "max": null, "min": null, "period": "monthly", "term": null}, "salary_visible": false, "title_keywords": ["project manager", "assistant project manager"], "responsibilities": ["installation", "management", "control", "supervising", "maintenance", "budgeting", "quotation", "daily operation", "monitoring", "coordinate", "repair", "work quality", "repair and maintenance works"], "requirements": {"degrees": ["degree or above", "bachelor"], "majors": ["building services", "electrical engineering"], "languages": ["english", "chinese"], "language_level": ["good command"], "hard_skills": ["maintenance", "autocad"], "soft_skills": ["interpersonal skill"], "languages_combined": [{"language": "english", "language_level": ["good command"]}, {"language": "chinese", "language_level": ["good command"]}]}, "experience_required": {"duration": ["minimum 10 years"], "field": ["relevant experience", "maintenance"]}}, {"job_id": "100003009027332", "location_code": "hk", "company": "Ching Lee Engineering Limited", "job_title": "ASSISTANT ENGINEERS", "description": "Requirements:\nDegree holder in Civil Engineering / Structural / Geological Engineering or above.\nMinimum 2 years solid experience in site supervision and project management in site formation & foundation works.\nGood understanding of Building Ordinance, BD\u2019s control mechanism in design & supervision of Building works, Structural works.\nAble to work independently, self-motivated and responsible.\nProficiency in English and Chinese language.\nResponsibilities:\n\u00a0Response for coordination with the project engineering team in handling the supervision and monitoring of ongoing projects, provision of technical supports and liaising with consultants on construction projects.\n\u00a0Interested candidate, please send your full resume, expected salary and contact number e-mail by clicking \"Apply now\"\u00a0", "employment_types": ["Full Time", "Permanent"], "selling_points": ["2 years solid experience in site supervision", "Good understanding of Building Ordinance", "Response for coordination with the project engin"], "locations": ["Not Specified"], "categories": ["Engineering", "Engineering Project Management", "Mechanical", "Others"], "post_time": "2022-01-16T21:50:08Z", "salary": {"currency": null, "max": null, "min": null, "period": "monthly", "term": null}, "salary_visible": false, "title_keywords": ["assistant"], "responsibilities": ["technical supports", "monitoring", "coordination with", "liaising with", "contact"], "requirements": {"degrees": ["degree holder"], "majors": ["engineering", "civil engineering"], "languages": ["english", "chinese"], "language_level": ["proficiency"], "hard_skills": ["project management"], "soft_skills": ["project management", "work independently", "self-motivated", "responsible"], "languages_combined": [{"language": "english", "language_level": ["proficiency"]}, {"language": "chinese", "language_level": ["proficiency"]}]}, "experience_required": {"duration": ["minimum 2 years"], "field": ["project management"]}}, {"job_id": "100003009046814", "location_code": "hk", "company": "Johnson Controls Hong Kong Limited", "job_title": "General Manager, Service & Maintenance (Building Services)", "description": "What you will do\n\nThe candidate will be managing the Service Business (including HVAC, BMS and Fire & Security services) of the company in HK and Macau. This role is expected to deliver superb maintenance and service solutions to a wide customer base across all industry segments.\n\n\u00a0How you will do it\n\nSet and execute strategies to grow HVAC, BMS and Fire & Security services businesses\nAchieve annual secured order, revenue and margin target in accordance with Company\u2019s objectives and direction\nManage service teams to provide preventive maintenance services and repair work for systems at customer sites; and testing and commissioning of systems installed by others\nCoordinate with Sales team to prepare maintenance and repair proposals and tenders\nDevelop and maintain key customer relationships with professional knowledge and excellent service quality\nHandle customer complaints and direct service managers to resolve issues\nManage subcontractors to achieve healthy partnership\nEnsure quality of work to the satisfaction of customer\nStrengthen relationships with customers to secure more orders\nEnsure teams adhering to the compliance of EHS, Ethics Code and Company policies in all work sites\n\nWhat we look for\n\nRequired\n\nDegree holder in Building Services or engineering-related disciplines\nMinimum 20 years\u2019 HVAC, BMS and Fire & Security services experience, of which at least 10 years at managerial level\nStrong technical knowledge and experience in HVAC, BMS and Fire & Security Systems\nExperience in tracking performance of service teams\nCompetency in project planning and have strong leadership skills\u00a0\n\nPreferred\n\nGood communication and interpersonal skills\nProficient in English and Chinese\nAbility to travel, learn and train up others\nGood problem-solving techniques, organizing and planning ability\nIndependent and able to work under pressure and tight deadline\nPrior experience with government maintenance contracts is a plus\n\n", "employment_types": ["Full Time", "Permanent"], "selling_points": ["GM Experience in HVAC, BMS and Fire & Security", "With strong project planning and leadership skills", "Cover scope in Hong Kong and Macau"], "locations": ["Kwun Tong"], "categories": ["Engineering", "Engineering Project Management", "Management", "General Management", "Building & Construction", "Others"], "post_time": "2022-01-16T21:50:16Z", "salary": {"currency": null, "max": null, "min": null, "period": "monthly", "term": null}, "salary_visible": false, "title_keywords": ["general manager"], "responsibilities": ["quality", "communication", "maintain", "work under pressure", "contracts", "compliance", "teams", "testing", "develop", "commissioning", "customer complaints", "coordinate with", "tracking", "project planning", "maintenance", "policies", "systems", "repair", "sales team", "maintenance services", "planning"], "requirements": {"degrees": ["degree holder"], "majors": ["related disciplines", "building services", "engineering"], "languages": ["english", "chinese"], "language_level": ["proficient"], "hard_skills": ["plus", "maintenance", "hvac", "problem-solving", "bms", "code"], "soft_skills": ["independent", "problem-solving", "leadership skills", "communication and interpersonal skills", "work under pressure"], "languages_combined": [{"language": "english", "language_level": ["proficient"]}, {"language": "chinese", "language_level": ["proficient"]}]}, "experience_required": {"duration": ["at least 10 years", "minimum 20 years"], "field": ["managerial", "security", "maintenance"]}}, {"job_id": "100003009051685", "location_code": "hk", "company": "S' Wah Engineering Co Ltd", "job_title": "Senior Engineer", "description": "Requirement:\nB.Degree / H.Dip in Mech / B.S. Engineering or equivalent.\nProficient in CSD / Shop drawing coordination is a must.\nOver 6 years experience in Plumbing & Drainage Works is preferable.\nFamiliar with Auto CAD is an advantage.\nSelf-motivated, hard working.\nOn / Off site is required.\nCandidates with less experience / education background will be considered as Site Engineer / Assistant Engineer.\nImmediate available.\n\n\nInterested parties please send full resume with expected salary to \u00a07/F, Unit B, China Fen Hin Bldg, \u00a05 Cheung Yue St, Cheung Sha Wan, KLN or click \"Apply Now\" for an application form.\n[All applications will be treated strictly confidential and will be used for recruitment purpose only]", "employment_types": ["Full Time", "Permanent"], "selling_points": [], "locations": ["Cheung Sha Wan"], "categories": ["Building & Construction", "Building / Construction / QS", "Engineering", "Engineering Project Management", "Mechanical"], "post_time": "2022-01-16T21:50:46Z", "salary": {"currency": null, "max": null, "min": null, "period": "monthly", "term": null}, "salary_visible": false, "title_keywords": ["senior engineer"], "responsibilities": ["coordination"], "requirements": {"degrees": ["dip", "degree"], "majors": [], "languages": [], "language_level": [], "hard_skills": ["auto cad"], "soft_skills": ["self-motivated", "coordination", "hard working"], "languages_combined": []}, "experience_required": {"duration": ["6 years"], "field": ["plumbing", "drainage", "education"]}}, {"job_id": "100003009047378", "location_code": "hk", "company": "AP Rentals Limited", "job_title": "Service Engineer", "description": "Job Description\n\nTo be\u00a0responsible for equipment service inspection, machines trouble shooting and claims reports preparation related issues\nTo tackle technical problems and carry out fault investigation\nTo assist daily workshop operation and housekeeping\nTo communicate with internal parties for parts & material procurement & transportation arrangement\nTo participate in ad-hoc projects\u00a0as assigned\n\nJob Requirements\n\nHigher Diploma holder or above in Mechanical or Electrical\u00a0related disciplines\nMinimum 5 years' technical\u00a0experience in workshop & construction sites\nSelf-motivated, responsible and able to work under pressure\nTeam player with good communication skills\nAcceptable written and spoken English & Chinese including Putonghua\nKnowledge in MS Office, i.e. Word, Excel, PowerPoint & Chinese Word Processing\n\n*Candidates with less experience will be considered as\u00a0Assistant Service Engineer\n\n*Fresh graduate will be considered as Engineer Trainee\n\nInterested parties, please click \"APPLY NOW\" and send us your full resume, stating date available, present\u00a0and expected salary.\n\n\n(Applicant without stating the expected salary will not be considered)\n\nAll data collected will be used for recruitment purpose only and will be treated as strictly confidential.\u00a0 All unsuccessful applications will be destroyed upon completion of the selection process.\n\nOur website: www.aprentalshk.com\u00a0", "employment_types": ["Full Time", "Permanent"], "selling_points": [], "locations": ["Yuen Long"], "categories": ["Engineering", "Electrical / Electronics", "Engineering Project Management", "Mechanical"], "post_time": "2022-01-14T02:56:37Z", "salary": {"currency": null, "max": null, "min": null, "period": "monthly", "term": null}, "salary_visible": false, "title_keywords": ["service engineer"], "responsibilities": ["housekeeping", "workshop", "investigation", "inspection", "reports", "communicate with internal parties", "ad-hoc projects"], "requirements": {"degrees": ["fresh graduate", "higher diploma holder"], "majors": ["related disciplines"], "languages": ["putonghua", "english", "chinese"], "language_level": [], "hard_skills": ["excel", "chinese word processing", "word", "powerpoint", "ms office"], "soft_skills": ["communication skills", "self-motivated", "responsible", "team player", "work under pressure"], "languages_combined": [{"language": "putonghua", "language_level": []}, {"language": "english", "language_level": []}, {"language": "chinese", "language_level": []}]}, "experience_required": {"duration": ["minimum 5 years"], "field": ["construction"]}}, {"job_id": "100003009044888", "location_code": "hk", "company": "Harbour City Estates Ltd", "job_title": "SENIOR BUILDING SERVICES ENGINEER (Tenancy Services & Premises Improvement)", "description": "Responsibilities:\n\n\nResponsible for day-to-day fitting out and reinstatement works for shops and office premises including feasibility study for A&A / conversion projects, project design and tendering; review of A&A submission and fit-out drawings; project management and coordination\n\nMonitor the site work progress and supervise the works of contractors\n\nParticipate in site meeting and handle contract administration\nEnsure all the works fulfill the legislative, health and safety requirements\nPerform ad-hoc assignments as required\n\nRequirements:\u00a0\n\n\nDegree holder in Building Services / Building Surveying / Building Studies or related disciplines\nAt least 5 years\u2019 solid experience in handling improvement or maintenance projects, experience gained in property management companies / shopping mall environment in relation to the fitting out works and government submission is an advantage\nGood project management, interpersonal and communication skills\nProficiency in using AutoCAD & Photoshop, preferably in using MS Project\nGood command in both written and spoken English and Chinese\nWe offer competitive remuneration package that commensurate with experience and qualifications. Interested parties are invited to send full resume stating contact telephone number, date available, present and expected salary to our recruitment email address.\n\n(Personal data provided will be used strictly in accordance with the Company's personal data policy which is available upon request.)", "employment_types": ["Full Time", "Permanent"], "selling_points": ["Degree holder in Building Services", "At least 5 years' solid experiences", "Proficiency in using AutoCAD & Photoshop"], "locations": ["Tsim Sha Tsui"], "categories": ["Building & Construction", "Building / Construction / QS", "Engineering", "Engineering Project Management", "Property / Real Estate", "Property Management"], "post_time": "2022-01-15T03:49:22Z", "salary": {"currency": null, "max": null, "min": null, "period": null, "term": null}, "salary_visible": false, "title_keywords": ["building services engineer"], "responsibilities": ["contract administration", "ad-hoc assignments", "review", "monitor", "tendering", "design", "drawings", "project management", "coordination"], "requirements": {"degrees": ["degree holder"], "majors": ["related disciplines", "building surveying", "building studies", "building services"], "languages": ["english", "chinese"], "language_level": ["good command"], "hard_skills": ["project management", "photoshop", "maintenance", "autocad"], "soft_skills": ["communication skills", "project management", "interpersonal"], "languages_combined": [{"language": "english", "language_level": ["good command"]}, {"language": "chinese", "language_level": ["good command"]}]}, "experience_required": {"duration": ["at least 5 years"], "field": ["management", "maintenance"]}}, {"job_id": "100003009047671", "location_code": "hk", "company": "Goodwell Property Management Ltd", "job_title": "Technical Officer (Ref: TO/J)", "description": "Higher Diploma /\u00a0Certificate in Building Services\u00a0Engineering or related disciplines\n2-4 years' experience in property & facilities management\nMonitor daily repair and maintenance works\nSelf-motivated with good communication skills\nGood command of both\u00a0written and spoken English and Chinese\n\nCandidates with less experience will be considered as Assistant Technical Officer\n\nWe will offer attractive compensation package to the right candidate. Please send application enclosing resume stating career and salary history, expected salary and date of availability to The Human Resources Manager, Goodwell Property Management Limited, 2/F New Treasure Centre, 10 Ng Fong Street, San Po Kong, Kowloon\u00a0or\u00a0by clicking \u201cApply Now\u201d (in Word format). Please quote the reference of the position you apply for in all correspondences.\n\nWe are an equal opportunity employer and welcome applications from all qualified candidates.\u00a0 Personal data collected will be treated in strictest confidence and handled confidentially by authorized personnel for recruitment-related purposes within the\u00a0Group. Applicants not hearing from us within six weeks from the date of\u00a0application may consider their applications unsuccessful.\n\n(Our website : http://www.goodwell.com.hk/)", "employment_types": ["Full Time", "Permanent"], "selling_points": ["2-4 years' experience in property management", "Monitor daily R&M for residential buildings", "Higher Diploma in Building Services Engineering"], "locations": ["Not Specified"], "categories": ["Building & Construction", "Building / Construction / QS", "Engineering", "Engineering Project Management", "Property / Real Estate", "Property Management"], "post_time": "2022-01-15T03:49:49Z", "salary": {"currency": null, "max": null, "min": null, "period": null, "term": null}, "salary_visible": false, "title_keywords": ["technical officer"], "responsibilities": ["management", "monitor", "website", "communication", "recruitment", "personal data", "repair and maintenance works"], "requirements": {"degrees": ["certificate", "diploma"], "majors": ["related disciplines", "building services", "engineering"], "languages": ["english", "chinese"], "language_level": ["good command"], "hard_skills": ["facilities management", "word", "maintenance"], "soft_skills": ["communication skills", "self-motivated", "confidence"], "languages_combined": [{"language": "english", "language_level": ["good command"]}, {"language": "chinese", "language_level": ["good command"]}]}, "experience_required": {"duration": ["2-4 years"], "field": ["management"]}}, {"job_id": "100003009046662", "location_code": "hk", "company": "Ovation Holdings Limited", "job_title": "Assistance Project  Engineer / Trainee (Hard toys and Soft-Toys)", "description": "1. Graduate of Diploma or above in Engineering / Textile/ Design\n2. 0-2 years working experience at OEM toys factory is preferrable and fresh graduate are also welcome\n3. knowledge in doll toys development is preferrable\n4. Interested in development for both hard and soft toys.\n5. Well knowledge in gobal toy safety (ASTM, EN, etc\u2026.) is preferrable\n6. Excellent communication skill and good command of Cantonese, English and Mandarin.\n7. Frequent travel to China factory / may need to stay in China if required.\n8. Experience to product cost structure and prepare quotations with advantage", "employment_types": ["Full Time"], "selling_points": ["Five-day work week, Double pay", "Medical insurance", "Transportation allowance"], "locations": ["Shatin Area"], "categories": ["Engineering", "Engineering Project Management", "Mechanical", "Others", "Student / Fresh Graduate / No Experience"], "post_time": "2022-01-13T18:54:09Z", "salary": {"currency": null, "max": null, "min": null, "period": "monthly", "term": null}, "salary_visible": false, "title_keywords": ["engineer", "assistance", "trainee"], "responsibilities": ["communication", "cost", "design"], "requirements": {"degrees": ["fresh graduate", "diploma or above"], "majors": ["engineering", "design"], "languages": ["cantonese", "english", "mandarin"], "language_level": ["excellent", "good command"], "hard_skills": [], "soft_skills": ["communication skill", "interested in"], "languages_combined": [{"language": "cantonese", "language_level": ["excellent", "good command"]}, {"language": "english", "language_level": ["excellent", "good command"]}, {"language": "mandarin", "language_level": ["excellent", "good command"]}]}, "experience_required": {"duration": ["0-2 years"], "field": ["toys"]}}, {"job_id": "100003009051231", "location_code": "hk", "company": "Diligence (VAB) Consultants Limited", "job_title": "Assistant Project Manager", "description": "Jobs Requirements:\n- Higher Diploma or above in Building Studies or related disciplines\n- Minimum 2-3 years relevant experiences in fitting-out project management\n- Strong attention to details,\u00a0high flexibility, able to work under pressure\n- Strong negotiation & communications skills and good team player\n- Good command in both written and spoken English and Chinese\n\nJobs Responsibilities:\n- Participate at the stage of preparation of tenders\n- To monitor and manage site activities progress and coordinate with internal and external parties\n- To assist preparing necessary document submission\u00a0\n- To monitor project progress, quality, cost control and technical matters\n- Report directly to Project Director/ Project Manager\n\n\n\nWe offer reasonable remuneration packages, including performance bonus, annual leave, birthday leave, bank holiday, 6-day work (alternative leave), medical & transportation allowances for the right candidate. Interested parties, welcome to browse to our website www.diligence.com.hk, and send detail resume with expected salary & date availability by clicking \"Apply Now\".\n\n*\u00a0Information provided will be treated with strict confidence and be used for the purpose of selection only.*", "employment_types": ["Full Time"], "selling_points": ["Higher Diploma or above in Building Studies", "2-3 Years in Fitting-out Experiences", "Performance Bonus, Bank Holiday, Medical"], "locations": ["Wan Chai"], "categories": ["Building & Construction", "Building / Construction / QS", "Engineering", "Engineering Project Management"], "post_time": "2022-01-15T19:11:49Z", "salary": {"currency": null, "max": null, "min": null, "period": "monthly", "term": null}, "salary_visible": false, "title_keywords": ["assistant project manager"], "responsibilities": ["monitor project progress", "site activities", "internal and external parties", "monitor", "coordinate with", "quality", "cost control", "report"], "requirements": {"degrees": ["higher diploma or above"], "majors": ["related disciplines", "building studies"], "languages": ["english", "chinese"], "language_level": ["good command"], "hard_skills": ["project management"], "soft_skills": ["good team player", "negotiation", "project management", "attention to details", "work under pressure"], "languages_combined": [{"language": "english", "language_level": ["good command"]}, {"language": "chinese", "language_level": ["good command"]}]}, "experience_required": {"duration": ["minimum 2-3 years"], "field": ["project management"]}}, {"job_id": "100003009051818", "location_code": "hk", "company": "Hong Kong Applied Science and Technology Research Institute Company Limited (ASTRI)", "job_title": "ASIC Digital Design and Development - Principal Engineer", "description": "Reference #:\u00a0CTO/CCT/04\n\nJob Responsibilities\nWork with the technical team in algorithm, hardware architecture design and development.\nWork with the technical team to implement RISC-V SoC on FPGA\nWork with Software engineers to boot up RISC-V processor\nAssist in R&D project\u2019s planning and management\nConduct research in RISC-V architecture and Trusted Execution Environment\nProvide training and to develop team members\nRequirements\nPh.D. or Master holder in Computer Science, Electronic Engineering, Electrical Engineering, Information Engineering, IC Design or relevant disciplines with a minimum of 6 years of related experience\nExperience in HDL coding is highly preferred\nHands-on experience in IC design and verification is highly preferred\nExperience in processor integration and development is an advantage\nKnowledge on Trusted Execution Environment is an advantage\nExperience in FPGA prototyping and debugging is an advantage\nExcellent analytical and troubleshooting skills is highly preferred\nPassionate about new technology\nLive the ASTRI values\nApplication\n\n\nThe appointment will be on renewable contract terms with a competitive salary and performance-linked variable pay. Fringe benefits include paid leave, medical and dental benefits, insurance coverage and contribution to MPF. The incumbent will normally work\u00a0a five-day week.\n\nInterested candidates, please send an application (quoting Ref. No.) with a detailed resume, current and expected salary to\u00a0Talent Acquisition by clicking \"APPLY NOW\".\u00a0The resume should\u00a0not\u00a0include any sensitive personal information such as HKID or passport number, photo, etc.\u00a0Application open until this position is filled.\n\nPosition offer is subject to the applicant\u2019s experience and academic qualification. The application will be open until the position is filled. Only short-listed candidates will be notified. ASTRI reserves the right not to fill the position.\n\nASTRI is an Equal Opportunities Employer. Personal data provided by job applicants will be used\u00a0exclusively\u00a0for recruitment\u00a0only. For details, please refer to\u00a0Privacy - ASTRI - Hong Kong Applied Science and Technology Research Institute Company Limited, in particular section 9.", "employment_types": ["Full Time", "Contract"], "selling_points": ["ASIC Digital Design and Development", "Algorithm, hardware architecture design", "Conduct research in RISC-V architecture"], "locations": ["Shatin Area"], "categories": ["Engineering", "Electrical / Electronics", "Engineering Project Management", "Sciences, Lab, R&D", "Research & Development (R&D)"], "post_time": "2022-01-17T01:16:32Z", "salary": {"currency": null, "max": null, "min": null, "period": "monthly", "term": null}, "salary_visible": false, "title_keywords": ["engineer"], "responsibilities": ["provide training", "management", "software", "conduct research", "design", "develop", "hardware", "architecture", "planning"], "requirements": {"degrees": ["master"], "majors": ["design", "engineering", "computer science", "electrical engineering"], "languages": [], "language_level": [], "hard_skills": ["integration"], "soft_skills": ["hands-on", "troubleshooting", "passionate about"], "languages_combined": []}, "experience_required": {"duration": ["minimum of 6 years"], "field": ["related", "development", "engineering", "design"]}}, {"job_id": "100003009044970", "location_code": "hk", "company": "Harbour City Estates Ltd", "job_title": "TECHNICAL SUPERVISOR (FITTING OUT)", "description": "Responsibilities:\n\nResponsible for day-to-day supervision of in-house technicians and contractors on fitting out and reinstatement works for shop and office premises in the shopping mall\nAttend emergency calls on fitting out and reinstatement related issues\nPrepare reports on inspections and incidents\nMaintain the inventory records and stock control in the warehouse\n\nRequirement:\n\nCertificate holder or above in Building Services Engineering or related disciplines\nHolder of Green Card, candidate with Grade \u201cA\u201d Certificate of Registered Electrical Worker is an advantage\nAt least 5 years\u2019 relevant experience in project management and building services system operation & maintenance gained in commercial building / hotel / large shopping mall, of which at least 1 year in supervisory role\nGood written in English and Chinese\n\nWe offer 5-day week and competitive salary package commensurate with experience and qualifications.\u00a0 Interested parties are invited to send full resume sating contact telephone number, date available, present and expected salary to our recruitment email address.\n\n(Personal data provided will be used strictly in accordance with the Company\u2019s personal data policy which is available upon request.)", "employment_types": ["Full Time", "Permanent"], "selling_points": ["Certificate in Building Services Engineering", "At least 5 years\u2019 solid experience", "Responsible for fitting out and reinstatement work"], "locations": ["Tsim Sha Tsui"], "categories": ["Building & Construction", "Building / Construction / QS", "Engineering", "Engineering Project Management", "Property / Real Estate", "Property Management"], "post_time": "2022-01-15T03:49:25Z", "salary": {"currency": null, "max": null, "min": null, "period": null, "term": null}, "salary_visible": false, "title_keywords": ["technical supervisor"], "responsibilities": ["prepare reports", "inventory", "maintain", "control"], "requirements": {"degrees": ["certificate"], "majors": ["related disciplines", "building services", "engineering"], "languages": ["english", "chinese"], "language_level": ["good"], "hard_skills": ["project management", "maintenance", "green card"], "soft_skills": ["project management"], "languages_combined": [{"language": "english", "language_level": ["good"]}, {"language": "chinese", "language_level": ["good"]}]}, "experience_required": {"duration": ["at least 5 years", "at least 1 year"], "field": ["supervisory", "maintenance", "project management", "commercial", "operation", "relevant experience", "building services"]}}, {"job_id": "100003009051860", "location_code": "hk", "company": "Hong Kong Applied Science and Technology Research Institute Company Limited (ASTRI)", "job_title": "Machine Learning - Senior Lead Engineer / Lead Engineer", "description": "Reference #:\u00a0CTO/IOTSEN/10\n\n\nJob Responsibilities\n\n\nPropose, review, and execute projects advancing the practical state-of-the-art in machine learning (ML) and deep learning (DL)\nResearch and implement ML and DL technologies both independently and as part of collaborative teams to solve industrial vision-related problems\nDevelop and prototype ML/DL algorithms and software\nWork with hardware engineers to integrate a software into a well-tested and robust system\nProvide excellent communication with customers, partners, and teammates\nTake business trips to other cities for onsite support occasionally\nPerform other related duties and responsibilities, on occasion, as assigned\nRequirements\nPhD holder or Master\u2019s degree in Computer Science, Electronic/Electrical Engineering, Information Engineering, Mathematics, Statistics, Physics or relevant disciplines with minimum 3 years of related experience. Candidates with less experience may also be considered.\nExposure to Python or C++ programming\nExperience with DL frameworks such as TensorFlow, PyTorch and others.\nExposure to C, C# or CUDA programming is a plus\nFamiliar with maintenance of workstations and clusters for ML/DL is a plus\nStrong teamwork and good analytical thinking skills\nGood verbal and written communication skills in English\nLive ASTRI values\nApplication\n\nThe appointment will be on renewable contract terms with a competitive salary and performance-linked variable pay. Fringe benefits include paid leave, medical and dental benefits, insurance coverage and contribution to MPF. The incumbent will normally work\u00a0a five-day week.\n\nInterested candidates, please send an application (quoting Ref. No.) with a detailed resume, current and expected salary to\u00a0Talent Acquisition by clicking \"APPLY NOW\".\u00a0The resume should\u00a0not\u00a0include any sensitive personal information such as HKID or passport number, photo, etc.\u00a0\n\nPosition offer is subject to the applicant\u2019s experience and academic qualification. The application will be open until the position is filled. Only short-listed candidates will be notified. ASTRI reserves the right not to fill the position.\n\nASTRI is an Equal Opportunities Employer. Personal data provided by job applicants will be used\u00a0exclusively\u00a0for recruitment\u00a0only. For details, please refer to\u00a0Privacy - ASTRI - Hong Kong Applied Science and Technology Research Institute Company Limited, in particular section 9.", "employment_types": ["Full Time", "Contract"], "selling_points": ["Deep learning", "Research and implement ML and DL technologies", "Develop and prototype ML/DL algorithms"], "locations": ["Shatin Area"], "categories": ["Engineering", "Electrical / Electronics", "Engineering Project Management", "Sciences, Lab, R&D", "Research & Development (R&D)"], "post_time": "2022-01-17T01:23:55Z", "salary": {"currency": null, "max": null, "min": null, "period": "monthly", "term": null}, "salary_visible": false, "title_keywords": ["engineer", "lead"], "responsibilities": ["software", "review", "teams", "develop", "communication", "hardware"], "requirements": {"degrees": ["degree", "master"], "majors": ["mathematics", "engineering", "electrical engineering", "statistics", "physics", "computer science"], "languages": ["english"], "language_level": ["good"], "hard_skills": ["plus", "c++", "maintenance", "cuda", "ml", "c", "programming", "python", "c#"], "soft_skills": ["communication skills", "teamwork"], "languages_combined": [{"language": "english", "language_level": ["good"]}]}, "experience_required": {"duration": ["minimum 3 years"], "field": ["related", "statistics", "engineering"]}}, {"job_id": "100003009056020", "location_code": "hk", "company": "VTech Telecommunications Limited", "job_title": "Senior Software Engineer \u2013 IoT Product Development (VTT263/J07)", "description": "We are expanding our research and development team in Hong Kong to research, develop, enhance and implement our innovative solutions for multiple industry/sector leaders. We are looking for a proactive and energetic candidate to join our R&D team. Since we are introducing a series of disruptive products to the market, we offer a unique opportunity for our colleagues to grow with us quickly and explore multiple disciplines in addition to cloud software development.\n\nThe incumbent of this role will deliver a scalable, innovative, high available software to support IoT applications, collaboration in line with the business strategy.\n\nJob Duties\n\nDevelop A.I. algorithms for Cloud severs and AIoT products;\nParticipate in product requirement collection, feasibility studies, system design and tender submissions.\nDesign and implement software for IoT/AIoT products;\nConduct software test & commissioning and systems validation & verifications of the works in compliance to the project requirement;\nLiaise with the information security team to ensure security, reliability integrity and robustness of solution design;\nProvide updates related to cloud infrastructure and platform technology.\n\nRequirements\n\nMaster or Bachelor Degree holder in Engineering, Computer Science, Business or equivalent;\nAt least 5 years of experience in embedded system and software development in C/C+;\nProficiency in Linux.\nExperience in AWS or IoT sensors or embedded system is a plus.\nAt least 2 years of working experience in AWS or IoT sensors is plus;\nProficient in both verbal and written English & Chinese (Cantonese & Mandarin);\nStrong communication, interpersonal and presentation skills with the ability to communicate in both verbal and written English and Chinese;\nLeadership and people management skills will be advantageous;\u00a0\nAbility to work independently and innovatively with good technical, analytical and problem-solving skill.\n\nWe offer attractive remuneration package including 5-day work, flexible work hours and other benefits to the right candidates. Interested parties please forward cover letter and full resume with expected salary and quote job reference number to\n\nVTech Group of Companies,\u00a0\nThe Human Resources and Administration Department,\u00a0\n23/F, Block 1, Tai Ping Industrial Centre,\n57 Ting Kok Road, Tai\u00a0Po,\u00a0Hong Kong\n\nOR\u00a0apply on-line directly through our corporate website at\u00a0www.vtech.com/en/careers/\u00a0\u00a0\u00a0\n\nFor more information about us, please visit our website at\u00a0www.vtech.com\u00a0\u00a0\u00a0\n\nAll applications will be used for the purpose of recruitment only. Applicants not invited for interview within 4 weeks may consider their applications unsuccessful. We will retain the applications for a maximum period of six months and may refer them to suitable openings within our Group.\u00a0\u00a0", "employment_types": ["Full Time", "Permanent"], "selling_points": ["Formulate cloud computing platform strategy", "Experience in IT infrastructure proj. & operation", "13-month pay, bonus and flexible working hours"], "locations": ["Tai Po Area"], "categories": ["Engineering", "Engineering Project Management", "Information Technology (IT)", "Software Development", "Network & System"], "post_time": "2022-01-18T03:11:52Z", "salary": {"currency": null, "max": null, "min": null, "period": "monthly", "term": null}, "salary_visible": false, "title_keywords": ["senior software engineer", "product development"], "responsibilities": ["commissioning", "software", "information security", "systems", "compliance", "infrastructure", "design", "develop", "system design", "tender", "liaise with"], "requirements": {"degrees": ["bachelor degree holder", "master"], "majors": ["business", "engineering", "computer science"], "languages": ["cantonese", "english", "chinese", "mandarin"], "language_level": ["proficient"], "hard_skills": ["linux", "plus", "problem-solving", "aws", "c"], "soft_skills": ["work independently", "problem-solving", "communication", "presentation skills", "leadership", "interpersonal"], "languages_combined": [{"language": "cantonese", "language_level": []}, {"language": "english", "language_level": ["proficient"]}, {"language": "chinese", "language_level": ["proficient"]}, {"language": "mandarin", "language_level": []}]}, "experience_required": {"duration": ["at least 2 years", "at least 5 years"], "field": ["software development"]}}, {"job_id": "100003009049810", "location_code": "hk", "company": "China Overseas Land & Investment Ltd", "job_title": "Senior Clerk of Works / Clerk of Works", "description": "Responsibilities:\n\nCoordinate with main contractor and monitor the building works of the assigned property development project\nLiaise with consultant and contractor to ensure construction quality, progress and cost meets the contract requirement\nMonitor site activities and report critical issues\nPrepare defect list and monitor defect rectification progress and result\nAttend site meeting and prepare weekly report\n\n\n\nRequirements:\n\nDiploma or Higher Certificate in Building Construction / Building Studies or other relevant disciplines with HKICW professional qualification preferred\nAt least 8 years relevant experience in construction industry particularly in fitting out, renovation, alteration/addition works and associated building services installation works etc.\nPrevious working experience with property developer is definitely an advantage, experience in new building development is preferred\nProficient in quality requirements of the industry\nPositive, hardworking and strong communication skills\nGood command of spoken and written Chinese and English\nApplicants with less experience will be considered for Clerk of Works\n\n\n\nInterested parties please send resume with day time contact telephone number and expected salary to the Human Resources Manager,\u00a07/F, Three Pacific Place, 1 Queen's Road East, Hong Kong or\u00a0fax to 2865 7517 or visit our\u00a0website\u00a0for email application.\n\nPlease visit our website\u00a0(www.coli.com.hk) for more information about us.\n\nApplicants who are not invited within 2 months may consider their applications unsuccessful.\u00a0 All information provided by applicants will be treated in strict confidence and used only for recruitment purposes.\u00a0 Applicants may be considered for other suitable positions within the China Overseas Group and its related companies over a one-year period, after which their personal data will be destroyed.", "employment_types": ["Contract"], "selling_points": ["Residential Project, Inspection, Site Management", "Liaise and coordinate with Main Contractor", "Bank holiday, Birthday leave, Dis. Bonus"], "locations": ["Admiralty"], "categories": ["Building & Construction", "Building / Construction / QS", "Engineering", "Engineering Project Management", "Property / Real Estate", "Others"], "post_time": "2022-01-16T21:50:24Z", "salary": {"currency": null, "max": null, "min": null, "period": "monthly", "term": null}, "salary_visible": false, "title_keywords": ["clerk", "senior clerk"], "responsibilities": ["cost", "site activities", "rectification", "quality", "monitor", "coordinate with", "liaise with", "report"], "requirements": {"degrees": ["diploma", "higher certificate"], "majors": ["building studies"], "languages": ["english", "chinese"], "language_level": ["good command"], "hard_skills": [], "soft_skills": ["communication skills", "hardworking", "positive"], "languages_combined": [{"language": "english", "language_level": ["good command"]}, {"language": "chinese", "language_level": ["good command"]}]}, "experience_required": {"duration": ["at least 8 years"], "field": ["installation", "development", "building services", "relevant experience", "developer", "construction industry"]}}, {"job_id": "100003009049594", "location_code": "hk", "company": "Fortune Link Engineering Co Ltd.", "job_title": "Engineer / Assistant Engineer(s) (MVAC or Electrical)", "description": "Higher Diploma or above in ME/EE/BSE\n(Senior Position available for MHKIE/RPE in EE/BSE)\nMin. 2 years experience in E&M/ Building Services Field\n(Lesser experience will be considered for Engineer Asst.)\nProficiency in Auto Cad 2015 or above\nSite experience is preferable\nAbility to written and spoken English\n(Remark : Our company will suitably recommend our Engineers to apply for REW registrations)\n\nPlease forward personal CV with Expected Salary and Date Available to Apply Now or Fax: 2342 2352 Miss Wong\n\n", "employment_types": ["Full Time", "Permanent"], "selling_points": [], "locations": ["Not Specified"], "categories": ["Engineering", "Electrical / Electronics", "Engineering Project Management", "Others"], "post_time": "2022-01-14T08:55:02Z", "salary": {"currency": null, "max": null, "min": null, "period": "monthly", "term": null}, "salary_visible": false, "title_keywords": ["engineer", "assistant"], "responsibilities": [], "requirements": {"degrees": ["higher diploma or above"], "majors": [], "languages": ["english"], "language_level": [], "hard_skills": ["auto cad 2015", "mhkie"], "soft_skills": [], "languages_combined": [{"language": "english", "language_level": []}]}, "experience_required": {"duration": ["2 years"], "field": ["building services"]}}, {"job_id": "100003009052073", "location_code": "hk", "company": "Meinhardt Consulting Engineers", "job_title": "Acoustic Consultant / Assistant Consultant  (Ref: 88090T5)", "description": "Degree holder in Mechanical Engineering/ Environmental related subject\nMore than 3 years\u2019 experience of acoustic design and noise & vibration control related projects. Less experience would be considered as assistant consultant.\nExperience of working in multi-discipline teams.\nAbility to multi-task and coordinate priorities and work on multiple projects simultaneously.\nBe motivated, confident, organized, efficient and effective worker and able to work independently.\nExcellent customer and proactive mindset; good and effective communication and presentation skills required.\nProficient computer skills and abilities in Microsoft Office, Adobe, AutoCAD, etc\nKnowledge in acoustic modelling software, e.g. Odeon, CATT, EASE, etc. would be an advantage\nGood written and spoken English and Chinese.\n\nPlease send full resume and employment references, state availability, expected salary package and contact telephone number (quoting reference) to:\n\nHuman Resources Manager\nMeinhardt Consulting Engineers\n10/F Genesis, 33 \u2013 35 Wong Chuk Hang Road, Hong Kong\n\nOR send e-mail by clicking \"Apply Now\" \u00a0\u00a0\u00a0\u00a0 http://www.meinhardtgroup.com\n\nCandidates who have not been contacted within 8 weeks of their date of application may assume their application has been unsuccessful. Data collected will be used for recruitment purpose only.", "employment_types": ["Full Time", "Permanent"], "selling_points": [], "locations": ["Not Specified"], "categories": ["Building & Construction", "Building / Construction / QS", "Engineering", "Engineering Project Management", "Others"], "post_time": "2022-01-17T02:02:12Z", "salary": {"currency": null, "max": null, "min": null, "period": "monthly", "term": null}, "salary_visible": false, "title_keywords": ["consultant", "assistant"], "responsibilities": ["control", "software", "consulting", "data", "teams", "design", "coordinate", "communication", "recruitment", "contact", "multiple projects"], "requirements": {"degrees": ["degree holder"], "majors": ["mechanical engineering"], "languages": ["english", "chinese"], "language_level": ["good"], "hard_skills": ["ease", "microsoft office", "adobe", "computer skills", "autocad"], "soft_skills": ["confident", "organized", "efficient", "work independently", "multi-task", "communication", "presentation skills", "motivated", "proactive"], "languages_combined": [{"language": "english", "language_level": ["good"]}, {"language": "chinese", "language_level": ["good"]}]}, "experience_required": {"duration": ["3 years"], "field": ["related", "acoustic", "design"]}}, {"job_id": "100003009046934", "location_code": "hk", "company": "Wing Tai Properties Estate Management Limited", "job_title": "Engineer", "description": "Responsibilities:\n\nOversee and lead a multi-disciplinary technical team to carry out preventive maintenance for all building services systems of Grade A commercial building;\nSupervise and monitor the performance of site facilities such as EL, ELV, MVAC, FS, PD and BMS;\nDeal with tenants\u2019 enquiries, requests and complaints in related to technical issues;\nMonitor the progress of all contracted-out projects and tenants\u2019 fit-out works;\nResponsible for tender preparation, coordination and execution of maintenance and improvement works for effective and efficient system operation; and\nAssist the ad hoc projects and perform any other duties as assigned by Facility Manager.\n\nRequirements:\n\nHigher Diploma or above in Building Services Engineering or related disciplines\nMinimum 5 years\u2019 solid experience in building services maintenance and preferably in Grade A office buildings or property management field\nHolder of Registered Electrical Worker (Grade B or above) is required\nHands-on experience in PC applications & familiar in using AutoCad\nSelf-initiative, mature and able to work independently\nGood team player with excellent leadership, communication and interpersonal skills\nGood command of both spoken and written English and Chinese\nImmediate available is highly preferred\n\nWe offer attractive remuneration package commensurate with experience and qualifications. Please send your full resume with current and expected salary, availability and contact telephone number to:\n\nHuman Resources & Administration Department\n\nWing Tai Properties Estate Management Limited\n\n8/F., AXA Tower, Landmark East, 100 How Ming Street, Kwun Tong, Kowloon\n\nOR by confidential fax to 2739 7876 OR Simply to click \u201cAPPLY NOW\u201d.\n\nFor more Company\u2019s information, please visit our website at www.wingtaiproperties.com\n\n(Information provided by applicants will be treated in strict confidence and used for recruitment purposes only.)", "employment_types": ["Full Time", "Permanent"], "selling_points": ["Certificate of Registration of Electrical Worker", "Building Services", "Minimum 5 years"], "locations": ["Kwun Tong"], "categories": ["Engineering", "Engineering Project Management", "Mechanical", "Property / Real Estate", "Property Management"], "post_time": "2022-01-14T01:47:55Z", "salary": {"currency": null, "max": null, "min": null, "period": "monthly", "term": null}, "salary_visible": false, "title_keywords": ["engineer"], "responsibilities": ["any other duties", "maintenance", "systems", "monitor", "ad hoc projects", "monitor the performance", "tender preparation", "coordination"], "requirements": {"degrees": ["higher diploma or above"], "majors": ["related disciplines", "building services", "engineering"], "languages": ["english", "chinese"], "language_level": ["good command"], "hard_skills": ["autocad", "maintenance", "pc applications"], "soft_skills": ["good team player", "work independently", "mature", "hands-on", "communication and interpersonal skills", "self-initiative", "leadership"], "languages_combined": [{"language": "english", "language_level": ["good command"]}, {"language": "chinese", "language_level": ["good command"]}]}, "experience_required": {"duration": ["minimum 5 years"], "field": ["management", "building services", "maintenance"]}}, {"job_id": "100003009049482", "location_code": "hk", "company": "Jones Lang LaSalle Ltd", "job_title": "Assistant Project Engineer", "description": "About JLL \u2013\u00a0\n\nWe\u2019re JLL. We\u2019re a professional services and investment management firm specializing in real estate. As a Fortune 500 company, we help real estate owners, occupiers and investors achieve their business ambitions.\u00a0\n\nIf you\u2019re looking to step up your career, JLL is the perfect professional home. With us, you\u2019ll have a chance to innovate with the world\u2019s leading businesses, put that expertise into action on landmark projects, and work on game-changing real estate initiatives. You\u2019ll also make long-lasting professional connections and be inspired by the best. We\u2019re focused on opportunity and want to help you make the most of yours. Achieve your ambitions - join us at JLL!\u00a0\n\nAbout the role:\u00a0\n\nWhat this job involves:\u00a0\n\nAssist the renovation, refurbishment & enhancement projects for sizeable composite development to ensure timely completion and within budgets\nAssist Senior Project Manager with the preparations of strategic plans, budgets and client reports\nSupport projects from project conception to project handover (including DLP)\nPreparate project specification, tender documentations, evaluation of tenders and preparation of contracts\nReview design submissions; and liaise with statutory bodies on approval of statutory submissions\nCo-ordinate with consultants\u00a0and contractors\u00a0to ensure projects are delivered accordingly project specifications, at high quality standard and compliance with statutory regulations / standards (e.g. fire, health and safety standards)\nSupervise the repair and maintenance works and assist in coordination of churn activities\nEnsure the implementation and management of Risk & Safety work practices during project implementation\nEnsure all safety procedures, including Crisis Management / Business Continuity and Emergency Procedures are maintained at all times\nCo-ordinate with Owners & the Business Units on Project issues\nPrepare & update Monthly\u00a0Management Report\n\nSound like you? To apply you will have:\n\nDegree or above in Building Surveying / Building Management / Building Services or related disciplines with minimum of 2 years\u2019 experience, preferably in project and construction management of retail shops, F&B\u00a0and offices space\nMembership of RICS, CIOB, HKICM, HKIE or equivalent is preferred\nKnowledge of HVAC, Fire Services System, Plumbing and Drainage system, ELV system, Electrical and Lighting system, AV system, Building and A&A works is preferred\nConversant with Construction Site Safety requirements, Hong Kong construction and building related legislations and submission process\nStrong interpersonal skills, mature, independent and strategic thinking with leadership skills\nFamiliar with MS applications and AutoCAD\nCandidates with more experience will be considered as Project Engineer\n\nWhat we can do for you:\u00a0\n\nAt JLL, we make sure that you become the best version of yourself by helping you realise your full potential in an entrepreneurial and inclusive work environment. We will empower your ambitions through our dedicated Total Rewards Program, competitive pay and benefits package.\u00a0\n\nApply today!\u00a0", "employment_types": ["Full Time", "Permanent"], "selling_points": ["Project Management / Construction Management", "Building Services / Building Surveying", "Good Career Development Opportunities"], "locations": ["Pok Fu Lam"], "categories": ["Building & Construction", "Building / Construction / QS", "Engineering", "Electrical / Electronics", "Engineering Project Management"], "post_time": "2022-01-14T08:44:15Z", "salary": {"currency": null, "max": null, "min": null, "period": "monthly", "term": null}, "salary_visible": false, "title_keywords": ["assistant project engineer"], "responsibilities": ["business continuity", "co-ordinate with", "quality", "compliance with statutory regulations", "building management", "review design submissions", "liaise with", "project conception", "support projects", "emergency procedures", "implementation", "churn activities", "project handover", "risk & safety work practices", "legislations", "crisis management", "client reports", "management", "construction management", "procedures", "tender documentations", "specifications", "approval of statutory submissions", "refurbishment & enhancement projects", "repair and maintenance works", "budgets", "strategic plans", "monthly management report", "assist the renovation", "preparation of contracts", "safety standards", "coordination", "preparate project specification", "evaluation of tenders"], "requirements": {"degrees": ["degree or above"], "majors": ["construction management", "related disciplines", "building management", "building services", "building surveying"], "languages": [], "language_level": [], "hard_skills": ["hong kong construction and building related legislations", "documentations", "hkie", "fire services system", "ms applications", "building and a&a works", "make", "plumbing and drainage system", "submission process", "knowledge of hvac", "electrical and lighting system", "ciob", "elv system", "hkicm", "maintenance", "rics", "av system", "construction site safety requirements", "autocad"], "soft_skills": ["independent", "focused", "strategic thinking", "timely", "leadership skills", "mature", "interpersonal skills", "coordination"], "languages_combined": []}, "experience_required": {"duration": ["minimum of 2 years"], "field": ["management", "related", "f&b", "building services", "building surveying", "retail", "construction"]}}, {"job_id": "100003009050983", "location_code": "hk", "company": "Hong Kong Science & Technology Parks Corporation", "job_title": "Senior Officer (Project Management/Interior Design) [JDB/SOPM_ID/220114]", "description": "Responsibilities:\n\nAssist Associate Director in the formulation of marketing, branding and visitor experience enhancement strategies through a series of architectural and interior design and implementation processes with integration of smart technologies and arts;\nCoordinate with a wide spectrum of stakeholders such as HKSTP departments (Marketing Team, Clusters, Facility Management Team, Project Team etc,), external strategic partners, consultants, contractors, etc. on the implementation and delivery of the approved strategies on upgrading works at the Spine, MICE venues, F&B, Tenants\u2019 Showcase plus strengthening of various spatial connections and landscape attractions and other related matters;\nPrepare presentation materials and progress reports for internal and external stakeholders;\nHandle various requests and matters initiated by F&B/MICE operators and users;\nLiaise with F&B tenants and review their design submissions for incorporation into the tenancy agreement as well as monitor tenant\u2019s implementation works to safeguard HKSTP brand standard; and\nPerform any other duties as assigned by supervisor.\n\nRequirements:\n\nA recognized degree or above in Architecture, Interior Design, or relevant disciplines with at least three years of relevant experience OR an Associate Degree/ a Higher Diploma with substantial years of relevant experience will also be considered;\nSolid experience in design and project management in development and/or A&A projects in similar scale and nature is preferred;\nExposure in global F&B scenes and their interiors lifestyle trending;\nGood understanding of local regulations on both building and licensing authorities;\nExcellent skills in using 2D and 3D computer softwares for preparing graphical presentation materials; \u00a0\nPassionate in art and culture, a team player with strong interpersonal and communication skills, self-motivated, confident, creative and strong desire to achieve better performance; and\nProficient in both written and spoken English and Chinese.\n\nWe offer market competitive compensation, 5-day work week, and generous benefits including medical and life insurance; and voluntary contribution in addition to the legal minimum MPF.\u00a0 To apply, please send your full resume with current and expected salary to the Human Resources & Office Administration Department, Hong Kong Science and Technology Parks Corporation, 5/F, Building 5E, 5 Science Park East Avenue, Hong Kong Science Park, Hong Kong or, by email via \"Apply Now\"\u00a0on or before 27 January 2022.\u00a0 \u00a0Please quote the reference number on the email subject/envelope and the application letter.\u00a0\n\nPersonal data provided will be treated in strict confidence and used for recruitment purpose only.\u00a0 All personal data collected will be used strictly in accordance with employer\u2019s personal data policies, you can access to HKSTP\u2019s Personal Information Collection Statement at https://www.hkstp.org/hkstp_web/en/hkstp/personal-information-collection-statement-recruitment\n\nApplicants not invited for interview within four weeks after application deadline may consider their applications unsuccessful.\u00a0 Personal data of unsuccessful applicants will be retained for a maximum of two years.\u00a0\n\nwww.hkstp.org", "employment_types": ["Full Time"], "selling_points": [], "locations": ["Shatin Area"], "categories": ["Design", "Interior", "Engineering", "Engineering Project Management", "Others"], "post_time": "2022-01-14T12:34:10Z", "salary": {"currency": null, "max": null, "min": null, "period": "monthly", "term": null}, "salary_visible": false, "title_keywords": ["senior officer"], "responsibilities": ["management team", "any other duties", "progress reports", "review", "coordinate with", "implementation", "design", "monitor", "liaise with"], "requirements": {"degrees": ["associate degree", "diploma", "degree or above"], "majors": ["architecture", "design"], "languages": ["english", "chinese"], "language_level": ["proficient"], "hard_skills": ["project management"], "soft_skills": ["passionate", "communication skills", "self-motivated", "confident", "presentation", "project management", "team player", "creative", "interpersonal"], "languages_combined": [{"language": "english", "language_level": ["proficient"]}, {"language": "chinese", "language_level": ["proficient"]}]}, "experience_required": {"duration": ["at least three years"], "field": ["project management", "development", "relevant experience", "design"]}}, {"job_id": "100003009047666", "location_code": "hk", "company": "Goodwell Property Management Ltd", "job_title": "Technical Assistant", "description": "Responsibilities\nResponsible for project design and submissions preparation for conveyor project\nManage planning for installation works and monitor sub-contractor\nSupport tender biding and follow up with the project installation progress\nAssist in design enhancement work to cover modification in electrical and system control aspects\nMaintain good relationships with client and business partner\nMonitor all site safety, quality and environmental matters\nRequirements\nDegree in Electrical Engineering or related disciplines\n5-6 years' working experience in electrical installation project\nRegistered Electrical Worker Grade B required and Baggage Handling System experience is an advantage\nAble to work with a team or independently under pressure\nGood command of English and proficient in computer skills\nPlease click \"Apply Now\" to submit your application.\n\n\nPersonal data collected will be used for recruitment purpose only.", "employment_types": ["Full Time", "Permanent"], "selling_points": ["Certificate in Engineering or related disciplines", "At least 1 year's relevant experience", "Monitor daily repair and maintenance works"], "locations": ["Tai Po Area"], "categories": ["Building & Construction", "Building / Construction / QS", "Engineering", "Engineering Project Management", "Property / Real Estate", "Property Management"], "post_time": "2022-01-15T03:49:49Z", "salary": {"currency": null, "max": null, "min": null, "period": null, "term": null}, "salary_visible": false, "title_keywords": ["technical assistant"], "responsibilities": ["installation", "control", "monitor", "quality", "design", "maintain", "tender", "planning"], "requirements": {"degrees": ["degree"], "majors": ["related disciplines", "electrical engineering"], "languages": ["english"], "language_level": ["good command", "proficient"], "hard_skills": ["computer skills"], "soft_skills": ["independently", "under pressure"], "languages_combined": [{"language": "english", "language_level": ["proficient", "good command"]}]}, "experience_required": {"duration": ["5-6 years"], "field": ["installation"]}}, {"job_id": "100003009052747", "location_code": "hk", "company": "Moses Wills Limited", "job_title": "Senior Environmental Consultant", "description": "Job Description\n\nCoordinate and monitor the progress of the project to fulfill the contractual schedule and quality standards;\nPrepare the site progress report for inspection of works;\nConduct regular meetings to identify and resolve problems in respect of technical, safety and environmental issues etc.;\u00a0\nLiaise with clients, consultants and sub-contractors for technical issues; and\nTake part in day-to-day site activities including drawing design, programming and structural calculation.\n\nJob Requirement\n\n\nHD or above in\u00a0Building / Civil\u00a0Engineering or equivalent;\n1 year or above of construction experience in consultant or contractor;\nConversant in\u00a0BIM\u00a0application is an advantage;\nGood command of written and spoken English and Chinese;\nTeam player and willing to learn;\nIANG is also welcome; and\nCandidates with more experience will be considered as Project Engineer.\n\n***What we offer?\n\nCompetitive remuneration package\nOT Allowance\nAdditional leave (Family Care Leave, Exam Leave, Qualification Leave, etc.)\nDiscretionary bonus\nStudy Subsidies\nComprehensive training and professional career development\n\nInterested parties please apply by clicking \"APPLY NOW\"\u00a0with detailed CV stating\u00a0expected salary\u00a0and\u00a0date of availability.\n\nCompany Website:\u00a0http://www.pyengineering.com/\n\nAll personal data provided will be used strictly in accordance with our \u201cPersonal Information Collection Statement Pertaining to Recruitment\u201d, a copy of which is available upon written request to us by E-mail.", "employment_types": ["Full Time", "Permanent"], "selling_points": ["MNC engineering consulting firms", "min. 3 years exp in EIA and EM&A project", "CALINE4, EMFAC, AERMOD and PATH"], "locations": ["Not Specified"], "categories": ["Building & Construction", "Building / Construction / QS", "Engineering", "Engineering Project Management", "Sciences, Lab, R&D", "Environmental Science / Waste Management"], "post_time": "2022-01-17T03:54:43Z", "salary": {"currency": null, "max": null, "min": null, "period": "monthly", "term": null}, "salary_visible": false, "title_keywords": ["senior environmental consultant"], "responsibilities": ["liaise with clients", "site activities", "quality", "monitor", "environmental issues", "design", "coordinate", "inspection of works", "schedule", "report"], "requirements": {"degrees": [], "majors": [], "languages": ["english", "chinese"], "language_level": ["good command"], "hard_skills": ["bim"], "soft_skills": ["team player", "willing to learn"], "languages_combined": [{"language": "english", "language_level": ["good command"]}, {"language": "chinese", "language_level": ["good command"]}]}, "experience_required": {"duration": ["1 year"], "field": ["construction"]}}, {"job_id": "100003009047076", "location_code": "hk", "company": "Arup", "job_title": "Engineer / Project Engineer (Civil Engineering)", "description": "Responsibilities:\n\nTo monitor and control site progress\nTo ensure all construction activities comply with contractual and statutory requirement\nTo monitor overall financial, commercial, contractual and technical matters for\u00a0current projects.\nTo control and supervise overall site activities and liaise with client's representatives and subcontractors\nTo gather and analyse data relating to work progress, adequacy and effectiveness\n\nRequirements:\n\nDiploma or above\u00a0in interior design / building studies / architecture or equivalent\nAt least 10 years solid experience in\u00a0FITTING-OUT projects of residential, offices, hotel etc\nAt least 3 years experience in managerial level\nStrong technical background and site experience\nGood communication and sound relationship with cooperation parties including clients and subcontractors\nConversant with interior fit-out nature, A&A work and contractual documents\nStrong in leadership/management and can work under pressure\nGood computer literacy, especially in MS Word, MS Excel and MS Project\nGood command in written and spoken in English & Chinese\nLess experience will be considered as Assistant Project Manager\n\nWe offer competitive remuneration package (14 days Annual Leave, Double Pay, Discretionary Bonus, Group Medical Insurance, Bank Holidays, Education Assistance) to the right candidate.\u00a0Interested parties please send full resume with current and expected salary, and availability\u00a0to our HR manager.\u00a0 \u00a0(Please quote reference number.)\n\n*Personal data collected will be used strictly for recruitment purposes only.", "employment_types": ["Full Time", "Permanent"], "selling_points": [], "locations": ["Kowloon City Area"], "categories": ["Building & Construction", "Civil / Structural", "Engineering", "Engineering Project Management", "Others"], "post_time": "2022-01-14T02:15:44Z", "salary": {"currency": null, "max": null, "min": null, "period": null, "term": null}, "salary_visible": false, "title_keywords": ["engineer", "project engineer"], "responsibilities": ["control", "site activities", "data", "monitor", "liaise with client", "analyse"], "requirements": {"degrees": ["diploma or above"], "majors": ["building studies", "architecture", "design"], "languages": ["english", "chinese"], "language_level": ["good command"], "hard_skills": ["ms excel", "ms word"], "soft_skills": ["communication", "computer literacy", "leadership", "work under pressure"], "languages_combined": [{"language": "english", "language_level": ["good command"]}, {"language": "chinese", "language_level": ["good command"]}]}, "experience_required": {"duration": ["at least 10 years", "at least 3 years"], "field": ["managerial"]}}, {"job_id": "100003009046856", "location_code": "hk", "company": "Cloud Light Technology Limited", "job_title": "Senior Mechanical Design Engineer (Job Ref. Apply-HK-2104-SMDE)", "description": "\u00a0Job Description:\n\nIP network configuration, including switches and routers of Cisco, Huawei, Juniper\nManage network resources, including POPs, connectivity capacity and network devices\nParticipate in network projects for smooth implementation\nCoordinate with external vendors for delivery of required services\nSupport Management on ad hoc report compilation\u00a0\n\n\u00a0Job\u00a0Requirement:\n\nBachelor Degree or above\u00a0in Information Technology, Computer Science or other related disciplines\nMinimum\u00a03 years of experience; with telecom experiences are preferred\nKnowledge of IP network, IP routing knowledge or MPLS, VPN\nOrganized, proactive and\u00a0a good team-player\nMature, independent and problem-solver\u00a0\nExcellent written and spoken English, Chinese and Mandarin\n\nInterested parties please send your full resume with current & expected salary\u00a0by e-mail to\u00a0hr @ cmi.chinamobile.com.\u00a0 Please indicate the reference in the subject line.\n\nAll personal data provided will be used for consideration of your job application only.", "employment_types": ["Full Time", "Permanent"], "selling_points": ["Master or higher in Mechanical Engineering", "experience in fiber-optic transceiver product desi", "experience in thermal and structural simulation"], "locations": ["Shatin Area"], "categories": ["Engineering", "Electrical / Electronics", "Engineering Project Management", "Mechanical"], "post_time": "2022-01-14T01:29:29Z", "salary": {"currency": null, "max": null, "min": null, "period": "monthly", "term": null}, "salary_visible": false, "title_keywords": ["senior mechanical design engineer"], "responsibilities": ["management", "configuration", "ad hoc report", "coordinate with", "implementation"], "requirements": {"degrees": ["degree or above", "bachelor"], "majors": ["related disciplines", "computer science", "information technology"], "languages": ["english", "chinese", "mandarin"], "language_level": ["excellent"], "hard_skills": ["ip", "vpn"], "soft_skills": ["organized", "independent", "team-player", "mature", "proactive"], "languages_combined": [{"language": "english", "language_level": ["excellent"]}, {"language": "chinese", "language_level": ["excellent"]}, {"language": "mandarin", "language_level": ["excellent"]}]}, "experience_required": {"duration": ["minimum 3 years"], "field": []}}, {"job_id": "100003009048516", "location_code": "hk", "company": "Times Square Ltd", "job_title": "TECHNICAL MANAGER (ENGINEERING)", "description": "Senior Appointment - Environmental Engineering \u00a0\u00a0\u00a0\n\nWe are commissioned exclusively by our client, a reputable Building Services contractor with projects in E&M package, HVAC, Electrical, FS, P&D and Environmental, to search for a competent veteran engineer to lead its Environmental Engineering operation.\n\nHead of Operation - Environmental Engineering \u00a0\n\nRequirements:\n\nMSc/BSc in Building Services/E&M Engineering or related disciplines\nMHKIE or equivalent professional qualifications\nMinimum 20 years\u2019 proven experience in site supervision and project management of E&M or Building Services Engineering projects, including WSD/DSD projects in water treatment, solid waste treatment or sewage treatment, with E&M contractors or main contractors\nGood communication skills in English and Chinese\nCommitment with drive, ownership and innovation \u00a0\n\n\u00a0ATTRACTIVE PACKAGE will be offered to the right talent.\n\nPlease e-mail your full resume (Word format) to APPLY NOW of Manlink Personnel Consultants. Personal data collected will be used for recruitment purpose only\n\n\n\u201cYour Career Partner, Your Talent Solution\u201d", "employment_types": ["Full Time", "Permanent"], "selling_points": ["Monitor operation of Building Service installation", "Monitor maintenance standards & improvement works", "Minimum 8 years\u2019 relevant experience"], "locations": ["Causeway Bay"], "categories": ["Building & Construction", "Building / Construction / QS", "Engineering", "Engineering Project Management", "Mechanical"], "post_time": "2022-01-15T03:50:01Z", "salary": {"currency": null, "max": null, "min": null, "period": null, "term": null}, "salary_visible": false, "title_keywords": ["technical manager"], "responsibilities": ["site supervision", "communication", "project management", "recruitment", "personal data"], "requirements": {"degrees": ["bsc"], "majors": ["related disciplines", "building services", "engineering"], "languages": ["english", "chinese"], "language_level": ["good"], "hard_skills": ["professional qualifications", "hvac", "word", "project management", "mhkie"], "soft_skills": ["communication skills", "project management", "competent"], "languages_combined": [{"language": "english", "language_level": ["good"]}, {"language": "chinese", "language_level": ["good"]}]}, "experience_required": {"duration": ["minimum 20 years"], "field": ["project management", "building services", "engineering"]}}, {"job_id": "100003009047224", "location_code": "hk", "company": "Wharf China Estates Limited", "job_title": "TECHNICAL MANAGER (Station in China)", "description": "Job Responsibilities:\n\nResponsible for building services design, tender preparation and project administration\nSite inspection and attend meetings for building development, and/or mission critical projects\nLiaise with clients, clients' consultants, contractors and authorities from concept to detailed design and construction administration\n\nRequirements:\n\nBachelor Degree or Higher Diploma\u00a0in Building Services Engineering,\u00a0Mechanical Engineering or Electrical\u00a0Engineering\nMinimum of 2 years relevant work experience in design and project management\nPrior experience in engineering consulting work or project management will be advantageous\nStrong sense of responsibility and organization\nStrong communication, presentation and project management skills\nCandidate with more experience and higher qualification will be considered for senior positions\n\nWhat we offer:\n\nCare and support for new parenthood\nLife, Medical and Dental Insurance\nWSP Professional Network\nOverseas Exchange Program\nMarriage Leave\n\nFor interested parties, please click below \"Apply now\" button to apply with your\u00a0resume\u00a0and\u00a0expected\u00a0salary.\u00a0 \u00a0\n\nAll applications will be treated in strict confidence and only be used for recruitment related purpose. Applicants not hearing from us within six weeks may consider their application filed for future reference. All personal data of unsuccessful applicants will be retained for 12 months for future recruitment purpose and will be destroyed afterward.", "employment_types": ["Full Time", "Permanent"], "selling_points": ["Degree holder in Building Services Engineering", "Experience gained in PRC commercial complex", "Will act as Deputy Head of technical team"], "locations": ["Tsim Sha Tsui"], "categories": ["Building & Construction", "Building / Construction / QS", "Engineering", "Engineering Project Management", "Property / Real Estate", "Property Management"], "post_time": "2022-01-15T03:49:38Z", "salary": {"currency": null, "max": null, "min": null, "period": "monthly", "term": null}, "salary_visible": false, "title_keywords": ["technical manager"], "responsibilities": ["liaise with clients", "design", "site inspection", "project administration", "tender preparation", "attend meetings", "building services design", "administration"], "requirements": {"degrees": ["diploma", "degree", "bachelor"], "majors": ["electrical engineering", "building services", "engineering", "mechanical engineering"], "languages": [], "language_level": [], "hard_skills": ["project management"], "soft_skills": ["sense of responsibility", "project management skills", "communication", "project management", "presentation"], "languages_combined": []}, "experience_required": {"duration": ["minimum of 2 years"], "field": ["project management", "engineering", "design", "consulting"]}}, {"job_id": "100003009047659", "location_code": "hk", "company": "Goodwell Property Management Ltd", "job_title": "Engineer (Commercial Building)", "description": "Degree holder in Civil Engineering or equivalent with relevant professional qualification such as MHKIE / MICE\nMinimum 5 years\u2019 working experience in drainage / sewerage / waterworks projects for public and private projects\nSelf-motivated, logical and systematic thinkers\nGood communication skills and proficient in written and spoken English and Chinese\nPlease send your full resume with expected salary and availability(quoting reference number) to:\n\n\nHuman Resources Manager\nMeinhardt Consulting Engineers\n10/F Genesis, 33-35 Wong Chuk Hang Road, Hong Kong\n\nOR send e-mail by clicking \"Apply Now\" \u00a0\u00a0\u00a0 http://www.meinhardtgroup.com\n\nCandidates who have not been contacted within 8 weeks of their date of application may assume their application has been unsuccessful. Data collected will be used for recruitment purpose only and will be destroyed after six months from date of application.", "employment_types": ["Full Time", "Permanent"], "selling_points": ["Supervise daily operations of E&M services", "High Dip. in Electrical/Mechanical Engineer", "5 years' exp. in office / commercial building"], "locations": ["Not Specified"], "categories": ["Building & Construction", "Building / Construction / QS", "Engineering", "Engineering Project Management", "Property / Real Estate", "Property Management"], "post_time": "2022-01-15T03:49:48Z", "salary": {"currency": null, "max": null, "min": null, "period": null, "term": null}, "salary_visible": false, "title_keywords": ["engineer"], "responsibilities": ["communication", "recruitment", "consulting", "data"], "requirements": {"degrees": ["degree holder"], "majors": ["civil engineering"], "languages": ["english", "chinese"], "language_level": ["proficient", "good"], "hard_skills": ["mhkie"], "soft_skills": ["communication skills", "self-motivated", "systematic"], "languages_combined": [{"language": "english", "language_level": ["proficient", "good"]}, {"language": "chinese", "language_level": ["proficient", "good"]}]}, "experience_required": {"duration": ["minimum 5 years"], "field": ["drainage"]}}, {"job_id": "100003009048301", "location_code": "hk", "company": "Polyfair Construction & Engineering Limited", "job_title": "Project Manager / Assistant Project Manager (Fa\u00e7ade / Curtain Wall)", "description": "Certificate in Engineering or related disciplines\nAt least 1 year's relevant experience\nMonitor daily repair and maintenance works\nPerform daily clerical duties and other ad hoc projects as assigned\nHands on experience in Microsoft applications, Excel and Chinese Word Processing\nSelf-motivated with good communication skills\n\nWe will offer attractive compensation package to the right candidate. Please send application enclosing resume stating career and salary history, expected salary and date of availability to The Human Resources Manager, Goodwell Property Management Limited, 2/F New Treasure Centre, 10 Ng Fong Street, San Po Kong, Kowloon\u00a0or\u00a0by clicking \u201cApply Now\u201d (in Word format). Please quote the reference of the position you apply for in all correspondences.\n\nWe are an equal opportunity employer and welcome applications from all qualified candidates.\u00a0 Personal data collected will be treated in strictest confidence and handled confidentially by authorized personnel for recruitment-related purposes within the\u00a0Group. Applicants not hearing from us within six weeks from the date of\u00a0application may consider their applications unsuccessful.\n\n(Our website : http://www.goodwell.com.hk/)", "employment_types": ["Full Time"], "selling_points": ["Career Level: Senior", "Years of Experience: 5-8", "Double Pay, Medical Insurance, Bank Holiday"], "locations": ["North Point"], "categories": ["Building & Construction", "Building / Construction / QS", "Civil / Structural", "Engineering", "Engineering Project Management"], "post_time": "2022-01-14T06:10:45Z", "salary": {"currency": null, "max": null, "min": null, "period": "monthly", "term": null}, "salary_visible": false, "title_keywords": ["project manager", "assistant project manager"], "responsibilities": ["management", "monitor", "website", "communication", "ad hoc projects", "recruitment", "personal data", "repair and maintenance works"], "requirements": {"degrees": ["certificate"], "majors": ["related disciplines", "engineering"], "languages": ["chinese"], "language_level": [], "hard_skills": ["excel", "chinese word processing", "microsoft applications", "maintenance", "word"], "soft_skills": ["communication skills", "self-motivated", "hands on", "confidence"], "languages_combined": [{"language": "chinese", "language_level": []}]}, "experience_required": {"duration": ["at least 1 year"], "field": ["relevant experience"]}}, {"job_id": "100003009048534", "location_code": "hk", "company": "Kum Shing Group", "job_title": "Site Agent / Senior Project Engineer \u2013 Civil (Government Project)", "description": "Our client is an international multi-disciplinary engineering design and project management consulting firm, the company is looking for Senior Environmental Consultant to join the team.\n\nJob Description\n\nResponsibilities:\n\nCoordinate and implement environmental-related consultancy projects related to environmental monitoring and audit (EM&A) and environmental assessment.\nProvide technical support on various aspects of environmental studies, such as air quality, noise, etc.\nBe responsible for project delivery including co-ordination, stakeholder management\nAssist in preparing consultancy reports and other relevant submissions.\n\nRequirement:\n\nDegree holder in Environmental related subject with at least 3 years\u2019 experience of EIA, EM&A and environmental management projects.\nExperience in air quality impact assessment with the use of CALINE4, EMFAC, AERMOD and PATH and experience of computer programming would be an advantage.\nExperience of working in multi-discipline teams.\nIndependent, proactive, result-oriented and able to handle multi-task with strong business acumen\nStrong analytical, interpersonal and communication skills with excellent attention to details.\nProficient computer skills and abilities in Microsoft Office, Adobe, etc.\nExcellent command of written and spoken English and Chinese.\n\nInterested parties may submit update CV with current and expected salary or contact Ms Cheung (+852 3952 0594) for confidential discussion.", "employment_types": ["Full Time", "Permanent"], "selling_points": ["Performance bonus, education subsidy, medical plan", "Excellent career path", "Supervise the project team members"], "locations": ["To Kwa Wan"], "categories": ["Building & Construction", "Building / Construction / QS", "Civil / Structural", "Engineering", "Engineering Project Management"], "post_time": "2022-01-14T06:45:23Z", "salary": {"currency": null, "max": null, "min": null, "period": "monthly", "term": null}, "salary_visible": false, "title_keywords": ["site agent", "senior project engineer"], "responsibilities": ["management", "technical support", "monitoring", "quality", "audit", "coordinate", "reports"], "requirements": {"degrees": ["degree holder"], "majors": [], "languages": ["english", "chinese"], "language_level": ["excellent"], "hard_skills": ["microsoft office", "adobe", "computer skills", "programming", "acumen"], "soft_skills": ["communication skills", "independent", "multi-task", "interpersonal", "attention to details", "business acumen", "proactive", "result-oriented"], "languages_combined": [{"language": "english", "language_level": ["excellent"]}, {"language": "chinese", "language_level": ["excellent"]}]}, "experience_required": {"duration": ["at least 3 years"], "field": ["related", "management", "environmental", "programming"]}}, {"job_id": "100003008885906", "location_code": "hk", "company": "Wing Ming Engineering Co. Limited", "job_title": "Project Engineer / Assistant Project Engineer", "description": "Reporting to the Strategy and New Project Lead, the appointee will be required to:\n\ntake a vital role of managing the project of setting up a new satellite sustainability-focused laboratory in Hong Kong (https://www.theopenlab.one/);\noversee all the activities involved and progress of work, ensuring an on-schedule and smooth commencement of the new lab;\nmanage the development of the lab including the involvement in the design stage, tender/award, construction, safety standards;\nbuild and lead project teams comprising of external consultants, contractors and suppliers as well as internal cross-divisional groups;\nmanage and control the budget;\nundergo other project administrative tasks, such as procurement, fund application, regular progress reporting;\nwork closely with Research, Business Development and Marketing team to coordinate project and new initiatives related the lab; and\nperform any other duties as assigned.\n\nRequirements:\n\nA bachelor\u2019s degree or above in a Construction Management / Architecture / Engineering or related disciplines;\n5 or more years of relevant work experience. Experience in industrial, lab management or lab operation would be an advantage but not a must;\nWith solid project management and people management skills, PMP/CAPM certification is a plus;\nConversant with government procedures and regulations is a plus;\nStrong sense of project ownership and proactive working attitude;\nExcellent planning and organizing skills;\nExcellent communication and interpersonal skills;\nHighly-organized and capable of working under pressure with multi-task assignments; and\nFluent in written and spoken English, with good command of Putonghua being an advantage.\nApplicants should state their current and expected salary in the application. Salary offered will be commensurate with qualifications and experience. Appointment will be offered on a contract basis, re-engagement thereafter is subject to mutual agreement.\n\n\nApplicants are invited to send detailed curriculum vitae in strict confidence to Human Resources Manager, HKRITA, R906-8, Shirley Chan Building, The Hong Kong Polytechnic University, Hung Hom, Kowloon. Recruitment will continue until the position is filled. HKRITA reserves the right to consider late applications and nominations, and to fill or not to fill the positions. Personal data provided by applicants will be used for recruitment and other employment-related purpose.\n\nPlease mark \u201cPRIVATE & CONFIDENTIAL\u201d and quote the position applied for and its reference number on the envelope.", "employment_types": ["Full Time", "Permanent"], "selling_points": ["Site Co-ordination", "Prepare project document", "Year end double pay"], "locations": ["Not Specified"], "categories": ["Engineering", "Electrical / Electronics", "Engineering Project Management", "Mechanical"], "post_time": "2022-01-14T01:41:58Z", "salary": {"currency": null, "max": null, "min": null, "period": "monthly", "term": null}, "salary_visible": false, "title_keywords": ["assistant project engineer", "project engineer"], "responsibilities": ["regulations", "any other duties", "budget", "design", "communication", "personal data", "control", "teams", "schedule", "tender", "architecture", "reporting", "management", "construction management", "procedures", "administrative tasks", "coordinate", "project management", "recruitment", "safety standards", "planning"], "requirements": {"degrees": ["degree or above", "bachelor"], "majors": ["related disciplines", "construction management", "architecture", "engineering"], "languages": ["putonghua", "english"], "language_level": ["advantage", "good command", "fluent"], "hard_skills": ["project management", "pmp", "plus"], "soft_skills": ["organized", "confidence", "under pressure", "capable", "focused", "multi-task", "project management", "communication and interpersonal skills", "smooth", "proactive", "detailed"], "languages_combined": [{"language": "putonghua", "language_level": ["good command"]}, {"language": "english", "language_level": ["fluent", "advantage", "good command"]}]}, "experience_required": {"duration": [], "field": ["management", "operation"]}}, {"job_id": "100003009050206", "location_code": "hk", "company": "Shun Hing Systems Integration Company Limited", "job_title": "Engineer / Assistant Engineer (ATC)", "description": "The successful candidate will be responsible for monitoring the daily operations and performance of Building Services installations including electrical system, extra low voltage system, lift & escalatory system, large video screen, CCTV system, gondola system, etc. in Times Square.\u00a0 The candidate will periodically review the maintenance standards, formulate preventive maintenance with schedule and budget plan, monitor work progress of improvement works, control expenses of systems upgrading projects as well as A&A works and building reliability.\u00a0 The candidate should conduct vetting of engineering proposal, compile comments on the Building Services system modification, prepare contingency plan, monitor contractors\u2019 quality of work and progress, liaise and coordinate with working partners, tenants, designers, contractors, consultants and relevant Government departments.\u00a0 The candidate should supervise and monitor in-house frontline staff members, operators and contractors to ensure Company policies, standards as well as safety requirement are achieved.\u00a0 The candidate should also be responsible for energy management of the property and implement energy conservation initiatives to achieve Company\u2019s sustainability directives.\nApplicants should be holder of Grade B registered electrical worker license and preferably be a Chartered Engineer and / or Corporate Member of HKIE / CIBSE / ASHRAE / IMechE / BSOMES, etc. and a degree holder in Building Services Engineering, Mechanical Engineering, or related discipline with minimum 8 years\u2019 relevant experience, 5 years of which at managerial level with exposure in managing large commercial complex and improvement projects with proven leadership skills.\u00a0 The ideal candidate should possess strong problem solving and project management skills, be resourceful with good negotiation and communication skills in both English and Chinese.\nWe offer competitive salary package that will be commensurate with experience and qualifications.\u00a0 Interested parties are invited to send full resume stating contact telephone number, date available, present and expected salary to our recruitment email address.\n(Personal data provided will be used strictly in accordance with the Company\u2019s personal data policy which is available upon request.)", "employment_types": ["Full Time", "Permanent"], "selling_points": [], "locations": ["Kwai Tsing Area"], "categories": ["Engineering", "Electrical / Electronics", "Engineering Project Management"], "post_time": "2022-01-14T09:56:33Z", "salary": {"currency": null, "max": null, "min": null, "period": "monthly", "term": null}, "salary_visible": false, "title_keywords": ["assistant engineer", "engineer"], "responsibilities": ["liaise", "budget", "quality", "communication", "plan", "control", "expenses", "monitor", "system modification", "schedule", "management", "review", "coordinate with", "monitoring", "daily operations", "maintenance", "policies", "systems", "comments", "project management"], "requirements": {"degrees": ["degree holder"], "majors": ["building services", "engineering", "mechanical engineering"], "languages": ["english", "chinese"], "language_level": ["good"], "hard_skills": ["hkie", "maintenance", "cctv", "problem solving", "project management"], "soft_skills": ["communication skills", "negotiation", "responsible", "resourceful", "project management skills", "leadership skills", "problem solving", "ideal"], "languages_combined": [{"language": "english", "language_level": ["good"]}, {"language": "chinese", "language_level": ["good"]}]}, "experience_required": {"duration": ["5 years", "minimum 8 years"], "field": ["managerial", "engineering", "related", "commercial", "building services", "relevant experience"]}}]