[{"job_id": "100003009052209", "location_code": "hk", "company": "Johnson Electric Industrial Manufactory Limited", "job_title": "Process Engineer (Base in Shenzhen / Jiangmen)", "description": "Job Responsibilities\n\nAssist the Maintenance Officer to oversee the on-site facilities management of a shopping mall.\nResponsible for supervision of technicians and contractors on on-site daily operation, facilities maintenance and repair works and building services systems.\nCentralize order requests and ensure fairness and appropriateness of job allocation for technicians.\nPrepare regular reports on daily repair and maintenance schedule, emergency call out activities and inventory level of equipment to the Maintenance Officer for a comprehensive control of on-site work and further analysis.\nHandle tenants\u2019 enquires, complains and requests in a professional manner.\nAttend 24-hour emergency calls on all facilities related issues.\nPrepare roster and carry out technician shift duty.\nParticipate in ad hoc projects and tasks as assigned by the superior.\nJob Requirements\n\nCertificate or above, in M&E, Building Services or related disciplines.\nMinimum 8 years\u2019 relevant experience with 3 years at supervisory level with sound knowledge of repair and maintenance of M&E services.\nHolder of Registered Electrical Worker Certificate Grade B or above and Safety Green Card.\nProficient in MS Office applications and Chinese Word Processing.\nGood interpersonal skills with strong sense of responsibility.\nImmediate available is preferred.\nCandidate with less experience at supervisory level may consider as Senior Technician.\nInterested parties\u00a0please apply with full resume, contact number, date available and expected salary by\u00a0clicking \"Apply Now\".\u00a0\n\nTo learn more about us, please visit our website\u00a0Liu Chong Hing Investment Ltd.\n\u00a0\nPersonal data provided by job applicants will be used for recruitment purpose only.", "employment_types": ["Full Time", "Permanent"], "selling_points": ["Based in Greater Bay Area (Shenzhen and Jiangmen)", "On-job training,free accommodation and shuttle bus", "Global exposure with development opportunity"], "locations": ["Others - China"], "categories": ["Engineering", "Manufacturing & Production", "Mechanical", "Others", "Student / Fresh Graduate / No Experience"], "post_time": "2022-01-17T02:28:10Z", "salary": {"currency": null, "max": null, "min": null, "period": "monthly", "term": null}, "salary_visible": false, "title_keywords": ["process engineer"], "responsibilities": ["management", "control", "maintenance", "inventory", "systems", "daily operation", "analysis", "professional manner", "repair", "reports", "schedule", "ad hoc projects"], "requirements": {"degrees": ["certificate"], "majors": ["related disciplines", "building services"], "languages": ["chinese"], "language_level": ["proficient"], "hard_skills": ["chinese word processing", "ms office", "maintenance", "green card"], "soft_skills": ["interpersonal skills", "sense of responsibility"], "languages_combined": [{"language": "chinese", "language_level": ["proficient"]}]}, "experience_required": {"duration": ["3 years", "minimum 8 years"], "field": ["supervisory level", "relevant experience", "maintenance"]}}, {"job_id": "100003009051709", "location_code": "hk", "company": "ASM Technology Hong Kong Limited", "job_title": "Thermal Engineer (Fresh Graduate / IANG Holder Is Welcome)", "description": "About The Role:\n\nTo provide system support, carry out routine and corrective maintenance, testing and commissioning of traffic control and surveillance system / traffic detection system\n\n\nAbout You:\n\nCertificate in Electronic/ Electrical/ Engineering/ Information Technology or relevant discipline\nAt least 2 years working experience in electrical, electronic and control engineer\nGood command of written English and Chinese;\nIT background is preferable\nDriver License (Class 1&2)is preferable\nInitiative and hard working\n\n\nWhat you can get from us\n\nOn-the-job training, learning and development\u00a0provided\nExecutive workshops, interest class, corporate purchase discount offered by SHKP\nCompetitive salary and annual leaves\nFlexible working opportunities\n\nInterested parties, please send full resume with expected salary and available date to\u00a0Human Resources and Administration Department by e-mail or by fax 2111 9459.\u00a0\n\n\u00a0(Data collected will be used for recruitment purpose only.)", "employment_types": ["Full Time", "Permanent"], "selling_points": ["Design cooling and heating systems", "Degree or higher in Mechanical Engineering", "Knowledge in precision machine design"], "locations": ["Tsing Yi"], "categories": ["Engineering", "Electrical / Electronics", "Mechanical", "Others"], "post_time": "2022-01-16T21:51:00Z", "salary": {"currency": null, "max": null, "min": null, "period": "monthly", "term": null}, "salary_visible": false, "title_keywords": ["engineer"], "responsibilities": ["control", "commissioning", "maintenance", "testing", "purchase"], "requirements": {"degrees": ["certificate"], "majors": ["engineering", "information technology"], "languages": ["english", "chinese"], "language_level": ["good command"], "hard_skills": ["workshops", "maintenance"], "soft_skills": ["flexible", "hard working", "learning", "initiative"], "languages_combined": [{"language": "english", "language_level": ["good command"]}, {"language": "chinese", "language_level": ["good command"]}]}, "experience_required": {"duration": ["at least 2 years"], "field": []}}, {"job_id": "100003009051706", "location_code": "hk", "company": "ASM Technology Hong Kong Limited", "job_title": "Thermal Engineer (Fresh Graduate / IANG Holder Is Welcome)", "description": "Being a member of Convenience Retail Asia Limited with company vision of \"We bake for the happiness & sharing moments of our Customers\", we provide the reinventing, tasty, fresh and beautifully presented bakery delicacies in Hong Kong, Macau and Guangzhou. To cope with our expanding business needs, we are looking for a high caliber candidate with the relevant professional experience to fill this position.\n\n\u8056\u5b89\u5a1c\u65bc\u9999\u6e2f\u3001\u6fb3\u9580\u53ca\u73e0\u6c5f\u4e09\u89d2\u6d32\u5747\u8a2d\u6709\u96f6\u552e\u5e97\u8216\u7db2\u7d61\uff0c\u4ee5\u81ea\u5bb6\u54c1\u724c\u5206\u92b7\u81ea\u5bb6\u751f\u7522\u4e4b\u9eb5\u5305\u897f\u9905\u53ca\u7bc0\u65e5\u98df\u54c1\u3002\u8056\u5b89\u5a1c\u81f4\u529b\u6bcf\u5929\u63d0\u4f9b\u7f8e\u5473\u3001\u65b0\u9bae\u53ca\u5225\u51fa\u5fc3\u88c1\u7684\u70d8\u7119\u7522\u54c1\uff0c\u8b93\u9867\u5ba2\u53ef\u8207\u646f\u611b\u5206\u4eab\u5feb\u6a02\u4e00\u523b\u3002\u6211\u5011\u5145\u6eff\u71b1\u8aa0\u7684\u5718\u968a\u81f4\u529b\u63d0\u4f9b\u512a\u8cea\u53ca\u53cb\u5584\u7684\u670d\u52d9\uff0c\u4e26\u900f\u904e\u591a\u5143\u5316\u7684\u7522\u54c1\u548c\u5275\u65b0\u7684\u63a8\u5ee3\u70ba\u9867\u5ba2\u5e36\u4f86\u7121\u9650\u6b61\u6a02\u3002\n\n\u8077\u8cac / \u8981\u6c42 \uff1a\n\n\u8ca0\u8cac\u8655\u7406\u98df\u54c1\u5ee0\u623f\u8a2d\u65bd\u548c\u8a2d\u5099\u7684\u4fdd\u990a\u53ca\u7dad\u4fee\u5de5\u4f5c\n\u51773\u5e74\u4ee5\u4e0a\u5ee0\u623f\u7dad\u4fee\u6216\u96ea\u623f\u4fdd\u990a\u7dad\u4fee\u76f8\u95dc\u7d93\u9a57\n\u5177\u96fb\u5de5A/R\u724c\n\u5de5\u4f5c\u5730\u9ede\uff1a\u8475\u6d8c\n\n\u5de5\u4f5c\u6642\u9593\uff1a08\uff1a30 - 17\uff1a30 \uff0c\u6bcf\u9031\u5de5\u4f5c5-6\u5929\uff0c\u6bcf\u67085\u5929\u4f8b\u5047\uff0c\u8f2a\u4f11\n\n\u6708\u85aa\uff1aHK$16,000 - $20,000\n\n\u54e1\u5de5\u798f\u5229\uff1a\u8d85\u6642\u6d25\u8cbc , \u81b3\u98df\u6d25\u8cbc, \u6709\u85aa\u81b3\u98df\u6642\u9593 , \u914c\u60c5\u6027\u82b1\u7d05 , \u91ab\u7642\u798f\u5229 , \u5bb6\u5ead\u53cb\u5584\u5047 , \u54e1\u5de5\u8cfc\u7269\u512a\u60e0\u7b49\n\n\u61c9\u5fb5\u8005\u53ef\u900f\u904e\u4ee5\u4e0b\u9014\u5f91\u9810\u7d04\u9762\u8a66\u6216\u67e5\u8a62\uff1a\n\n\u81f4\u96fb2991 6680\u9810\u7d04\u9762\u8a66\u6216\u67e5\u8a62\uff1b\u6216\n\u5c07\u59d3\u540d\u3001\u61c9\u5fb5\u8077\u4f4d\u3001\u5c45\u4f4f\u5730\u5340\u3001\u806f\u7d61\u96fb\u8a71Whatsapp\u52306596 6174 \uff1b\u6216\n\u5c07\u5c65\u6b77\u96fb\u90f5\u81f3\u672c\u516c\u53f8\n\u6240\u6709\u7533\u8acb\u5747\u7372\u56b4\u683c\u4fdd\u5bc6\u3002\u61c9\u5fb5\u8005\u6240\u63d0\u4f9b\u7684\u500b\u4eba\u8cc7\u6599\u53ea\u4f9b\u4f5c\u62db\u8058\u7528\u9014\u3002\u82e5\u99ae\u6c0f\u96c6\u5718\u7684\u5176\u4ed6\u6210\u54e1\u516c\u53f8\u6709\u985e\u4f3c\u8077\u4f4d\u7a7a\u7f3a\uff0c\u4fdd\u7559\u6b0a\u5229\u5c07\u7533\u8acb\u4eba\u6240\u63d0\u4f9b\u4e4b\u8cc7\u6599\u8f49\u4ea4\u5176\u4ed6\u6210\u54e1\u516c\u53f8\u4f5c\u62db\u8058\u7528\u9014\u3002\n\n\u61c9\u5fb5\u8005\u9700\u63d0\u4f9b\u5145\u8db3\u5b8c\u6574\u7684\u8cc7\u6599\u4ee5\u9032\u884c\u7504\u9078\u3002\u61c9\u5fb5\u8005\u6709\u6b0a\u67e5\u95b1\u53ca\u6539\u6b63\u6240\u63d0\u4f9b\u7684\u500b\u4eba\u8cc7\u6599\uff0c\u8acb\u4ee5\u66f8\u9762\u900f\u904e\u96fb\u90f5\u5411\u4eba\u529b\u8cc7\u6e90\u7d93\u7406\u63d0\u51fa\u3002\n\nInterested parties, please forward your resume stating salary expectation and available date to [email redacted, apply via Company website]\n\nFor more information of Saint Honore Cake Shop, please visit www.cr-asia.com.\n\n(All applications will be treated in the strictest confidence. Personal data provided will be used for recruitment purpose only. The information collected might also be disclosed to other associated companies of the Fung Group for job matching of similar vacancies.\n\nThe provision of full and complete information in support of your application is necessary for selection purposes. Applicant has the right to request access to and correction of personal data collected from him/her in writing to the Human Resource Manager by post to P.O. Box 92408, Tsim Sha Tsui Post Office, Hong Kong.)", "employment_types": ["Full Time", "Permanent"], "selling_points": ["Design cooling and heating systems", "Degree or higher in Mechanical Engineering", "Knowledge in precision machine design"], "locations": ["Tsing Yi"], "categories": ["Engineering", "Electrical / Electronics", "Mechanical", "Others"], "post_time": "2022-01-16T21:50:58Z", "salary": {"currency": null, "max": null, "min": null, "period": "monthly", "term": null}, "salary_visible": false, "title_keywords": ["engineer"], "responsibilities": [], "requirements": {"degrees": [], "majors": [], "languages": [], "language_level": [], "hard_skills": [], "soft_skills": [], "languages_combined": []}, "experience_required": {"duration": [], "field": ["business"]}}, {"job_id": "100003009052035", "location_code": "hk", "company": "Entrust Asia Pacific Limited", "job_title": "Technical Support Specialist", "description": "Responsibilities:\n\nDesign cooling and heating systems and follow through the deployment\nDrive thermal designs with numerical approaches, model based analysis\nConduct experiments to validate designs\nDevelop and optimize automation scripts for numerical analysis tools\nSupport thermal management for electronics\nInvolve in precision and mechatronics design work occasionally\n\nRequirements:\n\nDegree or higher in Mechanical Engineering / Physics or relevant disciplines\nGood understanding of thermal technologies including computational modeling and calculation\nWorking or research experience in thermal system design is a plus\nKnowledge in precision machine design, CFD or thermal modeling tools is a plus\n\nAttractive salary and fringe benefits package will be offered to the right candidates.\nInterested parties please submit your application with cover letter, resume, certificate and transcripts.\nData collected will be used for recruitment purpose only. Suitable candidates may be referred to other vacancies within our company.\nPlease visit our company website for our company background, products and other useful information.Website:\u00a0http://www.asmpacific.com/", "employment_types": ["Permanent"], "selling_points": ["Career in Payments, Identity, Digital Technology", "Flexible Working", "Best team in Security"], "locations": ["Kwun Tong"], "categories": ["Engineering", "Electrical / Electronics", "Mechanical", "Information Technology (IT)", "Support"], "post_time": "2022-01-17T01:53:26Z", "salary": {"currency": null, "max": null, "min": null, "period": "monthly", "term": null}, "salary_visible": false, "title_keywords": ["technical support specialist"], "responsibilities": ["design work", "management", "analysis", "systems", "design", "develop"], "requirements": {"degrees": ["degree"], "majors": ["physics", "mechanical engineering"], "languages": [], "language_level": [], "hard_skills": ["plus", "system design"], "soft_skills": [], "languages_combined": []}, "experience_required": {"duration": [], "field": ["research", "system design"]}}, {"job_id": "100003009053460", "location_code": "hk", "company": "UPS Parcel Delivery Service Limited", "job_title": "Plant Engineering Assistant Manager", "description": "Responsibilities\n\nThe Plant Engineer Assistant Manager execute plant engineering function in Hong Kong and Taiwan. the successful candidate will:\n\nSupport the appropriation of project funds. Produce 2D AutoCAD layout drawings, assemble estimates, and create project schedules. Input, review and approve funding requests and PE related supporting documents in UPS internal appropriation database.\nManage bidding and contracting of projects. Define project scope through direct production of 2D AutoCAD layout drawings, and editing of UPS specifications for use in both bid documents and contracts. Liaise with professional services companies (consultants). Write contracts.\nSupervise on-site construction, Lease Hold Improvement works, and Material Handling system installation. Ensure safe work environment, adherence to UPS specification and requirements, and completion of contracted scope. Drive effective use of resources, adherence to schedule, adherence to budget and process payments. Coordinate cross-functionally to ensure effective commissioning and deployment of new assets.\nBe responsible for facility and equipment maintenance through the dispatch of vendors. Ensure work is done in safe and proper manner and contracted scope is completed.\nAudit conveyor contractor preventative maintenance procedures to ensure quality work.\nAudit Facility Safety to UPS standards and regulatory requirements. Correct deficiencies in order to ensure a safe work environment.\nAudit Environmental compliance. Oversee deficiency correction.\nProvide support in HK and TW through a combination of directly completing tasks, and/or reviewing and advising, and/or training UPS local country teams in order to execute tasks described above.\n\nQualifications\n\nBachelor Degree in Engineering (Civil, Electrical, Mechanical or similar)\nMinimum 5 years of experience required in any of the following field: construction project management, building maintenance and industrial equipment maintenance\nFluent in oral and written communication, in both English and Chinese (Mandarin, Cantonese)\nAble to draw a building layout on 2D CAD software\nCompetent in Microsoft office applications\nAbility to travel within Asia\nAbility to work cross-culturally with the staff in other countries\nExperience with a formal Continuous Improvement Process system is an asset", "employment_types": ["Full Time", "Permanent"], "selling_points": ["Construction project and building maintenance", "Engineering (Civil, Electrical, Mechanical)", "5 years or above working experience"], "locations": ["Lai Chi Kok"], "categories": ["Building & Construction", "Building / Construction / QS", "Engineering", "Engineering Project Management", "Mechanical"], "post_time": "2022-01-17T07:00:26Z", "salary": {"currency": null, "max": null, "min": null, "period": "monthly", "term": null}, "salary_visible": false, "title_keywords": ["assistant manager"], "responsibilities": ["software", "schedules", "regulatory requirements", "budget", "quality", "audit", "drawings", "communication", "database", "liaise with", "editing", "contracts", "compliance", "teams", "material handling system", "schedule", "installation", "provide support", "commissioning", "review", "procedures", "specifications", "maintenance", "coordinate", "project management", "payments", "contracting"], "requirements": {"degrees": ["degree", "bachelor"], "majors": ["engineering"], "languages": ["cantonese", "english", "chinese", "mandarin"], "language_level": ["fluent"], "hard_skills": ["maintenance", "microsoft office", "cad", "project management", "safe", "material handling system", "deployment", "pe", "autocad"], "soft_skills": ["oral", "responsible", "competent", "communication", "project management"], "languages_combined": [{"language": "cantonese", "language_level": ["fluent"]}, {"language": "english", "language_level": ["fluent"]}, {"language": "chinese", "language_level": ["fluent"]}, {"language": "mandarin", "language_level": ["fluent"]}]}, "experience_required": {"duration": ["minimum 5 years"], "field": ["project management", "construction", "maintenance"]}}, {"job_id": "100003009051685", "location_code": "hk", "company": "S' Wah Engineering Co Ltd", "job_title": "Senior Engineer", "description": "About The Role :\n\n\nAssist the supervisor to perform in-house or field testing\nPrepare testing records\nDeal with any other duties as may be assigned from time to time by the supervisor\nAbout You :\n\n\nForm 3 or above\nSolid computer knowledge\nProactive, innovative and willing to learn & work\nGood working attitude\nGreat interest in career development in E&M, Transportation and construction field\nSuccessful candidate will join the Apprenticeship Training Scheme\nWhat you can get from us\n\n\nOn-the-job training, learning and development\u00a0provided\nExecutive workshops, interest class, corporate purchase discount offered by SHKP\nCompetitive salary and annual leaves\nFlexible working opportunities\nInterested parties, please send full resume with expected salary and available date to Human Resources and Administration Department by e-mail or by fax 2111 9459.\n\n(Data collected will be used for recruitment purpose only)", "employment_types": ["Full Time", "Permanent"], "selling_points": [], "locations": ["Cheung Sha Wan"], "categories": ["Building & Construction", "Building / Construction / QS", "Engineering", "Engineering Project Management", "Mechanical"], "post_time": "2022-01-16T21:50:46Z", "salary": {"currency": null, "max": null, "min": null, "period": "monthly", "term": null}, "salary_visible": false, "title_keywords": ["senior engineer"], "responsibilities": ["any other duties", "purchase", "career development", "testing"], "requirements": {"degrees": [], "majors": [], "languages": [], "language_level": [], "hard_skills": ["workshops", "scheme"], "soft_skills": ["flexible", "good working attitude", "willing to learn", "innovative", "learning", "proactive"], "languages_combined": []}, "experience_required": {"duration": [], "field": []}}, {"job_id": "100003009054982", "location_code": "hk", "company": "Fathom Precision International Limited", "job_title": "Project Managers", "description": "Requirement:\nB.Degree / H.Dip in Mech / B.S. Engineering or equivalent.\nProficient in CSD / Shop drawing coordination is a must.\nOver 6 years experience in Plumbing & Drainage Works is preferable.\nFamiliar with Auto CAD is an advantage.\nSelf-motivated, hard working.\nOn / Off site is required.\nCandidates with less experience / education background will be considered as Site Engineer / Assistant Engineer.\nImmediate available.\n\n\nInterested parties please send full resume with expected salary to \u00a07/F, Unit B, China Fen Hin Bldg, \u00a05 Cheung Yue St, Cheung Sha Wan, KLN or click \"Apply Now\" for an application form.\n[All applications will be treated strictly confidential and will be used for recruitment purpose only]", "employment_types": ["Full Time", "Permanent"], "selling_points": ["Station in Dongguan", "8 years or above relevant experience", "Tooling and Molding manufacturing Industry"], "locations": ["Others - China"], "categories": ["Engineering", "Manufacturing & Production", "Mechanical"], "post_time": "2022-01-17T16:22:44Z", "salary": {"currency": null, "max": null, "min": null, "period": "monthly", "term": null}, "salary_visible": false, "title_keywords": [], "responsibilities": ["coordination"], "requirements": {"degrees": ["dip", "degree"], "majors": [], "languages": [], "language_level": [], "hard_skills": ["auto cad"], "soft_skills": ["self-motivated", "coordination", "hard working"], "languages_combined": []}, "experience_required": {"duration": ["6 years"], "field": ["plumbing", "drainage", "education"]}}, {"job_id": "100003009054356", "location_code": "hk", "company": "Nice Property Management Limited", "job_title": "Assistant Maintenance Officer (Building Services) / Technical Assistant", "description": "Requirements\n\nIdeal candidate should be graduate in relevant engineering discipline, plus 8 years or above relevant experience in Tooling and Molding manufacturing Industry.\n\nSound experience in detailed mould design and manufacturing\nGood technical background and able to deal with overseas clients\nKnowledge and working experience on 3D CAD systems, preferably on Solidwork, Pro-E.\nFollow up & co-ordinate new tooling build process, tool qualification, tool debug and finally part qualification process.\nStrong Leadership with a team of engineers in tooling operation\nProficiency in spoken and written English is needed and Chinese as well\nSelf-starter, self-motivated, proactive and good communicator\nStation in Dongguan.\n\nWe offer an attractive remuneration to the successful candidate. Interested parties please send email by \"Apply Now\".\n\nPersonal data collected will be used for recruitment purposes only", "employment_types": ["Full Time"], "selling_points": [], "locations": ["Hung Hom"], "categories": ["Engineering", "Electrical / Electronics", "Mechanical", "Property / Real Estate", "Others"], "post_time": "2022-01-17T09:15:43Z", "salary": {"currency": null, "max": null, "min": null, "period": "monthly", "term": null}, "salary_visible": false, "title_keywords": ["maintenance officer", "assistant", "technical assistant"], "responsibilities": ["systems", "design"], "requirements": {"degrees": [], "majors": [], "languages": ["english", "chinese"], "language_level": ["proficiency"], "hard_skills": ["cad", "plus", "solidwork"], "soft_skills": ["self-motivated", "ideal", "communicator", "proactive", "leadership", "detailed"], "languages_combined": [{"language": "english", "language_level": ["proficiency"]}, {"language": "chinese", "language_level": []}]}, "experience_required": {"duration": ["8 years"], "field": ["manufacturing", "engineering", "design", "relevant experience", "manufacturing industry"]}}, {"job_id": "100003009054439", "location_code": "hk", "company": "Keio Engineering Co Ltd", "job_title": "Maintenance Supervisor", "description": "Holder of Diploma or Higher Certificate in Electrical Engineering or Mechanical Engineering or Building Services Engineering from a Hong Kong polytechnic university / polytechnic, the Hong Kong Institute of Vocational Education (IVE) or a technical institute / technical college, or equivalent\n\n\nPlease send resume & expected salary to HR Dept., Nice Property Management Ltd., Room 2-4, 18/F, New Trend Centre, 704 Prince Edward Road East, Kowloon or fax to 21947804, or email\n\nPersonal data collected will be used for recruitment purpose only.", "employment_types": ["Full Time", "Permanent"], "selling_points": ["Year-end double pay", "E&M or Building Services industry", "Supervise a team of maintenance technicians"], "locations": ["Sai Wan"], "categories": ["Engineering", "Electrical / Electronics", "Mechanical", "Others"], "post_time": "2022-01-17T09:36:53Z", "salary": {"currency": null, "max": null, "min": null, "period": "monthly", "term": null}, "salary_visible": false, "title_keywords": ["supervisor"], "responsibilities": ["hr", "recruitment", "management", "personal data"], "requirements": {"degrees": ["diploma", "higher certificate"], "majors": ["engineering", "building services", "electrical engineering", "mechanical engineering"], "languages": [], "language_level": [], "hard_skills": ["nice"], "soft_skills": [], "languages_combined": []}, "experience_required": {"duration": [], "field": []}}, {"job_id": "100003009053676", "location_code": "hk", "company": "Able Engineering Company Limited", "job_title": "Resident Building Services Engineer", "description": "The Job:\nThe incumbent is responsible for conducting regular inspections, testing and examination\u00a0for plant and machinery. He/she is also required to provide technical/mechanical\u00a0services/supports on installation, dismantling, operation, repair and maintenance of plant\u00a0and machinery to ensure work safety and smooth operation.\n\nRequirements:\n\nDegree holder in Mechanical Engineering or equivalent,\nProfessionally qualified, e.g. a Registered Professional Engineer (Mech)\nMinimum 7 years\u2019 relevant experience of which at least 2 years in mechanical\u00a0inspection of site plant and machinery\nExperience in HA & ASD projects is preferred\nHigh proficiency in both English and Chinese\nProactive, good communication and interpersonal skills\n\nInterested parties please send full resume stating your current and expected salary with\ncontact number via fax: 2390 4681 or click \"Apply Now\" below.\n\nFor more information about our company, please visit our website at\nhttp://www.socam.com/\n\n\nPersonal data provided by applicants will be used strictly in accordance with our Company's personal data\u00a0policies, a copy of which is available upon request. You may consider your application unsuccessful if you are\u00a0not contacted within 8 weeks.", "employment_types": ["Full Time", "Permanent"], "selling_points": [], "locations": ["Not Specified"], "categories": ["Building & Construction", "Building / Construction / QS", "Engineering", "Electrical / Electronics", "Mechanical"], "post_time": "2022-01-17T07:20:04Z", "salary": {"currency": null, "max": null, "min": null, "period": "monthly", "term": null}, "salary_visible": false, "title_keywords": ["building services engineer"], "responsibilities": ["installation", "repair", "maintenance", "testing"], "requirements": {"degrees": ["degree holder"], "majors": ["mechanical engineering"], "languages": ["english", "chinese"], "language_level": ["proficiency"], "hard_skills": [], "soft_skills": ["proactive", "communication and interpersonal skills"], "languages_combined": [{"language": "english", "language_level": ["proficiency"]}, {"language": "chinese", "language_level": ["proficiency"]}]}, "experience_required": {"duration": ["at least 2 years", "minimum 7 years"], "field": ["relevant experience"]}}, {"job_id": "100003009051711", "location_code": "hk", "company": "ASM Technology Hong Kong Limited", "job_title": "Test Engineer", "description": "Corporate member of a professional institution recognized for corporate membership in the status of registered professional engineer (RPE) of the Hong Kong Institution of Engineers (HKIE) in the Building Services Engineering or Electrical Engineering or Mechanical Engineering Discipline, or equivalent;\nAt least 5 years relevant post qualification experience in building services engineering, electrical engineering or mechanical engineering;\nWork on construction site.\n\nWe offer competitive salary package and career development opportunity to the successful candidate. Interested parties may send your full resume, present and expected salary, available date and contact number by email by clicking \"Apply Now\".\n\n\nTo visit our website for more information: www.ableeng.com.hk\n\n(As an Equal Opportunities Employer, Able is committed to eliminating discrimination in employment. The vacancy advertised is open to all applicants meeting the basic entry requirement irrespective of their disability, sex, marital status, pregnancy, age, family status, sexual orientation or race etc. Applicants not hearing from us within 6 months may consider their applications unsuccessful. Personal data collected will be used for recruitment related purposes only.)", "employment_types": ["Full Time", "Permanent"], "selling_points": ["Minimum 1 years relevant working experience", "Degree or above in Mechatronics", "Define test plan & create test cases for products"], "locations": ["Tsing Yi"], "categories": ["Engineering", "Electrical / Electronics", "Mechanical", "Others"], "post_time": "2022-01-16T21:51:01Z", "salary": {"currency": null, "max": null, "min": null, "period": "monthly", "term": null}, "salary_visible": false, "title_keywords": ["engineer"], "responsibilities": [], "requirements": {"degrees": [], "majors": [], "languages": [], "language_level": [], "hard_skills": ["the hong kong institution of engineers", "hkie"], "soft_skills": [], "languages_combined": []}, "experience_required": {"duration": ["at least 5 years"], "field": ["building services", "engineering"]}}, {"job_id": "100003009052926", "location_code": "hk", "company": "T W Design Consultants Limited", "job_title": "ASSOCIATE [Ref.TWD-A]", "description": "Job description\nDefine test plan and create test cases for the product\nImplement test plan with design team and production team\nStreamline test plan deployment process\nAnalyze the correlation of test data and machine performance\nDevelop and standardize test methodology on critical components, sub-assemblies modules and products prior to production phases and implementation\nDevelop machine diagnostic tool\nJob requirements\nDegree or above in Mechatronics/ Electronics Engineering / Computer Science / Information Engineering or related disciplines\nMinimum 1 years solid and relevant working experience in test engineer\nProficient with DOE, test data analysis skill and statistics\nFamiliar with testing software development tools, including C#, C++ and/ or Labview\nGood problem-solving skill.\nHands-on experience in any mechatronic project, project management or stage-gate is an advantage\nCandidates with more than 5 years' relevant experience will be considered for the Senior Engineer post\n\nAttractive salary and fringe benefits package will be offered to the right candidates.\n\nInterested parties please submit your application with cover letter, resume, certificate and transcripts.\n\nData collected will be used for recruitment purpose only. Suitable candidates may be referred to other vacancies within our company.", "employment_types": ["Full Time", "Permanent"], "selling_points": ["Degree holder in Engineering", "Member of HKIE, Chartered Engineer of CIBSE", "Minimum 12 years' relevant working experience"], "locations": ["Hung Hom"], "categories": ["Building & Construction", "Building / Construction / QS", "Engineering", "Engineering Project Management", "Mechanical"], "post_time": "2022-01-17T07:26:03Z", "salary": {"currency": null, "max": null, "min": null, "period": null, "term": null}, "salary_visible": false, "title_keywords": ["associate"], "responsibilities": ["data", "implementation", "design", "develop", "plan"], "requirements": {"degrees": ["degree or above"], "majors": ["related disciplines", "engineering", "computer science"], "languages": [], "language_level": [], "hard_skills": ["c++", "problem-solving", "analysis", "project management", "labview", "c#"], "soft_skills": ["project management", "problem-solving", "hands-on"], "languages_combined": []}, "experience_required": {"duration": ["5 years", "minimum 1 years"], "field": ["project management", "relevant experience", "relevant working experience", "senior engineer"]}}, {"job_id": "100003009051654", "location_code": "hk", "company": "ATAL Building Services Engineering Limited", "job_title": "Customer Service Coordinator (Part-Time) (Ref: SERG/CSO)", "description": "Degree holder in Electrical Engineering, Mechanical Engineering, Building Services Engineering or related disciplines\nMember of HKIE, Chartered Engineer of CIBSE or equivalent\nMinimum 12 years' experience, preferably with E&M consultants and/or developers\nTo prepare tender documents / drawings, tender analysis / report and systems design / vetting\nTo supervise testing and commissioning, approve drawing and material submissions and supervise statutory submission work\nFluent in written and spoken English and Chinese, including Putonghua\n\nWe offer salary and benefits commensurate with qualifications and experience. Please send a full resume with contact number and expected salary to General Manager - Human Resources & Administration, T W Design\u00a0Consultants Limited, 3/F., One Harbourfront, 18 Tak Fung Street, Hunghom, Kowloon (Please quote reference on envelope) or by clicking \"Apply Now\".\n\nWe are an equal opportunity employer and welcome applications from all qualified candidates. The information provided will be treated in strict confidence and be used only for consideration of your application for relevant/similar post(s).\n\nApplicants not hearing from us within six weeks from the date of advertisement may consider their applications unsuccessful. All personal data of unsuccessful applicants will be destroyed after the recruitment exercise when no longer required.", "employment_types": ["Part Time"], "selling_points": ["F.5 or above", "1 year\u2019s call centre experience", "Excellent telephone manner"], "locations": ["Kwai Fong"], "categories": ["Sales, CS & Business Devpt", "Call Centre", "Engineering", "Electrical / Electronics", "Mechanical"], "post_time": "2022-01-16T21:31:34Z", "salary": {"currency": null, "max": null, "min": null, "period": "hourly", "term": null}, "salary_visible": false, "title_keywords": ["customer service coordinator"], "responsibilities": ["commissioning", "prepare tender documents", "systems", "design", "drawings", "tender analysis", "testing", "report"], "requirements": {"degrees": ["degree holder"], "majors": ["engineering", "electrical engineering", "mechanical engineering", "related disciplines", "building services"], "languages": ["putonghua", "english", "chinese"], "language_level": ["fluent"], "hard_skills": ["analysis", "hkie"], "soft_skills": [], "languages_combined": [{"language": "putonghua", "language_level": ["fluent"]}, {"language": "english", "language_level": ["fluent"]}, {"language": "chinese", "language_level": ["fluent"]}]}, "experience_required": {"duration": ["minimum 12 years"], "field": []}}, {"job_id": "100003009054197", "location_code": "hk", "company": "Triangle Motors Limited", "job_title": "Technical Officer", "description": "Our client, a\u00a0sizeable & listed company,\u00a0is now seeking for a high caliber individual to join their team as\u00a0Engineer (BSE/FS/ELL/ELV/ME).\n\nResponsibilities\n\nResponsible for costing, tender estimation, tendering procurement, and subcontractor monitoring\nPrepare required drawings, corresponding documents and statutory submission\nAssist the Project Manager/Project Engineer in overall project operations, co-ordination and handover\nAssist the Project Manager/Project Engineer to supervise a team of junior technical staff/ subcontractors to ensure the smooth running of the project, on-time delivery and completion of site works in a safety manner\nMonitor work progress and site safety in compliance with the contractual and statutory requirements\n\nRequirement\n\nDegree / Higher Diploma in\u00a0Building Services Engineering, Fire Services, Electrical, Electronic,\u00a0Mechanical, Civil or other related Engineering disciplines\nGood communication and project coordination\nProactive, drive to success and able to work independently and under pressure\nGood command of both written and spoken English and Chinese\nProficiency in MS Office and AUTOCAD software applications\n\n\n\n\nInterested parties please send your application via email to\u00a0Apply Now.\nFor any enquiries, please do not hesitate to contact\u00a0Zac Cheng\u00a0at\u00a0(852) 2402-9838.\n\u00a0\n\nWe also have various job vacancies from our well-established clients in all kinds of fields, please feel free to contact us. We are always willing to give you support on your career development.\n\nAll information received will be treated in strict confidence and used for recruitment purpose only.", "employment_types": ["Full Time", "Permanent"], "selling_points": [], "locations": ["Kowloon Bay"], "categories": ["Engineering", "Manufacturing & Production", "Mechanical", "Others"], "post_time": "2022-01-17T08:46:37Z", "salary": {"currency": null, "max": null, "min": null, "period": "monthly", "term": null}, "salary_visible": false, "title_keywords": ["technical officer"], "responsibilities": ["operations", "monitoring", "monitor", "tendering", "compliance", "drawings", "statutory requirements", "tender"], "requirements": {"degrees": ["diploma", "degree"], "majors": ["building services", "engineering"], "languages": ["english", "chinese"], "language_level": ["good command"], "hard_skills": ["autocad", "ms office"], "soft_skills": ["work independently", "under pressure", "communication", "coordination", "proactive"], "languages_combined": [{"language": "english", "language_level": ["good command"]}, {"language": "chinese", "language_level": ["good command"]}]}, "experience_required": {"duration": [], "field": []}}, {"job_id": "100003009055147", "location_code": "hk", "company": "Teltec Semiconductor Pacific Limited", "job_title": "Sales Engineer / Senior Engineer", "description": "Job Highlights:\n\n\nEver-expanding organization with extensive career development pathways and opportunities;\nApply your talent where it counts, working with a highly skilled technical team;\nGood remuneration and benefits.\n\nAbout Us\n\nTeltec Pacific is a multinational technical sales and service organisation serving the Semiconductor, Photonics and Optoelectronics Industry for over 37 years; with headquarters based in Central, Hong Kong and branches across the Asia Pacific region. We represent some of the Industry\u2019s world leading equipment and materials manufacturers in the region.\n\nAn exciting opportunity is now available, and we invite applications for Sales Engineer and Senior Engineer to join our organization. Successful candidates will be responsible for the company\u2019s represented equipment or materials in the high-tech electronics industry. You will work alongside with our collaborative technical sales and service engineering teams staying in various cities and countries in the Far East.\n\n\n\nJob Description\n\nDuties & Responsibilities\n\nSupport Sales and Services Managers;\nHandles Sales and Application jobs for Research Instrument\nSkills, Experience & Attributes\u00a0\n\nDegree holders, Science or Engineering majors highly regarded;\n0-3 years of solid experience in electronic industries preferred. Senior engineers post will be offered to those who have very related experience;\u00a0\nFluent in English and Mandarin;\u00a0\nMature and independent individuals with a high attention to detail and a proactive attitude;\n\nApplications\n\nWe are seeking highly engaged and motivated individuals to join our dynamic and growing organization, which highly recognises and rewards outstanding performances. Senior positions may be offered to potential candidates who can demonstrate long and direct working experience in the electronics market. Those successful will be offered 5-day work weeks, attractive remuneration and fringe benefits including medical allowance.\n\nIf this sounds like you, and you can demonstrate that you fill the requirements above, please submit your cover letter, full resume with expected salary to:\n\nHR Department\nTeltec Semiconductor Pacific Limited\n2802 Wing On House,\n71 Des Voeux Road Central,\nHong Kong\nTel: 852-25214213\nFax: 852-28106090\nWebsite: www.teltec.asia", "employment_types": ["Full Time", "Permanent"], "selling_points": ["Degree holders, Science or Engineering majors", "0\u20133 years experience in electronic industries", "Excellent development opportunities"], "locations": ["Central"], "categories": ["Engineering", "Electrical / Electronics", "Mechanical", "Sales, CS & Business Devpt", "Technical Sales / Sales Engineer"], "post_time": "2022-01-18T02:05:10Z", "salary": {"currency": null, "max": null, "min": null, "period": "monthly", "term": null}, "salary_visible": false, "title_keywords": ["senior engineer", "sales engineer"], "responsibilities": ["career development"], "requirements": {"degrees": [], "majors": [], "languages": [], "language_level": [], "hard_skills": [], "soft_skills": ["extensive"], "languages_combined": []}, "experience_required": {"duration": [], "field": []}}, {"job_id": "100003009054206", "location_code": "hk", "company": "Auberge Hospitality Limited", "job_title": "And we are hiring \u2013 \u6280\u8853\u54e1, \u6109\u666f\u7063\u5eb7\u6a02\u6703", "description": "\u8077\u8cac\uff1a\n\n\u8ca0\u8cac\u6703\u6240\u6cb9\u6f06\u3001\u6728\u5de5\u3001\u6ce5\u6c34\u53ca\u4e00\u822c\u7dad\u4fee\u4fdd\u990a\u5de5\u4f5c\n\n\u8cc7\u6b77\uff1a\n\n\u6301\u6ce5\u6c34/\u6cb9\u6f06\u76f8\u95dc\u8b49\u66f8\u6216\u4e2d\u5de5\u724c\uff0c\u6301\u96fb\u5de5A\u724c\u8005\u512a\u5148\u8003\u616e\n\u5177\u4e09\u5e74\u4ee5\u4e0a\u76f8\u95dc\u5de5\u4f5c\u7d93\u9a57\uff0c\u6709\u6703\u6240\u6216\u9152\u5e97\u5de5\u4f5c\u7d93\u9a57\u8005\u512a\u5148\u8003\u616e\n\u80fd\u64cd\u6d41\u5229\u5ee3\u6771\u8a71\u53ca\u7c21\u55ae\u82f1\u8a9e\n\u9808\u8f2a\u73ed\u5de5\u4f5c (\u516c\u53f8\u63d0\u4f9b\u5bbf\u820d\u4e88\u6709\u9700\u8981\u4e4b\u54e1\u5de5)\n\u53ef\u5373\u6642\u4e0a\u73ed\u8005\u512a\u5148\u8003\u616e\n\nWe offer an attractive remuneration package and excellent career opportunities to the right candidate. Interested applicants please send your CV by email to Apply Now or by WhatsApp at 63173527.\n\nPersonal data provided by job applicants will be used strictly for recruitment purposes only.", "employment_types": ["Full Time", "Permanent"], "selling_points": ["\u8ca0\u8cac\u6703\u6240\u6cb9\u6f06\u3001\u6728\u5de5\u3001\u6ce5\u6c34\u53ca\u4e00\u822c\u7dad\u4fee\u4fdd\u990a\u5de5\u4f5c", "\u6301\u6ce5\u6c34/\u6cb9\u6f06\u76f8\u95dc\u8b49\u66f8\u6216\u4e2d\u5de5\u724c\uff0c\u6301\u96fb\u5de5A\u724c\u8005\u512a\u5148\u8003\u616e", "\u5177\u4e09\u5e74\u4ee5\u4e0a\u76f8\u95dc\u5de5\u4f5c\u7d93\u9a57\uff0c\u6709\u6703\u6240\u6216\u9152\u5e97\u5de5\u4f5c\u7d93\u9a57\u8005\u512a\u5148\u8003\u616e"], "locations": ["Lantau Island"], "categories": ["Engineering", "Electrical / Electronics", "Mechanical", "Others", "Technician"], "post_time": "2022-01-17T09:02:47Z", "salary": {"currency": null, "max": null, "min": null, "period": "monthly", "term": null}, "salary_visible": false, "title_keywords": ["\u6280\u8853\u54e1"], "responsibilities": [], "requirements": {"degrees": [], "majors": [], "languages": [], "language_level": [], "hard_skills": [], "soft_skills": [], "languages_combined": []}, "experience_required": {"duration": [], "field": []}}, {"job_id": "100003009052785", "location_code": "hk", "company": "Serco Group (HK) Limited", "job_title": "\u96fb\u5b50\u6280\u8853\u54e1", "description": "\u8077\u8cac\n\n\u8ca0\u8cac\u7dad\u4fee\u6e2c\u8a66\u53ca\u4fdd\u990aELV\u7b49\u96fb\u5b50\u76f8\u95dc\u8a2d\u5099\n\n\u5de5\u4f5c\u8981\u6c42\n\n\u4e94\u5e74\u6216\u4ee5\u4e0a\u76f8\u95dc\u7dad\u4fee\u4fdd\u990a\u7d93\u9a57;\n\u00a0\u00a0\u00a0\u00a0\u00a0\u00a0\u00a0\u00a0\u00a0\u00a0\u00a0\u00a0\u00a0\u00a0 \u00a0\u00a0 \u6216\n\n\u00a0\u00a0\u00a0\u00a0\u00a0\u00a0\u00a0\u00a0\u00a0\u00a0\u00a0\u00a0\u00a0 \u6301\u6709\u76f8\u95dc\u6587\u6191 / \u5b78\u6b77 \u53ca\u7562\u696d\u5f8c1 \u5e74\u6216\u4ee5\u4e0a\u76f8\u95dc\u7dad\u4fee\u4fdd\u990a\u7d93\u9a57;\n\n\u00a0\u00a0\u00a0\u00a0\u00a0\u00a0\u00a0\u00a0\u00a0\u00a0\u00a0\u00a0\u00a0\u00a0\u00a0\u00a0 \u6216\n\u00a0\n\u00a0\u00a0\u00a0\u00a0\u00a0\u00a0\u00a0\u00a0\u00a0\u00a0\u00a0\u00a0\u00a0 \u5b8c\u6210\u5b78\u5f92\u8a13\u7df4\u4e26\u53d6\u5f97\u7562\u696d\u5f8c3\u5e74\u6216\u4ee5\u4e0a\u76f8\u95dc\u7dad\u4fee\u4fdd\u990a\u7d93\u9a57;\n\n\n\u6301\u67091\u865f/2\u865f\u8eca\u724c(\u5982\u9700)\n\u53ef\u5373\u6642\u4e0a\u73ed\u8005\u512a\u5148\u8003\u616e\n\n\nKey responsibilities\n\nResponsible for the maintenance of electronic equipment, must equip the one of the following work experience (CCTV, Access Control System, building public antenna, computer, or other electronic related equipment, etc.)\n\nQualification\n\n(1)\u00a0\u00a0 Minimum 5 years relevant work experience;\n\nOR\n\n(2)\u00a0\u00a0 Holder of Diploma / Higher Certificate in electronics engineering or computer science\n\u00a0\u00a0\u00a0\u00a0\u00a0\u00a0\u00a0 with 1 year\u2019s relevant post-qualification working experience;\n\nOR\n\n(3)\u00a0\u00a0 Successful completion of a full craft or technician apprenticeship\n\u00a0\u00a0\u00a0\u00a0\u00a0\u00a0\u00a0 with 3 years\u2019 relevant post-qualification working experience;\n\n* Driving License class 1 & 2 (if required)\n\n* Immediate available is highly preferable.\n\nWe offer attractive remuneration package including discretionary bonus, medical insurance and excellent development opportunities to the right candidate.\u00a0 Interested parties please send detailed resume with salary expectation via \"APPLY NOW\" or please contact Ms. Lee for any job enquiries at (+852) 9857 2126.\n\n(All personal data provided will be treated in strict confidence and used for recruitment purposes only.)", "employment_types": ["Full Time"], "selling_points": ["Minimum 1 year post-qualification working exp.", "Competitive Remuneration Package", "Excellent development opportunities"], "locations": ["Sheung Shui"], "categories": ["Engineering", "Mechanical", "Others", "Technician"], "post_time": "2022-01-17T04:03:42Z", "salary": {"currency": null, "max": null, "min": null, "period": "monthly", "term": null}, "salary_visible": false, "title_keywords": ["\u96fb\u5b50\u6280\u8853\u54e1"], "responsibilities": ["access control", "maintenance", "insurance"], "requirements": {"degrees": ["diploma", "higher certificate"], "majors": ["engineering", "computer science"], "languages": [], "language_level": [], "hard_skills": ["cctv", "maintenance"], "soft_skills": ["responsible"], "languages_combined": []}, "experience_required": {"duration": ["3 years", "1 year", "minimum 5 years"], "field": ["related", "post-qualification", "maintenance"]}}, {"job_id": "100003009047894", "location_code": "hk", "company": "The Arca", "job_title": "Duty Engineer \u503c\u73ed\u5de5\u7a0b\u5e2b", "description": "Job Responsibilities \u5de5\u4f5c\u5167\u5bb9:\n\nResponsible for hotel daily maintenance and equipment inspection, such as water, electricity, mechanical equipment, furniture, electronic devices, bathroom equipment and basic air-conditioning maintenance work\n\u8ca0\u8cac\u9152\u5e97\u65e5\u5e38\u7dad\u4fee\u548c\u8a2d\u5099\u6aa2\u67e5\uff0c\u4f8b\u5982\u6c34\u3001\u96fb\u3001\u6a5f\u68b0\u8a2d\u5099\u3001\u5bb6\u5177\u3001\u96fb\u5b50\u8a2d\u5099\u3001\u6d74\u5ba4\u8a2d\u5099\u53ca\u7a7a\u8abf\u7dad\u4fee\u4fdd\u990a\u5de5\u4f5c\nSupervise and control the preventive maintenance schedule\n\u76e3\u7763\u548c\u63a7\u5236\u9810\u9632\u6027\u7dad\u4fee\u8a08\u5283\n\nJob Requirements \u5de5\u4f5c\u8981\u6c42:\n\nHolder of Diploma/Certificate holders in Building Services/Mechanical/Electrical Engineering or other related disciplines\n\u6301\u6709\u5c4b\u5b87\u8a2d\u5099/\u6a5f\u68b0/\u96fb\u6c23\u5de5\u7a0b\u6216\u5176\u4ed6\u76f8\u95dc\u5b78\u79d1\u7684\u6587\u6191/\u8b49\u66f8\nGrade B Certificate of Registration of Electrical Worker is preferred\n\u6301\u6709B\u7d1a\u96fb\u696d\u5de5\u7a0b\u4eba\u54e1\u8a3b\u518a\u8b49\u66f8\u8005\u512a\u5148\nMinimum 4 years\u2019 working experience in repairs and maintenance\n\u81f3\u5c114\u5e74\u7dad\u4fee\u548c\u4fdd\u990a\u7684\u5de5\u4f5c\u7d93\u9a57\nGood command of both spoken and written English and Chinese\n\u826f\u597d\u7684\u4e2d\u6587\u548c\u82f1\u6587\n\nWe offer career opportunities and excellent remuneration package to the right candidate. Please email your full resume with current and expected salary to Human Resources Department or on Whatsapp 5976 5391.\n\nYulan Group Limited is an equal opportunity employer. Applicants not invited for interview within six weeks may consider their applications unsuccessful. All information will be used solely for recruitment purpose and will be destroyed when the recruitment process is finished.", "employment_types": ["Full Time", "Permanent"], "selling_points": ["\u8ca0\u8cac\u9152\u5e97\u65e5\u5e38\u7dad\u4fee\u548c\u8a2d\u5099\u6aa2\u67e5", "\u76e3\u7763\u548c\u63a7\u5236\u9810\u9632\u6027\u7dad\u4fee\u8a08\u5283", "4\u5e74\u7dad\u4fee\u548c\u4fdd\u990a\u7684\u5de5\u4f5c\u7d93\u9a57"], "locations": ["Southern Area"], "categories": ["Engineering", "Electrical / Electronics", "Engineering Project Management", "Mechanical"], "post_time": "2022-01-14T04:23:21Z", "salary": {"currency": null, "max": null, "min": null, "period": "monthly", "term": null}, "salary_visible": false, "title_keywords": ["engineer"], "responsibilities": ["control", "schedule", "maintenance", "inspection"], "requirements": {"degrees": ["certificate", "diploma"], "majors": ["related disciplines", "building services", "electrical engineering"], "languages": ["english", "chinese"], "language_level": ["good command"], "hard_skills": ["certificate of registration of electrical worker", "maintenance"], "soft_skills": [], "languages_combined": [{"language": "english", "language_level": ["good command"]}, {"language": "chinese", "language_level": ["good command"]}]}, "experience_required": {"duration": ["minimum 4 years"], "field": ["maintenance"]}}, {"job_id": "100003009053502", "location_code": "hk", "company": "Able Engineering Company Limited", "job_title": "Electrical & Mechanical Inspector", "description": "Diploma or Higher Certificate or higher qualification in Building Services or Electrical or Mechanical Engineering from a Hong Kong Polytechnic University / Polytechnic or Hong Kong Institute of Vocational Education / technical institute / technical college or equivalent; and\nAttainment of language proficiency requirements of 'level 2' or above\u00a0 in Chinese and English Languages in HKDSEE or HKCEE, or equivalent;\nAt least 8 years site experience for E&M works including 4 years post-qualification experience in the capacity of Assistant Electrical or Mechanical Inspector or equivalent;\nWork on Site.\n\nWe offer competitive salary package and career development opportunity to the successful candidate. Interested parties may send your full resume, present and expected salary, available date and contact number by email by clicking \"Apply Now\".\n\nTo visit our website for more information: www.ableeng.com.hk\n\n(As an Equal Opportunities Employer, Able is committed to eliminating discrimination in employment. The vacancy advertised is open to all applicants meeting the basic entry requirement irrespective of their disability, sex, marital status, pregnancy, age, family status, sexual orientation or race etc. Applicants not hearing from us within 6 months may consider their applications unsuccessful. Personal data collected will be used for recruitment related purposes only.)", "employment_types": ["Full Time", "Permanent"], "selling_points": [], "locations": ["Not Specified"], "categories": ["Building & Construction", "Building / Construction / QS", "Engineering", "Electrical / Electronics", "Mechanical"], "post_time": "2022-01-17T07:04:07Z", "salary": {"currency": null, "max": null, "min": null, "period": "monthly", "term": null}, "salary_visible": false, "title_keywords": [], "responsibilities": [], "requirements": {"degrees": ["diploma", "higher certificate"], "majors": ["building services", "mechanical engineering"], "languages": ["english", "chinese"], "language_level": ["proficiency"], "hard_skills": [], "soft_skills": [], "languages_combined": [{"language": "english", "language_level": ["proficiency"]}, {"language": "chinese", "language_level": ["proficiency"]}]}, "experience_required": {"duration": ["at least 8 years", "4 years"], "field": ["post-qualification"]}}, {"job_id": "100003009047417", "location_code": "hk", "company": "Shun Cheong Electrical Engineering Co Ltd", "job_title": "Assistant Engineer (BSE/FS/ELL/ELV/ME)", "description": "Responsibilities\n\nResponsible for costing, tender estimation, tendering procurement, and subcontractor monitoring\nPrepare required drawings, corresponding documents and statutory submission\nAssist the Project Manager/Project Engineer in overall project operations, co-ordination and handover\nAssist the Project Manager/Project Engineer to supervise a team of junior technical staff/ subcontractors to ensure the smooth running of the project, on-time delivery and completion of site works in a safety manner\nMonitor work progress and site safety in compliance with the contractual and statutory requirements\n\nRequirement\n\nDegree / Higher Diploma in\u00a0Building Services Engineering, Fire Services, Electrical, Electronic,\u00a0Mechanical, Civil or other related Engineering disciplines\nGood communication and project coordination\nProactive, drive to success and able to work independently and under pressure\nGood command of both written and spoken English and Chinese\nProficiency in MS Office and AUTOCAD software applications\nFresh graduate are welcomed\n\nWe offer an attractive remuneration package, training and good career opportunities to the right candidate.\u00a0 Interested parties are invited to send your application enclosing full resume stating career and salary history to the HR Department (either in Word format or PDF format) by whatsapp to 9306-7864,\u00a0fax to 2370-2073 or by clicking \"Apply Now\".\n\n\nApplicants not invited for an interview within two months may consider their applications unsuccessful.\u00a0 All personal data collected will be used for recruitment purpose only.", "employment_types": ["Full Time", "Permanent"], "selling_points": ["BEng / H.Dip in BSE, EE, ME, FS, CIVIL, & ext.", "Overall project operations & co-ordination", "Fresh graduates are welcomed"], "locations": ["Lai Chi Kok"], "categories": ["Engineering", "Electrical / Electronics", "Engineering Project Management", "Mechanical"], "post_time": "2022-01-14T03:01:56Z", "salary": {"currency": null, "max": null, "min": null, "period": "monthly", "term": null}, "salary_visible": false, "title_keywords": ["assistant engineer"], "responsibilities": ["operations", "monitoring", "monitor", "tendering", "compliance", "drawings", "statutory requirements", "tender"], "requirements": {"degrees": ["diploma", "degree", "fresh graduate"], "majors": ["building services", "engineering"], "languages": ["english", "chinese"], "language_level": ["good command"], "hard_skills": ["autocad", "ms office"], "soft_skills": ["work independently", "under pressure", "communication", "coordination", "proactive"], "languages_combined": [{"language": "english", "language_level": ["good command"]}, {"language": "chinese", "language_level": ["good command"]}]}, "experience_required": {"duration": [], "field": []}}, {"job_id": "100003009051673", "location_code": "hk", "company": "Care For You Company Limited", "job_title": "Service Technician - Medical Equipment", "description": "Responsibilities:\u00a0\n\nProvide technical service support to hospitals, clinics and home patients, including equipment / system installation, repairing, regular preventive maintenance\nDiagnose problems and repair faulty devices\nOn-site trouble shooting, handle enquiries\nPromote products, services & sleep test for customers\n\n\u00a0Requirements:\u00a0\n\nDiploma in Electronics discipline or equivalent\nGood command in both written and spoken English/Cantonese\nSelf-motivated, good interpersonal skill\nOutgoing, pleasant & able to work independently", "employment_types": ["Full Time", "Permanent"], "selling_points": ["Technical support, repairing & promote products", "On-site trouble shooting & perform sleep test", "Self-motivated, pleasant & work independently"], "locations": ["Tsim Sha Tsui"], "categories": ["Engineering", "Electrical / Electronics", "Mechanical", "Medical Services", "Others"], "post_time": "2022-01-16T21:50:40Z", "salary": {"currency": null, "max": null, "min": null, "period": "monthly", "term": null}, "salary_visible": false, "title_keywords": ["technician"], "responsibilities": ["installation", "maintenance", "diagnose", "handle enquiries", "repair", "promote products"], "requirements": {"degrees": ["diploma"], "majors": [], "languages": ["cantonese", "english"], "language_level": ["good command"], "hard_skills": [], "soft_skills": ["outgoing", "self-motivated", "work independently", "pleasant", "interpersonal skill"], "languages_combined": [{"language": "cantonese", "language_level": ["good command"]}, {"language": "english", "language_level": ["good command"]}]}, "experience_required": {"duration": [], "field": []}}, {"job_id": "100003009050134", "location_code": "hk", "company": "Mitsubishi Elevator Hong Kong Company Limited", "job_title": "Assistant Engineer / Engineer \u2013 Technical Department (Welcome Fresh Graduate)", "description": "Ref.: AES13-JD20220103\n\nJob Description:\n\nSupport Sales activities and liaising with other departments to provide technical support such as technical study, traffic analysis and cage weight calculation;\nPreparation of order sheets (MSE) to factories to make order according to Sales specification and client\u2019s requirement in line with target dates;\nCheck the layout drawing according to Sales specification;\nOverall technical support on secured projects;\nCoordinate with factory and assist all EMSD model approval submission for new models and major equipment;\nProvide timely reports and updates on projects;\nOccasional business trip is required after pandemic.\n\nRequirements:\n\nDegree in Mechanical or Electrical Engineering or equivalent;\n1 year of relevant experience is preferable; Fresh graduate will also be considered;\nCandidate with more experience in lift and escalator industry will be considered for the position of Engineer;\nGood command of both spoken and written English and Chinese (including Mandarin);\nProficiency in MS Office Applications;\nKnowledge in BIM, AutoCAD, Visual Basic is an advantage;\nDynamic team player, initiative, conscientiousness and strong communication skills.\n\nWe offer 5-day work week and attractive remuneration package to the appointee.\n\nPlease apply with full resume stating the above job reference code, date available, present and expected salaries to Deputy Senior Manager, HR & Training Department, HMEC Group by clicking \"Apply Now\" or send to 36/F., Lee & Man Commercial Centre, 169 Electric Road, North Point or email to hr @hmecg.com.\n\nWe are an Equal Opportunities Employer. Personal data provided by applicants will be used strictly for recruitment purpose only and those of unsuccessful applicants will be destroyed after a period of three months from the submission date.\n\nWe are an environmental conscious company.\u00a0 Please join hands with us to protect the environment by sending your application via e-mail.\n\nWeb Site: http://www.hmecg.com", "employment_types": ["Full Time", "Permanent"], "selling_points": ["5-day work", "Welcome Fresh Graduate", "Technical Department"], "locations": ["North Point"], "categories": ["Engineering", "Electrical / Electronics", "Mechanical", "Others", "Student / Fresh Graduate / No Experience"], "post_time": "2022-01-14T09:50:19Z", "salary": {"currency": null, "max": null, "min": null, "period": "monthly", "term": null}, "salary_visible": false, "title_keywords": ["assistant engineer", "engineer"], "responsibilities": ["sales activities", "traffic analysis", "technical support", "technical study", "coordinate with", "liaising with", "occasional business trip", "timely reports", "cage weight calculation", "order sheets", "sales specification"], "requirements": {"degrees": ["degree", "fresh graduate"], "majors": ["electrical engineering"], "languages": ["english", "chinese", "mandarin"], "language_level": ["good command"], "hard_skills": ["bim", "dynamic", "visual basic", "ms office", "autocad"], "soft_skills": ["communication skills", "team player", "dynamic", "initiative"], "languages_combined": [{"language": "english", "language_level": ["good command"]}, {"language": "chinese", "language_level": ["good command"]}, {"language": "mandarin", "language_level": ["good command"]}]}, "experience_required": {"duration": ["1 year"], "field": ["relevant experience"]}}, {"job_id": "100003009051704", "location_code": "hk", "company": "ASM Technology Hong Kong Limited", "job_title": "Senior System Engineer/ System Engineer (R&D)", "description": "Job description\nGather system requirements, prepare technical specification and provide system design and solution suggestion\u00a0\nWork closely with technical leaders to deliver electrical system solution of products\nParticipate in multiple projects simultaneously\nJob requirements\nDegree or higher in Computer / Electrical / Electronic / Mechanical / Industrial / System Engineering or relevant disciplines\nKeen interest and ability in system integration, workflow standardization and staying abreast of new technology\nBasic knowledge in assembly & packaging equipment for semiconductor is an advantage\nGood command of Mandarin and English preferred\nCandidate with minimum 3 years\u2019 working experience in system integration or industrial controls will be considered as senior position\n\nAttractive salary and fringe benefits package will be offered to the right candidates.\nInterested parties please submit your application with cover letter, resume, certificate and transcripts.\nData collected will be used for recruitment purpose only. Suitable candidates may be referred to other vacancies within our company.", "employment_types": ["Full Time", "Permanent"], "selling_points": ["Degree in Computer / Engineering or relevant", "Participate in multiple projects simultaneously", "Fresh graduate are welcome"], "locations": ["Tsing Yi"], "categories": ["Engineering", "Electrical / Electronics", "Manufacturing & Production", "Mechanical"], "post_time": "2022-01-16T21:50:56Z", "salary": {"currency": null, "max": null, "min": null, "period": "monthly", "term": null}, "salary_visible": false, "title_keywords": ["system engineer", "senior system engineer"], "responsibilities": ["multiple projects", "system design"], "requirements": {"degrees": ["degree"], "majors": ["system engineering"], "languages": ["english", "mandarin"], "language_level": ["good command"], "hard_skills": ["integration", "basic"], "soft_skills": ["keen"], "languages_combined": [{"language": "english", "language_level": ["good command"]}, {"language": "mandarin", "language_level": ["good command"]}]}, "experience_required": {"duration": ["minimum 3 years"], "field": []}}, {"job_id": "100003009053250", "location_code": "hk", "company": "Tai Nam Industrial Co Ltd", "job_title": "Engineering Manager", "description": "Responsibilities:\n\nPlan and lead project from concept to production\nMonitor project progress and status\nDesign mechanism based on specification from customer\nLiaise with customers on design, cost, materials / components selection\nResponsible for product functionality and quality issues\nSupport sales teams in technical issue\nMaintain project development milestone on schedule\nDevelop and manage project plans and time lines within the scope of the new product development guidelines\nPlan, manage and control all project engineering processes for production and meet product safety standard\nSupervise Engineering Team\nCandidate with more experience will be considered as Senior Engineering Manager\n\nQualifications:\n\nDegree in Mechanical, Manufacturing Engineering or equivalent\nMinimum 5 yrs working experience in product development with at least\u00a02 yrs at management level\nExperience in Toys design and manufacturing process\nExcellent PC skills in MS Word and Excel\nProficiency in writing, fluent in spoken English and Mandarin\nGood interpersonal skill and able to communicate with customer\nWork and travel PRC frequently\n\nWe offer attractive remuneration package to the successful candidates. Interest parties, please send your application and full resume stating current and expected salary as well as date available to the Human Resources Department via email to HR Manager.\n\nWe are an equal opportunities employer. Personal data collected will be used for employment purpose only and all personal data of unsuccessful application will be destroyed within 6 months.", "employment_types": ["Full Time", "Permanent"], "selling_points": [], "locations": ["Kwai Fong"], "categories": ["Engineering", "Manufacturing & Production", "Mechanical", "Manufacturing", "Manufacturing Management"], "post_time": "2022-01-17T06:32:04Z", "salary": {"currency": null, "max": null, "min": null, "period": "monthly", "term": null}, "salary_visible": false, "title_keywords": ["engineering manager"], "responsibilities": ["communicate with", "cost", "control", "monitor project progress", "management", "guidelines", "quality", "teams", "design", "develop", "maintain", "schedule", "plan", "liaise with", "plans"], "requirements": {"degrees": ["degree"], "majors": ["manufacturing", "engineering"], "languages": ["english", "mandarin"], "language_level": ["proficiency", "fluent"], "hard_skills": ["excel", "pc skills", "ms word"], "soft_skills": ["responsible", "interpersonal skill"], "languages_combined": [{"language": "english", "language_level": ["proficiency", "fluent"]}, {"language": "mandarin", "language_level": ["proficiency", "fluent"]}]}, "experience_required": {"duration": [], "field": ["toys", "management", "manufacturing", "engineering", "design", "product development"]}}, {"job_id": "100003009055418", "location_code": "hk", "company": "Meinhardt (Hong Kong) Limited", "job_title": "Resident Building Services Inspectors (Ref: 21721T2)", "description": "Higher Diploma / Certificate in Electrical / Mechanical / Building Services Engineering, \u00a0or equivalent;\nMinimum 8 years post graduate experience in design and site supervision and minimum of 4 years post-qualification experience in the capacity of Resident Building Services Inspector, or equivalent;\nBe adaptable and able to work independently and have strong organization and communication skills and supervisory skills of technical / site staff; and\nGood command of both spoken and written English and Chinese.\n\nPlease send full resume with details of availability and last & expected salary (quoting reference) to:\n\nHuman Resources Manager\n\nMeinhardt Consulting Engineers\n\n10/F Genesis, 33-35 Wong Chuk Hang Road, Hong Kong\n\nOR click \u201cApply Now\u201d to submit your application \u00a0\u00a0\u00a0\u00a0\u00a0\u00a0\u00a0\u00a0\u00a0\u00a0\u00a0\u00a0http://www.meinhardtgroup.com\n\nData collected will be used for recruitment purpose only and will be destroyed within six months from date of application.", "employment_types": ["Full Time", "Contract"], "selling_points": [], "locations": ["Not Specified"], "categories": ["Building & Construction", "Building / Construction / QS", "Engineering", "Electrical / Electronics", "Mechanical"], "post_time": "2022-01-18T02:31:11Z", "salary": {"currency": null, "max": null, "min": null, "period": "monthly", "term": null}, "salary_visible": false, "title_keywords": [], "responsibilities": ["site supervision", "consulting", "data", "design", "communication", "recruitment"], "requirements": {"degrees": ["certificate", "diploma"], "majors": ["building services", "engineering"], "languages": ["english", "chinese"], "language_level": ["good command"], "hard_skills": [], "soft_skills": ["adaptable", "communication skills", "work independently"], "languages_combined": [{"language": "english", "language_level": ["good command"]}, {"language": "chinese", "language_level": ["good command"]}]}, "experience_required": {"duration": ["minimum 8 years", "minimum of 4 years"], "field": ["building services", "post-qualification", "design"]}}, {"job_id": "100003009052632", "location_code": "hk", "company": "Panda Hotel", "job_title": "Technician \u6280\u5de5", "description": "Responsibilities \u8077\u8cac:\n\nAlteration, repair & maintenance on all building services and equipment \u6539\u9020\u3001 \u7dad\u4fee\u53ca\u4fdd\u990a\u6240\u6709\u5c4b\u5b87\u8a2d\u5099\n\nRequirements \u8981\u6c42:\n\nDiploma of Secondary Education Examination or equivalent \u9999\u6e2f\u4e2d\u5b78\u6587\u6191\u8003\u8a66\u6216\u540c\u7b49\u5b78\u6b77\n2 year's relevant working experience 2\u5e74\u76f8\u95dc\u5de5\u4f5c\u7d93\u9a57\nHolder of\u00a0 Certificate of Registration of Electrical Workers (Grade A) \u9808\u6301\u6709\u96fb\u5de5A\u724c\n\nFringe Benefit \u54e1\u5de5\u798f\u5229:\n\nFree Duty Meal \u514d\u8cbb\u7576\u503c\u81b3\u98df\nMonthly Additional Day Off \u6bcf\u6708\u984d\u5916\u4f11\u606f\u65e5\n12 days Annual Leave 12\u5929\u6709\u85aa\u5e74\u5047\nBirthday Leave \u751f\u65e5\u5047\nMarriage Leave \u7d50\u5a5a\u5047\nFull Paid Paternity Leave \u5168\u85aa\u4f8d\u7522\u5047\nMedical Benefits (Outpatient and Hospitalization) \u91ab\u7642\u798f\u5229 (\u9580\u8a3a\u53ca\u4f4f\u9662)\nStaff Dining Privileges \u54e1\u5de5\u9910\u98f2\u6298\u6263\u512a\u60e0\nStaff Rates on Hotel Guest Room \u54e1\u5de5\u9152\u5e97\u5ba2\u623f\u6298\u6263\u512a\u60e0\nExternal Training Subsidy \u9032\u4fee\u88dc\u52a9\nDiscretionary Bonus \u5e74\u7d42\u914c\u60c5\u6027\u82b1\u7d05\n\nAs a family-friendly employer, we offer attractive remuneration package and fringe benefits to the right candidates. Interested parties can apply\u00a0with full resume and expected salary\u00a0to Human Resources & Training Department at email\u00a0 [via APPLY NOW] \u00a0", "employment_types": ["Full Time"], "selling_points": [], "locations": ["Tsuen Wan Area"], "categories": ["Engineering", "Mechanical", "Hospitality / F & B", "Others", "Others", "Technician"], "post_time": "2022-01-17T03:36:21Z", "salary": {"currency": null, "max": null, "min": null, "period": "monthly", "term": null}, "salary_visible": false, "title_keywords": ["technician", "\u6280\u5de5"], "responsibilities": ["repair", "maintenance"], "requirements": {"degrees": ["certificate", "diploma", "secondary education"], "majors": [], "languages": [], "language_level": [], "hard_skills": [], "soft_skills": [], "languages_combined": []}, "experience_required": {"duration": ["2 year"], "field": ["relevant working experience"]}}, {"job_id": "100003009053620", "location_code": "hk", "company": "Able Engineering Company Limited", "job_title": "Senior Building Services Inspector / (Assistant) Building Services Inspector", "description": "Diploma or Higher Certificate in Building Services or Electrical or Mechanical Engineering from a Hong Kong Polytechnic University / Polytechnic or Hong Kong Institute\u00a0 of Vocational Education / technical institute / technical college or equivalent;\nAttainment of\u00a0 'Level 2' or above in Chinese Language and English Language in HKDSE / HKCEE (Syllabus B);\nAt least 10 years relevant site experience including 6 years post qualification experience in the capacity of Building Services Inspector;\nCandidate with lesser experience will be considered as\u00a0 Building Services Inspector/ Assistant Building Services Inspector;\nWork on Construction Site in Hong Kong or Pre-fabrication Factory in PRC.\n\nWe offer competitive salary package and career development opportunity to the successful candidate. Interested parties may send your full resume, present and expected salary, available date and contact number by clicking \"Apply Now\"\n\nTo visit our website for more information:\u00a0www.ableeng.com.hk\n\n(As an Equal Opportunities Employer, Able is committed to eliminating discrimination in employment. The vacancy advertised is open to all applicants meeting the basic entry requirement irrespective of their disability, sex, marital status, pregnancy, age, family status, sexual orientation or race etc. Applicants not hearing from us within 6 months may consider their applications unsuccessful. Personal data collected will be used for recruitment related purposes only.)", "employment_types": ["Full Time"], "selling_points": [], "locations": ["Not Specified"], "categories": ["Building & Construction", "Building / Construction / QS", "Engineering", "Electrical / Electronics", "Mechanical"], "post_time": "2022-01-17T07:18:42Z", "salary": {"currency": null, "max": null, "min": null, "period": "monthly", "term": null}, "salary_visible": false, "title_keywords": ["building services inspector", "assistant"], "responsibilities": [], "requirements": {"degrees": ["diploma", "higher certificate", "hkdse"], "majors": ["building services", "mechanical engineering"], "languages": ["english", "chinese"], "language_level": [], "hard_skills": [], "soft_skills": [], "languages_combined": [{"language": "english", "language_level": []}, {"language": "chinese", "language_level": []}]}, "experience_required": {"duration": ["at least 10 years", "6 years"], "field": ["building services"]}}, {"job_id": "100003009050965", "location_code": "hk", "company": "ISS Facility Services Limited", "job_title": "Engineer / Assistant Engineer (HVAC or Building Service Projects) (Job Ref: ADV/22/018)", "description": "Responsibilities\n\nLiaise, communicate, and coordinate with clients/ contractors/ in-house technicians to perform daily work arrangement and on-site inspections to ensure the quality and progress of works,\nAssist in preparation of technical proposal, tender, and quotation relevant documents,\nMajor in maintenance and installation of Air Conditioning systems,\nHandle engineering problems in Building Service systems,\nParticipate in ad hoc projects or duties as assigned.\nRequirements\n\nDegree or Higher Diploma in Building Services Engineering, Electrical, Mechanical, or related discipline,\nPreferable with 3-years\u2019 relevant experience in E&M operation of air conditioning, mechanical and electrical facilities. Experience in sizable air-conditioning system will be an added advantage,\nFresh graduate will be considered as Assistant Engineer and Scheme \"A\" training programme accredited by the Hong Kong Institution of Engineers (HKIE) can be provided,\nStrong sense of accountability, result oriented and customer focused,\nImmediately available is preferred.\n(Candidates with less experience or fresh graduate from university will be considered for the post of ASSISTANT ENGINEER)\n\nWe offer professional development opportunities, attractive remuneration and fringe benefits to the right candidate. Interested parties please send a detailed resume, current / expected salary, contact number and the job reference no \u201cADV/22/018\u201d via \"Apply Now\".\n\nInformation provided by applicants will only be used for recruitment related purposes and will be handled confidentially by authorized personnel. All personal data of unsuccessful candidates will be destroyed after three months from the date of applications.", "employment_types": ["Full Time", "Permanent"], "selling_points": ["Liaise, communicate, and coordinate with clients", "Degree or Higher Diploma in Building Services", "With 3-years\u2019 relevant experience"], "locations": ["Not Specified"], "categories": ["Building & Construction", "Building / Construction / QS", "Engineering", "Electrical / Electronics", "Mechanical"], "post_time": "2022-01-14T12:08:46Z", "salary": {"currency": null, "max": null, "min": null, "period": "monthly", "term": null}, "salary_visible": false, "title_keywords": ["assistant engineer", "engineer"], "responsibilities": ["liaise", "installation", "maintenance", "quotation", "quality", "systems", "coordinate with clients", "ad hoc projects", "tender", "site inspections"], "requirements": {"degrees": ["diploma", "degree", "fresh graduate"], "majors": ["building services", "engineering"], "languages": [], "language_level": [], "hard_skills": ["the hong kong institution of engineers", "hkie", "scheme"], "soft_skills": ["result oriented", "focused", "accountability"], "languages_combined": []}, "experience_required": {"duration": [], "field": ["operation", "relevant experience", "air-conditioning"]}}, {"job_id": "100003009050574", "location_code": "hk", "company": "Lik Kai Engineering Company Limited", "job_title": "Maintenance Engineer \u2013 Fire Services (5-day work)", "description": "Job Responsibilities:\n\nProvide technical support of fire services maintenance to clients\nAssist in monitoring maintenance works and solving technical problems\nAssist on technical service enquiries, quotations, work orders and procurement\nAssist on execution of works, site supervision and commissioning\n\nJob Requirements:\n\nHolder of Higher Diploma in building services/mechanical/electrical/fire engineering or\u00a0equivalent\nAt least 3 years\u2019 relevant work experience\nGood command of both English and Chinese\nOutgoing, self-motivated and able to work independently\n\nCandidates with less experience will be considered as Assistant Maintenance Engineer\n\nWorking Location : Kwun Tong\n\n\nGood remuneration and attractive benefits will be offered to the right person. Interested parties please send full resume with expected salary via \"APPLY NOW\"\u00a0or by fax: 2611-4654 or by post to The Human Resources & Administration Department - Recruitment & Selection Section, Lik Kai Engineering Co., Ltd. 5th Floor, New East Sun Industrial Building, No. 18 Shing Yip Street, Kwun Tong, Kowloon.\n\nWe are an Equal Opportunity Employer. Personal data collected will be used for recruitment purpose only.", "employment_types": ["Full Time", "Permanent"], "selling_points": ["Holder of Higher Diploma in building services", "At least 3 years\u2019 relevant work experience", "Provide technical support"], "locations": ["Not Specified"], "categories": ["Engineering", "Engineering Project Management", "Mechanical", "Others"], "post_time": "2022-01-15T03:51:12Z", "salary": {"currency": null, "max": null, "min": null, "period": "monthly", "term": null}, "salary_visible": false, "title_keywords": ["engineer"], "responsibilities": ["commissioning", "site supervision", "maintenance", "technical support", "monitoring"], "requirements": {"degrees": ["diploma"], "majors": ["building services", "engineering"], "languages": ["english", "chinese"], "language_level": ["good command"], "hard_skills": ["maintenance"], "soft_skills": ["outgoing", "self-motivated", "work independently"], "languages_combined": [{"language": "english", "language_level": ["good command"]}, {"language": "chinese", "language_level": ["good command"]}]}, "experience_required": {"duration": ["at least 3 years"], "field": ["maintenance"]}}, {"job_id": "100003009052656", "location_code": "hk", "company": "Rise Associates Asia Limited", "job_title": "Senior Technical Services Manager / Technical Services Manager - Commercial Projects", "description": "About Client:\n\nOur client is a reputable property group with diversified property portfolio covers office buildings, retails malls and hotels in Hong Kong.\u00a0They are hiring a Senior Technical Services Manager to look after its commercial portfolio in Hong Kong.\u00a0\n\nJob Responsibilities:\n\n\u00a0\u00a0\u00a0\u00a0\u00a0\u00a0\u00a0\u00a0 Reporting to Executive member, the (senior) technical services manager will revise, review, and assist in developing project / renovation programmes and practice\n\u00a0\u00a0\u00a0\u00a0\u00a0\u00a0\u00a0\u00a0 Plan, implement and supervise fitting out/MEP/builder\u2019s renovation projects to comply with the latest statutory regulations and requirements\n\u00a0\u00a0\u00a0\u00a0\u00a0\u00a0\u00a0\u00a0 Review and monitor the performance of contractors, suppliers and technical team\n\u00a0\u00a0\u00a0\u00a0\u00a0\u00a0\u00a0\u00a0 Recommend, prepare and review preventive maintenance schedule as well as arrange and monitor the maintenance work for the designated property portfolio\n\u00a0\u00a0\u00a0\u00a0\u00a0\u00a0\u00a0\u00a0 Prepare annual maintenance budget, set up and review relevant operations policies and provide staff training\n\u00a0\u00a0\u00a0\u00a0\u00a0\u00a0\u00a0\u00a0 Handle enquiries and complaints about maintenance works and provide appropriate solutions after investigation\n\u00a0\u00a0\u00a0\u00a0\u00a0\u00a0\u00a0\u00a0 Supervise the performance of in-house technical staff\n\u00a0\u00a0\u00a0\u00a0\u00a0\u00a0\u00a0\u00a0 Liaise with relevant government authorities and public bodies\n\u00a0\u00a0\u00a0\u00a0\u00a0\u00a0\u00a0\u00a0 Lead or participate in other ad hoc tasks whenever necessary to satisfy the top manager\n\u00a0\u00a0\u00a0\u00a0\u00a0\u00a0\u00a0\u00a0 \u00a0Provide the roadmap for achieving value from physical assets by optimizing costs, risks and performance across the entire asset lifecycle.\n\nQualifications / Experiences\n\n\u00a0\u00a0\u00a0\u00a0\u00a0\u00a0\u00a0\u00a0 Degree in Building services, Building Surveying, Electrical Engineering, Electronic Engineering or Facilities Management, Operations Management\n\u00a0\u00a0\u00a0\u00a0\u00a0\u00a0\u00a0\u00a0 A member of HKIE, CIBSE is preferred\u00a0\n\u00a0\u00a0\u00a0\u00a0\u00a0\u00a0\u00a0\u00a0 \u00a012 years\u2019 experiences in related technical with at least 5 yeas in managing large scale operations in fitting out and renovation projects\n\u00a0\u00a0\u00a0\u00a0\u00a0\u00a0\u00a0\u00a0 Fluent in both written and spoken English and Chinese\n\u00a0\u00a0\u00a0\u00a0\u00a0\u00a0\u00a0\u00a0 Strong leadership and effective communication skill\n\u00a0\u00a0\u00a0\u00a0\u00a0\u00a0\u00a0\u00a0 Responsible, self-disciplined and able to work under pressure\n\u00a0\u00a0\u00a0\u00a0\u00a0\u00a0\u00a0\u00a0 Able to use Microsoft office software\n\u00a0 \u00a0 \u00a0 \u00a0 \u00a0Good Command in English and Chinese\u00a0", "employment_types": ["Full Time"], "selling_points": ["Retail and Commercial Portfolio", "Sizable organization", "Stable Career with Good Fringe Benefits"], "locations": ["Not Specified"], "categories": ["Engineering", "Electrical / Electronics", "Mechanical", "Property / Real Estate", "Property Consultancy"], "post_time": "2022-01-17T03:39:09Z", "salary": {"currency": null, "max": null, "min": null, "period": "monthly", "term": null}, "salary_visible": false, "title_keywords": ["manager"], "responsibilities": ["regulations", "software", "operations", "renovation", "budget", "communication", "plan", "liaise with", "costs", "work under pressure", "monitor", "developing", "handle enquiries and complaints", "schedule", "reporting", "management", "review", "ad hoc tasks", "investigation", "maintenance", "policies", "monitor the performance"], "requirements": {"degrees": ["degree"], "majors": ["building surveying", "building services", "electrical engineering", "engineering"], "languages": ["english", "chinese"], "language_level": ["good command", "fluent"], "hard_skills": ["facilities management", "hkie", "maintenance", "microsoft office software"], "soft_skills": ["communication skill", "leadership", "responsible", "work under pressure"], "languages_combined": [{"language": "english", "language_level": ["fluent", "good command"]}, {"language": "chinese", "language_level": ["fluent", "good command"]}]}, "experience_required": {"duration": ["12 years"], "field": ["related"]}}, {"job_id": "100003009051886", "location_code": "hk", "company": "Hong Kong Applied Science and Technology Research Institute Company Limited (ASTRI)", "job_title": "Optoelectronics Software - Lead Engineer", "description": "Reference #:\u00a0\u00a0CTO/IOTSEN/05\nJob Responsibilities\nDevelop the software and firmware, for process control, data collection and analysis of portable device with the optoelectronics module, optical sensing module, and acoustic sensing module\nWorking closely with the optoelectronics hardware team members to optimize the operation procedure of the device and to streamline the process flow for automations with computer aids\nWorking closely with the chemical sensing team members to construct customized databases for jewelry, food, environment, and health applications\nConstruction, evaluation, and interactive demonstration for the software development of the prototypes\nLiaison with external software suppliers and sub-contractors\nRequirements\nPh.D. holder or Master\u2019s degree in Physics, Mechanics, Electronics, Chemistry, Science, Engineering or relevant disciplines with a minimum of 3 years of related experience in the industry of Opto-electronics / Opto-mechatronics. Candidate with fewer experience may also be considered.\nFamiliar with R&D methodologies, design concepts and principles for the development of optical sensing device comprising optoelectronics modules\nFamiliar with computer programming languages, e.g., Python, C, C++, C#, Labview, etc. for both device control and data processing\nHands-on experience in constructing the software and firmware of the portable device with the optoelectronics modules\nPractical knowledge in the development of portable optoelectronics devices for food, environment, and health applications\nKnowledge in simulation tools, e.g., Matlab, COMSOL, AutoCAD, L-edit, Chem3D, is a plus\nFluent in English and be able to work as part of a team\nLive the ASTRI values\nApplication\n\nThe appointment will be on renewable contract terms with a competitive salary and performance-linked variable pay. Fringe benefits include paid leave, medical and dental benefits, insurance coverage and contribution to MPF. The incumbent will normally work\u00a0a five-day week.\n\nInterested candidates, please send an application (quoting Ref. No.) with a detailed resume, current and expected salary to\u00a0Talent Acquisition by clicking \"APPLY NOW\".\u00a0The resume should\u00a0not\u00a0include any sensitive personal information such as HKID or passport number, photo, etc.\u00a0\n\nPosition offer is subject to the applicant\u2019s experience and academic qualification. The application will be open until the position is filled. Only short-listed candidates will be notified. ASTRI reserves the right not to fill the position.\n\nASTRI is an Equal Opportunities Employer. Personal data provided by job applicants will be used\u00a0exclusively\u00a0for recruitment\u00a0only. For details, please refer to\u00a0Privacy - ASTRI - Hong Kong Applied Science and Technology Research Institute Company Limited, in particular section 9.", "employment_types": ["Full Time", "Contract"], "selling_points": ["Optoelectronics Software", "Technology Research and Development", "Develop the software and firmware"], "locations": ["Shatin Area"], "categories": ["Engineering", "Mechanical", "Information Technology (IT)", "Application Specialist - Software", "Sciences, Lab, R&D", "Research & Development (R&D)"], "post_time": "2022-01-17T01:27:06Z", "salary": {"currency": null, "max": null, "min": null, "period": "monthly", "term": null}, "salary_visible": false, "title_keywords": ["engineer", "lead"], "responsibilities": ["control", "evaluation", "software", "analysis", "develop", "hardware", "data collection", "databases"], "requirements": {"degrees": ["degree", "master"], "majors": ["science", "chemistry", "engineering", "physics"], "languages": ["english"], "language_level": ["fluent"], "hard_skills": ["r&d", "plus", "c++", "portable", "c", "autocad", "programming", "matlab", "python", "processing", "labview", "c#"], "soft_skills": ["hands-on"], "languages_combined": [{"language": "english", "language_level": ["fluent"]}]}, "experience_required": {"duration": ["minimum of 3 years"], "field": ["related", "engineering"]}}, {"job_id": "100003009052802", "location_code": "hk", "company": "Saint Honore Cake Shop Limited", "job_title": "\u51b7\u51cd\u8a2d\u5099\u7dad\u4fee\u54e1**", "description": "\u8077\u8cac :\u8ca0\u8cac\u8655\u7406\u98df\u54c1\u5ee0\u623f\u51b7\u51cd\u8a2d\u65bd\u548c\u8a2d\u5099\u7684\u4fdd\u990a\u53ca\u7dad\u4fee\u5de5\u4f5c\n\u8cc7\u6b77 :\u6c92\u6709\u5b78\u6b77\u8981\u6c42; 3\u5e74\u7d93\u9a57; \u4e00\u822c\u7cb5\u8a9e; \u61c2\u95b1\u8b80\u4e2d\u6587; \u6301\u6709\u96fb\u5de5R\u724c; \u61c2\u8655\u7406\u51b7\u51dd, \u7a7a\u8abf; \u51773\u5e74\u4ee5\u4e0a\u5ee0\u623f\u7dad\u4fee\u6216\u96ea\u623f\u4fdd\u990a\u7dad\u4fee\u76f8\u95dc\u7d93\u9a57\n\u5f85\u9047 :\u6bcf\u6708$20,000\u6216\u4ee5\u4e0a(\u8996\u4e4e\u7d93\u9a57\u800c\u5b9a), \u6709\u914c\u60c5\u6027\u82b1\u7d05, \u54e1\u5de5\u8cfc\u7269\u512a\u60e0, \u91ab\u7642\u798f\u5229, \u81b3\u98df\u6d25\u8cbc \u53ca\u8d85\u6642\u5de5\u4f5c\u6d25\u8cbc, \u4e0a\u53488\u6642\u534a\u81f3\u4e0b\u53485\u6642\u534a, \u6bcf\u9031\u5de5\u4f5c6\u5929,\u8f2a\u4f11, \u6bcf\u67085\u5929\u4f8b\u5047\n\u7533\u8acb\u9808\u77e5 :\u6c42\u8077\u8005\u53ef\u81f4\u96fb29916680\u8207\u8056\u5b89\u5a1c\u9905\u5c4b\u6709\u9650\u516c\u53f8\u9673\u5c0f\u59d0\u806f\u7d61\u3002\n\u5099\u8a3b :** \u50f1\u4e3b\u53ef\u5c31\u6b64\u8077\u4f4d\u7a7a\u7f3a\u7533\u8acb\u53c3\u52a0\u300c\u4e2d\u9ad8\u9f61\u5c31\u696d\u8a08\u5283\u300d\uff0c\u6b61\u8fce\u4e2d\u9ad8\u9f61\u6c42\u8077\u4eba\u58eb\u61c9\u5fb5\u3002", "employment_types": ["Full Time"], "selling_points": [], "locations": ["Kwai Tsing Area"], "categories": ["Engineering", "Mechanical", "Others", "Technician"], "post_time": "2022-01-17T04:06:57Z", "salary": {"currency": null, "max": null, "min": null, "period": "monthly", "term": null}, "salary_visible": false, "title_keywords": [], "responsibilities": [], "requirements": {"degrees": [], "majors": [], "languages": [], "language_level": [], "hard_skills": [], "soft_skills": [], "languages_combined": []}, "experience_required": {"duration": [], "field": []}}, {"job_id": "100003009050546", "location_code": "hk", "company": "Lik Kai Engineering Company Limited", "job_title": "Assistant Project Manager / Senior Engineer / Engineer ( Plumbing & Drainage) (5-day work)", "description": "Job Responsibilities:\n\nAssist Project Manager in P&D project execution, tender estimation, system installation,\u00a0testing & commissioning\nLiaise and communicate with client, architect, consultant, main contractor and others\nSupervise Plumbing & Drainage project\nPrepare tenders, job budget, drawing and equipment submission for project and A&A works\n\nJob Requirements:\n\nHolder of Degree / Higher Diploma in Building Services / Mechanical or equivalent\nAt least 4 years of proven experience in project execution\nHolder of Plumber\u2019s License is preferred\nGood command of both English and Chinese\nComputer literacy in AutoCAD\n\nGood remuneration and attractive benefits will be offered to the right person. Interested parties please send full resume with expected salary via \"APPLY NOW\"\u00a0or by fax: 2611-4654 or by post to The Human Resources & Administration Department - Recruitment & Selection Section, Lik Kai Engineering Co., Ltd. 5th Floor, New East Sun Industrial Building, No. 18 Shing Yip Street, Kwun Tong, Kowloon.\n\nWe are an Equal Opportunity Employer. Personal data collected will be used for recruitment purpose only.", "employment_types": ["Full Time", "Permanent"], "selling_points": ["Degree / Higher Diploma in Building Services", "At least 4 years of proven experience", "Assist Project Manager in P&D project execution"], "locations": ["Not Specified"], "categories": ["Building & Construction", "Building / Construction / QS", "Engineering", "Engineering Project Management", "Mechanical"], "post_time": "2022-01-15T03:51:11Z", "salary": {"currency": null, "max": null, "min": null, "period": "monthly", "term": null}, "salary_visible": false, "title_keywords": ["assistant project manager", "engineer", "senior engineer"], "responsibilities": ["liaise", "installation", "communicate with client", "commissioning", "budget", "testing", "tender"], "requirements": {"degrees": ["diploma", "degree"], "majors": ["building services"], "languages": ["english", "chinese"], "language_level": ["good command"], "hard_skills": ["autocad"], "soft_skills": ["computer literacy"], "languages_combined": [{"language": "english", "language_level": ["good command"]}, {"language": "chinese", "language_level": ["good command"]}]}, "experience_required": {"duration": ["at least 4 years"], "field": []}}, {"job_id": "100003009050225", "location_code": "hk", "company": "Sun Vigor Printing Company Limited", "job_title": "Project Engineer", "description": "~ Higher Diploma / Degree in Electronic / Mechanical / Manufacturing or equivalent\n\n~ 1-2 year(s) experience in toys engineering field\n\n\u00a0 \u00a0Fresh graduate will be also considered\n\n~ Experienced in engineering new products to comply with all required quality, safety and certification requirements (e.g. CE, FCC, RoHS, Phthalate, CPSIA, etc.)\n\n~ Cost estimation and quote preparation.\n\n~ Hand on R & D & Manufacturing experience is preferable\n\n~ Proven ability to write engineering spec;\u00a0\n\n~ Good interpersonal and project management skills and details-minded\n\n~ Travel to South PRC occasionally is required\u00a0\n\n~ Good command of both written and spoken English and Chinese (Cantonese and Putonghua)", "employment_types": ["Full Time", "Permanent"], "selling_points": ["Higher Diploma/Degree", "1-2 year(s) experience", "toy manufacturing"], "locations": ["Kowloon Bay"], "categories": ["Engineering", "Electrical / Electronics", "Manufacturing & Production", "Mechanical"], "post_time": "2022-01-14T10:01:07Z", "salary": {"currency": null, "max": null, "min": null, "period": "monthly", "term": null}, "salary_visible": false, "title_keywords": ["project engineer"], "responsibilities": ["project management", "quality", "cost estimation"], "requirements": {"degrees": ["diploma", "degree", "fresh graduate"], "majors": ["manufacturing"], "languages": ["cantonese", "putonghua", "english", "chinese"], "language_level": ["good command"], "hard_skills": ["r", "project management"], "soft_skills": ["project management skills", "interpersonal"], "languages_combined": [{"language": "cantonese", "language_level": ["good command"]}, {"language": "putonghua", "language_level": ["good command"]}, {"language": "english", "language_level": ["good command"]}, {"language": "chinese", "language_level": ["good command"]}]}, "experience_required": {"duration": [], "field": ["toys", "manufacturing", "engineering"]}}, {"job_id": "100003009054504", "location_code": "hk", "company": "Keio Engineering Co Ltd", "job_title": "Quantity Surveyor", "description": "To meet the rapid business expansion, we are looking for an additional new headcount of the QS talents to join our QS team. You will involve the entire tender management from evaluation to arrive the bid decisions and the cost management.\u00a0\u00a0\u00a0\n\nWhat we look for?\n\nExecute the cost estimation, cost control and analysis to reach the cost efficiency;\nPricing and estimate the cost of different material needed for the E&M projects;\nResponsible for the tender analysis & risk assessment and provide effective solution;\nPrepare and ensure tender documents and technical documentations are properly; complied with company policy and standard for tender document submission;\nLiaise with clients, or main contractors, or sub-contractors, or government regularly on tender documents, and attend tender meetings;\nDeliver the final account settlement;\nCoordinate and communicate with internal or external stakeholders.\n\nWhat you need to succeed?\n\nHigher Diploma/ Degree holder in Quantity Surveying, Engineering or Building Services Engineering;\nAt least\u00a04\u00a0years\u2019\u00a0relevant experience in E&M or Building Services industry;\nExperience in tendering, budgeting and cost control management is an advantage;\nStrong analytical mind, independent and a proactive team player;\nGood command of both written and spoken in Chinese and English.\n\nWhat we offer?\n\nStable and friendly work environment\nOpen office design\nAnnual leave\nMedical insurance\nEducation subsidy\nYear-end double pay\nDiscretionary bonus\nExcellent career development\nUnlimited beverages and snacks\nInternal and external training programme\nOn-job training\n\nInterested parties, please send your detailed resume with expected salary via \u201cApply Now\u201d for our consideration", "employment_types": ["Full Time", "Permanent"], "selling_points": ["E&M or Building Services industry", "Tendering, budgeting and cost control management", "Quantity Surveying"], "locations": ["Sai Wan"], "categories": ["Building & Construction", "Building / Construction / QS", "Engineering", "Engineering Project Management", "Mechanical"], "post_time": "2022-01-17T09:53:49Z", "salary": {"currency": null, "max": null, "min": null, "period": "monthly", "term": null}, "salary_visible": false, "title_keywords": ["quantity surveyor"], "responsibilities": ["liaise with clients", "communicate with", "cost", "management", "cost estimation", "tender documents", "budgeting", "analysis", "tendering", "tender analysis", "coordinate", "tender", "evaluation", "cost control", "tender document"], "requirements": {"degrees": ["diploma", "degree holder"], "majors": ["building services", "engineering", "surveying"], "languages": ["english", "chinese"], "language_level": ["good command"], "hard_skills": ["analysis", "documentations", "rapid"], "soft_skills": ["independent", "responsible", "analytical mind", "team player", "proactive"], "languages_combined": [{"language": "english", "language_level": ["good command"]}, {"language": "chinese", "language_level": ["good command"]}]}, "experience_required": {"duration": ["at least 4 years"], "field": ["building services", "management", "relevant experience"]}}, {"job_id": "100003009049081", "location_code": "hk", "company": "TalentQuest HR Limited", "job_title": "Mechanical Engineer / Senior Mechanical Engineer (Up to 55k)", "description": "Responsibilities\nSubmit relevant safety test and examination forms to EMSD as required by current codes and regulations\nConduct safety tests and monitor the work progress to meet statutory requirements and\u00a0in line with the company's procedures\nEnsure the test/examinations are processed in compliance with issued quality procedures and instructions\u00a0\nRequirements\nQualified Registered Lift/Escalator Engineer\nAt least 8\u00a0years\u2019 experience\u00a0in the installation, commissioning, testing and maintenance of lifts/escalators\nHighly initiative with excellent leadership skills\nStrong understanding of health & safety procedures\n\n\n\nWe offer remuneration package including attractive salary, comprehensive fringe benefits and excellent opportunities for the right candidate.\u00a0(*** Employee Scholar Program\u00a0up to $160,000/ person for each degree***)\n\nWebsite:\u00a0http://www.expresslift.com.hk\n\nInformation provided by applicants will be treated in strict confidence and will only be used for recruitment related purposes. All information on unsuccessful candidates will be deleted from our files within 24 months.", "employment_types": ["Full Time"], "selling_points": ["Building Services / Mechanical Engineering", "13 - 16 months Salary", "Good Project Reference"], "locations": ["Not Specified"], "categories": ["Engineering", "Electrical / Electronics", "Engineering Project Management", "Mechanical"], "post_time": "2022-01-14T08:04:56Z", "salary": {"currency": null, "max": null, "min": null, "period": "monthly", "term": null}, "salary_visible": false, "title_keywords": ["senior mechanical engineer", "mechanical engineer"], "responsibilities": ["regulations", "compliance", "monitor", "procedures", "quality", "statutory requirements"], "requirements": {"degrees": [], "majors": [], "languages": [], "language_level": [], "hard_skills": ["maintenance"], "soft_skills": ["leadership skills", "initiative"], "languages_combined": []}, "experience_required": {"duration": ["at least 8 years"], "field": ["installation", "maintenance", "testing"]}}, {"job_id": "100003009050116", "location_code": "hk", "company": "ATAL Engineering Ltd", "job_title": "(Senior/ Project) Engineer - Electrical/ HVAC/ BS/ Mechanical/ P&D/ Fire (REF: ADC/BS/SP/E)", "description": "Highe Diploma or above in Electrical, Mechanical, Building Services Engineering or related discipline.\nMinimum 3 years relevant working experience in any Electrical, HVAC or MVAC\nWorked in E&M Contractors is an advantage\nExperience in site coordination, supervision and submissions\nCandidate with less experience will be considered as Assistant Engineer\n\nFor application, please click \"APPLY NOW\" or WhatsApp CV to +852 3752\u00a08881\n\n\u00a0Please visit our website for more job openings\u00a0\nhttp://awclhk.com/job-opportunities/", "employment_types": ["Full Time", "Permanent"], "selling_points": ["(Senior / Project) Engineer", "Good command in English & Chinese", "Immediately available is preferred"], "locations": ["Not Specified"], "categories": ["Engineering", "Electrical / Electronics", "Engineering Project Management", "Mechanical"], "post_time": "2022-01-15T03:50:50Z", "salary": {"currency": null, "max": null, "min": null, "period": "monthly", "term": null}, "salary_visible": false, "title_keywords": ["engineer"], "responsibilities": ["site coordination", "website"], "requirements": {"degrees": ["diploma or above"], "majors": ["building services", "engineering"], "languages": [], "language_level": [], "hard_skills": ["hvac", "whatsapp"], "soft_skills": ["coordination"], "languages_combined": []}, "experience_required": {"duration": ["minimum 3 years"], "field": ["relevant working experience"]}}, {"job_id": "100003009034643", "location_code": "hk", "company": "S.H.K. Real Estate Management Company Limited", "job_title": "\u9ad8\u7d1a\u6280\u8853\u54e1/ \u6280\u8853\u54e1- \u6a5f\u96fb/\u51b7\u6c23/\u6c34\u5589 (5.5\u59299\u5c0f\u6642 / \u8f2a\u73ed)", "description": "Responsibilities\n\nPreparation of tender and job budget;\nPerform project planning and site supervision for\u00a0Fire Services\u00a0and Plumbing & Drainage works;\nCoordinate with clients, main contractors, consultants and sub-contractors;\nPreparation of drawings and equipment preparation and submission\n\nRequirements\n\nDegree in Building Services, Fire Engineering or related Discipline;\nAt least 3 years relevant experience in Fire\u00a0Services\u00a0and\u00a0Plumbing & Drainage works;\nProficient in using AutoCAD and MS Applications, Excel, Word etc.;\nGood command of both spoken and written English and Chinese;\nExcellent interpersonal skills with proactive and positive attitude\n\nBenefits and Package:\n\n13 days annual leave\nPublic holidays\nMedical Insurance (Out-patient, Hospitalization\u00a0and Dental coverage)\nLife insurance\nEducation subsidy / Sponsorship\nTravelling allowance\nFull pay Exam leave, marriage leave, compassionate leave\nStaff recreation club etc.\n\nAttractive remuneration package will be offered to the successful candidate\n\n\nPlease send in strict confidence with full resume stating the reference code and your current and expected salary to Human Resources Department, REC Engineering Company Limited, Units A-D, 15/F., Goodman Kwai Chung Logistics Centre, 585-609 Castle Peak Road, Kwai Chung, New Territories, Hong Kong or by\u00a0fax 2489 0044 or clicking \u201cApply Now\u201d button to apply.\n(Personal data provided\u00a0by applicants will be used strictly for recruitment purpose only.)", "employment_types": ["Full Time", "Permanent"], "selling_points": ["\u8ca0\u8cac\u5546\u696d\u5927\u5ec8\u51b7\u6c23\u6216\u6a5f\u96fb\u7dad\u4fee\u53ca\u4fdd\u990a", "\u521d\u4e2d\u7a0b\u5ea6\uff0c\u5177\u76f8\u95dc\u5de5\u7a0b\u7d93\u9a57\u53ca\u8b49\u66f8\u66f4\u4f73", "9\u5c0f\u6642\u8f2a\u73ed\u5de5\u4f5c"], "locations": ["Not Specified"], "categories": ["Engineering", "Mechanical", "Others", "Property / Real Estate", "Others"], "post_time": "2022-01-16T21:50:09Z", "salary": {"currency": null, "max": null, "min": null, "period": "monthly", "term": null}, "salary_visible": false, "title_keywords": ["\u6280\u8853\u54e1"], "responsibilities": ["project planning", "site supervision", "budget", "drawings", "coordinate with clients", "tender"], "requirements": {"degrees": ["degree"], "majors": ["building services", "engineering"], "languages": ["english", "chinese"], "language_level": ["good command"], "hard_skills": ["excel", "ms applications", "word", "autocad"], "soft_skills": ["positive attitude", "proactive", "interpersonal skills"], "languages_combined": [{"language": "english", "language_level": ["good command"]}, {"language": "chinese", "language_level": ["good command"]}]}, "experience_required": {"duration": ["at least 3 years"], "field": ["plumbing", "relevant experience", "drainage"]}}, {"job_id": "100003009047411", "location_code": "hk", "company": "Shun Cheong Electrical Engineering Co Ltd", "job_title": "Engineer (BSE/FS/ELL/ELV/ME)", "description": "What you will do:\n\nResponsible for owning the project management process and methodology acting as the gatekeeper to the production environment, while ensuring a smooth delivery of planned system implementation.\nLiaise with Asia business units and development resources on eCommerce management system improvements and implementation\nEngage with technical, business and stakeholders in business units to ensure BU is fully on-board and deployment readiness.\nManage project implementation end-to-end (i.e., requirements gathering, change documentation, and creation of release notes) and ensure smooth and timely communication among stakeholders.\nKeep abreast of market knowledge and to recommend process improvement and streamlining to identify the best practice\n\nRequirement:\n\nRelevant Bachelor degree or higher diploma, preferably in Business, Information Systems, Computer Science or IT related discipline\nExperience in implementation or support of eCommerce platform, or any other digital services such as website and mobile applications\nStrong logical mind with data manipulation skill like Excel/SQL tools\nSound knowledge in retail systems, and eCommerce digital application systems\nPassionate about Digital or E-commerce trends\nAbility to work in a fast-paced environment with a must-do attitude to deliver the best quality of work and provide account management services\nExcellent analytical, planning, and presentation skills\nExcellent written and verbal communication skills, fluent in both Cantonese and English, Mandarin is a plus\nCandidate with less experience will be considered as Assistant Business Analyst", "employment_types": ["Full Time", "Permanent"], "selling_points": ["BEng / H.Dip in BSE, EE, ME & etc.", "Overall project operations & co-ordination", "Double Pay, Bonus, Medical and more"], "locations": ["Lai Chi Kok"], "categories": ["Engineering", "Electrical / Electronics", "Engineering Project Management", "Mechanical"], "post_time": "2022-01-14T03:01:30Z", "salary": {"currency": null, "max": null, "min": null, "period": "monthly", "term": null}, "salary_visible": false, "title_keywords": ["engineer"], "responsibilities": ["manipulation", "management", "documentation", "data", "system improvements", "systems", "quality", "implementation", "website", "communication", "project management", "liaise with", "application systems", "planning"], "requirements": {"degrees": ["diploma", "degree", "bachelor"], "majors": ["business", "it", "computer science"], "languages": ["cantonese", "english", "mandarin"], "language_level": ["excellent", "fluent"], "hard_skills": ["excel", "plus", "documentation", "e-commerce", "sql", "project management", "mobile", "deployment", "system implementation", "data manipulation"], "soft_skills": ["communication skills", "responsible", "fast-paced environment", "timely", "communication", "project management", "presentation skills", "smooth", "passionate about"], "languages_combined": [{"language": "cantonese", "language_level": ["fluent", "excellent"]}, {"language": "english", "language_level": ["fluent", "excellent"]}, {"language": "mandarin", "language_level": ["excellent"]}]}, "experience_required": {"duration": [], "field": ["ecommerce", "digital", "business"]}}, {"job_id": "100003009050385", "location_code": "hk", "company": "SGS Hong Kong Limited", "job_title": "\u6a5f\u5668\u5de5\u5834\u6280\u8853\u54e1", "description": "Our client is one\u00a0of the fastest growing cryptocurrency exchanges, with more than 3 million registered users.\u00a0\n\n\n\nJob Description\n\nCollaborate with senior leadership to understand the organizations goals and strategy related to staffing, recruiting, Compensation & Benefits and retention.\u00a0\nWork directly with business stakeholders and provide HRBP service including recruitment, employee relations, talent review, remuneration review, performance management, talent development etc.\nBe one of the driver on change and transformation initiatives,such as HRIS implementation project, etc.\nIdentify and implement employee engagement opportunities and activities to build and sustain a positive and productive workforce\nImplement and review HR policies and procedures to support the Company\u2019s needs\n\nJob Requirements\n\nBachelor\u2019s degree in HR, Business Management or related disciplines\n6+ years\u2019\u00a0solid experience in Human Resources management and HRIS\nFamiliar with Hong Kong Employment ordinance\nResponsible, agile, adaptive to changes and resilient\nGood command of both spoken and written English and Chinese, including Mandarin\nProficiency in MS Office applications, particularly Excel", "employment_types": ["Full Time", "Permanent"], "selling_points": ["\u7121\u9808\u7d93\u9a57, \u5b8c\u5584\u798f\u5229", "\u6bcf\u9031\u5de5\u4f5c6\u5929", "\u6a5f\u5668\u8a2d\u5099\u7dad\u4fee"], "locations": ["Yuen Long"], "categories": ["Engineering", "Mechanical"], "post_time": "2022-01-15T03:51:04Z", "salary": {"currency": null, "max": null, "min": null, "period": "monthly", "term": null}, "salary_visible": false, "title_keywords": [], "responsibilities": ["collaborate with", "management", "policies", "hr", "review", "procedures", "implementation", "recruitment"], "requirements": {"degrees": ["degree", "bachelor"], "majors": ["related disciplines", "business"], "languages": ["english", "chinese", "mandarin"], "language_level": ["good command"], "hard_skills": ["business management", "excel", "hong kong employment ordinance", "agile", "ms office"], "soft_skills": ["agile", "responsible"], "languages_combined": [{"language": "english", "language_level": ["good command"]}, {"language": "chinese", "language_level": ["good command"]}, {"language": "mandarin", "language_level": ["good command"]}]}, "experience_required": {"duration": ["6+ years"], "field": ["management", "human resources"]}}, {"job_id": "100003009042249", "location_code": "hk", "company": "Manlink Personnel Consultants Limited", "job_title": "Head of Operation - Environmental Engineering", "description": "Are you passionate in joining a dynamic, creative & energetic team?\u00a0\nDo you want to work as an entrepreneur?\n\nWe are recruiting new members joining our Consulting\u00a0Team for our Hong Kong Office.\u00a0 \u00a0\u00a0\u00a0\n\nDegree in Business Administration, HR Management, IT or relevant disciplines\u00a0\n1-3 years of recruitment or sales & marketing experience\u00a0\nPassionate in people-oriented job tasks\u00a0\u00a0\nPro-active, sales-orientated, adaptable, eager to learn and target-driven\nGood interpersonal & communication skill\nAn effective change agent, a good team player\u00a0\nGood command of spoken & written English and Chinese\nIf you want to learn more about our company profile, our vision as well as the details of the position, please feel free contacting us immediately.\u00a0 We are looking forward to receiving your application.\u00a0 \u00a0\n\n\n\nPersonal data provided by job applicants will be used strictly in accordance with the employer's personal data policies and for recruitment purposes only.", "employment_types": ["Full Time", "Permanent"], "selling_points": ["MHKIE/MIMechE", "E&M contractors\u2019 experience in DSD/WSD projects", "Passion in Environmental Engineering"], "locations": ["Not Specified"], "categories": ["Engineering", "Engineering Project Management", "Mechanical"], "post_time": "2022-01-15T03:49:14Z", "salary": {"currency": null, "max": null, "min": null, "period": "monthly", "term": null}, "salary_visible": false, "title_keywords": [], "responsibilities": ["management", "consulting", "policies", "hr", "communication", "recruitment", "personal data", "administration"], "requirements": {"degrees": ["degree"], "majors": ["it", "business administration"], "languages": ["english", "chinese"], "language_level": ["good command"], "hard_skills": ["dynamic"], "soft_skills": ["passionate", "good team player", "creative", "interpersonal", "adaptable", "communication skill", "eager to learn", "dynamic", "people-oriented", "pro-active", "energetic", "driven"], "languages_combined": [{"language": "english", "language_level": ["good command"]}, {"language": "chinese", "language_level": ["good command"]}]}, "experience_required": {"duration": ["1-3 years"], "field": ["marketing", "recruitment"]}}, {"job_id": "100003009046934", "location_code": "hk", "company": "Wing Tai Properties Estate Management Limited", "job_title": "Engineer", "description": "Our client is an Europe client with solid global brand name. As the new product is planning to launch, they are looking for few experienced UI/UX Designers to join the team.\n\nResponsibilities\n\nResponsible for the UX/UI design output\nUnderstand the global branding philosophy and user experience and behavior\nResearch and evaluate the new and innovative technologies\nCreate the UX/UI for digital application with Adobe xD\nWork closely with the project team and our clients to optimize the workflow\nCreaton of UI concepts, prototypes, user interfaces and documentation of UI guidelines\nCollaborate with the local teams and HQ if required\nRequirements\u00a0\n\nBachelor degree in digital design or any relevant discipline\u00a0\nMinimum 3 years of hands on UX/UI design experience and work with Agile development team\nHave proven record on driving the product through concept, wire framing and visual phases\nHave practical experience in working on responsive web design projects and passionate about digital trends\u00a0 and website technologies with cross-device applications knowledge\u00a0\nExperience in using the design tools like Sketch, InVision, Zepplin, Adobe Photoshop, Adobe xD etc.\u00a0\nHave programming experience in C/C#,Java, JavaScript, HTML and CSS is an advantage\nDetail-minded to handle the design process and UX/UI design including usability evaluation, user cases, user scenarios, user journeys etc.\nStrong presentation skills is needed to present the ideas with clear concepts\nCreative, innovative, logical thinking, problem solving skills, team player with good communication skills\nExcellent language communication in both English and Cantonese\nPersonal data provided by job applicants will be used strictly in accordance with the employer's personal data policies and for recruitment purposes only.", "employment_types": ["Full Time", "Permanent"], "selling_points": ["Certificate of Registration of Electrical Worker", "Building Services", "Minimum 5 years"], "locations": ["Kwun Tong"], "categories": ["Engineering", "Engineering Project Management", "Mechanical", "Property / Real Estate", "Property Management"], "post_time": "2022-01-14T01:47:55Z", "salary": {"currency": null, "max": null, "min": null, "period": "monthly", "term": null}, "salary_visible": false, "title_keywords": ["engineer"], "responsibilities": ["collaborate with", "guidelines", "teams", "user experience", "design", "evaluate", "documentation", "ui"], "requirements": {"degrees": ["degree", "bachelor"], "majors": ["design"], "languages": ["cantonese", "english"], "language_level": ["excellent"], "hard_skills": ["web design", "agile", "adobe xd", "adobe photoshop", "html", "c", "javascript", "programming", "css", "problem solving skills"], "soft_skills": ["detail-minded", "communication skills", "agile", "innovative", "clear", "communication", "presentation skills", "hands on", "team player", "problem solving skills", "creative", "responsive", "passionate about"], "languages_combined": [{"language": "cantonese", "language_level": ["excellent"]}, {"language": "english", "language_level": ["excellent"]}]}, "experience_required": {"duration": ["minimum 3 years"], "field": ["development", "design", "programming", "digital", "team"]}}, {"job_id": "100003009048030", "location_code": "hk", "company": "REC Green Technologies Company Limited", "job_title": "Senior Engineer(Ref. SE/22/0043)", "description": "Responsibilities:\n\nTo be responsible for project design and development submission preparation and implementation of mechanical vehicle parking system projects and other sustainability system;\nTo provide on-site engineering supports, monitoring and follow-up the site progress;\nTo control the work quality in accordance with the requirements stipulated in the technical specifications and statutory requirements;\nCandidates with experience in mechanical system design or material handling system will be an advantage.\n\nRequirements:\n\nHigher Diploma or above in Mechanical, Building Services, Electrical Engineering or related discipline;\n5 years relevant experience in Mechanical Engineering Project;\nProficiency in Microsoft Office and AutoCAD;\nGood command of both written and spoken English and Chinese;\n\nBenefits and Package:\n\n13 days annual leave\nPublic holidays\nMedical Insurance (Out-patient, Hospitalization\u00a0and Dental coverage)\nLife insurance\nEducation subsidy / Sponsorship\nTravelling allowance\nFull pay Exam leave, marriage leave, compassionate leave\nStaff recreation club etc.\n\n\n\n\u00a0Less experience will be considered Engineer / Technical Engineer\n\n\u00a0Attractive remuneration package will be offered to the successful candidates.\u00a0Please send in strict confidence with full resume stating the reference code and your current and expected salary to Human Resources Department, REC Engineering Company Limited, Units A-D, 15/F., Goodman Kwai Chung Logistics Centre, 585-609 Castle Peak Road, Kwai Chung, New Territories, Hong Kong or\u00a0by fax 2489 0044\u00a0or\u00a0clicking\u00a0Apply Now\u00a0button to apply.\n\n\u00a0(Personal data provided by applicants will be used strictly for recruitment purpose only.)", "employment_types": ["Full Time", "Permanent"], "selling_points": ["Sustainability System", "follow-up the site progress", "5 Years Relevant Experience"], "locations": ["Kwai Tsing Area"], "categories": ["Engineering", "Electrical / Electronics", "Mechanical"], "post_time": "2022-01-14T04:33:19Z", "salary": {"currency": null, "max": null, "min": null, "period": null, "term": null}, "salary_visible": false, "title_keywords": [], "responsibilities": ["control", "monitoring", "implementation", "design", "statutory requirements", "material handling system", "specifications", "system design", "work quality"], "requirements": {"degrees": ["higher diploma or above"], "majors": ["building services", "electrical engineering"], "languages": ["english", "chinese"], "language_level": ["good command"], "hard_skills": ["autocad", "microsoft office"], "soft_skills": [], "languages_combined": [{"language": "english", "language_level": ["good command"]}, {"language": "chinese", "language_level": ["good command"]}]}, "experience_required": {"duration": ["5 years"], "field": ["relevant experience", "engineering"]}}, {"job_id": "100003009050475", "location_code": "hk", "company": "Chevalier Group - Lifts and Escalators", "job_title": "Engineer - Operation Division", "description": "Chevalier (HK) Limited is now inviting high calibre persons to apply for this position:\n\nResponsibilities\n\nPrepare technical specification for manufacturers and marketing department for quotation\nResponsible for shop drawings checking\nLiaise and coordinate with clients and other departments\nProvide support to installation and modernization projects\n\nRequirements\n\nDegree holder in Mechanical / Electrical / Building Services Engineering\n3 years' relevant experience\nGood command of both written and spoken English and Chinese\nGood communications and presentation skills\nProficient in MS Office application (Word, Excel, Powerpoint), AutoCAD and Chinese Word Processing\n\nCandidates with less experience will be considered for the position of Assistant Engineer\n\nAttractive remuneration package will be offered to the right candidate. Interested parties, please send us your resume with current and expected salary by clicking \"Apply Now\" or mail to:\n\nThe Human Resources Manager, Chevalier Group, 22/F, Chevalier Commercial Centre, 8 Wang Hoi Road, Kowloon Bay, Hong Kong\n\nWe are an equal opportunity employer and welcome applications from all qualified candidates. Personal data collected would be used for recruitment purpose only.", "employment_types": ["Full Time", "Permanent"], "selling_points": ["Prepare technical specifications", "Degree holder in Mechanical / Electrical / BS", "Prepare and check shop drawings"], "locations": ["Kowloon Bay"], "categories": ["Building & Construction", "Building / Construction / QS", "Engineering", "Electrical / Electronics", "Mechanical"], "post_time": "2022-01-14T10:29:06Z", "salary": {"currency": null, "max": null, "min": null, "period": null, "term": null}, "salary_visible": false, "title_keywords": ["engineer"], "responsibilities": ["liaise", "installation", "provide support", "quotation", "checking", "drawings", "coordinate with clients"], "requirements": {"degrees": ["degree holder"], "majors": ["building services", "engineering"], "languages": ["english", "chinese"], "language_level": ["good command", "proficient"], "hard_skills": ["excel", "chinese word processing", "word", "powerpoint", "ms office", "autocad"], "soft_skills": ["presentation skills"], "languages_combined": [{"language": "english", "language_level": ["good command"]}, {"language": "chinese", "language_level": ["good command", "proficient"]}]}, "experience_required": {"duration": ["3 years"], "field": ["relevant experience"]}}, {"job_id": "100003009048164", "location_code": "hk", "company": "P&T (M&E) Limited", "job_title": "Resident Building Services Engineer (RBSE) / Resident Building Services Inspector (RBSI & RABSI)", "description": "P&T (M&E) Limited invites applications to apply the following site staff position:\n\nResident Building Services Engineer (RBSE)\u00a0 (Ref. TW)\n\n\nApplicants shall be in university graduates in Degree of Building Services Engineering / Electrical\u00a0 or Mechanical Engineering or equivalent with relevant corporate member of MHKIE, MCIBSE or MIMechIE is preferred;\nWith 4 years solid experience in the capacity of RBSE and minimum 10 years of relevant experience in supervision and project administration of large scale shopping arcade, commercial projects;\nFamiliar with government regulations and code of practice specification, have strong organizational and interpersonal skills\nTai Wai commercial project period is approximately 36 months subject to further extension\n\nResident Building Services Inspector/ Resident Assistant Building Services Inspector\n(REF.:HSK, KTR, KTA, LMA, KT4B)\n\n\nA Higher Certificate or Diploma in Building Services Engineering or Electrical Engineering or Mechanical Engineering or equivalent.\nFor BSI, minimum 8 years' solid experience in the capacity of Building Services Inspector,\u00a0 minimum 4 years of relevant experience in the installation, maintenance or engineering services in residential, commercial, composite building , hotel project or equivalent;\nFor ABSI, minimum 4 years' solid experience in the capacity of Assistant Building Services Inspector in the installation, maintenance or engineering services in residential, commercial, composite building , hotel project or equivalent;\n[Note * Grade E in Chinese Language and English Language (Syllabus B) in previous HKCEE are accepted administratively as comparable to Level 2 in Chinese Language and English Language in the 2007 HKCEE and henceforth.]\n\nEmployment will be on contract basis and the remuneration package will be commensurate refer to applicants qualification and experience.\n\nPlease quoting the applied position and ref. no to the following site:\n\nRef: HSK - Residential & Composite Building - BSI & ABSI - Hung Shui Kiu Phase IB - Approx. 26 months subject to extension\nRef.: KTR - Residential - BSI - Kai Tak 6574\u00a0- Approx. 18 months subject to extension\nRef.: KTA - A&A - BSI - Kai Tak 6557 - Approx. 24 months subject to extension\nRef: LMA - Lift Modernization - BSI- Approx. 38 months subject to extension\nRef.: KT4B - Residential - Kai Tak 4B - BSI -\u00a0\u00a0Approx. 24 -30 months subject to extension\n\n\n\nWritten applications detailing personal particulars, qualifications, experience, present and expected salary, date of available for employment, contact telephone number and a recent photograph shall be sent to:\n\nP&T (M&E) Limited\n\n30/F, 633 King\u2019s Road, North Point, Hong Kong or email address to: by clicking \u201cApply Now\u201d[Quote belong Ref: No.:TW, HSK, KTR, KTA, LMA, KT4B]\n\nAll data collected would be used for recruitment purpose only", "employment_types": ["Contract"], "selling_points": [], "locations": ["Others"], "categories": ["Building & Construction", "Building / Construction / QS", "Engineering", "Electrical / Electronics", "Mechanical"], "post_time": "2022-01-14T07:37:06Z", "salary": {"currency": null, "max": null, "min": null, "period": "monthly", "term": null}, "salary_visible": false, "title_keywords": ["building services engineer", "building services inspector"], "responsibilities": ["regulations", "installation", "maintenance", "data", "project administration", "contact", "recruitment"], "requirements": {"degrees": ["higher certificate", "diploma", "degree"], "majors": ["electrical engineering", "building services", "engineering", "mechanical engineering"], "languages": ["english", "chinese"], "language_level": [], "hard_skills": ["code", "no", "mhkie", "maintenance"], "soft_skills": ["organizational", "interpersonal skills"], "languages_combined": [{"language": "english", "language_level": []}, {"language": "chinese", "language_level": []}]}, "experience_required": {"duration": ["4 years", "minimum 8 years", "minimum 4 years", "minimum 10 years"], "field": ["installation", "engineering", "maintenance", "commercial", "building services", "relevant experience", "administration"]}}, {"job_id": "100003009050455", "location_code": "hk", "company": "ATAL Engineering Ltd", "job_title": "(Macau) Draftsman (1-year renewable contract) (REF: BS(M)-CAD)", "description": "Responsibilities:\n\nPrepare drawings of E&M projects for submission\nPerform ad hoc duties as assigned\n\nRequirements:\n\nCertificate or above in Electrical / Mechanical / Building Services Engineering or equivalent, with AutoCAD training certificate is preferred\u00a0\nPossess 3 years\u2019 or above relevant working experience in participation of E&M / Building Services Contracts, preferably in Macau hotel projects\nProficient in AutoCAD and other design software\nGood command of both written and spoken English and Chinese\nGood communication and interpersonal skills\nSelf motivated, Independent and able to work under pressure\nStation in Macau is required\n\nPlease click the Apply Now button to send your full resume stating relevant job reference, present and expected salary and availability.\n\nPersonal data collected will be treated in strict confidence and used for recruitment related purposes only.", "employment_types": ["Full Time", "Contract"], "selling_points": ["Station in Macau is required", "Proficient in AutoCAD", "E&M / Building Services Contracts (Macau)"], "locations": ["Others - Macau"], "categories": ["Engineering", "Draftsman", "Electrical / Electronics", "Mechanical"], "post_time": "2022-01-14T10:27:31Z", "salary": {"currency": null, "max": null, "min": null, "period": "monthly", "term": null}, "salary_visible": false, "title_keywords": ["draftsman"], "responsibilities": ["ad hoc duties", "drawings"], "requirements": {"degrees": ["certificate"], "majors": ["building services", "engineering"], "languages": ["english", "chinese"], "language_level": ["good command"], "hard_skills": ["autocad"], "soft_skills": ["confidence", "independent", "self motivated", "communication and interpersonal skills", "work under pressure"], "languages_combined": [{"language": "english", "language_level": ["good command"]}, {"language": "chinese", "language_level": ["good command"]}]}, "experience_required": {"duration": ["3 years"], "field": ["building services", "relevant working experience"]}}, {"job_id": "100003009044494", "location_code": "hk", "company": "Holake Hong Kong Lifts Ltd", "job_title": "Senior / Project Engineer (Lift and Escalator)", "description": "The incumbent will be primarily responsible for the following duties : -\n\nDesign, plan and coordinate\u00a0lifts and escalators modernization\nMonitor the project progress, report the project status and identify any potential problems\nAttend site meetings and ensure that all project works are properly executed and followed through\nPerform site activities such as site coordination with architects, consultants, landlords and site supervisors, etc.\nConduct site Safety and Health inspections / observations to ensure corrective actions are taken for unsafe practices or conditions observed\n\nRequirements\n\nDegree or Diploma in Mechanical\u00a0 / Electrical /\u00a0Electronic Engineering, Building Services or a related discipline\nWith relevant working experience in project management, preferably in the Elevator\u00a0and Escalator industry\nGood communication, analytical and planning skills\nStrong problem solving skills, with an ability to work under pressure\nKnowledged of AutoCad is an advantage\nGood command of\u00a0spoken and written English and Chinese\nCandidates with less experience\u00a0will be considered as\u00a0Assistant Project Engineer\u00a0\n\nWe offer the right candidate\u00a0with competitive remuneration package and benefits including\u00a0marriage leave, paternity leave, study leave and\u00a0medical scheme (includes dependant coverage). Interested parties please send us your detailed resume with current and expected salary by clicking \"Apply Now\"\n\nAll information provided by applicants will be used for recruitment related purposes and handled in strict confidence by authorized personnel. The personal data collected will be destroyed after three months.\u00a0", "employment_types": ["Full Time", "Permanent"], "selling_points": ["Lifts & escalators industry", "Design, plan and coordinate projects", "Ability to work under pressure"], "locations": ["Quarry Bay"], "categories": ["Engineering", "Electrical / Electronics", "Engineering Project Management", "Mechanical"], "post_time": "2022-01-13T04:20:59Z", "salary": {"currency": null, "max": null, "min": null, "period": "monthly", "term": null}, "salary_visible": false, "title_keywords": ["project engineer"], "responsibilities": ["site activities", "work under pressure", "monitor", "project progress", "design", "plan and coordinate", "communication", "project management", "planning", "site coordination", "attend site meetings", "report"], "requirements": {"degrees": ["diploma", "degree"], "majors": ["building services", "engineering"], "languages": ["english", "chinese"], "language_level": ["good command"], "hard_skills": ["project management", "problem solving skills", "scheme", "autocad"], "soft_skills": ["planning skills", "responsible", "communication", "project management", "coordination", "problem solving skills", "work under pressure"], "languages_combined": [{"language": "english", "language_level": ["good command"]}, {"language": "chinese", "language_level": ["good command"]}]}, "experience_required": {"duration": [], "field": ["project management", "relevant working experience"]}}, {"job_id": "100003009050606", "location_code": "hk", "company": "Sino Group", "job_title": "Senior Building Services Engineer / Building Services Engineer (Ref: SBSE /JDB)", "description": "The incumbent will handle projects independently from inception to final completion including project planning, negotiation with project design teams and relevant Government sectors. Giving full advice on all contractual issues and M/E works, preparing budget for M/E installations and monitoring the progress of M/E works, checking and assessing the variation claims and payment claims from sub-contractors, and preparing the final account of M/E sub-contractors, interacting with project management teams and consultant team are also part of the role.\u00a0\n\nRequirements:\n\nBachelor Degree in Building Services Engineering, Mechanical Engineering or equivalent\nCorporate member of recognized professional bodies (e.g. HKIE, CIBSE, IMechE) preferred\nMinimum\u00a06 years of solid experience in handling M/E work in residential and commercial developments\nAble to work under pressure, achieve quality product and customer satisfaction\nMust have uncompromising integrity, strong sense of responsibility and good supervisory skills\nIncumbent with less experience will be considered for the position of Building Services Engineer\nWe offer attractive remuneration packages commensurate with experience and qualifications. If you aspire to an exciting and rewarding career, send your resume immediately, quoting your present and expected salaries by clicking the button \u201cApply Now\u201d.\nIf the applicant does not receive a response by 13 February 2022, the application will be considered unsuccessful. Please read our Personal Information Collection Statement at\u00a0https://www.sino.com/en-US/Careers/Personal-Information-Collection-Statement\u00a0before submitting your application. Information provided by applicants will be treated in strict confidence and used for recruitment purposes only.\n\n", "employment_types": ["Full Time", "Permanent"], "selling_points": [], "locations": ["Not Specified"], "categories": ["Building & Construction", "Building / Construction / QS", "Engineering", "Engineering Project Management", "Mechanical"], "post_time": "2022-01-14T10:55:03Z", "salary": {"currency": null, "max": null, "min": null, "period": "monthly", "term": null}, "salary_visible": false, "title_keywords": ["building services engineer"], "responsibilities": ["project planning", "budget", "teams", "monitoring", "design", "checking", "quality", "project management", "payment", "work under pressure"], "requirements": {"degrees": ["degree", "bachelor"], "majors": ["building services", "engineering", "mechanical engineering"], "languages": [], "language_level": [], "hard_skills": ["project management", "hkie"], "soft_skills": ["independently", "negotiation", "sense of responsibility", "integrity", "project management", "work under pressure"], "languages_combined": []}, "experience_required": {"duration": ["minimum 6 years"], "field": ["commercial", "building services"]}}, {"job_id": "100003009045041", "location_code": "hk", "company": "Wanson Construction Co Ltd", "job_title": "Building Services Coordinator / Building Services Engineer", "description": "Responsibilities:\n\nAssist Project Manager / Site Agent in monitoring / coordinating of all building services subcontractors' works, including their submissions and site installation works\nPrepare CSD and CBWD timely for consultant's approval to meet the site work progress\nAssist Site Agent in supervising and preparing site records and reports related to building services subcontractors' installation works\nLiaise and coordination with client, consultants, government department and utilities companies\n\n\u00a0Requirements:\u00a0\n\nHigher Diploma or above in Mechanical / Electrical Engineering or Building Services Engineering\nAt least 5- year experience with Main Contractor\nPrevious experience in ArchSD project is an advantage\nProficient in PC skills including MS office, MS project & AutoCAD\nGood command of both oral and written English and Chinese", "employment_types": ["Full Time", "Permanent"], "selling_points": [], "locations": ["Not Specified"], "categories": ["Building & Construction", "Building / Construction / QS", "Civil / Structural", "Engineering", "Mechanical"], "post_time": "2022-01-13T06:59:48Z", "salary": {"currency": null, "max": null, "min": null, "period": "monthly", "term": null}, "salary_visible": false, "title_keywords": ["building services engineer", "coordinator"], "responsibilities": ["liaise", "installation", "supervising", "monitoring", "coordination with", "reports"], "requirements": {"degrees": ["higher diploma or above"], "majors": ["building services", "electrical engineering", "engineering"], "languages": ["english", "chinese"], "language_level": ["good command"], "hard_skills": ["pc skills", "autocad", "ms office"], "soft_skills": ["oral"], "languages_combined": [{"language": "english", "language_level": ["good command"]}, {"language": "chinese", "language_level": ["good command"]}]}, "experience_required": {"duration": [], "field": []}}, {"job_id": "100003009048538", "location_code": "hk", "company": "Kum Shing Group", "job_title": "Project Manager / Assistant Project Manager \u2013 Mechanical Services", "description": "Reporting to the Department Head, the appointee will be responsible for but not limited to the following:\n\nResponsibilities:\n\nOverall planning and execution of heavy mechanical projects through liaising with relevant stakeholders to ensure the all works are completed timely and on budget;\nDevelop and implement action plan to enhance project performance;\nManage project team and subcontractors to achieve targeted profitability and committed objectives including capital expenditure control;\nParticipate in project development of new business.\n\nRequirements - Qualification:\n\nDegree or above in Mechanical / Electrical Engineering or equivalent;\nMin. 10 years experience in M&E projects;\nHolder of valid green card;\nWork experience in power station or heavy industrial plant is an advantage;\nQualification\u00a0of MHKIE, MIMechE or equivalent\u00a0is preferable;\nGood command of both written and spoken English and Chinese.\nCandidates with less experience will be considered as Assistant Project Manager.\n\nRequirements - Competences:\n\nPresentable, self-confidence, well-organized, cooperative with good problem solving skill and analytical mindset;\nStrong management, leadership, presentation, communication and interpersonal skills.\n\nWe look forward to receiving your application with detailed resume stating\u00a0working experience,\u00a0academic and language qualifications, existing and EXPECTED SALARY\u00a0as well as\u00a0availability.\u00a0All applications will be kept strictly confidential.\n\nWe offer promising professional career and exposure\u00a0to right candidate, together with attractive remuneration package including\u00a0discretionary bonus, continuing education allowance, medical and dental coverage, lunch & transportation allowance and free shuttle bus from various pickup points to work location.\n\nPersonal Data collected will be used for recruitment-related purposes only.", "employment_types": ["Full Time", "Permanent"], "selling_points": ["Performance bonus, education subsidy, medical plan", "Excellent career path", "Planning and execution of heavy mechanical project"], "locations": ["Tuen Mun Area"], "categories": ["Engineering", "Electrical / Electronics", "Engineering Project Management", "Mechanical"], "post_time": "2022-01-14T06:45:24Z", "salary": {"currency": null, "max": null, "min": null, "period": "monthly", "term": null}, "salary_visible": false, "title_keywords": ["project manager", "assistant project manager"], "responsibilities": ["control", "budget", "liaising with", "develop", "plan", "planning"], "requirements": {"degrees": ["degree or above"], "majors": ["electrical engineering"], "languages": ["english", "chinese"], "language_level": ["good command"], "hard_skills": ["problem solving", "mhkie", "green card"], "soft_skills": ["confidence", "cooperative", "well-organized", "presentable", "communication and interpersonal skills", "problem solving skill", "leadership", "presentation", "detailed"], "languages_combined": [{"language": "english", "language_level": ["good command"]}, {"language": "chinese", "language_level": ["good command"]}]}, "experience_required": {"duration": ["10 years"], "field": []}}, {"job_id": "100003009041165", "location_code": "hk", "company": "Great Link Engineering Limited", "job_title": "Assistant Engineer", "description": "Responsibilities:\n\n\u2022 Assist the Engineer/Senior Engineer to perform tasks required for completion of the engineering or maintenance projects for the company; and\n\u2022 Assist the Engineer/Senior Engineer in preparing the cost estimations, engineering drawings and other required documents\n\nRequirements:\n\n\u2022 1 - 2 years working experience in engineering/maintenance fields;\n\u2022 Fresh graduates with high calibre will also be considered;\n\u2022 Dip/High Cert./High Dip./Asso. Degree in Electrical/Mechanical Engineering or related engineering disciplines; and\n\u2022 Well-organized, able to meet tight deadlines, positive attitude, and a strong sense of responsibility", "employment_types": ["Full Time", "Permanent"], "selling_points": [], "locations": ["Not Specified"], "categories": ["Engineering", "Electrical / Electronics", "Engineering Project Management", "Mechanical"], "post_time": "2022-01-12T23:26:11Z", "salary": {"currency": null, "max": null, "min": null, "period": "monthly", "term": null}, "salary_visible": false, "title_keywords": ["assistant engineer"], "responsibilities": ["cost", "maintenance", "drawings"], "requirements": {"degrees": ["degree", "dip", "high dip"], "majors": ["engineering", "mechanical engineering"], "languages": [], "language_level": [], "hard_skills": ["maintenance"], "soft_skills": ["positive attitude", "meet tight deadlines", "well-organized", "sense of responsibility"], "languages_combined": []}, "experience_required": {"duration": ["1 - 2 years"], "field": ["engineering", "maintenance"]}}, {"job_id": "100003009046372", "location_code": "hk", "company": "Otis Elevator Co (HK) Limited", "job_title": "Safety Officer", "description": "Responsibilities\nDevelop EH&S strategies and plans to meet company objectives in an innovative way\nEvaluate, maintain and review the EH&S management system to ensure the EH&S\u00a0policy & procedure are carry out efficiently and creatively\nScan environment for potential risks & advise to devise methods /procedures to eliminate or control the risks identified\nConduct incident investigation, manage audits & regular site inspections to ensure the compliance with the company EH&S\u00a0management system\nMaintain, monitor and review the EH&S\u00a0communication and records\u00a0\nIdentify and conduct safety training needs for both internal & external parties in an contemporary way\nDevelop, review and revise safety instructions and work instruction\nOvernight work is required\nRequirements\u00a0\nHigh Diploma / Degree in Engineering, Safety or other relevant disciplines\nMinimum 3 years EH&S experience in construction industry\nMinimum\u00a03 years\u00a0of\u00a0Registered Safety Officer / Safety Auditor from HK Labour Dept. is a must\nSound knowledge of EH&S\u00a0management as well as overnight work experience\u00a0is a plus\nKnowledge in lift, elevator and escalator is an advantage\nGood command of both written and spoken English, Chinese and Mandarin\nProficient in MS Office, including Word, Excel\u00a0and Power Point\nWe offer remuneration package including attractive salary, comprehensive fringe benefits and excellent opportunities for the right candidate. (*** Employee Scholar Program up to $160,000/ person for each degree***)\n\n\nWebsite:\u00a0http://www.otis.com\n\nInformation provided by applicants will be treated in strict confidence and will only be used for recruitment related purposes. All information on unsuccessful candidates will be deleted from our files within 24 months.", "employment_types": ["Full Time", "Permanent"], "selling_points": ["13-month bonus + performance bonus", "Employee Scholar Program up to $160,000", "Innovative development in EH&S strategies & plans"], "locations": ["Kowloon Bay"], "categories": ["Engineering", "Mechanical", "Others", "Others", "Security / Safety Control"], "post_time": "2022-01-13T10:46:43Z", "salary": {"currency": null, "max": null, "min": null, "period": "monthly", "term": null}, "salary_visible": false, "title_keywords": ["safety officer"], "responsibilities": ["management", "control", "review", "procedures", "compliance", "investigation", "develop", "evaluate", "monitor", "communication", "maintain", "external parties", "site inspections", "audits", "plans"], "requirements": {"degrees": ["high diploma", "degree"], "majors": ["engineering"], "languages": ["english", "chinese", "mandarin"], "language_level": ["good command"], "hard_skills": ["excel", "plus", "word", "power point", "ms office"], "soft_skills": [], "languages_combined": [{"language": "english", "language_level": ["good command"]}, {"language": "chinese", "language_level": ["good command"]}, {"language": "mandarin", "language_level": ["good command"]}]}, "experience_required": {"duration": ["minimum 3 years"], "field": ["management", "construction industry"]}}, {"job_id": "100003009045617", "location_code": "hk", "company": "RNB Engineering Hong Kong Limited", "job_title": "Senior Project Engineer / Project Engineer / Engineer in Electrical Engineering", "description": "Responsibilities\u00a0\n\nResponsible for project managements, budgets, cost controls.\nProject and resource management including subcontractors and vendors.\nAttend site meeting, progress meeting.\nCoordination works with vary parties, main contractor, consultants, sub-contractors etc.\nPrepare E&M System planning, design, CAD drawing, tendering and calculation.\n\nRequirements\u00a0\n\nHigher Diploma or above in\u00a0Electrical /\u00a0Building Services\u00a0Engineering\u00a0or related disciplines;\nMinimum 1 year's relevant electrical working experience. Relevant experience on E&M or building projects is advantageous.\nProficient in AutoCAD.\nGood co-ordination and interpersonal skill.\nGood command of written and spoken English and Chinese.\n\n\u00a0For interested parties, please email your resume with expected salary to us.", "employment_types": ["Full Time", "Permanent"], "selling_points": [], "locations": ["To Kwa Wan"], "categories": ["Engineering", "Electrical / Electronics", "Engineering Project Management", "Mechanical"], "post_time": "2022-01-13T08:12:54Z", "salary": {"currency": null, "max": null, "min": null, "period": "monthly", "term": null}, "salary_visible": false, "title_keywords": ["senior project engineer", "engineer", "project engineer"], "responsibilities": ["budgets", "cost", "management", "coordination works", "tendering", "design", "planning"], "requirements": {"degrees": ["higher diploma or above"], "majors": ["related disciplines", "building services", "engineering"], "languages": ["english", "chinese"], "language_level": ["good command"], "hard_skills": ["autocad"], "soft_skills": ["interpersonal skill"], "languages_combined": [{"language": "english", "language_level": ["good command"]}, {"language": "chinese", "language_level": ["good command"]}]}, "experience_required": {"duration": ["minimum 1 year"], "field": ["relevant experience"]}}, {"job_id": "100003009049304", "location_code": "hk", "company": "Great Creation Construction Engineering Limited", "job_title": "Assistant Project Manager", "description": "\u00a0Responsibilities:\u00a0\n\nAct as the leader\u00a0\nMonitor the progress according to schedule and deadlines within budget\nDeals with all contractual matters with clients, subcontractors & suppliers\nOversee all incoming and outgoing project documentations\nResponsible for tendering process, project cost control & payment issues and prepare final account\nSupervise Project Team to prepare and submit project documents, such as design drawings, material submission, method statements, safety documents and maintenance manual for client's approval\nAssist in other ad-hoc assignment\n\nRequirements:\u00a0\n\nMinimum 8-10\u00a0years of experience in project management, manage in fit out retails, office and Hotel etc.\nExcellent leadership & management skill\nDegree in Structural / Civil / Building / Mechanical Engineering\nConversant with interior\u00a0fitting-out nature / surveying, A&A work and contractual documents are advantages\nFluent written and spoken in English & Cantonese is a must\nImmediate available will be an advantage\u00a0\n\nWe offer\n-\u00a0\u00a0\u00a0\u00a0\u00a0 project bonus\n-\u00a0\u00a0\u00a0\u00a0\u00a0 medical\n-\u00a0\u00a0\u00a0\u00a0\u00a0 study allowance\n\nInterested candidates please send full resume with current & expected salary (MUST) and project portfolio (MUST) to us.", "employment_types": ["Full Time"], "selling_points": [], "locations": ["Kwun Tong"], "categories": ["Building & Construction", "Architectural Services", "Engineering", "Engineering Project Management", "Mechanical"], "post_time": "2022-01-14T08:25:15Z", "salary": {"currency": null, "max": null, "min": null, "period": "monthly", "term": null}, "salary_visible": false, "title_keywords": ["assistant project manager"], "responsibilities": ["ad-hoc", "maintenance", "design drawings", "budget", "monitor", "tendering", "payment", "project documents", "schedule", "cost control"], "requirements": {"degrees": ["degree"], "majors": ["mechanical engineering"], "languages": ["cantonese", "english"], "language_level": ["fluent"], "hard_skills": ["project management"], "soft_skills": ["project management", "leadership"], "languages_combined": [{"language": "cantonese", "language_level": ["fluent"]}, {"language": "english", "language_level": ["fluent"]}]}, "experience_required": {"duration": ["minimum 8-10 years"], "field": ["project management"]}}, {"job_id": "100003009044950", "location_code": "hk", "company": "CLPe Solutions Limited", "job_title": "Assistant Project Manager (2-Year Contract) [Ref. CLPeS-EM-HVAC-APM]", "description": "CLPe Solutions Limited\u00a0(formerly CLP Engineering Limited), incorporated in Hong Kong in 1985, is a wholly-owned subsidiary of CLP Holdings Limited with extensive experience in providing total energy solution. The company undertakes a variety of services including energy management solutions, distributed energy as well as power engineering, infrastructure and facilities management.\u00a0\n\nWe are looking for an energetic and innovative engineering professional to join our HVAC Engineering Branch. Reporting to the supervisor, the appointee will be responsible for the following duties:\n\n\nResponsible for effective project management including but not limited to carrying out feasibility studies, scheduling, design, installation, testing and commissioning of chiller plant system, chiller optimization, Building Management System and other energy management solutions to meet contract programmes and requirements\nWork closely with customers, consultants and suppliers to identify and propose energy efficient equipment and system of the chiller plant.\nPrepare project programme, budget, site progress report and related information in a timely manner\nSupport pre-sales activities, conduct site visit and prepare proposal\nImplement and monitor the Safety, Health, Environment and Quality (SHEQ) systems to ensure that the required standards are achieved Other ad-hoc duties as assigned \u2003\n\nRequirements:\n\nA recognized University degree in Building Services Engineering, Electronic Engineering, Mechanical Engineering, or relevant engineering disciplines with a minimum of 5 years\u2019 relevant working experience\nSolid experience in chiller plant replacement, operation and maintenance as well as system configuration\n\nSounds familiar with chiller selection\n\nFamiliar with MS Office, MS Project and AutoCAD\n\nFamiliar with IoT, AI solutions and smart technologies would be an added advantage\n\nStrong communication, leadership and organisation skills\n\nSelf-motivated, enthusiastic and persistent\n\nCandidates with less experience will be considered for a lower position\n\nPlease apply by clicking the button \u201cApply Now\u201d below for application giving a detailed C.V., including academic qualification, career history, current and expected salary, major achievements and personal attributes on or before 21 January 2022.\n\nApplicants not invited for interview within 6 weeks from the closing date may assume their applications unsuccessful.\u00a0\n\nInformation provided will be for recruitment purpose within the CLP Group and only short-listed candidates will be contacted. We comply with all applicable laws and regulations of HKSAR in handling applications. For details of the Personal Information Collection Statement, please visit our website: https://clp.to/engPICS\u00a0\n\nFor further information on our company, please visit our website: https://www.clpgroup.com/", "employment_types": ["Full Time", "Contract"], "selling_points": [], "locations": ["Kwai Hing"], "categories": ["Engineering", "Electrical / Electronics", "Mechanical"], "post_time": "2022-01-14T06:06:29Z", "salary": {"currency": null, "max": null, "min": null, "period": "monthly", "term": null}, "salary_visible": false, "title_keywords": ["assistant project manager"], "responsibilities": ["regulations", "budget", "quality", "website", "design", "communication", "building management", "configuration", "infrastructure", "monitor", "testing", "report", "reporting", "management", "installation", "commissioning", "scheduling", "ad-hoc duties", "sales activities", "maintenance", "systems", "a timely manner", "project management", "recruitment"], "requirements": {"degrees": ["university degree"], "majors": ["building services", "engineering", "mechanical engineering"], "languages": [], "language_level": [], "hard_skills": ["maintenance", "ai", "hvac", "facilities management", "project management", "autocad", "building management system", "c", "ms office"], "soft_skills": ["efficient", "self-motivated", "responsible", "persistent", "timely", "innovative", "communication", "project management", "enthusiastic", "leadership", "organisation", "ad-hoc duties", "energetic", "extensive", "detailed"], "languages_combined": []}, "experience_required": {"duration": ["minimum of 5 years"], "field": ["engineering", "maintenance", "relevant working experience", "operation", "building services"]}}, {"job_id": "100003009047197", "location_code": "hk", "company": "Hong Kong Applied Science and Technology Research Institute Company Limited (ASTRI)", "job_title": "Mechanical - Senior Engineer / Engineer", "description": "Reference #:\u00a0CTO/IOTSEN/13\nJob Responsibilities\n\n\nPerform mechanical design, manufacturing, and automation related projects\nPerform outsource allocation for manufacturing mechanical parts and system integration based on the engineering specification of products and working schedule in project execution\nPerform hardware system on-site setup and debug\nAssist in ITF R&D project as assigned\nSupport other R&D projects under the guidance of Team leader\nRequirements\nPh.D. holder or Master\u2019s degree in Mechanical / Automation Engineering or relevant disciplines with a minimum of 3 years of related experience. Candidate with fewer experience may also be considered.\nExperience in automation or robotic development and project follow up is a plus\nProficient in 3D CAD (SolidWorks preferred) for machine design\nFamiliar with CNC machining processes and mass production processes such as stamping, welding, injection, die casting, 3D printing etc.\nStrong problem solving and troubleshooting skills\nFast learner of new technologies, good communication skills in written and spoken English, self-motivated and passionate in research and development\nTeam player and oral/written communication skills in English and Chinese\nApplication\n\nThe appointment will be on renewable contract terms with a competitive salary and performance-linked variable pay. Fringe benefits include paid leave, medical and dental benefits, insurance coverage and contribution to MPF. The incumbent will normally work\u00a0a five-day week.\n\nInterested candidates, please send an application (quoting Ref. No.) with a detailed resume, current and expected salary to\u00a0Talent Acquisition by clicking \"APPLY NOW\".\u00a0The resume should\u00a0not\u00a0include any sensitive personal information such as HKID or passport number, photo, etc.\u00a0\n\nPosition offer is subject to the applicant\u2019s experience and academic qualification. The application will be open until the position is filled. Only short-listed candidates will be notified. ASTRI reserves the right not to fill the position.\n\nASTRI is an Equal Opportunities Employer. Personal data provided by job applicants will be used\u00a0exclusively\u00a0for recruitment\u00a0only. For details, please refer to\u00a0Privacy - ASTRI - Hong Kong Applied Science and Technology Research Institute Company Limited, in particular section 9.", "employment_types": ["Full Time", "Contract"], "selling_points": ["Mechanical", "Perform hardware system on-site setup and debug", "Manufacturing mechanical parts"], "locations": ["Shatin Area"], "categories": ["Engineering", "Electrical / Electronics", "Mechanical", "Sciences, Lab, R&D", "Research & Development (R&D)"], "post_time": "2022-01-14T02:33:53Z", "salary": {"currency": null, "max": null, "min": null, "period": "monthly", "term": null}, "salary_visible": false, "title_keywords": ["senior engineer", "engineer"], "responsibilities": ["guidance", "hardware", "mechanical design", "schedule", "setup"], "requirements": {"degrees": ["degree", "master"], "majors": ["engineering"], "languages": ["english", "chinese"], "language_level": ["good"], "hard_skills": ["problem solving", "cad", "plus", "solidworks"], "soft_skills": ["passionate", "communication skills", "self-motivated", "oral", "troubleshooting", "problem solving", "team player", "fast learner"], "languages_combined": [{"language": "english", "language_level": ["good"]}, {"language": "chinese", "language_level": []}]}, "experience_required": {"duration": ["minimum of 3 years"], "field": ["related", "development", "engineering"]}}, {"job_id": "100003009038257", "location_code": "hk", "company": "J Roger Preston Limited", "job_title": "Graduate Engineer", "description": "Job Descriptions\n\nAssists in the\u00a0Building Services for projects including but not limited to prepare design deliverables, authorities\u2019 submissions and tender.\nAssists in Project delivery including preparation of reports, statutory submissions and presentations.\nAssists in supervising site works.\u00a0\nPrepares drawings and technical matters.\n\n\u00a0\u00a0Job Specifications\u00a0\n\nDegree holder in Building Services or Mechanical Engineering.\nProficiency in both written and spoken English and Chinese. Fluency in Putonghua is preferred.\nTeam player with excellent interpersonal and communication skills\u00a0\n\nJRP has registered under the Hong Kong Institution of Engineers (HKIE) in 1985 to provide the Training Scheme A for graduates graduated from Universities both in HK and overseas.\n\n\n\nInterested applicants, please send full resume stating the present & expected salary and date of availability to\u00a0Human Resources Department, Level 11, Tower 1, Millennium City 1, 388 Kwun Tong Road, Kowloon\u00a0or fax to\u00a02267 3299\u00a0or send the application by clicking the\u00a0\"Apply Now\" button.\u00a0\n\n(Personal data collected would be used for recruitment purpose only. All personal data of unsuccessful candidates will be destroyed after six months.)", "employment_types": ["Full Time", "Permanent"], "selling_points": [], "locations": ["Kwun Tong Area"], "categories": ["Engineering", "Draftsman", "Engineering Project Management", "Mechanical"], "post_time": "2022-01-11T06:22:29Z", "salary": {"currency": null, "max": null, "min": null, "period": "monthly", "term": null}, "salary_visible": false, "title_keywords": ["graduate engineer"], "responsibilities": ["supervising", "presentations", "design", "drawings", "communication", "specifications", "reports", "recruitment", "tender", "personal data"], "requirements": {"degrees": ["degree holder"], "majors": ["building services", "mechanical engineering"], "languages": ["putonghua", "english", "chinese"], "language_level": ["fluency", "proficiency"], "hard_skills": ["the hong kong institution of engineers", "hkie", "scheme", "presentations"], "soft_skills": ["communication skills", "team player", "interpersonal"], "languages_combined": [{"language": "putonghua", "language_level": ["fluency"]}, {"language": "english", "language_level": ["proficiency"]}, {"language": "chinese", "language_level": ["proficiency"]}]}, "experience_required": {"duration": [], "field": []}}, {"job_id": "100003009047378", "location_code": "hk", "company": "AP Rentals Limited", "job_title": "Service Engineer", "description": "Job Description\n\nTo be\u00a0responsible for equipment service inspection, machines trouble shooting and claims reports preparation related issues\nTo tackle technical problems and carry out fault investigation\nTo assist daily workshop operation and housekeeping\nTo communicate with internal parties for parts & material procurement & transportation arrangement\nTo participate in ad-hoc projects\u00a0as assigned\n\nJob Requirements\n\nHigher Diploma holder or above in Mechanical or Electrical\u00a0related disciplines\nMinimum 5 years' technical\u00a0experience in workshop & construction sites\nSelf-motivated, responsible and able to work under pressure\nTeam player with good communication skills\nAcceptable written and spoken English & Chinese including Putonghua\nKnowledge in MS Office, i.e. Word, Excel, PowerPoint & Chinese Word Processing\n\n*Candidates with less experience will be considered as\u00a0Assistant Service Engineer\n\n*Fresh graduate will be considered as Engineer Trainee\n\nInterested parties, please click \"APPLY NOW\" and send us your full resume, stating date available, present\u00a0and expected salary.\n\n\n(Applicant without stating the expected salary will not be considered)\n\nAll data collected will be used for recruitment purpose only and will be treated as strictly confidential.\u00a0 All unsuccessful applications will be destroyed upon completion of the selection process.\n\nOur website: www.aprentalshk.com\u00a0", "employment_types": ["Full Time", "Permanent"], "selling_points": [], "locations": ["Yuen Long"], "categories": ["Engineering", "Electrical / Electronics", "Engineering Project Management", "Mechanical"], "post_time": "2022-01-14T02:56:37Z", "salary": {"currency": null, "max": null, "min": null, "period": "monthly", "term": null}, "salary_visible": false, "title_keywords": ["service engineer"], "responsibilities": ["housekeeping", "workshop", "investigation", "inspection", "reports", "communicate with internal parties", "ad-hoc projects"], "requirements": {"degrees": ["fresh graduate", "higher diploma holder"], "majors": ["related disciplines"], "languages": ["putonghua", "english", "chinese"], "language_level": [], "hard_skills": ["excel", "chinese word processing", "word", "powerpoint", "ms office"], "soft_skills": ["communication skills", "self-motivated", "responsible", "team player", "work under pressure"], "languages_combined": [{"language": "putonghua", "language_level": []}, {"language": "english", "language_level": []}, {"language": "chinese", "language_level": []}]}, "experience_required": {"duration": ["minimum 5 years"], "field": ["construction"]}}, {"job_id": "100003009048998", "location_code": "hk", "company": "Liu Chong Hing Property Management & Agency Ltd", "job_title": "\u6280\u5de5", "description": "\u8077\u8cac :\n\n\u8ca0\u8cac\u76e3\u5bdf\u5404\u9805\u6a5f\u96fb\u7cfb\u7d71\u904b\u4f5c\u53ca\u4fdd\u990a\u7dad\u4fee; \u5b9a\u671f\u6aa2\u67e5\u5404\u9805\u6a5f\u96fb\u7cfb\u7d71\u548c\u8a2d\u65bd; \u9032\u884c\u9810\u9632\u6027\u53ca\u7dca\u6025\u6545\u969c\u7dad\u4fee; \u5354\u52a9\u76e3\u7763\u5916\u5224\u627f\u8fa6\u5546\u5de5\u7a0b\u9032\u5ea6\u3001\u8cea\u7d20\u53ca\u5b89\u5168; \u532f\u5831\u5de5\u7a0b\u53ca\u7dad\u4fee\u9032\u5ea6; \u57f7\u884c\u4e0a\u7d1a\u6307\u6d3e\u7684\u8077\u52d9; \u9700\u7368\u7acb\u8655\u7406\u7dad\u4fee\u5de5\u4f5c; \u9700\u7a7f\u8457\u5236\u670d\n\u8cc7\u6b77 :\n\n\u4e2d\u4e09\u7a0b\u5ea6; 3\u5e74\u7d93\u9a57; \u826f\u597d\u7cb5\u8a9e; \u61c2\u8b80\u5beb\u4e2d\u6587; \u6301\u6709\u5e73\u5b89\u54ad; \u61c2\u96fb\u5b50\u7dad\u4fee; \u6301\u6709\u96fb\u5de5A\u724c; \u61c2\u96fb\u5668\u7dad\u4fee; \u5177\u6709\u57fa\u672c\u96fb\u8166\u64cd\u4f5c\u77e5\u8b58\n\u5f85\u9047 :\n\n\u6bcf\u6708$20,000 - $23,000, \u6709\u8d85\u6642\u5de5\u4f5c\u6d25\u8cbc, \u91ab\u7642\u4fdd\u96aa, \u6649\u5347\u6a5f\u6703 \u53ca\u4eba\u58fd\u4fdd\u969c, \u4e0a\u53489\u6642\u81f3\u4e0b\u53486\u6642, \u6bcf\u9031\u5de5\u4f5c6\u5929,\u8f2a\u4f11, \u6bcf\u5929\u5de5\u4f5c 9 \u5c0f\u6642\n\u7533\u8acb\u9808\u77e5 :\u6c42\u8077\u8005\u53ef\u81f4\u96fb25592324\u8207\u5ed6\u5275\u8208\u7269\u696d\u7ba1\u7406\u53ca\u4ee3\u7406\u6709\u9650\u516c\u53f8\u4f55\u5148\u751f\u806f\u7d61\u3002", "employment_types": ["Full Time"], "selling_points": [], "locations": ["Sai Wan"], "categories": ["Engineering", "Mechanical", "Telecommunication / Wireless / Radio", "Others", "Technician"], "post_time": "2022-01-14T07:52:17Z", "salary": {"currency": null, "max": null, "min": null, "period": "monthly", "term": null}, "salary_visible": false, "title_keywords": ["\u6280\u5de5"], "responsibilities": [], "requirements": {"degrees": [], "majors": [], "languages": [], "language_level": [], "hard_skills": [], "soft_skills": [], "languages_combined": []}, "experience_required": {"duration": [], "field": []}}, {"job_id": "100003009049509", "location_code": "hk", "company": "Jones Lang LaSalle Ltd", "job_title": "Senior Engineer", "description": "About JLL \u2013\n\nWe\u2019re JLL. We\u2019re a professional services and investment management firm specializing in real estate. As a Fortune 500 company, we help real estate owners, occupiers and investors achieve their business ambitions.\n\nIf you\u2019re looking to step up your career, JLL is the perfect professional home. With us, you\u2019ll have a chance to innovate with the world\u2019s leading businesses, put that expertise into action on landmark projects, and work on game-changing real estate initiatives. You\u2019ll also make long-lasting professional connections and be inspired by the best. We\u2019re focused on opportunity and want to help you make the most of yours. Achieve your ambitions - join us at JLL!\n\nAbout the role:\n\nAssist technical team to deliver preventive and corrective maintenance\nResponsible for regular site inspection to monitor and check the subcontractors' work quality & progress.\nAttend meetings and submit site progress reports\nCoordinate with subcontractors and monitor site progress\nMay require to perform irregular shift duties\nAd-hoc tasks assigned by the supervisor\n\nWhat this job involves:\n\nGreasing the wheels of day-to-day operations\n\nYou will be involved in the overall upkeep of plant and facilities equipment to ensure smooth daily operations. To do this, you\u2019ll need to regularly inspect all equipment rooms and other facilities, and take note of any problems using the predefined checklists. Also part of your responsibilities is to walk the duty technicians through weekend work plans, and give out technical recommendations, as needed.\n\nBeing the front line for maintenance needs\n\nOur clients will come to you for equipment fixes, so you\u2019ll be expected to be skilled in carrying out repairs. At the same time, you should always be ready to get hold of vendors to do maintenance work at a moment\u2019s notice. On top of this, you\u2019ll also have to speed up any required equipment moves, adds and changes implementation. In every decision or action you will make, you\u2019ll need to keep in mind that you follow local governmental rules and regulations to avoid any legal troubles.\n\n\u00a0Sound like you? To apply you will have:\n\nHigher Diploma or above in Building Services/Electrical/Mechanical Engineering.\nGood knowledge in E&M industry is an advantageous.\nProficiency in AutoCAD drawings skills and MS office operations.\nSelf-motivated, detail-minded, with a high sense of responsibility and good communication skills.\nGood commands of both written and spoken English & Chinese.\n\nCertified and experienced\n\nAre you certified to do electrical or mechanical repair? Have you worked in a facilities and maintenance role before? If yes, then you are who we\u2019re looking for!\n\nGood-natured and customer-oriented\n\nCan you clearly report issues and problems and provide clear instruction to repair bugs and malfunctions? To serve clients the best way possible, good communication skills\u2014both written and spoken\u2014will also be indispensable for this role. Can you speak or write in English and Chinese? That\u2019ll be a big plus!\n\nWhat you can expect from us\n\nWe\u2019re an entrepreneurial, inclusive culture. We succeed together - across the desk and around the globe. We believe the best inspire the best, so we invest in supporting each other, learning together and celebrating our success.\n\nOur Total Rewards program reflects our commitment to helping you achieve your ambitions in career, recognition, well-being, benefits and pay. We\u2019ll offer you a competitive salary and benefits package.\n\nWith us, you\u2019ll develop your strengths and enjoy a career full of varied experiences. We can\u2019t wait to see where your ambitions take you at JLL.\n\nApply today!", "employment_types": ["Full Time", "Permanent"], "selling_points": ["Building Services / Electrical / Mechanical Engg", "Preventive & Corrective Maintenance", "Site Supervision & Contractors' Monitoring"], "locations": ["Pok Fu Lam"], "categories": ["Building & Construction", "Building / Construction / QS", "Engineering", "Electrical / Electronics", "Mechanical"], "post_time": "2022-01-14T08:46:27Z", "salary": {"currency": null, "max": null, "min": null, "period": "monthly", "term": null}, "salary_visible": false, "title_keywords": ["senior engineer"], "responsibilities": ["regulations", "monitor site progress", "operations", "day-to-day operations", "drawings", "communication", "attend meetings", "plans", "progress reports", "monitor", "implementation", "site inspection", "report", "management", "coordinate with", "daily operations", "maintenance", "ad-hoc tasks", "repair", "work quality"], "requirements": {"degrees": ["higher diploma or above"], "majors": ["building services", "mechanical engineering"], "languages": ["english", "chinese"], "language_level": ["good"], "hard_skills": ["plus", "maintenance", "make", "autocad", "ms office"], "soft_skills": ["detail-minded", "communication skills", "self-motivated", "focused", "responsible", "high sense of responsibility", "clear", "customer-oriented", "learning", "smooth"], "languages_combined": [{"language": "english", "language_level": ["good"]}, {"language": "chinese", "language_level": ["good"]}]}, "experience_required": {"duration": [], "field": []}}, {"job_id": "100003008989545", "location_code": "hk", "company": "Fathom Precision International Limited", "job_title": "Project Managers", "description": "Requirements\n\nIdeal candidate should be graduate in relevant engineering discipline, plus 8 years or above relevant experience in Tooling and Molding manufacturing Industry.\n\nSound experience in detailed mould design and manufacturing\nGood technical background and able to deal with overseas clients\nKnowledge and working experience on 3D CAD systems, preferably on Solidwork, Pro-E.\nFollow up & co-ordinate new tooling build process, tool qualification, tool debug and finally part qualification process.\nStrong Leadership with a team of engineers in tooling operation\nProficiency in spoken and written English is needed and Chinese as well\nSelf-starter, self-motivated, proactive and good communicator\nStation in Dongguan.\n\nWe offer an attractive remuneration to the successful candidate. Interested parties please send email by \"Apply Now\".\n\nPersonal data collected will be used for recruitment purposes only", "employment_types": ["Full Time", "Permanent"], "selling_points": ["Station in Dongguan", "8 years or above relevant experience", "Tooling and Molding manufacturing Industry"], "locations": ["Others - China"], "categories": ["Engineering", "Manufacturing & Production", "Mechanical"], "post_time": "2022-01-13T18:54:40Z", "salary": {"currency": null, "max": null, "min": null, "period": "monthly", "term": null}, "salary_visible": false, "title_keywords": [], "responsibilities": ["systems", "design"], "requirements": {"degrees": [], "majors": [], "languages": ["english", "chinese"], "language_level": ["proficiency"], "hard_skills": ["cad", "plus", "solidwork"], "soft_skills": ["self-motivated", "ideal", "communicator", "proactive", "leadership", "detailed"], "languages_combined": [{"language": "english", "language_level": ["proficiency"]}, {"language": "chinese", "language_level": []}]}, "experience_required": {"duration": ["8 years"], "field": ["manufacturing", "engineering", "design", "relevant experience", "manufacturing industry"]}}, {"job_id": "100003009047487", "location_code": "hk", "company": "Deltason Medical Ltd", "job_title": "Service Technician", "description": "Responsibilities:\n\n\n\nInstall & repair company medical/pharmacy automation products\nPerform regular check on medical/pharmacy automation products\nHandle product end-users technical enquires to achieve customer satisfaction\nField service is required\n\nRequirements:\n\n\n\nDiploma or above in Biomedical / Mechanical Engineering / Electronic Engineering or equivalent\nMature with strong sense of responsibility\nAggressive, strong desire to learn\nGood interpersonal skills with a customer service mindset\nImmediate available is preferred\nFresh graduate is welcome\n\nInterested parties please send \u200bthe\u00a0resume \u200bwith \u200bexpected salary by clicking \u201cAPPLY NOW\u201d.\n\nPersonal data collected will be used for recruitment purpose only.", "employment_types": ["Full Time", "Contract"], "selling_points": [], "locations": ["Not Specified"], "categories": ["Engineering", "Electrical / Electronics", "Mechanical", "Sciences, Lab, R&D", "Others"], "post_time": "2022-01-14T03:17:25Z", "salary": {"currency": null, "max": null, "min": null, "period": "monthly", "term": null}, "salary_visible": false, "title_keywords": ["technician"], "responsibilities": ["repair"], "requirements": {"degrees": ["fresh graduate", "diploma or above"], "majors": ["engineering", "mechanical engineering"], "languages": [], "language_level": [], "hard_skills": [], "soft_skills": ["customer service", "interpersonal skills", "mature", "sense of responsibility"], "languages_combined": []}, "experience_required": {"duration": [], "field": []}}, {"job_id": "100003009047582", "location_code": "hk", "company": "REC Engineering Company Limited", "job_title": "Operation and Maintenance Supervisor (Ref.: S/22/0040)", "description": "\n\n\nResponsibilities:\n\nDaily operation and maintenance of the Temporary Sewage Pumping Station;\u00a0\nPresent full time on the Site and be working solely on the duties related to operation and maintenance of the\u00a0Temporary Sewage Pumping Station throughout the operation period;\nAny other duties as assigned\n\nRequirements:\n\nCertificate or above in Electrical / Mechanical Engineering or other related disciplines;\nAt least 5\u00a0years\u00a0relevant working experience;\nExperience in Sewage Pumping Station / Sewage Treatment Works is preferred;\nHolder of Driving License is preferred;\nContract Period: Nov 2021 - October 2023\nWorking hours: Day Shift (08:00-20:00) / Night Shift (20:00-08:00)\nLocation: Tai Po Sewage Pumping Station\n\n\n\nAttractive remuneration package will be offered to the successful candidate\n\nPlease send in strict confidence with full resume stating the reference code and your current and expected salary to Human Resources Department, REC Engineering Company Limited, Units A-D, 15/F., Goodman Kwai Chung Logistics Centre, 585-609 Castle Peak Road, Kwai Chung, New Territories, Hong Kong or\u00a0by\u00a0fax 2489 0044 or\u00a0clicking \u201cApply Now\u201d\u00a0button to apply.\n(Personal data provided\u00a0by applicants will be used strictly for recruitment purpose only.)", "employment_types": ["Contract"], "selling_points": ["Daily operation and maintenance of the TSPF", "Tai Po Sewage Pumping Station", "5 years relevant experience"], "locations": ["Tai Po Area"], "categories": ["Engineering", "Electrical / Electronics", "Mechanical", "Others", "Technician"], "post_time": "2022-01-14T03:30:21Z", "salary": {"currency": null, "max": null, "min": null, "period": null, "term": null}, "salary_visible": false, "title_keywords": ["supervisor"], "responsibilities": ["any other duties", "daily operation", "maintenance"], "requirements": {"degrees": ["certificate"], "majors": ["related disciplines", "mechanical engineering"], "languages": [], "language_level": [], "hard_skills": ["code"], "soft_skills": ["confidence"], "languages_combined": []}, "experience_required": {"duration": ["at least 5 years"], "field": ["relevant working experience"]}}, {"job_id": "100003009044490", "location_code": "hk", "company": "Kin Yat Industrial Co Ltd", "job_title": "Assistant Mechanical / Electronics Engineering Manager", "description": "The\u00a0Assistant Engineering Manager will be responsible to lead and manage the engineering team for new project development by providing creative product concept and innovative technology design. Assist management ensuring the development projects are delivered on schedule and within budget.\n\nWhat You Will Achieve\n\nOversee product development and testing in order to ensure completion of projects\nProvide technical leadership and guidance / input within project execution team\nNPI Products planner from RFQ. / Schedule / EP to MP follow-up\nReview and validate the design and define corrective actions for customer complaints/incidents\nLiaise with project team, sales and customers on technical issues, specification definition and sample follow-up\nIdentified the skill of the staff and provide technical training to the staff\n\nWhat You Will Need\n\nDegree holder in Mechanical, Electronic Engineering or equivalent\nAt least 10 years\u2019 experience in\u00a0OBM / ODM product development especially SDA\nSolid knowledge in safety for US and EU regulations including food grade category\nHand-on experience with NX/UG is an advantage\nWilling to station in Shenzhen\nCandidate with more experience will be considered as Mechanical / Electronics Engineering Manager\n\nWe are an equal opportunity employer and welcome applications from all qualified candidates. Any interest candidate, please send your resume with expected salary and availability by clicking\u00a0\u201cApply Now\u201d.\n\n(Data collected will be treated as strictly confidential and will be used for recruitment purpose only and will be destroyed after the recruitment exercise when no longer required.)\n\n", "employment_types": ["Full Time", "Permanent"], "selling_points": ["Project Management", "Experience in OBM / ODM product development", "Willing to station in Shenzhen"], "locations": ["Wong Tai Sin Area"], "categories": ["Engineering", "Electrical / Electronics", "Engineering Project Management", "Mechanical"], "post_time": "2022-01-13T04:20:12Z", "salary": {"currency": null, "max": null, "min": null, "period": "monthly", "term": null}, "salary_visible": false, "title_keywords": ["engineering manager", "assistant"], "responsibilities": ["product concept", "guidance", "management", "regulations", "customer complaints", "data", "budget", "review", "design", "testing", "recruitment", "schedule", "liaise with"], "requirements": {"degrees": ["degree holder"], "majors": ["engineering"], "languages": [], "language_level": [], "hard_skills": ["planner", "no"], "soft_skills": ["creative", "leadership", "responsible", "innovative"], "languages_combined": []}, "experience_required": {"duration": ["at least 10 years"], "field": ["product development", "engineering"]}}, {"job_id": "100003009049056", "location_code": "hk", "company": "TalentQuest HR Limited", "job_title": "Project Manager / Assistant Project Manager (Lift and Escalator)", "description": "Our clients, some leading companies are currently looking for high calibers candidate to join their\u00a0professional team.\n\nResponsibilities:\n\nResponsible for project management of new installations and modernizations\nHandle project documentation and attend site meetings\nManage teams of Engineers, Supervisors. Technicians and Subcontracted staff\nSupervise the execution of works, materials, assemblies and documentation\nEnsure financial & performance targets of the projects are achieved\nRequirements:\n\nHigher Diploma or above in Engineering discipline\n8 years up of lift & escalator project management experience\nGood command of both written and spoken English & Chinese\nStrong planning, problem solving skills, with high level of resilience\u00a0and ability to work under pressure\nRelevant experience in elevator companies", "employment_types": ["Full Time"], "selling_points": ["5 days work", "New installations and modernizations", "New position"], "locations": ["Not Specified"], "categories": ["Building & Construction", "Building / Construction / QS", "Engineering", "Engineering Project Management", "Mechanical"], "post_time": "2022-01-14T08:00:03Z", "salary": {"currency": null, "max": null, "min": null, "period": "monthly", "term": null}, "salary_visible": false, "title_keywords": ["project manager", "assistant project manager"], "responsibilities": ["teams", "project management", "documentation", "attend site meetings", "project documentation"], "requirements": {"degrees": ["higher diploma or above"], "majors": ["engineering"], "languages": ["english", "chinese"], "language_level": ["good command"], "hard_skills": ["project management", "problem solving skills"], "soft_skills": ["project management", "problem solving skills", "work under pressure"], "languages_combined": [{"language": "english", "language_level": ["good command"]}, {"language": "chinese", "language_level": ["good command"]}]}, "experience_required": {"duration": ["8 years"], "field": ["project management", "relevant experience"]}}, {"job_id": "100003009047588", "location_code": "hk", "company": "REC Engineering Company Limited", "job_title": "Assistant Technical Officer (Ref.: ATO/22/0041)", "description": "Responsibilities\n\nAssist in simple equipment testing, installation and repairing;\nHandle Ad-hoc assignment when assigned\n\nRequirements\n\nF.5 / HKDSE or above ;\nAt least 2 years relevant experience in Electrical / Mechanical/ Chemical Engineering works;\nHolder of Registered Electrical Worker is preferred;\nProficient in MS Office applications;\nGood command of both English and Chinese\n\nBenefits and Package\u00a0\n\n13 days annual leave\nPublic holidays\nMedical Insurance (Out-patient, Hospitalization\u00a0and Dental coverage)\nLife insurance\nEducation subsidy / Sponsorship\nTravelling allowance\nFull pay Exam leave, marriage leave, compassionate leave\nStaff recreation club etc.\n\n\n\nAttractive remuneration package will be offered to the successful candidate\n\nPlease send in strict confidence with full resume stating the reference code and your current and expected salary to Human Resources Department, REC Engineering Company Limited, Units A-D, 15/F., Goodman Kwai Chung Logistics Centre, 585-609 Castle Peak Road, Kwai Chung, New Territories, Hong Kong or by\u00a0fax 2489 0044 or clicking \u201cApply Now\u201d button to apply.\n(Personal data provided\u00a0by applicants will be used strictly for recruitment purpose only.)", "employment_types": ["Full Time", "Permanent"], "selling_points": ["Assist in simple equipment testing", "equipment installation and repairing", "Electrical / Mechanical/ Chemical Engineering"], "locations": ["Kwai Tsing Area"], "categories": ["Engineering", "Chemical", "Electrical / Electronics", "Mechanical"], "post_time": "2022-01-14T03:30:58Z", "salary": {"currency": null, "max": null, "min": null, "period": null, "term": null}, "salary_visible": false, "title_keywords": ["assistant technical officer"], "responsibilities": ["ad-hoc", "installation", "testing"], "requirements": {"degrees": ["hkdse"], "majors": [], "languages": ["english", "chinese"], "language_level": ["good command"], "hard_skills": ["ms office"], "soft_skills": [], "languages_combined": [{"language": "english", "language_level": ["good command"]}, {"language": "chinese", "language_level": ["good command"]}]}, "experience_required": {"duration": ["at least 2 years"], "field": ["relevant experience", "engineering"]}}, {"job_id": "100003009049089", "location_code": "hk", "company": "Jebsen Motors Limited", "job_title": "Technician \u6a5f\u68b0\u7dad\u4fee\u6280\u8853\u54e1(Ref: PORSCHE-F044)", "description": "\u5de5\u4f5c\u5167\u5bb9\uff1a\n\n\u6309\u7167\u4fdd\u6642\u6377\u54c1\u724c\u7684\u7dad\u4fee\u6a19\u6e96\uff0c\u70ba\u8eca\u8f1b\u9032\u884c\u4fdd\u990a\u4fee\u7406\u3001\u8a3a\u65b7\n\u5354\u52a9\u57f9\u8a13\u5b78\u5f92\u53ca\u7dad\u4fee\u5de5\u5834\u7684\u65e5\u5e38\u904b\u4f5c\n\u9808\u7a7f\u8457\u5236\u670d\u3001\u5b89\u5168\u978b\uff0c\u9075\u5b88\u516c\u53f8\u696d\u52d9\u904b\u4f5c\u6d41\u7a0b\u53ca\u5b88\u5247\n\n\u00a0\u5165\u8077\u8981\u6c42\uff1a\n\n\u4e2d\u5b78\u7a0b\u5ea6\uff0c\u5fc5\u9808\u6301\u6709\u5b78\u5f92\u7562\u696d\u8b49\u66f8\u6216\u76f8\u95dc\u6587\u6191\u6216\u8b49\u66f8\u8ab2\u7a0b\n\u6700\u5c114\u5e74\u7684\u5927\u5ee0\u6c7d\u8eca\u7dad\u4fee\u53ca\u96fb\u5b50\u6a5f\u68b0\u7d93\u9a57\n\u5fc5\u9808\u6301\u6709\u79c1\u5bb6\u8eca\u53ca\u8f15\u578b\u8ca8\u8eca\u99d5\u99db\u57f7\u7167\n\u5177\u826f\u597d\u6e9d\u901a\u6280\u5de7\uff0c\u80fd\u8b80\u5beb\u7c21\u55ae\u4e2d\u82f1\u6587\uff0c\u61c2\u57fa\u672c\u96fb\u8166\u64cd\u4f5c\n\u4e3b\u52d5\u7a4d\u6975\uff0c\u56b4\u8b39\u8a8d\u771f\uff0c\u7368\u7acb\u6709\u8010\u6027\n\u5de5\u4f5c\u5730\u9ede: \u7d05\u78e1\u53ca\u67f4\u7063\n\n\u5c0d\u4ee5\u4e0a\u8077\u4f4d\u611f\u8208\u8da3\u7684\u7533\u8acb\u8005\uff0c\u8acb\u5c07\u60a8\u7684\u7c21\u6b77\u548c\u671f\u671b\u85aa\u916c\u901a\u904e\u4ee5\u4e0b\"Apply Now\"\u96fb\u90f5\u767c\u9001\u81f3\u96c6\u5718\u4eba\u529b\u8cc7\u6e90\u90e8\u3002\n\n\u5982\u9700\u77ad\u89e3\u6377\u6210\u96c6\u5718\u66f4\u591a\u8cc7\u8a0a\uff0c\u8acb\u767b\u9678\u96c6\u5718\u7db2\u7ad9www.jebsen.com\u6216\u8005\u4ee5\u4e0b\u9014\u5f91\uff1a\n\n\u65b0\u6d6a\u5fae\u535a\uff1a\u00a0\u00a0\u00a0\u00a0\u00a0http://weibo.com/jebsengroup\n\n\u5fae\u4fe1\uff1a\u00a0\u00a0\u00a0\u00a0 \u00a0\u00a0\u00a0\u00a0\u00a0\u00a0\u00a0\u00a0ID: jebsen1895\n\nLinkedIn: \u00a0 \u00a0 \u00a0 \u00a0 Jebsen Group\n\n\u00a0\u7533\u8acb\u8005\u63d0\u4f9b\u7684\u6240\u6709\u8cc7\u8a0a\u5c07\u50c5\u9650\u65bc\u62db\u8058\u7528\u9014\u3002\n\n\u00a0\u5728\u9019\u88e1\uff0c\u6210\u5c31\u6210\u529f\u3002", "employment_types": ["Full Time", "Permanent"], "selling_points": ["\u9999\u6e2f\u4fdd\u6642\u6377", "\u6a5f\u68b0\u7dad\u4fee", "\u512a\u539a\u6708\u5ea6\u82b1\u7d05, \u5e74\u7d42\u82b1\u7d05"], "locations": ["Chai Wan"], "categories": ["Engineering", "Electrical / Electronics", "Mechanical"], "post_time": "2022-01-14T08:06:09Z", "salary": {"currency": null, "max": null, "min": null, "period": "monthly", "term": null}, "salary_visible": false, "title_keywords": ["technician"], "responsibilities": [], "requirements": {"degrees": [], "majors": [], "languages": [], "language_level": [], "hard_skills": ["id"], "soft_skills": [], "languages_combined": []}, "experience_required": {"duration": [], "field": []}}, {"job_id": "100003009046827", "location_code": "hk", "company": "Johnson Controls Hong Kong Limited", "job_title": "Quality Assurance Engineer", "description": "What you will do\u00a0\u00a0\n\nThe person will in charge of Quality Circle to ensure all project works are meeting the quality standards. Responsible for identifying problems and suggest possible solutions in eliminating incidents.\n\nHow you will do it\n\nRevise and streamline the process from time-to-time in meeting customers' satisfaction\nEnsure all the work done are carried out in accordance with the project specifications and clients' requirements\nConduct regular review meeting with clients to streamline process and reduce the nuisance\nAttend regular meetings with Project Manager and Contractors\n\nWhat we look for\n\nRequired\n\nHigher Certificate in Building Services Engineering / Mechanical Engineering / Electrical Engineering or equivalent\nOver\u00a010\u00a0years\u2019 relevant work experience in Water Supply and Fire Services Installations\nQualified QA Auditor with not less than 3 years' experience in Quality Management/Audit\nHolder of valid certificate for Quality Management Systems Auditor/Lead Auditor Training Course certified by the International Register of Certified Auditors (IRCA)\nRegistered Electrical Worker qualified for Grade A Category 2 Electrical Work\nCompleted Safety Training Course for Site Management Staff provided by CIC\n\nPreferred\n\nGood communications and organization skills\nAttention to detail\u00a0\n\nInterest parties please send your application letter & CV including current and expected salary, date of availability to us.\n\nOnly the shortlisted candidates will be notified. Data collected would be used for recruitment purposes only.", "employment_types": ["Full Time", "Permanent"], "selling_points": ["Higher Cert. in BSE/Mechanical/Electrical Eng.", "Over 10 years' experience in Water Supply/Fire", "Registered Electrical Worker qualified for Grade A"], "locations": ["Kwun Tong"], "categories": ["Building & Construction", "Building / Construction / QS", "Engineering", "Electrical / Electronics", "Mechanical"], "post_time": "2022-01-16T21:50:17Z", "salary": {"currency": null, "max": null, "min": null, "period": "monthly", "term": null}, "salary_visible": false, "title_keywords": ["engineer"], "responsibilities": ["management", "data", "systems", "quality", "audit", "site management", "regular review", "specifications", "recruitment"], "requirements": {"degrees": ["certificate", "higher certificate"], "majors": ["electrical engineering", "engineering", "mechanical engineering", "building services", "quality management"], "languages": [], "language_level": [], "hard_skills": [], "soft_skills": ["organization skills", "attention to detail", "responsible"], "languages_combined": []}, "experience_required": {"duration": ["3 years", "10 years"], "field": ["quality management", "audit", "qa"]}}, {"job_id": "100003009050508", "location_code": "hk", "company": "WSP (Asia) Limited", "job_title": "Engineer - Electrical / HVAC / PDFS (for MEP projects)", "description": "Job Responsibilities:\n\nResponsible for building services design, tender preparation and project administration\nSite inspection and attend meetings for building development, and/or mission critical projects\nLiaise with clients, clients' consultants, contractors and authorities from concept to detailed design and construction administration\n\nRequirements:\n\nBachelor Degree or Higher Diploma\u00a0in Building Services Engineering,\u00a0Mechanical Engineering or Electrical\u00a0Engineering\nMinimum of 2 years relevant work experience in design and project management\nPrior experience in engineering consulting work or project management will be advantageous\nStrong sense of responsibility and organization\nStrong communication, presentation and project management skills\nCandidate with more experience and higher qualification will be considered for senior positions\n\nWhat we offer:\n\nCare and support for new parenthood\nLife, Medical and Dental Insurance\nWSP Professional Network\nOverseas Exchange Program\nMarriage Leave\n\nFor interested parties, please click below \"Apply now\" button to apply with your\u00a0resume\u00a0and\u00a0expected\u00a0salary.\u00a0 \u00a0\n\nAll applications will be treated in strict confidence and only be used for recruitment related purpose. Applicants not hearing from us within six weeks may consider their application filed for future reference. All personal data of unsuccessful applicants will be retained for 12 months for future recruitment purpose and will be destroyed afterward.", "employment_types": ["Full Time", "Permanent"], "selling_points": ["HVAC / PD / EL / FS Design", "Degree in Mechanical, BS or Electrical Engg.", "Min. 2 years work experience"], "locations": ["Kowloon Bay"], "categories": ["Engineering", "Electrical / Electronics", "Engineering Project Management", "Mechanical"], "post_time": "2022-01-14T10:35:03Z", "salary": {"currency": null, "max": null, "min": null, "period": "monthly", "term": null}, "salary_visible": false, "title_keywords": ["mep", "engineer"], "responsibilities": ["liaise with clients", "design", "site inspection", "project administration", "tender preparation", "attend meetings", "building services design", "administration"], "requirements": {"degrees": ["diploma", "degree", "bachelor"], "majors": ["electrical engineering", "building services", "engineering", "mechanical engineering"], "languages": [], "language_level": [], "hard_skills": ["project management"], "soft_skills": ["sense of responsibility", "project management skills", "communication", "project management", "presentation"], "languages_combined": []}, "experience_required": {"duration": ["minimum of 2 years"], "field": ["project management", "engineering", "design", "consulting"]}}, {"job_id": "100003009045748", "location_code": "hk", "company": "Pioneer Management Limited", "job_title": "Technical Assistant (Building Works)", "description": "\u00a0\u8077\u8cac\n\n\n\u57f7\u884c\u7269\u696d\u5c4b\u5b87\u8a2d\u5099\u7684\u65e5\u5e38\u7dad\u8b77\u4fdd\u990a\u3001\u4fee\u7406\u53ca\u6539\u52d5\u5de5\u4f5c\n\u5354\u52a9\u76e3\u7763\u5916\u5224\u627f\u8fa6\u5546\u4e26\u78ba\u4fdd\u5176\u4f9d\u7167\u516c\u53f8\u8981\u6c42\u53ca\u5b89\u5168\u6e96\u5247\u65bd\u5de5\n\u5b9a\u671f\u64b0\u5beb\u7c21\u55ae\u8a2d\u5099\u6027\u80fd\u5831\u544a\n\u4f9d\u7167\u516c\u53f8\u5b89\u5168\u653f\u7b56\u548c\u7a0b\u5e8f\u9032\u884c\u5176\u4ed6\u5c4b\u5b87\u88dd\u5099\u5de5\u4f5c\n\n\n\n\u5165\u8077\u8981\u6c42\n\n\n\u5177\u5169\u5e74\u7dad\u4fee\u5de5\u4f5c\u7d93\u9a57\uff0c\u5305\u62ec\u6a5f\u68b0\u6216\u7269\u696d\u7dad\u4fee\n\u6301\u6a5f\u68b0\u5de5\u7a0b / \u76f8\u95dc\u6280\u8853\u8b49\u66f8\u8005\u512a\u5148\u8003\u616e\n\u826f\u597d\u4e2d\u6587\u8a9e\u8a00\u80fd\u529b\n\n\u5de5\u4f5c\u6642\u9593\u00a0\u00a0\n\n\u8f2a\u73ed\u5236\uff0c\u4e3b\u8981\u70ba\u65e5\u9593\u5de5\u4f5c\n\u4e00\u661f\u671f\u5de5\u4f5c\u516d\u5929\uff0c\u6bcf\u73ed8\u5c0f\u664215\u5206\u9418 (\u5305\u62ec1\u5c0f\u6642\u7528\u81b3\u6642\u9593)\n\n\u798f\u5229\n\n\u8fb2\u66c6\u5e74\u82b1\u7d05\u3001\u914c\u60c5\u82b1\u7d05\u3001\u4ea4\u901a\u6d25\u8cbc\u3001\u52a0\u73ed\u6d25\u8cbc\u3001\u5e74\u5ea6\u5b89\u5168\u734e\u91d1\u3001\u5b63\u5ea6\u7279\u5225\u51fa\u52e4\u734e\u91d1\u3001\u50f1\u4e3b\u984d\u5916\u5f37\u7a4d\u91d1\u4f9b\u6b3e\u3001\u91ab\u7642\u4fdd\u969c \u2013 \u5305\u62ec\u5bb6\u5c6c\u3001\u81ea\u9858\u6027\u7259\u79d1\u4fdd\u5065 \u2013 \u5305\u62ec\u5bb6\u5c6c\u3001\u4eba\u58fd\u4fdd\u96aa\u3001\u751f\u65e5\u5047\u671f\u3001\u984d\u5916\u6709\u85aa\u5e74\u5047\u3001\u52de\u5de5\u53ca\u516c\u773e\u5047\u671f\u3001\u5a5a\u5047\u3001\u7522\u5047\u3001\u4f8d\u7522\u5047\u3001\u521d\u751f\u5b30\u5152\u79ae\u7269\u3001\u9ad4\u80b2\u9928\u3001\u514d\u8cbb\u7a7f\u68ad\u5df4\u58eb\n\n\u7533\u8acb\u8fa6\u6cd5\n\n\u7533\u8acb\u8005\u8acb\u628a\u7533\u8acb\u4fe1\u53ca\u5c65\u6b77\u50b3\u771f\u81f32753 2244\uff1b\u6216\u96fb\u90f5\u81f3\u516c\u53f8\u96fb\u90f5\uff1b\u6216\u5bc4\u5f80\u9999\u6e2f\u570b\u969b\u6a5f\u5834\u8d85\u7d1a\u4e00\u865f\u8ca8\u7ad9\u8fa6\u516c\u5927\u6a13\u5317\u5ea7\u516d\u6a13\u4eba\u529b\u8cc7\u6e90\u90e8\u6536 (\u8acb\u8a3b\u660e\u7533\u8acb\u8077\u4f4d\u53ca\u53c3\u8003\u7de8\u865f)\n\n\u00a0\u672c\u516c\u53f8\u7db2\u5740:\u00a0https://careers.hactl.com/\n\n\u00a0\u5982\u7533\u8acb\u4eba\u65bc\u56db\u661f\u671f\u5167\u672a\u7372\u9762\u8a66\u901a\u77e5\uff0c\u5373\u8868\u793a\u8a72\u7533\u8acb\u672a\u80fd\u6210\u529f\u3002\u7533\u8acb\u4eba\u6240\u63d0\u4f9b\u4e4b\u500b\u4eba\u8cc7\u6599\u53ea\u4f9b\u62db\u8058\u4e4b\u7528\uff0c\u672a\u88ab\u8058\u7528\u4eba\u58eb\u4e4b\u8cc7\u6599\u6703\u5728\u516d\u500b\u6708\u5167\u88ab\u92b7\u6bc0\u3002", "employment_types": ["Full Time", "Permanent"], "selling_points": ["Maintenance building Works in Housing Estate", "Diploma or Higher Certificate in Building Studies", "Hong Kong Institute of Vocation Education (IVE)"], "locations": ["Wong Tai Sin Area"], "categories": ["Building & Construction", "Building / Construction / QS", "Engineering", "Electrical / Electronics", "Mechanical"], "post_time": "2022-01-13T08:33:26Z", "salary": {"currency": null, "max": null, "min": null, "period": "monthly", "term": null}, "salary_visible": false, "title_keywords": ["technical assistant"], "responsibilities": [], "requirements": {"degrees": [], "majors": [], "languages": [], "language_level": [], "hard_skills": [], "soft_skills": [], "languages_combined": []}, "experience_required": {"duration": [], "field": []}}, {"job_id": "100003009048808", "location_code": "hk", "company": "Hong Kong Air Cargo Terminals Limited (Hactl)", "job_title": "\u7dad\u4fee\u6280\u8853\u54e1 (\u5c4b\u5b87\u7269\u696d\u8a2d\u65bd) Technician", "description": "\u8cc7\u6df1\u6280\u8853\u54e1 / \u6280\u8853\u54e1\n\n\u8ca0\u8cac\u5de1\u67e5\u3001\u76e3\u5bdf\u3001\u7dad\u4fee\u53ca\u6025\u4fee\u9152\u5e97\u5404\u985e\u8a2d\u5099\u7cfb\u7d71\u4ee5\u53ca\u5176\u4ed6\u7dad\u4fee\u5de5\u4f5c\uff1b\n\u5b9a\u671f\u6aa2\u67e5\u5ba2\u623f\u548c\u6240\u6709\u8a2d\u5099\uff0c\u4ee5\u78ba\u4fdd\u826f\u597d\u72c0\u6cc1\uff0c\u4e26\u78ba\u4fdd\u5feb\u901f\u8655\u7406\u6240\u6709\u6545\u969c\u554f\u984c\uff1b\n\u826f\u597d\u7cb5\u8a9e\u3001\u61c2\u8b80\u5beb\u4e2d\u6587\u53ca\u5177\u826f\u597d\u6e9d\u901a\u8207\u5c0d\u8a71\u6280\u5de7\uff1b\n\u614b\u5ea6\u8aa0\u61c7\u6709\u79ae\u3001\u5177\u8cac\u4efb\u611f\u3001\u5b88\u6642\u3001\u52e4\u596e\uff1b\n\u6bcf\u6708\u516d\u5929\u4f11\u606f\u65e5\uff0c\u6bcf\u5929\u5de5\u4f5c\u4e5d\u5c0f\u6642\uff0c\u516c\u773e\u5047\u671f\uff0c\u81b3\u98df\u6d25\u8cbc\u3002\n\n\u6709\u610f\u7533\u8acb\u8005\u8acb \u6309 APPLY NOW\u7533\u8acb", "employment_types": ["Full Time", "Permanent"], "selling_points": ["\u7269\u696d\u6a13\u5b87\u8a2d\u5099\u4e4b\u7dad\u4fee\u3001\u4fdd\u990a", "\u8f2a\u73ed\u5236\uff0c\u4e3b\u8981\u70ba\u65e5\u9593\u5de5\u4f5c", "\u4eab\u6709\u4ea4\u901a\u6d25\u8cbc, \u96d9\u7ce7\u53ca\u82b1\u7d05"], "locations": ["Airport Area"], "categories": ["Engineering", "Draftsman", "Mechanical", "Property / Real Estate", "Others"], "post_time": "2022-01-14T07:21:48Z", "salary": {"currency": null, "max": null, "min": null, "period": "monthly", "term": null}, "salary_visible": false, "title_keywords": ["technician"], "responsibilities": [], "requirements": {"degrees": [], "majors": [], "languages": [], "language_level": [], "hard_skills": [], "soft_skills": [], "languages_combined": []}, "experience_required": {"duration": [], "field": []}}, {"job_id": "100003009049162", "location_code": "hk", "company": "Soravit Hotels Group Limited", "job_title": "\u8cc7\u6df1\u6280\u8853\u54e1 / \u6280\u8853\u54e1", "description": "Responsibilities\n\nAssist in monitoring of BS submissions including drawings and equipment. Spatial coordination of building services installation via combined services drawings\nAssist in the coordination of BS installation program with master construction program and establish the detail work sequence of building services works on site\nCoordinate with all BS subcontractors as well as builder's representatives on site to effectively integrate BS systems into the building. Liaise with Statutory Authorities and Utilities Companies on BS work\nAttend site meetings, supervise progress and monitor the quality of BS works on site\nParticipate in testing and commissioning of BS System and monitor the defect rectification prior to system hand over\n\nRequirements\n\nDegree holder in Building Services Engineering or equivalent\nWith 1 year relevant experience in Building Services\nGood command of spoken and written English & Chinese\nProactive, outgoing and initiative\nSound interpersonal skills and a good team player\nConfident in liaising and coordinating with different internal and external parties\nCandidate with more experience will be considered as Building Services Engineer.\n\nAttractive salary and fringe benefits will be offered to the successful candidates. Please apply with full resume, available date, present and expected salary and quoting the reference code on the letter & envelope to\u00a0THE HUMAN RESOURCES & TRAINING DEPARTMENT, HIP HING CONSTRUCTION CO., LTD.,\u00a011/F., Chevalier Commercial Centre, No. 8 Wang Hoi Road, Kowloon Bay, Hong Kong OR click \"Apply Now\"\u00a0OR fax to 2530 4360.\n\nCompany Website:\u00a0www.hiphing.com.hk\nAll personal data collected will be used for recruitment purposes only.\u00a0\nApplicants who are not invited for an interview within 8 weeks may consider their applications unsuccessful.\nPlease enable the \"Pop-up\" setting of your browser, click\u00a0here\u00a0for steps.\u00a0", "employment_types": ["Full Time"], "selling_points": [], "locations": ["Tsim Sha Tsui"], "categories": ["Engineering", "Electrical / Electronics", "Mechanical", "Others", "Technician"], "post_time": "2022-01-14T08:12:01Z", "salary": {"currency": null, "max": null, "min": null, "period": "monthly", "term": null}, "salary_visible": false, "title_keywords": ["\u6280\u8853\u54e1"], "responsibilities": ["installation", "commissioning", "monitoring", "coordinate with", "systems", "monitor", "drawings", "bs", "quality", "bs installation", "testing", "rectification", "coordination", "liaise with", "attend site meetings"], "requirements": {"degrees": ["degree holder"], "majors": ["building services", "engineering"], "languages": ["english", "chinese"], "language_level": ["good command"], "hard_skills": [], "soft_skills": ["outgoing", "confident", "good team player", "interpersonal skills", "proactive", "initiative"], "languages_combined": [{"language": "english", "language_level": ["good command"]}, {"language": "chinese", "language_level": ["good command"]}]}, "experience_required": {"duration": ["1 year"], "field": ["building services", "relevant experience"]}}, {"job_id": "100003009044729", "location_code": "hk", "company": "Ladon Distributor Co Ltd", "job_title": "Project Manager - (Mechanical / Environmental)  5 DAYS WORK", "description": "Requirements\nBachelor Degree in electrical / mechanical engineering\nGood problem-solving skills\nInnovative\nGood academic background in mechanical engineering or related field is preferred\nAt least five years post graduate experience in project management & execution in the field of Electrical & Mechanical field\nGood knowledge of operation of water or waste water treatment facilities in Hong Kong\nAggressive, able to work under pressure and independently with limited instruction\nFluent in English, Mandarin and Cantonese\nJob Description\nLead project team and coordinate with all project stakeholders for project execution\nResponsible for overall project management to meet the contractual, technical, quality and cost requirement within work schedule\nTo closely monitor work progress of our projects and problem solving where arise\nProject execution including presentation, equipment submission, on-site testing and commissioning for mechanical water and waste water treatment equipment & instrumentations\nAssist client to develop new applications and projects\nPost-sales services\n\nInterested parties, please apply with CV including work experience and expected salary via email to Ms. Lau.", "employment_types": ["Full Time", "Permanent"], "selling_points": ["Project lead", "Bachelor Degree in electrical / mechanical", "Responsible for overall project management"], "locations": ["Not Specified"], "categories": ["Engineering", "Electrical / Electronics", "Engineering Project Management", "Mechanical"], "post_time": "2022-01-13T10:15:31Z", "salary": {"currency": null, "max": null, "min": null, "period": "monthly", "term": null}, "salary_visible": false, "title_keywords": ["project manager"], "responsibilities": ["cost", "commissioning", "coordinate with", "quality", "monitor", "testing", "develop", "project management", "schedule"], "requirements": {"degrees": ["degree", "bachelor"], "majors": ["mechanical engineering"], "languages": ["cantonese", "english", "mandarin"], "language_level": ["fluent"], "hard_skills": ["problem-solving skills", "project management"], "soft_skills": ["independently", "project management", "problem-solving skills", "innovative", "work under pressure"], "languages_combined": [{"language": "cantonese", "language_level": ["fluent"]}, {"language": "english", "language_level": ["fluent"]}, {"language": "mandarin", "language_level": ["fluent"]}]}, "experience_required": {"duration": ["at least five years"], "field": ["project management"]}}, {"job_id": "100003009044851", "location_code": "hk", "company": "Alliance Construction Materials Limited", "job_title": "Senior Engineer / Engineer  (Mechanical Engineering)", "description": "Alliance Construction Materials Limited\n\nWhen you choose Alliance, it means you will be working alongside some of our industry's best people while making a real contribution to the most exciting construction projects in Hong Kong. \u00a0Because we hire people as employees with a view to training and educating them for their long-term development, our employees have been able to develop their skills and thrive in a fast-paced and entrepreneurial environment. \u00a0Alliance's business culture is performance-based and customer-driven. So, we are looking for an individual who is motivated, a real team player and who shares our commitment to making it happen for our customers.\n\nSenior Engineer / Engineer\u00a0 (Mechanical Engineering)\n\n\nThis position is suited to a highly motivated individual, who is determined to develop his/her career in a thriving business. You will be required to :\n\nPlant Maintenance\nPlanned Preventative Maintenance\nShift Duty \u2013 if necessary\n\nJOB DESCRIPTION\n\nUtilize advanced skills to perform complex preventive maintenance and corrective repair of plant, industrial systems, barge unloading system and equipment. Working under limited supervision, monitor plant system operations and performance. Utilize several trade skills from such areas as mechanical, plumbing, electrical, painting, programming, automation and ice manufacturing system.\n\n\n\nESSENTIAL DUTIES AND RESPONSIBILITIES\n\n\n\nComply with all applicable codes, regulations, governmental and Company directives related to building operations and work safety.\nInspect plant systems including production facilities and plumbing to ensure operation of equipment is within design capabilities and environmental conditions prescribed by the end user.\nPrepare tender specifications, design drawing, pre-tender visit, tender report and follow-up on-site work.\nOversee and inspect the work performed by outside contractors. Contracted work includes overhaul, retrofit, conveyor system, storage tank, and cleaning system.\nPerform assigned repairs, emergency and preventive maintenance. Complete maintenance and repair records as required.\nReview assigned work orders. Estimate time and materials needed to complete the repair. Order necessary materials and supplies to complete all tasks.\nMaintain an energy management program to ensure measures are taken to operate all systems in the most efficient manner to minimize operating costs.\nMaintain the plant production system, including element and hydraulic & pneumatic repairs or replacements.\nPerform welding, on-site measurement, overhaul assembly and retrofit tasks as needed.\nRespond quickly to emergency situations and coordinate necessary resources to handle the situation.\nPerform other duties as assigned by the superior.\n\nSUPERVISORY RESPONSIBILITIES\n\nFormal supervisory responsibilities in this position. Providing technical guidance and/or training to coworkers.\n\n\u00a0Requirements :\n\nDegree / Higher Diploma in Mechanical Engineering or equivalent with a minimum of 3-5 years\u2019 experience in mechanical maintenance of production plant or large industrial equipment\nGood analytical and diagnostic skills for defect investigation and problem solving\nGood communication and supervisory skills for dealing with workmen, contractors and suppliers\nGood practical experience and technical knowledge of power plant equipment\nGood command of English and Chinese both spoken and written\n\nThose with less experience will be considered for the post of Engineer.\n\n\n\nA competitive package will be offered to the successful candidate who is willing to develop and grow with us.\u00a0\u00a0 If you wish to be considered for this opportunity, please apply now with your full resume and present and expected salary to HR team.", "employment_types": ["Full Time", "Permanent"], "selling_points": ["Plant Maintenance", "Planned Preventative Maintenance", "Shift Duty \u2013 if necessary"], "locations": ["Tsing Yi"], "categories": ["Engineering", "Electrical / Electronics", "Mechanical", "Others"], "post_time": "2022-01-13T06:27:33Z", "salary": {"currency": null, "max": null, "min": null, "period": "monthly", "term": null}, "salary_visible": false, "title_keywords": ["senior engineer", "engineer"], "responsibilities": ["regulations", "operations", "design", "maintain", "costs", "perform other duties", "monitor", "measurement", "tender", "report", "guidance", "management", "review", "specifications", "cleaning", "maintenance", "systems", "coordinate", "repair"], "requirements": {"degrees": ["diploma", "degree"], "majors": ["mechanical engineering"], "languages": ["english", "chinese"], "language_level": ["good command"], "hard_skills": ["problem solving", "maintenance"], "soft_skills": ["problem solving", "communication"], "languages_combined": [{"language": "english", "language_level": ["good command"]}, {"language": "chinese", "language_level": ["good command"]}]}, "experience_required": {"duration": ["minimum of 3-5 years"], "field": ["engineering", "maintenance"]}}, {"job_id": "100003009042341", "location_code": "hk", "company": "Sun Fook Kong E&M Management Limited", "job_title": "Assistant Building Services Engineer (Ref No: IS/2022) (Fresh Graduate is also welcome)", "description": "Holder of Degree in Building Services Engineering/ Mechanical/ Electrical Engineering or equivalent\nMinimum 3 years\u2019 working experience in BS/ E&M for government project (Housing Authority projects will be advantage)\nResponsible for building services work in building project operation, planning, supervision and site coordination\nPerform site coordination work with client, consultants, sub-contractors/ suppliers and government department\nFresh Graduate will be considered as Graduate Engineer\nInterested parties, please send detailed resume with expected salary to The Deputy Director - Administration,\u00a07/F, High Fashion Centre, 1-11 Kwai Hei Street, Kwai Chung, New Territories, Hong Kong or by e-mail via \"Apply Now\" or by fax (2511 3209)\nAll data collected will be used for recruitment purpose only and will be destroyed after three months", "employment_types": ["Full Time", "Permanent"], "selling_points": [], "locations": ["Not Specified"], "categories": ["Building & Construction", "Building / Construction / QS", "Engineering", "Electrical / Electronics", "Mechanical"], "post_time": "2022-01-12T07:07:38Z", "salary": {"currency": null, "max": null, "min": null, "period": null, "term": null}, "salary_visible": false, "title_keywords": ["building services engineer", "assistant"], "responsibilities": ["planning", "site coordination", "bs"], "requirements": {"degrees": ["degree", "fresh graduate"], "majors": ["building services", "engineering", "electrical engineering"], "languages": [], "language_level": [], "hard_skills": [], "soft_skills": ["coordination", "responsible"], "languages_combined": []}, "experience_required": {"duration": ["minimum 3 years"], "field": []}}, {"job_id": "100003009046859", "location_code": "hk", "company": "Cloud Light Technology Limited", "job_title": "Optical Product Engineer (Job Ref.Apply-HK-2101-OPE)", "description": "Engineering Firm located in Tuen Mun invites:\n\nCAD Draftsman / Project Coordinator\n\nJob Duties:\n\n- \u00a0\u00a0\u00a0\u00a0\u00a0\u00a0\u00a0\u00a0\u00a0\u00a0 CAD drafting;\u2028- prepare shop drawings submissions, and technical document\u00a0submission for Projects; \u00a0\u00a0\n\n- \u00a0\u00a0\u00a0\u00a0\u00a0\u00a0\u00a0\u00a0\u00a0\u00a0 To coordinate and liaise with vendors, and suppliers;\n\n- \u00a0\u00a0\u00a0\u00a0\u00a0\u00a0\u00a0\u00a0\u00a0\u00a0 To coordinate and organize project meetings;\n\n- \u00a0\u00a0\u00a0\u00a0\u00a0\u00a0\u00a0\u00a0\u00a0\u00a0 To supervise the site work progress\u2028\n\n- \u00a0\u00a0\u00a0\u00a0\u00a0\u00a0\u00a0\u00a0\u00a0\u00a0 To assist manager in daily work and ad hoc projects as assigned;\n\nRequirements:\n\n- \u00a0\u00a0\u00a0\u00a0\u00a0\u00a0\u00a0\u00a0\u00a0\u00a0 Diploma or above in Architectural, Electrical or Mechanical Studies;\n\n- \u00a0\u00a0\u00a0\u00a0\u00a0\u00a0\u00a0\u00a0\u00a0\u00a0 Interest in theatre & Stage Lighting;\n\n- \u00a0\u00a0\u00a0\u00a0\u00a0\u00a0\u00a0\u00a0\u00a0\u00a0 Proficient in MS Word, Excel, AutoCAD and Chinese Word Processing;\n\n- \u00a0\u00a0\u00a0\u00a0\u00a0\u00a0\u00a0\u00a0\u00a0\u00a0 Able to work at multi-tasking, good communication and negotiation skills;\n\n- \u00a0\u00a0\u00a0\u00a0\u00a0\u00a0\u00a0\u00a0\u00a0\u00a0 Good command of written/spoken English and Chinese;\n\n- \u00a0\u00a0\u00a0\u00a0\u00a0\u00a0\u00a0\u00a0\u00a0\u00a0 knowledge in Structure calculation is an advantage;\n\n- \u00a0\u00a0\u00a0\u00a0\u00a0\u00a0\u00a0\u00a0\u00a0\u00a0 Self-motivated, able to work independently and under pressure and meet tight deadlines;\n\n- \u00a0\u00a0\u00a0\u00a0\u00a0\u00a0\u00a0\u00a0\u00a0\u00a0 Immediate available is a must\n\nNO AGENCY", "employment_types": ["Full Time", "Permanent"], "selling_points": ["Product characterization, Failure Analysis", "Test Program Development", "Electronic Engineering or Applied Physics"], "locations": ["Shatin Area"], "categories": ["Engineering", "Electrical / Electronics", "Manufacturing & Production", "Mechanical"], "post_time": "2022-01-14T01:29:30Z", "salary": {"currency": null, "max": null, "min": null, "period": "monthly", "term": null}, "salary_visible": false, "title_keywords": ["engineer"], "responsibilities": ["coordinate", "liaise with", "ad hoc projects", "drawings"], "requirements": {"degrees": ["diploma or above"], "majors": [], "languages": ["english", "chinese"], "language_level": ["good command", "proficient"], "hard_skills": ["excel", "no", "chinese word processing", "ms word", "autocad"], "soft_skills": ["self-motivated", "work independently", "under pressure", "meet tight deadlines", "communication", "multi-tasking", "negotiation skills"], "languages_combined": [{"language": "english", "language_level": ["good command"]}, {"language": "chinese", "language_level": ["good command", "proficient"]}]}, "experience_required": {"duration": [], "field": []}}, {"job_id": "100003009046805", "location_code": "hk", "company": "Dah Chong Hong (Motor Service Centre) Limited", "job_title": "Technical Officer \u2013 Automotive", "description": "Job Highlights\n\nOptical product engineer (R&D)\nProduct characterization and development\nWorking Location in Hong Kong Science Park\n\nJob Role and Responsibilities\n\nThe successful candidates will join Hong Kong-based optical product R&D team and be involved in the development of high-speed fiber-optic transceiver products for data center applications.\n\nCharacterize and qualify key optical and RF components for opto-electronics products\nVerify new design, and characterize new products in alpha/beta phase\nDevelop software for products/components evaluation and demo\nPerform failure analysis and data analysis for design and yield improvement\nWorks with hardware and firmware team on new products bring up\nIntroduce new products to factory\nApplication support to customer\nOccasional traveling is required\n\nSkills Required\n\nFamiliar with the principle of fiber optics and semiconductor device physics\nFamiliar with optical components testing methodology\nProgramming knowledge of C/C++, LabVIEW or python is preferable\nKnowledge of electronic circuitry and firmware debug would be a plus\nAbility to summarize and communicate data and progress in a clear, understandable fashion\nAbility to work independently and have good problem-solving skills\nGood command of English and Chinese\n\nQualifications\n\nBachelor\u2019s degree or above in Electronic Engineering or Applied Physics or equivalent discipline with preferable 1 year of related working experience\nCandidate with more experience will be considered as senior engineer\nFresh graduate will also be considered\n\nApplication:\n\nTo apply, please email\u00a0us your resume, your availability to report duty and quote the Job Ref.\nOnly short-listed candidates will be notified. Personal data provided by applicants will be used for consideration of an application only.\n\nApplication Deadline:\n\nUntil this position is filled.\nResumes received will strictly be used for recruitment-related purpose.", "employment_types": ["Full Time", "Permanent"], "selling_points": [], "locations": ["Kowloon Bay"], "categories": ["Engineering", "Engineering Project Management", "Manufacturing & Production", "Mechanical"], "post_time": "2022-01-14T01:14:00Z", "salary": {"currency": null, "max": null, "min": null, "period": "monthly", "term": null}, "salary_visible": false, "title_keywords": ["technical officer"], "responsibilities": ["software", "data", "analysis", "design", "develop", "data analysis", "hardware", "evaluation"], "requirements": {"degrees": ["degree or above", "bachelor", "fresh graduate"], "majors": ["engineering", "physics"], "languages": ["english", "chinese"], "language_level": ["good command"], "hard_skills": ["plus", "c++", "c", "programming", "python", "problem-solving skills", "labview"], "soft_skills": ["clear", "problem-solving skills", "work independently"], "languages_combined": [{"language": "english", "language_level": ["good command"]}, {"language": "chinese", "language_level": ["good command"]}]}, "experience_required": {"duration": ["1 year"], "field": ["related", "senior engineer", "engineering"]}}, {"job_id": "100003009048798", "location_code": "hk", "company": "WM HOTEL", "job_title": "\u8cc7\u6df1\u7576\u503c\u5de5\u7a0b\u5e2b / \u7576\u503c\u5de5\u7a0b\u5e2b / \u5de5\u7a0b\u90e8\u6280\u5de5 / \u5f71\u8996\u6280\u8853\u54e1", "description": "Responsibilities:\n\nApply type approval and homologation for passenger car\nCommunicate with principles and government departments on homologation issues\nProvide technical support to service centres\nAssist in conducting technical training and repairing enhancement programs\nRequirements:\n\nHigher Diploma or above in Automotive, Mechanical Engineering or related disciplines\n3 year\u2019s relevant experience in motor industry\nGood command in both written and spoken English and Chinese\nPossess apprenticeship in Automotive Engineering will be an advantage\nValid driving license 1, 2 is required\nIndependent, well-organized and self-motivated achievers\n\nBeing part of the largest motor group in Hong Kong with a portfolio of major motor brands, we offer attractive salary, discretionary bonus, medical benefits and generous fringe benefits together with good career prospect to the successful candidate. For interested parties, please send your resume stating expected salary\u00a0by clicking \"Apply Now\".\n\nWe are an equal opportunities employer. Personal data collected will be treated in strict confidence and used for recruitment purposes only. All applications may be considered for other suitable positions with DCH Group / CITIC Pacific Group and the personal data collected will be deleted from our files after 6 months from the date of application.\n\nPlease visit our website at\u00a0http://www.dchml.com.hk\n\n(Personal data collected will be used for recruitment-related purpose only.)", "employment_types": ["Full Time"], "selling_points": ["\u975e\u4fdd\u8b49\u5e74\u7d42\u734e\u91d1", "\u514d\u8cbb\u8eab\u9ad4\u6aa2\u67e5", "\u5728\u8077\u57f9\u8a13"], "locations": ["Sai Kung"], "categories": ["Engineering", "Electrical / Electronics", "Mechanical", "Others", "Technician"], "post_time": "2022-01-14T07:19:39Z", "salary": {"currency": null, "max": null, "min": null, "period": "monthly", "term": null}, "salary_visible": false, "title_keywords": [], "responsibilities": ["communicate with", "technical support"], "requirements": {"degrees": ["higher diploma or above"], "majors": ["related disciplines", "mechanical engineering"], "languages": ["english", "chinese"], "language_level": ["good command"], "hard_skills": [], "soft_skills": ["self-motivated", "independent", "well-organized"], "languages_combined": [{"language": "english", "language_level": ["good command"]}, {"language": "chinese", "language_level": ["good command"]}]}, "experience_required": {"duration": ["3 year"], "field": ["relevant experience"]}}, {"job_id": "100003009042237", "location_code": "hk", "company": "Arup", "job_title": "Engineer / Project Engineer / Senior Engineer (Resource & Waste Management)", "description": "WM HOTEL is a newly built hotel and resort which located inshore at the city of Sai Kung in Hong Kong, equipped with 260 guestrooms, most of the guestrooms overlook the sea with balcony, food and beverage facilities, health centre, swimming pool, shopping arcade, car park and etc. We are sincerely inviting high calibre and energetic individuals to join our Team.\n\nWM \u9152\u5e97 \u662f\u4e00\u6240\u4f4d\u65bc\u9999\u6e2f\u897f\u8ca2\u5e02\u4e2d\u5fc3\u5168\u65b0\u8208\u5efa\u7684\u8fd1\u6d77\u5ea6\u5047\u5f0f\u9152\u5e97,\u9152\u5e97\u64c1\u6709260\u9593\u5ba2\u623f,\u5176\u5927\u90e8\u4efd\u623f\u9593\u5747\u5efa\u6709\u967d\u53f0\u53ca\u53ef\u773a\u671b\u6d77\u666f,\u66f4\u5099\u6709\u9910\u98f2\u8a2d\u65bd,\u5065\u8eab\u4e2d\u5fc3,\u6cf3\u6c60,\u5546\u5e97\u53ca\u505c\u8eca\u5834\u7b49\u3002 \u6211\u5011\u8aa0\u9080\u6709\u5e79\u52c1\u4e26\u5c0d\u5de5\u4f5c\u5145\u6eff\u71b1\u8aa0\u7684\u60a8,\u52a0\u5165\u6211\u5011\u9019\u500b\u5927\u5bb6\u5ead\u3002\n\nPermanent Staff Enjoy\u5168\u8077\u54e1\u5de5\u53ef\u4eab:\nCompetitive Pay \u53ef\u89c0\u85aa\u91d1\n\nDiscretionary Gratuity \u975e\u4fdd\u8b49\u5e74\u7d42\u734e\u91d1\n\nMedical Benefit \u91ab\u7642\u8914\u5229\n\nFree body check \u514d\u8cbb\u8eab\u9ad4\u6aa2\u67e5\n\nOn-the-job Training \u5728\u8077\u57f9\u8a13\n\nPromotion \u5347\u9077\u6a5f\u6703\n\nMarriage Leave \u5a5a\u5047\n\nAnnual Leave \u6709\u85aa\u5e74\u5047\n\nDuty Meal \u514d\u8cbb\u81b3\u98df\n\nCompassionate Leave \u6069\u6064\u5047\n\nStaff Activities \u54e1\u5de5\u6d3b\u52d5\n\nTransportation Allowance \u4ea4\u901a\u6d25\u8cbc\n\n5-Day Work Week \u4e94\u5929\u5de5\u4f5c\u5468\n\nWe offer attractive remuneration package and excellent career opportunities to the right candidate, please apply and submit your resume with expected salary to the recruitment office by following methods\n\n\u6709\u610f\u7533\u8acb\u8005\u8acb\u6309 APPLY NOW\u7533\u8acb \u00a0\u00a0\u00a0\n\n", "employment_types": ["Full Time", "Permanent"], "selling_points": [], "locations": ["Kowloon City Area"], "categories": ["Engineering", "Chemical", "Building & Construction", "Civil / Structural", "Mechanical"], "post_time": "2022-01-13T07:45:49Z", "salary": {"currency": null, "max": null, "min": null, "period": null, "term": null}, "salary_visible": false, "title_keywords": ["senior engineer", "engineer", "project engineer"], "responsibilities": ["recruitment"], "requirements": {"degrees": [], "majors": [], "languages": [], "language_level": [], "hard_skills": [], "soft_skills": ["energetic"], "languages_combined": []}, "experience_required": {"duration": [], "field": []}}, {"job_id": "100003009046033", "location_code": "hk", "company": "Airport Authority Hong Kong", "job_title": "Construction Superintendent, Electrical & Mechanical", "description": "Job Duties:\n\nResponsible for the project execution and management\nLiaise, communicate and coordinate with different parties including sub-contractors for on-site progress and ensure workmanship is according to contract standards.\nCoordinate with clients, suppliers, sub-contractors and technical staff\nHandle other ad-hoc projects/tasks as assigned.\n\n\u00a0Job Requirements:\n\nMinimum Higher Diploma in Building Services or Engineering-related disciplines\nAt least 2-3 years' relevant working experience, preferably with Main Contractor(Fresh graduate will also be considered)\nExperience including CSD/CBWD coordination, utilities liaison and project management are essential\nGood technical knowledge in either Building Services/Electrical/Mechanical Engineering\nProficient in English and Chinese, good communication and interpersonal skills; Proactive personality is preferred\nAble to work independently with good problem solving skills\n\nInterested parties, please send your detailed resume including employment history and expected salary by clicking \"Apply Now\".\n\nInformation provided by applicants will be treated in strict confidence and used only for recruitment purposes.\u00a0The Company will retain unsuccessful job applications for a maximum period of one year.", "employment_types": ["Full Time"], "selling_points": ["At least 8 years' relevant experience", "Site supervision of E&M works", "Installation of airport works"], "locations": ["Airport Area"], "categories": ["Engineering", "Electrical / Electronics", "Mechanical"], "post_time": "2022-01-13T09:27:44Z", "salary": {"currency": null, "max": null, "min": null, "period": "monthly", "term": null}, "salary_visible": false, "title_keywords": [], "responsibilities": ["liaise", "management", "coordinate with", "coordinate with clients", "ad-hoc projects"], "requirements": {"degrees": ["diploma"], "majors": ["related disciplines", "building services", "engineering"], "languages": ["english", "chinese"], "language_level": ["good", "proficient"], "hard_skills": ["project management", "problem solving skills"], "soft_skills": ["work independently", "project management", "communication and interpersonal skills", "coordination", "problem solving skills", "proactive"], "languages_combined": [{"language": "english", "language_level": ["proficient", "good"]}, {"language": "chinese", "language_level": ["proficient", "good"]}]}, "experience_required": {"duration": ["at least 2-3 years"], "field": ["project management", "relevant working experience"]}}, {"job_id": "100003009046565", "location_code": "hk", "company": "Hong Kong Aero Engine Services Ltd", "job_title": "Facilities Maintenance Engineer (Ref. no. : EMF340719-B)", "description": "Responsibilities:\nProvide technical input to strategy formulation, including strategies for buildings and developments, or for cities in the East Asia Region; and planning and design of resource and waste management scheme\nRequired input will vary on project basis, including waste forecasting, assessing opportunities for circular economy; assessing implications of changes to collection regimes and approaches; proposing separation and collection strategies for the development or area; evaluating and proposing resource and waste management infrastructure at a city or jurisdiction level; preparing outline designs and space proving requirements for the required facilities; coordinating with other disciplines to develop integrated solutions; preparing technical specifications; and other inputs as required related to resource and waste management\u00a0 \u00a0\nPrepare reports and presentations for clients and other stakeholders\nExecute projects from tendering to design work, project planning, procurement and site supervision, commissioning and operation, including collaboration with other technical disciplines\nProvide strong technical leadership to others in group and technical input to multi-disciplinary project teams\nQualifications & Experience required:\n\nDegree in Environmental / Chemical / Mechanical / Civil Engineering or related discipline\nAt least 3 years of post graduation experience for the position of Engineer; at least 1 year of post chartered experience for the position of Project Engineer; at least 2 years of post chartered experience for the position of Senior Engineer\nProfessional membership of a recognised institution is preferred\nStrong knowledge in project management and problem-solving skills\nAbility to logically structure presentations and reports to deliver concise message\nBe adaptable and able to work independently coupled with strong interpersonal skills\nProficiency in both written and spoken English and Chinese\nWe offer a competitive remuneration package commensurate with qualifications and experience to the right candidate including Global Profit Share scheme, additional fringe benefits of maternity/paternity leave and long-term career development opportunities.\u00a0\nFor interested applicants, please click \u201cApply Now\" to submit your online application.\n\nTo explore more job opportunities in Arup, please visit our website at http://www.arup.com/Careers/Experienced_Hires/ApplyForAJob\n\nPersonal data collected will be used for recruitment purpose only. Applicants not contacted within 8 weeks may consider their applications unsuccessful.", "employment_types": ["Full Time", "Permanent"], "selling_points": ["Double pay, Performance bonus", "Dental & Medical Insurance", "Transportation allowance"], "locations": ["Tseung Kwan O"], "categories": ["Building & Construction", "Building / Construction / QS", "Engineering", "Electrical / Electronics", "Mechanical"], "post_time": "2022-01-13T18:55:25Z", "salary": {"currency": null, "max": null, "min": null, "period": "monthly", "term": null}, "salary_visible": false, "title_keywords": ["engineer"], "responsibilities": ["tendering", "design", "website", "personal data", "infrastructure", "teams", "presentations", "develop", "reports", "forecasting", "management", "commissioning", "specifications", "career development", "design work", "project planning", "site supervision", "project management", "recruitment", "prepare reports", "planning"], "requirements": {"degrees": ["degree"], "majors": ["civil engineering"], "languages": ["english", "chinese"], "language_level": ["proficiency"], "hard_skills": ["problem-solving skills", "project management", "scheme", "presentations"], "soft_skills": ["work independently", "adaptable", "project management", "interpersonal skills", "problem-solving skills", "leadership"], "languages_combined": [{"language": "english", "language_level": ["proficiency"]}, {"language": "chinese", "language_level": ["proficiency"]}]}, "experience_required": {"duration": ["at least 2 years", "at least 3 years", "at least 1 year"], "field": ["senior engineer", "development"]}}, {"job_id": "100003009048605", "location_code": "hk", "company": "Cornerstone Technologies Holdings Limited", "job_title": "Project Manager", "description": "This is a fixed-term contract position of minimum 2 years with possibility for renewal subject to organization need and individual performance.\n\nResponsibilities:\n\nProvide daily site supervision of E&M works to ensure that the works are constructed to achieve the project objectives in a safe and timely manner\nMonitor quality assurance of the site to ensure all works are carried out to the specified requirements with respect to materials, workmanship and quality\nMonitor the site workforce to ensure that appropriate certified workers with required safety training & qualifications are deployed so as to ensure site works are constructed in a safe manner\nHandle daily coordination works with internal and external parties to facilitate the conduction of site works and ensure works are conducted in safe and efficient manner with minimal impact in daily airport operations\nMaintain comprehensive daily work records and prepare progress reports\nSupervise installation, testing, commissioning and handover of the completed works to project owners and / or user departments\nPerform shift duties including overnight as needed\n\nRequirements:\n\nHigher Diploma/ Higher Certificate or above in Electrical/ Mechanical/ Building Services Engineering or other related disciplines with at least 8 years' relevant experience in site supervision of large, multi-disciplinary E & M projects\nDegree Holder with at least 4 years' relevant experience will also be considered\nCandidates without the above specified academic qualification but have 12 years' relevant working\u00a0experience will also be considered\nCandidate with less experience would be considered for Assistant Construction Superintendent, Electrical & Mechanical\nRegistered Electrical Worker holding a Grade A certificate or above is preferred\nPossess sound knowledge and experience of E&M works\nExperience in installation of airport works under a live operation environment is an advantage\nGood command of spoken and written English and Chinese with knowledge of Putonghua is an advantage\nProficient in Microsoft Office applications\nHolder of a valid HK driving license (Class 1, 2) is preferred\u00a0", "employment_types": ["Full Time", "Permanent"], "selling_points": ["Degree in Electrical,BS,Electronics Engineering", "3-5 yrs exp. in project mgt.", "Site supervision, project planning and operation"], "locations": ["Tsim Sha Tsui"], "categories": ["Building & Construction", "Building / Construction / QS", "Engineering", "Engineering Project Management", "Mechanical"], "post_time": "2022-01-14T06:54:03Z", "salary": {"currency": null, "max": null, "min": null, "period": "monthly", "term": null}, "salary_visible": false, "title_keywords": ["project manager"], "responsibilities": ["installation", "commissioning", "site supervision", "coordination works", "progress reports", "operations", "internal and external parties", "quality", "monitor", "testing", "maintain"], "requirements": {"degrees": ["certificate", "diploma", "higher certificate", "degree holder"], "majors": ["related disciplines", "building services", "engineering"], "languages": ["putonghua", "english", "chinese"], "language_level": ["advantage", "good command"], "hard_skills": ["microsoft office"], "soft_skills": [], "languages_combined": [{"language": "putonghua", "language_level": ["advantage", "good command"]}, {"language": "english", "language_level": ["advantage", "good command"]}, {"language": "chinese", "language_level": ["advantage", "good command"]}]}, "experience_required": {"duration": ["at least 8 years", "at least 4 years", "12 years"], "field": ["installation", "engineering", "related", "relevant working experience", "operation", "building services", "relevant experience", "construction"]}}, {"job_id": "100003009044136", "location_code": "hk", "company": "Schindler Lifts (HK) Ltd", "job_title": "Senior / Sales Engineer  (Lift & Escalator, Modernization)", "description": "Responsibilities:\n\n\nTo provide technical support to Engine Overhaul / Component Repair shops\nTo assist in engine / component defect investigation\nTo assist in developing capabilities and tooling solutions for Component Repair or Engine Assembly Processes\nLiaise with Rolls-Royce team on technical issues\nTo ensure HAESL Technical Services documentation is compliant with all OEM and Airworthiness requirements\nRequirements:\nDegree/Higher Diploma in Mechanical Engineering or equivalent\nRelevant working experience in engineering field\nCandidate with more experience may be considered as Engineer\nInterested parties please send a full resume with expected salary and quote our reference number to Human Resources Department, Hong Kong Aero Engine Services Ltd., 70 Chun Choi Street, Tseung Kwan O Industrial Estate, N.T. or alternatively, email us via clicking \"Apply Now\"\n\nPlease feel free to visit our company website at www.haesl.com.\n\n\u00a0Data collected will be used for recruitment purpose only.\n\n\"Applicants not invited for interview within three weeks from the date of submitting CV may consider their application unsuccessful.\"", "employment_types": ["Full Time", "Permanent"], "selling_points": ["Degree in Mech / Elec / BS or related disciplines", "Self motivated &strong drive in target achievement", "Excellent presentation & negotiation skills"], "locations": ["Quarry Bay"], "categories": ["Sales, CS & Business Devpt", "Business Development", "Engineering", "Mechanical", "Technical Sales / Sales Engineer"], "post_time": "2022-01-13T03:10:49Z", "salary": {"currency": null, "max": null, "min": null, "period": "monthly", "term": null}, "salary_visible": false, "title_keywords": ["sales engineer"], "responsibilities": ["documentation", "technical support", "developing", "investigation", "repair", "liaise with"], "requirements": {"degrees": ["diploma", "degree"], "majors": ["mechanical engineering"], "languages": [], "language_level": [], "hard_skills": [], "soft_skills": [], "languages_combined": []}, "experience_required": {"duration": [], "field": ["engineering", "relevant working experience"]}}, {"job_id": "100003009048809", "location_code": "hk", "company": "Hong Kong Air Cargo Terminals Limited (Hactl)", "job_title": "\u7dad\u4fee\u6280\u8853\u54e1 (\u96fb\u6a5f/\u6a5f\u68b0/\u8eca\u8f1b\u7dad\u4fee) Technician", "description": "Responsibilities\n\nTRAININGS\nPrepare training (learning objective, contents, PowerPoint, participant's hand-out, aids/media and time frame ).\nConduct theoretical and practical training for HK & Macau dealerships\nConduct product training for MBHK staff and Mercedes-Benz customers\nMonitor, supervise and motivate the learning process of all participants during each allocated training course\nTRAINING EVALUATION\nEvaluate the effectiveness of training methods and make recommendations to the management\nTRANSLATOR\nAct as an interpreter during the OPL training which is conducted by the DAG trainer when required\nReading-proof for the translated document from agency, and/or translate the training materials if necessary\nSELF IMPROVEMENT\nAcquire updated knowledge of training/teaching methods and aids\nOTHERS\nMaintain hand tools, special tools, workshop equipment and training media/aids\n\nRequirements\n\nDiploma in automotive engineering, higher certificate in motor vehicle engineering or related engineering discipline\nCompletion of HK Government recognized technician apprenticeship in automobile Industrial\nCompletion of industrial trade instructor course in the HK Technical Teachers\u2019 College or equivalent\n5 years relevant working experience in automotive industrial after completion of the automotive technician apprenticeship\nTeaching experience in automotive training school, college etc. would be an advantage\nFamiliar with Mercedes-Benz products, systems and working procedures\nFluent in both spoken and written Cantonese and English. Putonghua would be an advantage\nProficient in Microsoft application, PowerPoint, Excel and Word\nTechniques in presentation, teaching and workshop instruction\nHazards in the respective trade, the necessary safety precautions to be taken and relevant Occupational Safety and Health and Environmental Protection Ordinances and Regulations\nConscientious & self-motivated, speak clearly, pleasant personality, team player and ability to adopt new ideas\n\nFor the successful candidate, we offer a 5-day week in addition to a salary that commensurate with your experience and qualification.\n\nPotential candidates who meet our requirements, kindly apply with full resume and application letter indicating your present and expected salary via \"Apply Now\".\n\nWe are an equal opportunity employer. The information provided will be treated in strict confidence and only be used for recruitment related purposes. The Company may refer suitable applicants to other vacancies within the Group. All personal data of unsuccessful applicants will be destroyed within 12 months on completion of the recruitment exercise.", "employment_types": ["Full Time", "Permanent"], "selling_points": ["\u5de5\u4f5c\u7bc4\u7587\u6309\u904e\u5f80\u7d93\u9a57\u5546\u8b70", "\u63d0\u4f9b\u4ea4\u901a\u6d25\u8cbc\u53ca\u514d\u8cbb\u7a7f\u68ad\u5df4\u58eb", "\u4eab\u6709\u96d9\u7ce7\u53ca\u82b1\u7d05 / \u6d25\u8cbc"], "locations": ["Airport Area"], "categories": ["Engineering", "Draftsman", "Electrical / Electronics", "Mechanical"], "post_time": "2022-01-14T07:21:48Z", "salary": {"currency": null, "max": null, "min": null, "period": "monthly", "term": null}, "salary_visible": false, "title_keywords": ["technician"], "responsibilities": ["make recommendations", "management", "workshop", "monitor", "evaluate", "contents", "maintain", "evaluation"], "requirements": {"degrees": ["diploma", "higher certificate"], "majors": ["engineering"], "languages": ["cantonese", "putonghua", "english"], "language_level": ["advantage", "fluent"], "hard_skills": ["excel", "word", "powerpoint"], "soft_skills": ["self-motivated", "pleasant", "conscientious", "team player", "presentation"], "languages_combined": [{"language": "cantonese", "language_level": ["fluent"]}, {"language": "putonghua", "language_level": ["advantage"]}, {"language": "english", "language_level": ["fluent"]}]}, "experience_required": {"duration": ["5 years"], "field": ["training", "teaching", "relevant working experience"]}}, {"job_id": "100003009047374", "location_code": "hk", "company": "Chevalier Group \u2013 Electrical & Mechanical Engineering", "job_title": "Senior Engineer / Engineer (Electrical / Mechanical)", "description": "Responsibilities:\nTo upkeep the HAESL facilities in good condition with practical preventive and corrective maintenance services;\nTo provide detailed design for change request on the existing or new facilities / equipment with specification;\nTo liaise work arrangement and monitor work performance of the services and work contractors to ensure their delivered work quality;\nTo plan and arrange the manpower deployment and departmental cost control during the works execution;\nTo maintain air conditioning equipment & automatic plant systems in good conditions; and\nTo provide energy saving opportunities to lower down the company operating cost.\nRequirements:\nDegree/High Diploma in Building Services/Mechanical/Electrical Engineering or above;\nFluent in both spoken and written English and Chinese.\nAt least 6 years' relevant experience in plant maintenance, property management, consultancy or project management and preferred with experiences in operating air conditioning plant and its automatic system, together with maintenance exposure in related equipment items.\nInterested parties please send a full resume with expected salary and quote our reference number to Human Resources Department, Hong Kong Aero Engine Services Ltd., 70 Chun Choi Street, Tseung Kwan O Industrial Estate, N.T. or alternatively, email us by clicking \"Apply Now\".\nPlease feel free to visit our company website at www.haesl.com.\nData collected will be used for recruitment purpose only\n\u201cApplicants not invited for interview within three weeks from the date of submitting CV may consider their application unsuccessful.\u201d", "employment_types": ["Full Time", "Permanent"], "selling_points": ["Experienec in MVAC or electrical installation", "Experience in large scale Casino and Hotel project", "Senior Engineer"], "locations": ["Kowloon Bay"], "categories": ["Engineering", "Electrical / Electronics", "Mechanical", "Building & Construction", "Others"], "post_time": "2022-01-14T02:56:34Z", "salary": {"currency": null, "max": null, "min": null, "period": null, "term": null}, "salary_visible": false, "title_keywords": ["senior engineer", "engineer"], "responsibilities": ["liaise", "cost", "systems", "monitor", "design", "maintain", "work quality", "maintenance services", "plan", "cost control"], "requirements": {"degrees": ["high diploma", "degree"], "majors": ["building services", "electrical engineering"], "languages": ["english", "chinese"], "language_level": ["fluent"], "hard_skills": ["project management", "maintenance"], "soft_skills": ["project management"], "languages_combined": [{"language": "english", "language_level": ["fluent"]}, {"language": "chinese", "language_level": ["fluent"]}]}, "experience_required": {"duration": ["at least 6 years"], "field": ["management", "maintenance", "related", "project management", "relevant experience", "plant maintenance"]}}, {"job_id": "100003009047380", "location_code": "hk", "company": "AP Rentals Limited", "job_title": "Sales Executive", "description": "We are seeking high caliber people like you to join us to fast-track your career with\u00a0Cornerstone Technologies.\n\nResponsibilities:\u00a0\n\n\nPrepare quotation for tender\nResponsible for electrical design work, site supervision, commissioning, project planning, operation and project documentation preparation or\u00a0Electrical Vehicles (EV) charging installation projects\nLead\u00a0a project team for\u00a0Electrical Vehicles (EV) charging installation projects\nAttend site meetings and address technical queries from clients\nMonitor the progress of project and ensure the quality of work\nLiaise with clients, consultants, main-contractors and sub-contractors for project implementation\nResolve ad hoc site matters and site coordination\n\nRequirements:\n\nDegree holder in Electrical, Building Services, Electronics Engineering or related disciplines\nHolder of Registered Electrical Worker License (A0, B0, or C0)\nAt least 3 years working experience in project management, preferably\u00a0in electrical subcontracting industry\nSolid experience in dealing and liaising with Property Developers, Consultants, Contractors, Management Offices, Power Utilities and Gov. Bodies is an advantage\nGood interpersonal skill and leadership\nWe offer 5-day work and medical benefits to the successful candidates. Interested parties please send your full CV with current and expected salary in MS Word format to the Human Resources & Administration Manager.\nTo know more about us, please visit our website at\u00a0https://www.cstl.com.hk.\nWe are an equal opportunity employer and welcome applications from all qualified candidates.\nPersonal data collected will be treated in strict confidence and used only for recruitment-related purpose. Applicants who have not heard from us within four weeks may consider their applications unsuccessful. All personal data will be destroyed after 6 months.", "employment_types": ["Full Time", "Permanent"], "selling_points": [], "locations": ["Yuen Long"], "categories": ["Building & Construction", "Building / Construction / QS", "Engineering", "Mechanical", "Sales, CS & Business Devpt", "Sales - Sales Management"], "post_time": "2022-01-14T02:56:37Z", "salary": {"currency": null, "max": null, "min": null, "period": "monthly", "term": null}, "salary_visible": false, "title_keywords": ["sales executive"], "responsibilities": ["design work", "installation", "project planning", "liaise with clients", "commissioning", "site supervision", "ad hoc site matters", "quotation", "monitor", "quality", "implementation", "site coordination", "tender", "attend site meetings", "project documentation"], "requirements": {"degrees": ["degree holder"], "majors": ["related disciplines", "building services", "engineering"], "languages": [], "language_level": [], "hard_skills": ["project management"], "soft_skills": ["project management", "leadership", "interpersonal skill"], "languages_combined": []}, "experience_required": {"duration": ["at least 3 years"], "field": ["project management", "property developers", "management"]}}, {"job_id": "100003009049449", "location_code": "hk", "company": "TK Elevator Hong Kong Limited", "job_title": "District Manager", "description": "\u00a0\u8077\u8cac\n\n\n\u57f7\u884c\u8ca8\u7ad9\u96fb\u6a5f\u5de5\u7a0b / \u6a5f\u68b0\u5de5\u7a0b /\u00a0\u8ca8\u7269\u8655\u7406\u7cfb\u7d71 / \u6d41\u52d5\u8a2d\u5099\u53ca\u8eca\u8f1b \u7684\u65e5\u5e38\u7dad\u8b77\u4fdd\u990a\u3001\u4fee\u7406\u53ca\u6539\u52d5\u5de5\u4f5c\n\u64b0\u5beb\u7c21\u55ae\u5831\u544a\u53ca\u586b\u5beb\u6e05\u55ae\n\u4f9d\u5f9e\u5b89\u5168\u5b88\u5247\uff0c\u6309\u7167\u65e2\u5b9a\u7a0b\u5e8f\u53ca\u6cd5\u4f8b\u5de5\u4f5c\n\n\u5165\u8077\u8981\u6c42\n\n\n\u5177\u5169\u5e74\u76f8\u95dc\u7dad\u4fee\u5de5\u4f5c\u7d93\u9a57\n\u6301\u6a5f\u68b0\u5de5\u7a0b / \u96fb\u6a5f\u5de5\u7a0b / \u76f8\u95dc\u5b78\u6b77\n\u826f\u597d\u4e2d\u6587\u8a9e\u8a00\u80fd\u529b\n\n\u5de5\u4f5c\u6642\u9593\n\n\u65e9\u3001\u4e2d\u3001\u591c\u73ed\u8f2a\u73ed\u5236\uff08\u8996\u4e4e\u5de5\u4f5c\u7bc4\u7587\uff0c\u90e8\u5206\u4e3b\u8981\u70ba\u65e5\u9593\u5de5\u4f5c\uff09\n\u4e00\u661f\u671f\u4e94\u81f3\u516d\u5929\u5de5\u4f5c\n\n\u798f\u5229\n\n\u8fb2\u66c6\u5e74\u82b1\u7d05\u3001\u914c\u60c5\u82b1\u7d05\u3001\u4ea4\u901a\u6d25\u8cbc\u3001\u52a0\u73ed\u6d25\u8cbc\u3001\u5e74\u5ea6\u5b89\u5168\u734e\u91d1\u3001\u5b63\u5ea6\u7279\u5225\u51fa\u52e4\u734e\u91d1\u3001\u50f1\u4e3b\u984d\u5916\u5f37\u7a4d\u91d1\u4f9b\u6b3e\u3001\u91ab\u7642\u4fdd\u969c \u2013 \u5305\u62ec\u5bb6\u5c6c\u3001\u81ea\u9858\u6027\u7259\u79d1\u4fdd\u5065 \u2013 \u5305\u62ec\u5bb6\u5c6c\u3001\u4eba\u58fd\u4fdd\u96aa\u3001\u751f\u65e5\u5047\u671f\u3001\u984d\u5916\u6709\u85aa\u5e74\u5047\u3001\u52de\u5de5\u53ca\u516c\u773e\u5047\u671f\u3001\u5a5a\u5047\u3001\u7522\u5047\u3001\u4f8d\u7522\u5047\u3001\u521d\u751f\u5b30\u5152\u79ae\u7269\u3001\u9ad4\u80b2\u9928\u3001\u514d\u8cbb\u7a7f\u68ad\u5df4\u58eb\n\n\n\n\u7533\u8acb\u8fa6\u6cd5\n\n\u7533\u8acb\u8005\u8acb\u628a\u7533\u8acb\u4fe1\u53ca\u5c65\u6b77\u50b3\u771f\u81f32753 2244\uff1b\u6216\u96fb\u90f5\u81f3\u516c\u53f8\u96fb\u90f5\uff1b\u6216\u5bc4\u5f80\u9999\u6e2f\u570b\u969b\u6a5f\u5834\u8d85\u7d1a\u4e00\u865f\u8ca8\u7ad9\u8fa6\u516c\u5927\u6a13\u5317\u5ea7\u516d\u6a13\u4eba\u529b\u8cc7\u6e90\u90e8\u6536 (\u8acb\u8a3b\u660e\u7533\u8acb\u8077\u4f4d\u53ca\u53c3\u8003\u7de8\u865f)\n\n\u00a0\u672c\u516c\u53f8\u7db2\u5740:\u00a0https://careers.hactl.com/\n\n\u00a0\u5982\u7533\u8acb\u4eba\u65bc\u56db\u661f\u671f\u5167\u672a\u7372\u9762\u8a66\u901a\u77e5\uff0c\u5373\u8868\u793a\u8a72\u7533\u8acb\u672a\u80fd\u6210\u529f\u3002\u7533\u8acb\u4eba\u6240\u63d0\u4f9b\u4e4b\u500b\u4eba\u8cc7\u6599\u53ea\u4f9b\u62db\u8058\u4e4b\u7528\uff0c\u672a\u88ab\u8058\u7528\u4eba\u58eb\u4e4b\u8cc7\u6599\u6703\u5728\u516d\u500b\u6708\u5167\u88ab\u92b7\u6bc0\u3002", "employment_types": ["Full Time", "Permanent"], "selling_points": [], "locations": ["Kowloon Bay"], "categories": ["Engineering", "Electrical / Electronics", "Engineering Project Management", "Mechanical"], "post_time": "2022-01-14T08:40:23Z", "salary": {"currency": null, "max": null, "min": null, "period": null, "term": null}, "salary_visible": false, "title_keywords": ["district manager"], "responsibilities": [], "requirements": {"degrees": [], "majors": [], "languages": [], "language_level": [], "hard_skills": [], "soft_skills": [], "languages_combined": []}, "experience_required": {"duration": [], "field": []}}, {"job_id": "100003009044487", "location_code": "hk", "company": "", "job_title": "Electrical Engineer", "description": "\u8077\u8cac:\u8ca0\u8cac\u4f4f\u5b85\u7269\u696d\u65e5\u5e38\u5404\u9805\u8a2d\u5099\u7dad\u4fee\u5de5\u4f5c,\u5305\u62ec\u4f9b\u96fb\u3001\u6c34\u6cf5\u3001\u51b7\u6c23\u3001\u6d88\u9632\u7cfb\u7d71;\u8a2d\u65bd\u4fdd\u990a\u3001\u6aa2\u67e5\u7dad\u4fee\u5de5\u4f5c\u7b49\n\n\u8981\u6c42:\u00a0\u6c92\u6709\u5b78\u6b77\u8981\u6c42; 2\u5e74\u7d93\u9a57; \u6301\u6709\u96fb\u5de5A\u724c;\u61c2\u8655\u7406\u51b7\u51dd,\u7a7a\u8abf,\u5177\u76f8\u95dc\u7d93\u9a57\u512a\u5148\n\n\u5730\u5340:\u9285\u947c\u7063\n\n\u6709\u610f\u7533\u8acb\u8005,\u53ef\u900f\u904e\u4ee5\u4e0b\u5176\u4e2d\u4e00\u7a2e\u9014\u5f91\u7533\u8acb:\n\n1) \u6309 \u201cAPPLY NOW\" \u5c07\u5c65\u6b77\u8868\u96fb\u90f5\u81f3\u672c\u516c\u53f8 \u6216\n\n2)\u00a0\u81f4\u96fb\u00a02864 4512\u00a0\u77f3\u5148\u751f\u00a0\u6216\n\n3)\u00a0WhatsApp 6462 0906\u00a0\u3002\n\nAll applications applied through our system will be delivered directly to the advertiser and privacy of personal data of the applicant will be ensured with security.", "employment_types": ["Full Time"], "selling_points": ["Higher dip or above in Electrical/Mechanical/BS", "Minimum 7 yrs work exp & 3yr supervisory exp", "5-Days Work Week, Competitive Remuneration Package"], "locations": ["Sheung Shui"], "categories": ["Building & Construction", "Building / Construction / QS", "Engineering", "Electrical / Electronics", "Mechanical"], "post_time": "2022-01-13T04:22:22Z", "salary": {"currency": null, "max": null, "min": null, "period": "monthly", "term": null}, "salary_visible": false, "title_keywords": ["electrical engineer"], "responsibilities": ["personal data"], "requirements": {"degrees": [], "majors": [], "languages": [], "language_level": [], "hard_skills": ["whatsapp"], "soft_skills": [], "languages_combined": []}, "experience_required": {"duration": [], "field": []}}, {"job_id": "100003009044455", "location_code": "hk", "company": "Kingsway Cars Service Limited", "job_title": "\u6c7d\u8eca\u7dad\u4fee\u6280\u5de5", "description": "\n\n\nJob Responsibilities\n\nReporting to the Engineering Manager, mainly responsible to and assist the following engineering issues and staff management:\n\n\nPrepare technical documents in accordance with client\u2019s guidelines and standards;\nAssist in the daily activities as well as training and discipline control of the team;\nProvide technical support, safety and quality controls and perform site supervision as an engineering expertise;\nTo research and recommend major equipment replacements and modification programmes to ensure proper functioning.\n\nJob Requirements:\n\nHigher Diploma or above in Electrical / Mechanical / Building Service engineering.\n\nEMSD 's Registered Electrical Worker of grade B0 or above.\nMinimum 7\u00a0years' post-qualification experience in relevant engineering.\nMinimum 3 years\u2019 supervisory experience.\n\n\n\nWe offer attractive remuneration to the right candidates. Interest parties please apply with full resume stating available reporting date, current and expected salary to Ms. Lee by Apply Now.\n\n(All personal data provided will be treated in strict confidence and used for recruitment purposes only.)", "employment_types": ["Full Time", "Permanent"], "selling_points": [], "locations": ["Tuen Mun Area"], "categories": ["Engineering", "Mechanical", "Others", "Technician"], "post_time": "2022-01-13T04:09:01Z", "salary": {"currency": null, "max": null, "min": null, "period": "monthly", "term": null}, "salary_visible": false, "title_keywords": [], "responsibilities": ["reporting", "management", "control", "site supervision", "guidelines", "technical support", "quality"], "requirements": {"degrees": ["higher diploma or above"], "majors": ["engineering"], "languages": [], "language_level": [], "hard_skills": [], "soft_skills": [], "languages_combined": []}, "experience_required": {"duration": ["minimum 7 years", "minimum 3 years"], "field": ["post-qualification", "engineering", "supervisory experience"]}}, {"job_id": "100003009046231", "location_code": "hk", "company": "Arup", "job_title": "Engineer (Designer) / Project Engineer (Designer) / Senior Engineer (Designer) (Fa\u00e7ade Engineering)", "description": "\nWelbot Technology is a pioneering technology company specializing in robotic solutions that redefine the construction automation workflow in the industry.\n\nOur Adaptive Robotic Welder has qualified for Welding Procedure Specification(WPS), fully capable of working under harsh environmental conditions. Our technological innovation not only brings new blood into the labour market, but also reforms the traditional working nature.\n\nIn the future, Welbot Technology will continue to sharpen its competitive edge. With the adoption of Building Information Modelling (BIM), big data and cutting-edge 5G technology into AI-based robotic systems, we are well poised to make a breakthrough in the eco platform of construction robotic solutions.\n\n\u8077\u8cac:\n\u65bc\u5730\u76e4\u4e3b\u7ba1\u5e36\u9818\u53ca\u6307\u5c0e\u4e0b,\u64cd\u4f5c\u6a5f\u68b0\u81c2\u9032\u884c\u5efa\u7bc9\u5730\u76e4\u5de5\u4f5c\n\n\u5354\u52a9\u5de5\u7a0b\u5e2b\u5728\u5de5\u5834\u9032\u884c\u79d1\u7814\n\n\u57f7\u884c\u4e0a\u7d1a\u6307\u6d3e\u7684\u5176\u4ed6\u8077\u52d9 \u8cc7\u6b77\n\n\u7121\u9700\u5de5\u4f5c\u7d93\u9a57 \u2022 \u7121\u9700\u5b78\u6b77\n\n\u826f\u597d\u7cb5\u8a9e\n\n\u6301\u6709\u5e73\u5b89\u5361\u53ca\u5de5\u4eba\u8a3b\u518a\u8a3c\u512a\u5148\n\n\u6301\u6709\u71d2\u710a\u5927\u5de5\u724c\u6703\u7372\u8058\u7528\u70ba\u9ad8\u7d1a\u6280\u8853\u54e1\n\n\u5177\u5718\u968a\u7cbe\u795e, \u8aa0\u5be6\u6709\u79ae, \u6709\u8010\u5fc3\u53ca\u7d30\u5fc3, \u6709\u8cac\u4efb\u611f, \u5de5\u4f5c\u7a4d\u6975\u4e3b\u52d5\n\n\u798f\u5229:\n\u6bcf\u9031\u5de5\u4f5c5-6\u5929\n\n\u914c\u60c5\u6027\u82b1\u7d05\n\n\u5728\u8077\u57f9\u8a13\n\n\u5e74\u504710\u5929\n\n\u751f\u65e5\u5047\n\n\u91ab\u7642\u4fdd\u96aa\n\n\u85aa\u916c: $15,000.00\u81f3$20,000.00(\u6bcf\u6708)\u8d77\n\nInterested candidates please apply with full resume, present & expected salary, available date by clicking \"Apply Now\". For further information, please visit our company website: https://www.welbot-tech.com/\n\nAll data collected will be used for recruitment purpose only.\n\nFull-time,Permanent\n\n", "employment_types": ["Full Time", "Permanent"], "selling_points": [], "locations": ["Kowloon City Area"], "categories": ["Building & Construction", "Architectural Services", "Civil / Structural", "Engineering", "Mechanical"], "post_time": "2022-01-13T10:04:25Z", "salary": {"currency": null, "max": null, "min": null, "period": null, "term": null}, "salary_visible": false, "title_keywords": ["senior engineer", "engineer", "designer", "project engineer"], "responsibilities": ["systems", "big data"], "requirements": {"degrees": [], "majors": [], "languages": [], "language_level": [], "hard_skills": ["building information modelling", "make", "bim", "ai"], "soft_skills": ["capable", "cutting-edge"], "languages_combined": []}, "experience_required": {"duration": [], "field": []}}, {"job_id": "100003009045476", "location_code": "hk", "company": "Global Development Personnel Co Limited", "job_title": "Engineering Manager, 5 day per week, HKD38,000 - 43,000", "description": "\nResponsibilities:\n\nResponsible for Design & Build Term Contract;\nPreparation of tender, job budget, drawings and equipment submission;\nPerform project planning and management;\nSupervise sub-contractors and attend building services & site meetings;\nAssist in prepare of payment, variation claim and negotiation\n\nRequirements:\n\nHigher Certificate or above in\u00a0Building Services/\u00a0Electrical/\u00a0Mechanical Engineering or related Discipline;\nAt least 7 years post qualification experience;\nExperience of B. S. Coordinator is highly preferred;\nProficient in using MS Applications and AutoCAD;\nGood command of both spoken and written English and Chinese;\nExcellent interpersonal and negotiation skills\n\nBenefits and Package:\n\n13 days annual leave\nPublic holidays\nMedical Insurance (Out-patient, Hospitalization\u00a0and Dental coverage)\nLife insurance\nEducation subsidy / Sponsorship\nTravelling allowance\nFull pay Exam leave, marriage leave, compassionate leave\nStaff recreation club etc.\n\n\n\nAttractive remuneration package will be offered to the successful candidate\n\nPlease send in strict confidence with full resume stating the reference code and your current and expected salary to Human Resources Department, REC Engineering Company Limited, Units A-D, 15/F., Goodman Kwai Chung Logistics Centre, 585-609 Castle Peak Road, Kwai Chung, New Territories, Hong Kong or by\u00a0fax 2489 0044 or clicking \u201cApply Now\u201d button to apply.\n(Personal data provided\u00a0by applicants will be used strictly for recruitment purpose only.)", "employment_types": ["Permanent"], "selling_points": ["preferably in field service Engineering project", "preferably in maintenance service project", "electrical or equivalent academic qualification"], "locations": ["Yuen Long"], "categories": ["Engineering", "Engineering Project Management", "Manufacturing & Production", "Mechanical"], "post_time": "2022-01-13T07:55:40Z", "salary": {"currency": "HKD", "max": 44999, "min": 35000, "period": "monthly", "term": null}, "salary_visible": true, "title_keywords": ["engineering manager"], "responsibilities": ["project planning", "management", "site meetings", "budget", "design", "drawings", "payment", "tender"], "requirements": {"degrees": ["higher certificate"], "majors": ["building services", "mechanical engineering"], "languages": ["english", "chinese"], "language_level": ["good command"], "hard_skills": ["ms applications", "autocad"], "soft_skills": ["negotiation skills", "interpersonal"], "languages_combined": [{"language": "english", "language_level": ["good command"]}, {"language": "chinese", "language_level": ["good command"]}]}, "experience_required": {"duration": ["at least 7 years"], "field": []}}, {"job_id": "100003009046059", "location_code": "hk", "company": "CLP Power Hong Kong Limited", "job_title": "Engineer II (2-Year Contract)  [Ref.: CLPP_CBD_BS&I_EII]", "description": "Responsibilities:\nCarry out engineering design/ calculation and documentation of fa\u00e7ade system design, including BD submissions in HK, DSSOPT submissions in Macau and expert panel review submissions in Mainland\nSupervise testing and construction (fabrication and installation) of fa\u00e7ade systems\nCoordinate with internal and external parties on all fa\u00e7ade related issues\nProvide professional and timely advices on all aspects of fa\u00e7ade, including and not limited to design, performance, material, quality, maintenance, progress and costing issues\nDevelop digital tools to enhance quality and efficiency of fa\u00e7ade design\nReview submittals according to project specific contract requirements\nQualifications & Experience required:\n\nDegree in Structural/ Civil / Mechanical Engineering or Architectural Studies with practical experience in fa\u00e7ade field\nAt least 3 years of practical experience for the position of Engineer or Designer; at least 7 years of practical experience for the position of Project Engineer or Designer; at least 12 years of practical experience for the position of Senior Engineer or Designer\nExperience in design and construction of fa\u00e7ade systems. Knowledge of local practices in Hong Kong and China will be an advantage\nProficient with engineering software packages (for Engineer), AutoCAD and 3D modelling software (for Designer).\u00a0 Knowledge on programming software will be an advantage\nFluency in written and spoken English.Good command in written and spoken Chinese (Putonghua) is preferable\n\nWe offer a competitive remuneration package commensurate with qualifications and experience to the right candidate including Global Profit Share scheme, additional fringe benefits of maternity/paternity leave and long-term career development opportunities.\u00a0\n\n\nFor interested applicants, please click \u201cApply Now\" to submit your online application.\n\n\nTo explore more job opportunities in Arup, please visit our website at http://www.arup.com/Careers/Experienced_Hires/ApplyForAJob\n\u00a0\nPersonal data collected will be used for recruitment purpose only. Applicants not contacted within 8 weeks may consider their applications unsuccessful.", "employment_types": ["Full Time", "Contract"], "selling_points": [], "locations": ["Sham Shui Po"], "categories": ["Engineering", "Electrical / Electronics", "Mechanical", "Others"], "post_time": "2022-01-13T18:54:33Z", "salary": {"currency": null, "max": null, "min": null, "period": "monthly", "term": null}, "salary_visible": false, "title_keywords": ["engineer"], "responsibilities": ["installation", "engineering design", "software", "maintenance", "review", "systems", "coordinate with", "internal and external parties", "testing", "design", "quality", "develop", "system design", "website", "recruitment", "career development", "documentation", "personal data"], "requirements": {"degrees": ["degree"], "majors": ["mechanical engineering"], "languages": ["putonghua", "english", "chinese"], "language_level": ["fluency", "good command"], "hard_skills": ["engineering software packages", "maintenance", "scheme", "3d modelling", "system design", "programming", "documentation", "autocad"], "soft_skills": ["timely"], "languages_combined": [{"language": "putonghua", "language_level": ["good command"]}, {"language": "english", "language_level": ["fluency"]}, {"language": "chinese", "language_level": ["good command"]}]}, "experience_required": {"duration": ["at least 3 years", "at least 7 years", "at least 12 years"], "field": ["designer", "engineering", "senior engineer", "structural", "development", "design", "construction"]}}, {"job_id": "100003009050473", "location_code": "hk", "company": "Chevalier Group - Lifts and Escalators", "job_title": "Technical Assistant", "description": "Applications are invited for appointment as\u00a0Research Assistant Professor / Post-doctoral Fellow in the Department of Mechanical Engineering\u00a0(Ref.: 509174), to commence on or before July 1, 2022 for up to three years.\n\nThe Department of Mechanical Engineering offers B.Eng., M.Sc., M.Phil. and Ph.D. degree programmes. The University of Hong Kong has a highly ranked engineering school and an active Mechanical Engineering Programme. The Department employs about 30 full-time faculty members and has well-equipped teaching and research facilities and support. Information about the Department can be obtained at\u00a0http://www.mech.hku.hk.\u00a0\n\nApplicants should possess a Ph.D. degree in Mechanical Engineering, Biomedical Engineering or a related engineering field. They should also have an excellent command of English, organizational, interpersonal and communication skills. Previous teaching experience will be a plus. Prior academic or industrial R&D track records in biotechnologies, biomicrofluidics and biochemistry will be advantageous. Those with strong motivation and willingness to engage in innovative teaching schemes such as flipped classroom and e-Learning are preferred.\n\nThe appointee will work within Professor H.C. Shum\u2019s research group and participate in a large-scale collaborative multidisciplinary research related to, but not limited to microfluidics-based biotechnologies, biomaterial engineering and biomedical instrumentations. He/She is expected to develop a sub-group with synergy and coherence with the larger group; teach or contribute to the teaching of undergraduate and Master\u2019s degree courses in Mechanical Engineering and Biomedical Engineering; apply for research funding; and supervise research postgraduate students and capstone projects with engineering contents for final year undergraduates. Administrative work which promotes the educational mission of the University may also be required. Enquiries about the duties of the post should be sent to Professor H.C. Shum at \u00a0[via APPLY NOW] Those with higher qualifications may be considered for appointment as Research Assistant Professor.\n\nA highly competitive salary commensurate with qualifications and experience will be offered, in addition to annual leave and medical benefits. At current rates, salaries tax does not exceed 15% of gross income.\n\nThe University only accepts online application for the above post.\u00a0 Applicants should apply online and upload an up-to-date C.V. Review of applications will start as soon as possible and continue until\u00a0April 30, 2022, or until the post is filled, whichever is earlier.\n\nAdvertised:Dec 9, 2021 (HK Time)\nApplications close:Apr 30, 2022 (HK Time)\n\n\u6709\u610f\u7533\u8acb\u8005\u8acb \u6309 APPLY NOW\u7533\u8acb\n\n", "employment_types": ["Full Time", "Permanent"], "selling_points": ["Maintain safety and quality records", "Handle ad hoc projects", "Non-Degree Tertiary or above"], "locations": ["Kowloon Bay"], "categories": ["Engineering", "Electrical / Electronics", "Mechanical", "Others"], "post_time": "2022-01-14T10:29:05Z", "salary": {"currency": null, "max": null, "min": null, "period": null, "term": null}, "salary_visible": false, "title_keywords": ["technical assistant"], "responsibilities": ["communication", "contents", "administrative work", "develop"], "requirements": {"degrees": ["degree", "master"], "majors": ["biomedical engineering", "engineering", "mechanical engineering"], "languages": ["english"], "language_level": ["excellent"], "hard_skills": ["r&d", "plus", "c"], "soft_skills": ["communication skills", "organizational", "collaborative", "innovative", "learning", "active", "interpersonal"], "languages_combined": [{"language": "english", "language_level": ["excellent"]}]}, "experience_required": {"duration": [], "field": ["teaching"]}}, {"job_id": "100003009044369", "location_code": "hk", "company": "Hong Kong Disneyland", "job_title": "Specialist, Fleet Services", "description": "Duties\n\n\nMonitor overall BIM model progress of involved projects\nPrepare BIM models with the instruction of engineers\nAllocate works to BIM modelers\nLiaise with client's team for problem solving\nAssist in day-to-day engineering related work\n\n\u00a0Requirements\n\nAny E&M engineering related disciplines\nAt least 1 year of relevant experience\nProficient in AutoCAD & REVIT\nPractical experience in using BIM (REVIT) software is highly preferred\nCandidates with lesser experience will be considered as Assistant BIM Modeller\n\nWe offer an attractive remuneration package, training and good career opportunities to the right candidate.\u00a0 Interested parties are invited to send your application enclosing full resume stating career and salary history (either in Word format or PDF format) to the HR Department by\u00a0Whatsapp to 9306-7864, or by\u00a0fax to 2370-2073 or click Apply Now.\n\nApplicants not invited for an interview within two months may consider their applications unsuccessful.\u00a0 All personal data collected will be used for recruitment purpose only.", "employment_types": ["Full Time"], "selling_points": ["Diagnose the problem, provide recommendation", "Bachelor Degree in mechanical", "At least 5 years of relevant working experience"], "locations": ["Lantau Island"], "categories": ["Engineering", "Mechanical", "Others"], "post_time": "2022-01-13T03:52:11Z", "salary": {"currency": null, "max": null, "min": null, "period": "monthly", "term": null}, "salary_visible": false, "title_keywords": ["specialist"], "responsibilities": ["liaise with client", "monitor"], "requirements": {"degrees": [], "majors": [], "languages": [], "language_level": [], "hard_skills": ["revit", "bim", "autocad"], "soft_skills": [], "languages_combined": []}, "experience_required": {"duration": ["at least 1 year"], "field": ["relevant experience"]}}, {"job_id": "100003009045682", "location_code": "hk", "company": "RNB Engineering Hong Kong Limited", "job_title": "Project Manager / Assistant Project Manager (Maintenance Services)", "description": "Responsibilities:\n\nCo-ordinate with clients, consultants, main-contractors and sub-contractors for project implementation in Data Centre project\nTo prepare work programs, drawings, technical document submission, material & equipment submission and other method statements submission.\nTo follow and observe the relevant Quality Procedures, Safety and Health, other company requirements, when applicable.\nTo assist ad hoc duty assign by supervisor\n\n\u00a0Requirements:\n\nDegree Holder in Electrical / Mechanical / Building Services or equivalent\n2 years\u2019 or above relevant working experience in participation of E&M / Building Services Contracts\nGood command of both written and spoken English and Chinese\nSelf motivated, Independent and able to work under pressure\nProficiency in AutoCAD and BIM\nImmediate available is highly appreciated\u00a0", "employment_types": ["Full Time", "Permanent"], "selling_points": [], "locations": ["To Kwa Wan"], "categories": ["Engineering", "Electrical / Electronics", "Engineering Project Management", "Mechanical"], "post_time": "2022-01-13T08:20:44Z", "salary": {"currency": null, "max": null, "min": null, "period": "monthly", "term": null}, "salary_visible": false, "title_keywords": ["project manager", "assistant project manager"], "responsibilities": ["ad hoc", "data", "quality", "implementation", "co-ordinate with clients", "drawings", "procedures"], "requirements": {"degrees": ["degree holder"], "majors": ["building services"], "languages": ["english", "chinese"], "language_level": ["good command"], "hard_skills": ["bim", "autocad"], "soft_skills": ["self motivated", "independent", "work under pressure"], "languages_combined": [{"language": "english", "language_level": ["good command"]}, {"language": "chinese", "language_level": ["good command"]}]}, "experience_required": {"duration": ["2 years"], "field": ["building services", "relevant working experience"]}}, {"job_id": "100003009038238", "location_code": "hk", "company": "J Roger Preston Limited", "job_title": "Engineer (HVAC)", "description": "Chevalier (HK) Limited is now inviting high calibre persons to apply for this position\n\u00a0\nResponsibilities\n\nAssist managers of maintenance department to handle safety, quality and daily operating documents\nCoordinate with internal and external parties for daily operation of the section\nHandle ad hoc projects assigned by managers\nOutdoor work is required\n\nRequirements\n\nHigher Diploma in Mechanical / Electrical Engineering\n1 year's relevant working experience / Fresh graduates are also welcome\nGood command of spoken and written English and Chinese\nOrganized, detailed minded and outgoing personality\nProficient in MS Office applications (MS Word, Excel) and Chinese Word Processing\nImmediate available is highly preferred\nAttractive remuneration package will be offered to the right candidate. Interested parties, please send us your resume with current and expected salary by clicking \"Apply Now\" or mail to:\n\nThe Human Resources Manager, Chevalier Group, 22/F, Chevalier Commercial Centre, 8 Wang Hoi Road, Kowloon Bay, Hong Kong\n\nWe are an equal opportunity employer and welcome applications from all qualified candidates. Personal data collected would be used for recruitment purpose only.", "employment_types": ["Full Time", "Permanent"], "selling_points": [], "locations": ["Kwun Tong Area"], "categories": ["Engineering", "Draftsman", "Engineering Project Management", "Mechanical"], "post_time": "2022-01-11T06:16:54Z", "salary": {"currency": null, "max": null, "min": null, "period": "monthly", "term": null}, "salary_visible": false, "title_keywords": ["engineer"], "responsibilities": ["outdoor work", "maintenance", "internal and external parties", "quality", "coordinate with", "daily operation", "assist managers", "ad hoc projects"], "requirements": {"degrees": ["diploma"], "majors": ["electrical engineering"], "languages": ["english", "chinese"], "language_level": ["good command", "proficient"], "hard_skills": ["ms word", "excel", "chinese word processing", "ms office"], "soft_skills": ["outgoing personality", "organized", "detailed"], "languages_combined": [{"language": "english", "language_level": ["good command"]}, {"language": "chinese", "language_level": ["good command", "proficient"]}]}, "experience_required": {"duration": ["1 year"], "field": ["relevant working experience"]}}, {"job_id": "100003009046070", "location_code": "hk", "company": "Ocean Park Corporation", "job_title": "\u7dad\u751f\u7cfb\u7d71\u64cd\u4f5c\u54e1 / Life Support Operations Operator", "description": "\u516c\u53f8\u8cc7\u6599:\n\n\u76ee\u524d\u4e16\u754c\u4e0a\u6700\u5927\u7684\u904b\u8f38\u516c\u53f8\u4e4b\u4e00\n\n\u85aa\u916c\u798f\u5229 :\n\n\n\u96d9\u7ce7\u3001 \u914c\u60c5\u6027\u82b1\u7d05\n12\u81f318\u500b\u5de5\u4f5c\u5929\u6709\u85aa\u5e74\u5047\n5\u5929\u6709\u85aa\u4f8d\u7522\u5047\n\u9580\u8a3a\u53ca\u4f4f\u9662\u798f\u5229(\u5305\u62ec\u4e2d\u91ab\u3001\u8dcc\u6253)\n\u7259\u79d1\u4fdd\u5065\n\u4eba\u58fd\u4fdd\u96aa\n\u5bb6\u5ead\u91ab\u4fdd\n\u8077\u8cac:\n\n\n\u8ca0\u8cac\u8a08\u5283\u53ca\u57f7\u884c\u5de5\u4f5c\u5730\u9ede\u5167\u4f8b\u884c\u8a2d\u65bd\u4fdd\u990a\u6216\u6545\u969c\u7dad\u4fee\u5de5\u4f5c\n\u5354\u52a9\u7ba1\u7406\u53ca\u4f8b\u884c\u6aa2\u67e5\u516c\u53f8\u8a2d\u65bd\u548c\u6a5f\u5668\n\u78ba\u4fdd\u6240\u6709\u5de5\u7a0b\u7b26\u5408\u53ca\u9075\u5b88\u653f\u5e9c\u6cd5\u4f8b\n\u8ca0\u8cac\u96fb\u5668\u548c\u6e2c\u91cf\u8a2d\u5099\u7684\u57fa\u672c\u710a\u63a5\u3001\u64cd\u4f5c\u548c\u5b89\u88dd\n\u70ba\u66f4\u63db\u6216\u5347\u7d1a\u7cfb\u7d71\u6027\u80fd\u63d0\u4f9b\u5efa\u8b70\u548c\u89e3\u6c7a\u65b9\u6848\n\u5fc5\u9808\u719f\u6089\u61c9\u7528\u65bc\u76f8\u95dc\u5de5\u4f5c\u7684\u516c\u53f8\u5b89\u5168\u898f\u5247\n\u5fc5\u9808\u540c\u610f\u6309\u7167\u8f2a\u73ed\u6642\u9593\u8868\u5de5\u4f5c\n\u8cc7\u6b77 :\n\n\n\u6301\u6709\u6a5f\u96fb/\u6a5f\u68b0/\u5c4b\u5b87\u88dd\u5099\u5de5\u7a0b/\u8a2d\u65bd\u7ba1\u7406\u7684\u6587\u6191; \u6216\u540c\u7b49\u5b78\u6b77\n\u5177\u81f3\u5c115\u5e74\u6709\u95dc\u5927\u5ec8\u8a2d\u65bd\u7dad\u4fee\u5de5\u4f5c\u7d93\u9a57\n\u9808\u6301\u6709\u6548\u96fb\u5de5A\u724c\n\u826f\u597d\u89e3\u96e3\u53ca\u61c9\u5c0d\u6295\u8a34\u7684\u80fd\u529b\n\n\n\nTo apply online, \u00a0please click the Apply button below. For a confidential discussion about this role please contact us on +852 5593 9228.\n\n\n\nPersonal data collected will be used for recruitment purposes only.", "employment_types": ["Full Time", "Contract"], "selling_points": ["\u6cf5\u623f\u8a2d\u65bd\u64cd\u4f5c", "\u52d5\u7269\u6c34\u6c60\u5faa\u74b0\u3001\u904e\u6ffe\u3001\u6bba\u83cc\u3001\u51b7\u51cd\u52a0\u71b1\u7cfb\u7d71", "\u6c34\u548c\u7a7a\u6c23\u8cea\u7d20\u63a7\u5236"], "locations": ["Aberdeen"], "categories": ["Others", "Agriculture / Forestry / Fishing", "Engineering", "Electrical / Electronics", "Mechanical"], "post_time": "2022-01-13T09:31:56Z", "salary": {"currency": null, "max": null, "min": null, "period": "monthly", "term": null}, "salary_visible": false, "title_keywords": ["operations", "operator"], "responsibilities": ["personal data", "recruitment", "contact"], "requirements": {"degrees": [], "majors": [], "languages": [], "language_level": [], "hard_skills": [], "soft_skills": [], "languages_combined": []}, "experience_required": {"duration": [], "field": []}}, {"job_id": "100003009043256", "location_code": "hk", "company": "Cathay Pacific Airways Ltd", "job_title": "Deputy Simulator Engineering Team Lead", "description": "Job Summary:\nThe primary purpose of this role is to manage the company owned vehicles, club cars, equipment and related facilities, such as fuel stations, and support Office and Fleet Services (OFS) Manager to manage daily operations/ad hoc requests.\nResponsibilities:\nManage company owned vehicles, club cars, equipment and related facilities in safe, good conditions and compliance with regulatory requirement\nSchedule preventive/corrective maintenance schedule in cost effective and safety manners\nDiagnose the problem, provide recommendation and improvement plan to drive safety, efficiency and cost savings opportunities\nManage vendor performance to ensure their KPIs and deliverables. Coordinate with vendor to preform vehicle inspection and prepare all required document for license renewal\nIdentify business requirement for RFP/quotation and comply with the company policy\nDrive possible safety measures with stakeholder/vendor to prevent vehicles incidents.\nLead the study on new technology and insight to drive efficiency and sustainability\nPrepare regular report for management reporting\nProvide backup and support to OFS operation upon request\nBasic Qualifications:\nBachelor Degree in mechanical, automotive engineering or related disciplines\nAt least 5 years of relevant working experience in MNCs\nGood communication and interpersonal skill to deal with executives, internal and external stakeholders and vendor\nValid HK driving license \u2013 Class 1 or 2 is preferred\nFluent in both English and Cantonese\nAdditional Information:\nSUBMITTING YOUR APPLICATION\nAfter clicking \u201cApply for this job\u201d below, the employment application will open in a new window. Please complete ALL pages of the application in ENGLISH by clicking \u201cNext\u201d on each page, then \u201cSubmit\u201d on the final page.\n#LI-CL1 HKProfessional", "employment_types": ["Full Time"], "selling_points": ["At least 6 years relevant experience", "Maintenance & operations on training equipment", "Travel Benefits, 5-days work, Medical Benefits"], "locations": ["Lantau Island"], "categories": ["Transportation & Logistics", "Aviation Services", "Engineering", "Mechanical"], "post_time": "2022-01-12T10:23:36Z", "salary": {"currency": null, "max": null, "min": null, "period": "monthly", "term": null}, "salary_visible": false, "title_keywords": ["lead"], "responsibilities": ["cost", "maintenance", "ad hoc requests", "compliance", "diagnose", "coordinate with", "quotation", "inspection", "provide recommendation", "communication", "schedule", "plan", "management reporting", "prepare regular report", "kpis", "manage daily operations"], "requirements": {"degrees": ["degree", "bachelor"], "majors": ["related disciplines", "engineering"], "languages": ["cantonese", "english"], "language_level": ["fluent"], "hard_skills": ["safe", "basic", "vendor", "maintenance"], "soft_skills": ["communication", "interpersonal skill"], "languages_combined": [{"language": "cantonese", "language_level": ["fluent"]}, {"language": "english", "language_level": ["fluent"]}]}, "experience_required": {"duration": ["at least 5 years"], "field": ["relevant working experience"]}}, {"job_id": "100003009042890", "location_code": "hk", "company": "Ngong Ping 360 Limited", "job_title": "Technical Services Engineer - Systems (Ref: 220013)", "description": "Responsibilities\n\n\nCoordinate the installation, repair and maintenance works which included electrical, plumbing & drainage, air-conditioning and builder works for all kinds of building properties, including bidding and customer relationship\u00a0management and guiding subordinates to complete related engineering tasks.\nResponsible for bidding quotation, budgeting and settlement statistics.\nResponsible for daily operation management of maintenance and repair projects and execute related processes.\nMonitoring and control the work quality and safety as per client required.\nResponsible for coordinating all related projects with customers, suppliers, subcontractors and subordinates.\nResponsible for arranging, guiding and supervising subordinates and subcontractors to complete related maintenance and repair projects.\nParticipate in various types of project meetings\n\n\u00a0Requirements\n\nBachelor\u2019s degree or above in Mechanical / Building Services / Electrical Engineering or related discipline;\nMinimum 10 years' experience in E&M, relevant experience on\u00a0Maintenance Services projects is advantageous\nProficient in AutoCAD\nGood co-ordination and interpersonal skill\nGood command of written and spoken English and Chinese\n\n\u00a0Candidates with less experience will be consider as Assistant Project Manager.\n\nFor interested parties, please email your resume with expected salary to us.\u00a0\u00a0", "employment_types": ["Full Time", "Permanent"], "selling_points": ["Provide engineering / technical support", "Degree holder or above in Mechanical", "Minimum 8 years\u2019 relevant experience"], "locations": ["Not Specified"], "categories": ["Engineering", "Electrical / Electronics", "Engineering Project Management", "Mechanical"], "post_time": "2022-01-12T09:11:05Z", "salary": {"currency": null, "max": null, "min": null, "period": "monthly", "term": null}, "salary_visible": false, "title_keywords": ["technical services engineer"], "responsibilities": ["installation", "management", "control", "supervising", "maintenance", "budgeting", "quotation", "daily operation", "monitoring", "coordinate", "repair", "work quality", "repair and maintenance works"], "requirements": {"degrees": ["degree or above", "bachelor"], "majors": ["building services", "electrical engineering"], "languages": ["english", "chinese"], "language_level": ["good command"], "hard_skills": ["maintenance", "autocad"], "soft_skills": ["interpersonal skill"], "languages_combined": [{"language": "english", "language_level": ["good command"]}, {"language": "chinese", "language_level": ["good command"]}]}, "experience_required": {"duration": ["minimum 10 years"], "field": ["relevant experience", "maintenance"]}}, {"job_id": "100003009047392", "location_code": "hk", "company": "Hip Hing Construction Co Ltd", "job_title": "Technical Assistant (Building Services)", "description": "Job Descriptions\n\nAssists in the HVAC for projects including but not limited to prepare design deliverables, authorities\u2019 submissions and tender.\nAssists in Project delivery including preparation of reports, statutory submissions and presentations.\nAssists in supervising site works.\u00a0\nPrepares drawings and technical matters.\n\n\u00a0Job Specifications\u00a0\n\nDegree holder in Mechanical or Building Services Engineering with 2 years or above related disciplines working experience.\nCompletion of HKIE Scheme \u2018A\u2019 Training or Higher Diploma with 2 years or above relevant working experience.\nProficiency in both written and spoken English and Chinese. Fluency in Putonghua is preferred.\nTeam player with excellent interpersonal and communication skills\u00a0\n\nInterested applicants, please send full resume stating the present & expected salary and date of availability to\u00a0Human Resources Department, Level 11, Tower 1, Millennium City 1, 388 Kwun Tong Road, Kowloon\u00a0or fax to\u00a02267 3299\u00a0or send the application by clicking the\u00a0\"Apply Now\" button.\u00a0\n\n(Personal data collected would be used for recruitment purpose only. All personal data of unsuccessful candidates will be destroyed after six months.)", "employment_types": ["Full Time", "Permanent"], "selling_points": ["Electrical or Mechanical or BS Engineering", "3 years drafting experience", "AutoCAD, Revit and Photoshop"], "locations": ["Not Specified"], "categories": ["Building & Construction", "Building / Construction / QS", "Engineering", "Electrical / Electronics", "Mechanical"], "post_time": "2022-01-14T02:58:46Z", "salary": {"currency": null, "max": null, "min": null, "period": null, "term": null}, "salary_visible": false, "title_keywords": ["technical assistant"], "responsibilities": ["supervising", "presentations", "design", "drawings", "communication", "specifications", "reports", "recruitment", "tender", "personal data"], "requirements": {"degrees": ["diploma", "degree holder"], "majors": ["related disciplines", "building services", "engineering"], "languages": ["putonghua", "english", "chinese"], "language_level": ["fluency", "proficiency"], "hard_skills": ["hvac", "hkie", "scheme", "presentations"], "soft_skills": ["communication skills", "team player", "interpersonal"], "languages_combined": [{"language": "putonghua", "language_level": ["fluency"]}, {"language": "english", "language_level": ["proficiency"]}, {"language": "chinese", "language_level": ["proficiency"]}]}, "experience_required": {"duration": ["2 years"], "field": ["training", "engineering", "related", "relevant working experience", "building services"]}}]