[{"job_id": "100003009044818", "location_code": "hk", "company": "Hai Kang Life Corporation Ltd", "job_title": "Engineering Manager", "description": "Responsibilities:\n\nWork closely with the research scientists and support a small team of engineers, primarily, you will take charge of all technical engineering needs for R&D project plans, manage project status and overall process in achieving project goals:\nAdministering the project and monitoring all engineering work;\nFinish architect design for molecular diagnosis medical devices including machine work-flow and procedure layout to identify key steps for completeing a sample-in-result-out test, control layout & AP specifications;\nEffectively manage problems throughout prototyping phase, e.g. identify and troubleshoot technical issues;\nIndustrial design to include 3D hardware structure data, BOM and drawings of all modules and components, finalize system integration including system architecture and liquid level detection control;\nPre-clinical evaluations, and transfer of product to manufacturing;\nComplete project reports\nLiaise with vendors and external research organizations to carry out the strategic partnerships;\nDevelop and strengthen the engineering team.\n\nRequirements:\n\nMaster Degrees or above in bioengineering, mechatronics, mechanics, electronics, optical and related disciplines;\nOver 5-10years relevant project management and leadership experience in the development of medical devices, especially in the application and commercialization of research findings;\nStrong technical competencies in design, debug and problem solving;\nAbility to formulate scientific hypothesis and demonstrate technical proficiency, scientific creativity,\nAble to collaborate with others while maintain independent thought;\nDetail-minded, committed, can-do attitude and can work under pressure;\nExcellent communications and interpersonal skills;\nGood command of the English and Chinese languages, written and spoken, including Cantonese and Mandarin.\nIf you are passionate, driven and looking for a new and exciting opportunity within a successful and growing company, this may be the right role for you.\nPlease click \u201cApply Now\u201d to submit your application.\nAll Personal data collected will be strictly confidential and used for recruitment purpose only. Applicants who are not invited to an interview within one month from the closing date should consider their applications unsuccessful. If you are not selected, all data will be destroyed within six months from the date you applied.\u00a0", "employment_types": ["Full Time", "Permanent"], "selling_points": ["Provide technical leadership, execute R&D project", "Competitive Salary", "5 days work, group medical insurance"], "locations": ["Shatin Area"], "categories": ["Engineering", "Electrical / Electronics", "Mechanical", "Others"], "post_time": "2022-01-13T06:24:47Z", "salary": {"currency": null, "max": null, "min": null, "period": "monthly", "term": null}, "salary_visible": false, "title_keywords": ["engineering manager"], "responsibilities": ["ap", "control", "data", "monitoring", "design", "drawings", "project reports", "hardware", "develop", "specifications", "troubleshoot", "liaise with", "plans", "architecture"], "requirements": {"degrees": ["master"], "majors": ["related disciplines"], "languages": ["cantonese", "english", "chinese", "mandarin"], "language_level": ["good command"], "hard_skills": ["problem solving", "project management"], "soft_skills": ["detail-minded", "passionate", "independent", "can-do attitude", "problem solving", "project management", "committed", "interpersonal skills", "leadership", "driven", "work under pressure"], "languages_combined": [{"language": "cantonese", "language_level": ["good command"]}, {"language": "english", "language_level": ["good command"]}, {"language": "chinese", "language_level": ["good command"]}, {"language": "mandarin", "language_level": ["good command"]}]}, "experience_required": {"duration": [], "field": ["project management", "development", "research", "medical"]}}, {"job_id": "100003009055037", "location_code": "hk", "company": "Meinhardt (Hong Kong) Limited", "job_title": "Assistant Secretary (Ref: 12021)", "description": "Job Duties\nResponsible Office and General Admin;\nSecretarial duties and data input, scan and photocopy, etc.;\nSupport daily operation;\nAble to handle and organize multi-task;\nAssist Ad hoc tasks as assigned.\nRequirements\nHKDSEE or above;\n2-3 years\u2019 experience;\nGood PC knowledge;\nGood command of English and Chinese;\nSelf-motivated with positive working attitude.\nBenefit Package including\n5 days\u2019 work;\nMedical insurance;\nPublic holiday, Birthday leave, Marriage leave etc.;\nDiscretionary reward pay.\nLocation: 5 minutes\u2019 walk from Wong Chuk Hang Station\n(Candidates with more experience will be considered as Secretary)\nPlease send full resume with details of availability and last & expected salary (quoting reference) to:\nHuman Resources Manager\nMeinhardt Consulting Engineers\n10/F Genesis, 33-35 Wong Chuk Hang Road, Hong Kong\nOR click \u201cApply Now\u201d to submit your application\u00a0\u00a0\u00a0\u00a0\u00a0\u00a0\u00a0 \u00a0http://www.meinhardtgroup.com\nData collected will be used for recruitment purpose only and will be destroyed within six months from date of application.", "employment_types": ["Full Time", "Permanent"], "selling_points": ["HKDSEE or above", "5 days' work, medical insurance, birthday leave", "More experience will be considered as Secretary"], "locations": ["Southern Area"], "categories": ["Admin & HR", "Clerical / Admin Staff", "Secretary", "Engineering", "Others"], "post_time": "2022-01-18T00:42:20Z", "salary": {"currency": null, "max": null, "min": null, "period": "monthly", "term": null}, "salary_visible": false, "title_keywords": ["secretary", "assistant"], "responsibilities": ["ad hoc tasks", "daily operation", "data input"], "requirements": {"degrees": [], "majors": [], "languages": ["english", "chinese"], "language_level": ["good command"], "hard_skills": ["pc knowledge"], "soft_skills": ["positive working attitude", "self-motivated"], "languages_combined": [{"language": "english", "language_level": ["good command"]}, {"language": "chinese", "language_level": ["good command"]}]}, "experience_required": {"duration": ["2-3 years"], "field": []}}, {"job_id": "100003009052412", "location_code": "hk", "company": "MVA Hong Kong Ltd", "job_title": "Traffic Engineer (Graduate / Assistant / Engineer / Senior / Principal)", "description": "We are now looking for high calibres to join our professional team to cope with our business growth. Appropriate roles will be offered to the qualified candidates subject to their past working experience. Candidates with more professional & project experience will be considered as Senior / Principal.\u00a0 \u00a0\n\nRequirements:\n\nFresh Graduate and upto 10+ years working experience and interested in developing a career in Traffic Engineering and Transportation Planning\nDegree in Civil Engineering, Transportation Engineering/ Planning or equivalent\nBased in Hong Kong\nWillingness to travel to fit in with the regional work geographic coverage\nAble to work independently\nGood communication skills in English are essential, with Cantonese/Putonghua an advantage\nCandidates may be offered appropriate grades subject to past working experience \u00a0\n\nWe offer an attractive remuneration package with 5-day work week to the right candidate. Interested parties who are confident of fulfilling the above requirements can send us your most recent CV, detailing academic profile/ Transcript and work experiences, as well as current and expected salary packages by pressing \u201cApply Now\u201d.\n\nFor more details on MVA, please check our website at www.mvaasia.com\n\n\u00a0**Personal data collected will be used for recruitment purposes only**", "employment_types": ["Full Time", "Permanent"], "selling_points": [], "locations": ["Southern Area"], "categories": ["Engineering", "Others", "Others", "Student / Fresh Graduate / No Experience", "Transportation & Logistics", "Public Transportation"], "post_time": "2022-01-17T02:58:54Z", "salary": {"currency": null, "max": null, "min": null, "period": "monthly", "term": null}, "salary_visible": false, "title_keywords": ["engineer", "assistant"], "responsibilities": ["communication", "developing", "planning"], "requirements": {"degrees": ["degree", "fresh graduate"], "majors": ["engineering", "civil engineering"], "languages": ["cantonese", "putonghua", "english"], "language_level": ["advantage", "good"], "hard_skills": [], "soft_skills": ["communication skills", "work independently", "interested in"], "languages_combined": [{"language": "cantonese", "language_level": ["advantage", "good"]}, {"language": "putonghua", "language_level": ["advantage", "good"]}, {"language": "english", "language_level": ["good"]}]}, "experience_required": {"duration": ["10+ years"], "field": ["engineering", "developing", "planning"]}}, {"job_id": "100003009051693", "location_code": "hk", "company": "Pyrofoe Engineers Ltd", "job_title": "Asst. Engineer", "description": "1-2 years experience min. in Fire Services Installation\nCan work independently\nRequire full-time on site\nGood at ACAD\nApplicant is required to send CV and expected salary to Pyrofoe Engineers Ltd (\u885e\u5b89\u5de5\u7a0b\u6709\u9650\u516c\u53f8) by fax 2385 2150 or email via \"Apply Now\" for interview arrangement.", "employment_types": ["Full Time", "Permanent"], "selling_points": [], "locations": ["Not Specified"], "categories": ["Engineering", "Electrical / Electronics", "Others", "Building & Construction", "Others"], "post_time": "2022-01-16T21:50:50Z", "salary": {"currency": null, "max": null, "min": null, "period": "monthly", "term": null}, "salary_visible": false, "title_keywords": ["asst. engineer"], "responsibilities": ["installation", "interview arrangement"], "requirements": {"degrees": [], "majors": [], "languages": [], "language_level": [], "hard_skills": [], "soft_skills": ["work independently"], "languages_combined": []}, "experience_required": {"duration": ["1-2 years"], "field": []}}, {"job_id": "100003009054980", "location_code": "hk", "company": "Asia Airfreight Terminal Co Ltd", "job_title": "Technical Services Engineer (Shift duty is required)", "description": "Duties\n\nLead the in-house specialist team and external contractor to complete services improvement projects including but not limited to Material Handling System enhancement, facilities enhancement, operations flow analysis and system automation\nManage and monitor the project completion within budget, assigned time frame and comply quality requirement\nAssist on project budget preparation\n\n\u00a0Requirements\n\nBachelor Degree\u00a0or above\u00a0in Mechanical\u00a0or\u00a0Industrial Engineering\n2\u00a0years\u00a0experience\u00a0in project management and contractor management\nKnowledge in Microsoft Office and AutoCAD\nMature,\u00a0independent\u00a0and analytical mind\nExperience in cargo terminal and logistic industry will be an advantage\nShift duty is required\nFresh graduates are welcome\n\nWe offer the right incumbent attractive remuneration package including 13 days annual leave, 5-day week, double pay, performance bonus, medical scheme, life insurance, travel allowance and education subsidy.\u00a0\n\nInterested parties please send your full resume with reference no., recent and expected salary to:\u00a0Human Resources Department, Asia Airfreight Terminal Co. Ltd., 10 Chun Ping Road, Hong Kong International Airport, Lantau, Hong Kong\u00a0OR Fax to\u00a02286 0374\u00a0OR\u00a0Please click \u201cApply Now\u201d to submit your application.\n\n\u00a0To know more about AAT, please visit\u00a0http://www.aat.com.hk/\n\nWe are an equal opportunity employer and welcome applications from all qualified candidates. We will not be responsible for any disclosure or the loss of personal data during transmission. All personal data collected will be used for recruitment only. Information of unsuccessful candidates will be destroyed after 3 months from the date of application.", "employment_types": ["Full Time", "Permanent"], "selling_points": ["5-day week, double pay, performance bonus", "Lead in-house contractors to complete maintenance", "Fresh graduates are welcome"], "locations": ["Airport Area"], "categories": ["Transportation & Logistics", "Others", "Engineering", "Engineering Project Management", "Others"], "post_time": "2022-01-17T16:22:43Z", "salary": {"currency": null, "max": null, "min": null, "period": "monthly", "term": null}, "salary_visible": false, "title_keywords": ["technical services engineer"], "responsibilities": ["operations", "analysis", "budget", "monitor", "quality", "material handling system"], "requirements": {"degrees": ["degree or above", "bachelor"], "majors": ["engineering"], "languages": [], "language_level": [], "hard_skills": ["project management", "autocad", "scheme", "microsoft office"], "soft_skills": ["project management", "analytical mind", "independent", "mature"], "languages_combined": []}, "experience_required": {"duration": ["2 years"], "field": ["project management", "management"]}}, {"job_id": "100003009055191", "location_code": "hk", "company": "Hong Da Landscaping Limited", "job_title": "Project Coordinator", "description": "We are one of the rapid growing landscape contractor offer multiple specialized services in Hong Kong. Our scope of service covers soft and hard landscape construction, arboriculture consulting and contracting, sports turf construction and management, nursery productions and sophisticated data analysis and diagnosis services such as Geological Information System spatial data collections, Tree Sonic Tomography, Chlorophyll Fluorescence check and Ground Penetration Radar scanning in Hong Kong, China and Australia. Our local projects involve majority of the properties developers and main contractors and government departments in HK. We are approved landscape specialist contractor under the list of Development Bureau, Hong Kong SAR Government.\n\nWe are looking for multiple high calibre personnel to join our team in HK.\n\nProject Coordinator\n\nJob description\n~ Report to Project Supervisor and Project Manager.\n~ Assistant to prepare project documentation, materials take-off, programme planning, site progress\n\u00a0\u00a0 monitoring and reporting and soft landscape related coordination in the project.\n~ Assistant to coordinate and liaise with client, architects, main contractors, government departments,\n\u00a0\u00a0 and sub-contractors, etc.\n~ Oversee site labour safety.\n~ Assistant to prepare materials submissions, method statement and safety plans.\n\nJob requirements\n~ Sound knowledge of soft landscape and/or horticulture.\n~ High Diploma or above in horticulture, arboriculture, botany, forestry, biology, environment study or\n\u00a0\u00a0 equivalent.\n~ Proficient in Auto CAD, MS Project, Word, Excel, and Report Editing.\n~ Good command in English and Chinese.\n~ Confidence to liaise with clients, architect, main contractors, consultants and sub-contractors.\n~ 1-2 years of site related management experiences.\n~ Valid HK driving license is an advantage.\n\nOur remuneration package includes, 5.5 days works, 12 days annual leaves, year-end bonus, oversea training, job related study-aid and good career prospects for the candidates.\n\nPlease provide your detailed resume with expected salaries and date available.", "employment_types": ["Full Time", "Permanent"], "selling_points": [], "locations": ["Not Specified"], "categories": ["Engineering", "Others", "Sciences, Lab, R&D", "Environmental Science / Waste Management", "Building & Construction", "Others"], "post_time": "2022-01-18T01:43:35Z", "salary": {"currency": null, "max": null, "min": null, "period": "monthly", "term": null}, "salary_visible": false, "title_keywords": ["project coordinator"], "responsibilities": ["reporting", "monitoring", "safety plans", "coordinate", "planning", "liaise with client", "coordination", "report", "project documentation"], "requirements": {"degrees": ["high diploma or above"], "majors": ["biology", "forestry", "botany"], "languages": ["english", "chinese"], "language_level": ["good command"], "hard_skills": ["excel", "auto cad", "word"], "soft_skills": ["confidence", "detailed"], "languages_combined": [{"language": "english", "language_level": ["good command"]}, {"language": "chinese", "language_level": ["good command"]}]}, "experience_required": {"duration": ["1-2 years"], "field": ["related", "management"]}}, {"job_id": "100003009034643", "location_code": "hk", "company": "S.H.K. Real Estate Management Company Limited", "job_title": "\u9ad8\u7d1a\u6280\u8853\u54e1/ \u6280\u8853\u54e1- \u6a5f\u96fb/\u51b7\u6c23/\u6c34\u5589 (5.5\u59299\u5c0f\u6642 / \u8f2a\u73ed)", "description": "\u8ca0\u8cac\u5546\u696d\u5927\u5ec8\u51b7\u6c23\u6216\u6c34\u5589\u7dad\u4fee\u53ca\u4fdd\u990a\n\u521d\u4e2d\u7a0b\u5ea6\u6216\u5177\u8cc7\u6b77\u67b6\u69cb\u540c\u7b49\u8cc7\u6b77\uff0c\u5177\u76f8\u95dc\u5de5\u7a0b\u8b49\u66f8\u66f4\u4f73\n\u5177\u76f8\u95dc\u5de5\u7a0b\u7d93\u9a57\u512a\u5148\u8003\u616e\uff0c\u7d93\u9a57\u8f03\u591a\u8005\u53ef\u8058\u7528\u70ba\u9ad8\u7d1a\u6280\u8853\u54e1\n\u85aa\u91d1\u53ef\u9054\u6bcf\u6708 $19,000 - $23,500\n\n\u4ee5\u4e0a\u8077\u4f4d\u53ef\u4eab\u6709\u512a\u539a\u54e1\u5de5\u798f\u5229\uff0c\u5305\u62ec\u6bcf\u67086\u5929\u6709\u85aa\u4f11\u606f\u65e5\u3001\u6709\u85aa\u5e74\u50479\u5929\u3001\u52e4\u5de5\u734e\u3001\u5e74\u7d42\u96d9\u7ce7\u3001\u91ab\u7642\u798f\u5229\u3001\u5b8c\u5584\u57f9\u8a13\u53ca\u6649\u5347\u6a5f\u6703\u7b49\u3002\n\n\u6709\u610f\u8005\uff0c\u8acb\u900f\u904e\u4ee5\u4e0b\u65b9\u6cd5\u7533\u8acb\uff1a\n\n\u7063\u4ed4\u5340\uff1a3766 6155\u00a0\u5f35\u5c0f\u59d0\n\u8343\u7063\u5340\uff1a2412 5772 \u6c60\u5148\u751f\n\u5c16\u6c99\u5480\u5340\uff1a2312 2110 \u5468\u5c0f\u59d0\n\n\u9664\u4e0a\u8ff0\u8077\u4f4d\u5916\uff0c\u5c1a\u6709\u5176\u4ed6\u7a7a\u7f3a\u3002\u8acb\u900f\u904e\u4ee5\u4e0b\u65b9\u6cd5\u5c07\u5c65\u6b77\u4ea4\u5230S.H.K. \u7269\u696d\u7ba1\u7406\u6709\u9650\u516c\u53f8\u4e4b\u4eba\u529b\u8cc7\u6e90\u53ca\u884c\u653f\u90e8\u3002\n\n\u90f5\u5bc4\uff1a\u89c0\u5858\u5de7\u660e\u885795\u865f\u4e16\u9054\u4e2d\u5fc316\u6a13\u3000\u50b3\u771f\uff1a2827 2125\n\nS.H.K. \u7269\u696d\u7ba1\u7406\u6709\u9650\u516c\u53f8\u4e43\u5e73\u7b49\u6a5f\u6703\u50f1\u4e3b\uff0c\u800c\u6240\u6709\u6536\u96c6\u8cc7\u6599\u7d55\u5c0d\u4fdd\u5bc6\u53ca\u53ea\u7528\u4f5c\u96c6\u5718\u5167\u90e8\u62db\u8058\u4e4b\u7528\u9014\u3002", "employment_types": ["Full Time", "Permanent"], "selling_points": ["\u8ca0\u8cac\u5546\u696d\u5927\u5ec8\u51b7\u6c23\u6216\u6a5f\u96fb\u7dad\u4fee\u53ca\u4fdd\u990a", "\u521d\u4e2d\u7a0b\u5ea6\uff0c\u5177\u76f8\u95dc\u5de5\u7a0b\u7d93\u9a57\u53ca\u8b49\u66f8\u66f4\u4f73", "9\u5c0f\u6642\u8f2a\u73ed\u5de5\u4f5c"], "locations": ["Not Specified"], "categories": ["Engineering", "Mechanical", "Others", "Property / Real Estate", "Others"], "post_time": "2022-01-16T21:50:09Z", "salary": {"currency": null, "max": null, "min": null, "period": "monthly", "term": null}, "salary_visible": false, "title_keywords": ["\u6280\u8853\u54e1"], "responsibilities": [], "requirements": {"degrees": [], "majors": [], "languages": [], "language_level": [], "hard_skills": [], "soft_skills": [], "languages_combined": []}, "experience_required": {"duration": [], "field": []}}, {"job_id": "100003009054439", "location_code": "hk", "company": "Keio Engineering Co Ltd", "job_title": "Maintenance Supervisor", "description": "To meet the rapid business expansion, we are looking for an additional new headcount for the position of Maintenance Supervisor to join our Maintenance team.\n\nWhat we look for?\n\nSupervise a team of maintenance technicians and coordinate with sub-contractors on daily work progress;\nProvide effective solutions for solving the maintenance issues;\nResponsible for the entire work progress including but not limited to monitoring, and inspecting E&M A&A Projects, Operation, Maintenance, and Repair works;\nEstablish, update, and implement routine of maintenance services schedule as well as emergency repairs;\nMaintain relationship with existing clients, and able to resolve client enquiries in a professional manner;\nPerform internal and external administrative reports and ad hoc duties assigned by Maintenance Engineer and Manager, Mechanical.\n\nWhat you need to succeed?\n\nCertificate or Higher Diploma in Electrical or Mechanical Engineering or Building Services Engineering;\n5 years relevant experience in E&M or Building Services industry;\nGood command of both written and spoken in Chinese and English;\nExcellent communication, and analytical skills with strong sense of responsibility;\nCandidate with certificate of Registration of Electrical Worker (Grade A0) or above, Driver License, certificate of Safety Supervisor will be an advantage.\nWilling to work on night shift when it is required.\n\nWhat we offer?\n\nStable and friendly work environment\nOpen office design\nAnnual leave\nMedical insurance\nEducation subsidy\nYear-end double pay\nDiscretionary bonus\nExcellent career development\nUnlimited beverages and snacks\nInternal and external training programme\nOn-job training\n\nInterested parties, please send your detailed resume with expected salary via \u201cApply Now\u201d for our consideration. All data collected will be used for recruitment purpose only.", "employment_types": ["Full Time", "Permanent"], "selling_points": ["Year-end double pay", "E&M or Building Services industry", "Supervise a team of maintenance technicians"], "locations": ["Sai Wan"], "categories": ["Engineering", "Electrical / Electronics", "Mechanical", "Others"], "post_time": "2022-01-17T09:36:53Z", "salary": {"currency": null, "max": null, "min": null, "period": "monthly", "term": null}, "salary_visible": false, "title_keywords": ["supervisor"], "responsibilities": ["ad hoc duties", "maintenance", "monitoring", "coordinate with", "professional manner", "communication", "repair", "maintain", "reports", "schedule", "maintenance services"], "requirements": {"degrees": ["certificate", "diploma"], "majors": ["building services", "engineering", "mechanical engineering"], "languages": ["english", "chinese"], "language_level": ["good command"], "hard_skills": ["certificate of registration of electrical worker", "analytical skills", "maintenance", "rapid"], "soft_skills": ["communication", "sense of responsibility", "responsible", "analytical skills"], "languages_combined": [{"language": "english", "language_level": ["good command"]}, {"language": "chinese", "language_level": ["good command"]}]}, "experience_required": {"duration": ["5 years"], "field": ["building services", "relevant experience"]}}, {"job_id": "100003009053599", "location_code": "hk", "company": "AFSC Operations Limited", "job_title": "\u6cb9\u5eab\u7dad\u4fee\u6280\u5de5", "description": "\n\u2022\u00a0 \u6cb9\u5eab\u8a2d\u5099\u7dad\u4fee\u53ca\u4fdd\u990a\u5de5\u4f5c\n\u2022\u00a0 \u6301\u6709\u6709\u6548\u96fb\u5de5A\u724c\n\u2022\u00a0 \u5354\u52a9\u5b89\u88dd\u53ca\u6e2c\u8a66\u6a5f\u5668\u53ca\u8a2d\u5099\n\u2022\u00a0 \u5177\u6cb9\u5eab /\u6a5f\u5834\u76f8\u95dc\u5de5\u4f5c\u7d93\u9a57\u512a\u5148\n\u4e0a\u8ff0\u8077\u4f4d\u9808\u6236\u5916\u5de5\u4f5c\uff0c\u4e2d\u4e09\u6216\u4ee5\u4e0a\u7a0b\u5ea6\uff0c\u9808\u6301\u6709\u99d5\u99db\u57f7\u7167(1-2\u865f)\uff0c\u5982\u670918\u724c\u8005\u66f4\u4f73\uff0c\u5177\u826f\u597d\u99d5\u99db\u8a18\u9304\u3002\n\n", "employment_types": ["Full Time"], "selling_points": [], "locations": ["Not Specified"], "categories": ["Engineering", "Others", "Others", "Technician"], "post_time": "2022-01-17T07:13:11Z", "salary": {"currency": null, "max": null, "min": null, "period": "monthly", "term": null}, "salary_visible": false, "title_keywords": [], "responsibilities": [], "requirements": {"degrees": [], "majors": [], "languages": [], "language_level": [], "hard_skills": [], "soft_skills": [], "languages_combined": []}, "experience_required": {"duration": [], "field": []}}, {"job_id": "100003009052819", "location_code": "hk", "company": "The Hongkong Electric Co., Ltd", "job_title": "Technician (CS) (Ref. No.  CS-CS-TCS-JD)", "description": "Responsibilities:\n\nReporting to the Customer Services Manager, the appointee will perform the following responsibilities:\n\nTo conduct site checking and verification on meter condition and perform meter readings related duties\nTo perform connection and disconnection of electricity supply at customer premises\n\nRequirements:\n\nForm 5 or above\nA minimum of 3 years\u2019 work experience preferably in relation to customer services, installation or meter readings\nFamiliar with the roads on Hong Kong Island and Lamma Island\nHolder of a valid driving license for class 1 preferred\nAble to read, write and speak Cantonese and simple English\n\nWorking Location: North Point\n\nThis is a 2-year contract position. Renewal of contract is subject to the Company\u2019s business needs and performance of the individual.\n\nApplication:\n\nIf you are interested in this position, please send your resume\u00a0(in PDF format)\u00a0with details of qualification, experience, present and expected salaries, and contact number to the Human Resources Division, The Hongkong Electric Co., Ltd. on or before 31 January 2022\u00a0and quote the reference number in your application. Please also visit our website to know more about our Company http://www.hkelectric.com.\n\nApplicants not invited for interview within one month from the closing date may consider their applications unsuccessful. All unsuccessful applications will be kept for six months after the date of this advertisement.\n\nWe are an equal opportunity employer.\u00a0 Personal data provided by job applicants will be treated in strictest confidence and used only for recruitment-related purposes in accordance with the laws and ordinance of the HKSAR.", "employment_types": ["Full Time", "Contract"], "selling_points": ["Conduct site checking and verification", "Form 5 or above", "Familiar with the roads on Hong Kong Island"], "locations": ["North Point"], "categories": ["Engineering", "Draftsman", "Others", "Others", "Technician"], "post_time": "2022-01-17T04:09:46Z", "salary": {"currency": null, "max": null, "min": null, "period": "monthly", "term": null}, "salary_visible": false, "title_keywords": ["technician"], "responsibilities": ["reporting", "checking", "customer services"], "requirements": {"degrees": ["form 5 or above"], "majors": [], "languages": ["cantonese", "english"], "language_level": [], "hard_skills": ["simple"], "soft_skills": ["interested in", "confidence"], "languages_combined": [{"language": "cantonese", "language_level": []}, {"language": "english", "language_level": []}]}, "experience_required": {"duration": ["minimum of 3 years"], "field": ["installation", "human resources", "customer services"]}}, {"job_id": "100003009054409", "location_code": "hk", "company": "Atkins China Ltd", "job_title": "Junior Clerk", "description": "Responsibilities:\n\nProvide clerical duties to the project team: typing, filing, register\u00a0correspondence and report\u2019s preparation;\nAssist with ad-hoc duties when required;\nRequirements:\nF.5 or above;\nMin. 3 years' relevant experience, preferably has experience in construction industry;\nProficiency in MS Office (Word, Excel & PowerPoint) and Chinese Word Processing;\nGood command of written and spoken English and Chinese;\nInitiative and able to organize work efficiently and independently;\nStrong communication and interpersonal skills; and\nImmediate available is preferred.\n\nFor interested parties, please submit your application with detailed resume, current and expected salary by clicking \"Apply Now\".\n\nApplications will be treated in confidence and only be used for recruitment purposes. Those not being invited for interview within 3 months may consider their applications unsuccessful.", "employment_types": ["Full Time", "Contract"], "selling_points": ["3 years+ admin background", "HKCEE  / DSE or above", "Familiar with MS Office including Word & Excel"], "locations": ["Tsim Sha Tsui"], "categories": ["Admin & HR", "Clerical / Admin Staff", "Others", "Engineering", "Others"], "post_time": "2022-01-17T09:25:46Z", "salary": {"currency": null, "max": null, "min": null, "period": "monthly", "term": null}, "salary_visible": false, "title_keywords": ["junior clerk"], "responsibilities": ["ad-hoc duties", "report"], "requirements": {"degrees": [], "majors": [], "languages": ["english", "chinese"], "language_level": ["proficiency", "good command"], "hard_skills": ["excel", "chinese word processing", "word", "powerpoint", "ms office"], "soft_skills": ["independently", "initiative", "communication and interpersonal skills"], "languages_combined": [{"language": "english", "language_level": ["good command"]}, {"language": "chinese", "language_level": ["proficiency", "good command"]}]}, "experience_required": {"duration": ["3 years"], "field": ["construction industry", "relevant experience"]}}, {"job_id": "100003009055238", "location_code": "hk", "company": "Shun Tung Electric Co Ltd", "job_title": "Sales and Marketing Assistant", "description": "Responsibilities:\n\n- Responsible for full range of sales and marketing activities\u00a0\n\n- Handling enquiries by phone, email and business meetings\n\n- Develop sales network,\u00a0good customer relationship and service\n\n- Work closely with\u00a0external parties\n\n\nRequirements:\n\n- High Dip in Engineering, Sales and Marketing, IT or related disciplines.\n\n- Interest in Marketing / Sales\u00a0\n\n- Proactive, self disciplined with good time management\n\n\n- Good PC skills in MS Office\u00a0\n\nInterested parties please send full resume with expected salary and availability to us.\n", "employment_types": ["Full Time"], "selling_points": [], "locations": ["Kwai Hing"], "categories": ["Engineering", "Others", "Marketing / Public Relations", "Marketing - Marketing Communication", "Sales, CS & Business Devpt", "Sales - Sales Management"], "post_time": "2022-01-18T01:54:36Z", "salary": {"currency": null, "max": null, "min": null, "period": "monthly", "term": null}, "salary_visible": false, "title_keywords": ["sales and marketing assistant"], "responsibilities": ["external parties", "develop"], "requirements": {"degrees": ["high dip"], "majors": ["related disciplines", "marketing", "it", "engineering"], "languages": [], "language_level": [], "hard_skills": ["pc skills", "ms office"], "soft_skills": ["time management", "proactive"], "languages_combined": []}, "experience_required": {"duration": [], "field": []}}, {"job_id": "100003009055242", "location_code": "hk", "company": "Mun Hean Electrical Engineering (H.K.) Co Ltd", "job_title": "Engineer / Assistant Engineer (5 days work)", "description": "Duties:\n\nProvide technical support and on-site services to our clients\nPerform the equipment & software installation and maintenance.\nPreparing the documents and report.\nOpen field work and Shift Duty may be required.\nAble to work with main contractor.\n\n\n\nRequirements:\n\nCertificate or above in Electrical Engineering / Building Services Engineering or equivalent.\nMinimum 1 years' experience in field service and technical support\nGood team player, Self initiative, independent and able to work under pressure\nGood command of spoken and written English, Mandarin and Cantonese\nGood knowledge on computer & software applications\n\n\n\nInterested parties, please send full resume & expected remuneration \u00a0by clicking \u2018Apply Now\u2019 for interview. For more company details of Mun Hean, please visit our website: www.munhean.com\n\nPersonal data will be used for recruitment purpose only.", "employment_types": ["Full Time", "Permanent"], "selling_points": ["Preparing the documents and report.", "Minimum 1 years' experience", "Certificate or above in Electrical Engineering"], "locations": ["Quarry Bay"], "categories": ["Engineering", "Electrical / Electronics", "Others", "Others", "Technician"], "post_time": "2022-01-18T01:54:55Z", "salary": {"currency": null, "max": null, "min": null, "period": "monthly", "term": null}, "salary_visible": false, "title_keywords": ["assistant engineer", "engineer"], "responsibilities": ["installation", "software", "maintenance", "technical support", "report"], "requirements": {"degrees": ["certificate"], "majors": ["building services", "electrical engineering", "engineering"], "languages": ["cantonese", "english", "mandarin"], "language_level": ["good command"], "hard_skills": [], "soft_skills": ["good team player", "independent", "initiative", "work under pressure"], "languages_combined": [{"language": "cantonese", "language_level": ["good command"]}, {"language": "english", "language_level": ["good command"]}, {"language": "mandarin", "language_level": ["good command"]}]}, "experience_required": {"duration": ["minimum 1 years"], "field": []}}, {"job_id": "100003009055097", "location_code": "hk", "company": "Autotoll Limited", "job_title": "Engineer Trainee (2 Years Contract)", "description": "About The Role\u00a0:\n\nAssist day to day system maintenance & installation team works\nProject implementation\nEquipment testing & evaluation\nAbout You\u00a0:\n\nDegree in Engineering or Transport related\nGood command of both written and spoken English & Chinese\nSelf-initiative & independent & hardworking\nFresh graduate (within 2~3 years after graduation) will be also considered\n\nWhat you can get from us\n\n\nOn-the-job training, learning and development\u00a0provided\nExecutive workshops, interest class, corporate purchase discount offered by SHKP\nCompetitive salary and annual leaves\nFlexible working opportunities\n\nInterested parties, please send full resume with expected salary and available date to Human Resources and Administration Department by e-mail or by fax 2111 9459.\n\n(Data collected will be used for recruitment purpose only.)", "employment_types": ["Full Time", "Contract"], "selling_points": ["Project implementation", "Plan and manage the maintenance work", "5 days work, flexible working hour"], "locations": ["Kowloon Bay"], "categories": ["Engineering", "Electrical / Electronics", "Mechanical", "Others"], "post_time": "2022-01-18T01:15:11Z", "salary": {"currency": null, "max": null, "min": null, "period": "monthly", "term": null}, "salary_visible": false, "title_keywords": ["engineer", "trainee"], "responsibilities": ["installation", "maintenance", "implementation", "testing", "purchase", "evaluation"], "requirements": {"degrees": ["degree", "fresh graduate"], "majors": ["engineering"], "languages": ["english", "chinese"], "language_level": ["good command"], "hard_skills": ["workshops", "maintenance"], "soft_skills": ["flexible", "independent", "learning", "self-initiative", "hardworking"], "languages_combined": [{"language": "english", "language_level": ["good command"]}, {"language": "chinese", "language_level": ["good command"]}]}, "experience_required": {"duration": [], "field": []}}, {"job_id": "100003009043662", "location_code": "hk", "company": "Royal Elite Service Company Limited", "job_title": "\u6280\u5de5 (Fitter)", "description": "\u5165\u8077\u8981\u6c42\ufe55\n\n\u521d\u4e2d\u7a0b\u5ea6\u6216\u5177\u8cc7\u6b77\u67b6\u69cb\u540c\u7b49\u8cc7\u6b77\n\u51771\u5e74\u6216\u4ee5\u4e0a\u6c34/\u96fb/\u51b7\u6c23/\u6cb9\u6f06\u7d93\u9a57\n\u9808\u6301\u6709\u5e73\u5b89\u54ad\n\u6708\u85aa\u6700\u9ad8\u53ef\u9054$18,000\n\n\u00a0\u5de5\u4f5c\u5730\u9ede\ufe55\u99ac\u978d\u5c71\u5340\u4f4f\u5b85\u00a0\n\n\u4ee5\u4e0a\u8077\u4f4d\u53ef\u4eab\u6709\u512a\u539a\u798f\u5229\uff0c\u5305\u62ec\u6709\u85aa\u5e74\u50479\u5929\u3001\u52e4\u5de5\u734e\u3001\u5404\u7a2e\u7279\u5225\u5047\u671f\u3001\u91ab\u7642\u798f\u5229\u3001\u5b8c\u5584\u57f9\u8a13\u3001\u6649\u5347\u6a5f\u6703\u53ca\u50f1\u54e1\u652f\u63f4\u670d\u52d9\u3002\u500b\u5225\u5c4b\u82d1\u66f4\u8a2d\u6709\u65b0\u5165\u8077\u54e1\u5de5\u734e\u91d1\u548c\u54e1\u5de5\u63a8\u85a6\u734e\u91d1\u7b49\u3002\n\n\u6709\u610f\u8005\uff0c\u8acb\u81f4\u96fb2656 6133\u8207\u90b1\u5c0f\u59d0\u7d04\u898b\u3002\n\n\u9664\u4e0a\u8ff0\u8077\u4f4d\u5916\uff0c\u5c1a\u6709\u5176\u4ed6\u7a7a\u7f3a\u3002\u8acb\u900f\u904e\u4ee5\u4e0b\u65b9\u6cd5\u5c07\u5c65\u6b77\u4ea4\u5230\u5e1d\u8b7d\u4eba\u529b\u8cc7\u6e90\u53ca\u884c\u653f\u90e8\u3002\n\n\u90f5\u5bc4\uff1a\u89c0\u5858\u5de7\u660e\u885795\u865f\u4e16\u9054\u4e2d\u5fc316\u6a13\n\n\u5e1d\u8b7d\u670d\u52d9\u6709\u9650\u516c\u53f8\u4e43\u5e73\u7b49\u6a5f\u6703\u50f1\u4e3b\uff0c\u800c\u6240\u6709\u6536\u96c6\u8cc7\u6599\u53ea\u7528\u4f5c\u96c6\u5718\u5167\u90e8\u62db\u8058\u4e4b\u7528\u9014\u3002", "employment_types": ["Full Time", "Permanent"], "selling_points": ["\u9808\u6301\u6709\u5e73\u5b89\u54ad", "\u51771\u5e74\u6216\u4ee5\u4e0a\u6c34/\u96fb/\u51b7\u6c23/\u6cb9\u6f06\u7d93\u9a57", "\u6708\u85aa\u6700\u9ad8\u53ef\u9054$18,000"], "locations": ["Not Specified"], "categories": ["Engineering", "Others", "Property / Real Estate", "Property Management", "Others"], "post_time": "2022-01-16T21:50:13Z", "salary": {"currency": null, "max": null, "min": null, "period": "monthly", "term": null}, "salary_visible": false, "title_keywords": ["\u6280\u5de5"], "responsibilities": [], "requirements": {"degrees": [], "majors": [], "languages": [], "language_level": [], "hard_skills": [], "soft_skills": [], "languages_combined": []}, "experience_required": {"duration": [], "field": []}}, {"job_id": "100003009053684", "location_code": "hk", "company": "Gala Gold Hong Kong Limited", "job_title": "\u6c7d\u8eca\u96fb\u5b50\u7cfb\u7d71\u521d\u7d1a\u6280\u8853\u54e1", "description": "\n\u8077\u8cac :\u70ba\u672c\u6e2f\u5404\u5c08\u71df\u5df4\u58eb\u8eca\u968a\u63d0\u4f9b\u884c\u8eca\u8a18\u9304, \u5b89\u5168\u8f14\u52a9\u7cfb\u7d71 , \u5354\u52a9\u5de5\u7a0b\u5718\u968a\u65b0\u7522\u54c1\u8abf\u8a66, \u5982\u884c\u8eca\u8a18\u9304, CCTV, ADAS \u7cfb\u7d71, \u5b89\u5168\u8f14\u52a9\u7cfb\u7d71\u53ca\u6280\u8853\u652f\u63f4\u5de5\u7a0b\u90e8\u9032\u884c\u5b89\u88dd\u53ca\u4fdd\u990a, \u9700\u5916\u52e4\u5de5\u4f5c (\u5c0dCAN BUS, \u6709\u7db2\u8def\u7cfb\u7d71\u8a2d\u5b9a\u7d93\u9a57\u512a\u5148)\n\n\u8cc7\u6b77 :\u5c08\u4e0a\u6559\u80b2\uff1a\u6587\u6191/\u8b49\u66f8; 5\u5e74\u7d93\u9a57; \u826f\u597d\u7cb5\u8a9e\u512a\u5148; \u4e00\u822c\u666e\u901a\u8a71; \u4e00\u822c\u82f1\u8a9e\u512a\u5148; \u61c2\u8b80\u5beb\u4e2d\u6587; \u7565\u61c2\u8b80\u5beb\u82f1\u6587; \u61c2MS PowerPoint; \u6301\u6709\u8f15\u578b\u8ca8\u8eca\u99d5\u99db\u57f7\u7167; \u5177\u6709\u57fa\u672c\u96fb\u8166\u64cd\u4f5c\u77e5\u8b58; \u5b88\u6642, \u5de5\u4f5c\u7a4d\u6975\uff0c\u5177\u5718\u968a\u7cbe\u795e, \u80fd\u7368\u7acb\u8655\u4e8b\n\n\u5f85\u9047 :\u6bcf\u6708$12,000-$15,000,\u6709\u8d85\u6642\u5de5\u4f5c\u6d25\u8cbc,\u5e74\u504714\u5929,\u751f\u65e5\u5047,\u91ab\u7642\u798f\u5229,\u7537\u58eb\u4f8d\u7522\u50477\u5929,\u6649\u5347\u6a5f\u6703, \u5e74\u7d42\u734e\u91d1\u53ca\u5728\u8077\u57f9\u8a13, \u661f\u671f\u4e00\u81f3\u516d: \u4e0a\u53489\u6642\u81f3\u4e0b\u53486\u6642, \u6bcf\u9031\u5de5\u4f5c5\u5929\u81f36\u5929, \u661f\u671f\u516d\u9577\u77ed\u9031, \u6bcf\u5929\u5de5\u4f5c 9 \u5c0f\u6642, \u9593\u4e2d\u9700\u8981\u8d85\u6642\u5de5\u4f5c\n\n\u7533\u8acb\u9808\u77e5 :\u6c42\u8077\u8005\u53ef\u50b3\u771f(35435891)\u6216\u96fb\u90f5(Apply Now)\u5c65\u6b77\u8868\u7d66\u6ea2\u661f\u5cef\u9999\u6e2f\u6709\u9650\u516c\u53f8\u3002\u5982\u8981\u7d22\u53d6\u6536\u96c6\u500b\u4eba\u8cc7\u6599\u8072\u660e, \u8acb\u8207\u9673\u5148\u751f(Tel.39973912)\u806f\u7d61\u3002\n\n", "employment_types": ["Full Time"], "selling_points": [], "locations": ["Yuen Long"], "categories": ["Engineering", "Others", "Others", "Technician"], "post_time": "2022-01-17T07:21:06Z", "salary": {"currency": null, "max": null, "min": null, "period": "monthly", "term": null}, "salary_visible": false, "title_keywords": [], "responsibilities": [], "requirements": {"degrees": [], "majors": [], "languages": [], "language_level": [], "hard_skills": ["cctv", "powerpoint"], "soft_skills": [], "languages_combined": []}, "experience_required": {"duration": [], "field": []}}, {"job_id": "100003009053364", "location_code": "hk", "company": "DMC Gas Equipment Limited", "job_title": "Assistant Engineer / Technician", "description": "\nA gas equipment-trading firm in Kwai Fong close to MTR Station - Hong Kong based company with over 40-years solid experience in gas equipment industry.\nTo cope with our expansion, we are now seeking for a high caliber candidate for the position:\nJob Duties\n\u2022 Support the Company\u2019s service activities\n\u2022 Experience and ability to analyze service problems\n\u2022 Cooperate with and support customers\n\u2022 Provide technical support of equipment on customers\u2019 site\n\u2022 Carry out system installation and routine maintenance\n\u2022 Keep accurate up-to-date records and regularly maintenance, technical and business documentations\nRequirements\n\u2022 Diploma or above in Mechanical Engineering or relevant disciplines\n\u2022 Fresh Graduate will also be considered\n\u2022 Adapt to learn new technology\n\u2022 Good command of spoken & written English/Chinese, and fluency in Mandarin is preferable\n\u2022 Strong interpersonal, problem solving and analytical skills\n\u2022 Well organized, career minded and with good presentation skills\n\u2022 Required to travel occasionally\n\u2022 Immediate available is preferred\nPlease send your full resume with employment history, availability, current and expected salary by [via\u00a0 Apply Now ].\nPersonal data collected will be used for recruitment purpose only.\n\n", "employment_types": ["Full Time"], "selling_points": [], "locations": ["Kwai Fong"], "categories": ["Engineering", "Others", "Others", "Technician"], "post_time": "2022-01-17T06:51:47Z", "salary": {"currency": null, "max": null, "min": null, "period": "monthly", "term": null}, "salary_visible": false, "title_keywords": ["assistant engineer", "technician"], "responsibilities": ["technical support", "installation", "cooperate with", "maintenance"], "requirements": {"degrees": ["fresh graduate", "diploma or above"], "majors": ["mechanical engineering"], "languages": ["english", "chinese", "mandarin"], "language_level": ["fluency", "good command"], "hard_skills": ["problem solving", "analytical skills"], "soft_skills": ["problem solving and analytical skills", "presentation skills", "well organized", "interpersonal"], "languages_combined": [{"language": "english", "language_level": ["fluency", "good command"]}, {"language": "chinese", "language_level": ["fluency", "good command"]}, {"language": "mandarin", "language_level": ["good command"]}]}, "experience_required": {"duration": [], "field": []}}, {"job_id": "100003009053985", "location_code": "hk", "company": "Senton Engineering Limited", "job_title": "Clerk / Clerical Assistant / Admin staff (13k-15k)", "description": "Responsibilities:\n\nPerform general clerical duties in the Office\nHandle all clerical/filing works, word processing, typing and telephone operation.\nCommunicate with client and contractor\nOther relevant duties as assigned by senior\nHandle ad hoc duties and assignments as required\n\nRequirements:\n\nHKDSE or HKCEE\nGood command of both written and spoken English and Chinese\nGood PC knowledge in MS office applicants (MS Word and Excel) and in both Chinese and English word processing\nClerical Assistant experience is preferred", "employment_types": ["Full Time"], "selling_points": ["Entry Level", "School Certificate", "Full Time"], "locations": ["Chai Wan"], "categories": ["Admin & HR", "Clerical / Admin Staff", "Engineering", "Others"], "post_time": "2022-01-17T07:55:24Z", "salary": {"currency": null, "max": null, "min": null, "period": "monthly", "term": null}, "salary_visible": false, "title_keywords": ["clerical assistant", "admin", "clerk", "staff"], "responsibilities": ["ad hoc duties", "communicate with client"], "requirements": {"degrees": ["hkdse"], "majors": [], "languages": ["english", "chinese"], "language_level": ["good command", "good"], "hard_skills": ["excel", "chinese and english word processing", "pc knowledge", "ms office", "ms word"], "soft_skills": [], "languages_combined": [{"language": "english", "language_level": ["good command", "good", "good"]}, {"language": "chinese", "language_level": ["good command", "good", "good"]}]}, "experience_required": {"duration": [], "field": ["clerical"]}}, {"job_id": "100003009052386", "location_code": "hk", "company": "J&D Holdings Limited", "job_title": "\u7dad\u4fee\u6280\u8853\u5b78\u5f92", "description": "\u8077\u8cac:\n\n\u8ca0\u8cac\u5ee0\u623f\u8a2d\u65bd\u7dad\u4fee\u53ca\u4fdd\u990a\u5de5\u4f5c\uff0c\u5305\u62ec\u51b7\u6c23\u3001\u6c34\u96fb\u53ca\u7dca\u6025\u652f\u63f4\n\n\u8ca0\u8cac\u5206\u5e97\u5b89\u88dd\u53ca\u7dad\u4fee\u4fdd\u990a\u5eda\u623f\u96fb\u5668\u5de5\u4f5c\n\n\u9700\u586b\u5831\u65e5\u5e38\u7dad\u4fee\u5831\u544a\u7d00\u9304\u3001\u5e97\u8216\u51fa\u52e4\u7d00\u9304\u53ca\u5c0d\u627f\u5224\u5546\u8aaa\u660e\u3001\u5354\u8abf\u53ca\u8ddf\u9032\u5de5\u4f5c\n\n\u9700\u8ca0\u8cac\u65e5\u5e38\u7684\u7dad\u4fee\u7269\u6599\u5099\u91cf\u53ca\u6709\u95dc\u5009\u5b58\u6574\u7406\u5b89\u6392\n\n\u9700\u8f2a\u4f11/\u5916\u52e4\u5de5\u4f5c\n\n\u6708\u85aa:$13,000\u8d77\n\n\u4e0a\u73ed\u6642\u9593: 09:00-06:00 / 14:00-23:00\n\n\u89c0\u5858\u5340\u5de5\u4f5c\n\nWhatsapp\ufe305918 1693\n\n\u7533\u8acb\u8077\u4f4d\uff1ahttps://bit.ly/3zF6xoQ\n\n\u7533\u8acb\u4eba\u6240\u63d0\u4f9b\u4e4b\u5168\u90e8\u8cc7\u6599\u5c07\u7d55\u5c0d\u4fdd\u5bc6\u53ca\u53ea\u4f5c\u62db\u8058\u7528\u9014\u3002\n\nWe offer competitive remuneration and benefit packages to the right candidate. Interested parties please click\u00a0Apply Now\u00a0button and also submit your application letter, resume with expected salary and availability.\n\nWe are an equal opportunity employer and welcome applications from all qualified candidates. The information provided will be treated in strict confidence and be used only for consideration of your application for relevant / similar posts within the J&D Holdings Limited. Applicants not hearing from us within four weeks from the date of advertisement may consider their applications unsuccessful.", "employment_types": ["Full Time"], "selling_points": [], "locations": ["Not Specified"], "categories": ["Engineering", "Others", "Others", "Technician"], "post_time": "2022-01-17T02:55:04Z", "salary": {"currency": null, "max": null, "min": null, "period": "monthly", "term": null}, "salary_visible": false, "title_keywords": [], "responsibilities": [], "requirements": {"degrees": [], "majors": [], "languages": [], "language_level": [], "hard_skills": [], "soft_skills": [], "languages_combined": []}, "experience_required": {"duration": [], "field": []}}, {"job_id": "100003009053242", "location_code": "hk", "company": "Haystar Consultant Limited", "job_title": "TRAINEE 1) Sales & Marketing Executive 2) Admin. Assistant (\u5728\u8077\u57f9\u8a13+\u96d9\u85aa\u52a0\u734e\u91d1 Building Services Product)", "description": "On-the-job training will be provided to the right candidates\n\n1) Sales & Marketing Executive\u00a0\n\nDuties:\n\nSupport the formulation of strategic marketing plans to achieve company goals\nConduct market research and data analysis\nImplement sales activities and marketing support to all related customers\nHandle clients' inquiries and\u00a0correspondence\nMaintain close relationships with valued clients\nAssist in ad hoc projects and assignments\nRequirements:\n1-2 years working experience in the sales/marketing industry\u00a0\nLess experience with part-time/summer job\nFresh graduate with high calibre is also welcome\nExperience and knowledge in the trading will be an advantage\nGood command of Cantonese, English, and Mandarin\u00a0\nHolder of\u00a0 IVE certificates or Poly graduates is also welcome\nOutdoor work is required\u00a0\nImmediate available is highly preferable\n\n2) Administrative Assistant\u00a0\n\nDuties:\u00a0\n\n\u00a0Support daily sales operation and documentation\nProvide general administrative and clerical work\nHandle shipment booking and logistic arrangement\nAssist in ad hoc assignments\u00a0\n\nRequirements:\u00a0\n\nDiploma or above\n1-2 years working experience\n\nLess experience with high caliber is also welcome\nProficiency in MS Office application and Chinese Word Processing\nImmediate availability is highly preferable", "employment_types": ["Full Time", "Permanent"], "selling_points": ["A stable financial background company", "a work-life balance job", "Good MS Office & Chinese Word Processing"], "locations": ["Yau Tsim Mong Area"], "categories": ["Engineering", "Others", "Sales, CS & Business Devpt", "Account Servicing", "Others", "Student / Fresh Graduate / No Experience"], "post_time": "2022-01-17T06:31:46Z", "salary": {"currency": null, "max": null, "min": null, "period": "monthly", "term": null}, "salary_visible": false, "title_keywords": ["admin", "assistant", "trainee", "sales & marketing executive"], "responsibilities": ["sales activities", "marketing plans", "conduct market research", "data analysis", "maintain", "ad hoc projects"], "requirements": {"degrees": ["diploma or above", "fresh graduate"], "majors": [], "languages": ["cantonese", "english", "chinese", "mandarin"], "language_level": ["proficiency", "good command"], "hard_skills": ["documentation", "chinese word processing", "ms office"], "soft_skills": [], "languages_combined": [{"language": "cantonese", "language_level": ["good command"]}, {"language": "english", "language_level": ["good command"]}, {"language": "chinese", "language_level": ["proficiency"]}, {"language": "mandarin", "language_level": ["good command"]}]}, "experience_required": {"duration": ["1-2 years"], "field": ["marketing", "trading"]}}, {"job_id": "100003009053563", "location_code": "hk", "company": "Juraron Industries Limited", "job_title": "\u751f\u7522\u6280\u8853\u54e1/\u6280\u5de5", "description": "\n\u8077\u8cac :\u8ca0\u8cac\u6ce8\u5851\u6a5f, \u8f14\u52a9\u8a2d\u5099\u7684\u64cd\u4f5c\u548c\u65e5\u5e38\u4fdd\u990a\n\n\u8cc7\u6b77 :\u4e2d\u4e09\u7a0b\u5ea6; \u826f\u597d\u7cb5\u8a9e; \u61c2\u8b80\u5beb\u4e2d\u6587; \u6709\u6a21\u5177\u76f8\u95dc\u5de5\u4f5c\u7d93\u9a57\u512a\u5148\n\n\u5f85\u9047 :\u6bcf\u6708$12,000 - $13,000, \u6709\u8d85\u6642\u5de5\u4f5c\u6d25\u8cbc, \u96d9\u7ce7, \u734e\u8cde, \u82b1\u7d05 \u53ca\u91ab\u7642\u798f\u5229, \u4e0a\u53489\u6642\u81f3\u4e0b\u53486\u6642, \u6bcf\u9031\u5de5\u4f5c5\u5929\u81f36\u5929,\u8f2a\u4f11\n\n\u7533\u8acb\u9808\u77e5 :\u6c42\u8077\u8005\u53ef\u50b3\u771f(24657982)\u6216\u96fb\u90f5(Apply Now)\u5c65\u6b77\u8868\u7d66\u805a\u6a02\u9686\u5de5\u696d\u6709\u9650\u516c\u53f8\u3002\u5982\u8981\u7d22\u53d6\u6536\u96c6\u500b\u4eba\u8cc7\u6599\u8072\u660e, \u8acb\u8207\u674e\u5c0f\u59d0(Email)\u806f\u7d61\u3002\n\n", "employment_types": ["Full Time"], "selling_points": [], "locations": ["Tuen Mun Area"], "categories": ["Engineering", "Others", "Others", "Technician"], "post_time": "2022-01-17T07:10:02Z", "salary": {"currency": null, "max": null, "min": null, "period": "monthly", "term": null}, "salary_visible": false, "title_keywords": ["\u751f\u7522\u6280\u8853\u54e1", "\u6280\u5de5"], "responsibilities": [], "requirements": {"degrees": [], "majors": [], "languages": [], "language_level": [], "hard_skills": [], "soft_skills": [], "languages_combined": []}, "experience_required": {"duration": [], "field": []}}, {"job_id": "100003009053673", "location_code": "hk", "company": "Regent Long Limited", "job_title": "\u71d2\u5473\u5b78\u5f92", "description": "\u8077\u8cac:\u00a0\n\n\u9032\u884c\u7269\u696d\u5167\u5404\u9805\u7dad\u4fee\u4fdd\u990a\u5de5\u7a0b\uff0c\u7dad\u6301\u6a5f\u96fb\u7cfb\u7d71\u53ca\u6240\u6709\u7269\u696d\u8a2d\u65bd\u904b\u4f5c\u6b63\u5e38\n\u76e3\u5bdf\u670d\u52d9\u627f\u8fa6\u5546\u4e4b\u670d\u52d9\u8cea\u7d20\n\n\u8981\u6c42:\u00a0\n\n\u9808\u70ba\u8a3b\u518a\u96fb\u696d\u5de5\u7a0b\u4eba\u54e1\uff08\u7d1a\u5225\u7532\uff09\u3001\u6301\u6709\u6548\u5e73\u5b89\u54ad\u53ca\u5efa\u9020\u696d\u5de5\u4eba\u8a3b\u518a\u8b49\n\u4e00\u5e74\u6216\u4ee5\u4e0a\u7dad\u4fee\u5de5\u7a0b\u5de5\u4f5c\u7d93\u9a57\n\u80fd\u7368\u7acb\u5de5\u4f5c\u53ca\u8655\u7406\u7dca\u6025\u7dad\u4fee\u4e8b\u5b9c\n\u6bcf\u5929\u5de5\u4f5c9\u5c0f\u6642, \u6bcf\u661f\u671f\u5de5\u4f5c5.5\u5929\n\u4e0a\u73ed\u6642\u9593:\u65e9\u66f4 (0800-1700)\u3001\u4e2d\u66f4 (1400-2300)\n\nResponsibilities:\n\nTo carry out daily maintenance and improvement works\nTo operate and maintain building service facilities in good condition\u00a0\nTo supervise the performance of maintenance contractors to ensure the smooth execution of maintenance or improvement works to the required standard\n\nRequirements:\n\nHolder of Registered Electrical Worker Grade (A) or above, Construction Industry Safety Card and Construction Workers Registration Card\nAt least 1-year relevant building repair and maintenance experience\nIndependent, able to handle emergency maintenance work\n9 working hours per day, 5.5 days a week\nWorking Hours: Day Shift (0800-1700) / Middle Shift (1400-2300)\n\nWe offer attractive remuneration package and good career prospect for the right applicant.\n\nPlease apply by clicking\u00a0\"Apply Now\", or submit full resume and expected salary to the\u00a0HR Department, Room 1402, 14/F, Dorset House, Taikoo Place, 979 King's Road, Quarry Bay, HK\u00a0or\u00a0fax to 2968-4177.\u00a0Or WhatsApp / WeChat at 9127 0207 for more information.\u00a0\n\n(Please quote the reference number on the subject of email)", "employment_types": ["Full Time"], "selling_points": [], "locations": ["Sham Shui Po"], "categories": ["Engineering", "Others", "Others", "Student / Fresh Graduate / No Experience", "Technician"], "post_time": "2022-01-17T07:19:59Z", "salary": {"currency": null, "max": null, "min": null, "period": "monthly", "term": null}, "salary_visible": false, "title_keywords": [], "responsibilities": ["maintain", "maintenance"], "requirements": {"degrees": [], "majors": [], "languages": [], "language_level": [], "hard_skills": ["construction workers registration card", "maintenance"], "soft_skills": ["independent"], "languages_combined": []}, "experience_required": {"duration": ["at least 1-year"], "field": ["maintenance"]}}, {"job_id": "100003009053376", "location_code": "hk", "company": "Web Alarm System Ltd", "job_title": "\u6280\u8853\u54e1", "description": "\n\u8077\u8cac : \u5b89\u88dd\u3001\u4fdd\u990a\u3001\u7dad\u4fee\u4fdd\u5b89\u7cfb\u7d71 (\u9632\u76dc\u8b66\u9418\u3001\u9589\u8def\u96fb\u8996\u3001\u62cd\u54ad\u9580\u7981\u3001\u5c0d\u8b1b\u6a5f\u7b49)\n\u8cc7\u6b77 :\u5c0f\u4e09\u7a0b\u5ea6; 1\u5e74\u7d93\u9a57; \u826f\u597d\u7cb5\u8a9e; \u4e00\u822c\u82f1\u8a9e; \u7565\u61c2\u8b80\u5beb\u4e2d\u6587; \u7565\u61c2\u8b80\u5beb\u82f1\u6587; \u5df2\u6301\u6709\u4fdd\u5b89\u4eba\u54e1\u8a31\u53ef\u8a3c(\u4e01\u724c)\u512a\u7b45\n\u5f85\u9047 :\u6bcf\u6708$16,000, \u6709\u9280\u884c\u5047\u671f, \u914c\u60c5\u6027\u82b1\u7d05, \u8d85\u6642\u5de5\u4f5c\u6d25\u8cbc\u53ca\u5916\u52e4\u4ea4\u901a\u8cbb(\u5be6\u5831\u5be6\u92b7), \u661f\u671f\u4e00\u81f3\u516d: \u4e0a\u53489\u6642\u81f3\u4e0b\u53486\u6642, \u6bcf\u9031\u5de5\u4f5c6\u5929, \u6bcf\u5929\u5de5\u4f5c 9 \u5c0f\u6642\n\u7533\u8acb\u9808\u77e5 :\u6c42\u8077\u8005\u53ef\u81f4\u96fb23763596\u8207\u5a01\u5bf6\u8b66\u9418\u7cfb\u7d71\u6709\u9650\u516c\u53f8\u9676\u5c0f\u59d0\u806f\u7d61\u3002\n\n", "employment_types": ["Full Time"], "selling_points": [], "locations": ["Not Specified"], "categories": ["Engineering", "Others", "Others", "Technician"], "post_time": "2022-01-17T06:53:15Z", "salary": {"currency": null, "max": null, "min": null, "period": "monthly", "term": null}, "salary_visible": false, "title_keywords": ["\u6280\u8853\u54e1"], "responsibilities": [], "requirements": {"degrees": [], "majors": [], "languages": [], "language_level": [], "hard_skills": [], "soft_skills": [], "languages_combined": []}, "experience_required": {"duration": [], "field": []}}, {"job_id": "100003009054197", "location_code": "hk", "company": "Triangle Motors Limited", "job_title": "Technical Officer", "description": "Responsibilities:\n\nProduct development and improvement\nOn-site technical supports to body builders customer,\u00a0Transport Department Vehicle Examination Centres\nOn-road emergency service upon vehicle failure during transportation and storage\nRegular check on body builders' workshop tp ensure product's quality\nAssist to follow up on technical issue of product\n\nRequirements:\n\n\nForm 5 or above\nPreferably 1-2 years\u2019\u00a0relevant experience in motor industry\nValid driving license 1, 2 is required\nProblem Solving skill, mechanical knowledge\nIndependent, well-organized and self-motivated achievers\n\nAttractive salary package and fringe benefits will be offered to the successful candidate. Interested parties please send your resume stating reference number and expected salary to Human Resources Manager by email to click \"Apply Now\", whatsapp to 9318 2638 or fax to 2394 5518.\n\nWe are an equal opportunities employer. Personal data collected will be treated in strict confidence and used for recruitment purposes only. All applications may be considered for other suitable positions with DCH Group / CITIC Pacific Group and the personal data collected will be deleted from our files after 6 months from the date of application.", "employment_types": ["Full Time", "Permanent"], "selling_points": [], "locations": ["Kowloon Bay"], "categories": ["Engineering", "Manufacturing & Production", "Mechanical", "Others"], "post_time": "2022-01-17T08:46:37Z", "salary": {"currency": null, "max": null, "min": null, "period": "monthly", "term": null}, "salary_visible": false, "title_keywords": ["technical officer"], "responsibilities": ["workshop", "technical supports", "quality"], "requirements": {"degrees": ["form 5 or above"], "majors": [], "languages": [], "language_level": [], "hard_skills": ["problem solving"], "soft_skills": ["problem solving skill", "independent", "well-organized", "self-motivated"], "languages_combined": []}, "experience_required": {"duration": ["1-2 years"], "field": ["relevant experience"]}}, {"job_id": "100003009053881", "location_code": "hk", "company": "Boss Technology (HK) Limited", "job_title": "\u96fb\u5b50\u7dad\u4fee\u54e1", "description": "\n\u8077\u8cac :\u7dad\u4fee\u9589\u8def\u96fb\u8996(CCTV), \u9580\u7981 , \u8b66\u9418\n\n\u8cc7\u6b77 :\u6c92\u6709\u5b78\u6b77\u8981\u6c42; 1\u5e74\u7d93\u9a57; \u4e00\u822c\u7cb5\u8a9e; \u7565\u61c2\u8b80\u5beb\u4e2d\u6587\n\n\u5f85\u9047 :\u6bcf\u65e5$650.00 - $1,000.00, \u6709\u4ea4\u901a\u6d25\u8cbc, \u661f\u671f\u4e00\u81f3\u516d: \u4e0a\u53489\u6642\u81f3\u4e0b\u53486\u6642, \u6bcf\u9031\u5de5\u4f5c5\u5929\u81f36\u5929\n\n\u7533\u8acb\u9808\u77e5 :\u6c42\u8077\u8005\u53ef\u96fb\u90f5(Apply Now)\u5c65\u6b77\u8868\u7d66\u5bf6\u6642\u79d1\u6280(\u9999\u6e2f)\u6709\u9650\u516c\u53f8\u3002\u5982\u8981\u7d22\u53d6\u6536\u96c6\u500b\u4eba\u8cc7\u6599\u8072\u660e, \u8acb\u8207\u9673\u5c0f\u59d0(Tel:67630898)\u806f\u7d61\u3002\n\n", "employment_types": ["Full Time"], "selling_points": [], "locations": ["Not Specified"], "categories": ["Engineering", "Others", "Others", "Technician"], "post_time": "2022-01-17T07:41:06Z", "salary": {"currency": null, "max": null, "min": null, "period": "hourly", "term": null}, "salary_visible": false, "title_keywords": [], "responsibilities": [], "requirements": {"degrees": [], "majors": [], "languages": [], "language_level": [], "hard_skills": [], "soft_skills": [], "languages_combined": []}, "experience_required": {"duration": [], "field": []}}, {"job_id": "100003009040178", "location_code": "hk", "company": "Vicki Engineering Company Limited", "job_title": "General Clerk & Engineering Clerk", "description": "\u5de5\u7a0b\u6587\u54e1\n\n\u00a0\u00a0\u61c2AutoCAD (\u512a\u5148\u8003\u616e)\n\n\u00a0\u5354\u52a9\u540c\u4e8b\u8655\u7406\u591a\u9805\u5de5\u4f5c\n\u00a0\u9700\u63a5\u807d\u5ba2\u6236\u96fb\u8a71\n\u00a0\u5982\u6709\u5de5\u7a0b/\u5efa\u7bc9\u516c\u53f8\u5de5\u4f5c\u7d93\u9a57\u512a\u5148\n\u00a0\u5b88\u6642,\u00a0\u5de5\u4f5c\u614b\u5ea6\u826f\u597d\u53ca\u505a\u4e8b\u8b39\u614e\n\u00a0\u7d93\u9a57:0-1\u00a0\u5e74\u00a0(\u6b61\u8fce\u00a0\u61c9\u5c46\u7562\u696d\u751f)\n\u00a0\u4e2d\u4e94\u7a0b\u5ea6\u6216\u4ee5\u4e0a\n\u00a0\u9700\u7368\u7acb,\u52e4\u596e\u53ca\u6709\u79ae\u8c8c\n\u00a0\u81ea\u6211\u8981\u6c42\u9032\u6b65,\u00a0\u9858\u610f\u767c\u6398,\u00a0\u5617\u8a66\u548c\u6311\u6230\u65b0\u4e8b\u7269,\u00a0\u8207\u5718\u968a\u5171\u540c\u9032\u6b65\n\u00a0\u5177\u6709\u57fa\u672c\u96fb\u8166\u64cd\u4f5c\u77e5\u8b58\u00a0;\u61c2\u4e2d\u82f1\u6587\u96fb\u8166\u64cd\u4f5c\n\u00a0\u61c2Microsoft Office, Excel\n\u00a0\u8ca0\u8cac\u6587\u4ef6\u63d0\u4ea4,\u4e0a\u55ae\n\n\u5de5\u4f5c\u985e\u578b:\u00a0\u5168\u8077,\u00a0\u9577\u671f", "employment_types": ["Full Time"], "selling_points": [], "locations": ["Shatin Area"], "categories": ["Admin & HR", "Clerical / Admin Staff", "Engineering", "Others"], "post_time": "2022-01-16T21:50:11Z", "salary": {"currency": null, "max": null, "min": null, "period": "monthly", "term": null}, "salary_visible": false, "title_keywords": ["general clerk", "clerk"], "responsibilities": [], "requirements": {"degrees": [], "majors": [], "languages": [], "language_level": [], "hard_skills": ["excel"], "soft_skills": [], "languages_combined": []}, "experience_required": {"duration": [], "field": []}}, {"job_id": "100003009052291", "location_code": "hk", "company": "Hong Kong Labware Company Limited", "job_title": "Field Service Engineer", "description": "Responsibilities:\nPerform installation of analytical instruments for chemical laboratories\nProvide on-site preventive maintenance, troubleshooting and repair services of instruments\nLog service activities\nWork with sales team to drive customer satisfaction\nRequirements:\nHigher Diploma or Bachelor Degree holder in electronic engineering, science or related disciplines, fresh graduates will also be considered\n0-3 year(s) experience\nAbility to troubleshoot\nGood computer knowledge\nSelf-motivated and able to work independently\nGood communication and interpersonal skills", "employment_types": ["Full Time", "Permanent"], "selling_points": ["Perform installation of analytical instruments", "Provide on-site preventive maintenance", "Fresh graduates will also be considered"], "locations": ["Kwai Hing"], "categories": ["Engineering", "Electrical / Electronics", "Others"], "post_time": "2022-01-17T02:39:28Z", "salary": {"currency": null, "max": null, "min": null, "period": "monthly", "term": null}, "salary_visible": false, "title_keywords": ["service engineer"], "responsibilities": ["installation", "maintenance", "troubleshooting", "repair", "sales team"], "requirements": {"degrees": ["diploma", "bachelor degree holder"], "majors": ["related disciplines", "science", "engineering"], "languages": [], "language_level": [], "hard_skills": [], "soft_skills": ["self-motivated", "communication and interpersonal skills", "troubleshoot", "work independently"], "languages_combined": []}, "experience_required": {"duration": [], "field": []}}, {"job_id": "100003009053811", "location_code": "hk", "company": "Haier International Co., Limited", "job_title": "\u51b7\u6c23\u6280\u5de5**", "description": "\n\u8077\u8cac :\u8ca0\u8cac\u51b7\u6c23\u6a5f\uff08\u55ae\u982d\u6a5f\u53ca\u591a\u806f\u6a5f\uff09\u7dad\u4fee\u3001\u4fdd\u990a\u53ca\u8abf\u8a66\u5de5\u4f5c\n\n\u8cc7\u6b77 :\u4e2d\u4e09\u7a0b\u5ea6; 2\u5e74\u7d93\u9a57; \u826f\u597d\u7cb5\u8a9e\u512a\u5148; \u4e00\u822c\u666e\u901a\u8a71\u512a\u5148; \u4e00\u822c\u82f1\u8a9e\u512a\u5148; \u61c2\u8b80\u5beb\u4e2d\u6587; \u7565\u61c2\u8b80\u5beb\u82f1\u6587; \u6301\u6709\u5e73\u5b89\u54ad; \u6709\u96fb\u5de5A\u724c\u53ca2\u5e74\u4ee5\u4e0a\u51b7\u6c23\u7dad\u4fee\u5de5\u4f5c\u7d93\u9a57\u512a\u5148\n\n\u5f85\u9047 :\u6bcf\u6708$16,000-$18,000,\u6709\u96d9\u7ce7,\u751f\u65e5\u5047,\u7259\u79d1\u798f\u5229,\u5728\u8077\u57f9\u8a13,\u91ab\u7642\u798f\u5229,\u624b\u63d0\u96fb\u8a71\u6d25\u8cbc,\u4ea4\u901a\u6d25\u8cbc,\u751f\u65e5\u6d25\u8cbc\u53ca\u65e5\u6d25\u8cbc, \u661f\u671f\u4e00\u81f3\u516d: \u4e0a\u53489\u6642\u81f3\u4e0b\u53486\u6642, \u6bcf\u9031\u5de5\u4f5c6\u5929, \u6bcf\u5929\u5de5\u4f5c 8 \u5c0f\u6642, \u7121\u9700\u8d85\u6642\u5de5\u4f5c\n\n\u7533\u8acb\u9808\u77e5 :\u6c42\u8077\u8005\u53ef\u81f4\u96fb31608935\u8207\u6d77\u723e\u570b\u969b\u6709\u9650\u516c\u53f8\u9ea5\u5c0f\u59d0\u806f\u7d61\u3002\n\n", "employment_types": ["Full Time"], "selling_points": [], "locations": ["Not Specified"], "categories": ["Engineering", "Others", "Others", "Technician"], "post_time": "2022-01-17T07:33:27Z", "salary": {"currency": null, "max": null, "min": null, "period": "monthly", "term": null}, "salary_visible": false, "title_keywords": [], "responsibilities": [], "requirements": {"degrees": [], "majors": [], "languages": [], "language_level": [], "hard_skills": [], "soft_skills": [], "languages_combined": []}, "experience_required": {"duration": [], "field": []}}, {"job_id": "100003009055296", "location_code": "hk", "company": "Country House Property Management Limited", "job_title": "\u6280\u5de5 / \u9ad8\u7d1a\u6280\u5de5", "description": "\u4e3b\u8981\u8077\u8cac:\n\n\u8ca0\u8cac\u5927\u5ec8 / \u5beb\u5b57\u6a13\u53ca\u5546\u5834\u7684\u4fdd\u990a\u53ca\u7dad\u4fee\u5de5\u4f5c\n\u57f7\u884c\u4e0a\u53f8\u6307\u6d3e\u4e4b\u6280\u8853\u5de5\u7a0b\u5de5\u4f5c\n\n\u5165\u8077\u689d\u4ef6:\n\n\u4e2d\u4e09\u7a0b\u5ea6\n\u4e09\u5e74\u6216\u4ee5\u4e0a\u76f8\u95dc\u5de5\u4f5c\u7d93\u9a57\n\u6301\u6709\u96fb\u5de5A\u724c\u3001\u5e73\u5b89\u54ad\u3001\u5efa\u9020\u696d\u5de5\u4eba\u8a3b\u518a\u8b49\u53ca\u6709\u6548\u51b7\u6c23\u6216\u6a5f\u96fb\u8b49\u66f8\n\u80fd\u7368\u7acb\u5de5\u4f5c\u53ca\u9700\u8655\u7406\u7dca\u6025\u7dad\u4fee\u670d\u52d9\n\u9700\u7a7f\u8457\u5236\u670d\n\u6211\u5011\u70ba\u5408\u9069\u7684\u5019\u9078\u4eba\u63d0\u4f9b\u512a\u539a\u7684\u85aa\u916c\u5f85\u9047\u548c\u51fa\u8272\u7684\u8077\u696d\u524d\u666f\u3002\u5982\u6709\u8208\u8da3\uff0c\u8acb\u5c07\u5c65\u6b77\u8868 (\u5de5\u4f5c\u7d00\u9304\u3001\u8cc7\u6b77\u3001\u53ef\u5230\u8077\u65e5\u671f\u3001\u73fe\u6642\u548c\u671f\u671b\u85aa\u91d1\uff0c\u53ca\u806f\u7d61\u96fb\u8a71) \u767c\u9001\u81f3\u50b3\u771f\u96fb\u8a712394 1424\u00a0\u6216\u9ede\u64ca\n[via APPLY NOW]\n\u3002\u6709\u95dc\u516c\u53f8\u7684\u66f4\u591a\u8cc7\u8a0a\uff0c\u8acb\u700f\u89bdwww.kdc.com.hk\u3002\u65bc\u5169\u500b\u6708\u5167\u672a\u53d7\u9080\u53c3\u52a0\u9762\u8a66\u7684\u7533\u8acb\u8005\uff0c\u5c07\u88ab\u8996\u70ba\u843d\u9078\u3002\u6240\u6709\u500b\u4eba\u8cc7\u6599\u5c07\u56b4\u683c\u4fdd\u5bc6\uff0c\u50c5\u7528\u65bc\u62db\u8058\u7528\u9014\u3002\n\n\nSummary\nIndustry:\nReal Estate / Property Management\nJob Category / Function:\nEngineering (Mechanical)\nEngineering (Others)\nJob Position Level:\nGeneral\nEmployment Term:\nFull Time\nMin. Edu. Level Req:\nBelow F.5\nMinimum QF Level attained:\n-\nTotal Working Exp:\n3 or above\nSalary(HKD):\n-\nBenefits:\nDouble Pay\nMedical Insurance\nPerformance Bonus", "employment_types": ["Full Time"], "selling_points": [], "locations": ["Not Specified"], "categories": ["Engineering", "Others", "Others", "Technician"], "post_time": "2022-01-18T02:05:39Z", "salary": {"currency": null, "max": null, "min": null, "period": "monthly", "term": null}, "salary_visible": false, "title_keywords": ["\u6280\u5de5"], "responsibilities": ["management"], "requirements": {"degrees": [], "majors": [], "languages": [], "language_level": [], "hard_skills": [], "soft_skills": [], "languages_combined": []}, "experience_required": {"duration": [], "field": []}}, {"job_id": "100003009051705", "location_code": "hk", "company": "ASM Technology Hong Kong Limited", "job_title": "Software Engineer (C / C++ Preferred) (Fresh Graduate / IANG Holder Is Welcome)", "description": "Job description\nResponsible for semiconductor equipment software development, including\nImplement user interface for machine operations\nRealize the manufacturing process automation through robotic control in micron scale\nIntegrate with machine vision software for alignment and inspection in micron scale\nImplement industrial standard network protocols to communicate with manufacturing executing system\nProvision for Industry 4.0\nJob requirements\nDegree or higher in Computer Science / Engineering / Mathematics / Physics or relevant disciplines\nAround 1 \u2013 2 years\u2019 relevant working experience in software development or relevant field is preferred\nProficient in C/C++ and application programming\nGood knowledge of multi-threading, object-oriented programming, design patterns and UML statechart\nHands-on experience in developing software in MS Windows, Visual Studio or Linux\nFamiliar with Operating System Internals is a plus\nAttractive salary and fringe benefits package will be offered to the right candidates.\nInterested parties please submit your application with cover letter, resume, certificate and transcripts.\nData collected will be used for recruitment purpose only. Suitable candidates may be referred to other vacancies within our company.", "employment_types": ["Full Time", "Permanent"], "selling_points": ["Degree or higher in Computer Science", "1 \u2013 2 years\u2019 experience in software development", "Proficient in C/C++ and application programming"], "locations": ["Tsing Yi"], "categories": ["Engineering", "Others", "Information Technology (IT)", "Software Development"], "post_time": "2022-01-16T21:50:57Z", "salary": {"currency": null, "max": null, "min": null, "period": "monthly", "term": null}, "salary_visible": false, "title_keywords": ["software engineer"], "responsibilities": ["communicate with", "control", "software", "operations", "inspection", "user interface", "executing"], "requirements": {"degrees": ["degree"], "majors": ["mathematics", "engineering", "computer science", "physics"], "languages": [], "language_level": [], "hard_skills": ["linux", "plus", "ms windows", "c++", "c", "programming"], "soft_skills": ["hands-on"], "languages_combined": []}, "experience_required": {"duration": ["2 years"], "field": ["developing", "relevant working experience", "software development"]}}, {"job_id": "100003009053813", "location_code": "hk", "company": "Quko Int'l Development Limited", "job_title": "\u92b7\u552e\u5de5\u7a0b\u5e2b**", "description": "\n\u8077\u8cac :\u4e00\u822c\u92b7\u552e\u5de5\u7a0b\u5e2b\u5de5\u4f5c, \u92b7\u552e\u53ca\u63a8\u5ee3\u5404\u985e\u578b\u5ba4\u5167\u7a7a\u6c23\u8cea\u7d20IAQ\u7522\u54c1\uff0c\u4f8b\u5982\u7a7a\u6c23\u6de8\u5316\u6a5f,\u9ad8\u6548\u7a7a\u6c23\u6de8\u5316\u6bba\u83cc\u6a5f,\u6bba\u83cc\u5668\u548c\u5100\u8868\u7b49\n\n\u8cc7\u6b77 :\u5c08\u4e0a\u6559\u80b2\uff1a\u6587\u6191/\u8b49\u66f8; 2\u5e74\u7d93\u9a57; \u826f\u597d\u7cb5\u8a9e; \u4e00\u822c\u666e\u901a\u8a71; \u826f\u597d\u82f1\u8a9e; \u61c2\u8b80\u5beb\u4e2d\u6587; \u61c2\u8b80\u5beb\u82f1\u6587; Sales experience is preferred, \u5177\u92b7\u552e\u91ab\u7642,\u8b77\u8001,\u6559\u80b2\u7b49\u7522\u54c1\u7d93\u9a57\u512a\u5148\n\n\u5f85\u9047 :\u6bcf\u6708$13,500 - $15,500, \u6709\u9280\u884c\u5047\u671f, \u7259\u79d1\u798f\u5229, \u5728\u8077\u57f9\u8a13, \u91ab\u7642\u4fdd\u96aa \u53ca\u4f63\u91d1, \u661f\u671f\u4e00\u81f3\u4e94: \u4e0a\u53489\u6642\u81f3\u4e0b\u53486\u6642, \u6bcf\u9031\u5de5\u4f5c5\u5929\n\n\u7533\u8acb\u9808\u77e5 :\u6c42\u8077\u8005\u53ef\u96fb\u90f5(Apply Now)\u5c65\u6b77\u8868\u7d66\u7ff9\u9ad8\u570b\u969b\u767c\u5c55\u6709\u9650\u516c\u53f8\u3002\u5982\u8981\u7d22\u53d6\u6536\u96c6\u500b\u4eba\u8cc7\u6599\u8072\u660e, \u8acb\u8207\u7f85\u5c0f\u59d0(Email)\u806f\u7d61\u3002\n\n", "employment_types": ["Full Time"], "selling_points": [], "locations": ["Kwun Tong"], "categories": ["Media & Advertising", "Others", "Engineering", "Others", "Sales, CS & Business Devpt", "Others"], "post_time": "2022-01-17T07:34:10Z", "salary": {"currency": null, "max": null, "min": null, "period": "monthly", "term": null}, "salary_visible": false, "title_keywords": [], "responsibilities": [], "requirements": {"degrees": [], "majors": [], "languages": [], "language_level": [], "hard_skills": [], "soft_skills": [], "languages_combined": []}, "experience_required": {"duration": [], "field": []}}, {"job_id": "100003009046661", "location_code": "hk", "company": "Pyrofoe Engineers Ltd", "job_title": "Asst. Engineer", "description": "1-2 years experience min. in Fire Services Installation\nCan work independently\nRequire full-time on site\nGood at ACAD\nApplicant is required to send CV and expected salary to Pyrofoe Engineers Ltd (\u885b\u5b89\u5de5\u7a0b\u6709\u9650\u516c\u53f8) by email via clicking \"Apply Now\"\u00a0 for interview arrangement.", "employment_types": ["Full Time", "Permanent"], "selling_points": [], "locations": ["Not Specified"], "categories": ["Engineering", "Electrical / Electronics", "Others", "Building & Construction", "Others"], "post_time": "2022-01-13T18:54:09Z", "salary": {"currency": null, "max": null, "min": null, "period": "monthly", "term": null}, "salary_visible": false, "title_keywords": ["asst. engineer"], "responsibilities": ["installation", "interview arrangement"], "requirements": {"degrees": [], "majors": [], "languages": [], "language_level": [], "hard_skills": [], "soft_skills": ["work independently"], "languages_combined": []}, "experience_required": {"duration": ["1-2 years"], "field": []}}, {"job_id": "100003009053471", "location_code": "hk", "company": "Kin Fat Construction Company Limited", "job_title": "\u5730\u76e4\u96dc\u52d9\u54e1", "description": "\n\u8077\u8cac :\u4e00\u822c\u5730\u76e4\u5de5\u4f5c\n\n\u8cc7\u6b77 :\u4e2d\u4e09\u7a0b\u5ea6; 2\u5e74\u7d93\u9a57; \u826f\u597d\u7cb5\u8a9e; \u4e00\u822c\u82f1\u8a9e; \u61c2\u8b80\u5beb\u4e2d\u6587; \u7565\u61c2\u8b80\u5beb\u82f1\u6587; \u6301\u6709\u5efa\u9020\u696d\u5de5\u4eba\u8a3b\u518a\u8b49; \u80fd\u7368\u7acb\u8655\u7406\u5730\u76e4\u5de5\u4f5c\n\n\u5f85\u9047 :\u6bcf\u6708$23,000 - $25,000, \u6709\u82b1\u7d05, \u661f\u671f\u4e00\u81f3\u516d: \u4e0a\u53488\u6642\u534a\u81f3\u4e0b\u53485\u6642\u534a, \u6bcf\u9031\u5de5\u4f5c6\u5929, \u6bcf\u5929\u5de5\u4f5c 9 \u5c0f\u6642\n\n\u7533\u8acb\u9808\u77e5 :\u6c42\u8077\u8005\u53ef\u81f4\u96fb23802121\u8207\u5065\u767c\u5efa\u7bc9\u6709\u9650\u516c\u53f8\u5442\u5c0f\u59d0\u806f\u7d61\u3002\n\n", "employment_types": ["Full Time"], "selling_points": [], "locations": ["Not Specified"], "categories": ["Engineering", "Others", "Others", "Others", "Building & Construction", "Others"], "post_time": "2022-01-17T07:01:46Z", "salary": {"currency": null, "max": null, "min": null, "period": "monthly", "term": null}, "salary_visible": false, "title_keywords": [], "responsibilities": [], "requirements": {"degrees": [], "majors": [], "languages": [], "language_level": [], "hard_skills": [], "soft_skills": [], "languages_combined": []}, "experience_required": {"duration": [], "field": []}}, {"job_id": "100003009055121", "location_code": "hk", "company": "Autotoll Limited", "job_title": "\u6280\u8853\u54e1/\u9ad8\u7d1a\u6280\u8853\u54e1", "description": "\u5de5\u4f5c\u7bc4\u570d:\n\n\u5b89\u88dd\u6c7d\u8eca\u5b9a\u4f4d\u53ca\u5176\u4ed6\u8eca\u8f09\u96fb\u5668\u8a2d\u5099\uff0c\u4e94\u5929\u5de5\u4f5c\u5305\u62ec\uff08\u661f\u671f\u516d/\u65e5\uff09\n\n\n\u5165\u8077\u8981\u6c42:\n\n\u4e2d\u4e94\u7a0b\u5ea6\uff0c\u66fe\u4fee\u8b80\u6c7d\u8eca\u76f8\u95dc\u8ab2\u7a0b\n\u6709\u6c7d\u8eca\u7dad\u4fee/\u97f3\u97ff/\u96fb\u5668\u5de5\u4f5c\u7d93\u9a57\u4e00\u5e74\u6216\u4ee5\u4e0a\n\u63011\u53ca2\u985e\u99d5\u99db\u57f7\u7167\n\nWhat you can get from us\n\nOn-the-job training, learning and development\u00a0provided\nExecutive workshops, interest class, corporate purchase discount offered by SHKP\nCompetitive salary and annual leaves\nFlexible working opportunities\n\n\nInterested parties, please send full resume with\u00a0expected salary\u00a0and\u00a0available date\u00a0to Human Resources and Administration Department by e-mail or by fax 2111 9459.\n\n(Data collected will be used for recruitment purpose only.)", "employment_types": ["Full Time"], "selling_points": ["13 days annual leave", "5 day work", "OT Paid"], "locations": ["Not Specified"], "categories": ["Transportation & Logistics", "Others", "Engineering", "Others", "Others", "Others"], "post_time": "2022-01-18T01:15:54Z", "salary": {"currency": null, "max": null, "min": null, "period": "monthly", "term": null}, "salary_visible": false, "title_keywords": ["\u6280\u8853\u54e1"], "responsibilities": ["purchase"], "requirements": {"degrees": [], "majors": [], "languages": [], "language_level": [], "hard_skills": ["workshops"], "soft_skills": ["flexible", "learning"], "languages_combined": []}, "experience_required": {"duration": [], "field": []}}, {"job_id": "100003009053413", "location_code": "hk", "company": "TopChamp Technology Limited", "job_title": "\u63db\u82af\u7dad\u4fee\u6280\u8853\u54e1**", "description": "\n\u8077\u8cac :\u63db\u82af, \u7dad\u4fee,\u4fdd\u990a, \u6aa2\u67e5, (\u6de8\u6c34\u8a2d\u5099, \u51b7\u71b1\u98f2\u6c34\u6a5f)\n\n\u8cc7\u6b77 :\u6c92\u6709\u5b78\u6b77\u8981\u6c42; 1\u5e74\u7d93\u9a57; \u826f\u597d\u7cb5\u8a9e; \u4e00\u822c\u666e\u901a\u8a71; \u61c2\u8b80\u5beb\u4e2d\u6587; \u5177\u76f8\u95dc\u7d93\u9a57\u512a\u5148, \u53ef\u7368\u7acb\u5de5\u4f5c\n\n\u5f85\u9047 :\u6bcf\u6708$14,000 - $16,000, \u6709\u9280\u884c\u5047\u671f, \u624b\u63d0\u96fb\u8a71\u6d25\u8cbc, \u5e74\u7d42\u734e\u91d1 \u53ca\u5be6\u5831\u5be6\u92b7\u4ea4\u901a\u652f\u51fa, \u661f\u671f\u4e00\u81f3\u516d: \u4e0a\u53489\u6642\u81f3\u4e0b\u53486\u6642, \u6bcf\u9031\u5de5\u4f5c6\u5929, \u6bcf\u5929\u5de5\u4f5c 8 - 9 \u5c0f\u6642\n\n\u7533\u8acb\u9808\u77e5 :\u6c42\u8077\u8005\u53ef\u81f4\u96fb25431898\u8207\u92d2\u5353\u79d1\u6280\u6709\u9650\u516c\u53f8\u8449 \u5c0f\u59d0\u806f\u7d61\u3002\n\n", "employment_types": ["Full Time"], "selling_points": [], "locations": ["Not Specified"], "categories": ["Engineering", "Others", "Others", "Technician"], "post_time": "2022-01-17T06:57:14Z", "salary": {"currency": null, "max": null, "min": null, "period": "monthly", "term": null}, "salary_visible": false, "title_keywords": [], "responsibilities": [], "requirements": {"degrees": [], "majors": [], "languages": [], "language_level": [], "hard_skills": [], "soft_skills": [], "languages_combined": []}, "experience_required": {"duration": [], "field": []}}, {"job_id": "100003009053771", "location_code": "hk", "company": "Hing Sing Engineering Limited", "job_title": "\u51b7\u6c23\u5b78\u5f92/\u6280\u5de5", "description": "\n\u8077\u8cac :\u5354\u52a9/\u8ca0\u8cac\u4e2d\u592e\u51b7\u6c23\u4e4b\u4fdd\u990a\u53ca\u7dad\u4fee, \u6e05\u6d17\u51b7\u6c23\n\n\u8cc7\u6b77 :\u6c92\u6709\u5b78\u6b77\u8981\u6c42; \u826f\u597d\u7cb5\u8a9e; \u61c2\u95b1\u8b80\u4e2d\u6587\n\n\u5f85\u9047 :\u6bcf\u6708$12,500 - $26,000, \u6709\u8d85\u6642\u5de5\u4f5c\u6d25\u8cbc, \u914c\u60c5\u6027\u82b1\u7d05, \u81b3\u98df\u6d25\u8cbc \u53ca\u4ea4\u901a\u6d25\u8cbc, \u661f\u671f\u4e00\u81f3\u516d: \u4e0a\u53489\u6642\u81f3\u4e0b\u53486\u6642, \u6bcf\u9031\u5de5\u4f5c6\u5929, \u6bcf\u5929\u5de5\u4f5c 9 \u5c0f\u6642\n\n\u7533\u8acb\u9808\u77e5 :\u6c42\u8077\u8005\u53ef\u81f4\u96fb96870595\u8207\u5144\u8aa0\u5de5\u7a0b\u6709\u9650\u516c\u53f8\u674e\u5148\u751f\u806f\u7d61\u3002\n\n", "employment_types": ["Full Time"], "selling_points": [], "locations": ["Not Specified"], "categories": ["Engineering", "Others", "Others", "Technician"], "post_time": "2022-01-17T07:29:46Z", "salary": {"currency": null, "max": null, "min": null, "period": "monthly", "term": null}, "salary_visible": false, "title_keywords": ["\u6280\u5de5"], "responsibilities": [], "requirements": {"degrees": [], "majors": [], "languages": [], "language_level": [], "hard_skills": [], "soft_skills": [], "languages_combined": []}, "experience_required": {"duration": [], "field": []}}, {"job_id": "100003009052537", "location_code": "hk", "company": "CLP Power Hong Kong Limited", "job_title": "Engineer I (2-Year Contract) [Ref: CLPP-GBG-GED-PMB-EI]", "description": "We are looking for an energetic and self-driven professional to join the Generation Engineering Department of our Generation Business Group. Reporting to the Project Manager, the appointee will be responsible for participating in the development of project control strategy, managing of project schedule and cost control function and execution of major plant engineering projects of the power generation facilities. Major duties include:\n\nProject Scheduling & Cost control:\n\n\nManage the project schedule and cost control to ensure project schedules and deliverables targets within the required budget, scope, time and quality;\nMonitor and report the overall project progress and expenditure to ensure corrective actions are taken on deviation from the overall project milestones and financial targets;\nEffectively identify the factors affecting the project progress and deployment of resources, both internal and external, for the successful delivery of projects.\n\nProject Management:\n\nIn collaboration with project team members, develop and define project basis, prepare specifications, evaluate tenders and make recommendations for contract award, develop project execution plans, and oversee the execution of a portfolio of projects to ensure safe implementation within pre-defined cost targets, timeframe, quality and performance objectives;\nLead engineering and construction of assigned projects, supervise contractors\u2019 activities, and collaborate with relevant project stakeholders to achieve safe and cost-effective project delivery in full compliance with CLP Power internal policies and relevant statutory requirements;\nReview design submissions, construction schedules, techniques to ensure the technical integrity of project and the contractor\u2019s conformity with contract terms and specification. Manage changes of work and handover the completed systems and documentation to asset owners;\nCollaborate with internal stakeholders to identify and implement best practices in construction safety throughout project development, specification, design review, construction and commissioning of works, and to resolve conflicts and disputes that may arise;\nConduct frequent site inspections to monitor progress, safety and quality of works, and collaborate with contractors to identify and implement continuous improvement initiative to achieve world class safety, health, environmental and quality standards;\nLiaise with equipment manufacturers, suppliers, services contractors, and internal stakeholders to ensure the design, installation, commissioning, operation and maintenance requirements can satisfy the company business needs and all statutory requirements.\nRequirements\n\nA recognized university in engineering or project management or quantity surveying plus at least 5 years relevant working experience preferably in project scheduling/ planning, cost control, engineering and implementation of multi-discipline infrastructure project\nPossession of professional qualification from HKIE or HKIS or other recognized engineering or quantity surveying professional bodies is preferable;\u00a0\nProfessional qualification in any Project management certification program or equivalent would be advantageous;\nStrong experience in project management process and good working knowledge of critical planning techniques;\nGood working knowledge of critical planning techniques using MS Project software;\nSound knowledge and experience of contract management;\nTrack record in project management including the development, scheduling, planning, engineering and execution of multi-disciplinary industrial projects;\nConversant with the latest code of practice, engineering standards, statutory requirements and SHEQ requirements pertaining to maintenance and project works in the generation/ construction industry.\nPractical knowledge and experience in personnel safety, safe systems of works and process safety to ensure projects are designed, constructed and operated safely in line with industry\u2019s best practice;\nProven supervisory, interpersonal, influencing and communication skills, good team player;\nProficient in specification writing, report and proposal compilation;\nGood command of English and Chinese, and excellence in communication with project stakeholders, consultants, contractors and workforce. Putonghua would be advantageous;\nFlexible, self-driven, and adaptable to changes and willing to meet challenges.\nThe appointee will be required to work in the Power Stations located at Tuen Mun area.\n\n\n\nPlease apply by sending\u00a0a detailed C.V., including academic qualifications, career history, major achievements and personal attributes on or before 25 January 2022.\u00a0To facilitate our easy tracking please use a unique file name for all attachments and your email subject box in this format: CLPP-GBG-GED-PMB-EI_Last Name_First Name_Other Names.\n\nApplicants not invited for interview within 6 weeks from the closing date may assume their applications unsuccessful.\n\nInformation provided will be for recruitment purpose within the CLP Group and only short-listed candidates will be contacted. We comply with all applicable laws and regulations of HKSAR in handling applications. For details of the Personal Information Collection Statement, please visit our website:\u00a0https://clp.to/engPICS\n\nFor further information on our company, please visit our website:\u00a0https://www.clpgroup.com/", "employment_types": ["Full Time", "Contract"], "selling_points": [], "locations": ["Tuen Mun Area"], "categories": ["Engineering", "Electrical / Electronics", "Mechanical", "Others"], "post_time": "2022-01-17T16:20:49Z", "salary": {"currency": null, "max": null, "min": null, "period": "monthly", "term": null}, "salary_visible": false, "title_keywords": ["engineer"], "responsibilities": ["collaborate with", "supervise contractors", "monitor progress", "schedules", "budget", "quality", "design", "statutory requirements", "review design submissions", "liaise with", "plans", "make recommendations", "compliance", "monitor", "project progress", "implementation", "develop", "schedule", "report", "installation", "cost", "commissioning", "review", "specifications", "documentation", "maintenance", "policies", "systems", "evaluate", "project management", "project scheduling", "cost control", "site inspections"], "requirements": {"degrees": [], "majors": [], "languages": ["putonghua", "english", "chinese"], "language_level": ["good command"], "hard_skills": ["plus", "hkie", "hkis", "maintenance", "project management", "safe", "c", "code"], "soft_skills": ["flexible", "communication skills", "good team player", "adaptable", "driven", "unique", "communication", "project management", "interpersonal", "detailed"], "languages_combined": [{"language": "putonghua", "language_level": []}, {"language": "english", "language_level": ["good command"]}, {"language": "chinese", "language_level": ["good command"]}]}, "experience_required": {"duration": ["at least 5 years"], "field": ["management", "engineering", "infrastructure", "relevant working experience", "project management", "planning"]}}, {"job_id": "100003009054007", "location_code": "hk", "company": "Impacts Technology Limited", "job_title": "Web / Mobile Developer", "description": "Job Description and Responsibilities\n\nDesign and Develop corporate training platforms for corporate in Hong Kong;\nPerform AI-related research for applying AI-related functions to e-learning systems.\u00a0\n\n\u00a0Job Openings\n\n2+\n\n\u00a0Job Requirements\n\nAt least 1 year of working experience (Fresh graduate will also be considered)\nExperience in e-learning platform development is a plus\nFamiliar with at least one of the following areas\nWeb Programming (HTML, CSS, JavaScript, PHP, MySQL) + Laravel (PHP Framework)\nSystem administration or Database administration (e.g. linux-based server, cloud based servers, MySQL administration, etc.)\niOS Programming (Objective-C / Swift)\nAndroid Programming (Java)\nFull-time working mode (5-day work)\n\n\u00a0Monthly Salary & Bonus:\n\nSalary will be offered based on experience, skills and education level\nRanged from 18,000 to 28,000 per month\nPerformance-based bonus will be considered at the end of the year\n\n\u00a0Team's Focus:\n\nCorporate Training Platform Development\nMobile Learning Platforms (Apps & Web)\nSoftware Product Development\n\n\u00a0Products and Services Highlight\n\niTrain - Self-learning corporate training platform\n\nA self-learning corporate training platform developed for MNC. Over 100,000 users have been enrolled to our system.", "employment_types": ["Full Time"], "selling_points": [], "locations": ["Pok Fu Lam"], "categories": ["Engineering", "Others", "Information Technology (IT)", "IT Management", "Software Development"], "post_time": "2022-01-17T16:21:02Z", "salary": {"currency": null, "max": null, "min": null, "period": "monthly", "term": null}, "salary_visible": false, "title_keywords": ["developer"], "responsibilities": ["systems", "design and develop"], "requirements": {"degrees": ["fresh graduate"], "majors": [], "languages": [], "language_level": [], "hard_skills": ["linux", "plus", "java", "servers", "web", "php", "swift", "html", "objective-c", "mobile", "javascript", "programming", "server", "css", "focus", "android"], "soft_skills": ["focus", "learning"], "languages_combined": []}, "experience_required": {"duration": ["at least 1 year"], "field": ["development", "education"]}}, {"job_id": "100003009053918", "location_code": "hk", "company": "Obrien Tech Limited", "job_title": "\u96fb\u6a5f\u5de5\u7a0b\u5e2b", "description": "\n\u8077\u8cac :\u4e00\u822c\u96fb\u6a5f\u5de5\u7a0b\u5e2b\u5de5\u4f5c, \u8ca0\u8cac\u65b0\u96fb\u529b\u8a2d\u5099\u4e4b\u8a2d\u8a08\u3001\u7b56\u5283\u3001\u7e6a\u5236\u5716\u5247\u3001\u76e3\u7ba1\u5de5\u4f5c\uff0c\u8207\u627f\u5efa\u5546\u53ca\u5ba2\u6236\u5354\u8abf\u53ca\u76e3\u7ba1\u9032\u5ea6\n\n\u8cc7\u6b77 :\u5c08\u4e0a\u6559\u80b2\uff1a\u6587\u6191/\u8b49\u66f8; \u4e00\u822c\u7cb5\u8a9e; \u4e00\u822c\u666e\u901a\u8a71; \u4e00\u822c\u82f1\u8a9e\u512a\u5148; \u61c2\u95b1\u8b80\u4e2d\u6587; \u61c2\u95b1\u8b80\u82f1\u6587\n\n\u5f85\u9047 :\u6bcf\u6708$13,000 - $15,000, \u6709\u9280\u884c\u5047\u671f \u53ca\u91ab\u7642\u4fdd\u96aa, \u661f\u671f\u4e00\u81f3\u4e94: \u4e0a\u53489\u6642\u81f3\u4e0b\u53486\u6642, \u6bcf\u9031\u5de5\u4f5c5\u5929, \u6bcf\u5929\u5de5\u4f5c 8 - 9 \u5c0f\u6642\n\n\u7533\u8acb\u9808\u77e5 :\u6c42\u8077\u8005\u53ef\u96fb\u90f5(Apply Now)\u5c65\u6b77\u8868\u7d66OBRIEN TECH LIMITED\u3002\u5982\u8981\u7d22\u53d6\u6536\u96c6\u500b\u4eba\u8cc7\u6599\u8072\u660e, \u8acb\u8207\u9673\u5148\u751f(Email)\u806f\u7d61\u3002\n\n", "employment_types": ["Full Time"], "selling_points": [], "locations": ["Tsim Sha Tsui"], "categories": ["Engineering", "Electrical / Electronics", "Engineering Project Management", "Others"], "post_time": "2022-01-17T07:46:09Z", "salary": {"currency": null, "max": null, "min": null, "period": "monthly", "term": null}, "salary_visible": false, "title_keywords": [], "responsibilities": [], "requirements": {"degrees": [], "majors": [], "languages": [], "language_level": [], "hard_skills": [], "soft_skills": [], "languages_combined": []}, "experience_required": {"duration": [], "field": []}}, {"job_id": "100003009053569", "location_code": "hk", "company": "Run Wide Engineering Limited", "job_title": "\u5730\u76e4\u5b89\u5168\u96dc\u5de5", "description": "\n\u8077\u8cac :\u4e00\u822c\u5730\u76e4\u5b89\u5168\u96dc\u5de5\u5de5\u4f5c, \u9700\u6236\u5916\u5de5\u4f5c, \u5de5\u4f5c\u5730\u9ede: \u746a\u9e97\u91ab\u9662\n\n\u8cc7\u6b77 :\u6c92\u6709\u5b78\u6b77\u8981\u6c42; \u4e00\u822c\u7cb5\u8a9e; \u61c2\u8b80\u5beb\u4e2d\u6587; \u6301\u6709\u5e73\u5b89\u54ad; \u6301\u6709\u5efa\u9020\u696d\u5de5\u4eba\u8a3b\u518a\u8b49; \u9808\u7b26\u5408\u76f8\u95dc\u50f1\u4e3b\u7684\u9632\u75ab\u898f\u5b9a(\u5305\u62ec\u63a5\u7a2e\u75ab\u82d7\u6216\u65b0\u51a0\u75c5\u6bd2\u6aa2\u6e2c\u898f\u5b9a)\n\n\u5f85\u9047 :\u6bcf\u65e5$800.00, \u661f\u671f\u4e00\u81f3\u516d: \u4e0a\u53488\u6642\u81f3\u4e0b\u53486\u6642, \u6bcf\u9031\u5de5\u4f5c6\u5929, \u6bcf\u5929\u5de5\u4f5c 10 \u5c0f\u6642\n\n\u7533\u8acb\u9808\u77e5 :\u6c42\u8077\u8005\u53ef\u81f4\u96fb66061430\u8207\u5b8f\u5049\u5de5\u7a0b\u6709\u9650\u516c\u53f8\u913a\u5c0f\u59d0\u806f\u7d61\u3002\n\n", "employment_types": ["Full Time"], "selling_points": [], "locations": ["Pok Fu Lam"], "categories": ["Engineering", "Others", "Others", "Others", "Building & Construction", "Others"], "post_time": "2022-01-17T07:10:38Z", "salary": {"currency": null, "max": null, "min": null, "period": "hourly", "term": null}, "salary_visible": false, "title_keywords": [], "responsibilities": [], "requirements": {"degrees": [], "majors": [], "languages": [], "language_level": [], "hard_skills": [], "soft_skills": [], "languages_combined": []}, "experience_required": {"duration": [], "field": []}}, {"job_id": "100003009053907", "location_code": "hk", "company": "Park Rich Environmental Technology Ltd.", "job_title": "\u81ea\u63a7\u6280\u8853\u54e1", "description": "\n\u8077\u8cac :\u8ca0\u8cacPLC\u8abf\u8a66\u5de5\u4f5c\n\n\u8cc7\u6b77 :\u6c92\u6709\u5b78\u6b77\u8981\u6c42; \u4e00\u822c\u7cb5\u8a9e; \u6301\u6709\u5e73\u5b89\u54ad; \u6301\u6709\u5efa\u9020\u696d\u5de5\u4eba\u8a3b\u518a\u8b49\n\n\u5f85\u9047 :\u6bcf\u65e5$1,500.00 - $2,000.00, \u4e0a\u53489\u6642\u81f3\u4e0b\u53486\u6642, \u6bcf\u9031\u5de5\u4f5c3\u5929\u81f35\u5929, \u5de5\u4f5c\u671f1\u500b\u6708, \u6709\u9700\u8981\u6642\u9700\u52a0\u73ed\n\n\u7533\u8acb\u9808\u77e5 :\u6c42\u8077\u8005\u53ef\u96fb\u90f5(Apply Now)\u5c65\u6b77\u8868\u7d66\u767e\u5bcc\u74b0\u4fdd\u79d1\u6280\u6709\u9650\u516c\u53f8\u3002\u5982\u8981\u7d22\u53d6\u6536\u96c6\u500b\u4eba\u8cc7\u6599\u8072\u660e, \u8acb\u8207\u6797\u5148\u751f(Email)\u806f\u7d61\u3002\n\n", "employment_types": ["Contract"], "selling_points": [], "locations": ["Tuen Mun Area"], "categories": ["Engineering", "Others", "Others", "Technician"], "post_time": "2022-01-17T07:44:21Z", "salary": {"currency": null, "max": null, "min": null, "period": "hourly", "term": null}, "salary_visible": false, "title_keywords": [], "responsibilities": [], "requirements": {"degrees": [], "majors": [], "languages": [], "language_level": [], "hard_skills": [], "soft_skills": [], "languages_combined": []}, "experience_required": {"duration": [], "field": []}}, {"job_id": "100003009053570", "location_code": "hk", "company": "HK Systems Limited", "job_title": "\u96fb\u8166\u6280\u8853\u54e1", "description": "\n\u8077\u8cac :\u8ca0\u8cac\u4e00\u822c\u96fb\u8166\u7cfb\u7d71\u7dad\u4fee\u3001\u4fdd\u990a\u53ca\u6e2c\u8a66\uff0c\u9700\u5916\u52e4\u5de5\u4f5c\n\u8981\u6c42 :\u4e2d\u4e94\u7a0b\u5ea6; 2\u5e74\u7d93\u9a57; \u826f\u597d\u7cb5\u8a9e; \u4e00\u822c\u82f1\u8a9e; \u61c2\u8b80\u5beb\u4e2d\u6587; \u7565\u61c2\u8b80\u5beb\u82f1\u6587; \u5177\u6709\u57fa\u672c\u96fb\u8166\u64cd\u4f5c\u77e5\u8b58\u53ca\u5177\u76f8\u95dc\u5de5\u4f5c\u7d93\u9a57\u512a\u5148\n\u5f85\u9047 :\u6bcf\u6708$13,000 - $15,000, \u6709\u9280\u884c\u5047\u671f, \u91ab\u7642\u798f\u5229 \u53ca\u914c\u60c5\u6027\u82b1\u7d05, \u661f\u671f\u4e00\u81f3\u4e94: \u4e0a\u53489\u6642\u81f3\u4e0b\u53486\u6642, \u6bcf\u9031\u5de5\u4f5c5\u5929\n\u6709\u610f\u8005\u8acb\u5177\u5c65\u6b77\u53ca\u53ef\u5230\u8077\u65e5\u671f\uff0cApply Now\n\n", "employment_types": ["Full Time"], "selling_points": [], "locations": ["Kwun Tong"], "categories": ["Engineering", "Others", "Others", "Technician"], "post_time": "2022-01-17T07:10:43Z", "salary": {"currency": null, "max": null, "min": null, "period": "monthly", "term": null}, "salary_visible": false, "title_keywords": [], "responsibilities": [], "requirements": {"degrees": [], "majors": [], "languages": [], "language_level": [], "hard_skills": [], "soft_skills": [], "languages_combined": []}, "experience_required": {"duration": [], "field": []}}, {"job_id": "100003009055645", "location_code": "hk", "company": "Links International", "job_title": "Building Services Engineer", "description": "Job Responsibilities:\n\nProvide support to the Project Manager in tender preparation, tender analysis, price negotiation and budget control\nCo-ordinate with clients, consultants, main-contractors and sub-contractors for project implementation\nHandle project administration\nResolve site matters and site coordination\nAd hoc duties as required\n\nJob Requirements:\n\nDegree Holder in Electrical / Mechanical / Building Services or equivalent\nAt lease 4 years' relevant experience in participation of E&M / Building Services Contracts, senior experience will be considering as Senior Engineer\nGood command of both written and spoken English and Chinese\nGood communication and interpersonal skills\nSelf motivated, Independent and able to work under pressure\nProficiency in AutoCAD and Microsoft Project", "employment_types": ["Full Time", "Permanent"], "selling_points": ["4+ years experience in E&M / building services", "Tender management experience", "Immediate available is preferred"], "locations": ["Not Specified"], "categories": ["Engineering", "Electrical / Electronics", "Engineering Project Management", "Others"], "post_time": "2022-01-18T02:49:42Z", "salary": {"currency": null, "max": null, "min": null, "period": "monthly", "term": null}, "salary_visible": false, "title_keywords": ["building services engineer"], "responsibilities": ["ad hoc duties", "provide support", "price negotiation", "handle project administration", "co-ordinate with clients", "implementation", "tender analysis", "site coordination", "tender preparation", "budget control"], "requirements": {"degrees": ["degree holder"], "majors": ["building services"], "languages": ["english", "chinese"], "language_level": ["good command"], "hard_skills": ["microsoft project", "autocad"], "soft_skills": ["self motivated", "communication and interpersonal skills", "independent", "work under pressure"], "languages_combined": [{"language": "english", "language_level": ["good command"]}, {"language": "chinese", "language_level": ["good command"]}]}, "experience_required": {"duration": ["4 years"], "field": ["building services", "relevant experience", "senior engineer"]}}, {"job_id": "100003009055658", "location_code": "hk", "company": "Tata Consultancy Services Limited", "job_title": "Data Engineer", "description": "5-10 years\u2019 experience in ETL development in data transformation projects (e.g. DWH)\n5-10 years\u2019 experience in SQL development\nStrong insurance industry and IFRS17 knowledge is critical\nStrong experience in ETL tools such as Talend (highly desirable), Informatica, IBM DataStage, Microsoft SSIS\nStrong experience in cloud services, specifically AWS\nAccounting and/or actuarial knowledge an advantage", "employment_types": ["Full Time", "Permanent"], "selling_points": ["Experience in ETL development", "Experience in SQL development", "Strong experience in cloud services"], "locations": ["Others"], "categories": ["Engineering", "Others"], "post_time": "2022-01-18T02:50:07Z", "salary": {"currency": null, "max": null, "min": null, "period": "monthly", "term": null}, "salary_visible": false, "title_keywords": ["data engineer"], "responsibilities": ["insurance", "data"], "requirements": {"degrees": [], "majors": [], "languages": [], "language_level": [], "hard_skills": ["sql", "aws"], "soft_skills": [], "languages_combined": []}, "experience_required": {"duration": ["5-10 years"], "field": ["sql", "development"]}}, {"job_id": "100003009048274", "location_code": "hk", "company": "Media-Go Engineering Ltd", "job_title": "Project Engineer (ELV / Building Service / Audio Visual System)", "description": "Job Responsibilities:\n\n\nResponsibilities on project installation design and related document submission.\nMonitoring and report the project work progress.\nLiaise with clients, consultants, and subcontractors.\nHandle ad hoc duties and assignments as required.\u00a0\n\nJob Requirements:\n\n\nCertificate or above in Building services / Electrical / Electronic Engineering or relevant disciplines.\nExperience in ELV, CCTV, Communication and Networking projects.\nCandidates with less experience will be considered as Assistant Project Engineer.\n\"Green Card\" holder\nGood command of spoken and written English & Chinese.\nGood interpersonal and communication skills.\nProficient in using Microsoft Office and AutoCAD.\nImmediate available is preferred.\n\nWe offer competitive remuneration package and good prospects to the right candidates. Interested parties please send your full resume, current and expected salary to us by clicking\u00a0\u201cAPPLY NOW\u201d, or post to\u00a025/F, Westin Centre, 26 Hung To Road, Kwun Tong, Kowloon,\u00a0Hong Kong, or fax to\u00a0+852-3101-2614.\u00a0(Please quote the job reference number and job title on the subject).\n\nFor more information, please visit our website:\u00a0www.mediago-group.com\n\nData collected will be kept confidential and used for recruitment purposes only.", "employment_types": ["Full Time"], "selling_points": [], "locations": ["To Kwa Wan"], "categories": ["Engineering", "Mechanical", "Others"], "post_time": "2022-01-15T03:49:54Z", "salary": {"currency": null, "max": null, "min": null, "period": "monthly", "term": null}, "salary_visible": false, "title_keywords": ["project engineer"], "responsibilities": ["liaise with clients", "installation", "ad hoc duties", "monitoring", "design", "report"], "requirements": {"degrees": ["certificate"], "majors": ["building services", "engineering"], "languages": ["english", "chinese"], "language_level": ["good command"], "hard_skills": ["microsoft office", "cctv", "autocad", "green card"], "soft_skills": ["communication", "communication skills", "interpersonal"], "languages_combined": [{"language": "english", "language_level": ["good command"]}, {"language": "chinese", "language_level": ["good command"]}]}, "experience_required": {"duration": [], "field": []}}, {"job_id": "100003009052003", "location_code": "hk", "company": "Giesecke & Devrient Asia Pacific Ltd", "job_title": "Customer Service Engineer", "description": "MAJOR DUTIES AND RESPONSIBILITIES include the followings. Other duties may be assigned as necessary to fulfil optimum efficiency of this position:\n\nBe responsible for banknote processing systems\u2019 installation\nProvide service\u00a0maintenance and after sales services for banknote processing systems\nHandle inquires and complaints from customers\nProvide support on new product launch, demo and product presentation\nBe responsible for service documentations (service report and spare parts transaction)\nSpare parts inventory management and control\nManage and implement preventive and corrective maintenance program to ensure the banknote processing systems in customer sites are in good condition.\nConduct fault analysis and formulate maintenance and improvement plan\nCompile management report and purpose recommendations for service enhancement\nAudit and facilitate the implementation of service support to compile with safety requirement\nPerform any ad hoc projects as required from time to time; and undertake functions and responsibilities of the company as reasonably assigned by the management\n\nREQUIREMENT:\n\nDegree or Diploma holder in Mechanical /Electronic Engineering/Electrical Engineering or equivalent\nFresh graduates may be considered as junior customer service engineer\nAggressive, self-motivated and able to work independently\nGood communication skill, coordination and time management skill\nFluent in speaking and writing English and Chinese\nGood Computer knowledge and literacy\n\nAn attractive package that is commensurate with successful candidate's qualifications and experience will be offered. Please apply with detailed resume including availability, current & expected salary and contact number to HR Department, Giesecke & Devrient Asia Pacific Limited, Room 2901 Hysan Place, 500 Hennessy Road, Causeway Bay, Hong Kong or apply in JobsDB.com directly.\n\nAll information received will be kept in strict confidence and only for employment-related purpose.", "employment_types": ["Full Time", "Permanent"], "selling_points": ["Provide service maintenance", "Mechanical Engineering / Electronic Engineering", "Machinery repairing"], "locations": ["Causeway Bay"], "categories": ["Engineering", "Electrical / Electronics", "Mechanical", "Others"], "post_time": "2022-01-17T01:48:37Z", "salary": {"currency": null, "max": null, "min": null, "period": "monthly", "term": null}, "salary_visible": false, "title_keywords": ["customer service engineer"], "responsibilities": ["installation", "provide support", "control", "management", "maintenance", "other duties", "analysis", "systems", "audit", "implementation", "inventory management", "ad hoc projects", "plan", "management report", "report"], "requirements": {"degrees": ["diploma holder", "degree"], "majors": ["engineering", "electrical engineering"], "languages": ["english", "chinese"], "language_level": ["fluent"], "hard_skills": [], "soft_skills": ["self-motivated", "work independently", "confidence", "communication skill", "customer service", "time management skill", "coordination", "detailed"], "languages_combined": [{"language": "english", "language_level": ["fluent"]}, {"language": "chinese", "language_level": ["fluent"]}]}, "experience_required": {"duration": [], "field": []}}, {"job_id": "100003009053724", "location_code": "hk", "company": "Cyber-Pro Technology Limited", "job_title": "\u96fb\u8166\u6280\u8853\u54e1", "description": "\n\u8077\u8cac :\u96fb\u8166\u7dad\u4fee\u53ca\u66f4\u63db\u96f6\u4ef6, \u9700\u5916\u52e4\u5de5\u4f5c\n\n\u8cc7\u6b77 :\u6c92\u6709\u5b78\u6b77\u8981\u6c42; \u4e00\u822c\u7cb5\u8a9e; \u4e00\u822c\u666e\u901a\u8a71; \u4e00\u822c\u82f1\u8a9e; \u7565\u61c2\u8b80\u5beb\u4e2d\u6587; \u7565\u61c2\u8b80\u5beb\u82f1\u6587; \u6709\u79ae\u8c8c, \u6709\u8010\u6027, \u6709\u8cac\u4efb\u5fc3, \u5c0d\u5de5\u4f5c\u6709\u71b1\u8aa0\n\n\u5f85\u9047 :\u6bcf\u6708$11,000 - $13,000, \u6709\u9280\u884c\u5047\u671f, \u91ab\u7642\u798f\u5229 \u53ca\u4ea4\u901a\u6d25\u8cbc, \u661f\u671f\u4e00\u81f3\u4e94: \u4e0a\u53489\u6642\u534a\u81f3\u4e0b\u53486\u6642\u534a, \u6bcf\u9031\u5de5\u4f5c5\u5929, \u6709\u9700\u8981\u6642\u9700\u65bc\u661f\u671f\u65e5\u6216\u516c\u773e\u5047\u671f\u4e0a\u73ed\n\n\u7533\u8acb\u9808\u77e5 :\u6c42\u8077\u8005\u53ef\u96fb\u90f5(Apply Now)\u5c65\u6b77\u8868\u7d66\u5275\u7cfb\u96fb\u8166\u79d1\u6280\u6709\u9650\u516c\u53f8\u3002\u5982\u8981\u7d22\u53d6\u6536\u96c6\u500b\u4eba\u8cc7\u6599\u8072\u660e, \u8acb\u8207\u7f85\u5148\u751f(Email)\u806f\u7d61\u3002\n\n", "employment_types": ["Full Time"], "selling_points": [], "locations": ["Not Specified"], "categories": ["Engineering", "Others", "Others", "Technician"], "post_time": "2022-01-17T07:24:46Z", "salary": {"currency": null, "max": null, "min": null, "period": "monthly", "term": null}, "salary_visible": false, "title_keywords": [], "responsibilities": [], "requirements": {"degrees": [], "majors": [], "languages": [], "language_level": [], "hard_skills": [], "soft_skills": [], "languages_combined": []}, "experience_required": {"duration": [], "field": []}}, {"job_id": "100003009053470", "location_code": "hk", "company": "Tak Kai Co Ltd", "job_title": "\u5370\u5237\u5ee0\u5370\u5237\u6280\u5de5", "description": "\n\u8077\u8cac :\u5354\u52a9\u64cd\u4f5c\u5370\u5237\u5ee0\u623f\u5167\u4e4b \"\u67ef\u5f0f\" \u5370\u5237\u6a5f\u53ca\u4e00\u822c\u5ee0\u5167\u65e5\u5e38\u5de5\u4f5c\n\n\u8cc7\u6b77 :\u5c0f\u516d\u7a0b\u5ea6; 2\u5e74\u7d93\u9a57; \u4e00\u822c\u7cb5\u8a9e; \u7565\u61c2\u8b80\u5beb\u4e2d\u6587; \u52e4\u596e, \u6709\u8cac\u4efb\u611f\n\n\u5f85\u9047 :\u6bcf\u6708$13,000 - $17,000, \u6709\u8d85\u6642\u5de5\u4f5c\u6d25\u8cbc, \u751f\u65e5\u5047 \u53ca\u91ab\u7642\u798f\u5229, \u661f\u671f\u4e00\u81f3\u516d: \u4e0a\u53489\u6642\u81f3\u4e0b\u53486\u6642, \u6bcf\u9031\u5de5\u4f5c6\u5929, \u6bcf\u5929\u5de5\u4f5c 8 \u5c0f\u6642\n\n\u7533\u8acb\u9808\u77e5 :\u6c42\u8077\u8005\u53ef\u81f4\u96fb67637896\u8207\u5fb7\u4f73\u6709\u9650\u516c\u53f8\u9ec3\u5c0f\u59d0\u806f\u7d61\u3002\n\n", "employment_types": ["Full Time"], "selling_points": [], "locations": ["Southern Area"], "categories": ["Engineering", "Others", "Others", "Technician", "Others"], "post_time": "2022-01-17T07:01:50Z", "salary": {"currency": null, "max": null, "min": null, "period": "monthly", "term": null}, "salary_visible": false, "title_keywords": [], "responsibilities": [], "requirements": {"degrees": [], "majors": [], "languages": [], "language_level": [], "hard_skills": [], "soft_skills": [], "languages_combined": []}, "experience_required": {"duration": [], "field": []}}, {"job_id": "100003009053164", "location_code": "hk", "company": "Princess Yachts Greater China Limited", "job_title": "Yacht Technician / Technical Specialist (\u904a\u8247\u6280\u8853\u54e1)", "description": "Job Duties:\n\nManage warranty & aftersales service for a range of marine group products\nEnsure all warranty & service repairs are completed at a high level of standard\nInspect & prepare new yachts for delivery to customers\nLiaise with the principal on yachts handover & pre-delivery inspection reports\nOrganize for the unloading with shipyard, tugs & shipping company\nDeliver prompt technical advice & training to customers & their crew members related to the operation & maintenance of yachts\nTrain up junior staff on company products\n\nRequirements:\n\nMinimum 5 years\u2019 relevant experience\nResponsible with good attitude\nGood command of English\nAttractive salary package and fringe benefits will be offered to the successful candidate. Interested parties please send your resume stating reference number and expected salary to Human Resources Manager\u00a0by email\u00a0\u00a0\"Apply Now\", whatsapp to 9318 2638 or fax to 2798 9562.\u00a0\n\n\nWe are an equal opportunities employer. Personal data collected will be treated in strict confidence and used for recruitment purposes only. All applications may be considered for other suitable positions with DCH Group / CITIC Pacific Group and the personal data collected will be deleted from our files after 6 months from the date of application.", "employment_types": ["Full Time", "Permanent"], "selling_points": [], "locations": ["Tsing Yi"], "categories": ["Engineering", "Electrical / Electronics", "Mechanical", "Others"], "post_time": "2022-01-17T06:10:49Z", "salary": {"currency": null, "max": null, "min": null, "period": "monthly", "term": null}, "salary_visible": false, "title_keywords": ["technical specialist", "technician"], "responsibilities": ["shipping", "inspection reports", "maintenance", "technical advice", "liaise with"], "requirements": {"degrees": [], "majors": [], "languages": ["english"], "language_level": ["good command"], "hard_skills": [], "soft_skills": ["responsible"], "languages_combined": [{"language": "english", "language_level": ["good command"]}]}, "experience_required": {"duration": ["minimum 5 years"], "field": ["relevant experience"]}}, {"job_id": "100003009053400", "location_code": "hk", "company": "Gentleman's Style Limited", "job_title": "Technician", "description": "\nResponsibilities:Core focus on line cleaning and basic maintenance of beer and water filtration equipment; Perform on-site technical support for customers; Support technical manager/ess and senior technicians with beer installs (\u5177\u9152\u5e97\u7dad\u4fee\u90e8\u9580\u6216\u7dad\u4fee\u51b7\u6c23\u3001\u5564\u9152/\u5496\u5561\u53ca\u6c34\u6a5f\u7d93\u9a57\u512a\u5148\uff1b\u6709\u8cac\u4efb\u611f\u53ca\u5de5\u4f5c\u4e3b\u52d5)\n\nRequirements :Secondary 3; Fair Cantonese ; Fair Putonghua ; Fair English ; Able to read & write Chinese ; Able to read & write English ; Basic technical background pref.\n\nEmployment Terms:$17,000 - $20,000 per month, with Annual Leave 10 days, 9:00AM-6:00PM, 5 - 6 working days per week, shift holiday on Sat and Sun, 9 working hours per day\n\nApplication Information:Job seekers may e-mail(Apply Now) resume to METADESIGN LTD.. To obtain a copy of Personal Information Collection Statement, please contact MR. LAU by Email.\n\n", "employment_types": ["Full Time"], "selling_points": [], "locations": ["Not Specified"], "categories": ["Engineering", "Others", "Others", "Technician"], "post_time": "2022-01-17T06:55:50Z", "salary": {"currency": null, "max": null, "min": null, "period": "monthly", "term": null}, "salary_visible": false, "title_keywords": ["technician"], "responsibilities": ["sat", "maintenance", "technical support", "contact", "cleaning"], "requirements": {"degrees": [], "majors": [], "languages": ["cantonese", "putonghua", "english", "chinese"], "language_level": [], "hard_skills": ["focus", "basic", "maintenance"], "soft_skills": ["focus"], "languages_combined": [{"language": "cantonese", "language_level": []}, {"language": "putonghua", "language_level": []}, {"language": "english", "language_level": []}, {"language": "chinese", "language_level": []}]}, "experience_required": {"duration": [], "field": []}}, {"job_id": "100003009053954", "location_code": "hk", "company": "Safemark Alliance Security Co Limited", "job_title": "\u9632\u76dc\u6280\u5de5", "description": "\n\u8077\u8cac :\u8ca0\u8cac\u653e\u7dda, \u5b89\u88dd, \u7dad\u4fee, \u6aa2\u67e5, \u6e2c\u8a66\u53ca\u76e3\u7763\u5beb\u5b57\u6a13, \u9580\u8216\u9632\u76dc\u7cfb\u7d71, \u9589\u8def\u96fb\u8166, \u96fb\u9396, \u62cd\u5361\u7b49\u9580\u76e3\u7cfb\u7d71\n\n\u8cc7\u6b77 :\u4e2d\u4e09\u7a0b\u5ea6; 3\u5e74\u7d93\u9a57; \u4e00\u822c\u7cb5\u8a9e; \u4e00\u822c\u666e\u901a\u8a71; \u4e00\u822c\u82f1\u8a9e; \u61c2\u8b80\u5beb\u4e2d\u6587; \u61c2\u8b80\u5beb\u82f1\u6587; \u6301\u6709\u4fdd\u5b89\u4eba\u54e1\u8a31\u53ef\u8b49; \u6709\u8cac\u4efb\u5fc3, \u5b88\u6642, \u80fd\u7368\u7acb\u5de5\u4f5c, \u826f\u597d\u89e3\u96e3\u6280\u5de7, \u719f\u6089\u76f8\u95dc\u7cfb\u7d71\n\n\u5f85\u9047 :\u6bcf\u6708$17,000, \u6709\u9280\u884c\u5047\u671f \u53ca\u4ea4\u901a\u6d25\u8cbc, \u661f\u671f\u4e00\u81f3\u516d: \u4e0a\u53489\u6642\u534a\u81f3\u4e0b\u53486\u6642\u534a, \u6bcf\u9031\u5de5\u4f5c6\u5929, \u6bcf\u5929\u5de5\u4f5c 8 \u5c0f\u6642\n\n\u7533\u8acb\u9808\u77e5 :\u6c42\u8077\u8005\u53ef\u81f4\u96fb35719130\u8207\u5b89\u76df\u4fdd\u5b89\u6709\u9650\u516c\u53f8CHAN\u5c0f\u59d0\u806f\u7d61\u3002\n\n", "employment_types": ["Full Time"], "selling_points": [], "locations": ["Not Specified"], "categories": ["Engineering", "Others", "Others", "Technician"], "post_time": "2022-01-17T07:50:46Z", "salary": {"currency": null, "max": null, "min": null, "period": "monthly", "term": null}, "salary_visible": false, "title_keywords": [], "responsibilities": [], "requirements": {"degrees": [], "majors": [], "languages": [], "language_level": [], "hard_skills": [], "soft_skills": [], "languages_combined": []}, "experience_required": {"duration": [], "field": []}}, {"job_id": "100003009053696", "location_code": "hk", "company": "Arup", "job_title": "Engineer/Project Engineer/Sr Engineer (Structural Engineering for Energy Infra) (Perm/1-yr Contract)", "description": "Arup\u2019s Energy Infrastructure business in East Asia is experiencing rapid growth. With Hong Kong as our base, we provide detailed planning, design and engineering services for a wide spectrum of energy development projects. The work of our Energy Infrastructure Team is focused around some significant infrastructure projects including combined cycle power plants, offshore LNG receiving terminal, gas receiving stations and offshore wind farms. In addition to multidisciplinary design and construction management, we also provide project management service to our clients for execution of their projects from inception through to commercial operation. We are seeking to recruit capable and independent individuals for the following positions to join our energetic team.\n\nResponsibilities:\n\n\nDevelop design concepts and construction methodologies and provide leadership in project execution\nUndertake detailed design in Energy Infrastructure projects in HK and overseas\nLiaise with Client, Client\u2019s Consultants, Contractor, and Authorities for project development from concept to construction\nAssist business line leaders in maintaining high quality standards of design and construction\nAssist business line leaders in the management of division employees\n\nQualifications and Experiences required:\n\n\nDegree in civil engineering, post-graduate degree in relevant discipline is an advantage\nCorporate Member of HKIE or equivalent, such as MIStructE, MHKIE (Structural)\nAt least 3 years of post graduation experience for the position of Engineer; at least 1 year of post chartered experience for the position of Project Engineer; at least 2 years of post chartered experience for the position of Senior Engineer\nExperience in steelwork design would be an advantage\nProficiency in the use of structural engineering design related computing software and BIM tools including Staad Pro, GSA, SAP2000 and SAFE\nStrong interest in digital engineering design with demonstrable proficiency in Python scripting or visual programming in Grasshopper will be an advantage\nAble to prioritize and handle multi-tasks with strong organizational and time management skills\nStrong sense of responsibility and organization\nStrong communication, presentation and project management skill\nFluent in written and spoken English and Chinese\n\n\n\nWe offer a competitive remuneration package commensurate with qualifications and experience to the right candidate.\u00a0For permanent offer,\u00a0Global Profit Share scheme, additional fringe benefits of maternity / paternity leave and long-term career development opportunities will be provided.\n\nFor interested applicants, please click \u201cApply Now\" to submit your online application.\n\nTo explore more job opportunities in Arup, please visit our website at http://www.arup.com/Careers/Experienced_Hires/ApplyForAJob\n\u00a0\nPersonal data collected will be used for recruitment purpose only. Applicants not contacted within 8 weeks may consider their applications unsuccessful.", "employment_types": ["Full Time"], "selling_points": [], "locations": ["Kowloon City Area"], "categories": ["Building & Construction", "Civil / Structural", "Engineering", "Engineering Project Management", "Others"], "post_time": "2022-01-17T07:22:13Z", "salary": {"currency": null, "max": null, "min": null, "period": null, "term": null}, "salary_visible": false, "title_keywords": ["engineer", "project engineer"], "responsibilities": ["infrastructure"], "requirements": {"degrees": [], "majors": [], "languages": [], "language_level": [], "hard_skills": ["rapid"], "soft_skills": [], "languages_combined": []}, "experience_required": {"duration": [], "field": []}}, {"job_id": "100003009052367", "location_code": "hk", "company": "Cartrack Technologies (China) Limited", "job_title": "\u6280\u8853\u54e1 (\u6b61\u8fce\u525b\u7562\u696d\u751f\u7533\u8acb)", "description": "\n\u8077\u8cac :\u4e00\u822c\u6280\u5de5\u5de5\u4f5c,\u8ca0\u8cac\u5b89\u88dd,\u6aa2\u67e5,\u4fdd\u990a\u53ca\u7dad\u4fee\u8eca\u8f09\u96fb\u5b50\u6709\u95dc\u8a2d\u5099\u548c\u5668\u6750,\u63d0\u4f9b\u6280\u8853\u652f\u63f4,\u9700\u6237\u5916\u5de5\u4f5c\n\n\u8cc7\u6b77 :\u6c92\u6709\u5b78\u6b77\u8981\u6c42; 1\u5e74\u7d93\u9a57; \u826f\u597d\u7cb5\u8a9e; \u4e00\u822c\u666e\u901a\u8a71; \u826f\u597d\u82f1\u8a9e; \u7565\u61c2\u8b80\u5beb\u4e2d\u6587; \u7565\u61c2\u8b80\u5beb\u82f1\u6587; \u5177\u96fb\u5b50\u7dad\u4fee/\u6c7d\u8eca\u6a5f\u68b0/\u6c7d\u8eca\u4fee\u7406\u7d93\u9a57\u512a\u5148,\u6709\u5b89\u88dd\u8eca\u968a\u5be6\u6642\u76e3\u63a7\u7cfb\u7d71\u7d93\u9a57\u512a\u5148,\u5de5\u4f5c\u52e4\u596e\u4e0a\u9032,\u5de5\u4f5c\u7a4d\u6975\u4e3b\u52d5\n\n\u5f85\u9047 :\u6bcf\u6708$15,000 - $20,000, \u6709\u9280\u884c\u5047\u671f, \u8d85\u6642\u5de5\u4f5c\u6d25\u8cbc \u53ca\u7259\u79d1\u798f\u5229, \u661f\u671f\u4e00\u81f3\u4e94: \u4e0a\u53489\u6642\u81f3\u4e0b\u53486\u6642, \u6bcf\u9031\u5de5\u4f5c5\u5929\n\n\u7533\u8acb\u9808\u77e5 :\u6c42\u8077\u8005\u53ef\u96fb\u90f5(Apply Now)\u5c65\u6b77\u8868\u7d66CARTRACK TECHNOLOGIES (CHINA) LIMITED\u3002\u5982\u8981\u7d22\u53d6\u6536\u96c6\u500b\u4eba\u8cc7\u6599\u8072\u660e, \u8acb\u8207\u9ec4\u5c0f\u59d0(Email)\u806f\u7d61\u3002\n\n", "employment_types": ["Full Time"], "selling_points": ["\u6c92\u6709\u5b78\u6b77\u8981\u6c42", "1\u5e74\u7d93\u9a57", "\u826f\u597d\u7cb5\u8a9e"], "locations": ["Kwun Tong Area"], "categories": ["Engineering", "Others", "Others", "Technician"], "post_time": "2022-01-17T02:52:22Z", "salary": {"currency": null, "max": null, "min": null, "period": "monthly", "term": null}, "salary_visible": false, "title_keywords": ["\u6280\u8853\u54e1"], "responsibilities": [], "requirements": {"degrees": [], "majors": [], "languages": [], "language_level": [], "hard_skills": [], "soft_skills": [], "languages_combined": []}, "experience_required": {"duration": [], "field": []}}, {"job_id": "100003009052830", "location_code": "hk", "company": "The Hongkong Electric Co., Ltd.", "job_title": "Senior Meter Asset Management Engineer (Ref: CS-M-SMAME-JD)", "description": "Responsibilities:\n\nReporting to the Head of Metering, the appointee will mainly perform the following responsibilities:\n\n\nTo oversee the administration and operations of a team, prepare capital and revenue budgets and control expenditures, and formulate strategies to cope with the changing rules and legislations as well as technical advancement\nTo supervise the team to handle meter asset management works including planning, evaluation, inspection, testing, procurement, housekeeping and scrapping of the meters\nTo lead the team to develop, integrate, test and commission of various Advanced Metering Infrastructure (AMI) metering related systems, e.g. Field Area Network design, Head-End system, Meter Data Management (MDM) System and Network Management System (NMS)\nTo design, plan and manage metering installations in relation to Remote Meter Reading (RMR) / AMI communications\n\nRequirements:\n\n\nBachelor Degree in Electrical Engineering, Electronics Engineering or related disciplines with Corporate Membership of HKIE\nA minimum of 10 years\u2019 relevant work experience, of which with at least 4 years\u2019 in supervisory level\nFamiliar with local and international regulations related to tariff meters, metering principles, meter system design and meter technologies\nKnowledge of and experience in Advanced Metering Infrastructure, smart meter deployment, ISO Management Systems and 5S Good Housekeeping preferred\nGood command of English and Chinese languages, both spoken and written\nHolder of a valid driving license for Class 1 vehicle an advantage\n\nCandidate with qualification leading to Corporate Membership of HKIE or less relevant experience may also be considered for the position of Meter Asset Management Engineer I.\n\n\nWorking Location: North Point\n\n\nApplication:\n\nIf you are interested in this position, please send your resume\u00a0(in PDF format)\u00a0with details of qualification, experience, present and expected salary, and contact number to the Human Resources Division, The Hongkong Electric Co., Ltd. on or before 31 January 2022\u00a0and quote the reference number in your application. Please also visit our website to know more about our Company http://www.hkelectric.com.\n\nApplicants not invited for interview within\u00a0one month from the closing date may consider their applications unsuccessful. All unsuccessful applications will be kept for\u00a0six months after the date of this advertisement.\n\nWe are an equal opportunity employer.\u00a0 Personal data provided by job applicants will be treated in strictest confidence and used only for recruitment-related purposes in accordance with the laws and ordinance of the HKSAR.", "employment_types": ["Full Time", "Permanent"], "selling_points": ["To oversee the administration and operations", "Bachelor Degree in Electrical Engineering", "A minimum of 10 years\u2019 relevant work experience"], "locations": ["North Point"], "categories": ["Engineering", "Electrical / Electronics", "Engineering Project Management", "Others"], "post_time": "2022-01-17T04:13:15Z", "salary": {"currency": null, "max": null, "min": null, "period": "monthly", "term": null}, "salary_visible": false, "title_keywords": ["engineer", "asset management"], "responsibilities": ["data", "operations", "oversee the administration", "design", "plan", "evaluation", "control", "infrastructure", "testing", "develop", "legislations", "reporting", "management", "inspection", "budgets", "housekeeping", "systems", "asset management", "planning"], "requirements": {"degrees": ["degree", "bachelor"], "majors": ["related disciplines", "engineering", "electrical engineering"], "languages": ["english", "chinese"], "language_level": ["good command"], "hard_skills": ["system design", "hkie", "deployment"], "soft_skills": ["confidence", "interested in", "advanced"], "languages_combined": [{"language": "english", "language_level": ["good command"]}, {"language": "chinese", "language_level": ["good command"]}]}, "experience_required": {"duration": ["at least 4 years", "minimum of 10 years"], "field": ["management", "infrastructure", "relevant experience", "supervisory level", "human resources", "asset management"]}}, {"job_id": "100003009027332", "location_code": "hk", "company": "Ching Lee Engineering Limited", "job_title": "ASSISTANT ENGINEERS", "description": "Requirements:\nDegree holder in Civil Engineering / Structural / Geological Engineering or above.\nMinimum 2 years solid experience in site supervision and project management in site formation & foundation works.\nGood understanding of Building Ordinance, BD\u2019s control mechanism in design & supervision of Building works, Structural works.\nAble to work independently, self-motivated and responsible.\nProficiency in English and Chinese language.\nResponsibilities:\n\u00a0Response for coordination with the project engineering team in handling the supervision and monitoring of ongoing projects, provision of technical supports and liaising with consultants on construction projects.\n\u00a0Interested candidate, please send your full resume, expected salary and contact number e-mail by clicking \"Apply now\"\u00a0", "employment_types": ["Full Time", "Permanent"], "selling_points": ["2 years solid experience in site supervision", "Good understanding of Building Ordinance", "Response for coordination with the project engin"], "locations": ["Not Specified"], "categories": ["Engineering", "Engineering Project Management", "Mechanical", "Others"], "post_time": "2022-01-16T21:50:08Z", "salary": {"currency": null, "max": null, "min": null, "period": "monthly", "term": null}, "salary_visible": false, "title_keywords": ["assistant"], "responsibilities": ["technical supports", "monitoring", "coordination with", "liaising with", "contact"], "requirements": {"degrees": ["degree holder"], "majors": ["engineering", "civil engineering"], "languages": ["english", "chinese"], "language_level": ["proficiency"], "hard_skills": ["project management"], "soft_skills": ["project management", "work independently", "self-motivated", "responsible"], "languages_combined": [{"language": "english", "language_level": ["proficiency"]}, {"language": "chinese", "language_level": ["proficiency"]}]}, "experience_required": {"duration": ["minimum 2 years"], "field": ["project management"]}}, {"job_id": "100003009053647", "location_code": "hk", "company": "Arup", "job_title": "Resident Engineer", "description": "Qualifications & Experience required:\n\n\nDegree in Civil/Geotechnical/Structural engineering or related discipline\nRecognized engineering chartered qualification with 2 years of post-chartered experience\nFamiliar with common practice in foundation, site formation, reinforced concrete and structural steel construction for private development projects\nBe adaptable and able to work independently with strong interpersonal skills\nProficient in both written and spoken English and Chinese\n\n\n\nThe above positions based in Macau will be on contract basis to work on a big building project. The contract is approximately 12 months which may be lengthened or shortened subject to project development. Standard working hours will be 6 days per week, shift work may be required. Attractive remuneration package with gratuity will be offered to the successful candidate.\n\nFor interested applicants, please click \"Apply Now\" \u00a0to submit your online application.\nTo explore more job opportunities in Arup, please visit our website at http://www.arup.com/Careers/Experienced_Hires/ApplyForAJob\n\u00a0\nPersonal data collected will be used for recruitment purpose only. Applicants not contacted within 8 weeks may consider their applications unsuccessful.", "employment_types": ["Full Time", "Contract"], "selling_points": [], "locations": ["Others - Macau"], "categories": ["Building & Construction", "Civil / Structural", "Engineering", "Others", "Others"], "post_time": "2022-01-17T07:17:54Z", "salary": {"currency": null, "max": null, "min": null, "period": null, "term": null}, "salary_visible": false, "title_keywords": ["resident engineer"], "responsibilities": ["personal data", "recruitment", "website"], "requirements": {"degrees": ["degree"], "majors": ["structural engineering"], "languages": ["english", "chinese"], "language_level": ["proficient"], "hard_skills": [], "soft_skills": ["adaptable", "work independently", "interpersonal skills"], "languages_combined": [{"language": "english", "language_level": ["proficient"]}, {"language": "chinese", "language_level": ["proficient"]}]}, "experience_required": {"duration": ["2 years"], "field": ["engineering"]}}, {"job_id": "100003009055743", "location_code": "hk", "company": "KOS International Limited", "job_title": "Building Services Engineer (Main Contractor)", "description": "Job Description\n\nAbout our client\n\nOur client is a leading main contractor with a stable project pipeline in Hong Kong. To cope with its business growth, they are looking for a high caliber Building Services Engineer to join.\n\nAbout the role\n\nKeep track on design issuance with consultants according to agreed timeline\nIdentify design problem and liaise with consultants on alternatives\nCoordinate with sub-contractor on site progress and provide technical advice\nEstablish and monitor schedule for submission of CSD, CBW, drawings and material samples\nPerform site inspection and project meetings to monitor the quality and safety standard of the installation\n\n\nThe successful applicants\n\nDegree holder or above in Building Services / Mechanical / Electrical Engineering or related disciplines\n3 years of experience in Main Contractor or Consultant\nProfessional qualification (e.g. MHKIE, MCIBSE, MIMech or equivalent) is preferred", "employment_types": ["Full Time", "Permanent"], "selling_points": ["Degree holder in Building Services or equivalent", "Main Contractor", "Minimum 3 years of relevant experience"], "locations": ["Not Specified"], "categories": ["Engineering", "Electrical / Electronics", "Mechanical", "Others"], "post_time": "2022-01-18T02:54:47Z", "salary": {"currency": null, "max": null, "min": null, "period": "monthly", "term": null}, "salary_visible": false, "title_keywords": ["building services engineer"], "responsibilities": ["installation", "technical advice", "monitor", "coordinate with", "design", "drawings", "site inspection", "quality", "schedule", "liaise with consultants"], "requirements": {"degrees": ["degree holder"], "majors": ["related disciplines", "building services", "electrical engineering"], "languages": [], "language_level": [], "hard_skills": ["mhkie"], "soft_skills": ["stable"], "languages_combined": []}, "experience_required": {"duration": ["3 years"], "field": []}}, {"job_id": "100003009053576", "location_code": "hk", "company": "Chef Works Sourcing Limited", "job_title": "Textile In-House Laboratory Technician (5 Days work)", "description": "\nJob Highlights\n\u2022 5 Days work week\n\u2022 Bank holiday\n\u2022 Double pay\n\u2022 Medical insurance\n\u2022 Performance bonus\nJob duties / Responsibilities:\n\u2022 Responsible in routine testing of Garment, Fabric, Trims.\n\u2022 Handle all textile documents and administrative processes related to textile testing.\n\u2022 Review the lab test reports from 3rd party laboratory and fabric mills as per company testing manual.\n\u2022 Monitor In-House Laboratory operation\n\u2022 Maintain quality of work to ensure that all jobs can meet client\u2019s requirement.\n\u2022 Follow supervisor\u2019s instruction to meet daily operation\u2019s target time.\n\u2022 Help to perform sample preparation, breakdown and cutting.\n\u2022 Assist in monitoring daily report status and upload test reports into the PLM system.\n\u2022 Finish required work within designated turnaround time and the candidate can multi-task.\n\u2022 Collaborate with 3rd party Laboratory to ensure all jobs and results delivered on schedule.\n\u2022 Work closely with the USA team.\nRequirements:\n\u2022 Diploma or above in Textiles or any related discipline.\n\u2022 With 2 years relevant experience is preferable.\n\u2022 Good computer knowledge of Excel, Word, Outlook, PowerPoint.\nProficiency in English, Chinese and Mandarin (Spoken and Written).\n\u2022 A team player with good communications skills.\n\u2022 Able to learn and work under pressure, willing to work overtime and work independently.\n\u2022 Responsible and hardworking with positive attitude.\n\u2022 Immediately availability is an advantage\n\n", "employment_types": ["Full Time"], "selling_points": [], "locations": ["Not Specified"], "categories": ["Engineering", "Others", "Others", "Technician"], "post_time": "2022-01-17T07:11:32Z", "salary": {"currency": null, "max": null, "min": null, "period": "monthly", "term": null}, "salary_visible": false, "title_keywords": ["laboratory technician"], "responsibilities": ["collaborate with", "maintain quality", "sample preparation", "review", "monitor", "daily operation", "monitoring", "testing", "reports", "schedule", "daily report", "administrative processes"], "requirements": {"degrees": ["diploma or above"], "majors": [], "languages": ["english", "chinese", "mandarin"], "language_level": ["proficiency"], "hard_skills": ["excel", "outlook", "word", "powerpoint"], "soft_skills": ["work overtime", "work independently", "responsible", "positive attitude", "team player", "hardworking", "work under pressure"], "languages_combined": [{"language": "english", "language_level": ["proficiency"]}, {"language": "chinese", "language_level": ["proficiency"]}, {"language": "mandarin", "language_level": ["proficiency"]}]}, "experience_required": {"duration": ["2 years"], "field": ["relevant experience"]}}, {"job_id": "100003009037273", "location_code": "hk", "company": "The Jardine Engineering Corporation Ltd", "job_title": "Site Safety Supervisor", "description": "Responsibilities:\n\nMonitor the site to ensure that all works are carried out effectively and in a safe manner;\nPrepare technical reports and other documents as required;\nCoach and supervise subordinates;\nProvide solutions to technical problems encountered;\nWork location: Shek Wu Hui (Sheung Shui);\n1-year Contract.\n\nRequirements:\n\nCertificate from Construction Industry Council in Hong Kong / Hong Kong Institute of Construction /\u00a0Hong Kong Institute of Vocational Education / technical institute / technical college / Hong Kong Polytechnic University / Polytechnic or equivalent\u00a0 in\u00a0 related disciplines;\nCompletion of Construction Safety Supervisor course by\u00a0Construction Industry Council;\nMinimum 2 years\u2019 relevant experience;\nStrong interpersonal skill with good command of English & Chinese.\n\nWe offer attractive salary and fringe benefits package to the successful candidate.\u00a0 Apply now with full resume including current and expected salary, date available to the Manager - Human Capital, The Jardine Engineering Corporation Limited, 5/F, Tower A, Manulife Financial Centre, 223\u2013231 Wai Yip Street, Kwun Tong, Kowloon, Hong Kong\u00a0or by fax to\u00a028879516.\u00a0(Please quote reference no. in your application letter).\u00a0\n\nFor more information about our company, please visit our website :\u00a0www.jec.com\n\nPersonal data provided by job applicants will be used strictly in accordance with the company's personal data policies, a copy of which will be provided immediately upon request.", "employment_types": ["Full Time", "Contract"], "selling_points": ["Site", "Safety Supervisor", "Safety"], "locations": ["Sheung Shui"], "categories": ["Engineering", "Others"], "post_time": "2022-01-11T02:16:51Z", "salary": {"currency": null, "max": null, "min": null, "period": "monthly", "term": null}, "salary_visible": false, "title_keywords": ["safety supervisor"], "responsibilities": ["provide solutions", "monitor", "reports"], "requirements": {"degrees": [], "majors": [], "languages": [], "language_level": [], "hard_skills": [], "soft_skills": [], "languages_combined": []}, "experience_required": {"duration": [], "field": []}}, {"job_id": "100003009052281", "location_code": "hk", "company": "Wo Lee Group (Holding) Company Limited", "job_title": "Project Sale (Innovative Building Materials)", "description": "Responsibilities:\n\n\nDevelop market share & sourcing new clients\nEngage in construction projects' tender & quotation\nAnalysis sale & market trend of company's building materials\nInternal & external site visit & meeting with clients\nProvide professional sale solutions to our clients\u00a0\u00a0\n\nRequirements:\n\n\n2 years or above related sales experience\nKnowledge in building materials or steel products\u00a0 \u00a0\nRelated construction industry experience preferred\nGood interpersonal skill & problem solving ability, well known clients' need\nAbility to communicate in English & Putonghua\nFamiliar in MS Office\u00a0\nDetailed job scope will be discussed during the interview and is subject to candidate\u2019s experience and qualifications.\u00a0\nPotential candidates\u00a0please apply\u00a0with full resume\u00a0indicating\u00a0present\u00a0and expected salary, employment\u00a0history\u00a0to\u00a0the Human Resources Department.\nPersonal data collected will be used for recruitment purpose only and will be kept strictly confidential.\u00a0\u00a0Unsuccessful applications will be destroyed after an appropriate time.", "employment_types": ["Full Time", "Permanent"], "selling_points": ["Project Sale - Building Materials", "Construction / Engineering", "Construction Project Sale"], "locations": ["Mong Kok"], "categories": ["Building & Construction", "Building / Construction / QS", "Engineering", "Others", "Sales, CS & Business Devpt", "Technical Sales / Sales Engineer"], "post_time": "2022-01-17T02:38:54Z", "salary": {"currency": null, "max": null, "min": null, "period": "monthly", "term": null}, "salary_visible": false, "title_keywords": [], "responsibilities": ["analysis", "quotation", "tender", "develop"], "requirements": {"degrees": [], "majors": [], "languages": ["putonghua", "english"], "language_level": [], "hard_skills": ["problem solving", "ms office"], "soft_skills": ["problem solving", "detailed", "interpersonal skill"], "languages_combined": [{"language": "putonghua", "language_level": []}, {"language": "english", "language_level": []}]}, "experience_required": {"duration": ["2 years"], "field": ["related", "construction industry"]}}, {"job_id": "100003009055105", "location_code": "hk", "company": "Autotoll Limited", "job_title": "Project Administrator", "description": "About The Role:\n\nAssist the project team for any contract administrative support and document submission\nHandle routine administrative works for project implementation\nAssist in issuing any procurement, payment related document including issuing purchase order, payment requisition form, payment notice, etc.\n\nAbout You:\n\nAt lease 2years relevant experience in project administration\n\n\n\nWhat you can get from us:\n\nOn-the-job training, learning and development\u00a0provided\nExecutive workshops, interest class, corporate purchase discount offered by SHKP\nCompetitive salary and annual leaves\nFlexible working opportunities\n\nInterested parties, please send full resume with\u00a0expected salary\u00a0and\u00a0available date\u00a0to Human Resources and Administration Department by e-mail or by fax 2111 9459.\n\n(Data collected will be used for recruitment purpose only.)", "employment_types": ["Full Time", "Permanent"], "selling_points": ["5 days work", "12 days annual leave", "flexible working hour"], "locations": ["Kowloon Bay"], "categories": ["Engineering", "Others"], "post_time": "2022-01-18T01:15:13Z", "salary": {"currency": null, "max": null, "min": null, "period": "monthly", "term": null}, "salary_visible": false, "title_keywords": ["project administrator"], "responsibilities": ["administrative support", "implementation", "payment", "purchase", "project administration"], "requirements": {"degrees": [], "majors": [], "languages": [], "language_level": [], "hard_skills": ["workshops"], "soft_skills": ["flexible", "learning"], "languages_combined": []}, "experience_required": {"duration": [], "field": ["relevant experience", "administration"]}}, {"job_id": "100003009051754", "location_code": "hk", "company": "POWERCO Electric (Far East) Company Limited", "job_title": "Assistant Engineer / Engineer", "description": "-\u00a0 \u00a0 \u00a0 Diploma / Degree in Electrical and Mechanical Engineering\n\n-\u00a0\u00a0\u00a0\u00a0\u00a0 1-2 years relevant working experiences.\n\n-\u00a0\u00a0\u00a0\u00a0\u00a0 Knowledge in AutoCad and Microsoft Office\n\n-\u00a0\u00a0\u00a0\u00a0\u00a0 Good command of both spoken and written English and Chinese\n\nWe offer attractive salary and medical insurance.\u00a0 Interested parties please send full resume with current and expected salary email by clicking apply now\n", "employment_types": ["Full Time", "Permanent"], "selling_points": ["Diploma / Degree in E&M Engineering", "1-2 years relevant working experience", "Knowledge in AutoCad and Microsoft Office"], "locations": ["Shatin Area"], "categories": ["Engineering", "Electrical / Electronics", "Mechanical", "Others"], "post_time": "2022-01-17T00:28:45Z", "salary": {"currency": null, "max": null, "min": null, "period": "monthly", "term": null}, "salary_visible": false, "title_keywords": ["assistant engineer", "engineer"], "responsibilities": [], "requirements": {"degrees": ["diploma", "degree"], "majors": ["mechanical engineering"], "languages": ["english", "chinese"], "language_level": ["good command"], "hard_skills": ["microsoft office", "autocad"], "soft_skills": [], "languages_combined": [{"language": "english", "language_level": ["good command"]}, {"language": "chinese", "language_level": ["good command"]}]}, "experience_required": {"duration": ["1-2 years"], "field": []}}, {"job_id": "100003009049726", "location_code": "hk", "company": "Shun Cheong Works Limited", "job_title": "\u9ad8\u7d1a\u6280\u8853\u54e1", "description": "\n\u8077\u8cac :\u8ca0\u8cac\u96fb\u529b\u5b89\u88dd,\u7dad\u4fee\u53ca\u6e2c\u8a66\u5de5\u4f5c,\u9700\u5916\u52e4\u5de5\u4f5c\n\n\u8cc7\u6b77 :\u5c08\u4e0a\u6559\u80b2\uff1a\u6587\u6191/\u8b49\u66f8; 5\u5e74\u7d93\u9a57; \u826f\u597d\u7cb5\u8a9e; \u4e00\u822c\u666e\u901a\u8a71; \u4e00\u822c\u82f1\u8a9e; \u61c2\u8b80\u5beb\u4e2d\u6587; \u7565\u61c2\u8b80\u5beb\u82f1\u6587; \u6301\u6709\u96fb\u5de5B\u724c\u6216\u4ee5\u4e0a, \u6301\u6709\u96fb\u6a5f\u5de5\u7a0b\u8b49\u66f8\u6216\u5c4b\u5b87\u88dd\u5099\u6587\u6191\u6216\u4ee5\u4e0a, 5\u5e74\u6216\u4ee5\u4e0a\u76f8\u95dc\u7d93\u9a57\n\n\u5f85\u9047 :\u6bcf\u6708$25,000 - $33,000, \u661f\u671f\u4e00\u81f3\u516d: \u4e0a\u53489\u6642\u81f3\u4e0b\u53486\u6642, \u6bcf\u9031\u5de5\u4f5c6\u5929\n\n\u7533\u8acb\u9808\u77e5 :\u6c42\u8077\u8005\u53ef\u50b3\u771f(21454291)\u6216\u96fb\u90f5(Apply Now)\u5c65\u6b77\u8868\u7d66\u4fe1\u660c\u96fb\u5668\u5de5\u7a0b\u6709\u9650\u516c\u53f8\u3002\u5982\u8981\u7d22\u53d6\u6536\u96c6\u500b\u4eba\u8cc7\u6599\u8072\u660e, \u8acb\u8207\u9ec3\u5c0f\u59d0(Fax/Email)\u806f\u7d61\u3002\n\n", "employment_types": ["Full Time"], "selling_points": [], "locations": ["Not Specified"], "categories": ["Engineering", "Others", "Others", "Technician"], "post_time": "2022-01-14T09:10:07Z", "salary": {"currency": null, "max": null, "min": null, "period": "monthly", "term": null}, "salary_visible": false, "title_keywords": [], "responsibilities": [], "requirements": {"degrees": [], "majors": [], "languages": [], "language_level": [], "hard_skills": [], "soft_skills": [], "languages_combined": []}, "experience_required": {"duration": [], "field": []}}, {"job_id": "100003009052382", "location_code": "hk", "company": "J&D Holdings Limited", "job_title": "\u7dad\u4fee\u4e2d\u5de5/\u7dad\u4fee\u5e2b\u5085", "description": "\u8077\u8cac:\n\u8ca0\u8cac\u5ee0\u623f\u8a2d\u65bd\u7dad\u4fee\u53ca\u4fdd\u990a\u5de5\u4f5c\uff0c\u5305\u62ec\u51b7\u6c23\u3001\u6c34\u96fb\u53ca\u7dca\u6025\u652f\u63f4\n\u8ca0\u8cac\u5206\u5e97\u5b89\u88dd\u53ca\u7dad\u4fee\u4fdd\u990a\u5eda\u623f\u96fb\u5668\u5de5\u4f5c\n\u9700\u586b\u5831\u65e5\u5e38\u7dad\u4fee\u5831\u544a\u7d00\u9304\u3001\u5e97\u8216\u51fa\u52e4\u7d00\u9304\u53ca\u5c0d\u627f\u5224\u5546\u8aaa\u660e\u3001\u5354\u8abf\u53ca\u8ddf\u9032\u5de5\u4f5c\n\u9700\u8ca0\u8cac\u65e5\u5e38\u7684\u7dad\u4fee\u7269\u6599\u5099\u91cf\u53ca\u6709\u95dc\u5009\u5b58\u6574\u7406\u5b89\u6392\n\u9700\u8f2a\u4f11/\u5916\u52e4\u5de5\u4f5c\n\n\u7dad\u4fee\u4e2d\u5de5\n\n\u6708\u85aa:$15,000-$18,000 (\u5e74\u5047 12-18\u65e5)\n\n\u7dad\u4fee\u5e2b\u5085\n\n\u6708\u85aa:$20,000-$24,000 (\u5e74\u5047 12-18\u65e5)\n\n\u5165\u8077\u8981\u6c42:\n\u4e2d\u5b78\u7a0b\u5ea6\u6216\u6301\u6709\u5de5\u696d\u5b78\u9662\u6280\u8853\u8a3c\u66f8\u6216\u540c\u7b49\u6280\u80fd\u8a3c\u66f8\n\u6709\u8a3b\u518a\u96fb\u5de5A\u724c\n\u53ef\u5373\u6642\u4e0a\u73ed\u8005\u512a\u5148\u8003\u616e\n\n\u5168\u8077\u54e1\u5de5\u798f\u5229\uff1a\n\u2022\u5de5\u4f5c\u6642\u9593\uff1a\u4e0a\u53489:00-\u4e0b\u53486:00\u6216\u4e0b\u53482:00-\u4e0b\u534811:00\n\u2022\u514d\u8cbb\u81b3\u98df\n\u2022\u63d0\u4f9b\u5b8c\u5584\u5728\u8077\u57f9\u8a13\u3001\u826f\u597d\u6649\u5347\u6a5f\u6703\n\u2022\u984d\u5916\u5047\u671f (\u751f\u65e5\u5047\u3001\u4f8d\u7522\u5047\u3001\u6069\u6064\u5047\u3001\u5a5a\u5047)\n\u2022\u5e74\u7d42\u82b1\u7d05\n\u2022\u91ab\u7642\u798f\u5229\n\u2022\u9032\u4fee\u6d25\u8cbc\n\n\u6709\u610fWhatsapp/Wechat\uff1a5918 1693\nhttps://bit.ly/3zF6xoQ\n-\n\nWe offer competitive remuneration and benefit packages to the right candidate. Interested parties please click\u00a0Apply Now\u00a0button and also submit your application letter, resume with expected salary and availability.\n\nWe are an equal opportunity employer and welcome applications from all qualified candidates. The information provided will be treated in strict confidence and be used only for consideration of your application for relevant / similar posts within the J&D Holdings Limited. Applicants not hearing from us within four weeks from the date of advertisement may consider their applications unsuccessful.", "employment_types": ["Full Time"], "selling_points": [], "locations": ["Not Specified"], "categories": ["Engineering", "Others", "Others", "Technician"], "post_time": "2022-01-17T02:54:24Z", "salary": {"currency": null, "max": null, "min": null, "period": "monthly", "term": null}, "salary_visible": false, "title_keywords": [], "responsibilities": [], "requirements": {"degrees": [], "majors": [], "languages": [], "language_level": [], "hard_skills": [], "soft_skills": [], "languages_combined": []}, "experience_required": {"duration": [], "field": []}}, {"job_id": "100003009054567", "location_code": "hk", "company": "Shun Shing Contractors Limited", "job_title": "Quantity Surveyor / Estimators", "description": "Job Responsibilities:\n\nDirectly reporting to the QS Director\nAct as the Main Contractor to independently supervise domestic sub-contractors and various Nominated Sub-Contractors (NSC) in respect of all QS matters\nPrepare cost estimates for bidding of tenders\nIndependently carry out building contract administration such as the valuation of variations, preparation of Notification of Delays (NODs) for extension of time, the valuation of Loss and Expense and the preparation of Interim Payments and Final Account\nLiaise with Client, Architect and various Consultants\nManage the ordering of materials, in particular those require long lead-time. Managing Sub-contractors / Nominated Sub-contractors. Inspect works for interim payment applications\n\nRequirement:\n\nDegree / Master Degree in QS or Construction Management\nProfessional Corporate Member of the Hong Kong Institute of Surveyors (HKIS) Quantity Surveying Division, or Chartered Quantity Surveyor (MRICS)\nMinimum 10 years solid post-qualification working experience\nHands-on site experience is essential\nGood knowledge of local Building Regulations as well as other utility regulation requirements\nconversant in using computer-aided-design, excel and powerpoint\nGood command of spoken and written Chinese and English\nSelf-motivated, energetic and composed team player\n\nWe offer attractive remuneration package with comprehensive fringe benefits to the right candidate.\u00a0 The incumbent will become part of the in-house project management team which consists of authorized person, qualified quantity surveyor and other construction professional.\n\n\nFor those who slightly fall short of the requirements mentioned hereinabove, we may consider them for the post of \u201cAssistant Quantity Surveyor I\u201d.", "employment_types": ["Full Time"], "selling_points": [], "locations": ["Kwun Tong"], "categories": ["Building & Construction", "Building / Construction / QS", "Engineering", "Others", "Others"], "post_time": "2022-01-17T10:03:01Z", "salary": {"currency": null, "max": null, "min": null, "period": "monthly", "term": null}, "salary_visible": false, "title_keywords": ["quantity surveyor"], "responsibilities": ["reporting", "cost", "valuation", "contract administration", "payment", "liaise with client", "payments"], "requirements": {"degrees": ["degree", "master degree"], "majors": ["construction management"], "languages": ["english", "chinese"], "language_level": ["good command"], "hard_skills": ["powerpoint", "excel", "the hong kong institute of surveyors", "hkis"], "soft_skills": ["hands-on", "energetic", "team player", "self-motivated"], "languages_combined": [{"language": "english", "language_level": ["good command"]}, {"language": "chinese", "language_level": ["good command"]}]}, "experience_required": {"duration": ["minimum 10 years"], "field": ["post-qualification"]}}, {"job_id": "100003009055328", "location_code": "hk", "company": "Computime Ltd", "job_title": "Senior Software Engineer / Engineer \u2013 IoT Platform", "description": "Major Responsibilities\n\nResponsible for IoT cloud development and maintenance\nDevelop IoT cloud service to support all internet connected product across the company\nDefine cloud software architecture and application interface\nCollaborate with another team member to develop and enhance the IoT platform\n\nRequirements\n\nDegree or above in Computer Science or related discipline\n2+ programming experience with Python or JavaScript.\nExperience in AWS platform and AWS Micro-Service development (such as Lambda)\nFamiliar with network protocol, such as HTTP, TCP/IP, MQTT, WebSocket is an advantage\nExperience with software management tools, such as Jira, Confluence, Github\nGood command of spoken and written Chinese and English, Mandarin is an advantage\nLess experienced or fresh graduate can also be considered\n\nInterested parties, please apply together with a detailed resume, stating current and expected salary, and send it via APPLY NOW.\u00a0 Attractive remuneration will be offered in commensurate with qualification and experience.\u00a0\n\nAll personal information received will be treated in strict confidence for employment purpose only.\u00a0 Your application can be considered as unsuccessful if you have not been reached within 3 months.\u00a0 On the other hand, it may be transferred to other companies of our group for job openings.\u00a0 Unsuccessful applications will be destroyed for a period not more than 12 months.\u00a0\n\nhttps://www.computime.com/\nhttps://salus-controls.com/", "employment_types": ["Full Time", "Permanent"], "selling_points": ["5 days work, double pay, and free shuttle coach", "IoT cloud development and maintenance", "Experience in AWS platform and AWS Service"], "locations": ["Shatin Area"], "categories": ["Engineering", "Others", "Information Technology (IT)", "Application Specialist - Software", "Software Development"], "post_time": "2022-01-18T02:12:47Z", "salary": {"currency": null, "max": null, "min": null, "period": "monthly", "term": null}, "salary_visible": false, "title_keywords": ["senior software engineer", "engineer"], "responsibilities": ["collaborate with", "software", "maintenance", "develop", "architecture"], "requirements": {"degrees": ["degree or above", "fresh graduate"], "majors": ["computer science"], "languages": ["english", "chinese", "mandarin"], "language_level": ["advantage", "good command"], "hard_skills": ["tcp", "aws", "ip", "javascript", "programming", "python"], "soft_skills": [], "languages_combined": [{"language": "english", "language_level": ["advantage", "good command"]}, {"language": "chinese", "language_level": ["advantage", "good command"]}, {"language": "mandarin", "language_level": ["advantage", "good command"]}]}, "experience_required": {"duration": [], "field": ["development", "management", "programming"]}}, {"job_id": "100003009048231", "location_code": "hk", "company": "Glory Place Limited", "job_title": "\u96fb\u8166\u6280\u8853\u54e1 (\u9589\u8def\u96fb\u8996\u53ca\u9580\u7981\u7cfb\u7d71)", "description": "\n\u8077\u8cac :\u63d0\u4f9b\u9589\u8def\u96fb\u8996\u53ca\u9580\u7981\u7cfb\u7d71\u4e4b\u6280\u8853\u652f\u63f4,\u8a2d\u5b9a\u53ca\u652f\u63f4\u9589\u8def\u96fb\u8996, \u9580\u7981\u7cfb\u7d71\u53ca\u76f8\u95dc\u4fdd\u5b89\u7cfb\u7d71,\u6709\u9700\u8981\u63d0\u4f9b\u5230\u5834\u7dad\u4fee\u670d\u52d9\n\n\u8cc7\u6b77 :\u5c0f\u4e94\u7a0b\u5ea6; 1\u5e74\u7d93\u9a57; \u826f\u597d\u7cb5\u8a9e\u512a\u5148; \u4e00\u822c\u666e\u901a\u8a71; \u4e00\u822c\u82f1\u8a9e; \u61c2\u8b80\u5beb\u4e2d\u6587; \u7565\u61c2\u8b80\u5beb\u82f1\u6587; \u6709\u8cac\u4efb\u5fc3\u53ca\u9858\u610f\u63a5\u53d7\u6311\u6230,self-motivated\n\n\u5f85\u9047 :\u6bcf\u6708$14,000 - $16,000, \u6709\u624b\u63d0\u96fb\u8a71\u6d25\u8cbc \u53ca\u4ea4\u901a\u6d25\u8cbc, \u661f\u671f\u4e00\u81f3\u4e94: \u4e0a\u53489\u6642\u81f3\u4e0b\u53486\u6642\u53ca\u661f\u671f\u516d: \u4e0a\u53489\u6642\u81f3\u4e0b\u53481\u6642, \u6bcf\u9031\u5de5\u4f5c5\u5929\u534a\n\n\u7533\u8acb\u9808\u77e5 :\u6c42\u8077\u8005\u53ef\u96fb\u90f5(Apply Now)\u5c65\u6b77\u8868\u7d66GLORY PLACE LIMITED\u3002\u5982\u8981\u7d22\u53d6\u6536\u96c6\u500b\u4eba\u8cc7\u6599\u8072\u660e, \u8acb\u8207\u6797\u5c0f\u59d0(Email)\u806f\u7d61\u3002\n\n", "employment_types": ["Full Time"], "selling_points": [], "locations": ["Not Specified"], "categories": ["Engineering", "Others", "Others", "Technician"], "post_time": "2022-01-14T05:59:24Z", "salary": {"currency": null, "max": null, "min": null, "period": "monthly", "term": null}, "salary_visible": false, "title_keywords": [], "responsibilities": [], "requirements": {"degrees": [], "majors": [], "languages": [], "language_level": [], "hard_skills": [], "soft_skills": ["self-motivated"], "languages_combined": []}, "experience_required": {"duration": [], "field": []}}, {"job_id": "100003009055109", "location_code": "hk", "company": "Autotoll Limited", "job_title": "Engineer", "description": "About The Role:\n\nAssist in Project, Implementation, Test and Commissioning\nAssist in daily operation and monitor system performance\u00a0\n\n\nAbout You:\n\nBachelor's degree or above in Electronics or Electrical Engineering\n3 years or above relevant experience\nProficient in AutoCAD and Microsoft Office\nObtain HKSAR driving license category 1 and 2 is an advantage\nGood communication skill, able to handle pressure\u00a0\n\nWhat you can get from us\n\nOn-the-job training, learning and development\u00a0provided\nExecutive workshops, interest class, corporate purchase discount offered by SHKP\nCompetitive salary and annual leaves\nFlexible working opportunities\n\nInterested parties, please send full resume with expected salary and available date to Human Resources and Administration Department by e-mail or by fax 2111 9459.\n\n(Data collected will be used for recruitment purpose only.)", "employment_types": ["Full Time", "Permanent"], "selling_points": ["Daily operation and monitor system performance", "3 years or above relevant experience", "Proficient in AutoCAD and Microsoft Office"], "locations": ["Kowloon Bay"], "categories": ["Engineering", "Electrical / Electronics", "Mechanical", "Others"], "post_time": "2022-01-18T01:15:15Z", "salary": {"currency": null, "max": null, "min": null, "period": "monthly", "term": null}, "salary_visible": false, "title_keywords": ["engineer"], "responsibilities": ["commissioning", "daily operation", "monitor", "implementation", "communication", "purchase"], "requirements": {"degrees": ["degree or above", "bachelor"], "majors": ["electrical engineering"], "languages": [], "language_level": [], "hard_skills": ["microsoft office", "workshops", "autocad"], "soft_skills": ["flexible", "communication skill", "learning"], "languages_combined": []}, "experience_required": {"duration": ["3 years"], "field": ["relevant experience"]}}, {"job_id": "100003009052411", "location_code": "hk", "company": "MVA Hong Kong Ltd", "job_title": "Draughtsman", "description": "Job Duties:\n\nSupport project team on project proposals and reports\nPrepare layout plans and drawings\nAny other duties that may be assigned from time to time by management\n\nJob Requirements\n\nCertificate/Diploma or above in engineering fields\nKnowledge in Micro-Station/AutoCAD/Revit\nSelf-motivated, responsible, and able to work under pressure\nGood command of English and Cantonese\nFresh Graduate will also be considered\n\nWe offer an attractive remuneration package with 5-day work week to the right candidate. Interested parties who are confident of fulfilling the above requirements can send us your most recent CV, detailing academic profile/ Transcript and work experiences, as well as current and expected salary packages by pressing \u201cApply Now\u201d.\n\nFor more details on MVA, please check our website at www.mvaasia.com\n\n\u00a0**Personal data collected will be used for recruitment purposes only**", "employment_types": ["Full Time"], "selling_points": [], "locations": ["Southern Area"], "categories": ["Engineering", "Others"], "post_time": "2022-01-17T02:58:54Z", "salary": {"currency": null, "max": null, "min": null, "period": "monthly", "term": null}, "salary_visible": false, "title_keywords": [], "responsibilities": ["any other duties", "management", "drawings", "reports", "plans"], "requirements": {"degrees": ["fresh graduate", "certificate", "diploma or above"], "majors": ["engineering"], "languages": ["cantonese", "english"], "language_level": ["good command"], "hard_skills": ["revit", "autocad"], "soft_skills": ["self-motivated", "responsible", "work under pressure"], "languages_combined": [{"language": "cantonese", "language_level": ["good command"]}, {"language": "english", "language_level": ["good command"]}]}, "experience_required": {"duration": [], "field": []}}, {"job_id": "100003009054822", "location_code": "hk", "company": "Avantec Manufacturing Ltd", "job_title": "Electronics Engineer(IoT)", "description": "\u00a0Requirement:\n\nProficient in C and/or assembly language\nDegree holder in Computer Science, Computer Engineering, I.T., Electronics Engineering\nFamiliar with embedded Linux product development environment\nSolid experience in sensor, thermostat and/or HVAC hardware design\n\nKnowledge in MSTP, networking, SIP protocol stack is a plus but not required\n\nProduct scope (A)\n\n\nnetworked sensors, wireless and wired room climatic control\nAWS\nPLC\n\nProduct scope (B)\n\n\nVoIP\nembedded Linux\n\n\nJob description:\n\nProduct development from prototyping, customizing user features, to debugging, field tests and production optimization.", "employment_types": ["Full Time"], "selling_points": [], "locations": ["Kwun Tong"], "categories": ["Engineering", "Electrical / Electronics", "Others"], "post_time": "2022-01-17T11:23:06Z", "salary": {"currency": null, "max": null, "min": null, "period": "monthly", "term": null}, "salary_visible": false, "title_keywords": [], "responsibilities": [], "requirements": {"degrees": ["degree holder"], "majors": ["computer engineering", "computer science"], "languages": [], "language_level": [], "hard_skills": ["linux", "plus", "assembly language", "hvac", "plc", "aws", "hardware", "c"], "soft_skills": [], "languages_combined": []}, "experience_required": {"duration": [], "field": ["design"]}}, {"job_id": "100003009051806", "location_code": "hk", "company": "Ensec Solutions Hong Kong Limited", "job_title": "Project Engineer", "description": "Responsible for design work, project planning, site supervision, commissioning and operation of ELV systems for Access Control , CCTV and Burglar Alarm System installations\nResponsible in project management\nSecurity system installation, programming, testing and commissioning\nConduct on-site system training to customer\nSystem trouble shooting and problem solving\nProviding technical support to Sales Department\nProvide service support on delivery and collection of equipment or parts to the customers whenever necessary\n\nRequirements\n\nDiploma / Certificate in Electronic / Electrical Engineering or Computer Engineering or other related Engineering discipline\nHolder of Security Personnel Permit (Cat. D) is an advantage\nAt least 2 years experience with security systems, such as CCTV, Access Control, Burglar Alarm, etc.\nProject management experience is an advantage\nGood knowledge of MS Office and AutoCAD\n\n\n\nRemuneration\n\nAttractive remuneration package includes 13 months salary will be offered to the right candidate. (5.5 working days per week)\n\nApply Method\n\nInterested? Please send your cover letter and resume in Word format with your availability, current and expected salary\u00a0by clicking \"Apply Now\".\n\nPersonal data collected will be used for recruitment purpose only.", "employment_types": ["Full Time", "Permanent"], "selling_points": ["Familiar with security system", "Project management", "Double pay, bonus, medical insurance etc."], "locations": ["Kwun Tong"], "categories": ["Engineering", "Electrical / Electronics", "Engineering Project Management", "Others"], "post_time": "2022-01-17T01:14:08Z", "salary": {"currency": null, "max": null, "min": null, "period": "monthly", "term": null}, "salary_visible": false, "title_keywords": ["project engineer"], "responsibilities": ["design work", "installation", "project planning", "commissioning", "site supervision", "technical support", "systems", "testing", "burglar alarm", "project management", "recruitment", "personal data", "access control"], "requirements": {"degrees": ["certificate", "diploma"], "majors": ["computer engineering", "electrical engineering", "engineering"], "languages": [], "language_level": [], "hard_skills": ["cctv", "security personnel permit", "word", "problem solving", "project management", "autocad", "programming", "ms office"], "soft_skills": ["problem solving", "project management", "responsible"], "languages_combined": []}, "experience_required": {"duration": ["at least 2 years"], "field": ["project management", "security"]}}, {"job_id": "100003009055081", "location_code": "hk", "company": "Newtech Management Services Ltd", "job_title": "Electrical Engineer (Electrical Design)", "description": "Responsibilities:\n\n\nHandling data center infrastructure design & technical support for projects, in-house design co-ordination and administration;\nPreparation of tender documentation, system specification and drawings;\nParticipate in electrical system design & process;\nProvide on-site technical support and verification, T&C etc.;\nPrepare feasibility report, design proposal, budgetary estimation, electrical design calculation, and tender bidding document for E&M projects.\nOther relevant assignments as specified by managers.\n\n\u00a0Requirements:\n\n\nDiploma / Higher\u00a0Diploma / Degree or above in Electrical Engineering or related disciplines;\n3-5 years' solid experience in\u00a0consulting firm / electrical contracting company;\nExperience in infrastructure design, such as, HV, LV, ELV, Genset system, UPS system, discrimination study etc.\nProficient in MS Office, Sketchup, AutoCAD or BIM, luminaire calculation software knowledge is preferable;\nHolder of relevant electrical license and with knowledge of using BIM & CFD will be an advantage;\nAble to work with tight schedules;\nSelf-motivated, self-disciplined, organized, detail-oriented and responsible;\nGood communication, interpersonal and problem-solving skills;\nAn attractive remuneration package and fringe benefits will be offered to the right candidate. Interested parties, please send your resume stating with current and expected salary to the Human Resources Department by clicking Apply Now.\n\n\nFor more information, please visit the corporate website at\u00a0www.newtechapac.com\n\nAll information collected will be kept strictly confidential and for recruitment purpose only.", "employment_types": ["Full Time"], "selling_points": [], "locations": ["Kowloon Bay"], "categories": ["Engineering", "Electrical / Electronics", "Engineering Project Management", "Others"], "post_time": "2022-01-18T01:11:43Z", "salary": {"currency": null, "max": null, "min": null, "period": "monthly", "term": null}, "salary_visible": false, "title_keywords": ["electrical engineer"], "responsibilities": ["data", "technical support", "infrastructure", "design", "drawings", "system design", "tender", "documentation", "report", "administration"], "requirements": {"degrees": ["diploma", "degree or above"], "majors": ["related disciplines", "electrical engineering"], "languages": [], "language_level": [], "hard_skills": ["sketchup", "bim", "problem-solving skills", "ms office", "autocad"], "soft_skills": ["organized", "self-motivated", "responsible", "detail-oriented", "communication", "problem-solving skills", "interpersonal"], "languages_combined": []}, "experience_required": {"duration": ["3-5 years"], "field": ["infrastructure", "consulting", "design"]}}, {"job_id": "100003009055106", "location_code": "hk", "company": "Autotoll Limited", "job_title": "Engineer (2 years Contract)", "description": "About The Role:\n\nLiaison with RMO and prepare documentation for application of roadworks advice\nAssist installation and maintenance works team for any documentation submissions\u00a0\nAssist in site operation in E&M Works\u00a0\n\nAbout You:\n\nHigh Diploma or above\u00a0\nAt least one year working experience in relevant field\nGood command written\u00a0spoken English & Chinese\nInitiative and hard working\u00a0\n\nWhat you can get from us:\n\nOn-the-job training, learning and development\u00a0provided\nExecutive workshops, interest class, corporate purchase discount offered by SHKP\nCompetitive salary and annual leaves\nFlexible working opportunities", "employment_types": ["Full Time", "Permanent"], "selling_points": ["Liaison with RMO and prepare documentation", "13 days annual leave", "5 days work, flexible working hour"], "locations": ["Kwai Fong"], "categories": ["Engineering", "Others", "Others", "Others"], "post_time": "2022-01-18T01:15:14Z", "salary": {"currency": null, "max": null, "min": null, "period": "monthly", "term": null}, "salary_visible": false, "title_keywords": ["engineer"], "responsibilities": ["documentation", "installation", "purchase", "maintenance"], "requirements": {"degrees": ["high diploma or above"], "majors": [], "languages": ["english", "chinese"], "language_level": ["good command"], "hard_skills": ["documentation", "workshops", "maintenance"], "soft_skills": ["flexible", "hard working", "learning", "initiative"], "languages_combined": [{"language": "english", "language_level": ["good command"]}, {"language": "chinese", "language_level": ["good command"]}]}, "experience_required": {"duration": ["at least one year"], "field": []}}, {"job_id": "100003009051813", "location_code": "hk", "company": "Hong Kong Applied Science and Technology Research Institute Company Limited (ASTRI)", "job_title": "ASIC Digital Development - Senior Lead Engineer/ Lead Engineer", "description": "Reference #:\u00a0CTO/CCT/02\nJob Responsibilities\nAssist in R&D project development\nConduct research in RISC-V architecture and Trusted Execution Environment\nCarry out logic design, module-level or top-level verification\nWork with the technical team to implement RISC-V SoC on FPGA\nCarry out firmware design to support ASIC/FPGA development\nWork with Software engineers to boot up RISC-V processor\n\u00a0\nRequirements\nPh.D. or Master holder in Computer Science, Electronic Engineering, Electrical Engineering, Information Engineering, IC Design or relevant disciplines with a minimum of 3 years of related experience\nExperience in HDL coding is highly preferred\nHands-on experience in IC design and verification is highly preferred\nExperience in processor integration and development is an advantage\nKnowledge on Trusted Execution Environment is an advantage\nExperience in FPGA prototyping and debugging is an advantage\nExcellent analytical and troubleshooting skills is highly preferred\nPassionate about new technology\nLive the ASTRI values\nApplication\n\n\nThe appointment will be on renewable contract terms with a competitive salary and performance-linked variable pay. Fringe benefits include paid leave, medical and dental benefits, insurance coverage and contribution to MPF. The incumbent will normally work\u00a0a five-day week.\n\nInterested candidates, please send an application (quoting Ref. No.) with a detailed resume, current and expected salary to\u00a0Talent Acquisition by clicking \"APPLY NOW\".\u00a0The resume should\u00a0not\u00a0include any sensitive personal information such as HKID or passport number, photo, etc.\u00a0\n\nPosition offer is subject to the applicant\u2019s experience and academic qualification. The application will be open until the position is filled. Only short-listed candidates will be notified. ASTRI reserves the right not to fill the position.\n\nASTRI is an Equal Opportunities Employer. Personal data provided by job applicants will be used\u00a0exclusively\u00a0for recruitment\u00a0only. For details, please refer to\u00a0Privacy - ASTRI - Hong Kong Applied Science and Technology Research Institute Company Limited, in particular section 9.", "employment_types": ["Full Time", "Contract"], "selling_points": ["ASIC Digital Development", "RISC-V architecture", "ASIC/FPGA development"], "locations": ["Shatin Area"], "categories": ["Engineering", "Electrical / Electronics", "Others", "Sciences, Lab, R&D", "Research & Development (R&D)"], "post_time": "2022-01-17T01:15:34Z", "salary": {"currency": null, "max": null, "min": null, "period": "monthly", "term": null}, "salary_visible": false, "title_keywords": ["engineer", "lead"], "responsibilities": ["conduct research", "software", "architecture", "design"], "requirements": {"degrees": ["master"], "majors": ["design", "engineering", "computer science", "electrical engineering"], "languages": [], "language_level": [], "hard_skills": ["integration"], "soft_skills": ["hands-on", "troubleshooting", "passionate about"], "languages_combined": []}, "experience_required": {"duration": ["minimum of 3 years"], "field": ["related", "development", "engineering", "design"]}}, {"job_id": "100003009053409", "location_code": "hk", "company": "TopChamp Technology Limited", "job_title": "\u98f2\u7528\u71b1\u6c34\u7210\u5b89\u88dd\u7dad\u4fee\u5e2b\u5085", "description": "\n\u8077\u8cac :\u4fdd\u990a,\u6aa2\u67e5,\u7dad\u4fee\u51b7\u71b1\u6c34\u6a5f\u53ca\u639b\u7246\u98f2\u7528\u96fb\u71b1\u6c34\u7210;\u5b89\u88dd, \u63db\u82af,\u4fdd\u990a,\u6aa2\u67e5,\u7dad\u4fee\u6de8\u6c34\u8a2d\u5099\n\n\u8cc7\u6b77 :\u6c92\u6709\u5b78\u6b77\u8981\u6c42; 1\u5e74\u7d93\u9a57; \u826f\u597d\u7cb5\u8a9e; \u61c2\u8b80\u5beb\u4e2d\u6587; \u6709\u76f8\u95dc\u7d93\u9a57,\u96fb\u5de5A\u724c\u512a\u5148 \u61c2\u5b89\u88dd,\u7dad\u4fee\u4fdd\u990a\u639b\u7246\u98f2\u7528\u96fb\u71b1\u6c34\u7210;\u9700\u5916\u52e4\u7368\u7acb\u5de5\u4f5c,\u6709\u8cac\u4efb\u5fc3\u53ca\u6709\u826f\u597d\u5de5\u4f5c\u614b\u5ea6\n\n\u5f85\u9047 :\u6bcf\u6708$20,000 - $22,000, \u6709\u9280\u884c\u5047\u671f, \u624b\u63d0\u96fb\u8a71\u6d25\u8cbc, \u82b1\u7d05 \u53ca\u5be6\u5831\u5be6\u92b7\u4ea4\u901a\u652f\u51fa, \u661f\u671f\u4e00\u81f3\u516d: \u4e0a\u53489\u6642\u81f3\u4e0b\u53486\u6642, \u6bcf\u9031\u5de5\u4f5c6\u5929, \u6bcf\u5929\u5de5\u4f5c 8 - 9 \u5c0f\u6642\n\n\u7533\u8acb\u9808\u77e5 :\u6c42\u8077\u8005\u53ef\u81f4\u96fb25431898\u8207\u92d2\u5353\u79d1\u6280\u6709\u9650\u516c\u53f8\u8449\u5c0f\u59d0\u806f\u7d61\u3002\n\n", "employment_types": ["Full Time"], "selling_points": [], "locations": ["Not Specified"], "categories": ["Engineering", "Others", "Others", "Technician"], "post_time": "2022-01-17T06:56:41Z", "salary": {"currency": null, "max": null, "min": null, "period": "monthly", "term": null}, "salary_visible": false, "title_keywords": [], "responsibilities": [], "requirements": {"degrees": [], "majors": [], "languages": [], "language_level": [], "hard_skills": [], "soft_skills": [], "languages_combined": []}, "experience_required": {"duration": [], "field": []}}, {"job_id": "100003009055871", "location_code": "hk", "company": "Hays", "job_title": "Shift & Field Operators  -  Registered Worker (Grade H)", "description": "Are you an offshore engineering expert? Here's your chance to be the first on board in Hong Kong. Registered Worker (Grade H)\n\nYour new company\n\nIn support of the Hong-Kong Government's policy to reduce carbon intensity and increase the proportion of natural gas used for power generation, an offshore LNG import terminal in Hong Kong has been constructed and will be ready to start its operations in 2022! The terminal will contribute to the enhancement and diversification of Hong Kong's natural gas supply sources, and ensure a more reliable supply of fuel at competitive prices.\n\nYour new role\n\nRunning a safe, effective, and efficient day-to-day operation of the Joint Venture (JV) Hong Kong Offshore LNG Terminal facility, implementing operational plans and auditing their application to optimise facility operation in line with HK LNG performance criteria; Operating the terminal's mechanical & Electrical systems and acting in compliance with company policies and procedures, appropriate legislation, and relevant codes of practice.\n\n\nMember of the offshore based O&M team of 12; 6 supervisors and 6 operators\nReports to the Operations Manager and supervises Shift Operators.\nEnsures adequate transfer of information when changing shifts. Engages with peers to share knowledge and accountable for applying best practices for solving problems\n\n\n\nWhat you'll need to succeed\n\n\nAssociate Degree/Higher Diploma or above in Mechanical, Electrical or Instrumentation Engineering\nRegistered Worker (Grade H)\nRelevant operational experience preferably in LNG, Oil, Gas, Refining, and Processing industry\nExcellence in English language (oral and written)\nKnowledge of HK and/or international codes of practice within the LNG or Energy industry\nKnowledge of Health, Safety, and Environmental requirements\nMotivated to work with an international team\n\n\n\nWhat you'll get in return\n\n\nAll required training and development\nLong term career opportunities\nA chance to join Hong Kong first ever offshore LNG project\nIndividual accommodation cabins will be provided on-board in the FSRU, including food and health-care facilities.\nFun international culture\nGreat salary\n\n\n\nWhat you need to do now\n\nIf you are interested in reducing emissions in Hong Kong and support a clean energy projects like this, please send your CV to timothy.smith@hays.com.hk", "employment_types": ["Full Time", "Permanent"], "selling_points": ["Registered Worker (Grade H)", "Environmentally advanced initiative", "Great career opportunities and salary"], "locations": ["Not Specified"], "categories": ["Engineering", "Engineering Project Management", "Others"], "post_time": "2022-01-18T03:02:03Z", "salary": {"currency": null, "max": null, "min": null, "period": "monthly", "term": null}, "salary_visible": false, "title_keywords": [], "responsibilities": ["day-to-day operation", "operations", "policies", "systems", "compliance", "procedures", "reports", "plans", "auditing"], "requirements": {"degrees": ["associate degree", "higher diploma or above"], "majors": ["engineering"], "languages": ["english"], "language_level": [], "hard_skills": ["clean", "fun", "safe", "processing", "codes"], "soft_skills": ["efficient", "oral", "interested in", "accountable", "motivated", "reliable"], "languages_combined": [{"language": "english", "language_level": []}]}, "experience_required": {"duration": [], "field": []}}, {"job_id": "100003009051874", "location_code": "hk", "company": "LAWSGROUP", "job_title": "Project Engineer (Redevelopment Project)", "description": "Job Responsibilities:\n\n\nAssist in project planning, execution and construction supervision of comprehensive development projects in Hong Kong\nAssist to monitoring and ensuring the work standards are of a sufficient quality and are cost-efficient\nResponsible for market research, feasibility study and monthly report\nPerform detailed documentation to track project development and design process\nPerform properties, licensing, insurance, legal matters related to properties, and corresponding maintenance issues\nWork with internal and external parties including but not limit to consultants, contractors, suppliers to ensure the project implement seamlessly\nAssist Project Manager to tackle problem and provide solutions to improve the efficiency of various project\nAssist the team on various ad-hoc projects as assigned\n\nJob Requirements:\n\n\n\nDegree or above in Architecture / Building Survey or related disciplines\nMinimum 2 years\u2019 relevant experience in Building / Architectural consultancy firm and involving in high end residential / commercial / office projects is preferred\u00a0\nWell versed in local government regulations\nExcellent command in AutoCAD and Microsoft Office\nFamiliar with in Adobe Photoshop, Revit and SketchUp would be an advantage\nStrong sense of responsibility, well-organized, able to work under pressure and a team player with good communication skills\nExcellent command in both written and spoken English and Chinese\nWe\u00a0offer\u00a0attractive remuneration package to the right candidate. Interested parties please click the \"APPLY NOW\" button below and send your application together with a detailed resume including current & expected salary and availability to Human Resources Department.\n\nCompany website:\u00a0https://www.lawsgroup.com\n\n(Data collected will be treated in strict confidence and used for recruitment purpose only)", "employment_types": ["Full Time", "Permanent"], "selling_points": ["At least  2 years' relevant exprience", "Degree holder in  Architecture / Building Survey", "Handle various redevelopment projects in HK"], "locations": ["Lai Chi Kok"], "categories": ["Engineering", "Engineering Project Management", "Others"], "post_time": "2022-01-17T01:25:50Z", "salary": {"currency": null, "max": null, "min": null, "period": "monthly", "term": null}, "salary_visible": false, "title_keywords": ["project engineer"], "responsibilities": ["cost", "project planning", "maintenance", "monitoring", "quality", "market research", "design", "internal and external parties", "provide solutions", "monthly report", "documentation", "ad-hoc projects", "insurance"], "requirements": {"degrees": ["degree or above"], "majors": ["related disciplines", "architecture"], "languages": ["english", "chinese"], "language_level": ["excellent"], "hard_skills": ["microsoft office", "adobe photoshop", "sketchup", "autocad", "revit"], "soft_skills": ["communication skills", "sense of responsibility", "well-organized", "team player", "work under pressure"], "languages_combined": [{"language": "english", "language_level": ["excellent"]}, {"language": "chinese", "language_level": ["excellent"]}]}, "experience_required": {"duration": ["minimum 2 years"], "field": ["commercial", "relevant experience"]}}, {"job_id": "100003009053373", "location_code": "hk", "company": "Able Engineering Company Limited", "job_title": "Assistant Resident Engineer", "description": "A degree holder in civil or structural engineering;\nMinimum 2 years relevant working experience;\nGood interpersonal communication skills;\nWork on Site.\n\nWe offer competitive salary package and career development opportunity to the successful candidate. Interested parties may send your full resume, present and expected salary, available date and contact number by email by clicking \"Apply Now\".\n\nTo visit our website for more information: www.ableeng.com.hk\n\n(As an Equal Opportunities Employer, Able is committed to eliminating discrimination in employment. The vacancy advertised is open to all applicants meeting the basic entry requirement irrespective of their disability, sex, marital status, pregnancy, age, family status, sexual orientation or race etc. Applicants not hearing from us within 6 months may consider their applications unsuccessful. Personal data collected will be used for recruitment related purposes only.)", "employment_types": ["Full Time", "Permanent"], "selling_points": [], "locations": ["Not Specified"], "categories": ["Building & Construction", "Civil / Structural", "Engineering", "Others", "Others"], "post_time": "2022-01-17T06:52:31Z", "salary": {"currency": null, "max": null, "min": null, "period": "monthly", "term": null}, "salary_visible": false, "title_keywords": ["assistant resident engineer"], "responsibilities": ["communication"], "requirements": {"degrees": ["degree holder"], "majors": ["structural engineering"], "languages": [], "language_level": [], "hard_skills": [], "soft_skills": ["communication skills", "interpersonal"], "languages_combined": []}, "experience_required": {"duration": ["minimum 2 years"], "field": ["relevant working experience"]}}, {"job_id": "100003009050733", "location_code": "hk", "company": "Hutchison Telecommunications (Hong Kong) Limited", "job_title": "Technical Officer (6 months contract)", "description": "\u00a0Responsibilities:\n\n\u00a0 \u00a0 \u00a0 \u00a0 \u00a0Conduct field test and drive test\n\u00a0\u00a0\u00a0\u00a0\u00a0\u00a0\u00a0\u00a0 Assist for site searching\n\u00a0\u00a0\u00a0\u00a0\u00a0\u00a0\u00a0\u00a0 Prepare site related documents, e.g. proposal and work order\n\u00a0\u00a0\u00a0\u00a0\u00a0\u00a0\u00a0\u00a0 Assist Engineer to perform field survey\n\nRequirements:\n\n\u00a0 \u00a0 \u00a0 \u00a0 \u00a0Certificate / Diploma / Higher Diploma or above in Engineering, Electronic /\u00a0Telecom Engineering is preferable\n\u00a0\u00a0\u00a0\u00a0\u00a0\u00a0\u00a0\u00a0 1 year or above experience, telecom industry is preferable\n\u00a0\u00a0\u00a0\u00a0\u00a0\u00a0\u00a0\u00a0 Self-motivated and able to work under pressure\n\nApart from competitive remuneration package and exciting opportunity for career development within the Group, we provide attractive employee benefits such as free company shuttle, free company SIM card and preferential SIM plan offers, comprehensive medical & insurance schemes, as well as full range of other employee well-being provisions.\u00a0\n\nInterested parties, please apply with full resume, present and expected salary, by clicking \u201cAPPLY NOW\u201d. Please quote the reference number on the e-mail subject.\n\nWe are an equal opportunity employer and welcome applications from all qualified candidates. Personal data collected will be treated in the strictest confidence and handled confidentially by authorised personnel for recruitment-related purposes only within the CK Hutchison Group of companies. The personal data of unsuccessful applicants will be destroyed after the recruitment exercise pursuant to the requirements of the Personal Data (Privacy) Ordinance in Hong Kong.", "employment_types": ["Full Time", "Contract"], "selling_points": [], "locations": ["Tsing Yi"], "categories": ["Engineering", "Engineering Project Management", "Telecommunication / Wireless / Radio", "Others"], "post_time": "2022-01-14T11:15:00Z", "salary": {"currency": null, "max": null, "min": null, "period": "monthly", "term": null}, "salary_visible": false, "title_keywords": ["technical officer"], "responsibilities": ["related documents"], "requirements": {"degrees": ["certificate", "diploma", "higher diploma or above"], "majors": ["engineering"], "languages": [], "language_level": [], "hard_skills": [], "soft_skills": ["self-motivated", "comprehensive", "work under pressure"], "languages_combined": []}, "experience_required": {"duration": ["1 year"], "field": []}}, {"job_id": "100003009044429", "location_code": "hk", "company": "Lingnan University", "job_title": "Project Engineer (Multiple positions) (Post Ref.: 21/328)", "description": "Lingnan University, a distinctive liberal arts institution in the Hong Kong Special Administrative Region, is committed to the provision of quality whole-person education by combining the best of Chinese and Western liberal arts traditions. It strives to pursue excellence in teaching, learning, scholarship and community engagement. With three academic Faculties, it offers a wide range of undergraduate degree programmes in arts, business and social sciences. Lingnan\u2019s liberal arts education is characterised by a broad-based interdisciplinary curriculum with specialised disciplinary studies; close student-staff relationship; a vibrant residential campus; ample global learning opportunities; active community engagement and multifarious workplace experience. The School of Graduate Studies also offers postgraduate programmes up to doctoral level in various disciplines and provides professional education for the wider society. \u00a0\u00a0Applications are now invited for the following posts:\n\nProject Engineer (Multiple positions)\nOffice of Service-Learning\n(Post Ref.: 21/328)\n\nThe Office of Service-Learning (OSL) is looking for Project Engineers with strong interest in designing exciting mechatronic products and nurturing future generations of innovators.\n\nThese positions offers opportunities for innovators to tackle unique challenges and develop novel products with a multinational team of engineers, social workers and scientists. The ideal candidates are interested in designing products that improves the living in urban and rural environment. Current design products range from ultra-violet disinfection robots, transparent filtration masks and intelligent wheelchairs. The appointees will also support the design and delivery of technology literacy programmes to undergraduate students. These positions will offer on-the-job training and are open to fresh university graduates.\n\nResponsibilities\nDesign innovative mechatronics products and humanitarian technologies for making real impact\nConduct research to evaluate and refine user experiences\nPrepare material for design competitions, marketing, and stakeholder engagement\nDesign and deliver integrated technology literacy programmes for students, faculty, and community members\nProvide mentorship to students engaged in design and technology-heavy competitions\nSupport entrepreneurship events and facilities (including student startups, coworking space operations, and programme promotions)\nPerform administrative duties (including report preparation, programme promotions and Service-Learning coordination)\n\nRequirements\nGraduate with a background in Science, Engineering, Technology or Social Sciences\nExperience in creating 2D drawings, 3D models and assemblies using CAD software such as SolidWorks, Fusion 360, Inventor, or Rhino\nExperience with basic microcontroller programming (Arduino, etc.) to aid in rapid prototyping\nPractical understanding of various manufacturing methods such as 3D printing, laser/waterjet cutting, CNC machining, injection moulding, and knowing which is appropriate for a given design\nHands-on experience with assembling and testing prototypes, using benchtop tools including multimeter, oscilloscopes\nGood knowledge in mechanical design and common components (including motors, fasteners, transmissions, bearing, etc.)\nExperience with technical programming languages such as MATLAB, C++, and Python\nSuccessful candidates will be working in a team with diverse expertise from science to engineering, and social science to marketing.\u00a0Preference will be given to candidates with passions in solving social problems with technology.\u00a0\nSalary and Fringe Benefits\nThe rank and commencing salary will be commensurate with qualifications and experience. Fringe benefits, where applicable, include annual leave, medical and dental benefits and mandatory provident fund.\n\nApplication Procedure\nPlease click \"Apply Now\" to submit your application with a 2-page design portfolio highlighting ONE outstanding project with pictures. Personal data collected will be used for recruitment purposes only.\n\nWe are an equal opportunities employer. Review of applications will start from January 2022 and continue until the post is filled. Qualified candidates are advised to submit their applications early for consideration.\n\nThe University reserves the right not to make an appointment for the post advertised, or to fill the post by invitation or by search. We regret that only shortlisted candidates will be notified.", "employment_types": ["Full Time"], "selling_points": ["Design innovative mechatronics products", "Conduct research to evaluate", "Prepare material for design competitions"], "locations": ["Tuen Mun Area"], "categories": ["Engineering", "Engineering Project Management", "Manufacturing & Production", "Others"], "post_time": "2022-01-17T01:01:22Z", "salary": {"currency": null, "max": null, "min": null, "period": "monthly", "term": null}, "salary_visible": false, "title_keywords": ["project engineer"], "responsibilities": ["operations", "design", "evaluate", "administrative duties", "coordination", "conduct research", "report"], "requirements": {"degrees": [], "majors": [], "languages": [], "language_level": [], "hard_skills": ["basic", "c++", "rhino", "cad", "python", "programming", "rapid", "matlab", "solidworks"], "soft_skills": ["diverse", "hands-on"], "languages_combined": []}, "experience_required": {"duration": [], "field": ["programming", "testing"]}}, {"job_id": "100003009047703", "location_code": "hk", "company": "Ramboll Hong Kong Limited", "job_title": "Senior Managing Consultant - Sustainability", "description": "Higher Diploma or above in ME/EE/BSE\n(Senior Position available for MHKIE/RPE in EE/BSE)\nMin. 2 years experience in E&M/ Building Services Field\n(Lesser experience will be considered for Engineer Asst.)\nProficiency in Auto Cad 2015 or above\nSite experience is preferable\nAbility to written and spoken English\n(Remark : Our company will suitably recommend our Engineers to apply for REW registrations)\n\nPlease forward personal CV with Expected Salary and Date Available to Apply Now or Fax: 2342 2352 Miss Wong\n\n", "employment_types": ["Full Time", "Permanent"], "selling_points": ["10 years relevant experience", "Sustainable Building & Environmental Consultancy", "Leadership skill to lead, motivate & grow the team"], "locations": ["Wan Chai"], "categories": ["Engineering", "Engineering Project Management", "Others", "Sciences, Lab, R&D", "Environmental Science / Waste Management"], "post_time": "2022-01-14T03:47:30Z", "salary": {"currency": null, "max": null, "min": null, "period": "monthly", "term": null}, "salary_visible": false, "title_keywords": ["consultant"], "responsibilities": [], "requirements": {"degrees": ["higher diploma or above"], "majors": [], "languages": ["english"], "language_level": [], "hard_skills": ["auto cad 2015", "mhkie"], "soft_skills": [], "languages_combined": [{"language": "english", "language_level": []}]}, "experience_required": {"duration": ["2 years"], "field": ["building services"]}}, {"job_id": "100003009044828", "location_code": "hk", "company": "Global Development Personnel Co Limited", "job_title": "Engineer  /  Assistant Engineer (Fire Services)", "description": "Responsibilities:\nProvide support to engineers and managers in managing daily component repair business\nLead the component repair team to carry out continuous improvement activities\nConduct quality investigations and trouble shoot technical problems\nRequirements:\nDegree in Mechanical Engineering or related field\nGood communication and interpersonal skills\nGood command of written and spoken English\nFresh university graduates will also be considered\nInterested parties please send a full resume with expected salary and quote our reference number to Human Resources Department, Hong Kong Aero Engine Services Ltd., 70 Chun Choi Street, Tseung Kwan O Industrial Estate, N.T. or alternatively, email us by clicking \"Apply Now\".\nPlease feel free to visit our company website at www.haesl.com.\nData collected will be used for recruitment purpose only\n\nApplicants not invited for interview within three weeks from the date of submitting CV may consider their application unsuccessful.", "employment_types": ["Full Time"], "selling_points": ["Listing Company with Bonus", "15-25K", "Fresh graduates are Welcome"], "locations": ["Tsim Sha Tsui"], "categories": ["Engineering", "Engineering Project Management", "Others"], "post_time": "2022-01-13T06:26:16Z", "salary": {"currency": null, "max": null, "min": null, "period": "monthly", "term": null}, "salary_visible": false, "title_keywords": ["assistant engineer", "engineer"], "responsibilities": ["provide support", "quality", "repair"], "requirements": {"degrees": ["degree"], "majors": ["mechanical engineering"], "languages": ["english"], "language_level": ["good command"], "hard_skills": [], "soft_skills": ["communication and interpersonal skills"], "languages_combined": [{"language": "english", "language_level": ["good command"]}]}, "experience_required": {"duration": [], "field": []}}, {"job_id": "100003009044933", "location_code": "hk", "company": "Well Sight Property Management Limited", "job_title": "Assistant Engineer/Sr. Technical Officer/Technical Officer", "description": "Responsibilities:\n\u2022\u00a0Perform routine maintenance and repairs for all crane equipment and workshop equipment\n\u2022\u00a0Assist in preparing and keeping maintenance and repair records\n\u2022\u00a0Attend all faults & emergency repair works and supervise the remedy as well as provide failures troubles shooting & technical diagnosis\n\u2022\u00a0Ensure all the cranes maintenance works carried out by the contractors meet with the Company\u2019s needs and reports to supervisor\n\u2022\u00a0Lead team members to carry out assigned jobs\n\nRequirements:\n\u2022\u00a0Higher Certificate/Diploma in electrical engineering or related discipline\n\u2022\u00a06 years relevant working experience in heavy electrical industrials with 3 years supervisory experience\n\u2022\u00a0Knowledge of AC/DC motor drives, PLC and cranes control is preferred\n\u2022\u00a0Holder of Electrical License B is preferred\n\u2022\u00a0Holder of Container Handling Industry Safety Card\n\u2022\u00a0Holder of driving license Class 1 & Class 2 is preferred\n\u2022\u00a0Willing to perform shift work\n\u2022\u00a0Good interpersonal and communication skills\n\n**Candidates with less experience will be considered as Assistant Engineer.\n\nBenefit:\n5 Shift Per Week / Night Shift Allowance / Annual Leave / General Holidays / Group Medical Insurance (Included dependent) & Life Insurance / Discretionary Bonus / Free Shuttle Bus Service\n\n(All information collected will be kept strictly confidential and for recruitment and employment-related purposes only)", "employment_types": ["Full Time", "Permanent"], "selling_points": ["Holder of Cert/Dip in related discipline", "Minimum 5 years relevant experience", "Certificate of Registration of Electrical Worker"], "locations": ["Chai Wan"], "categories": ["Engineering", "Others", "Property / Real Estate", "Property Management"], "post_time": "2022-01-13T06:40:56Z", "salary": {"currency": null, "max": null, "min": null, "period": "monthly", "term": null}, "salary_visible": false, "title_keywords": ["technical officer", "assistant engineer"], "responsibilities": ["workshop", "reports", "maintenance", "repair"], "requirements": {"degrees": ["diploma", "higher certificate"], "majors": ["electrical engineering"], "languages": [], "language_level": [], "hard_skills": ["dc", "plc", "container"], "soft_skills": ["communication skills", "interpersonal"], "languages_combined": []}, "experience_required": {"duration": ["6 years", "3 years"], "field": ["relevant working experience", "supervisory experience"]}}, {"job_id": "100003009051701", "location_code": "hk", "company": "ASM Technology Hong Kong Limited", "job_title": "Process Engineer (Fresh Graduate / IANG Holder Is Welcome)", "description": "Responsibilities:\nResponsible for creating the Building Information Models & providing necessary onsite support and advisory services to the operation team;\nCollaborate innovation initiatives to support the tender presentations and promote execution strategies at corporate level;\nManage BIM technology implementation and assuring the quality deliverables on construction projects;\nMaintain accurate data set in drawings, design specifications and project schedules;\nAssist in the research and facilitating the means of better BIM applications in order to improve the communication, co-ordination, management and delivery time, cost and quality throughout the building life cycle of the projects;\nCommunicate and co-ordinate with different stakeholders including consultants, architects and internal operation team in the smooth execution and delivery of projects with architectural designs and the usage of BIM models.\nRequirements:\nDiploma/Degree in\u00a0Electrical, Mechanical, Building Services, Engineering\u00a0or related disciplines;\n2\u00a0 years or above relevant experience\u00a0from construction industry and in tunnel project is preferred;\nHands-on BIM software / applications experience is preferred (Autodesk Revit, Navisworks, Solidworks)\nAbility to generate construction CSD & ISD drawing from Revit BIM model is preferred;\nGood interpersonal and communication skills.\nYou may apply via https://career.gammonconstruction.com/home/index?jobid=c6f40b7d-ec1d-4f6b-a784-56f6d02140b7&source=003, providing you full resume, current and expected salary.\nFor more information about Gammon Construction Limited, please visit our company's website at http://www.gammonconstruction.com.\nWe are an equal opportunity employer and welcome application from all qualified candidates. Information provided will be treated in strict confidence and only be used for consideration of your application for the relevant post within the Company. Applicants who are not invited for an interview within 6 weeks may consider their application unsuccessful.", "employment_types": ["Full Time", "Permanent"], "selling_points": ["Degree or higher in Applied Physics / Applied Math", "Good understanding of DoE, FMECA, statistics", "Strong in analytical methods"], "locations": ["Kwai Tsing Area"], "categories": ["Engineering", "Electrical / Electronics", "Mechanical", "Others"], "post_time": "2022-01-16T21:50:55Z", "salary": {"currency": null, "max": null, "min": null, "period": "monthly", "term": null}, "salary_visible": false, "title_keywords": ["process engineer"], "responsibilities": ["collaborate", "management", "cost", "data", "schedules", "co-ordinate with", "quality", "implementation", "presentations", "drawings", "design specifications", "communication", "maintain", "tender"], "requirements": {"degrees": ["diploma", "degree"], "majors": ["related disciplines", "building services", "engineering"], "languages": [], "language_level": [], "hard_skills": ["bim", "solidworks", "revit"], "soft_skills": ["communication skills", "hands-on", "confidence", "interpersonal"], "languages_combined": []}, "experience_required": {"duration": [], "field": ["construction industry", "relevant experience"]}}, {"job_id": "100003009052057", "location_code": "hk", "company": "Meinhardt Consulting Engineers", "job_title": "Technical Director / Executive Engineer / Senior Engineer (Ref: 88072T6)", "description": "About The Role:\n\nResponsible for system design, implementation and maintenance preferably in Traffic Control and Surveillance System discipline\nCoordinate and interface with external systems and subsystems\n\nAbout You:\n\nDegree holder or above in Electronic Engineering, or related subjects\nMinimum 5 years of relevant experience of electronic engineering\nHolder of driving license class 1 and 2 will be an advantage\nGood command of both written and spoken English & Chinese\nWhat you can get from us:\n\nOn-the-job training, learning and development\u00a0provided\nExecutive workshops, interest class, corporate purchase discount offered by SHKP\nCompetitive salary and annual leaves\nFlexible working opportunities\n\nInterested parties, please send full resume with expected salary and available date to Human Resources and Administration Department by e-mail or by fax 2111 9459.\n\n(Data collected will be used for recruitment purpose only.)", "employment_types": ["Full Time", "Permanent"], "selling_points": [], "locations": ["Not Specified"], "categories": ["Building & Construction", "Civil / Structural", "Engineering", "Engineering Project Management", "Others"], "post_time": "2022-01-17T01:59:13Z", "salary": {"currency": null, "max": null, "min": null, "period": "monthly", "term": null}, "salary_visible": false, "title_keywords": ["senior engineer", "executive engineer", "director"], "responsibilities": ["control", "maintenance", "systems", "implementation", "coordinate", "purchase", "system design"], "requirements": {"degrees": ["degree holder"], "majors": ["engineering"], "languages": ["english", "chinese"], "language_level": ["good command"], "hard_skills": ["workshops", "system design", "maintenance"], "soft_skills": ["flexible", "learning", "responsible"], "languages_combined": [{"language": "english", "language_level": ["good command"]}, {"language": "chinese", "language_level": ["good command"]}]}, "experience_required": {"duration": ["minimum 5 years"], "field": ["relevant experience", "engineering"]}}, {"job_id": "100003009050183", "location_code": "hk", "company": "Shun Hing Systems Integration Company Limited", "job_title": "Site Engineer", "description": "Job Duties\n\n\n\u00a0Act as RSE/RGE T3 and both the RSE/RGE\u2019s Representative full time on site;\nAccountable and report to the AP/RSE/RGE under supervision of the RSE/RGE\u2019s Representative;\nProvide professional assistance to Resident Engineer/TCP T5 or design office as appropriate;\nCarry out specific tasks as per requirement and checklist devised from RSE/RGE and representative of Client;\nCheck the works in compliance with the approved plans, the approved temporary works, method statements, precautionary and protective measures;\nMonitor the work of the Registered Contractor\u2019s TCPs;\nDeal with non-conformities by making referral to the RSE/RGE\u2019s representative and notify TCPs in other streams; and\nAssist to check the contractor\u2019s structural works are in compliance with the statutory and contractual requirements.\nEnforce ethics and compliance policy including Third Party payment, Sub-consultancy engagement process and Gift and Entertainment policy.\n\nRequirements\n\n\nMinimum 5 years of relevant experience post Higher certificate or higher diploma in civil/structural engineering; or Minimum 2 years of relevant experience post Degree in civil/ structural engineering with GIFW;\nRelevant experience with Demolition Works;\nFluency in written and spoken English and Cantonese.\n\nProject Brief\n\n\nThe project site is located in Shau Kei Wan\nThe project includes demolition of residential blocks and demolition of residential blocks and ground investigation field works\nTentative Contract period of employment:\u00a0 Around 15 months", "employment_types": ["Full Time"], "selling_points": [], "locations": ["Not Specified"], "categories": ["Building & Construction", "Building / Construction / QS", "Engineering", "Engineering Project Management", "Others"], "post_time": "2022-01-14T09:54:47Z", "salary": {"currency": null, "max": null, "min": null, "period": "monthly", "term": null}, "salary_visible": false, "title_keywords": ["site engineer"], "responsibilities": ["ap", "compliance", "monitor", "design", "payment", "plans", "third party", "report"], "requirements": {"degrees": ["diploma", "degree", "higher certificate"], "majors": ["structural engineering"], "languages": ["cantonese", "english"], "language_level": ["fluency"], "hard_skills": ["wan"], "soft_skills": [], "languages_combined": [{"language": "cantonese", "language_level": ["fluency"]}, {"language": "english", "language_level": ["fluency"]}]}, "experience_required": {"duration": ["minimum 2 years", "minimum 5 years"], "field": ["structural", "relevant experience", "engineering"]}}, {"job_id": "100003009050184", "location_code": "hk", "company": "Shun Hing Systems Integration Company Limited", "job_title": "Engineer (Mechanical)", "description": "\u200b\u70ba\u914d\u5408\u9999\u6e2f\u696d\u52d9\u7684\u8fc5\u901f\u767c\u5c55\uff0c\u672c\u516c\u53f8\u4e4b\u5b89\u88dd\u53ca\u4fdd\u990a\u90e8\u73fe\u8aa0\u8058\u6b64\u8077\u4f4d:\n\n\n\u5165\u8077\u8981\u6c42\n\n\u5df2\u5b8c\u6210\u8a8d\u53ef\u7684\u5c4b\u5b87\u8a2d\u5099\u5de5\u7a0b\u3001\u96fb\u6a5f\u5de5\u7a0b\u3001\u96fb\u5b50\u5de5\u7a0b\u3001\u8f2a\u6a5f\u5de5\u7a0b\u6216\u6a5f\u68b0\u5de5\u7a0b\u9ad8\u7d1a\u6587\u6191\u6216\u4ee5\u4e0a\u7a0b\u5ea6\n\u7121\u9700\u76f8\u95dc\u5de5\u4f5c\u7d93\u9a57\n\n\u5728\u8077\u57f9\u8a13\u8a08\u5283\n\n\n\u63d0\u4f9b\u5c08\u696d\u7684\u5728\u8077\u57f9\u8a13\u8a08\u5283\uff0c\u5305\u62ec\u8ab2\u5802\u53ca\u5be6\u5730\u5de5\u4f5c\u57f9\u8a13\n\u65bc\u53d7\u8a13\u671f\u9593\u6703\u88ab\u5b89\u6392\u5230\u4e0d\u540c\u90e8\u9580\u5be6\u7fd2\u53ca\u63a5\u89f8\u4e0d\u540c\u5de5\u4f5c\uff0c\u5305\u62ec\u7dad\u4fee\u3001\u4fdd\u990a\u3001\u7ffb\u65b0\u3001\u5b89\u88dd\u7b49\n\n\u5b8c\u5584\u6649\u5347\u5236\u5ea6\n\n\u52a9\u7406\u6280\u8853\u54e1 \u2192 \u5c08\u696d\u6280\u8853\u54e1 \u2192 \u5de5\u7a0b\u5e2b \u2192 \u8a3b\u518a\u5de5\u7a0b\u5e2b \u2192 \u5206\u5340\u7d93\u7406\n\n\u54e1\u5de5\u798f\u5229\n\n\u5e74\u7d42\u82b1\u7d05\n\u91ab\u7642\u798f\u5229\n\u52a0\u73ed\u6d25\u8cbc\n\u6709\u85aa\u5e74\u5047\n\u52e4\u5de5\u734e\n\n\u7533\u8acb\u8fa6\u6cd5\n\n\u672c\u516c\u53f8\u63d0\u4f9b\u512a\u539a\u85aa\u916c\u53ca\u826f\u597d\u6649\u5347\u6a5f\u6703\u3002\u6709\u610f\u8005\u8acb\u81f4\u96fb2331 5590\u6d3d\u6216WhatsApp / WeChat : 9013 0012\u6216\u6309\"Apply Now\"\u905e\u4ea4\u7533\u8acb\u3002\n\n\n\n\u4f5c\u70ba\u63d0\u5021\u5e73\u7b49\u6a5f\u6703\u7684\u50f1\u4e3b\uff0c\u672c\u516c\u53f8\u6b61\u8fce\u4efb\u4f55\u7b26\u5408\u5165\u8077\u8981\u6c42\u7684\u4eba\u58eb\u63d0\u4ea4\u8077\u4f4d\u7533\u8acb\u3002\u7533\u8acb\u8005\u4e4b\u500b\u4eba\u8cc7\u6599\u8b39\u4f5c\u62db\u8058\u7528\u9014\u3002", "employment_types": ["Full Time", "Permanent"], "selling_points": [], "locations": ["Not Specified"], "categories": ["Engineering", "Engineering Project Management", "Mechanical", "Others"], "post_time": "2022-01-14T09:54:48Z", "salary": {"currency": null, "max": null, "min": null, "period": "monthly", "term": null}, "salary_visible": false, "title_keywords": ["engineer"], "responsibilities": [], "requirements": {"degrees": [], "majors": [], "languages": [], "language_level": [], "hard_skills": ["wechat"], "soft_skills": [], "languages_combined": []}, "experience_required": {"duration": [], "field": []}}, {"job_id": "100003009051855", "location_code": "hk", "company": "Hong Kong Applied Science and Technology Research Institute Company Limited (ASTRI)", "job_title": "Optics Design - Senior Lead Engineer / Lead Engineer", "description": "Job responsibilities:\n\n\nUndertake Business development activities to secure new business and develop new clients;\nMaintain existing clients through relationship building and excellent service in order to attain repeat business;\nAchieve financial and non-financial targets for a Portfolio of jobs agreed with the Managing Director;\nContribute to the strategic direction of the service line;\nBeing a recognized service line expert; leading and undertaking environmental and building projects and projects that maintain our environmental service portfolio;\nManage and lead a team of professionals to deliver excellent project execution which involves data collection and interpretation, simulations/modelling, report writing, field measurements and inspections for the preparation of project deliverables; and\nBeing a people manager to coach and mentor of junior staffs.\nJob requirements:\n\nAt least Degree/Master\u2019s in building services, environmental science, environmental engineering or related fields,\n10 to 15 years\u2019 project delivery experiences in Hong Kong SAR and/or Asia Pacific Region,\nProven track record in winning and managing sustainable building and environmental consultancy related projects,\nA registered BEAM Pro, LEED AP and/or WELL AP is preferable;\nA member of the recognized professional body including HKIE, Hong Kong Institute of Acoustics, or Hong Kong Institute of Environmental Impact Assessment, Chartered Institute of Water and Environmental Management and/or Hong Kong Institute of Qualified Environmental Professional;\nChinese and English fluency and excellent oral and written communication skills;\nAbility to interact well with clients and other project stakeholders; and\nExcellent leadership skill, able to lead, motivate and grow the team.\n\nAttractive remuneration package and excellent career prospect will be offered to the right candidate.\u00a0 Interested parties please e-mail your resume, current and expected salary and availability to the Administration Manager by clicking \"Apply Now\".\n\nAll Personal data collected will be used for recruitment purpose only.", "employment_types": ["Full Time", "Contract"], "selling_points": ["Optics Design", "Technology Research and Development", "Optical Engineering, Applied Optics, Physics"], "locations": ["Shatin Area"], "categories": ["Engineering", "Manufacturing & Production", "Others", "Sciences, Lab, R&D", "Research & Development (R&D)"], "post_time": "2022-01-17T01:23:16Z", "salary": {"currency": null, "max": null, "min": null, "period": "monthly", "term": null}, "salary_visible": false, "title_keywords": ["engineer", "lead"], "responsibilities": ["project deliverables", "develop", "lead a team", "maintain", "data collection", "report"], "requirements": {"degrees": ["degree", "master"], "majors": ["environmental science", "environmental engineering", "building services"], "languages": ["english", "chinese"], "language_level": ["fluency", "excellent"], "hard_skills": ["ap", "hkie"], "soft_skills": ["communication skills", "oral", "leadership skill"], "languages_combined": [{"language": "english", "language_level": ["fluency", "excellent"]}, {"language": "chinese", "language_level": ["fluency", "excellent"]}]}, "experience_required": {"duration": ["10 to 15 years"], "field": []}}, {"job_id": "100003009051686", "location_code": "hk", "company": "ASM Technology Hong Kong Limited", "job_title": "Project Engineer", "description": "Engineer\u00a0 /\u00a0 Assistant Engineer (Fire Services)\n\n\n\nResponsibilities:\n\nTo prepare FS system shop drawings and layout drawing etc., as well as equipment, individual preparation, and submission for approval and procurement\nSite progress supervision, site inspection and documentary recording as required\n\nRequirements:\n\nHigher Diploma or above in Fire Services Engineering or related disciplines\nFresh graduates are Welcome\u00a0\nProficiency in AutoCAD drawings skills and MS office operations\nSelf-motivated, detail-minded, with a high sense of responsibility and good communication skills\nGood command of both written and spoken English & Chinese", "employment_types": ["Full Time", "Permanent"], "selling_points": ["Bachelor\u2019s degree in Engineering discipline", "1-2 years of experience", "Assist project management on maintain project plan"], "locations": ["Tsing Yi"], "categories": ["Engineering", "Engineering Project Management", "Others"], "post_time": "2022-01-16T21:50:47Z", "salary": {"currency": null, "max": null, "min": null, "period": "monthly", "term": null}, "salary_visible": false, "title_keywords": ["project engineer"], "responsibilities": ["site inspection", "drawings"], "requirements": {"degrees": ["higher diploma or above"], "majors": ["related disciplines", "engineering"], "languages": ["english", "chinese"], "language_level": ["good command"], "hard_skills": ["ms office", "autocad"], "soft_skills": ["detail-minded", "communication skills", "self-motivated", "high sense of responsibility"], "languages_combined": [{"language": "english", "language_level": ["good command"]}, {"language": "chinese", "language_level": ["good command"]}]}, "experience_required": {"duration": [], "field": []}}, {"job_id": "100003009042874", "location_code": "hk", "company": "NV5 Limited", "job_title": "Senior / Project Engineer \u2013 Fire Service", "description": "Responsibilities:\n\nTo monitor property maintenance, building renovation and builders work\nTo prepare the tender document of R & M builders work\n\nRequirements:\n\nCert/Dip holder in Building Services Engineering / Electrical Engineering or equivalent\nCertificate of Registration of Electrical Worker (Grade A)\n\nMinimum 5 years experience in maintenance of building service\nGood command of spoken English and Cantonese\nKnowledge in PC applications including MS Excel and Word\nResponsible, independent, self-motivated, willing to work under pressure, with good communication skill\u00a0\nCandidates with less experience will be considered as Senior Technical Officer or Technical Officer\n\n\u00a0\n\nWe offer generous remuneration package and excellent career development to the right candidates. Shall you have any queries; please feel free to contact Ms. Chan at 2781 2208. Please apply now.\n\n(All data collected will be used for recruitment purpose only.)", "employment_types": ["Full Time", "Permanent"], "selling_points": ["Support the team for tendering, project planning", "Provide support on project site visits", "Degree / Diploma Holder in Fire / Building Service"], "locations": ["Kwun Tong"], "categories": ["Building & Construction", "Building / Construction / QS", "Engineering", "Engineering Project Management", "Others"], "post_time": "2022-01-12T09:05:08Z", "salary": {"currency": null, "max": null, "min": null, "period": "monthly", "term": null}, "salary_visible": false, "title_keywords": ["project engineer"], "responsibilities": ["tender document", "renovation", "monitor", "maintenance"], "requirements": {"degrees": ["certificate", "dip"], "majors": ["building services", "engineering", "electrical engineering"], "languages": ["cantonese", "english"], "language_level": ["good command"], "hard_skills": ["maintenance", "word", "pc applications", "ms excel", "certificate of registration of electrical worker"], "soft_skills": ["self-motivated", "independent", "responsible", "communication skill", "work under pressure"], "languages_combined": [{"language": "cantonese", "language_level": ["good command"]}, {"language": "english", "language_level": ["good command"]}]}, "experience_required": {"duration": ["minimum 5 years"], "field": ["maintenance"]}}, {"job_id": "100003009047636", "location_code": "hk", "company": "Modern Concrete Drill Cut Co., Limited", "job_title": "HR & Admin Clerk", "description": "Responsibilities:\n\n\n\nDay-to-day site inspections and checks on compliance with drawings, specifications and working procedures as necessary\nCarry out relevant design checking and method statement checking\nLiaise with internal design team and external clients\n\nQualifications & Requirements:\n\n\nDegree holder in Geotechnical / Civil Engineering with 2+ years of relevant working experience\nFamiliar with Technically Competent Persons (TCP) requirements and duties\nLooking for progressive challenges and opportunities\nStrong analytical mind set and problem solving skills\nGood command of written English\nShould be detail-oriented, discipline and self-motivated\nGood team player with high degree of commitment to complete works\nFamiliar with structural design software is an advantage\n\n\u00a0Please send your full resume with expected salary and availability(quoting reference number) to:\n\nHuman Resources Manager\nMeinhardt Consulting Engineers\n10/F Genesis, 33-35 Wong Chuk Hang Road, Hong Kong\n\nOR send e-mail by clicking \"Apply Now\" \u00a0\u00a0\u00a0 http://www.meinhardtgroup.com\n\nCandidates who have not been contacted within 8 weeks of their date of application may assume their application has been unsuccessful. Data collected will be used for recruitment purpose only and will be destroyed after six months from date of application.", "employment_types": ["Full Time", "Permanent"], "selling_points": [], "locations": ["Kwun Tong"], "categories": ["Engineering", "Others"], "post_time": "2022-01-15T03:49:46Z", "salary": {"currency": null, "max": null, "min": null, "period": "monthly", "term": null}, "salary_visible": false, "title_keywords": ["hr", "admin clerk"], "responsibilities": ["compliance", "procedures", "checking", "design", "drawings", "specifications", "site inspections", "liaise with"], "requirements": {"degrees": ["degree", "degree holder"], "majors": ["civil engineering"], "languages": ["english"], "language_level": ["good command"], "hard_skills": ["problem solving skills", "tcp"], "soft_skills": ["self-motivated", "good team player", "competent", "detail-oriented", "analytical mind", "progressive", "problem solving skills"], "languages_combined": [{"language": "english", "language_level": ["good command"]}]}, "experience_required": {"duration": ["2+ years"], "field": ["relevant working experience", "engineering"]}}, {"job_id": "100003009051698", "location_code": "hk", "company": "ASM Technology Hong Kong Limited", "job_title": "Digital Electronic Engineer / Senior Digital Electronic Engineer", "description": "Responsibilities\nResponsible for overall planning, coordination and management of site works for conveyor project at airport\nCarry out daily site work supervision with proper records\nLiaise with clients and sub-contractors to solve non-conformities\nAttend project meetings with external parties\nMonitor site progress and ensure the works performed in required standard\nRequirements\nDiploma or above in Engineering or related disciplines\n5 years' working experience in large E&M project\nGood communication and site management skills\nSelf-motivated, mature and able to work independently under pressure\nPlease click \"Apply Now\" to submit your application.\nPersonal data collected will be used for recruitment purpose only.", "employment_types": ["Full Time", "Permanent"], "selling_points": ["Degree or higher in Electronic / Computer Engineer", "Fresh graduate is welcome", "Develop and support digital hardware platform"], "locations": ["Tsing Yi"], "categories": ["Engineering", "Electrical / Electronics", "Others"], "post_time": "2022-01-16T21:50:53Z", "salary": {"currency": null, "max": null, "min": null, "period": "monthly", "term": null}, "salary_visible": false, "title_keywords": ["electronic engineer"], "responsibilities": ["liaise with clients", "management", "monitor site progress", "external parties", "coordination", "planning"], "requirements": {"degrees": ["diploma or above"], "majors": ["related disciplines", "engineering"], "languages": [], "language_level": [], "hard_skills": [], "soft_skills": ["self-motivated", "work independently", "under pressure", "mature", "communication"], "languages_combined": []}, "experience_required": {"duration": ["5 years"], "field": []}}, {"job_id": "100003009055086", "location_code": "hk", "company": "OneAsia Network Limited", "job_title": "Administrative Clerk", "description": "Responsibilities:\n\nPrepare technical documents in accordance with company\u2019s guidelines and standards\nProvide engineering design, documentation and project administration\nProvide support on project site visits, project acceptance and progress inspection\nSupport the team for tendering, project planning, project production and delivery\nWSD submission and documentation preparation\nAble to communicate effectively with the team and various project parties\nPerform ad hoc assignments or tasks as required\n\nRequirements:\n\nDegree /Diploma holder in Building Service Engineering or Fire Engineering\n5-8 years consultancy, wet and dry fire design and project management experience\nFamiliarize with Hong Kong and Macau fire service department regulation and submission process\nProficient in AutoCAD application software and good command of computer knowledge\nUnderstand technical documents, specifications and design drawings\nProactive, team player, good project coordination, communication and organization skills\nGood command of both written and spoken English and Chinese\n\n\nWe support and encourage long-term career development and offer competitive remuneration package to the successful candidate.\u00a0 Applications with detailed resume, present and expected salaries, date of availability and contact telephone number via the below button \u201cAPPLY NOW\u201d.\n\n(Personal data collected will be used for recruitment purposes only.)", "employment_types": ["Full Time", "Permanent"], "selling_points": [], "locations": ["Kowloon Bay"], "categories": ["Admin & HR", "Clerical / Admin Staff", "Engineering", "Others", "Information Technology (IT)", "Others"], "post_time": "2022-01-18T01:13:17Z", "salary": {"currency": null, "max": null, "min": null, "period": "monthly", "term": null}, "salary_visible": false, "title_keywords": ["administrative clerk"], "responsibilities": ["provide support", "project planning", "engineering design", "guidelines", "tendering", "inspection", "project administration", "ad hoc assignments", "documentation", "support the team"], "requirements": {"degrees": ["diploma holder", "degree"], "majors": ["engineering"], "languages": ["english", "chinese"], "language_level": ["good command"], "hard_skills": ["project management", "submission process", "autocad"], "soft_skills": ["communication", "project management", "coordination", "organization skills", "team player", "proactive", "detailed"], "languages_combined": [{"language": "english", "language_level": ["good command"]}, {"language": "chinese", "language_level": ["good command"]}]}, "experience_required": {"duration": ["5-8 years"], "field": ["project management", "design"]}}, {"job_id": "100003009048537", "location_code": "hk", "company": "Kum Shing Group", "job_title": "Project Engineer - Civil", "description": "Responsibilities\nResponsible for project designs and submissions preparation for conveyor project at airport\nPerform installation planning and monitor sub-contractor works\nSupport tender biding and follow up with the project installation progress\nAssist in design enhancement work to cover modification in mechanical aspect\nMaintain good relationships with clients and business partners\nMonitor all site safety, quality and environmental matters\nRequirements\nDegree in Mechanical Engineering or related disciplines\n3-4 years' working experience in large E&M installation project\nOrganized, self-motivated and cooperative\nGood command of English and proficient in computer skills\nPlease click \"Apply Now\" to submit your application.\n\nPersonal data collected will be used for recruitment purpose only.", "employment_types": ["Full Time", "Permanent"], "selling_points": ["Performance bonus, education subsidy, medical plan", "Excellent career path", "Participate in project planning & site supervision"], "locations": ["To Kwa Wan"], "categories": ["Building & Construction", "Building / Construction / QS", "Civil / Structural", "Engineering", "Others"], "post_time": "2022-01-14T06:45:24Z", "salary": {"currency": null, "max": null, "min": null, "period": "monthly", "term": null}, "salary_visible": false, "title_keywords": ["project engineer"], "responsibilities": ["installation", "monitor", "quality", "design", "maintain", "tender", "planning"], "requirements": {"degrees": ["degree"], "majors": ["related disciplines", "mechanical engineering"], "languages": ["english"], "language_level": ["good command", "proficient"], "hard_skills": ["computer skills"], "soft_skills": ["cooperative", "organized", "self-motivated"], "languages_combined": [{"language": "english", "language_level": ["proficient", "good command"]}]}, "experience_required": {"duration": ["3-4 years"], "field": ["installation"]}}, {"job_id": "100003009046372", "location_code": "hk", "company": "Otis Elevator Co (HK) Limited", "job_title": "Safety Officer", "description": "Job Responsibilities:\nWork closely with design teams to develop and explore intellectual property opportunities;\nResearch and analyze inventions and patent information and to identify prior arts;\nConduct patent research of intellectual property such as novelty search, infringement research to identify patent assets before patent application;\nLiaise with external parties such as attorneys and inventors to define patent specification, and follow up and review documents;\nAssist in registration and renewal of patent both locally and internationally;\nPerform administrative duties such as maintain database for IP, filing applications and granted patents.\nJob Requirements:\nB.Sc or above in Engineering / Law or equivalent;\nWith at least 1-year relevant experience in the areas of IP / patent administration;\nGood command in both English and Chinese (include Mandarin);\nHighly sensitive to timelines and meeting deliverables;\nCandidate with more experience will be consider as IP Manager.", "employment_types": ["Full Time", "Permanent"], "selling_points": ["13-month bonus + performance bonus", "Employee Scholar Program up to $160,000", "Innovative development in EH&S strategies & plans"], "locations": ["Kowloon Bay"], "categories": ["Engineering", "Mechanical", "Others", "Others", "Security / Safety Control"], "post_time": "2022-01-13T10:46:43Z", "salary": {"currency": null, "max": null, "min": null, "period": "monthly", "term": null}, "salary_visible": false, "title_keywords": ["safety officer"], "responsibilities": ["external parties", "teams", "review", "design", "develop", "maintain", "administrative duties", "database", "liaise with"], "requirements": {"degrees": [], "majors": [], "languages": ["english", "chinese", "mandarin"], "language_level": ["good command"], "hard_skills": ["ip"], "soft_skills": ["sensitive to"], "languages_combined": [{"language": "english", "language_level": ["good command"]}, {"language": "chinese", "language_level": ["good command"]}, {"language": "mandarin", "language_level": ["good command"]}]}, "experience_required": {"duration": ["at least 1-year"], "field": ["relevant experience", "administration"]}}, {"job_id": "100003009051711", "location_code": "hk", "company": "ASM Technology Hong Kong Limited", "job_title": "Test Engineer", "description": "Degree holder in Civil Engineering or equivalent with relevant professional qualification such as MHKIE / MICE\nMinimum 5 years\u2019 working experience in drainage / sewerage / waterworks projects for public and private projects\nSelf-motivated, logical and systematic thinkers\nGood communication skills and proficient in written and spoken English and Chinese\nPlease send your full resume with expected salary and availability(quoting reference number) to:\n\n\nHuman Resources Manager\nMeinhardt Consulting Engineers\n10/F Genesis, 33-35 Wong Chuk Hang Road, Hong Kong\n\nOR send e-mail by clicking \"Apply Now\" \u00a0\u00a0\u00a0 http://www.meinhardtgroup.com\n\nCandidates who have not been contacted within 8 weeks of their date of application may assume their application has been unsuccessful. Data collected will be used for recruitment purpose only and will be destroyed after six months from date of application.", "employment_types": ["Full Time", "Permanent"], "selling_points": ["Minimum 1 years relevant working experience", "Degree or above in Mechatronics", "Define test plan & create test cases for products"], "locations": ["Tsing Yi"], "categories": ["Engineering", "Electrical / Electronics", "Mechanical", "Others"], "post_time": "2022-01-16T21:51:01Z", "salary": {"currency": null, "max": null, "min": null, "period": "monthly", "term": null}, "salary_visible": false, "title_keywords": ["engineer"], "responsibilities": ["communication", "recruitment", "consulting", "data"], "requirements": {"degrees": ["degree holder"], "majors": ["civil engineering"], "languages": ["english", "chinese"], "language_level": ["proficient", "good"], "hard_skills": ["mhkie"], "soft_skills": ["communication skills", "self-motivated", "systematic"], "languages_combined": [{"language": "english", "language_level": ["proficient", "good"]}, {"language": "chinese", "language_level": ["proficient", "good"]}]}, "experience_required": {"duration": ["minimum 5 years"], "field": ["drainage"]}}, {"job_id": "100003009053526", "location_code": "hk", "company": "Aurecon Hong Kong Limited", "job_title": "Environmental Consultant / Assistant Environmental Consultant", "description": "ASM is a high-tech manufacturer involved in the development, manufacturing and marketing of semiconductor assembly equipment and materials. To cope with our strategic planning, we are looking for this incumbent to support on project management by ensuring the projects are executed within scope, on time, on budget, and with requirements met. In addition, the incumbent will assists project manager in the full spectrum of project lifecycle.\n\nJob Responsibilities\n\nAssist project management on maintain project plans and schedules, and ensures the project requirements are defined and meet the project\u2019s objectives\nEnsures all project milestones and deliverables are documented, approved, and stored for reusability, support, and audit purposes in designated project tools\nPrepare regular reports on project budgets, financial forecasts, and tracks actual costs and variance to the approved budget\nFinalizes projects by ensuring all necessary close-down and transition steps are taken and documented\nWorks with Management and other Project Managers to develop processes to maintain dependency tracking, and ensures project dependencies are identified and managed\nAssists in other areas of the department and company as necessary\nJob Requirements\u00a0\n\nBachelor\u2019s degree in Engineering discipline is preferred\n1-2 years of experience with engineering equipment development is preferrable\nFluent in spoken and written English, Chinese and Mandarin\nAnalytical and problem-solving ability\nDetail-oriented mindset\nStrong interpersonal skills, with the ability to build positive working relationships with diverse teams in a dynamic environment\n\n\n\nAttractive salary and fringe benefits package will be offered to the right candidates.\n\nInterested parties please submit your application with cover letter, resume, certificate and transcripts.\n\nData collected will be used for recruitment purpose only. Suitable candidates may be referred to other vacancies within our company.", "employment_types": ["Full Time", "Permanent"], "selling_points": ["1-5 years of Experience", "Good organisation, multi-tasking skill", "Competitive Remuneration Package"], "locations": ["Kwun Tong"], "categories": ["Engineering", "Others"], "post_time": "2022-01-17T07:06:00Z", "salary": {"currency": null, "max": null, "min": null, "period": "monthly", "term": null}, "salary_visible": false, "title_keywords": ["assistant", "environmental consultant"], "responsibilities": ["project requirements", "budgets", "management", "schedules", "budget", "audit", "develop", "project management", "maintain", "reports", "plans", "costs", "tracking"], "requirements": {"degrees": ["degree", "bachelor"], "majors": ["engineering"], "languages": ["english", "chinese", "mandarin"], "language_level": ["fluent"], "hard_skills": ["problem-solving"], "soft_skills": ["problem-solving"], "languages_combined": [{"language": "english", "language_level": ["fluent"]}, {"language": "chinese", "language_level": ["fluent"]}, {"language": "mandarin", "language_level": ["fluent"]}]}, "experience_required": {"duration": ["1-2 years"], "field": ["development", "engineering"]}}, {"job_id": "100003009049831", "location_code": "hk", "company": "Hays", "job_title": "(Senior) Services Engineer - Medical Devices", "description": "\u5de5\u4f5c\u8077\u8cac:\n\n\u5354\u52a9\u6cb9\u5eab\u4e3b\u7ba1\u6839\u64da\u5de5\u4f5c\u6307\u5f15\u5c0d\u6536\u767c\u7531\u7522\u54c1\u9032\u884c\u5b89\u5168\u53ca\u9ad8\u6548\u7684\u65e5\u5e38\u64cd\u4f5c\n\u5354\u52a9\u6cb9\u5eab\u4e3b\u7ba1/\u79d1\u6587\u76e3\u7763\u627f\u5305\u5546\u57f7\u884c\u548c\u9075\u5b88\u9069\u7528\u7684\u516c\u53f8\u653f\u7b56\u548c\u7a0b\u5e8f\uff0c\u91cd\u9ede\u662f\u5b89\u5168\u63a7\u5236\u548c\u9054\u81f3\u5b8c\u5584\u64cd\u4f5c\u7684\u76ee\u6a19\n\u6309\u7167\u8655\u7406\u61c9\u8ab2\u7a05\u54c1\u548c\u5371\u96aa\u54c1\u7684\u76f8\u95dc\u898f\u5b9a\uff0c\u57f7\u884c\u65e5\u5e38\u4efb\u52d9\n\u5728\u4e3b\u7ba1/\u79d1\u6587\u7684\u6307\u5c0e\u4e0b\uff0c\u57f7\u884c\u8239\u8259\u6cb9\u7522\u54c1\u54c1\u8cea\u53d6\u6a23\u548c\u8a08\u91cf\u4e4b\u5de5\u4f5c\uff1b\u99c1\u8239\u88dd\u5378\u7b49\u5de5\u4f5c\n\u9700\u4e8c\u5341\u56db\u5c0f\u6642\u8f2a\u73ed\u5de5\u4f5c(\u5305\u62ec\u7bc0\u65e5\u5047\u671f\u53ca\u98b1\u98a8\u671f\u9593)\n\u4fdd\u6301\u9ad8\u6a19\u6e96\u7684\u5b89\u5168\u8077\u8cac\uff0c\u4e26\u57f7\u884c\u7dca\u6025\u61c9\u8b8a\u64cd\u4f5c\n\u71df\u904b\u7d93\u7406/\u4e3b\u7ba1/\u79d1\u6587\u6307\u5b9a\u5176\u4ed6\u8077\u8cac\uff0c\u5982\u9700\u8981\u64cd\u4f5c\u540a\u6a5f\uff0c\u8239\u96bb\u7e6b\u7e9c\u53ca\u78bc\u982d\u6709\u95dc\u7b49\u4e4b\u5de5\u4f5c\n\n\u00a0\u8981\u6c42\uff1a\n\n\u4e2d\u4e94\u7a0b\u5ea6\u6216\u4ee5\u4e0a\n\u5177\u6cb9\u5eab/\u8239\u8236\u78bc\u982d/\u540a\u6a5f\u64cd\u4f5c\u7d93\u9a57\u3001\u884c\u696d\u77e5\u8b58\uff0c\u6216\u8b66\u885b\u724c\u7167\u8005\u512a\u5148\n\u80fd\u95b1\u8b80\u53ca\u5beb\u4f5c\u4e2d\u6587\u548c\u64cd\u6d41\u5229\u5ee3\u6771\u8a71\uff0c\u4e26\u80fd\u95b1\u8b80\u7406\u89e3\u7c21\u55ae\u82f1\u8a9e\n\u5177\u826f\u597d\u9ad4\u683c\u4ee5\u61c9\u4ed8\u63d0\u8209\u91cd\u7269\u53ca\u7c97\u91cd\u5de5\u4f5c\uff0c\u4e26\u80fd\u61c9\u4ed8\u6236\u5916\u5de5\u4f5c\n\u5de5\u4f5c\u614b\u5ea6\u7a4d\u6975\u4e3b\u52d5\uff0c\u80fd\u627f\u53d7\u5de5\u4f5c\u58d3\u529b\uff0c\u5177\u8cac\u4efb\u611f\n\n\u5728\u8fd9\u91cc\u7533\u8bf7", "employment_types": ["Full Time", "Permanent"], "selling_points": ["MNC working environment", "Stable Working Opportunity", "Competitive Package"], "locations": ["Not Specified"], "categories": ["Engineering", "Electrical / Electronics", "Others"], "post_time": "2022-01-14T09:18:05Z", "salary": {"currency": "HKD", "max": 29999, "min": 25000, "period": "monthly", "term": null}, "salary_visible": true, "title_keywords": ["engineer"], "responsibilities": [], "requirements": {"degrees": [], "majors": [], "languages": [], "language_level": [], "hard_skills": [], "soft_skills": [], "languages_combined": []}, "experience_required": {"duration": [], "field": []}}, {"job_id": "100003009053232", "location_code": "hk", "company": "Transport Infrastructure Management Limited", "job_title": "Technician (E & M / Electronic / Vehicles & Heavy Mechanical)", "description": "Responsibilites:\n-Handle all rounded HR functions\n-Provide administrative support to the office\n-Perform ad-hoc tasks as assigned\n\nRequirements:\n\n- Diploma or above in business related discipline, English passed in HKCEE/DSE\n- Min. 2 years working experience, experience from Engineering company is\u00a0preferable\n- Good command of both written and spoken English\n- Familiar with MS Word, Excel and Chinese word processing\n- Self-motived, independent and a strong sense of responsibility\n\n\n\n\u00a0\nAn attractive remuneration package will be offered to the right candidate. \u00a0Interested parties, please send full resume with your expected salary by clicking \"APPLY NOW\".\n\n\n\nPersonal data collected will be used for recruitment purpose only", "employment_types": ["Full Time", "Permanent"], "selling_points": ["Holder of Certificate / Diploma", "At least 2 years' working experience", "holder of Safety Green Card"], "locations": ["Not Specified"], "categories": ["Engineering", "Others", "Others", "Technician"], "post_time": "2022-01-17T06:30:05Z", "salary": {"currency": null, "max": null, "min": null, "period": "monthly", "term": null}, "salary_visible": false, "title_keywords": ["technician"], "responsibilities": ["hr", "ad-hoc tasks", "administrative support"], "requirements": {"degrees": ["diploma or above", "dse"], "majors": ["business"], "languages": ["english", "chinese"], "language_level": ["good command"], "hard_skills": ["excel", "chinese word processing", "ms word"], "soft_skills": ["independent", "sense of responsibility"], "languages_combined": [{"language": "english", "language_level": ["good command"]}, {"language": "chinese", "language_level": []}]}, "experience_required": {"duration": ["2 years"], "field": ["engineering"]}}, {"job_id": "100003009039480", "location_code": "hk", "company": "CLP Power Hong Kong Limited", "job_title": "Senior Technical Officer (2-Year Contract) [Ref. CLPP-PSBG-WER-OB-STO]", "description": "Responsibilities:\n\nResponsible for all-round office administrative and clerical support;\nCommunicate\u00a0with\u00a0teammates and vendors and follow up procurement status in daily operations;\nMaintain stock and procurement of office supplies;\nAssist in ad-hoc duties assigned by supervisor\n\nRequirements:\n\nDiploma or above;\nExperience in IT industry is an advantage;\nA good team player, energetic and enthusiastic;\nWell-organised and detailed minded;\nProficient with MS Office applications;\nGood command in English and Cantonese;\nFresh graduates are welcome\nYou have a career opportunity in gaining knowledge and experience in serving one of the largest Data Center providers for local and international enterprises.\n\n\nAn attractive remuneration package and fringe benefits will be offered to the right candidate. Interested parties, we appreciate it if you\u00a0must send your resume stating with current and expected salary\u00a0to the Human Resources Department\u00a0by\u00a0clicking\u00a0Apply Now.\n\nFor more information, please visit our website at\u00a0http://www.oneas1a.com\nAll information collected will be kept strictly confidential and for recruitment purpose only.", "employment_types": ["Full Time", "Contract"], "selling_points": [], "locations": ["Not Specified"], "categories": ["Engineering", "Electrical / Electronics", "Others"], "post_time": "2022-01-13T18:54:47Z", "salary": {"currency": null, "max": null, "min": null, "period": "monthly", "term": null}, "salary_visible": false, "title_keywords": ["senior technical officer"], "responsibilities": ["communicate with", "office supplies", "daily operations", "maintain", "administrative and clerical support", "ad-hoc duties"], "requirements": {"degrees": ["diploma or above"], "majors": [], "languages": ["cantonese", "english"], "language_level": ["good command"], "hard_skills": ["ms office"], "soft_skills": ["good team player", "enthusiastic", "well-organised", "energetic", "detailed"], "languages_combined": [{"language": "cantonese", "language_level": ["good command"]}, {"language": "english", "language_level": ["good command"]}]}, "experience_required": {"duration": [], "field": ["it"]}}]