[{"job_id": "100003009052661", "location_code": "hk", "company": "China Mobile International Limited", "job_title": "IP Network Engineer (Ref: CMIJD-0117-IPENOMHK)", "description": "\u00a0Job Description:\n\nIP network configuration, including switches and routers of Cisco, Huawei, Juniper\nManage network resources, including POPs, connectivity capacity and network devices\nParticipate in network projects for smooth implementation\nCoordinate with external vendors for delivery of required services\nSupport Management on ad hoc report compilation\u00a0\n\n\u00a0Job\u00a0Requirement:\n\nBachelor Degree or above\u00a0in Information Technology, Computer Science or other related disciplines\nMinimum\u00a03 years of experience; with telecom experiences are preferred\nKnowledge of IP network, IP routing knowledge or MPLS, VPN\nOrganized, proactive and\u00a0a good team-player\nMature, independent and problem-solver\u00a0\nExcellent written and spoken English, Chinese and Mandarin\n\nInterested parties please send your full resume with current & expected salary\u00a0by e-mail to\u00a0hr @ cmi.chinamobile.com.\u00a0 Please indicate the reference in the subject line.\n\nAll personal data provided will be used for consideration of your job application only.", "employment_types": ["Full Time", "Permanent"], "selling_points": ["IP Network managemnet", "Network project", "Stable work environment"], "locations": ["Kwai Hing"], "categories": ["Engineering", "Engineering Project Management", "Telecommunication / Wireless / Radio", "Information Technology (IT)", "Network & System"], "post_time": "2022-01-17T03:39:38Z", "salary": {"currency": null, "max": null, "min": null, "period": "monthly", "term": null}, "salary_visible": false, "title_keywords": ["engineer"], "responsibilities": ["management", "configuration", "ad hoc report", "coordinate with", "implementation"], "requirements": {"degrees": ["degree or above", "bachelor"], "majors": ["related disciplines", "computer science", "information technology"], "languages": ["english", "chinese", "mandarin"], "language_level": ["excellent"], "hard_skills": ["ip", "vpn"], "soft_skills": ["organized", "independent", "team-player", "mature", "proactive"], "languages_combined": [{"language": "english", "language_level": ["excellent"]}, {"language": "chinese", "language_level": ["excellent"]}, {"language": "mandarin", "language_level": ["excellent"]}]}, "experience_required": {"duration": ["minimum 3 years"], "field": []}}, {"job_id": "100003009054234", "location_code": "hk", "company": "BAI Communications Limited", "job_title": "Radio Network Maintenance Engineer", "description": "Your role\n\nLead a small team to support mobile core network and maintain mobile services by fast restoration\nManage the change request in mobile core network to support new requirements or network enhancement raised from planning team\nSetup and perform routine checking of mobile core network to identify the potential risk in early stage\nFollow up outstanding problem of mobile core network with vendor and planning team to ensure stability of mobile services\nMonitor the performance of mobile core network in order to keep track of service quality and performance trend\nAttend shift duties and emergency support outside normal working hours when necessary\n\nTo succeed in the role\n\nDegree / High Diploma holder in Electronics, Information Technology, Communication or related disciplines with minimum 5 years\u2019 relevant experience in mobile communication and server administration\nTechnical and practical knowledge in managing and supporting mobile core network, such as mobile CS/IMS core network, mobile PS and IPBB network, and network management tools\nExcellent analytical, communication and customer handling skills\nProvident in written and spoken English and Chinese\nSelf-motivated and able to work independently under high pressure\nKnowledge in fault management and experience in supervision of small team will be an advantage\n\nIf you have the desire for an exciting and rewarding career, please send us your resume, quoting the reference number, your present and expected salary by Whatsapp, email or post to the Human Resources Department.\n\n\u00a0Whatsapp:\u00a05410 6137\n\nPost: HR-ENGINEERING, 13/F, Lai Chi Kok Engineering Center, 4 Yuet Lun Street, Lai Chi Kok, Kowloon.on other job opportunities of PCCW, please visit our website at http://www.pccw.com/Careers/Job+Opportunities+%26+Application/Current+Opportunities?language=en_US", "employment_types": ["Full Time"], "selling_points": ["Radio Network Maintenance Engineer", "Cellar Network Maintenance", "Telecom Network Maintenance"], "locations": ["Kwun Tong Area"], "categories": ["Engineering", "Electrical / Electronics", "Telecommunication / Wireless / Radio", "Others"], "post_time": "2022-01-17T08:52:28Z", "salary": {"currency": null, "max": null, "min": null, "period": "monthly", "term": null}, "salary_visible": false, "title_keywords": ["engineer"], "responsibilities": ["administration", "management", "lead a small team", "hr", "quality", "website", "communication", "maintain", "monitor the performance", "routine checking", "setup", "planning"], "requirements": {"degrees": ["high diploma", "degree"], "majors": ["related disciplines", "information technology"], "languages": ["english", "chinese"], "language_level": [], "hard_skills": ["small", "network management", "server administration", "vendor", "mobile", "whatsapp"], "soft_skills": ["communication", "self-motivated", "work independently"], "languages_combined": [{"language": "english", "language_level": []}, {"language": "chinese", "language_level": []}]}, "experience_required": {"duration": ["minimum 5 years"], "field": ["management", "server administration", "related", "information technology", "relevant experience", "team"]}}, {"job_id": "100003009052340", "location_code": "hk", "company": "Hong Kong Broadband Network Limited", "job_title": "Engineer ( Data Center Facility Management )", "description": "Your role\n\nLead a team to build and manage the network / data center\nCarry out equipment installation and restoration, service provision for voice, broadband, data, mobile and / or network\nDevelop the guideline, procedures on operation process and workflow\nAssist the superior for trouble shooting, escalation and decision making on emergency situation during network incident handling\nTrain up new team members to be a capable technical operation and support member.\n\nTo succeed in the role\n\nBachelor degree in Information Technology, Computer Science, Communication Engineering, Electronic Engineering or related disciplines with 3 years of operation / support experience in voice, broadband, data, mobile and / or cloud network / systems and related network management systems\nExcellent technical skills and hands-on experience in managing networking devices and deploying network management systems\nGood supervisory, analytical and troubleshooting skills\nProficient in spoken and written in both English and Chinese\nSelf-motivated, flexible and able to work independently under high pressure\nCandidate with less experience or lower qualifications (Higher Diploma / Diploma in related disciplines) will be considered as\u00a0Senior Technical Officer\n\nIf you have the desire for an exciting and rewarding career, please send us your resume, quoting the reference number, your present and expected salary by Whatsapp, email or post to the Human Resources Department.\n\n\u00a0Whatsapp:\u00a05410 6137\n\nPost: HR-ENGINEERING, 13/F, Lai Chi Kok Engineering Center, 4 Yuet Lun Street, Lai Chi Kok, Kowloon.on other job opportunities of PCCW, please visit our website at http://www.pccw.com/Careers/Job+Opportunities+%26+Application/Current+Opportunities?language=en_US", "employment_types": ["Full Time", "Permanent"], "selling_points": ["Talent-first Culture & LIFE-work priority", "Execute improvement projects for E&M facility", "Monitor E&M facility performance"], "locations": ["Kwai Hing"], "categories": ["Engineering", "Telecommunication / Wireless / Radio", "Information Technology (IT)", "Network & System", "Technical / Functional Consulting"], "post_time": "2022-01-17T02:48:21Z", "salary": {"currency": null, "max": null, "min": null, "period": "monthly", "term": null}, "salary_visible": false, "title_keywords": ["engineer"], "responsibilities": ["installation", "management", "data", "hr", "systems", "procedures", "troubleshooting", "website", "develop", "communication", "lead a team"], "requirements": {"degrees": ["diploma", "degree", "bachelor"], "majors": ["related disciplines", "engineering", "computer science", "information technology"], "languages": ["english", "chinese"], "language_level": ["proficient"], "hard_skills": ["network management", "mobile", "whatsapp"], "soft_skills": ["flexible", "self-motivated", "work independently", "capable", "troubleshooting", "communication", "hands-on", "technical skills", "superior", "decision making"], "languages_combined": [{"language": "english", "language_level": ["proficient"]}, {"language": "chinese", "language_level": ["proficient"]}]}, "experience_required": {"duration": ["3 years"], "field": ["management", "engineering", "related", "information technology", "operation"]}}, {"job_id": "100003009052186", "location_code": "hk", "company": "Equinix Hong Kong Ltd", "job_title": "Data Center Lead Facility Engineer (Career Transition Program)", "description": "The candidate will report to the Engineer for technical design, system implementation, planned and corrective maintenance of both or either one of the following streams:\n\nExtra Low Voltage (ELV) stream\nVoice & Data Cabling (VDC),\nPublic Address (PAS),\nClosed Circuit Television (CCTV),\nTrunk Mobile Radio (TMR), or\nAccess Control (ACS), etc.\nInformation & Communication Technology (ICT) stream\nWindows / Linux / Cloud based Environment,\nNetworking / Database / Data Storage, or\nSoftware Development, etc.\nData Analytic will be an advantage.\nPlan & supervise contractors and control workmanship for various ELV / ICT projects\nManage the work progress, including design submissions, factory inspections, site works, testing and commissioning activities, defect rectifications and as-built drawings preparation\nAssist in the coordination with various internal and external parties to ensure that interfaces and works programme are achieved.\nOvertime work might require\nMight work in Hong Kong International Airport\n\nRequirements:\n\nHigh Diploma / Degree in Electronic, Computer Engineering, Computer Science, IT, or equivalent.\nFor Assistant Engineer, at least three (3) years ELV / ICT systems working experience (with 3 years playing the design and planning / supervisory role);\nFor Senior Technical Officer, at least two (2) years ELV / ICT systems working experience (with 1 years playing the design and planning / supervisory role);\nFor Technical Officer, at least one (1) years related working experience.\nGood in documentation and writing skills.\nGood in communication and interpersonal skill.\nProficiency in Microstation and/or AutoCAD is an advantage.\nFluency in written and spoken English and Cantonese; Mandarin will be an advantage.\nHave Green Card and Construction Worker Registration Card are essential.\nHave valid HK Type 1 & Type 2 driving license is an advantage.", "employment_types": ["Full Time"], "selling_points": ["Site Administration", "Performs preventative maintenance on site", "Leads repairs and corrective maintenance"], "locations": ["Tseung Kwan O"], "categories": ["Engineering", "Engineering Project Management", "Telecommunication / Wireless / Radio"], "post_time": "2022-01-17T02:23:31Z", "salary": {"currency": null, "max": null, "min": null, "period": "monthly", "term": null}, "salary_visible": false, "title_keywords": ["facility engineer", "lead"], "responsibilities": ["software", "supervise contractors", "data", "coordination with", "internal and external parties", "design", "drawings", "communication", "database", "plan", "control", "implementation", "testing", "closed circuit television", "report", "commissioning", "documentation", "maintenance", "systems", "access control", "planning"], "requirements": {"degrees": ["high diploma", "degree"], "majors": ["it", "computer engineering", "computer science"], "languages": ["cantonese", "english", "mandarin"], "language_level": ["fluency", "advantage"], "hard_skills": ["linux", "documentation", "maintenance", "cctv", "writing skills", "green card", "mobile", "system implementation", "data storage", "autocad"], "soft_skills": ["writing skills", "interpersonal skill", "communication", "overtime work", "coordination"], "languages_combined": [{"language": "cantonese", "language_level": ["fluency"]}, {"language": "english", "language_level": ["fluency"]}, {"language": "mandarin", "language_level": ["advantage"]}]}, "experience_required": {"duration": ["3 years", "1 years"], "field": ["related", "supervisory", "design", "planning"]}}, {"job_id": "100003009053247", "location_code": "hk", "company": "Classy Wheeler Limited", "job_title": "Technical Director / Operations Manager (Data Network) (Regional Telecom Carrier)", "description": "We are searching for a Site Supervisor for our client, it's a client representative role for a newly awarded ELV project:\n\nResponsibilities:\n\nMonitor day-to-day site work progress and contractor workmanship to ensure project delivery quality\nSupervise contractor safety and work performance\nRepresent Enginneer or Engineer's representative to attend and witness system testing and commissioning\nSite coordination and resolve construction site issues to ensure timely delivery of project works\n\nRequirements:\n\nDiploma or above in Electronics Engineering / Electrical Engineering/ Computer and Information Engineering or equivalent\nAt least 3 years' relevant experience in site coordination and project implementation of telecommunications, electronic or information & communications technology project or equivalent\nPossess a valid Construction Industry Safety Training Certificate", "employment_types": ["Full Time", "Permanent"], "selling_points": ["Regional IT services and solutions provider", "Technical / NOC operations management", "Stable environment, attractive renumeration"], "locations": ["Tsuen Wan Area"], "categories": ["Engineering", "Telecommunication / Wireless / Radio", "Information Technology (IT)", "IT Management", "Mobile / Wireless Communications"], "post_time": "2022-01-17T06:31:27Z", "salary": {"currency": null, "max": null, "min": null, "period": "monthly", "term": null}, "salary_visible": false, "title_keywords": ["operations manager", "director"], "responsibilities": ["commissioning", "quality", "monitor", "testing", "site coordination"], "requirements": {"degrees": ["certificate", "diploma or above"], "majors": ["engineering", "electrical engineering"], "languages": [], "language_level": [], "hard_skills": [], "soft_skills": ["coordination"], "languages_combined": []}, "experience_required": {"duration": ["at least 3 years"], "field": ["telecommunications", "relevant experience"]}}, {"job_id": "100003009053453", "location_code": "hk", "company": "PERSOL Hong Kong", "job_title": "(Urgent!!) Electrical Engineer", "description": "Job Description:\u00a0\n\nOnsite deliver networking services to our corporate customers.\nYour work include provisioning, troubleshooting and maintenance support services for networking.\nOn job trainings will be provided to the right candidate.\nNon-Office hours emergency call support is required.\n\nRequirements:\n\nHigher Diploma or above in Telecommunication and Networking or related discipline\nExperience in Cisco Router/Switch, Firewall, VPN\nCertificate holder of Cisco CCNA or higher is preferred\nRelated working experience in ISP, SI vendor or network support is definite a value added\nKnowledge in OSPF, EIGRP, BGP, MPLS, VoIP is an advantage\nExperience in SDWAN would be preferred\u00a0\nFluent in Cantonese, conversable in English and Mandarin\nAble to work under pressure, willing to work overtime\nFresh Graduate will also be considered\n\nAttractive remuneration and compensation package, including year end bonus, medical scheme as well as career development opportunities will be offered.\u00a0\n\nInterested parties please send your resume with expected salary and availability to Human Resources Department, Dyxnet Group, 37/F, Tower 1, Metorplaza, 223 Hing Fong Road, Kwai Fong.\u00a0\n\nWelcome to visit our website:\u00a0http://www.dyxnet.com/\u00a0for further information of our company.\u00a0\n\nData collected will be used for recruitment purpose only.", "employment_types": ["Full Time", "Contract"], "selling_points": ["Excellent salary package + bonus", "Good promotion / training opportunity", "3-yr exp in E&M/HVAC/MVAC/P&D"], "locations": ["Shatin Area"], "categories": ["Engineering", "Electrical / Electronics", "Engineering Project Management", "Telecommunication / Wireless / Radio"], "post_time": "2022-01-17T07:00:09Z", "salary": {"currency": "HKD", "max": 44999, "min": 35000, "period": "monthly", "term": null}, "salary_visible": true, "title_keywords": ["electrical engineer"], "responsibilities": ["maintenance support", "troubleshooting"], "requirements": {"degrees": ["certificate", "higher diploma or above", "fresh graduate"], "majors": [], "languages": ["cantonese", "english", "mandarin"], "language_level": ["fluent"], "hard_skills": ["switch", "ccna", "vendor", "scheme", "router", "vpn", "firewall"], "soft_skills": ["work overtime", "work under pressure"], "languages_combined": [{"language": "cantonese", "language_level": ["fluent"]}, {"language": "english", "language_level": []}, {"language": "mandarin", "language_level": []}]}, "experience_required": {"duration": [], "field": ["related"]}}, {"job_id": "100003009051268", "location_code": "hk", "company": "China Mobile International Limited", "job_title": "Mobile Network Engineer (Ref:CMIJD-0115-NWNOCEHK)", "description": "Your role\n\nResponsible for voice over IP network and traditional voice network planning\nUpdate voice feature testing & voice network inventory\nTest and verify voice over IP phone and feature\nPlan voice system migration\nPrepare the Installation Request diagram drawing\n\nTo succeed in the role\n\nDegree / High Diploma in Information Technology, Computer Science, Communication\u00a0Engineering or related disciplines with minimum 3 years\u2019 relevant experience in telecommunication industry\nInterested in developing technical knowledge on voice over IP technologies\nKnowledge or experience in the following areas will be an advantage\nIP Networking\nVoIP SIP protocol, ISUP signaling\nVoice system inter-working with other operators\nCloud computing technology\nGood analytical and problem solving skills\nProvident in written and spoken English and Chinese\nCandidate with less experience will be considered as Technical Officer", "employment_types": ["Full Time", "Permanent"], "selling_points": ["7x24 shift duty", "Transportation allowance", "Team-work oriented"], "locations": ["Tseung Kwan O"], "categories": ["Engineering", "Telecommunication / Wireless / Radio", "Information Technology (IT)", "Network & System", "Mobile / Wireless Communications"], "post_time": "2022-01-15T06:59:23Z", "salary": {"currency": null, "max": null, "min": null, "period": "monthly", "term": null}, "salary_visible": false, "title_keywords": ["engineer"], "responsibilities": ["installation", "inventory", "developing", "testing", "communication", "plan", "migration", "planning"], "requirements": {"degrees": ["high diploma", "degree"], "majors": ["related disciplines", "engineering", "computer science", "information technology"], "languages": ["english", "chinese"], "language_level": [], "hard_skills": ["ip", "problem solving skills"], "soft_skills": ["communication", "analytical and problem solving skills", "interested in", "responsible"], "languages_combined": [{"language": "english", "language_level": []}, {"language": "chinese", "language_level": []}]}, "experience_required": {"duration": ["minimum 3 years"], "field": ["related", "relevant experience", "engineering", "information technology"]}}, {"job_id": "100003009051267", "location_code": "hk", "company": "China Mobile International Limited", "job_title": "(Assistant) Engineer, Mobile Service (Ref: CMIJD-0103-AENOMHK)", "description": "We are searching for our client for a AV Engineer, it's a client representative role and below you may find the job details:\n\nResponsibilities:\n\nExecute Audiovisual projects professionally\nRepresent client and liaise with sub contractor in project coordination\nManage external resources and support teammates to complete project fully\n\nRequirements:\n\nDiploma or above in Electronic Engineering, Electrical Engineer or related disciplines\nMinimum 3 years relevant experiences\nCandidates with less experience will be considered as Assistant Engineer\nGood command of spoken and written English & Chinese", "employment_types": ["Full Time", "Permanent"], "selling_points": ["Mobile network development", "Career growth opportunity", "Friendly working environment"], "locations": ["Kwai Hing"], "categories": ["Engineering", "Electrical / Electronics", "Telecommunication / Wireless / Radio", "Information Technology (IT)", "Mobile / Wireless Communications"], "post_time": "2022-01-15T06:58:56Z", "salary": {"currency": null, "max": null, "min": null, "period": "monthly", "term": null}, "salary_visible": false, "title_keywords": ["engineer", "assistant"], "responsibilities": ["liaise with", "project coordination"], "requirements": {"degrees": ["diploma or above"], "majors": ["related disciplines", "engineering"], "languages": ["english", "chinese"], "language_level": ["good command"], "hard_skills": [], "soft_skills": [], "languages_combined": [{"language": "english", "language_level": ["good command"]}, {"language": "chinese", "language_level": ["good command"]}]}, "experience_required": {"duration": ["minimum 3 years"], "field": []}}, {"job_id": "100003009050205", "location_code": "hk", "company": "Shun Hing Systems Integration Company Limited", "job_title": "Assistant Engineer (Electronic)/(Network)", "description": "Key Responsibilities\n\nCommunicate with customer at all levels to establish their specific business needs\nForm and build solution out of in-house standard and external 3rd party products\nPlan, design and build specific solution, bridging the customer's business needs\nRespond to functional and technical elements of RFIs/RFPs\nResponsible for technology consulting and solution presentation to target customer\nConvey customer business needs and requirements into Product and Development teams\nResponsible for monitoring of the support industry technology needs and service trends\n\nPerson Specifications\n\nUniversity graduate in Telecommunication, Computing Science, Information Technology or related discipline; Professional certificates, e.g. CCNP, CISSP, is a plus\nAround 5 years of\u00a0relevant experience in network and telecommunication solution design. Minimum 4 years as a telecommunication solution consulting role\nPossess strong industry specific understanding and a diverse set of technical knowledge on various types of networking technologies, like IP, MPLS, IPLC, Satellite, and value added services (e.g. security, data centre, etc),\u00a0experience in aviation industry, and actual knowledge on aviation network implementation and operation is definitely a plus\nExperience and familiarity of network planning, design, implementation and operation on large data network\nKnowledge in relevant technology trends and outlooks\nSelf-motivated with a proven track record in solutions consulting\u00a0including network connectivity and network design\nDemonstrate strong business sense\nExcellent verbal and written communication skills in both Chinese (Mandarin and Cantonese) and English, other languages are added advantage", "employment_types": ["Full Time", "Permanent"], "selling_points": [], "locations": ["Not Specified"], "categories": ["Engineering", "Electrical / Electronics", "Telecommunication / Wireless / Radio", "Information Technology (IT)", "Network & System"], "post_time": "2022-01-14T09:56:33Z", "salary": {"currency": null, "max": null, "min": null, "period": "monthly", "term": null}, "salary_visible": false, "title_keywords": ["assistant engineer"], "responsibilities": ["communicate with", "consulting", "data", "monitoring", "teams", "implementation", "design", "communication", "specifications", "plan", "planning"], "requirements": {"degrees": ["university graduate"], "majors": ["science", "information technology"], "languages": ["cantonese", "english", "chinese", "mandarin"], "language_level": ["advantage", "excellent"], "hard_skills": ["ip", "ccnp", "data network", "plus"], "soft_skills": ["communication skills", "self-motivated", "responsible", "business sense", "diverse", "presentation"], "languages_combined": [{"language": "cantonese", "language_level": ["advantage", "excellent"]}, {"language": "english", "language_level": ["advantage", "excellent"]}, {"language": "chinese", "language_level": ["advantage", "excellent"]}, {"language": "mandarin", "language_level": ["advantage", "excellent"]}]}, "experience_required": {"duration": ["5 years"], "field": ["design", "operation", "relevant experience", "security", "planning"]}}, {"job_id": "100003009054549", "location_code": "hk", "company": "China Mobile International Limited", "job_title": "Business Project Management Manager(CMIJD-1101-BPMMIBDCN)", "description": "Your role\n\nCo-ordinate with various parties for Broadband projects in business case preparation, and cost scenario studies\nCarry out business case performance tracking, monthly capex spending monitor / forecast, and to support procurement audit\nHandle equipment ordering and equipment disposal\nManage nowTV CDN channel assignment and management\n\nTo succeed in the role\n\nDegree in Engineering, Computer Science, Information Technology, Communication Engineering or related disciplines with minimum 2 years\u2019 relevant working experience\nFamiliar with MS Office\nStrong in handling financial figures with excellent analytical skill\nGood interpersonal and communication skills\nProficient in spoken and written in both English and Chinese\nResponsible, self-motivated, flexible attitude and independent\n\nIf you have the desire for an exciting and rewarding career, please send us your resume, quoting the reference number, your present and expected salary by Whatsapp, email or post to the Human Resources Department.\n\n\u00a0Whatsapp:\u00a05410 6137\n\nPost: HR-ENGINEERING, 13/F, Lai Chi Kok Engineering Center, 4 Yuet Lun Street, Lai Chi Kok, Kowloon.on other job opportunities of PCCW, please visit our website at http://www.pccw.com/Careers/Job+Opportunities+%26+Application/Current+Opportunities?language=en_US", "employment_types": ["Full Time", "Permanent"], "selling_points": ["Business Management", "Project", "International Business"], "locations": ["Kwai Hing"], "categories": ["Engineering", "Telecommunication / Wireless / Radio"], "post_time": "2022-01-17T09:57:32Z", "salary": {"currency": null, "max": null, "min": null, "period": "monthly", "term": null}, "salary_visible": false, "title_keywords": [], "responsibilities": ["cost", "management", "co-ordinate with", "hr", "capex", "monitor", "audit", "website", "communication", "forecast", "tracking"], "requirements": {"degrees": ["degree"], "majors": ["related disciplines", "engineering", "computer science", "information technology"], "languages": ["english", "chinese"], "language_level": ["proficient"], "hard_skills": ["whatsapp", "analytical skill", "ms office"], "soft_skills": ["flexible", "communication skills", "analytical skill", "self-motivated", "independent", "responsible", "communication", "interpersonal"], "languages_combined": [{"language": "english", "language_level": ["proficient"]}, {"language": "chinese", "language_level": ["proficient"]}]}, "experience_required": {"duration": ["minimum 2 years"], "field": ["related", "relevant working experience", "engineering", "information technology"]}}, {"job_id": "100003009052052", "location_code": "hk", "company": "China Mobile International Limited", "job_title": "Assistant Business Operations Manager (Ref: CMIJD-1213-ABOMPMHK)", "description": "Your role\n\nAssist an operation team to deliver project implementation service and maintenance support service to the customer\nCoach the operation team in the way of service delivery and improvement on their technical skills\nConduct preparation, equipment staging, installation and commissioning, network acceptance test and project document upon completion of the project\nAssist manager to review the daily service reports and take improvement actions\nCollaborate with internal parties the test plan, implementation plan and migration plan\nBuild the network documents to supervisor verify for the completed projects/installation\n\nTo succeed in the role\n\nDegree or Higher Diploma holders in Communications, Electronics, Information Technology or related disciplines with 2 years of relevant working experience in technologies\nA quick learner to explore new technologies and solutions\nHands-on experience with large-scale implementation and support\nA good team player with good communication, problem solving and interpersonal skills to deal with vendor and internal parties\nIn-depth hands-on technical knowledge of routing and switching and wireless network technology and product knowledge of Cisco, Juniper, Huawei, Fortinet, AWS, Azure or Google Cloud\nGood command of both written and spoken English", "employment_types": ["Full Time", "Permanent"], "selling_points": ["Bachelor's degree or above", "Data Analysis", "Cloud network products lifecycle management"], "locations": ["Kwai Hing"], "categories": ["Engineering", "Engineering Project Management", "Telecommunication / Wireless / Radio"], "post_time": "2022-01-17T01:58:06Z", "salary": {"currency": null, "max": null, "min": null, "period": "monthly", "term": null}, "salary_visible": false, "title_keywords": ["operations manager", "assistant"], "responsibilities": ["service delivery", "installation", "collaborate with", "commissioning", "maintenance support", "review", "implementation", "communication", "reports", "plan", "migration", "internal parties"], "requirements": {"degrees": ["diploma", "degree"], "majors": ["related disciplines", "communications", "information technology"], "languages": ["english"], "language_level": ["good command"], "hard_skills": ["azure", "maintenance", "vendor", "aws", "problem solving"], "soft_skills": ["good team player", "quick learner", "communication", "problem solving", "hands-on", "interpersonal skills", "technical skills"], "languages_combined": [{"language": "english", "language_level": ["good command"]}]}, "experience_required": {"duration": ["2 years"], "field": ["related", "relevant working experience", "information technology"]}}, {"job_id": "100003008995673", "location_code": "hk", "company": "Pricom Technology & System Limited", "job_title": "Project Engineer", "description": "Your role\n\nAssist supervisor to operate Data Center in high service level to meet the ISO Quality and Security Standard\nResolve network problem in Data Center\nOperate and maintain the building facilities inside Data Center\nManage customers on service provisioning and service restoration\nCarry out 7 x 24 shift duties in Data Center is required\n\nTo succeed in the role\n\nHigher Diploma/Higher Certificate in Information Technology, Computer Science, Communication Engineering with 2 years\u2019 experience in Data Center or less experience with strong recommendation will also be considered\nDSE graduated with 3 years\u2019 relevant experience or less experience with strong recommendation will also be considered\nHolder of related certifications e.g. CDCP, CCNA or ITIL\u00a0will be an advantage\nGood customer services and interpersonal skills\nA team player who is able to work independently\nProficient in spoken and written in both English and Chinese\n\nIf you have the desire for an exciting and rewarding career, please send us your resume, quoting the reference number, your present and expected salary by Whatsapp, email or post to the Human Resources Department.\n\n\u00a0Whatsapp:\u00a05410 6137\n\nPost: HR-ENGINEERING, 13/F, Lai Chi Kok Engineering Center, 4 Yuet Lun Street, Lai Chi Kok, Kowloon.on other job opportunities of PCCW, please visit our website at http://www.pccw.com/Careers/Job+Opportunities+%26+Application/Current+Opportunities?language=en_US", "employment_types": ["Full Time"], "selling_points": ["5-day work week", "Bank Holiday", "3 years working experience"], "locations": ["Cheung Sha Wan"], "categories": ["Engineering", "Engineering Project Management", "Telecommunication / Wireless / Radio"], "post_time": "2022-01-16T21:50:06Z", "salary": {"currency": null, "max": null, "min": null, "period": "monthly", "term": null}, "salary_visible": false, "title_keywords": ["project engineer"], "responsibilities": ["data", "hr", "quality", "website", "customer services", "communication", "maintain"], "requirements": {"degrees": ["diploma", "higher certificate", "dse"], "majors": ["engineering", "computer science", "information technology"], "languages": ["english", "chinese"], "language_level": ["proficient"], "hard_skills": ["itil", "whatsapp", "ccna"], "soft_skills": ["communication", "team player", "interpersonal skills", "work independently"], "languages_combined": [{"language": "english", "language_level": ["proficient"]}, {"language": "chinese", "language_level": ["proficient"]}]}, "experience_required": {"duration": ["3 years", "2 years"], "field": ["relevant experience", "engineering", "information technology"]}}, {"job_id": "100003009048636", "location_code": "hk", "company": "CITIC Telecom International Holdings Limited", "job_title": "Engineer / Engineer Trainee - Network Operations", "description": "Responsibilities:\n1. Responsible to manage engineering project which includes solution design and site management.\n2. Responsible to supervise the construction, testing and commissioning of E&M systems on data center construction projects.\n3. Responsible to manage and ensure timely delivery of IDC Projects.\n4. Responsible to perform day-to-day operation, repairing and maintenance of the data center.\n5. Responsible to handle ad hoc duties.\n\nRequirements:\n1. Bachelor degree or above and a good knowledge of project management and facilities management.\n2. 5 years working experience in M&E industry, Grade B electrical worker.\n3. Degree in Building Services and Electrical engineering or equivalent.\n4. Good written communication and verbal presentation skill in both English and Chinese (Cantonese and Putonghua).\n5. Solid experience in data center construction project, facility management, testing and commissioning .\n6. Working experience in Data Center will be an advantage.\n7. Willing to work over-time.", "employment_types": ["Full Time", "Permanent"], "selling_points": ["With double pay, discretionary bonus & 14 days AL", "Sizable and energetic team", "Fresh graduates are welcome"], "locations": ["Kwai Fong"], "categories": ["Engineering", "Electrical / Electronics", "Telecommunication / Wireless / Radio", "Others", "Student / Fresh Graduate / No Experience"], "post_time": "2022-01-14T06:56:22Z", "salary": {"currency": null, "max": null, "min": null, "period": "monthly", "term": null}, "salary_visible": false, "title_keywords": ["operations", "engineer", "trainee"], "responsibilities": ["ad hoc duties", "commissioning", "maintenance", "data", "systems", "site management", "design", "testing", "day-to-day operation"], "requirements": {"degrees": ["degree", "degree or above", "bachelor"], "majors": ["project management", "building services", "electrical engineering"], "languages": ["cantonese", "putonghua", "english", "chinese"], "language_level": ["good"], "hard_skills": ["presentation skill", "project management", "facilities management"], "soft_skills": ["communication", "project management", "presentation skill"], "languages_combined": [{"language": "cantonese", "language_level": ["good"]}, {"language": "putonghua", "language_level": ["good"]}, {"language": "english", "language_level": ["good"]}, {"language": "chinese", "language_level": ["good"]}]}, "experience_required": {"duration": ["5 years"], "field": ["management", "construction", "testing"]}}, {"job_id": "100003009054096", "location_code": "hk", "company": "China Mobile International Limited", "job_title": "Operations Support Executive (Pricing Analysis) (CMIJD-0117-OSEMKTHK)", "description": "Your role\n\nAs a key member of our Smart Living Team, the successful candidate will be responsible for planning & implementation of business development proposals to achieve business targets for Smart Living wholesales business. \u00a0\u00a0Major responsibilities include:\n\nIdentify and define new Smart Living solutions to new residential projects in Hong Kong and Macau\nConduct market research and analysis to define market positioning, monitor the market trend, recommend the target pricing and formulate sales forecast for Hong Kong projects\nConduct strategic research and analysis to identify, evaluate and recommend business opportunities in property development and re-development sectors; interpret government policies and documents related to the business\nMonitor the project cost, cash flow and profitability, report any deviations & irregularity identified, and implement risk management solutions and remedial actions\nLiaise with external parties on potential partnership, coordinate with the internal parties in formulating and implementing sales & marketing plans for the successful projects\nPerform any ad hoc responsibilities as assigned by the senior management\u00a0\n\nTo succeed in this role\n\nUniversity graduate in Marketing, Business Administration, Social Science or related discipline\nMinimum 5 years working experience in sales or marketing field, preferably gained in telecommunication / IT industry\nAggressive and meticulous, with good communication and negotiation skills\nAble to work independently under tight schedule\nGood command of written and spoken English and Chinese\nCandidate with more working experience may be considered for the position of Business Development Manager\n\nWe offer you\n\nORSO/MPF retirement scheme\n16 days annual leave\nMedical and hospitalization insurance with dependent\nFull-paid sick leave\nExclusive staff discount plan and sales offer(i.e. CSL,1010,Now TV, Nevigator and more)\nPre-sales on new product / service (i.e. mobile device, service plan, star concert and more)\nMarriage and compassionate leave\nSponsorship of external study\n\nWorking location\n\nQuarry Bay", "employment_types": ["Full Time", "Permanent"], "selling_points": ["Review margin analysis & others", "Data services", "Immediate available is preferred"], "locations": ["Kwai Hing"], "categories": ["Professional Services", "Business Analysis / Data Analysis", "Engineering", "Telecommunication / Wireless / Radio", "Information Technology (IT)", "Product Management / Business Analyst"], "post_time": "2022-01-17T08:22:31Z", "salary": {"currency": null, "max": null, "min": null, "period": "monthly", "term": null}, "salary_visible": false, "title_keywords": ["operations", "executive"], "responsibilities": ["marketing plans", "conduct market research", "external parties", "communication", "liaise with", "senior management", "administration", "monitor", "implementation", "schedule", "forecast", "report", "ad hoc responsibilities", "cost", "management", "business opportunities", "coordinate with", "cash flow", "policies", "analysis", "evaluate", "internal parties", "planning"], "requirements": {"degrees": ["university graduate"], "majors": ["science", "marketing", "business administration"], "languages": ["english", "chinese"], "language_level": ["good command"], "hard_skills": ["analysis"], "soft_skills": ["meticulous", "work independently", "responsible", "communication", "negotiation skills"], "languages_combined": [{"language": "english", "language_level": ["good command"]}, {"language": "chinese", "language_level": ["good command"]}]}, "experience_required": {"duration": ["minimum 5 years"], "field": ["marketing", "it", "business development"]}}, {"job_id": "100003009050738", "location_code": "hk", "company": "Hutchison Telecommunications (Hong Kong) Limited", "job_title": "Engineer - 5G Core New Service Development", "description": "Your role\n\nCarry out installation, operation & maintenance work of DC power plants in HKT premises and customer sites\nCarry out performance test, commissioning and acceptance test of dc power equipment\nPerform emergency support duty on DC power equipment\nCoordinate with relevant parties to perform installation, operation and maintenance work\nHandle achoc job assigned by supervisor\n\nTo succeed in the role\n\nForm 5 / DSE graduate/ Certificate /Diploma in Electronic or related disciplines\nKnowledge in DC power equipment\nGood communication and writing skills in English and Chinese\nFresh graduate is welcome", "employment_types": ["Full Time", "Permanent"], "selling_points": [], "locations": ["Tsing Yi"], "categories": ["Engineering", "Telecommunication / Wireless / Radio", "Information Technology (IT)", "Network & System"], "post_time": "2022-01-14T11:15:01Z", "salary": {"currency": null, "max": null, "min": null, "period": "monthly", "term": null}, "salary_visible": false, "title_keywords": ["engineer"], "responsibilities": ["installation", "commissioning", "maintenance", "coordinate with", "communication"], "requirements": {"degrees": ["diploma", "fresh graduate", "certificate", "form 5", "dse"], "majors": ["related disciplines"], "languages": ["english", "chinese"], "language_level": ["good"], "hard_skills": ["dc", "maintenance", "writing skills"], "soft_skills": ["communication", "writing skills"], "languages_combined": [{"language": "english", "language_level": ["good"]}, {"language": "chinese", "language_level": ["good"]}]}, "experience_required": {"duration": [], "field": []}}, {"job_id": "100003009051852", "location_code": "hk", "company": "Hong Kong Applied Science and Technology Research Institute Company Limited (ASTRI)", "job_title": "IC Design - Senior Manager /Principal Engineer / Lead Engineer", "description": "Your role\u00a0\n\nThe successful candidate will provide assistance in the planning and operation activities for HKT exchanges and data centers in either one of the two disciplines\n\nInfrastructure Planning and design - Data Center / Exchange Center\nLead a small team to design in accommodation planning, equipment layout, cable route and building facilities provision to support the telecom equipment infrastructure\nPerform the planning in Data Center, design equipment layout, implementation works and contractors\u2019 management\nKeep building facilities knowledge update to fulfill the telecom equipment growth\nDevelop the process automation to improve work efficiency\nDC Power Planning & Operations\nCollaborate with various parties on ISO quality audit and ensure works are meeting the standard requirement.\nSupervise the installation and upgrade works of DC power plant\nCarry out operation and maintenance work of DC power plant\nManage vendors to secure the supply of high quality and cost effective products\n\n\nTo succeed in the role\u00a0\n\u00a0\n\nDegree holder or Higher Diploma/Higher Certificate in Electrical, Information System, Computer Science, Communication Engineering or related disciplines with 3 years\u2019 relevant experiences in telecommunications or IT industry.\nWell organized, analytical, hardworking and good interpersonal skills\nHolder of registered electrical worker license A or above is preferable\nKnowledge in Data Center design, AutoCAD / BIM (Building Information Modeling) / software program and holding professional certificate of CDCP is an advantage\nProficient in spoken and written in both English and Chinese\nCandidate with less experience or lower qualifications will be considered as Senior Technical Officer\n\nIf you have the desire for an exciting and rewarding career, please send us your resume, quoting the reference number, your present and expected salary by Whatsapp, email or post to the Human Resources Department.\n\n\u00a0Whatsapp:\u00a05410 6137\n\nPost: HR-ENGINEERING, 13/F, Lai Chi Kok Engineering Center, 4 Yuet Lun Street, Lai Chi Kok, Kowloon.on other job opportunities of PCCW, please visit our website at http://www.pccw.com/Careers/Job+Opportunities+%26+Application/Current+Opportunities?language=en_US", "employment_types": ["Full Time", "Contract"], "selling_points": ["5 days work with career path", "IC Design", "Government Funded company with job security"], "locations": ["Shatin Area"], "categories": ["Engineering", "Electrical / Electronics", "Mechanical", "Telecommunication / Wireless / Radio"], "post_time": "2022-01-17T01:22:38Z", "salary": {"currency": null, "max": null, "min": null, "period": "monthly", "term": null}, "salary_visible": false, "title_keywords": ["senior manager", "engineer", "lead"], "responsibilities": ["collaborate with", "software", "data", "operations", "quality", "audit", "design", "website", "communication", "infrastructure", "implementation", "develop", "provide assistance", "installation", "management", "cost", "maintenance", "lead a small team", "hr", "planning"], "requirements": {"degrees": ["certificate", "diploma", "higher certificate", "degree holder"], "majors": ["engineering", "design", "related disciplines", "it", "computer science"], "languages": ["english", "chinese"], "language_level": ["proficient"], "hard_skills": ["small", "maintenance", "information system", "bim", "autocad", "whatsapp", "dc", "exchange"], "soft_skills": ["communication", "well organized", "hardworking", "interpersonal skills"], "languages_combined": [{"language": "english", "language_level": ["proficient"]}, {"language": "chinese", "language_level": ["proficient"]}]}, "experience_required": {"duration": ["3 years"], "field": ["related", "telecommunications", "it", "engineering"]}}, {"job_id": "100003009050700", "location_code": "hk", "company": "Hutchison Telecommunications (Hong Kong) Limited", "job_title": "Engineer (Project management)", "description": "- Support Public Cloud Managed Services on-boarding and service delivery.\n\n- Handle customer monthly review and complex MS issues\n\n- Help develop and test automation tools to enhance MS service\n\n- Perform private cloud network equipments testing and provide technical support to operation team\n\n- Experience in Cloud computing and networking is a must\n\n- Holder of Public Cloud certificates (e.g. AWS, Azure)\u00a0is desired", "employment_types": ["Full Time", "Permanent"], "selling_points": [], "locations": ["Tsing Yi"], "categories": ["Engineering", "Electrical / Electronics", "Engineering Project Management", "Telecommunication / Wireless / Radio"], "post_time": "2022-01-14T11:13:25Z", "salary": {"currency": null, "max": null, "min": null, "period": "monthly", "term": null}, "salary_visible": false, "title_keywords": ["engineer"], "responsibilities": ["service delivery", "technical support", "review", "testing", "develop"], "requirements": {"degrees": [], "majors": [], "languages": [], "language_level": [], "hard_skills": ["azure", "aws"], "soft_skills": [], "languages_combined": []}, "experience_required": {"duration": [], "field": []}}, {"job_id": "100003009046818", "location_code": "hk", "company": "Johnson Controls Hong Kong Limited", "job_title": "Senior Engineer / Engineer / Assistant Engineer (HVAC / FS / BMS)", "description": "Technical Officer of Civil Aviation Engineering (Air Traffic Control Systems Operation and Maintenance / Project)\n\nThe Job:\n\nDepartment of Travel and Transportation is looking for Technical Officer(s) in following Civil Aviation Engineering teams:\n\n\u00a0Air Traffic Control Systems Operation and Maintenance Team\n\nAssist in performing technical operations, maintenance/repair for air traffic control (ATC), airport related systems or electronic/communication/IT equipment/systems and its ancillary support facilities\nAssist in planning, organizing, supervising and/or directly carrying out maintenance/repair works of systems/equipment and conducting system review to ensure system reliability and availability\nAssist in or directly and dependently carrying out equipment preventive/corrective maintenance, on-site equipment installation, testing and commissioning, fault diagnosis and repair according to a rectification plan/solution as well as helping one\u2019s supervisor in preparing fault/problem investigation report and/or procurement plan for spare parts or maintenance/repair services\nAssist in coordination with various internal and external parties such as various government departments, local or overseas airport authority, vendors/suppliers, sub-contractors and so on for operations and maintenance works\n\n\u00a0Project Team\n\nAssist in performing project work for air traffic control (ATC), airport related systems or electronic/communication/IT equipment/systems and its ancillary support facilities\nAssist in preparing solution for project tender bidding and implementation of project including drafting design submission, requirements for materials/service procurement, supervision/monitoring of sub-contractors installation works, preparation of test plan/report, conduct testing and commissioning\nAssist in project progress monitoring, financial monitoring and control of projects to ensure satisfactory completion of project within budget and schedule and help one\u2019s supervisor to prepare project/works progress reports for submission or logistics support\nAssist in coordination with various internal and external parties such as various government departments, local or overseas airport authority, vendors/suppliers, sub-contractors and so on for operations and maintenance works\n\nTeam allocation is based on qualifications, experience and personal attributes of the appointee.\n\nThe Person\n\nCertificate or above in Electronics/Electrical/Telecommunication/Computer/ Software/Information/e-logistics/Industrial Engineering or other related disciplines\nPossession of training record of Air Traffic Safety Electronic Personnel/Professional (ATSEP) training course is an advantage\nPossessing track record of relevant hands-on working experience in system design, building, testing and commissioning, operations and maintenance in mission critical service or project is highly preferable\nGood team player, customer-focused mindset, open-mindedness, proactive, result/service oriented, total quality management and safety concept with strong logical analytical, communication and interpersonal skills\nAble to work independently under pressure with strong desire and commitment to deliver high quality of works in short notice\nGood spoken and written English is a must. Knowledge of Putonghua is preferred\nFresh graduates will also be considered\nPossessing driving license is an advantage\nMay work in shift duty and/or irregular hours including overnight, Saturdays, Sundays and public holidays and/or outdoor as required", "employment_types": ["Full Time", "Permanent"], "selling_points": ["HVAC / FS / BMS retrofit/ T&C project", "HD or Degree in BS/ E&M or related disciplines", "Competitive Remuneration and Benefits Package"], "locations": ["Kwun Tong"], "categories": ["Engineering", "Electrical / Electronics", "Mechanical", "Telecommunication / Wireless / Radio"], "post_time": "2022-01-16T21:50:16Z", "salary": {"currency": null, "max": null, "min": null, "period": "monthly", "term": null}, "salary_visible": false, "title_keywords": ["senior engineer", "assistant engineer", "engineer"], "responsibilities": ["supervising", "operations", "coordination with", "internal and external parties", "budget", "design", "communication", "plan", "control", "progress reports", "teams", "implementation", "project progress", "testing", "logistics", "schedule", "tender", "report", "installation", "commissioning", "review", "rectification", "monitoring", "investigation", "maintenance", "systems", "repair", "it equipment", "planning"], "requirements": {"degrees": ["certificate"], "majors": ["related disciplines", "engineering"], "languages": ["putonghua", "english"], "language_level": ["good"], "hard_skills": ["system design", "maintenance"], "soft_skills": ["good team player", "work independently", "under pressure", "customer-focused mindset", "hands-on", "communication and interpersonal skills", "proactive"], "languages_combined": [{"language": "putonghua", "language_level": []}, {"language": "english", "language_level": ["good"]}]}, "experience_required": {"duration": [], "field": ["system design", "maintenance", "testing"]}}, {"job_id": "100003009050727", "location_code": "hk", "company": "Hutchison Telecommunications (Hong Kong) Limited", "job_title": "Engineer - 5G Packet Core Engineering", "description": "Our client, a reputable main contractor / sub-contractor in Hong Kong is seeking a number of high caliber Engineer(s) \u2013 E&M / HVAC / MVAC / P&D for their new projects.\n\nRequirements:\n\nH.D. in Electrical Engineering / Mechanical Engineering / Building Services Engineering or equivalent\n3 years\u2019 Electrical /\u00a0HVAC /\u00a0MVAC /\u00a0Plumbing and Drainage experience from subcontracting experience\nFamiliar with environmental assessment standards\nHands-on BIM software / applications experiences preferable\u00a0\nProficiency in MS Office (Word, Excel and PowerPoint)\nGood interpersonal, project management and site supervision skills\nGood spoken and written in English and Chinese\n\nCandidates with more experience will be considered for senior positions.\n\nPlease send your CV by clicking the button \u201cApply Now\u201d or email to\u202f corex_tang @persolkelly.com. For inquiries about this role or any other exciting opportunities, please call 2971-2525.\n\nAll information received will be treated in strict confidence and used for recruitment purpose only.", "employment_types": ["Full Time", "Permanent"], "selling_points": [], "locations": ["Tsing Yi"], "categories": ["Engineering", "Telecommunication / Wireless / Radio", "Information Technology (IT)", "Network & System"], "post_time": "2022-01-14T11:14:57Z", "salary": {"currency": null, "max": null, "min": null, "period": "monthly", "term": null}, "salary_visible": false, "title_keywords": ["engineer"], "responsibilities": ["project management", "site supervision", "recruitment", "software"], "requirements": {"degrees": [], "majors": [], "languages": ["english", "chinese"], "language_level": ["good"], "hard_skills": ["excel", "hvac", "word", "powerpoint", "project management", "bim", "ms office"], "soft_skills": ["project management", "hands-on", "confidence", "interpersonal"], "languages_combined": [{"language": "english", "language_level": ["good"]}, {"language": "chinese", "language_level": ["good"]}]}, "experience_required": {"duration": ["3 years"], "field": ["plumbing", "drainage"]}}, {"job_id": "100003009050702", "location_code": "hk", "company": "Hutchison Telecommunications (Hong Kong) Limited", "job_title": "Senior Engineer (Radio Planning Team)", "description": "Responsibilities:\n\nProject management for data business service delivery, including IEPL/IPLC, IDC, MPLS VPN, IP Transit and etc.\nManage and provide regular progress update during the project lifecycle for new circuit installation, upgrade, and relocation etc.\nCoordinate with domestic China Mobile Company and business partner/vendor to deliver the service on time.\nConduct risk management, procedure optimization and escalate all outstanding issue during provisioning stage.\nEstablish and maintain a good relationship with customers, internal teams.\nWork with overseas customers during non-office hour if necessary.\nCoordinate with internal parties to enhance the quality level if necessary.\nConsolidate, revise and update internal reports weekly and monthly.\nRequirements:\n\nBachelor's degree or above\nTechnical background such as CCNA, CCNP, IP networking skills will be an advantage\nMinimum 5 years of experience\nExcellent teamwork skills, hardworking, self-motived and able to work under pressure\nExcellent written and verbal communication skills in both English and Mandarin\n*Candidate with less experience will be considered as Senior Specialist\n\n\nInterested parties please apply in\u00a0full resume with current and expected salary\u00a0by e-mail to\u00a0hr\u00a0@\u00a0cmi.chinam obil e.com.\u00a0 Please indicate the reference in the subject line.\n\nAll personal data collected will be used for recruitment and employment related purpose only.", "employment_types": ["Full Time", "Permanent"], "selling_points": [], "locations": ["Tsing Yi"], "categories": ["Engineering", "Electrical / Electronics", "Telecommunication / Wireless / Radio", "Others"], "post_time": "2022-01-14T11:13:26Z", "salary": {"currency": null, "max": null, "min": null, "period": "monthly", "term": null}, "salary_visible": false, "title_keywords": ["senior engineer"], "responsibilities": ["service delivery", "installation", "management", "data", "coordinate with", "teams", "quality", "good relationship", "project management", "maintain", "reports", "internal parties"], "requirements": {"degrees": ["degree or above", "bachelor"], "majors": [], "languages": ["english", "mandarin"], "language_level": ["excellent"], "hard_skills": ["ip", "ccnp", "ccna"], "soft_skills": ["communication skills", "teamwork", "hardworking", "work under pressure"], "languages_combined": [{"language": "english", "language_level": ["excellent"]}, {"language": "mandarin", "language_level": ["excellent"]}]}, "experience_required": {"duration": ["minimum 5 years"], "field": []}}, {"job_id": "100003009050714", "location_code": "hk", "company": "Hutchison Telecommunications (Hong Kong) Limited", "job_title": "Senior Engineer (In-Building Planning & Design)", "description": "Job Responsibilities:\n\nPerform operation and maintenance support covering Mobile network system\nMonitor the mobile network and ensure proper system performance\nTroubleshoot & resolve the incidents and problem tickets according to Service Level Agreement\nInteract with internal stakeholders and external vendors to resolve network issues\n\n\nJob\u00a0Requirements:\n\nDegree in Electronics, Information engineering or Telecommunications is preferred\nMinimum 3-year relevant working experience. Candidates with lesser experience will also be considered.\nFamiliar with data\u00a0communication and\u00a0mobile network\nPossess IT/Telecom related certificates is a definite advantage\nPositive attitude, self-motivated with good communication and interpersonal skills\nGood command of spoken and written English, Chinese and Mandarin\nAble to perform shift duty (7x24 shift)\n\nInterested parties please apply in full resume with working experience, current and expected salary together with a contact telephone number by email to hr @ cmi.chinamobile.com.\n\nAll personal data collected will be used for recruitment and employment-related purpose only.", "employment_types": ["Full Time", "Permanent"], "selling_points": [], "locations": ["Tsing Yi"], "categories": ["Engineering", "Electrical / Electronics", "Telecommunication / Wireless / Radio", "Others"], "post_time": "2022-01-14T11:13:30Z", "salary": {"currency": null, "max": null, "min": null, "period": "monthly", "term": null}, "salary_visible": false, "title_keywords": ["senior engineer"], "responsibilities": ["network issues", "maintenance support", "monitor", "troubleshoot"], "requirements": {"degrees": ["degree"], "majors": ["engineering"], "languages": ["english", "chinese", "mandarin"], "language_level": ["good command"], "hard_skills": ["mobile"], "soft_skills": ["communication", "positive attitude", "self-motivated", "communication and interpersonal skills"], "languages_combined": [{"language": "english", "language_level": ["good command"]}, {"language": "chinese", "language_level": ["good command"]}, {"language": "mandarin", "language_level": ["good command"]}]}, "experience_required": {"duration": ["minimum 3-year"], "field": ["relevant working experience"]}}, {"job_id": "100003009049348", "location_code": "hk", "company": "HGC Global Communications Limited", "job_title": "Engineer (Network Configuration)", "description": "Technical Officer of Civil Aviation Engineering (Air Traffic Control Systems Operation and Maintenance / Project)\n\nThe Job:\n\nDepartment of Travel and Transportation is looking for Technical Officer(s) in following Civil Aviation Engineering teams:\n\n\u00a0Air Traffic Control Systems Operation and Maintenance Team\n\nAssist in performing technical operations, maintenance/repair for air traffic control (ATC), airport related systems or electronic/communication/IT equipment/systems and its ancillary support facilities\nAssist in planning, organizing, supervising and/or directly carrying out maintenance/repair works of systems/equipment and conducting system review to ensure system reliability and availability\nAssist in or directly and dependently carrying out equipment preventive/corrective maintenance, on-site equipment installation, testing and commissioning, fault diagnosis and repair according to a rectification plan/solution as well as helping one\u2019s supervisor in preparing fault/problem investigation report and/or procurement plan for spare parts or maintenance/repair services\nAssist in coordination with various internal and external parties such as various government departments, local or overseas airport authority, vendors/suppliers, sub-contractors and so on for operations and maintenance works\n\n\u00a0Project Team\n\nAssist in performing project work for air traffic control (ATC), airport related systems or electronic/communication/IT equipment/systems and its ancillary support facilities\nAssist in preparing solution for project tender bidding and implementation of project including drafting design submission, requirements for materials/service procurement, supervision/monitoring of sub-contractors installation works, preparation of test plan/report, conduct testing and commissioning\nAssist in project progress monitoring, financial monitoring and control of projects to ensure satisfactory completion of project within budget and schedule and help one\u2019s supervisor to prepare project/works progress reports for submission or logistics support\nAssist in coordination with various internal and external parties such as various government departments, local or overseas airport authority, vendors/suppliers, sub-contractors and so on for operations and maintenance works\n\nTeam allocation is based on qualifications, experience and personal attributes of the appointee.\n\nThe Person\n\nCertificate or above in Electronics/Electrical/Telecommunication/Computer/ Software/Information/e-logistics/Industrial Engineering or other related disciplines\nPossession of training record of Air Traffic Safety Electronic Personnel/Professional (ATSEP) training course is an advantage\nPossessing track record of relevant hands-on working experience in system design, building, testing and commissioning, operations and maintenance in mission critical service or project is highly preferable\nGood team player, customer-focused mindset, open-mindedness, proactive, result/service oriented, total quality management and safety concept with strong logical analytical, communication and interpersonal skills\nAble to work independently under pressure with strong desire and commitment to deliver high quality of works in short notice\nGood spoken and written English is a must. Knowledge of Putonghua is preferred\nFresh graduates will also be considered\nPossessing driving license is an advantage\nMay work in shift duty and/or irregular hours including overnight, Saturdays, Sundays and public holidays and/or outdoor as required", "employment_types": ["Full Time", "Permanent"], "selling_points": ["Perform network data configuration work", "Diploma in Computer Science / IT", "2 years' working experience in IT networking"], "locations": ["Tsing Yi"], "categories": ["Engineering", "Telecommunication / Wireless / Radio", "Information Technology (IT)", "Network & System", "Mobile / Wireless Communications"], "post_time": "2022-01-14T08:30:54Z", "salary": {"currency": null, "max": null, "min": null, "period": "monthly", "term": null}, "salary_visible": false, "title_keywords": ["engineer"], "responsibilities": ["supervising", "operations", "coordination with", "internal and external parties", "budget", "design", "communication", "plan", "control", "progress reports", "teams", "implementation", "project progress", "testing", "logistics", "schedule", "tender", "report", "installation", "commissioning", "review", "rectification", "monitoring", "investigation", "maintenance", "systems", "repair", "it equipment", "planning"], "requirements": {"degrees": ["certificate"], "majors": ["related disciplines", "engineering"], "languages": ["putonghua", "english"], "language_level": ["good"], "hard_skills": ["system design", "maintenance"], "soft_skills": ["good team player", "work independently", "under pressure", "customer-focused mindset", "hands-on", "communication and interpersonal skills", "proactive"], "languages_combined": [{"language": "putonghua", "language_level": []}, {"language": "english", "language_level": ["good"]}]}, "experience_required": {"duration": [], "field": ["system design", "maintenance", "testing"]}}, {"job_id": "100003009050744", "location_code": "hk", "company": "Hutchison Telecommunications (Hong Kong) Limited", "job_title": "Engineer (Fault Investigation)", "description": "To be part of our mission, we are looking for a Network Engineer to\u2026\n\n\nProvide best value and superior ICT services to customers\n\nWhat efforts you need to make for this role?\n\nOversee mission critical data center facility installation progress to meet schedule, specifications and industry practices\nExecute improvement projects for E&M facility to meet SLA\nPrepare tender requirement and perform T&C for systems prior to production stage\nPrepare performance report for data center facility to evaluate serviceability\nMonitor E&M facility performance and execute \u201cad hoc\u201d recovery procedure in timely manner\nAttend non-office hour ECO to execute equipment recovery procedures when necessary\n\nLet's check if you are /have\u2026\n\nHigh diploma or above in building service / electrical / mechanical or related discipline\nPrefer 1-2 years related data center operation experiences\nGood command of both written and spoken English and Cantonese\nHolder of Electrical worker license A will have an advantage\nCandidate with less experience will be considered as Assistant Engineer\n\n\n\nWhat you get in return\u2026\n\nApart from competitive salary package and benefits, in HKBN, you will work flexibly under our Talent-first\u00a0culture\u00a0and we uphold Life-Work Priority. Examples of our flexible initiatives:\n\nFive-day work week and shorten working hours (8 hours including 1 hour 15 mins meal break)\nHalf Day Off Friday once a month (compensation leave for Talents who work on shift)\nHalf Day Off on Festival Eve (compensation leave for Talents who work on shift)\nUnique leaves arrangement: Family-care leave, Anniversary leave, Bonus leave, Volunteer leave, Sabbatical leave, etc.\nComprehensive medical and life insurance coverage\nUpgraded maternity leave and paternity leave\nDiscounted Talent plan offers including broadband and mobile plans and other promoted products\nEducation subsidies and Examination leave\nYear-end discretionary bonus", "employment_types": ["Full Time", "Permanent"], "selling_points": [], "locations": ["Tsing Yi"], "categories": ["Engineering", "Electrical / Electronics", "Telecommunication / Wireless / Radio", "Others"], "post_time": "2022-01-14T11:15:04Z", "salary": {"currency": null, "max": null, "min": null, "period": "monthly", "term": null}, "salary_visible": false, "title_keywords": ["engineer"], "responsibilities": ["installation", "ad hoc", "data", "systems", "monitor", "procedures", "evaluate", "specifications", "schedule", "tender", "report"], "requirements": {"degrees": ["high diploma or above"], "majors": [], "languages": ["cantonese", "english"], "language_level": ["good command"], "hard_skills": ["sla", "make"], "soft_skills": ["timely", "superior"], "languages_combined": [{"language": "cantonese", "language_level": ["good command"]}, {"language": "english", "language_level": ["good command"]}]}, "experience_required": {"duration": ["1-2 years"], "field": ["related", "operation"]}}, {"job_id": "100003009050742", "location_code": "hk", "company": "Hutchison Telecommunications (Hong Kong) Limited", "job_title": "Engineer (RAN Development)", "description": "Seeking for applicants who are experienced individuals from different sectors\n\nJob Summary:\n\nLeads repairs, corrective maintenance, and complex installations. Guides others in resolving incidents, and recommends new procedures to resolve faults.\n\nResponsibilities\n\nFacility/Infrastructure Maintenance\n\nPerforms site inspections and monitors the building and IBX alarms\nPerforms preventative maintenance on site infrastructure (e.g. maintenance of primary infrastructures), or manages vendors\nLeads repairs and corrective maintenance\nAdvises other team members on repairs and preventative maintenance\nLeads and coordinates critical infrastructure operations\n\nSite Administration\n\nCompletion of site logs and issuing of permits, such as MOPs and scripts\n\nIncident Management\n\nInstructs on-site staff during incidents\n\nWork Orders\n\nLeads others with work requests and circuit installations\nPerforms capacity management\n\nCollaboration\n\nIdentifies and understands underlying issues probes the facts\nCan identify component level faults and provide recommendations for new procedures\nUtilizes resources outside of the department as necessary\n\nAdditional Projects\n\nLeads infrastructure project activities\nMay recommend infrastructure projects", "employment_types": ["Full Time", "Permanent"], "selling_points": [], "locations": ["Tsing Yi"], "categories": ["Engineering", "Electrical / Electronics", "Telecommunication / Wireless / Radio", "Others"], "post_time": "2022-01-14T11:15:03Z", "salary": {"currency": null, "max": null, "min": null, "period": "monthly", "term": null}, "salary_visible": false, "title_keywords": ["engineer"], "responsibilities": ["management", "maintenance", "infrastructure", "procedures", "infrastructure operations", "provide recommendations", "site inspections", "administration"], "requirements": {"degrees": [], "majors": [], "languages": [], "language_level": [], "hard_skills": ["maintenance"], "soft_skills": [], "languages_combined": []}, "experience_required": {"duration": [], "field": []}}, {"job_id": "100003009051540", "location_code": "hk", "company": "Iotena Technology Limited \u611b\u5929\u7acb\u79d1\u6280\u6709\u9650\u516c\u53f8", "job_title": "Electronic Engineer (IoT System Design)", "description": "Responsibilities:\n\nDesign, plan and participate in project related to\u00a0development of\u00a0international network which consists of PoP sites, data centers, internet and internal IP backbones.\nTrack\u00a0network project progress\u00a0including\u00a0solution evaluation and selection, migration, expansion, feature development, software upgrade.\nProvide technical support relate to mobile service.\nProvide support in daily operation and emergency\u00a0services\u00a0\n\nRequirements:\n\nUniversity degree in Electrical/ Telecommunications or related disciplines, with definite advantage by processing relevant professional certification\nMinimum 3 years or above relevant experience in Mobile and IP network engineering\nExposure to\u00a0the design, planning,\u00a0implementation, maintenance and support of Mobile or IP network is an advantage\nProficiency in MS Office applications and Chinese Word Processing\nGood command of spoken and written Chinese and English, proficiency in Putonghua is an advantage\n\nInterested parties please send your full resume with current & expected salary by email to hr@ cmi.chinamobile.com.\u00a0Please indicate the reference number in the subject line.\n\nAll personal data provided will be used for consideration of your job application only.", "employment_types": ["Full Time"], "selling_points": ["Bachelor in Electrical & Electronics Eng/5+ yr exp", "Solid exp in ele & wireless hardware system design", "Solid exp in PCB Layout & ele circuit design"], "locations": ["Shatin Area"], "categories": ["Engineering", "Electrical / Electronics", "Telecommunication / Wireless / Radio", "Others"], "post_time": "2022-01-16T09:28:27Z", "salary": {"currency": null, "max": null, "min": null, "period": "monthly", "term": null}, "salary_visible": false, "title_keywords": ["electronic engineer"], "responsibilities": ["provide support", "software", "data", "technical support", "daily operation", "project progress", "design", "plan", "evaluation", "migration"], "requirements": {"degrees": ["university degree"], "majors": ["related disciplines"], "languages": ["putonghua", "english", "chinese"], "language_level": ["advantage", "proficiency", "good command"], "hard_skills": ["chinese word processing", "maintenance", "mobile", "ip", "processing", "ms office"], "soft_skills": [], "languages_combined": [{"language": "putonghua", "language_level": ["proficiency", "advantage", "good command"]}, {"language": "english", "language_level": ["advantage", "good command"]}, {"language": "chinese", "language_level": ["proficiency", "advantage", "good command"]}]}, "experience_required": {"duration": ["minimum 3 years"], "field": ["relevant experience", "engineering"]}}, {"job_id": "100003009050733", "location_code": "hk", "company": "Hutchison Telecommunications (Hong Kong) Limited", "job_title": "Technical Officer (6 months contract)", "description": "\u00a0Responsibilities\nAssist in design, implementation and commissioning of network project.\nPrepare technical design, implementation and T&C related documents.\nPerform workshop testing, on-site deployment and T&C.\nProvide technical support to customers during maintenance period.\nRequirements\n\nDegree in Electronic Engineering/ Computer Science/ IT or related disciplines.\n1-year relevant experience and fresh graduate will also be considered.\nCandidates with more experience will be considered as Engineer\nCertificates such as CCNA/ HCIA will be an advantage.\nKnowledge and experience in database administration and support of MS SQL Server is a plus.\nGood communication skill, mature, self-motivated and be able to work under pressure.\nProficiency in spoken and written Chinese and English.\nIELTS 6.5 or above preferred", "employment_types": ["Full Time", "Contract"], "selling_points": [], "locations": ["Tsing Yi"], "categories": ["Engineering", "Engineering Project Management", "Telecommunication / Wireless / Radio", "Others"], "post_time": "2022-01-14T11:15:00Z", "salary": {"currency": null, "max": null, "min": null, "period": "monthly", "term": null}, "salary_visible": false, "title_keywords": ["technical officer"], "responsibilities": ["commissioning", "maintenance", "related documents", "technical support", "workshop", "implementation", "design", "testing"], "requirements": {"degrees": ["degree", "fresh graduate"], "majors": ["related disciplines", "it", "engineering", "computer science"], "languages": ["english", "chinese"], "language_level": ["proficiency"], "hard_skills": ["ms sql server", "plus", "ccna"], "soft_skills": ["self-motivated", "communication skill", "mature", "work under pressure"], "languages_combined": [{"language": "english", "language_level": ["proficiency"]}, {"language": "chinese", "language_level": ["proficiency"]}]}, "experience_required": {"duration": ["1-year"], "field": ["sql", "relevant experience", "database", "administration"]}}, {"job_id": "100003009049259", "location_code": "hk", "company": "SmarTone Telecommunications Limited", "job_title": "Engineer, Core Network Engineering", "description": "Responsibilities:\n\nSet target for international business and individual business unit, track and analyze the performance of each unit, research and analyze incentive policies for key projects and products\nDevelop and improve the work mechanism, coordinate across divisions to promote Company services and products to overseas market, enhance oversea subnet product capabilities\nResearch key issues fronted by international business\nSet up and refine policies and process on international business development and support\nComplete other tasks assigned by management\n\nRequirement:\n\nBachelor degree or above\nMinimum 4 years relevant working experience\nPrior experience in mobile market or Government and Enterprise market in Telecommunication environment is a plus\nOpen-minded, responsive, attention to details and able to work under pressure\nStrong communication skill and able to work as a team\nGood command of spoken and written Chinese and English, proficiency in Putonghua is an advantage\nProficient in MS office applications and Chinese Word Processing\n\nInterested parties please apply in\u00a0full resume with current and expected salary\u00a0by e-mail to\u00a0hr\u00a0@\u00a0cmi.chinam obil e.com.\u00a0 Please indicate the reference in the subject line.\n\nAll personal data collected will be used for recruitment and employment related purpose only.", "employment_types": ["Full Time"], "selling_points": ["System evaluation and testing", "Intelligent bandwidth management & Radius platform", "System fault resolutions"], "locations": ["Kowloon Bay"], "categories": ["Engineering", "Telecommunication / Wireless / Radio", "Information Technology (IT)", "Application Specialist - Network", "Network & System"], "post_time": "2022-01-14T08:19:54Z", "salary": {"currency": null, "max": null, "min": null, "period": "monthly", "term": null}, "salary_visible": false, "title_keywords": ["engineer"], "responsibilities": ["management", "policies", "develop", "coordinate", "other tasks"], "requirements": {"degrees": ["degree or above", "bachelor"], "majors": [], "languages": ["putonghua", "english", "chinese"], "language_level": ["advantage", "proficiency", "good command", "proficient"], "hard_skills": ["mobile", "plus", "chinese word processing", "ms office"], "soft_skills": ["work as a team", "open-minded", "communication skill", "attention to details", "responsive", "work under pressure"], "languages_combined": [{"language": "putonghua", "language_level": ["proficiency", "advantage", "good command"]}, {"language": "english", "language_level": ["advantage", "good command"]}, {"language": "chinese", "language_level": ["proficiency", "advantage", "good command", "proficient"]}]}, "experience_required": {"duration": ["minimum 4 years"], "field": ["relevant working experience"]}}, {"job_id": "100003009055456", "location_code": "hk", "company": "HKT", "job_title": "Assistant Engineer, Mobile Radio Network", "description": "Your role\n\nLead a small team to support mobile core network and maintain mobile services by fast restoration\nManage the change request in mobile core network to support new requirements or network enhancement raised from planning team\nSetup and perform routine checking of mobile core network to identify the potential risk in early stage\nFollow up outstanding problem of mobile core network with vendor and planning team to ensure stability of mobile services\nMonitor the performance of mobile core network in order to keep track of service quality and performance trend\nAttend shift duties and emergency support outside normal working hours when necessary\n\nTo succeed in the role\n\nDegree / High Diploma holder in Electronics, Information Technology, Communication or related disciplines with minimum 5 years\u2019 relevant experience in mobile communication and server administration\nTechnical and practical knowledge in managing and supporting mobile core network, such as mobile CS/IMS core network, mobile PS and IPBB network, and network management tools\nExcellent analytical, communication and customer handling skills\nProvident in written and spoken English and Chinese\nSelf-motivated and able to work independently under high pressure\nKnowledge in fault management and experience in supervision of small team will be an advantage\n\nIf you have the desire for an exciting and rewarding career, please send us your resume, quoting the reference number, your present and expected salary by Whatsapp, email or post to the Human Resources Department.\n\n\u00a0Whatsapp:\u00a05410 6137\n\nPost: HR-ENGINEERING, 13/F, Lai Chi Kok Engineering Center, 4 Yuet Lun Street, Lai Chi Kok, Kowloon.on other job opportunities of PCCW, please visit our website at http://www.pccw.com/Careers/Job+Opportunities+%26+Application/Current+Opportunities?language=en_US", "employment_types": ["Full Time"], "selling_points": [], "locations": ["Lai Chi Kok"], "categories": ["Engineering", "Electrical / Electronics", "Telecommunication / Wireless / Radio"], "post_time": "2022-01-18T02:37:01Z", "salary": {"currency": null, "max": null, "min": null, "period": "monthly", "term": null}, "salary_visible": false, "title_keywords": ["assistant engineer"], "responsibilities": ["administration", "management", "lead a small team", "hr", "quality", "website", "communication", "maintain", "monitor the performance", "routine checking", "setup", "planning"], "requirements": {"degrees": ["high diploma", "degree"], "majors": ["related disciplines", "information technology"], "languages": ["english", "chinese"], "language_level": [], "hard_skills": ["small", "network management", "server administration", "vendor", "mobile", "whatsapp"], "soft_skills": ["communication", "self-motivated", "work independently"], "languages_combined": [{"language": "english", "language_level": []}, {"language": "chinese", "language_level": []}]}, "experience_required": {"duration": ["minimum 5 years"], "field": ["management", "server administration", "related", "information technology", "relevant experience", "team"]}}, {"job_id": "100003009055460", "location_code": "hk", "company": "HKT", "job_title": "Assistant Engineer, Network monitoring and surveillance (Exchange Operations)", "description": "Your role\n\nLead a team to build and manage the network / data center\nCarry out equipment installation and restoration, service provision for voice, broadband, data, mobile and / or network\nDevelop the guideline, procedures on operation process and workflow\nAssist the superior for trouble shooting, escalation and decision making on emergency situation during network incident handling\nTrain up new team members to be a capable technical operation and support member.\n\nTo succeed in the role\n\nBachelor degree in Information Technology, Computer Science, Communication Engineering, Electronic Engineering or related disciplines with 3 years of operation / support experience in voice, broadband, data, mobile and / or cloud network / systems and related network management systems\nExcellent technical skills and hands-on experience in managing networking devices and deploying network management systems\nGood supervisory, analytical and troubleshooting skills\nProficient in spoken and written in both English and Chinese\nSelf-motivated, flexible and able to work independently under high pressure\nCandidate with less experience or lower qualifications (Higher Diploma / Diploma in related disciplines) will be considered as\u00a0Senior Technical Officer\n\nIf you have the desire for an exciting and rewarding career, please send us your resume, quoting the reference number, your present and expected salary by Whatsapp, email or post to the Human Resources Department.\n\n\u00a0Whatsapp:\u00a05410 6137\n\nPost: HR-ENGINEERING, 13/F, Lai Chi Kok Engineering Center, 4 Yuet Lun Street, Lai Chi Kok, Kowloon.on other job opportunities of PCCW, please visit our website at http://www.pccw.com/Careers/Job+Opportunities+%26+Application/Current+Opportunities?language=en_US", "employment_types": ["Full Time"], "selling_points": [], "locations": ["Lai Chi Kok"], "categories": ["Engineering", "Electrical / Electronics", "Telecommunication / Wireless / Radio"], "post_time": "2022-01-18T02:37:16Z", "salary": {"currency": null, "max": null, "min": null, "period": "monthly", "term": null}, "salary_visible": false, "title_keywords": ["operations", "assistant engineer"], "responsibilities": ["installation", "management", "data", "hr", "systems", "procedures", "troubleshooting", "website", "develop", "communication", "lead a team"], "requirements": {"degrees": ["diploma", "degree", "bachelor"], "majors": ["related disciplines", "engineering", "computer science", "information technology"], "languages": ["english", "chinese"], "language_level": ["proficient"], "hard_skills": ["network management", "mobile", "whatsapp"], "soft_skills": ["flexible", "self-motivated", "work independently", "capable", "troubleshooting", "communication", "hands-on", "technical skills", "superior", "decision making"], "languages_combined": [{"language": "english", "language_level": ["proficient"]}, {"language": "chinese", "language_level": ["proficient"]}]}, "experience_required": {"duration": ["3 years"], "field": ["management", "engineering", "related", "information technology", "operation"]}}, {"job_id": "100003009056059", "location_code": "hk", "company": "PCCW Solutions", "job_title": "Technical Officer - ELV/ ICT System", "description": "The candidate will report to the Engineer for technical design, system implementation, planned and corrective maintenance of both or either one of the following streams:\n\nExtra Low Voltage (ELV) stream\nVoice & Data Cabling (VDC),\nPublic Address (PAS),\nClosed Circuit Television (CCTV),\nTrunk Mobile Radio (TMR), or\nAccess Control (ACS), etc.\nInformation & Communication Technology (ICT) stream\nWindows / Linux / Cloud based Environment,\nNetworking / Database / Data Storage, or\nSoftware Development, etc.\nData Analytic will be an advantage.\nPlan & supervise contractors and control workmanship for various ELV / ICT projects\nManage the work progress, including design submissions, factory inspections, site works, testing and commissioning activities, defect rectifications and as-built drawings preparation\nAssist in the coordination with various internal and external parties to ensure that interfaces and works programme are achieved.\nOvertime work might require\nMight work in Hong Kong International Airport\n\nRequirements:\n\nHigh Diploma / Degree in Electronic, Computer Engineering, Computer Science, IT, or equivalent.\nFor Assistant Engineer, at least three (3) years ELV / ICT systems working experience (with 3 years playing the design and planning / supervisory role);\nFor Senior Technical Officer, at least two (2) years ELV / ICT systems working experience (with 1 years playing the design and planning / supervisory role);\nFor Technical Officer, at least one (1) years related working experience.\nGood in documentation and writing skills.\nGood in communication and interpersonal skill.\nProficiency in Microstation and/or AutoCAD is an advantage.\nFluency in written and spoken English and Cantonese; Mandarin will be an advantage.\nHave Green Card and Construction Worker Registration Card are essential.\nHave valid HK Type 1 & Type 2 driving license is an advantage.", "employment_types": ["Full Time"], "selling_points": [], "locations": ["Airport Area"], "categories": ["Engineering", "Electrical / Electronics", "Telecommunication / Wireless / Radio", "Information Technology (IT)", "Network & System"], "post_time": "2022-01-18T03:14:04Z", "salary": {"currency": null, "max": null, "min": null, "period": "monthly", "term": null}, "salary_visible": false, "title_keywords": ["technical officer"], "responsibilities": ["software", "supervise contractors", "data", "coordination with", "internal and external parties", "design", "drawings", "communication", "database", "plan", "control", "implementation", "testing", "closed circuit television", "report", "commissioning", "documentation", "maintenance", "systems", "access control", "planning"], "requirements": {"degrees": ["high diploma", "degree"], "majors": ["it", "computer engineering", "computer science"], "languages": ["cantonese", "english", "mandarin"], "language_level": ["fluency", "advantage"], "hard_skills": ["linux", "documentation", "maintenance", "cctv", "writing skills", "green card", "mobile", "system implementation", "data storage", "autocad"], "soft_skills": ["writing skills", "interpersonal skill", "communication", "overtime work", "coordination"], "languages_combined": [{"language": "cantonese", "language_level": ["fluency"]}, {"language": "english", "language_level": ["fluency"]}, {"language": "mandarin", "language_level": ["advantage"]}]}, "experience_required": {"duration": ["3 years", "1 years"], "field": ["related", "supervisory", "design", "planning"]}}, {"job_id": "100003009055593", "location_code": "hk", "company": "Robert Walters (HK)", "job_title": "Site Supervisor (ELV, 30K, 5-day, Client side)", "description": "We are searching for a Site Supervisor for our client, it's a client representative role for a newly awarded ELV project:\n\nResponsibilities:\n\nMonitor day-to-day site work progress and contractor workmanship to ensure project delivery quality\nSupervise contractor safety and work performance\nRepresent Enginneer or Engineer's representative to attend and witness system testing and commissioning\nSite coordination and resolve construction site issues to ensure timely delivery of project works\n\nRequirements:\n\nDiploma or above in Electronics Engineering / Electrical Engineering/ Computer and Information Engineering or equivalent\nAt least 3 years' relevant experience in site coordination and project implementation of telecommunications, electronic or information & communications technology project or equivalent\nPossess a valid Construction Industry Safety Training Certificate", "employment_types": ["Full Time", "Temporary"], "selling_points": ["Client side representative", "", ""], "locations": ["Not Specified"], "categories": ["Engineering", "Electrical / Electronics", "Engineering Project Management", "Telecommunication / Wireless / Radio"], "post_time": "2022-01-18T02:46:26Z", "salary": {"currency": null, "max": null, "min": null, "period": "monthly", "term": null}, "salary_visible": false, "title_keywords": ["site supervisor"], "responsibilities": ["commissioning", "quality", "monitor", "testing", "site coordination"], "requirements": {"degrees": ["certificate", "diploma or above"], "majors": ["engineering", "electrical engineering"], "languages": [], "language_level": [], "hard_skills": [], "soft_skills": ["coordination"], "languages_combined": []}, "experience_required": {"duration": ["at least 3 years"], "field": ["telecommunications", "relevant experience"]}}, {"job_id": "100003009056024", "location_code": "hk", "company": "Dyxnet Limited", "job_title": "Assistance Network Support Engineer", "description": "Job Description:\u00a0\n\nOnsite deliver networking services to our corporate customers.\nYour work include provisioning, troubleshooting and maintenance support services for networking.\nOn job trainings will be provided to the right candidate.\nNon-Office hours emergency call support is required.\n\nRequirements:\n\nHigher Diploma or above in Telecommunication and Networking or related discipline\nExperience in Cisco Router/Switch, Firewall, VPN\nCertificate holder of Cisco CCNA or higher is preferred\nRelated working experience in ISP, SI vendor or network support is definite a value added\nKnowledge in OSPF, EIGRP, BGP, MPLS, VoIP is an advantage\nExperience in SDWAN would be preferred\u00a0\nFluent in Cantonese, conversable in English and Mandarin\nAble to work under pressure, willing to work overtime\nFresh Graduate will also be considered\n\nAttractive remuneration and compensation package, including year end bonus, medical scheme as well as career development opportunities will be offered.\u00a0\n\nInterested parties please send your resume with expected salary and availability to Human Resources Department, Dyxnet Group, 37/F, Tower 1, Metorplaza, 223 Hing Fong Road, Kwai Fong.\u00a0\n\nWelcome to visit our website:\u00a0http://www.dyxnet.com/\u00a0for further information of our company.\u00a0\n\nData collected will be used for recruitment purpose only.", "employment_types": ["Full Time", "Permanent"], "selling_points": ["Onsite deliver networking services", "Fresh Graduate will also be considered", "Five days work"], "locations": ["Kwai Fong"], "categories": ["Engineering", "Telecommunication / Wireless / Radio", "Information Technology (IT)", "Support", "Network & System"], "post_time": "2022-01-18T03:12:02Z", "salary": {"currency": null, "max": null, "min": null, "period": "monthly", "term": null}, "salary_visible": false, "title_keywords": ["support engineer", "assistance"], "responsibilities": ["maintenance support", "troubleshooting"], "requirements": {"degrees": ["certificate", "higher diploma or above", "fresh graduate"], "majors": [], "languages": ["cantonese", "english", "mandarin"], "language_level": ["fluent"], "hard_skills": ["switch", "ccna", "vendor", "scheme", "router", "vpn", "firewall"], "soft_skills": ["work overtime", "work under pressure"], "languages_combined": [{"language": "cantonese", "language_level": ["fluent"]}, {"language": "english", "language_level": []}, {"language": "mandarin", "language_level": []}]}, "experience_required": {"duration": [], "field": ["related"]}}, {"job_id": "100003009055455", "location_code": "hk", "company": "HKT", "job_title": "Senior Technical Officer, Voice Network Planning (Welcome fresh grad.)", "description": "Your role\n\nResponsible for voice over IP network and traditional voice network planning\nUpdate voice feature testing & voice network inventory\nTest and verify voice over IP phone and feature\nPlan voice system migration\nPrepare the Installation Request diagram drawing\n\nTo succeed in the role\n\nDegree / High Diploma in Information Technology, Computer Science, Communication\u00a0Engineering or related disciplines with minimum 3 years\u2019 relevant experience in telecommunication industry\nInterested in developing technical knowledge on voice over IP technologies\nKnowledge or experience in the following areas will be an advantage\nIP Networking\nVoIP SIP protocol, ISUP signaling\nVoice system inter-working with other operators\nCloud computing technology\nGood analytical and problem solving skills\nProvident in written and spoken English and Chinese\nCandidate with less experience will be considered as Technical Officer", "employment_types": ["Full Time"], "selling_points": [], "locations": ["Lai Chi Kok"], "categories": ["Engineering", "Telecommunication / Wireless / Radio", "Information Technology (IT)", "Network & System", "Mobile / Wireless Communications"], "post_time": "2022-01-18T02:36:56Z", "salary": {"currency": null, "max": null, "min": null, "period": "monthly", "term": null}, "salary_visible": false, "title_keywords": ["senior technical officer"], "responsibilities": ["installation", "inventory", "developing", "testing", "communication", "plan", "migration", "planning"], "requirements": {"degrees": ["high diploma", "degree"], "majors": ["related disciplines", "engineering", "computer science", "information technology"], "languages": ["english", "chinese"], "language_level": [], "hard_skills": ["ip", "problem solving skills"], "soft_skills": ["communication", "analytical and problem solving skills", "interested in", "responsible"], "languages_combined": [{"language": "english", "language_level": []}, {"language": "chinese", "language_level": []}]}, "experience_required": {"duration": ["minimum 3 years"], "field": ["related", "relevant experience", "engineering", "information technology"]}}, {"job_id": "100003009056010", "location_code": "hk", "company": "Robert Walters (HK)", "job_title": "AV Engineer/ ELV Engineer (5-day, client side, 32K)", "description": "We are searching for our client for a AV Engineer, it's a client representative role and below you may find the job details:\n\nResponsibilities:\n\nExecute Audiovisual projects professionally\nRepresent client and liaise with sub contractor in project coordination\nManage external resources and support teammates to complete project fully\n\nRequirements:\n\nDiploma or above in Electronic Engineering, Electrical Engineer or related disciplines\nMinimum 3 years relevant experiences\nCandidates with less experience will be considered as Assistant Engineer\nGood command of spoken and written English & Chinese", "employment_types": ["Full Time", "Temporary"], "selling_points": ["Client-side representative", "5-day work, attractive package", "Salary up to HKD 32, 000"], "locations": ["Not Specified"], "categories": ["Engineering", "Electrical / Electronics", "Engineering Project Management", "Telecommunication / Wireless / Radio"], "post_time": "2022-01-18T03:11:18Z", "salary": {"currency": null, "max": null, "min": null, "period": "monthly", "term": null}, "salary_visible": false, "title_keywords": ["engineer"], "responsibilities": ["liaise with", "project coordination"], "requirements": {"degrees": ["diploma or above"], "majors": ["related disciplines", "engineering"], "languages": ["english", "chinese"], "language_level": ["good command"], "hard_skills": [], "soft_skills": [], "languages_combined": [{"language": "english", "language_level": ["good command"]}, {"language": "chinese", "language_level": ["good command"]}]}, "experience_required": {"duration": ["minimum 3 years"], "field": []}}, {"job_id": "100003009055646", "location_code": "hk", "company": "PCCW Global Limited", "job_title": "Solutions Consultant", "description": "Key Responsibilities\n\nCommunicate with customer at all levels to establish their specific business needs\nForm and build solution out of in-house standard and external 3rd party products\nPlan, design and build specific solution, bridging the customer's business needs\nRespond to functional and technical elements of RFIs/RFPs\nResponsible for technology consulting and solution presentation to target customer\nConvey customer business needs and requirements into Product and Development teams\nResponsible for monitoring of the support industry technology needs and service trends\n\nPerson Specifications\n\nUniversity graduate in Telecommunication, Computing Science, Information Technology or related discipline; Professional certificates, e.g. CCNP, CISSP, is a plus\nAround 5 years of\u00a0relevant experience in network and telecommunication solution design. Minimum 4 years as a telecommunication solution consulting role\nPossess strong industry specific understanding and a diverse set of technical knowledge on various types of networking technologies, like IP, MPLS, IPLC, Satellite, and value added services (e.g. security, data centre, etc),\u00a0experience in aviation industry, and actual knowledge on aviation network implementation and operation is definitely a plus\nExperience and familiarity of network planning, design, implementation and operation on large data network\nKnowledge in relevant technology trends and outlooks\nSelf-motivated with a proven track record in solutions consulting\u00a0including network connectivity and network design\nDemonstrate strong business sense\nExcellent verbal and written communication skills in both Chinese (Mandarin and Cantonese) and English, other languages are added advantage", "employment_types": ["Full Time"], "selling_points": [], "locations": ["Wan Chai"], "categories": ["Sales, CS & Business Devpt", "Business Development", "Engineering", "Telecommunication / Wireless / Radio", "Account Servicing"], "post_time": "2022-01-18T02:49:47Z", "salary": {"currency": null, "max": null, "min": null, "period": "monthly", "term": null}, "salary_visible": false, "title_keywords": ["consultant"], "responsibilities": ["communicate with", "consulting", "data", "monitoring", "teams", "implementation", "design", "communication", "specifications", "plan", "planning"], "requirements": {"degrees": ["university graduate"], "majors": ["science", "information technology"], "languages": ["cantonese", "english", "chinese", "mandarin"], "language_level": ["advantage", "excellent"], "hard_skills": ["ip", "ccnp", "data network", "plus"], "soft_skills": ["communication skills", "self-motivated", "responsible", "business sense", "diverse", "presentation"], "languages_combined": [{"language": "cantonese", "language_level": ["advantage", "excellent"]}, {"language": "english", "language_level": ["advantage", "excellent"]}, {"language": "chinese", "language_level": ["advantage", "excellent"]}, {"language": "mandarin", "language_level": ["advantage", "excellent"]}]}, "experience_required": {"duration": ["5 years"], "field": ["design", "operation", "relevant experience", "security", "planning"]}}, {"job_id": "100003009055461", "location_code": "hk", "company": "HKT", "job_title": "Assistant Engineer, Broadband Planning and Operations", "description": "Your role\n\nCo-ordinate with various parties for Broadband projects in business case preparation, and cost scenario studies\nCarry out business case performance tracking, monthly capex spending monitor / forecast, and to support procurement audit\nHandle equipment ordering and equipment disposal\nManage nowTV CDN channel assignment and management\n\nTo succeed in the role\n\nDegree in Engineering, Computer Science, Information Technology, Communication Engineering or related disciplines with minimum 2 years\u2019 relevant working experience\nFamiliar with MS Office\nStrong in handling financial figures with excellent analytical skill\nGood interpersonal and communication skills\nProficient in spoken and written in both English and Chinese\nResponsible, self-motivated, flexible attitude and independent\n\nIf you have the desire for an exciting and rewarding career, please send us your resume, quoting the reference number, your present and expected salary by Whatsapp, email or post to the Human Resources Department.\n\n\u00a0Whatsapp:\u00a05410 6137\n\nPost: HR-ENGINEERING, 13/F, Lai Chi Kok Engineering Center, 4 Yuet Lun Street, Lai Chi Kok, Kowloon.on other job opportunities of PCCW, please visit our website at http://www.pccw.com/Careers/Job+Opportunities+%26+Application/Current+Opportunities?language=en_US", "employment_types": ["Full Time"], "selling_points": [], "locations": ["Lai Chi Kok"], "categories": ["Engineering", "Telecommunication / Wireless / Radio", "Information Technology (IT)", "Network & System", "Mobile / Wireless Communications"], "post_time": "2022-01-18T02:37:21Z", "salary": {"currency": null, "max": null, "min": null, "period": "monthly", "term": null}, "salary_visible": false, "title_keywords": ["operations", "assistant engineer"], "responsibilities": ["cost", "management", "co-ordinate with", "hr", "capex", "monitor", "audit", "website", "communication", "forecast", "tracking"], "requirements": {"degrees": ["degree"], "majors": ["related disciplines", "engineering", "computer science", "information technology"], "languages": ["english", "chinese"], "language_level": ["proficient"], "hard_skills": ["whatsapp", "analytical skill", "ms office"], "soft_skills": ["flexible", "communication skills", "analytical skill", "self-motivated", "independent", "responsible", "communication", "interpersonal"], "languages_combined": [{"language": "english", "language_level": ["proficient"]}, {"language": "chinese", "language_level": ["proficient"]}]}, "experience_required": {"duration": ["minimum 2 years"], "field": ["related", "relevant working experience", "engineering", "information technology"]}}, {"job_id": "100003009055936", "location_code": "hk", "company": "HKT", "job_title": "External Job TitleSenior Technical Officer, Network Monitoring and Surveillance", "description": "Your role\n\nAssist an operation team to deliver project implementation service and maintenance support service to the customer\nCoach the operation team in the way of service delivery and improvement on their technical skills\nConduct preparation, equipment staging, installation and commissioning, network acceptance test and project document upon completion of the project\nAssist manager to review the daily service reports and take improvement actions\nCollaborate with internal parties the test plan, implementation plan and migration plan\nBuild the network documents to supervisor verify for the completed projects/installation\n\nTo succeed in the role\n\nDegree or Higher Diploma holders in Communications, Electronics, Information Technology or related disciplines with 2 years of relevant working experience in technologies\nA quick learner to explore new technologies and solutions\nHands-on experience with large-scale implementation and support\nA good team player with good communication, problem solving and interpersonal skills to deal with vendor and internal parties\nIn-depth hands-on technical knowledge of routing and switching and wireless network technology and product knowledge of Cisco, Juniper, Huawei, Fortinet, AWS, Azure or Google Cloud\nGood command of both written and spoken English", "employment_types": ["Full Time"], "selling_points": [], "locations": ["Lai Chi Kok"], "categories": ["Engineering", "Telecommunication / Wireless / Radio"], "post_time": "2022-01-18T03:06:23Z", "salary": {"currency": null, "max": null, "min": null, "period": "monthly", "term": null}, "salary_visible": false, "title_keywords": ["technical officer"], "responsibilities": ["service delivery", "installation", "collaborate with", "commissioning", "maintenance support", "review", "implementation", "communication", "reports", "plan", "migration", "internal parties"], "requirements": {"degrees": ["diploma", "degree"], "majors": ["related disciplines", "communications", "information technology"], "languages": ["english"], "language_level": ["good command"], "hard_skills": ["azure", "maintenance", "vendor", "aws", "problem solving"], "soft_skills": ["good team player", "quick learner", "communication", "problem solving", "hands-on", "interpersonal skills", "technical skills"], "languages_combined": [{"language": "english", "language_level": ["good command"]}]}, "experience_required": {"duration": ["2 years"], "field": ["related", "relevant working experience", "information technology"]}}, {"job_id": "100003009055457", "location_code": "hk", "company": "HKT", "job_title": "Senior Technical Officer, Network monitoring and surveillance (Exchange Operations)", "description": "Your role\n\nAssist supervisor to operate Data Center in high service level to meet the ISO Quality and Security Standard\nResolve network problem in Data Center\nOperate and maintain the building facilities inside Data Center\nManage customers on service provisioning and service restoration\nCarry out 7 x 24 shift duties in Data Center is required\n\nTo succeed in the role\n\nHigher Diploma/Higher Certificate in Information Technology, Computer Science, Communication Engineering with 2 years\u2019 experience in Data Center or less experience with strong recommendation will also be considered\nDSE graduated with 3 years\u2019 relevant experience or less experience with strong recommendation will also be considered\nHolder of related certifications e.g. CDCP, CCNA or ITIL\u00a0will be an advantage\nGood customer services and interpersonal skills\nA team player who is able to work independently\nProficient in spoken and written in both English and Chinese\n\nIf you have the desire for an exciting and rewarding career, please send us your resume, quoting the reference number, your present and expected salary by Whatsapp, email or post to the Human Resources Department.\n\n\u00a0Whatsapp:\u00a05410 6137\n\nPost: HR-ENGINEERING, 13/F, Lai Chi Kok Engineering Center, 4 Yuet Lun Street, Lai Chi Kok, Kowloon.on other job opportunities of PCCW, please visit our website at http://www.pccw.com/Careers/Job+Opportunities+%26+Application/Current+Opportunities?language=en_US", "employment_types": ["Full Time"], "selling_points": [], "locations": ["Lai Chi Kok"], "categories": ["Engineering", "Electrical / Electronics", "Telecommunication / Wireless / Radio"], "post_time": "2022-01-18T02:37:06Z", "salary": {"currency": null, "max": null, "min": null, "period": "monthly", "term": null}, "salary_visible": false, "title_keywords": ["operations", "senior technical officer"], "responsibilities": ["data", "hr", "quality", "website", "customer services", "communication", "maintain"], "requirements": {"degrees": ["diploma", "higher certificate", "dse"], "majors": ["engineering", "computer science", "information technology"], "languages": ["english", "chinese"], "language_level": ["proficient"], "hard_skills": ["itil", "whatsapp", "ccna"], "soft_skills": ["communication", "team player", "interpersonal skills", "work independently"], "languages_combined": [{"language": "english", "language_level": ["proficient"]}, {"language": "chinese", "language_level": ["proficient"]}]}, "experience_required": {"duration": ["3 years", "2 years"], "field": ["relevant experience", "engineering", "information technology"]}}, {"job_id": "100003009052028", "location_code": "hk", "company": "China Unicom (Hong Kong) Operations Limited", "job_title": "Senior IDC Engineer", "description": "Responsibilities:\n1. Responsible to manage engineering project which includes solution design and site management.\n2. Responsible to supervise the construction, testing and commissioning of E&M systems on data center construction projects.\n3. Responsible to manage and ensure timely delivery of IDC Projects.\n4. Responsible to perform day-to-day operation, repairing and maintenance of the data center.\n5. Responsible to handle ad hoc duties.\n\nRequirements:\n1. Bachelor degree or above and a good knowledge of project management and facilities management.\n2. 5 years working experience in M&E industry, Grade B electrical worker.\n3. Degree in Building Services and Electrical engineering or equivalent.\n4. Good written communication and verbal presentation skill in both English and Chinese (Cantonese and Putonghua).\n5. Solid experience in data center construction project, facility management, testing and commissioning .\n6. Working experience in Data Center will be an advantage.\n7. Willing to work over-time.", "employment_types": ["Full Time", "Permanent"], "selling_points": ["Free shuttle bus", "Lunch allowance", "Performance Bonus + Group Medical"], "locations": ["Tseung Kwan O"], "categories": ["Engineering", "Engineering Project Management", "Telecommunication / Wireless / Radio"], "post_time": "2022-01-17T01:52:44Z", "salary": {"currency": null, "max": null, "min": null, "period": "monthly", "term": null}, "salary_visible": false, "title_keywords": ["engineer"], "responsibilities": ["ad hoc duties", "commissioning", "maintenance", "data", "systems", "site management", "design", "testing", "day-to-day operation"], "requirements": {"degrees": ["degree", "degree or above", "bachelor"], "majors": ["project management", "building services", "electrical engineering"], "languages": ["cantonese", "putonghua", "english", "chinese"], "language_level": ["good"], "hard_skills": ["presentation skill", "project management", "facilities management"], "soft_skills": ["communication", "project management", "presentation skill"], "languages_combined": [{"language": "cantonese", "language_level": ["good"]}, {"language": "putonghua", "language_level": ["good"]}, {"language": "english", "language_level": ["good"]}, {"language": "chinese", "language_level": ["good"]}]}, "experience_required": {"duration": ["5 years"], "field": ["management", "construction", "testing"]}}, {"job_id": "100003009055603", "location_code": "hk", "company": "HKT", "job_title": "Technicain", "description": "Your role\n\nCarry out installation, operation & maintenance work of DC power plants in HKT premises and customer sites\nCarry out performance test, commissioning and acceptance test of dc power equipment\nPerform emergency support duty on DC power equipment\nCoordinate with relevant parties to perform installation, operation and maintenance work\nHandle achoc job assigned by supervisor\n\nTo succeed in the role\n\nForm 5 / DSE graduate/ Certificate /Diploma in Electronic or related disciplines\nKnowledge in DC power equipment\nGood communication and writing skills in English and Chinese\nFresh graduate is welcome", "employment_types": ["Full Time"], "selling_points": [], "locations": ["Lai Chi Kok"], "categories": ["Engineering", "Telecommunication / Wireless / Radio"], "post_time": "2022-01-18T02:47:01Z", "salary": {"currency": null, "max": null, "min": null, "period": "monthly", "term": null}, "salary_visible": false, "title_keywords": [], "responsibilities": ["installation", "commissioning", "maintenance", "coordinate with", "communication"], "requirements": {"degrees": ["diploma", "fresh graduate", "certificate", "form 5", "dse"], "majors": ["related disciplines"], "languages": ["english", "chinese"], "language_level": ["good"], "hard_skills": ["dc", "maintenance", "writing skills"], "soft_skills": ["communication", "writing skills"], "languages_combined": [{"language": "english", "language_level": ["good"]}, {"language": "chinese", "language_level": ["good"]}]}, "experience_required": {"duration": [], "field": []}}, {"job_id": "100003009055454", "location_code": "hk", "company": "HKT", "job_title": "Assistant Engineer, Exchange Infrastructure planning & design", "description": "Your role\u00a0\n\nThe successful candidate will provide assistance in the planning and operation activities for HKT exchanges and data centers in either one of the two disciplines\n\nInfrastructure Planning and design - Data Center / Exchange Center\nLead a small team to design in accommodation planning, equipment layout, cable route and building facilities provision to support the telecom equipment infrastructure\nPerform the planning in Data Center, design equipment layout, implementation works and contractors\u2019 management\nKeep building facilities knowledge update to fulfill the telecom equipment growth\nDevelop the process automation to improve work efficiency\nDC Power Planning & Operations\nCollaborate with various parties on ISO quality audit and ensure works are meeting the standard requirement.\nSupervise the installation and upgrade works of DC power plant\nCarry out operation and maintenance work of DC power plant\nManage vendors to secure the supply of high quality and cost effective products\n\n\nTo succeed in the role\u00a0\n\u00a0\n\nDegree holder or Higher Diploma/Higher Certificate in Electrical, Information System, Computer Science, Communication Engineering or related disciplines with 3 years\u2019 relevant experiences in telecommunications or IT industry.\nWell organized, analytical, hardworking and good interpersonal skills\nHolder of registered electrical worker license A or above is preferable\nKnowledge in Data Center design, AutoCAD / BIM (Building Information Modeling) / software program and holding professional certificate of CDCP is an advantage\nProficient in spoken and written in both English and Chinese\nCandidate with less experience or lower qualifications will be considered as Senior Technical Officer\n\nIf you have the desire for an exciting and rewarding career, please send us your resume, quoting the reference number, your present and expected salary by Whatsapp, email or post to the Human Resources Department.\n\n\u00a0Whatsapp:\u00a05410 6137\n\nPost: HR-ENGINEERING, 13/F, Lai Chi Kok Engineering Center, 4 Yuet Lun Street, Lai Chi Kok, Kowloon.on other job opportunities of PCCW, please visit our website at http://www.pccw.com/Careers/Job+Opportunities+%26+Application/Current+Opportunities?language=en_US", "employment_types": ["Full Time"], "selling_points": [], "locations": ["Lai Chi Kok"], "categories": ["Engineering", "Electrical / Electronics", "Telecommunication / Wireless / Radio"], "post_time": "2022-01-18T02:36:51Z", "salary": {"currency": null, "max": null, "min": null, "period": "monthly", "term": null}, "salary_visible": false, "title_keywords": ["assistant engineer"], "responsibilities": ["collaborate with", "software", "data", "operations", "quality", "audit", "design", "website", "communication", "infrastructure", "implementation", "develop", "provide assistance", "installation", "management", "cost", "maintenance", "lead a small team", "hr", "planning"], "requirements": {"degrees": ["certificate", "diploma", "higher certificate", "degree holder"], "majors": ["engineering", "design", "related disciplines", "it", "computer science"], "languages": ["english", "chinese"], "language_level": ["proficient"], "hard_skills": ["small", "maintenance", "information system", "bim", "autocad", "whatsapp", "dc", "exchange"], "soft_skills": ["communication", "well organized", "hardworking", "interpersonal skills"], "languages_combined": [{"language": "english", "language_level": ["proficient"]}, {"language": "chinese", "language_level": ["proficient"]}]}, "experience_required": {"duration": ["3 years"], "field": ["related", "telecommunications", "it", "engineering"]}}, {"job_id": "100003009055463", "location_code": "hk", "company": "HKT", "job_title": "Senior Technical Officer", "description": "- Support Public Cloud Managed Services on-boarding and service delivery.\n\n- Handle customer monthly review and complex MS issues\n\n- Help develop and test automation tools to enhance MS service\n\n- Perform private cloud network equipments testing and provide technical support to operation team\n\n- Experience in Cloud computing and networking is a must\n\n- Holder of Public Cloud certificates (e.g. AWS, Azure)\u00a0is desired", "employment_types": ["Full Time"], "selling_points": [], "locations": ["Lai Chi Kok"], "categories": ["Engineering", "Telecommunication / Wireless / Radio"], "post_time": "2022-01-18T02:37:26Z", "salary": {"currency": null, "max": null, "min": null, "period": "monthly", "term": null}, "salary_visible": false, "title_keywords": ["senior technical officer"], "responsibilities": ["service delivery", "technical support", "review", "testing", "develop"], "requirements": {"degrees": [], "majors": [], "languages": [], "language_level": [], "hard_skills": ["azure", "aws"], "soft_skills": [], "languages_combined": []}, "experience_required": {"duration": [], "field": []}}, {"job_id": "100003009056022", "location_code": "hk", "company": "PCCW Solutions", "job_title": "Technical Officer - Civil Aviation Engineering- Open For Fresh Graduates", "description": "Technical Officer of Civil Aviation Engineering (Air Traffic Control Systems Operation and Maintenance / Project)\n\nThe Job:\n\nDepartment of Travel and Transportation is looking for Technical Officer(s) in following Civil Aviation Engineering teams:\n\n\u00a0Air Traffic Control Systems Operation and Maintenance Team\n\nAssist in performing technical operations, maintenance/repair for air traffic control (ATC), airport related systems or electronic/communication/IT equipment/systems and its ancillary support facilities\nAssist in planning, organizing, supervising and/or directly carrying out maintenance/repair works of systems/equipment and conducting system review to ensure system reliability and availability\nAssist in or directly and dependently carrying out equipment preventive/corrective maintenance, on-site equipment installation, testing and commissioning, fault diagnosis and repair according to a rectification plan/solution as well as helping one\u2019s supervisor in preparing fault/problem investigation report and/or procurement plan for spare parts or maintenance/repair services\nAssist in coordination with various internal and external parties such as various government departments, local or overseas airport authority, vendors/suppliers, sub-contractors and so on for operations and maintenance works\n\n\u00a0Project Team\n\nAssist in performing project work for air traffic control (ATC), airport related systems or electronic/communication/IT equipment/systems and its ancillary support facilities\nAssist in preparing solution for project tender bidding and implementation of project including drafting design submission, requirements for materials/service procurement, supervision/monitoring of sub-contractors installation works, preparation of test plan/report, conduct testing and commissioning\nAssist in project progress monitoring, financial monitoring and control of projects to ensure satisfactory completion of project within budget and schedule and help one\u2019s supervisor to prepare project/works progress reports for submission or logistics support\nAssist in coordination with various internal and external parties such as various government departments, local or overseas airport authority, vendors/suppliers, sub-contractors and so on for operations and maintenance works\n\nTeam allocation is based on qualifications, experience and personal attributes of the appointee.\n\nThe Person\n\nCertificate or above in Electronics/Electrical/Telecommunication/Computer/ Software/Information/e-logistics/Industrial Engineering or other related disciplines\nPossession of training record of Air Traffic Safety Electronic Personnel/Professional (ATSEP) training course is an advantage\nPossessing track record of relevant hands-on working experience in system design, building, testing and commissioning, operations and maintenance in mission critical service or project is highly preferable\nGood team player, customer-focused mindset, open-mindedness, proactive, result/service oriented, total quality management and safety concept with strong logical analytical, communication and interpersonal skills\nAble to work independently under pressure with strong desire and commitment to deliver high quality of works in short notice\nGood spoken and written English is a must. Knowledge of Putonghua is preferred\nFresh graduates will also be considered\nPossessing driving license is an advantage\nMay work in shift duty and/or irregular hours including overnight, Saturdays, Sundays and public holidays and/or outdoor as required", "employment_types": ["Full Time"], "selling_points": [], "locations": ["Tung Chung"], "categories": ["Transportation & Logistics", "Aerospace", "Engineering", "Electrical / Electronics", "Telecommunication / Wireless / Radio"], "post_time": "2022-01-18T03:11:54Z", "salary": {"currency": null, "max": null, "min": null, "period": "monthly", "term": null}, "salary_visible": false, "title_keywords": ["technical officer"], "responsibilities": ["supervising", "operations", "coordination with", "internal and external parties", "budget", "design", "communication", "plan", "control", "progress reports", "teams", "implementation", "project progress", "testing", "logistics", "schedule", "tender", "report", "installation", "commissioning", "review", "rectification", "monitoring", "investigation", "maintenance", "systems", "repair", "it equipment", "planning"], "requirements": {"degrees": ["certificate"], "majors": ["related disciplines", "engineering"], "languages": ["putonghua", "english"], "language_level": ["good"], "hard_skills": ["system design", "maintenance"], "soft_skills": ["good team player", "work independently", "under pressure", "customer-focused mindset", "hands-on", "communication and interpersonal skills", "proactive"], "languages_combined": [{"language": "putonghua", "language_level": []}, {"language": "english", "language_level": ["good"]}]}, "experience_required": {"duration": [], "field": ["system design", "maintenance", "testing"]}}, {"job_id": "100003009055530", "location_code": "hk", "company": "China Mobile International Limited", "job_title": "Assistant Project Manager (CMIJD-0819-APMD&SDCHK)", "description": "Responsibilities:\n\nProject management for data business service delivery, including IEPL/IPLC, IDC, MPLS VPN, IP Transit and etc.\nManage and provide regular progress update during the project lifecycle for new circuit installation, upgrade, and relocation etc.\nCoordinate with domestic China Mobile Company and business partner/vendor to deliver the service on time.\nConduct risk management, procedure optimization and escalate all outstanding issue during provisioning stage.\nEstablish and maintain a good relationship with customers, internal teams.\nWork with overseas customers during non-office hour if necessary.\nCoordinate with internal parties to enhance the quality level if necessary.\nConsolidate, revise and update internal reports weekly and monthly.\nRequirements:\n\nBachelor's degree or above\nTechnical background such as CCNA, CCNP, IP networking skills will be an advantage\nMinimum 5 years of experience\nExcellent teamwork skills, hardworking, self-motived and able to work under pressure\nExcellent written and verbal communication skills in both English and Mandarin\n*Candidate with less experience will be considered as Senior Specialist\n\n\nInterested parties please apply in\u00a0full resume with current and expected salary\u00a0by e-mail to\u00a0hr\u00a0@\u00a0cmi.chinam obil e.com.\u00a0 Please indicate the reference in the subject line.\n\nAll personal data collected will be used for recruitment and employment related purpose only.", "employment_types": ["Full Time", "Permanent"], "selling_points": ["Manage global project delivery process", "Data service project management", "IP Transit, IEPL/UPLC, IDC, MPLS VPN"], "locations": ["Kwai Hing"], "categories": ["Engineering", "Engineering Project Management", "Telecommunication / Wireless / Radio", "Sales, CS & Business Devpt", "Technical Sales / Sales Engineer"], "post_time": "2022-01-18T02:40:53Z", "salary": {"currency": null, "max": null, "min": null, "period": "monthly", "term": null}, "salary_visible": false, "title_keywords": ["assistant project manager"], "responsibilities": ["service delivery", "installation", "management", "data", "coordinate with", "teams", "quality", "good relationship", "project management", "maintain", "reports", "internal parties"], "requirements": {"degrees": ["degree or above", "bachelor"], "majors": [], "languages": ["english", "mandarin"], "language_level": ["excellent"], "hard_skills": ["ip", "ccnp", "ccna"], "soft_skills": ["communication skills", "teamwork", "hardworking", "work under pressure"], "languages_combined": [{"language": "english", "language_level": ["excellent"]}, {"language": "mandarin", "language_level": ["excellent"]}]}, "experience_required": {"duration": ["minimum 5 years"], "field": []}}, {"job_id": "100003009056025", "location_code": "hk", "company": "PCCW Solutions", "job_title": "Technical Officer - Civil Aviation Engineering", "description": "Technical Officer of Civil Aviation Engineering (Air Traffic Control Systems Operation and Maintenance / Project)\n\nThe Job:\n\nDepartment of Travel and Transportation is looking for Technical Officer(s) in following Civil Aviation Engineering teams:\n\n\u00a0Air Traffic Control Systems Operation and Maintenance Team\n\nAssist in performing technical operations, maintenance/repair for air traffic control (ATC), airport related systems or electronic/communication/IT equipment/systems and its ancillary support facilities\nAssist in planning, organizing, supervising and/or directly carrying out maintenance/repair works of systems/equipment and conducting system review to ensure system reliability and availability\nAssist in or directly and dependently carrying out equipment preventive/corrective maintenance, on-site equipment installation, testing and commissioning, fault diagnosis and repair according to a rectification plan/solution as well as helping one\u2019s supervisor in preparing fault/problem investigation report and/or procurement plan for spare parts or maintenance/repair services\nAssist in coordination with various internal and external parties such as various government departments, local or overseas airport authority, vendors/suppliers, sub-contractors and so on for operations and maintenance works\n\n\u00a0Project Team\n\nAssist in performing project work for air traffic control (ATC), airport related systems or electronic/communication/IT equipment/systems and its ancillary support facilities\nAssist in preparing solution for project tender bidding and implementation of project including drafting design submission, requirements for materials/service procurement, supervision/monitoring of sub-contractors installation works, preparation of test plan/report, conduct testing and commissioning\nAssist in project progress monitoring, financial monitoring and control of projects to ensure satisfactory completion of project within budget and schedule and help one\u2019s supervisor to prepare project/works progress reports for submission or logistics support\nAssist in coordination with various internal and external parties such as various government departments, local or overseas airport authority, vendors/suppliers, sub-contractors and so on for operations and maintenance works\n\nTeam allocation is based on qualifications, experience and personal attributes of the appointee.\n\nThe Person\n\nCertificate or above in Electronics/Electrical/Telecommunication/Computer/ Software/Information/e-logistics/Industrial Engineering or other related disciplines\nPossession of training record of Air Traffic Safety Electronic Personnel/Professional (ATSEP) training course is an advantage\nPossessing track record of relevant hands-on working experience in system design, building, testing and commissioning, operations and maintenance in mission critical service or project is highly preferable\nGood team player, customer-focused mindset, open-mindedness, proactive, result/service oriented, total quality management and safety concept with strong logical analytical, communication and interpersonal skills\nAble to work independently under pressure with strong desire and commitment to deliver high quality of works in short notice\nGood spoken and written English is a must. Knowledge of Putonghua is preferred\nFresh graduates will also be considered\nPossessing driving license is an advantage\nMay work in shift duty and/or irregular hours including overnight, Saturdays, Sundays and public holidays and/or outdoor as required", "employment_types": ["Full Time"], "selling_points": [], "locations": ["Tung Chung"], "categories": ["Engineering", "Electrical / Electronics", "Engineering Project Management", "Telecommunication / Wireless / Radio"], "post_time": "2022-01-18T03:11:59Z", "salary": {"currency": null, "max": null, "min": null, "period": "monthly", "term": null}, "salary_visible": false, "title_keywords": ["technical officer"], "responsibilities": ["supervising", "operations", "coordination with", "internal and external parties", "budget", "design", "communication", "plan", "control", "progress reports", "teams", "implementation", "project progress", "testing", "logistics", "schedule", "tender", "report", "installation", "commissioning", "review", "rectification", "monitoring", "investigation", "maintenance", "systems", "repair", "it equipment", "planning"], "requirements": {"degrees": ["certificate"], "majors": ["related disciplines", "engineering"], "languages": ["putonghua", "english"], "language_level": ["good"], "hard_skills": ["system design", "maintenance"], "soft_skills": ["good team player", "work independently", "under pressure", "customer-focused mindset", "hands-on", "communication and interpersonal skills", "proactive"], "languages_combined": [{"language": "putonghua", "language_level": []}, {"language": "english", "language_level": ["good"]}]}, "experience_required": {"duration": [], "field": ["system design", "maintenance", "testing"]}}, {"job_id": "100003009055459", "location_code": "hk", "company": "HKT", "job_title": "Assistant Engineer, Networking Operations Center", "description": "Your role\n\nLead a team to manage the operation in Data Center to meet the ISO Quality and Security Standard\nManage and communicate with customers to meet the requirements\nAssist manager to formulate daily operation manual, event handling procedures and business continuity plan\nPrepare operation and incident reports to maintain service level and prevention of future incident\nSupport emergency duties and 7 x 24 shift duties in Data Center is required\n\nTo succeed in the role\n\nDegree holder in Information Technology / Computer Science / Communication Engineering with 3 years\u2019 working experience or Higher Diploma with 5 years\u2019 experience in Data Center\u00a0\nObtain CDCP certificate\nHolder of ITIL, AOS or VCP certificate is an advantage\nStrong leadership and interpersonal skills\nGood customer handling\u00a0skill\nProficient in spoken and written English and Chinese\n\nIf you have the desire for an exciting and rewarding career, please send us your resume, quoting the reference number, your present and expected salary by Whatsapp, email or post to the Human Resources Department.\n\n\u00a0Whatsapp:\u00a05410 6137\n\nPost: HR-ENGINEERING, 13/F, Lai Chi Kok Engineering Center, 4 Yuet Lun Street, Lai Chi Kok, Kowloon.on other job opportunities of PCCW, please visit our website at http://www.pccw.com/Careers/Job+Opportunities+%26+Application/Current+Opportunities?language=en_US", "employment_types": ["Full Time"], "selling_points": [], "locations": ["Lai Chi Kok"], "categories": ["Engineering", "Electrical / Electronics", "Telecommunication / Wireless / Radio"], "post_time": "2022-01-18T02:37:11Z", "salary": {"currency": null, "max": null, "min": null, "period": "monthly", "term": null}, "salary_visible": false, "title_keywords": ["operations", "assistant engineer"], "responsibilities": ["communicate with", "business continuity", "data", "hr", "daily operation", "quality", "procedures", "website", "communication", "lead a team", "maintain", "reports", "plan"], "requirements": {"degrees": ["certificate", "diploma", "degree holder"], "majors": ["engineering", "computer science", "information technology"], "languages": ["english", "chinese"], "language_level": ["proficient"], "hard_skills": ["itil", "whatsapp"], "soft_skills": ["communication", "leadership", "interpersonal skills"], "languages_combined": [{"language": "english", "language_level": ["proficient"]}, {"language": "chinese", "language_level": ["proficient"]}]}, "experience_required": {"duration": ["3 years", "5 years"], "field": ["engineering", "information technology"]}}, {"job_id": "100003009055746", "location_code": "hk", "company": "PCCW Solutions", "job_title": "Tech Talent - Enginnering Associate", "description": "The Job\n\nAcquire engineering solutions knowledge and soft skills through on-the-job training in different projects in Hong Kong and Macau\nAttach to high-value engineering projects in the areas of sound and innovative technical solutions, solutions development and delivery, project management, engineering system operations, support and management\nDevelop a rewarding career in an advanced, fast-paced and multi cultural environment\n\nThe Person\n\nBachelor / Master degree in Electronic / Electrical / Information Engineering, Communication Engineering, IT or related disciplines with less than 2 years of full-time working experience\nGood presentation, interpersonal and communication skills\nA good team player with analytical and problem-solving skills and who relishes challenges\nGood command of spoken and written English and Chinese\n\n\u00b7\u00a0\u00a0\u00a0\u00a0\u00a0\u00a0\u00a0\u00a0\u00a0\n\n\u00b7\u00a0\u00a0\u00a0\u00a0\u00a0\u00a0\u00a0\u00a0\u00a0", "employment_types": ["Full Time"], "selling_points": [], "locations": ["Mong Kok"], "categories": ["Engineering", "Electrical / Electronics", "Engineering Project Management", "Telecommunication / Wireless / Radio"], "post_time": "2022-01-18T02:55:02Z", "salary": {"currency": null, "max": null, "min": null, "period": "monthly", "term": null}, "salary_visible": false, "title_keywords": ["associate"], "responsibilities": ["project management", "management", "operations", "develop"], "requirements": {"degrees": ["bachelor", "master degree"], "majors": ["related disciplines", "it", "engineering"], "languages": ["english", "chinese"], "language_level": ["good command"], "hard_skills": ["problem-solving skills"], "soft_skills": ["communication skills", "good team player", "presentation", "communication", "problem-solving skills", "interpersonal"], "languages_combined": [{"language": "english", "language_level": ["good command"]}, {"language": "chinese", "language_level": ["good command"]}]}, "experience_required": {"duration": ["2 years"], "field": ["related", "it", "engineering"]}}, {"job_id": "100003009055453", "location_code": "hk", "company": "HKT", "job_title": "Mobile/ Web Programmer (holding the Senior Technical Officer position, welcome fresh grad.)", "description": "Your role\n\nDevelopment and implementation of Full stack mobile or web applications for customer\nResponsible for design, implement, test and maintenance on the Full stack mobile or web applications\nManage customer requirements and transform into functional requirements and technical specifications\nMaintain good documentation of developed applications\n\nTo succeed in the role\n\nDegree / High Diploma in Computer Science, Communication\u00a0Engineering or related disciplines with minimum 2 years\u2019 relevant experience in telecommunication industry\nStrong knowledge in\u00a0HTML5, CSS3, JavaScript, jQuery, Ajax, JSON, XML, RESTful API, SQL\nFamiliar with Git or other version control tools\nKnowledge in JavaScript framework (Vue, React, Angular), backend programming language such as PHP, Python, JAVA, or C++ will be an advantage\nCertification in Networking is preferable (e.g. CCNA)\nGood team player with strong analytical skills, problem solving and interpersonal skills\nProficient in spoken and written English and Chinese\nCandidate with less experience will be considered as Technical Officer\n\nIf you have the desire for an exciting and rewarding career, please send us your resume, quoting the reference number, your present and expected salary by Whatsapp, email or post to the Human Resources Department.\n\n\u00a0Whatsapp:\u00a05410 6137\n\nPost: HR-ENGINEERING, 13/F, Lai Chi Kok Engineering Center, 4 Yuet Lun Street, Lai Chi Kok, Kowloon.on other job opportunities of PCCW, please visit our website at http://www.pccw.com/Careers/Job+Opportunities+%26+Application/Current+Opportunities?language=en_US", "employment_types": ["Full Time"], "selling_points": [], "locations": ["Lai Chi Kok"], "categories": ["Engineering", "Electrical / Electronics", "Telecommunication / Wireless / Radio"], "post_time": "2022-01-18T02:36:46Z", "salary": {"currency": null, "max": null, "min": null, "period": "monthly", "term": null}, "salary_visible": false, "title_keywords": ["web programmer", "senior technical officer"], "responsibilities": ["control", "maintenance", "hr", "implementation", "design", "website", "communication", "maintain", "specifications", "documentation"], "requirements": {"degrees": ["high diploma", "degree"], "majors": ["related disciplines", "engineering", "computer science"], "languages": ["english", "chinese"], "language_level": ["proficient"], "hard_skills": ["c++", "jquery", "java", "git", "ccna", "problem solving", "ajax", "restful api", "analytical skills", "sql", "whatsapp", "javascript", "angular", "python", "documentation", "web applications", "maintenance", "react", "php", "mobile", "programming"], "soft_skills": ["good team player", "responsible", "analytical skills", "communication", "problem solving", "interpersonal skills"], "languages_combined": [{"language": "english", "language_level": ["proficient"]}, {"language": "chinese", "language_level": ["proficient"]}]}, "experience_required": {"duration": ["minimum 2 years"], "field": ["related", "relevant experience", "engineering"]}}, {"job_id": "100003009051992", "location_code": "hk", "company": "China Mobile International Limited", "job_title": "Global Graduate Trainee 2022 (Ref:CMIJD-0117-GGTHK)", "description": "Your Bright Future Starts Here\n\nThe Global Graduate Trainee Program is designed as a 12-month fast-track career development for talented university graduates in our regional office. We aim to unleash your potential and lead you a promising career at China Mobile International Limited (CMI) with the following program details.\n\nStart YOUR career journey with CMI by 3 Streams:\n\nTechnology and Network Stream\u00a0 (e.g. Solution Management, Project Management, Network Planning & Development, Implementation Engineer, Information Technology, etc)\nBusiness Stream\u00a0 (e.g. Sales & Business Development, Product Management, Marketing & Market Analysis, Business Operations Support, etc.)\nGeneral Supporting Stream\u00a0 (e.g. Human Resources, Finance & Accounting, Merge & Acquisition, Procurement, Legal, etc.)\n\nProgram Structure:\n\nIntensive learning and development program to acquire core job knowledge and skillsets\nFor Hong Kong applicants, he/she will be based in Hong Kong Global Headquarters with International assignment participation\nOverseas Working Opportunities and Job Rotation in global operations\nValuable opportunity for personal development and catch the exponential growth of CMI\nCross-departmental and international exposure through various projects to understand company business and operations\nDirect coaching and mentoring provided by managers\n\nExploring by Visit and Activities:\n\nGlobal Network Center Visit\nChina Mobile Southern Base Visit\nStrategic Partner Learning Tour\nCMCC Learning Tour\nCMI Corporate Social Responsibility Activities\n\nQualification\uff1a\n\n\n\nFinal year students or recent graduates from Business, Engineering and Information Technology or related disciplines\nEntrepreneurial and innovative\nPassionate in the IT & Telecommunications industry\nExcellent command of written and spoken English\nKnowledge of Mandarin and Cantonese will be an advantage\n\nApplication Method:\n\nPlease submit your application through our online application system on or before 13 March 2022 (Sunday)\n(https://careers.cmi.chinamobile.com/#/recruitIndex?channel=school&location=school&channelId=1001S31000000003WCK6&publishId=1001S3100000000GI80Y&isApplicant=true)\n\nYou may visit our Career Page for more details of GGT 2022 Program.(https://www.cmi.chinamobile.com/corporate-information/who-you-can-be).\n\nFor any enquiries on our Global Graduate Trainee Program, please contact us by email, HR.GTProgram @ cmi.chinamobile.com and state the apply location on email subjects, e.g. \"Hong Kong\u00a0- Global Graduate Trainee\".", "employment_types": ["Full Time", "Permanent"], "selling_points": ["Global Graduate Trainee", "12-month fast-track career development for talents", "Intensive learning and development program"], "locations": ["Kwai Hing"], "categories": ["Engineering", "Telecommunication / Wireless / Radio", "Marketing / Public Relations", "Public Relations - General / Support", "Management", "Management Trainee"], "post_time": "2022-01-17T01:46:35Z", "salary": {"currency": null, "max": null, "min": null, "period": "monthly", "term": null}, "salary_visible": false, "title_keywords": ["graduate trainee"], "responsibilities": ["management", "operations", "hr", "implementation", "application system", "project management", "market analysis", "contact", "career development", "planning"], "requirements": {"degrees": [], "majors": [], "languages": ["cantonese", "english", "mandarin"], "language_level": ["advantage", "excellent"], "hard_skills": ["mobile", "project management", "analysis", "application system"], "soft_skills": ["passionate", "project management", "learning", "innovative"], "languages_combined": [{"language": "cantonese", "language_level": ["advantage"]}, {"language": "english", "language_level": ["excellent"]}, {"language": "mandarin", "language_level": ["advantage"]}]}, "experience_required": {"duration": [], "field": []}}, {"job_id": "100003009049374", "location_code": "hk", "company": "HGC Global Communications Limited", "job_title": "Technical Officer / Senior Technical Officer (Fixed Network)", "description": "Job Responsibilities:\n\nTo conduct site measurement & inspection of external cable network to various target of planning building / area;\nTo liaise with internal and external parties such as contractor, engineers and technical staff for necessary planning and fitting out project;\nConduct site measurement and inspection of external cable network for planning and proposal of building / area;\nProvide management services to monitor the work progress of the contractor for work implementation;\nPrepare site drawing , site proposal, as-built drawings and update on system;\nPrepare planning and proposal for major project and to liaise concerned internal and external parties for necessary implementation.\n\nJob Requirements:\n\nDiploma holder in IT or related discipline;\n2-3 years relevant working experience;\nHands on experience in MS Office Applications ;\nHolder of driving license will be an advantage;\nGood analytical, PC / device trouble shooting, and problem solving skills;\nGood interpersonal skill and a good team player;\nMature, dynamic, work independent and self-motivated;\nGood spoken and written English and Cantonese, Mandarin a plus.\n\nWe offer competitive salary package and career development opportunity. Free company coach is provided.\u00a0 Interested parties, please quote our reference number and apply with full resume, present and expected salary, by clicking \u201cAPPLY NOW\u201d.\u00a0\n\nWe are an equal opportunity employer and welcome applications from all qualified candidates. Information provided will be treated in strict confidence and only be used for consideration of your application for the relevant post within HGC Global Communications Limited. Personal data provided by job applicants will be used strictly according to our Personal Information Collection Statement, a copy of which will be available upon written request. Information of unsuccessful candidates will be destroyed within six months.", "employment_types": ["Full Time", "Permanent"], "selling_points": ["Diploma holder in IT or related discipline", "2-3 years relevant working experience", "To conduct site measurement & inspection"], "locations": ["Tsing Yi"], "categories": ["Public / Civil", "Civil Services", "Engineering", "Engineering Project Management", "Telecommunication / Wireless / Radio"], "post_time": "2022-01-14T08:31:46Z", "salary": {"currency": null, "max": null, "min": null, "period": "monthly", "term": null}, "salary_visible": false, "title_keywords": ["technical officer", "senior technical officer"], "responsibilities": ["liaise", "management", "internal and external parties", "measurement", "monitor", "implementation", "inspection", "drawings", "liaise with", "planning"], "requirements": {"degrees": ["diploma holder"], "majors": ["it"], "languages": ["cantonese", "english", "mandarin"], "language_level": ["good"], "hard_skills": ["plus", "dynamic", "pc", "problem solving skills", "ms office"], "soft_skills": ["good team player", "self-motivated", "independent", "mature", "interpersonal skill", "hands on", "dynamic", "problem solving skills"], "languages_combined": [{"language": "cantonese", "language_level": ["good"]}, {"language": "english", "language_level": ["good"]}, {"language": "mandarin", "language_level": ["good"]}]}, "experience_required": {"duration": ["2-3 years"], "field": ["relevant working experience"]}}, {"job_id": "100003009049373", "location_code": "hk", "company": "HGC Global Communications Limited", "job_title": "Technical Officer - Network Surveillance", "description": "Responsibility:\n\nProactively monitors network devices (IP/Transmission/Voice) and other facilities and components\nAnalyzes alarms information from operation support systems and follow up further actions if required\nEscalates network problems to appropriate vendors and/or internal personnel in accordance with department procedure and manages issues through to resolution\nReceives network alerts and logs them onto Ticketing System if required\nProvide 7 x 24 shift duty based on NOC Roster\nReviewing the quality of work performed by the shift\nTroubleshoots network faults impacting customer services or backbone network\u00a0\u00a0\u00a0\u00a0\u00a0\u00a0\u00a0\u00a0\u00a0\u00a0\u00a0\u00a0\u00a0\u00a0\u00a0\u00a0\u00a0\u00a0\u00a0\u00a0\u00a0\u00a0\u00a0\nExecutes detailed verification and acceptance plans of network maintenance and network change requests activity\n\nRequirements:\n\nSecondary / Matriculation major in Information & Communications Technology or related disciplines\nFresh Graduates are welcome to apply or minimum 2 years practical experience in telecom network working in a Network Operations Center\nSolid and hand on experience in operating system in Microsoft system\nSelf-motivated and able to work independently\nHolder of CCNA is referable\nGood command of written and spoken English and average in Mandarin\nShift duty is required\n\nWe offer competitive salary package and career development opportunity. Free company coach is provided.\u00a0 Interested parties, please quote our reference number and apply with full resume, present and expected salary, by clicking \u201cAPPLY NOW\u201d.\u00a0\n\nWe are an equal opportunity employer and welcome applications from all qualified candidates. Information provided will be treated in strict confidence and only be used for consideration of your application for the relevant post within HGC Global Communications Limited. Personal data provided by job applicants will be used strictly according to our Personal Information Collection Statement, a copy of which will be available upon written request. Information of unsuccessful candidates will be destroyed within six months.", "employment_types": ["Full Time", "Permanent"], "selling_points": ["7 X 24 shift duty", "experience in telecom network", "network devices (IP/Transmission/Voice)"], "locations": ["Shatin Area"], "categories": ["Engineering", "Telecommunication / Wireless / Radio", "Information Technology (IT)", "Support", "Network & System"], "post_time": "2022-01-14T08:31:46Z", "salary": {"currency": null, "max": null, "min": null, "period": "monthly", "term": null}, "salary_visible": false, "title_keywords": ["technical officer"], "responsibilities": ["maintenance", "systems", "quality", "customer services", "resolution", "plans"], "requirements": {"degrees": [], "majors": [], "languages": ["english", "mandarin"], "language_level": ["average", "good command"], "hard_skills": ["ccna"], "soft_skills": ["self-motivated", "work independently"], "languages_combined": [{"language": "english", "language_level": ["average", "good command"]}, {"language": "mandarin", "language_level": ["good command"]}]}, "experience_required": {"duration": ["minimum 2 years"], "field": []}}, {"job_id": "100003009049257", "location_code": "hk", "company": "SmarTone Telecommunications Limited", "job_title": "Engineer, Operation Systems Support", "description": "Responsibilities:\n\nResponsible for system operations and administration of OSSs and NMSs that supports SmarTone's 2G/3G, LTE and IMS mobile network surveillance and operations\nAssist in system administration activities and in-house programming development\nTrouble-shooting on hardware / software and hands-on problem diagnosis for end users.\nParticipate OSS major upgrade/ migrations project execution\nLiaise with vendor for all sorts of system hardware/software troubleshooting and system recovery actions.\nProvide after office hours on-call emergency support services upon request.\n\nRequirements:\u00a0\n\nDegree in Electronic Engineering, Computer Science, Information Technology or related disciplines\n2 years\u2019 relevant experience in system administration is preferred, fresh graduates will also be considered as junior position\nSolid experience in computer operating systems such as HP Blade platform, Oracle Solaris, Linux and Window platform\nKnowledge in Shell, Perl, PHP, SQL, Python and Java Programming\nExperience in telecommunication network management systems or operations support systems is preferred\nGood interpersonal and analytical skills\nAble to work independently and under pressure\n\nInterested parties please apply with full resume stating present and expected salary by clicking \"Apply Now\" or visiting our Website:\u00a0www.smartone.com/tc/about_us/careers/\n\nSmarTone is an equal-opportunity employer. All data supplied will be kept in strict confidence and will be used for employment related purpose. We may transfer such data to any agent, contractor or third party who provides services to us with respect to matters relating to your application. Only short-listed candidates will be contacted.\n\n\nYou are welcome to visit our website :\u00a0www.smartone.com\u00a0\u00a0", "employment_types": ["Full Time", "Permanent", "Contract"], "selling_points": ["Operations Support System operations and admin", "System upgrade/ migrations project execution", "In-house programming development"], "locations": ["Kowloon Bay"], "categories": ["Engineering", "Telecommunication / Wireless / Radio", "Information Technology (IT)", "Support", "Mobile / Wireless Communications"], "post_time": "2022-01-14T08:19:53Z", "salary": {"currency": null, "max": null, "min": null, "period": "monthly", "term": null}, "salary_visible": false, "title_keywords": ["engineer"], "responsibilities": ["migrations", "software", "operations", "support services", "troubleshooting", "hardware", "liaise with", "administration"], "requirements": {"degrees": ["degree"], "majors": ["related disciplines", "engineering", "computer science", "information technology"], "languages": [], "language_level": [], "hard_skills": ["linux", "oracle", "java", "network management", "php", "analytical skills", "sql", "programming", "python", "perl"], "soft_skills": ["work independently", "under pressure", "interpersonal", "analytical skills"], "languages_combined": []}, "experience_required": {"duration": ["2 years"], "field": ["management", "relevant experience", "administration"]}}, {"job_id": "100003009001298", "location_code": "hk", "company": "Lik On Security Limited", "job_title": "\u5730\u76e4\u7ba1\u5de5 Site Supervisor", "description": "\u00a0\u8077\u8cac\u7bc4\u7587\uff1a\n\n\n\u00a0\u00a0\u00a0\u00a0\u00a0\u00a0\u00a0\u00a0 \u76e3\u7763\u5404\u627f\u5224\u5546\u5b89\u88dd\u5f31\u96fb\u5de5\u7a0b\u9805\u76ee\n\u00a0\u00a0\u00a0\u00a0\u00a0\u00a0\u00a0\u00a0 \u8ca0\u8cac\u50b3\u905e\u826f\u597d\u5b89\u5168\u3001\u74b0\u4fdd\u548c\u8cea\u91cf\u63a7\u5236\n\u00a0\u00a0\u00a0\u00a0\u00a0\u00a0\u00a0\u00a0 \u8655\u7406\u65e5\u5e38\u5730\u76e4\u7ba1\u7406\u53ca\u5354\u8abf\u65bd\u5de5\n\u00a0\u00a0\u00a0\u00a0\u00a0\u00a0\u00a0\u00a0 \u5b9a\u671f\u51fa\u5e2d\u5de5\u7a0b\u9032\u5ea6\u53ca\u5b89\u5168\u6703\u8b70\uff0c\u4e26\u4f5c\u51fa\u76f8\u61c9\u5b89\u6392\u53ca\u5de5\u4f5c\u5206\u914d\n\u00a0\u00a0\u00a0\u00a0\u00a0\u00a0\u00a0\u00a0 \u76e3\u7763\u6e2c\u8a66\u53ca\u8abf\u8a66\u5de5\u4f5c\n\n\u5165\u8077\u8981\u6c42\uff1a\n\n\n\u00a0\u00a0\u00a0\u00a0\u00a0\u00a0\u00a0\u00a0 \u6700\u5c113\u5e74\u5f31\u96fb\u6216\u9805\u76ee\u5730\u76e4\u76e3\u7763\u7d93\u9a57\n\u00a0\u00a0\u00a0\u00a0\u00a0\u00a0\u00a0\u00a0 \u826f\u597d\u7684\u6e9d\u901a\u548c\u5730\u76e4\u7ba1\u7406\u80fd\u529b\n\u00a0\u00a0\u00a0\u00a0\u00a0\u00a0\u00a0\u00a0 \u6301\u6709\u6548\u96fb\u5de5\u724c\u548c\u5efa\u9020\u696d\u5de5\u4eba\u8a3b\u518a\u8b49\n\u00a0\u00a0\u00a0\u00a0\u00a0\u00a0\u00a0\u00a0 \u53ef\u5373\u6642\u4e0a\u73ed\u512a\u5148\u8003\u616e\n\n\u61c9\u5fb5\u8005\u8acb\u5c07\u5c65\u6b77\u8868\u53ca\u8981\u6c42\u85aa\u91d1\u96fb\u90f5(\u8acb\u6309\"APPLY NOW\") \u6216 \u90f5\u5bc4\u81f3:\u00a0\u529b\u5b89\u8b77\u885b\u6709\u9650\u516c\u53f8\u4e5d\u9f8d\u9577\u6c99\u7063\u9577\u7fa9\u885710\u865f\u660c\u9686\u5de5\u696d\u5927\u5ec88\u6a13\u884c\u653f\u90e8\u6536\u00a0\u6216\u81f4\u96fb\u00a02485-2485 \u884c\u653f\u90e8\u9810\u7d04\u9762\u8a66\u6642\u9593\u3002\n\n\u672c\u516c\u53f8\u662f\u5e73\u7b49\u6a5f\u6703\u50f1\u4e3b\uff0c\u6240\u6709\u6536\u96c6\u8cc7\u6599\u53ea\u6703\u7528\u4f5c\u62db\u8058\u7528\u9014\u3002", "employment_types": ["Full Time", "Permanent"], "selling_points": ["\u6700\u5c113\u5e74\u5f31\u96fb\u6216\u9805\u76ee\u5730\u76e4\u76e3\u7763\u7d93\u9a57", "\u6301\u6709\u6548\u96fb\u5de5\u724c\u548c\u5efa\u9020\u696d\u5de5\u4eba\u8a3b\u518a\u8b49", "\u76e3\u7763\u5404\u627f\u5224\u5546\u5b89\u88dd\u5f31\u96fb\u5de5\u7a0b\u9805\u76ee"], "locations": ["Not Specified"], "categories": ["Engineering", "Electrical / Electronics", "Telecommunication / Wireless / Radio", "Others", "Security / Safety Control"], "post_time": "2022-01-16T21:50:07Z", "salary": {"currency": null, "max": null, "min": null, "period": "monthly", "term": null}, "salary_visible": false, "title_keywords": ["site supervisor"], "responsibilities": [], "requirements": {"degrees": [], "majors": [], "languages": [], "language_level": [], "hard_skills": [], "soft_skills": [], "languages_combined": []}, "experience_required": {"duration": [], "field": []}}, {"job_id": "100003009050681", "location_code": "hk", "company": "Hutchison Telecommunications (Hong Kong) Limited", "job_title": "Senior Engineer - Data Network & Packet Core Development", "description": "Responsibilities\u00a0\n\nMobile core technology development\u00a0\nMobile policy and charging technology (PCRF, PCEF, Diameter)\nNetwork enabling technology (AAA, DRA, Traffic Load Balancing)\nVendor management\nProject management\nBusiness user requirement collection\nWork with vendor to finalize the solution details\n\nRequirements\n\nBachelor degree holder in Electronic\u00a0Engineering / Computer Science / Engineering /\u00a0Telecommunication Engineering\u00a0\n3 years of relevant working experience or above\nGood command of written and spoken Chinese and English\n\nApart from competitive remuneration package and exciting opportunity for career development within the Group, we provide attractive employee benefits such as free company shuttle, free company SIM card and preferential SIM plan offers, comprehensive medical & insurance schemes, as well as full range of other employee well-being provisions.\n\nInterested parties, please apply with full resume, present and expected salary, by clicking \u201cAPPLY NOW\u201d. Please quote the reference number on the e-mail subject.\n\nWe are an equal opportunity employer and welcome applications from all qualified candidates. Personal data collected will be treated in the strictest confidence and handled confidentially by authorised personnel for recruitment-related purposes only within the CK Hutchison Group of companies. The personal data of unsuccessful applicants will be destroyed after the recruitment exercise pursuant to the requirements of the Personal Data (Privacy) Ordinance in Hong Kong.", "employment_types": ["Full Time", "Permanent"], "selling_points": [], "locations": ["Tsing Yi"], "categories": ["Engineering", "Electrical / Electronics", "Telecommunication / Wireless / Radio", "Information Technology (IT)", "Mobile / Wireless Communications"], "post_time": "2022-01-14T11:10:24Z", "salary": {"currency": null, "max": null, "min": null, "period": "monthly", "term": null}, "salary_visible": false, "title_keywords": ["senior engineer"], "responsibilities": ["project management", "management"], "requirements": {"degrees": ["bachelor degree holder"], "majors": ["engineering", "computer science"], "languages": ["english", "chinese"], "language_level": ["good command"], "hard_skills": ["vendor"], "soft_skills": ["comprehensive"], "languages_combined": [{"language": "english", "language_level": ["good command"]}, {"language": "chinese", "language_level": ["good command"]}]}, "experience_required": {"duration": ["3 years"], "field": ["relevant working experience"]}}, {"job_id": "100003009050707", "location_code": "hk", "company": "Hutchison Telecommunications (Hong Kong) Limited", "job_title": "Engineer (In-Building Planning & Design)", "description": "Responsibilities:\n\nResponsible for indoor system design, mobile project planning, network design, document submission\u00a0and delivery\nConducting site survey, performance test and data analysis\nCoordinating project and monitoring process performance\u00a0\nPerforming system acceptance, technical verification and optimization\nExamining network performance and assurance\nAssisting in MNO related projects\nEvaluating products and tools for indoor network design\n\nRequirements:\n\nBachelor Degree in Electronics and Telecommunications or relevant discipline\n1-2 years in related working experience\nKnowledge in RF and mobile communication technology, MS Office, AutoCAD, CorelDraw, Windows and WiFi\nFamiliar with RF testers and measurement tools\nGood command of both spoken and written English, Cantonese and Mandarin\n\nApart from competitive remuneration package and exciting opportunity for career development within the Group, we provide attractive employee benefits such as free company shuttle, free company SIM card and preferential SIM plan offers, comprehensive medical & insurance schemes, as well as full range of other employee well-being provisions.\n\nInterested parties, please apply with full resume, present and expected salary, by clicking \u201cAPPLY NOW\u201d. Please quote the reference number on the e-mail subject.\n\nWe are an equal opportunity employer and welcome applications from all qualified candidates. Personal data collected will be treated in the strictest confidence and handled confidentially by authorised personnel for recruitment-related purposes only within the CK Hutchison Group of companies. The personal data of unsuccessful applicants will be destroyed after the recruitment exercise pursuant to the requirements of the Personal Data (Privacy) Ordinance in Hong Kong.", "employment_types": ["Full Time", "Permanent"], "selling_points": [], "locations": ["Tsing Yi"], "categories": ["Engineering", "Electrical / Electronics", "Telecommunication / Wireless / Radio", "Others"], "post_time": "2022-01-14T11:13:27Z", "salary": {"currency": null, "max": null, "min": null, "period": "monthly", "term": null}, "salary_visible": false, "title_keywords": ["engineer"], "responsibilities": ["project planning", "monitoring", "design", "data analysis", "system design"], "requirements": {"degrees": ["degree", "bachelor"], "majors": [], "languages": ["cantonese", "english", "mandarin"], "language_level": ["good command"], "hard_skills": ["mobile", "autocad", "ms office"], "soft_skills": ["communication", "comprehensive"], "languages_combined": [{"language": "cantonese", "language_level": ["good command"]}, {"language": "english", "language_level": ["good command"]}, {"language": "mandarin", "language_level": ["good command"]}]}, "experience_required": {"duration": ["1-2 years"], "field": ["related"]}}, {"job_id": "100003009050726", "location_code": "hk", "company": "Hutchison Telecommunications (Hong Kong) Limited", "job_title": "Technician - Radio Frequency", "description": "Responsibilities:\n\nPerform field testing in Mobile network with the use of Radio Frequency testing tool\nResponsible for data analyzing for field measurement data\nOther ad-hoc duties as assigned\nRequirements:\u00a0 \u00a0 \u00a0 \u00a0\n\n\nCertificate or above\u00a0in Telecommunications or equivalent\nMay require to OT if needed\nRelevant working experience in mobile field testing is preferred\nMinimum 1 years' experience in telecom industry\n\nApart from competitive remuneration package and exciting opportunity for career development within the Group, we provide attractive employee benefits such as free company shuttle, free company SIM card and preferential SIM plan offers, comprehensive medical & insurance schemes, as well as full range of other employee well-being provisions.\u00a0\n\nInterested parties, please apply with full resume, present and expected salary, by clicking \u201cAPPLY NOW\u201d. Please quote the reference number on the e-mail subject.\n\nWe are an equal opportunity employer and welcome applications from all qualified candidates. Personal data collected will be treated in the strictest confidence and handled confidentially by authorised personnel for recruitment-related purposes only within the CK Hutchison Group of companies. The personal data of unsuccessful applicants will be destroyed after the recruitment exercise pursuant to the requirements of the Personal Data (Privacy) Ordinance in Hong Kong.", "employment_types": ["Full Time", "Permanent"], "selling_points": [], "locations": ["Tsing Yi"], "categories": ["Engineering", "Draftsman", "Electrical / Electronics", "Telecommunication / Wireless / Radio"], "post_time": "2022-01-14T11:14:57Z", "salary": {"currency": null, "max": null, "min": null, "period": "monthly", "term": null}, "salary_visible": false, "title_keywords": ["technician"], "responsibilities": ["measurement", "data", "ad-hoc duties", "testing"], "requirements": {"degrees": ["certificate"], "majors": [], "languages": [], "language_level": [], "hard_skills": ["mobile"], "soft_skills": ["comprehensive"], "languages_combined": []}, "experience_required": {"duration": ["minimum 1 years"], "field": ["relevant working experience", "testing"]}}, {"job_id": "100003009050682", "location_code": "hk", "company": "Hutchison Telecommunications (Hong Kong) Limited", "job_title": "Senior Engineer - Data Network & Packet Core Development", "description": "Responsibilities\u00a0\n\nMobile core technology development\u00a0\nMobile policy and charging technology (PCRF, PCEF, Diameter)\nNetwork enabling technology (AAA, DRA, Traffic Load Balancing)\nVendor management\nProject management\nBusiness user requirement collection\nWork with vendor to finalize the solution details\n\nRequirements\n\nBachelor degree holder in Electronic\u00a0Engineering / Computer Science / Engineering /\u00a0Telecommunication Engineering\u00a0\n5 years of relevant working experience or above, focus on Mobile Policy, Charging Technology and Network Enabling Technology.\nBiz requirement collection, project management ad vendor management.\u00a0\nProficiency in Microsoft Office\nFamiliar with Linux and Windows\nMature, self-motivated and excellent communication skill.\u00a0\nGood command of both written & spoken English and Chinese, including Mandarin.\n\nApart from competitive remuneration package and exciting opportunity for career development within the Group, we provide attractive employee benefits such as free company shuttle, free company SIM card and preferential SIM plan offers, comprehensive medical & insurance schemes, as well as full range of other employee well-being provisions.\n\nInterested parties, please apply with full resume, present and expected salary, by clicking \u201cAPPLY NOW\u201d. Please quote the reference number on the e-mail subject.\n\nWe are an equal opportunity employer and welcome applications from all qualified candidates. Personal data collected will be treated in the strictest confidence and handled confidentially by authorised personnel for recruitment-related purposes only within the CK Hutchison Group of companies. The personal data of unsuccessful applicants will be destroyed after the recruitment exercise pursuant to the requirements of the Personal Data (Privacy) Ordinance in Hong Kong.", "employment_types": ["Full Time", "Permanent"], "selling_points": [], "locations": ["Tsing Yi"], "categories": ["Engineering", "Electrical / Electronics", "Telecommunication / Wireless / Radio", "Information Technology (IT)", "Mobile / Wireless Communications"], "post_time": "2022-01-14T11:10:24Z", "salary": {"currency": null, "max": null, "min": null, "period": "monthly", "term": null}, "salary_visible": false, "title_keywords": ["senior engineer"], "responsibilities": ["project management", "management"], "requirements": {"degrees": ["bachelor degree holder"], "majors": ["engineering", "computer science"], "languages": ["english", "chinese", "mandarin"], "language_level": ["good command"], "hard_skills": ["linux", "microsoft office", "vendor", "mobile", "project management", "focus"], "soft_skills": ["self-motivated", "communication skill", "mature", "project management", "comprehensive", "focus"], "languages_combined": [{"language": "english", "language_level": ["good command"]}, {"language": "chinese", "language_level": ["good command"]}, {"language": "mandarin", "language_level": ["good command"]}]}, "experience_required": {"duration": ["5 years"], "field": ["relevant working experience"]}}, {"job_id": "100003009050717", "location_code": "hk", "company": "Hutchison Telecommunications (Hong Kong) Limited", "job_title": "Engineer (Radio Planning)", "description": "Responsibilities:\n\nPerform site visit and prepare technical proposal according to the coverage planning and landlord's requirements\nAssis manager to review and optimize the site plan continuously\nPerform site survey and identify candidate for cell site deployment\nPrepare project details and corresponding documents to assist for site acquisition and\u00a0implementation\nDetermine optimal site configuration for maximizing\u00a0the cell site value\nPerform field test for collecting meaningful data to assist for planning\n\nRequirements:\n\n\n\nDegree in Electronics Engineering or Telecommunication Engineering\nMinimum 1 year working experience in Telecommunication industry\nProficient\u00a0to MS Office, CorelDRAW, Autocad, MapInfo\nGood command of written and spoken English and Chinese\nHolder of valid HK driving license with class 1 & 2 is an advantage\n\nApart from competitive remuneration package and exciting opportunity for career development within the Group, we provide attractive employee benefits such as free company shuttle, free company SIM card and preferential SIM plan offers, comprehensive medical & insurance schemes, as well as full range of other employee well-being provisions.\n\nInterested parties, please apply with full resume, present and expected salary, by clicking \u201cAPPLY NOW\u201d. Please quote the reference number on the e-mail subject.\n\nWe are an equal opportunity employer and welcome applications from all qualified candidates. Personal data collected will be treated in the strictest confidence and handled confidentially by authorised personnel for recruitment-related purposes only within the CK Hutchison Group of companies. The personal data of unsuccessful applicants will be destroyed after the recruitment exercise pursuant to the requirements of the Personal Data (Privacy) Ordinance in Hong Kong.", "employment_types": ["Full Time", "Permanent"], "selling_points": [], "locations": ["Tsing Yi"], "categories": ["Engineering", "Electrical / Electronics", "Engineering Project Management", "Telecommunication / Wireless / Radio"], "post_time": "2022-01-14T11:13:31Z", "salary": {"currency": null, "max": null, "min": null, "period": "monthly", "term": null}, "salary_visible": false, "title_keywords": ["engineer"], "responsibilities": ["data", "configuration", "review", "implementation", "plan", "planning"], "requirements": {"degrees": ["degree"], "majors": ["engineering"], "languages": ["english", "chinese"], "language_level": ["good command"], "hard_skills": ["autocad", "ms office"], "soft_skills": ["comprehensive"], "languages_combined": [{"language": "english", "language_level": ["good command"]}, {"language": "chinese", "language_level": ["good command"]}]}, "experience_required": {"duration": ["minimum 1 year"], "field": []}}, {"job_id": "100003009049000", "location_code": "hk", "company": "Bank of China (Hong Kong) Limited", "job_title": "Senior Network Administration Managers", "description": "\nJob Responsibilities:\nProvide day-to-day telecommunication needs & support to backoffice, Call Center, subsidiary, branches, oversea branches users, etc.\n\nSupport & maintain telecom change management\n\nAlias with vendors to support & provide solution to Call Center, Trading Floor, branches, subsidiaries\u2019 telecom requests\n\nSupport & maintain systems including Avaya PABX, trading floor Dealer Board / Turret system, voice recording systems, Audiocodes, IVRS, CTI, etc.\n\nAssist management to execute a series of development projects from planning to implementation, provide and recommend appropriate technical solutions and alternatives for project issues identified\n\nResponsible for the procurement of voice systems, maintenance service and projects\n\nResponsible for the budget management of voice systems, maintenance service and projects\n\nTake responsibilities to complete all jobs assigned from management\n\nJob requirements:\n5+ years of experience in Telecom services, with minimum 2 years in finance industry\n\nExpertise in Call Center operational systems, Such as, Avaya ACD & PABX, Nice , Redbox & Verint voice recording system, CTI, CRM, IVR, trading floor Dealer Board / Turret is a \u2018plus\u2019\n\nGood communication skills and be able to interact in a professional manner with End Users\n\nPossess excellent PC, communication, and organizational skills.\n\nExperience with price comparisons and procurement of RFI and RFP\n\nAbility to work under pressure\n\nFluency in English ,Cantonese and Mandarin\n\nWe offer competitive remuneration package and coprehensive fringe benefits including medical and life insurance, and different types of allowances to the right candidate. Interested parties, please submit your application online. For details, please visit our website http://www.bochk.com\n\nData collected would be used for recruitment purposes only. It might also be disclosed to our subsidiaries or Associated Companies to process the information for appointment. Applicants who do not hear from us within 8 weeks may consider their application unsuccessful and their data will be destroyed within 12 months of receipt.", "employment_types": ["Full Time"], "selling_points": ["Provide day-to-day telecommunication needs", "Support & maintain telecom change management", "5+ years of experience in Telecom services"], "locations": ["Not Specified"], "categories": ["Engineering", "Telecommunication / Wireless / Radio", "Information Technology (IT)", "Support"], "post_time": "2022-01-14T07:53:05Z", "salary": {"currency": null, "max": null, "min": null, "period": "monthly", "term": null}, "salary_visible": false, "title_keywords": [], "responsibilities": ["management", "change management", "maintenance", "systems", "budget", "implementation", "maintain", "planning"], "requirements": {"degrees": [], "majors": [], "languages": ["cantonese", "english", "mandarin"], "language_level": ["fluency"], "hard_skills": ["pc", "nice", "plus"], "soft_skills": ["communication", "communication skills", "organizational skills", "work under pressure"], "languages_combined": [{"language": "cantonese", "language_level": ["fluency"]}, {"language": "english", "language_level": ["fluency"]}, {"language": "mandarin", "language_level": ["fluency"]}]}, "experience_required": {"duration": ["5+ years", "minimum 2 years"], "field": ["procurement", "finance industry"]}}, {"job_id": "100003009049371", "location_code": "hk", "company": "HGC Global Communications Limited", "job_title": "Technical Officer - Field Support Service", "description": "Responsibilities:\n\nInstall, maintain, verify, repair network equipment and various cable patching in access network;\nHandle emergency call out operation if required;\nParticipate in ad-hoc projects in access network;\nShift duty is required.\u00a0 \u00a0\u00a0\n\n\u00a0Requirements:\n\nSecondary / Matriculation / Diploma major in Electronics, IT, Telecommunications or other related disciplines\n5 years of above working experience on field services in networking or telecommunications;\nHolder of CCNA is preferable;\nHolder of driving licence is preferable;\u00a0\nSelf-motivated and able to work independently and under pressure;\nGood command of written and spoken English and average in Mandarin;\nShift duty is required;\nLess experienced candidate / fresh graduate is welcome and considered as \"Technical Officer\".\n\nWe offer competitive salary package and career development opportunity. Free company coach is provided.\u00a0 Interested parties, please quote our reference number and apply with full resume, present and expected salary, by clicking \u201cAPPLY NOW\u201d.\u00a0\n\nWe are an equal opportunity employer and welcome applications from all qualified candidates. Information provided will be treated in strict confidence and only be used for consideration of your application for the relevant post within HGC Global Communications Limited. Personal data provided by job applicants will be used strictly according to our Personal Information Collection Statement, a copy of which will be available upon written request. Information of unsuccessful candidates will be destroyed within six months.", "employment_types": ["Full Time", "Permanent"], "selling_points": ["Shift duty is required", "5 years experience on field services", "Install and repair network equipment"], "locations": ["Tsing Yi"], "categories": ["Engineering", "Electrical / Electronics", "Telecommunication / Wireless / Radio", "Others", "Technician"], "post_time": "2022-01-14T08:31:45Z", "salary": {"currency": null, "max": null, "min": null, "period": "monthly", "term": null}, "salary_visible": false, "title_keywords": ["technical officer"], "responsibilities": ["ad-hoc projects", "repair", "maintain"], "requirements": {"degrees": ["diploma", "fresh graduate"], "majors": ["related disciplines", "it"], "languages": ["english", "mandarin"], "language_level": ["average", "good command"], "hard_skills": ["ccna"], "soft_skills": ["self-motivated", "under pressure", "work independently"], "languages_combined": [{"language": "english", "language_level": ["average", "good command"]}, {"language": "mandarin", "language_level": ["good command"]}]}, "experience_required": {"duration": ["5 years"], "field": ["telecommunications"]}}, {"job_id": "100003009049050", "location_code": "hk", "company": "Karin Solutions and Services Limited", "job_title": "Unified Communication Engineer/Assistant Unified Communication Engineer", "description": "Understand customer requirement\nTranslate business needs into technical requirements\nPrepare technical proposal and product BOM\nConduct presentation and Proof-of-Concept of proposed solutions\nProvide solution consultations to our customer\nBe a Voice of Customer to share insights and best practices\n\n\u00a0Drive successful project delivery activities, include:\n\nInitiate kickoff meetings\nBuild solution implementation roadmaps\nCollaborate with project delivery team\nEnsure successful execution of project plans\nTechnology area focus (one of the following), include:\nIP telephony solution (e.g. Cisco, Avaya\u2026..etc.)\nCustomer meeting service and solution (e.g. Zoom, Microsoft Teams, Webex Meeting, etc.)\n\nRequirements:\n\nUniversity graduate in Computer Science, Information Engineering, Electronics Engineering or related disciplines, with at least 2-year work experiences\nDemonstrate a good learning track record and experience in solution design or implementation in complex projects\nSelf-motivated and interested to explore new technologies and solutions\nOther latest technical knowledge in unified communication solution\nGood command of both written and spoken English and Chinese\nLess experienced candidate will be considered as Assistant Unified Communication Engineer\n\nWe offer a competitive remuneration package to the right candidate. Interested parties please send your full resume with\u00a0present and expected salary\u00a0by clicking 'Apply Now'.\n\nCompany Address: 9/F, The Whitney, 183 Wai Yip Street, Kwun Tong, Hong Kong\n\n(We are an Equal Opportunity Employer and personal data collected would be used for recruitment purpose only.)", "employment_types": ["Full Time", "Permanent"], "selling_points": ["Conduct presentation and Proof-of-Concept", "Prepare technical proposal and product BOM", "IP telephony solution (e.g. Cisco, Avaya)"], "locations": ["Kwun Tong"], "categories": ["Engineering", "Telecommunication / Wireless / Radio", "Information Technology (IT)", "Network & System", "Technical / Functional Consulting"], "post_time": "2022-01-14T08:06:38Z", "salary": {"currency": null, "max": null, "min": null, "period": "monthly", "term": null}, "salary_visible": false, "title_keywords": ["engineer", "assistant"], "responsibilities": ["collaborate with", "teams", "implementation", "design", "communication", "plans"], "requirements": {"degrees": ["university graduate"], "majors": ["related disciplines", "engineering", "computer science"], "languages": ["english", "chinese"], "language_level": ["good command"], "hard_skills": ["unified communication", "ip", "focus"], "soft_skills": ["self-motivated", "communication", "learning", "focus", "presentation"], "languages_combined": [{"language": "english", "language_level": ["good command"]}, {"language": "chinese", "language_level": ["good command"]}]}, "experience_required": {"duration": ["at least 2-year"], "field": ["related", "engineering", "design"]}}, {"job_id": "100003005585293", "location_code": "hk", "company": "Infracable Limited", "job_title": "Civil Implementation Assistant/Officer", "description": "Job Description:\n\nTo Monitor civil contractors to carry out site work according to set target drawing and company standard\n\nResponsible for site inspection, provide technical advice to contractors, handle and solve site problems and public complaints, it any\n\nAttend meetings with concerned parties about civil work issues\n\nResponsible for certification of as-built civil works and conduct site measurements\n\nRequirement:\n\nDiploma holder of Civil/Electrical/Electronic/Communications or related disciplines\n\nMature and independent with good communication skills\n\nGood command in verbal and written English and Chinese\n\nPossess 2 years experience in telecom civil works/construction field is an advantage\n\nFresh graduate will also be considered\n\n\u00a0Benefits: Medical & Dental Insurance, Five-day work week\n\nWe offer attractive remuneration package to the right candidate. To apply, please send a full resume with contact telephone number, date of availability, expected salary by clicking \"Apply Now\". (All information collected will be kept strictly confidential and be used for recruitment purpose only.)", "employment_types": ["Full Time", "Permanent"], "selling_points": [], "locations": ["Kwun Tong"], "categories": ["Engineering", "Electrical / Electronics", "Engineering Project Management", "Telecommunication / Wireless / Radio"], "post_time": "2022-01-14T06:25:50Z", "salary": {"currency": "HKD", "max": 19999, "min": 11000, "period": "monthly", "term": null}, "salary_visible": true, "title_keywords": ["officer", "assistant"], "responsibilities": ["attend meetings", "technical advice", "monitor", "site inspection"], "requirements": {"degrees": ["diploma holder", "fresh graduate"], "majors": ["related disciplines", "communications"], "languages": ["english", "chinese"], "language_level": ["good command"], "hard_skills": [], "soft_skills": ["communication skills", "independent", "mature"], "languages_combined": [{"language": "english", "language_level": ["good command"]}, {"language": "chinese", "language_level": ["good command"]}]}, "experience_required": {"duration": ["2 years"], "field": ["construction"]}}, {"job_id": "100003009049375", "location_code": "hk", "company": "HGC Global Communications Limited", "job_title": "Senior Technical Officer / Technical Officer (Blockwiring)", "description": "Job Responsibilities:\n\nTo prepare purchase order;\nTo prepare proposals to contractors for installation works;\nCoordinate internal & external stakeholders (i.e. builders, management office, contractors) for works commencement;\nSite / Progress monitoring;\nSite inspection after works completion and measurement report verification;\nData update in system and project handover.\n\nJob Requirements:\n\nDiploma holder in IT or related discipline;\n1-2 years relevant working experience;\nHands on experience in MS Office Applications ;\nGood analytical, PC / device trouble shooting, and problem solving skills;\nGood interpersonal skill and a good team player;\nMature, dynamic, work independent and self-motivated;\nGood spoken and written English and Cantonese, Mandarin a plus.\n\nWe offer competitive salary package and career development opportunity. Free company coach is provided.\u00a0 Interested parties, please quote our reference number and apply with full resume, present and expected salary, by clicking \u201cAPPLY NOW\u201d.\u00a0\n\nWe are an equal opportunity employer and welcome applications from all qualified candidates. Information provided will be treated in strict confidence and only be used for consideration of your application for the relevant post within HGC Global Communications Limited. Personal data provided by job applicants will be used strictly according to our Personal Information Collection Statement, a copy of which will be available upon written request. Information of unsuccessful candidates will be destroyed within six months.", "employment_types": ["Full Time", "Permanent"], "selling_points": ["Coordinate internal & external stakeholders", "Diploma holder in IT / related discipline", "1-2 years relevant working experience"], "locations": ["Tsing Yi"], "categories": ["Engineering", "Mechanical", "Telecommunication / Wireless / Radio", "Information Technology (IT)", "Mobile / Wireless Communications"], "post_time": "2022-01-14T08:31:47Z", "salary": {"currency": null, "max": null, "min": null, "period": "monthly", "term": null}, "salary_visible": false, "title_keywords": ["technical officer", "senior technical officer"], "responsibilities": ["installation", "management", "data", "monitoring", "measurement", "site inspection", "coordinate", "project handover", "purchase", "report"], "requirements": {"degrees": ["diploma holder"], "majors": ["it"], "languages": ["cantonese", "english", "mandarin"], "language_level": ["good"], "hard_skills": ["plus", "dynamic", "pc", "problem solving skills", "ms office"], "soft_skills": ["good team player", "self-motivated", "independent", "mature", "interpersonal skill", "hands on", "dynamic", "problem solving skills"], "languages_combined": [{"language": "cantonese", "language_level": ["good"]}, {"language": "english", "language_level": ["good"]}, {"language": "mandarin", "language_level": ["good"]}]}, "experience_required": {"duration": ["1-2 years"], "field": ["relevant working experience"]}}, {"job_id": "100003009041950", "location_code": "hk", "company": "HKBN Enterprise Solutions HK Limited", "job_title": "Network Engineer", "description": "What effort do you need to make?\u202f\n\nParticipate in testing, researching, learning and applying specific new technologies and products\nProvide second-tier technical support and solutions to the implementation and fault handling in networking projects\nDevelop documentation manual and provide briefing session of project completion to customer\nShift duty and outdoor work are required with allowance provided\n\n\u00a0Let\u2019s check if you are\u2026\n\nHigher diploma or above in telecommunications, information technology, computer science or related discipline\nMinimum 3 years of network engineering experience in telecommunication / IT industry\nHands-on experience with Cisco / Juniper / Fortinet 's Router / Switch / Firewall(SRX/ASA/FortiGate) support and administration\nHolder of Cisco's CCNP/CCNA, Juniper's JNCIP/JNCIS, Fortinet NSE Certification is an advantage\nHands-on experience in Cisco Call Manager or other IP phone conferencing network will be a plus\nWork independently, self-initiative, good interpersonal skills & work under pressure\nCandidates with less experience will be considered as \"Assistant Engineer\"\n\n\n\nWhat you get in return\u2026\n\nApart from competitive salary package and benefits, in HKBN, you will work flexibly under our\u00a0Talent-first culture\u00a0and we uphold\u00a0Life-Work Priority. Examples of our flexible initiatives:\n\nFive-day work week\nHalf Day Off Friday once a month\u00a0\nHalf Day Off on Festival Eve\nUnique leaves arrangement: Family-care leave, Anniversary leave, Bonus leave, Volunteer leave, Sabbatical leave, etc.\nComprehensive medical and life insurance coverage\nUpgraded maternity leave and paternity leave\nDiscounted Talent plan offers including broadband and mobile plans and other promoted products\nEducation subsidies and Examination leave\nYear-end discretionary bonus\n\nJoin Us Today!\n\nAll information provided by applicants will be treated in strict confidence and used for consideration in relation to the relevant post within the company.\n\nAll personal data of unsuccessful applicants will be destroyed within\u00a0one year. Applicants who are not invited for an interview within 3 weeks may consider their application unsuccessful.", "employment_types": ["Full Time", "Permanent"], "selling_points": ["Talent-first Culture & LIFE-work priority", "Testing & researching new technologies and product", "Provide second-tier technical network support"], "locations": ["Kowloon Bay"], "categories": ["Engineering", "Engineering Project Management", "Telecommunication / Wireless / Radio", "Information Technology (IT)", "Network & System"], "post_time": "2022-01-12T04:47:40Z", "salary": {"currency": null, "max": null, "min": null, "period": "monthly", "term": null}, "salary_visible": false, "title_keywords": ["engineer"], "responsibilities": ["outdoor work", "technical support", "work under pressure", "implementation", "develop", "testing", "documentation", "administration"], "requirements": {"degrees": ["higher diploma or above"], "majors": ["computer science", "information technology"], "languages": [], "language_level": [], "hard_skills": ["plus", "switch", "ccnp", "ccna", "router", "make", "ip", "documentation"], "soft_skills": ["work independently", "hands-on", "learning", "self-initiative", "interpersonal skills", "work under pressure"], "languages_combined": []}, "experience_required": {"duration": ["minimum 3 years"], "field": ["it", "engineering", "administration"]}}, {"job_id": "100003009001224", "location_code": "hk", "company": "Lik On Security Limited", "job_title": "\u521d\u7d1a\u6280\u8853\u54e1 - \u7dad\u4fee\uff08\u5f31\u96fb / \u8b66\u9418\uff09", "description": "\u8077\u8cac\u7bc4\u7587\uff1a\n\n\u8ca0\u8cac\u6aa2\u67e5\u53ca\u7dad\u8b77\u5404\u985e\u5f31\u96fb\u7cfb\u7d71\u5305\u62ec\uff1aCCTV\u3001\u9580\u7981\u3001\u8b66\u9418\u3001\u516c\u773e\u5929\u7dda\u3001\u7db2\u7d61\u7cfb\u7d71\u7b49\u00a0\n\n\u5165\u8077\u8981\u6c42\uff1a\n\n\u7121\u9700\u7d93\u9a57\n\n\u5177\u76f8\u95dc\u96fb\u5b50\u53ca\u5c4b\u5b87\u88dd\u5099\u6587\u6191\u5b78\u6b77\u512a\u5148\n\n\u5728\u8077\u57f9\u8a13\n\n\u5ee3\u6771\u8a71\u4ea4\u8ac7\n\n\u6e9d\u901a\u80fd\u529b\u5f37\n\n\u61c9\u5fb5\u8005\u8acb\u5c07\u5c65\u6b77\u8868\u53ca\u8981\u6c42\u85aa\u91d1\u96fb\u90f5(\u8acb\u6309\"APPLY NOW\") \u6216 \u90f5\u5bc4\u81f3:\u00a0\u529b\u5b89\u8b77\u885b\u6709\u9650\u516c\u53f8\u4e5d\u9f8d\u9577\u6c99\u7063\u9577\u7fa9\u885710\u865f\u660c\u9686\u5de5\u696d\u5927\u5ec88\u6a13\u884c\u653f\u90e8\u6536\u00a0\u6216\u81f4\u96fb\u00a02485-2485 \u884c\u653f\u90e8\u9810\u7d04\u9762\u8a66\u6642\u9593\u3002\n\n\u672c\u516c\u53f8\u662f\u5e73\u7b49\u6a5f\u6703\u50f1\u4e3b\uff0c\u6240\u6709\u6536\u96c6\u8cc7\u6599\u53ea\u6703\u7528\u4f5c\u62db\u8058\u7528\u9014\u3002", "employment_types": ["Full Time", "Permanent"], "selling_points": ["\u6709\u76f8\u95dc\u96fb\u5b50\u53ca\u5c4b\u5b87\u88dd\u5099\u6587\u6191\u5b78\u6b77\u512a\u5148", "\u7121\u9700\u76f8\u95dc\u5de5\u4f5c\u7d93\u9a57\u8005", "\u6e9d\u901a\u80fd\u529b\u5f37"], "locations": ["Cheung Sha Wan"], "categories": ["Engineering", "Electrical / Electronics", "Telecommunication / Wireless / Radio", "Others", "Security / Safety Control"], "post_time": "2022-01-16T21:50:06Z", "salary": {"currency": null, "max": null, "min": null, "period": "monthly", "term": null}, "salary_visible": false, "title_keywords": [], "responsibilities": [], "requirements": {"degrees": [], "majors": [], "languages": [], "language_level": [], "hard_skills": [], "soft_skills": [], "languages_combined": []}, "experience_required": {"duration": [], "field": []}}, {"job_id": "100003009055332", "location_code": "hk", "company": "Computime Ltd", "job_title": "Senior Engineer \u2013 Electronics", "description": "Major Responsibilities\n\nDesign and develop electronic and wireless products\nPrepare schematic drawing, review PCB layout, prepare test plan and specifications\nBuild prototype and hardware performance evaluation\nWork with software team for driver, firmware and apps development\nPerform engineering verification test and design verification test\nSupport production for sample build, pilot run and mass production\nWork with test lab to resolve EMC/EMI issues to meet international standards\nSupport sales and business team for RFI and RFQ\nWork at multi-sites with multi-cultural teams\n\nRequirements\n\nBachelor Degree in Electrical & Electronics Engineering\nMinimum 5 years of solid experience in electronic hardware system design and development\nKnowledge in 3-phase motor control\nExperience in Heat Pump and/or AC control an advantage\nSolid experience in circuit design and PCB layout\nHands-on experience in SoC design of electronics products\nFamiliar in using oscilloscope, multi meter, E-load, data logger, etc. to do design verification\nFamiliar with any of the following sub-systems a plus:\n- Radar, LTE, WiFi, BLE, Zigbee, NFC\n- AC/DC conversion, DC/DC conversion, battery charging, wireless charging\n- AC motor, DC motor, Brushless motor\n- Power electronics design\nKnowledgeable with EMC / CE / VDE / FCC/ UL Standards and familiar with approval process\nProblem solving skills, quick learner and a good team player\nGood command of spoken English and Chinese, including Putonghua\nLess experience considered as Engineer\n\nInterested parties, please apply together with a detailed resume, stating current and expected salary, and send it via APPLY NOW.\u00a0 Attractive remuneration will be offered in commensurate with qualification and experience.\u00a0\n\nAll personal information received will be treated in strict confidence for employment purpose only.\u00a0 Your application can be considered as unsuccessful if you have not been reached within 3 months.\u00a0 On the other hand, it may be transferred to other companies of our group for job openings.\u00a0 Unsuccessful applications will be destroyed for a period not more than 12 months.\u00a0\n\nhttps://www.computime.com/\nhttps://salus-controls.com/", "employment_types": ["Full Time", "Permanent"], "selling_points": ["5 days work, double pay, and free shuttle coach", "Prepare schematic drawing, review PCB layout", "SoC design of electronics products"], "locations": ["Shatin Area"], "categories": ["Engineering", "Electrical / Electronics", "Telecommunication / Wireless / Radio", "Information Technology (IT)", "Mobile / Wireless Communications"], "post_time": "2022-01-18T02:12:49Z", "salary": {"currency": null, "max": null, "min": null, "period": "monthly", "term": null}, "salary_visible": false, "title_keywords": ["senior engineer"], "responsibilities": ["software", "review", "design and develop", "teams", "design", "hardware", "specifications", "plan", "evaluation"], "requirements": {"degrees": ["degree", "bachelor"], "majors": ["engineering"], "languages": ["putonghua", "english", "chinese"], "language_level": ["good command"], "hard_skills": ["plus", "hardware", "system design", "dc", "problem solving skills"], "soft_skills": ["quick learner", "good team player", "hands-on", "problem solving skills"], "languages_combined": [{"language": "putonghua", "language_level": ["good command"]}, {"language": "english", "language_level": ["good command"]}, {"language": "chinese", "language_level": ["good command"]}]}, "experience_required": {"duration": ["minimum 5 years"], "field": ["development", "system design", "design"]}}, {"job_id": "100003009049031", "location_code": "hk", "company": "HKT Enterprise Solutions", "job_title": "Sales Operations Supervisor", "description": "Your new role:\n\nUnderstand the customer demand and establish the intelligent billing mechanism to cater enterprise market\nLead the team to prepare the usage analysis report and tailor made the report format for customer review\nPerform regular system audit to ensure the accuracy of billing & provisioning in order to eliminate the customer complaint\nWork with business partners and IT to develop and well test the billing system function in supporting new product/services implementation\nInitiate improvement to billing systems and procedures for efficient operations\nLead and develop staff to ensure procedures are complied with Company standards\n\nTo succeed in this role:\n\nHigher Diploma or above in Business or related disciplines with minumum 5 years of experience preferably in telecommunications industry\nSolid exposures in systems implementation / conversion with leading a team\nStrong leadership and problem solving capabilities\nSelf-motivated, analytical and ability to work under pressure with\u00a0tight deadlines\nGood communications skill both in written and spoken (English and Chinese)\n\nIf you are excited about the new challenging role, please call us at 2883 8518 for more information.\n\nLearn more about HKT Commercial Group business portfolios:\u00a0\n\nHKT Enterprise Solutions:\u00a0\u00a0https://www.hkt-enterprise.com/\n\n1O1O Corporate Solutions:\u00a0\u00a0https://www.1010corporate.com/\n\nHKT is an equal opportunity employer and welcomes applications from all qualified candidates. Information provided will be treated in strict confidence and will only be used for recruitment-related purposes. Personal data provided by job applicants will be used strictly in accordance with the employer's privacy statement (http://www.hkt.com/privacy-statement), a copy of which will be provided immediately upon request.", "employment_types": ["Full Time"], "selling_points": [], "locations": ["Quarry Bay"], "categories": ["Engineering", "Telecommunication / Wireless / Radio", "Sales, CS & Business Devpt", "Others"], "post_time": "2022-01-14T07:57:17Z", "salary": {"currency": null, "max": null, "min": null, "period": "monthly", "term": null}, "salary_visible": false, "title_keywords": ["operations", "supervisor", "sales"], "responsibilities": ["analysis report", "operations", "work under pressure", "review", "systems", "audit", "implementation", "develop", "procedures", "recruitment", "personal data", "report"], "requirements": {"degrees": ["higher diploma or above"], "majors": ["related disciplines", "business"], "languages": ["english", "chinese"], "language_level": ["good"], "hard_skills": ["problem solving capabilities", "analysis", "billing system"], "soft_skills": ["efficient", "self-motivated", "confidence", "problem solving", "leadership", "work under pressure"], "languages_combined": [{"language": "english", "language_level": ["good"]}, {"language": "chinese", "language_level": ["good"]}]}, "experience_required": {"duration": ["5 years"], "field": ["related", "business", "telecommunications"]}}, {"job_id": "100003009001213", "location_code": "hk", "company": "Lik On Security Limited", "job_title": "\u6280\u8853\u54e1 / \u9ad8\u7d1a\u6280\u8853\u54e1 - \u7dad\u4fee (\u5f31\u96fb / \u8b66\u9418)", "description": "\u00a0\u8077\u8cac\u7bc4\u7587\uff1a\n\n\u8ca0\u8cac\u5b89\u88dd\u4e0d\u540c\u7684\u4fdd\u5b89\u7cfb\u7d71\uff0c\u5982\uff1a\u8b66\u9418\u7cfb\u7d71\u3001\u9589\u8def\u96fb\u8996\u3001\u516c\u5171\u5929\u7dda\u53ca\u5176\u4ed6\u96fb\u5b50\u7522\u54c1\u00a0\n\n\u5165\u8077\u8981\u6c42\uff1a\n\n2-5\u5e74\u76f8\u95dc\u5de5\u4f5c\u7d93\u9a57\n\u57fa\u672c\u4e2d\u3001\u82f1\u6587\u8b80\u5beb\n\u7a4d\u6975\u76e1\u8cac\u53ca\u80fd\u7368\u7acb\u8655\u7406\u65e5\u5e38\u5de5\u4f5c\n\u5728\u8077\u57f9\u8a13\n\n\u61c9\u5fb5\u8005\u8acb\u5c07\u5c65\u6b77\u8868\u53ca\u8981\u6c42\u85aa\u91d1\u96fb\u90f5(\u8acb\u6309\"APPLY NOW\") \u6216 \u90f5\u5bc4\u81f3:\u00a0\u529b\u5b89\u8b77\u885b\u6709\u9650\u516c\u53f8\u4e5d\u9f8d\u9577\u6c99\u7063\u9577\u7fa9\u885710\u865f\u660c\u9686\u5de5\u696d\u5927\u5ec88\u6a13\u884c\u653f\u90e8\u6536\u00a0\u6216\u81f4\u96fb\u00a02485-2485 \u884c\u653f\u90e8\u9810\u7d04\u9762\u8a66\u6642\u9593\u3002\n\n\u672c\u516c\u53f8\u662f\u5e73\u7b49\u6a5f\u6703\u50f1\u4e3b\uff0c\u6240\u6709\u6536\u96c6\u8cc7\u6599\u53ea\u6703\u7528\u4f5c\u62db\u8058\u7528\u9014\u3002", "employment_types": ["Full Time", "Permanent"], "selling_points": ["\u8ca0\u8cac\u5b89\u88dd\u4e0d\u540c\u7684\u4fdd\u5b89\u7cfb\u7d71", "2-5\u5e74\u76f8\u95dc\u5de5\u4f5c\u7d93\u9a57\u8005", "\u7565\u61c2\u4fdd\u5b89\u7cfb\u7d71\u76f8\u95dc\u4e4b\u96fb\u8166\u8edf\u4ef6\u64cd\u4f5c\u66f4\u4f73"], "locations": ["Cheung Sha Wan"], "categories": ["Engineering", "Electrical / Electronics", "Telecommunication / Wireless / Radio", "Others", "Security / Safety Control"], "post_time": "2022-01-16T21:50:06Z", "salary": {"currency": null, "max": null, "min": null, "period": "monthly", "term": null}, "salary_visible": false, "title_keywords": ["\u6280\u8853\u54e1"], "responsibilities": [], "requirements": {"degrees": [], "majors": [], "languages": [], "language_level": [], "hard_skills": [], "soft_skills": [], "languages_combined": []}, "experience_required": {"duration": [], "field": []}}, {"job_id": "100003009050705", "location_code": "hk", "company": "Hutchison Telecommunications (Hong Kong) Limited", "job_title": "Technician (In-Building Planning & Design)", "description": "Responsibilities:\n\nConducting site survey, field measurement and performance test\nPerforming data logger processing and record house-keeping\nAssisting in system design and document preparation\nSupporting in the MNO related projects\nPreserving the measurement tools\n\nRequirements:\n\nCertificate or above in Electronics and Telecommunications or relevant discipline\nHolder of valid Hong Kong Driving license\nKnowledge in mobile communication technology, MS Office and Windows\nAverage command of written English, Cantonese and Mandarin\nGood Command of spoken English, Cantonese and Mandarin\n\nApart from competitive remuneration package and exciting opportunity for career development within the Group, we provide attractive employee benefits such as free company shuttle, free company SIM card and preferential SIM plan offers, comprehensive medical & insurance schemes, as well as full range of other employee well-being provisions.\n\nInterested parties, please apply with full resume, present and expected salary, by clicking \u201cAPPLY NOW\u201d. Please quote the reference number on the e-mail subject.\n\nWe are an equal opportunity employer and welcome applications from all qualified candidates. Personal data collected will be treated in the strictest confidence and handled confidentially by authorised personnel for recruitment-related purposes only within the CK Hutchison Group of companies. The personal data of unsuccessful applicants will be destroyed after the recruitment exercise pursuant to the requirements of the Personal Data (Privacy) Ordinance in Hong Kong.", "employment_types": ["Full Time", "Permanent"], "selling_points": [], "locations": ["Not Specified"], "categories": ["Engineering", "Electrical / Electronics", "Telecommunication / Wireless / Radio", "Others"], "post_time": "2022-01-14T11:13:27Z", "salary": {"currency": null, "max": null, "min": null, "period": "monthly", "term": null}, "salary_visible": false, "title_keywords": ["technician"], "responsibilities": ["system design", "measurement", "data"], "requirements": {"degrees": ["certificate"], "majors": [], "languages": ["cantonese", "english", "mandarin"], "language_level": ["good command", "average"], "hard_skills": ["mobile", "ms office"], "soft_skills": ["communication", "comprehensive"], "languages_combined": [{"language": "cantonese", "language_level": ["good command", "average"]}, {"language": "english", "language_level": ["good command", "average"]}, {"language": "mandarin", "language_level": ["good command", "average"]}]}, "experience_required": {"duration": [], "field": []}}, {"job_id": "100003009048998", "location_code": "hk", "company": "Liu Chong Hing Property Management & Agency Ltd", "job_title": "\u6280\u5de5", "description": "\u8077\u8cac :\n\n\u8ca0\u8cac\u76e3\u5bdf\u5404\u9805\u6a5f\u96fb\u7cfb\u7d71\u904b\u4f5c\u53ca\u4fdd\u990a\u7dad\u4fee; \u5b9a\u671f\u6aa2\u67e5\u5404\u9805\u6a5f\u96fb\u7cfb\u7d71\u548c\u8a2d\u65bd; \u9032\u884c\u9810\u9632\u6027\u53ca\u7dca\u6025\u6545\u969c\u7dad\u4fee; \u5354\u52a9\u76e3\u7763\u5916\u5224\u627f\u8fa6\u5546\u5de5\u7a0b\u9032\u5ea6\u3001\u8cea\u7d20\u53ca\u5b89\u5168; \u532f\u5831\u5de5\u7a0b\u53ca\u7dad\u4fee\u9032\u5ea6; \u57f7\u884c\u4e0a\u7d1a\u6307\u6d3e\u7684\u8077\u52d9; \u9700\u7368\u7acb\u8655\u7406\u7dad\u4fee\u5de5\u4f5c; \u9700\u7a7f\u8457\u5236\u670d\n\u8cc7\u6b77 :\n\n\u4e2d\u4e09\u7a0b\u5ea6; 3\u5e74\u7d93\u9a57; \u826f\u597d\u7cb5\u8a9e; \u61c2\u8b80\u5beb\u4e2d\u6587; \u6301\u6709\u5e73\u5b89\u54ad; \u61c2\u96fb\u5b50\u7dad\u4fee; \u6301\u6709\u96fb\u5de5A\u724c; \u61c2\u96fb\u5668\u7dad\u4fee; \u5177\u6709\u57fa\u672c\u96fb\u8166\u64cd\u4f5c\u77e5\u8b58\n\u5f85\u9047 :\n\n\u6bcf\u6708$20,000 - $23,000, \u6709\u8d85\u6642\u5de5\u4f5c\u6d25\u8cbc, \u91ab\u7642\u4fdd\u96aa, \u6649\u5347\u6a5f\u6703 \u53ca\u4eba\u58fd\u4fdd\u969c, \u4e0a\u53489\u6642\u81f3\u4e0b\u53486\u6642, \u6bcf\u9031\u5de5\u4f5c6\u5929,\u8f2a\u4f11, \u6bcf\u5929\u5de5\u4f5c 9 \u5c0f\u6642\n\u7533\u8acb\u9808\u77e5 :\u6c42\u8077\u8005\u53ef\u81f4\u96fb25592324\u8207\u5ed6\u5275\u8208\u7269\u696d\u7ba1\u7406\u53ca\u4ee3\u7406\u6709\u9650\u516c\u53f8\u4f55\u5148\u751f\u806f\u7d61\u3002", "employment_types": ["Full Time"], "selling_points": [], "locations": ["Sai Wan"], "categories": ["Engineering", "Mechanical", "Telecommunication / Wireless / Radio", "Others", "Technician"], "post_time": "2022-01-14T07:52:17Z", "salary": {"currency": null, "max": null, "min": null, "period": "monthly", "term": null}, "salary_visible": false, "title_keywords": ["\u6280\u5de5"], "responsibilities": [], "requirements": {"degrees": [], "majors": [], "languages": [], "language_level": [], "hard_skills": [], "soft_skills": [], "languages_combined": []}, "experience_required": {"duration": [], "field": []}}, {"job_id": "100003009048445", "location_code": "hk", "company": "Hong Kong Broadband Network Limited", "job_title": "System Engineer / Senior System Engineer", "description": "To be part of our mission, we are looking for a Senior System Engineer to\u2026\n\nWork with a dynamic team to\u00a0bring next generation digital services to production\nBe an exceptional Talent \u2013 The Talent who will challenge us and make our teams stronger\n\nWhat efforts you need to make for this role?\n\nResponsible for system monitoring, support and maintenances\nProvide routine operation, incident support and troubleshooting\nDesign and implementation of system enhancements and upgrades\nPrepare system documents and training to user departments\nOn-call support may be required\n\nLet's check if you are /have\u2026\n\nHigher Diploma or above in Computer Science or related disciplines\n4 years or more relevant working experiences in system support\nSolid knowledge of Internet services and applications\nHands on experience on system and application virtualization technology\nFamiliar with Unix, Linux and Windows platforms, data networking and firewalls\nCandidate with experiences in scripting or programming languages is preferred\nCandidate with experiences in project management is a plus\nA good team player as well as ability to work independently and under pressure\nCandidate with less experiences will be considered as System\u00a0Engineer", "employment_types": ["Full Time", "Permanent"], "selling_points": ["Talent-first Culture & LIFE-work priority", "System monitoring, support and maintenances", "Familiar with Unix, Linux and Windows platforms"], "locations": ["Kwai Hing"], "categories": ["Engineering", "Electrical / Electronics", "Engineering Project Management", "Telecommunication / Wireless / Radio"], "post_time": "2022-01-14T06:35:54Z", "salary": {"currency": null, "max": null, "min": null, "period": "monthly", "term": null}, "salary_visible": false, "title_keywords": ["system engineer", "senior system engineer"], "responsibilities": ["data", "upgrades", "monitoring", "teams", "troubleshooting", "design", "implementation", "internet services", "project management"], "requirements": {"degrees": ["higher diploma or above"], "majors": ["related disciplines", "computer science"], "languages": [], "language_level": [], "hard_skills": ["linux", "virtualization technology", "plus", "make", "project management", "dynamic", "programming"], "soft_skills": ["good team player", "work independently", "under pressure", "responsible", "troubleshooting", "project management", "hands on", "dynamic"], "languages_combined": []}, "experience_required": {"duration": ["4 years"], "field": ["project management", "system support", "programming"]}}, {"job_id": "100003009041440", "location_code": "hk", "company": "HGC Global Communications Limited", "job_title": "(Senior) Engineer - Network Transmission", "description": "Roles & Responsibilities\n\n\nTo coordinate and participate in global transmission network setup in different countries.\n\nCarrying out transmission network planning, network maintenance and upgrade to ensure the highest levels of network and infrastructure availability.\nCarrying out transmission network monitoring and performing network analysis to drive network efficiency, work with external and internal parties coordinating and troubleshooting network events.\nSupporting delivery and testing of projects.\nMaintaining up-to-date network inventory records.\nRequirements\n\n\nMinimum 3 years\u2019 relevant experience in\u00a0transmission operation.\n\nHigher Diploma/Diploma in Telecommunications, Engineering or related disciplines.\nSolid knowledge of OTN,\u00a0SDH and DWDM transmission technology.\nTechnical experience in transmission systems and project implementation will be an advantage.\nKnowledge of major transmission test equipment and network operation system.\nProactive, responsible and a good team player.\nExcellent command in spoken and written English and Chinese.\n\n\n\nWe offer competitive salary package and career development opportunity. Free company coach is provided.\u00a0 Interested parties, please quote our reference number and apply with full resume, present and expected salary, by clicking \u201cAPPLY NOW\u201d.\u00a0\n\nWe are an equal opportunity employer and welcome applications from all qualified candidates. Information provided will be treated in strict confidence and only be used for consideration of your application for the relevant post within HGC Global Communications Limited. Personal data provided by job applicants will be used strictly according to our Personal Information Collection Statement, a copy of which will be available upon written request. Information of unsuccessful candidates will be destroyed within six months.", "employment_types": ["Full Time"], "selling_points": ["Global transmission network setup", "Transmission network monitoring", "Troubleshooting"], "locations": ["Chai Wan"], "categories": ["Engineering", "Telecommunication / Wireless / Radio", "Information Technology (IT)", "Network & System", "Mobile / Wireless Communications"], "post_time": "2022-01-12T03:53:06Z", "salary": {"currency": null, "max": null, "min": null, "period": "monthly", "term": null}, "salary_visible": false, "title_keywords": ["engineer"], "responsibilities": ["maintenance", "maintaining", "analysis", "infrastructure", "monitoring", "troubleshooting", "inventory", "testing", "coordinate", "internal parties", "setup", "planning"], "requirements": {"degrees": ["diploma"], "majors": ["related disciplines", "engineering"], "languages": ["english", "chinese"], "language_level": ["excellent"], "hard_skills": [], "soft_skills": ["good team player", "proactive", "responsible"], "languages_combined": [{"language": "english", "language_level": ["excellent"]}, {"language": "chinese", "language_level": ["excellent"]}]}, "experience_required": {"duration": ["minimum 3 years"], "field": ["operation", "relevant experience"]}}, {"job_id": "100003009043248", "location_code": "hk", "company": "Huawei International Co., Ltd", "job_title": "Assistant Solution Engineer (5G Network/ Professional Services/ Enterprise Network)", "description": "This is a pre-sale and 2-Year Renewable Contract Position. (Service Provider: Manpower).\n\nAs a global ICT company with a presence in over 170 countries and regions, we provide a broad platform where employees can realize their personal value. This is an excellent opportunity to build up your career in ICT industry where you be enriched with our Huawei innovative business solutions. We seek and reward talent. At Huawei, if you are driven and show results, your efforts will be rewarded. Join us for a Building a Better Connected World.\u00a0\n\n\nJob Responsibilities:\n\n\nResponsible to provide support in 5G Network/ Professional Services/ Enterprise Network solutions to our partners through Quotation Preparation, Products Configuration, Products Licensing, Market Data Analysis\nResponsible to keep track with the solution timeline with our leading-edge operating system ensure service customer satisfaction;\nResponsible to understand market demands and customer requirements and provide feedback to R&D;\nResponsible to communicate closely with different stakeholders to ensure smooth process\n\n\n\n\u00a0Job\u00a0Requirements:\n\n\nBachelor degree or above. Major in Electronic and Computer Engineering, Computer Science, Electrical and Electronic Engineering or other related engineering or science disciplines is preferred.\nGood command of written and spoken English and Cantonese. Ability to speak Mandarin is an advantage.\nSound knowledge of communications network is a big advantage\nAbility to take responsibility and commitment of your own missions\nAbility to work under pressure with a self-motivated and challenging mindset\nAbility to communicate with different stakeholders and be the problem resolver\nAbility to enrich yourself with new concepts and theories\nFresh graduate will also be considered", "employment_types": ["Full Time", "Contract"], "selling_points": ["Pre-sales in 5G/ Enterprise Network", "Excellent career opportunity & work environment", "Fresh Graduates are welcomed to apply!"], "locations": ["Tsim Sha Tsui"], "categories": ["Engineering", "Telecommunication / Wireless / Radio", "Information Technology (IT)", "Product Management / Business Analyst", "Technical / Functional Consulting"], "post_time": "2022-01-12T10:21:35Z", "salary": {"currency": null, "max": null, "min": null, "period": "monthly", "term": null}, "salary_visible": false, "title_keywords": ["assistant solution engineer"], "responsibilities": [], "requirements": {"degrees": [], "majors": [], "languages": [], "language_level": [], "hard_skills": [], "soft_skills": [], "languages_combined": []}, "experience_required": {"duration": [], "field": []}}, {"job_id": "100003009041441", "location_code": "hk", "company": "HGC Global Communications Limited", "job_title": "(Senior) Engineer - International IP Network", "description": "Roles & Responsibilities\nInternational IP and VPN network implementation and Operations & Maintenance\nIP and VPN services provisioning\nTechnical arrangement with overseas carrier in network interconnection implementation\nLayer 2, layer 3 and application equipment evaluation\nTier 2 fault support\u00a0\nNetwork performance review\nRequirements\n3-7 year experience in IP engineering, operations and maintenance\nHolder of CCNP or equivalent\nIn-depth and operational experience in routers and internet protocols such as BGP, OSPF, MPLS, VPLS.\nHand on experience in Layer 2 switch protocols such as spanning tree, Bridging protocol, IEEE802.3, Ethernet, VLAN, Trunking and etc.\nGood coordination of works and able to handle multiple tasks in organized and efficient manner.\nBasic understanding in SDH, PDH and TDM.\nGood communications skills with good spoken English, Mandarin and Cantonese.\n\n\n\nWe offer competitive salary package and career development opportunity. Free company coach is provided.\u00a0 Interested parties, please quote our reference number and apply with full resume, present and expected salary, by clicking \u201cAPPLY NOW\u201d.\u00a0\n\nWe are an equal opportunity employer and welcome applications from all qualified candidates. Information provided will be treated in strict confidence and only be used for consideration of your application for the relevant post within HGC Global Communications Limited. Personal data provided by job applicants will be used strictly according to our Personal Information Collection Statement, a copy of which will be available upon written request. Information of unsuccessful candidates will be destroyed within six months.", "employment_types": ["Full Time"], "selling_points": ["International IP and VPN network implementation", "Operations & Maintenance, Service provisioning", "Network performance review"], "locations": ["Chai Wan"], "categories": ["Engineering", "Telecommunication / Wireless / Radio", "Information Technology (IT)", "Network & System", "Mobile / Wireless Communications"], "post_time": "2022-01-12T03:53:06Z", "salary": {"currency": null, "max": null, "min": null, "period": "monthly", "term": null}, "salary_visible": false, "title_keywords": ["engineer"], "responsibilities": ["maintenance", "operations", "review", "implementation", "evaluation"], "requirements": {"degrees": [], "majors": [], "languages": ["cantonese", "english", "mandarin"], "language_level": ["good"], "hard_skills": ["basic", "maintenance", "switch", "ccnp", "ip"], "soft_skills": ["handle multiple tasks", "organized", "efficient", "coordination"], "languages_combined": [{"language": "cantonese", "language_level": ["good"]}, {"language": "english", "language_level": ["good"]}, {"language": "mandarin", "language_level": ["good"]}]}, "experience_required": {"duration": ["3-7 year"], "field": ["engineering", "maintenance"]}}, {"job_id": "100003009047275", "location_code": "hk", "company": "CITIC Telecom International Holdings Limited", "job_title": "Product Engineer", "description": "\u00a0Responsibilities:\u00a0\n\nHandle implementation, installation, launching and supporting of new\u00a0products and projects developed\u00a0in-house\nPerform system monitoring, platform enhancement and capacity\u00a0planning\nProvide tier 3 support for engineering and operation\u00a0team\n\nRequirements:\n\nDegree holder in Information Technology, Computer Science, Electronic Engineering, Telecommunications or related disciplines\nMinimum 3 years' solid experience in telecommunication industry\nKnowledge in Microsoft server applications, MSSQL, Linux / UNIX, virtualization and Cloud native\u00a0environment\u00a0\nGood analytical and problem solving skills\nGood command in both spoken and written English and Chinese (Cantonese & Mandarin)\n\nFringe Benefits:\n\nOn-the-job training\nDouble pay\nAttractive performance bonus\nTransportation allowance\nMedical & dental insurance\nFree meals\nFree shuttle bus service\nTraining subsidies\nStaff discount\n\n\nWe offer competitive salary and benefit package including double pay, medical and dental benefits, 5-day work, 14 days paid annual leave and free shuttle bus service to the capable candidate. If you are interested, please immediately send your application stating\u00a0your current & expected salary and date availability with full resume\u00a0to\u00a0Human Resources Department\u00a0by email by clicking \"Apply Now\". Please clearly indicate the applied position and reference number on your application.\n\n\nAll personal data received will be treated strictly confidential and will be used for employment related purpose only.", "employment_types": ["Full Time", "Permanent"], "selling_points": ["Engineer position in telecommunications industry", "Sizable and energetic team", "Double Pay, Bonus, 5-day work, Medical & Dental"], "locations": ["Kwai Fong"], "categories": ["Engineering", "Electrical / Electronics", "Telecommunication / Wireless / Radio", "Information Technology (IT)", "Others"], "post_time": "2022-01-14T02:48:03Z", "salary": {"currency": null, "max": null, "min": null, "period": "monthly", "term": null}, "salary_visible": false, "title_keywords": ["engineer"], "responsibilities": ["installation", "monitoring", "implementation", "planning"], "requirements": {"degrees": ["degree holder"], "majors": ["related disciplines", "engineering", "computer science", "information technology"], "languages": ["cantonese", "english", "chinese", "mandarin"], "language_level": ["good command"], "hard_skills": ["server", "linux", "problem solving skills", "mssql"], "soft_skills": ["analytical and problem solving skills"], "languages_combined": [{"language": "cantonese", "language_level": ["good command"]}, {"language": "english", "language_level": ["good command"]}, {"language": "chinese", "language_level": ["good command"]}, {"language": "mandarin", "language_level": ["good command"]}]}, "experience_required": {"duration": ["minimum 3 years"], "field": []}}, {"job_id": "100003009047335", "location_code": "hk", "company": "Hong Kong Applied Science and Technology Research Institute Company Limited (ASTRI)", "job_title": "Mixed Signal / RF Circuit Design - Senior Engineer / Engineer", "description": "Reference #:\u00a0CTO/IOTSEN/14\nJob Responsibilities\nAssist in ITF R&D project as assigned\nHand on RF and electronic sub-system design\nPCB schematic design and layout optimization\nPrototypes assemble and circuit validation and failure analysis\nPrepare testing data for the deliverables, write reports documenting detail methods and results\nRequirements\nPhD holder or Master\u2019s degree in Electronic Engineering, Information Engineering, or relevant disciplines with a minimum of 3 years of related experience. Candidates with fewer experience may also be considered.\nExperiences in PCB schematic & layout design, mixed signal IC design, digital & analog signal processing\nFamiliar with EDA software such as Altium/Cadence/Mentor/Synopsys, etc.\nFamiliar with EE equipment like oscilloscope, multimeter etc.\nGood command of written and spoken English and Chinese\nApplication\n\nThe appointment will be on renewable contract terms with a competitive salary and performance-linked variable pay. Fringe benefits include paid leave, medical and dental benefits, insurance coverage and contribution to MPF. The incumbent will normally work\u00a0a five-day week.\n\nInterested candidates, please send an application (quoting Ref. No.) with a detailed resume, current and expected salary to\u00a0Talent Acquisition by clicking \"APPLY NOW\".\u00a0The resume should\u00a0not\u00a0include any sensitive personal information such as HKID or passport number, photo, etc.\u00a0\n\nPosition offer is subject to the applicant\u2019s experience and academic qualification. The application will be open until the position is filled. Only short-listed candidates will be notified. ASTRI reserves the right not to fill the position.\n\nASTRI is an Equal Opportunities Employer. Personal data provided by job applicants will be used\u00a0exclusively\u00a0for recruitment\u00a0only. For details, please refer to\u00a0Privacy - ASTRI - Hong Kong Applied Science and Technology Research Institute Company Limited, in particular section 9.", "employment_types": ["Full Time", "Contract"], "selling_points": ["Mixed Signal / RF Circuit Design", "Hand on RF and electronic sub-system design", "PCB schematic design"], "locations": ["Shatin Area"], "categories": ["Engineering", "Electrical / Electronics", "Telecommunication / Wireless / Radio", "Information Technology (IT)", "Mobile / Wireless Communications"], "post_time": "2022-01-14T02:50:59Z", "salary": {"currency": null, "max": null, "min": null, "period": "monthly", "term": null}, "salary_visible": false, "title_keywords": ["senior engineer", "engineer"], "responsibilities": ["data", "analysis", "design", "testing", "system design", "reports"], "requirements": {"degrees": ["degree", "master"], "majors": ["engineering"], "languages": ["english", "chinese"], "language_level": ["good command"], "hard_skills": ["processing", "signal"], "soft_skills": [], "languages_combined": [{"language": "english", "language_level": ["good command"]}, {"language": "chinese", "language_level": ["good command"]}]}, "experience_required": {"duration": ["minimum of 3 years"], "field": ["related", "digital", "engineering", "design"]}}, {"job_id": "100003009044630", "location_code": "hk", "company": "HKT Consumer Group", "job_title": "Snr Technical Specialist, Field Engineering, Smart Living Engineering", "description": "Being a member of our Smart Living Engineering Team, you will be responsible for:\u00a0\n\nService provisioning and maintenance of home networking systems & e-Smart Health Projects\nDaily routine router maintenance for residential flats & Houses\nOn-site support in construction sites\nCoordinate with CS to ensure service quality\nCarry out shift duties\n\nTo succeed in this role\n\nKnowledge of Networking in both design and provisioning\nKnowledge of Security System in both provisioning and maintenance is an advantage\nGood problem solving skills and able to work in frontline customer service\nGood team player and self-motivated\nEager to learn and willing to take up new assignments & challenges\nGood command of both spoken & written English and Chinese\nCandidate with more experience will be considered as field control\nWilling to work under pressure and irregular working hours\n\n\u5de5\u4f5c\u5167\u5bb9\uff1a\n\n\u5b89\u88dd\u53ca\u7dad\u4fee\u5bb6\u5c45\u7db2\u7d61\u7cfb\u7d71\u548ce-Smart Health\u8a08\u5283\u65b9\u6848\n\u57f7\u884c\u5bb6\u5c45\u4f4f\u5b85\u7684\u8def\u7531\u5668\u7dad\u4fee\u53ca\u3001\u7ba1\u7406\u53ca\u6545\u969c\u6392\u9664\u7b49\u65e5\u5e38\u5de5\u4f5c\n\u63d0\u4f9b\u5de5\u5730\u4e0a\u7684\u73fe\u5834\u6280\u8853\u652f\u63f4\n\u8207\u5ba2\u6236\u670d\u52d9\u90e8\u4e92\u76f8\u914d\u5408\uff0c\u4ee5\u78ba\u4fdd\u670d\u52d9\u8cea\u91cf\n\u9700\u8f2a\u73ed\u5de5\u4f5c\n\n\u8981\u6c42\uff1a\n\n\u5177\u5099\u7db2\u7d61\u8a2d\u5099\u5b89\u88dd\u77e5\u8b58\n\u5177\u5099\u4fdd\u5b89\u7cfb\u7d71\u914d\u7f6e\u548c\u7dad\u8b77\u7b49\u76f8\u95dc\u77e5\u8b58\u8005\u512a\u5148\u8003\u616e\n\u826f\u597d\u89e3\u6c7a\u554f\u984c\u80fd\u529b\uff0c\u80fd\u5728\u524d\u7dda\u5ba2\u6236\u670d\u52d9\u5de5\u4f5c\n\u5718\u968a\u5408\u4f5c\u7cbe\u795e\u53ca\u4e0a\u9032\u5fc3\n\u6a02\u65bc\u5b78\u7fd2\uff0c\u9858\u610f\u63a5\u53d7\u65b0\u7684\u4efb\u52d9\u548c\u6311\u6230\n\u826f\u597d\u7684\u4e2d\u82f1\u6587\u53e3\u8a9e\u53ca\u66f8\u5beb\u80fd\u529b\n\u8f03\u591a\u7d93\u9a57\u8005\u53ef\u8003\u616e\u6210\u70baField Control\n\u80fd\u5728\u58d3\u529b\u4e0b\u5de5\u4f5c\u53ca\u63a5\u53d7\u8f2a\u73ed\u5de5\u4f5c\u5b89\u6392", "employment_types": ["Full Time"], "selling_points": [], "locations": ["Mong Kok"], "categories": ["Engineering", "Electrical / Electronics", "Telecommunication / Wireless / Radio"], "post_time": "2022-01-13T04:57:00Z", "salary": {"currency": null, "max": null, "min": null, "period": "monthly", "term": null}, "salary_visible": false, "title_keywords": ["technical specialist"], "responsibilities": ["control", "maintenance", "systems", "quality", "coordinate with", "design", "customer service", "work under pressure"], "requirements": {"degrees": [], "majors": [], "languages": ["english", "chinese"], "language_level": ["good command"], "hard_skills": ["networking systems", "problem solving skills", "maintenance", "router"], "soft_skills": ["good team player", "self-motivated", "responsible", "eager to learn", "customer service", "problem solving skills", "work under pressure"], "languages_combined": [{"language": "english", "language_level": ["good command"]}, {"language": "chinese", "language_level": ["good command"]}]}, "experience_required": {"duration": [], "field": []}}, {"job_id": "100003009038463", "location_code": "hk", "company": "Shen Milsom & Wilke Ltd", "job_title": "Senior Consultant / Consultant / Technical Engineer \u2013 Information and Communication Technology (ICT)", "description": "We have a legacy of creating innovative user experiences, pushing the boundaries of possibilities, and making sure those we partner with succeed.\u00a0 Looking forward, we\u2019ll hold true to our values and the culture that make us SM&W.\n\n\nKey Responsibilities :\n\n\n\nPlan and design of ICT Infrastructure includes structured cabling system, telephone system, wired and wireless data network and its applications, with consideration of system flexibility, redundancy, stability, security and sustainability.\nDevelop feasibility analysis and functional requirement reports, project budget, and prepare design schematic and layout drawing for commercial building, exhibition center, stadium, hotel, data centre, education (under-/post-graduate institution) and government projects.\nLead and manage internal resources & external vendors; evaluate work processes to improve quality of services.\nSelf-initiative, fast learning, creative and innovative sense for smart solutions and systems.\nPrepare tender document and drawing incorporating technical requirements in the specification, schematic and layout drawing for competitive bidding by the system integrators.\nOversee the implementation of ICT projects with technical and inspection reports.\nAttend end user and site coordination meeting, technical meeting and regular site inspection.\nReview and comment the technical submissions (i.e. method statement, equipment data sheet, shop drawing, etc.) prepared by the system integrator.\nParticipate testing and commissioning of the ICT system with the architect, owner and system integrator.\nOverseas travel is occasionally required includes Mainland China, Macau, Taiwan and Southeast Asia countries.\n\nJob Requirements:\n\nBSc or BEng (Hons) in Information and Communication Technology, Computer Science, Information Technology / Electronic / Electrical Engineering / Building Services Engineering.\nSolid experience in the design and implementation of structured cabling system, telephone system, enterprise network and wireless network.\nTechnical knowledge on various smart initiatives for integration with various M&E and ELV systems and mobile app functional workflow for smart applications will be an advantage.\nExcellent analytical, problem solving, communication and interpersonal skills, possessing good business understanding with intent to add value to the designs and deliverables.\nBasic knowledge on AutoCAD / Microsoft Visio are essential.\nHolder of various professional certificates (such as CCIE / CCNA / CCNP, WiSE, and Certified Designer of Structured Cabling System) is preferred.\nMinimum 3+ years of relevant working experience in design and project management.\nGood command of written and spoken English and Chinese (Cantonese and Mandarin).\nThe post of Senior Consultant and Technical Engineer will be offered for experienced candidates and University fresh graduate, respectively.", "employment_types": ["Full Time"], "selling_points": [], "locations": ["North Point"], "categories": ["Engineering", "Telecommunication / Wireless / Radio", "Information Technology (IT)", "IT Project Management / Team Lead", "Technical / Functional Consulting"], "post_time": "2022-01-11T07:04:35Z", "salary": {"currency": null, "max": null, "min": null, "period": "monthly", "term": null}, "salary_visible": false, "title_keywords": ["senior consultant", "consultant", "technical engineer"], "responsibilities": ["inspection reports", "data", "budget", "quality", "design", "plan", "tender document", "telephone system", "infrastructure", "implementation", "testing", "develop", "site inspection", "reports", "commissioning", "review", "site coordination", "analysis", "systems", "evaluate"], "requirements": {"degrees": ["fresh graduate", "bsc"], "majors": ["engineering", "electrical engineering", "information technology", "building services", "computer science"], "languages": ["cantonese", "english", "chinese", "mandarin"], "language_level": ["good command"], "hard_skills": ["basic", "ccnp", "ccna", "problem solving", "mobile", "project management", "integration", "autocad"], "soft_skills": ["communication", "project management", "problem solving", "communication and interpersonal skills", "structured"], "languages_combined": [{"language": "cantonese", "language_level": ["good command"]}, {"language": "english", "language_level": ["good command"]}, {"language": "chinese", "language_level": ["good command"]}, {"language": "mandarin", "language_level": ["good command"]}]}, "experience_required": {"duration": ["minimum 3+ years"], "field": ["project management", "relevant working experience", "design"]}}, {"job_id": "100003009046483", "location_code": "hk", "company": "China Mobile International Limited", "job_title": "Product Manager, Cloud Computing (Ref: CMIJD-0113-PMPMCPCHK)", "description": "Responsibilities:\n\nCooperate with cloud providers such as AWS/ Huawei to build CMI's edge computing products\nFamiliar with pre-sale, in-sale and post-sale processes of the cloud product\nInternal training for sales and pre-sales team\nProduct supporting for sales and pre-sales team\nProcess management and pricing of edge computing products\nBusiness model design of CMI's edge computing products\nResearch the industry development trend of public cloud, private cloud and hybrid cloud\nResearch customer needs and business competitor's cloud products, and make forward-looking cloud product product innovation\nOther ad hoc duties as assigned\u00a0\n\nRequirements\n\nBachelor degree or above\nMinimum 3 years of relevant experience\u00a0\nProfessional qualification in cloud production certification,\u00a0e.g. AWS, Azure is preferred\nExcellent teamwork skills, hardworking, self-motivated and able to work under pressure\nExcellent written and verbal communication skills in both English and Chinese\nDeeply understand the business model of Cloud Computing products\nFamiliar with service process of cloud product\u00a0\n\nInterested parties please send your full resume with current & expected salary to hr @ cmi. chinamobile. com. Please indicate the reference number in the subject line.\n\nAll personal data collected will be used for recruitment and employment related purpose only", "employment_types": ["Full Time", "Permanent"], "selling_points": ["Bachelor Degree or above", "Cloud Computing, AWS, Azure certification", "Product Management, Product Innovation"], "locations": ["Kwai Hing"], "categories": ["Engineering", "Electrical / Electronics", "Engineering Project Management", "Telecommunication / Wireless / Radio"], "post_time": "2022-01-13T11:47:26Z", "salary": {"currency": null, "max": null, "min": null, "period": "monthly", "term": null}, "salary_visible": false, "title_keywords": ["product manager"], "responsibilities": ["ad hoc duties", "management", "design", "sales team", "cooperate with"], "requirements": {"degrees": ["degree or above", "bachelor"], "majors": [], "languages": ["english", "chinese"], "language_level": ["excellent"], "hard_skills": ["azure", "aws"], "soft_skills": ["communication skills", "self-motivated", "teamwork", "hardworking", "work under pressure"], "languages_combined": [{"language": "english", "language_level": ["excellent"]}, {"language": "chinese", "language_level": ["excellent"]}]}, "experience_required": {"duration": ["minimum 3 years"], "field": ["relevant experience"]}}, {"job_id": "100003009042912", "location_code": "hk", "company": "Process Automation International Ltd", "job_title": "PLC Engineer", "description": "Job Descriptions:\u00a0\n\nYou will be responsible for developing a custom-made PLC program for large-scale automation systems that address a wide variety of safety requirements and operating conditions.\u00a0 It will be an added asset, although not a mandatory requirement, if you have hardware knowledge and be able to design an electrical control panel. You will support the testing, troubleshooting electrical power/control issues at our own factory and at our customers\u2019 sites. You may also require to design and develop HMI\u00a0(Human Machine Interface)\u00a0design. Be cost conscious and provide cost-effective designs are key traits we are looking for. Overseas travel is required.\n\nJob Requirements:\u00a0\n\n\nBachelor Degree in Electrical Engineering, Automation or other related disciplines;\nStrong computer skills in particular PLC programming (Siemens, Omron, Allen-Bradley etc);\nKnowledge of AutoCad and/or Solidwork are an additional assets but it is not a must;\nGood command of both English and Putonghua;\nFresh graduates\u00a0are also\u00a0welcome\u00a0to apply.\n\nOur office is at Tai Po and we own a three-storey building. We offer attractive remuneration including 5-day week, bank holiday, medical scheme, free lunch and company coach to the successful candidate. Please send your CV with expected salary and availability to the HR&A Manager, No. 11 Dai Hei Street, Tai Po Industrial Estate, Tai Po, N.T. or email or WhatsApp 5368 8083.\n\nMajor stops of company coach, to name a few, are Kwun Tong, Shum Shui Po, Kowloon Tong, Tsuen\u00a0Wan and Yuen Long.\n\nPersonal data collected will be used in recruitment purpose only.", "employment_types": ["Full Time", "Permanent"], "selling_points": [], "locations": ["Tai Po Area"], "categories": ["Engineering", "Electrical / Electronics", "Telecommunication / Wireless / Radio", "Information Technology (IT)", "Software Development"], "post_time": "2022-01-12T09:13:30Z", "salary": {"currency": null, "max": null, "min": null, "period": "monthly", "term": null}, "salary_visible": false, "title_keywords": ["engineer"], "responsibilities": ["control", "cost", "systems", "design and develop", "developing", "design", "testing", "troubleshooting", "hardware"], "requirements": {"degrees": ["degree", "bachelor"], "majors": ["related disciplines", "electrical engineering"], "languages": ["putonghua", "english"], "language_level": ["good command"], "hard_skills": ["plc", "computer skills", "solidwork", "programming", "autocad"], "soft_skills": [], "languages_combined": [{"language": "putonghua", "language_level": ["good command"]}, {"language": "english", "language_level": ["good command"]}]}, "experience_required": {"duration": [], "field": []}}, {"job_id": "100003009039182", "location_code": "hk", "company": "PCCW Global Limited", "job_title": "Senior Manager, Transmission Engineering", "description": "Job Responsibilities:\n\nInteract with consortium cable network administrators or external capacity suppliers to activate international cable capacity owned or acquired by the company\nLiaise with distance end network counterparts for provisioning activities on bilateral network\nDeveloping and nurturing PCCW Global relationships with Parties to cable consortia, so as to provide a basis for influencing key industry issues impacting PCCW Global\nManaging the engineering and operations aspects and formulating development plan of all PCCW Global cable landing stations in line with the overall cable strategies\nEnsure submarine and terrestrial cable infrastructure is seamlessly and cost effectively acquired and implemented to meet all advised product requirements and forecast demands of the network\nIdentifying and developing initiatives to improve Activation and Restoration performance and efficiencies in PCCW Global Transmission Network\nDeveloping and authorizing ad-hoc restoration plan to satisfy business units\u2019 impromptu requirement during network crisis events\nSupport Internal and External Parties Enquiry (Feasibility Study) and network resource assignment\nResponsible for network infrastructure management and operations across the bank\nLead the network team to resolve bottlenecks, weaknesses, restrictions, and security concerns imposed by the current infrastructure setup\nAct as the senior escalation point to serve network incidents and provide swift technical resolutions\n\n\u00a0Job Requirements:\n\nDegree in Telecommunications / Engineering / Information Technology or related disciplines with about\u00a010 years of relevant working experience\nGood knowledge and understanding of local and global communications developments and directions, particularly for submarine cables\nExtensive experience in Telecommunications Transmission and Network Planning and Development\nGood knowledge of\u00a0 transport network technology including OTN, DWDM, SDH, SONET, Ethernet and optical transmission\nMedium/High level of innovative thinking and initiative aimed at recognition and promotion of new ideas and innovative approaches rather than maintenance of the status quo\nGood Presentation and negotiation skills, especially in multilateral forums\nGood judgment and risk assessment/acceptance based on technical and business skills\nGood command of both written and spoken English and Chinese, proficient in Mandarin is definitely an advantage", "employment_types": ["Full Time"], "selling_points": [], "locations": ["Wan Chai"], "categories": ["Engineering", "Electrical / Electronics", "Mechanical", "Telecommunication / Wireless / Radio"], "post_time": "2022-01-11T08:56:48Z", "salary": {"currency": null, "max": null, "min": null, "period": "monthly", "term": null}, "salary_visible": false, "title_keywords": ["senior manager"], "responsibilities": ["ad-hoc", "network infrastructure", "cost", "management", "operations", "infrastructure", "internal and external parties", "developing", "plan", "forecast", "liaise with", "setup"], "requirements": {"degrees": ["degree"], "majors": ["related disciplines", "engineering", "information technology"], "languages": ["english", "chinese", "mandarin"], "language_level": ["advantage", "good command", "proficient"], "hard_skills": ["maintenance"], "soft_skills": ["initiative", "negotiation skills", "innovative", "extensive", "presentation"], "languages_combined": [{"language": "english", "language_level": ["proficient", "advantage", "good command"]}, {"language": "chinese", "language_level": ["proficient", "advantage", "good command"]}, {"language": "mandarin", "language_level": ["proficient", "advantage", "good command"]}]}, "experience_required": {"duration": ["10 years"], "field": ["engineering", "related", "development", "relevant working experience", "information technology", "telecommunications", "planning"]}}, {"job_id": "100003009044412", "location_code": "hk", "company": "Lik On Security Limited", "job_title": "\u5730\u76e4\u7ba1\u5de5 Site Supervisor", "description": "\u00a0\u8077\u8cac\u7bc4\u7587\uff1a\n\n\n\u00a0\u00a0\u00a0\u00a0\u00a0\u00a0\u00a0\u00a0 \u76e3\u7763\u5404\u627f\u5224\u5546\u5b89\u88dd\u5f31\u96fb\u5de5\u7a0b\u9805\u76ee\n\u00a0\u00a0\u00a0\u00a0\u00a0\u00a0\u00a0\u00a0 \u8ca0\u8cac\u50b3\u905e\u826f\u597d\u5b89\u5168\u3001\u74b0\u4fdd\u548c\u8cea\u91cf\u63a7\u5236\n\u00a0\u00a0\u00a0\u00a0\u00a0\u00a0\u00a0\u00a0 \u8655\u7406\u65e5\u5e38\u5730\u76e4\u7ba1\u7406\u53ca\u5354\u8abf\u65bd\u5de5\n\u00a0\u00a0\u00a0\u00a0\u00a0\u00a0\u00a0\u00a0 \u5b9a\u671f\u51fa\u5e2d\u5de5\u7a0b\u9032\u5ea6\u53ca\u5b89\u5168\u6703\u8b70\uff0c\u4e26\u4f5c\u51fa\u76f8\u61c9\u5b89\u6392\u53ca\u5de5\u4f5c\u5206\u914d\n\u00a0\u00a0\u00a0\u00a0\u00a0\u00a0\u00a0\u00a0 \u76e3\u7763\u6e2c\u8a66\u53ca\u8abf\u8a66\u5de5\u4f5c\n\n\u5165\u8077\u8981\u6c42\uff1a\n\n\n\u00a0\u00a0\u00a0\u00a0\u00a0\u00a0\u00a0\u00a0 \u6700\u5c113\u5e74\u5f31\u96fb\u6216\u9805\u76ee\u5730\u76e4\u76e3\u7763\u7d93\u9a57\n\u00a0\u00a0\u00a0\u00a0\u00a0\u00a0\u00a0\u00a0 \u826f\u597d\u7684\u6e9d\u901a\u548c\u5730\u76e4\u7ba1\u7406\u80fd\u529b\n\u00a0\u00a0\u00a0\u00a0\u00a0\u00a0\u00a0\u00a0 \u6301\u6709\u6548\u96fb\u5de5\u724c\u548c\u5efa\u9020\u696d\u5de5\u4eba\u8a3b\u518a\u8b49\n\u00a0\u00a0\u00a0\u00a0\u00a0\u00a0\u00a0\u00a0 \u53ef\u5373\u6642\u4e0a\u73ed\u512a\u5148\u8003\u616e\n\n\u61c9\u5fb5\u8005\u8acb\u5c07\u5c65\u6b77\u8868\u53ca\u8981\u6c42\u85aa\u91d1\u96fb\u90f5(\u8acb\u6309\"APPLY NOW\") \u6216 \u90f5\u5bc4\u81f3:\u00a0\u529b\u5b89\u8b77\u885b\u6709\u9650\u516c\u53f8\u4e5d\u9f8d\u9577\u6c99\u7063\u9577\u7fa9\u885710\u865f\u660c\u9686\u5de5\u696d\u5927\u5ec88\u6a13\u884c\u653f\u90e8\u6536\u00a0\u6216\u81f4\u96fb\u00a02485-2485 \u884c\u653f\u90e8\u9810\u7d04\u9762\u8a66\u6642\u9593\u3002\n\n\u672c\u516c\u53f8\u662f\u5e73\u7b49\u6a5f\u6703\u50f1\u4e3b\uff0c\u6240\u6709\u6536\u96c6\u8cc7\u6599\u53ea\u6703\u7528\u4f5c\u62db\u8058\u7528\u9014\u3002", "employment_types": ["Full Time", "Permanent"], "selling_points": ["\u6700\u5c113\u5e74\u5f31\u96fb\u6216\u9805\u76ee\u5730\u76e4\u76e3\u7763\u7d93\u9a57", "\u6301\u6709\u6548\u96fb\u5de5\u724c\u548c\u5efa\u9020\u696d\u5de5\u4eba\u8a3b\u518a\u8b49", "\u76e3\u7763\u5404\u627f\u5224\u5546\u5b89\u88dd\u5f31\u96fb\u5de5\u7a0b\u9805\u76ee"], "locations": ["Not Specified"], "categories": ["Engineering", "Electrical / Electronics", "Telecommunication / Wireless / Radio", "Others", "Security / Safety Control"], "post_time": "2022-01-13T03:59:01Z", "salary": {"currency": null, "max": null, "min": null, "period": "monthly", "term": null}, "salary_visible": false, "title_keywords": ["site supervisor"], "responsibilities": [], "requirements": {"degrees": [], "majors": [], "languages": [], "language_level": [], "hard_skills": [], "soft_skills": [], "languages_combined": []}, "experience_required": {"duration": [], "field": []}}, {"job_id": "100003008995670", "location_code": "hk", "company": "Pricom Technology & System Limited", "job_title": "Project Engineer", "description": "Responsibilities\nCarry out Block-wiring Systems included fiber, copper cables & ELV System\n\nPrepare cost estimation, quotation, proposals and tender documents\nConduct site survey and meeting\nCollect site information for proposal preparation & submission\nMonitor work progress, installation schedule & report to Project Manager\nRequirements\n\nHigher Diploma or above\n3 years working experience\nGood command in spoken & written English & Chinese\nGood command of MS Office, AutoCAD\nGood communication skills\nImmediately available is preferred", "employment_types": ["Full Time"], "selling_points": ["5-day work week", "Bank Holiday", "3 years working experience"], "locations": ["Cheung Sha Wan"], "categories": ["Engineering", "Engineering Project Management", "Telecommunication / Wireless / Radio"], "post_time": "2022-01-12T23:26:04Z", "salary": {"currency": null, "max": null, "min": null, "period": "monthly", "term": null}, "salary_visible": false, "title_keywords": ["project engineer"], "responsibilities": ["installation", "cost estimation", "tender documents", "quotation", "systems", "monitor", "schedule", "report"], "requirements": {"degrees": ["higher diploma or above"], "majors": [], "languages": ["english", "chinese"], "language_level": ["good command"], "hard_skills": ["autocad", "ms office"], "soft_skills": ["communication skills"], "languages_combined": [{"language": "english", "language_level": ["good command"]}, {"language": "chinese", "language_level": ["good command"]}]}, "experience_required": {"duration": ["3 years"], "field": []}}, {"job_id": "100003009043162", "location_code": "hk", "company": "China Mobile International Limited", "job_title": "Solution / Project Manager (Data Center) (Ref: CMIJD-0112-SPMCMIXHK)", "description": "Responsibilities:\n\nSupport Sales team in providing pre-sales solutions and assistance during sales cycle\nIdentifies customer\u2019s needs and technical requirements to derive Data Center related solutions\nProvides support to customers pertaining to global deployments of solution design and deliverables\nProject management in developing the deployment schedule and ensure implementation according to schedule and minimize potential risk\nComplete service acceptance and project handover to operation team\u00a0\n\nRequirements:\n\nUniversity degree in Electrical Engineering/ Mechanical Engineering related disciplines\nMinimum 5 years or above relevant experience in\u00a0Pre-Sales\u00a0/ Facility Management\nExperience in Telecommunications, Networking, Internet, Data Center are preferred\nExcellent Communication and problem-solving skills\nFlexible, Result-oriented, and Organized\nProficiency in MS Office applications and Chinese Word Processing\nGood command of spoken and written Chinese and English, proficiency in Putonghua is an advantage\n\nInterested parties please send your full resume with current & expected salary by email to hr@ cmi.chinamobile.com.\u00a0Please indicate the reference number in the subject line.\n\nAll personal data provided will be used for consideration of your job application only.", "employment_types": ["Full Time", "Permanent"], "selling_points": ["Pre-Sales & Project Management", "Electrical / Mechanical engineering preferred", "Manage the global Data Center solution"], "locations": ["Tseung Kwan O"], "categories": ["Professional Services", "Business Consultancy", "Engineering", "Engineering Project Management", "Telecommunication / Wireless / Radio"], "post_time": "2022-01-12T09:59:11Z", "salary": {"currency": null, "max": null, "min": null, "period": "monthly", "term": null}, "salary_visible": false, "title_keywords": ["project manager"], "responsibilities": ["data", "developing", "design", "implementation", "project management", "project handover", "sales team", "schedule"], "requirements": {"degrees": ["university degree"], "majors": ["related disciplines", "electrical engineering", "mechanical engineering"], "languages": ["putonghua", "english", "chinese"], "language_level": ["advantage", "proficiency", "good command"], "hard_skills": ["problem-solving skills", "chinese word processing", "ms office"], "soft_skills": ["flexible", "organized", "communication", "problem-solving skills", "result-oriented"], "languages_combined": [{"language": "putonghua", "language_level": ["proficiency", "advantage", "good command"]}, {"language": "english", "language_level": ["advantage", "good command"]}, {"language": "chinese", "language_level": ["proficiency", "advantage", "good command"]}]}, "experience_required": {"duration": ["minimum 5 years"], "field": ["telecommunications", "management", "relevant experience"]}}, {"job_id": "100003009035793", "location_code": "hk", "company": "Macroview Telecom Limited", "job_title": "Solution Consultant / Engineer - Network Infrastructure Solutions (Pre-Sales)", "description": "Responsibility\n\nHandle customer engagement activities on network infrastructure domain majority in enterprise networking, mobility and network security solution\nResponsible for gathering customer requirements, solution design, proposal and presentation, and also, focus on demonstration, proof of concept test\nWork together with Sales and Product team for solution development\nDevelop good relationships with clients and propose appropriate solutions according to their needs\nDevelop customer oriental automation and software driven use cases to help in strategic decision process\nHandle project implementation service in occasional basis\nRequirement\nDegree holder in Computer Science or IT related\n2 years\u2019 experience in \u00a0IT networking field\nNetworking vendor certified or equivalent is\u00a0proffered\nHands-on experience in Network infrastructure solutions\nSelf-motivated and able to work under pressure\nGood interpersonal communication, team player and presentation skill\nFresh graduate & candidates with less experience will be considered as Solution Engineer\n\n\nWe offer attractive remuneration package, medical benefits and marriage leave to the right candidate. Interested parties please send full resume with expected salary by clicking 'Apply Now'.\n\nAll information collected will be used for recruitment purpose only.\n\nTo learn more, please visit Macroview\u2019s website at:\u00a0www.macroview.com\u00a0", "employment_types": ["Full Time", "Permanent"], "selling_points": ["Presales role in network infrastructure", "Fresh graduate is welcome", "Prepare design, proposal, presentation, PoC test"], "locations": ["Quarry Bay"], "categories": ["Engineering", "Telecommunication / Wireless / Radio", "Information Technology (IT)", "Network & System", "Others"], "post_time": "2022-01-10T08:27:02Z", "salary": {"currency": null, "max": null, "min": null, "period": "monthly", "term": null}, "salary_visible": false, "title_keywords": ["engineer", "consultant", "sales"], "responsibilities": ["network infrastructure", "software", "implementation", "design", "develop"], "requirements": {"degrees": ["fresh graduate", "degree holder"], "majors": ["it", "computer science"], "languages": [], "language_level": [], "hard_skills": ["presentation skill", "vendor"], "soft_skills": ["presentation skill", "self-motivated", "communication", "hands-on", "team player", "interpersonal", "work under pressure"], "languages_combined": []}, "experience_required": {"duration": ["2 years"], "field": ["it networking", "infrastructure"]}}, {"job_id": "100003009035199", "location_code": "hk", "company": "Hongkong International Terminals Limited", "job_title": "Technician - Electronics & Communication Systems", "description": "Main Duties:\n\n\nProvide maintenance services on communication systems and networking equipment\nParticipate in engineering projects & system development\nWork at outdoor and height\n\nRequirements:\n\nDiploma or Certificate in Electronic / Computer / Telecommunication / Information Engineering related discipline\nAt least 2 years relevant working experience\nGood learning and cooperative working attitude\nHolder of REW and Valid Driving License Class 1 & 2 is preferable\nCandidates with less experience and Higher Diploma in Engineering related discipline will be considered as Technician Trainee\n\nPlease apply through our Career Centre at\u00a0https://www.hit.com.hk/cn/Career-With-Us/Career-Oppotunities.html. You may also apply the job\u00a0by sending your\u00a0full resume with current and expected salary to Human Resources Manager, Terminal 4, Container Port Road South, Kwai Chung.\n\nFor further information, please visit our website at http://www.hit.com.hk/.\n\nPlease read the Personal Information Collection Statement before submitting your application.\n\nWe are an equal opportunity employer and welcome applications from all qualified candidates. The information provided will be treated in strict confidence and used only for consideration of application for relevant/similar positions within the Hutchison Group of Companies. Applicants not invited for interview in 6 weeks after job posting may consider their application unsuccessful and your personal data will be destroyed after a period of\u00a06 months.", "employment_types": ["Full Time", "Permanent"], "selling_points": ["Double Pay, Discretionary Bonus, Free Shuttle Bus", "Engineering Projects", "2 Years Working Experience"], "locations": ["Kwai Fong"], "categories": ["Engineering", "Electrical / Electronics", "Engineering Project Management", "Telecommunication / Wireless / Radio"], "post_time": "2022-01-10T06:24:06Z", "salary": {"currency": null, "max": null, "min": null, "period": null, "term": null}, "salary_visible": false, "title_keywords": ["technician"], "responsibilities": ["communication", "systems", "maintenance services"], "requirements": {"degrees": ["certificate", "diploma"], "majors": ["engineering"], "languages": [], "language_level": [], "hard_skills": ["container", "html"], "soft_skills": ["cooperative", "learning", "confidence"], "languages_combined": []}, "experience_required": {"duration": ["at least 2 years"], "field": ["related", "engineering", "relevant working experience"]}}, {"job_id": "100003009038858", "location_code": "hk", "company": "HKT", "job_title": "Technical Officer, Network Operation Center", "description": "Your role\n\nCarry out network monitoring, system surveillance and first line fault diagnosis / resolution for various telecom services (voice, data and broadband networks)\nCarry out service provisioning and restoration for telecom services\nHandle service reports and follow up service status with customers\nAttend shift / emergency support duties outside normal working hours as necessary with allowance or time off\n\nTo succeed to the role\u00a0\n\nHigher Diploma/Diploma in Electronic, Information Technology, Computer Science, Communication Engineering or related disciplines with minimum\u00a03 years\u2019 relevant experience in telecommunications or IT industry\nGood interpersonal and communication skills\nKnowledge in any programming language will be an advantage\nSelf-motivated and able to work independently under minimal supervision\nGood command of written and spoken English and Chinese\n\nIf you have the desire for an exciting and rewarding career, please send us your resume, quoting the reference number, your present and expected salary by Whatsapp, email or post to the Human Resources Department.\n\n\u00a0Whatsapp:\u00a05410 6137\n\nPost: HR-ENGINEERING, 13/F, Lai Chi Kok Engineering Center, 4 Yuet Lun Street, Lai Chi Kok, Kowloon.on other job opportunities of PCCW, please visit our website at http://www.pccw.com/Careers/Job+Opportunities+%26+Application/Current+Opportunities?language=en_US", "employment_types": ["Full Time"], "selling_points": [], "locations": ["Lai Chi Kok"], "categories": ["Engineering", "Telecommunication / Wireless / Radio"], "post_time": "2022-01-11T07:56:48Z", "salary": {"currency": null, "max": null, "min": null, "period": "monthly", "term": null}, "salary_visible": false, "title_keywords": ["technical officer"], "responsibilities": ["data", "hr", "monitoring", "website", "resolution", "communication", "reports"], "requirements": {"degrees": ["diploma"], "majors": ["engineering", "information technology", "related disciplines", "it", "computer science"], "languages": ["english", "chinese"], "language_level": ["good command"], "hard_skills": ["whatsapp", "programming"], "soft_skills": ["communication skills", "self-motivated", "work independently", "communication", "interpersonal"], "languages_combined": [{"language": "english", "language_level": ["good command"]}, {"language": "chinese", "language_level": ["good command"]}]}, "experience_required": {"duration": ["minimum 3 years"], "field": ["engineering", "related", "information technology", "it", "relevant experience", "telecommunications"]}}, {"job_id": "100003009039184", "location_code": "hk", "company": "HKT", "job_title": "Technical Officer, Network monitoring and surveillance (Exchange Operations)", "description": "Your role\n\nBuild, operate and maintain various telecom infrastructure and Data Center\nSet up proper operation systems to improve operation efficiency in Data Center Administration, Cloud and telecom service provision\nCarry out diagnosis and restoration actions to resume service from equipment failure\nEstablish operation procedures and suggestion for work practice improvement\nCommunicate with customer on service support and inventory control\nShift and emergency support duties outside normal working hours when necessary\n\nTo succeed in the role\n\nForm 5, HKCEE/ HKDSE\u00a0\nHKIVE graduate in Electronic/ Electrical/ Computing or Engineering relevant discipline with 1 year of experience will be an avdantage\nPractical experience in telecom field is considered with priority\nGood interpersonal and communication skills\nSelf-motivated and able to work independently under minimal supervision\nProficient in spoken and written in both English and Chinese\n\nIf you have the desire for an exciting and rewarding career, please send us your resume, quoting the reference number, your present and expected salary by Whatsapp, email or post to the Human Resources Department.\n\n\u00a0Whatsapp:\u00a05410 6137\n\nPost: HR-ENGINEERING, 13/F, Lai Chi Kok Engineering Center, 4 Yuet Lun Street, Lai Chi Kok, Kowloon.on other job opportunities of PCCW, please visit our website at http://www.pccw.com/Careers/Job+Opportunities+%26+Application/Current+Opportunities?language=en_US", "employment_types": ["Full Time"], "selling_points": [], "locations": ["Lai Chi Kok"], "categories": ["Engineering", "Electrical / Electronics", "Telecommunication / Wireless / Radio"], "post_time": "2022-01-11T08:56:58Z", "salary": {"currency": null, "max": null, "min": null, "period": "monthly", "term": null}, "salary_visible": false, "title_keywords": ["technical officer", "operations"], "responsibilities": ["communicate with", "data", "hr", "infrastructure", "systems", "procedures", "website", "communication", "maintain", "inventory control", "administration"], "requirements": {"degrees": ["form 5", "hkdse"], "majors": [], "languages": ["english", "chinese"], "language_level": ["proficient"], "hard_skills": ["whatsapp"], "soft_skills": ["communication skills", "self-motivated", "interpersonal", "work independently"], "languages_combined": [{"language": "english", "language_level": ["proficient"]}, {"language": "chinese", "language_level": ["proficient"]}]}, "experience_required": {"duration": ["1 year"], "field": ["engineering"]}}, {"job_id": "100003009040922", "location_code": "hk", "company": "XTX Technology Limited", "job_title": "Principal/Senior Analog/Mixed-Signal Design Engineer", "description": "Key Tasks / Responsibilities\nDetailed design and simulation of high accuracy analogue/mixed signal IC blocks like references, amplifiers, filters, DAC/ADC, power management, synthesizers building blocks etc. -- as well as the higher-level integration of these blocks\nFull involvement in circuit design flow from definition and specification to production/IP delivery\nTop level IC/SoC analogue/mixed-signal performance and functional verification\nSupervision of circuit physical implementation\nInvolvement with system design and modelling\nInvolvement in silicon evaluation and test\nWorking with a multi-disciplined SoC design team: including digital, software, production, test and application engineers\n\n\u00a0Key skills / Background\n\nGood bachelor\u2019s degree in Electronic Engineering or related discipline, relevant Analogue/Mixed-Signal IC design MSc or PhD preferred\nExperience in Analogue/Mixed Signal schematic design in CMOS\n> 3 years of design experience in analogue/mixed signal circuits, specifically in one or more of the following areas:\nData converters\nSynthesizer building blocks and oscillators\nFilters and amplifiers\nPower management building blocks in low voltage deep submicron CMOS: DC-DC convertors, regulators, references etc\nExperience in custom IC layout and physical implementation\nExperienced in CAD tools:\nCadence Virtuoso Platform: Spectre/SpectreRF/AMS simulation, Layout XL etc\nMentor Calibre physical verification tools: DRC/LVS/PEX etc\nHands on knowledge of Analogue/Mixed signal IC evaluation and test\nUp to date on AMS IC design techniques and methodologies\n\nBeneficial Skills\n\nKnowledge or experience in Analogue/Mixed signal IP delivery, DSP, CMOS process, production test\nExperience in IO and ESD/EMC design\nExperience in RFIC design in silicon technologies\n\nPersonal Skills\n\nExcellent communication and interpersonal skills\nStrong/Creative problem-solving skills\nOrganized and efficient with demonstrated ability to meet deadlines\nGood team player\nSelf-motivated\nTake ownership of problems", "employment_types": ["Full Time"], "selling_points": ["analog/mixed-signal module design and integration", "3+ years hands on experience", "Attractive staff benefits, bonus, share option"], "locations": ["Shatin Area"], "categories": ["Engineering", "Electrical / Electronics", "Telecommunication / Wireless / Radio"], "post_time": "2022-01-12T03:13:22Z", "salary": {"currency": null, "max": null, "min": null, "period": "monthly", "term": null}, "salary_visible": false, "title_keywords": ["design engineer"], "responsibilities": ["management", "software", "esd", "data", "implementation", "design", "communication", "system design", "evaluation"], "requirements": {"degrees": ["degree", "bachelor"], "majors": ["engineering", "design"], "languages": [], "language_level": [], "hard_skills": ["xl", "io", "cad", "dc", "ip", "system design", "integration", "problem-solving skills", "signal"], "soft_skills": ["efficient", "organized", "good team player", "self-motivated", "deep", "hands on", "communication and interpersonal skills", "problem-solving skills", "meet deadlines", "creative", "detailed"], "languages_combined": []}, "experience_required": {"duration": ["3 years"], "field": ["design"]}}, {"job_id": "100003009038316", "location_code": "hk", "company": "DigiMobi Technology Limited", "job_title": "Technical Manager / Director - System Integration of Mobile IoT Systems for Smart City Solutions", "description": "What we want to achieve:\n\nWe are the market leader of \u201cTelematics & Fleet Management\u201d in HK with strong customer base in the Airport, Government, Logistics and Transportation segments\nThis position will help strengthen our leadership in the existing segments and\u00a0expand our business for\u00a0Smart City Solutions applicable to Connected Vehicles & Machines\n\nWho should apply:\n\nTechnically capable persons with Engineering and IT background\nWe prefer our candidates to have the following traits:\nPassion for innovative solutions & new technologies\nEagerness to push personal and organizational growth\nEnjoy hands-on implementation process by working in a lean organization\nCandidates with entrepreneur spirit will be considered for the position of \u201cTechnical Director\u201d\n\nAbout the job:\n\nThe major responsibility is to integrate onboard devices/sensors with our existing IoT server.\u00a0 More details of routine tasks are as follows:\nLead a small \u201cEngineering + IT\u201d team working on both hardware & software\nConfigure the following hardware to network with existing IoT server:\nGPS Tracker\n4G Router\nMobile CCTV\nAndroid-based Mobile Data Terminal\nVarious Sensors for use on Vehicles & Machines\nImplement Software Development with in-house or outsourced developers:\nWeb applications at our existing IoT server\nAndroid development of Mobile Data Terminal\nAPI for data import/export\nMaintain our IoT Server\u00a0\u00a0\u00a0\u00a0\nUsing AWS/Azure Cloud Services\nProject management for government projects\n\nWho will qualify:\n\nDegree holder in Engineering or Computer Science or Related Disciplines\nAt least 5 years of Hands-on & Management Experience on System Integration\nKnowledge with Location-based technologies like GPS, GIS, Google Geolocation API etc.\nKnowledge with RF technologies and sensors like RFID, Bluetooth and other wireless sensors\nFamiliar with server and infrastructure such as Windows/Linux/SQL/Apache/AWS/Azure\nPrevious experience on Fleet Management, Mobile Workforce or Mobile Video solutions is appreciated\nProfessional knowledge on Project Management preferably with PMP and PRINCE2 qualifications\nGood documentation skills\nAble to communicate both in English and Mandarin\nPreferably with driving Licence and driving experience\n\nWe offer competitive remuneration package for suitable candidates. For interested parties, please click \"APPLY NOW\" below to submit your CV with Expected Salary.", "employment_types": ["Full Time", "Permanent"], "selling_points": ["Engineering + IT Background", "Tech-savvy candidates with entrepreneurship", "5-day Work; Office close to Lai Chi Kok MTR"], "locations": ["Lai Chi Kok"], "categories": ["Engineering", "Telecommunication / Wireless / Radio", "Information Technology (IT)", "IT Project Management / Team Lead", "Software Development"], "post_time": "2022-01-11T06:31:40Z", "salary": {"currency": null, "max": null, "min": null, "period": "monthly", "term": null}, "salary_visible": false, "title_keywords": ["technical manager", "director"], "responsibilities": ["management", "software", "data", "infrastructure", "implementation", "hardware", "project management", "maintain", "logistics", "documentation"], "requirements": {"degrees": ["degree holder"], "majors": ["related disciplines", "engineering", "computer science"], "languages": ["english", "mandarin"], "language_level": [], "hard_skills": ["azure", "server", "pmp", "integration", "small", "router", "aws", "sql", "documentation", "android development", "lean", "linux", "web applications", "apache", "cctv", "hardware", "mobile", "project management", "android"], "soft_skills": ["capable", "passion for", "organizational", "project management", "hands-on", "team working", "innovative", "leadership"], "languages_combined": [{"language": "english", "language_level": []}, {"language": "mandarin", "language_level": []}]}, "experience_required": {"duration": ["at least 5 years"], "field": ["management", "video"]}}, {"job_id": "100003009040899", "location_code": "hk", "company": "XTX Technology Limited", "job_title": "Sr. Manager/Manager, Digital IC Design", "description": "Key Tasks / Responsibilities\nTake high level requirements and write chip or block level micro-architecture specifications.\nUndertake die-sizing, power estimation, technology selection etc to define an optimal solution for a given IC development.\nRTL coding of modules, sub-system or full-chip (primarily Verilog or SystemVerilog)\nSelection and integration of 3rd party IP into a SoC design\nLead a digital team on a SoC project \u2013 mentoring and reviewing the work of colleagues and ensuring that code quality is at the highest level and consistent with coding guidelines and applicable quality processes.\nChip level integration and liaising with implementation and physical design staff to ensure that the RTL code is optimized and aligned with the requirements of the back-end team.\n\nKey skills / Background\n\nPh.D or Master in Electronic Engineering, Computer Science or related discipline.\n5+ year experience as a digital designer or digital lead in a number design of SoC developments.\nA good understanding of the complete SoC flow from specification through to tape-out, validation and test.\nExperience in system integration of main stream CPU cores, like ARM Cortex-M0, Cortex-M0+ etc.\nGood working knowledge of verification techniques and methodologies and proven ability to debug issues in a structured and timely way.\nLow power design expertise\n\nBeneficial Skills\n\nGood knowledge of DFT techniques and the impact on the RTL design\nAnalog design knowledge or experience of working on mixed-signal SoC developments.\nExtensive knowledge of verification methodologies particularly UVM and SystemVerilog.\nExperience in the planning and implementation of verification infrastructures, test benches, models, assertions and functional tests in Verilog and SystemVerilog.\nExperience of FPGA design and associated tools", "employment_types": ["Full Time"], "selling_points": ["SoC system design and integration, team management", "5+ years experience on digital IC design", "Attractive staff benefits, bonus, share options"], "locations": ["Shatin Area"], "categories": ["Engineering", "Electrical / Electronics", "Telecommunication / Wireless / Radio"], "post_time": "2022-01-12T03:11:54Z", "salary": {"currency": null, "max": null, "min": null, "period": "monthly", "term": null}, "salary_visible": false, "title_keywords": ["manager"], "responsibilities": ["guidelines", "quality", "liaising with", "coding", "design", "implementation", "specifications", "architecture", "planning"], "requirements": {"degrees": ["master"], "majors": ["engineering", "computer science"], "languages": [], "language_level": [], "hard_skills": ["systemverilog", "verilog", "ip", "integration", "code", "signal"], "soft_skills": ["timely", "structured", "extensive"], "languages_combined": []}, "experience_required": {"duration": ["5+ year"], "field": ["digital", "designer", "design", "planning"]}}, {"job_id": "100003009036837", "location_code": "hk", "company": "Huawei Tech. Investment Co., Ltd", "job_title": "(Senior) Digital Design Engineer", "description": "Huawei Hong Kong Research Center\n\n\nHuawei Hong Kong Research Center was established in 2018, focusing on chipsets, software engineering, AI, and theoretical researches. We are currently seeking high-caliber Engineers and Researchers at all levels to join our new team.\n\n(Senior) Digital Design Engineer\n\nYou will take part in defining the micro-architecture of different major functional units of a processor/AI core and contribute to the various phases of the development work, including but not limited to feasibility studies, performance/power/area estimation and optimization, benchmarking analysis, micro-architecture definition, front end design and synthesis.\n\nResponsibilities\n\nInteract with architect, software teams and ASIC product development teams to define the micro-architecture of the processor/AI core including memory hierarchy and various interconnects;\nEvaluate and perform trade off analysis of hardware implementation between performance, power and area;\nDefine verification and validation strategies at different levels for the processor/ AI core and carry out the related work to ensure functional correctness.\n\nQualifications\n\nBachelor or higher degree in Electronic/Computer Engineering with experience in ASIC design/verification;\nExperience with multi-core processors /AI core architecture / design / verification;\nExperience with designs of complex high speed RTL modules;\nGood understanding of computer system architecture, memory systems or cache coherency;\nGood understanding of general CPU/GPU instruction set;\nGood understanding high speed circuit and low power design is a plus;\nGood command of written and spoken English and Chinese (Mandarin).\nGood team player with strong communication skills.\n\nFor interested parties, please send your full resume with and salary expectation by clicking the apply button.\u00a0Applicants who are not invited for interview within 6 weeks may assume their application unsuccessful.", "employment_types": ["Full Time"], "selling_points": ["Competitive compensation and benefits", "ASIC design/verification,5 working days", "CPU/AI Architecture,friendly working environment"], "locations": ["Tsim Sha Tsui"], "categories": ["Engineering", "Electrical / Electronics", "Engineering Project Management", "Telecommunication / Wireless / Radio"], "post_time": "2022-01-10T16:52:09Z", "salary": {"currency": null, "max": null, "min": null, "period": "monthly", "term": null}, "salary_visible": false, "title_keywords": ["design engineer"], "responsibilities": ["software", "analysis", "systems", "teams", "implementation", "design", "evaluate", "hardware", "communication", "architecture"], "requirements": {"degrees": ["degree", "bachelor"], "majors": ["computer engineering", "design"], "languages": ["english", "chinese", "mandarin"], "language_level": ["good command"], "hard_skills": ["hardware", "analysis", "plus", "ai"], "soft_skills": ["communication skills", "good team player"], "languages_combined": [{"language": "english", "language_level": ["good command"]}, {"language": "chinese", "language_level": ["good command"]}, {"language": "mandarin", "language_level": ["good command"]}]}, "experience_required": {"duration": [], "field": ["engineering", "design"]}}, {"job_id": "100003009050732", "location_code": "hk", "company": "Hutchison Telecommunications (Hong Kong) Limited", "job_title": "Account Manager \u2013 Enterprise Sales", "description": "Responsibilities:\n\nPromote mobile solution / service and provide comprehensive account servicing to corporate accounts\nCapture profitable and continuous business from clients and acquire the largest market share for sales achievement\nBuild up executive relations with all parties to maximize the business growth\n\n\u00a0Requirements:\n\nDiploma or above in Business Management or related disciplines\n2 years\u2019 sales experience in telecom services is preferred\nEnergetic, proactive and self-motivated\nExcellent communication and interpersonal skills\nGood command of\u00a0 both spoken and written English and Chinese\u00a0\u00a0\n\nApart from competitive remuneration package and exciting opportunity for career development within the Group, we provide attractive employee benefits such as free company shuttle, free company SIM card and preferential SIM plan offers, comprehensive medical & insurance schemes, as well as full range of other employee well-being provisions.\u00a0\n\nInterested parties, please apply with full resume, present and expected salary, by clicking \u201cAPPLY NOW\u201d. Please quote the reference number on the e-mail subject.\n\nWe are an equal opportunity employer and welcome applications from all qualified candidates. Personal data collected will be treated in the strictest confidence and handled confidentially by authorised personnel for recruitment-related purposes only within the CK Hutchison Group of companies. The personal data of unsuccessful applicants will be destroyed after the recruitment exercise pursuant to the requirements of the Personal Data (Privacy) Ordinance in Hong Kong.", "employment_types": ["Full Time", "Permanent"], "selling_points": [], "locations": ["Tsing Yi"], "categories": ["Sales, CS & Business Devpt", "Business Development", "Engineering", "Telecommunication / Wireless / Radio", "Account Servicing"], "post_time": "2022-01-14T11:14:59Z", "salary": {"currency": null, "max": null, "min": null, "period": "monthly", "term": null}, "salary_visible": false, "title_keywords": ["account manager", "sales"], "responsibilities": [], "requirements": {"degrees": ["diploma or above"], "majors": ["related disciplines", "business"], "languages": ["english", "chinese"], "language_level": ["good command"], "hard_skills": ["business management"], "soft_skills": ["self-motivated", "proactive", "comprehensive", "communication and interpersonal skills", "energetic"], "languages_combined": [{"language": "english", "language_level": ["good command"]}, {"language": "chinese", "language_level": ["good command"]}]}, "experience_required": {"duration": ["2 years"], "field": []}}, {"job_id": "100003009039183", "location_code": "hk", "company": "PCCW Global Limited", "job_title": "DevOps Engineer", "description": "Key Responsibilities\n\nInteract with users globally to understand the business requirements and design adequate IT solutions\nDesign and develop high quality, robust and scalable in-house systems, perform application tuning and offer UAT support\nPrepare business and technical documentation on IT solutions and design\nProvide application training and technical support to users\nSupport purchased applications and coordinate with vendor support team\nAssist to evaluate open-source or vendor software solutions and do Proof-of-Concept to verify applicability when needed\nAssist to develop ad-hoc reports\n\nPerson Specifications\n\nDegree holder in Information Technology, Computer Science or related disciplines\nAround 4 years of hands-on experience in system design and software/system\u00a0 development, such as J2EE, Spring, Hibernate, JMS, JUnit, JBoss, ActiveMQ, Maven, Git, Linux, RESTful API, Swagger, JSON, OAuth, Common web frameworks (AngularJS, ReactJS, HTML5, CSS3, JQuery, PHP, Struts), Relational database (MySQL, schema design)\nStrong ability to design and implement pragmatic solutions according to complex business requirements\nIn-depth knowledge of object-oriented design, SOLID principles, distributed system design and software design patterns\nPrevious exposure in SOA, Microservices or using API Management tools\nExperience in using Cloud platform (e.g. Azure, AWS, GCP)\nExperience in using container technologies (e.g. Kubernetes, Docker) is an advantage\nExperience in Agile/Scrum development methodology is a plus\nStrong analytical and problem solving skills, self-motivated and a good team player\nEffective oral, written, and interpersonal communication skills in both English and Chinese", "employment_types": ["Full Time"], "selling_points": [], "locations": ["Wan Chai"], "categories": ["Engineering", "Telecommunication / Wireless / Radio"], "post_time": "2022-01-11T08:56:53Z", "salary": {"currency": null, "max": null, "min": null, "period": "monthly", "term": null}, "salary_visible": false, "title_keywords": ["engineer"], "responsibilities": ["ad-hoc", "management", "uat", "software", "technical support", "systems", "quality", "design and develop", "design", "coordinate with", "evaluate", "develop", "communication", "specifications", "reports", "system design", "database", "documentation"], "requirements": {"degrees": ["degree holder"], "majors": ["related disciplines", "computer science", "information technology"], "languages": ["english", "chinese"], "language_level": [], "hard_skills": ["plus", "azure", "agile", "web", "jquery", "vendor", "git", "microservices", "restful api", "hibernate", "struts", "aws", "container", "documentation", "linux", "php", "system design", "spring", "problem solving skills"], "soft_skills": ["communication skills", "self-motivated", "good team player", "oral", "agile", "robust", "analytical and problem solving skills", "hands-on", "interpersonal"], "languages_combined": [{"language": "english", "language_level": []}, {"language": "chinese", "language_level": []}]}, "experience_required": {"duration": ["4 years"], "field": ["development", "system design", "database", "design"]}}, {"job_id": "100003009039335", "location_code": "hk", "company": "HSBC Group", "job_title": "IDS Technical Specialist - Digital Business Services", "description": "The health and safety of our employees and candidates is very important to us. Due to the current situation related to the Novel Coronavirus (2019-nCoV), we\u2019re leveraging our digital capabilities to ensure we can continue to recruit top talent at HSBC. \u00a0As your application progresses, you may be asked to use one of our digital tools to help you through your recruitment journey.\u00a0\u00a0If so, one of our Resourcing colleagues will explain how our video-interviewing technology will be used throughout the recruitment process and will be on hand to answer any questions you might have.\n\nSome careers have more impact than others.\n\nIf you\u2019re looking for a career where you can make a real impression, join HSBC and discover how valued you\u2019ll be. Whether you want a career that could take you to the top, or simply take you in an exciting new direction, HSBC offers opportunities, support and rewards that will take you further.\n\nIT Operations manages the IT infrastructure and supporting services that are critical for HSBC employees and customers, such as cost-efficient hardware, system software, middleware and databases, data centres, voice and data networks, ATMs, desktops and other devices.\n\nThe area comprises five functions: Client Services, Enterprise Services and Architecture, Data Centre and Service Management, Relationship Management, Project Management and Risk and Administration. Collectively, these areas define and deliver HSBC\u2019s technology strategy to support the Group\u2019s goals.\n\nWe are currently seeking a high calibre professional to join our team as an IDS Technical Specialist.\n\nPrincipal Responsibilities\n\nAn SME within the Proxy Engineering Agile team, this role is critical to ensuring the designs and solutions delivered are of high quality, align with our strategies, and follow best practices. Much of the role entails providing QA/Consultancy to our customers and peers\nDesigning and delivering high quality solutions\nLead POC and recommendation of strategic solutions\nIdentify improvements to existing solutions and processes\nQA complex engineering solutions\nSupporting and providing consultancy to customers and peers\n\nRequirements\n\nProven track record of working with Proxy technologies and solutions\nAbility to understand complex policies and security controls, and design solutions to complex problems\nExperience and understanding of leading SaaS SWG solutions, and management tools\nGood communication skills, and ability to communicate to different audiences and stakeholders\nExperience working in an agile environment, and familiarity with automation tools and orchestration\nUnderstanding of scripting languages\n\nYou\u2019ll achieve more when you join HSBC.\u00a0\nhttp://www.hsbc.com/careers\n\nHSBC is committed to building a culture where all employees are valued, respected and opinions count. We take pride in providing a workplace that fosters continuous professional development, flexible working and opportunities to grow within an inclusive and diverse environment. Personal data held by the Bank relating to employment applications will be used in accordance with our Privacy Statement, which is available on our website.\n\nIssued by The Hongkong and Shanghai Banking Corporation Limited.", "employment_types": ["Full Time"], "selling_points": ["One of the world\u2019s leading international banks", "Excellent Career Progression", "Senior Management Opportunity"], "locations": ["Tseung Kwan O"], "categories": ["Engineering", "Telecommunication / Wireless / Radio", "Information Technology (IT)"], "post_time": "2022-01-11T09:26:31Z", "salary": {"currency": null, "max": null, "min": null, "period": "monthly", "term": null}, "salary_visible": false, "title_keywords": ["technical specialist"], "responsibilities": ["sme", "quality", "proxy", "designing"], "requirements": {"degrees": [], "majors": [], "languages": [], "language_level": [], "hard_skills": ["agile"], "soft_skills": ["flexible", "communication skills", "agile", "committed", "diverse"], "languages_combined": []}, "experience_required": {"duration": [], "field": ["management"]}}, {"job_id": "100003009034764", "location_code": "hk", "company": "APT Satellite Company Limited", "job_title": "Engineer (IDC- Business Operation Engineer/ Assistant Business Operation Engineer)", "description": "Responsibilities:\n\nParticipate in daily operation in SAC (Satellite Access Center) to provide technical Support for satellite transponder service on a 24/7 basis.\nMonitor and analysis satellite payload data and identify anomalies on the transponder and perform preliminary troubleshooting for the interference\nConduct service line-up test with customers\nWork closely with Communication Engineer Team to provide highest service availably and quality to customers \u00a0\nMonitor and maintain the communication equipment in good condition\n\nRequirements:\n\nBachelor degree and major in Communication Engineering, Electronic engineering is preferred but not limited\nFundamental Knowledge in wireless communication, cellular base station can be bonus\nSelf-motivated and great sense of responsibility\nStrong problem solving skills and comfortable for multitasking\nGood communication and interpersonal skills\nFluency in both spoken and written English, mandarin is preferred\nFresh graduates will also be considered\nShift duty is required\nBenefits:\n\nCompetitive Compensation Package\nShift Allowance and Meal Allowance\nDouble Pay and Discretionary Bonus\nMedical Scheme, Dental Benefits and Additional Leave\nSalary Review and Development Opportunity", "employment_types": ["Full Time"], "selling_points": ["Telecommunication engineering", "Competitive compensation package", "Comfortable work environment"], "locations": ["Tai Po Area"], "categories": ["Engineering", "Telecommunication / Wireless / Radio"], "post_time": "2022-01-10T04:17:49Z", "salary": {"currency": null, "max": null, "min": null, "period": null, "term": null}, "salary_visible": false, "title_keywords": ["engineer", "assistant"], "responsibilities": ["data", "technical support", "analysis", "monitor", "daily operation", "troubleshooting", "quality", "communication", "maintain"], "requirements": {"degrees": ["degree", "bachelor"], "majors": ["engineering"], "languages": ["english", "mandarin"], "language_level": ["fluency"], "hard_skills": ["problem solving skills"], "soft_skills": ["self-motivated", "sense of responsibility", "communication", "communication and interpersonal skills", "problem solving skills"], "languages_combined": [{"language": "english", "language_level": ["fluency"]}, {"language": "mandarin", "language_level": ["fluency"]}]}, "experience_required": {"duration": [], "field": []}}, {"job_id": "100003009037678", "location_code": "hk", "company": "China Telecom Global Limited", "job_title": "Part-time Intern", "description": "Responsibilities:\n\nAssist in producing different business documents, including but not limit to solution, quotation, agreement, proposal\nPerform business analysis and generate report\nTake part in product management process and provide support to the internal team\nCollect market intelligence\nMaintain system record and database to ensure accuracy of data management\nAssist in the daily operational tasks, reporting and meeting arrangement\nProvide other clerical and administrative support to the department\n\nRequirements:\n\nUndergraduate students studying\u00a0Business, Telecommunications, IT, Engineering or related disciplines\nStrong in Excel and Power Point\nStrong sense of responsibility and able to work independently\nGood command of both spoken and written English and Chinese, including Cantonese and Mandarin\nWork from 9:00am - 5:30pm, 2-3 days a week\n\n\n\nWe offer 5 days work, competitive salary package and attractive career development opportunities to the right candidate.\n\nInterested parties please email your full resume with your current & expected salary to us.\n\nApplicants not invited for interview within 3 months may assume their applications unsuccessful.\n\nIf you are interested in other job opportunities, please check with below career website.\n\nPersonal data collected would be used for recruitment purpose only.", "employment_types": ["Part Time", "Internship"], "selling_points": ["Assist in different business documents", "Opportunity for graduate job & further development", "Work from 9:00am - 5:30pm, 2-3 days a week"], "locations": ["Wan Chai"], "categories": ["Engineering", "Telecommunication / Wireless / Radio", "Information Technology (IT)", "Support"], "post_time": "2022-01-11T03:28:38Z", "salary": {"currency": null, "max": null, "min": null, "period": "monthly", "term": null}, "salary_visible": false, "title_keywords": ["intern"], "responsibilities": ["reporting", "management", "provide support", "data", "administrative support", "operational tasks", "quotation", "maintain", "database", "business analysis", "report"], "requirements": {"degrees": [], "majors": [], "languages": ["cantonese", "english", "chinese", "mandarin"], "language_level": ["good command"], "hard_skills": ["power point", "excel"], "soft_skills": ["work independently", "sense of responsibility"], "languages_combined": [{"language": "cantonese", "language_level": ["good command"]}, {"language": "english", "language_level": ["good command"]}, {"language": "chinese", "language_level": ["good command"]}, {"language": "mandarin", "language_level": ["good command"]}]}, "experience_required": {"duration": [], "field": []}}, {"job_id": "100003009029255", "location_code": "hk", "company": "Chubb Hong Kong Limited", "job_title": "Project Engineer / Asst. Engineer (Electronic Security / ELV System)", "description": "Major Responsibilities\n\n\n\nTo plan installation activities of electronic security system and ELV system, prepare master installation programme\nTo monitor the work progress and coordinate the work with sub-contractors in order to meet the project delivery schedule\nTo plan, prepare and update related drawings based on project specifications, prepare design manuals and contract related documents\nTo finalize product specifications with customers and plan material delivery schedule\nTo join site meetings with related external and internal parties\nTo capture variation works to complete system design which are not covered in the contract\nTo prepare training materials for system handover\nAny other job duties assigned by the supervisors\n\nQualifications\nHigh Diploma / Associate Degree or above in Electronics / Electrical Engineering or Computer Engineering\nAt least 4 years' experience in project co-ordination and installation of ELV systems\nHolder of valid Security Personnel Permit Cat. D (SPP-D)\nHolder of Electrical Worker License (A), proficiency in MS Application and AUTOCAD software application are preferred\nGood communication\u00a0 and\u00a0 project coordination skills\nProactive, cooperative, drive to success and able to work independently and under pressure\nGood command of both written and spoken English and Chinese\u00a0\nCandidate with less expereince will be considered as Assistant Engineer, whereas with more experience will be considered as Senior Engineer\n\n\n\nAttractive compensation and benefits packages will be offered to the right candidate. Interested parties, please click \"Apply Now\" & send your application together with a full resume stating your present and expected salary and date of availability to us\u00a0; or\n\n\n\nBy mail\nThe Talent Acquisition Manager, Chubb Hong Kong Limited, 10/F, Habourside HQ, 8 Lam Chak Street, Kowloon Bay, Kowloon ; or\n\nBy fax\n2764 3098\n\nYou may also contact us by our recruitment hotline at 5362 3810 (WhatsApp welcomed) in case you have any enquiries.\n\nPersonal data provided in your application will be kept in the strictest confidence. It will only be used for employment-related purposes by any entity within our Group. Applicants not notified within 1 month will be considered as unsuccessful. Unsuccessful application may be kept for another 6 months for new openings or consideration by another entity within our Group before properly shredded.\n\nSecurity Licence No. : 0961", "employment_types": ["Full Time", "Contract"], "selling_points": ["***Sign-on Bonus will be offered***", "ELV system design and project management", "HD or above in Electronic Eng+4 yrs' related exp"], "locations": ["Kowloon Bay"], "categories": ["Engineering", "Electrical / Electronics", "Engineering Project Management", "Telecommunication / Wireless / Radio"], "post_time": "2022-01-09T16:25:45Z", "salary": {"currency": "HKD", "max": 34999, "min": 25000, "period": "monthly", "term": null}, "salary_visible": true, "title_keywords": ["asst. engineer", "project engineer"], "responsibilities": ["installation", "software", "site meetings", "project coordination", "related documents", "systems", "monitor", "design", "drawings", "coordinate", "delivery schedule", "communication", "specifications", "system design", "plan", "internal parties"], "requirements": {"degrees": ["high diploma", "degree or above", "master"], "majors": ["computer engineering", "electrical engineering"], "languages": ["english", "chinese"], "language_level": ["good command"], "hard_skills": ["ms application", "security personnel permit", "system design", "elv system", "autocad"], "soft_skills": ["work independently", "under pressure", "coordination skills", "cooperative", "communication", "proactive"], "languages_combined": [{"language": "english", "language_level": ["good command"]}, {"language": "chinese", "language_level": ["good command"]}]}, "experience_required": {"duration": ["at least 4 years"], "field": ["installation", "senior engineer"]}}, {"job_id": "100003009033851", "location_code": "hk", "company": "HKT", "job_title": "Unit Manager", "description": "Your role\n\nLead a team in Field Services Works Control to arrange field technician manpower resources for daily installation / restoration services field jobs\nPrepare monthly reports and regular performance analysis for management\u2019s\u00a0 review\nHandle escalation cases arise from both internal & external customers\nAssist and participate in defining user requirements for system enhancement and workflow development\nPlay an active role to drive for digital transformation to improve team work efficiency and reduce operating costs\nLiaise across departments to solve daily issues and smoothen the operation\nRecommend improvement actions to Manager\n\nTo succeed in this role\n\nDegree holders in Electronic Engineering, Information Engineering, Telecommunications or related disciplines with 3-5 years\u2019 working experience in related field.\nGood knowledge in voice & broadband services/products, field working procedures and operation systems.\nWith knowledge and experience of a formal project management methodology will be an advantage.\nInitiative and good interpersonal and communication skills with customer-oriented mindset.\nAble to work independently and proactive.\nGood Digital Transformation\u00a0knowledge in related work.\u00a0\nExperience in customer management is preferable.", "employment_types": ["Full Time"], "selling_points": [], "locations": ["Lai Chi Kok"], "categories": ["Engineering", "Electrical / Electronics", "Engineering Project Management", "Telecommunication / Wireless / Radio"], "post_time": "2022-01-10T01:56:42Z", "salary": {"currency": null, "max": null, "min": null, "period": "monthly", "term": null}, "salary_visible": false, "title_keywords": ["manager"], "responsibilities": ["liaise", "installation", "control", "management", "monthly reports", "analysis", "review", "procedures", "systems", "communication", "lead a team", "project management", "costs"], "requirements": {"degrees": ["degree"], "majors": ["related disciplines", "engineering"], "languages": [], "language_level": [], "hard_skills": ["project management", "analysis"], "soft_skills": ["communication skills", "work independently", "proactive", "interpersonal", "project management", "customer-oriented", "active", "initiative"], "languages_combined": []}, "experience_required": {"duration": ["3-5 years"], "field": ["management", "engineering", "related", "project management", "telecommunications"]}}, {"job_id": "100003009033846", "location_code": "hk", "company": "HKT", "job_title": "Assistant Project Manager", "description": "Your role\n\nTo carry out Outside Plant project studies mainly on Fibre Cable.\nTo prepare fibre cabling work items contracts agreement and specifications.\nTo review specifications and company drawings relating to Fibre Cable Product & relevant T&C items.\nTo prepare concise technical evaluation criteria for tender exercise.\nTo support Mega-size project by developing an efficient and practical\u00a0timeline\u00a0for\u00a0project\u00a0completion.\nTo monitor the customer project progress and allocate adequate resource for performing site supervision and inspection under project requirement.\nTo analysis and optimise the dark fibre link performance in order \u00a0to fully comply with customer's requirement.\nTo undergo samples evaluation for ascertaining their compliance with specification.\nTo liaise and coordinate between all peers, internal department, company contractor and suppliers for the standardisation of working procedures and fibre facilities to get the job done.\nTo communicate with Outside Plant Services sections, Strategic Purchasing Section and Stores Section for securing the supply with effective inventory control.\n\nTo succeed in this\u00a0role\n\nForm 5 standard or equivalent plus 5 years\u2019 work experience in telecommunications field, OR Certificate in Electrical / Electronic / Civil Engineering or equivalent disciplines plus 3 years\u2019 work experience, OR Degree/ Higher Diploma in Electrical / Electronic / Civil Engineering or equivalent disciplines\u00a0 plus 3 years\u2019 work experience in telecommunications field.\nGood knowledge and practices of computer operations.\nGood command of spoken / written English and Chinese.\nGood interpersonal, problem-solving, contractor and project management skills.\nSelf-motivated and able to take up challenge.", "employment_types": ["Full Time"], "selling_points": [], "locations": ["Lai Chi Kok"], "categories": ["Engineering", "Engineering Project Management", "Telecommunication / Wireless / Radio", "Others"], "post_time": "2022-01-10T01:56:17Z", "salary": {"currency": null, "max": null, "min": null, "period": "monthly", "term": null}, "salary_visible": false, "title_keywords": ["assistant project manager"], "responsibilities": ["liaise", "operations", "drawings", "evaluation", "review specifications", "contracts", "compliance", "monitor", "developing", "project progress", "tender", "procedures", "inspection", "specifications", "inventory control", "communicate with", "site supervision", "analysis", "coordinate", "project management"], "requirements": {"degrees": ["diploma", "certificate", "form 5", "degree"], "majors": ["civil engineering"], "languages": ["english", "chinese"], "language_level": ["good command"], "hard_skills": ["problem-solving", "project management", "analysis", "plus"], "soft_skills": ["efficient", "self-motivated", "project management skills", "problem-solving", "interpersonal"], "languages_combined": [{"language": "english", "language_level": ["good command"]}, {"language": "chinese", "language_level": ["good command"]}]}, "experience_required": {"duration": ["5 years", "3 years"], "field": ["telecommunications", "engineering"]}}]