[{"job_id": "100003009048264", "location_code": "hk", "company": "Q P Group Holdings Limited", "job_title": "Environmental Protection Officer/ Manager", "description": "Job Highlight\n\n5 years\u2019 experience in environmental compliance\nFamiliar with ISO9001/ISO45001/ISO14001/ISO14064 GHG Emission\n\nJob Responsibilities:\n\nDevelop and implement the Group\u2019s environmental compliance; strategies and plan to achieve our sustainability goals.\nTo build and drive environmental compliance mindset of employees\u2019 behavior to achieve green environment in factories.\nSet up road map and lead the environmental protection team on sustainability of green manufacturing.\nDeploy and implement the environmental policies and guidelines, set up KPI indicators and control mechanism in line with international standards and statutory requirements.\nProvide guidance to the environmental management of factories and organize regular meetings in reviewing the progress of compliance.\nMonitor environmental safety implementation issues, oversee improvement progress on corrective action plans and communicate with relevant internal / external parties for the results achieved. Organize regular meetings about environmental matters.\nTrack and evaluate wastes discharge mechanism effectiveness, identify alternatives to drive reduction of discharge of chemical waste and GHG, to eliminate any potential environmental hazards and pollution.\nLead and Facilitate factories on 3rd party certification on relevant accreditation of environmental compliance scheme in accordance with statutory requirements / regulations and international standards.\nPrevent, reduce or eliminate hazards that may affect the health of employees.\nSet up crisis management policies and procedures, and site crisis management team to analyze and mitigate risks and strengthen the capability of all sites to deal with crisis.\nOrganize social and environmental engagement events both within and outside the group.\nPrepare the group Environmental report required by the listing rule of the Hong Kong stock Exchange.\n\nRequirements:\n\nUniversity degree or above in environment.\nAt least 5 years\u2019 experience in environmental compliance and health and safety work experience in sizable manufacturing enterprises.\nFamiliar with the statutory requirements and international on safety and environmental protection as well as related measurement and production processes.\nFamiliar with standards and audit requirements of ISO9001/ISO45001/ISO14001/ISO14064 or other related systems.\nStrong leadership and management skills required.\nSound project management, analytical and problem solving skills.\nProactive and tactful in communication.\nProficiency in computer software, and in both spoken and written English and Chinese, including Mandarin.\nFrequent travel to support overseas operation is required.\nCandidate with more experience will be considered as\u00a0Environmental Protection Manager\u00a0\n\nApplication:\n\nPlease send your CV, recent salary & expected salary in word file to hkghr @ qpp.com\n\n*** All personal information collected will be kept for employment related purposes only ***", "employment_types": ["Full Time", "Permanent"], "selling_points": ["5 years\u2019 experience in environmental compliance", "Familiar with ISO GHG Emission", "Frequent travel is required"], "locations": ["Others - China"], "categories": ["Sciences, Lab, R&D", "Energy / Natural Resources / Oil & Gas", "Environmental Science / Waste Management", "Public / Civil", "Others"], "post_time": "2022-01-15T03:49:53Z", "salary": {"currency": null, "max": null, "min": null, "period": "monthly", "term": null}, "salary_visible": false, "title_keywords": ["officer", "manager"], "responsibilities": ["regulations", "external parties", "statutory requirements", "plan", "deploy", "plans", "listing", "control", "compliance", "monitor", "implementation", "develop", "crisis management", "report", "management", "procedures", "provide guidance", "communicate with", "guidelines", "policies", "evaluate"], "requirements": {"degrees": ["degree or above"], "majors": [], "languages": ["english", "chinese", "mandarin"], "language_level": ["proficiency"], "hard_skills": ["project management", "problem solving skills", "word"], "soft_skills": ["communication", "project management", "analytical and problem solving skills", "tactful", "proactive", "leadership"], "languages_combined": [{"language": "english", "language_level": ["proficiency"]}, {"language": "chinese", "language_level": ["proficiency"]}, {"language": "mandarin", "language_level": ["proficiency"]}]}, "experience_required": {"duration": ["at least 5 years"], "field": ["manufacturing", "compliance", "environmental"]}}, {"job_id": "100003009047129", "location_code": "hk", "company": "Arup", "job_title": "Senior Renewable Energy Specialist", "description": "Following several recent successes in the region, we are expanding our energy business through targeted recruitment of capable and independent individuals with a background in energy. The candidate should have an out-going personality with drive and ambition to effectively promote and support the company\u2019s global energy business skills. The successful candidates will be based in our Hong Kong office but will be expected to travel.\nRelevant engineering related degree holder or equivalent\nPossesses or working towards professional membership of a recognised institution in\u00a0 the Civil/Mechanical/Industrial field\nAt least 8 years of post graduation experience and track record in delivering renewable and low carbon energy projects\nWith knowledge of technologies, including wind, solar photovoltaic, biomass, Combined Heat & Power (CHP) and geothermal in the East Asia region to complement the existing team\nFluency in both written and spoken English\nCandidates with less experience will be considered for the position of Renewable Energy Specialist.\n\nWe offer a competitive remuneration package commensurate with qualifications and experience to the right candidate including Global Profit Share scheme, additional fringe benefits of maternity/paternity leave and long-term career development opportunities.\n\nFor interested applicants, please click \"Apply Now\" to submit your online application.\n\nTo explore more job opportunities in Arup, please visit our website at http://www.arup.com/Careers/Experienced_Hires/ApplyForAJob\n\nPersonal data collected will be used for recruitment purpose only. Applicants not contacted within 8 weeks may consider their applications unsuccessful.", "employment_types": ["Full Time", "Permanent"], "selling_points": [], "locations": ["Kowloon City"], "categories": ["Sciences, Lab, R&D", "Energy / Natural Resources / Oil & Gas", "Building & Construction", "Civil / Structural", "Engineering", "Engineering Project Management"], "post_time": "2022-01-14T02:24:24Z", "salary": {"currency": null, "max": null, "min": null, "period": null, "term": null}, "salary_visible": false, "title_keywords": ["specialist"], "responsibilities": ["personal data", "recruitment", "website", "career development"], "requirements": {"degrees": ["degree holder"], "majors": ["engineering"], "languages": ["english"], "language_level": ["fluency"], "hard_skills": ["scheme"], "soft_skills": ["independent", "capable"], "languages_combined": [{"language": "english", "language_level": ["fluency"]}]}, "experience_required": {"duration": ["at least 8 years"], "field": ["development"]}}, {"job_id": "100003009045393", "location_code": "hk", "company": "Morgan Philips Hong Kong Limited", "job_title": "ESG Manager/ Assistant ESG Manager", "description": "My client is a well known Sportswear brand with strong presence globally. As of business expansion, they are now recruiting an ESG Manager to join their team.\u00a0\n\n\nManage an organization's sustainability programs.\nConduct research and analysis used to develop corporate sustainability strategies to ensure that business practices, products, and services are environmentally friendly and compliant with government rules and regulations.\nHelp to design the sustainability projects and initiatives required to achieve the group's ESG targets\nCollaborate with other parties to implement ESG related projects and initiatives\nPromote and explain the organization's sustainability philosophy to internal and external parties\nLead the preparation of the group's annual ESG report to fulfil the Hong Kong stock exchange requirement\nAssist in responding to various ESG ratings (e.g., MSCI, Sustainalytics, DJSI, etc.)\nEnsure that projects, milestones, and goals are met and adhering to approved budgets", "employment_types": ["Full Time"], "selling_points": ["Leading Sportswear Brand", "Project Management", "HK Listed Company"], "locations": ["Not Specified"], "categories": ["Sciences, Lab, R&D", "Energy / Natural Resources / Oil & Gas", "Environmental Science / Waste Management", "Manufacturing", "Manufacturing Management"], "post_time": "2022-01-13T07:45:36Z", "salary": {"currency": null, "max": null, "min": null, "period": "monthly", "term": null}, "salary_visible": false, "title_keywords": ["manager", "assistant"], "responsibilities": ["regulations", "collaborate with", "budgets", "analysis", "internal and external parties", "design", "develop", "conduct research", "report"], "requirements": {"degrees": [], "majors": [], "languages": [], "language_level": [], "hard_skills": ["analysis", "exchange"], "soft_skills": ["friendly"], "languages_combined": []}, "experience_required": {"duration": [], "field": []}}, {"job_id": "100003009047410", "location_code": "hk", "company": "Arup", "job_title": "Engineer (Consultant)/ Project Engineer (Consultant)/ Senior Engineer (Consultant) \u2013 Sustainability", "description": "Responsibilities:\n\nUse practical engineering knowledge to develop sustainable and innovative building and masterplan design\nUndertake design on sustainable building, Building Physics, Environmentally Sustainable Design (ESD), district energy and renewable energy engineering projects\nWork on sustainability policy development and analysis, carbon management, renewables and climate services\nContribute to the development of integrated design with in-house architectural, MEP and facades teams, specifically in the areas of green, resilient and smart design\nQualifications & Experience required:\n\nDegree in Electrical, Mechanical, Building Services, Energy Engineering, Architecture or related disciplines\nCorporate membership of relevant professional institution(s)\nFresh chartered for the position of Consultant or Engineer; at least 1 year of post chartered experience for the position of Project Consultant or Engineer; at least 3 years of post chartered experience for the position of Senior Consultant or Engineer\nRelevant industry experience in climate services, district energy system, sustainable building services design, energy efficient system design, ESD or Building Physics\nDemonstrated experience with design of sustainable buildings or masterplans\nStrong interest in green economy, environmental and sustainability issues, with a true passion and growth mindset in making positive impact on sustainability\nBe able to undertake strong project and technical analysis, reporting and presentation\nBe adaptable and able to work independently coupled with strong presentation, client management and interpersonal skills\nProficient in written and spoken English and Chinese. Good command of Putonghua will be an advantage\n\n\n\nWe offer a competitive remuneration package commensurate with qualifications and experience to the right candidate including Global Profit Share scheme, additional fringe benefits of maternity/paternity leave and long-term career development opportunities.\u00a0\n\nFor interested applicants, please click \u201cApply Now\" to submit your online application.\n\n\nTo explore more job opportunities in Arup, please visit our website at http://www.arup.com/Careers/Experienced_Hires/ApplyForAJob\n\u00a0\nPersonal data collected will be used for recruitment purpose only. Applicants not contacted within 8 weeks may consider their applications unsuccessful.", "employment_types": ["Full Time", "Permanent"], "selling_points": [], "locations": ["Kowloon City Area"], "categories": ["Sciences, Lab, R&D", "Energy / Natural Resources / Oil & Gas", "Building & Construction", "Building / Construction / QS", "Engineering", "Others"], "post_time": "2022-01-14T03:01:44Z", "salary": {"currency": null, "max": null, "min": null, "period": null, "term": null}, "salary_visible": false, "title_keywords": ["senior engineer", "engineer", "consultant", "project engineer"], "responsibilities": ["website", "design", "personal data", "building services design", "environmentally sustainable design", "esd", "climate services", "teams", "develop", "policy development", "architecture", "reporting", "management", "masterplan design", "career development", "carbon management", "analysis", "system design", "recruitment"], "requirements": {"degrees": ["degree"], "majors": ["related disciplines", "building services", "engineering", "architecture"], "languages": ["putonghua", "english", "chinese"], "language_level": ["advantage", "good command", "proficient"], "hard_skills": ["analysis", "system design", "technical analysis", "scheme"], "soft_skills": ["efficient", "work independently", "adaptable", "interpersonal skills", "innovative", "presentation", "positive"], "languages_combined": [{"language": "putonghua", "language_level": ["advantage", "good command"]}, {"language": "english", "language_level": ["proficient"]}, {"language": "chinese", "language_level": ["proficient"]}]}, "experience_required": {"duration": ["at least 3 years", "at least 1 year"], "field": ["development", "system design", "building services", "design"]}}, {"job_id": "100003009044017", "location_code": "hk", "company": "Tricor Staffing Solutions Limited", "job_title": "Conservation Assistant (Museum) Ref No: CT56MA", "description": "Job Descriptions\n\nOur client is working in the cultural sector. They are now looking for new candidates that could support their further operations.\n\nResponsibilities\n\nAssist in preservation and conservation of museum collections\nAssist in exhibit mounting and dismounting\nHandle data input and digitization of museum\nAssist in delivery of education activities and extension programs\nProvide conservation services and prepare relevant reports\n\nRequirements\n\nBachelor Holder in Conservation / Applied Chemistry / Chemistry / Material Science / Materials Engineering from Hong Kong University or equivalent\nLevel 5 or above in English Language (CRE Level 2)\nLevel 4 or above in Chinese Language (CRE Level 1)\nGood command in both written and spoken English and Chinese\nCandidates with working experience in the art field / cultural heritage conservation would be considered first\nFresh graduates are also welcomed\nProficient in MS Office applications and have good English and Chinese typing skills\n\nApplicants should click \u201cAPPLY NOW\u201d to apply the job.\u00a0 Please quote the ref. \u2018Conservation Assistant (Museum) Ref No: CT56MA\u2019 on your application.\u00a0\u00a0 For enquiries, please contact on +852 55477049 (WhatsApp only)\n\nPersonal data provided by applicants will be used strictly in accordance with the employer\u2019s personal data policies, a copy of which will be provided immediately upon request.", "employment_types": ["Full Time", "Contract"], "selling_points": ["Working hours: 9:00am \u2013 6:00pm", "5 days of work", "Conservation"], "locations": ["Tsim Sha Tsui"], "categories": ["Sciences, Lab, R&D", "Chemical", "Energy / Natural Resources / Oil & Gas", "Research & Development (R&D)"], "post_time": "2022-01-13T02:47:45Z", "salary": {"currency": null, "max": null, "min": null, "period": null, "term": null}, "salary_visible": false, "title_keywords": ["assistant"], "responsibilities": ["operations", "relevant reports", "data input"], "requirements": {"degrees": ["bachelor"], "majors": ["science", "chemistry", "engineering"], "languages": ["english", "chinese"], "language_level": ["good", "good command", "proficient"], "hard_skills": ["whatsapp", "no", "typing", "ms office"], "soft_skills": [], "languages_combined": [{"language": "english", "language_level": ["good", "good command", "proficient"]}, {"language": "chinese", "language_level": ["good", "good command", "proficient"]}]}, "experience_required": {"duration": [], "field": []}}, {"job_id": "100003009042736", "location_code": "hk", "company": "ECO Aviation Fuel Services Limited", "job_title": "Operations Officer", "description": "About the position\n\nThe Operations Officer works closely with team members from multiple disciplines and manages information for routine operations, projects, and knowledge transfer. He / she shall:\n\nGather technical information from subject matter experts.\nComprehend specifications and industry standards and communicate the information which can engage end-users.\nCreate working instructions and procedures with aligned consistency in terminology and style.\nGenerate monthly operations report for management review.\nPerform internal review and make recommendations to resolve problems or improve performance.\nIntegrate internal and external resources to accomplish project objectives assigned by management\n\nThe Operations Officer reports directly to Operations Manager.\n\nAbout you\n\nEducation & skills:\n\nDegree in relevant to communications, science or engineering background preferred\nProficiency in English and Chinese literacy and conversations\nTechnical acumen\n\nExperience preferable:\n\nExperience with highly-regulated industries, such as dangerous goods, aviation, maritime etc.\nExperience in technical publication, quality assurance, project management\n\nQualities we look for:\n\nDetail-oriented\nSelf-organized\nDiplomatic\nInquisitive\nCreative\n\nIf you find yourself fit for the role, we would like to meet you and look forward to receiving your resume.", "employment_types": ["Permanent"], "selling_points": ["Operations", "Projects", "Procedures"], "locations": ["Tuen Mun Area"], "categories": ["Sciences, Lab, R&D", "Energy / Natural Resources / Oil & Gas", "Others", "Others"], "post_time": "2022-01-12T08:34:59Z", "salary": {"currency": null, "max": null, "min": null, "period": "monthly", "term": null}, "salary_visible": false, "title_keywords": ["operations officer"], "responsibilities": ["make recommendations", "management", "operations", "review", "procedures", "quality", "project management", "specifications", "reports", "publication", "management review", "report"], "requirements": {"degrees": ["degree"], "majors": ["science", "engineering", "communications"], "languages": ["english", "chinese"], "language_level": ["proficiency"], "hard_skills": ["make", "project management", "acumen"], "soft_skills": ["make recommendations", "organized", "diplomatic", "detail-oriented", "project management", "creative"], "languages_combined": [{"language": "english", "language_level": ["proficiency"]}, {"language": "chinese", "language_level": ["proficiency"]}]}, "experience_required": {"duration": [], "field": ["project management", "quality assurance"]}}, {"job_id": "100003009006416", "location_code": "hk", "company": "Mott MacDonald Hong Kong Limited", "job_title": "Net Zero Carbon Advisor", "description": "Reporting to Principal Environmental Consultant, you will be responsible for planning, developing and managing net zero carbon related works.\n\nYour Next Challenge\n\nSupport the Sustainability Team and the wider business to establish and shape the development and success of our Net Zero Advisory business by contributing to the strategy, implementation plans and build out of key activities.\nIdentify target and emerging clients, and creating winning proposals to seed new business opportunities\nContribute to growing our business with respect to Net Zero advisory services, ultimately becoming a \u2018trusted advisor\u2019 to our existing and future client base\nIdentify and realise opportunities for application of Mott MacDonald\u2019s Moata Carbon Portal, and the deployment of other digital tools and services to assist clients in reducing their carbon footprint\nContribute to the creation of Net Zero advisory marketing and communication initiatives, campaigns and products, including thought leadership and events\nSupport in building internal alignment, engagement and support for the Net Zero Initiative and acting as the local interface in coordinating with the region Net Zero Advisors, sharing knowledge, learnings and success, and leveraging experience across the Group\nConduct benchmarking and advising clients on strategy, targets, priorities, pathways, road mapping and solutions associated with Net Zero objectives\nDriving high levels of technical quality delivery of Net Zero advisory services, ensuring the production of deliverables to agreed timelines and within budget\n\nWhat You'll Need\n\n\u00a0Bachelor Degree in Environmental Engineering, Building Services or related discipline\n\u00a0At least 7 years\u2019 experience working in corporate sustainability and environment roles\n\u00a0Knowledge of key methodologies associated with energy and carbon reduction in the built environment, e.g. carbon foot printing, energy assessments, life cycle assessment, carbon management and broader sustainability such as the PAS2080, the UN SDGs, etc.\n\u00a0Policy development and/or research experience in low and net zero carbon themes\n\u00a0Experience in client engagement with an ability to establish strong client relationships\n\u00a0An attitude and desire to help clients on their decarbonisation journey and progress towards Net Zero\n\u00a0Bring a range of report writing, and visual and verbal presentation techniques\n\u00a0Have a keen interest and enthusiasm for sustainability in buildings and infrastructure.\n\u00a0Be a versatile, quick thinker and show willingness and ability to pick up new concepts quickly.\n\u00a0Have excellent verbal and written communication skills.\n\u00a0Agile and collaborative, leveraging expertise from others when needed.\n\u00a0Enjoy a client-facing role with proven track record in managing projects and clients.\n\nWe offer competitive remuneration package including\u00a013th month salary, MPF plan\u00a0and\u00a0group medical insurance for dependents.\n\nInterested parties, please click 'Apply now' to submit your application with full resume including your current and expected salary, or send your full resume to recruitment.MMHK @mottmac.com .\n\nTo explore more opportunities with us, please visit www.mottmac.com/careers.\n\nAll personal data collected will be treated in strict confidence and be used for recruitment purpose only.\u00a0\n\nWe are an equal opportunity employer and value diversity at our company. We do not discriminate, and take positive steps to create an inclusive culture.", "employment_types": ["Full Time", "Permanent"], "selling_points": ["Contribute to the strategy, implementation plans", "7 years\u2019 experience in corporate sustainability", "5 days work, 13th month salary, wellness program"], "locations": ["Ngau Tau Kok"], "categories": ["Sciences, Lab, R&D", "Energy / Natural Resources / Oil & Gas", "Environmental Science / Waste Management", "Others"], "post_time": "2022-01-09T16:25:36Z", "salary": {"currency": null, "max": null, "min": null, "period": "monthly", "term": null}, "salary_visible": false, "title_keywords": ["advisor"], "responsibilities": ["reporting", "business opportunities", "budget", "quality", "implementation", "developing", "infrastructure", "communication", "client base", "policy development", "visual", "plans", "carbon management", "report", "planning"], "requirements": {"degrees": ["degree", "bachelor"], "majors": ["environmental engineering", "building services"], "languages": [], "language_level": [], "hard_skills": ["deployment", "agile"], "soft_skills": ["communication skills", "agile", "responsible", "keen", "versatile", "collaborative", "communication", "initiative", "leadership", "presentation", "client-facing"], "languages_combined": []}, "experience_required": {"duration": ["at least 7 years"], "field": ["development", "research", "sustainability"]}}, {"job_id": "100003009054467", "location_code": "hk", "company": "Epro Telecom Services Limited", "job_title": "Museum Research Assistant (Contract/Government)", "description": "Job duty\n\nTo assist in conducting scientific research and studies on museum collection, heritage and conservation materials, preservation and conservation methodologies, environment in museums and collection store\nTo assist in conducting research for exhibitions and condition checking on the exhibits in the exhibition halls and/or in collection store\nTo provide research and conservation services as required and prepare the associated report\nTo assist with the organization of educational and extension preogrames\nTo perform any other duties as assigned by the supervisors\n\nJob requirement\n\nA bachelor's degree from a University in Hong Kong, or equivalent, majoring in one of the following subjects: Conservation, Applied Chemistry/Chemistry, Materials Science, Materials Engineering, or equivalent;\nPossess a good command of both Chinese and English and have met the language proficiency requirements of \"Level 2\" result in Use of English and \"Level l\" result in Use of Chinese in the CRE or equivalent results (refers to Note 1 and 2); fluency in Putonghua is an advantage\nPossess good knowledge in computer applications, including MS word, excel, powerpoint and Chinese word processing\nHave at least 12 months of full time work experience, with proven experience in conducting scientific research\u00a0\nWork experience in the field of art/cultural heritage conservation and operating analytical equipment is preferred.\n\nNote 1:\nGrade C or above in Use of English of the Hong\u00a0 Kong\u00a0 Advanced\u00a0 Level Examination (HKALE), or equivalent, are accepted as equivalent to Level 2 result in the UE paper of the CRE. Grade D or above in Chinese Language and Culture or Chinese Language and Litera1ure of the HKALE are accepted as equivalent to Level 1 result in the UC paper of the CRE.\n\nLevel 5 or above in English Language of the Hong Kong Diploma of Secondary Education Examination (HKDSEE) is accepted as equivalent to Level 2 in the UE paper of the CRE. Level 4 or above in Chinese Language of the HKDS EE is accepted as equivalent to Level 1 in the UC paper of the CRE.\n\nNote 2:\u00a0\nAn overall band of 6.5 or above with no subtest score below band 6\u00a0 obtained in the same sitting in the Academic Module of the International English Language Testing System (IELTS) within the two-year validity period of the test result are considered as having met the English language proficiency requirement of the post.)", "employment_types": ["Full Time", "Contract"], "selling_points": [], "locations": ["Tsim Sha Tsui"], "categories": ["Admin & HR", "Personal / Executive Assistant", "Sciences, Lab, R&D", "Energy / Natural Resources / Oil & Gas", "Environmental Science / Waste Management"], "post_time": "2022-01-17T09:40:22Z", "salary": {"currency": null, "max": null, "min": null, "period": "monthly", "term": null}, "salary_visible": false, "title_keywords": ["research assistant"], "responsibilities": ["any other duties", "checking", "testing", "computer applications", "report"], "requirements": {"degrees": ["diploma", "degree", "bachelor", "secondary education"], "majors": ["chemistry", "engineering", "materials science"], "languages": ["putonghua", "english", "chinese"], "language_level": ["proficiency", "good command", "advantage", "good", "fluency"], "hard_skills": ["excel", "no", "chinese word processing", "powerpoint", "c", "ms word"], "soft_skills": ["advanced"], "languages_combined": [{"language": "putonghua", "language_level": ["fluency", "advantage"]}, {"language": "english", "language_level": ["proficiency", "proficiency", "good command", "good"]}, {"language": "chinese", "language_level": ["proficiency", "good command", "good", "good"]}]}, "experience_required": {"duration": [], "field": ["research", "analytical"]}}, {"job_id": "100003009034749", "location_code": "hk", "company": "ATAL Building Services Engineering Limited", "job_title": "Energy Consultant \u2013 Energy Saving Solutions / Green Technology (REF: CESS/ENY)", "description": "Responsibilities:\n\nPerform pre-sales activities and suggest energy solutions to potential clients\nHandle sales and technical inquiries, client visit, solutions selling and presentations\nPrepare proposal or tendering related documents\nLiaise with inhouse tech team on product development and requirement\nConduct research to understand market trend and latest green technology\u00a0\n\nRequirements:\n\nDegree in Energy, Engineering, Building Services, Sales & Marketing or any related disciplines\u00a0\nAble to Self-learning, independent and aggressive\nStrong analytical mind with good customer service skills\nGood communication and presentation skills\nGood command of both written and spoken English and Chinese\nCandidates who have more experience may be considered as Senior Energy Consultant\n\nPlease click the\u00a0Apply Now\u00a0button to send your full resume stating relevant job reference, present and expected salary and availability.\n\nPersonal data collected will be treated in strict confidence and used for recruitment related purposes only.", "employment_types": ["Full Time", "Permanent"], "selling_points": ["Pre-sales and suggest energy solutions", "Handle tendering and solutions presentation", "Strong analytical mind with good customer services"], "locations": ["Kwun Tong"], "categories": ["Sciences, Lab, R&D", "Energy / Natural Resources / Oil & Gas", "Engineering", "Electrical / Electronics", "Sales, CS & Business Devpt", "Technical Sales / Sales Engineer"], "post_time": "2022-01-10T04:08:34Z", "salary": {"currency": null, "max": null, "min": null, "period": "monthly", "term": null}, "salary_visible": false, "title_keywords": ["consultant"], "responsibilities": ["sales activities", "related documents", "tendering", "presentations", "liaise with", "conduct research"], "requirements": {"degrees": ["degree"], "majors": ["related disciplines", "marketing", "building services", "engineering"], "languages": ["english", "chinese"], "language_level": ["good command"], "hard_skills": [], "soft_skills": ["customer service skills", "confidence", "independent", "communication", "presentation skills", "analytical mind", "learning"], "languages_combined": [{"language": "english", "language_level": ["good command"]}, {"language": "chinese", "language_level": ["good command"]}]}, "experience_required": {"duration": [], "field": []}}, {"job_id": "100003009032021", "location_code": "hk", "company": "Epro Telecom Services Limited", "job_title": "Museum Assistant (Contract/Government)", "description": "Job duty\n\nTo assist in preservation and conservation of museum collections\nTo assist in exhibit mounting and dismounting\nTo help data input, checking and digitization of museum / archival material\nTo assist in delivery of education activities and extension programmes\nTo provide conservation services as required and prepare the associated report\nTo perform any other duties as assigned by the supervisors.\n\nJob requirement\n\n\nA bachelor's degree from a University in Hong Kong, or equivalent, majoring in one of the following subjects: Conservation, Applied Chemistry/Chemistry, Materials Science, Materials Engineering, or equivalent;\nPossess a good command of both Chinese and English and have met the language proficiency requirements of \"Level 2\" result in Use of English and \"Level l\" result in Use of Chinese in the CRE or equivalent results (refers to Note 1 and 2); and\nPossess good knowledge in computer application, including MS word, excel, powerpoint and Chinese word processing.\nWork experience in the field of art/cultural heritage conservation is preferred\n\nNote 1:\nGrade C or above in Use of English of the Hong\u00a0 Kong\u00a0 Advanced\u00a0 Level Examination (HKALE), or equivalent, are accepted as equivalent to Level 2 result in the UE paper of the CRE. Grade D or above in Chinese Language and Culture or Chinese Language and Litera1ure of the HKALE are accepted as equivalent to Level 1 result in the UC paper of the CRE.\n\nLevel 5 or above in English Language of the Hong Kong Diploma of Secondary Education Examination (HKDSEE) is accepted as equivalent to Level 2 in the UE paper of the CRE. Level 4 or above in Chinese Language of the HKDS EE is accepted as equivalent to Level 1 in the UC paper of the CRE.\n\nNote 2:\u00a0\nAn overall band of 6.5 or above with no subtest score below band 6\u00a0 obtained in the same sitting in the Academic Module of the International English Language Testing System (IELTS) within the two-year validity period of the test result are considered as having met the English language proficiency requirement of the post. The IELTS test result be valid on the interview date.", "employment_types": ["Full Time", "Contract"], "selling_points": [], "locations": ["Tsim Sha Tsui"], "categories": ["Admin & HR", "Personal / Executive Assistant", "Sciences, Lab, R&D", "Energy / Natural Resources / Oil & Gas", "Environmental Science / Waste Management"], "post_time": "2022-01-07T19:21:03Z", "salary": {"currency": null, "max": null, "min": null, "period": "monthly", "term": null}, "salary_visible": false, "title_keywords": ["assistant"], "responsibilities": ["any other duties", "checking", "data input", "testing", "report"], "requirements": {"degrees": ["diploma", "degree", "bachelor", "secondary education"], "majors": ["chemistry", "engineering", "materials science"], "languages": ["english", "chinese"], "language_level": ["proficiency", "good command", "good"], "hard_skills": ["excel", "no", "chinese word processing", "powerpoint", "c", "ms word"], "soft_skills": ["advanced"], "languages_combined": [{"language": "english", "language_level": ["proficiency", "proficiency", "good command", "good"]}, {"language": "chinese", "language_level": ["proficiency", "good command", "good", "good"]}]}, "experience_required": {"duration": [], "field": []}}, {"job_id": "100003009025909", "location_code": "hk", "company": "Knight Recruitment Services Limited", "job_title": "Project Manager (Petrochemicals) 5 day work", "description": "Our client, a Public Listed Company, is looking for high-caliber person to fill the position.\n\nResponsibilities:-\n\nDevelop and maintain spatial data platforms\nDesign and analyze the development of large scale spatial data dissemination platform riding on cloud environment\nValidate data modeling, design data processing workflows, verify data conversion integrity and examine spatial data dissemination via API\nIdentify and rectify data issues during functional testing, system integration testing, and support useracceptance test\nReview, comment and revise technical project documents to enhance the quality of project deliverables\nPrepare documentation, project reports and specifications\n\nRequirements:-\n\nAt least 2 years' working experience in data modelling and management\nSolid knowledge and experience in data architecture design and modelling, implementing and development of data dissemination platform\nHands-on experience in working with spatial data modelling spatial data conversion is a plus\nExperience in Python, web programming or Java programming is an advantage\nPossess strong sense of analytical and problem solving skills\nGood command of both spoken and written Chinese and English", "employment_types": ["Full Time", "Permanent"], "selling_points": ["Project Management in Petrochemical Company", "Salary Negotiable; 5day work!", "Excellent Career Path & Opportunity"], "locations": ["Not Specified"], "categories": ["Sciences, Lab, R&D", "Energy / Natural Resources / Oil & Gas", "Engineering", "Chemical", "Transportation & Logistics", "Supply Chain"], "post_time": "2022-01-06T06:46:51Z", "salary": {"currency": null, "max": null, "min": null, "period": "monthly", "term": null}, "salary_visible": false, "title_keywords": ["project manager"], "responsibilities": ["data", "project deliverables", "review", "quality", "design", "data processing", "develop", "testing", "project documents", "maintain", "project reports", "specifications", "documentation"], "requirements": {"degrees": [], "majors": [], "languages": ["english", "chinese"], "language_level": ["good command"], "hard_skills": ["plus", "java", "web", "programming", "python", "problem solving skills"], "soft_skills": ["analytical and problem solving skills", "hands-on"], "languages_combined": [{"language": "english", "language_level": ["good command"]}, {"language": "chinese", "language_level": ["good command"]}]}, "experience_required": {"duration": ["at least 2 years"], "field": ["programming", "development", "management", "design"]}}]