[{"job_id": "100003009054633", "location_code": "hk", "company": "Maxim's Caterers Ltd", "job_title": "Research and Development Officer/ Assistant (Cakes & Bakery Factory)", "description": "Responsibilities:\nManage the product development process for new lines and the improvement process for existing products\nPerform raw materials / packaging materials testing and sample preparation\nPrepare technical specification such as product specification\nLiaise with internal and external parties relating to product research and development\nPrepare for costing analysis\nRequirements:\nDiploma or above in Food Science or related background\n1 year or above relevant working experience, preferably gained from food or catering industry\nKnowledge in Hong Kong food legislation and requirements\nCreative, self-motivated and able to develop new ideas / approaches\nProficient in MS Office & Chinese Word Processing\nGood command of spoken and written in English and Chinese\nFresh Graduates are welcomed\nStaff Benefits\nMedical Insurance Coverage\nBirthday & Wedding Leave\nFree Meal & Shuttle Bus\nStaff Purchase Benefits\nAll applications and data collected will be treated in strict confidence and used exclusively for recruitment purposes.\u00a0 Only short-listed candidates will be invited for interview.\u00a0 The company will retain the applications for a maximum period of 24 months and may refer suitable candidates to other vacancies within the Group.", "employment_types": ["Full Time", "Permanent"], "selling_points": ["Medical Insurance Coverage, Shuttle Bus", "Diploma or above in Food Science", "Product development"], "locations": ["Tai Po Area"], "categories": ["Hospitality / F & B", "Food & Beverage", "Sciences, Lab, R&D", "Food Science", "Research & Development (R&D)"], "post_time": "2022-01-17T10:19:40Z", "salary": {"currency": null, "max": null, "min": null, "period": null, "term": null}, "salary_visible": false, "title_keywords": ["officer", "assistant"], "responsibilities": ["sample preparation", "internal and external parties", "testing", "costing analysis", "liaise with"], "requirements": {"degrees": ["diploma or above"], "majors": ["food science"], "languages": ["english", "chinese"], "language_level": ["good command", "proficient"], "hard_skills": ["chinese word processing", "ms office"], "soft_skills": ["self-motivated", "creative"], "languages_combined": [{"language": "english", "language_level": ["good command"]}, {"language": "chinese", "language_level": ["good command", "proficient"]}]}, "experience_required": {"duration": ["1 year"], "field": ["food", "relevant working experience"]}}, {"job_id": "100003009055759", "location_code": "hk", "company": "Amoy Food Ltd", "job_title": "QC Inspector (Food Industry)", "description": "Responsibilities:\n\nPerform daily production on-line testing and analysis, review and decide the status of incoming\u00a0materials and finished products\nCompare lab results with specification standards and coordinate with internal and external parties for follow up and improvement actions\nPerform routine sampling, recording, and inspection\nParticipate in\u00a0quality inspections, audits, and other quality-related projects\n\nRequirements:\n\nHigher Diploma in Food Science/Nutrition or related discipline\n1-2 year working experience preferably gained\u00a0in the laboratory of food manufacturing industry (Fresh graduates will also be considered)\nDetail-minded with good analytical skills\nGood interpersonal and communication skills, ability to solve problems and work under pressure\nProficiency in both Chinese and English as well as computer applications\nImmediate available is highly preferred\n\nInterested parties please send your resume with current and expected salary and availability:\n\n- \u00a0by fax to 2666 6575\n- \u00a0by mail to\n\u00a0 \u00a0Human Resources Department\n\u00a0 \u00a0Amoy Food Limited\n\u00a0 \u00a011-15 Dai Fu Street,Tai Po Industrial Estate,Tai Po, N.T.\n- \u00a0by \u201cApply Now\u201d\n\nFor enquiries, please contact our Recruitment Hotline at 2660-3403 / 5545-8814.\u00a0Employment Application Form can be downloaded from the company website\u00a0www.amoy.com\u00a0\n\nAll applications will be treated in strict confidence and retained for 6 months for recruitment purposes only.\u00a0", "employment_types": ["Full Time", "Permanent"], "selling_points": ["Higher Diploma in Food Science/Nutrition", "1-2 year working experience / Fresh graduates", "Shuttle bus, Strong food safety awareness"], "locations": ["Tai Po Area"], "categories": ["Sciences, Lab, R&D", "Food Science", "Manufacturing", "Quality Assurance, Control & Testing / ISO", "Others"], "post_time": "2022-01-18T02:55:45Z", "salary": {"currency": null, "max": null, "min": null, "period": "monthly", "term": null}, "salary_visible": false, "title_keywords": ["qc inspector"], "responsibilities": ["analysis", "internal and external parties", "review", "coordinate with", "quality", "testing", "inspection", "audits"], "requirements": {"degrees": ["diploma"], "majors": ["food science"], "languages": ["english", "chinese"], "language_level": ["proficiency"], "hard_skills": ["analytical skills"], "soft_skills": ["detail-minded", "communication skills", "analytical skills", "solve problems", "interpersonal", "work under pressure"], "languages_combined": [{"language": "english", "language_level": ["proficiency"]}, {"language": "chinese", "language_level": ["proficiency"]}]}, "experience_required": {"duration": ["1-2 year"], "field": ["laboratory", "food manufacturing industry"]}}, {"job_id": "100003009056207", "location_code": "hk", "company": "DFI Retail Group DFI\u96f6\u552e\u96c6\u5718", "job_title": "Quality Assurance /Technical Manager \u2013 Fresh Food & RTE", "description": "Responsibilities:\n\nTo handle daily quality assurance activities\nTo conduct Food manufacturing / Supermarket\u00a0 \u00a0audit in time according to company requirements\nTo review and update processing flow chart and products specification\nTo oversee and manage all specifications of our products with risk management approach\nTo investigate and handle complaints related to food quality\nAssist the ad-hoc projects as assigned\n\nRequirements:\n\nTertiary education in Business Management / Food Safety or related disciplines\nKnowledge on\u00a0HACCP & ISO22000 is preferred\n1-2 years relevant working experience in\u00a0Food manufacturing audit\u00a0 / Supermarket /Food store is preferred\nProficient in MS Office application (Excel, Word & PowerPoint) and Chinese Word Processing\nBe proactive, self-motivated and work independently\nGood time management skill, well-organized with strong analytical mind\nImmediate available is highly preferred\nFresh graduate is welcome\n\nInterested parties, please send your detailed resume, availability, present and expected salary to Human Resources Department by clicking \u201cApply Now\u201d.\n\nWe are an equal opportunity employer. Applications from all qualified candidates are welcome.\n\nAll information collected will be used for recruitment related purpose only.\u00a0", "employment_types": ["Full Time"], "selling_points": ["Local product standards & EU regulations knowledge", "Quality Assurance for own brand products", "Technical, Regulatory, Ingredient, Process"], "locations": ["Quarry Bay"], "categories": ["Sciences, Lab, R&D", "Food Science"], "post_time": "2022-01-18T03:32:35Z", "salary": {"currency": null, "max": null, "min": null, "period": "monthly", "term": null}, "salary_visible": false, "title_keywords": ["technical manager"], "responsibilities": ["management", "review", "quality", "audit", "handle complaints", "specifications", "ad-hoc projects"], "requirements": {"degrees": ["fresh graduate"], "majors": [], "languages": ["chinese"], "language_level": ["proficient"], "hard_skills": ["business management", "excel", "chinese word processing", "word", "powerpoint", "ms office"], "soft_skills": ["self-motivated", "work independently", "well-organized", "analytical mind", "time management skill", "proactive"], "languages_combined": [{"language": "chinese", "language_level": ["proficient"]}]}, "experience_required": {"duration": ["1-2 years"], "field": ["food manufacturing", "food store", "relevant working experience", "audit"]}}, {"job_id": "100003009054438", "location_code": "hk", "company": "Intertek Testing Services H.K. Ltd.", "job_title": "Customer Services Executive (Food)", "description": "The Job\n\nSupport the function\u2019s head and team members in establishing and implementing any Fresh & RTE Product Technology initiatives related to own brand product integrity\nSupport all aspects of Fresh & RTE Product Technology strategic planning, both short term and long term\nProvide input to the selection of appropriate and competent Suppliers, 3rd party service providers to support of the implementation of Fresh 3 Steps to Quality Program\nCoach and support BU and Banner team members to ensure that there is a consistent understanding of Group Technical policies, SOP and Guidelines\nSupport Group and local Procurement and Brand Teams or Commercial Team through product development and product improvement without compromising on quality\nSupport the function\u2019s head to participate in technical network, connections with the government or non-government agencies, internal stakeholders (e.g. Legal, BU and Banner team members) and outsourced international organizations to proactively review and plan in advance of any new regulatory requirements and industry QA trends\nProvide technical, regulatory, process, ingredient and packaging expertise in the development of concepts and products to market\n\nThe Person\n\nUniversity Degree in Food Science and Technology, Agriculture Science or related discipline\nMinimum 5 years working experience in related field; retail business managing the Fresh and Ready to Eat Categories\nExperience working with growers or in farms, packhouses, laboratory experience in pesticide, heavy metal and contaminants is an advantage\nTechnical Experience across multiple Fresh Product Categories - Produce, Seafood, Meat\nFamiliar with local product standards, regulatory requirements and registration of Asian markets, strong knowledge in EU regulations\nStrong knowledge in manufacturing processes and retailer Technical practices of Meats, Seafood and processed foods\nExperience implementing and certification of Halal systems\nExperience developing, implementing and certification of GMP, HACCP, GFSI\u2019s Food Safety Management Systems\nGood command of both written & spoken English\nProficient in MS Office including MS Excel, Word and PowerPoint\n\nDFI Retail Group is an equal opportunity employer and responsible for ensuring that all personal information collected from each Candidate presented to DFI Retail Group is used for recruitment purposes only and the personal data will be kept and handled confidentially. We will retain the applications of candidates not selected for a period of no more than 24 months. The data collection process is in accordance with all applicable laws and compliant with the Code of Practice on Human Resource Management.\n\nTo find out more about Our Businesses and Our People, please visit our website: https://www.DFIretailgroup.com\n\n\u00a0\nIssued by The Dairy Farm Company, Limited", "employment_types": ["Full Time", "Permanent"], "selling_points": ["Fresh Graduates are welcome", "Double Pay, Discretionary Bonus", "On-the-job training for fast development"], "locations": ["Lai Chi Kok"], "categories": ["Sales, CS & Business Devpt", "Customer Service - Supervisor / Officer", "Sciences, Lab, R&D", "Food Science", "Account Servicing"], "post_time": "2022-01-17T09:33:51Z", "salary": {"currency": null, "max": null, "min": null, "period": "monthly", "term": null}, "salary_visible": false, "title_keywords": ["executive"], "responsibilities": ["strategic planning", "guidelines", "policies", "regulatory requirements", "review", "quality", "implementation", "teams", "plan"], "requirements": {"degrees": ["university degree"], "majors": ["science", "food science"], "languages": ["english"], "language_level": ["good command"], "hard_skills": ["no", "word", "powerpoint", "ms excel", "code", "ms office"], "soft_skills": ["responsible"], "languages_combined": [{"language": "english", "language_level": ["good command"]}]}, "experience_required": {"duration": ["minimum 5 years"], "field": ["laboratory", "management", "related", "developing", "food"]}}, {"job_id": "100003009052873", "location_code": "hk", "company": "Telford International Co Ltd", "job_title": "Quality Assurance Officer / Assistant", "description": "Our purpose is to bring safety, quality and\u00a0sustainability\u00a0to life.\nThe Job\u00a0\nAn excellent career opportunity in a listed multinational corporation to deliver superior B2B services to food traders / food manufacturers / food caterers / overseas food retailer clients\nHandle\u00a0inquiries\u00a0and complaints from clients\nIntroduce and promote our services to clients proactively\nCoordinate between external clients and internal technical colleagues to monitor and follow up the progress of testing projects and all related events\nOn-the-job training will be provided to equip our staff to deliver the best service to clients\nThe Person\nDegree / Higher Diploma holder in Science related subjects, preferably in Food Science or Chemistry\nPossess strong client services mindset\nGood command of written and spoken English and Chinese (Cantonese / Mandarin)\nGood interpersonal and communication skill\nFresh graduates are welcome\nImmediately available would be an advantage\nThe Package\nDouble pay\nPerformance bonus\nMedical benefit\nDental plan with discount\n14 days annual leave\nLife insurance\nGood career prospects\n\u00a0Join us in bringing quality and safety to life.", "employment_types": ["Full Time", "Permanent"], "selling_points": ["Degree or above in Food Science", "1-2 years relevant work experiences", "Travel to Mainland if the circumstances permit"], "locations": ["Yuen Long"], "categories": ["Engineering", "Manufacturing & Production", "Sciences, Lab, R&D", "Food Science", "Manufacturing", "Quality Assurance, Control & Testing / ISO"], "post_time": "2022-01-17T04:23:01Z", "salary": {"currency": null, "max": null, "min": null, "period": "monthly", "term": null}, "salary_visible": false, "title_keywords": ["quality assurance officer", "assistant"], "responsibilities": ["coordinate", "inquiries and complaints", "monitor", "testing"], "requirements": {"degrees": ["degree", "higher diploma holder"], "majors": ["science", "chemistry", "food science"], "languages": ["cantonese", "english", "chinese", "mandarin"], "language_level": ["good command"], "hard_skills": [], "soft_skills": ["communication skill", "interpersonal"], "languages_combined": [{"language": "cantonese", "language_level": ["good command"]}, {"language": "english", "language_level": ["good command"]}, {"language": "chinese", "language_level": ["good command"]}, {"language": "mandarin", "language_level": ["good command"]}]}, "experience_required": {"duration": [], "field": []}}, {"job_id": "100003009056256", "location_code": "hk", "company": "Maxim's Caterers Ltd", "job_title": "Part Time - Quality Assurance Assistant (Cakes & Bakery)", "description": "Roles and Responsibilities\n\n\nProvide technical support on food and beverage regulatory\nCommunicate with internal and external parties to ensure the product are compliance with regulation\nReview product label base on local and overseas regulatory requirements\nHandle routine QA duties, such as verify the raw materials / finished products whether comply with relevant regulations and have safety certifications\u00a0\nInvolve in new product development\nProduct specifications follow up and finished product check\nAssist in compliant investigation, root cause analysis and correction\nPerform other Ad hoc duties as assigned\nRequirements\n\nDegree or above in Food Science or related disciplines\n1-2 years work experience as quality assurance in food or beverage industry\nLiaise with food authority on food regulation/food labelling law\nGood communication skills and able to work independently\nSelf-motivated, well-organized with good analytical skill\nRegular travel to Mainland China if the circumstances permit\n\nWe offer attractive remuneration package and career prospects plus 5-day week to right candidate. Interest parties; please forward your full resume with expected salary to us.\n\nAll data collected shall be solely for recruitment purposes.\n\nWebsite: www.telford.com.hk", "employment_types": ["Part Time", "Temporary", "Contract"], "selling_points": ["Implementing and maintain the documentation system", "Support the implementation of food safety, hygiene", "5-day work week and rotate day off"], "locations": ["Tai Po Area"], "categories": ["Sciences, Lab, R&D", "Food Science", "Laboratory", "Manufacturing", "Quality Assurance, Control & Testing / ISO"], "post_time": "2022-01-18T03:43:24Z", "salary": {"currency": null, "max": null, "min": null, "period": null, "term": null}, "salary_visible": false, "title_keywords": ["quality assurance assistant"], "responsibilities": ["communicate with", "regulations", "ad hoc duties", "technical support", "regulatory requirements", "analysis", "compliance", "review", "internal and external parties", "investigation", "specifications"], "requirements": {"degrees": ["degree or above"], "majors": ["related disciplines", "food science"], "languages": [], "language_level": [], "hard_skills": ["analytical skill"], "soft_skills": ["communication skills", "work independently", "self-motivated", "analytical skill", "well-organized"], "languages_combined": []}, "experience_required": {"duration": ["1-2 years"], "field": ["food or beverage industry", "quality assurance"]}}, {"job_id": "100003009051715", "location_code": "hk", "company": "\u6a13\u4e0a\u6709\u9650\u516c\u53f8 / HK JEBN LIMITED", "job_title": "Senior Microbiologist / Microbiologist", "description": "Responsibilities:\n\nPerform routine on line and finished food products inspection at various stages on the production line to implement ISO/HACCP policy.\nAssist in implementing and maintain the documentation system and quality management system.\nSupport the implementation of food safety, hygiene and quality assurance operation policies, guidelines and procedures to ensure the entire production process is in compliance with the corporate standard.\nCoordinate and participate work safety, quality assurance and hygiene procedures training to related staff.\nAssist in other ad-hoc projects as assigned.\n\nRequirements:\n\nDiploma holder or above in biochemistry, Food Science or related disciplines;\nSelf-motivated, independent and with good communication skill;\nWell-organized with good analytical skill;\nProficient in PC applications including Chinese word processing;\nGood command of spoken and written English and Chinese / Cantonese;\nWorking location: Tai Po Industrial Estate (with shuttle bus)\nFresh graduate will also be considered.\n\nInterested parties please apply with full resume, state current and expected salaries via clicking \"Apply Now\".\n\n\nAll applications and data collected will be treated in strict confidence and used exclusively for recruitment purposes.\u00a0 Only short listed candidates will be invited for interview.\u00a0 The company will retain the applications for a maximum period of 6 months and may refer suitable candidates to other vacancies within the Group.", "employment_types": ["Full Time"], "selling_points": ["5-Day Work, 12 AL, Free Lunch", "Work in Tai Wai", "HOKLAS system, Food microbial testing"], "locations": ["Shatin Area"], "categories": ["Sciences, Lab, R&D", "Food Science"], "post_time": "2022-01-16T21:51:04Z", "salary": {"currency": null, "max": null, "min": null, "period": "monthly", "term": null}, "salary_visible": false, "title_keywords": [], "responsibilities": ["management", "production process", "food safety", "guidelines", "policies", "compliance", "quality", "implementation", "procedures", "inspection", "coordinate", "hygiene", "maintain", "documentation", "ad-hoc projects"], "requirements": {"degrees": ["diploma holder", "fresh graduate"], "majors": ["related disciplines", "food science"], "languages": ["cantonese", "english", "chinese"], "language_level": ["good command", "proficient"], "hard_skills": ["analytical skill", "chinese word processing", "pc applications"], "soft_skills": ["self-motivated", "analytical skill", "independent", "communication skill", "well-organized"], "languages_combined": [{"language": "cantonese", "language_level": ["good command"]}, {"language": "english", "language_level": ["good command"]}, {"language": "chinese", "language_level": ["good command", "proficient"]}]}, "experience_required": {"duration": [], "field": []}}, {"job_id": "100003009050110", "location_code": "hk", "company": "A.S. Watson Industries", "job_title": "QC Technician", "description": "Main Duties\n\n\nMaintain the operation of accredited Food Microbiology Laboratory.\nPerform various microbial testing on food, water and environmental samples.\nPrepare culture media and reagents as specified by SOP.\nMaintain the supply of laboratory materials such as culture medium, reagents, apparatus, equipment.\nConduct calibration and maintenance of laboratory equipment.\nResponsible for handling the bacteria culture and verification activities.\nAssist in monitoring hygiene program.\nParticipate in ad-hoc projects as assigned.\nAble to work on holidays (Roster bases).\n\nRequirement\n\n\nHigher diploma or above in Microbiology, Biotechnology, Biology, Food Science or related disciplines.\nMinimum 3 years\u2019 experience in food microbial testing. Candidate with less experience and/ or qualification may be considered as Junior Microbiologist.\nGood knowledge of food microbial testing is essential.\nKnowledge on HOKLAS system, accreditation requirement is an advantage.\nResponsible, careful and detail minded.\nAble to work multitasking activities.\nWorks both independently and as part of team.\n\n\nWe offer\u00a05-day work, Free lunch, Monthly incentive, 12 days annual leave, Birthday leave, 10 days paternity leave, Employee purchase discount, Medical insurance and Annual body check\u00a0to the above position.\n\n\n\u00a0\nInterested parties please send Full resume to HK JEBN LIMITED, including the following details:\n\u00a0\n\nAvailability\nExpected salary\nPresent salary", "employment_types": ["Full Time", "Permanent"], "selling_points": ["Free Shuttle Bus", "Discretionary bonus, Competitive pay", "QC for Water Production Line"], "locations": ["Tai Po Area"], "categories": ["Sciences, Lab, R&D", "Food Science", "Manufacturing", "Quality Assurance, Control & Testing / ISO", "Others"], "post_time": "2022-01-14T09:47:40Z", "salary": {"currency": null, "max": null, "min": null, "period": "monthly", "term": null}, "salary_visible": false, "title_keywords": ["qc technician"], "responsibilities": ["maintenance", "monitoring", "testing", "hygiene", "maintain", "ad-hoc projects"], "requirements": {"degrees": ["higher diploma or above"], "majors": ["related disciplines", "microbiology", "food science", "biology"], "languages": [], "language_level": [], "hard_skills": [], "soft_skills": ["independently", "careful", "responsible"], "languages_combined": []}, "experience_required": {"duration": ["minimum 3 years"], "field": ["food", "testing"]}}, {"job_id": "100003009054649", "location_code": "hk", "company": "Hop Hing Management Company (Hong Kong) Limited", "job_title": "QC Technician (Ref No.: LT/1701/22)", "description": "Job Duties:\n\nMonitor production process and conduct hourly inspection for finished products\nConduct test and inspection for raw materials and imported products\nPerform physiochemical test\nSupport new product evaluation process\nHandle ad hoc projects assigned by Supervisor\n\nJob Requirements:\n\nIVE / Diploma holder in Science or related discipline\nMinimum\u00a01 year related experience in food industry or commercial laboratory\nKnowledge of HACCP / ISO22000 / Microbiological test are preferred\nEnergetic, well-organized, able to work independently and capable of working under pressure\nGood communication, presentation and interpersonal skill\nGood command of written and spoken English and Chinese\nPC Knowledge in MS Excel, Word & PowerPoint and Chinese Processing\nRequired to work on a roster basis including overnight\nFresh graduated / less experience will be considered as Assistant QC Technician\n\nWe offer competitive salary\u00a0discretionary performance bonus, medical and retirement benefits, free company coach services and excellent career prospects. Please send your resume together with salary expectation via APPLY NOW.\n\nFor more information, please visit our website at www.aswatson.com\u00a0\u00a0\n\nWe are an equal opportunity employer. The information provided will be treated in strict confidence and only be used for consideration of application for similar posts within the A.S. Watson Group of Companies.\n\nApplicants not hearing from us within 6 weeks from the date of advertisement may consider their application unsuccessful.\u00a0 All personal data of unsuccessful applicants will be destroyed within 12 months.\n\nAll information collected is for recruitment purpose only.", "employment_types": ["Full Time"], "selling_points": ["Diploma in Science or related disciplines", "Knowledge of food hygiene", "Experience for analytical equipment"], "locations": ["Yuen Long"], "categories": ["Sciences, Lab, R&D", "Food Science", "Laboratory", "Others"], "post_time": "2022-01-17T10:24:25Z", "salary": {"currency": null, "max": null, "min": null, "period": "monthly", "term": null}, "salary_visible": false, "title_keywords": ["qc technician"], "responsibilities": ["production process", "monitor", "evaluation process", "inspection", "ad hoc projects"], "requirements": {"degrees": ["diploma holder"], "majors": ["science"], "languages": ["english", "chinese"], "language_level": ["good command"], "hard_skills": ["word", "powerpoint", "ms excel", "pc knowledge", "processing"], "soft_skills": ["work independently", "confidence", "under pressure", "capable", "well-organized", "interpersonal skill", "communication", "energetic", "presentation"], "languages_combined": [{"language": "english", "language_level": ["good command"]}, {"language": "chinese", "language_level": ["good command"]}]}, "experience_required": {"duration": ["minimum 1 year"], "field": ["related", "food industry", "commercial laboratory"]}}, {"job_id": "100003009050796", "location_code": "hk", "company": "City Super Ltd", "job_title": "Assistant Officer, Supply Base Quality, QA", "description": "Responsibilities:\n\nRoutine analysis of products, raw materials and on-line process samples.\nResult reporting, equipment maintenance and laboratory safety.\nCarried out QC tasks as assigned.\nDocumentation work related to customers and Sale Team.\nParticipation in problem solving with Refinery, Bottling and Warehouse.\nSupport to ISO certification and external parties communication\n\nRequirements:\n\nDiploma in Science or related disciplines.\nMinimum 1 year experience is preferred.\u00a0\nHand-on experience for analytical equipment such as chromatography or mass spectrometer.\nKnowledge of ISO 9001, ISO 17025, HACCP or food hygiene.\n\nInterested parties, please email detail resume and expected salary email to the Human Resources Department\u00a0(Please quote the reference no.).\n\n\nData collected will be treated in strictly confidential and in used for recruitment purposes only.", "employment_types": ["Full Time", "Permanent"], "selling_points": ["Support the development of SMART annual goals", "Support complaints investigation", "Food Science or Food Technology"], "locations": ["Tsim Sha Tsui"], "categories": ["Hospitality / F & B", "Food & Beverage", "Sciences, Lab, R&D", "Food Science"], "post_time": "2022-01-14T11:24:06Z", "salary": {"currency": null, "max": null, "min": null, "period": "monthly", "term": null}, "salary_visible": false, "title_keywords": ["assistant officer"], "responsibilities": ["reporting", "maintenance", "analysis", "external parties", "communication", "documentation"], "requirements": {"degrees": ["diploma"], "majors": ["related disciplines", "science"], "languages": [], "language_level": [], "hard_skills": [], "soft_skills": [], "languages_combined": []}, "experience_required": {"duration": ["minimum 1 year"], "field": ["analytical"]}}, {"job_id": "100003009049211", "location_code": "hk", "company": "", "job_title": "(Senior) Quality Assurance Inspector - food labeling", "description": "Responsibilities:\n\n\nSupport the development of SMART annual goals which align with the strategic plan of the QA Division\nProvide support to City Super Central Kitchen ensuring the effective execution and development of its food safety and quality system based on HACCAP principles\nSupport the external store audit program and follow up on findings with all relevant stakeholders and suppliers for continuous improvement purposes\nEnsuring supplier audit program is executed at a timely manner and follow up on findings with all relevant stakeholders and suppliers for continuous improvement purposes\nSupport supply base management system as well as\u00a0risk assessment program\nSupport complaints investigation and provide root cause analysis and suggestions on remedial and preventive actions for all suppliers\nRequirement:\u00a0\nBachelor\u2019s degree in Food Science or\u00a0Food Technology\nMinimum of 1 year relevant experience, preferably in food retail / industry\nQA experience in Retail & Food/Beverage industry preferred\nCertified HACCP qualification needed and knowledge on external certification standards (BRC, ISO, AIB) preferred\nStrong written and verbal communication skills, excellent problem solving skills\nAble to handle multiple tasks under a tight schedule & rapidly changing environment while maintaining attention to details and accuracy\nResponsible with good interpersonal skill and able to communicate with all walks of people\nProactive with good problem solving skill\nGood command of spoken & written English & Chinese, with basic knowledge of Japanese and Korean is an advantage\nProficiency in MS Word, Excel, PowerPoint and Chinese word processing\n\nWe offer competitive remuneration package and good prospects to the right candidates. Interested parties please send your full resume with expected salary to us.\n\nData collected will be kept confidential and used for recruitment purposes only.\u00a0", "employment_types": ["Full Time", "Permanent"], "selling_points": ["Good knowledge of food labeling", "Factory and stores audit", "Relevant experience in food/ retail /FMCG industry"], "locations": ["Sham Shui Po Area"], "categories": ["Hospitality / F & B", "Food & Beverage", "Sciences, Lab, R&D", "Food Science", "Manufacturing", "Quality Assurance, Control & Testing / ISO"], "post_time": "2022-01-14T09:30:05Z", "salary": {"currency": null, "max": null, "min": null, "period": "monthly", "term": null}, "salary_visible": false, "title_keywords": ["quality assurance inspector"], "responsibilities": ["provide support", "management", "food safety", "analysis", "quality", "audit", "a timely manner", "investigation", "plan"], "requirements": {"degrees": ["degree", "bachelor"], "majors": ["food science"], "languages": ["japanese", "english", "chinese", "korean"], "language_level": ["advantage", "proficiency", "good command", "basic"], "hard_skills": ["excel", "basic", "chinese word processing", "powerpoint", "problem solving", "problem solving skills", "ms word"], "soft_skills": ["communication skills", "responsible", "interpersonal skill", "handle multiple tasks", "attention to details", "problem solving skill", "problem solving skills", "proactive"], "languages_combined": [{"language": "japanese", "language_level": ["advantage", "good command", "basic"]}, {"language": "english", "language_level": ["advantage", "good command", "basic"]}, {"language": "chinese", "language_level": ["advantage", "proficiency", "good command", "basic"]}, {"language": "korean", "language_level": ["advantage", "good command", "basic"]}]}, "experience_required": {"duration": ["minimum of 1 year"], "field": ["qa", "food or beverage industry", "relevant experience", "food", "retail"]}}, {"job_id": "100003009052804", "location_code": "hk", "company": "Hong Kong Traditional Chinese Pharmaceutical Limited", "job_title": "Regulatory Affair Assistant", "description": "Responsibilities:\nLead all quality assurance and control activities\nResponsible for food labeling checking and approval to ensure compliance with local regulations\nSupervise the quality assurance activities eg. product quality checking and conduct food sampling test\nConduct regular supplier audit and prepare reports\nRequirements:\n\nDegree or above in Nutritional Chemistry/ Food Science or related disciplines\n2\u00a0years\u2019\u00a0relevant experience in food/\u00a0retail / FMCG industry\nGood knowledge of food labeling\nDetail-minded, well-organized, self-motivated and willing to take up challenges\nTeam-player, willing to learn and with good communication and problem-solving skills\n\n\n\nInterested parties,\u00a0please send us an email to obtain an application form to Human Resources Department.\n\nWe are an equal opportunity employer. Applications from all qualified candidates are welcome.\n\nAll information collected will be used for recruitment related purpose only.\u00a0\n\nInterested candidates, please contact us at 67570958 for company details before applying.", "employment_types": ["Full Time"], "selling_points": [], "locations": ["Tsim Sha Tsui"], "categories": ["Sciences, Lab, R&D", "Food Science", "Life Science", "Others"], "post_time": "2022-01-17T04:07:53Z", "salary": {"currency": "HKD", "max": 34999, "min": 25000, "period": "monthly", "term": null}, "salary_visible": true, "title_keywords": ["assistant"], "responsibilities": ["regulations", "control", "quality checking", "quality", "checking", "audit", "ensure compliance", "prepare reports"], "requirements": {"degrees": ["degree or above"], "majors": ["related disciplines", "nutritional chemistry", "food science"], "languages": [], "language_level": [], "hard_skills": ["problem-solving skills", "fmcg industry"], "soft_skills": ["detail-minded", "self-motivated", "team-player", "willing to learn", "well-organized", "communication", "problem-solving skills"], "languages_combined": []}, "experience_required": {"duration": ["2 years"], "field": ["food", "retail", "relevant experience", "fmcg"]}}, {"job_id": "100003009053277", "location_code": "hk", "company": "Intertek Testing Services Hong Kong Ltd", "job_title": "Sales & Business Development Executive (Food)", "description": "Job Duties:\nPrepare samples by various digestion and extraction methods\nConduct chemical analysis according to standard operating procedures\nRun analytical instruments (e.g GC-MS. HPLC, LC-MS, UV-VIS, ICP, AAS etc.)\nMaintain instruments sustainability\nAnalyze data and issue result\nImplement of the laboratory management system in accordance with ISO/IEC 17025 and related requirement by accreditation/ certification body (CB, CNAS, DAkkS, HOKLAS, ZLS etc)\nJob Requirements:\nHigher Diploma/ Degree holder in Chemistry or related discipline\nRelevant working experience in chemical testing or chemistry related industry is an advantage\nGood understanding in quality and safety requirements in chemical laboratories\nWith hand on experiences in operating and performing maintenance for instruments: (1) ICP-OES, (2) UV-VIS, (3) GC-MS, (4) HPLC-MS is an advantage\nHardworking, self-motivated and a good team player\nAble to work independently and under pressure\nCandidate with more experience will be considered as Test Engineer\nWorking location : Yuen Long (5 mins walk from Long Ping Station)\u00a0\n\nWe offer attractive remuneration package with potential career advancement to the right candidate. Interested parties, please apply with detailed resume, stating expected salary and date of availability to Human Resources Department by\u00a0clicking 'Apply Now'.\n\nFor more company information, please visit our webpage www.tuvsud.com\n(Data collected will be treated as strictly confidential and will be used for recruitment purpose only)\u00a0\u00a0", "employment_types": ["Full Time", "Permanent"], "selling_points": [], "locations": ["Lai Chi Kok"], "categories": ["Sales, CS & Business Devpt", "Business Development", "Sciences, Lab, R&D", "Food Science"], "post_time": "2022-01-17T06:41:57Z", "salary": {"currency": null, "max": null, "min": null, "period": "monthly", "term": null}, "salary_visible": false, "title_keywords": ["sales & business development executive"], "responsibilities": ["management", "analysis", "procedures", "maintain", "analyze data"], "requirements": {"degrees": ["diploma", "degree holder"], "majors": ["chemistry"], "languages": [], "language_level": [], "hard_skills": ["maintenance"], "soft_skills": ["good team player", "self-motivated", "under pressure", "work independently", "hardworking"], "languages_combined": []}, "experience_required": {"duration": [], "field": ["related", "chemical testing", "relevant working experience", "maintenance"]}}, {"job_id": "100003009046031", "location_code": "hk", "company": "Ocean Park Corporation", "job_title": "Food Technologist", "description": "Opportunities\n\nYou will be working in a uprising TCM related business of a large international group.\u00a0You will be involved mainly in Regulatory Affairs related works. \u00a0\n\nYou will need to work independently, and executing not only the RA related work, also need to execute administrative tasks such as maintain office filing system, execute and follow up on the instruction given by the superiors. You will build up strength in the competitive environment of both local and global pharmaceutical industries.\n\nAbout the job:\n\nWork closely with internal and external partners as required,\nCommunicate, initiate, and facilitate the R&D collaboration with third parties, if required,\nPerform the preparation of the new drug application, and handle works related to it,\n\nMaintains file system for different projects, also including administrative files,\u00a0\n\nAbout the talent:\n\nBachelor Degree or above in health-related science, Medicine, Pharmacy, Biological Science or other Medical related field\nAt least 2 years solid experience in pharmaceutical regulatory affairs related area is highly preferred,\nAble to work independently and under pressure, adaptability and attention to detail with a strong orientation, well-organized and responsible\nExcellent communication and presentation skills, positive thinking, high team spirit,\nGood command in spoken and written Chinese and English\nCandidate with less experience will be considered as RA Assistant, fresh graduates are welcomed to apply with confidence", "employment_types": ["Full Time", "Contract"], "selling_points": ["Food Safety", "product testing", "hygiene inspection"], "locations": ["Aberdeen"], "categories": ["Sciences, Lab, R&D", "Food Science", "Manufacturing", "Quality Assurance, Control & Testing / ISO", "Others", "Others"], "post_time": "2022-01-13T09:27:38Z", "salary": {"currency": null, "max": null, "min": null, "period": "monthly", "term": null}, "salary_visible": false, "title_keywords": ["food technologist"], "responsibilities": ["administrative tasks", "maintain", "executing", "communication"], "requirements": {"degrees": ["degree or above", "bachelor"], "majors": ["science", "biological science"], "languages": ["english", "chinese"], "language_level": ["good command"], "hard_skills": ["r&d"], "soft_skills": ["work independently", "team spirit", "under pressure", "confidence", "responsible", "well-organized", "positive thinking", "communication", "presentation skills", "adaptability", "attention to detail"], "languages_combined": [{"language": "english", "language_level": ["good command"]}, {"language": "chinese", "language_level": ["good command"]}]}, "experience_required": {"duration": ["at least 2 years"], "field": ["pharmaceutical", "regulatory affairs", "related"]}}, {"job_id": "100003009050214", "location_code": "hk", "company": "Saint Honore Cake Shop Ltd", "job_title": "Senior Quality Assurance Officer", "description": "(Long-Term Contract)\n\nThe incumbent will be responsible for implementing and maintain ISO22000 Food Safety Management System to ensure food safety. He/she will conduct microbiological testing on food/environmental samples collected at different food outlets. He/she will also conduct routine hygiene inspection and provide report to outlets to improve the outlet\u2019s hygiene. Besides, he/she will arrange third party services\u2019 for food outlets (Deep clean, Pest control etc.). In addition, he/she will assist in in or conduct food compliant investigation and regular internal and external audits including ISO22000 & Halal. S/he will also provide routine food safety training for staff and perform other ad hoc duties as assigned by manager.\n\n\n\n\u00a0Requirements:\n- Higher Diploma or above in Food Science or relevant disciplines\n- Relevant work experience in food manufacturing plant / catering industry is preferred\n- Hands-on experience in microbiological testing of food is preferred\n-\u00a0Familiar with HACCP / ISO22000, local food regulatory requirements and standards\n- Good communication and interpersonal skills\n- Good team player, hardworking and self-motivated\n-\u00a0Occasional travel in park area is required\n\nCandidates with more experience will be considered as Senior Food Technologist\n\nApplications including details of qualifications, working experience, expected salary, contact telephone number and address should be applied via: http://careers.oceanpark.com.hk --> Job opening --> Full time/ Long-term.\n\nApplicants not contacted within six weeks may consider their application unsuccessful. Personal data collected will be used for recruitment-related purpose only.", "employment_types": ["Full Time"], "selling_points": ["Focus on quality enhancement", "Implementation & maintenance of quality mgt system", "5 yrs exp. in food manufacturing industry"], "locations": ["Kwai Tsing Area"], "categories": ["Sciences, Lab, R&D", "Food Science", "Laboratory", "Manufacturing", "Quality Assurance, Control & Testing / ISO"], "post_time": "2022-01-14T09:57:02Z", "salary": {"currency": null, "max": null, "min": null, "period": null, "term": null}, "salary_visible": false, "title_keywords": ["senior quality assurance officer"], "responsibilities": ["ad hoc duties", "management", "control", "food safety", "regulatory requirements", "internal and external audits", "investigation", "testing", "inspection", "hygiene", "communication", "maintain", "recruitment", "contact", "catering", "personal data", "third party", "report"], "requirements": {"degrees": ["higher diploma or above"], "majors": ["food science"], "languages": [], "language_level": [], "hard_skills": ["clean"], "soft_skills": ["good team player", "self-motivated", "responsible", "deep", "hands-on", "communication and interpersonal skills", "hardworking"], "languages_combined": []}, "experience_required": {"duration": [], "field": ["food manufacturing", "food", "testing"]}}, {"job_id": "100003009042246", "location_code": "hk", "company": "Fairwood Fast Food Ltd", "job_title": "Group Assistant Quality Assurance Supervisor", "description": "Responsibilities:\nImplementation and maintenance of quality management system;\nPerform food safety, hygiene inspection and monitor in production floor to ensure the operation complies with all statutory requirements and in-house hygiene standard;\nFocus on quality enhancement;\nAssist in\u00a0ad hoc projects as assigned.\n\u00a0Requirements:\n\nBachelor Degree in Food & Nutritional Science or equivalent;\n5 years relevant experience in food manufacturing industry;\nKnowledge of GMP/ HACCP & ISO 9001 and food regulation would be an advantage;\nIndependent, responsible with good communication skill;\nProficient in Chinese Word, Excel and PowerPoint;\nCandidate with more experience could be considered as Assistant QA Manager\nInterested parties, please forward your resume stating salary expectation and available date to us.\n\nFor more information of Saint Honore Cake Shop, please visit www.cr-asia.com\nAll applications will be treated in the strictest confidence. Personal data provided will be used for recruitment purpose only. The information collected might also be disclosed to other associated companies of the Fung Group for job matching of similar vacancies.\nThe provision of full and complete information in support of your application is necessary for selection purposes. Applicant has the right to request access to and correction of personal data collected from him/her in writing to the Human Resource Manager by post to P.O. Box 92408, Tsim Sha Tsui Post Office, Hong Kong.", "employment_types": ["Full Time", "Permanent"], "selling_points": ["Regular food safety, hygiene and quality audit", "Manage sample scheduling and sampling", "Degree/Diploma w/2-year relevant experience"], "locations": ["Tai Po Area"], "categories": ["Hospitality / F & B", "Food & Beverage", "Sciences, Lab, R&D", "Food Science"], "post_time": "2022-01-12T06:43:17Z", "salary": {"currency": null, "max": null, "min": null, "period": "monthly", "term": null}, "salary_visible": false, "title_keywords": ["quality assurance supervisor", "assistant"], "responsibilities": ["management", "food safety", "maintenance", "quality", "implementation", "monitor", "inspection", "hygiene", "statutory requirements", "ad hoc projects"], "requirements": {"degrees": ["degree", "bachelor"], "majors": ["science"], "languages": ["chinese"], "language_level": ["proficient"], "hard_skills": ["excel", "word", "powerpoint"], "soft_skills": ["communication skill", "independent", "responsible"], "languages_combined": [{"language": "chinese", "language_level": ["proficient"]}]}, "experience_required": {"duration": ["5 years"], "field": ["food manufacturing industry", "relevant experience", "qa"]}}, {"job_id": "100003009046591", "location_code": "hk", "company": "Nestle Hong Kong Ltd", "job_title": "Laboratory Technician", "description": "Our purpose is to bring safety and quality to life.\n\nThe Job\n\n\nExplore and develop new business by different channels such as participating sales and marketing events, client visit etc\nExecute corporate strategies on developing new business growth\nManage key accounts by effectively organizing, automating, and synchronizing processes between the external and internal clients\nExplore and increase key accounts business potential\nAchieve customer satisfaction through dynamic and effective client relationship management skills\nThe Person\n\n\nDegree holder in Food / Science related disciplines\nPossess customer services experience, with experience gained in laboratory testing field is a definite advantage\nGood command of both written and spoken English and Chinese / Mandarin\nGood interpersonal and communication skills\nSelf-motivated, outgoing and able to work under pressure\nImmediate available is preferred\nThe Package\n\n\nDouble pay\nIncentive Scheme\nMedical benefit\nDental plan with discount\n14 days annual leave\nLife insurance\nGood career prospects\nJoin us in bringing quality and safety to life\nInterested parties please forward full resume stating your availability, present and expected salary to The Human Resources Manager, Intertek Testing Services HK Ltd., via ONE of the following channels: (Pls quote ref. no. on all correspondence.)\n\nAddress:\u00a02/F Garment Centre, 576 Castle Peak Rd., Kowloon, H.K.\n\nE-mail:\u00a0[email redacted, apply via Company website] ; Fax:\u00a03403 2691\u00a0; Whatsapp: 6329 0464\n\nWelcome to visit our website http://www.intertek.com for corporate information\n\nConfidentiality assured and all applications will be kept solely for recruitment purpose for not more than 6 months.", "employment_types": ["Full Time", "Permanent"], "selling_points": ["Great opportunity in FMCG/F&B", "World No.1 F&B company with collaborative culture", "Laboratory Testing"], "locations": ["Yuen Long"], "categories": ["Sciences, Lab, R&D", "Food Science", "Laboratory", "Manufacturing", "Quality Assurance, Control & Testing / ISO"], "post_time": "2022-01-13T15:29:27Z", "salary": {"currency": null, "max": null, "min": null, "period": "monthly", "term": null}, "salary_visible": false, "title_keywords": ["laboratory technician"], "responsibilities": ["marketing events", "management", "develop new business", "developing"], "requirements": {"degrees": ["degree holder"], "majors": ["related disciplines", "science"], "languages": ["english", "chinese", "mandarin"], "language_level": ["good command"], "hard_skills": ["scheme"], "soft_skills": ["outgoing", "communication skills", "self-motivated", "interpersonal", "work under pressure"], "languages_combined": [{"language": "english", "language_level": ["good command"]}, {"language": "chinese", "language_level": ["good command"]}, {"language": "mandarin", "language_level": ["good command"]}]}, "experience_required": {"duration": [], "field": ["laboratory testing", "customer services"]}}, {"job_id": "100003009047037", "location_code": "hk", "company": "Vitasoy International Holdings Ltd", "job_title": "Group Assistant Regulatory Manager", "description": "Position Summary\n\n\nWorking Location: Yuen Long Industrial Estate\n\nDuty Pattern: 8:00am - 4:30pm or 11:00am - 7:30pm\n(5.5 days per week, alternative Saturday)\n\u00a0\u00a0Responsibilities:\n\nSampling and testing food and beverage raw materials and finished products\nAnalyze test data, verify results and prepare reports\nSAP system preparation work\nParcel packing, agar preparation and material purchasing\nConduct equipment maintenance and calibration\nMonitor factory environment and hygiene conditions\n\n\u00a0\u00a0Requirements:\u00a0\n\nHigher Diploma or above in Food Technology, Food Science, Chemistry, Biology or Biochemistry\nGood analytical and organizational skills\nGood communication skills in both written and spoken English and Chinese\nFresh graduates are also considered\n\nPlease submit\u00a0 application with your resume stating the employment history, present and expected salary by clicking \"Apply Now\".\n\nWe, at all levels, are strongly committed to the Company, its development and its culture. We practice what we preach and give great importance to training and development of people. We offer excellent career development opportunities, attractive remuneration package, comprehensive fringe benefits and wellness programs to the right candidates\n\nWe are an equal opportunity employer and committed to workforce diversity with opportunity for continuous development and growth to all employees.\n\n(All information will be treated in strict confidence and will be used exclusively for recruitment related purpose only. Information of unsuccessful applicants will be destroyed upon completion of the recruitment process.)", "employment_types": ["Full Time"], "selling_points": ["5 days work with company shuttle bus", "Handles import registration of USA", "Updated labeling requirement"], "locations": ["Tuen Mun Area"], "categories": ["Sciences, Lab, R&D", "Food Science", "Manufacturing", "Product Development / Management", "Others"], "post_time": "2022-01-14T02:07:19Z", "salary": {"currency": "HKD", "max": 44999, "min": 30000, "period": "monthly", "term": null}, "salary_visible": true, "title_keywords": ["manager", "assistant"], "responsibilities": ["maintenance", "data", "monitor", "testing", "hygiene", "prepare reports"], "requirements": {"degrees": ["higher diploma or above"], "majors": ["biology", "chemistry", "food science"], "languages": ["english", "chinese"], "language_level": ["good"], "hard_skills": [], "soft_skills": ["communication skills", "organizational skills", "confidence", "committed", "comprehensive"], "languages_combined": [{"language": "english", "language_level": ["good"]}, {"language": "chinese", "language_level": ["good"]}]}, "experience_required": {"duration": [], "field": []}}, {"job_id": "100003009044336", "location_code": "hk", "company": "Hong Kong Standards & Testing Centre", "job_title": "Technical Officer / Asst. Technical Officer (Chemical & Food Testing)", "description": "A Manager, Technical Services is now required as a result of business growth:\n\nResponsibilities:\n\u2022 Responsible for the product development of our health products (Adrien Gagnon) for Hong Kong, the Mainland & Asian markets;\n\u2022 Coordinate with the R&D team to develop product formulation/ modification and prepare documentation in order to cope with related registration requirements;\n\u2022 Provide technical advice and work closely with the commercial team on marketing / promotional materials and nutrition labels, etc.;\n\u2022 Develop regulatory strategy and communicate the regulatory trend and its business impact to management and cross-functional teammates;\n\u2022 Manage product registration and present registration dossiers to expedite the approval progress;\n\u2022 Monitor the quality of raw materials/ finished products / facilities to ensure the full compliance of audits and inspections by HK FEHC and CFS;\n\u2022 Provide professional assessment and analysis to our customer service team to settle customer\u2019s complaint;\n\u2022 Organize health talk to corporate associations and deliver new product & compliance training to the retailers, promoters and cross-functional teammates.\n\nRequirements:\n\u2022 A Master\u2019s / Bachelor\u2019s degree in Food & Nutritional Science, Pharmacy or other related discipline;\n\u2022 A minimum of 8 years\u2019 experience in R&D (health supplement and / or food), regulatory affairs and quality assurance;\n\u2022 Previous experience in Hong Kong, the Mainland & Asian markets is a plus;\n\u2022 Solid knowledge in regulatory submissions, policy and procedures;\n\u2022 Hands-on experience in GMP and ISO is an advantage;\n\u2022 Demonstrate advanced skills in report writing and documentation;\n\u2022 Decisive, attentive to details and with strong organizational skills;\n\u2022 Can work under pressure and a fast-paced working environment.\n\nThank you for your interest in a career with CK Life Sciences. Competitive compensation and benefits package will be offered to the right candidate. We operate a 5-day workweek, and our benefits cover retirement, health and life. Regular shuttle bus service is also provided with pick-ups and drop-offs at designated and convenient locations.\n\nTo apply for our position, you should write, enclosing a current resume to Chief Manager, Human Resources & Administration, CK Life Sciences Limited, 2 Dai Fu Street, Tai Po Industrial Estate, Hong Kong or by clicking the APPLY NOW button. For more company information, please visit www.ck-lifesciences.com.\n\nWe are an equal opportunity employer and welcome applications from all qualified candidates. Personal data collected will be treated in strictest confidence and handled confidentially by authorized personnel for recruitment-related purposes within the Group.", "employment_types": ["Full Time", "Permanent"], "selling_points": ["5-day work week, Double pay & Performance bonus", "Free Shuttle Bus, Medical Benefit", "Diploma or above in Chemistry/ related disciplines"], "locations": ["Tai Po Area"], "categories": ["Sciences, Lab, R&D", "Chemical", "Food Science", "Laboratory"], "post_time": "2022-01-13T03:46:06Z", "salary": {"currency": null, "max": null, "min": null, "period": "monthly", "term": null}, "salary_visible": false, "title_keywords": ["technical officer", "chemical"], "responsibilities": ["management", "technical advice", "compliance", "coordinate with", "monitor", "quality", "develop", "audits", "analysis", "promotional materials", "customer service", "documentation"], "requirements": {"degrees": ["degree", "bachelor", "master"], "majors": ["science"], "languages": [], "language_level": [], "hard_skills": ["r&d", "plus", "documentation"], "soft_skills": ["organizational skills", "advanced", "attentive to details", "hands-on", "decisive", "work under pressure"], "languages_combined": []}, "experience_required": {"duration": ["minimum of 8 years"], "field": ["food", "regulatory affairs", "quality assurance"]}}, {"job_id": "100003009047416", "location_code": "hk", "company": "Tai Hing Catering Group Limited", "job_title": "Assistant Officer - Occupational Safety & Hygiene \u4e94\u5e38\u90e8\u526f\u4e3b\u4efb (\u8077\u696d\u5b89\u5168\u53ca\u74b0\u5883\u885e\u751f)", "description": "Responsibilities:\n\nTo conduct tests in accordance with prescribed procedures\nTo assist group leader in providing technical support to clients\nTo produce traceable test records in suitable format\nTo develop new test methods / optimize existing analytical procedures whenever necessary\nTo perform other necessary duties as directed by superiors\n\nRequirements:\n\nHigher Diploma or above in Analytical Chemistry/ Applied Chemistry/ Applied Science or related disciplines\nPrevious experiences in consumer products testing industry would be an advantage\nProficient in English and Chinese\nFresh graduate will also be considered\n\nBenefits:\u00a0\n\n5-day work week\nDouble pay &\u00a0Performance bonus\nOver-time allowance\nEducation & Training allowance\nMedical benefit\nFree shuttle bus\nAnnual leave, Birthday leave, Marriage leave\nCompany\u00a0activities\n\nInterested parties please send your resume\u00a0with availability, present\u00a0salary\u00a0and expected salary to our Human Resources Department by Clicking\u00a0\"Apply Now\" / By Fax: 2664 4353:/ By Post: STC, 10 Dai Wang Street, Tai Po Industrial Estate, Tai Po, NT\n\nWelcome to visit our company website\u00a0www.stc.group for corporate information.\n\n(All personal data collected are for recruitment purposes only.)", "employment_types": ["Full Time", "Permanent"], "selling_points": [], "locations": ["Shatin Area"], "categories": ["Hospitality / F & B", "Food & Beverage", "Sciences, Lab, R&D", "Food Science", "Admin & HR", "Training & Development"], "post_time": "2022-01-14T03:01:51Z", "salary": {"currency": null, "max": null, "min": null, "period": "monthly", "term": null}, "salary_visible": false, "title_keywords": ["assistant officer"], "responsibilities": ["technical support", "procedures", "develop"], "requirements": {"degrees": ["higher diploma or above", "fresh graduate"], "majors": ["analytical chemistry", "science", "related disciplines", "chemistry"], "languages": ["english", "chinese"], "language_level": ["proficient"], "hard_skills": [], "soft_skills": [], "languages_combined": [{"language": "english", "language_level": ["proficient"]}, {"language": "chinese", "language_level": ["proficient"]}]}, "experience_required": {"duration": [], "field": ["products testing"]}}, {"job_id": "100003009043735", "location_code": "hk", "company": "Good View Fruits Company Limited", "job_title": "QC Technician", "description": "Responsibilities:\n\n\nPerform regular food safety, hygiene and quality audits for the Fairwood outlets and production plants.\nEnsure the implementation of Food Safety and Hygiene management systems and maintain relevant documentation.\nManage sample scheduling and sampling.\nFollow up on quality complaints, perform investigation into the root cause and suggest the possible corrective and preventive action.\nConduct in-house training for operators.\nOther ad- hoc projects as required by supervisor.\n\nRequirements:\n\n\nDegree/ Diploma in food science or related disciplines\nMinimum 2-year related experience in food and catering industry\nFSMS Internal/ Lead Auditor qualification is advantageous\nStrong interpersonal and communication skills\nAttentive to details, mature, independent, strong analytical and problem-solving skills, work well in a team\nExtensive local duty travel required\n\nCompetitive remuneration package will be offered to the right candidate. Interested parties please click\u00a0\"Apply Now\"\u00a0or send full resume with expected salary by 1) email to\u00a0 recruitoffice@ fairwood.com.hk\u00a0or 2) direct mail to HR Manager, 2/F TRP Commercial Centre, 18 Tanner Road, North Point, Hong Kong.\n\n\n(Data collected will be used for recruitment purpose only)", "employment_types": ["Full Time", "Permanent"], "selling_points": [], "locations": ["Tsing Yi"], "categories": ["Sciences, Lab, R&D", "Food Science", "Manufacturing", "Others", "Quality Assurance, Control & Testing / ISO"], "post_time": "2022-01-13T01:45:59Z", "salary": {"currency": null, "max": null, "min": null, "period": "monthly", "term": null}, "salary_visible": false, "title_keywords": ["qc technician"], "responsibilities": ["management", "documentation", "food safety", "systems", "quality", "implementation", "investigation", "hygiene", "scheduling", "maintain", "audits"], "requirements": {"degrees": ["diploma", "degree"], "majors": ["related disciplines", "food science"], "languages": [], "language_level": [], "hard_skills": ["problem-solving skills"], "soft_skills": ["communication skills", "independent", "attentive to details", "mature", "problem-solving skills", "extensive", "interpersonal"], "languages_combined": []}, "experience_required": {"duration": ["minimum 2-year"], "field": ["related", "food"]}}, {"job_id": "100003009042064", "location_code": "hk", "company": "Caf\u00e9 de Coral Group Limited", "job_title": "Quality Control Manager", "description": "Responsibilities\n\nSupport the implementation of \u201c5-S\u201d management system and perform on-site audit in restaurants;\nMaintain environmental, health & safety record and documents;\nFollow up work injury case and prepare related reports and documents;\nOrganize the occupational safety training and modify & update the training materials from time to time;\nEnsure the operations in restaurants are in compliance with safety regulations and corporate requirements;\nPerform ad-hoc duties as assigned\n\nRequirements:\n\nDiploma holder or above in related disciplines;\nA minimum of 1 year\u2019s working experience in clerical support, recent graduates will be also considered;\nExperience in F&B operations and restaurant group is preferable;\nKnowledge in Safety and Health Ordinance is an advantage;\nStrong presentation and communications skills;\nGood inter-personal skills & able to work independently;\nGood written and spoken English and Chinese;\nProficiency in Microsoft Word, Excel, and PowerPoint\nWorking Location : Fotan\n\n\n\nWe offer\u00a0competitive\u00a0package and benefits:\n\n\u00a0\u00a0\u00a0\u00a0\u00a0\u00a0\u00a0\u00a0 Five-Day work week\n\u00a0\u00a0\u00a0\u00a0\u00a0\u00a0\u00a0\u00a0 3 Days Marriage Leave\n\u00a0\u00a0\u00a0\u00a0\u00a0\u00a0\u00a0\u00a0 5 Days Full Pay Paternity Leave\n\u00a0\u00a0\u00a0\u00a0\u00a0\u00a0\u00a0\u00a0 Family-Friendly Leave\n\u00a0\u00a0\u00a0\u00a0\u00a0\u00a0\u00a0\u00a0 Birthday Leave\n\u00a0\u00a0\u00a0\u00a0\u00a0\u00a0\u00a0\u00a0 Free Duty Meal\n\u00a0\u00a0\u00a0\u00a0\u00a0\u00a0\u00a0\u00a0 Staff Discount\n\u00a0\u00a0\u00a0\u00a0\u00a0\u00a0\u00a0\u00a0 Medical Allowance\n\u00a0\u00a0\u00a0\u00a0\u00a0\u00a0\u00a0\u00a0 Insurance Plan\n\u00a0\u00a0\u00a0\u00a0\u00a0\u00a0\u00a0\u00a0 Promotion Opportunities\n\nFor more company information, please visit our web site at\u00a0www.taihing.com\n\nInterested parties please send\u00a0full resume with expected salary\u00a0and availability\u00a0to the\u00a0Human Resources Department via email.\n\nAll information received will be kept in strict confidence and only used for employment-related purposes. Applicants who are not invited for interview within 6 weeks may consider their applications unsuccessful.", "employment_types": ["Full Time", "Permanent"], "selling_points": ["ISO 22000 & HACCP System management", "Ensure food safety & compliance", "Degree in Food Science/ Nutrition, with 8 yrs exp."], "locations": ["Shatin Area"], "categories": ["Hospitality / F & B", "Food & Beverage", "Sciences, Lab, R&D", "Food Science", "Manufacturing", "Quality Assurance, Control & Testing / ISO"], "post_time": "2022-01-12T05:49:32Z", "salary": {"currency": null, "max": null, "min": null, "period": "monthly", "term": null}, "salary_visible": false, "title_keywords": ["manager"], "responsibilities": ["regulations", "management", "operations", "compliance", "implementation", "audit", "maintain", "reports", "ad-hoc duties"], "requirements": {"degrees": ["diploma holder"], "majors": ["related disciplines"], "languages": ["english", "chinese"], "language_level": ["good"], "hard_skills": ["excel", "microsoft word", "powerpoint"], "soft_skills": ["inter-personal skills", "work independently", "presentation"], "languages_combined": [{"language": "english", "language_level": ["good"]}, {"language": "chinese", "language_level": ["good"]}]}, "experience_required": {"duration": ["minimum of 1 year"], "field": ["f&b", "restaurant", "clerical"]}}, {"job_id": "100003009044132", "location_code": "hk", "company": "Vitasoy International Holdings Ltd", "job_title": "Process Officer", "description": "Working Location: Tsing Yi\n\nWorking Time: 09:00 \u2013 17:30\n\n5 days work, Shift\u00a0\n\nBank Holiday\n\nMedical benefit\n\nShuttle bus\n\nKey roles and duties\n\nConduct inspection from raw material, processing and end products\nConduct sampling, physical / chemical testing on starting materials, intermediates and finished products\nConduct environmental monitoring in production area\nArrange the pest control service\nCalibrate the analytical equipment in the QC Laboratory\nReview and maintain the update of product specification record system\nAccomplish other tasks assigned by supervisor\n\nRequirements:\n\nF.6 or above in food science or related disciplines\nHygiene course certificate is preferable\nAble to work under pressure and independently\nExcellent interpersonal and communication skills\nStrong sense of responsibility and willing to learn\nProficient in MS Word, Excel and Chinese Word Processing\nGood command of spoken and written English and Chinese\nFresh graduates are also welcome\u00a0\n\nPlease apply with full resume including expected salary\u00a0by clicking \"Apply\"\n\n\nAll information collected will be kept in strict confidence and used for recruitment purpose only", "employment_types": ["Full Time", "Permanent"], "selling_points": ["Staff Canteen/ Company Shuttle Bus/ Medical", "HD or above in Engineering or Science related", "1 year exp. in processing/ manufacturing areas"], "locations": ["Tuen Mun Area"], "categories": ["Engineering", "Chemical", "Manufacturing & Production", "Sciences, Lab, R&D", "Food Science"], "post_time": "2022-01-13T03:10:22Z", "salary": {"currency": null, "max": null, "min": null, "period": "monthly", "term": null}, "salary_visible": false, "title_keywords": ["officer"], "responsibilities": ["control", "review", "monitoring", "testing", "inspection", "other tasks", "maintain"], "requirements": {"degrees": ["certificate"], "majors": [], "languages": ["english", "chinese"], "language_level": ["good command", "proficient"], "hard_skills": ["excel", "chinese word processing", "ms word"], "soft_skills": ["communication skills", "independently", "confidence", "sense of responsibility", "willing to learn", "interpersonal", "work under pressure"], "languages_combined": [{"language": "english", "language_level": ["good command"]}, {"language": "chinese", "language_level": ["good command", "proficient"]}]}, "experience_required": {"duration": [], "field": []}}, {"job_id": "100003009036959", "location_code": "hk", "company": "Tao Heung Group Limited", "job_title": "Laboratory Technician (Fresh Graduates are welcome)", "description": "Key Responsibilities:\nSupport process owner and execute validation protocol for IQ, OQ, PQ for the processing equipment as well as utilities and facilities\nResponsible for cleaning validation and verification activities for equipment in factory including validation plan review, protocol preparation & execution\nPrepare cleaning assessment reports for new product and equipment\nResolve deviations, analyze test results and prepare final reports for all qualification and validation projects\nImplement statistical data collection and analyze corrective and preventive action\nParticipate in quality audit and trouble-shooting activities in plant\nPerform other duties as assigned\n\u00a0Requirements:\nHigher Diploma or above in Engineering/ Science related disciplines preferable major in Food Engineering/ Technology or Chemical Engineering or Applied Science\nWith 1 year working experience in processing/ manufacturing/ QA/ QC areas in F&B industry\nStrong in engineering knowledge and analytical mindset\u00a0\nAble to work independently and under pressure\nFresh graduate will also be considered for a junior position\nWays to apply:\u00a0\u00a0\nInterested parties please send your detailed resume stating your available date, current & expected salary to Human Resources Manager, by clicking the \u201cAPPLY NOW\u201d button below.\n\n\n\nAll information provided by applicants will be treated in strict confidence and used only for recruitment purposes. If you do not provide the information mentioned in the advertisement, we may not be able to assess your job application. You have the right to request access to, and correction of, your personal data held by us and you may lodge such request with our Data Protection Officer at pdpo@ vitasoy.com, but any such data access request will only be processed after the completion of the recruitment process.", "employment_types": ["Full Time", "Permanent"], "selling_points": ["Food & Beverage", "Product Sampling", "Food Science and Safety"], "locations": ["Tai Po Area"], "categories": ["Hospitality / F & B", "Food & Beverage", "Sciences, Lab, R&D", "Food Science", "Manufacturing", "Quality Assurance, Control & Testing / ISO"], "post_time": "2022-01-11T01:00:52Z", "salary": {"currency": null, "max": null, "min": null, "period": "monthly", "term": null}, "salary_visible": false, "title_keywords": ["laboratory technician"], "responsibilities": ["perform other duties", "review", "quality", "audit", "reports", "data collection", "plan", "cleaning"], "requirements": {"degrees": ["higher diploma or above", "fresh graduate"], "majors": ["related disciplines", "science", "chemical engineering", "engineering"], "languages": [], "language_level": [], "hard_skills": ["processing"], "soft_skills": ["work independently", "under pressure"], "languages_combined": []}, "experience_required": {"duration": ["1 year"], "field": ["f&b", "manufacturing", "qa"]}}, {"job_id": "100003009043584", "location_code": "hk", "company": "Maxim's Caterers Ltd", "job_title": "Quality Assurance Assistant (Cakes & Bakery)", "description": "Working in Tao Heung Group, besides remuneration and benefits, you can also\n1) Get a chance to work in one of the largest F&B groups,\n2) Get cross-border exposure, and\n3) Get some challenging yet fulfilling and rewarding experience.\n\nPlease join us as:\n\nLaboratory Technician\n\nJob Description:\n\nPerform sampling and testing of raw materials and finished products;\n\nExecute onsite sampling for food and environmental samples;\nAnalyze test data; verify results and prepare reports;\nConduct equipment calibration and maintenance;\nMonitor factory environment and hygiene conditions.\nJob Requirements:\n\nHigher Diploma or above in Food Technology, Food Science, Chemistry, Biology or Biochemistry;\n2 years' food manufacturing or laboratory experience in food analysis or quality control;\nGood analytical and organizational skills;\nKnowledge in food production and processing would be an advantage;\nFresh graduates are welcome.\nInterested parties please apply with resume, current salary, expected salary and contact numbers to the Human Resources Manager, Tao Heung Group Ltd. by clicking \"APPLY NOW\".\n\nApplication letters collected will be used for recruitment purpose only.", "employment_types": ["Full Time", "Permanent"], "selling_points": ["Implementing and maintain the documentation system", "Support the implementation of food safety, hygiene", "5-day work week and rotate day off"], "locations": ["Tai Po Area"], "categories": ["Sciences, Lab, R&D", "Food Science", "Laboratory", "Manufacturing", "Quality Assurance, Control & Testing / ISO"], "post_time": "2022-01-12T23:19:09Z", "salary": {"currency": null, "max": null, "min": null, "period": null, "term": null}, "salary_visible": false, "title_keywords": ["quality assurance assistant"], "responsibilities": [], "requirements": {"degrees": [], "majors": [], "languages": [], "language_level": [], "hard_skills": [], "soft_skills": [], "languages_combined": []}, "experience_required": {"duration": [], "field": []}}, {"job_id": "100003009044265", "location_code": "hk", "company": "Concord Alliance Limited", "job_title": "Nutritionist", "description": "Responsibilities:\n\nPerform routine on line and finished food products inspection at various stages on the production line to implement ISO/HACCP policy.\nAssist in implementing and maintain the documentation system and quality management system.\nSupport the implementation of food safety, hygiene and quality assurance operation policies, guidelines and procedures to ensure the entire production process is in compliance with the corporate standard.\nCoordinate and participate work safety, quality assurance and hygiene procedures training to related staff.\nAssist in other ad-hoc projects as assigned.\n\nRequirements:\n\nDiploma holder or above in biochemistry, Food Science or related disciplines;\nAt least 1 year laboratory working experience;\nSelf-motivated, independent and with good communication skill;\nWell-organized with good analytical skill;\nProficient in PC applications including Chinese word processing;\nGood command of spoken and written English and Chinese / Cantonese;\n5-day work week and rotate day off;\nWorking location: Tai Po Industrial Estate (with shuttle bus)\nFresh graduate will also be considered.\n\nInterested parties please apply with full resume, state current and expected salaries via clicking \"Apply Now\".\n\n\nAll applications and data collected will be treated in strict confidence and used exclusively for recruitment purposes.\u00a0 Only short listed candidates will be invited for interview.\u00a0 The company will retain the applications for a maximum period of 6 months and may refer suitable candidates to other vacancies within the Group.", "employment_types": ["Full Time", "Permanent"], "selling_points": ["Degree in Nutrition and / or Food science", "At least 3 years exp. in Health Care Industry", "Double Pay"], "locations": ["Tsim Sha Tsui"], "categories": ["Sciences, Lab, R&D", "Food Science", "Beauty Care / Health", "Nutritionist", "Medical Services", "Pharmaceutical"], "post_time": "2022-01-13T03:35:43Z", "salary": {"currency": null, "max": null, "min": null, "period": "monthly", "term": null}, "salary_visible": false, "title_keywords": ["nutritionist"], "responsibilities": ["management", "production process", "food safety", "guidelines", "policies", "compliance", "quality", "implementation", "procedures", "inspection", "coordinate", "hygiene", "maintain", "documentation", "ad-hoc projects"], "requirements": {"degrees": ["diploma holder", "fresh graduate"], "majors": ["related disciplines", "food science"], "languages": ["cantonese", "english", "chinese"], "language_level": ["good command", "proficient"], "hard_skills": ["analytical skill", "chinese word processing", "pc applications"], "soft_skills": ["self-motivated", "analytical skill", "independent", "communication skill", "well-organized"], "languages_combined": [{"language": "cantonese", "language_level": ["good command"]}, {"language": "english", "language_level": ["good command"]}, {"language": "chinese", "language_level": ["good command", "proficient"]}]}, "experience_required": {"duration": ["at least 1 year"], "field": ["laboratory"]}}, {"job_id": "100003009035816", "location_code": "hk", "company": "Hong Kong Yamazaki Baking Co Ltd", "job_title": "Quality Control Supervisor", "description": "Job Responsibilities:\n\nResponsible for ISO 22000 & HACCP System management and maintenance for a food manufacturing plant\nEnsure the food safety procedures outlined in the ISO system are communicated to all necessary parties and correctly implemented via training;\u00a0maintain up to date documentation, internal audit & follow up , oversee the certification renewal process, etc\nWorks with senior management on development and revision of policies and procedures pertaining to food quality and safety\nManage reporting and communication to prepare for audits and assessments, management meetings etc.\nCoordinate customer complaints incident investigation, report and analysis, develop plan for corrective & preventive actions\nCommunicate all Hold and Release activity to relevant department\nCollaborate with other related departments to assure timely and accurate reporting of food safety/ quality issues and or worker safety issues\nStay up to date on the latest regulatory requirements, and review company standards to ensure food safety & compliance\nLead and provide coaching to the team members\nPerform other duties as requested by Management\n\u00a0\nRequirements:\n\nBachelor\u2019s degree or above in Food Science/Nutrition or related discipline\nMinimum\u00a0 8 years\u2019 relevant experience in food industry QA or QC management, in which at least 5 years in supervisory/managerial roles\nSolid experience in Manufacturing industry, Quality & Food Safety Management System standard & setup; with ISO22000 lead auditor certification\nExperience with implementing ISO22000, HACCP system\nPassionate , details minded, self-motivated and able to work independently\nGood leadership and a good team player as well\nExcellent communication, training, and interpersonal skills\nProficient in MS Office applications\nGood command of both written and spoken English and Cantonese\n\nInterested parties please send full resume with\u00a0PRESENT & EXPECTED SALARY\u00a0to Human Resources Department by clicking \"APPLY NOW\".\n\nWe are an EQUAL OPPORTUNITIES EMPLOYER.\nAll information received will be kept in strict confidence and be used for employment related purpose only.", "employment_types": ["Full Time", "Permanent"], "selling_points": [], "locations": ["Tai Po Area"], "categories": ["Hospitality / F & B", "Food & Beverage", "Sciences, Lab, R&D", "Food Science", "Manufacturing", "Quality Assurance, Control & Testing / ISO"], "post_time": "2022-01-10T08:27:58Z", "salary": {"currency": null, "max": null, "min": null, "period": "monthly", "term": null}, "salary_visible": false, "title_keywords": ["supervisor"], "responsibilities": ["collaborate with", "internal audit", "regulatory requirements", "quality", "communication", "maintain", "plan", "senior management", "perform other duties", "compliance", "develop", "report", "reporting", "management", "food safety", "customer complaints", "review", "procedures", "investigation", "audits", "documentation", "maintenance", "policies", "analysis", "coordinate"], "requirements": {"degrees": ["degree or above", "bachelor"], "majors": ["food science"], "languages": ["cantonese", "english"], "language_level": ["good command"], "hard_skills": ["ms office"], "soft_skills": ["passionate", "good team player", "self-motivated", "work independently", "communication", "interpersonal skills", "leadership"], "languages_combined": [{"language": "cantonese", "language_level": ["good command"]}, {"language": "english", "language_level": ["good command"]}]}, "experience_required": {"duration": ["at least 5 years", "8 years"], "field": ["managerial", "management", "supervisory", "qa", "food industry", "relevant experience", "food", "manufacturing industry"]}}, {"job_id": "100003009036394", "location_code": "hk", "company": "Saraya (Hong Kong Sales) Co., Limited", "job_title": "Senior Food Hygiene Instructor (5 days, Japanese Company)", "description": "Provide professional nutrition consultation and dietary advice to clients\nProvide excellent customer service, establish, and maintain excellent customer relationship\nIntroduce and detail health supplements and provide appropriate product suggestions and advices\nOrganize and conduct public health education, seminars and workshops\nConduct health supplement market research and assist in product development\nEmbrace company culture and core values and actively participate in CSR activities and volunteer work\nParticipate and support daily operations and work closely with other departments on different projects\nExciting opportunities to develop career based on interests and talents and equip with the skills and knowledge required for success\n\nRequirement\n\nDegree in Nutrition and / or Food science or other relevant disciplines\nAt least 3 years' working experience in healthcare / pharmaceutical industry is preferred. Experience in retail / service industry is an advantage\nExcellent command of both written & spoken English, Mandarin and Cantonese\nPleasant, out-going with strong communication, interpersonal & presentation skill\nAble to work independently and under pressure\nOn-job training will be provided\n\nWe offer competitive remuneration package to the right candidate. Interested parties please send your application together with a detailed resume, current & expected salary and availability by clicking the \"APPLY NOW\" button below.", "employment_types": ["Permanent"], "selling_points": [], "locations": ["North Point"], "categories": ["Sciences, Lab, R&D", "Food Science", "Manufacturing", "Quality Assurance, Control & Testing / ISO"], "post_time": "2022-01-10T10:14:39Z", "salary": {"currency": null, "max": null, "min": null, "period": "monthly", "term": null}, "salary_visible": false, "title_keywords": [], "responsibilities": ["market research", "work closely with other departments", "develop", "communication", "daily operations", "maintain", "customer service"], "requirements": {"degrees": ["degree"], "majors": ["food science"], "languages": ["cantonese", "english", "mandarin"], "language_level": ["excellent"], "hard_skills": ["workshops", "presentation skill"], "soft_skills": ["presentation skill", "work independently", "under pressure", "pleasant", "communication", "customer service", "interpersonal"], "languages_combined": [{"language": "cantonese", "language_level": ["excellent"]}, {"language": "english", "language_level": ["excellent"]}, {"language": "mandarin", "language_level": ["excellent"]}]}, "experience_required": {"duration": ["at least 3 years"], "field": ["pharmaceutical", "healthcare", "retail", "service industry"]}}, {"job_id": "100003009055764", "location_code": "hk", "company": "Amoy Food Ltd", "job_title": "Assistant / QA Officer (Food Manufacturing)", "description": "Responsibilities:\n\nLead a team of QC to ensure product quality is in compliance with company standard\n\nConduct online trouble-shooting activities, implement and monitor corrective and preventive actions on quality issues\nEnsure the implementation of quality management systems in production and related parties, and maintain relevant documentation\nMaintain and improve product quality, communicate and coordinate with internal parties on quality control issues\nHandle customers\u2019 complaints, investigate on the cause of problem and propose corrective actions and preventive measures\nConduct GMP audit and coordinate Pest Management activities\nConduct regular audits on suppliers to ensure their products are up to standard\nPrepare monthly reports and analysis and take up ad hoc assignments\n\nRequirements:\n\nHigher Diploma /\u00a0University degree in Food Science, Food Technology or related discipline\n\n3-4 years\u2019 relevant working experience in food related factory\nKnowledge of HACCP / BRC / ISO22000 will be required\nStrong analytical, communication and interpersonal skills\nDetail-minded with multiple-tasking capabilities, ability to work independently and willing to take up challenges\nProficiency in English and Mandarin as well as computer applications, knowledge of SAP will be an advantage\nImmediate available is highly preferred\n\nInterested parties please send your resume with current and expected salary and availability:\n\n- \u00a0by fax to 2666 6575\n- \u00a0by mail to\n\u00a0 \u00a0Human Resources Department\n\u00a0 \u00a0Amoy Food Limited\n\u00a0 \u00a011-15 Dai Fu Street,Tai Po Industrial Estate,Tai Po, N.T.\n- \u00a0by \u201cApply Now\u201d\n\nFor enquiries, please contact our Recruitment Hotline at 26603403.\u00a0Employment Application Form can be downloaded from the company website\u00a0www.amoy.com\u00a0\n\nAll applications will be treated in strict confidence and retained for 6 months for recruitment purposes only.\u00a0", "employment_types": ["Full Time", "Permanent"], "selling_points": ["HD / University degree in Food Science/Nutrition", "3-4 year working experience,food science backgroud", "5-day work, Shuttle bus, Free lunch meal"], "locations": ["Tai Po Area"], "categories": ["Sciences, Lab, R&D", "Food Science", "Manufacturing", "Quality Assurance, Control & Testing / ISO", "Others"], "post_time": "2022-01-18T02:55:47Z", "salary": {"currency": null, "max": null, "min": null, "period": "monthly", "term": null}, "salary_visible": false, "title_keywords": ["officer", "assistant"], "responsibilities": ["management", "monthly reports", "analysis", "compliance", "monitor", "quality", "implementation", "systems", "coordinate with", "lead a team", "audit", "maintain", "coordinate", "audits", "quality control", "ad hoc assignments", "documentation", "internal parties"], "requirements": {"degrees": ["diploma", "university degree"], "majors": ["food science"], "languages": ["english", "mandarin"], "language_level": ["advantage", "proficiency"], "hard_skills": ["sap"], "soft_skills": ["detail-minded", "work independently", "communication and interpersonal skills"], "languages_combined": [{"language": "english", "language_level": ["advantage", "proficiency"]}, {"language": "mandarin", "language_level": ["advantage", "proficiency"]}]}, "experience_required": {"duration": ["3-4 years"], "field": ["related", "food", "relevant working experience"]}}, {"job_id": "100003009056709", "location_code": "hk", "company": "Bao Dim Sin Seng Limited", "job_title": "Quality Assurance Inspector / Assistant (Supermarket/Food Factory)", "description": "Responsibilities:\n\nTo handle daily quality assurance activities\nTo conduct Food manufacturing / Supermarket\u00a0 \u00a0audit in time according to company requirements\nTo review and update processing flow chart and products specification\nTo oversee and manage all specifications of our products with risk management approach\nTo investigate and handle complaints related to food quality\nAssist the ad-hoc projects as assigned\n\nRequirements:\n\nTertiary education in Business Management / Food Safety or related disciplines\nKnowledge on\u00a0HACCP & ISO22000 is preferred\n1-2 years relevant working experience in\u00a0Food manufacturing audit\u00a0 / Supermarket /Food store is preferred\nProficient in MS Office application (Excel, Word & PowerPoint) and Chinese Word Processing\nBe proactive, self-motivated and work independently\nGood time management skill, well-organized with strong analytical mind\nImmediate available is highly preferred\nFresh graduate is welcome\n\nInterested parties, please send your detailed resume, availability, present and expected salary to Human Resources Department by clicking \u201cApply Now\u201d.\n\nWe are an equal opportunity employer. Applications from all qualified candidates are welcome.\n\nAll information collected will be used for recruitment related purpose only.\u00a0", "employment_types": ["Full Time", "Permanent"], "selling_points": ["ISO 22000", "HACCP", "Fresh graduate is welcome"], "locations": ["Not Specified"], "categories": ["Hospitality / F & B", "Food & Beverage", "Sciences, Lab, R&D", "Food Science", "Manufacturing", "Quality Assurance, Control & Testing / ISO"], "post_time": "2022-01-18T05:57:42Z", "salary": {"currency": null, "max": null, "min": null, "period": "monthly", "term": null}, "salary_visible": false, "title_keywords": ["quality assurance inspector", "assistant"], "responsibilities": ["management", "review", "quality", "audit", "handle complaints", "specifications", "ad-hoc projects"], "requirements": {"degrees": ["fresh graduate"], "majors": [], "languages": ["chinese"], "language_level": ["proficient"], "hard_skills": ["business management", "excel", "chinese word processing", "word", "powerpoint", "ms office"], "soft_skills": ["self-motivated", "work independently", "well-organized", "analytical mind", "time management skill", "proactive"], "languages_combined": [{"language": "chinese", "language_level": ["proficient"]}]}, "experience_required": {"duration": ["1-2 years"], "field": ["food manufacturing", "food store", "relevant working experience", "audit"]}}, {"job_id": "100003009056757", "location_code": "hk", "company": "TUV SUD Hong Kong Limited", "job_title": "Assistant Test Engineer / Test Engineer  - Chemical Lab (Fresh Graduate Welcome)", "description": "Job Duties:\nPrepare samples by various digestion and extraction methods\nConduct chemical analysis according to standard operating procedures\nRun analytical instruments (e.g GC-MS. HPLC, LC-MS, UV-VIS, ICP, AAS etc.)\nMaintain instruments sustainability\nAnalyze data and issue result\nImplement of the laboratory management system in accordance with ISO/IEC 17025 and related requirement by accreditation/ certification body (CB, CNAS, DAkkS, HOKLAS, ZLS etc)\nJob Requirements:\nHigher Diploma/ Degree holder in Chemistry or related discipline\nRelevant working experience in chemical testing or chemistry related industry is an advantage\nGood understanding in quality and safety requirements in chemical laboratories\nWith hand on experiences in operating and performing maintenance for instruments: (1) ICP-OES, (2) UV-VIS, (3) GC-MS, (4) HPLC-MS is an advantage\nHardworking, self-motivated and a good team player\nAble to work independently and under pressure\nCandidate with more experience will be considered as Test Engineer\nWorking location : Yuen Long (5 mins walk from Long Ping Station)\u00a0\n\nWe offer attractive remuneration package with potential career advancement to the right candidate. Interested parties, please apply with detailed resume, stating expected salary and date of availability to Human Resources Department by\u00a0clicking 'Apply Now'.\n\nFor more company information, please visit our webpage www.tuvsud.com\n(Data collected will be treated as strictly confidential and will be used for recruitment purpose only)\u00a0\u00a0", "employment_types": ["Full Time", "Permanent"], "selling_points": ["Higher Diploma/ Degree holder in Chemistry", "Prepare samples by various digestion", "Able to work independently and under pressure"], "locations": ["Yuen Long Area"], "categories": ["Sciences, Lab, R&D", "Chemical", "Food Science", "Laboratory"], "post_time": "2022-01-18T06:13:57Z", "salary": {"currency": null, "max": null, "min": null, "period": "monthly", "term": null}, "salary_visible": false, "title_keywords": ["chemical", "engineer", "assistant"], "responsibilities": ["management", "analysis", "procedures", "maintain", "analyze data"], "requirements": {"degrees": ["diploma", "degree holder"], "majors": ["chemistry"], "languages": [], "language_level": [], "hard_skills": ["maintenance"], "soft_skills": ["good team player", "self-motivated", "under pressure", "work independently", "hardworking"], "languages_combined": []}, "experience_required": {"duration": [], "field": ["related", "chemical testing", "relevant working experience", "maintenance"]}}, {"job_id": "100003009049883", "location_code": "hk", "company": "CK Life Sciences Limited", "job_title": "Manager, Technical Services (health supplement/product development/ regulatory affairs)", "description": "A Manager, Technical Services is now required as a result of business growth:\n\nResponsibilities:\n\u2022 Responsible for the product development of our health products (Adrien Gagnon) for Hong Kong, the Mainland & Asian markets;\n\u2022 Coordinate with the R&D team to develop product formulation/ modification and prepare documentation in order to cope with related registration requirements;\n\u2022 Provide technical advice and work closely with the commercial team on marketing / promotional materials and nutrition labels, etc.;\n\u2022 Develop regulatory strategy and communicate the regulatory trend and its business impact to management and cross-functional teammates;\n\u2022 Manage product registration and present registration dossiers to expedite the approval progress;\n\u2022 Monitor the quality of raw materials/ finished products / facilities to ensure the full compliance of audits and inspections by HK FEHC and CFS;\n\u2022 Provide professional assessment and analysis to our customer service team to settle customer\u2019s complaint;\n\u2022 Organize health talk to corporate associations and deliver new product & compliance training to the retailers, promoters and cross-functional teammates.\n\nRequirements:\n\u2022 A Master\u2019s / Bachelor\u2019s degree in Food & Nutritional Science, Pharmacy or other related discipline;\n\u2022 A minimum of 8 years\u2019 experience in R&D (health supplement and / or food), regulatory affairs and quality assurance;\n\u2022 Previous experience in Hong Kong, the Mainland & Asian markets is a plus;\n\u2022 Solid knowledge in regulatory submissions, policy and procedures;\n\u2022 Hands-on experience in GMP and ISO is an advantage;\n\u2022 Demonstrate advanced skills in report writing and documentation;\n\u2022 Decisive, attentive to details and with strong organizational skills;\n\u2022 Can work under pressure and a fast-paced working environment.\n\nThank you for your interest in a career with CK Life Sciences. Competitive compensation and benefits package will be offered to the right candidate. We operate a 5-day workweek, and our benefits cover retirement, health and life. Regular shuttle bus service is also provided with pick-ups and drop-offs at designated and convenient locations.\n\nTo apply for our position, you should write, enclosing a current resume to Chief Manager, Human Resources & Administration, CK Life Sciences Limited, 2 Dai Fu Street, Tai Po Industrial Estate, Hong Kong or by clicking the APPLY NOW button. For more company information, please visit www.ck-lifesciences.com.\n\nWe are an equal opportunity employer and welcome applications from all qualified candidates. Personal data collected will be treated in strictest confidence and handled confidentially by authorized personnel for recruitment-related purposes within the Group.", "employment_types": ["Full Time", "Permanent"], "selling_points": ["MSc /BSc in Food & Nutritional Science or Pharmacy", "8 years\u2019 experience in R&D(health supplement/food)", "5-day workweek"], "locations": ["Tai Po Area"], "categories": ["Sciences, Lab, R&D", "Food Science", "Beauty Care / Health", "Nutritionist", "Manufacturing", "Product Development / Management"], "post_time": "2022-01-14T09:23:24Z", "salary": {"currency": null, "max": null, "min": null, "period": "monthly", "term": null}, "salary_visible": false, "title_keywords": ["product development", "manager"], "responsibilities": ["management", "technical advice", "compliance", "coordinate with", "monitor", "quality", "develop", "audits", "analysis", "promotional materials", "customer service", "documentation"], "requirements": {"degrees": ["degree", "bachelor", "master"], "majors": ["science"], "languages": [], "language_level": [], "hard_skills": ["r&d", "plus", "documentation"], "soft_skills": ["organizational skills", "advanced", "attentive to details", "hands-on", "decisive", "work under pressure"], "languages_combined": []}, "experience_required": {"duration": ["minimum of 8 years"], "field": ["food", "regulatory affairs", "quality assurance"]}}, {"job_id": "100003009046764", "location_code": "hk", "company": "N. Law & Associates Company Limited", "job_title": "Consultant / Assistant Consultant - ISO Management System", "description": "Job Responsibilities:\n\nProvide food hygiene training, on-site audit service, and proposal for improvement to support customers\u2019 food safety & hygiene management\nCooperate with salesman (food sanitation segment) to maximize the customer satisfaction\nProvide technical support, products training to customers\nProvide HACCP, ISO22000 consultation to customer\nPerform ad hoc project/assignment as required\n\nRequirements:\n\nHigher diploma or above\nMin. 2 year's experience in the food and beverage industry\nSolid experience in setting up, monitoring HACCP, ISO22000, PRP, SOP, and related documents\nMeticulous, good communication and presentation skills\nGood command of spoken and written English and Cantonese, Japanese speaking is an advantage\nImmediate available is highly preferred\n\nWe offer attractive career development opportunities and excellent fringe benefits including banking holidays, medical & dental insurance, double pay, and discretionary bonus to the right candidates.\u00a0\n\n\nInterested parties please send your resume and portfolio with present and expected salary, and the available date by clicking \"Apply Now\".\n\n\nPersonal data will be used for recruitment purposes only.", "employment_types": ["Full Time", "Permanent", "Contract"], "selling_points": ["Conduct training in QMS, EMS, OHSAS, HACCP, FSMS", "Consulting in ISO system e.g. 9K, 14K, 22K, 45K", "Internal ISO system auditor, project management"], "locations": ["Not Specified"], "categories": ["Professional Services", "Business Consultancy", "Hospitality / F & B", "Food & Beverage", "Sciences, Lab, R&D", "Food Science"], "post_time": "2022-01-14T00:55:46Z", "salary": {"currency": null, "max": null, "min": null, "period": "monthly", "term": null}, "salary_visible": false, "title_keywords": ["consultant", "assistant"], "responsibilities": ["management", "ad hoc", "food safety", "technical support", "audit", "hygiene", "cooperate with"], "requirements": {"degrees": ["higher diploma or above"], "majors": [], "languages": ["cantonese", "japanese", "english"], "language_level": ["advantage", "good command"], "hard_skills": [], "soft_skills": ["communication", "meticulous", "presentation skills"], "languages_combined": [{"language": "cantonese", "language_level": ["advantage", "good command"]}, {"language": "japanese", "language_level": ["advantage", "good command"]}, {"language": "english", "language_level": ["advantage", "good command"]}]}, "experience_required": {"duration": ["2 year"], "field": ["related", "food", "beverage industry"]}}, {"job_id": "100003009033862", "location_code": "hk", "company": "Koon Chun Hing Kee Soy & Sauce Factory Limited", "job_title": "Head of Quality Assurance (QA)", "description": "Responsibilities\n\nCoordinate product development projects of new health supplements, for instance, formulation design, ingredient research, production setup & monitoring, etc.\nConduct literature and market trend research such as overviews of disease management, latest research findings, competitor landscape, etc.\nDevelop educational materials on health, food and science that are on target per client needs and company\u2019s directions\nWork closely with internal stakeholders such as Marketing and Sales teams in market research and new product launch\nLiaise with CRO institutions on the project progress and results\n\nQualifications\n\nMaster's degree or above in Biological Sciences, Organic Chemistry, Immunology or medical-related disciplines, with at least 3 years work experience in healthcare/research industry\nExcellent written and verbal communications\u00a0in science\nSelf-motivated, well-organised and proactive\nProficiency in MS Office application - Excel, Word, PowerPoint, and key software applications relevant to literature research (e.g., EndNote, literature search indices, journal databases, BLAST, etc.)\nFluency in both written and spoken English & Chinese (Cantonese & Mandarin)", "employment_types": ["Full Time"], "selling_points": [], "locations": ["Yuen Long"], "categories": ["Hospitality / F & B", "Food & Beverage", "Sciences, Lab, R&D", "Food Science", "Manufacturing", "Quality Assurance, Control & Testing / ISO"], "post_time": "2022-01-10T01:59:00Z", "salary": {"currency": null, "max": null, "min": null, "period": "monthly", "term": null}, "salary_visible": false, "title_keywords": [], "responsibilities": ["management", "software", "monitoring", "teams", "market research", "design", "develop", "coordinate", "project progress", "databases", "liaise with", "setup"], "requirements": {"degrees": ["degree or above", "master"], "majors": ["related disciplines", "chemistry"], "languages": ["cantonese", "english", "chinese", "mandarin"], "language_level": ["fluency"], "hard_skills": ["excel", "word", "powerpoint", "databases", "ms office"], "soft_skills": ["well-organised", "self-motivated", "proactive"], "languages_combined": [{"language": "cantonese", "language_level": ["fluency"]}, {"language": "english", "language_level": ["fluency"]}, {"language": "chinese", "language_level": ["fluency"]}, {"language": "mandarin", "language_level": ["fluency"]}]}, "experience_required": {"duration": ["at least 3 years"], "field": ["related", "healthcare", "research", "medical"]}}, {"job_id": "100003009040227", "location_code": "hk", "company": "Intertek Testing Services H.K. Ltd.", "job_title": "Sales & Business Development Executive (Food)", "description": "Job Duties:\n\nTo undertake consultancy projects provided to clients in different industry sectors\nTo deliver training and audit related to system development project\nTo provide support on delivery and implementation of consultancy projects\nTo assist in organizing training, seminars and promotional events\n\n\nJob Requirements:\n\nBachelor Degree from disciplines such as Information Technology, Business, Quality Management, Food Science, Hotel Management or equivalent with 3 years\u2019 relevant experience\nHands-on implementation or consulting experience in management system such as ISO 22000, ISO 9000, ISO 14000, ISO 27001, ISO 45001, Hazard Analysis and Critical Control Points (HACCP) etc.\nExperience in internal auditor and project management is an advantage\nSelf-motivated and analytical with good communication skill\nExcellent command of both written and spoken English and Chinese\n\nCandidate with less experience can apply for Assistant Consultant.\n\n\u00a0\nA competitive salary package commensurate with academic qualifications and experience will be offered. Applicants should send application, together with a detailed resume, current and expected salary and contact telephone number by email\u00a0(quoting the reference number on the subject heading).\n\nPersonal data collected will be used for recruitment purpose only. Candidates not invited for interviews within 6 weeks may consider their applications unsuccessful and the applications will be disposed within 12 months.", "employment_types": ["Full Time", "Permanent"], "selling_points": ["Develop new business by different channels", "1 year experience in sales & marketing", "Proactive with good communication skill"], "locations": ["Lai Chi Kok"], "categories": ["Sales, CS & Business Devpt", "Business Development", "Sciences, Lab, R&D", "Food Science", "Account Servicing"], "post_time": "2022-01-12T01:56:44Z", "salary": {"currency": null, "max": null, "min": null, "period": "monthly", "term": null}, "salary_visible": false, "title_keywords": ["sales & business development executive"], "responsibilities": ["provide support", "implementation", "audit"], "requirements": {"degrees": ["degree", "bachelor"], "majors": ["hotel", "information technology", "business", "quality management", "food science"], "languages": ["english", "chinese"], "language_level": ["excellent"], "hard_skills": ["project management", "analysis"], "soft_skills": ["self-motivated", "communication skill", "project management", "hands-on", "detailed"], "languages_combined": [{"language": "english", "language_level": ["excellent"]}, {"language": "chinese", "language_level": ["excellent"]}]}, "experience_required": {"duration": ["3 years"], "field": ["management", "consulting", "information technology", "project management", "business", "relevant experience", "quality management", "food", "hotel management"]}}, {"job_id": "100003009004017", "location_code": "hk", "company": "Jardine Restaurant Group", "job_title": "Quality Assurance Assistant", "description": "Responsibilities:\nProvide technical support on food regulatory.\nMaintain regular QA activity to ensure food safety and quality standard are achieved.\nCoordinate work safety, quality assurance and hygiene procedures training to related staff.\nHandle and follow up the complaint cases related to food regulation.\nConduct routine food regulatory and labeling checking to implement ISO / HACCP policy.\nPrepare products\u2019 labels based on local regulatory requirements.\nLiaise with local / overseas food authority and customers on food regulation.\nRequirements:\nHigher Diploma / Degree holder or above in Food Science / Food and Nutrition or related disciplines.\nAbility to handle multiple tasks while maintaining attention to detail and accuracy, working under tight deadlines.\nSelf-motivated, independent, excellent problem-solving skills, and with good communication skill.\nGood command of spoken and written English and Chinese / Cantonese.\nProficient in PC applications including Chinese word and excel processing.\nCandidate with less experience will be considered as QA Assistant.\nInterested parties please apply with full resume, state current and expected salaries via e-mail by clicking \"Apply Now\".\n\nAll applications and data collected will be treated in strict confidence and used exclusively for recruitment purposes. Only short listed candidates will be invited for interview.\u00a0 The company will retain the applications for a maximum period of 24 months and may refer suitable candidates to other vacancies within the Group.", "employment_types": ["Full Time", "Permanent"], "selling_points": ["Conduct shop inspection and supplier audit", "1 year QA experience in Catering / Food Industry", "Knowledge of the hygiene regulations and HACCP"], "locations": ["Hung Hom"], "categories": ["Hospitality / F & B", "Food & Beverage", "Sciences, Lab, R&D", "Food Science"], "post_time": "2021-12-28T15:29:05Z", "salary": {"currency": null, "max": null, "min": null, "period": "monthly", "term": null}, "salary_visible": false, "title_keywords": ["quality assurance assistant"], "responsibilities": ["food safety", "technical support", "regulatory requirements", "quality", "procedures", "checking", "coordinate", "hygiene", "maintain", "liaise with"], "requirements": {"degrees": ["diploma", "degree holder"], "majors": ["related disciplines", "food science"], "languages": ["cantonese", "english", "chinese"], "language_level": ["good command", "proficient"], "hard_skills": ["excel", "word", "pc applications", "problem-solving skills", "processing"], "soft_skills": ["self-motivated", "independent", "communication skill", "handle multiple tasks", "attention to detail", "problem-solving skills"], "languages_combined": [{"language": "cantonese", "language_level": ["good command"]}, {"language": "english", "language_level": ["good command"]}, {"language": "chinese", "language_level": ["good command", "proficient"]}]}, "experience_required": {"duration": [], "field": ["qa"]}}, {"job_id": "100003009007266", "location_code": "hk", "company": "SGS Hong Kong Limited", "job_title": "Food Certification Auditor", "description": "Job Description:\n\nResponsible for the overall planning, coordination, management and the daily operations of the factory\nManage the production schedule, budgets, delivery and production in the factory\nEnhance the procedures and flows for the factory operations to ensure the productivity and efficiency also the\u00a0yielding of production section\nImprove the operational standards, SOP and instruction for food production process\nResponsible for improving the production capacity and ensure compliance of quality & safety system requirements\nResponsible to resolve the technique issue during production\nCoach and develop staff members to ensure that they deliver their best to achieve the company target\nAssist R&D team to convert the prototype into mass production\n\nQualifications and Requirements:\n\nTertiary education in Food Science/ Manufacturing Management/ Engineering or related disciplines\nAt least 10 years experience in food industry in which Chinese Culinary is an advantage\nGood knowledge in Food Safety Management Systems and Quality Management Systems\nExperience in developing system and procedures to maximize operational efficiency\nStrong leadership skills, self-motivated and able to build a disciplined production team with good morale\nDetailed, well planning, business acumen and problem-solving capability\nGood command of both spoken & written English and Mandarin\n\nAll personal data collected will be used for recruitment purpose only and kept confidential.", "employment_types": ["Full Time", "Permanent"], "selling_points": ["Double Pay and Performance Bonus", "Testing and Certification", "Food Science"], "locations": ["Shatin Area"], "categories": ["Sciences, Lab, R&D", "Food Science", "Laboratory", "Manufacturing", "Quality Assurance, Control & Testing / ISO"], "post_time": "2021-12-30T02:12:11Z", "salary": {"currency": null, "max": null, "min": null, "period": "monthly", "term": null}, "salary_visible": false, "title_keywords": [], "responsibilities": ["budgets", "management", "production process", "operations", "procedures", "quality", "ensure compliance", "develop", "daily operations", "schedule", "coordination", "planning"], "requirements": {"degrees": [], "majors": [], "languages": ["english", "chinese", "mandarin"], "language_level": ["advantage", "good command"], "hard_skills": ["problem-solving", "acumen"], "soft_skills": ["self-motivated", "leadership skills", "problem-solving", "business acumen", "detailed"], "languages_combined": [{"language": "english", "language_level": ["good command"]}, {"language": "chinese", "language_level": ["advantage"]}, {"language": "mandarin", "language_level": ["good command"]}]}, "experience_required": {"duration": ["at least 10 years"], "field": ["food industry", "developing"]}}, {"job_id": "100003009007344", "location_code": "hk", "company": "TUV Rheinland Hong Kong Limited", "job_title": "Project Chemist / Senior Project Chemist (Food Contact Materials)", "description": "Responsibilities\n\nEnforce and develop Quality Assurance System\nConduct shop inspection and supplier audit to ensure good hygiene environment and quality ingredients\nAssist in food safety related issue and support in Quality Assurance related projects\nProvide Quality Assurance administration supports to shop\n\nRequirements\n\nDiploma or above in Food Science or related discipline\n1 year relevant experience in Catering or Food Industry is preferred\nKnowledge of the hygiene regulations and HACCP is preferred\nProactive with good communication\nGood team player and able to work independently\nProficient in MS Word, Excel, PowerPoint and Chinese Word Processing\nGood command of Cantonese and English, Mandarin preferred", "employment_types": ["Full Time", "Permanent"], "selling_points": ["Project coordination", "Customer-orientated", "Immediately available is definitely an advantage"], "locations": ["Tsuen Wan Area"], "categories": ["Sciences, Lab, R&D", "Chemical", "Food Science", "Others"], "post_time": "2021-12-30T02:29:44Z", "salary": {"currency": null, "max": null, "min": null, "period": "monthly", "term": null}, "salary_visible": false, "title_keywords": ["chemist"], "responsibilities": ["food safety", "quality", "audit", "inspection", "develop", "hygiene", "administration"], "requirements": {"degrees": ["diploma or above"], "majors": ["food science"], "languages": ["cantonese", "english", "chinese", "mandarin"], "language_level": ["good command", "proficient"], "hard_skills": ["excel", "chinese word processing", "powerpoint", "ms word"], "soft_skills": ["communication", "good team player", "proactive", "work independently"], "languages_combined": [{"language": "cantonese", "language_level": ["good command"]}, {"language": "english", "language_level": ["good command"]}, {"language": "chinese", "language_level": ["proficient"]}, {"language": "mandarin", "language_level": ["good command"]}]}, "experience_required": {"duration": ["1 year"], "field": ["relevant experience", "food industry"]}}, {"job_id": "100003009007895", "location_code": "hk", "company": "Vita Green Pharmaceutical (H.K.) Limited", "job_title": "Senior Quality Assurance Officer (Food)", "description": "Job Description\n\n\n\nCarry out hygiene audit or supplier audit for registered firm based on global procedure and checklists provided by the company and provide integrity audits reports with recommendation to the customers\nCoordinate with the Technical and clerical staff to ensure efficient operation and optimum utilization of department service\nManage the project from the hygiene auditing program\nLiaise with personnel in other departments/divisions/affiliates regarding hygiene auditing and training arrangement\nInteract and communicate with customers relating to hygiene auditing, training and laboratory testing\nHelp to deal with client inquiries and complaints\nPlan and control job assignments so that high quality of work is maintained within a reasonable turnaround time\nKeep all auditing reports and training records in safe and good conditions\nPrepare hygiene training materials, design and tailor-made training course and conduct the training course to the customer\nDeliver Food Safety Training to public and in-house course\nUndertake any other duties when deemed as appropriate by the Section Mangers and Senior staff\n\n\nQualifications\n\n\n\nHigher Diploma, Degree or above in Food Science or other related disciplines\nMinimum 3 years of food related working experience\n\n\nAdditional Information\n\n\n\nAs a caring company, SGS not only offers a competitive remuneration package but also offers staff caring items to the right candidate, including:\n\n5-day Work Week\u00a0\nDouble Pay and Performance Bonus\nDental and Medical Benefits\nLife Insurance\nAnnual Leave\nBirthday Leave\nPaid Maternity Leave, Paternity Leave, and Marriage Leave\nOn-the-Job Training\u00a0\nEducation and Training Subsidies\nTransportation Subsidies\nShuttle Bus Service\nEmployee Assistance Program (EAP)\nCareer Advancement Opportunities\nStaff Activities", "employment_types": ["Full Time", "Permanent"], "selling_points": ["Great Promotion Opportunities", "Dynamic and Fun Working Culture", "Leading PIC/s GMP Manufacturer"], "locations": ["Tai Po Area"], "categories": ["Sciences, Lab, R&D", "Food Science", "Medical Services", "Pharmaceutical", "Research & Development (R&D)"], "post_time": "2021-12-30T05:07:17Z", "salary": {"currency": null, "max": null, "min": null, "period": "monthly", "term": null}, "salary_visible": false, "title_keywords": ["senior quality assurance officer"], "responsibilities": ["communicate with", "any other duties", "control", "food safety", "coordinate with", "audit", "quality", "testing", "design", "hygiene", "liaise with", "inquiries and complaints", "reports", "plan", "audits", "auditing"], "requirements": {"degrees": ["diploma", "degree or above"], "majors": ["related disciplines", "food science"], "languages": [], "language_level": [], "hard_skills": ["safe"], "soft_skills": ["efficient", "integrity"], "languages_combined": []}, "experience_required": {"duration": ["minimum 3 years"], "field": ["related", "food"]}}, {"job_id": "100003006699388", "location_code": "hk", "company": "Maxim's Caterers Ltd", "job_title": "Product Manager (Branded Products)", "description": "Job\u00a0Responsibilities:\n\n\n\n\u2022 Prepare and review test protocols and related quality documents for clients to fulfil chemical safety and legal compliance purpose of food contact materials\n\u2022 Check quotation, sample breakdown checklist, test result and test reports in accordance with related safety standards and specific chemical safety requirements food contact materials in worldwide\n\u2022 Monitor test project status and ensure the smooth running of assigned projects\n\u2022 Support the team to advise and make decision on the consumer product testing enquiry\u00a0\n\u2022 Work closely with internal departments and branch offices, also with local and Retails clients\n\u2022 Handle communication with customers for assigned projects and other enquires if necessary\n\u2022 Assist supervisor to provide training and supervise for the junior staff\n\u2022 Assist sales team and Business Lines for marketing, sales activities and provide training to external client if necessary\n\nJob Requirements:\n\n\n\n\u2022 Diploma or above in Sciences, or other disciplines\n\u2022 4-5 years working experience in commercial laboratory\n\u2022 Good knowledge in EU, Germany, US worldwide chemical requirements of food contact materials is preferable\n\u2022 Good command of both written and spoken English and Chinese/ Putonghua\n\u2022 Proficiency in PC operation, excellent in MS words & Excel\n\u2022 Excellent communication skills, self-motivated, team and customer orientated\n\u2022 Immediate available is preferred\u00a0\n\nOther Benefits:\n\nPublic Holidays\nDouble Pay and Performance Bonus\nMedical, Dental and Life Insurance\nAnnual Leave, Maternity Leave, Paternity Leave, Marriage Leave, Compassionate Leave\nOn-the-job training as well as Training Sponsorship/ Subsidies\n\nApplications:\n\nInterested parties please send your full resume with expected salary and date available to the Human Resources Department by clicking \"Apply Now\".\n\nAll information received will be kept in strict confidence and used for employment purpose only. Applicants who are not invited for interview within\u00a05 weeks may assume their applications unsuccessful and their data will be retained for 6 months for other suitable vacancies in our organization and thereafter destroyed.", "employment_types": ["Full Time", "Permanent"], "selling_points": ["Lead product development direction and process", "Manage feedback from customers and trade partners", "Project management and internal coordination"], "locations": ["Lai Chi Kok"], "categories": ["Hospitality / F & B", "Food & Beverage", "Sciences, Lab, R&D", "Food Science", "Marketing / Public Relations", "Marketing - Brand / Product Management"], "post_time": "2022-01-01T16:49:30Z", "salary": {"currency": null, "max": null, "min": null, "period": null, "term": null}, "salary_visible": false, "title_keywords": ["product manager"], "responsibilities": ["provide training", "sales activities", "quotation", "compliance", "review", "quality", "monitor", "testing", "communication", "reports", "contact", "sales team", "safety standards", "support the team"], "requirements": {"degrees": ["diploma or above"], "majors": [], "languages": ["putonghua", "english", "chinese"], "language_level": ["good command"], "hard_skills": ["pc", "excel", "ms words"], "soft_skills": ["communication skills", "self-motivated"], "languages_combined": [{"language": "putonghua", "language_level": ["good command"]}, {"language": "english", "language_level": ["good command"]}, {"language": "chinese", "language_level": ["good command"]}]}, "experience_required": {"duration": ["4-5 years"], "field": ["commercial laboratory"]}}, {"job_id": "100003009008816", "location_code": "hk", "company": "Bright Future Pharmaceutical Laboratories Ltd", "job_title": "QC Analyst", "description": "Responsibilities:\n\nTake charge of Branded Products' mid to long term product development direction, process and work closely with internal partners such as factories\u2019 R&D team, Supply Chain and Sales, etc.\nManage customers\u2019 and trade partners\u2019 feedback on branded products, follow up with related parties for improvement measures when required.\nSupport Sales Team with\u00a0product information, and sales forecast for new products.\nManage project timeframe, coordinate with different parties to follow the set timeline\nManage packaging activities, outer pack dimension, material and cost negotiation as well as abuse test\nLiaise with QA/QC team regarding product complaints and labelling\nProvide insight on product pricing strategies.\nProvide marketing strategies input for new products.\nResearch and keep track of market trend.\n\nRequirements:\n\nAt least 8 years' experience in related role;\nA degree holder, preferably with food science background;\nStrong analytical capacity, good communication and people management skill;\nGood planning, time management and presentation skills required;\nExcellent Microsoft Office application\nInterested parties please apply with full resume, state current and expected salaries via 'Apply Now'.\n\nAll applications and data collected will be treated in strict confidence and used exclusively for recruitment purposes.\u00a0 Only short-listed candidates will be invited for interview. The company will retain the applications for a maximum period of 6 months and may refer suitable candidates to other vacancies within the Group.", "employment_types": ["Full Time"], "selling_points": ["Gas chromatography analytical test", "Familiar with operating the Gas chromatograph", "5 days\u2019 work, free luncheon and shuttle bus"], "locations": ["Yuen Long"], "categories": ["Sciences, Lab, R&D", "Food Science", "Research & Development (R&D)"], "post_time": "2021-12-30T09:18:21Z", "salary": {"currency": null, "max": null, "min": null, "period": "monthly", "term": null}, "salary_visible": false, "title_keywords": ["analyst"], "responsibilities": ["cost", "marketing strategies", "coordinate with", "sales team", "forecast", "liaise with"], "requirements": {"degrees": ["degree holder"], "majors": ["food science"], "languages": [], "language_level": [], "hard_skills": ["microsoft office"], "soft_skills": ["communication", "presentation skills", "time management"], "languages_combined": []}, "experience_required": {"duration": ["at least 8 years"], "field": ["related"]}}, {"job_id": "100003009011235", "location_code": "hk", "company": "TUV SUD Hong Kong Limited", "job_title": "Assistant Test Engineer / Test Engineer  - Chemical Lab (Fresh Graduate Welcome)", "description": "Job Description\nAbout Bright Future\nFounded in 1993, Bright Future is a Hong Kong research-based leading multinational pharmaceutical company focused on skin health, pediatrics, respiratory and pain management. With experience and capabilities in the development, manufacturing and commercialization of prescription medications, OTC products and health functional products, Bright Future puts quality of life first and is committed to offering excellent health solutions to make every life healthier. As is our vision:\u00a0 \u201cbrighter life better future\u201d.\nTo cope with our business expansion and new product development, we are looking for the right talent to join our growing Hong Kong office.\nJob Title : QC Analyst (Gas chromatograph)\n\nJob Description:\n\n\nResponsible for Gas chromatography analytical test, including method development and method validation\u00a0\nPrepare method validation protocols, reports, and relevant GMP documents\nDaily maintenance of Gas chromatograph\n\nRequirements:\n\nBachelor or above, major in chemistry/ Chinese medicines / drug analysis/ science or related fields\n2 years of GC operation experience\u00a0\nHave knowledge of daily maintenance of Gas chromatograph\nWe offer 5-day work with good career prospects and excellent fringe benefits to the right candidates\u00a0including shuttle bus, medical insurance, free luncheon, and discretionary bonus.\n\nInterested parties please send your full resume stating your current and expected salary and date of availability to the Human Resources Department by clicking Apply NOW.\n(Data collected will be used for recruitment purposes only.)", "employment_types": ["Full Time", "Permanent"], "selling_points": ["Higher Diploma/ Degree holder in Chemistry", "Prepare samples by various digestion", "Able to work independently and under pressure"], "locations": ["Yuen Long Area"], "categories": ["Sciences, Lab, R&D", "Chemical", "Food Science", "Laboratory"], "post_time": "2021-12-31T06:47:43Z", "salary": {"currency": null, "max": null, "min": null, "period": "monthly", "term": null}, "salary_visible": false, "title_keywords": ["chemical", "engineer", "assistant"], "responsibilities": ["management", "maintenance", "quality", "commercialization", "reports"], "requirements": {"degrees": ["bachelor"], "majors": ["science", "chemistry"], "languages": ["chinese"], "language_level": [], "hard_skills": ["analysis", "maintenance"], "soft_skills": [], "languages_combined": [{"language": "chinese", "language_level": []}]}, "experience_required": {"duration": ["2 years"], "field": ["operation"]}}, {"job_id": "100003009008778", "location_code": "hk", "company": "Bright Future Pharmaceutical Laboratories Ltd", "job_title": "Analytical Research", "description": "Job Description\nAbout Bright Future\nFounded in 1993, Bright Future is a Hong Kong research-based leading multinational pharmaceutical company focused on skin health, pediatrics, respiratory and pain management. With experience and capabilities in the development, manufacturing and commercialization of prescription medications, OTC products and health functional products, Bright Future puts quality of life first and is committed to offering excellent health solutions to make every life healthier. As is our vision:\u00a0 \u201cbrighter life better future\u201d.\nTo cope with our business expansion and new product development, we are looking for the right talent to join our growing Hong Kong office.\nJob Title : QC Analyst (\u00a0Analytical Research)\n\nJob Description:\n\n\nResponsible for the analytical test (routine test and stability study)\nExecute method validation, calculate/ summarize analytical data and prepare relevant documents\nAssist in Method development and Method transfer\nLab equipment maintenance and calibration\n\nRequirements:\n\nBachelor or above, major in chemistry/ Chinese medicines / drug analysis/ science or related fields\nCandidate with less experience will be considered for the position of Technician\u00a0\nCandidate with more experience will be considered for the position of Chemist (Researcher)\u00a0\nExperience with method validation in GMP Lab is a plus\nFresh graduates and IANG are also welcomed\nWe offer 5-day work with good career prospects and excellent fringe benefits to the right candidates\u00a0including shuttle bus, medical insurance, free luncheon, and discretionary bonus.\n\nInterested parties please send your full resume stating your current and expected salary and date of availability to the Human Resources Department by clicking Apply NOW.\n(Data collected will be used for recruitment purposes only.)", "employment_types": ["Full Time"], "selling_points": ["Responsible for analytical test", "Exp. with method validation in GMP Lab is a plus", "5 days work, free luncheon and shuttle bus"], "locations": ["Yuen Long"], "categories": ["Sciences, Lab, R&D", "Food Science", "Research & Development (R&D)"], "post_time": "2021-12-30T09:09:52Z", "salary": {"currency": null, "max": null, "min": null, "period": "monthly", "term": null}, "salary_visible": false, "title_keywords": [], "responsibilities": ["management", "maintenance", "data", "quality", "commercialization"], "requirements": {"degrees": ["bachelor"], "majors": ["science", "chemistry"], "languages": ["chinese"], "language_level": [], "hard_skills": ["analysis", "plus"], "soft_skills": [], "languages_combined": [{"language": "chinese", "language_level": []}]}, "experience_required": {"duration": [], "field": []}}, {"job_id": "100003009003855", "location_code": "hk", "company": "Maxim's Caterers Ltd", "job_title": "Quality Assurance Specialist", "description": "Job Responsibilities:\u00a0\n\nImplement Food and Quality Standards in Raw Materials Management\u00a0\nReview New Materials Specification and update existing materials regularly\nMonitor progress of Raw Materials Specification review and relevant complaint follow-up\nCommunicate with business Unit on technical information of Raw Materials\nJob Specifications:\n\nBachelor Degree holder in Food Science or equivalent\n1-2 years' work experience as Quality Assurance person in Food or Catering Business\nCommunication, Interpersonal and Problem-solving skill\nExperience in QA work at Regulation Compliance is ideal. Less experience will be considered as assistant specialist.", "employment_types": ["Full Time", "Permanent"], "selling_points": ["Degree holder in Food Science", "1-2 years of relevant experiences is preferred", "Welcome fresh graduates"], "locations": ["Lai Chi Kok"], "categories": ["Hospitality / F & B", "Food & Beverage", "Sciences, Lab, R&D", "Food Science", "Others"], "post_time": "2021-12-28T11:07:58Z", "salary": {"currency": null, "max": null, "min": null, "period": null, "term": null}, "salary_visible": false, "title_keywords": ["specialist"], "responsibilities": ["communicate with", "management", "monitor progress", "review", "quality", "compliance", "communication", "specifications", "catering"], "requirements": {"degrees": ["bachelor degree holder"], "majors": ["food science"], "languages": [], "language_level": [], "hard_skills": ["problem-solving"], "soft_skills": ["communication", "problem-solving", "interpersonal", "ideal"], "languages_combined": []}, "experience_required": {"duration": ["1-2 years"], "field": ["qa", "compliance", "business", "food", "quality assurance"]}}, {"job_id": "100003009005410", "location_code": "hk", "company": "Maxim's Caterers Ltd", "job_title": "Research and Development Manager (Cakes & Bakery)", "description": "About the job:\nYou will be working in a growing department with a team of specialist. You will participate in quality systems processes including deviation, change and document control, production line clearance as well as internal and external audits. You will also be involved in the enhancement of our quality systems processes. This role will let you acquire solid experience of PIC/s GMP standard and gain supervisory experience. With a fast-growing business like us, there are always opportunities and possibilities for the right talent!\n\n\n\nAbout the talent:\n\nBachelor\u2019s degree or above in Science.\n1-3 years GMP experience in the pharmaceutical or food industry is highly preferable.\nKnowledge of HACCP and GMP/PICS is preferable.\nProactive, good communication and able to be a good team player.\nMore experienced candidates will be considered as Senior QA Officer, less experienced candidates will be considered as QA Officer.\n\nWhat we offer:\n\nCareer with the market leader in health product sector from Hong Kong\nDynamic working culture with great team spirit\nShuttle to/from Yau Tong, Kowloon Tong, Tai Wai, Tai Po, Tuen Mun, Tsuen Wan, Tin Shui Wai and Causeway Bay\nRapid growth opportunities for strong performers\nStaff purchase discount\nCasual wear at work", "employment_types": ["Full Time", "Permanent"], "selling_points": ["Competitive Remuneration", "Birthday Leave", "Excellent Career Development"], "locations": ["Tai Po Area"], "categories": ["Sciences, Lab, R&D", "Food Science", "Laboratory", "Manufacturing", "Quality Assurance, Control & Testing / ISO"], "post_time": "2021-12-29T03:50:53Z", "salary": {"currency": null, "max": null, "min": null, "period": "monthly", "term": null}, "salary_visible": false, "title_keywords": ["manager"], "responsibilities": ["control", "systems", "quality", "internal and external audits", "communication"], "requirements": {"degrees": ["degree or above", "bachelor"], "majors": ["science"], "languages": [], "language_level": [], "hard_skills": [], "soft_skills": ["communication", "good team player", "proactive"], "languages_combined": []}, "experience_required": {"duration": ["1-3 years"], "field": ["pharmaceutical", "food industry", "supervisory experience"]}}, {"job_id": "100003008998781", "location_code": "hk", "company": "Maxim's Caterers Ltd", "job_title": "Senior Food System Technologist / Food System Technologist", "description": "Job Responsibiliies:\n\nManage the full cycle of product development timeline, cost estimation, production trial, shelf life testing arrangement, specification information analysis and setting and documentation\nCommunicate with different parties, including Production, Procurement, Quality Assurance, chef & etc. to facilitate product development work\nKeep abreast of food regulatory standards of different countries\nParticipate in other ad-hoc projects as assigned\nRequirements:\n\nDegree in Food Science or related disciplines\n10 years relevant working experience in food industry\nFamiliar with ISO9001, 22000, HACCP, GMP\nFamiliar with food regulatory standards of different countries\nSelf-motivated, independent and able to work under pressure\nWell organized with good interpersonal and communication skill\nProficient in MS Office applications and Chinese Word Processing\nCandidate with less experience will be considered as Assistant Manager\nWork location: Tai Po Industrial Estate (shuttle bus will be provided)\nInterested parties please apply with full resume, state current and expected salaries by clicking \"Apply Now\". All applications and data collected will be treated in strict confidence and used exclusively for recruitment purposes. Only short listed candidates will be invited for interview. The company will retain the applications for a maximum period of 24 months and may refer suitable candidates to other vacancies within the Group.", "employment_types": ["Full Time", "Permanent"], "selling_points": ["Develop and implement food safety & QA Sys", "Execute HACCP, ISO 22000 and FSSC 22000 program", "3 years\u2019 related experience"], "locations": ["Tai Po Area"], "categories": ["Sciences, Lab, R&D", "Food Science"], "post_time": "2021-12-24T04:16:57Z", "salary": {"currency": null, "max": null, "min": null, "period": "monthly", "term": null}, "salary_visible": false, "title_keywords": [], "responsibilities": ["communicate with", "cost estimation", "analysis", "quality", "testing", "documentation", "ad-hoc projects"], "requirements": {"degrees": ["degree"], "majors": ["related disciplines", "food science"], "languages": ["chinese"], "language_level": ["proficient"], "hard_skills": ["chinese word processing", "ms office"], "soft_skills": ["self-motivated", "independent", "communication skill", "well organized", "interpersonal", "work under pressure"], "languages_combined": [{"language": "chinese", "language_level": ["proficient"]}]}, "experience_required": {"duration": ["10 years"], "field": ["food industry", "relevant working experience"]}}, {"job_id": "100003008998338", "location_code": "hk", "company": "Tao Heung Group Limited", "job_title": "QA Manager", "description": "Responsibilities\n\nDevelop and implement food safety and quality assurance system\nSet up and execute HACCP, ISO 22000 and FSSC 22000 program\nConduct internal hygiene audits and site inspections\nHave good problem-solving skills on quality issue\nAssist in ad-hoc assignment as required\n\nJob requirements\n\nDegree holder in Food Science or related disciplines\nAs least 3 years\u2019 experience in food processing quality management role\nKnowledge and experience in quality management system (HACCP, ISO 22000, FSSC 22000)\nKnowledge of food processing technology\nKnowledge on Hong Kong & Mainland China food regulations is preferred\nSound PC operation including MS Word and Excel\nGood command of both written & spoken English & Chinese\nStrong leadership, communication & interpersonal skills\n\nLess experience will be considered as Food System Technologist", "employment_types": ["Full Time", "Permanent"], "selling_points": ["Food & Beverage", "Quality Assurance", "Food Science/Food Safety"], "locations": ["Tai Po Area"], "categories": ["Hospitality / F & B", "Food & Beverage", "Sciences, Lab, R&D", "Food Science", "Manufacturing", "Quality Assurance, Control & Testing / ISO"], "post_time": "2021-12-24T03:13:29Z", "salary": {"currency": null, "max": null, "min": null, "period": "monthly", "term": null}, "salary_visible": false, "title_keywords": ["manager"], "responsibilities": ["ad-hoc", "food safety", "quality", "develop", "hygiene", "site inspections", "audits"], "requirements": {"degrees": ["degree holder"], "majors": ["related disciplines", "food science"], "languages": ["english", "chinese"], "language_level": ["good command"], "hard_skills": ["pc", "processing", "excel", "ms word"], "soft_skills": ["communication", "leadership", "interpersonal skills"], "languages_combined": [{"language": "english", "language_level": ["good command"]}, {"language": "chinese", "language_level": ["good command"]}]}, "experience_required": {"duration": ["least 3 years"], "field": ["food", "quality management"]}}, {"job_id": "100003008998448", "location_code": "hk", "company": "Bao Dim Sin Seng Limited", "job_title": "Quality Assurance Inspector / Assistant (Supermarket/Food Factory)", "description": "Working in Tao Heung Group, besides remuneration and benefits, you can also\n1) Get a chance to work in one of the largest F&B groups,\n2) Get cross-border exposure, and\n3) Get some challenging yet fulfilling and rewarding experience.\n\nPlease join us as:\n\nQA Manager\n\nQuality Assurance Team\n\nJob Description:\n\nDesign, implement, and improve company quality standards to achieve quality goals;\nConduct factory and outlets audits to identify any deviations from quality, hygiene and food safety standards;\nPerform regular review of the manufacturing standard operating procedures (SOP) to ensure higher-quality goods and increase productivity;\nCoordinate and follow through external audits by customers and third-party accreditation bodies;\nInvestigate customer complaints related to food quality.\n\nJob Requirements:\n\nDegree in Food science, Food safety or related disciplines;\nFamiliar with ISO22000 or ISO9000 and HACCP implementation;\n5 years' relevant experience in QA management, with food industry experience would be an advantage;\nIndependent, fast-paced, multi-tasking, result-oriented and self-motivated.\nInterested parties please apply with resume, current salary, expected salary and contact numbers to the Human Resources Manager, Tao Heung Group Ltd. by clicking \"APPLY NOW\".\n\nApplication letters collected will be used for recruitment purpose only.", "employment_types": ["Full Time", "Permanent"], "selling_points": ["ISO 22000", "HACCP", "Fresh graduate is welcome"], "locations": ["Not Specified"], "categories": ["Hospitality / F & B", "Food & Beverage", "Sciences, Lab, R&D", "Food Science", "Manufacturing", "Quality Assurance, Control & Testing / ISO"], "post_time": "2021-12-24T03:34:21Z", "salary": {"currency": null, "max": null, "min": null, "period": "monthly", "term": null}, "salary_visible": false, "title_keywords": ["quality assurance inspector", "assistant"], "responsibilities": [], "requirements": {"degrees": [], "majors": [], "languages": [], "language_level": [], "hard_skills": [], "soft_skills": [], "languages_combined": []}, "experience_required": {"duration": [], "field": []}}, {"job_id": "100003008993881", "location_code": "hk", "company": "International Housewares Retail Company Limited", "job_title": "Quality Assurance Officer / Product Safety Officer", "description": "Responsibilities:\n\nTo handle daily quality assurance activities\nTo conduct Food manufacturing / Supermarket\u00a0 \u00a0audit in time according to company requirements\nTo review and update processing flow chart and products specification\nTo oversee and manage all specifications of our products with risk management approach\nTo investigate and handle complaints related to food quality\nAssist the ad-hoc projects as assigned\n\nRequirements:\n\nTertiary education in Business Management / Food Safety or related disciplines\nKnowledge on\u00a0HACCP & ISO22000 is preferred\n1-2 years relevant working experience in\u00a0Food manufacturing audit\u00a0 / Supermarket /Food store is preferred\nProficient in MS Office application (Excel, Word & PowerPoint) and Chinese Word Processing\nBe proactive, self-motivated and work independently\nGood time management skill, well-organized with strong analytical mind\nImmediate available is highly preferred\nFresh graduate is welcome\n\nInterested parties, please send your detailed resume, availability, present and expected salary to Human Resources Department by clicking \u201cApply Now\u201d.\n\nWe are an equal opportunity employer. Applications from all qualified candidates are welcome.\n\nAll information collected will be used for recruitment related purpose only.\u00a0", "employment_types": ["Full Time", "Permanent"], "selling_points": ["Good knowledge of food labeling", "Develop and review labeling of Food / FMGC product", "Relevant experience in food/ retail /FMCG industry"], "locations": ["Southern Area"], "categories": ["Sciences, Lab, R&D", "Food Science", "Manufacturing", "Quality Assurance, Control & Testing / ISO", "Sales, CS & Business Devpt", "Retail Sales"], "post_time": "2021-12-22T09:39:23Z", "salary": {"currency": null, "max": null, "min": null, "period": "monthly", "term": null}, "salary_visible": false, "title_keywords": ["quality assurance officer", "safety officer"], "responsibilities": ["management", "review", "quality", "audit", "handle complaints", "specifications", "ad-hoc projects"], "requirements": {"degrees": ["fresh graduate"], "majors": [], "languages": ["chinese"], "language_level": ["proficient"], "hard_skills": ["business management", "excel", "chinese word processing", "word", "powerpoint", "ms office"], "soft_skills": ["self-motivated", "work independently", "well-organized", "analytical mind", "time management skill", "proactive"], "languages_combined": [{"language": "chinese", "language_level": ["proficient"]}]}, "experience_required": {"duration": ["1-2 years"], "field": ["food manufacturing", "food store", "relevant working experience", "audit"]}}, {"job_id": "100003008996408", "location_code": "hk", "company": "The Hong Kong Standards And Testing Centre Ltd", "job_title": "Assistant Chemist / Technical Officer (Traditional Chinese Medicine Products Testing)", "description": "Responsibilities:\n\n\nDevelop and review labeling of Food / FMGC products to ensure compliance with legal requirements and regulations in Hong Kong\nWork closely with merchandising team / supplier on the labeling details\nUpdate local and overseas food and label regulation\nFollow up the quality and labeling issues\nAssist in ad hoc projects as assigned\nRequirements:\n\nDegree or above in Nutritional Chemistry/ Food Science or related disciplines\n2 years\u2019 relevant experience in food/ retail / FMCG industry\nGood knowledge of food labeling\nDetail-minded, well-organized, self-motivated and willing to take up challenges\nTeam-player, willing to learn and with good communication and problem-solving skills\nProficient in MS applications and Chinese Word processing, knowledge in SAP will be an advantage\nWe offer attractive salary and benefits to the right candidates. \u00a0Interested parties please send full resume with present and expected salary\u00a0by clicking \"Apply Now\".\nPersonal data will be used for recruitment purpose only", "employment_types": ["Full Time", "Permanent"], "selling_points": ["Higher Diploma or above in Analytical Chemistry", "1-2 years working experience in testing laboratory", "Free Shuttle Bus, Education & Training allowance"], "locations": ["Tai Po Area"], "categories": ["Sciences, Lab, R&D", "Chemical", "Food Science", "Laboratory"], "post_time": "2021-12-23T07:04:59Z", "salary": {"currency": null, "max": null, "min": null, "period": "monthly", "term": null}, "salary_visible": false, "title_keywords": ["technical officer", "assistant", "chemist"], "responsibilities": ["regulations", "review", "merchandising", "quality", "ensure compliance", "develop", "ad hoc projects"], "requirements": {"degrees": ["degree or above"], "majors": ["related disciplines", "nutritional chemistry", "food science"], "languages": ["chinese"], "language_level": ["advantage", "proficient"], "hard_skills": ["chinese word processing", "ms applications", "sap", "fmcg industry", "problem-solving skills"], "soft_skills": ["detail-minded", "self-motivated", "team-player", "willing to learn", "well-organized", "communication", "problem-solving skills"], "languages_combined": [{"language": "chinese", "language_level": ["advantage", "proficient"]}]}, "experience_required": {"duration": ["2 years"], "field": ["food", "retail", "relevant experience", "fmcg"]}}, {"job_id": "100003008987858", "location_code": "hk", "company": "Delivery Hero Food Hong Kong Limited", "job_title": "Quality Assurance Executive", "description": "Responsibilities:\n\nTo assist Traditional Chinese Medicine\u00a0group leader.\nTo conduct chemical test on routine Traditional Chinese Medicine\u00a0sample.\nTo assist the team to perform method development and validation for new test methods.\nTo assist the team to maintain good quality system as to fulfill HOKLAS/CNAS. requirements\n\n\u00a0Requirements:\n\nHigher Diploma or above in Chinese Medicine / Analytical Chemistry or equivalent.\nExperienced on TCM/CMM analysis by TLC, HPLC, GC instruments are preferred.\nKnowledge of HOKLAS/CNAS system is preferred.\nWork under pressure, initiative, organized and independent.\nFresh graduate will also be considered.\n\nBenefits:\n\n5-day work week (Mon - Fri)\nEducation & Training allowance\nDouble pay &\u00a0Performance bonus\nFree shuttle bus\nLife & Medical insurance\nOvertime allowance\nAnnual leave, Birthday leave, Marriage leave\nCompany\u00a0activities\n\nInterested parties please send your resume\u00a0with availability, present\u00a0salary\u00a0and expected salary to our Human Resources Department by Clicking \"Apply Now\"\u00a0/ By Fax: 2664 4353:/ By Post: STC, 10 Dai Wang Street, Tai Po Industrial Estate, Tai Po, NT\n\nWelcome to visit our company website\u00a0www.stc.group for corporate information.\n\n(All personal data collected are for recruitment purposes only.)\u00a0", "employment_types": ["Full Time", "Permanent"], "selling_points": ["Opportunity to join a rapidly growing business", "Environment for grooming and personal growth", "Steep learning curve in entrepreneurial culture"], "locations": ["Causeway Bay"], "categories": ["Hospitality / F & B", "Food & Beverage", "Sciences, Lab, R&D", "Food Science", "Manufacturing", "Quality Assurance, Control & Testing / ISO"], "post_time": "2021-12-20T08:20:18Z", "salary": {"currency": null, "max": null, "min": null, "period": "monthly", "term": null}, "salary_visible": false, "title_keywords": ["executive"], "responsibilities": ["maintain", "quality"], "requirements": {"degrees": ["higher diploma or above", "fresh graduate"], "majors": ["analytical chemistry"], "languages": ["chinese"], "language_level": [], "hard_skills": ["analysis"], "soft_skills": ["organized", "independent", "initiative", "work under pressure"], "languages_combined": [{"language": "chinese", "language_level": []}]}, "experience_required": {"duration": [], "field": []}}, {"job_id": "100003008989402", "location_code": "hk", "company": "Delivery Hero Food Hong Kong Limited", "job_title": "Training Manager - Kitchens & Concepts", "description": "'Hungry to make a difference? Then foodpanda may be the place for you!'\n\n\u00a0At foodpanda, we\u2019re on a mission to redefine customers\u2019 food and shopping experience as a multifaceted online platform across the 14 countries we operate in. We\u2019re all about bringing on the smartest and brightest minds as we continue to grow in a fast-moving and agile environment, and hiring those who can thrive in an energetic and hardworking start-up culture. We strive to become everybody\u2019s most loved delivery platform, however, this won't happen without some really awesome people!\n\nWe are looking for a highly-driven and motivated\u00a0Quality Assurance Executive\u00a0to join our fun, professional and dedicated Shared Kitchens Department based here in Hong Kong. Shared Kitchens is a new division at foodpanda, aiming to provide our customers and vendors with exciting new cuisine choices. Wait no longer and join us if you want to make a direct and visible impact and contribute to large-scale success!\u00a0\u00a0\n\nKnow more about the team\n\nOur operations team within Shared Kitchens works closely with culinary experts in creating virtual brands. As an operations professional, you will take the initiative in discovering new brand opportunities and developing virtual brand models for business growth. Aiming to bring in more cuisine varieties into different areas, you will play a vital role in ensuring all brands are performing to best in class standards.\u00a0\n\nRoles and Responsibilities:\n\nManage quality programs, production process, implements Quality Assurance & Quality Control strategies\nLead the implementation of quality related projects, including new requirements, continuous improvement projects, corrective plans etc.\nConduct internal hygiene audits and vendor site inspections\nResearch and introduce any new related quality requirements, tools and technologies as needed to support the Shared Kitchens business.\nAdvise management and vendors on the overall quality standard of products and suggest future strategies\nDevelop food safety procedures / standards according to foodpanda local and regional QA policy\n\nJob Requirements\n\nDegree or above in Food Science or related disciplines\n2 years of relevant experience in food manufacturing / food retail business / F&B business\nFamiliar with Hong Kong food law or relevant regulatory\nFamiliar with quality assurance systems (HACCP and ISO) and certification standards\nExcellent analytical, communication and interpersonal skills.\nDetail-oriented with strong organisational skills\nGood knowledge of MS Office and Google Suite is highly preferable\n\nWhat We Offer\n\nA dynamic, fast paced environment\nA vibrant and international team with diverse background\nSteep learning curve in e-commerce & entrepreneurship\nLearning & development programs and skills trainings\u00a0\nFlexible working hours and agile company with a flat hierarchical structure\nMonthly staff allowance and corporate discounts including at restaurants, gyms and many more\nAgile office environment with a fully-stocked beverage fridge and self-serve beer\u00a0\nUnlimited paid leave policy", "employment_types": ["Full Time", "Permanent"], "selling_points": ["Opportunity to join a rapidly growing business", "Environment for grooming and personal growth", "Steep learning curve in entrepreneurial culture"], "locations": ["Causeway Bay"], "categories": ["Hospitality / F & B", "Food & Beverage", "Sciences, Lab, R&D", "Food Science", "Admin & HR", "Training & Development"], "post_time": "2021-12-21T03:33:45Z", "salary": {"currency": null, "max": null, "min": null, "period": "monthly", "term": null}, "salary_visible": false, "title_keywords": ["manager"], "responsibilities": ["continuous improvement projects", "management", "production process", "food safety", "quality", "implementation", "procedures", "develop", "hygiene", "quality control", "site inspections", "audits", "plans"], "requirements": {"degrees": ["degree or above"], "majors": ["related disciplines", "food science"], "languages": [], "language_level": [], "hard_skills": ["ms office"], "soft_skills": ["communication and interpersonal skills", "organisational skills", "detail-oriented"], "languages_combined": []}, "experience_required": {"duration": ["2 years"], "field": ["food manufacturing", "f&b", "business", "relevant experience", "food", "retail"]}}, {"job_id": "100003008988784", "location_code": "hk", "company": "Tsit Wing Coffee Co Ltd", "job_title": "Coffee Trainer", "description": "'Hungry to make a difference? Then foodpanda may be the place for you!'\n\nAt foodpanda, we\u2019re on a mission to redefine customers\u2019 food and shopping experience as a multifaceted online platform across the 14 countries we operate in. We\u2019re all about bringing on the smartest and brightest minds as we continue to grow in a fast-moving and agile environment, and hiring those who can thrive in an energetic and hardworking start-up culture. We strive to become everybody\u2019s most loved delivery platform, however, this won't happen without some really awesome people!\n\nWe are looking for a highly-driven and motivated\u00a0Training Manager\u00a0to join our fun, professional and dedicated Kitchens & Concepts Department based here in Hong Kong. Kitchens & Concepts is a vertical established in 2020 that has now reached its hyper-growth phase.\u00a0 At the core, this vertical develops its own virtual food brands (made available only on delivery) with the help of R&D chefs, that are then franchised to existing restaurants\u2019 kitchens.\u00a0\n\nWait no longer and join us if you want to make a direct and visible impact and contribute to large-scale success!\u00a0\u00a0\n\nKnow more about the team\n\nOur R&D team within Kitchen & Concepts works closely with culinary experts in creating virtual brands. As an operations professional, you will take the initiative in discovering new brand opportunities and developing virtual brand models for business growth. Aiming to bring in more cuisine varieties into different areas, you will play a vital role in ensuring all brands are performing to best in class standards.\u00a0\n\nRoles & Responsibilities:\n\nOversee foodpanda training implementation for concepts via web-based and physical methods, delivering group sessions, training videos, gamified training and \u2018how to\u2019 guides.\nWorking with Culinary Manager in SOP content formation, ensuring simple and compact contents of existing and future brand training guides\u00a0\nConstantly review training methods and results for improvements.\nSchedule and run training sessions of new content and refresher training with restaurants\nOwn the CX metrics for the concepts and kitchens\nEnsure concept launches on time in each country\nAbility to challenge concepts menus for speed (preparation time) and quality control (CX)\nResponsible for maintaining above market average customer ratings for foodpanda concepts through menu feedback tools and identifying re-training needs of vendors.\nLiaison with country QC/Operations managers on all aspects of vendor training during onboarding and after.\nIdentify learning issues and adapt training methods to ensure a high level of execution.\nCreate monthly updates on associated KPI\u2019s\n\nQualifications & Requirements:\n\nOver 3 years of experience as a Training Specialist, Area Trainer or similar role within a leading fast food/QSR chain\nBachelor's Degree in Hospitality Management/F&B Facilities Management, Culinary Arts or equivalent\nExperience in F&B chains, retail or franchised networks will be an added advantage\nKnowledge of virtual training platforms\nKnowledge of various training and teaching methods\nProficiency in Google tools and database software\n\n\n\nWhat We Offer\n\nA dynamic, fast paced environment\nA vibrant and international team with diverse background\nSteep learning curve in e-commerce & entrepreneurship\nLearning & development programs and skills trainings\u00a0\nFlexible working hours and agile company with a flat hierarchical structure\nMonthly staff allowance and corporate discounts including at restaurants, gyms and many more\nUnlimited paid leave policy", "employment_types": ["Full Time", "Permanent"], "selling_points": [], "locations": ["Kwai Fong"], "categories": ["Hospitality / F & B", "Food & Beverage", "Sciences, Lab, R&D", "Food Science", "Research & Development (R&D)"], "post_time": "2021-12-21T01:17:16Z", "salary": {"currency": null, "max": null, "min": null, "period": "monthly", "term": null}, "salary_visible": false, "title_keywords": ["coffee trainer"], "responsibilities": ["maintaining", "operations", "review", "implementation", "schedule", "quality control", "contents"], "requirements": {"degrees": ["degree", "bachelor"], "majors": ["hospitality management"], "languages": [], "language_level": [], "hard_skills": ["facilities management"], "soft_skills": [], "languages_combined": []}, "experience_required": {"duration": ["3 years"], "field": ["food", "f&b", "retail", "training"]}}, {"job_id": "100003008994697", "location_code": "hk", "company": "Haven of Hope Christian Service", "job_title": "\u53f8\u6a5f (\u7de8\u865f: RSD/SMPDACH/D/CT)", "description": "The Job\nCoffee development, assist in coffee product formulation changes\nAssist Sales & Marketing dept in solving and evaluating customers issues\nNew coffee material testing\u00a0\nAssist in raw\u00a0materials sample tasting and retention arrangement\nPrepare training materials and execute the beverage training to internal and external parties\nBeverage knowledge and operation support to teams\nBeverage demonstration in events\nAd-hoc tasks assigned by supervisor\nAbout You\n\nHigher Diploma or above in Food Science or related discipline\nOver 2 years working experience in hotels or catering institutions\u00a0\nLicensed Q Grader, authorized SCA trainers or equivalent professional qualifications\nHands on experience in brewing coffee/tea/beverage\nGood coffee/beverage knowledge\nExcellent presentation skill\u00a0\nProficiency in written and oral English and Chinese\n\nLess experience with good attitude would also be considered\n\nWorking Location:\u00a0Kwai Chung\n\nYou will enjoy:\n\nDiscretionary Bonus\nMedical & Life Insurance\nAnnual Leave\nPayable Sick Leave\nEncourage continuing education and on-job training\nOpen office working environment\nOffer promotion opportunities and long-term career path\u00a0\n\nWe offer a competitive remuneration package to the right candidate.\u00a0Interested parties\u00a0please click\u00a0\"Apply Now\"\u00a0to submit your application\u00a0or by email to\u00a0\nhr1 @twcoffee.com\n\n\u00a0(All personal data provided by applicants will be treated in strict confidence and used for employment-related purpose only.)", "employment_types": ["Full Time"], "selling_points": [], "locations": ["Not Specified"], "categories": ["Sciences, Lab, R&D", "Food Science", "Manufacturing", "Product Development / Management", "Research & Development (R&D)"], "post_time": "2021-12-23T02:21:04Z", "salary": {"currency": null, "max": null, "min": null, "period": "monthly", "term": null}, "salary_visible": false, "title_keywords": [], "responsibilities": ["ad-hoc tasks", "internal and external parties", "teams", "testing", "insurance", "catering"], "requirements": {"degrees": ["higher diploma or above"], "majors": ["food science"], "languages": ["english", "chinese"], "language_level": ["proficiency"], "hard_skills": ["presentation skill", "tea", "operation support", "professional qualifications"], "soft_skills": ["presentation skill", "oral", "hands on"], "languages_combined": [{"language": "english", "language_level": ["proficiency"]}, {"language": "chinese", "language_level": ["proficiency"]}]}, "experience_required": {"duration": ["2 years"], "field": ["hotels", "catering institutions"]}}]