[{"job_id": "100003009052636", "location_code": "hk", "company": "Zhong Ji Longevity Science Group Limited", "job_title": "Laboratory Assistant / Technician", "description": "Duties:\n\nRequired to perform medical laboratory tests and procedures according to the Standard Operation Procedure (SOP)\n\nHandle and record the laboratory data for the reports and reviews\n\nCarry out laboratory administrative work such as procurement, inventory control and documents filing\n\nRequirements:\n\nBachelor\u2019s degree or above, majoring in molecular biology, laboratory science, or biotechnology, or any related major.\n\nWith any laboratory related work experience preferred.\n\nImmediate available preferred.\n\nWork overtime or work at weekends or holidays may be required.", "employment_types": ["Full Time"], "selling_points": [], "locations": ["Kowloon Bay"], "categories": ["Sciences, Lab, R&D", "Laboratory"], "post_time": "2022-01-17T03:36:54Z", "salary": {"currency": null, "max": null, "min": null, "period": "monthly", "term": null}, "salary_visible": false, "title_keywords": ["technician", "laboratory assistant"], "responsibilities": ["documents filing", "administrative work", "data", "procedures", "inventory control", "reports"], "requirements": {"degrees": ["degree or above", "bachelor"], "majors": ["molecular biology", "science"], "languages": [], "language_level": [], "hard_skills": [], "soft_skills": ["work overtime"], "languages_combined": []}, "experience_required": {"duration": [], "field": ["related", "laboratory"]}}, {"job_id": "100003009055239", "location_code": "hk", "company": "Karen Pharmaceutical Company Limited", "job_title": "Laboratory Assistant", "description": "Key Roles and Responsibilities\n\nPerform sampling and chemical testing on Purified water, Raw materials, intermediates, finished products and stability samples\nUndertake maintenance and calibration of related analytical instruments\nRevision of SOP documents\n\nQualifications and Experience\n\nIn Science subjects, preferably in Pharmaceutical Science/Chemistry related discipline\n1-2 years working experience in Quality Control of pharmaceutical or commercial laboratory is preferred\nFamiliar with pharmacopeia (BP/USP/CP) and GMP requirements as per FDA, PIC/S\nProficiency in MS Words and Excel\nSelf-motivated and responsible\nGood command of English and Chinese\nFresh graduates are also considered\n\nHow to Apply\n\nYou are invited to send in your application and CV stating the position\u00a0(with reference number)\u00a0you are applying for together with your current and expected salary, apply via JobsDB\u00a0on or before 17 February 2022.\n\nKaren Pharmaceutical Company Limited is an Equal Opportunities Employer. Personal data provided by job applicants will be used strictly in accordance with our personal data policy and for recruitment purposes only. We aim to respond to successful applicants within 8 weeks and related information will be kept in our file for up to 12 months for other suitable vacancies in our organization and thereafter destroyed.", "employment_types": ["Full Time"], "selling_points": [], "locations": ["Tuen Mun Area"], "categories": ["Sciences, Lab, R&D", "Laboratory", "Medical Services", "Pharmaceutical", "Manufacturing", "Quality Assurance, Control & Testing / ISO"], "post_time": "2022-01-18T01:54:32Z", "salary": {"currency": null, "max": null, "min": null, "period": null, "term": null}, "salary_visible": false, "title_keywords": ["laboratory assistant"], "responsibilities": ["maintenance", "testing", "recruitment", "quality control", "personal data"], "requirements": {"degrees": [], "majors": [], "languages": ["english", "chinese"], "language_level": ["good command"], "hard_skills": ["excel", "maintenance", "ms words"], "soft_skills": ["self-motivated", "responsible"], "languages_combined": [{"language": "english", "language_level": ["good command"]}, {"language": "chinese", "language_level": ["good command"]}]}, "experience_required": {"duration": ["1-2 years"], "field": ["pharmaceutical", "quality control", "commercial laboratory"]}}, {"job_id": "100003009052684", "location_code": "hk", "company": "First Choice (Hong Kong) Medical Laboratory Limited", "job_title": "Laboratory Technician/ Assistant (Afternoon shift)", "description": "Duties:\n\nPerform all initial specimen preparation\nPerform housekeeping duties at the laboratory\nAssist the Admin Officer to perform general clerical duties\nPerform any laboratory duties assigned by the Medical Technologist and Lab Manager\nParticipate in-house and external training as required\nOther ad-hoc duties are also required\n\nRequirements:\n\nBachelor\u2019s Degree or Higher Diploma in Biomedical Science or other related Life Science disciplines\nExperience in genetic/DNA analysis, including DNA extraction, sequencing, PCR etc. is preferable\nResponsible and hardworking with good initiatives\nMust be a good team player with excellent communication skills as well as be able to work independently\nTo be able to communicate in Cantonese, Mandarin and English\nGood PC knowledge and typing skills are essential\nCandidates with less experience will be considered as Laboratory Assistant\nFresh graduates are also welcome", "employment_types": ["Full Time", "Permanent"], "selling_points": [], "locations": ["Shatin Area"], "categories": ["Sciences, Lab, R&D", "Laboratory", "Life Science"], "post_time": "2022-01-17T03:41:49Z", "salary": {"currency": "HKD", "max": 24999, "min": 17000, "period": "monthly", "term": null}, "salary_visible": true, "title_keywords": ["laboratory technician", "assistant"], "responsibilities": ["housekeeping", "ad-hoc duties"], "requirements": {"degrees": ["diploma", "degree", "bachelor"], "majors": ["biomedical science", "science"], "languages": ["cantonese", "english", "mandarin"], "language_level": [], "hard_skills": ["analysis", "pc knowledge", "typing"], "soft_skills": ["communication skills", "good team player", "work independently", "responsible", "hardworking"], "languages_combined": [{"language": "cantonese", "language_level": []}, {"language": "english", "language_level": []}, {"language": "mandarin", "language_level": []}]}, "experience_required": {"duration": [], "field": ["laboratory"]}}, {"job_id": "100003009055896", "location_code": "hk", "company": "Page Group Hong Kong", "job_title": "Operations Executive \u71df\u904b\u52a9\u7406", "description": "This position is an all-rounded supporting position that provides a good stepping stone to enter the biotech/diagnostics sector.\n\nClient Details\n\nOur client is a fast-growing start-up biotech company with a strong financial background. They have established a strong global position in the biotechnology field within a short period of time.\n\nDescription\n\nResponsible for general administrative duties to support COVID testing projects\n\u8ca0\u8cac\u4e00\u822c\u884c\u653f\u5de5\u4f5c\uff0c\u652f\u63f4\u516c\u53f8\u65b0\u51a0\u75c5\u6bd2\u6aa2\u6e2c\u9805\u76ee\nFulfil daily operational duties in required projects\n\u8f14\u52a9\u65e5\u5e38\u904b\u71df\uff0c\u78ba\u4fdd\u9805\u76ee\u9806\u5229\u9032\u884c\nHandle customer enquiries\n\u8655\u7406\u5ba2\u4eba\u54a8\u8a62\nFulfil any ad hoc duties as required\n\u6309\u8981\u6c42\u8655\u7406\u5404\u96dc\u52d9\n\nProfile\n\nBachelor degree or Diploma holder\n\u6559\u80b2\u7a0b\u5ea6\u5927\u5c08\u6216\u4ee5\u4e0a\nFresh graduates welcomed\n\u61c9\u5c4a\u7562\u696d\u751f\u4ea6\u53ef\u8003\u616e\nBasic computational skills\n\u57fa\u672c\u96fb\u8166\u64cd\u4f5c\nGood verbal and communication skills in both Chinese and English\n\u826f\u597d\u4e2d\u82f1\u6587\u66f8\u5beb\u53ca\u8a9e\u8a00\u80fd\u529b\nGood communication skills, customer-oriented and detail-minded\n\u6e9d\u901a\u80fd\u529b\u5f37\uff0c\u9867\u5ba2\u5c0e\u5411\uff0c\u7d30\u5fc3\u8fa6\u4e8b\n\nJob Offer\n\nA fair and competitive remuneration package will be offered to the suitable candidate.\n\nTo apply online please click the 'Apply' button below. For a confidential discussion about this role please contact Heart Kwok on +852 2848 9583.", "employment_types": ["Full Time", "Permanent"], "selling_points": ["Fast growing Start-up Biotech Company", "Fresh Graduates Welcome", "Fair and Competitive Salary"], "locations": ["Not Specified"], "categories": ["Others", "Junior Executive", "Sciences, Lab, R&D", "Laboratory", "Others"], "post_time": "2022-01-18T03:03:43Z", "salary": {"currency": null, "max": null, "min": null, "period": "monthly", "term": null}, "salary_visible": false, "title_keywords": ["\u71df\u904b\u52a9\u7406", "operations executive"], "responsibilities": ["ad hoc duties", "handle customer enquiries", "testing", "communication", "administrative duties", "contact", "operational duties"], "requirements": {"degrees": ["diploma holder", "degree", "bachelor"], "majors": [], "languages": ["english", "chinese"], "language_level": ["good"], "hard_skills": ["basic"], "soft_skills": ["detail-minded", "communication skills", "customer-oriented", "responsible"], "languages_combined": [{"language": "english", "language_level": ["good"]}, {"language": "chinese", "language_level": ["good"]}]}, "experience_required": {"duration": [], "field": []}}, {"job_id": "100003009052679", "location_code": "hk", "company": "Hong Kong Laboratory Co., Limited", "job_title": "Laboratory Technician/ Assistant (Afternoon shift)", "description": "Located in HKSTP, the Drug Safety Testing Centre (DSC) aims to facilitate the translation of promising therapeutics and medical devices from the pre-clinical phase to the clinical stage.\u00a0 This first of its kind facility adheres to the highest international and industry standards, including AAALAC and Good Laboratory Practices (GLP), which is an international standard prescribing a set of rigid and quality criteria for conducting studies, data collection and reporting. \u00a0It defines how preclinical data is required and accepted by different regulatory authorities (for example, China NMPA, US FDA and OECD).\u00a0 The facility commits to provide the GLP-compliant preclinical services on toxicology, genotoxicity, toxicokinetics, safety pharmacology, reproductive toxicology, ADME etc for facilitating the development of new drug.\n\n\nResponsibilities:\nFully understand the importance of pre-clinical animal study for human medicine research and drug development process; ensure a high level of animal welfare and work to improve the quality of life for laboratory animals.\nCarry out rodent\u2019s GLP and non-GLP study according to the designed protocol. \u00a0Experimental \u00a0procedures would include, but not limited to, clinical observations, different routes of administration, blood collections and live data acquisition etc.\nComplete the experimental records in accordance with GLP specifications and related standard operating procedures (SOP) within the facility.\nWork in a team to undertake technical and staff supervision/ management duties in connection with the operation of the facility.\nOn-the-job training will be provided.\nQualifications:\nApplicants should possess a Bachelor\u2019s degree or equivalent;\nBe self-motivated, responsible, empathetic, and curious; excellent communication, analytical and problem-solving skills; an interest in laboratory animal science and technology; and demonstrated commitment to continuing professional development in the field.\nWilling to join the pharmaceutical research and development industry and contribute to the cause of human medicine and health.\nGood command of spoken and written English and Chinese; fluent in Putonghua would be an advantage.\nExperience in animal husbandry, operation and maintenance of equipment for sanitation and sterilisation (e.g. autoclave), or inventory/record keeping will be an advantage but not essential.", "employment_types": ["Full Time", "Permanent"], "selling_points": [], "locations": ["Shatin Area"], "categories": ["Sciences, Lab, R&D", "Laboratory", "Life Science", "Others"], "post_time": "2022-01-17T03:41:19Z", "salary": {"currency": "HKD", "max": 24999, "min": 17000, "period": "monthly", "term": null}, "salary_visible": true, "title_keywords": ["laboratory technician", "assistant"], "responsibilities": ["reporting", "management", "maintenance", "data", "inventory", "quality", "procedures", "testing", "communication", "specifications", "data collection", "administration"], "requirements": {"degrees": ["degree", "bachelor"], "majors": [], "languages": ["putonghua", "english", "chinese"], "language_level": ["advantage", "good command", "fluent"], "hard_skills": ["animal science", "maintenance", "animal husbandry", "animal welfare", "problem-solving skills", "translation"], "soft_skills": ["communication", "problem-solving skills", "self-motivated", "responsible"], "languages_combined": [{"language": "putonghua", "language_level": ["fluent", "advantage"]}, {"language": "english", "language_level": ["good command"]}, {"language": "chinese", "language_level": ["good command"]}]}, "experience_required": {"duration": [], "field": ["operation", "maintenance"]}}, {"job_id": "100003009055036", "location_code": "hk", "company": "TUV Rheinland Hong Kong Limited", "job_title": "Assistant Engineer, Electrical - Safety Laboratory (Fresh graduates are welcome)", "description": "Duties:\n\nPerform all initial specimen preparation\nPerform housekeeping duties at the laboratory\nAssist the Admin Officer to perform general clerical duties\nPerform any laboratory duties assigned by the Medical Technologist and Lab Manager\nParticipate in-house and external training as required\nOther ad-hoc duties are also required\n\nRequirements:\n\nBachelor\u2019s Degree or Higher Diploma in Biomedical Science or other related Life Science disciplines\nExperience in genetic/DNA analysis, including DNA extraction, sequencing, PCR etc. is preferable\nResponsible and hardworking with good initiatives\nMust be a good team player with excellent communication skills as well as be able to work independently\nTo be able to communicate in Cantonese, Mandarin and English\nGood PC knowledge and typing skills are essential\nCandidates with less experience will be considered as Laboratory Assistant\nFresh graduates are also welcome", "employment_types": ["Full Time", "Permanent"], "selling_points": ["Electrical - Safety Laboratory", "Fresh graduates are welcome", "On-the-job training"], "locations": ["Tsuen Wan Area"], "categories": ["Engineering", "Electrical / Electronics", "Sciences, Lab, R&D", "Laboratory"], "post_time": "2022-01-18T00:34:54Z", "salary": {"currency": null, "max": null, "min": null, "period": null, "term": null}, "salary_visible": false, "title_keywords": ["assistant engineer"], "responsibilities": ["housekeeping", "ad-hoc duties"], "requirements": {"degrees": ["diploma", "degree", "bachelor"], "majors": ["biomedical science", "science"], "languages": ["cantonese", "english", "mandarin"], "language_level": [], "hard_skills": ["analysis", "pc knowledge", "typing"], "soft_skills": ["communication skills", "good team player", "work independently", "responsible", "hardworking"], "languages_combined": [{"language": "cantonese", "language_level": []}, {"language": "english", "language_level": []}, {"language": "mandarin", "language_level": []}]}, "experience_required": {"duration": [], "field": ["laboratory"]}}, {"job_id": "100003009054150", "location_code": "hk", "company": "Catagene Limited", "job_title": "Medical Laboratory Technologist I / II (Full Time / Part Time)", "description": "Job Responsibilities:\n\nPerform testing and related activities at the safety laboratory\nPerform maintenance and calibration of equipment in the laboratory\nConduct evaluation of laboratory measurement uncertainty according to the ISO guide to the expression of uncertainty\nPerform ad-hoc assignments as required\n\nJob Requirements:\n\nHigher Diploma\u00a0or above in Electrical and Electronic Engineering or related disciplines\nMinimum 1 year experience in safety laboratory\nSelf-motivated and independent\nAbility to work on tight deadlines\nGood command of spoken and written English and Chinese\n\nOther Benefits:\n\nPublic Holidays\nDouble Pay and Performance Bonus\nMedical, Dental and Life Insurance\nAnnual Leave, Maternity Leave, Paternity Leave, Marriage Leave, Compassionate Leave\nOn-the-job training as well as Training Sponsorship/ Subsidies\n\nApplications:\n\nInterested parties please send your full resume with expected salary and date available to the Human Resources Department by clicking \"Apply Now\".\n\nAll information received will be kept in strict confidence and used for employment purpose only. Applicants who are not invited for interview within\u00a05 weeks may assume their applications unsuccessful and their data will be retained for 6 months for other suitable vacancies in our organization and thereafter destroyed.", "employment_types": ["Full Time", "Permanent"], "selling_points": ["Valid MLT Part I/II practicing cert by HKMLT", "Degree/HTC in Biomedical/Medical Lab. Science", "Attractive salary package and double pay"], "locations": ["Shatin Area"], "categories": ["Sciences, Lab, R&D", "Laboratory", "Medical Services", "Medical Services Technician", "Others"], "post_time": "2022-01-17T08:34:19Z", "salary": {"currency": null, "max": null, "min": null, "period": "monthly", "term": null}, "salary_visible": false, "title_keywords": ["medical laboratory technologist"], "responsibilities": ["maintenance", "ad-hoc assignments", "measurement", "testing", "evaluation"], "requirements": {"degrees": ["higher diploma or above"], "majors": ["related disciplines", "engineering"], "languages": ["english", "chinese"], "language_level": ["good command"], "hard_skills": [], "soft_skills": ["self-motivated", "independent"], "languages_combined": [{"language": "english", "language_level": ["good command"]}, {"language": "chinese", "language_level": ["good command"]}]}, "experience_required": {"duration": ["minimum 1 year"], "field": ["laboratory"]}}, {"job_id": "100003009054286", "location_code": "hk", "company": "Vita Green Pharmaceutical (H.K.) Limited", "job_title": "Senior Laboratory Technician", "description": "Responsibilities:\n\n\n\nMonitor and manage the process of testing procedures, including reception, handling, processing, storage and testing of human blood according to the Standard Operation Procedure (SOP)\nEstablish new and review current SOP\nReview and approve quality control data for testing\nReview and approve laboratory report\nParticipate in-house and external training as required\nOther ad-hoc duties are also required\n\nRequirements\n\n\nValid Medical Laboratory Technologist Part I / II practicing cert issued by the HKMLT Board\nBachelor Degree or Higher Technical Certificate (HTC) in Biomedical Science, Medical Laboratory Sciences other related disciplines\nExperience in genetic/DNA analysis, including DNA extraction, sequencing, PCR etc. is preferable.\nStrong sense of responsibility\nMust be a good team worker with excellent communication skills as well as be able to work independently\nAble to communicate in Mandarin and Cantonese\n\nWe offer a competitive remuneration package as well as other benefits encompassing:\n\n\n5-day Work\nAnnual Leave\nBirthday Leave\nDouble Pay\nMedical Insurance\nMentoring\nCareer Advancement Opportunities\nEducation and Training Subsidies\nFree Shuttle Bus Service\nStaff Activities\nOvertime pay\n\nWe offer attractive remuneration package and excellent career opportunities to the right candidates. Interested parties please send your full resume with availability, current and expected salary to our HR Division.\nWelcome to visit our company website www.catagene.com.hk\u00a0or more information.\n\nWe are an Equal Opportunities Employer and welcome applications from all qualified candidates. All Personal data collected will be kept in strict confidence and used for recruitment purpose only.", "employment_types": ["Full Time", "Permanent"], "selling_points": ["\u2022GMP manufacturer", "Welcome candidate from food, drug or related field", "Great career opportunity in a leading HK brand"], "locations": ["Tai Po Area"], "categories": ["Sciences, Lab, R&D", "Laboratory", "Manufacturing", "Production Planning / Control", "Quality Assurance, Control & Testing / ISO"], "post_time": "2022-01-17T09:03:02Z", "salary": {"currency": null, "max": null, "min": null, "period": "monthly", "term": null}, "salary_visible": false, "title_keywords": ["laboratory technician"], "responsibilities": ["data", "review", "monitor", "procedures", "testing", "quality control", "ad-hoc duties", "report"], "requirements": {"degrees": ["certificate", "degree", "bachelor"], "majors": ["biomedical science", "related disciplines"], "languages": ["cantonese", "mandarin"], "language_level": [], "hard_skills": ["analysis"], "soft_skills": ["communication skills", "work independently", "sense of responsibility"], "languages_combined": [{"language": "cantonese", "language_level": []}, {"language": "mandarin", "language_level": []}]}, "experience_required": {"duration": [], "field": []}}, {"job_id": "100003009053227", "location_code": "hk", "company": "Singapore International School (Hong Kong)", "job_title": "Science Lab Assistant / Technician", "description": "The Role:\n\nQuality control is one of the most important processes for Vita Green Group to ensure all our production materials and finished products with the highest qualities to meet our customer satisfaction. We are looking for candidates with great interest in developing their career in quality control discipline to join our laboratory team. You will be participating in the role of conducting sample preparation and tests in both chemistry and microbiology laboratory. Moreover, you will be contributing to method validation, performance check, instrument calibration and maintenance in a reputable, stable local manufactory company.\n\nIf you are ...\u00a0\n\nthe holder of Bachelor Degree major in\u00a0Chemistry, Biochemistry, Biology or equivalent science discipline.\nhaving strong sense in science and familiar with GMP.\nhaving experience in microbial testing.\na team player and willing to learn to develop yourself.\nself-motivated, detail-oriented and multi-tasking.\nparticularly interested in growing yourself in a stable manufacturing environment.\n\nWe will offer you...\n\nA career opportunity with the market leader in health product sector.\nCasual wear everyday to enjoy your work.\nFree shuttles from various locations.\nChallenging jobs to learn and grow together.\u00a0\nRapid growth opportunities for strong performers.\u202f\u00a0\nAttractive staff purchase discount to experience our quality products.\n\nInterested parties, please send full resume with last & expected salary and date of available by clicking \u2018Apply\u2019.\n\nPersonal data collected is for recruitment purpose only.\n\nFor corporate information, please visit:\u00a0www.vitagreen.com", "employment_types": ["Full Time", "Permanent"], "selling_points": [], "locations": ["Aberdeen"], "categories": ["Education", "Others", "Sciences, Lab, R&D", "Laboratory"], "post_time": "2022-01-17T06:29:29Z", "salary": {"currency": null, "max": null, "min": null, "period": "monthly", "term": null}, "salary_visible": false, "title_keywords": ["technician", "assistant"], "responsibilities": ["maintenance", "sample preparation", "quality", "developing", "testing", "develop", "purchase", "quality control"], "requirements": {"degrees": ["degree", "bachelor"], "majors": ["science", "biology", "chemistry"], "languages": [], "language_level": [], "hard_skills": ["maintenance", "rapid"], "soft_skills": ["self-motivated", "interested in", "willing to learn", "detail-oriented", "multi-tasking", "team player", "stable"], "languages_combined": []}, "experience_required": {"duration": [], "field": ["testing"]}}, {"job_id": "100003009051800", "location_code": "hk", "company": "PrimoGenomic Bioscience Limited", "job_title": "Laboratory Technician / Senior Laboratory Technician", "description": "Job Duties\n\nPerform routine testing and ensure the availability of equipment resources\nEnsure all the working procedures follow the SOPs and requirements from Quality Assurance\nKeep data and result with accuracy, analyse date correctly and independently\nConduct equipment maintenance and calibration\nManage laboratory inventory\u00a0\nPerform others tasks as assigned by manager\nRequirements\nDegree above in Biology / other related science disciplines\nExperience in any of laboratory disciplines\u00a0\nExperience in PCR and sequencing\u00a0\nAble to work shift\nResponsible, reliable and well organized\nGood interpersonal and communication skills\nProficiency in both Chinese and English\nMore experience will be considered as Senior Laboratory Technician\u00a0\u00a0\n\nInterested parties, please send your full resume. All personal data collected will be kept in strict confidence and would only be used for recruitment purpose.", "employment_types": ["Full Time"], "selling_points": ["Bachelor Degree in Science", "Molecular testing", "Fresh graduates are welcome"], "locations": ["Lai Chi Kok"], "categories": ["Sciences, Lab, R&D", "Laboratory", "Medical Services", "Medical Services Technician", "Others"], "post_time": "2022-01-17T01:13:45Z", "salary": {"currency": null, "max": null, "min": null, "period": "monthly", "term": null}, "salary_visible": false, "title_keywords": ["laboratory technician"], "responsibilities": ["maintenance", "data", "inventory", "quality", "procedures", "testing", "sops", "analyse"], "requirements": {"degrees": ["degree"], "majors": ["science", "biology"], "languages": ["english", "chinese"], "language_level": ["proficiency"], "hard_skills": [], "soft_skills": ["communication skills", "responsible", "well organized", "reliable", "interpersonal"], "languages_combined": [{"language": "english", "language_level": ["proficiency"]}, {"language": "chinese", "language_level": ["proficiency"]}]}, "experience_required": {"duration": [], "field": ["laboratory"]}}, {"job_id": "100003009054338", "location_code": "hk", "company": "Pathlab Medical Laboratories Limited", "job_title": "Medical Laboratory Technologist", "description": "Job description and responsibilities\n\nPerform routine laboratory tests and data analysis\nCarry out maintenance of facilities and equipment, inventory control, QC/QA procedures\nCoordinate and participate other laboratory tasks assigned by supervisors\nJob requirements\n\nRegistered MLT Part I or Part II\u00a0\nMinimum 1 year working experience required\nEvening Shift duty is required\nGood in both spoken and written in English & Cantonese\nWe offer attractive remuneration package and other fringe benefits to competitive candidate\n\n\n1-2 days evening shift per week, 5.5 working days or equivalent\nMedical & dental plans\n14 days Annual Leave\nPublic holiday & Sundays off\nConvenient Locations - Fortress Hill\nTo find out more about our company, please visit our website :\u00a0www.pathlabhk.com\n\n(All personal data collected are used for recruitment purpose only.)\n", "employment_types": ["Full Time"], "selling_points": ["MLT Board Part II or Part I Registered", "Laboratory tests and data analysis", "Competitive scaled salary & benefits"], "locations": ["North Point"], "categories": ["Sciences, Lab, R&D", "Laboratory", "Medical Services", "Medical Services Technician"], "post_time": "2022-01-17T09:11:53Z", "salary": {"currency": null, "max": null, "min": null, "period": "monthly", "term": null}, "salary_visible": false, "title_keywords": ["medical laboratory technologist"], "responsibilities": ["maintenance", "procedures", "data analysis", "coordinate", "inventory control"], "requirements": {"degrees": [], "majors": [], "languages": ["cantonese", "english"], "language_level": ["good"], "hard_skills": [], "soft_skills": [], "languages_combined": [{"language": "cantonese", "language_level": ["good"]}, {"language": "english", "language_level": ["good"]}]}, "experience_required": {"duration": ["minimum 1 year"], "field": []}}, {"job_id": "100003009053186", "location_code": "hk", "company": "API Lab Testing Limited", "job_title": "Chemical Lab Sr. Chemist (Organic) (Multiple Vacancy)", "description": "Responsibilities:\u00a0\n\nPerform routine laboratory tests and data\u00a0analysis\u00a0\nEnsure good laboratory practices and standard operating\u00a0procedures\u00a0\nCarry out maintenance of facilities and\u00a0equipment\u00a0\nCoordinate and participate other laboratory tasks assigned by\u00a0supervisors\u00a0\n\n\u00a0Requirements:\u00a0\n\nDegree or above in Biomedical Sciences, Molecular Biology,\u00a0Biotechnology,\u00a0Biochemistry, Medical Laboratory\u00a0Science\u00a0or related discipline\u00a0\nRegistered\u00a0with\u00a0MLT Board Part II License\u00a0(with valid practicing certificate)\u00a0is a\u00a0must\u00a0\nFresh\u00a0graduates are\u00a0welcome\u00a0\nKnowledge in molecular\u00a0test,\u00a0such as DNA/RNA extraction\u00a0and\u00a0PCR\u00a0is\u00a0an\u00a0advantage\u00a0\nGood at\u00a0both written and spoken English and\u00a0Chinese\u00a0\nSelf-motivated,\u00a0independent\u00a0and responsible\u00a0\nImmediately available is\u00a0preferred\u00a0\n\nWe are an equal opportunity employer and welcome applications from all qualified candidates. We offer competitive remuneration package to the right candidates. Interested parties, please send your full resume with current and expected salary by clicking the \u2018Quick Apply\u201d.\n\n\u00a0For more details, please visit our website:\u00a0www.leespharm.com\n\nInformation provided will be treated in strict confidence and used for recruitment purposes within our Group only. Personal data of unsuccessful applicants will be retained for a maximum of 12 months.", "employment_types": ["Full Time"], "selling_points": ["HOKLAS", "Chemical Lab Sr. Chemist (Organic)", "English & Chinese"], "locations": ["Tsuen Wan Area"], "categories": ["Sciences, Lab, R&D", "Laboratory"], "post_time": "2022-01-17T06:21:05Z", "salary": {"currency": null, "max": null, "min": null, "period": "monthly", "term": null}, "salary_visible": false, "title_keywords": ["chemical", "chemist"], "responsibilities": ["data analysis", "procedures", "coordinate", "maintenance"], "requirements": {"degrees": ["certificate", "degree or above"], "majors": ["molecular biology", "medical laboratory science"], "languages": ["english", "chinese"], "language_level": ["good"], "hard_skills": [], "soft_skills": ["self-motivated", "independent", "responsible"], "languages_combined": [{"language": "english", "language_level": ["good"]}, {"language": "chinese", "language_level": ["good"]}]}, "experience_required": {"duration": [], "field": []}}, {"job_id": "100003009056257", "location_code": "hk", "company": "Lee's Pharmaceutical (HK) Limited", "job_title": "Medical Laboratory Technologist (Part II)", "description": "Job Overview:\n\nTo do a sample review and test assignment for chemical tests.\n\nEssential Duties and Responsibilities:\n\nSample review and test assignment for chemical tests\nChemical test sorting\nPrepare sample breakdown sheet\nPrepare worksheet for chemical lab\nQuotation for chemical tests\n\nExperience & Competencies Required:\u00a0\n\nHighly-organized and able to work independently\nGood command of English and Chinese\nGood computer skills\n\u00a0Familiar with European regulations like REACH and food contact test is an advantage\nHaving the experience of component sorting is an advantage\n\nEducation and Qualifications Required:\n\nMinimum 5 years\u2019 relevant experience in laboratory testing company\nKnowledge of US & CANADA regulations for toys and childcare articles\n5 days work\nCandidate with less experience will consider to a junior post\n\nTools Skills:\n\nProficient in Microsoft Programs, including Word, Excel, PowerPoint and Outlook. Experience with CRM systems, Facebook ad manager and Google analytic", "employment_types": ["Full Time"], "selling_points": [], "locations": ["Shatin Area"], "categories": ["Sciences, Lab, R&D", "Laboratory", "Medical Services", "Medical Services Technician"], "post_time": "2022-01-18T03:43:30Z", "salary": {"currency": null, "max": null, "min": null, "period": "monthly", "term": null}, "salary_visible": false, "title_keywords": ["medical laboratory technologist"], "responsibilities": ["regulations", "quotation", "review", "systems", "testing", "contact", "facebook"], "requirements": {"degrees": [], "majors": [], "languages": ["english", "chinese"], "language_level": ["good command"], "hard_skills": ["excel", "word", "powerpoint", "outlook", "computer skills", "facebook"], "soft_skills": ["organized", "work independently"], "languages_combined": [{"language": "english", "language_level": ["good command"]}, {"language": "chinese", "language_level": ["good command"]}]}, "experience_required": {"duration": ["minimum 5 years"], "field": ["laboratory testing", "relevant experience"]}}, {"job_id": "100003009053565", "location_code": "hk", "company": "API Lab Testing Limited", "job_title": "Sr. Chemist / Chemist (breakdown)", "description": "Responsibilities:\u00a0\n\n\n\nHandling\u00a0of chemical tests related to routine sample;\nSample preparation, perform chemical test, instrumental analysis;\nOperation of analytical instrument (e.g. GC/MS, LC-DAD, LC/MS, LC/MS/MS);\nInstrument maintenance and calibration;\nMethod validation and preparation for accreditation audit;\nAssist in R&D work;\nUndertake any other duties as assigned.\n\nRequirements:\n\n\nHigher Diploma or above in Chemistry or relevant discipline;\nKnowledge of ISO 17025 quality system and accreditation requirements;\nAnalytical instrumentation skill;\nImmediately available is highly preferred.\nCandidate with less experience will be considered as Lab Technician\n\nOther Benefits:\n\n5 days work week\nMedical Insurance\nOver Time Pay\nDouble pay\nFree shuttle bus\n\nWe offer attractive remuneration package and excellent career opportunities to the right candidates. Interested parties please send your full resume with availability, current and expected salary to\u00a0our HR department.\n\nWelcome to visit our company website\u00a0http://www.cmatesting.org/ or more information.\n\nWe are an Equal Opportunities Employer and welcome applications from all qualified candidates. All Personal data collected will be kept in strict confidence and used for recruitment purpose only.", "employment_types": ["Full Time"], "selling_points": ["Chemist", "Toys and childcare", "Laboratory testing"], "locations": ["Tsuen Wan Area"], "categories": ["Sciences, Lab, R&D", "Laboratory"], "post_time": "2022-01-17T07:09:53Z", "salary": {"currency": null, "max": null, "min": null, "period": "monthly", "term": null}, "salary_visible": false, "title_keywords": ["chemist"], "responsibilities": ["any other duties", "maintenance", "sample preparation", "analysis", "audit"], "requirements": {"degrees": ["higher diploma or above"], "majors": ["chemistry"], "languages": [], "language_level": [], "hard_skills": [], "soft_skills": [], "languages_combined": []}, "experience_required": {"duration": [], "field": []}}, {"job_id": "100003009056249", "location_code": "hk", "company": "CMA Testing and Certification Laboratories Limited", "job_title": "Assistant Technical Officer - Organic Division", "description": "Responsibilities:\n\nPerform physical & chemical tests on raw materials, intermediates, finished products, stability samples and validation samples\nConduct clean-room environmental monitoring test and purified water quality test\nPerform calibration, validation and maintenance of lab instrumentation\nLiaise with internal departments and external testing laboratories to arrange sampling & testing activities and monitor the testing status\nMaintain documentation system in compliance with GMP requirements\nProvide support to other ad hoc projects\nRequirements:\n\nHigher Diploma or above in Science, Pharmacy in Chinese Medicine, Food Safety and Technology, or other related disciplines (Candidates with knowledge in Chinese medicine is a definite advantage)\nHands-on experience in analytical equipment such as TLC, HPLC/UPLC, GC, etc.\nExperience in food or pharmaceutical testing industry is an advantage\nHardworking, self-motivated, and enthusiastic about laboratory work\nFresh graduates or candidates with less experience will be considered as Assistant Officer.\n\nWe offer attractive remuneration package to the successful candidates. \u00a0\nPlease send detailed resume, stating qualification, experience, current and expected salary and career history\u00a0by clicking\u00a0\u201cApply Now\u201d.\n\nAll information received will be kept in strict confidence and only for employment-related purpose.", "employment_types": ["Full Time", "Permanent"], "selling_points": ["Handling of chemical tests related routine sample", "Higher Diploma in Chemistry or relevant discipline", "5 days,Medical, OT Pay,Double pay,Free shuttle bus"], "locations": ["Shatin Area"], "categories": ["Sciences, Lab, R&D", "Chemical", "Laboratory", "Life Science"], "post_time": "2022-01-18T03:42:09Z", "salary": {"currency": null, "max": null, "min": null, "period": "monthly", "term": null}, "salary_visible": false, "title_keywords": ["assistant technical officer"], "responsibilities": ["provide support", "maintain documentation", "maintenance", "monitoring", "quality", "monitor", "testing activities", "testing", "compliance", "ad hoc projects", "liaise with"], "requirements": {"degrees": ["higher diploma or above"], "majors": ["related disciplines", "science"], "languages": ["chinese"], "language_level": ["advantage"], "hard_skills": [], "soft_skills": ["hands-on", "self-motivated", "hardworking", "enthusiastic"], "languages_combined": [{"language": "chinese", "language_level": ["advantage"]}]}, "experience_required": {"duration": [], "field": ["pharmaceutical", "food", "analytical", "testing"]}}, {"job_id": "100003009056448", "location_code": "hk", "company": "Eu Yan Sang (HK) Ltd", "job_title": "Officer/Assistant Officer - Quality Control", "description": "Job Responsibilities:\n\n\u5728\u4e3b\u7ba1\u7684\u6307\u5c0e\u4e0b\uff0c\u6309\u7167\u6a19\u6e96\u64cd\u4f5c\u7a0b\u5e8f\u9032\u884c\u98df\u54c1\u5bb9\u5668\u6aa2\u6e2c\u7b49\u5e38\u898f\u5316\u5b78\u6e2c\u8a66\n\u5728\u6e2c\u8a66\u5de5\u4f5c\u8868\u4e0a\u5408\u4f75\u548c\u8a18\u9304\u76f8\u95dc\u6578\u64da\n\u76e3\u63a7\u6e2c\u8a66\u6642\u9593\u4ee5\u78ba\u4fdd\u5de5\u4f5c\u5728\u8a08\u5283\u6642\u9593\u5167\u5b8c\u6210\n\nJob Requirements:\n\n\u4e2d\u4e94\u6216\u4ee5\u4e0a\u5b78\u6b77\n\u7121\u9700\u76f8\u95dc\u5de5\u4f5c\u7d93\u9a57\n\nOther benefits:\n\n\u9280\u884c\u5047\u671f\n\u8f2a\u73ed\u6d25\u8cbc,\u9ad8\u9054\u6708\u85aa\u768440%\n\u52a0\u73ed\u8cbb\n\u96d9\u7ce7\u53ca\u5e74\u5ea6\u8868\u73fe\u734e\u91d1\n\u91ab\u7642\u3001\u7259\u79d1\u548c\u4eba\u58fd\u4fdd\u96aa\n\u5e74\u5047\u3001\u7522\u5047\u3001\u4f8d\u7522\u5047\u3001\u5a5a\u5047\u3001\u9ad4\u6064\u5047\n\u5728\u8077\u57f9\u8a13\u4ee5\u53ca\u9032\u4fee\u88dc\u8cbc\n\nAll information received will be kept in strict confidence and used for employment purpose only. Applicants who are not invited for interview within\u00a05 weeks may assume their applications unsuccessful and their data will be retained for 6 months for other suitable vacancies in our organization and thereafter destroyed.", "employment_types": ["Full Time", "Permanent"], "selling_points": ["Perform physical & chemical tests on raw materials", "Working location: Yuen Long Industrial Estate", "13-month salary+Performance Bonus"], "locations": ["Yuen Long"], "categories": ["Sciences, Lab, R&D", "Chemical", "Laboratory"], "post_time": "2022-01-18T04:21:35Z", "salary": {"currency": null, "max": null, "min": null, "period": "monthly", "term": null}, "salary_visible": false, "title_keywords": ["assistant officer", "officer"], "responsibilities": [], "requirements": {"degrees": [], "majors": [], "languages": [], "language_level": [], "hard_skills": [], "soft_skills": [], "languages_combined": []}, "experience_required": {"duration": [], "field": []}}, {"job_id": "100003009053703", "location_code": "hk", "company": "TUV Rheinland Hong Kong Limited", "job_title": "\u5be6\u9a57\u5ba4\u6280\u8853\u54e1(\u7121\u9700\u5de5\u4f5c\u7d93\u9a57)", "description": "Job Duties:\nPrepare samples by various digestion and extraction methods\nConduct chemical analysis according to standard operating procedures\nRun analytical instruments (e.g GC-MS. HPLC, LC-MS, UV-VIS, ICP, AAS etc.)\nMaintain instruments sustainability\nAnalyze data and issue result\nImplement of the laboratory management system in accordance with ISO/IEC 17025 and related requirement by accreditation/ certification body (CB, CNAS, DAkkS, HOKLAS, ZLS etc)\nJob Requirements:\nHigher Diploma/ Degree holder in Chemistry or related discipline\nRelevant working experience in chemical testing or chemistry related industry is an advantage\nGood understanding in quality and safety requirements in chemical laboratories\nWith hand on experiences in operating and performing maintenance for instruments: (1) ICP-OES, (2) UV-VIS, (3) GC-MS, (4) HPLC-MS is an advantage\nHardworking, self-motivated and a good team player\nAble to work independently and under pressure\nCandidate with more experience will be considered as Test Engineer\nWorking location : Yuen Long (5 mins walk from Long Ping Station)\u00a0\n\nWe offer attractive remuneration package with potential career advancement to the right candidate. Interested parties, please apply with detailed resume, stating expected salary and date of availability to Human Resources Department by\u00a0clicking 'Apply Now'.\n\nFor more company information, please visit our webpage www.tuvsud.com\n(Data collected will be treated as strictly confidential and will be used for recruitment purpose only)\u00a0\u00a0", "employment_types": ["Full Time", "Permanent"], "selling_points": ["\u7a69\u5b9a\u5de5\u4f5c\u74b0\u5883", "\u7121\u9700\u5de5\u4f5c\u7d93\u9a57", "\u4fdd\u8b49\u96d9\u7ce7\u53ca\u8868\u73fe\u734e\u91d1"], "locations": ["Tsuen Wan Area"], "categories": ["Sciences, Lab, R&D", "Chemical", "Laboratory", "Manufacturing", "Others"], "post_time": "2022-01-17T07:22:32Z", "salary": {"currency": null, "max": null, "min": null, "period": null, "term": null}, "salary_visible": false, "title_keywords": [], "responsibilities": ["management", "analysis", "procedures", "maintain", "analyze data"], "requirements": {"degrees": ["diploma", "degree holder"], "majors": ["chemistry"], "languages": [], "language_level": [], "hard_skills": ["maintenance"], "soft_skills": ["good team player", "self-motivated", "under pressure", "work independently", "hardworking"], "languages_combined": []}, "experience_required": {"duration": [], "field": ["related", "chemical testing", "relevant working experience", "maintenance"]}}, {"job_id": "100003009055183", "location_code": "hk", "company": "Karen Pharmaceutical Company Limited", "job_title": "QC Technician", "description": "Key Roles and Responsibilities\n\nPerform sampling and chemical testing on Purified water, Raw materials, intermediates, finished products and stability samples\nUndertake maintenance and calibration of related analytical instruments\nRevision of SOP documents\n\nQualifications and Experience\n\nIn Science subjects, preferably in Pharmaceutical Science/Chemistry related discipline\n1-2 years working experience in Quality Control of pharmaceutical or commercial laboratory is preferred\nFamiliar with pharmacopeia (BP/USP/CP) and GMP requirements as per FDA, PIC/S\nProficiency in MS Words and Excel\nSelf-motivated and responsible\nGood command of English and Chinese\nFresh graduates are also considered\n\nHow to Apply\n\nYou are invited to send in your application and CV stating the position\u00a0(with reference number)\u00a0you are applying for together with your current and expected salary, apply via JobsDB\u00a0on or before 17 February 2022.\n\nKaren Pharmaceutical Company Limited is an Equal Opportunities Employer. Personal data provided by job applicants will be used strictly in accordance with our personal data policy and for recruitment purposes only. We aim to respond to successful applicants within 8 weeks and related information will be kept in our file for up to 12 months for other suitable vacancies in our organization and thereafter destroyed.", "employment_types": ["Full Time"], "selling_points": [], "locations": ["Tuen Mun Area"], "categories": ["Sciences, Lab, R&D", "Laboratory", "Medical Services", "Pharmaceutical", "Manufacturing", "Quality Assurance, Control & Testing / ISO"], "post_time": "2022-01-18T01:41:36Z", "salary": {"currency": null, "max": null, "min": null, "period": null, "term": null}, "salary_visible": false, "title_keywords": ["qc technician"], "responsibilities": ["maintenance", "testing", "recruitment", "quality control", "personal data"], "requirements": {"degrees": [], "majors": [], "languages": ["english", "chinese"], "language_level": ["good command"], "hard_skills": ["excel", "maintenance", "ms words"], "soft_skills": ["self-motivated", "responsible"], "languages_combined": [{"language": "english", "language_level": ["good command"]}, {"language": "chinese", "language_level": ["good command"]}]}, "experience_required": {"duration": ["1-2 years"], "field": ["pharmaceutical", "quality control", "commercial laboratory"]}}, {"job_id": "100003009054649", "location_code": "hk", "company": "Hop Hing Management Company (Hong Kong) Limited", "job_title": "QC Technician (Ref No.: LT/1701/22)", "description": "Responsibilities:\n\nRoutine analysis of products, raw materials and on-line process samples.\nResult reporting, equipment maintenance and laboratory safety.\nCarried out QC tasks as assigned.\nDocumentation work related to customers and Sale Team.\nParticipation in problem solving with Refinery, Bottling and Warehouse.\nSupport to ISO certification and external parties communication\n\nRequirements:\n\nDiploma in Science or related disciplines.\nMinimum 1 year experience is preferred.\u00a0\nHand-on experience for analytical equipment such as chromatography or mass spectrometer.\nKnowledge of ISO 9001, ISO 17025, HACCP or food hygiene.\n\nInterested parties, please email detail resume and expected salary email to the Human Resources Department\u00a0(Please quote the reference no.).\n\n\nData collected will be treated in strictly confidential and in used for recruitment purposes only.", "employment_types": ["Full Time"], "selling_points": ["Diploma in Science or related disciplines", "Knowledge of food hygiene", "Experience for analytical equipment"], "locations": ["Yuen Long"], "categories": ["Sciences, Lab, R&D", "Food Science", "Laboratory", "Others"], "post_time": "2022-01-17T10:24:25Z", "salary": {"currency": null, "max": null, "min": null, "period": "monthly", "term": null}, "salary_visible": false, "title_keywords": ["qc technician"], "responsibilities": ["reporting", "maintenance", "analysis", "external parties", "communication", "documentation"], "requirements": {"degrees": ["diploma"], "majors": ["related disciplines", "science"], "languages": [], "language_level": [], "hard_skills": [], "soft_skills": [], "languages_combined": []}, "experience_required": {"duration": ["minimum 1 year"], "field": ["analytical"]}}, {"job_id": "100003009056245", "location_code": "hk", "company": "CMA Testing and Certification Laboratories", "job_title": "Laboratory Technician - Environmental Division", "description": "Responsibilities:\n\nConduct field environmental sampling and testing\nPerform environmental laboratory testing\nAssist in handling routine laboratory works\nData logging and analysis\nUndertake any other duties as assigned\n\nRequirements:\n\nDiploma in Chemistry, Environmental Protection and Management, or Environmental Science or equivalent;\nBeing proactive\nImmediately available is highly preferred\n\n\n\u00a0Work Location:\n\n\u00a0Fo Tan & Kwai Tsing area\n\nWe offer a competitive remuneration package as well as other benefits encompassing:\n\n5-day Work\nAnnual Leave\nBirthday Leave\nDouble Pay\nGroup Medical Insurance\nMentoring\nCareer Advancement Opportunities\nEducation and Training Subsidies\nFree Shuttle Bus Service\nStaff Activities\n\nWe offer attractive remuneration package and excellent career opportunities to the right candidates. Interested parties please send your full resume\u00a0with\u00a0availability, current and expected salary\u00a0to our HR Division.\n\nWelcome to visit our company website\u00a0www.cmatesting.org\u00a0or more information.\n\nWe are an Equal Opportunities Employer and welcome applications from all qualified candidates. All Personal data collected will be kept in strict confidence and used for recruitment purpose only.", "employment_types": ["Full Time", "Permanent"], "selling_points": ["Diploma in Chemistry and Environmental related", "Work Location: Fo Tan & Kwai Tsing area", "5 day work, birthday leave, free shuttle bus"], "locations": ["Shatin Area"], "categories": ["Sciences, Lab, R&D", "Chemical", "Environmental Science / Waste Management", "Laboratory"], "post_time": "2022-01-18T03:42:08Z", "salary": {"currency": null, "max": null, "min": null, "period": "monthly", "term": null}, "salary_visible": false, "title_keywords": ["laboratory technician"], "responsibilities": ["any other duties", "analysis", "data", "testing"], "requirements": {"degrees": ["diploma"], "majors": ["environmental science", "chemistry"], "languages": [], "language_level": [], "hard_skills": [], "soft_skills": ["proactive"], "languages_combined": []}, "experience_required": {"duration": [], "field": []}}, {"job_id": "100003009056248", "location_code": "hk", "company": "CMA Testing and Certification Laboratories Limited", "job_title": "Technical Officer / Senior Technical Officer - Research & Development Division", "description": "Role and Responsibilities\n\nThe job scope of the lab technician involves assisting HOD/Science, supporting the Science department and the school in the following areas:\n\nManagement of science laboratories\nPack and organise the resources in the Science laboratories\nLabel and keep records of all existing and new Science resources and maintain loan records of these resources. Inform HOD if any resource needs to be replenished\nKeep records of consumables (to replenish when quantity is low).\u00a0 Monitor and maintain records of substances listed under Schedule 1 or Schedule 2 of the Control of Chemicals Ordinance (if applicable)\nLiaise with vendors and request for quotations for Science resources\nSource and make purchases for lab supplies and keep records of the expenditure\n\u00a0Monitor and maintain licences, warranties and maintenance contracts as necessary\n\u00a0Service and maintain equipment in good condition. Ensure that equipment like Microscopes are serviced once a year and are kept in a ready-to-use condition\n\u00a0Conduct audit of the inventory list as required by the Finance Department, at the end of every semester\n\u00a0\u00a0Ensure proper disposal of waste materials such as sharp waste objects and chemicals\n\u00a0Prepare and set up lab resources for teachers\u2019 demonstrations and students\u2019 use during science practical lessons\n\u00a0Prepare and set up the materials for Science Practical Assessments and Project Works\n\u00a0Set up lab resources for science enrichment activities, e.g. post-exam activities and during the Summer Programme\n\u00a0Ensure adherence to safe laboratory practices by staff and students. Report any incident to the Science HOD immediately\n\u00a0Maintain tidiness and cleanliness of laboratories\n\u00a0Take care of the plants and animals in the laboratories. Feed and maintain the habitats of the animals in the Science laboratories\n\u00a0Conduct technical training for staff as required\n\u00a0Liaise with Campus Management team to ensure that the Science laboratories are well-maintained\n\u00a0Liaise with Nurse on the validity of items in the first aid kit in the Science laboratories\nAdministrative support for science teachers\nAssist teachers in preparing materials and laboratory protocols for science programmes and students\u2019 projects\nAssist teachers in conducting demonstrations and hands-on activities/experiments\nCreate videos of Science activities/experiments\nSearch for and recommend web-based resources for teaching and learning purposes\nCollate feedback data from surveys on science activities and School Excellence Model-related surveys for review purposes\nAccompany students on learning journeys and field trips (when necessary)\nUpdate information and displays on the science notice board (when necessary)\nPrepare the schedule for the Science Practical Assessments and assist teachers in\u00a0\u00a0 invigilation\nAssist teachers in conducting make-up for students who miss the Science Practical Assessments\u00a0\nLogistical and administrative support for school and departmental events/programmes\nAssist the Science department in the implementation of programmes, e.g. hydroponics programme and student volunteer programme\nMaintain the hydroponic facilities and take care of the vegetables\nMaintain the Science planters and take care of the plants\nAssist in running school events such as Green Day, Family Fest, Summer Programme etc.\nAssist the Exam Committee in invigilation of students with special considerations\nAssist in Science examination paper marking sessions\nProvide logistical support to school and departments as necessary\u00a0\n\nRequirements\n\nDiploma / Degree holder in the study of Physics, Biology, Chemistry or Science subjects\nHave work experience in a school environment or laboratory is preferable\nFresh graduates will also be considered\nBe an effective communicator in oral and written English\nBe a good team player\n\nCompetitive remuneration and benefits will be offered to the suitable candidate.\nInterested parties, please send a cover letter, detailed resume including\u00a0availability, present and expected salary\u00a0either\u00a0by online application\u00a0or by post to the Human Resources Department at 23 Nam Long Shan Road, Aberdeen, Hong Kong.\u00a0 Only shortlisted candidates will be notified.\n\nAll personal data collected will be used for recruitment purposes only.", "employment_types": ["Full Time", "Permanent"], "selling_points": ["Chemical testing, analytical instruments", "GC-MSMS, Headspace GC-MS, LC-MSMS", "5 days, Medical, Double pay, Shuttle bus"], "locations": ["Shatin Area"], "categories": ["Sciences, Lab, R&D", "Chemical", "Laboratory", "Life Science"], "post_time": "2022-01-18T03:42:08Z", "salary": {"currency": null, "max": null, "min": null, "period": "monthly", "term": null}, "salary_visible": false, "title_keywords": ["technical officer", "senior technical officer"], "responsibilities": ["management team", "management", "control", "maintenance", "administrative support", "data", "contracts", "inventory", "ensure adherence", "monitor", "audit", "review", "implementation", "school events", "maintain", "schedule", "liaise with", "report"], "requirements": {"degrees": ["diploma", "degree holder"], "majors": ["science", "biology", "chemistry", "physics"], "languages": ["english"], "language_level": [], "hard_skills": [], "soft_skills": ["good team player", "communicator", "oral"], "languages_combined": [{"language": "english", "language_level": []}]}, "experience_required": {"duration": [], "field": ["laboratory"]}}, {"job_id": "100003009053704", "location_code": "hk", "company": "TUV Rheinland Hong Kong Limited", "job_title": "Technician / Senior Technician", "description": "Responsibilities:\n\nResponsible for chemical testing, project development;\nConduct researches and develop test methods;\nValidate or verify the test methods with various analytical instruments and estimate measurement uncertainty;\nPerform pilot test and feasibility study on the test methods;\nDocument the developed test methods and transfer the technical skill and knowledge of the tests to operation team;\nContinuous optimization of instrumentation and test methods;\nParticipate in ad-hoc projects and routine chemical testing as assigned.\n\nRequirements:\n\nDegree\u00a0holder or\u00a0above in Chemistry or other science relevant disciplines;\nAt least 1 year of relevant hands-on\u00a0laboratory\u00a0testing experience;\nExperience in handling analytical instruments is a Must (e.g. GC-MSMS, Headspace GC-MS, LC-MSMS);\nKnowledge of HOKLAS requirements and ISO/IEC 17025;\nInitiative, organized, independent and willing to work under pressure;\nGood problem solving and communication skills;\nGood command of English and Chinese;\nCandidate with less experience will be considered as Technical officer\n\nWe offer attractive remuneration package and excellent career opportunities to the right candidates. Interested parties please send your full resume with availability, current and expected salary to\u00a0our HR department.\n\nWelcome to visit our company website\u00a0http://www.cmatesting.org/ or more information.\n\nWe are an Equal Opportunities Employer and welcome applications from all qualified candidates. All Personal data collected will be kept in strict confidence and used for recruitment purpose only.", "employment_types": ["Full Time", "Permanent"], "selling_points": ["Fresh graduates are welcome", "On-the-job training", "Immediately available is definitely an advantage"], "locations": ["Tsuen Wan Area"], "categories": ["Sciences, Lab, R&D", "Chemical", "Laboratory", "Others"], "post_time": "2022-01-17T07:22:32Z", "salary": {"currency": null, "max": null, "min": null, "period": null, "term": null}, "salary_visible": false, "title_keywords": ["technician"], "responsibilities": ["develop", "ad-hoc projects", "measurement", "testing"], "requirements": {"degrees": ["degree holder"], "majors": ["science", "chemistry"], "languages": ["english", "chinese"], "language_level": ["good command"], "hard_skills": ["problem solving"], "soft_skills": ["organized", "communication skills", "independent", "problem solving", "hands-on", "initiative", "work under pressure"], "languages_combined": [{"language": "english", "language_level": ["good command"]}, {"language": "chinese", "language_level": ["good command"]}]}, "experience_required": {"duration": ["at least 1 year"], "field": ["laboratory testing", "analytical"]}}, {"job_id": "100003009056243", "location_code": "hk", "company": "CMA Testing and Certification Laboratories", "job_title": "Monitoring Team Leader - Environmental Division", "description": "Job Responsibilities:\n\nCarry out routine chemical testing, such as Heavy metal testing, Azo dye testing, phthalate testing, food container testing and etc, according to standard operating procedure under the guidance of supervisors\nOperating instruments (e.g. GCMS, LCMS) for routine test\nConsolidate and record relevant data on the test worksheet\nMonitor and maintain testing to meet the scheduled turnaround time\nPerform equipment and instrument calibrations according to standard operating procedures\n\nJob Requirements:\n\nHigher Diploma or above in Science/ Chemistry or other related disciplines\nExperience in testing laboratory will be an advantage\nFresh graduates will be considered\n\nOther Benefits:\n\nPublic Holidays\nMonthly Shift Allowance\nOvertime Pay\nDouble Pay and Performance Bonus\nMedical, Dental and Life Insurance\nAnnual Leave, Maternity Leave, Paternity Leave, Marriage Leave, Compassionate Leave\nOn-the-job training as well as Training Sponsorship/ Subsidies\n\nAll information received will be kept in strict confidence and used for employment purpose only. Applicants who are not invited for interview within\u00a05 weeks may assume their applications unsuccessful and their data will be retained for 6 months for other suitable vacancies in our organization and thereafter destroyed.", "employment_types": ["Full Time", "Permanent"], "selling_points": ["Testing and Sampling Services", "Project Management for environmental projects", "Project Management for wastewater/water/BEAM Plus"], "locations": ["Shatin Area"], "categories": ["Sciences, Lab, R&D", "Environmental Science / Waste Management", "Laboratory", "Research & Development (R&D)"], "post_time": "2022-01-18T03:42:07Z", "salary": {"currency": null, "max": null, "min": null, "period": "monthly", "term": null}, "salary_visible": false, "title_keywords": ["team leader"], "responsibilities": ["guidance", "data", "monitor", "procedures", "testing", "maintain"], "requirements": {"degrees": ["higher diploma or above"], "majors": ["related disciplines", "science", "chemistry"], "languages": [], "language_level": [], "hard_skills": [], "soft_skills": [], "languages_combined": []}, "experience_required": {"duration": [], "field": ["laboratory", "testing"]}}, {"job_id": "100003009043726", "location_code": "hk", "company": "Ecospace Limited", "job_title": "Senior Chemist/Chemist", "description": "This position will take lead to oversee the full spectrum of technical operations under the Environmental Division, with the focus on the areas relating to Water and Air testing.\n\nResponsibilities\n\n\n\nProject Management for wastewater / water / BEAM Plus /environmental projects\nCheck daily preliminary report/check data compliance/follow-up the non-compliance/check report format of concern raised by client\nPrepare monthly report to client\nreview project on-site monitoring schedule\nConduct on-site inspection of sampling practices\nArrange / check and follow up annual proficiency\nOther duties as required / requested by client\u00a0\n\n\n\nRequirements\n\n\n\nDegree holder in environmental science or other relevant qualification\nSeven years working experience in chemistry and environmental laboratory experience\nSeven years project management experience\nImmediately available is highly preferred", "employment_types": ["Full Time", "Permanent"], "selling_points": ["Global leader in waste management", "Plan & conduct chemical analysis", "Degree in Science/ Chemistry with min 2 yr exp"], "locations": ["Tsing Yi"], "categories": ["Sciences, Lab, R&D", "Chemical", "Environmental Science / Waste Management", "Laboratory"], "post_time": "2022-01-18T02:05:30Z", "salary": {"currency": null, "max": null, "min": null, "period": "monthly", "term": null}, "salary_visible": false, "title_keywords": ["senior chemist", "chemist"], "responsibilities": ["other duties", "data", "compliance", "review", "monitoring", "site inspection", "project management", "schedule", "monthly report", "report"], "requirements": {"degrees": ["degree holder"], "majors": ["environmental science"], "languages": [], "language_level": [], "hard_skills": ["project management"], "soft_skills": ["project management"], "languages_combined": []}, "experience_required": {"duration": ["seven years"], "field": ["laboratory", "project management", "environmental"]}}, {"job_id": "100003009056256", "location_code": "hk", "company": "Maxim's Caterers Ltd", "job_title": "Part Time - Quality Assurance Assistant (Cakes & Bakery)", "description": "Responsibilities\n\nPlans projects and carries out chemical analysis to ensure work conforms to standard operating procedures and is completed accurately and in a timely manner;\nDirects training of chemists and technicians on performing routine analysis according to standard operating procedures and QA/QC SDPs;\nModifies, evaluates and verifies analytical methods and procedures required for analytical testing;\nAssists in reviewing logbooks to ensure QA/QC standards are met and applies safety rules and adheres to general conduct regulations in handling laboratory materials and equipment;\nArranges for removal of waste material generated by laboratory work in area of responsibility.\n\nRequirements\n\n\nBachelor's Degree in basic science with minimum 2 years applicable experience or equivalent;\nMust be able to apply analytical chemistry methods and techniques in working laboratory situation and participate actively in laboratory problem solving and production.\u00a0 Previous experience on modern instruments and organic chemistry is required;\nSound background of applying QA/QC standards to analytical laboratory is an advantage;\nGood command of both spoken and written English and Chinese.\n\nWe offer attractive remuneration package and fringe benefits to the right candidates. Interested candidates are invited to send detailed resume with Current & Expected Salary and Availability to the Human Resources Department by clicking the \u201cAPPLY NOW\u201d button.\u00a0\n\nEcospace Limited is an equal opportunity employer and welcomes applicants from all qualified candidates. The information provided will be treated in strict confidence and be used only for consideration of your application for relevant / similar posts within the Veolia Group.\nAll personal data of unsuccessful applicants will be destroyed within 24 months from the date of application.", "employment_types": ["Part Time", "Temporary", "Contract"], "selling_points": ["Implementing and maintain the documentation system", "Support the implementation of food safety, hygiene", "5-day work week and rotate day off"], "locations": ["Tai Po Area"], "categories": ["Sciences, Lab, R&D", "Food Science", "Laboratory", "Manufacturing", "Quality Assurance, Control & Testing / ISO"], "post_time": "2022-01-18T03:43:24Z", "salary": {"currency": null, "max": null, "min": null, "period": null, "term": null}, "salary_visible": false, "title_keywords": ["quality assurance assistant"], "responsibilities": ["regulations", "analysis", "a timely manner", "procedures", "testing", "plans"], "requirements": {"degrees": ["degree", "bachelor"], "majors": ["science"], "languages": ["english", "chinese"], "language_level": ["good command"], "hard_skills": ["problem solving", "basic"], "soft_skills": ["problem solving"], "languages_combined": [{"language": "english", "language_level": ["good command"]}, {"language": "chinese", "language_level": ["good command"]}]}, "experience_required": {"duration": ["minimum 2 years"], "field": []}}, {"job_id": "100003009056251", "location_code": "hk", "company": "CMA Testing and Certification Laboratories", "job_title": "Senior Technical Officer - Environmental Division", "description": "Responsibilities:\n\nPerform routine on line and finished food products inspection at various stages on the production line to implement ISO/HACCP policy.\nAssist in implementing and maintain the documentation system and quality management system.\nSupport the implementation of food safety, hygiene and quality assurance operation policies, guidelines and procedures to ensure the entire production process is in compliance with the corporate standard.\nCoordinate and participate work safety, quality assurance and hygiene procedures training to related staff.\nAssist in other ad-hoc projects as assigned.\n\nRequirements:\n\nDiploma holder or above in biochemistry, Food Science or related disciplines;\nSelf-motivated, independent and with good communication skill;\nWell-organized with good analytical skill;\nProficient in PC applications including Chinese word processing;\nGood command of spoken and written English and Chinese / Cantonese;\nWorking location: Tai Po Industrial Estate (with shuttle bus)\nFresh graduate will also be considered.\n\nInterested parties please apply with full resume, state current and expected salaries via clicking \"Apply Now\".\n\n\nAll applications and data collected will be treated in strict confidence and used exclusively for recruitment purposes.\u00a0 Only short listed candidates will be invited for interview.\u00a0 The company will retain the applications for a maximum period of 6 months and may refer suitable candidates to other vacancies within the Group.", "employment_types": ["Full Time", "Permanent"], "selling_points": ["indoor environmental quality", "Perform environmental tests", "5 days work, birthday leave, free shuttle bus"], "locations": ["Shatin Area"], "categories": ["Sciences, Lab, R&D", "Chemical", "Environmental Science / Waste Management", "Laboratory"], "post_time": "2022-01-18T03:42:09Z", "salary": {"currency": null, "max": null, "min": null, "period": "monthly", "term": null}, "salary_visible": false, "title_keywords": ["senior technical officer"], "responsibilities": ["management", "production process", "food safety", "guidelines", "policies", "compliance", "quality", "implementation", "procedures", "inspection", "coordinate", "hygiene", "maintain", "documentation", "ad-hoc projects"], "requirements": {"degrees": ["diploma holder", "fresh graduate"], "majors": ["related disciplines", "food science"], "languages": ["cantonese", "english", "chinese"], "language_level": ["good command", "proficient"], "hard_skills": ["analytical skill", "chinese word processing", "pc applications"], "soft_skills": ["self-motivated", "analytical skill", "independent", "communication skill", "well-organized"], "languages_combined": [{"language": "cantonese", "language_level": ["good command"]}, {"language": "english", "language_level": ["good command"]}, {"language": "chinese", "language_level": ["good command", "proficient"]}]}, "experience_required": {"duration": [], "field": []}}, {"job_id": "100003009055765", "location_code": "hk", "company": "ConnectedGroup Limited", "job_title": "Senior Quality Assurance Engineer", "description": "Responsibilities:\n\nTechnical support in team: project methodology, site inspection, data analysis, endorse reports, consultancy service for clients, technical service accreditation assessment\u00a0\n\nRequirements:\n\n\n\nMaster degree in engineering, environmental science or other relevant qualification\nTwo years working experience in environmental science, indoor environmental quality or relevant working experience\u00a0\nImmediately available is highly preferred\n\nWe offer attractive remuneration package and excellent career opportunities to the right candidates. Interested parties please send your full resume with\u00a0availability, current and expected salary to our HR Division.\n\nWelcome to visit our company website\u00a0www.cmatesting.org\u00a0or more information.\n\nWe are an Equal Opportunities Employer and welcome applications from all qualified candidates. All Personal data collected will be kept in strict confidence and used for recruitment purpose only.", "employment_types": ["Full Time", "Permanent"], "selling_points": ["Well-established multinational company", "Attractive remuneration package", "Responsible for handling Hardgoods Products"], "locations": ["Not Specified"], "categories": ["Sciences, Lab, R&D", "Laboratory", "Manufacturing", "Quality Assurance, Control & Testing / ISO", "Others"], "post_time": "2022-01-18T02:55:47Z", "salary": {"currency": null, "max": null, "min": null, "period": "monthly", "term": null}, "salary_visible": false, "title_keywords": ["engineer"], "responsibilities": ["technical support", "data analysis", "reports", "site inspection"], "requirements": {"degrees": ["master degree"], "majors": ["environmental science", "engineering"], "languages": [], "language_level": [], "hard_skills": [], "soft_skills": [], "languages_combined": []}, "experience_required": {"duration": ["two years"], "field": ["environmental", "relevant working experience"]}}, {"job_id": "100003009056247", "location_code": "hk", "company": "CMA Testing and Certification Laboratories", "job_title": "Laboratory Technician - Environmental Division", "description": "Responsibility:\n\n\nResponsible for R&D method development and validation using various analytical instruments\nPrepare analytical test procedure and test instructions\nSupport other processes with all\u00a0technical related issues\nDeliver quality services and solution on technical issues to both internal and external clients\nKeep abreast of the new testing standards and regulations\nSupport enquiries for Chemical safety assessment\nJob Requirements:\n\n\nBachelor Degree or above in Chemistry related disciplines\nMinimum 1-2 years\u2019 experience in laboratory\nExperience in handling GC, LC, ICPAES, ICPMS, AAS is an advantage\nBasic knowledge on ISO 17025/HOKLAS is a plus\nInitiative, well-organized and willing to work under pressure\nGood analytical, communication and problem solving skills\nGood command of English and Chinese, including Mandarin\nGood PC knowledge in MS Word, Excel and PowerPoint\nFresh graduate will also be considered\n\nWe offer competitive salary and benefits to\u00a0the right candidate.\u00a0 Interested parties please send your application with date of availability, present & expected salary to the\u00a0Human Resources Department,\u00a0Bureau Veritas Hong Kong\u00a0Limited\u00a0by mail or\u00a0clicking \u201cAPPLY NOW\u201d.\u00a0\u00a0To submit your application by mail, please mark\u00a0\"Confidential\" and position applied on the envelope.\n\nOur Benefits:\n\n5-day Work Week\u00a0\nOvertime Payment\nPublic Holiday, Annual Leave, Marriage Leave, Maternity Leave & Paternity Leave\nDouble Pay, Performance Bonus\nLife & Medical Insurance Benefits\nMandatory Provident Fund Contribution\nEducation & Training Subsidies\nExcellent Training & Career Advancement Opportunities\n\nJoin us on Linkedin:\u00a0\u00a0https://hk.linkedin.com/company/bureau-veritas-consumer-products-services\n\nMail\u00a0\n7/F,\u00a0Harbourside HQ\n8 Lam Chak Street\nKowloon Bay, Kowloon\n\nPersonal data collected will be used for recruitment purposes only.", "employment_types": ["Full Time", "Permanent"], "selling_points": ["Environmental laboratory work", "Perform environmental tests", "5 days work, birthday leave, free shuttle bus"], "locations": ["Shatin Area"], "categories": ["Sciences, Lab, R&D", "Chemical", "Environmental Science / Waste Management", "Laboratory"], "post_time": "2022-01-18T03:42:08Z", "salary": {"currency": null, "max": null, "min": null, "period": "monthly", "term": null}, "salary_visible": false, "title_keywords": ["laboratory technician"], "responsibilities": ["regulations", "quality", "testing"], "requirements": {"degrees": ["degree or above", "bachelor", "fresh graduate"], "majors": ["related disciplines", "chemistry"], "languages": ["english", "chinese", "mandarin"], "language_level": ["good command"], "hard_skills": ["excel", "plus", "basic", "powerpoint", "problem solving skills", "pc knowledge", "ms word"], "soft_skills": ["well-organized", "communication", "problem solving skills", "initiative", "work under pressure"], "languages_combined": [{"language": "english", "language_level": ["good command"]}, {"language": "chinese", "language_level": ["good command"]}, {"language": "mandarin", "language_level": ["good command"]}]}, "experience_required": {"duration": ["minimum 1-2 years"], "field": ["laboratory"]}}, {"job_id": "100003009052327", "location_code": "hk", "company": "API Lab Testing Limited", "job_title": "Chemical Lab Assistant Chemist (Multiple Vacancy)", "description": "Our Client is a well-established multinational company, they are looking for a Senior Quality Assurance Engineer to join their expanding business.\n\nKey Job Responsibilities include:\n\nResponsible to handle all technical aspects of hardgoods product\nEnsure the technical process and quality manual are in line with customers requirement.\nResponsible to handle related testing documents and review all testing report.\nKeep up to date with new industry innovation and best practice to drive continuous improvement\nWork close with internal parties for testing requirements and customers enquires\nConduct factories audit and ensure the performance meet company standard.\nProvide training to newcomers and support on product areas\nMaintain a strong relationship with supplier\n\nOther requirements include:\n\nTertiary education with minimum 3 years' experience in Quality assurance/testing or other related discipline\nExperienced in hardgoods items\nAbility to conduct risk assessments\nFamiliar with Quality Management System.\nGood communication skills, self-motivated, proactive and open minded\nExcellent in English, Cantonese and Mandarin, both spoken and written", "employment_types": ["Full Time"], "selling_points": ["Self-motivated", "Chemical Lab Assistant Chemist", "English & Chinese"], "locations": ["Tsuen Wan Area"], "categories": ["Sciences, Lab, R&D", "Laboratory"], "post_time": "2022-01-17T02:46:38Z", "salary": {"currency": null, "max": null, "min": null, "period": "monthly", "term": null}, "salary_visible": false, "title_keywords": ["chemical lab assistant", "chemist"], "responsibilities": ["provide training", "review", "quality", "audit", "testing", "maintain", "internal parties", "report"], "requirements": {"degrees": [], "majors": [], "languages": ["cantonese", "english", "mandarin"], "language_level": ["excellent"], "hard_skills": [], "soft_skills": ["communication skills", "self-motivated", "proactive", "open minded"], "languages_combined": [{"language": "cantonese", "language_level": ["excellent"]}, {"language": "english", "language_level": ["excellent"]}, {"language": "mandarin", "language_level": ["excellent"]}]}, "experience_required": {"duration": ["minimum 3 years"], "field": ["related", "quality assurance", "testing", "education"]}}, {"job_id": "100003009052678", "location_code": "hk", "company": "Hong Kong Laboratory Co., Limited", "job_title": "Medical Laboratory Technologist (Part I)", "description": "Job Overview:\n\nYou will work in an organic team of Chemical lab and carry out the routine testing which includes sample preparation, instrument analysis and resulting.\n\nEssential Duties and Responsibilities:\n\n\n1.\u00a0Carry out routine testing in the chemical lab\n\n2. Maintain the smooth of daily operation which include sample preparation, instrument analysis and result issue\n\n3. Maintenance and calibration of chemical lab equipment\n\n4. Implement the ISO 17025 and HOKLAS requirement in the lab\n\n5. Assist other duties as directed by lab manager\n\n6. 5 days work week from Monday to Friday.\n\nExperience & Competencies Required:\n\n\nSolid experience in daily operation of chemical testing laboratory\u00a0\nMinimum 5 years of experience in analytical instruments such as GCMS, LCMS & LCMSMS\nKnowledge of chemical tests for toys and food contact requirements of EU & US and REACH\nLess experience will consider for junior position (Chemist)\n\nEducation and Qualifications Required:\n\nDegree in chemistry or related discipline\nProficiency in both written and spoken English & Chinese\nSelf-motivated, hardworking and detail-minded", "employment_types": ["Full Time", "Permanent"], "selling_points": [], "locations": ["Shatin Area"], "categories": ["Sciences, Lab, R&D", "Laboratory", "Life Science", "Others"], "post_time": "2022-01-17T03:41:19Z", "salary": {"currency": null, "max": null, "min": null, "period": "monthly", "term": null}, "salary_visible": false, "title_keywords": ["medical laboratory technologist"], "responsibilities": ["maintenance", "other duties", "sample preparation", "analysis", "daily operation", "testing", "maintain", "contact"], "requirements": {"degrees": ["degree"], "majors": ["chemistry"], "languages": ["english", "chinese"], "language_level": ["proficiency"], "hard_skills": ["analysis", "maintenance"], "soft_skills": ["detail-minded", "self-motivated", "hardworking", "smooth"], "languages_combined": [{"language": "english", "language_level": ["proficiency"]}, {"language": "chinese", "language_level": ["proficiency"]}]}, "experience_required": {"duration": ["minimum 5 years"], "field": ["laboratory", "chemical testing", "operation", "analytical"]}}, {"job_id": "100003009056627", "location_code": "hk", "company": "ZSHK Laboratories Limited", "job_title": "Laboratory Animal Technician", "description": "Located in HKSTP, the Drug Safety Testing Centre (DSC) aims to facilitate the translation of promising therapeutics and medical devices from the pre-clinical phase to the clinical stage.\u00a0 This first of its kind facility adheres to the highest international and industry standards, including AAALAC and Good Laboratory Practices (GLP), which is an international standard prescribing a set of rigid and quality criteria for conducting studies, data collection and reporting. \u00a0It defines how preclinical data is required and accepted by different regulatory authorities (for example, China NMPA, US FDA and OECD).\u00a0 The facility commits to provide the GLP-compliant preclinical services on toxicology, genotoxicity, toxicokinetics, safety pharmacology, reproductive toxicology, ADME etc for facilitating the development of new drug.\n\n\nResponsibilities:\nFully understand the importance of pre-clinical animal study for human medicine research and drug development process; ensure a high level of animal welfare and work to improve the quality of life for laboratory animals.\nCarry out rodent\u2019s GLP and non-GLP study according to the designed protocol. \u00a0Experimental \u00a0procedures would include, but not limited to, clinical observations, different routes of administration, blood collections and live data acquisition etc.\nComplete the experimental records in accordance with GLP specifications and related standard operating procedures (SOP) within the facility.\nWork in a team to undertake technical and staff supervision/ management duties in connection with the operation of the facility.\nOn-the-job training will be provided.\nQualifications:\nApplicants should possess a Bachelor\u2019s degree or equivalent;\nBe self-motivated, responsible, empathetic, and curious; excellent communication, analytical and problem-solving skills; an interest in laboratory animal science and technology; and demonstrated commitment to continuing professional development in the field.\nWilling to join the pharmaceutical research and development industry and contribute to the cause of human medicine and health.\nGood command of spoken and written English and Chinese; fluent in Putonghua would be an advantage.\nExperience in animal husbandry, operation and maintenance of equipment for sanitation and sterilisation (e.g. autoclave), or inventory/record keeping will be an advantage but not essential.", "employment_types": ["Full Time", "Permanent", "Contract"], "selling_points": [], "locations": ["Shatin Area"], "categories": ["Sciences, Lab, R&D", "Laboratory", "Medical Services", "Pharmaceutical", "Research & Development (R&D)"], "post_time": "2022-01-18T05:14:31Z", "salary": {"currency": null, "max": null, "min": null, "period": "monthly", "term": null}, "salary_visible": false, "title_keywords": ["technician"], "responsibilities": ["reporting", "management", "maintenance", "data", "inventory", "quality", "procedures", "testing", "communication", "specifications", "data collection", "administration"], "requirements": {"degrees": ["degree", "bachelor"], "majors": [], "languages": ["putonghua", "english", "chinese"], "language_level": ["advantage", "good command", "fluent"], "hard_skills": ["animal science", "maintenance", "animal husbandry", "animal welfare", "problem-solving skills", "translation"], "soft_skills": ["communication", "problem-solving skills", "self-motivated", "responsible"], "languages_combined": [{"language": "putonghua", "language_level": ["fluent", "advantage"]}, {"language": "english", "language_level": ["good command"]}, {"language": "chinese", "language_level": ["good command"]}]}, "experience_required": {"duration": [], "field": ["operation", "maintenance"]}}, {"job_id": "100003009056757", "location_code": "hk", "company": "TUV SUD Hong Kong Limited", "job_title": "Assistant Test Engineer / Test Engineer  - Chemical Lab (Fresh Graduate Welcome)", "description": "Job Duties:\nPrepare samples by various digestion and extraction methods\nConduct chemical analysis according to standard operating procedures\nRun analytical instruments (e.g GC-MS. HPLC, LC-MS, UV-VIS, ICP, AAS etc.)\nMaintain instruments sustainability\nAnalyze data and issue result\nImplement of the laboratory management system in accordance with ISO/IEC 17025 and related requirement by accreditation/ certification body (CB, CNAS, DAkkS, HOKLAS, ZLS etc)\nJob Requirements:\nHigher Diploma/ Degree holder in Chemistry or related discipline\nRelevant working experience in chemical testing or chemistry related industry is an advantage\nGood understanding in quality and safety requirements in chemical laboratories\nWith hand on experiences in operating and performing maintenance for instruments: (1) ICP-OES, (2) UV-VIS, (3) GC-MS, (4) HPLC-MS is an advantage\nHardworking, self-motivated and a good team player\nAble to work independently and under pressure\nCandidate with more experience will be considered as Test Engineer\nWorking location : Yuen Long (5 mins walk from Long Ping Station)\u00a0\n\nWe offer attractive remuneration package with potential career advancement to the right candidate. Interested parties, please apply with detailed resume, stating expected salary and date of availability to Human Resources Department by\u00a0clicking 'Apply Now'.\n\nFor more company information, please visit our webpage www.tuvsud.com\n(Data collected will be treated as strictly confidential and will be used for recruitment purpose only)\u00a0\u00a0", "employment_types": ["Full Time", "Permanent"], "selling_points": ["Higher Diploma/ Degree holder in Chemistry", "Prepare samples by various digestion", "Able to work independently and under pressure"], "locations": ["Yuen Long Area"], "categories": ["Sciences, Lab, R&D", "Chemical", "Food Science", "Laboratory"], "post_time": "2022-01-18T06:13:57Z", "salary": {"currency": null, "max": null, "min": null, "period": "monthly", "term": null}, "salary_visible": false, "title_keywords": ["chemical", "engineer", "assistant"], "responsibilities": ["management", "analysis", "procedures", "maintain", "analyze data"], "requirements": {"degrees": ["diploma", "degree holder"], "majors": ["chemistry"], "languages": [], "language_level": [], "hard_skills": ["maintenance"], "soft_skills": ["good team player", "self-motivated", "under pressure", "work independently", "hardworking"], "languages_combined": []}, "experience_required": {"duration": [], "field": ["related", "chemical testing", "relevant working experience", "maintenance"]}}, {"job_id": "100003009055500", "location_code": "hk", "company": "Bureau Veritas Hong Kong Limited", "job_title": "Chemist / Assistant Chemist (R&D)", "description": "Responsibility:\n\n\nResponsible for R&D method development and validation using various analytical instruments\nPrepare analytical test procedure and test instructions\nSupport other processes with all\u00a0technical related issues\nDeliver quality services and solution on technical issues to both internal and external clients\nKeep abreast of the new testing standards and regulations\nSupport enquiries for Chemical safety assessment\nJob Requirements:\n\n\nBachelor Degree or above in Chemistry related disciplines\nMinimum 1-2 years\u2019 experience in laboratory\nExperience in handling GC, LC, ICPAES, ICPMS, AAS is an advantage\nBasic knowledge on ISO 17025/HOKLAS is a plus\nInitiative, well-organized and willing to work under pressure\nGood analytical, communication and problem solving skills\nGood command of English and Chinese, including Mandarin\nGood PC knowledge in MS Word, Excel and PowerPoint\nFresh graduate will also be considered\n\nWe offer competitive salary and benefits to\u00a0the right candidate.\u00a0 Interested parties please send your application with date of availability, present & expected salary to the\u00a0Human Resources Department,\u00a0Bureau Veritas Hong Kong\u00a0Limited\u00a0by mail or\u00a0clicking \u201cAPPLY NOW\u201d.\u00a0\u00a0To submit your application by mail, please mark\u00a0\"Confidential\" and position applied on the envelope.\n\nOur Benefits:\n\n5-day Work Week\u00a0\nOvertime Payment\nPublic Holiday, Annual Leave, Marriage Leave, Maternity Leave & Paternity Leave\nDouble Pay, Performance Bonus\nLife & Medical Insurance Benefits\nMandatory Provident Fund Contribution\nEducation & Training Subsidies\nExcellent Training & Career Advancement Opportunities\n\nJoin us on Linkedin:\u00a0\u00a0https://hk.linkedin.com/company/bureau-veritas-consumer-products-services\n\nMail\u00a0\n7/F,\u00a0Harbourside HQ\n8 Lam Chak Street\nKowloon Bay, Kowloon\n\nPersonal data collected will be used for recruitment purposes only.", "employment_types": ["Full Time", "Permanent"], "selling_points": ["Global Leader in Testing Industry", "Major in Chemistry or Related Science Disciplines", "Double Pay, Medical Insurance, Discretionary Bonus"], "locations": ["Kowloon Bay"], "categories": ["Sciences, Lab, R&D", "Chemical", "Laboratory", "Research & Development (R&D)"], "post_time": "2022-01-18T06:40:39Z", "salary": {"currency": null, "max": null, "min": null, "period": "monthly", "term": null}, "salary_visible": false, "title_keywords": ["assistant", "chemist"], "responsibilities": ["regulations", "quality", "testing"], "requirements": {"degrees": ["degree or above", "bachelor", "fresh graduate"], "majors": ["related disciplines", "chemistry"], "languages": ["english", "chinese", "mandarin"], "language_level": ["good command"], "hard_skills": ["excel", "plus", "basic", "powerpoint", "problem solving skills", "pc knowledge", "ms word"], "soft_skills": ["well-organized", "communication", "problem solving skills", "initiative", "work under pressure"], "languages_combined": [{"language": "english", "language_level": ["good command"]}, {"language": "chinese", "language_level": ["good command"]}, {"language": "mandarin", "language_level": ["good command"]}]}, "experience_required": {"duration": ["minimum 1-2 years"], "field": ["laboratory"]}}, {"job_id": "100003009056244", "location_code": "hk", "company": "CMA Testing and Certification Laboratories Limited", "job_title": "Senior Technical Officer - Organic Division", "description": "Job Overview:\n\nYou will work in Chemical lab and carry out the routine testing which includes sample preparation, instrument analysis and resulting.\n\nEssential Duties and Responsibilities:\n\n\n1.\u00a0Carry out routine testing in the chemical lab\n\n2. Maintain the smooth of daily operation which include sample preparation, instrument analysis and result issue\n\n3. Maintenance and calibration of chemical lab equipment\n\n4. Implement the ISO 17025 and HOKLAS requirement in the lab\n\n5. Assist other duties as directed by lab manager\n\n6. 5 days work week from Monday to Friday.\n\nExperience & Competencies Required:\n\n\nSolid experience in daily operation of chemical testing laboratory is preferred\nKnowledge in operation of analytical instruments such as ICP, GCMS and food contact test is an advantage\n\nEducation and Qualifications Required:\n\nHigher Diploma or above in chemistry or related discipline\nProficiency in both written and spoken English & Chinese\nSelf-motivated, hardworking and detail-minded", "employment_types": ["Full Time", "Permanent"], "selling_points": ["Handling of chemical tests related routine sample", "Degree in Chemistry or relevant discipline", "5 days,Medical, OT Pay,Double pay,Free shuttle bus"], "locations": ["Shatin Area"], "categories": ["Sciences, Lab, R&D", "Chemical", "Laboratory", "Life Science"], "post_time": "2022-01-18T03:42:07Z", "salary": {"currency": null, "max": null, "min": null, "period": "monthly", "term": null}, "salary_visible": false, "title_keywords": ["senior technical officer"], "responsibilities": ["maintenance", "other duties", "sample preparation", "analysis", "daily operation", "testing", "maintain", "contact"], "requirements": {"degrees": ["higher diploma or above"], "majors": ["chemistry"], "languages": ["english", "chinese"], "language_level": ["proficiency"], "hard_skills": ["analysis", "maintenance"], "soft_skills": ["detail-minded", "self-motivated", "hardworking", "smooth"], "languages_combined": [{"language": "english", "language_level": ["proficiency"]}, {"language": "chinese", "language_level": ["proficiency"]}]}, "experience_required": {"duration": [], "field": ["laboratory", "chemical testing", "operation"]}}, {"job_id": "100003009054647", "location_code": "hk", "company": "Prenetics Limited", "job_title": "Registered Nurse", "description": "\nDuties:\n\n\nMonitor and manage the process of testing procedures, including reception, handling, processing, storage and testing of human blood according to the Standard Operation Procedure (SOP)\nEstablish new and review current SOP\nReview and approve quality control data for testing\nReview and approve laboratory report\nParticipate in-house and external training as required\nOther ad-hoc duties are also required\n\nRequirements:\n\n\nValid Medical Laboratory Technologist Part I practicing cert issued by the HKMLT Board\nBachelor Degree or Higher Technical Certificate (HTC) in Biomedical Science, Medical Laboratory Sciences other related disciplines\nExperience in genetic/DNA analysis, including DNA extraction, sequencing, PCR etc. is preferable.\nStrong sense of responsibility\nMust be a good team worker with excellent communication skills as well as be able to work independently\nAble to communicate in Mandarin and Cantonese", "employment_types": ["Part Time"], "selling_points": ["Registered Nurse", "HA Project / CTC Project / CHP Project", "CNTS/NS Method"], "locations": ["Quarry Bay"], "categories": ["Sciences, Lab, R&D", "Laboratory", "Life Science", "Medical Services", "Nursing"], "post_time": "2022-01-17T10:24:10Z", "salary": {"currency": null, "max": null, "min": null, "period": "hourly", "term": null}, "salary_visible": false, "title_keywords": ["registered nurse"], "responsibilities": ["data", "review", "monitor", "procedures", "testing", "quality control", "ad-hoc duties", "report"], "requirements": {"degrees": ["certificate", "degree", "bachelor"], "majors": ["biomedical science", "related disciplines"], "languages": ["cantonese", "mandarin"], "language_level": [], "hard_skills": ["analysis"], "soft_skills": ["communication skills", "work independently", "sense of responsibility"], "languages_combined": [{"language": "cantonese", "language_level": []}, {"language": "mandarin", "language_level": []}]}, "experience_required": {"duration": [], "field": []}}, {"job_id": "100003009056242", "location_code": "hk", "company": "CMA Testing and Certification Laboratories", "job_title": "Assistant Manager / Senior Technical Officer (Air Team) - Environmental Division", "description": "\u8077\u8cac :\u8ca0\u8cac\u8655\u7406\u6a23\u677f, \u6536\u96c6\u5316\u5b78\u54c1\u6578\u64da, \u6e2c\u8a66\u5206\u6790; \u5354\u52a9\u5be6\u9a57\u5ba4\u7684\u65e5\u5e38\u904b\u4f5c; \u5354\u52a9\u7de8\u5beb\u5316\u5b78\u54c1\u5206\u6790\u5831\u544a; \u6e05\u6d17\u5be6\u9a57\u5ba4\u7528\u5177\u53ca\u5668\u76bf, \u4fdd\u6301\u5be6\u9a57\u5ba4\u6574\u6f54\n\u8cc7\u6b77 :\u5c08\u4e0a\u6559\u80b2\uff1a\u6587\u6191/\u8b49\u66f8; \u4e00\u822c\u7cb5\u8a9e; \u7565\u61c2\u8b80\u5beb\u4e2d\u6587; \u7565\u61c2\u8b80\u5beb\u82f1\u6587; \u61c2\u96fb\u8166\u6587\u66f8\u8655\u7406; \u61c2Microsoft Office\n\u5f85\u9047 :\u6bcf\u6708$11,000 - $13,000, \u6709\u8d85\u6642\u5de5\u4f5c\u6d25\u8cbc, \u5e74\u504714\u5929, \u9280\u884c\u5047\u671f, \u914c\u60c5\u6027\u82b1\u7d05, \u91ab\u7642\u4fdd\u96aa, \u7a7f\u68ad\u5df4\u58eb\u670d\u52d9 \u53ca\u91ab\u7642\u798f\u5229, \u661f\u671f\u4e00\u81f3\u4e94: \u4e0a\u53488\u6642\u534a\u81f3\u4e0b\u53485\u6642\u534a\u53ca\u661f\u671f\u516d: \u4e0a\u53488\u6642\u534a\u81f3\u4e2d\u534812\u6642\u534a, \u6bcf\u9031\u5de5\u4f5c5\u5929\u534a\n\u7533\u8acb\u9808\u77e5 :\u6c42\u8077\u8005\u53ef\u81f4\u96fb28945678\u8207\u8f1d\u56fa\u6280\u8853\u670d\u52d9\u6709\u9650\u516c\u53f8\u5b6b\u5148\u751f\u806f\u7d61\u3002", "employment_types": ["Full Time", "Permanent"], "selling_points": ["Testing and Sampling Services", "Approved signatory to sign HKIAS endorsed IAQ", "3 years experiences in IAQ/BEAM Plus/LEED/WELL"], "locations": ["Shatin Area"], "categories": ["Sciences, Lab, R&D", "Environmental Science / Waste Management", "Laboratory", "Research & Development (R&D)"], "post_time": "2022-01-18T03:42:07Z", "salary": {"currency": null, "max": null, "min": null, "period": "monthly", "term": null}, "salary_visible": false, "title_keywords": ["assistant manager", "senior technical officer"], "responsibilities": [], "requirements": {"degrees": [], "majors": [], "languages": [], "language_level": [], "hard_skills": [], "soft_skills": [], "languages_combined": []}, "experience_required": {"duration": [], "field": []}}, {"job_id": "100003009046591", "location_code": "hk", "company": "Nestle Hong Kong Ltd", "job_title": "Laboratory Technician", "description": "Responsibilities:\n\n\n\nHandling\u00a0of chemical tests related to routine sample;\nTest result analysis and review;\nOut of specification results investigation;\nDevelop and review test methods;\nHandling of test enquiry;\nOperation and maintenance of analytical instrument (e.g. GC/MS, LC-DAD, LC/MS, LC/MS/MS);\nMethod validation and preparation for accreditation audit;\nAssist in R&D work;\nUndertake any other duties as assigned.\n\nRequirements:\n\n\n\nDegree or above in Chemistry or relevant discipline;\nKnowledge of ISO 17025 quality system and accreditation requirements;\nExperienced in lab supervision and operation management;\nAnalytical instrumentation skill;\nInitiative, organized and comprehensive\nCandidate with less experience will be considered as Technical Officer\n\nOther Benefits:\n\n5 days work week\nMedical Insurance\nOver Time Pay\nDouble pay\nFree shuttle bus\n\nWe offer attractive remuneration package and excellent career opportunities to the right candidates. Interested parties please send your full resume with availability, current and expected salary to\u00a0our HR department.\n\nWelcome to visit our company website\u00a0http://www.cmatesting.org/ or more information.\n\nWe are an Equal Opportunities Employer and welcome applications from all qualified candidates. All Personal data collected will be kept in strict confidence and used for recruitment purpose only.", "employment_types": ["Full Time", "Permanent"], "selling_points": ["Great opportunity in FMCG/F&B", "World No.1 F&B company with collaborative culture", "Laboratory Testing"], "locations": ["Yuen Long"], "categories": ["Sciences, Lab, R&D", "Food Science", "Laboratory", "Manufacturing", "Quality Assurance, Control & Testing / ISO"], "post_time": "2022-01-13T15:29:27Z", "salary": {"currency": null, "max": null, "min": null, "period": "monthly", "term": null}, "salary_visible": false, "title_keywords": ["laboratory technician"], "responsibilities": ["any other duties", "maintenance", "analysis", "review", "audit", "investigation", "develop"], "requirements": {"degrees": ["degree or above"], "majors": ["chemistry"], "languages": [], "language_level": [], "hard_skills": [], "soft_skills": ["organized", "comprehensive", "initiative"], "languages_combined": []}, "experience_required": {"duration": [], "field": []}}, {"job_id": "100003009047740", "location_code": "hk", "company": "Catagene Limited", "job_title": "Part Time Laboratory Assistant", "description": "Founded in 2014, Prenetics is a major global diagnostics and genetic testing company with the mission to bring health closer to millions of people globally and decentralize healthcare by making the three pillars \u2014 Prevention, Diagnostics and Personalized Care \u2014 comprehensive and accessible to anyone, at anytime and anywhere. Prenetics is led by visionary entrepreneur,\u00a0Danny Yeung, with a team of over 800 employees and operations across 9 locations, including\u00a0United Kingdom,\u00a0Hong Kong,\u00a0India,\u00a0South Africa, and\u00a0Southeast Asia. Prenetics develops consumer genetic testing and early colorectal cancer screening; provides COVID-19 testing, rapid point of care and at-home diagnostic testing and medical genetic testing.\n\nMost recently, Prenetics made\u00a0international headlines to become the first Unicorn in Hong Kong to publicly list on the Nasdaq via merger with\u00a02021 Adrian Cheng's Artisan Acquisition Corp, valuing Prenetics at approximately US $1.7b.\n\nMake a difference to the community! Let's fight COVID-19 together for Hong Kong and make Hong Kong safe again. This is a unique opportunity to make a difference to the community and to play a role to fight COVID-19 here in Hong Kong. The faster we identify, the faster we can stop the virus chain! Please note that all safety guidelines and protocols will be met to ensure safety for everyone. Join us as a Registered Nurse and make a difference today!\u00a0\n\nThis position will begin with a 6-months contract and with the potential opportunity to extend the contract to a permanent role after organizational and performance review when the initial 6-month period ends.\n\nKey Responsibilities\n\nResponsible for conducting sample collection on site by \"CNTS/NS\" method\nExecute operation training\nReview procedure to ensure all operations fulfill the guideline\n\n\n\nJob Requirements\n\nHolder of Registered Nurse License with valid practicing certificate\nFamiliar with Infection Control Guideline\nGood communication and problem-solving skills\nExperience in NS and CNTS\nImmediate availability is an advantage\nCompetitive hourly remuneration will be provided\n\n\n\nOur DNA is\u00a0P-R-E-N-E-T-I-C-S.\u00a0See what each word of our company name means:\n\nPassion\n\nYou love what you do and accomplish amazing result\nYou spread positivity, bring enthusiasm to work and inspire team members\nYou drive team toward specific goals, even when they seem unlikely or difficult\n\nResilience\n\nYou embrace changes and be able to drive through uncertainty, ambiguity and uncomfortable situations\nYou bounce back quickly from setbacks and challenges\nYou are persistent and determined to achieve the desired outcome\n\nEmpowerment\n\nYou trust others to play their positions well like an elite sports team\nYou foster a strong team spirit while encouraging others to take initiatives and risks\nYou create a space to allow team to grow and hold each other accountable\n\niNtegrity\n\nYou are trustworthy and lead by example\nYou are consistent in your message and action all the times\nYou deliver what you have promised\n\nEpic\n\nYou challenge your own comfort zone and always outperform yourself\nYou make meaningful and amazing impact to the world\nYou dare to take risks and you move fast\n\nTransparency\n\nYou are completely honest and committed to giving candid feedbacks, no matter how challenging it might be\nYou share ideas, knowledge and skills that empower others and create access to information with the wider team\nYou share wins and failures openly\n\nIngenuity\n\nYou make sound judgement and come up with solutions that are creative and smart. Copy when feasible\nYou challenge the status quo and question things that could be done differently for better. Modify the wheel if you can\u2019t change it\nYou think outside of the box and make value-based innovation\n\nCommunications\n\nYou articulate your thoughts and ideas effectively and respectfully\nYou know your audience and talk in a way they want to be told\nYou make sure communications happens, no matter where you are\n\nSelflessness\n\nYou put the needs of others before one's own and find ways in helping other to succeed\nYou focus on team wins than personal wins and share credits\nYou act in the company's best interest\nWe are Prenetics, our people make us who we are.", "employment_types": ["Full Time", "Permanent"], "selling_points": ["Diploma in Chemistry, Biology or equivalent", "Being proactive and able to work independently", "Immediately available is highly preferred"], "locations": ["Shatin Area"], "categories": ["Sciences, Lab, R&D", "Laboratory", "Medical Services", "Medical Services Technician", "Others"], "post_time": "2022-01-14T03:49:44Z", "salary": {"currency": null, "max": null, "min": null, "period": "hourly", "term": null}, "salary_visible": false, "title_keywords": ["laboratory assistant"], "responsibilities": ["operations", "review"], "requirements": {"degrees": ["certificate"], "majors": [], "languages": [], "language_level": [], "hard_skills": ["no", "r", "word", "make", "c", "problem-solving skills", "focus"], "soft_skills": ["team spirit", "determined", "trustworthy", "persistent", "articulate", "integrity", "accountable", "communication", "committed", "honest", "problem-solving skills", "focus", "creative"], "languages_combined": []}, "experience_required": {"duration": [], "field": []}}, {"job_id": "100003009052107", "location_code": "hk", "company": "Leader Enterprise Limited", "job_title": "Clinical Embryologist (Trainee/Experienced)", "description": "This position will take lead to oversee the full spectrum of technical operations under the Environmental Division, with the focus on the areas relating to Water and Air testing.\n\nResponsibilities\n\nPerform on-site indoor air quality inspection;\nTo prepare test reports, technical proposals and other relevant project submissions;\nFollow projects on indoor air quality/BEAM Plus/LEED/WELL/acoustics/Carbon & Energy Audit\nTo liaise with clients on technical issues\n\n\n\nRequirements\n\nDegree holder or Master in environmental engineering/environmental science/building services or other relevant qualification\nFive years or above working experience in environmental science, indoor air quality environmental quality or relevant working experience\nExperience as approved signatory for signing HKIAS endorsed IAQ inspection reports is highly preferred\nCandidate with less experience might be consider as Senior Technical Officer\nImmediately available is highly preferred", "employment_types": ["Full Time"], "selling_points": ["Degree in Science", "Embryologist", "salary"], "locations": ["Tsim Sha Tsui"], "categories": ["Sciences, Lab, R&D", "Laboratory", "Life Science", "Others"], "post_time": "2022-01-17T02:10:21Z", "salary": {"currency": null, "max": null, "min": null, "period": "monthly", "term": null}, "salary_visible": false, "title_keywords": ["trainee"], "responsibilities": ["liaise with clients", "quality", "audit", "inspection", "reports"], "requirements": {"degrees": ["master", "degree holder"], "majors": ["environmental science", "environmental engineering", "building services"], "languages": [], "language_level": [], "hard_skills": [], "soft_skills": [], "languages_combined": []}, "experience_required": {"duration": ["five years"], "field": ["environmental", "relevant working experience"]}}, {"job_id": "100003009056246", "location_code": "hk", "company": "CMA Testing and Certification Laboratories Limited", "job_title": "Assistant Business Executive  - Environmental", "description": "Position Summary\n\n\nWorking Location: Yuen Long Industrial Estate\n\nDuty Pattern: 8:00am - 4:30pm or 11:00am - 7:30pm\n(5.5 days per week, alternative Saturday)\n\u00a0\u00a0Responsibilities:\n\nSampling and testing food and beverage raw materials and finished products\nAnalyze test data, verify results and prepare reports\nSAP system preparation work\nParcel packing, agar preparation and material purchasing\nConduct equipment maintenance and calibration\nMonitor factory environment and hygiene conditions\n\n\u00a0\u00a0Requirements:\u00a0\n\nHigher Diploma or above in Food Technology, Food Science, Chemistry, Biology or Biochemistry\nGood analytical and organizational skills\nGood communication skills in both written and spoken English and Chinese\nFresh graduates are also considered\n\nPlease submit\u00a0 application with your resume stating the employment history, present and expected salary by clicking \"Apply Now\".\n\nWe, at all levels, are strongly committed to the Company, its development and its culture. We practice what we preach and give great importance to training and development of people. We offer excellent career development opportunities, attractive remuneration package, comprehensive fringe benefits and wellness programs to the right candidates\n\nWe are an equal opportunity employer and committed to workforce diversity with opportunity for continuous development and growth to all employees.\n\n(All information will be treated in strict confidence and will be used exclusively for recruitment related purpose only. Information of unsuccessful applicants will be destroyed upon completion of the recruitment process.)", "employment_types": ["Full Time", "Permanent"], "selling_points": ["Business Development in Science, Engineering", "Fresh grduated will also be considered", "5 days works, Proactive, Well-organized"], "locations": ["Shatin Area"], "categories": ["Sales, CS & Business Devpt", "Business Development", "Sciences, Lab, R&D", "Laboratory", "Account Servicing"], "post_time": "2022-01-18T03:42:08Z", "salary": {"currency": null, "max": null, "min": null, "period": "monthly", "term": null}, "salary_visible": false, "title_keywords": ["assistant business executive"], "responsibilities": ["maintenance", "data", "monitor", "testing", "hygiene", "prepare reports"], "requirements": {"degrees": ["higher diploma or above"], "majors": ["biology", "chemistry", "food science"], "languages": ["english", "chinese"], "language_level": ["good"], "hard_skills": [], "soft_skills": ["communication skills", "organizational skills", "confidence", "committed", "comprehensive"], "languages_combined": [{"language": "english", "language_level": ["good"]}, {"language": "chinese", "language_level": ["good"]}]}, "experience_required": {"duration": [], "field": []}}, {"job_id": "100003009054562", "location_code": "hk", "company": "\u5967\u6717\u751f\u7269\u91ab\u85e5\u6709\u9650\u516c\u53f8", "job_title": "Senior Research Scientist / Project Manager", "description": "Responsibilities:\n\nDeployed on undertaking laboratory work in connection with the diagnosis and control of disease;\nOperate molecular diagnostic equipment and instruments according to laboratory procedures;\nAssist in handling routine laboratory works in polymerase chain reaction laboratories;\nPerform equipment maintenance works;\nUndertake any other duties as assigned by the laboratory supervisor.\nRequirements:\n\n\nDiploma in Chemistry, Biology or equivalent;\nA good team worker with excellent communication skills;\nBeing proactive and able to work independently;\nImmediately available is highly preferred\n\nWe offer attractive remuneration package and excellent career opportunities to the right candidates. Interested parties please send your full resume with availability, current and expected salary to our HR Division.\n\nWelcome to visit our company website www.catagene.com.hk\u00a0or more information.\n\nWe are an Equal Opportunities Employer and welcome applications from all qualified candidates. All Personal data collected will be kept in strict confidence and used for recruitment purpose only.", "employment_types": ["Full Time", "Permanent"], "selling_points": [], "locations": ["Shatin Area"], "categories": ["Sciences, Lab, R&D", "Laboratory", "Life Science", "Research & Development (R&D)"], "post_time": "2022-01-17T09:59:43Z", "salary": {"currency": null, "max": null, "min": null, "period": "monthly", "term": null}, "salary_visible": false, "title_keywords": ["senior research scientist", "project manager"], "responsibilities": ["any other duties", "control", "procedures", "maintenance"], "requirements": {"degrees": ["diploma"], "majors": ["biology", "chemistry"], "languages": [], "language_level": [], "hard_skills": [], "soft_skills": ["communication skills", "work independently", "proactive"], "languages_combined": []}, "experience_required": {"duration": [], "field": []}}, {"job_id": "100003009053972", "location_code": "hk", "company": "Webster Personnel Agency Limited", "job_title": "Technical Support Engineer (Electronics Industry)", "description": "This is a full time position. The candidate will be required to perform all IVF techniques and procedures including:\n\nSperm preparation\nOocyte Pick up\nICSI/cIVF\nGamete/embryo cryopreservation\nEmbryo transfer\nEmbryo biopsy\nJob requirement:\n\nDegree or above in Science\u00a0\nParticipation on some weekends, public holidays and out of hours rota will be required\nSalary:\n\nCommensurate with experience\nDevelopment opportunities i.e.: overseas training will be provided", "employment_types": ["Full Time", "Contract"], "selling_points": [], "locations": ["Fanling"], "categories": ["Sciences, Lab, R&D", "Laboratory", "Research & Development (R&D)", "Others"], "post_time": "2022-01-17T07:52:48Z", "salary": {"currency": null, "max": null, "min": null, "period": "monthly", "term": null}, "salary_visible": false, "title_keywords": ["technical support engineer"], "responsibilities": ["procedures"], "requirements": {"degrees": ["degree or above"], "majors": ["science"], "languages": [], "language_level": [], "hard_skills": [], "soft_skills": [], "languages_combined": []}, "experience_required": {"duration": [], "field": []}}, {"job_id": "100003009049297", "location_code": "hk", "company": "HealthBaby Biotech (Hong Kong) Co Ltd", "job_title": "Laboratory Technician / Medical Laboratory Technician (MLT Part II)", "description": "Responsibilities:\n\nWork closely with the Quality Supervisor for internal and external audits, as well as process improvement activities\nSupport and assist in the maintenance of ISO certificates\nExercise document control for all management systems\nCoordinate with internal parties to maintain and update all necessary documentation to comply with system requirements\nAssist in establishing policies and procedures for the company\nConduct internal audit and assist internal parties to develop improvement plan\nHandle ad hoc assignments as required\n\n\u00a0Qualifications:\n\n1 years of work experience in quality management / audit field is a plus\u00a0\nPossess audit experience would be an advantage\nFamiliar with ISO9001 and 14001, with TAPA and ISO45001 knowledge will be an advantage\nGood communication, presentation, interpersonal, and organizational skills.\nCapacity to work both independently and in a team-oriented environment\nExceptional analytical, problem solving & root-cause analysis skills.\nAbility to learn quickly and attention to detail.\nProficient in MS Office\nGood command of spoken and written English and Chinese", "employment_types": ["Full Time", "Permanent"], "selling_points": ["Fast-growing biotech company/ Biomedical", "5-day work week(09:00-18:00), double pay and bonus", "Dental, medical and life insurance, birthday leave"], "locations": ["Shatin Area"], "categories": ["Sciences, Lab, R&D", "Laboratory", "Medical Services", "Others", "Others"], "post_time": "2022-01-14T08:24:50Z", "salary": {"currency": null, "max": null, "min": null, "period": "monthly", "term": null}, "salary_visible": false, "title_keywords": ["laboratory technician", "medical laboratory technician"], "responsibilities": ["internal audit", "quality", "audit", "communication", "maintain", "plan", "control", "develop", "management", "internal and external audits", "coordinate with", "procedures", "documentation", "maintenance", "policies", "analysis", "systems", "ad hoc assignments", "internal parties"], "requirements": {"degrees": [], "majors": [], "languages": ["english", "chinese"], "language_level": ["good command"], "hard_skills": ["plus", "maintenance", "analysis", "problem solving", "documentation", "ms office"], "soft_skills": ["organizational skills", "independently", "presentation", "communication", "problem solving", "attention to detail", "interpersonal"], "languages_combined": [{"language": "english", "language_level": ["good command"]}, {"language": "chinese", "language_level": ["good command"]}]}, "experience_required": {"duration": ["1 years"], "field": ["audit experience", "audit", "quality management"]}}, {"job_id": "100003009056222", "location_code": "hk", "company": "Maxim's Caterers Ltd", "job_title": "Senior / Quality Assurance Officer (Cakes & Bakery Factory)", "description": "Responsibilities:\n\n\nFollow up environmental projects related to indoor air quality testing, water quality testing, green building assessment (e.g. BEAM Plus, LEED and WELL), carbon audit, etc.\nMaintain business relationship with existing clients and also handle new inquiry to explore new business opportunities;\nGenerate leads by market research, exhibition, etc., identify and secure meetings with prospective clients.\nPrepare quotation and tender submission;\nSupport teammates for routine tasks and report to supervisor.\nAd hoc projects assigned.\n\nRequirements:\n\n\nDiploma or above in Science, Environmental Science, Environmental Engineering, Business or related disciplines;\nFresh graduate is welcome;\nGood interpersonal and communication skills;\nWell-organized, proactive and positive thinking;\nCandidates with more experience will be considered as Business Executive.\n\nWe offer a competitive remuneration package as well as other benefits encompassing:\n\n\n5-day Work\nDouble Pay\nAnnual Leave\nBirthday Leave\nMentoring\nCareer Advancement Opportunities\nDental and Medical Benefits\nEducation and Training Subsidies\nFree Shuttle Bus Service\nStaff Activities\n\nInterested parties please send your\u00a0full resume with\u00a0availability, current and expected salary\u00a0by clicking the \"Apply Now\" button .\u00a0Welcome to visit our company website\u00a0http://www.cmatesting.org/\u00a0for more information.\n\nWe are an Equal Opportunities Employer and welcome applications from all qualified candidates. All Personal data collected will be kept in strict confidence and used for recruitment purpose only.", "employment_types": ["Full Time", "Permanent"], "selling_points": ["Food Factory", "Perform routine on line and finished food products", "At least 2 year laboratory working experience"], "locations": ["Tai Po Area"], "categories": ["Sciences, Lab, R&D", "Laboratory", "Life Science", "Manufacturing", "Quality Assurance, Control & Testing / ISO"], "post_time": "2022-01-18T03:38:21Z", "salary": {"currency": null, "max": null, "min": null, "period": null, "term": null}, "salary_visible": false, "title_keywords": ["quality assurance officer"], "responsibilities": ["explore new business opportunities", "quotation", "quality", "audit", "market research", "testing", "maintain", "ad hoc projects", "tender", "report"], "requirements": {"degrees": ["fresh graduate", "diploma or above"], "majors": ["science", "related disciplines", "environmental science", "business", "environmental engineering"], "languages": [], "language_level": [], "hard_skills": [], "soft_skills": ["communication skills", "well-organized", "positive thinking", "proactive", "interpersonal"], "languages_combined": []}, "experience_required": {"duration": [], "field": ["business"]}}, {"job_id": "100003009052688", "location_code": "hk", "company": "Hong Kong Medical Laboratory Centre Limited", "job_title": "Medical Laboratory Technologist (Part I)", "description": "As a Senior Research Scientist / Project Manager, you will be responsible for research and development of innovative non-viral gene as well as biological drug delivery to address unmet medical needs. The ideal candidate will also have a strong passion and curiosity for cell and gene therapy with the desire to bring needed cures from bench to bedside. Demonstrated genuine interest and curiosity in research and development is highly valued.\n\n\nResponsibilities\n\nExpand our proprietary, patent-pending cell and gene delivery platform to develop new tools and/or applications for specialized and enhanced implementation in cell and gene therapy. In addition, utilizing our patented technology on expanding the non-invasive ophthalmic drug delivery platform with new biological candidates in treating eye diseases.\nApply your strong background in molecular biology, transposon, and gene delivery technology to develop new gene delivery systems for use in ex vivo and in vivo therapies.\nPrepare formulations and perform characterization assays /data analysis with focus on in vivo studies, drug carrier design/development, assay development and quality control.\nDevelop novel formulations and processes to further expand delivery capabilities\nSupport formulation development activities related to increasing stability and formulation optimization.\nWork in close interaction with internal and external industrial partners and academic institutes to ensure smooth flow of information and data.\nPrepare technical reports and presentations for clear communication of scientific findings across interdisciplinary teams.\nExecute the plans according to IND enabling timelines for both China and US regulatory submission.\n\n\u00a0Requirements\n\nPh.D. in chemistry, pharmaceutical science, molecular biology, virology or related discipline with 2-4 years of industry or post-doctoral experience.\nPrior experience with in vitro cell and gene delivery platforms and mammalian cell culture is required. Experience with non-viral gene delivery technology is strongly preferred.\nExperience with DNA/mRNA encapsulation, quantification, characterization, and handling is preferred.\nExperience with biological drug development.\nProficiency in analytical techniques like HPLC/UPLC, DLS, CD, zeta potential, UV-Vis, cryo-TEM, and fluorescence spectrophotometry etc. is preferred.\nProven track record in method development, including experimental design, execution and evaluation.\nExperience with GMP and ICH regulations is desired.\nAbility to work in a fast-paced environment, meet deadlines, and prioritize work on multiple projects.\nProven problem solving and troubleshooting abilities.\nAbility to direct and lead junior R&D staff as well as managing research grant.\nStrong communication skills in technical writing and oral presentation in English and Chinese.\nStrong sense of responsibility, accountability, and integrity.\u00a0\n\nWe offer competitive remuneration package and excellent career prospects to qualified candidates. Interested parties please send your CV together with present and expected salaries to the Human Resources Manager by clicking apply now.\n\nApplicants who are not contacted by email or call within 1 month may consider their application is unsuccessful and the personal data collected will be destroyed in due course.", "employment_types": ["Full Time", "Permanent"], "selling_points": [], "locations": ["Shatin Area"], "categories": ["Sciences, Lab, R&D", "Laboratory", "Life Science", "Medical Services", "Medical Services Technician"], "post_time": "2022-01-17T03:42:26Z", "salary": {"currency": "HKD", "max": 54999, "min": 35000, "period": "monthly", "term": null}, "salary_visible": true, "title_keywords": ["medical laboratory technologist"], "responsibilities": ["data", "systems", "teams", "implementation", "design", "develop", "data analysis", "presentations", "communication", "reports", "quality control", "plans"], "requirements": {"degrees": [], "majors": [], "languages": ["english", "chinese"], "language_level": [], "hard_skills": ["problem solving", "r&d"], "soft_skills": ["communication skills", "oral", "accountability", "sense of responsibility", "fast-paced environment", "integrity", "troubleshooting", "prioritize", "problem solving", "meet deadlines", "presentation"], "languages_combined": [{"language": "english", "language_level": []}, {"language": "chinese", "language_level": []}]}, "experience_required": {"duration": ["2-4 years"], "field": ["pharmaceutical", "development", "related"]}}, {"job_id": "100003009031965", "location_code": "hk", "company": "Bureau Veritas Hong Kong Limited", "job_title": "\u52a9\u7406 (\u6a23\u8fa6\u8655\u7406\u53ca\u5668\u5177\u6e05\u6f54)", "description": "Our client is an international supplier of materials and technology to the electronics industry. \u00a0To fuel with their growth, they are looking for a junior technical engineer to support the Sales and Research & Product Development team in helping on preliminary product analysis and diversified lab tests. \u00a0On-the-job training will be offered to potential candidate.\u00a0\n\nBenefits: 13th month salary, medical insurance, 5-day work week, bank holiday\n\nThe job:\nAssist the Sales and R&D team to evaluate product against market requirements\nUnderstand the market technical requirement and support R&D team for new product evaluation and beta testing\nGenerate lab test result and perform analysis on product performance\nHelp customer to trouble shoot products\u00a0\nAssist engineers to offer on-site technical support\nThe person:\nBachelor degree in Chemistry or related discipline\n\n1 year laboratory experience in operating analytical instruments is highly preferred\nInterest to trouble shoot and find product solution with laboratory work\nKeen to learn new technology, good team player, good interpersonal and communication skills\nComputer knowledge, oral and written communication skills in English & Chinese\nInterested parties please apply through email and provide latest resume and salary expectation.\u00a0All information provided will be used for recruitment purposes only", "employment_types": ["Full Time", "Permanent"], "selling_points": ["\u6e2c\u8a66\u884c\u696d\u7684\u5168\u7403\u9818\u5c0e\u8005", "\u4e94\u5929\u5de5\u4f5c\u3001\u9280\u884c\u5047\u671f\u3001\u8d85\u6642\u5de5\u4f5c\u6d25\u8cbc", "\u53ef\u5373\u6642\u5230\u8077\u512a\u5148"], "locations": ["Kowloon Bay"], "categories": ["Sciences, Lab, R&D", "Laboratory", "Others", "Others", "Others"], "post_time": "2022-01-13T08:31:15Z", "salary": {"currency": null, "max": null, "min": null, "period": "monthly", "term": null}, "salary_visible": false, "title_keywords": ["\u52a9\u7406"], "responsibilities": [], "requirements": {"degrees": [], "majors": [], "languages": [], "language_level": [], "hard_skills": [], "soft_skills": [], "languages_combined": []}, "experience_required": {"duration": [], "field": []}}, {"job_id": "100003009054292", "location_code": "hk", "company": "CHOW TAI FOOK JEWELLERY CO LTD", "job_title": "\u54c1\u8cea\u6aa2\u5b9a\u54e1", "description": "Job Responsibilities:\n\nDirectly responsible for the processing and storage preparation of cord blood and umbilical cord units according to laboratory Standard Operation Procedures\nPlan, set up and undertake controlled experiments and trials\nMonitor the laboratory consumables in stock are well organized\u00a0\nHandle and accurate recording laboratory data, present results to Lab Manager/ Lab Director\nDemonstrate of procedures and scientific analysis\nReceive and accept of incoming materials\nPerform maintenance and calibration of laboratory equipment\nWrite reports, reviews and summaries\nParticipate in-house and external training as required\nMaintain safe and clean working environment in the lab\n5-day week (09:00 - 18:00), roster duty on Saturday, Sunday and Public Holiday required\n\nJob Requirements:\n\nBachelor Degree or Higher Diploma in Medical Laboratory Sciences, Biological Science, Biotechnology or Life Science related disciplines.\u00a0Fresh graduates are also welcome.\nExperience in processing of cord blood or performing laboratory testing would be an advantage, but not a must\u00a0\nExperience in phlebotomy would be an advantage\nHigh sense of responsibility and teamwork\nAble to work independently and without supervision\nGood command of written and spoken English, Cantonese and Mandarin\nMust be Hepatitis B immunized\nCandidate with Registered Part II MLT will be considered as Medical Laboratory Technician\n\nWe offer:\u00a0\n\nAttractive remuneration package and staff benefits\nShuttle bus provided by Hong Kong Science Park\nComprehensive on-the-job and continuous trainings\nOpportunities for professional and personal development\nFriendly working environment\nIf you are interested in this position, please send your resume with details of qualification, experience, present and expected salary, address and contact number to HR by clicking \u201cAPPLY NOW\u201d.\n\n\nAll personal data collected would be used for recruitment purpose.", "employment_types": ["Full Time"], "selling_points": ["\u4e94\u5929\u5de5\u4f5c", "\u947d\u77f3\u6aa2\u6e2c", "\u8cc7\u6599\u8f38\u5165"], "locations": ["Kwai Hing"], "categories": ["Manufacturing", "Jewelry", "Sciences, Lab, R&D", "Laboratory"], "post_time": "2022-01-17T09:04:45Z", "salary": {"currency": null, "max": null, "min": null, "period": "monthly", "term": null}, "salary_visible": false, "title_keywords": [], "responsibilities": ["maintenance", "data", "analysis", "monitor", "procedures", "maintain", "reports", "plan"], "requirements": {"degrees": ["diploma", "degree", "bachelor"], "majors": ["related disciplines", "science", "biological science"], "languages": ["cantonese", "english", "mandarin"], "language_level": ["good command"], "hard_skills": ["processing"], "soft_skills": ["work independently", "high sense of responsibility and teamwork"], "languages_combined": [{"language": "cantonese", "language_level": ["good command"]}, {"language": "english", "language_level": ["good command"]}, {"language": "mandarin", "language_level": ["good command"]}]}, "experience_required": {"duration": [], "field": ["laboratory testing"]}}, {"job_id": "100003009049955", "location_code": "hk", "company": "Qima Limited", "job_title": "Laboratory Testing Specialist (Phy)", "description": "Responsibilities:\nPerform routine on line and finished food products inspection at various stages on the production line to implement ISO/HACCP policy.\nAssist in implementing and maintain the documentation system and quality management system.\nSupport the implementation of food safety, hygiene and quality assurance operation policies, guidelines and procedures to ensure the entire production process is in compliance with the corporate standard.\nCoordinate and participate work safety, quality assurance and hygiene procedures training to related staff.\nAssist in other ad-hoc projects as assigned.\nRequirements:\nDegree holder or above in biochemistry, Food Science or related disciplines;\nAt least 2 year laboratory working experience;\nSelf-motivated, independent and with good communication skill;\nWell-organized with good analytical skill;\nProficient in PC applications including Chinese word processing;\nGood command of spoken and written English and Chinese / Cantonese\nStaff Benefits\nMedical Insurance Coverage\nBirthday& Wedding Leave\nFree Meal & Shuttle Bus\nStaff Purchase Benefits\nAll applications and data collected will be treated in strict confidence and used exclusively for recruitment purposes.\u00a0 Only short listed candidates will be invited for interview.\u00a0 The company will retain the applications for a maximum period of 6 months and may refer suitable candidates to other vacancies within the Group.", "employment_types": ["Full Time", "Permanent"], "selling_points": ["Performance bonus and Medical benefits", "Fresh Graduates are welcome", "Good career development"], "locations": ["Kwun Tong"], "categories": ["Sciences, Lab, R&D", "Laboratory"], "post_time": "2022-01-14T09:30:05Z", "salary": {"currency": null, "max": null, "min": null, "period": "monthly", "term": null}, "salary_visible": false, "title_keywords": ["specialist"], "responsibilities": ["management", "production process", "food safety", "guidelines", "policies", "compliance", "quality", "implementation", "procedures", "inspection", "coordinate", "hygiene", "maintain", "documentation", "ad-hoc projects"], "requirements": {"degrees": ["degree holder"], "majors": ["related disciplines", "food science"], "languages": ["cantonese", "english", "chinese"], "language_level": ["good command", "proficient"], "hard_skills": ["analytical skill", "chinese word processing", "pc applications"], "soft_skills": ["self-motivated", "analytical skill", "independent", "communication skill", "well-organized"], "languages_combined": [{"language": "cantonese", "language_level": ["good command"]}, {"language": "english", "language_level": ["good command"]}, {"language": "chinese", "language_level": ["good command", "proficient"]}]}, "experience_required": {"duration": ["at least 2 year"], "field": ["laboratory"]}}, {"job_id": "100003009052079", "location_code": "hk", "company": "Hong Kong Standards & Testing Centre", "job_title": "Business Development Manager / Sales Manager in Commercial Laboratory \uff08Haiphong,Vietnam\uff09", "description": "Duties\n\nMonitor and manage the process of testing procedures, including reception, handling, processing, storage and testing of human blood according to the Standard Operation Procedure (SOP)\nEstablish new and review current SOP\nReview and approve quality control data for testing\nReview and approve laboratory report\nParticipate in-house and external training as required\nOther ad-hoc duties are also required\n\nRequirements\n\nValid Medical Laboratory Technologist Part I practicing cert issued by the HKMLT Board\nBachelor Degree or Higher Technical Certificate (HTC) in Biomedical Science, Medical Laboratory Sciences other related disciplines\nExperience in genetic/DNA analysis, including DNA extraction, sequencing, PCR etc. is preferable.\nStrong sense of responsibility\nMust be a good team worker with excellent communication skills as well as be able to work independently\nAble to communicate in Mandarin and Cantonese", "employment_types": ["Full Time", "Permanent"], "selling_points": ["product testing, inspection & certification", "5 years work experience in Sales & Marketing", "Haiphong, Vietnam; Working experience in Vietnam"], "locations": ["Overseas"], "categories": ["Sales, CS & Business Devpt", "Customer Service - Manager", "Sciences, Lab, R&D", "Laboratory", "Others"], "post_time": "2022-01-17T02:02:43Z", "salary": {"currency": null, "max": null, "min": null, "period": "monthly", "term": null}, "salary_visible": false, "title_keywords": ["business development manager", "sales manager"], "responsibilities": ["data", "review", "monitor", "procedures", "testing", "quality control", "ad-hoc duties", "report"], "requirements": {"degrees": ["certificate", "degree", "bachelor"], "majors": ["biomedical science", "related disciplines"], "languages": ["cantonese", "mandarin"], "language_level": [], "hard_skills": ["analysis"], "soft_skills": ["communication skills", "work independently", "sense of responsibility"], "languages_combined": [{"language": "cantonese", "language_level": []}, {"language": "mandarin", "language_level": []}]}, "experience_required": {"duration": [], "field": []}}, {"job_id": "100003009050629", "location_code": "hk", "company": "The Independent Schools Foundation Academy Ltd", "job_title": "Laboratory Technician III (Ref: SEC/LT/20211124_ jdb)", "description": "\u8077\u8cac\n\n\n\u5354\u52a9\u8655\u7406\u3001\u5207\u5272\u3001\u88c1\u526a\u53ca\u6e96\u5099\u6e2c\u8a66\u6a23\u677f\n\u8ca0\u8cac\u6e05\u6d17\u53ca\u6d88\u6bd2\u5be6\u9a57\u5668\u5177\n\u7c21\u55ae\u6587\u66f8\u5de5\u4f5c\n\u8655\u7406\u4e0a\u53f8\u6307\u6d3e\u7684\u5176\u4ed6\u76f8\u95dc\u8077\u52d9\n\n\u5de5\u4f5c\u8981\u6c42\n\n\n\u4e2d\u5b78\u7562\u696d\u6216\u4ee5\u4e0a\n\u826f\u597d\u7cb5\u8a9e; \u4e00\u822c\u82f1\u8a9e\n\u61c2\u8b80\u5beb\u4e2d\u6587; \u7565\u61c2\u8b80\u5beb\u82f1\u6587\n\u53ef\u5373\u6642\u5230\u8077\u512a\u5148\n\u6216\u9808\u8d85\u6642\u5de5\u4f5c (\u6709\u8d85\u6642\u5de5\u4f5c\u6d25\u8cbc)\n\u5de5\u4f5c\u6642\u9593\ufe30\u661f\u671f\u4e00\u81f3\u4e94 (09:00 - 18:00)\n\n\n\u4e94\u5929\u5de5\u4f5c\u3001\u9280\u884c\u5047\u671f\u3001\u8d85\u6642\u5de5\u4f5c\u6d25\u8cbc\u3001\u4eba\u58fd\u4fdd\u96aa\u3001\u5728\u8077\u57f9\u8a13\n\n\u6c42\u8077\u8005\u8acb\u5c07\u500b\u4eba\u5c65\u6b77\u9023\u540c\u8981\u6c42\u85aa\u91d1\u90f5\u5bc4\u81f3\u201c\u4e5d\u9f8d\u7063\u81e8\u6fa4\u88578\u865f\u555f\u532f7\u6a13(\u4eba\u529b\u8cc7\u6e90\u90e8) \u7acb\u5fb7\u570b\u969b\u516c\u8b49\u9999\u6e2f\u6709\u9650\u516c\u53f8\" \u6216 \u9ede\u64caApply Now\u6309\u9215\u7533\u8acb\u3002\n\n\u7533\u8acb\u8005\u6240\u63d0\u4f9b\u5168\u90e8\u7684\u8cc7\u6599\u7d55\u5c0d\u4fdd\u5bc6\u53ca\u53ea\u4f5c\u62db\u8058\u7528\u9014\u3002\n\n\u5982\u6b32\u67e5\u8a62\u66f4\u591a\u516c\u53f8\u8cc7\u6599\uff0c\u8acb\u700f\u89bd:\u00a0https://group.bureauveritas.com/\n", "employment_types": ["Full Time", "Permanent"], "selling_points": ["Ensure the availability of suitable materials", "With 1 to 2 years of relevant experience", "Diploma in Science related discipline"], "locations": ["Pok Fu Lam"], "categories": ["Sciences, Lab, R&D", "Laboratory", "Others"], "post_time": "2022-01-14T11:00:50Z", "salary": {"currency": null, "max": null, "min": null, "period": "monthly", "term": null}, "salary_visible": false, "title_keywords": ["laboratory technician"], "responsibilities": [], "requirements": {"degrees": [], "majors": [], "languages": [], "language_level": [], "hard_skills": [], "soft_skills": [], "languages_combined": []}, "experience_required": {"duration": [], "field": []}}, {"job_id": "100003009056250", "location_code": "hk", "company": "CMA Testing and Certification Laboratories Limited", "job_title": "Business Development Executive - Food and Pharmaceutical", "description": "\u8077\u8cac\uff1a\n\n\u8655\u7406\u947d\u77f3\u539f\u6599\u7684\u6aa2\u6e2c\u7a0b\u5e8f\n\u64cd\u4f5c\u6aa2\u6e2c\u5100\u5668\u53ca\u9032\u884c\u65e5\u5e38\u7dad\u8b77\n\u5354\u52a9\u6578\u64da\u5206\u6790\u53ca\u8cc7\u6599\u8f38\u5165\n\u4fdd\u6301\u5be6\u9a57\u5ba4\u6574\u6f54\n\u5176\u4ed6\u5de5\u4f5c\u652f\u63f4\n\n\u8077\u4f4d\u8981\u6c42\uff1a\n\n\u4e2d\u5b78\u7a0b\u5ea6\n2 - 4\u5e74\u6587\u66f8\u8655\u7406\u7d93\u9a57\u53ca\u5177\u76f8\u95dc\u73e0\u5bf6\u8655\u7406\u7d93\u9a57\u8f03\u4f73\n\u61c2\u4e00\u822c\u96fb\u8166\u64cd\u4f5c\uff08 Word \u3001 Excel \uff09\uff1b\u61c2\u5009\u9821\uff0f\u901f\u6210\u8f38\u5165\u6cd5\n\u66fe\u4fee\u8b80\u73e0\u5bf6\u9996\u98fe\u9451\u8b49\u76f8\u95dc\u8ab2\u7a0b\u66f4\u4f73\n\u8aa0\u5be6\u3001\u7d30\u5fc3\u3001\u6e96\u78ba\u3001\u6709\u8cac\u4efb\u611f\n\n\u53ef\u4eab\u798f\u5229\ufe30\u00a0\n\n\u4e94\u5929\u5de5\u4f5c\n\u512a\u85aa\u3001\u54e1\u5de5\u81b3\u98df\uff0c\u91ab\u7642\u53ca\u7259\u79d1\u798f\u5229\uff0c\u4eba\u58fd\u4fdd\u96aa\n\u4eab\u5404\u985e\u5047\u671f\uff0c\u5305\u62ec\u5e78\u798f\u5bb6\u5ead\u5047\u3001\u81ea\u6211\u767c\u5c55\u5047\u3001\u8003\u8a66\u5047\u3001\u751f\u65e5\u5047\u3001\u7d50\u5a5a\u5047\u3001\u7fa9\u5de5\u5047\u7b49\u2026\u2026", "employment_types": ["Full Time", "Permanent"], "selling_points": ["Business Development in Science, Chemistry, BBA", "A sales driven position, explore new business", "5 days works, Proactive, Well-organized"], "locations": ["Shatin Area"], "categories": ["Sales, CS & Business Devpt", "Business Development", "Sciences, Lab, R&D", "Laboratory", "Account Servicing"], "post_time": "2022-01-18T03:42:09Z", "salary": {"currency": null, "max": null, "min": null, "period": "monthly", "term": null}, "salary_visible": false, "title_keywords": ["business development executive"], "responsibilities": [], "requirements": {"degrees": [], "majors": [], "languages": [], "language_level": [], "hard_skills": ["excel", "word"], "soft_skills": [], "languages_combined": []}, "experience_required": {"duration": [], "field": []}}, {"job_id": "100003009050399", "location_code": "hk", "company": "Qima Limited", "job_title": "Laboratory Calibration Engineer (Fresh Grad is welcome)", "description": "Objective\n\n\nAssist the leader and manager to run the daily operation smoothly and in a good discipline according to a number of international standards.\n\nJob Responsibilities\n\n\nImplement the management system and ISO 17025;\nWork with Sample Control Team for receiving and returning of tested items;\nHandle preparation work before testing;\nConduct simple testing after internal training and the supervision of engineer or above;\nProcess data to engineer, or above as needed;\nCarry out maintenance and calibration plan of the laboratory;\nUndertake any other duties as assigned.\nRequirements\n\nSecondary school graduated, Science stream preferred.\nGood communication skills.\nNo working experience is required. Internal training will be provided.\nFluent in written and spoken English and Chinese.\nMature and be able to work independently.\nFor interested parties, please click Apply now.", "employment_types": ["Full Time", "Permanent"], "selling_points": ["5-day work", "Year end bonus and performance bonus", "Young and good work environment"], "locations": ["Kwun Tong"], "categories": ["Engineering", "Mechanical", "Sciences, Lab, R&D", "Laboratory", "Manufacturing", "Quality Assurance, Control & Testing / ISO"], "post_time": "2022-01-14T10:18:05Z", "salary": {"currency": null, "max": null, "min": null, "period": "monthly", "term": null}, "salary_visible": false, "title_keywords": ["engineer"], "responsibilities": ["any other duties", "management", "control", "maintenance", "data", "testing", "plan"], "requirements": {"degrees": [], "majors": [], "languages": ["english", "chinese"], "language_level": ["fluent"], "hard_skills": ["no"], "soft_skills": ["communication skills", "work independently", "mature"], "languages_combined": [{"language": "english", "language_level": ["fluent"]}, {"language": "chinese", "language_level": ["fluent"]}]}, "experience_required": {"duration": [], "field": []}}, {"job_id": "100003009050601", "location_code": "hk", "company": "PIT Limited", "job_title": "Assistant Technical Officer / Technical Officer (Indoor Air Quality / Environment)", "description": "An international consumer products testing, inspection and certification company, STC (www.stc.group), with headquarters in Hong Kong, is looking for high caliber candidates to fill the position of Business Development Manager / Sales Manager. The successful candidate is expected to be stationed in Haiphong, Vietnam.\n\nResponsibilities\n\n\nTo generate and bring in new customers to the company\nTo acquire and develop all necessary professional selling skills, to effectively and efficiently promote the laboratory services\nTo follow up with customers\u2019 in-jobs and after sales services. To develop relationships with customers that further the goodwill of the company\nTo collect market information and explore market trend for business development\nTo have unique channel(s) to work with different manufacturers and factories to become our customers\nTo manage the work sub-contracted to other STC laboratories or to other subcontractor laboratories outside the company\nTo plan the business growth and meet the monthly sales revenue targets\n\nRequirements\n\nAuthorized to work in Vietnam\u00a0\nUniversity / College graduates in relevant discipline. Must have an outgoing character and can work independently with minimum supervision\nPrevious working experience in Vietnam is a must\nKnowledge in international consumer products testing regulatory standards and compliance, especially for toys and textiles\nHands-on customers base for fast business development\nPrevious experience in laboratory sales and marketing is preferred\nProficiency in English and Vietnamese is preferred\n\nInterested parties please send your resume\u00a0with availability, present\u00a0salary\u00a0and expected salary to our Human Resources Department by Clicking\u00a0\"Apply Now\" .\n\n\nWelcome to visit our company website\u00a0www.stc.group\u00a0for corporate information.\n\n(All personal data collected are for recruitment purposes only.)", "employment_types": ["Full Time"], "selling_points": [], "locations": ["Tsuen Wan Area"], "categories": ["Sciences, Lab, R&D", "Environmental Science / Waste Management", "Laboratory", "Life Science"], "post_time": "2022-01-15T03:51:13Z", "salary": {"currency": null, "max": null, "min": null, "period": "monthly", "term": null}, "salary_visible": false, "title_keywords": ["technical officer", "assistant technical officer"], "responsibilities": ["market information", "plan", "develop"], "requirements": {"degrees": [], "majors": [], "languages": ["vietnamese", "english"], "language_level": ["proficiency"], "hard_skills": [], "soft_skills": ["outgoing", "work independently", "hands-on"], "languages_combined": [{"language": "vietnamese", "language_level": ["proficiency"]}, {"language": "english", "language_level": ["proficiency"]}]}, "experience_required": {"duration": [], "field": ["laboratory", "marketing"]}}, {"job_id": "100003009042926", "location_code": "hk", "company": "City University of Hong Kong", "job_title": "Senior Safety Officer (Laboratory) in the Office of Vice-President (Research & Technology)", "description": "We are looking for 2 dynamic individuals to join a growing team of technicians as The ISF Academy continues to provide the best science Education in Hong Kong.\nJob Responsibilities:\nAssist the team-leader / Senior Laboratory Technician in coordinating the use of practical resources and facilities;\nProvide assistance and advice in meeting the practical needs of the science curriculum, including liaising with teaching staff and support staff outside the Science Faculty;\nEnsure the availability of suitable materials and equipment by compiling orders and liaising or negotiating with suppliersand finance office;\nKeep up-to-date stock records;\nMaintain the required standard of bothroutine and non-routine checking, cleaning, maintenance, calibration, testing andrepairing of equipment; and\nCollect, check and return equipment to stores.\nRequirements:\nDiploma in Science related discipline;\nWith 1 to 2 years of relevant experience;\nGood command of both written and spoken English and Chinese (including Mandarin);\nProficient in PC skills (e.g. MS Office Suite, Chinese Character Input); and\nAble to work independently and also a team player.\nThe ISF Foundation, Academy & Pre-School are committed to ensuring safety and well-being of our students. We hold high standards of recruitment practices with specific attention to child protection. All applicants must be willing to undergo relevant background checks and screenings.\nFree Shuttle Bus travelling to and from The ISF Academy will be provided:\nRoute: North Point > Admiralty Centre > Causeway Bay > Aberdeen > The ISF Academy\nApplication Deadline:\u00a0 28 January 2022\n\nRemuneration will commensurate with qualifications and experience. We will offer an attractive benefits package including medical, life insurance, and opportunities for professional development and continuing education to the right candidate. Please submit your application by completing the Application Form, Reference Check Statement which could be downloaded from our website: www.isf.edu.hk together with full Curriculum Vitae and Covering Letter.Please quote with our \u201cRef: no.\u201d by email via \"Apply Now\"\nPersonal data is collected for employment purposes only.", "employment_types": ["Full Time", "Contract"], "selling_points": ["A Bachelor\u2019s degree", "Perform regular inspections and compliance checks", "Gratuity, leave, medical and dental schemes"], "locations": ["Not Specified"], "categories": ["Sciences, Lab, R&D", "Laboratory", "Research & Development (R&D)", "Others"], "post_time": "2022-01-13T18:54:37Z", "salary": {"currency": null, "max": null, "min": null, "period": "monthly", "term": null}, "salary_visible": false, "title_keywords": ["vice president", "safety officer"], "responsibilities": ["maintenance", "provide assistance", "liaising with", "testing", "maintain", "cleaning", "routine checking"], "requirements": {"degrees": ["diploma"], "majors": ["science"], "languages": ["english", "chinese", "mandarin"], "language_level": ["good command"], "hard_skills": ["no", "pc skills", "ms office"], "soft_skills": ["committed", "work independently", "team player"], "languages_combined": [{"language": "english", "language_level": ["good command"]}, {"language": "chinese", "language_level": ["good command"]}, {"language": "mandarin", "language_level": ["good command"]}]}, "experience_required": {"duration": ["1 to 2 years"], "field": ["relevant experience"]}}, {"job_id": "100003009050389", "location_code": "hk", "company": "SGS Hong Kong Limited", "job_title": "Quality Officer / Assistant", "description": "Responsibilities:\n\n\nExplore new business opportunities through cold call, participation in fairs and website checking and maintain a solid client rapport;\nBe well-versed in preparing PowerPoint presentation;\nParticipate in client meeting and client visit;\nProvide contribution to sustain current clients;\nAd hoc project assigned.\n\nRequirements:\n\n\nHigher Diploma or above in BBA, Science\u00a0and\u00a0Pharmaceutical or related disciplines;\nGood interpersonal and communication skills to establish good relationship with clients;\nWell-organized, proactive, aggressive;\nInitiative, self-motivated and strong business sense;\nExcellent spoken and written English & Mandarin;\nFresh graduate will also be considered;\n\nWe offer attractive remuneration package and excellent career opportunities to the right candidates. Interested parties please send your full resume with availability, current and expected salary\u00a0to our HR Department.\n\nWelcome to visit our company website http://www.cmatesting.org/ for more information.\n\nWe are an Equal Opportunities Employer and welcome applications from all qualified candidates. All Personal data collected will be kept in strict confidence and used for recruitment purpose only.", "employment_types": ["Full Time", "Permanent"], "selling_points": ["Experience in constructional field", "ISO 17025, ISO 14001, ISO45001", "Management system, promotion & training"], "locations": ["Yuen Long"], "categories": ["Building & Construction", "Civil / Structural", "Engineering", "Others", "Sciences, Lab, R&D", "Laboratory"], "post_time": "2022-01-15T03:51:05Z", "salary": {"currency": null, "max": null, "min": null, "period": "monthly", "term": null}, "salary_visible": false, "title_keywords": ["quality officer", "assistant"], "responsibilities": ["ad hoc", "explore new business opportunities", "checking", "website", "maintain"], "requirements": {"degrees": ["higher diploma or above", "fresh graduate"], "majors": ["related disciplines", "bba", "science"], "languages": ["english", "mandarin"], "language_level": ["excellent"], "hard_skills": [], "soft_skills": ["communication skills", "self-motivated", "interpersonal", "business sense", "well-organized", "proactive", "initiative"], "languages_combined": [{"language": "english", "language_level": ["excellent"]}, {"language": "mandarin", "language_level": ["excellent"]}]}, "experience_required": {"duration": [], "field": []}}, {"job_id": "100003009049884", "location_code": "hk", "company": "CK Life Sciences Limited", "job_title": "Manager / Assistant Manager, Laboratory Administration & Compliance", "description": "Objective\n\nEnsure the equipment achieves the accuracy required at all time, support and perform calibration / verification for a wide range of Chemical, Physical and Optical laboratory equipment, as well as equipment purchasing, intermediate check, repair, and maintenance.\n\nYour Responsibilities\n\nSchedule and perform equipment calibration, verification, intermediate check, repair and maintenance, by following the calibration standards and requirement;\nPrepare and review calibration procedures, measurement uncertainty and internal calibration reports to fulfill ISO/IEC 17025 requirements;\nCo-ordinate with internal laboratory and calibration laboratory for internal/external calibration;\nManage the status and stock of laboratory\u2019s equipment. Co-ordinate with supplier for sourcing and purchasing new equipment;\nMaintain equipment record;\nSimple office facilities maintenance;\nHandle other equipment related tasks for quality assurance issues, such as internal/external auditing, document control, quality improvement projects, etc.\nMaintain document control system;\nHandle internal audit administration supporting tasks\n\nThe Skills We\u2019re Looking For\n\nHigher diploma / associate degree / degree holder of physics, mathematics or relevant engineering discipline;\nBasic understanding of ISO/IEC 17025 quality system document;\nGood communication skills and interpersonal skills;\nGood trouble shooting skills;\nExperiences of working in testing laboratory or toy industry is preferred;\nGood command of written and spoken English and Chinese;\nSelf-motivated and detail-minded;\nAnalytical mind and logical thinking;\nStrong technical knowledge;\nFresh graduate is also welcome.\nOther Benefits:\n\n5-day work, public holidays\nPerformance bonus and year-end bonus\nMedical and dental insurance\nOT allowance\nAnnual Leave, Compensation Leave, Compassionate Leave", "employment_types": ["Full Time", "Permanent"], "selling_points": ["A degree or above in Science or Engineering", "5 years\u2019 relevant experience", "Laboratory management & operation"], "locations": ["Tai Po Area"], "categories": ["Sciences, Lab, R&D", "Laboratory", "Research & Development (R&D)", "Others"], "post_time": "2022-01-14T09:23:25Z", "salary": {"currency": null, "max": null, "min": null, "period": "monthly", "term": null}, "salary_visible": false, "title_keywords": ["manager", "assistant manager,"], "responsibilities": ["control", "maintenance", "internal audit", "co-ordinate with", "review", "procedures", "measurement", "quality", "testing", "communication", "repair", "maintain", "reports", "schedule", "auditing", "administration"], "requirements": {"degrees": ["associate degree", "diploma", "fresh graduate", "degree holder"], "majors": ["mathematics", "engineering", "physics"], "languages": ["english", "chinese"], "language_level": ["good command"], "hard_skills": ["simple", "basic", "maintenance"], "soft_skills": ["detail-minded", "communication skills", "self-motivated", "analytical mind", "interpersonal skills"], "languages_combined": [{"language": "english", "language_level": ["good command"]}, {"language": "chinese", "language_level": ["good command"]}]}, "experience_required": {"duration": [], "field": ["laboratory", "testing"]}}, {"job_id": "100003009044884", "location_code": "hk", "company": "QAT Services Limited", "job_title": "(Assistant) Chemists", "description": "Job Description\n\nPerform on-site Indoor Air Quality inspection;\n\nConduct sampling and handle related tasks;\n\nTraining will be provided;\n\nPerform any other ad hoc tasks assigned.\n\nRequirements\n\nHigher Diploma or above in any discipline;\n\nResponsible, hardworking with positive working attitude;\n\n1 year or more Indoor Air Quality experiences are advantages;\n\nFresh graduates with proactive attitude are also welcomed;\n\nImmediately available is highly preferred;\n\nTravel to China and Overseas is required;", "employment_types": ["Full Time"], "selling_points": ["Minimum 1 year experience in chemical testing", "Fresh graduates will also be considered", "5-day work week; double pay; dental and medical"], "locations": ["Kwai Hing"], "categories": ["Sciences, Lab, R&D", "Laboratory"], "post_time": "2022-01-13T06:33:54Z", "salary": {"currency": null, "max": null, "min": null, "period": null, "term": null}, "salary_visible": false, "title_keywords": ["assistant"], "responsibilities": ["ad hoc tasks", "quality", "inspection"], "requirements": {"degrees": ["higher diploma or above"], "majors": [], "languages": [], "language_level": [], "hard_skills": [], "soft_skills": ["positive working attitude", "hardworking", "proactive", "responsible"], "languages_combined": []}, "experience_required": {"duration": ["1 year"], "field": []}}, {"job_id": "100003009043090", "location_code": "hk", "company": "Advance Pharmaceutical Company Limited", "job_title": "Quality Control Technician", "description": "Senior Safety Officer (Laboratory) in the Office of Vice-President (Research & Technology)\u00a0[Ref. B/519/03]Duties\n\nLaboratory Safety Unit (LSU) is a central university unit under the OVPRT to oversee safety and regulatory compliance issues related to teaching and research activities in laboratories.\u00a0 The appointee will assist the Senior Laboratory Safety Manager in discharging the job duties in relation to projects, programmes and services under LSU.\u00a0 Main duties include to:\n\nAssist in managing the operation of online systems and updating the inventory databases of laboratory assets;\nPerform regular inspections and compliance checks in the laboratories to ensure that activities are in compliance with legislations, policies and procedures (both internal and external);\nAssist in the implementation of the laboratory safety management programmes to mitigate the risk, such as conduct on-site monitoring and hazard assessments, provide safety advice, make recommendations on appropriate control measures and carry out accident/incident investigations;\nProvide administrative, clerical and daily operation supports in the unit;\nConduct laboratory design review and pre-occupation safety check;\nPrepare timely reports and follow up remedial actions when necessary;\nLiaise with internal and external stakeholders on laboratory safety-related issues;\nProvide technical supports to LSU laboratory service technical team; and\nPerform any other duties as assigned.\nRequirements\n\nA Bachelor\u2019s degree in Biology/Biochemistry/Chemistry/Occupational Hygiene or related disciplines with a minimum of 5 years\u2019 relevant working experience or a Master\u2019s degree in related disciplines with a minimum of 3 years\u2019 relevant working experience.\n\nApplicants should have a good command of both written and spoken English and Chinese (including Putonghua); good communication and interpersonal skills; strong quantitative, computer (e.g. Word, Excel, PowerPoint), and analytical skills.\n\nPreference will be given to candidates with relevant training certificate of laboratory safety associated courses (e.g. certificate in radiation protection, laser safety, safe use of x-ray, etc.) and experience in a safety unit of tertiary institution with laboratory facilities.\n\nShortlisted candidates may be invited for a written test.\n\nSuccessful candidate will be required to attend training related to laboratory safety and risk management, where appropriate.\n\nSalary and Conditions of Service\n\nRemuneration package will be highly competitive, commensurate with qualifications and experience.\u00a0 Appointment will be made on a fixed-term contract; fringe benefits include gratuity, leave, medical and dental schemes.\n\nInformation and Application\n\nFurther information on the post and the University is available at\u00a0http://www.cityu.edu.hk, or from the Human Resources Office, City University of Hong Kong, Tat Chee Avenue, Kowloon Tong, Hong Kong [Fax : 2788 1154 or 3442 0311].\u00a0\n\nTo apply, please submit an online application at\u00a0http://jobs.cityu.edu.hk. The closing date is\u00a028 January 2022.\u00a0 Applications will receive full consideration and only shortlisted applicants will be contacted.\u00a0 The University\u2019s privacy policy is available on the homepage.\n\nCity University of Hong Kong is an equal opportunity employer. We are committed to the principle of diversity. Personal data provided by applicants will be used for recruitment and other employment-related purposes.\n\nWorldwide recognition ranking #53 (QS survey 2022), and #4 among top 50 universities under age 50 (QS survey 2021); #1 in the World\u2019s Most International Universities (THE survey 2020); #1 in Engineering/Technology/Computer Sciences in Hong Kong (ARWU survey 2016); and #1 Business School in Asia-Pacific region (UT Dallas survey 2019).", "employment_types": ["Full Time"], "selling_points": [], "locations": ["Tai Po Area"], "categories": ["Sciences, Lab, R&D", "Laboratory", "Medical Services", "Pharmaceutical", "Others", "Technician"], "post_time": "2022-01-12T09:47:46Z", "salary": {"currency": null, "max": null, "min": null, "period": "monthly", "term": null}, "salary_visible": false, "title_keywords": ["quality control technician"], "responsibilities": ["any other duties", "technical supports", "inventory", "design", "timely reports", "liaise with", "make recommendations", "control", "compliance", "implementation", "legislations", "management", "monitoring", "procedures", "review", "policies", "systems", "daily operation", "databases"], "requirements": {"degrees": ["certificate", "degree", "bachelor", "master"], "majors": ["related disciplines", "biology", "chemistry"], "languages": ["putonghua", "english", "chinese"], "language_level": ["good command"], "hard_skills": ["excel", "word", "powerpoint", "analytical skills", "safe"], "soft_skills": ["communication and interpersonal skills", "analytical skills"], "languages_combined": [{"language": "putonghua", "language_level": ["good command"]}, {"language": "english", "language_level": ["good command"]}, {"language": "chinese", "language_level": ["good command"]}]}, "experience_required": {"duration": ["minimum of 3 years", "minimum of 5 years"], "field": ["related", "laboratory", "relevant working experience"]}}, {"job_id": "100003009048561", "location_code": "hk", "company": "Bureau Veritas Hong Kong Limited", "job_title": "Chemist / Assistant Chemist", "description": "\u00a0Key Responsibilities:\n\nBe responsible on all matters related to management systems\nCarry out QHSE training for relevant parties\nOrganize internal audit and ensure the internal audit being carried out regularly\nHandle document control, maintain audit records, and verify practices and training\nArrange and monitor the follow-up actions and ensure that corrective actions are taken properly\nControl and monitor the progress of the entire management system\nHandle and maintain records of technical and non-technical feedback or complaints\n\n\u00a0Requirements/Qualification:\u00a0\n\nDegree or higher in the related Science is preferred\n1-2 years of experience in Quality/ Health & Safety/ Environmental Management system (Experience in constructional field is a plus)\nFamiliar with ISO17025\u00a0(mainly construction laboratory), ISO14001 and ISO 45001 requirements\nStrong communication skills in both oral and written Chinese and English\nEffective time management skills to meet assigned deadlines and prioritize multiple work assignments\nComputer literate in Microsoft Office and\nProactive and willing to learn\nLess experience will be considered as Assistant\n\nInterested parties please send your full resume with expected salary and date available by clicking \"Apply Now\".\n\n(Data received will be kept confidential and used for processing application only.)", "employment_types": ["Full Time", "Permanent"], "selling_points": ["Global Leader in Testing Industry", "Perform Calibration on Laboratory Wares", "Major in Chemistry or Related Science Disciplines"], "locations": ["Kowloon Bay"], "categories": ["Sciences, Lab, R&D", "Chemical", "Laboratory", "Others"], "post_time": "2022-01-14T06:48:00Z", "salary": {"currency": null, "max": null, "min": null, "period": "monthly", "term": null}, "salary_visible": false, "title_keywords": ["assistant", "chemist"], "responsibilities": ["management", "control", "internal audit", "systems", "monitor", "audit", "maintain"], "requirements": {"degrees": ["degree"], "majors": ["science"], "languages": ["english", "chinese"], "language_level": [], "hard_skills": ["plus", "microsoft office"], "soft_skills": ["communication skills", "oral", "time management skills", "willing to learn", "prioritize", "proactive"], "languages_combined": [{"language": "english", "language_level": []}, {"language": "chinese", "language_level": []}]}, "experience_required": {"duration": ["1-2 years"], "field": ["management", "environmental"]}}, {"job_id": "100003009044596", "location_code": "hk", "company": "Quality HealthCare Medical Services Ltd", "job_title": "Medical Laboratory Technician Trainee", "description": "A Manager / Assistant Manager, Laboratory Administration & Compliance is now required as a result of business growth:\nResponsibilities:\nResponsible for all laboratory management related activities, including equipment re-allocation & disposal, and chemical & clinical wastes disposal;\nMaintain routine laboratory operations, including equipment maintenance & calibration, inventory taking and laboratory record maintenance;\nPlan and execute quality control assignment on various research & development activities;\nPerform risk assessment of operations and evaluate adequacy of internal controls;\nCarry out reviews and investigations, provide findings and recommendations to operation teams and top management;\nTimely follow up the implementation of recommendations / corrective action plans;\nDeliver trainings on integrity and compliance and share of audit requirements to team members;\nAssist in laboratory accreditation application and implementation of standard operating procedures;\nLiaise with team members and internal audit department on quality matters.\n\u00a0Requirements:\nA degree or above in Science, Engineering or related disciplines;\nA minimum of 5 years\u2019 relevant experience, some exposure of regulatory compliance / audit in academia or industry is desirable;\nHands-on experience in laboratory operation and equipment management is preferable;\nProficient in various aspects of laboratory management, including laboratory building services, electrical and mechanical services, laboratory safety, principle, regulation, compliance and ISO international standards;\nSelf-motivated and team oriented with problem solving ability and excellent documentation skills;\nProficient in both written and spoken English and Chinese;\u00a0\nCandidates with less\u00a0experience will be considered for Assistant Manager role.\nThank you for your interest in a career with CK Life Sciences.\u00a0Competitive compensation and benefits package will be offered to the right candidate.\u00a0We operate a 5-day workweek, and our benefits cover retirement, health and life.\u00a0Regular shuttle bus service is also provided with pick-ups and drop-offs at designated and convenient locations.\u00a0\nTo apply for our position, you should write, enclosing a current resume to\u00a0Chief Manager,\u00a0Human Resources & Administration, CK Life Sciences Limited, 2 Dai Fu Street, Tai Po Industrial Estate, Hong Kong\u00a0or by clicking the\u00a0APPLY NOW\u00a0button.\u00a0For more company information, please visit\u00a0www.ck-lifesciences.com.\u00a0\nWe are an equal opportunity employer and welcome applications from all qualified candidates.\u00a0 Personal data collected will be treated in strictest confidence and handled confidentially by authorized personnel for recruitment-related purposes within the Group.\u00a0\u00a0", "employment_types": ["Full Time", "Internship"], "selling_points": ["Address outstanding problems", "Monitor and check the quality control", "Practical experience in laboratory disciplines"], "locations": ["Kowloon Bay"], "categories": ["Sciences, Lab, R&D", "Laboratory", "Medical Services", "Medical Services Technician", "Others"], "post_time": "2022-01-13T04:45:29Z", "salary": {"currency": null, "max": null, "min": null, "period": "monthly", "term": null}, "salary_visible": false, "title_keywords": ["medical laboratory technician", "trainee"], "responsibilities": ["management", "maintenance", "internal audit", "operations", "inventory", "compliance", "teams", "implementation", "audit", "procedures", "evaluate", "quality", "maintain", "plan", "quality control", "liaise with", "plans"], "requirements": {"degrees": ["degree or above"], "majors": ["related disciplines", "science", "engineering"], "languages": ["english", "chinese"], "language_level": ["proficient"], "hard_skills": ["problem solving", "documentation"], "soft_skills": ["problem solving", "hands-on", "self-motivated"], "languages_combined": [{"language": "english", "language_level": ["proficient"]}, {"language": "chinese", "language_level": ["proficient"]}]}, "experience_required": {"duration": ["minimum of 5 years"], "field": ["laboratory operation", "management", "compliance", "audit", "relevant experience"]}}, {"job_id": "100003009045914", "location_code": "hk", "company": "Intertek Testing Services H.K. Ltd.", "job_title": "Assistant Engineer / Engineer (Toys / Hardlines)", "description": "1)\u00a0\u00a0\u00a0\u00a0 Sampling and chemical testing of raw material, intermediate samples, stability samples and\u00a0 finished products;\n\n2)\u00a0\u00a0\u00a0\u00a0 Perform calibration and maintenance of laboratory instrument;\n\n3)\u00a0\u00a0\u00a0\u00a0 Prepare the testing report and GMP document;\n\n4)\u00a0 \u00a0 \u00a0Ad hoc tasks as assigned by manager;\n\n\n5)\u00a0\u00a0\u00a0\u00a0 University graduate in Applied Chemistry, Chemical Technology or related disciplines;\n\n6)\u00a0\u00a0\u00a0\u00a0 Hands on experience in HPLC, GC, UV, IR or other testing instrument is an advantage;\n\n7)\u00a0\u00a0\u00a0\u00a0 Hardworking, self-motivated, fast learner and able to work under pressure and overtime;\n\n8)\u00a0\u00a0\u00a0\u00a0 Knowledge of PIC/s GMP, ISO 17025 or other quality system would be an advantage;\n\n9)\u00a0\u00a0\u00a0\u00a0 Proficient in MS Word and Excel;\n\n10)\u00a0 \u00a0 Good verbal and written communication skills in English.\n\n\n", "employment_types": ["Full Time", "Permanent"], "selling_points": ["Higher Diploma or above in Science Background", "Independent and well-organized", "Fresh graduate are also considered"], "locations": ["Lai Chi Kok"], "categories": ["Engineering", "Mechanical", "Sciences, Lab, R&D", "Laboratory", "Manufacturing", "Quality Assurance, Control & Testing / ISO"], "post_time": "2022-01-13T09:06:53Z", "salary": {"currency": null, "max": null, "min": null, "period": null, "term": null}, "salary_visible": false, "title_keywords": ["assistant engineer", "engineer"], "responsibilities": ["maintenance", "ad hoc tasks", "quality", "testing", "communication", "report", "work under pressure"], "requirements": {"degrees": ["university graduate"], "majors": ["related disciplines", "chemistry"], "languages": ["english"], "language_level": ["good"], "hard_skills": ["excel", "maintenance", "ms word"], "soft_skills": ["communication skills", "self-motivated", "hands on", "fast learner", "hardworking", "work under pressure"], "languages_combined": [{"language": "english", "language_level": ["good"]}]}, "experience_required": {"duration": [], "field": ["testing"]}}, {"job_id": "100003009050459", "location_code": "hk", "company": "Links International", "job_title": "Quality (EHS) Specialist - Construction industry", "description": "Job Responsibilities\n\nAddress outstanding problems carried over from the previous shift, including the Outstanding List for the workstation.\nMaintain a level of knowledge that will enable adequate commenting on all results.\nMonitor and check the quality control of daily runs and participate in the QC programs\nWith regular reference to laboratory documentation and other literature, be aware of any changes in analytical or other procedures.\nRecord workload and quality control statistics.\nGenerally be prepared to identify and report deficiencies in any aspect of workstation operations.\nMonitor and properly maintain lab instruments at optional status (e.g. in-service training).\nFollow up all problems to an appropriate solution or ensure proper escalation to the Workstation Supervisor or other senior staff.\nPerform housekeeping duties (e.g. cleaning, preventative maintenance stock and order of laboratory reagents and consumables.).\nBe involved in the day, night and irregular lab duties (e.g. relief or Sunday duties).\nWork as a professional medical lab technicians/technologists according to the Code of Practice, SPCM.\n\nJob Requirements\n\nProfessionally qualified with a Bachelor Degree or equivalent in Medical Laboratory Science\nPractical experience in any of laboratory disciplines e.g. hematology, microbiology, immunology and biochemistry.\nAble to work shift\nResponsible, initiative and hard working\nGood interpersonal and communication skills\nPart 2 registration with the HKMLT board\n\n\n\nInterested candidates, please click APPLY NOW \u00a0to apply.", "employment_types": ["Full Time", "Permanent"], "selling_points": ["Civil Engineering / Construction related", "Around 10 years' relevant working experience", "ISO9001 / ISO14001 / ISO17025 / OHSAS18001"], "locations": ["Yuen Long Area"], "categories": ["Sciences, Lab, R&D", "Chemical", "Building & Construction", "Building / Construction / QS", "Laboratory"], "post_time": "2022-01-14T10:28:01Z", "salary": {"currency": null, "max": null, "min": null, "period": "monthly", "term": null}, "salary_visible": false, "title_keywords": ["specialist"], "responsibilities": ["maintenance", "housekeeping", "operations", "monitor", "procedures", "maintain", "quality control", "cleaning", "documentation", "report"], "requirements": {"degrees": ["degree", "bachelor"], "majors": ["medical laboratory science"], "languages": [], "language_level": [], "hard_skills": [], "soft_skills": ["communication skills", "responsible", "hard working", "initiative", "interpersonal"], "languages_combined": []}, "experience_required": {"duration": [], "field": ["laboratory"]}}, {"job_id": "100003009045892", "location_code": "hk", "company": "HK Research Institute of Textiles & Apparel Ltd", "job_title": "Project Manager (New Sustainability Lab Development) (Ref. No.: HKRITA-PM-01/22)", "description": "Our purpose is to bring safety, quality and sustainability\u00a0to life.\n\nThe Job:\n\nConduct Physical test on toys & hard goods\nPrepare and evaluate test report on their safety, reliability and functional performance\nProvide professional advice to internal & external clients\u2019 on test report\n\u00a0The Person:\nHigher Diploma / Degree in Product Testing / Electronic Engineering / Applied Science / Mechanical\u00a0/Manufacturing Engineering/ Physics any science subject\n1 year experience in laboratory is preferable\nIndependent and well-organized\nGood command of English & Chinese\nFresh graduate and IANG will also be considered\u00a0\nCandidate with more experience will be considered as Senior Engineer\n\nThe Package\n\nDouble pay\nPerformance bonus\nMedical benefit\nDental plan with discount\n14 days annual leave\nOvertime allowance\nLife insurance\nGood career prospects\n\nInterested parties please forward full resume stating your availability, present and expected salary to\u00a0The Human Resources Manager, Intertek Testing Services HK Ltd., via\u00a0ONE\u00a0of the following channels: (Pls quote ref. no. on all correspondence.)\n\nAddress: 2/F Garment Centre, 576 Castle Peak Rd., Kowloon, H.K.\nEmail: Please click \"APPLY NOW\" Fax: 3403 2417\n\nWelcome to visit our website\u00a0http://www.intertek.com.hk for corporate information\n\n\nConfidentiality assured and all applications will be kept solely for recruitment purpose for not more than 6 months.", "employment_types": ["Full Time", "Contract"], "selling_points": [], "locations": ["Not Specified"], "categories": ["Building & Construction", "Building / Construction / QS", "Engineering", "Engineering Project Management", "Sciences, Lab, R&D", "Laboratory"], "post_time": "2022-01-15T03:50:47Z", "salary": {"currency": null, "max": null, "min": null, "period": "monthly", "term": null}, "salary_visible": false, "title_keywords": ["project manager"], "responsibilities": ["evaluate", "report"], "requirements": {"degrees": ["diploma", "degree", "fresh graduate"], "majors": ["science", "manufacturing", "engineering", "physics"], "languages": ["english", "chinese"], "language_level": ["good command"], "hard_skills": [], "soft_skills": ["independent", "well-organized"], "languages_combined": [{"language": "english", "language_level": ["good command"]}, {"language": "chinese", "language_level": ["good command"]}]}, "experience_required": {"duration": ["1 year"], "field": ["laboratory", "senior engineer"]}}, {"job_id": "100003009044955", "location_code": "hk", "company": "Intertek Testing Services H.K. Ltd.", "job_title": "Testing Specialist", "description": "Assistant Quality Manager (EHS) - Construction industry, Open to Senior Officer!\n\nOur client is looking an experienced Quality Manager responsible for the company, construction site and material testing lab quality management systems.\n\nKey Responsibilities:\n\nResponsible for develop, implement and enhance Quality Management System, Environmental Management System and Occupational Health & Safety Management System\nCreate and update the quality manuals and procedures of management systems for continuous improvement\nResponsible for regular internal audits, quality meeting, inspection and training within the Company/ Sites\nCreate training material, maintain audit record and carry out corrective action plans\nAct as the primary position holder of Document Control Centre for quality assurance unit\nHandle all technical and non-technical complaints and feedback from internal and external (Clients/Government) parties\nPerform other related duties and assignments as required by the Management\n\nRequirements:\n\nDegree Holder in Civil Engineering / Construction / Science discipline\nAt least 10 years related working experience in construction industry, with at least 5 years' experience in managing quality management system and procedures.\nCandidate with Building material testing laboratory quality experience is a plus\nWith professional qualifications in ISO 9001/ ISO 14001/ ISO 17025/ OHSAS 18001\nStrong interpersonal and communication skills in both English and Chinese\nSelf-motivated, confident and strong sense of responsibility, strong planning and organizing capabilities", "employment_types": ["Full Time", "Permanent"], "selling_points": ["Communicate with clients to about testing", "Act as Co-ordinator of internal parties & clients", "Immediate available is highly preferred"], "locations": ["Not Specified"], "categories": ["Sciences, Lab, R&D", "Laboratory", "Merchandising & Purchasing", "Toy", "Manufacturing", "Quality Assurance, Control & Testing / ISO"], "post_time": "2022-01-13T06:43:37Z", "salary": {"currency": null, "max": null, "min": null, "period": null, "term": null}, "salary_visible": false, "title_keywords": ["specialist"], "responsibilities": ["management", "control", "systems", "quality", "procedures", "audit", "develop", "inspection", "maintain", "audits", "plans"], "requirements": {"degrees": ["degree holder"], "majors": ["science", "civil engineering"], "languages": ["english", "chinese"], "language_level": [], "hard_skills": ["plus", "professional qualifications"], "soft_skills": ["confident", "communication skills", "self-motivated", "sense of responsibility", "interpersonal"], "languages_combined": [{"language": "english", "language_level": []}, {"language": "chinese", "language_level": []}]}, "experience_required": {"duration": ["at least 10 years", "at least 5 years"], "field": ["laboratory", "related", "testing", "quality management", "construction industry"]}}, {"job_id": "100003009050390", "location_code": "hk", "company": "SGS Hong Kong Limited", "job_title": "Customer Service Officer", "description": "Reporting to the Strategy and New Project Lead, the appointee will be required to:\n\ntake a vital role of managing the project of setting up a new satellite sustainability-focused laboratory in Hong Kong (https://www.theopenlab.one/);\noversee all the activities involved and progress of work, ensuring an on-schedule and smooth commencement of the new lab;\nmanage the development of the lab including the involvement in the design stage, tender/award, construction, safety standards;\nbuild and lead project teams comprising of external consultants, contractors and suppliers as well as internal cross-divisional groups;\nmanage and control the budget;\nundergo other project administrative tasks, such as procurement, fund application, regular progress reporting;\nwork closely with Research, Business Development and Marketing team to coordinate project and new initiatives related the lab; and\nperform any other duties as assigned.\n\nRequirements:\n\nA bachelor\u2019s degree or above in a Construction Management / Architecture / Engineering or related disciplines;\n5 or more years of relevant work experience. Experience in industrial, lab management or lab operation would be an advantage but not a must;\nWith solid project management and people management skills, PMP/CAPM certification is a plus;\nConversant with government procedures and regulations is a plus;\nStrong sense of project ownership and proactive working attitude;\nExcellent planning and organizing skills;\nExcellent communication and interpersonal skills;\nHighly-organized and capable of working under pressure with multi-task assignments; and\nFluent in written and spoken English, with good command of Putonghua being an advantage.\nApplicants should state their current and expected salary in the application. Salary offered will be commensurate with qualifications and experience. Appointment will be offered on a contract basis, re-engagement thereafter is subject to mutual agreement.\n\n\nApplicants are invited to send detailed curriculum vitae in strict confidence to Human Resources Manager, HKRITA, R906-8, Shirley Chan Building, The Hong Kong Polytechnic University, Hung Hom, Kowloon. Recruitment will continue until the position is filled. HKRITA reserves the right to consider late applications and nominations, and to fill or not to fill the positions. Personal data provided by applicants will be used for recruitment and other employment-related purpose.\n\nPlease mark \u201cPRIVATE & CONFIDENTIAL\u201d and quote the position applied for and its reference number on the envelope.", "employment_types": ["Full Time", "Permanent"], "selling_points": ["Performance Bonus", "CS, Handle email & phone enquiries", "Prepare proposal, quotation and tenders"], "locations": ["Yuen Long"], "categories": ["Sales, CS & Business Devpt", "Customer Service - Supervisor / Officer", "Sciences, Lab, R&D", "Laboratory", "Account Servicing"], "post_time": "2022-01-15T03:51:05Z", "salary": {"currency": null, "max": null, "min": null, "period": "monthly", "term": null}, "salary_visible": false, "title_keywords": ["customer service officer"], "responsibilities": ["regulations", "any other duties", "budget", "design", "communication", "personal data", "control", "teams", "schedule", "tender", "architecture", "reporting", "management", "construction management", "procedures", "administrative tasks", "coordinate", "project management", "recruitment", "safety standards", "planning"], "requirements": {"degrees": ["degree or above", "bachelor"], "majors": ["related disciplines", "construction management", "architecture", "engineering"], "languages": ["putonghua", "english"], "language_level": ["advantage", "good command", "fluent"], "hard_skills": ["project management", "pmp", "plus"], "soft_skills": ["organized", "confidence", "under pressure", "capable", "focused", "multi-task", "project management", "communication and interpersonal skills", "smooth", "proactive", "detailed"], "languages_combined": [{"language": "putonghua", "language_level": ["good command"]}, {"language": "english", "language_level": ["fluent", "advantage", "good command"]}]}, "experience_required": {"duration": [], "field": ["management", "operation"]}}, {"job_id": "100003009046783", "location_code": "hk", "company": "Europharm Laboratoires (Hong Kong) Company Limited", "job_title": "Senior / Quality Control Technician", "description": "Duties &\u00a0Responsibilities:\n\n\u00a0\u00a0\u00a0\u00a0\u00a0\u00a0 Provide support to team leader\n\u00a0\u00a0\u00a0\u00a0\u00a0\u00a0 Coordinating with customers\n\u00a0\u00a0\u00a0\u00a0\u00a0\u00a0 Issuance of quotation/tenders\n\u00a0\u00a0\u00a0\u00a0\u00a0\u00a0 Assist in customer order processing, daily operation and document duties, etc.\n\u00a0\u00a0\u00a0\u00a0\u00a0\u00a0 Perform marketing job\n\nRequirements/Qualification:\n\n\u00a0\u00a0\u00a0\u00a0\u00a0\u00a0 Form 6 or above\n\u00a0\u00a0\u00a0\u00a0\u00a0\u00a0 1 year of customer service experience preferably in construction material testing\n\u00a0\u00a0\u00a0\u00a0\u00a0\u00a0 Strong communication and interpersonal skills, both oral and written.\n\u00a0\u00a0\u00a0\u00a0\u00a0\u00a0 Ability to effectively supervise time to meet assigned deadlines and prioritize multiple work assignments under management instruction.\n\u00a0\u00a0\u00a0\u00a0\u00a0\u00a0 Ability to read, write, and speak English.\n\u00a0\u00a0\u00a0\u00a0\u00a0\u00a0 Ability to work independently with minimal instruction and supervision.\n\u00a0\u00a0\u00a0\u00a0\u00a0\u00a0 Computer literate in Microsoft Office and Excel.\u00a0\n\n\u00a0Working Days:\n\n\u00a0Monday to\u00a0Friday 0830 - 1730\u00a0and Saturday 0830 \u2013 1230\n\n\u00a0Benefit:\n\nAnnual Leave 11 days\nBank holiday\nGood attendance bonus\nMedical insurance\nYear-end Bonus\u00a0\n\nInterested parties please send your full resume with expected salary and date available by clicking \"Apply Now\".\n\n(Data received will be kept confidential and used for processing application only.)", "employment_types": ["Full Time", "Permanent"], "selling_points": [], "locations": ["Tai Po Area"], "categories": ["Sciences, Lab, R&D", "Chemical", "Laboratory", "Research & Development (R&D)"], "post_time": "2022-01-14T01:03:58Z", "salary": {"currency": null, "max": null, "min": null, "period": "monthly", "term": null}, "salary_visible": false, "title_keywords": ["quality control technician"], "responsibilities": ["provide support", "quotation", "daily operation", "order processing"], "requirements": {"degrees": [], "majors": [], "languages": ["english"], "language_level": [], "hard_skills": ["excel", "microsoft office"], "soft_skills": ["oral", "work independently", "prioritize", "customer service", "communication and interpersonal skills"], "languages_combined": [{"language": "english", "language_level": []}]}, "experience_required": {"duration": ["1 year"], "field": ["customer service", "construction", "testing"]}}, {"job_id": "100003009050386", "location_code": "hk", "company": "SGS Hong Kong Limited", "job_title": "\u5efa\u6750\u6aa2\u6e2c\u6280\u8853\u54e1 Technician (\u6a5f\u5834\u4e09\u8dd1)", "description": "Job Responsibilities\n\nResponsible in daily sampling and analysis of environmental samples, raw materials, in-process materials and finished products;\nConduct calibration and routine maintenance of laboratory instrumentation;\nAssist in generation of report and filing of test result;\nResponsible for house-keeping duty and cleaning of laboratory glassware; &\nTo perform general support duties assigned by supervisor.\n\nJob Requirements\n\nDiploma in Pharmacy of Chinese Medicine or related science Discipline;\nInterested in quality control and laboratory work;\nHardworking, self-motivated;\nKnowledge of using computer is preferred; &\nCandidate with more relevant experience or higher qualification will be considered as Senior Quality Control Technician.\n\nHow to Apply\n\nYou are invited to send in your application and CV stating the position you are applying for together with your current and expected salary, either by clicking \"APPLY NOW\"\u00a0 or Mail to 12-14 Dai Wang Street, Tai Po Industrial Estate, Tai Po, NT.\u00a0\n\nEuropharm Laboratoires (Hong Kong) Company Limited\u00a0is an equal opportunities employer. The information provided will be treated in strict confidence and used only for consideration of application for relevant/similar post(s).\u00a0 All personal data of unsuccessful applicants will be destroyed within 6 months.\n\n", "employment_types": ["Full Time", "Permanent"], "selling_points": ["\u984d\u5916\u8868\u73fe\u734e\u91d1 \u5e74\u7d42\u8cde\u91d1 \u52e4\u5de5\u734e\u7b49", "\u6709\u85aa\u5728\u8077\u57f9\u8a13 \u826f\u597d\u6649\u5347\u968e\u68af", "\u5efa\u7bc9\u6750\u6599\u6e2c\u8a66 \u6236\u5916\u5de5\u4f5c"], "locations": ["Yuen Long"], "categories": ["Sciences, Lab, R&D", "Laboratory"], "post_time": "2022-01-15T03:51:04Z", "salary": {"currency": null, "max": null, "min": null, "period": "monthly", "term": null}, "salary_visible": false, "title_keywords": ["technician"], "responsibilities": ["maintenance", "analysis", "cleaning", "general support", "report"], "requirements": {"degrees": ["diploma"], "majors": ["science"], "languages": ["chinese"], "language_level": [], "hard_skills": [], "soft_skills": ["self-motivated", "interested in", "confidence", "hardworking"], "languages_combined": [{"language": "chinese", "language_level": []}]}, "experience_required": {"duration": [], "field": ["relevant experience", "quality control"]}}, {"job_id": "100003009047259", "location_code": "hk", "company": "SinoMab BioScience Ltd", "job_title": "Research Associate / Research Assistant", "description": "\u4e3b\u8981\u8077\u8cac\n\n\u5728\u5be6\u9a57\u5ba4\u6216\u5de5\u5730\u73fe\u57f8\u5354\u52a9\u62bd\u53d6\u5efa\u7bc9\u6750\u6599\u6a23\u672c\uff0c\u53ca\u9032\u884c\u6e2c\u8a66\u5de5\u4f5c\n\n\u5165\u8077\u8981\u6c42\n\n\u6709\u85aa\u5728\u8077\u57f9\u8a13\u3001\u7121\u9808\u76f8\u95dc\u5b78\u6b77\u53ca\u5de5\u4f5c\u7d93\u9a57\n\u4e2d\u4e09\u6216\u4ee5\u4e0a\u5b78\u6b77\n\u9858\u610f\u6236\u5916\u5de5\u4f5c\n\u5730\u9ede\uff1a\u6a5f\u5834\u4e09\u8dd1\n\u5de5\u4f5c\u6642\u9593\n\n\n\u661f\u671f\u4e00\u81f3\u661f\u671f\u516d 8:30-18:30 / 9:30-19:30 (\u5468\u65e5\u53ca\u9280\u884c\u5047\u671f\u4f11\u606f)\n\n\u85aa\u916c\n\n\u6708\u85aa$16,000, \u6708\u5165\u53ef\u9054$21,000\u6216\u4ee5\u4e0a (\u984d\u5916\u8868\u73fe\u734e\u91d1\u53ca\u8d85\u6642\u6d25\u8cbc)\n\u798f\u5229\n\n\n\u8d85\u6642\u6d25\u8cbc\u00a0\u00a0\n\u6709\u85aa\u5e74\u5047\u00a0\u00a0\n\u52e4\u5de5\u734e\n\u91ab\u7642\u4fdd\u96aa\u00a0 \u00a0\n\u914c\u60c5\u6027\u82b1\u7d05\u00a0\n\u6709\u85aa\u5728\u8077\u57f9\u8a13\n\u6649\u5347\u968e\u68af (\u6280\u8853\u54e1\u00e0\u9ad8\u7d1a\u6280\u8853\u54e1\u00e0\u4e3b\u7ba1\u7d1a\u6280\u8853\u54e1)\n\n\u00a0\u5982\u6709\u8208\u8da3\uff0c\u53ef\u7528Whatsapp\u4e86\u89e3\u66f4\u591a\uff1a9206 6024", "employment_types": ["Full Time", "Permanent"], "selling_points": ["Plan, Design and Perform Experiments", "Purchase and Maintenance of Laboratory Reagents", "Opportunity to engage at the forefront of Biopharm"], "locations": ["Shatin Area"], "categories": ["Sciences, Lab, R&D", "Laboratory", "Medical Services", "Pharmaceutical", "Research & Development (R&D)"], "post_time": "2022-01-14T02:41:05Z", "salary": {"currency": null, "max": null, "min": null, "period": "monthly", "term": null}, "salary_visible": false, "title_keywords": ["research associate", "research assistant"], "responsibilities": [], "requirements": {"degrees": [], "majors": [], "languages": [], "language_level": [], "hard_skills": [], "soft_skills": [], "languages_combined": []}, "experience_required": {"duration": [], "field": []}}, {"job_id": "100003009042484", "location_code": "hk", "company": "Webster Personnel Agency Limited", "job_title": "Scientific Laboratory Technician - R&D", "description": "We are now seeking a potential incumbent to join our expanding company with the following responsibilities:\n\n\n\nResponsibilities:\n\nAssist in the execution of different experiments assigned by the team leader.\nEngage in scientific discussions entailing innovative ideas, current literature research and experimental design.\nData logging and analysis\nOrganize and report experiments progress to the corresponding supervisor and senior management.\nEnsure the laboratory equipment and reagents are in good condition and assist in purchase when required.\n\nRequirements:\n\nDegree or Master in Biochemistry, Biomedical Science, Biotechnology or equivalent disciplines.\nWith 1 -2 years relevant working experience\u00a0\nCandidates who process\u00a0MPhil education level will be considered as associate position.\u00a0\nPossess experience in Molecular Cloning, Western Blot, PCR, Antibody Production, or Cell Culturing is preferred.\nGood commands of written and spoken English and Chinese (Mandarin).\nProficiency in Microsoft Word and Excel.\n\n\nWe offer 5-day Work Week, Bank Holiday, Medical & Dental insurance, 13-Month Salary, Promising Career Path and Competitive Remuneration\u00a0Package to the right candidate. Interested parties please send your detailed resume with current and expected salary, contact number and email address by clicking \"Apply Now\".\n(We regret only shortlisted candidates will be notified, personal data collected will be treated as confidential and for recruitment purpose only.)", "employment_types": ["Full Time", "Contract"], "selling_points": [], "locations": ["Not Specified"], "categories": ["Sciences, Lab, R&D", "Laboratory", "Research & Development (R&D)", "Others"], "post_time": "2022-01-12T07:42:20Z", "salary": {"currency": null, "max": null, "min": null, "period": "monthly", "term": null}, "salary_visible": false, "title_keywords": ["laboratory technician"], "responsibilities": ["ideas", "data", "analysis", "purchase", "experimental design", "senior management", "report"], "requirements": {"degrees": ["degree", "master"], "majors": ["biomedical science"], "languages": ["english", "chinese", "mandarin"], "language_level": ["good"], "hard_skills": ["excel", "microsoft word"], "soft_skills": [], "languages_combined": [{"language": "english", "language_level": ["good"]}, {"language": "chinese", "language_level": ["good"]}, {"language": "mandarin", "language_level": ["good"]}]}, "experience_required": {"duration": ["1 -2 years"], "field": ["relevant working experience"]}}, {"job_id": "100003009049511", "location_code": "hk", "company": "Intertek Testing Services H.K. Ltd.", "job_title": "Customer Services Executive / Supervisor (Softlines)", "description": "If you have a chemistry or science background and want to support scientific analysis, investigation, research and development, consider a career as a scientific laboratory technician to conduct diversified and non-standardised lab experiments.\nScientific laboratory technicians\u00a0carry out the work that allows scientists to concentrate on, and perform, the more complex analytical processes in the laboratory.\u00a0\u00a0You\u2019ll play an important role in the foundation stages of research and development and in scientific analysis and investigation.\nOur client is a global industrial materials supplier with high-throughput research capabilities driving to develop market-driven technical product solutions.\u00a0\u00a0They seek potential candidates to strengthen their R&D team in the region.\n\nYou\u2019ll be involved in:\n\na variety of laboratory-based investigations\u00a0\ndesigning and executing lab works, which include sampling, testing, measuring, recording and analysing results as part of the scientific research team\nproviding all the required technical support to enable the laboratory to function effectively with adhering to defined procedures and safety guidelines\noperating and maintaining laboratory analytical instruments\nassisting the advancement and development of new products\n\nRequired Qualifications:\n\nAssociate degree or above in Chemistry or Science subjects\nHands-on experience in executing lab experiments or working experience in commercial lab\nWilling to learn specific & practical techniques and apply them to solve technical problems\u00a0\nAttention to detail, patience and teamwork skills\nFlexibility to work with and provide support for a number of people\nGood communication skills and able to speak English and Chinese\n\nInterested parties please apply through email and provide latest resume and salary expect.\u00a0All information provided will be used for recruitment purposes only", "employment_types": ["Full Time", "Permanent"], "selling_points": ["Good career prospect", "Attractive remuneration package", "On-the-job training for fast development"], "locations": ["Lai Chi Kok"], "categories": ["Sciences, Lab, R&D", "Laboratory", "Sales, CS & Business Devpt", "Account Servicing"], "post_time": "2022-01-14T08:53:08Z", "salary": {"currency": null, "max": null, "min": null, "period": "monthly", "term": null}, "salary_visible": false, "title_keywords": ["executive", "supervisor"], "responsibilities": ["provide support", "maintaining", "technical support", "guidelines", "analysis", "procedures", "investigation", "develop", "testing", "communication", "executing", "solve technical problems", "designing"], "requirements": {"degrees": ["degree or above"], "majors": ["science", "chemistry"], "languages": ["english", "chinese"], "language_level": ["good"], "hard_skills": ["r&d", "analysis"], "soft_skills": ["communication skills", "teamwork", "willing to learn", "hands-on", "attention to detail", "patience", "driven"], "languages_combined": [{"language": "english", "language_level": ["good"]}, {"language": "chinese", "language_level": ["good"]}]}, "experience_required": {"duration": [], "field": ["commercial"]}}, {"job_id": "100003009045980", "location_code": "hk", "company": "KingMed Diagnostics (Hong Kong) Limited", "job_title": "Medical Laboratory Technologist", "description": "Our purpose is to bring safety, quality and sustainability to life.\n\nThe Job\n\nAn excellent development of career in a listed multinational corporation to deliver the best-in-class B2B services to safeguard quality\nDeliver customer services by acting as the coordinator between our clients\u00a0of world top brands of fashion & retails\u00a0and internal technical\u00a0colleagues\nHandle test requisitions and follow up orders\nReview Chemical test results and report content from a technical perspective\nProvide professional advice and appropriate technical support to internal parties in order to achieve a high level of client satisfaction\nAnalyze\u00a0client menu and follow up the whole process with internal co-partners (e.g. physical Lab, chemical Lab and post-lab)\nOn-the-job training will be provided\n\nThe Person\n\nDegree / Higher Diploma holder in Chemistry or Textile related discipline\nWorking experience in chemical testing laboratory is an advantage\nGood command of written and spoken English and Chinese (Cantonese and Mandarin)\nGood interpersonal and communication skills\nImmediate availability is an advantage\n\nThe Package\n\nFive day work week\nDouble pay\nMedical benefit\nDental plan with discount\n14 days annual leave\nOvertime allowance\nLife insurance\nGood career prospects\n\nJoin us in bringing quality and safety to life\u00a0", "employment_types": ["Full Time", "Permanent"], "selling_points": ["Warm & Harmonious working environment", "Public Holidays, Double Pay, Performance Bonus", "Long-term career development"], "locations": ["Ngau Tau Kok"], "categories": ["Sciences, Lab, R&D", "Laboratory", "Medical Services", "Medical Services Technician", "Others"], "post_time": "2022-01-13T09:19:15Z", "salary": {"currency": null, "max": null, "min": null, "period": "monthly", "term": null}, "salary_visible": false, "title_keywords": ["medical laboratory technologist"], "responsibilities": ["follow up orders", "technical support", "review", "quality", "customer services", "internal parties", "report"], "requirements": {"degrees": ["degree", "higher diploma holder"], "majors": ["chemistry"], "languages": ["cantonese", "english", "chinese", "mandarin"], "language_level": ["good command"], "hard_skills": [], "soft_skills": ["communication skills", "interpersonal"], "languages_combined": [{"language": "cantonese", "language_level": ["good command"]}, {"language": "english", "language_level": ["good command"]}, {"language": "chinese", "language_level": ["good command"]}, {"language": "mandarin", "language_level": ["good command"]}]}, "experience_required": {"duration": [], "field": ["laboratory", "chemical testing"]}}, {"job_id": "100003009047332", "location_code": "hk", "company": "Hong Kong Cyclotron Laboratories Limited", "job_title": "Assistant Chemist / Technician", "description": "Responsibilities:\u00a0\n\nRequired to\u00a0carry out all kinds of medical laboratory tests and procedures\nAble to work on different functions in\u00a0medical laboratory under instructions\nInterface with doctors and laboratory technicians to ensure adherence to quality requirements\nCustomer oriented with good communications with doctors, nurses and other corporate clients\n\n\nRequirements:\u00a0\n\nRegistered MLT with valid practicing certificate issued by HKMLT Board\nBachelor degree in Biomedical Science/ Medical Laboratory Science or related field\nStrong sense of teamwork and able to work under pressure\nGood command of written and spoken English and Cantonese\nGood interpersonal and communication skills\nRemuneration is according to experience and qualifications\n\nInterested parties please apply with full resume, stating availability plus present and expected salary.", "employment_types": ["Full Time", "Permanent"], "selling_points": ["Synthesis & Quality Control of Radiopharmaceutical", "Perform daily routine task along with general lab", "Familiar with pharmaceutical analysis"], "locations": ["Shatin Area"], "categories": ["Sciences, Lab, R&D", "Chemical", "Laboratory", "Medical Services", "Medical Services Technician"], "post_time": "2022-01-14T02:50:42Z", "salary": {"currency": null, "max": null, "min": null, "period": "monthly", "term": null}, "salary_visible": false, "title_keywords": ["technician", "assistant", "chemist"], "responsibilities": ["communications with", "quality", "ensure adherence", "procedures"], "requirements": {"degrees": ["certificate", "degree", "bachelor"], "majors": ["biomedical science", "medical laboratory science"], "languages": ["cantonese", "english"], "language_level": ["good command"], "hard_skills": [], "soft_skills": ["communication skills", "teamwork", "interpersonal", "work under pressure"], "languages_combined": [{"language": "cantonese", "language_level": ["good command"]}, {"language": "english", "language_level": ["good command"]}]}, "experience_required": {"duration": [], "field": []}}, {"job_id": "100003009050214", "location_code": "hk", "company": "Saint Honore Cake Shop Ltd", "job_title": "Senior Quality Assurance Officer", "description": "Responsibilities\n\nSynthesis & Quality Control of Radiopharmaceuticals in Cleanroom Environment using Medical Cyclotron;\nPerform daily routine task along with general lab cleaning;\nPerforms clerical and administrative tasks, including maintenance of daily production records, report preparation and maintenance records;\nRequirement\n\nDegree or Higher Diploma in Analytical Science/Applied Chemistry or other related disciplines;\nFamiliar with pharmaceutical analysis in GC, HPLC and TLC\u00a0\nKnowledge of cGMP/ISO and working experience in relevant position will be an advantage;\nStrong documentation practices, oral communication, and writing skills\nProficiency in reading, writing and comprehension skill of English & Chinese;\nProficiency in MS Office applications;\nShift duty is required\nCandidate with less experience will be considered as technician.\nContact us\n\nQualified candidate, please email your full resume with academic credentials, working experience, expected salary and availability by clicking the \"apply now\" button as below.", "employment_types": ["Full Time"], "selling_points": ["Focus on quality enhancement", "Implementation & maintenance of quality mgt system", "5 yrs exp. in food manufacturing industry"], "locations": ["Kwai Tsing Area"], "categories": ["Sciences, Lab, R&D", "Food Science", "Laboratory", "Manufacturing", "Quality Assurance, Control & Testing / ISO"], "post_time": "2022-01-14T09:57:02Z", "salary": {"currency": null, "max": null, "min": null, "period": null, "term": null}, "salary_visible": false, "title_keywords": ["senior quality assurance officer"], "responsibilities": ["maintenance", "maintenance records", "quality control", "cleaning", "administrative tasks", "report"], "requirements": {"degrees": ["diploma", "degree"], "majors": ["related disciplines", "science", "chemistry"], "languages": ["english", "chinese"], "language_level": ["proficiency"], "hard_skills": ["documentation", "analysis", "writing skills", "ms office"], "soft_skills": ["communication", "oral", "writing skills"], "languages_combined": [{"language": "english", "language_level": ["proficiency"]}, {"language": "chinese", "language_level": ["proficiency"]}]}, "experience_required": {"duration": [], "field": []}}, {"job_id": "100003009048298", "location_code": "hk", "company": "GIA Hong Kong Laboratory Limited", "job_title": "Diamond Grader Associate (Excellent career prospect)", "description": "Responsibilities:\nImplementation and maintenance of quality management system;\nPerform food safety, hygiene inspection and monitor in production floor to ensure the operation complies with all statutory requirements and in-house hygiene standard;\nFocus on quality enhancement;\nAssist in\u00a0ad hoc projects as assigned.\n\u00a0Requirements:\n\nBachelor Degree in Food & Nutritional Science or equivalent;\n5 years relevant experience in food manufacturing industry;\nKnowledge of GMP/ HACCP & ISO 9001 and food regulation would be an advantage;\nIndependent, responsible with good communication skill;\nProficient in Chinese Word, Excel and PowerPoint;\nCandidate with more experience could be considered as Assistant QA Manager\nInterested parties, please forward your resume stating salary expectation and available date to us.\n\nFor more information of Saint Honore Cake Shop, please visit www.cr-asia.com\nAll applications will be treated in the strictest confidence. Personal data provided will be used for recruitment purpose only. The information collected might also be disclosed to other associated companies of the Fung Group for job matching of similar vacancies.\nThe provision of full and complete information in support of your application is necessary for selection purposes. Applicant has the right to request access to and correction of personal data collected from him/her in writing to the Human Resource Manager by post to P.O. Box 92408, Tsim Sha Tsui Post Office, Hong Kong.", "employment_types": ["Full Time", "Permanent"], "selling_points": ["6-Month Paid Training Period", "5-Day Work Week & Double Pay & Performance Bonus", "Excellent Career Prospect"], "locations": ["Kowloon Bay"], "categories": ["Manufacturing", "Jewelry", "Sciences, Lab, R&D", "Laboratory", "Quality Assurance, Control & Testing / ISO"], "post_time": "2022-01-15T03:49:56Z", "salary": {"currency": null, "max": null, "min": null, "period": "monthly", "term": null}, "salary_visible": false, "title_keywords": ["associate"], "responsibilities": ["management", "food safety", "maintenance", "quality", "implementation", "monitor", "inspection", "hygiene", "statutory requirements", "ad hoc projects"], "requirements": {"degrees": ["degree", "bachelor"], "majors": ["science"], "languages": ["chinese"], "language_level": ["proficient"], "hard_skills": ["excel", "word", "powerpoint"], "soft_skills": ["communication skill", "independent", "responsible"], "languages_combined": [{"language": "chinese", "language_level": ["proficient"]}]}, "experience_required": {"duration": ["5 years"], "field": ["food manufacturing industry", "relevant experience", "qa"]}}, {"job_id": "100003009044901", "location_code": "hk", "company": "QAT Services Limited", "job_title": "(Assistant) Technical Engineer - Hardgoods", "description": "2022 March Group Diamond Grader Hiring\n\nInterested to join Jewelry Industry and be a professional Diamond Grader? Due to our aggressive expansion, we are hiring a large group of Diamond Graders to meet our high production requirements.\n\nCome build a unique career as a Diamond Grader Associate in GIA Hong Kong Laboratory. You will work with diamonds, microscopes and computers in a laboratory production environment that emphasizes detail, quality and precision.\n\nWe offer an intensive 6 month paid training period that provides hands-on individualized training incorporating GIA Laboratory policies, procedures, and established guidelines in the documentation of pertinent data for the GIA Laboratory Diamond Grading Report.\n\nRESPONSIBILITIES\n\nEvaluate and grade loose diamonds. Identify, documents and plot characteristics, treatments and other features of a diamond.\nWork in a team setting with other graders of various skill levels.\nPerformed detailed evaluations using tools such as a microscope, a loupe, tweezers and a computer.\n\n\u00a0QUALIFICATIONS/REQUIREMENTS\n\nDiploma or above required with fluent English.\nNo relevant education or working experience required.\nAbility to work with microscopes.\u00a0\nDetail-minded with good concentration skills.\u00a0\nEffective communication and good interpersonal skills is a must.\u00a0\nAbility to get along with a diverse group of individuals in Hong Kong and other international locations.\u00a0\nProven ability to accept and learn from constructive criticism.\u00a0\nWell organized, responsible, mature & ability to work independently.\u00a0\n\n\u201cWe are an equal opportunity employer and welcome applications from all qualified candidates.\u00a0 Personal data provided by job applicants will be used strictly in accordance with our personal data policy. The information will only be used for appointment to the Company and other company-related purposes.\u201d\n\nContact & Company Information\n\nPlease submit resumes via Apply Now. All resumes must include your past salary history and current salary requirements.\u00a0\n\nWe encourage you to visit our corporate website at http://www.gia.edu/ to learn more information about GIA.", "employment_types": ["Full Time"], "selling_points": ["HD/ Degree in Science Background", "Physical testing on hardgoods products", "5-day work week; double pay; dental and medical"], "locations": ["Kwai Hing"], "categories": ["Sciences, Lab, R&D", "Laboratory"], "post_time": "2022-01-13T06:35:11Z", "salary": {"currency": null, "max": null, "min": null, "period": null, "term": null}, "salary_visible": false, "title_keywords": ["assistant", "technical engineer"], "responsibilities": ["evaluate"], "requirements": {"degrees": ["diploma or above"], "majors": [], "languages": ["english"], "language_level": ["fluent"], "hard_skills": ["no"], "soft_skills": ["detail-minded", "work independently", "responsible", "well organized", "mature", "communication", "diverse", "interpersonal skills", "constructive"], "languages_combined": [{"language": "english", "language_level": ["fluent"]}]}, "experience_required": {"duration": [], "field": ["education"]}}, {"job_id": "100003009047622", "location_code": "hk", "company": "DNA - Tech Limited", "job_title": "R&D Technician", "description": "Responsibilities\n\nParticipate in BioRadar related R&D projects;\nPerform laboratory tests and data analysis independently by strictly following the standard operation procedures. Conduct experiments including nucleic acid extraction, PCR and quantitative PCR, isothermal amplification, DNA cloning, bacterial culture, bio-chip examination, etc.. Complete the research tasks assigned by supervisor;\nReport experimental results, progressions and arising problems to supervisor routinely;\nCarry out method development, optimization and validation under the supervision of R&D director;\nLab organizational duties such as sourcing of laboratory consumables, preparation of reagents and buffers, calibration and daily maintenance of laboratory instrumentation \u00a0related documentation.\nPerform other duties as assigned.\n\nRequirements\n\nHigher Diploma\u00a0\u00a0or above in molecular biology, microbiology,\u00a0biochemistry,\u00a0or other biotech-related disciplines;\nHands-on experience in basic \u00a0molecular bio-techniques including nucleic acid extraction and PCR\nMature, responsible, independent, career-minded and able to work under pressure;\nFamiliar with GLP or ISO regulations is a plus;Good command in both verbal and written Chinese and English\nRelevant working experience preferred;\n\nIf you are passionate, driven and looking for a new and exciting opportunity within a successful and growing company, this may be the right role for you.\n\nPlease click \u201cApply Now\u201d to submit your application.\n\nAll Personal data collected will be strictly confidential and used for recruitment purpose only. Applicants who are not invited to an interview within one month from the closing date should consider their applications unsuccessful. If you are not selected, all data will be destroyed within six months from the date you applied.\u00a0", "employment_types": ["Full Time", "Permanent"], "selling_points": ["In vitro diagnosis system (IVD)", "Competitive salary", "DNA microchips"], "locations": ["Shatin Area"], "categories": ["Sciences, Lab, R&D", "Laboratory", "Life Science", "Research & Development (R&D)"], "post_time": "2022-01-14T03:36:04Z", "salary": {"currency": null, "max": null, "min": null, "period": "monthly", "term": null}, "salary_visible": false, "title_keywords": ["r&d technician"], "responsibilities": ["perform other duties", "related documentation", "maintenance", "procedures", "data analysis", "report"], "requirements": {"degrees": ["diploma"], "majors": ["molecular biology", "related disciplines", "microbiology"], "languages": ["english", "chinese"], "language_level": ["good command"], "hard_skills": ["plus", "basic"], "soft_skills": ["passionate", "independent", "responsible", "mature", "hands-on", "driven", "work under pressure"], "languages_combined": [{"language": "english", "language_level": ["good command"]}, {"language": "chinese", "language_level": ["good command"]}]}, "experience_required": {"duration": [], "field": ["relevant working experience"]}}, {"job_id": "100003009050106", "location_code": "hk", "company": "A.S. Watson Industries", "job_title": "\u53e3\u7f69\u54c1\u8cea\u76e3\u63a7\u54e1", "description": "Summary\n\nQATS are hiring a (Assistant) Chemist to join our Textile's Chemical Laboratory team.\u00a0The successful candidate will be assist\u00a0Supervisor to implement quality system in the laboratory, laboratory operations.\n\nWhat will you do?\n\u00a0 \u00a0 \u00a0\u00a0Perform daily operations and test data analysis\n\u00a0 \u00a0 \u00a0\u00a0Responsible for the calibration and maintenance of equipment\n\u00a0 \u00a0 \u00a0\u00a0Maintain stock on consumables and monitor environmental conditions of the laboratory\n\u00a0 \u00a0 \u00a0Operation and maintenance on analytical instruments including GC-MS, LC-MS, ICP-OES, ICP-MS, UV-Vis, etc is preferred\nWhat will you need?\nDiploma holder in Analytical Chemistry / Textile or related disciplines\nMinimum 1 year experience in laboratory operation\nKnowledge and experience in quality management of ISO/IEC 1702\nHands on experience on operating analytical instruments including GC-MS, LC-MS\nFamiliar with the European safety regulations of consumer goods and handling of international customers is preferred\nStrong team spirit and good communication skills\nInitiative, organised and able to work independently\nGood communication and presentation skills\nGood command of English and Chinese including Mandarin\nMore experienced personnel will be considered as Chemist\nWhat do we offer?\n\nWe are dedicated to fostering a family-friendly culture and work environment and we are an equal opportunities employer and welcome applications from all candidates with the required skills and experience.\n\n\u00a0\nMarket Leading Remuneration Package:\n\nDouble pay and discretionary bonus\nChoice of MPF provider\nLife Insurance\nMedical Insurance\n\nSupportive Environment:\n\nRental re-imbursement scheme\nFlexible work arrangements\nIn-house training courses\nTraining sponsorship scheme\nHealth Check\nVision Check\nSupporting your child\u2019s education with advice from a leading education consultant\n\nWork-Life Balance:\n\n5 day week\nCompetitive Annual Leave\nCharity, Community and Sporting Events", "employment_types": ["Full Time", "Permanent"], "selling_points": ["\u514d\u8cbb\u5ee0\u8eca\u63a5\u9001\u3001\u914c\u60c5\u6027\u82b1\u7d05", "\u63a1\u96c6\u6a23\u672c\u548c\u6aa2\u6e2c\u53e3\u7f69", "\u6587\u6191\u7a0b\u5ea6\u6216\u4ee5\u4e0a, \u7121\u9808\u7d93\u9a57"], "locations": ["Tai Po Area"], "categories": ["Sciences, Lab, R&D", "Laboratory", "Manufacturing", "Quality Assurance, Control & Testing / ISO", "Others", "Student / Fresh Graduate / No Experience"], "post_time": "2022-01-14T09:47:26Z", "salary": {"currency": null, "max": null, "min": null, "period": "monthly", "term": null}, "salary_visible": false, "title_keywords": ["\u53e3\u7f69\u54c1\u8cea\u76e3\u63a7\u54e1"], "responsibilities": ["regulations", "management", "maintenance", "operations", "quality", "monitor", "data analysis", "communication", "daily operations", "maintain"], "requirements": {"degrees": ["diploma holder"], "majors": ["analytical chemistry", "related disciplines"], "languages": ["english", "chinese", "mandarin"], "language_level": ["good command"], "hard_skills": ["analysis", "maintenance"], "soft_skills": ["communication skills", "work independently", "team spirit", "responsible", "communication", "presentation skills", "hands on", "organised", "initiative"], "languages_combined": [{"language": "english", "language_level": ["good command"]}, {"language": "chinese", "language_level": ["good command"]}, {"language": "mandarin", "language_level": ["good command"]}]}, "experience_required": {"duration": ["minimum 1 year"], "field": ["laboratory operation", "analytical", "quality management"]}}, {"job_id": "100003009034543", "location_code": "hk", "company": "Prenetics Limited", "job_title": "Part-time Laboratory Assistant", "description": "\u5de5\u4f5c\u5167\u5bb9:\n\n\u7d00\u9304\u548c\u7ba1\u7406\u8ca8\u54c1\u6578\u91cf, \u78ba\u4fdd\u7522\u54c1\u7b26\u5408\u5b89\u5168\u8981\u6c42\n\u63a1\u96c6\u6a23\u672c\u548c\u6aa2\u6e2c\u53e3\u7f69\n\u8ca0\u8cac\u65e5\u5e38\u751f\u7522\u7dda\u4e0a\u534a\u6210\u54c1\u6216\u6210\u54c1\u4e4b\u6aa2\u67e5\u53ca\u70ba\u534a\u6210\u54c1\u5305\u88dd\u888b\u5c01\u53e3\n\u8a18\u9304\u6709\u95dc\u534a\u6210\u54c1\u6216\u6210\u54c1\u4e4b\u6aa2\u67e5\u5831\u544a\n\n\u5165\u8077\u8981\u6c42:\n\n\u6587\u6191\u7a0b\u5ea6\u6216\u4ee5\u4e0a\n\u6700\u5c11\u4e00\u5e74\u76f8\u95dc\u7d93\u9a57\n\u6709\u8cac\u4efb\u611f\u3001\u7a4d\u6975\u3001\u4e3b\u52d5\u3001\u80fd\u7368\u7acb\u8655\u7406\u5de5\u4f5c\n\u826f\u597d\u95b1\u8b80\u53ca\u66f8\u5beb\u4e2d\u6587\u53ca\u82f1\u6587\n\u61c2\u6587\u66f8\u8655\u7406\uff0c\u5982MS Excel\u3001Word\u53caPowerpoint\n\u9808\u8f2a\u73ed\u5de5\u4f5c\n\u7562\u696d\u751f\u6216\u8f03\u5c11\u7d93\u9a57\u8005\u6216\u88ab\u8003\u616e\u4f5c\u52a9\u7406\u53e3\u7f69\u54c1\u8cea\u76e3\u63a7\u54e1\n\n\u54e1\u5de5\u798f\u5229\u5305\u62ec:\n\n\u914c\u60c5\u6027\u82b1\u7d05\n\u52a0\u73ed\u6d25\u8cbc\n\u81b3\u98df\u6d25\u8cbc\n\u514d\u8cbb\u5ee0\u8eca\u63a5\u9001\n12\u5929\u6709\u85aa\u5e74\u5047\n\u91ab\u7642\u4fdd\u96aa(\u5305\u62ec\u5bb6\u5c6c)\n\u751f\u65e5/\u751f\u80b2\u79ae\u5238\n\u5a5a\u5047\u3001\u6069\u6064\u5047\n\u826f\u597d\u8077\u696d\u767c\u5c55\n\u54e1\u5de5\u6d3b\u52d5\n\u5728\u8077\u57f9\u8a13\u3001\u9032\u4fee\u8cc7\u52a9\n\u54e1\u5de5\u53ca\u5bb6\u5c6c\u8cfc\u7269\u512a\u60e0\n\n\u5de5\u4f5c\u5730\u9ede\uff1a\u5927\u57d4\u5de5\u696d\u90a8\n\n\u6709\u610f\u8005\u8acb\u81f4\u96fb\u62db\u8058\u7d44\u96fb\u8a71: 2660 1880\u6216\u6309 APPLY NOW \u7533\u8acb\u8077\u4f4d\u3002\n\n\u6240\u6709\u6c42\u8077\u8005\u4e4b\u8cc7\u6599\u53ea\u4f5c\u62db\u8058\u7528\u9014\u4e26\u7d55\u5c0d\u4fdd\u5bc6, \u82e5\u6c42\u8077\u8005\u65bc6\u661f\u671f\u5167\u4e26\u672a\u7372\u672c\u516c\u53f8\u63a5\u898b, \u672c\u516c\u53f8\u6703\u5c07\u5176\u8cc7\u659912\u500b\u6708\u5167\u6bc0\u6ec5\u3002", "employment_types": ["Part Time", "Permanent"], "selling_points": ["fast-paced, dynamic team environment", "Proactive, energetic and fun culture", "Part-time, HKD 100 per hour"], "locations": ["Quarry Bay"], "categories": ["Sciences, Lab, R&D", "Laboratory", "Life Science", "Research & Development (R&D)"], "post_time": "2022-01-10T03:37:44Z", "salary": {"currency": null, "max": null, "min": null, "period": "monthly", "term": null}, "salary_visible": false, "title_keywords": ["laboratory assistant"], "responsibilities": [], "requirements": {"degrees": [], "majors": [], "languages": [], "language_level": [], "hard_skills": [], "soft_skills": [], "languages_combined": []}, "experience_required": {"duration": [], "field": []}}, {"job_id": "100003009047425", "location_code": "hk", "company": "Tai Hing Catering Group Limited", "job_title": "Quality Assurance Technician (Food Hygiene)", "description": "Founded in 2014, Prenetics is a major global diagnostics and genetic testing company with the mission to bring health closer to millions of people globally and decentralize healthcare by making the three pillars \u2014 Prevention, Diagnostics and Personalized Care \u2014 comprehensive and accessible to anyone, at anytime and anywhere. Prenetics is led by visionary entrepreneur,\u00a0Danny Yeung, with a team of over 800 employees and operations across 9 locations, including\u00a0United Kingdom,\u00a0Hong Kong,\u00a0India,\u00a0South Africa, and\u00a0Southeast Asia. Prenetics develops consumer genetic testing and early colorectal cancer screening; provides COVID-19 testing, rapid point of care and at-home diagnostic testing and medical genetic testing.\n\nMost recently, Prenetics made\u00a0international headlines to become the first Unicorn in Hong Kong to publicly list on the Nasdaq via merger with\u00a02021 Adrian Cheng's Artisan Acquisition Corp, valuing Prenetics at approximately US $1.7b.\n\nMake a difference to the community! Let's fight COVID-19 together for Hong Kong and make Hong Kong safe again. This is a unique opportunity to make a difference to the community and to play a role to fight COVID-19 here in Hong Kong. The faster we identify, the faster we can stop the virus chain!\n\nResponsibilities\u00a0\n\nAssist Medical Laboratory Technicians and Assistant Technical Officers for the specimens pre-processing steps, e.g. equipment calibration and daily laboratory operational maintenance\nConduct assigned laboratory and administrative tasks to ensure timely delivery and accuracy of tests\nComply with all current best-in-class laboratory practices and laboratory standard operating procedure and company policies and procedures\nHandle ad hoc record data into the laboratory system and databases\u00a0\nPerform quality control and external proficiency testing\n\nOur ideal candidate will have\n\nExperience in processing of clinical laboratory testing would be an advantage\nFluent in Cantonese and English, writing and speaking, fluency in Mandarin a plus\nStrong sense of teamwork and able to work under pressure\nComfortable and flexible in a fast-paced, dynamic team environment\nShift and weekend duties are required, extra\u00a0monetary\u00a0incentives for overnight shifts\nStrong commitment to the vision and mission of Prenetics and our focus on Health and Wellness\nAbility to work independently\nSelected candidates will be offered HKD 100 per hour (plus overnight incentives\n\nOur DNA is\u00a0P-R-E-N-E-T-I-C-S.\u00a0See what each word of our company name means:\n\nPassion\n\nYou love what you do and accomplish amazing result\nYou spread positivity, bring enthusiasm to work and inspire team members\nYou drive team toward specific goals, even when they seem unlikely or difficult\n\nResilience\n\nYou embrace changes and be able to drive through uncertainty, ambiguity and uncomfortable situations\nYou bounce back quickly from setbacks and challenges\nYou are persistent and determined to achieve the desired outcome\n\nEmpowerment\n\nYou trust others to play their positions well like an elite sports team\nYou foster a strong team spirit while encouraging others to take initiatives and risks\nYou create a space to allow team to grow and hold each other accountable\n\niNtegrity\n\nYou are trustworthy and lead by example\nYou are consistent in your message and action all the times\nYou deliver what you have promised\n\nEpic\n\nYou challenge your own comfort zone and always outperform yourself\nYou make meaningful and amazing impact to the world\nYou dare to take risks\n\nTransparency\n\nYou are completely honest and committed to giving candid feedbacks, no matter how challenging it might be\nYou share ideas, knowledge and skills that empower others and create access to information with the wider team\nYou share wins and failures openly\n\nIngenuity\n\nYou make sound judgement and come up with solutions that are creative and smart. Copy when feasible\nYou challenge the status quo and question things that could be done differently for better. Modify the wheel if you can\u2019t change it\nYou think outside of the box and make value-based innovation\n\nCommunication\n\nYou articulate your thoughts and ideas effectively and respectfully\nYou know your audience and talk in a way they want to be told\nYou make sure communications happens, no matter where you are\n\nSelfless\n\nYou put the needs of others before one's own and find ways in helping other to succeed\nYou focus on team wins than personal wins and share credits\nYou act in the company's best interest\n\nWe are Prenetics, our people make us who we are.", "employment_types": ["Full Time", "Permanent"], "selling_points": [], "locations": ["Shatin Area"], "categories": ["Hospitality / F & B", "Food & Beverage", "Sciences, Lab, R&D", "Laboratory", "Manufacturing", "Quality Assurance, Control & Testing / ISO"], "post_time": "2022-01-14T03:03:05Z", "salary": {"currency": null, "max": null, "min": null, "period": "monthly", "term": null}, "salary_visible": false, "title_keywords": ["technician"], "responsibilities": ["ad hoc", "ideas", "maintenance", "data", "operations", "policies", "procedures", "testing", "communication", "databases", "quality control", "administrative tasks", "work under pressure"], "requirements": {"degrees": [], "majors": [], "languages": ["cantonese", "english", "mandarin"], "language_level": ["fluency", "fluent"], "hard_skills": ["plus", "no", "maintenance", "word", "make", "safe", "dynamic", "c", "databases", "rapid", "r", "focus", "processing"], "soft_skills": ["team spirit", "trustworthy", "persistent", "communication", "comprehensive", "visionary", "articulate", "focus", "work under pressure", "determined", "integrity", "committed", "honest", "creative", "ideal", "work independently", "unique", "dynamic", "flexible", "timely", "teamwork", "accountable"], "languages_combined": [{"language": "cantonese", "language_level": ["fluent"]}, {"language": "english", "language_level": ["fluent"]}, {"language": "mandarin", "language_level": ["fluency"]}]}, "experience_required": {"duration": [], "field": ["laboratory testing", "clinical"]}}, {"job_id": "100003009050969", "location_code": "hk", "company": "Hong Kong Science & Technology Parks Corporation", "job_title": "Senior Officer, Biomedical Technology Support Centre [JDB/SOBMTSC/220114]", "description": "Responsibilities\n\nConduct factory inspection in accordance with company standard and governmental regulations\nPerform equipment calibration and on-site sampling in food production center and shops\nConduct checking and testing of raw materials and final products\nAssist in developing, maintaining and monitoring of HACCP and ISO 22000 system\nDeal with quality and hygiene related documents\nHandle ad-hoc duties as specified by the superiors\n\nRequirements\n\nHigher Diploma or above in Food Science or other related discipline\n1 year relevant experience or above (Experience in F&B industry is preferred)\nBasic knowledge on GMP, HACCP and ISO 22000 system\nProficiency in MS Office (Word, Excel & PowerPoint)\nGood command of both spoken and written English and Chinese\nShift duty is required (including public holiday & lunar new year)\nFresh graduates are also welcome\nImmediately available is preferred\n\nWe offer\u00a0competitive\u00a0package and benefits:\n\nFive-Day work week\u00a0(Shift duties is required)\n3 Days Marriage Leave\n5 Days Full Pay Paternity Leave\nFamily-Friendly Leave\nBirthday Leave\nFree Duty Meal\nStaff Discount\nMedical Allowance\nInsurance Plan\nPromotion Opportunities\n\nFor more company information, please visit our web site at\u00a0www.taihing.com\n\nInterested parties please send\u00a0full resume with expected salary\u00a0and availability\u00a0to the\u00a0Human Resources Department via email.\n\nAll information received will be kept in strict confidence and only used for employment-related purposes. Applicants who are not invited for interview within 6 weeks may consider their applications unsuccessful.", "employment_types": ["Full Time"], "selling_points": [], "locations": ["Shatin Area"], "categories": ["Sciences, Lab, R&D", "Chemical", "Laboratory", "Life Science"], "post_time": "2022-01-14T12:15:19Z", "salary": {"currency": null, "max": null, "min": null, "period": "monthly", "term": null}, "salary_visible": false, "title_keywords": ["senior officer"], "responsibilities": ["regulations", "maintaining", "related documents", "monitoring", "quality", "developing", "checking", "testing", "inspection", "hygiene", "ad-hoc duties"], "requirements": {"degrees": ["higher diploma or above"], "majors": ["food science"], "languages": ["english", "chinese"], "language_level": ["good command"], "hard_skills": ["excel", "basic", "word", "powerpoint", "ms office"], "soft_skills": [], "languages_combined": [{"language": "english", "language_level": ["good command"]}, {"language": "chinese", "language_level": ["good command"]}]}, "experience_required": {"duration": ["1 year"], "field": ["f&b", "relevant experience"]}}, {"job_id": "100003009044348", "location_code": "hk", "company": "Quality HealthCare Medical Services Ltd", "job_title": "Medical Laboratory Technician Part I / II", "description": "Responsibilities:\n\nBuild and maintain collaborative relationships with all stakeholders of the Institute for Translational Research (ITR) of HKSTP, including but not limited to academia, researchers, and business clients;\nProvide instrumentation and application support to Biomedical Technology Support Centre (BSC); \u00a0\nAssist users in operation and maintenance of laboratory instruments as well as support projects of BSC users;\nHandle technical writing such as standard operating procedures, protocols, technical notes, guidelines and flow charts;\nUnderstand customers\u2019 technical requirements and develop effective solutions;\nProvide overall administrative and procurement support; and\nPerform any other duties as assigned by supervisors and management.\n\nRequirements:\n\nA bachelor\u2019s degree or above in Biology, Biochemistry, Biotechnology, Biomedical Science, Microbiology, Pharmacology, or other discipline related to life science;\nMinimum 2 years of relevant experience in life science or biomedical research laboratory; Less experience with higher qualification will also be considered;\nA proven practical experience in operation of flow cytometer, sequencer or confocal microscopy would be preferred;\nKeep abreast of the latest development in instrumentation and analytical methods;\nFamiliar with occupational hazards and standard safety practices;\nCustomer-centered service attitude with strong problem-solving skills is a must;\nA good team player with excellent communication, analytical, interpersonal and presentation skills as well as able to work independently;\nProficient in MS office (Words, Excel and PowerPoint); and\nProficient in both written and spoken English and Chinese.\n\nWe offer market competitive compensation, 5-day work week, and generous benefits including medical and life insurance; and voluntary contribution in addition to the legal minimum MPF.\u00a0 To apply, please send your full resume with current and expected salary to the Human Resources & Office Administration Department, Hong Kong Science and Technology Parks Corporation, 5/F, Building 5E, 5 Science Park East Avenue, Hong Kong Science Park, Hong Kong or, by email via \"Apply Now\"\u00a0on or before 27 January 2022.\u00a0 \u00a0Please quote the reference number on the email subject/envelope and the application letter.\u00a0\n\nPersonal data provided will be treated in strict confidence and used for recruitment purpose only.\u00a0 All personal data collected will be used strictly in accordance with employer\u2019s personal data policies, you can access to HKSTP\u2019s Personal Information Collection Statement at https://www.hkstp.org/hkstp_web/en/hkstp/personal-information-collection-statement-recruitment\n\nApplicants not invited for interview within four weeks after application deadline may consider their applications unsuccessful.\u00a0 Personal data of unsuccessful applicants will be retained for a maximum of two years.\u00a0\n\nwww.hkstp.org", "employment_types": ["Full Time", "Permanent"], "selling_points": ["Part 1 or 2 registration with the HKMLT board", "Welcome fresh graduates to apply", "5 days work week"], "locations": ["Kowloon Bay"], "categories": ["Sciences, Lab, R&D", "Laboratory", "Medical Services", "Medical Services Technician"], "post_time": "2022-01-13T03:46:32Z", "salary": {"currency": null, "max": null, "min": null, "period": "monthly", "term": null}, "salary_visible": false, "title_keywords": ["medical laboratory technician"], "responsibilities": ["support projects", "any other duties", "management", "maintenance", "guidelines", "procedures", "develop", "maintain"], "requirements": {"degrees": ["degree or above", "bachelor"], "majors": ["biomedical science", "science", "pharmacology", "microbiology", "biology"], "languages": ["english", "chinese"], "language_level": ["proficient"], "hard_skills": ["excel", "words", "powerpoint", "problem-solving skills", "ms office"], "soft_skills": ["good team player", "work independently", "communication", "presentation skills", "problem-solving skills", "interpersonal"], "languages_combined": [{"language": "english", "language_level": ["proficient"]}, {"language": "chinese", "language_level": ["proficient"]}]}, "experience_required": {"duration": ["minimum 2 years"], "field": ["laboratory", "research", "relevant experience", "operation"]}}, {"job_id": "100003009046782", "location_code": "hk", "company": "Europharm Laboratoires Company Limited", "job_title": "Assistant / Quality Control Chemist", "description": "Responsibilities:\n\nPerform calibration on laboratory wares and equipment and manage reference equipment\nAssist in preparation work of laboratory accreditation, method validation (MV), measurement uncertainty (MU), inter-laboratory correlation (ILC) performance evaluation, etc.\nAssist the maintenance of QA system in lab such as PT arrangement and evaluation\nAssist in new test setup and deployment in project basis\nPerform and monitor equipment calibration and ensure proper handling and maintenance of test equipment by technical staff in the laboratory\nUndertake any other duties as deemed appropriate by Supervisor\n\nJob Requirements:\n\nHigher Diploma or above in Chemistry, Applied Chemistry, Chemical Technology, Analytical Science, Environmental Science or related disciplines\nAt least 1 year work experience in commercial testing laboratory, chemical lab is highly preferred\nKnowledge in ISO/IEC 17025, MV and MU is a definite advantage\nExperience of participation in HOKLAS and/or CNAS accreditation activities is a definite advantage\nKnowledge in analytical & chemical testing and use of related instrumentation\nBasic knowledge in worldwide regulations on consumer products safety (including toys) is a plus\nGood analytical skill and attention to details\nStrong sense of responsibility\nGood command of spoken and written Chinese and English (Mandarin is a plus)\nCandidates with less experience will be considered as Assistant Chemist\nImmediate available is highly preferred\n\nWe offer competitive salary and benefits to\u00a0the right candidate.\u00a0 Interested parties please send your application with date of availability, present & expected salary to the\u00a0Human Resources Department,\u00a0Bureau Veritas Hong Kong\u00a0Limited\u00a0by mail or\u00a0clicking \u201cAPPLY NOW\u201d.\u00a0\u00a0To submit your application by mail, please mark\u00a0\"Confidential\" and position applied on the envelope.\n\nOur Benefits:\n\n5-day Work Week\u00a0\nOvertime Payment\nPublic Holiday, Annual Leave, Marriage Leave, Maternity Leave & Paternity Leave\nDouble Pay, Performance Bonus\nLife & Medical Insurance Benefits\nMandatory Provident Fund Contribution\nEducation & Training Subsidies\nExcellent Training & Career Advancement Opportunities\n\nJoin us on Linkedin:\u00a0\u00a0https://www.linkedin.com/company/bureau-veritas-consumer-products-services/mycompany/\n\nMail\u00a0\n1/F,\u00a0Pacific Trade Centre\n2 Kai Hing Road\nKowloon Bay, Kowloon\n\nWhatsApp\u00a0:\u00a0(852)\u00a09637 6655\n\nPersonal data collected will be used for recruitment purposes only.\n\n\n", "employment_types": ["Full Time", "Permanent"], "selling_points": [], "locations": ["Tai Po Area"], "categories": ["Sciences, Lab, R&D", "Chemical", "Laboratory", "Medical Services", "Medical Services Technician"], "post_time": "2022-01-14T01:03:57Z", "salary": {"currency": null, "max": null, "min": null, "period": "monthly", "term": null}, "salary_visible": false, "title_keywords": ["quality control chemist", "assistant"], "responsibilities": ["any other duties", "maintenance", "measurement", "monitor", "evaluation", "setup"], "requirements": {"degrees": ["higher diploma or above"], "majors": ["related disciplines", "science", "environmental science", "chemistry"], "languages": ["english", "chinese", "mandarin"], "language_level": ["good command"], "hard_skills": ["plus", "basic", "analytical skill"], "soft_skills": ["analytical skill", "attention to details", "sense of responsibility"], "languages_combined": [{"language": "english", "language_level": ["good command"]}, {"language": "chinese", "language_level": ["good command"]}, {"language": "mandarin", "language_level": ["good command"]}]}, "experience_required": {"duration": ["at least 1 year"], "field": ["commercial", "laboratory", "testing"]}}, {"job_id": "100003009047479", "location_code": "hk", "company": "Intertek Testing Services H.K. Ltd.", "job_title": "Clerk (Electrical Lab)", "description": "Job Responsibilities\u00a0\n\nTo work as a professional medical lab technicians/technologists according to the Code of Practice, SPCM.\nTo monitor and check the quality control of daily runs and participate in the QC programs\nAddress outstanding problems carried over from the previous shift, including the Outstanding List for the workstation.\nMaintain a level of knowledge that will enable adequate commenting on all results.\nJob Requirements\u00a0\n\nRegistered Medical Laboratory Technologist in Part I or II\u00a0\nHigher Diploma or above\u00a0\u00a0\n5 days work week\u00a0 (Shift Duty: 9:30am - 6:30pm or 1:30pm - 10:30pm)\u00a0\nImmediate available is highly preferred\n\nWe offer attractive remuneration and fringe benefits. Interested parties please send your full resume with\u00a0current salary and\u00a0expected salary to\u00a0Human Resources Department, Quality HealthCare Medical Services Limited, 3/F, Skyline Tower, 39 Wang Kwong Road, Kowloon Bay,\u00a0Kowloon\u00a0or by clicking \"Apply Now\".\n\n(All applications will be treated in strict confidence and data collected will be used for recruitment purposes only)", "employment_types": ["Full Time", "Permanent"], "selling_points": ["World Leading Testing Lab to Ensure Safety", "Fresh Graduate is welcome", "Five day work week"], "locations": ["Lai Chi Kok"], "categories": ["Admin & HR", "Clerical / Admin Staff", "Others", "Sciences, Lab, R&D", "Laboratory"], "post_time": "2022-01-14T03:15:49Z", "salary": {"currency": null, "max": null, "min": null, "period": null, "term": null}, "salary_visible": false, "title_keywords": ["clerk"], "responsibilities": ["maintain", "monitor", "quality control"], "requirements": {"degrees": ["higher diploma or above"], "majors": [], "languages": [], "language_level": [], "hard_skills": [], "soft_skills": [], "languages_combined": []}, "experience_required": {"duration": [], "field": []}}, {"job_id": "100003009045750", "location_code": "hk", "company": "Qima Limited", "job_title": "Senior CSR / Client Services Representative", "description": "Job Responsibilities\n\nResponsible for day to day chemical analysis of raw/in-process materials and finished products;\nPrepare / review of test result;\nAssist in development, modification and validation of testing method;\nConduct calibration and routine maintenance of laboratory instrumentation;\nAssist in generation and review of laboratory documents; &\nImplement requirements of GMP in daily operation.\n\nJob Requirements\n\nDegree or above in Chemistry, Pharmacy, Analytical Science or related discipline;\nMinimum 1 year hands on experience chemical testing preferably in pharmaceutical, herbal material or food testing;\nKnowledge on method development and validations will have additional advantage;\nFamiliar with instrumental analysis including GC-FID and\u00a0HPLC;\nExperience with GMP and ISO 17025 is preferred but not essential;\nSelf-initiative and a good team player;\nProficient in written/spoken English and Chinese;\nProficient in Microsoft Office; &\nCandidate with less relevant experience or lower qualification will be considered as Assistant Quality Control Chemist.\n\nHow to Apply\n\nYou are invited to send in your application and CV stating the position you are applying for together with your current and expected salary, either by Clicking\u00a0\"Apply Now\"\u00a0or Mail to 12-14 Dai Wang Street, Tai Po Industrial Estate, Tai Po, NT.\u00a0\n\nEuropharm Laboratoires Company Limited\u00a0is an equal opportunities employer. The information provided will be treated in strict confidence and used only for consideration of application for relevant/similar post(s).\u00a0 All personal data of unsuccessful applicants will be destroyed within 6 months.", "employment_types": ["Full Time", "Permanent"], "selling_points": ["Performance bonus, medical and dental benefits", "Near Kwun Tong MTR station; 5-min walk", "Flexible working hours"], "locations": ["Kwun Tong"], "categories": ["Sciences, Lab, R&D", "Laboratory"], "post_time": "2022-01-13T08:33:55Z", "salary": {"currency": null, "max": null, "min": null, "period": "monthly", "term": null}, "salary_visible": false, "title_keywords": ["representative"], "responsibilities": ["maintenance", "analysis", "review", "daily operation", "testing"], "requirements": {"degrees": ["degree or above"], "majors": ["science", "chemistry"], "languages": ["english", "chinese"], "language_level": ["proficient"], "hard_skills": ["analysis", "microsoft office"], "soft_skills": ["good team player", "confidence", "hands on", "self-initiative", "instrumental"], "languages_combined": [{"language": "english", "language_level": ["proficient"]}, {"language": "chinese", "language_level": ["proficient"]}]}, "experience_required": {"duration": ["minimum 1 year"], "field": ["testing", "pharmaceutical", "relevant experience", "quality control", "food", "chemical testing"]}}, {"job_id": "100003009046816", "location_code": "hk", "company": "Luxembourg Medicine Co Ltd", "job_title": "QC Technician(Microbiology)", "description": "Our purpose is to bring safety, quality and sustainability to life.\n\n\nThe Job\u00a0\n\nPrepare testing report (data entry and formatting)\n\nSupport daily documentation\u00a0\nPerform ad-hoc tasks as assigned\n\n\u00a0The Person\n\nHKDSE / \u00a0Higher Diploma holder or above in\u00a0any discipline\nWilling to learn and work overtime\nResponsible, detail minded, independent with good communication skill\nFresh graduate will also be considered\nImmediate available is perferred\n\n\u00a0The Package\u00a0\n\nFive day work week\nDouble pay\nPerformance bonus\nMedical benefit\nDental plan with discount\n14 days annual leave\nOvertime allowance\nLife insurance\nGood career prospects\n\nJoin us in bringing quality and safety to life\n\nInterested parties please forward full resume stating your availability, present and expected salary to The Human Resources Manager, Intertek Testing Services HK Ltd., via ONE of the following channels: (Pls quote ref. no. on all correspondence.)\n\nAddress: 2/F, Garment Centre, 576 Castle Peak Rd., Kowloon, Hong Kong SAR, China\n\n\nE-mail: Please click \"APPLY NOW\"\u00a0; Fax: 3403 2437 ; Whatsapp for enquiries: 6329 0464\n\nWelcome to visit our website http://www.intertek.com.hk for corporate information\n\nConfidentiality assured and all applications will be kept solely for recruitment purpose for not more than 6 months.", "employment_types": ["Full Time"], "selling_points": ["Higher Diploma or above in Biology/ Micro-biology", "1 yr solid exp preferably in commercial laboratory", "Proactive, attentive to details"], "locations": ["Yuen Long"], "categories": ["Sciences, Lab, R&D", "Laboratory", "Others"], "post_time": "2022-01-14T01:20:05Z", "salary": {"currency": null, "max": null, "min": null, "period": "monthly", "term": null}, "salary_visible": false, "title_keywords": [], "responsibilities": ["data entry", "ad-hoc tasks", "testing", "formatting", "documentation", "report"], "requirements": {"degrees": ["hkdse", "fresh graduate", "higher diploma holder"], "majors": [], "languages": [], "language_level": [], "hard_skills": [], "soft_skills": ["work overtime", "independent", "responsible", "communication skill", "willing to learn"], "languages_combined": []}, "experience_required": {"duration": [], "field": []}}, {"job_id": "100003009042585", "location_code": "hk", "company": "CMA Testing & Certification Laboratories Limited", "job_title": "Accounts Clerk", "description": "Objective\n\nMaintain good relations with clients and coordinate work efficiently to ensure high levels of service quality.\n\nYour Responsibilities\n\nHandle customer enquiries;\nProvide quotation and follow-up orders;\nCoordinate between external and internal clients to ensure to complete the order on time;\nDevelop a relationship with client;\nHandle ad-hoc assignment as required.\n\nThe Skills We\u2019re Looking For\n\nDiploma/degree holder in any discipline (though Science, Engineering, or another technical discipline will be a plus);\nFresh graduate is welcome; Candidate with more experiences can be Senior Client Service Representative;\nGood interpersonal and communication skills;\nGood problem-solving skill;\nSelf-initiated, independent and a good team player.\n\nOther Benefits\n\n5-day work, public holidays\nPerformance bonus and year-end bonus\nMedical and dental insurance\nAnnual Leave, Compensation Leave, Compassionate Leave\n\nInterested parties, please send\u00a0resume with\u00a0expected salary\u00a0to us by clicking \"APPLY NOW\".", "employment_types": ["Full Time", "Permanent"], "selling_points": ["Diploma or above in Accounting with LCCI higher", "Minimum 1 year accounting experience", "Perform AP and prepare vouchers"], "locations": ["Shatin Area"], "categories": ["Accounting", "Accountant", "Accounting Clerk / Supervisor", "Sciences, Lab, R&D", "Laboratory"], "post_time": "2022-01-12T08:05:28Z", "salary": {"currency": null, "max": null, "min": null, "period": "monthly", "term": null}, "salary_visible": false, "title_keywords": ["accounts clerk"], "responsibilities": ["ad-hoc", "handle customer enquiries", "quotation", "quality", "develop", "coordinate", "communication", "maintain"], "requirements": {"degrees": ["diploma", "fresh graduate", "degree holder"], "majors": ["science", "engineering"], "languages": [], "language_level": [], "hard_skills": ["problem-solving", "plus"], "soft_skills": ["communication skills", "good team player", "independent", "problem-solving", "interpersonal"], "languages_combined": []}, "experience_required": {"duration": [], "field": []}}, {"job_id": "100003009047279", "location_code": "hk", "company": "Business Environment Council Limited", "job_title": "Officer - EHS Performance Testing (Job ref. no.: BEC/2021/15-JB)", "description": "Responsibilities:\n\nFollow company policies and execute approved SOPs strictly.\nPerform assigned microbiological testing activities\nFollow operational procedures related to QC apparatus / equipment regarding microbiological testing\nFollow and record the procedures for the preparation of testing reagents and culture media\nCarry out microbial sampling duties, such as the handling of receiving and retention samples, etc.\nPerform microbiological tests for the stability studies of finished products according to approved protocols\nPerform microbiological equipment maintenance and calibration according to approved schedules\nParticipate in testing of process validation (PV) and cleaning validation (CV)\nMaintain the supplies of working materials, culture media, reagents, instruments, etc. for QC daily operations\nPerform Ad-hoc tasks as assigned by management.\n\nRequirements:\n\nHigher Diploma or above in Life science, chemistry / Pharmaceutical or related disciplines\nMinimum 1 year solid experience preferably in commercial laboratory/ GMP certified pharmaceutical plant\nProactive, attentive to details with good communication and interpersonal skills\nComputer knowledge in MS Office and Chinese Word Processing\n\nInterested parties please send full resume with present and expected salary to Human Resources Department by clicking APPLY NOW.", "employment_types": ["Full Time", "Permanent"], "selling_points": ["Degree in Environmental Management / Science", "Assist in implementing environmental projects", "Conduct air quality and noise measurement"], "locations": ["Kowloon City"], "categories": ["Sciences, Lab, R&D", "Environmental Science / Waste Management", "Laboratory", "Others", "Technician"], "post_time": "2022-01-14T02:44:10Z", "salary": {"currency": null, "max": null, "min": null, "period": "monthly", "term": null}, "salary_visible": false, "title_keywords": ["officer"], "responsibilities": ["management", "maintenance", "schedules", "policies", "ad-hoc tasks", "procedures", "testing activities", "testing", "daily operations", "operational procedures", "maintain", "sops", "cleaning"], "requirements": {"degrees": ["higher diploma or above"], "majors": ["related disciplines", "science", "chemistry"], "languages": ["chinese"], "language_level": [], "hard_skills": ["chinese word processing", "ms office"], "soft_skills": ["proactive", "communication and interpersonal skills", "attentive to details"], "languages_combined": [{"language": "chinese", "language_level": []}]}, "experience_required": {"duration": ["minimum 1 year"], "field": ["commercial laboratory", "pharmaceutical"]}}, {"job_id": "100003009043698", "location_code": "hk", "company": "Bureau Veritas Hong Kong Limited", "job_title": "Assistant Chemist", "description": "\u00a0Responsibilities:\u00a0\u00a0\n\nPerform general accounting duties include AR/AP, prepare vouchers and document filing\nAssist to prepare monthly report\nAssist in ad hoc tasks as assigned by supervisor\n\nRequirements:\u00a0\n\nDiploma or above in Accounting\u00a0\nMinimum 1 year accounting experience\nProficient in MS Office including MS Word, Excel\nOrganized, hardworking and strong sense of responsibility\nGood command of written and spoken English and Chinese\nImmediately available is preferred\nFresh graduates will also be considered\n\nInterested parties please send your full resume with\u00a0availability, current and expected salary\u00a0by clicking the \"Apply Now\" button.\u00a0Welcome to visit our company website\u00a0http://www.cmatesting.org/\u00a0for more information.\n\nWe are an Equal Opportunities Employer and welcome applications from all qualified candidates. All Personal data collected will be kept in strict confidence and used for recruitment purpose only.", "employment_types": ["Full Time", "Permanent"], "selling_points": ["Global Leader in Testing Industry", "Perform Chemical Tests in Laboratory Setting", "Major in Chemistry or Related Science Disciplines"], "locations": ["Kowloon Bay"], "categories": ["Sciences, Lab, R&D", "Chemical", "Laboratory", "Others"], "post_time": "2022-01-13T01:31:33Z", "salary": {"currency": null, "max": null, "min": null, "period": "monthly", "term": null}, "salary_visible": false, "title_keywords": ["assistant", "chemist"], "responsibilities": ["ap", "document filing", "ar", "ad hoc tasks", "general accounting duties", "monthly report"], "requirements": {"degrees": ["diploma or above"], "majors": ["accounting"], "languages": ["english", "chinese"], "language_level": ["good command"], "hard_skills": ["ms word", "excel", "ms office"], "soft_skills": ["organized", "hardworking", "sense of responsibility"], "languages_combined": [{"language": "english", "language_level": ["good command"]}, {"language": "chinese", "language_level": ["good command"]}]}, "experience_required": {"duration": ["minimum 1 year"], "field": ["accounting experience"]}}, {"job_id": "100003009045931", "location_code": "hk", "company": "Silenus (Hong Kong) Limited", "job_title": "Senior Manager (HRBP, Learning & Development)", "description": "Major Responsibilities:\n\nAssist in implementing environmental projects including indoor and outdoor air quality, water quality and noise\nAssist in preparing technical proposals and quotations\nConduct indoor and outdoor air quality and noise measurement\nMonitor site environmental performance regularly\nPrepare indoor air quality and EM&A reports\nMay work on Saturday, Sunday and Public Holiday\nPerform duties as assigned by Supervisor\nRequirements:\nDegree in Environmental Management / Science or related disciplines\nConstruction Industry Safety Training Certificate holder is preferred\nProficient in MS Word, Excel, PowerPoint and Chinese Word Processing\nGood command of written and spoken English and Chinese\nGood communication skills\nIndependent\u00a0\nImmediate availability is preferred\nHow to Apply:\nBEC is an equal opportunity employer and offers attractive career prospects to the successful candidate. \u00a0Please click \u201cAPPLY NOW\u201d to submit your full resume including current and expected salary and date of availability.\nApplicants who do not hear from us within 6 weeks from the date of this advertisement may consider their applications unsuccessful. \u00a0All information received including the CVs will be filed for future reference. \u00a0Personal data will be used strictly for recruitment related purposes only and retained for no more than six months.", "employment_types": ["Full Time", "Permanent"], "selling_points": ["HR Business Partner for Learning & Development", "Planning L&D objectives for over 800 staff (Global", "At least 8 years of exp in L&D functions"], "locations": ["Eastern Area"], "categories": ["Admin & HR", "HR Director / Manager", "Training & Development", "Sciences, Lab, R&D", "Laboratory"], "post_time": "2022-01-13T09:10:55Z", "salary": {"currency": "HKD", "max": 119999, "min": 90000, "period": "monthly", "term": null}, "salary_visible": true, "title_keywords": ["senior manager"], "responsibilities": ["measurement", "quality", "monitor", "reports"], "requirements": {"degrees": ["certificate", "degree"], "majors": ["related disciplines", "science"], "languages": ["english", "chinese"], "language_level": ["good command", "proficient"], "hard_skills": ["excel", "no", "chinese word processing", "powerpoint", "ms word"], "soft_skills": ["communication skills", "independent"], "languages_combined": [{"language": "english", "language_level": ["good command"]}, {"language": "chinese", "language_level": ["good command", "proficient"]}]}, "experience_required": {"duration": [], "field": []}}, {"job_id": "100003009047066", "location_code": "hk", "company": "Vickmans Laboratories Limited", "job_title": "Quality Control Technician", "description": "Responsibilities:\n\n\nPerforming chemical test with instruments and related tools in accordance with international safety standards and safety requirements\nAnalyze test data and compile test report\nPrepare necessary samples for chemical testing\nReviewing test result\nResponsible to implement the Quality Assurance Program\nJob Requirements:\u00a0\n\nUniversity degree in Chemistry, Chemical Technology, Analytical Science, Environmental Science or related disciplines\n1-3 years solid experience in commercial laboratory environment\nHands-on experience in organic/heavy metal test will be a definite advantage\nFamiliar with safety standards of consumer products will be a definite advantage\nAttentive to details with strong interest in developing career in commercial lab\nGood communication and interpersonal skills\nStrong analytical skills, attentive to details\nExcellent spoken & written English and Chinese\nFresh graduates will be considered as Graduate Chemist Trainee. On-the-job training will be provided.\n\nWe offer competitive salary and benefits to\u00a0the right candidate.\u00a0 Interested parties please send your application with date of availability, present & expected salary to the\u00a0Human Resources Department,\u00a0Bureau Veritas Hong Kong\u00a0Limited\u00a0by mail or\u00a0clicking \u201cAPPLY NOW\u201d.\u00a0\u00a0To submit your application by mail, please mark\u00a0\"Confidential\" and position applied on the envelope.\n\nOur Benefits:\n\n5-day Work Week\u00a0\nOvertime Payment\nPublic Holiday, Annual Leave, Marriage Leave, Maternity Leave & Paternity Leave\nDouble Pay, Performance Bonus\nLife & Medical Insurance Benefits\nMandatory Provident Fund Contribution\nEducation & Training Subsidies\nExcellent Training & Career Advancement Opportunities\n\nJoin us on Linkedin:\u00a0\u00a0https://www.linkedin.com/company/bureau-veritas-consumer-products-services/mycompany/\n\nMail\u00a0\n1/F,\u00a0Pacific Trade Centre\n2 Kai Hing Road\nKowloon Bay, Kowloon\n\nWhatsApp\u00a0:\u00a0(852)\u00a09637 6655\n\nPersonal data collected will be used for recruitment purposes only.", "employment_types": ["Full Time", "Permanent"], "selling_points": [], "locations": ["Ngau Tau Kok"], "categories": ["Sciences, Lab, R&D", "Laboratory", "Medical Services", "Pharmaceutical", "Manufacturing", "Quality Assurance, Control & Testing / ISO"], "post_time": "2022-01-14T02:13:31Z", "salary": {"currency": null, "max": null, "min": null, "period": null, "term": null}, "salary_visible": false, "title_keywords": ["quality control technician"], "responsibilities": ["data", "quality", "testing", "safety standards", "report"], "requirements": {"degrees": ["university degree"], "majors": ["related disciplines", "science", "environmental science", "chemistry"], "languages": ["english", "chinese"], "language_level": ["excellent"], "hard_skills": ["analytical skills"], "soft_skills": ["hands-on", "communication and interpersonal skills", "attentive to details", "analytical skills"], "languages_combined": [{"language": "english", "language_level": ["excellent"]}, {"language": "chinese", "language_level": ["excellent"]}]}, "experience_required": {"duration": ["1-3 years"], "field": ["commercial laboratory"]}}, {"job_id": "100003009042211", "location_code": "hk", "company": "Vita Green Pharmaceutical (H.K.) Limited", "job_title": "Senior Quality Control Technician", "description": "Our client, a well-established MNC in Medical and health industry, is now looking for a high-caliber candidate to join them.\n\n\nResponsibilities:\u00a0\n\nResponsible for talent management and development plan for the all employees in the company\nDesign development roadmap for different functional department and position in order to enhance the performance and nurture potential leaders for succession planning\nCommunicate with different team head for advices on learning and development goals\nEstablish a company culture through all the trainings and activities, in order to enhance the harmony within internal teams\n\nRequirements:\u00a0\n\nAt least 8 years of Talent Management/ Learning & Development/ Succession project experiences\nSolid experience on building the learning/ training/ develop function and driving culture change in a relatively large-scale company, preferably MNC\nStrong project execution and preferably with HRBP/Consultancy background\nExcellent communication skills, especially in shareholder/ senior management communication\nFluent English and Mandarin, public speaking skill is a plus\n\nFor a confidential discussion about this role please contact Clarence at 2185 6309.", "employment_types": ["Full Time", "Permanent"], "selling_points": ["PIC/s GMP pharmaceutical manufacturer", "Welcome candidate from food, drug or related field", "Great career opportunity in a leading HK brand"], "locations": ["Tai Po Area"], "categories": ["Sciences, Lab, R&D", "Laboratory", "Manufacturing", "Production Planning / Control", "Quality Assurance, Control & Testing / ISO"], "post_time": "2022-01-14T11:21:08Z", "salary": {"currency": null, "max": null, "min": null, "period": "monthly", "term": null}, "salary_visible": false, "title_keywords": ["senior quality control technician"], "responsibilities": ["communicate with", "management", "teams", "design", "plan", "planning"], "requirements": {"degrees": [], "majors": [], "languages": ["english", "mandarin"], "language_level": ["fluent"], "hard_skills": ["plus"], "soft_skills": ["communication", "communication skills", "learning"], "languages_combined": [{"language": "english", "language_level": ["fluent"]}, {"language": "mandarin", "language_level": ["fluent"]}]}, "experience_required": {"duration": ["at least 8 years"], "field": ["learning & development", "management", "training"]}}, {"job_id": "100003009044336", "location_code": "hk", "company": "Hong Kong Standards & Testing Centre", "job_title": "Technical Officer / Asst. Technical Officer (Chemical & Food Testing)", "description": "Our purpose is to bring safety, quality and sustainability to life.\u00a0\n\n\nThe Job\n\nStation in client\u2019s office and assist client\u2019s on report approvals\nFollow up e-mail and / or phone calls enquiry which related report approvals\nConsolidate information from clients for the requests on results acceptance\nCommunicate with clients to solve question about testing\nWork with internal staffs to follow up report issues\n\nThe Person\n\nAt least\u00a02 years\u2019 experience\u00a0of\u00a0clients communication in product testing/manufacturing/ mechanical aspect\nWorking experience in commercial testing\u00a0laboratory\u00a0/ in house testing laboratory will be an advantage\nGood command of spoken and written Chinese and English\nIndependent and well-organized\nProficiency in\u00a0Microsoft Office including Word and Excel\nCandidate with less experience will also be considered for the position of Assistant Testing Specialist\n\nInterested parties please forward full resume stating your availability, present and expected salary to The Human Resources Manager, Intertek Testing Services HK Ltd., via ONE of the following channels: (Pls quote ref. no. on all correspondence.)\u00a0\n\nAddress: 2/F Garment Centre, 576 Castle Peak Rd., Kowloon, H.K.\n\nE-mail:\u00a0Please click \"APPLY NOW\"\u00a0\u00a0Fax: 3403 2691\u00a0\n\nWelcome to visit our website http://www.intertek.com for corporate information\u00a0\n\nConfidentiality assured and all applications will be kept solely for recruitment purpose for not more than 6 months.", "employment_types": ["Full Time", "Permanent"], "selling_points": ["5-day work week, Double pay & Performance bonus", "Free Shuttle Bus, Medical Benefit", "Diploma or above in Chemistry/ related disciplines"], "locations": ["Tai Po Area"], "categories": ["Sciences, Lab, R&D", "Chemical", "Food Science", "Laboratory"], "post_time": "2022-01-13T03:46:06Z", "salary": {"currency": null, "max": null, "min": null, "period": "monthly", "term": null}, "salary_visible": false, "title_keywords": ["technical officer", "chemical"], "responsibilities": ["communicate with", "testing", "phone calls", "report"], "requirements": {"degrees": [], "majors": [], "languages": ["english", "chinese"], "language_level": ["good command"], "hard_skills": ["excel", "word", "microsoft office"], "soft_skills": ["communication", "independent", "well-organized"], "languages_combined": [{"language": "english", "language_level": ["good command"]}, {"language": "chinese", "language_level": ["good command"]}]}, "experience_required": {"duration": ["at least 2 years"], "field": ["commercial", "manufacturing", "laboratory", "testing"]}}, {"job_id": "100003009050104", "location_code": "hk", "company": "ALDI Services Asia Limited", "job_title": "Quality Consultant / Specialist (Hardgoods) (m/f)", "description": "Key Roles and Responsibilities:\n\nSampling and testing of pharmaceutical products\nCalibration and maintenance of equipment\nDocumentation and other quality control activities\n\n\nQualifications and Experience:\n\nDegree or above in Chemistry or other related science disciplines\n1 year above experience is preferred\nFamiliar with testing instrumental analysis in HPLC, UV & FTIR\nFamiliar with GMP and ISO is a definite advantage\nHardworking, initiative, self-motivated and fast learner\nGood problem solving skills\nGood command in both written and spoken Cantonese and English\n\n\nWe offer to the right candidates with competitive remuneration package including 12-16 day annual leave, marriage leave, maternity leave, paternity leave, compassionate leave, Public Holidays, medical and dental insurance, educational sponsorship, overtime allowance, performance bonus, MPF and other fringe benefits.\n\nHow to Apply\n\nYou are invited to send in your application and CV stating the position you are applying for together with your current and expected salary by clicking the \"apply button\".\n\n\nVickmans Laboratories Limited is an Equal Opportunities Employer. Personal data provided by job applicants will be used strictly in accordance with our personal data policy and for recruitment purposes only. We aim to respond to successful applicants within 8 weeks and related information will be kept in our file for up to 12 months for other suitable vacancies in our organization and thereafter destroyed", "employment_types": ["Full Time", "Permanent"], "selling_points": ["Research & investigate quality requirement", "Finalize quality comparison documents", "Advise on the product quality of individual sample"], "locations": ["Kwun Tong"], "categories": ["Sciences, Lab, R&D", "Laboratory", "Manufacturing", "Quality Assurance, Control & Testing / ISO"], "post_time": "2022-01-14T09:47:15Z", "salary": {"currency": null, "max": null, "min": null, "period": "monthly", "term": null}, "salary_visible": false, "title_keywords": ["specialist", "consultant"], "responsibilities": ["mpf", "maintenance", "analysis", "testing", "recruitment", "quality control", "documentation", "personal data", "insurance"], "requirements": {"degrees": ["degree or above"], "majors": ["science", "chemistry"], "languages": ["cantonese", "english"], "language_level": ["good command"], "hard_skills": ["documentation", "analysis", "problem solving skills", "maintenance"], "soft_skills": ["self-motivated", "fast learner", "problem solving skills", "instrumental", "initiative", "hardworking"], "languages_combined": [{"language": "cantonese", "language_level": ["good command"]}, {"language": "english", "language_level": ["good command"]}]}, "experience_required": {"duration": ["1 year"], "field": []}}, {"job_id": "100003009044321", "location_code": "hk", "company": "Enviro Labs Limited", "job_title": "Chemist II (5-day work)", "description": "The Role:\n\nQuality control is one of the most important processes for Vita Green Group to ensure all our production materials and finished products with the highest qualities to meet our customer satisfaction. We are looking for candidates with great interest in developing their career in quality control discipline. You will be participating in the role of conducting sample preparation and tests in both chemistry and microbiology laboratory. Moreover, you will be contributing to method validation, performance check, instrument calibration and maintenance in a reputable, stable local manufactory company.\n\nIf you are ...\u00a0\n\nthe holder of Bachelor Degree major in\u00a0Chemistry, Biochemistry, Biology or equivalent science discipline.\nhaving strong sense in science and familiar with GMP.\nhaving experience in microbial testing.\na team player and willing to learn to develop yourself.\nself-motivated, detail-oriented and multi-tasking.\nparticularly interested in growing yourself in a stable manufacturing environment.\n\nWe will offer you...\n\nA career opportunity with the market leader in health product sector.\nCasual wear everyday to enjoy your work.\nFree shuttles from various locations.\nChallenging jobs to learn and grow together.\u00a0\nRapid growth opportunities for strong performers.\u202f\u00a0\nAttractive staff purchase discount to experience our quality products.\n\nInterested parties, please send full resume with last & expected salary and date of available by clicking \u2018Apply\u2019.\n\nPersonal data collected is for recruitment purpose only.\n\nFor corporate information, please visit:\u00a0www.vitagreen.com", "employment_types": ["Full Time"], "selling_points": [], "locations": ["Fanling"], "categories": ["Sciences, Lab, R&D", "Chemical", "Environmental Science / Waste Management", "Laboratory"], "post_time": "2022-01-13T03:45:35Z", "salary": {"currency": null, "max": null, "min": null, "period": "monthly", "term": null}, "salary_visible": false, "title_keywords": ["chemist"], "responsibilities": ["maintenance", "sample preparation", "quality", "developing", "testing", "develop", "purchase", "quality control"], "requirements": {"degrees": ["degree", "bachelor"], "majors": ["science", "biology", "chemistry"], "languages": [], "language_level": [], "hard_skills": ["maintenance", "rapid"], "soft_skills": ["self-motivated", "interested in", "willing to learn", "detail-oriented", "multi-tasking", "team player", "stable"], "languages_combined": []}, "experience_required": {"duration": [], "field": ["testing"]}}, {"job_id": "100003009042873", "location_code": "hk", "company": "Minsen Testing (Hong Kong) Limited", "job_title": "Assistant Chemist / Senior Technician / Technician", "description": "Responsibilities:\n\nTo conduct tests in accordance with prescribed procedures\nTo assist group leader in providing technical support to clients\nTo produce traceable test records in suitable format\nTo develop new test methods / optimize existing analytical procedures whenever necessary\nTo perform other necessary duties as directed by superiors\n\nRequirements:\n\nHigher Diploma or above in Analytical Chemistry/ Applied Chemistry/ Applied Science or related disciplines\nPrevious experiences in consumer products testing industry would be an advantage\nProficient in English and Chinese\nFresh graduate will also be considered\n\nBenefits:\u00a0\n\n5-day work week\nDouble pay &\u00a0Performance bonus\nOver-time allowance\nEducation & Training allowance\nMedical benefit\nFree shuttle bus\nAnnual leave, Birthday leave, Marriage leave\nCompany\u00a0activities\n\nInterested parties please send your resume\u00a0with availability, present\u00a0salary\u00a0and expected salary to our Human Resources Department by Clicking\u00a0\"Apply Now\" / By Fax: 2664 4353:/ By Post: STC, 10 Dai Wang Street, Tai Po Industrial Estate, Tai Po, NT\n\nWelcome to visit our company website\u00a0www.stc.group for corporate information.\n\n(All personal data collected are for recruitment purposes only.)", "employment_types": ["Full Time", "Permanent"], "selling_points": ["Higher Diploma in Chemistry or equivalent", "Public Holiday", "Fresh graduate are welcome"], "locations": ["Tuen Mun Area"], "categories": ["Sciences, Lab, R&D", "Chemical", "Laboratory"], "post_time": "2022-01-12T09:05:04Z", "salary": {"currency": "HKD", "max": 19999, "min": 14000, "period": "monthly", "term": null}, "salary_visible": true, "title_keywords": ["technician", "assistant", "chemist"], "responsibilities": ["technical support", "procedures", "develop"], "requirements": {"degrees": ["higher diploma or above", "fresh graduate"], "majors": ["analytical chemistry", "science", "related disciplines", "chemistry"], "languages": ["english", "chinese"], "language_level": ["proficient"], "hard_skills": [], "soft_skills": [], "languages_combined": [{"language": "english", "language_level": ["proficient"]}, {"language": "chinese", "language_level": ["proficient"]}]}, "experience_required": {"duration": [], "field": ["products testing"]}}, {"job_id": "100003009046784", "location_code": "hk", "company": "Europharm Laboratoires (Hong Kong) Company Limited", "job_title": "Assistant / Quality Control Chemist", "description": "We invite now high caliber talent to apply for Quality\u00a0Consultant / Quality Specialist (m/f)\u00a0to join our rapidly growing sourcing team in Hong Kong. This position supports product development and commercialization with a fast-paced successful team.\n\nResponsibilities.\n\nProduces regular communication updates for the Quality & Compliance Manager on developments within their categories and areas of responsibility\nResearches and investigates the relevant quality requirements in preparation for submissions, completing the submission process in line with company procedures\nFinalizes quality comparison documents and advises on the product quality of individual samples\nInstructs suppliers to conform to ALDI\u2019s Social Monitoring Programmes and implements relevant action plan\nManages and controls artwork creation and approval in line with department procedures\nFollows up after-sales service support for items within his/her commodity area including liaising with after sales service providers and national teams\n\n\n\u00a0Your Profile.\n\nAt least (Non-Degree) Tertiary education required.\nMinimum of 2 years' relevant working experience, preferably gained in sourcing/buying offices, working with consumer products.\nHands-on experience with QA topics and packaging follow-up highly advantageous.\nExcellent communication and interpersonal skills, team player.\nGood command of both verbal and written business English and fluency in Mandarin essential.\nAble to work independently, self-motivated, responsible, well-organized and willing to learn.\nAttention to detail and good organizing, coordination and planning skills.\nGeneral knowledge of MS office and Exchange essential.\nHigh level of maturity, integrity, trustworthiness.\n\nKey Benefits of working at ALDI.\n\nMarket leading remuneration package\n\nRewarding, attractive remuneration package.\nGroup Medical Insurance covering dental and maternity* benefits .\n\nWork-life balance\n\nFull time, permanent position, 5-day-work-week.\n20 days of paid Annual Leave.\n\nBeing part of a pleasant, successful, growing business\n\nALDI\u2019s business is expanding, same for the Hong Kong Office with lots of opportunities for growth and development.\nPleasant working atmosphere where proactive communication, teamwork and collaboration is highly valued.\n\nPeople Focused\n\nStructured, comprehensive orientation and on-the-job training.\nALDI empowers our people allowing staff ownership of their areas of responsibilities.\n\nTrust and Integrity\n\nWE DO WHAT WE SAY - \u00a0for us there is no grey area, we have robust business processes, procedures and strong governance in place.\nWe treat our staff members, customers, suppliers and service providers with trust and fairness as business partners.\n\n\u00a0* Maternity benefits only apply for female employees due to local Insurance policy\n\nHow to apply\u00a0\u00a0\n\nIf you are interested in applying for the job, we look forward to receiving your full application in English, including salary expectation and possible starting date. The application should be sent through JobsDB by clicking icon \u201cApply Now\u201d or addressed to ALDI HR Dept, 18/F, Millennium City 6, 392 Kwun Tong Road, Kwun Tong, Kowloon, Hong Kong.\n\nALDI is an Equal Opportunity employer. We are dedicated to create an equal opportunity throughout recruitment process and staff employment to build a diverse and inclusive workforce. We oppose all forms of unfair or unlawful discrimination in our selection process.\n\nAll personal data collected will be used for recruitment purposes only and be treated in strictest confidence and highest security level in accordance with Hong Kong Data (Privacy) Ordinance as well as ALDI internal Security Policy.\n\nNo part of this job content including but not limited to company information, logo and job description may be reproduced, presented, uploaded, transmitted, modified or distributed \u00a0in any form or by any means without prior permission of ALDI Services Asia Limited / ALDI Sourcing Asia Limited (\u201cthe Company\u201d). The Company reserves the right to take legal action on any unauthorized reproduction, presentation, upload, transmission, modification or distribution. Only applications submitted directly to the Company in response to this advertisement will be considered and any application received by the Company through unauthorized third party agents or via any other channels will not be considered.", "employment_types": ["Full Time", "Permanent"], "selling_points": [], "locations": ["Tai Po Area"], "categories": ["Sciences, Lab, R&D", "Chemical", "Laboratory", "Medical Services", "Medical Services Technician"], "post_time": "2022-01-14T01:03:58Z", "salary": {"currency": null, "max": null, "min": null, "period": "monthly", "term": null}, "salary_visible": false, "title_keywords": ["quality control chemist", "assistant"], "responsibilities": ["compliance", "quality", "procedures", "monitoring", "liaising with", "communication", "teams", "commercialization", "after-sales service", "plan", "coordination", "planning"], "requirements": {"degrees": ["degree"], "majors": [], "languages": ["english", "mandarin"], "language_level": ["fluency", "good command"], "hard_skills": ["exchange", "submission process", "ms office"], "soft_skills": ["planning skills", "work independently", "self-motivated", "responsible", "well-organized", "willing to learn", "integrity", "communication", "hands-on", "communication and interpersonal skills", "attention to detail", "coordination", "team player"], "languages_combined": [{"language": "english", "language_level": ["fluency", "good command"]}, {"language": "mandarin", "language_level": ["good command"]}]}, "experience_required": {"duration": ["minimum of 2 years"], "field": ["buying offices", "relevant working experience", "qa"]}}, {"job_id": "100003009046779", "location_code": "hk", "company": "Europharm Laboratoires Company Limited", "job_title": "Senior Quality Control Technician / Quality Control Technician", "description": "Job Description\n\nConduct testing on water, wastewater, food, and other sample\nPerform calibration and maintenance of instruments/apparatus\nDevelop and validate new test methods to comply with customer's requirements\nPerform other laboratory-related works as assigned.\n\nRequirement\n\nDegree. or above in Chemistry / \u00a0Analytical Science\u00a0 / Environmental Science / Food Science or equivalent\nAt least 2 yr Hand-on experience in Environmental testing is preferred.\u00a0\nResponsible, initiative, and good team player\nCandidates will less experience will be considered as Assistant Chemist .", "employment_types": ["Full Time", "Permanent"], "selling_points": [], "locations": ["Tai Po Area"], "categories": ["Sciences, Lab, R&D", "Chemical", "Laboratory", "Others"], "post_time": "2022-01-14T01:03:57Z", "salary": {"currency": null, "max": null, "min": null, "period": "monthly", "term": null}, "salary_visible": false, "title_keywords": ["quality control technician", "senior quality control technician"], "responsibilities": ["develop", "maintenance", "testing"], "requirements": {"degrees": ["degree"], "majors": [], "languages": [], "language_level": [], "hard_skills": [], "soft_skills": ["good team player", "initiative", "responsible"], "languages_combined": []}, "experience_required": {"duration": [], "field": ["environmental", "testing"]}}, {"job_id": "100003009036228", "location_code": "hk", "company": "Karen Pharmaceutical Company Limited", "job_title": "Laboratory Assistant", "description": "Responsibilities:\u00a0\n\nUndertakes the preparation of samples for analysis;\nProvides support to senior chemists in general laboratory procedures;\nOperation and maintenance of analytical instruments including ICP-OES, Carbon & Sulphur Analyzer, Nitrogen Analyzer, etc.\nImplement the quality system according to ISO 17025\n\n\u00a0Requirements :\u00a0\n\nHigher Diploma or above in Analytical Chemistry, Applied Chemistry or related disciplines;\nWork independently with strong problem solving skills;\nFresh graduates are welcome;\nCandidate with more experience and qualification can be considered for employment as Chemist\n\u00a0Able to read & write Chinese and English ;\n\nEmployment Terms:\n\nGood Attendance Bonus, Bank Holiday, Overtime Allowance and Performance Award,\n\nMon to Fri: 9:00AM-5:30PM and\n\nSat: 9:00AM-1:00PM, 5.5 working days per week\n\n** For this job vacancy, the employer may enroll for joining the Employment Programme for the Elderly and Middle-aged and hence elderly and middle-aged job seekers are welcome to apply.\n\nApplication Information:\u00a0Job seekers may e-mail resume to\u00a0MINSEN\u00a0TESTING (HONG KONG) LIMITED. To obtain a copy of Personal Information Collection Statement, please contact MR. HUANG by Email.\n\nCompany Overview:\n\nhttp://www.minsen.com.hk\n\nAdditional Information\n\nCareer Level: Entry Level\n\nQualification: High Diploma or above\n\nEmployment Type: Full time\n\nJob Function: Chemical, R&D, Laboratory\n\n\u00a0\nAdditional Company Information\n\nBenefits & Others:\n\nPublic Holiday\nAnnual Leave\nMPF", "employment_types": ["Full Time"], "selling_points": [], "locations": ["Tuen Mun Area"], "categories": ["Sciences, Lab, R&D", "Laboratory", "Medical Services", "Pharmaceutical", "Manufacturing", "Quality Assurance, Control & Testing / ISO"], "post_time": "2022-01-10T09:44:42Z", "salary": {"currency": null, "max": null, "min": null, "period": null, "term": null}, "salary_visible": false, "title_keywords": ["laboratory assistant"], "responsibilities": ["quality", "analysis", "procedures", "maintenance"], "requirements": {"degrees": ["higher diploma or above", "high diploma or above"], "majors": ["analytical chemistry", "related disciplines", "chemistry"], "languages": ["english", "chinese"], "language_level": [], "hard_skills": ["r&d", "problem solving skills"], "soft_skills": ["work independently", "problem solving skills"], "languages_combined": [{"language": "english", "language_level": []}, {"language": "chinese", "language_level": []}]}, "experience_required": {"duration": [], "field": []}}, {"job_id": "100003009046812", "location_code": "hk", "company": "Luxembourg Medicine Co Ltd", "job_title": "QC Officer / Senior QC Officer", "description": "Job Responsibilities\n\nResponsible for day to day chemical analysis of raw/in-process materials and finished products;\nPrepare / review of test result;\nAssist in development, modification and validation of testing method;\nConduct calibration and routine maintenance of laboratory instrumentation;\nAssist in generation and review of laboratory documents; &\nImplement requirements of GMP in daily operation.\n\nJob Requirements\n\nDegree or above in Chemistry, Chinese Medicine, Analytical Science or related discipline;\nMinimum 1 year hands on experience chemical testing preferably in pharmaceutical, herbal material or food testing;\nKnowledge on method development and validations will have additional advantage;\nFamiliar with instrumental analysis including GC-FID and\u00a0HPLC;\nExperience with GMP and ISO 17025 is preferred but not essential;\nSelf-initiative and a good team player;\nProficient in written/spoken English and Chinese;\nProficient in Microsoft Office; &\nCandidate with less relevant experience or lower qualification will be considered as Assistant Quality Control Chemist.\n\nHow to Apply\n\nYou are invited to send in your application and CV stating the position you are applying for together with your current and expected salary, either by Clicking\u00a0\"Apply Now\"\u00a0or Mail to 12-14 Dai Wang Street, Tai Po Industrial Estate, Tai Po, NT.\u00a0\n\nEuropharm Laboratoires (Hong Kong) Company Limited\u00a0is an equal opportunities employer. The information provided will be treated in strict confidence and used only for consideration of application for relevant/similar post(s).\u00a0 All personal data of unsuccessful applicants will be destroyed within 6 months.", "employment_types": ["Full Time", "Permanent"], "selling_points": ["Higher Diploma or above", "Minimum 1-2 year's work experiences", "Familiar with GMP environment"], "locations": ["Yuen Long"], "categories": ["Sciences, Lab, R&D", "Chemical", "Laboratory"], "post_time": "2022-01-14T01:17:10Z", "salary": {"currency": null, "max": null, "min": null, "period": "monthly", "term": null}, "salary_visible": false, "title_keywords": ["qc officer"], "responsibilities": ["maintenance", "analysis", "review", "daily operation", "testing"], "requirements": {"degrees": ["degree or above"], "majors": ["science", "chemistry"], "languages": ["english", "chinese"], "language_level": ["proficient"], "hard_skills": ["analysis", "microsoft office"], "soft_skills": ["good team player", "confidence", "hands on", "self-initiative", "instrumental"], "languages_combined": [{"language": "english", "language_level": ["proficient"]}, {"language": "chinese", "language_level": ["proficient"]}]}, "experience_required": {"duration": ["minimum 1 year"], "field": ["testing", "pharmaceutical", "relevant experience", "quality control", "food", "chemical testing"]}}, {"job_id": "100003009051018", "location_code": "hk", "company": "ATCG Limited", "job_title": "Product Manager (Life Science Labs)", "description": "Key Roles and Responsibilities\u00a0\n\nResponsible for conduct analytical instrumental analysis and chemical testing;\nResponsible to perform some instrument calibration and maintenance programs;\nSampling and testing of in-process and finished products; &\nAssist and perform any quality control duties as assigned.\n\n\n\nQualifications and Experience\u00a0\u00a0\u00a0\n\n\nDiploma level or above in Chemistry-related studies or Equivalent;\nOver or at 3 years of relevant working experience can be \"Senior Quality Control Technician\";\nFor applying Quality Control Technician, 1 year of relevant laboratory working experience is preferable but fresh graduates are welcome;\nSelf-motivated, responsible and a good team player;\nHard working & being able to work under pressure;\nGood computer knowledge is preferred (i.e. Microsoft Office); &\nImmediate available is preferable.\u00a0\n\nHow to Apply\n\nYou are invited to send in your application and CV stating the position you are applying for together with your current and expected salary, either by\u00a0Clicking\u00a0\"Apply Now\".\u00a0\n\nEuropharm Laboratoires Company Limited\u00a0is an equal opportunities employer. The information provided will be treated in strict confidence and used only for consideration of application for relevant/similar post(s).\u00a0 All personal data of unsuccessful applicants will be destroyed within 6 months.", "employment_types": ["Full Time"], "selling_points": [], "locations": ["Shatin Area"], "categories": ["Sciences, Lab, R&D", "Laboratory", "Life Science", "Sales, CS & Business Devpt", "Technical Sales / Sales Engineer"], "post_time": "2022-01-15T01:10:05Z", "salary": {"currency": null, "max": null, "min": null, "period": "monthly", "term": null}, "salary_visible": false, "title_keywords": ["product manager"], "responsibilities": ["maintenance", "analysis", "testing", "quality control", "personal data", "work under pressure"], "requirements": {"degrees": ["diploma"], "majors": ["chemistry"], "languages": [], "language_level": [], "hard_skills": ["analysis", "maintenance", "microsoft office"], "soft_skills": ["good team player", "self-motivated", "confidence", "responsible", "hard working", "instrumental", "work under pressure"], "languages_combined": []}, "experience_required": {"duration": ["1 year", "at 3 years"], "field": ["laboratory", "relevant working experience", "quality control"]}}]