[{"job_id": "100003009052684", "location_code": "hk", "company": "First Choice (Hong Kong) Medical Laboratory Limited", "job_title": "Laboratory Technician/ Assistant (Afternoon shift)", "description": "As a Senior Research Scientist / Project Manager, you will be responsible for research and development of innovative non-viral gene as well as biological drug delivery to address unmet medical needs. The ideal candidate will also have a strong passion and curiosity for cell and gene therapy with the desire to bring needed cures from bench to bedside. Demonstrated genuine interest and curiosity in research and development is highly valued.\n\n\nResponsibilities\n\nExpand our proprietary, patent-pending cell and gene delivery platform to develop new tools and/or applications for specialized and enhanced implementation in cell and gene therapy. In addition, utilizing our patented technology on expanding the non-invasive ophthalmic drug delivery platform with new biological candidates in treating eye diseases.\nApply your strong background in molecular biology, transposon, and gene delivery technology to develop new gene delivery systems for use in ex vivo and in vivo therapies.\nPrepare formulations and perform characterization assays /data analysis with focus on in vivo studies, drug carrier design/development, assay development and quality control.\nDevelop novel formulations and processes to further expand delivery capabilities\nSupport formulation development activities related to increasing stability and formulation optimization.\nWork in close interaction with internal and external industrial partners and academic institutes to ensure smooth flow of information and data.\nPrepare technical reports and presentations for clear communication of scientific findings across interdisciplinary teams.\nExecute the plans according to IND enabling timelines for both China and US regulatory submission.\n\n\u00a0Requirements\n\nPh.D. in chemistry, pharmaceutical science, molecular biology, virology or related discipline with 2-4 years of industry or post-doctoral experience.\nPrior experience with in vitro cell and gene delivery platforms and mammalian cell culture is required. Experience with non-viral gene delivery technology is strongly preferred.\nExperience with DNA/mRNA encapsulation, quantification, characterization, and handling is preferred.\nExperience with biological drug development.\nProficiency in analytical techniques like HPLC/UPLC, DLS, CD, zeta potential, UV-Vis, cryo-TEM, and fluorescence spectrophotometry etc. is preferred.\nProven track record in method development, including experimental design, execution and evaluation.\nExperience with GMP and ICH regulations is desired.\nAbility to work in a fast-paced environment, meet deadlines, and prioritize work on multiple projects.\nProven problem solving and troubleshooting abilities.\nAbility to direct and lead junior R&D staff as well as managing research grant.\nStrong communication skills in technical writing and oral presentation in English and Chinese.\nStrong sense of responsibility, accountability, and integrity.\u00a0\n\nWe offer competitive remuneration package and excellent career prospects to qualified candidates. Interested parties please send your CV together with present and expected salaries to the Human Resources Manager by clicking apply now.\n\nApplicants who are not contacted by email or call within 1 month may consider their application is unsuccessful and the personal data collected will be destroyed in due course.", "employment_types": ["Full Time", "Permanent"], "selling_points": [], "locations": ["Shatin Area"], "categories": ["Sciences, Lab, R&D", "Laboratory", "Life Science"], "post_time": "2022-01-17T03:41:49Z", "salary": {"currency": "HKD", "max": 24999, "min": 17000, "period": "monthly", "term": null}, "salary_visible": true, "title_keywords": ["laboratory technician", "assistant"], "responsibilities": ["data", "systems", "teams", "implementation", "design", "develop", "data analysis", "presentations", "communication", "reports", "quality control", "plans"], "requirements": {"degrees": [], "majors": [], "languages": ["english", "chinese"], "language_level": [], "hard_skills": ["problem solving", "r&d"], "soft_skills": ["communication skills", "oral", "accountability", "sense of responsibility", "fast-paced environment", "integrity", "troubleshooting", "prioritize", "problem solving", "meet deadlines", "presentation"], "languages_combined": [{"language": "english", "language_level": []}, {"language": "chinese", "language_level": []}]}, "experience_required": {"duration": ["2-4 years"], "field": ["pharmaceutical", "development", "related"]}}, {"job_id": "100003009054562", "location_code": "hk", "company": "\u5967\u6717\u751f\u7269\u91ab\u85e5\u6709\u9650\u516c\u53f8", "job_title": "Senior Research Scientist / Project Manager", "description": "Responsibilities:\u00a0\n\n\n\nHandling\u00a0of chemical tests related to routine sample;\nSample preparation, perform chemical test, instrumental analysis;\nOperation of analytical instrument (e.g. GC/MS, LC-DAD, LC/MS, LC/MS/MS);\nInstrument maintenance and calibration;\nMethod validation and preparation for accreditation audit;\nAssist in R&D work;\nUndertake any other duties as assigned.\n\nRequirements:\n\n\nHigher Diploma or above in Chemistry or relevant discipline;\nKnowledge of ISO 17025 quality system and accreditation requirements;\nAnalytical instrumentation skill;\nImmediately available is highly preferred.\nCandidate with less experience will be considered as Lab Technician\n\nOther Benefits:\n\n5 days work week\nMedical Insurance\nOver Time Pay\nDouble pay\nFree shuttle bus\n\nWe offer attractive remuneration package and excellent career opportunities to the right candidates. Interested parties please send your full resume with availability, current and expected salary to\u00a0our HR department.\n\nWelcome to visit our company website\u00a0http://www.cmatesting.org/ or more information.\n\nWe are an Equal Opportunities Employer and welcome applications from all qualified candidates. All Personal data collected will be kept in strict confidence and used for recruitment purpose only.", "employment_types": ["Full Time", "Permanent"], "selling_points": [], "locations": ["Shatin Area"], "categories": ["Sciences, Lab, R&D", "Laboratory", "Life Science", "Research & Development (R&D)"], "post_time": "2022-01-17T09:59:43Z", "salary": {"currency": null, "max": null, "min": null, "period": "monthly", "term": null}, "salary_visible": false, "title_keywords": ["senior research scientist", "project manager"], "responsibilities": ["any other duties", "maintenance", "sample preparation", "analysis", "audit"], "requirements": {"degrees": ["higher diploma or above"], "majors": ["chemistry"], "languages": [], "language_level": [], "hard_skills": [], "soft_skills": [], "languages_combined": []}, "experience_required": {"duration": [], "field": []}}, {"job_id": "100003009052679", "location_code": "hk", "company": "Hong Kong Laboratory Co., Limited", "job_title": "Laboratory Technician/ Assistant (Afternoon shift)", "description": "Duties:\n\nPerform all initial specimen preparation\nPerform housekeeping duties at the laboratory\nAssist the Admin Officer to perform general clerical duties\nPerform any laboratory duties assigned by the Medical Technologist and Lab Manager\nParticipate in-house and external training as required\nOther ad-hoc duties are also required\n\nRequirements:\n\nBachelor\u2019s Degree or Higher Diploma in Biomedical Science or other related Life Science disciplines\nExperience in genetic/DNA analysis, including DNA extraction, sequencing, PCR etc. is preferable\nResponsible and hardworking with good initiatives\nMust be a good team player with excellent communication skills as well as be able to work independently\nTo be able to communicate in Cantonese, Mandarin and English\nGood PC knowledge and typing skills are essential\nCandidates with less experience will be considered as Laboratory Assistant\nFresh graduates are also welcome", "employment_types": ["Full Time", "Permanent"], "selling_points": [], "locations": ["Shatin Area"], "categories": ["Sciences, Lab, R&D", "Laboratory", "Life Science", "Others"], "post_time": "2022-01-17T03:41:19Z", "salary": {"currency": "HKD", "max": 24999, "min": 17000, "period": "monthly", "term": null}, "salary_visible": true, "title_keywords": ["laboratory technician", "assistant"], "responsibilities": ["housekeeping", "ad-hoc duties"], "requirements": {"degrees": ["diploma", "degree", "bachelor"], "majors": ["biomedical science", "science"], "languages": ["cantonese", "english", "mandarin"], "language_level": [], "hard_skills": ["analysis", "pc knowledge", "typing"], "soft_skills": ["communication skills", "good team player", "work independently", "responsible", "hardworking"], "languages_combined": [{"language": "cantonese", "language_level": []}, {"language": "english", "language_level": []}, {"language": "mandarin", "language_level": []}]}, "experience_required": {"duration": [], "field": ["laboratory"]}}, {"job_id": "100003009052688", "location_code": "hk", "company": "Hong Kong Medical Laboratory Centre Limited", "job_title": "Medical Laboratory Technologist (Part I)", "description": "Job Duties:\n\n\u00a0\u00a0\u00a0\u00a0\u00a0\u00a0\u00a0\u00a0 Promote and sell designated molecular diagnostics products to life science and clinical customers\n\u00a0\u00a0\u00a0\u00a0\u00a0\u00a0\u00a0\u00a0 Achieve pre-set sales targets and prepare sales forecast\n\u00a0\u00a0\u00a0\u00a0\u00a0\u00a0\u00a0\u00a0 Prepare quotations, proposals, and execute business plan correspondence with customers\n\u00a0\u00a0\u00a0\u00a0\u00a0\u00a0\u00a0\u00a0 Collaborate with other supporting teams including logistics, technical service and application colleagues\n\u00a0\u00a0\u00a0\u00a0\u00a0\u00a0\u00a0\u00a0 Maintain good after-sales service and excellent relationship with customers\n\nJob Qualifications:\n\n\u00a0\u00a0\u00a0\u00a0\u00a0\u00a0\u00a0\u00a0 University graduate in Biochemistry, Biomedical Science or related discipline\n\u00a0\u00a0\u00a0\u00a0\u00a0\u00a0\u00a0\u00a0 2 years of sales experience in diagnostics instruments or medical devices\n\u00a0\u00a0\u00a0\u00a0\u00a0\u00a0\u00a0\u00a0 Excellent communication, interpersonal and negotiation skills\n\u00a0\u00a0\u00a0\u00a0\u00a0\u00a0\u00a0\u00a0 Accountable, self-motivated and a good team player\n\u00a0\u00a0\u00a0\u00a0\u00a0\u00a0\u00a0\u00a0 Good command of written and spoken English, Cantonese and Mandarin\n\u00a0\u00a0\u00a0\u00a0\u00a0\u00a0\u00a0\u00a0 Proficient in MS Office applications\n\u00a0\u00a0\u00a0\u00a0\u00a0\u00a0\u00a0\u00a0 Candidate with less experience will be considered for Sales Executive", "employment_types": ["Full Time", "Permanent"], "selling_points": [], "locations": ["Shatin Area"], "categories": ["Sciences, Lab, R&D", "Laboratory", "Life Science", "Medical Services", "Medical Services Technician"], "post_time": "2022-01-17T03:42:26Z", "salary": {"currency": "HKD", "max": 54999, "min": 35000, "period": "monthly", "term": null}, "salary_visible": true, "title_keywords": ["medical laboratory technologist"], "responsibilities": ["collaborate with", "teams", "prepare sales", "communication", "after-sales service", "maintain", "logistics", "forecast", "business plan"], "requirements": {"degrees": ["university graduate"], "majors": ["biomedical science"], "languages": ["cantonese", "english", "mandarin"], "language_level": ["good command"], "hard_skills": ["ms office"], "soft_skills": ["self-motivated", "good team player", "accountable", "communication", "negotiation skills", "interpersonal"], "languages_combined": [{"language": "cantonese", "language_level": ["good command"]}, {"language": "english", "language_level": ["good command"]}, {"language": "mandarin", "language_level": ["good command"]}]}, "experience_required": {"duration": ["2 years"], "field": ["medical"]}}, {"job_id": "100003009055796", "location_code": "hk", "company": "QIAGEN Hong Kong Pte. Ltd", "job_title": "Sr. Sales Specialist", "description": "Duties:\n\nPerform all initial specimen preparation\nPerform housekeeping duties at the laboratory\nAssist the Admin Officer to perform general clerical duties\nPerform any laboratory duties assigned by the Medical Technologist and Lab Manager\nParticipate in-house and external training as required\nOther ad-hoc duties are also required\n\nRequirements:\n\nBachelor\u2019s Degree or Higher Diploma in Biomedical Science or other related Life Science disciplines\nExperience in genetic/DNA analysis, including DNA extraction, sequencing, PCR etc. is preferable\nResponsible and hardworking with good initiatives\nMust be a good team player with excellent communication skills as well as be able to work independently\nTo be able to communicate in Cantonese, Mandarin and English\nGood PC knowledge and typing skills are essential\nCandidates with less experience will be considered as Laboratory Assistant\nFresh graduates are also welcome", "employment_types": ["Full Time"], "selling_points": [], "locations": ["Tsim Sha Tsui"], "categories": ["Sciences, Lab, R&D", "Life Science", "Medical Services", "Specialist", "Sales, CS & Business Devpt", "Technical Sales / Sales Engineer"], "post_time": "2022-01-18T02:57:27Z", "salary": {"currency": null, "max": null, "min": null, "period": "monthly", "term": null}, "salary_visible": false, "title_keywords": ["sales specialist"], "responsibilities": ["housekeeping", "ad-hoc duties"], "requirements": {"degrees": ["diploma", "degree", "bachelor"], "majors": ["biomedical science", "science"], "languages": ["cantonese", "english", "mandarin"], "language_level": [], "hard_skills": ["analysis", "pc knowledge", "typing"], "soft_skills": ["communication skills", "good team player", "work independently", "responsible", "hardworking"], "languages_combined": [{"language": "cantonese", "language_level": []}, {"language": "english", "language_level": []}, {"language": "mandarin", "language_level": []}]}, "experience_required": {"duration": [], "field": ["laboratory"]}}, {"job_id": "100003009052678", "location_code": "hk", "company": "Hong Kong Laboratory Co., Limited", "job_title": "Medical Laboratory Technologist (Part I)", "description": "Responsibilities:\n\nResponsible for chemical testing, project development;\nConduct researches and develop test methods;\nValidate or verify the test methods with various analytical instruments and estimate measurement uncertainty;\nPerform pilot test and feasibility study on the test methods;\nDocument the developed test methods and transfer the technical skill and knowledge of the tests to operation team;\nContinuous optimization of instrumentation and test methods;\nParticipate in ad-hoc projects and routine chemical testing as assigned.\n\nRequirements:\n\nDegree\u00a0holder or\u00a0above in Chemistry or other science relevant disciplines;\nAt least 1 year of relevant hands-on\u00a0laboratory\u00a0testing experience;\nExperience in handling analytical instruments is a Must (e.g. GC-MSMS, Headspace GC-MS, LC-MSMS);\nKnowledge of HOKLAS requirements and ISO/IEC 17025;\nInitiative, organized, independent and willing to work under pressure;\nGood problem solving and communication skills;\nGood command of English and Chinese;\nCandidate with less experience will be considered as Technical officer\n\nWe offer attractive remuneration package and excellent career opportunities to the right candidates. Interested parties please send your full resume with availability, current and expected salary to\u00a0our HR department.\n\nWelcome to visit our company website\u00a0http://www.cmatesting.org/ or more information.\n\nWe are an Equal Opportunities Employer and welcome applications from all qualified candidates. All Personal data collected will be kept in strict confidence and used for recruitment purpose only.", "employment_types": ["Full Time", "Permanent"], "selling_points": [], "locations": ["Shatin Area"], "categories": ["Sciences, Lab, R&D", "Laboratory", "Life Science", "Others"], "post_time": "2022-01-17T03:41:19Z", "salary": {"currency": null, "max": null, "min": null, "period": "monthly", "term": null}, "salary_visible": false, "title_keywords": ["medical laboratory technologist"], "responsibilities": ["develop", "ad-hoc projects", "measurement", "testing"], "requirements": {"degrees": ["degree holder"], "majors": ["science", "chemistry"], "languages": ["english", "chinese"], "language_level": ["good command"], "hard_skills": ["problem solving"], "soft_skills": ["organized", "communication skills", "independent", "problem solving", "hands-on", "initiative", "work under pressure"], "languages_combined": [{"language": "english", "language_level": ["good command"]}, {"language": "chinese", "language_level": ["good command"]}]}, "experience_required": {"duration": ["at least 1 year"], "field": ["laboratory testing", "analytical"]}}, {"job_id": "100003009052804", "location_code": "hk", "company": "Hong Kong Traditional Chinese Pharmaceutical Limited", "job_title": "Regulatory Affair Assistant", "description": "Responsibilities:\n\n\n\nHandling\u00a0of chemical tests related to routine sample;\nTest result analysis and review;\nOut of specification results investigation;\nDevelop and review test methods;\nHandling of test enquiry;\nOperation and maintenance of analytical instrument (e.g. GC/MS, LC-DAD, LC/MS, LC/MS/MS);\nMethod validation and preparation for accreditation audit;\nAssist in R&D work;\nUndertake any other duties as assigned.\n\nRequirements:\n\n\n\nDegree or above in Chemistry or relevant discipline;\nKnowledge of ISO 17025 quality system and accreditation requirements;\nExperienced in lab supervision and operation management;\nAnalytical instrumentation skill;\nInitiative, organized and comprehensive\nCandidate with less experience will be considered as Technical Officer\n\nOther Benefits:\n\n5 days work week\nMedical Insurance\nOver Time Pay\nDouble pay\nFree shuttle bus\n\nWe offer attractive remuneration package and excellent career opportunities to the right candidates. Interested parties please send your full resume with availability, current and expected salary to\u00a0our HR department.\n\nWelcome to visit our company website\u00a0http://www.cmatesting.org/ or more information.\n\nWe are an Equal Opportunities Employer and welcome applications from all qualified candidates. All Personal data collected will be kept in strict confidence and used for recruitment purpose only.", "employment_types": ["Full Time"], "selling_points": [], "locations": ["Tsim Sha Tsui"], "categories": ["Sciences, Lab, R&D", "Food Science", "Life Science", "Others"], "post_time": "2022-01-17T04:07:53Z", "salary": {"currency": "HKD", "max": 34999, "min": 25000, "period": "monthly", "term": null}, "salary_visible": true, "title_keywords": ["assistant"], "responsibilities": ["any other duties", "maintenance", "analysis", "review", "audit", "investigation", "develop"], "requirements": {"degrees": ["degree or above"], "majors": ["chemistry"], "languages": [], "language_level": [], "hard_skills": [], "soft_skills": ["organized", "comprehensive", "initiative"], "languages_combined": []}, "experience_required": {"duration": [], "field": []}}, {"job_id": "100003009044074", "location_code": "hk", "company": "City University of Hong Kong", "job_title": "Veterinary Assistant/Veterinary Nurse (2 posts) in the Department of Veterinary Clinical Sciences", "description": "Duties\n\nMonitor and manage the process of testing procedures, including reception, handling, processing, storage and testing of human blood according to the Standard Operation Procedure (SOP)\nEstablish new and review current SOP\nReview and approve quality control data for testing\nReview and approve laboratory report\nParticipate in-house and external training as required\nOther ad-hoc duties are also required\n\nRequirements\n\nValid Medical Laboratory Technologist Part I practicing cert issued by the HKMLT Board\nBachelor Degree or Higher Technical Certificate (HTC) in Biomedical Science, Medical Laboratory Sciences other related disciplines\nExperience in genetic/DNA analysis, including DNA extraction, sequencing, PCR etc. is preferable.\nStrong sense of responsibility\nMust be a good team worker with excellent communication skills as well as be able to work independently\nAble to communicate in Mandarin and Cantonese", "employment_types": ["Full Time"], "selling_points": ["5 passes in HKCEE/HKDSEE", "Experience in handling animals", "Leave, medical and dental consultations"], "locations": ["Wong Tai Sin Area"], "categories": ["Admin & HR", "Clerical / Admin Staff", "Sciences, Lab, R&D", "Life Science", "Others", "Others"], "post_time": "2022-01-16T21:50:02Z", "salary": {"currency": null, "max": null, "min": null, "period": "monthly", "term": null}, "salary_visible": false, "title_keywords": ["nurse", "veterinary assistant"], "responsibilities": ["data", "review", "monitor", "procedures", "testing", "quality control", "ad-hoc duties", "report"], "requirements": {"degrees": ["certificate", "degree", "bachelor"], "majors": ["biomedical science", "related disciplines"], "languages": ["cantonese", "mandarin"], "language_level": [], "hard_skills": ["analysis"], "soft_skills": ["communication skills", "work independently", "sense of responsibility"], "languages_combined": [{"language": "cantonese", "language_level": []}, {"language": "mandarin", "language_level": []}]}, "experience_required": {"duration": [], "field": []}}, {"job_id": "100003009056222", "location_code": "hk", "company": "Maxim's Caterers Ltd", "job_title": "Senior / Quality Assurance Officer (Cakes & Bakery Factory)", "description": "Veterinary Assistant/Veterinary Nurse (2 posts) in the Department of Veterinary Clinical Sciences (Appointment for 12 months) [Ref. C/R/386/03]\u00a0Duties\nAct as translators between clients and veterinary staff (English and Cantonese) during veterinary consultations in clinical setting and during ambulatory veterinary service consultations on production animal farms, raising goats, cattle, pigs and poultry;\nSupport animal handling practicals and clinical skills practicals including pre-extra-mural studies (EMS), pre-clinical EMS and clinical EMS, including cats, dogs and other species as required;\nProvide logistical support for events/activities (e.g. workshops, seminars, student study tours); and\nPerform any other duties as assigned.\nRequirements\n\n5 passes in HKCEE/HKDSEE including English Language and Chinese Language. Good command of written and spoken English and Chinese (including Putonghua); experience in handling animals (e.g. cats, dogs); and abilities to work independently and under pressure are required.\n\nFor Veterinary Assistant position, prior experience in the veterinary industry is required. \u00a0Candidates with AIRC Certificate at Grade 2 are preferred. \u00a0Possession of an Associate Degree/Higher Diploma/Diploma would be an advantage.\n\nFor Veterinary Nurse position, possession of formal Veterinary Nursing qualification such as AIRC Certificate at Grade 4, Advanced Diploma in Veterinary Nursing, or RVN status is required. \u00a0Possession of an Associate Degree/Higher Diploma/Diploma would be an advantage. \u00a0Prior experience in a training/mentorship role within the veterinary industry would be an advantage.\n\nShortlisted candidates will be invited for a written test.\n\nSalary and Conditions of Service\n\nSalary offered will be highly competitive, commensurate with qualifications and experience.\u00a0 Fringe benefits include leave, medical and dental consultations at the campus clinic.\n\nInformation and Application\n\nFurther information on the posts and the University is available at\u00a0http://www.cityu.edu.hk, or from the Human Resources Office, City University of Hong Kong, Tat Chee Avenue, Kowloon Tong, Hong Kong [Fax : 2788 1154 or 3442 0311].\u00a0\n\nTo apply, please submit an online application at\u00a0http://jobs.cityu.edu.hk.\u00a0 The closing date is\u00a031\u00a0January 2022.\u00a0 Applications will receive full consideration and only shortlisted applicants will be contacted.\u00a0 The University\u2019s privacy policy is available on the homepage.\n\nCity University of Hong Kong is an equal opportunity employer. We are committed to the principle of diversity. Personal data provided by applicants will be used for recruitment and other employment-related purposes.\n\nWorldwide recognition ranking #53 (QS survey 2022), and #4 among top 50 universities under age 50 (QS survey 2021); #1 in the World\u2019s Most International Universities (THE survey 2020); #1 in Engineering/Technology/Computer Sciences in Hong Kong (ARWU survey 2016); and #1 Business School in Asia-Pacific region (UT Dallas survey 2019).", "employment_types": ["Full Time", "Permanent"], "selling_points": ["Food Factory", "Perform routine on line and finished food products", "At least 2 year laboratory working experience"], "locations": ["Tai Po Area"], "categories": ["Sciences, Lab, R&D", "Laboratory", "Life Science", "Manufacturing", "Quality Assurance, Control & Testing / ISO"], "post_time": "2022-01-18T03:38:21Z", "salary": {"currency": null, "max": null, "min": null, "period": null, "term": null}, "salary_visible": false, "title_keywords": ["quality assurance officer"], "responsibilities": ["ems", "any other duties"], "requirements": {"degrees": ["certificate", "diploma", "associate degree"], "majors": ["nursing"], "languages": ["cantonese", "putonghua", "english", "chinese"], "language_level": ["good command"], "hard_skills": ["ems", "animal handling", "c", "workshops", "r"], "soft_skills": ["work independently", "under pressure", "advanced"], "languages_combined": [{"language": "cantonese", "language_level": []}, {"language": "putonghua", "language_level": ["good command"]}, {"language": "english", "language_level": ["good command"]}, {"language": "chinese", "language_level": ["good command"]}]}, "experience_required": {"duration": [], "field": ["training"]}}, {"job_id": "100003009047294", "location_code": "hk", "company": "Hai Kang Life Corporation Ltd", "job_title": "Research Scientist", "description": "Responsibilities:\nPerform routine on line and finished food products inspection at various stages on the production line to implement ISO/HACCP policy.\nAssist in implementing and maintain the documentation system and quality management system.\nSupport the implementation of food safety, hygiene and quality assurance operation policies, guidelines and procedures to ensure the entire production process is in compliance with the corporate standard.\nCoordinate and participate work safety, quality assurance and hygiene procedures training to related staff.\nAssist in other ad-hoc projects as assigned.\nRequirements:\nDegree holder or above in biochemistry, Food Science or related disciplines;\nAt least 2 year laboratory working experience;\nSelf-motivated, independent and with good communication skill;\nWell-organized with good analytical skill;\nProficient in PC applications including Chinese word processing;\nGood command of spoken and written English and Chinese / Cantonese\nStaff Benefits\nMedical Insurance Coverage\nBirthday& Wedding Leave\nFree Meal & Shuttle Bus\nStaff Purchase Benefits\nAll applications and data collected will be treated in strict confidence and used exclusively for recruitment purposes.\u00a0 Only short listed candidates will be invited for interview.\u00a0 The company will retain the applications for a maximum period of 6 months and may refer suitable candidates to other vacancies within the Group.", "employment_types": ["Full Time", "Permanent"], "selling_points": ["Excellent career development prospects", "Competitive salary and welfare", "Congenial working atmosphere"], "locations": ["Shatin Area"], "categories": ["Sciences, Lab, R&D", "Life Science", "Research & Development (R&D)", "Others"], "post_time": "2022-01-14T02:47:37Z", "salary": {"currency": null, "max": null, "min": null, "period": "monthly", "term": null}, "salary_visible": false, "title_keywords": ["research scientist"], "responsibilities": ["management", "production process", "food safety", "guidelines", "policies", "compliance", "quality", "implementation", "procedures", "inspection", "coordinate", "hygiene", "maintain", "documentation", "ad-hoc projects"], "requirements": {"degrees": ["degree holder"], "majors": ["related disciplines", "food science"], "languages": ["cantonese", "english", "chinese"], "language_level": ["good command", "proficient"], "hard_skills": ["analytical skill", "chinese word processing", "pc applications"], "soft_skills": ["self-motivated", "analytical skill", "independent", "communication skill", "well-organized"], "languages_combined": [{"language": "cantonese", "language_level": ["good command"]}, {"language": "english", "language_level": ["good command"]}, {"language": "chinese", "language_level": ["good command", "proficient"]}]}, "experience_required": {"duration": ["at least 2 year"], "field": ["laboratory"]}}, {"job_id": "100003009054647", "location_code": "hk", "company": "Prenetics Limited", "job_title": "Registered Nurse", "description": "About the Job:\n\nWe have openings for Research Scientist in the area of molecular diagnostics development. He/she will perform experiments\u00a0and data analysis independently. He/she will assist in experimental design in the areas of nucleic acid extraction, PCR and quantitative PCR, isothermal amplification, hybridization and probe/primer validation.\n\n\nResponsibilities:\n\n\nConduct experiments in the assigned projects\nData analysis and trouble shooting\nReport experimental results, progress and problems to project manager\nPerform other duties as assigned\n\nRequirements:\n\n\nMSc\u00a0or above in molecular biology, microbiology\u00a0or other biological science\u00a0disciplines\nHands-on experience in molecular biology techniques including nucleic acid extraction and PCR\nResponsible, independent, career-minded and able to work under pressure\nRelevant working experience preferred\nGood command in both verbal and written Chinese and English\nIf you are passionate, driven and looking for a new and exciting opportunity within a successful and growing company, this may be the right role for you.\nPlease click \u201cApply Now\u201d to submit your application.\nAll Personal data collected will be strictly confidential and used for recruitment purpose only. Applicants who are not invited to an interview within one month from the closing date should consider their applications unsuccessful. If you are not selected, all data will be destroyed within six months from the date you applied.\u00a0", "employment_types": ["Part Time"], "selling_points": ["Registered Nurse", "HA Project / CTC Project / CHP Project", "CNTS/NS Method"], "locations": ["Quarry Bay"], "categories": ["Sciences, Lab, R&D", "Laboratory", "Life Science", "Medical Services", "Nursing"], "post_time": "2022-01-17T10:24:10Z", "salary": {"currency": null, "max": null, "min": null, "period": "hourly", "term": null}, "salary_visible": false, "title_keywords": ["registered nurse"], "responsibilities": ["data analysis", "experimental design", "perform other duties", "report"], "requirements": {"degrees": [], "majors": [], "languages": ["english", "chinese"], "language_level": ["good command"], "hard_skills": [], "soft_skills": ["passionate", "independent", "responsible", "hands-on", "driven", "work under pressure"], "languages_combined": [{"language": "english", "language_level": ["good command"]}, {"language": "chinese", "language_level": ["good command"]}]}, "experience_required": {"duration": [], "field": ["relevant working experience"]}}, {"job_id": "100003009050601", "location_code": "hk", "company": "PIT Limited", "job_title": "Assistant Technical Officer / Technical Officer (Indoor Air Quality / Environment)", "description": "Founded in 2014, Prenetics is a major global diagnostics and genetic testing company with the mission to bring health closer to millions of people globally and decentralize healthcare by making the three pillars \u2014 Prevention, Diagnostics and Personalized Care \u2014 comprehensive and accessible to anyone, at anytime and anywhere. Prenetics is led by visionary entrepreneur,\u00a0Danny Yeung, with a team of over 800 employees and operations across 9 locations, including\u00a0United Kingdom,\u00a0Hong Kong,\u00a0India,\u00a0South Africa, and\u00a0Southeast Asia. Prenetics develops consumer genetic testing and early colorectal cancer screening; provides COVID-19 testing, rapid point of care and at-home diagnostic testing and medical genetic testing.\n\nMost recently, Prenetics made\u00a0international headlines to become the first Unicorn in Hong Kong to publicly list on the Nasdaq via merger with\u00a02021 Adrian Cheng's Artisan Acquisition Corp, valuing Prenetics at approximately US $1.7b.\n\nMake a difference to the community! Let's fight COVID-19 together for Hong Kong and make Hong Kong safe again. This is a unique opportunity to make a difference to the community and to play a role to fight COVID-19 here in Hong Kong. The faster we identify, the faster we can stop the virus chain! Please note that all safety guidelines and protocols will be met to ensure safety for everyone. Join us as a Registered Nurse and make a difference today!\u00a0\n\nThis position will begin with a 6-months contract and with the potential opportunity to extend the contract to a permanent role after organizational and performance review when the initial 6-month period ends.\n\nKey Responsibilities\n\nResponsible for conducting sample collection on site by \"CNTS/NS\" method\nExecute operation training\nReview procedure to ensure all operations fulfill the guideline\n\n\n\nJob Requirements\n\nHolder of Registered Nurse License with valid practicing certificate\nFamiliar with Infection Control Guideline\nGood communication and problem-solving skills\nExperience in NS and CNTS\nImmediate availability is an advantage\nCompetitive hourly remuneration will be provided\n\n\n\nOur DNA is\u00a0P-R-E-N-E-T-I-C-S.\u00a0See what each word of our company name means:\n\nPassion\n\nYou love what you do and accomplish amazing result\nYou spread positivity, bring enthusiasm to work and inspire team members\nYou drive team toward specific goals, even when they seem unlikely or difficult\n\nResilience\n\nYou embrace changes and be able to drive through uncertainty, ambiguity and uncomfortable situations\nYou bounce back quickly from setbacks and challenges\nYou are persistent and determined to achieve the desired outcome\n\nEmpowerment\n\nYou trust others to play their positions well like an elite sports team\nYou foster a strong team spirit while encouraging others to take initiatives and risks\nYou create a space to allow team to grow and hold each other accountable\n\niNtegrity\n\nYou are trustworthy and lead by example\nYou are consistent in your message and action all the times\nYou deliver what you have promised\n\nEpic\n\nYou challenge your own comfort zone and always outperform yourself\nYou make meaningful and amazing impact to the world\nYou dare to take risks and you move fast\n\nTransparency\n\nYou are completely honest and committed to giving candid feedbacks, no matter how challenging it might be\nYou share ideas, knowledge and skills that empower others and create access to information with the wider team\nYou share wins and failures openly\n\nIngenuity\n\nYou make sound judgement and come up with solutions that are creative and smart. Copy when feasible\nYou challenge the status quo and question things that could be done differently for better. Modify the wheel if you can\u2019t change it\nYou think outside of the box and make value-based innovation\n\nCommunications\n\nYou articulate your thoughts and ideas effectively and respectfully\nYou know your audience and talk in a way they want to be told\nYou make sure communications happens, no matter where you are\n\nSelflessness\n\nYou put the needs of others before one's own and find ways in helping other to succeed\nYou focus on team wins than personal wins and share credits\nYou act in the company's best interest\nWe are Prenetics, our people make us who we are.", "employment_types": ["Full Time"], "selling_points": [], "locations": ["Tsuen Wan Area"], "categories": ["Sciences, Lab, R&D", "Environmental Science / Waste Management", "Laboratory", "Life Science"], "post_time": "2022-01-15T03:51:13Z", "salary": {"currency": null, "max": null, "min": null, "period": "monthly", "term": null}, "salary_visible": false, "title_keywords": ["technical officer", "assistant technical officer"], "responsibilities": ["operations", "review"], "requirements": {"degrees": ["certificate"], "majors": [], "languages": [], "language_level": [], "hard_skills": ["no", "r", "word", "make", "c", "problem-solving skills", "focus"], "soft_skills": ["team spirit", "determined", "trustworthy", "persistent", "articulate", "integrity", "accountable", "communication", "committed", "honest", "problem-solving skills", "focus", "creative"], "languages_combined": []}, "experience_required": {"duration": [], "field": []}}, {"job_id": "100003009052399", "location_code": "hk", "company": "Tegent Scientific Limited", "job_title": "Product Specialist", "description": "\nDuties:\n\n\nMonitor and manage the process of testing procedures, including reception, handling, processing, storage and testing of human blood according to the Standard Operation Procedure (SOP)\nEstablish new and review current SOP\nReview and approve quality control data for testing\nReview and approve laboratory report\nParticipate in-house and external training as required\nOther ad-hoc duties are also required\n\nRequirements:\n\n\nValid Medical Laboratory Technologist Part I practicing cert issued by the HKMLT Board\nBachelor Degree or Higher Technical Certificate (HTC) in Biomedical Science, Medical Laboratory Sciences other related disciplines\nExperience in genetic/DNA analysis, including DNA extraction, sequencing, PCR etc. is preferable.\nStrong sense of responsibility\nMust be a good team worker with excellent communication skills as well as be able to work independently\nAble to communicate in Mandarin and Cantonese", "employment_types": ["Full Time"], "selling_points": ["#strategic sales & business development", "#bio, biochem, life science, an-chem", "#looking for talent & maker"], "locations": ["Kwun Tong"], "categories": ["Sales, CS & Business Devpt", "Business Development", "Sciences, Lab, R&D", "Chemical", "Life Science"], "post_time": "2022-01-17T02:57:30Z", "salary": {"currency": null, "max": null, "min": null, "period": "monthly", "term": null}, "salary_visible": false, "title_keywords": ["product specialist"], "responsibilities": ["data", "review", "monitor", "procedures", "testing", "quality control", "ad-hoc duties", "report"], "requirements": {"degrees": ["certificate", "degree", "bachelor"], "majors": ["biomedical science", "related disciplines"], "languages": ["cantonese", "mandarin"], "language_level": [], "hard_skills": ["analysis"], "soft_skills": ["communication skills", "work independently", "sense of responsibility"], "languages_combined": [{"language": "cantonese", "language_level": []}, {"language": "mandarin", "language_level": []}]}, "experience_required": {"duration": [], "field": []}}, {"job_id": "100003009052334", "location_code": "hk", "company": "Hai Kang Life Corporation Ltd", "job_title": "AI Research Engineer", "description": "Opportunities\n\nYou will be working in a uprising TCM related business of a large international group.\u00a0You will be involved mainly in Regulatory Affairs related works. \u00a0\n\nYou will need to work independently, and executing not only the RA related work, also need to execute administrative tasks such as maintain office filing system, execute and follow up on the instruction given by the superiors. You will build up strength in the competitive environment of both local and global pharmaceutical industries.\n\nAbout the job:\n\nWork closely with internal and external partners as required,\nCommunicate, initiate, and facilitate the R&D collaboration with third parties, if required,\nPerform the preparation of the new drug application, and handle works related to it,\n\nMaintains file system for different projects, also including administrative files,\u00a0\n\nAbout the talent:\n\nBachelor Degree or above in health-related science, Medicine, Pharmacy, Biological Science or other Medical related field\nAt least 2 years solid experience in pharmaceutical regulatory affairs related area is highly preferred,\nAble to work independently and under pressure, adaptability and attention to detail with a strong orientation, well-organized and responsible\nExcellent communication and presentation skills, positive thinking, high team spirit,\nGood command in spoken and written Chinese and English\nCandidate with less experience will be considered as RA Assistant, fresh graduates are welcomed to apply with confidence", "employment_types": ["Full Time", "Permanent"], "selling_points": ["AI research engineer", "Competitive Salary", "Comfortable work environment"], "locations": ["Shatin Area"], "categories": ["Information Technology (IT)", "Software Development", "Sciences, Lab, R&D", "Life Science"], "post_time": "2022-01-17T02:47:58Z", "salary": {"currency": null, "max": null, "min": null, "period": "monthly", "term": null}, "salary_visible": false, "title_keywords": ["engineer"], "responsibilities": ["administrative tasks", "maintain", "executing", "communication"], "requirements": {"degrees": ["degree or above", "bachelor"], "majors": ["science", "biological science"], "languages": ["english", "chinese"], "language_level": ["good command"], "hard_skills": ["r&d"], "soft_skills": ["work independently", "team spirit", "under pressure", "confidence", "responsible", "well-organized", "positive thinking", "communication", "presentation skills", "adaptability", "attention to detail"], "languages_combined": [{"language": "english", "language_level": ["good command"]}, {"language": "chinese", "language_level": ["good command"]}]}, "experience_required": {"duration": ["at least 2 years"], "field": ["pharmaceutical", "regulatory affairs", "related"]}}, {"job_id": "100003009052107", "location_code": "hk", "company": "Leader Enterprise Limited", "job_title": "Clinical Embryologist (Trainee/Experienced)", "description": "Job Description\n\nExplore on new technologies to develop and support on software projects(Medical device)\nImplement AI algorithms and prototypes to test new ideas\nDeploy machine learning models and APIs to the production environment\nSupport full software lifecycle including design, development, debugging, and testing\nCoordinate resources to carry out R&D tasks against the plans and complete the projects as scheduled with high standard\nBuild up and maintain a good network with other development departments so as to acquire new technologies and create synergy\nQualifications\n\nApplicants should possess a Bachelor degree in Computer Science, Computer Engineering, Information Engineering or related disciplines, preferably in artificial intelligence and deep learning. Other qualifications may include:-\n\nKnowledge/experience with modern operating systems.\nTechnical proficiency in programming languages: Python or C/C++\u00a0 \u00a0 \u00a0 \u00a0\u00a0\nProven experience in working with large databases and relational databases (e.g., SQL/ MongoDB/MariaDB )\nPassionate, mature, self-motivated, and able to work independently and meet tight deadlines\nGood command of both spoken and written English, Chinese (including Putonghua) preferred", "employment_types": ["Full Time"], "selling_points": ["Degree in Science", "Embryologist", "salary"], "locations": ["Tsim Sha Tsui"], "categories": ["Sciences, Lab, R&D", "Laboratory", "Life Science", "Others"], "post_time": "2022-01-17T02:10:21Z", "salary": {"currency": null, "max": null, "min": null, "period": "monthly", "term": null}, "salary_visible": false, "title_keywords": ["trainee"], "responsibilities": ["ideas", "software", "design", "develop", "testing", "coordinate", "maintain", "databases", "deploy", "plans", "operating systems"], "requirements": {"degrees": ["degree", "bachelor"], "majors": ["related disciplines", "computer engineering", "engineering", "computer science"], "languages": ["putonghua", "english", "chinese"], "language_level": ["good command"], "hard_skills": ["r&d", "c++", "ai", "sql", "c", "programming", "databases", "python"], "soft_skills": ["passionate", "self-motivated", "work independently", "meet tight deadlines", "deep", "mature", "learning"], "languages_combined": [{"language": "putonghua", "language_level": ["good command"]}, {"language": "english", "language_level": ["good command"]}, {"language": "chinese", "language_level": ["good command"]}]}, "experience_required": {"duration": [], "field": []}}, {"job_id": "100003009047606", "location_code": "hk", "company": "DNA - Tech Limited", "job_title": "R&D Project Manager", "description": "Job Description\n\nPerform on-site Indoor Air Quality inspection;\n\nConduct sampling and handle related tasks;\n\nTraining will be provided;\n\nPerform any other ad hoc tasks assigned.\n\nRequirements\n\nHigher Diploma or above in any discipline;\n\nResponsible, hardworking with positive working attitude;\n\n1 year or more Indoor Air Quality experiences are advantages;\n\nFresh graduates with proactive attitude are also welcomed;\n\nImmediately available is highly preferred;\n\nTravel to China and Overseas is required;", "employment_types": ["Full Time", "Permanent"], "selling_points": ["Competitive Salary", "5-day work a week", "IVD"], "locations": ["Shatin Area"], "categories": ["Sciences, Lab, R&D", "Life Science", "Research & Development (R&D)"], "post_time": "2022-01-14T03:33:45Z", "salary": {"currency": null, "max": null, "min": null, "period": "monthly", "term": null}, "salary_visible": false, "title_keywords": ["project manager"], "responsibilities": ["ad hoc tasks", "quality", "inspection"], "requirements": {"degrees": ["higher diploma or above"], "majors": [], "languages": [], "language_level": [], "hard_skills": [], "soft_skills": ["positive working attitude", "hardworking", "proactive", "responsible"], "languages_combined": []}, "experience_required": {"duration": ["1 year"], "field": []}}, {"job_id": "100003009047914", "location_code": "hk", "company": "The University of Hong Kong", "job_title": "Post-doctoral Fellow in Philosophy(508783)", "description": "This is a full time position. The candidate will be required to perform all IVF techniques and procedures including:\n\nSperm preparation\nOocyte Pick up\nICSI/cIVF\nGamete/embryo cryopreservation\nEmbryo transfer\nEmbryo biopsy\nJob requirement:\n\nDegree or above in Science\u00a0\nParticipation on some weekends, public holidays and out of hours rota will be required\nSalary:\n\nCommensurate with experience\nDevelopment opportunities i.e.: overseas training will be provided", "employment_types": ["Full Time"], "selling_points": ["participate actively in the work of AI&H.", "submit project proposals", "provide a plan for a two-year research project"], "locations": ["Pok Fu Lam"], "categories": ["Sciences, Lab, R&D", "Life Science", "Research & Development (R&D)", "Others"], "post_time": "2022-01-14T04:14:13Z", "salary": {"currency": null, "max": null, "min": null, "period": "monthly", "term": null}, "salary_visible": false, "title_keywords": [], "responsibilities": ["procedures"], "requirements": {"degrees": ["degree or above"], "majors": ["science"], "languages": [], "language_level": [], "hard_skills": [], "soft_skills": [], "languages_combined": []}, "experience_required": {"duration": [], "field": []}}, {"job_id": "100003009047622", "location_code": "hk", "company": "DNA - Tech Limited", "job_title": "R&D Technician", "description": "About the Job:\nWe have openings for Project Managers who will lead projects on different aspects related to the development of an IVD platform to facilitate guided treatment. The focuses of these projects include:\n1. Capture probe design and validation\n2. Pathogenic nucleic acid extraction from clinical samples\n3. Optimization of target-probe hybridization\n\nResponsibilities\nCarry out method development, optimization and validation under the supervision of R&D director\u00a0\nLead the project and be responsible for its timely completion\nMaintain effective communication with management\nPresent research reports that communicate the research ideas and the research data\u00a0\nManage ad hoc projects as assigned\nRequirements:\nPhD or MSc Degree with training in molecular biology, microbiology, analytical chemistry, electrochemistry, or biotech-related science studies;\nAt least 1 year of experience in research project management with demonstrated ability to design experiments\nAbility to prepare clear, succinct, and organized scientific reports\nSelf-motivated and passionate in contributing to the betterment of human life\nEnjoy problem-solving and critical thinking with an inquisitive mindset\nCommitted; team-oriented; good communication and leaderships skills\nProficient in English and Chinese languages\nIf you are passionate, driven and looking for a new and exciting opportunity within a successful and growing company, this may be the right role for you.\nPlease click \u201cApply Now\u201d to submit your application.\nAll Personal data collected will be strictly confidential and used for recruitment purpose only. Applicants who are not invited to an interview within one month from the closing date should consider their applications unsuccessful. If you are not selected, all data will be destroyed within six months from the date you applied.\u00a0", "employment_types": ["Full Time", "Permanent"], "selling_points": ["In vitro diagnosis system (IVD)", "Competitive salary", "DNA microchips"], "locations": ["Shatin Area"], "categories": ["Sciences, Lab, R&D", "Laboratory", "Life Science", "Research & Development (R&D)"], "post_time": "2022-01-14T03:36:04Z", "salary": {"currency": null, "max": null, "min": null, "period": "monthly", "term": null}, "salary_visible": false, "title_keywords": ["r&d technician"], "responsibilities": ["management", "ideas", "data", "design", "communication", "maintain", "reports", "ad hoc projects"], "requirements": {"degrees": ["degree"], "majors": ["molecular biology", "science", "microbiology", "analytical chemistry"], "languages": ["english", "chinese"], "language_level": ["proficient"], "hard_skills": ["project management", "problem-solving"], "soft_skills": ["passionate", "organized", "self-motivated", "problem-solving", "clear", "project management", "committed", "communication", "driven"], "languages_combined": [{"language": "english", "language_level": ["proficient"]}, {"language": "chinese", "language_level": ["proficient"]}]}, "experience_required": {"duration": ["at least 1 year"], "field": ["project management", "research", "design"]}}, {"job_id": "100003009049630", "location_code": "hk", "company": "New Beta Innovation Limited", "job_title": "Manager - R&D (Protein Purification Development/ Scale-up)", "description": "Responsibilities\n\nParticipate in BioRadar related R&D projects;\nPerform laboratory tests and data analysis independently by strictly following the standard operation procedures. Conduct experiments including nucleic acid extraction, PCR and quantitative PCR, isothermal amplification, DNA cloning, bacterial culture, bio-chip examination, etc.. Complete the research tasks assigned by supervisor;\nReport experimental results, progressions and arising problems to supervisor routinely;\nCarry out method development, optimization and validation under the supervision of R&D director;\nLab organizational duties such as sourcing of laboratory consumables, preparation of reagents and buffers, calibration and daily maintenance of laboratory instrumentation \u00a0related documentation.\nPerform other duties as assigned.\n\nRequirements\n\nHigher Diploma\u00a0\u00a0or above in molecular biology, microbiology,\u00a0biochemistry,\u00a0or other biotech-related disciplines;\nHands-on experience in basic \u00a0molecular bio-techniques including nucleic acid extraction and PCR\nMature, responsible, independent, career-minded and able to work under pressure;\nFamiliar with GLP or ISO regulations is a plus;Good command in both verbal and written Chinese and English\nRelevant working experience preferred;\n\nIf you are passionate, driven and looking for a new and exciting opportunity within a successful and growing company, this may be the right role for you.\n\nPlease click \u201cApply Now\u201d to submit your application.\n\nAll Personal data collected will be strictly confidential and used for recruitment purpose only. Applicants who are not invited to an interview within one month from the closing date should consider their applications unsuccessful. If you are not selected, all data will be destroyed within six months from the date you applied.\u00a0", "employment_types": ["Full Time", "Permanent"], "selling_points": ["Research Job in Professional firm", "Attractive remuneration and benefits", "5 days work and location closed to MTR"], "locations": ["Kowloon Bay"], "categories": ["Sciences, Lab, R&D", "Life Science", "Medical Services", "Pharmaceutical", "Research & Development (R&D)"], "post_time": "2022-01-14T08:59:48Z", "salary": {"currency": null, "max": null, "min": null, "period": "monthly", "term": null}, "salary_visible": false, "title_keywords": ["manager"], "responsibilities": ["perform other duties", "related documentation", "maintenance", "procedures", "data analysis", "report"], "requirements": {"degrees": ["diploma"], "majors": ["molecular biology", "related disciplines", "microbiology"], "languages": ["english", "chinese"], "language_level": ["good command"], "hard_skills": ["plus", "basic"], "soft_skills": ["passionate", "independent", "responsible", "mature", "hands-on", "driven", "work under pressure"], "languages_combined": [{"language": "english", "language_level": ["good command"]}, {"language": "chinese", "language_level": ["good command"]}]}, "experience_required": {"duration": [], "field": ["relevant working experience"]}}, {"job_id": "100003009046086", "location_code": "hk", "company": "The University of Hong Kong", "job_title": "Professor in Psychology(509150)", "description": "Job Duties:\n\nParticipate in manufacturing & quality control of In-vitro diagnosis reagents;\nMonitor and review of manufacturing and quality control process;\nCoordinate with multi-functional teams for new product launching;\nPerform materials sourcing and quality control of incoming materials;\nReview and update standard operation procedure and documents;\nProvide technical training to ensure strictly follows to the approved SOP;\nAssist in QMS accreditation and product registration;\nPlan and perform stability study of new products;\nMonitor and maintenance production facility and equipment.\n\nRequirements:\n\nPostgraduate, degree or diploma holder in life science or related discipline with knowledge in molecular genetics / molecular biology;\n1 year of manufacturing experience in pharmaceutical, medical device or health care products;\nExperienced in PCR or molecular lab is preferred;\nExperience in handling equipment maintenance and calibration work;\nKnowledge in ISO 9001, ISO 13485 or GMP / six sigma is an advantage;\nGood written and verbal communication skills;\nGood problem solving skill and able to work under pressure;\nTeam player attitude, proactive and self-motivated.\n\nIf you are passionate, driven and looking for a new and exciting opportunity within a successful and growing company, this may be the right role for you.\n\nPlease click \u201cApply Now\u201d to submit your application.\n\nFor more info, please visit our web page at\u00a0http://www.diagcorlifescience.com/\n\nWe will only consider applicants who apply directly to our firm and not through recruitment agencies. All applications will be treated in strict confidence. Personal data collected will be used for recruitment purposes only. Applicants who do not hear from us within 4 weeks may consider their applications unsuccessful and the applications will be destroyed within 6", "employment_types": ["Full Time"], "selling_points": [], "locations": ["Pok Fu Lam"], "categories": ["Education", "Lecturer / Professor", "Others", "Sciences, Lab, R&D", "Life Science"], "post_time": "2022-01-13T09:34:56Z", "salary": {"currency": null, "max": null, "min": null, "period": "monthly", "term": null}, "salary_visible": false, "title_keywords": [], "responsibilities": ["maintenance", "review", "teams", "monitor", "coordinate with", "quality control", "plan"], "requirements": {"degrees": ["diploma holder", "degree"], "majors": ["molecular biology", "science", "genetics"], "languages": [], "language_level": [], "hard_skills": ["problem solving", "six sigma", "web", "maintenance"], "soft_skills": ["passionate", "communication skills", "self-motivated", "confidence", "team player", "problem solving skill", "proactive", "driven", "work under pressure"], "languages_combined": []}, "experience_required": {"duration": ["1 year"], "field": ["manufacturing", "maintenance", "medical device", "pharmaceutical", "health care"]}}, {"job_id": "100003009050339", "location_code": "hk", "company": "Hong Kong Science & Technology Parks Corporation", "job_title": "Manager/Assistant Manager (Clinical Translation Catalyst), Institute for Translational Research", "description": "Applications are invited for appointment as\u00a0Professor in Psychology in the Department of Psychology\u00a0(Ref.:509150), to commence on July 1, 2022 or as soon as possible thereafter. It is expected that the appointment as Professor will be made on tenure terms, although it may be made on a three-year fixed-term basis, with the possibility of renewal and consideration for tenure upon satisfactory completion of a second three-year fixed-term contract.\n\nThe Department of Psychology was founded in 1968 and was the first department of psychology in Hong Kong.\u00a0 The Department is represented by 20 faculty members with different areas of expertise, including clinical psychology/neuropsychology, cognitive psychology/cognitive science, neuroscience, educational and developmental psychology, as well as social/health psychology.\u00a0 Our faculty members engage in a broad range of research across the discipline, from basic human neuroscience to educational policy, as these different areas of research inform and complement each other.\u00a0 This unique research environment enables the integration of different disciplinary areas into cohesive and empirically sound research programmes that are translated into measurable societal impact.\u00a0 We also support open science and strive for high integrity, trustworthy, replicable and reproducible research. We value diverse research methodologies. Further information about the Department can be obtained at\u00a0https://www.psychology.hku.hk.\n\nApplicants should possess a Ph.D. degree in Psychology or related fields, demonstrated evidence of international standing in the field and a proven track record of impactful research, publications, external grants and leadership.\u00a0 The appointee is expected to maintain an active research programme, and be responsible for teaching courses and supervising students at both graduate and undergraduate levels, as well as contributing to the administration of academic programmes.\u00a0 The appointee may be asked to provide leadership across the Mental Wellness research cluster which is one of the areas of focus in the Faculty of Social Sciences.\n\nA highly competitive salary commensurate with qualifications and experience will be offered, in addition to annual leave and medical benefits.\u00a0 At current rates, salaries tax does not exceed 15% of gross income.\u00a0 The appointment will attract a contract-end gratuity and University contribution to a retirement benefits scheme, totalling up to 15% of basic salary.\u00a0 Housing benefits will be provided as applicable.\n\nThe University only accepts online application for the above post.\u00a0 Applicants should apply online at the University\u2019s careers site (https://jobs.hku.hk) and upload (1) an up-to-date CV, (2) a research statement, (3) a teaching statement, and (4) state the contact information of three referees on the online application form.\u00a0At least one of the referees should be able to comment on your research/teaching ability and your contribution to research/teaching in your department, while the remaining two should have knowledge of your recent academic or employment experience. Enquiries about the post can be sent to the Head of Department, Dr Janet Hsiao [via APPLY NOW] \u00a0or the Chair of Selection Committee [via APPLY NOW] . Review of applications will start as soon as possible and continue until\u00a0January 15, 2022, or until the post is filled, whichever is earlier\n\n\u6709\u610f\u7533\u8acb\u8005\u8acb \u6309 APPLY NOW\u7533\u8acb\n\n", "employment_types": ["Full Time"], "selling_points": [], "locations": ["Shatin Area"], "categories": ["Sciences, Lab, R&D", "Life Science", "Medical Services", "Others", "Pharmaceutical"], "post_time": "2022-01-14T10:09:49Z", "salary": {"currency": null, "max": null, "min": null, "period": "monthly", "term": null}, "salary_visible": false, "title_keywords": ["assistant manager", "manager"], "responsibilities": ["supervising", "maintain", "administration"], "requirements": {"degrees": ["degree"], "majors": ["psychology"], "languages": [], "language_level": [], "hard_skills": ["integration", "inform", "focus", "basic"], "soft_skills": ["trustworthy", "responsible", "integrity", "cohesive", "unique", "diverse", "focus", "active", "leadership"], "languages_combined": []}, "experience_required": {"duration": [], "field": []}}, {"job_id": "100003009047624", "location_code": "hk", "company": "The University of Hong Kong", "job_title": "Post-doctoral Fellow (508632)", "description": "[JDB/M_AMCTCITR/220114]\n\n\n\nResponsibilities:\n\nSupport the management of the new Clinical Translational Catalyst initiative which provides funding and regulatory support for biotech companies to catalyze the translation of their pipeline from pre-clinical to clinical stage;\nEstablish and maintain collaborative relationships with key stakeholders in the clinical translational path including Principal Investigators for Clinical Studies, Regulatory Professionals, Contract Research Organizations, Contract Manufacturing Organizations, and domain experts focusing in the fields of therapeutics and medical devices;\nImplement and organize the overall administrative process for admission, assessment panel meeting and disbursement;\nPromote the new HKSTP initiative within and outside of Hong Kong Science Park to attract qualified companies to participate in the initiative;\nInteract with partner companies to understand their business/technical requirements and develop effective solutions;\nReview and update Standard Operating Procedures, Programme Guide, protocols, flow charts, etc.;\nWork collaboratively with other ITR teams and HKSTP organizational units; and\nPerform any other duties as assigned by supervisors and management.\n\n\u00a0Requirements:\n\nMaster degree in Pharmacology, Pharmaceutical Sciences, Pharmacy, Biomedical Sciences, Biochemistry, Biology, Biomedical Engineering and related clinical science or medicine disciplines;\u00a0 A Clinical or PhD degree would be an advantage;\nMinimum of 8 years of experience in R&D of therapeutics or medical devices with focus in IND or PMA regulatory submissions (e.g. FDA, NMPA), GMP manufacturing and QC/QA;\nExperience in regulatory submission, clinical trial and marketing approval of small molecules, biologics, regenerative medicine, gene therapy or medical devices would be a plus;\nGood analytical, interpersonal, presentation and communication skills;\nSelf-driven and work effectively in a highly collaborative environment;\nAbility to manage up, down and across different functional teams will be crucial;\nProficient in MS office (Words, Excel and PowerPoint); and\nProficient in both written and spoken English and Chinese (Putonghua and Cantonese).\nCandidate with higher qualification but less experience will also be considered.\n\n[This position is open for referral by Recruitment agencies. The profile should be sent to our HR email address\u00a0a g e n c y c v @ h k s t p . o r g ]\n\nWe offer market competitive compensation, 5-day work week and generous benefits including medical and life insurance.\u00a0 To apply, please send your full resume with current and expected salary to the Human Resources & Office Administration Department, Hong Kong Science and Technology Parks Corporation, 5/F, Building 5E, 5 Science Park East Avenue, Hong Kong Science Park, Hong Kong or, by email on or before 27 January 2022. Please quote the reference number on the email subject/envelope and the application letter.\u00a0\n\n\u00a0Personal data provided will be treated in strict confidence and used for recruitment purpose only. All personal data collected will be used strictly in accordance with employer\u2019s personal data policies, you can access to HKSTP\u2019s Personal Information Collection Statement at\u00a0https://www.hkstp.org/hkstp_web/en/hkstp/personal-information-collection-statement-recruitment\u00a0\n\nApplicants not invited for interview within four weeks after application deadline may consider their applications unsuccessful. Personal data of unsuccessful applicants will be retained for a maximum of two years.\u00a0\n\nwww.hkstp.org", "employment_types": ["Full Time"], "selling_points": [], "locations": ["Pok Fu Lam"], "categories": ["Sciences, Lab, R&D", "Laboratory", "Life Science", "Research & Development (R&D)"], "post_time": "2022-01-14T03:36:28Z", "salary": {"currency": null, "max": null, "min": null, "period": "monthly", "term": null}, "salary_visible": false, "title_keywords": [], "responsibilities": ["any other duties", "management", "review", "procedures", "teams", "develop", "maintain"], "requirements": {"degrees": ["degree", "master degree"], "majors": ["pharmacology", "biomedical engineering", "biology", "science"], "languages": ["cantonese", "putonghua", "english", "chinese"], "language_level": ["proficient"], "hard_skills": ["r&d", "small", "plus", "excel", "words", "powerpoint", "c", "r", "focus", "ms office"], "soft_skills": ["work effectively", "communication skills", "driven", "collaborative", "focus", "interpersonal", "presentation"], "languages_combined": [{"language": "cantonese", "language_level": []}, {"language": "putonghua", "language_level": []}, {"language": "english", "language_level": ["proficient"]}, {"language": "chinese", "language_level": ["proficient"]}]}, "experience_required": {"duration": ["minimum of 8 years"], "field": ["marketing", "clinical", "medical"]}}, {"job_id": "100003009042351", "location_code": "hk", "company": "DiagCor Life Science Limited", "job_title": "Scientist/ Research Scientist for Product development", "description": "Applications are invited for appointment as\u00a0Post-doctoral Fellow in the Department of Pathology\u00a0(Ref.: 508632), to commence as soon as possible for two to three years, with the possibility of renewal subject to funding availability and satisfactory performance.\n\nApplicants should have a Ph.D. degree in cancer/molecular/cellular biology or related disciplines, with research experience in genomics data and bioinformatics. They should demonstrate a strong passion for scientific and clinical research and huge motivation to make contributions to patients with significant medical needs. They should have a good command of English, good interpersonal and communication skills, self-initiative, knowledge of research-related computer software, and the ability to work independently. Preference will be given to those with experience in cell culture, transfection,\u00a0in vitro/in vivo\u00a0functional studying of signal transduction pathways, flow cytometry analysis, preclinical drug testing, and animal handling. A good publication record and grant application experience would also be advantages.\n\nThe appointee will join a research group with opportunities to conduct projects on female genital cancers supported by major research grants. A main focus of his/her work will be on the analysis and validation of genomics data, while maintaining the smooth running of a research laboratory.\n\nA highly competitive salary commensurate with qualifications and experience will be offered, in addition to annual leave and medical benefits.\n\nThe University only accepts online applications for the above post.\u00a0 Applicants should apply online and upload an up-to-date C.V. together with a research publication list. Review of applications will start on October 30, 2021 and continue until\u00a0January 31, 2022, or until the post is filled, whichever is earlier.\n\nInterested candidates, please click APPLY NOW \u00a0to apply.", "employment_types": ["Full Time", "Permanent"], "selling_points": [], "locations": ["Kowloon Bay"], "categories": ["Sciences, Lab, R&D", "Life Science", "Manufacturing", "Product Development / Management", "Research & Development (R&D)"], "post_time": "2022-01-12T07:09:06Z", "salary": {"currency": null, "max": null, "min": null, "period": "monthly", "term": null}, "salary_visible": false, "title_keywords": ["product development", "scientist", "research scientist"], "responsibilities": ["software", "maintaining", "data", "analysis", "testing", "communication", "publication"], "requirements": {"degrees": ["degree"], "majors": ["related disciplines", "biology"], "languages": ["english"], "language_level": ["good command", "good"], "hard_skills": ["analysis", "animal handling", "make", "focus", "signal"], "soft_skills": ["communication skills", "work independently", "passion for", "self-initiative", "smooth", "focus", "interpersonal"], "languages_combined": [{"language": "english", "language_level": ["good command", "good"]}]}, "experience_required": {"duration": [], "field": ["related", "research", "testing"]}}, {"job_id": "100003009035642", "location_code": "hk", "company": "HKG Epitherapeutics Limited", "job_title": "Research Assistant/Researcher", "description": "Job Duties:\n\nParticipate in a team for MDx product development and advancement;\nResponsible for planning, organizing and overseeing process or production trial and scale up, generating ideas for new products and researching feasibility in terms of profitability, resource availability and compliance with regulations;\nRecording and analyzing data, investigating and testing new equipment, technology transfer, documentation and filing;\nProvide technical support to cross-functional team for product quality control, validation and evaluation;\nLiaise with engineering, research, technical and/or production staff, vendors, academic researchers and external collaborators to coordinate research or commercialization projects;\nResponsible for writing and reading technical papers, reports, reviews and specifications, patent and grant applications; and\nReport findings and project update at group and departmental meetings.\n\n\u00a0Requirements:\n\nMPhil/Ph.D./Postdoc in Molecular Biology, Microbiology, Biomedical Engineering, or relevant disciplines;\nProficient and meticulous in Molecular techniques are preferable;\nHands-on experience in clinical research/ healthcare product, medical device or Point-Of-Care systems development, CE, FDA, or China NMPA application, ISO 9001 and ISO13485 process management will be beneficial;\nStrong team spirit, interpersonal and communication skills, good English writing and reading ability; and\nProactive, creative, positive attitude, result-oriented, capable of multi-tasking along with problem-solving expertise and capable of independent in-depth research.\n\nIf you are passionate, driven and looking for a new and exciting opportunity within a successful and growing company, this may be the right role for you.\n\nPlease click \u201cApply Now\u201d to submit your application.\n\nFor more info, please visit our web page at\u00a0http://www.diagcorlifescience.com/\n\n\nWe will only consider applicants who apply directly to our firm and not through recruitment agencies. All applications will be treated in strict confidence. Personal data collected will be used for recruitment purposes only. Applicants who do not hear from us within 4 weeks may consider their applications unsuccessful and the applications will be destroyed within 6 months.", "employment_types": ["Full Time"], "selling_points": [], "locations": ["Shatin Area"], "categories": ["Sciences, Lab, R&D", "Life Science"], "post_time": "2022-01-10T16:52:42Z", "salary": {"currency": null, "max": null, "min": null, "period": null, "term": null}, "salary_visible": false, "title_keywords": ["researcher", "research assistant"], "responsibilities": ["regulations", "ideas", "data", "technical support", "compliance", "testing", "coordinate", "liaise with", "commercialization", "specifications", "reports", "departmental meetings", "quality control", "evaluation", "documentation", "report", "planning"], "requirements": {"degrees": [], "majors": [], "languages": ["english"], "language_level": ["good"], "hard_skills": ["problem-solving", "web"], "soft_skills": ["result-oriented", "communication skills", "meticulous", "team spirit", "independent", "creative", "capable", "passionate", "confidence", "problem-solving", "driven", "positive attitude", "hands-on", "multi-tasking", "proactive", "interpersonal"], "languages_combined": [{"language": "english", "language_level": ["good"]}]}, "experience_required": {"duration": [], "field": ["healthcare", "management", "research", "development", "medical device", "clinical"]}}, {"job_id": "100003009051018", "location_code": "hk", "company": "ATCG Limited", "job_title": "Product Manager (Life Science Labs)", "description": "Job Description\n\n\u00a0We are looking for talented researcher who will be involved in performing experiments to optimize sets of DNA methylation markers for diagnosing diseases. The job will involve experimental design, optimization of procedures, performing and reporting experiments by following lab standard operating procedures under the supervision of the lab manager. The successful candidate will be a graduate who has completed a Bachelor degree or higher, have good knowledge of molecular biology techniques, have desire to learn new methods and is excited about developing molecular-based new products.\n\n\u00a0Responsibilities\n\nPerform experiments using molecular biology tools and next generation sequencing techniques under the regulation of lab standard operating procedures\nConduct experimental design;\nDocument experiment results and methodologies properly following standard operating procedures;\nMaintain lab equipment, lab area and supplies in a neat and professional manner;\nReport experiments to the lab manager.\n\n\u00a0Qualifications\n\n\u00a0Bachelor degree or above in molecular biology, biochemistry or related fields\nExperience in DNA and RNA preparations, conducting PCR and primer optimization is preferred\nKnowledge of sequencing techniques is desirable\nSkills in organization and time management\nAttention to details and analytical skills\nAble to work in a team under the guidance of senior staffs\n\nWe offer competitive salary, provident fund, medical package and 5-day work week. Candidates who are interested in the position should submit their full resume and cover letter.\n\nAll Personal data collected will be used for recruitment purpose only.", "employment_types": ["Full Time"], "selling_points": [], "locations": ["Shatin Area"], "categories": ["Sciences, Lab, R&D", "Laboratory", "Life Science", "Sales, CS & Business Devpt", "Technical Sales / Sales Engineer"], "post_time": "2022-01-15T01:10:05Z", "salary": {"currency": null, "max": null, "min": null, "period": "monthly", "term": null}, "salary_visible": false, "title_keywords": ["product manager"], "responsibilities": ["reporting", "management", "guidance", "procedures", "developing", "professional manner", "maintain", "experimental design", "report"], "requirements": {"degrees": ["degree or above", "degree", "bachelor"], "majors": ["molecular biology"], "languages": [], "language_level": [], "hard_skills": ["analytical skills"], "soft_skills": ["time management", "attention to details", "analytical skills"], "languages_combined": []}, "experience_required": {"duration": [], "field": []}}, {"job_id": "100003009050969", "location_code": "hk", "company": "Hong Kong Science & Technology Parks Corporation", "job_title": "Senior Officer, Biomedical Technology Support Centre [JDB/SOBMTSC/220114]", "description": "Applications are invited for appointment as\u00a0Post-doctoral Fellow in Philosophy in the Faculty of Arts\u00a0(Ref.: 508783), to commence as soon as possible for a period of two years.\n\nApplicants should have completed a Ph.D. degree in relevant fields of philosophy or cognitive science by the time of appointment. The position is open to all areas of specialization, but applicants will need to provide a plan for a two-year research project related to the philosophy of AI or philosophy of technology more generally.\n\nThis appointment will be affiliated with Chair Professor Herman Cappelen\u2019s new research group: AI&Humanity-Lab@HKU (AI&H).\u00a0 The Post-doctoral Fellow is expected to participate actively in the work of AI&H. Applicants should submit project proposals (max. 5 pages) that falls within the project\u2019s remit, including but not limited to: explainable and interpretable AI, the ethics and politics of AI, AI governance, algorithmic bias, the alignment problem, AI risk, AI and the extended mind thesis, the role of AI in online communication, and the metaphysics of virtual reality.\n\nInformation about the Faculty and the Department of Philosophy can be found at\u00a0https://arts.hku.hk/\u00a0and\u00a0https://philosophy.hku.hk/dept/. Enquiries about the duties of the post can be directed to Chair Professor Herman Cappelen\u00a0[via APPLY NOW]\n\nA highly competitive salary commensurate with qualifications and experience will be offered, in addition to annual leave and medical benefits.\u00a0 At current rates, salaries tax does not exceed 15% of gross income.\n\nThe University only accepts online application for the above post. Applicants should apply online and upload a letter of application, an up-to-date C.V., a writing sample of scholarly work, research proposal (max. 5 pages), and provide (at least) two referees\u2019 names and contact details.\u00a0\u00a0Shortlisted\u00a0applicants will be requested to arrange for at least two references, including one from their Ph.D. supervisor/advisor.\u00a0 Review of applications will start as soon as possible and continue until\u00a0May 31, 2022\u00a0or until the post is filled, whichever is earlier.\n\n\u6709\u610f\u7533\u8acb\u8005\u8acb \u6309 APPLY NOW\u7533\u8acb\n\n", "employment_types": ["Full Time"], "selling_points": [], "locations": ["Shatin Area"], "categories": ["Sciences, Lab, R&D", "Chemical", "Laboratory", "Life Science"], "post_time": "2022-01-14T12:15:19Z", "salary": {"currency": null, "max": null, "min": null, "period": "monthly", "term": null}, "salary_visible": false, "title_keywords": ["senior officer"], "responsibilities": ["communication", "plan"], "requirements": {"degrees": ["degree"], "majors": ["science"], "languages": [], "language_level": [], "hard_skills": ["max", "ai"], "soft_skills": ["communication"], "languages_combined": []}, "experience_required": {"duration": [], "field": []}}, {"job_id": "100003009045536", "location_code": "hk", "company": "Tegent Scientific Limited", "job_title": "Business Development Officer (Laboratory)", "description": "ATCG Limited is a venture set-up to better serve local biological sciences by providing novel solutions, services, consultations to our clients. Come join us if you are:\n\n\u00a0\u00a0\u00a0\u00a0\u00a0\u00a0\u00a0\u00a0\u00a0\u00a0 Interested in the latest development in Biotechnology\n\u00a0\u00a0\u00a0\u00a0\u00a0\u00a0\u00a0\u00a0\u00a0\u00a0 Want to connect with Pioneers of the Life Science field\n\u00a0\u00a0\u00a0\u00a0\u00a0\u00a0\u00a0\u00a0\u00a0\u00a0 Provide Innovative solutions to researchers\n\nProduct Managers are in charge of discovering, overseeing, and managing potential sales leads for Lab devices & euqipments in Hong Kong. Product Managers are to provide a solution to researchers in Hong Kong, by understanding the research landscape in Hong Kong as well as individual projects. Tools and training will be provided to tackle technical problems, while learning more about the latest technology on the market!\n\nWe are a young and target-oriented team that encourages everyone to develop their working style. Try us out if you want a fresh and lively environment!\n\n\u00a0Responsibilities:\n\n\u00a0\u00a0\u00a0\u00a0\u00a0\u00a0\u00a0\u00a0\u00a0\u00a0 Independent research to discover potentially interested parties\n\u00a0\u00a0\u00a0\u00a0\u00a0\u00a0\u00a0\u00a0\u00a0\u00a0 Deliver professional presentations and technical advice\n\u00a0\u00a0\u00a0\u00a0\u00a0\u00a0\u00a0\u00a0\u00a0\u00a0 Tracking and pushing the progress of multiple key leads\n\n\u00a0Requirements:\n\n\u00a0\u00a0\u00a0\u00a0\u00a0\u00a0\u00a0\u00a0\u00a0\u00a0 Bachelor's Degree or above in life science or related disciplines.\n\u00a0\u00a0\u00a0\u00a0\u00a0\u00a0\u00a0\u00a0\u00a0\u00a0 Previous relative experience in Sales & Marketing is preferred\n\u00a0\u00a0\u00a0\u00a0\u00a0\u00a0\u00a0\u00a0\u00a0\u00a0 Experience in laboratory research will be beneficial\n\u00a0\u00a0\u00a0\u00a0\u00a0\u00a0\u00a0\u00a0\u00a0\u00a0 Cantonese and English required, Mandarin is a plus\n\u00a0 \u00a0 \u00a0 \u00a0 \u00a0 \u00a0Previous experience in device /equipment operation is a plus\n\u00a0 \u00a0 \u00a0 \u00a0 \u00a0 \u00a0Less experienced will be considered for an account manager position:\u00a0https://hk.jobsdb.com/hk/en/job/account-manager-100003009012564\n\nBenefits upon joining our team:\n\n\u00a0\u00a0\u00a0\u00a0\u00a0\u00a0\u00a0\u00a0\u00a0\u00a0 Independent work schedule\n\u00a0\u00a0\u00a0\u00a0\u00a0\u00a0\u00a0\u00a0\u00a0\u00a0 Base salary plus attractive commission\n\u00a0\u00a0\u00a0\u00a0\u00a0\u00a0\u00a0\u00a0\u00a0\u00a0 Meeting and working with top researchers in Hong Kong", "employment_types": ["Full Time"], "selling_points": ["Regional Business, Product Specialist", "B2B, B2C, technologies, scientific", "Ready for digital selling"], "locations": ["Kwun Tong"], "categories": ["Sales, CS & Business Devpt", "Business Development", "Sciences, Lab, R&D", "Chemical", "Life Science"], "post_time": "2022-01-13T08:02:41Z", "salary": {"currency": null, "max": null, "min": null, "period": "monthly", "term": null}, "salary_visible": false, "title_keywords": ["business development officer"], "responsibilities": [], "requirements": {"degrees": [], "majors": [], "languages": [], "language_level": [], "hard_skills": [], "soft_skills": [], "languages_combined": []}, "experience_required": {"duration": [], "field": []}}, {"job_id": "100003009044359", "location_code": "hk", "company": "InvivoGen Limited", "job_title": "Technical Sales Specialist", "description": "Responsibilities:\n\nBuild and maintain collaborative relationships with all stakeholders of the Institute for Translational Research (ITR) of HKSTP, including but not limited to academia, researchers, and business clients;\nProvide instrumentation and application support to Biomedical Technology Support Centre (BSC); \u00a0\nAssist users in operation and maintenance of laboratory instruments as well as support projects of BSC users;\nHandle technical writing such as standard operating procedures, protocols, technical notes, guidelines and flow charts;\nUnderstand customers\u2019 technical requirements and develop effective solutions;\nProvide overall administrative and procurement support; and\nPerform any other duties as assigned by supervisors and management.\n\nRequirements:\n\nA bachelor\u2019s degree or above in Biology, Biochemistry, Biotechnology, Biomedical Science, Microbiology, Pharmacology, or other discipline related to life science;\nMinimum 2 years of relevant experience in life science or biomedical research laboratory; Less experience with higher qualification will also be considered;\nA proven practical experience in operation of flow cytometer, sequencer or confocal microscopy would be preferred;\nKeep abreast of the latest development in instrumentation and analytical methods;\nFamiliar with occupational hazards and standard safety practices;\nCustomer-centered service attitude with strong problem-solving skills is a must;\nA good team player with excellent communication, analytical, interpersonal and presentation skills as well as able to work independently;\nProficient in MS office (Words, Excel and PowerPoint); and\nProficient in both written and spoken English and Chinese.\n\nWe offer market competitive compensation, 5-day work week, and generous benefits including medical and life insurance; and voluntary contribution in addition to the legal minimum MPF.\u00a0 To apply, please send your full resume with current and expected salary to the Human Resources & Office Administration Department, Hong Kong Science and Technology Parks Corporation, 5/F, Building 5E, 5 Science Park East Avenue, Hong Kong Science Park, Hong Kong or, by email via \"Apply Now\"\u00a0on or before 27 January 2022.\u00a0 \u00a0Please quote the reference number on the email subject/envelope and the application letter.\u00a0\n\nPersonal data provided will be treated in strict confidence and used for recruitment purpose only.\u00a0 All personal data collected will be used strictly in accordance with employer\u2019s personal data policies, you can access to HKSTP\u2019s Personal Information Collection Statement at https://www.hkstp.org/hkstp_web/en/hkstp/personal-information-collection-statement-recruitment\n\nApplicants not invited for interview within four weeks after application deadline may consider their applications unsuccessful.\u00a0 Personal data of unsuccessful applicants will be retained for a maximum of two years.\u00a0\n\nwww.hkstp.org", "employment_types": ["Full Time", "Permanent", "Contract"], "selling_points": ["Salary, Performance Bonus, Health Insurance", "French Biotech (Established in 1977)", "Non-experienced Ph.D. is considered"], "locations": ["Shatin Area"], "categories": ["Sciences, Lab, R&D", "Life Science"], "post_time": "2022-01-13T03:49:16Z", "salary": {"currency": null, "max": null, "min": null, "period": "monthly", "term": null}, "salary_visible": false, "title_keywords": ["sales specialist"], "responsibilities": ["support projects", "any other duties", "management", "maintenance", "guidelines", "procedures", "develop", "maintain"], "requirements": {"degrees": ["degree or above", "bachelor"], "majors": ["biomedical science", "science", "pharmacology", "microbiology", "biology"], "languages": ["english", "chinese"], "language_level": ["proficient"], "hard_skills": ["excel", "words", "powerpoint", "problem-solving skills", "ms office"], "soft_skills": ["good team player", "work independently", "communication", "presentation skills", "problem-solving skills", "interpersonal"], "languages_combined": [{"language": "english", "language_level": ["proficient"]}, {"language": "chinese", "language_level": ["proficient"]}]}, "experience_required": {"duration": ["minimum 2 years"], "field": ["laboratory", "research", "relevant experience", "operation"]}}, {"job_id": "100003009044439", "location_code": "hk", "company": "Hugh Source (International) Ltd", "job_title": "Regulatory Affairs Associate /Executive (5 Days Work)", "description": "Business Development Officer\u00a0\n\nResponsibilities\n\n\nSupport the development of e-commerce platform for Scientific Consumables & Equipment products\u00a0\nWork as Product Specialist to communicate with suppliers for product information and knowledge\u00a0\nTo generate and maintain the content of platform\u00a0\nDesign and prepare promotion material as necessary\u00a0\nSupport the development and execution of marketing plan\u00a0\nPromote e-commerce platform in AP countries\u00a0\nSupport to manage sales and dealers to grow business through e-commerce platform\u00a0\nTrain up & support customer support team to serve customer\u2019s online enquiries and orders\u00a0\nAssist to develop business strategy and plan of e-commerce platform\u00a0\n\n\nRequirements\n\nDegree holder in any related discipline, life sciences background is an advantage.\nPassionate in science and emerging technologies.\nAble to work under pressure, quick learner.\nExcellent written and spoken English. Native English speaker is an advantage.\nIndependent, detail-oriented, self-motivated and responsible.\nLogical thinking, dynamic and energetic.\nExperience in international B2C sales, pre-sales & post-sales or business development is an advantage.\nLess experience will be considered as Technical Sales & Business Development Assistant.", "employment_types": ["Full Time"], "selling_points": [], "locations": ["Tsim Sha Tsui"], "categories": ["Professional Services", "Legal & Compliance", "Sciences, Lab, R&D", "Life Science", "Medical Services", "Pharmaceutical"], "post_time": "2022-01-13T04:07:22Z", "salary": {"currency": null, "max": null, "min": null, "period": "monthly", "term": null}, "salary_visible": false, "title_keywords": ["executive", "regulatory affairs associate"], "responsibilities": ["communicate with", "ap", "design", "develop", "marketing plan", "maintain", "plan", "e-commerce platform"], "requirements": {"degrees": ["degree holder"], "majors": [], "languages": ["english"], "language_level": ["native", "excellent", "advantage"], "hard_skills": ["dynamic"], "soft_skills": ["passionate", "self-motivated", "independent", "responsible", "quick learner", "detail-oriented", "dynamic", "energetic", "work under pressure"], "languages_combined": [{"language": "english", "language_level": ["excellent", "native", "advantage"]}]}, "experience_required": {"duration": [], "field": ["business development"]}}, {"job_id": "100003009056249", "location_code": "hk", "company": "CMA Testing and Certification Laboratories Limited", "job_title": "Assistant Technical Officer - Organic Division", "description": "Responsibilities:\u00a0\n\n\n\nHandling\u00a0of chemical tests related to routine sample;\nSample preparation, perform chemical test, instrumental analysis;\nOperation of analytical instrument (e.g. GC/MS, LC-DAD, LC/MS, LC/MS/MS);\nInstrument maintenance and calibration;\nMethod validation and preparation for accreditation audit;\nAssist in R&D work;\nUndertake any other duties as assigned.\n\nRequirements:\n\n\nHigher Diploma or above in Chemistry or relevant discipline;\nKnowledge of ISO 17025 quality system and accreditation requirements;\nAnalytical instrumentation skill;\nImmediately available is highly preferred.\nCandidate with less experience will be considered as Lab Technician\n\nOther Benefits:\n\n5 days work week\nMedical Insurance\nOver Time Pay\nDouble pay\nFree shuttle bus\n\nWe offer attractive remuneration package and excellent career opportunities to the right candidates. Interested parties please send your full resume with availability, current and expected salary to\u00a0our HR department.\n\nWelcome to visit our company website\u00a0http://www.cmatesting.org/ or more information.\n\nWe are an Equal Opportunities Employer and welcome applications from all qualified candidates. All Personal data collected will be kept in strict confidence and used for recruitment purpose only.", "employment_types": ["Full Time", "Permanent"], "selling_points": ["Handling of chemical tests related routine sample", "Higher Diploma in Chemistry or relevant discipline", "5 days,Medical, OT Pay,Double pay,Free shuttle bus"], "locations": ["Shatin Area"], "categories": ["Sciences, Lab, R&D", "Chemical", "Laboratory", "Life Science"], "post_time": "2022-01-18T03:42:09Z", "salary": {"currency": null, "max": null, "min": null, "period": "monthly", "term": null}, "salary_visible": false, "title_keywords": ["assistant technical officer"], "responsibilities": ["any other duties", "maintenance", "sample preparation", "analysis", "audit"], "requirements": {"degrees": ["higher diploma or above"], "majors": ["chemistry"], "languages": [], "language_level": [], "hard_skills": [], "soft_skills": [], "languages_combined": []}, "experience_required": {"duration": [], "field": []}}, {"job_id": "100003009056248", "location_code": "hk", "company": "CMA Testing and Certification Laboratories Limited", "job_title": "Technical Officer / Senior Technical Officer - Research & Development Division", "description": "Responsibilities:\n\nResponsible for chemical testing, project development;\nConduct researches and develop test methods;\nValidate or verify the test methods with various analytical instruments and estimate measurement uncertainty;\nPerform pilot test and feasibility study on the test methods;\nDocument the developed test methods and transfer the technical skill and knowledge of the tests to operation team;\nContinuous optimization of instrumentation and test methods;\nParticipate in ad-hoc projects and routine chemical testing as assigned.\n\nRequirements:\n\nDegree\u00a0holder or\u00a0above in Chemistry or other science relevant disciplines;\nAt least 1 year of relevant hands-on\u00a0laboratory\u00a0testing experience;\nExperience in handling analytical instruments is a Must (e.g. GC-MSMS, Headspace GC-MS, LC-MSMS);\nKnowledge of HOKLAS requirements and ISO/IEC 17025;\nInitiative, organized, independent and willing to work under pressure;\nGood problem solving and communication skills;\nGood command of English and Chinese;\nCandidate with less experience will be considered as Technical officer\n\nWe offer attractive remuneration package and excellent career opportunities to the right candidates. Interested parties please send your full resume with availability, current and expected salary to\u00a0our HR department.\n\nWelcome to visit our company website\u00a0http://www.cmatesting.org/ or more information.\n\nWe are an Equal Opportunities Employer and welcome applications from all qualified candidates. All Personal data collected will be kept in strict confidence and used for recruitment purpose only.", "employment_types": ["Full Time", "Permanent"], "selling_points": ["Chemical testing, analytical instruments", "GC-MSMS, Headspace GC-MS, LC-MSMS", "5 days, Medical, Double pay, Shuttle bus"], "locations": ["Shatin Area"], "categories": ["Sciences, Lab, R&D", "Chemical", "Laboratory", "Life Science"], "post_time": "2022-01-18T03:42:08Z", "salary": {"currency": null, "max": null, "min": null, "period": "monthly", "term": null}, "salary_visible": false, "title_keywords": ["technical officer", "senior technical officer"], "responsibilities": ["develop", "ad-hoc projects", "measurement", "testing"], "requirements": {"degrees": ["degree holder"], "majors": ["science", "chemistry"], "languages": ["english", "chinese"], "language_level": ["good command"], "hard_skills": ["problem solving"], "soft_skills": ["organized", "communication skills", "independent", "problem solving", "hands-on", "initiative", "work under pressure"], "languages_combined": [{"language": "english", "language_level": ["good command"]}, {"language": "chinese", "language_level": ["good command"]}]}, "experience_required": {"duration": ["at least 1 year"], "field": ["laboratory testing", "analytical"]}}, {"job_id": "100003009056244", "location_code": "hk", "company": "CMA Testing and Certification Laboratories Limited", "job_title": "Senior Technical Officer - Organic Division", "description": "Responsibilities:\n\n\n\nHandling\u00a0of chemical tests related to routine sample;\nTest result analysis and review;\nOut of specification results investigation;\nDevelop and review test methods;\nHandling of test enquiry;\nOperation and maintenance of analytical instrument (e.g. GC/MS, LC-DAD, LC/MS, LC/MS/MS);\nMethod validation and preparation for accreditation audit;\nAssist in R&D work;\nUndertake any other duties as assigned.\n\nRequirements:\n\n\n\nDegree or above in Chemistry or relevant discipline;\nKnowledge of ISO 17025 quality system and accreditation requirements;\nExperienced in lab supervision and operation management;\nAnalytical instrumentation skill;\nInitiative, organized and comprehensive\nCandidate with less experience will be considered as Technical Officer\n\nOther Benefits:\n\n5 days work week\nMedical Insurance\nOver Time Pay\nDouble pay\nFree shuttle bus\n\nWe offer attractive remuneration package and excellent career opportunities to the right candidates. Interested parties please send your full resume with availability, current and expected salary to\u00a0our HR department.\n\nWelcome to visit our company website\u00a0http://www.cmatesting.org/ or more information.\n\nWe are an Equal Opportunities Employer and welcome applications from all qualified candidates. All Personal data collected will be kept in strict confidence and used for recruitment purpose only.", "employment_types": ["Full Time", "Permanent"], "selling_points": ["Handling of chemical tests related routine sample", "Degree in Chemistry or relevant discipline", "5 days,Medical, OT Pay,Double pay,Free shuttle bus"], "locations": ["Shatin Area"], "categories": ["Sciences, Lab, R&D", "Chemical", "Laboratory", "Life Science"], "post_time": "2022-01-18T03:42:07Z", "salary": {"currency": null, "max": null, "min": null, "period": "monthly", "term": null}, "salary_visible": false, "title_keywords": ["senior technical officer"], "responsibilities": ["any other duties", "maintenance", "analysis", "review", "audit", "investigation", "develop"], "requirements": {"degrees": ["degree or above"], "majors": ["chemistry"], "languages": [], "language_level": [], "hard_skills": [], "soft_skills": ["organized", "comprehensive", "initiative"], "languages_combined": []}, "experience_required": {"duration": [], "field": []}}, {"job_id": "100003009042354", "location_code": "hk", "company": "DiagCor Life Science Limited", "job_title": "Senior Production Technologist/ Production Technologist/ Production Technician", "description": "The Job:\n\nResponsible for protein drug development\nResponsible for protein purification process and relevant in-process control\nLead and supervise the technicians on manufacturing process optimization and validation based on the international guidelines\nWork with other parties to resolve the technical issues related to in-process control, process optimization and improvements in product quality\u00a0\nTo prepare the SOP documents for manufacturing process and in-process control tests\nTo prepare the relevant documentation for new drug registration\nThe Person:\nPh.D/ Master in Biology, Biochemistry, Biotechnology or relevant discipline\nMinimum of 4-5 years of working experience in protein field (especially the purification) and\u00a0 process development\nExperiences of handling biopharmaceutical process in industrial scale and working in GMP environment are preferred\nAdvance knowledge or experience in process development and scale-up are preferred\nHave good time management and organization skills with ability to function independently, with little supervision\nIndependent and enthusiastic, with good communication skills and team spirit\nHave good analytical and problem solving skills\nProficiency in spoken and written English and Chinese\nTravelling to PRC and overseas as well as stationing for a short period may be required\nCandidate with less experience will be considered as Assistant Manager\nCandidate with more experience will be considered as Senior Manager\nWe offer attractive remuneration and benefits, 5-day work week, annual leave, medical scheme, comprehensive training and career development opportunities to the qualified candidates.\n\nPlease send your application with full resume stating your present and expected salary to the Company by clicking\u00a0on the \"Apply now\" or by following methods.\u00a0Please quote the\u00a0reference number\u00a0of the applied position in the subject field.\u00a0\n\nMail:\u00a0Human Resources Department, New\u00a0Beta Innovation Limited, 18 Chevalier Commercial Centre, 8 Wang Hoi Road, Kowloon Bay, Kowloon, Hong Kong.\n\nPersonal data collected will be used for recruitment purpose only.", "employment_types": ["Full Time"], "selling_points": [], "locations": ["Kowloon Bay"], "categories": ["Sciences, Lab, R&D", "Life Science", "Manufacturing", "Production Planning / Control", "Quality Assurance, Control & Testing / ISO"], "post_time": "2022-01-12T07:10:03Z", "salary": {"currency": null, "max": null, "min": null, "period": "monthly", "term": null}, "salary_visible": false, "title_keywords": ["production technician"], "responsibilities": ["guidelines", "control", "documentation", "quality"], "requirements": {"degrees": ["master"], "majors": ["biology"], "languages": ["english", "chinese"], "language_level": ["proficiency"], "hard_skills": ["beta", "problem solving skills", "scheme"], "soft_skills": ["communication skills", "independently", "independent", "team spirit", "analytical and problem solving skills", "comprehensive", "enthusiastic", "organization skills", "time management"], "languages_combined": [{"language": "english", "language_level": ["proficiency"]}, {"language": "chinese", "language_level": ["proficiency"]}]}, "experience_required": {"duration": ["minimum of 4-5 years"], "field": ["development", "biopharmaceutical"]}}, {"job_id": "100003009049396", "location_code": "hk", "company": "Hays", "job_title": "Product Specialist (Fresh Grad and CS background are Welcome!)", "description": "Top 10 biopharmaceutical focusing on research, development, and commercialization of prescription medicines\n\nYour new company\nA global leading biopharmaceutical focusing on the research, development, and commercialization of prescription medicines that is global, science-led, and patient-centered.\n\nYour new role\nResponsible for sales activities in assigned accounts or regions. Managed quality and consistency of product and service delivery.\n\n\nPromoting key products to current and new clients in the private and public sectors\nIdentify potential clients and collect market intelligence\nActively manage and grow dedicated sales territory in product pipeline\nResponsible for sales proposal\nCo-operate with marketing team to do promotion for growth of business\nBuild and maintain a good relationship with medical and pharmaceutical KOLs.\n\n\n\nWhat you'll need to succeed\n\nBachelor's degree or above in life science related disciplines (CS background are welcome!)\n2 to 3 years sales experience in pharmaceutical or medical company (fresh grad also welcome)\nStrong communication, interpersonal and presentation skills\nSales driven and customer focus to enhance good relationship with different parties\nProactive, self-motivated with passion to overcome challenges\nFluent in English and Cantonese, fluent in Mandarin will be an advantage\n\n\nWhat you need to do now\nIf you are interested in the above opportunity, please forward your latest resume to rooney.wu@hays.com.hk or contact +852 Rooney at 2230 7913 for more information.\n\nIf this role isn't quite right for you but you are looking to explore new opportunities in the life science sector, please contact Rooney for a confidential discussion about your options.", "employment_types": ["Full Time", "Permanent"], "selling_points": ["Top 10 MNC Pharma", "Products of Market Leader", "Competitive salary package"], "locations": ["Not Specified"], "categories": ["Sciences, Lab, R&D", "Life Science", "Medical Services", "Pharmaceutical"], "post_time": "2022-01-14T08:33:06Z", "salary": {"currency": "HKD", "max": 34999, "min": 14000, "period": "monthly", "term": null}, "salary_visible": true, "title_keywords": ["product specialist"], "responsibilities": ["service delivery", "sales activities", "quality", "good relationship", "communication", "commercialization", "co-operate with", "maintain", "contact"], "requirements": {"degrees": ["degree or above", "bachelor"], "majors": ["related disciplines", "science"], "languages": ["cantonese", "english", "mandarin"], "language_level": ["advantage", "fluent"], "hard_skills": ["focus"], "soft_skills": ["self-motivated", "responsible", "interested in", "driven", "communication", "presentation skills", "customer focus", "patient", "proactive", "interpersonal"], "languages_combined": [{"language": "cantonese", "language_level": ["advantage"]}, {"language": "english", "language_level": ["advantage"]}, {"language": "mandarin", "language_level": ["fluent", "advantage"]}]}, "experience_required": {"duration": ["2 to 3 years"], "field": ["pharmaceutical", "medical"]}}, {"job_id": "100003009042094", "location_code": "hk", "company": "New Zeta Innoviation Limited", "job_title": "Manager - R&D (Protein Purification Development/ Scale-up)", "description": "Responsibilities\n\nPerform molecular clinical testing according to standard operating procedures;\nMaintain routine laboratory operation including but not limited to equipment maintenance and calibration, inventory management, lab records management;\nAssist in the setup of a new clinical molecular laboratory;\nAssist in laboratory accreditation preparation including but not limited to protocol writing and carrying out validation;\nSupport in research and development activities;\nHandle ad-hoc duties assigned by senior management;\nShift duty is required.\n\nRequirements\n\n\nBachelor Degree or Higher Diploma in Medical Laboratory Science, Biomedical Science, Life Science or related field;\nPart I/II Registered Medical Laboratory Technologist with a valid Practising Certificate issued by the HKMLT Board;\u00a0\nExperience in molecular genetics would be an advantage;\nSelf-motivated, strong sense of responsibility, and good team work;\nGood command of both spoken and written English and Chinese including Mandarin", "employment_types": ["Full Time", "Permanent"], "selling_points": ["Research Job in Professional firm", "Attractive remuneration and benefits", "5 days work and location closed to MTR"], "locations": ["Kowloon Bay"], "categories": ["Sciences, Lab, R&D", "Laboratory", "Life Science", "Research & Development (R&D)"], "post_time": "2022-01-12T06:05:10Z", "salary": {"currency": null, "max": null, "min": null, "period": "monthly", "term": null}, "salary_visible": false, "title_keywords": ["manager"], "responsibilities": ["management", "maintenance", "procedures", "testing", "inventory management", "maintain", "ad-hoc duties", "senior management", "setup"], "requirements": {"degrees": ["certificate", "diploma", "degree", "bachelor"], "majors": ["biomedical science", "science", "medical laboratory science"], "languages": ["english", "chinese", "mandarin"], "language_level": ["good command"], "hard_skills": [], "soft_skills": ["good team work", "self-motivated", "sense of responsibility"], "languages_combined": [{"language": "english", "language_level": ["good command"]}, {"language": "chinese", "language_level": ["good command"]}, {"language": "mandarin", "language_level": ["good command"]}]}, "experience_required": {"duration": [], "field": ["molecular genetics"]}}, {"job_id": "100003009038955", "location_code": "hk", "company": "Take2 Health Limited", "job_title": "Associate Medical Technologist (AMT)", "description": "Follow up shipment booking and handle all logistics activities with internal and external parties to ensure smooth delivery.\nPurchasing orders and monitoring the inventory.\nInventory management to determine when new purchases should be scheduled.\nAble to handle full set of shipping documents, Tradelink system, custom declaration and all related issues.\nOperate storeroom activities of dispatching, receiving, sorting, and distributing deliveries.\nSupport sales team to deliver the goods to local customers.\nPrepare sales reports & analysis for inventory management purposes.\nVarious office administrative duties such as local and international courier to support office daily operations.\nOther ad-hoc job duties if necessary.\nJob Requirements\n\nDiploma graduated or above.\n2-3 years of experience in shipping and logistic is preferred or familiar with international trade.\nGood command of both written and spoken English and Chinese.\nAdvanced computer skills including MS Word and excel.\nAble to work independently with a high sense of responsibility, reliable, detail-minded and team player.\n\u00a0", "employment_types": ["Full Time", "Permanent"], "selling_points": [], "locations": ["Shatin Area"], "categories": ["Sciences, Lab, R&D", "Laboratory", "Life Science", "Research & Development (R&D)"], "post_time": "2022-01-11T08:12:40Z", "salary": {"currency": null, "max": null, "min": null, "period": "monthly", "term": null}, "salary_visible": false, "title_keywords": ["associate medical technologist"], "responsibilities": ["ad-hoc"], "requirements": {"degrees": ["diploma graduated"], "majors": [], "languages": ["english", "chinese"], "language_level": ["good command"], "hard_skills": ["excel", "computer skills", "ms word"], "soft_skills": ["detail-minded", "work independently", "advanced", "high sense of responsibility", "team player", "reliable"], "languages_combined": [{"language": "english", "language_level": ["good command"]}, {"language": "chinese", "language_level": ["good command"]}]}, "experience_required": {"duration": ["2-3 years"], "field": []}}, {"job_id": "100003009045306", "location_code": "hk", "company": "Medikonia Limited", "job_title": "Shipping & Operations Officer", "description": "Key Roles and Responsibilities:\n\n\nResponsible for assisting the Head of Regulatory Affairs as well as the General Manager in maintaining the operation of the Regulatory Affairs and Pharmacovigilance Department\u00a0to handle all regulatory related matters;\nCommunicate with Department of Health and respond to their queries;\nLiaise closely with our Production and Quality Control Department regarding documentation and product files for pharmaceutical products;\nCoordinate prompt registration of new pharmaceutical products in Hong Kong, application for change of particulars of products and renewal of product registration certificates;\nMaintain product registration files and monitor submission timeline; &\nSupport any other special tasks as assigned by the Head of Regulatory Affairs and the General Manager.\n\n\nQualifications and Experience\n\n\nDegree-holder in Life Science, Pharmacology or Medical related field, or Language Studies who studied Sciences in Secondary School;\nExcellent communication and interpersonal skills to work with people of different levels and cultures;\nAble to work independently with good organization skills, highly self-motivated and detail oriented;\nProficiency in both written and spoken English;\n\nCandidate with relevant work experience in RA / Pharmaceutical industry will be considered as Senior Regulatory Affairs Assistant;\n\nImmediately available is highly preferred.\n\u00a0\n\n\nYou are invited to send in your application and CV stating your expected salary (please remember to mention your expected salary), either by Clicking \"Apply Now\".\n\nEuropharm Laboratoires Company Limited is an equal opportunities employer. The information provided will be treated in strict confidence and used only for consideration of application for relevant/similar post(s).\u00a0 All personal data of unsuccessful applicants will be destroyed within 6 months.", "employment_types": ["Full Time", "Permanent"], "selling_points": [], "locations": ["Mong Kok"], "categories": ["Admin & HR", "Clerical / Admin Staff", "Sciences, Lab, R&D", "Life Science", "Transportation & Logistics", "Shipping"], "post_time": "2022-01-13T18:55:07Z", "salary": {"currency": null, "max": null, "min": null, "period": "monthly", "term": null}, "salary_visible": false, "title_keywords": ["operations officer", "shipping"], "responsibilities": ["communicate with", "liaise", "maintaining", "monitor", "coordinate", "communication", "maintain", "quality control", "documentation", "personal data"], "requirements": {"degrees": ["degree"], "majors": ["pharmacology", "science"], "languages": ["english"], "language_level": ["proficiency"], "hard_skills": ["documentation"], "soft_skills": ["work independently", "self-motivated", "confidence", "responsible", "prompt", "detail oriented", "communication and interpersonal skills", "organization skills"], "languages_combined": [{"language": "english", "language_level": ["proficiency"]}]}, "experience_required": {"duration": [], "field": ["pharmaceutical", "regulatory affairs"]}}, {"job_id": "100003009046780", "location_code": "hk", "company": "Europharm Laboratoires Company Limited", "job_title": "Senior / Regulatory Affairs Assistant", "description": "Applications are invited for appointment as\u00a0Post-doctoral Fellow (several posts) in the Division of Public Health Laboratory Sciences (PHLS) of the School of Public Health\u00a0(Ref.: 508654), to commence as soon as possible for one to two years, with the possibility of renewal subject to satisfactory performance.\n\nApplicants should possess a Ph.D. degree with a strong background in biological/medical sciences or related fields, and experience in molecular virology and immunology.\u00a0 Experience in animal work and pathogen-induced immune response will be an advantage.\u00a0The appointees will work in an influenza research group.\u00a0 Enquiries about the duties of the post should be sent to Professor Leo Poon at [via APPLY NOW]\u00a0.\n\nA highly competitive salary commensurate with qualifications and experience will be offered, in addition to annual leave and medical benefits.\n\nThe University only accepts online application for the above posts.\u00a0 Applicants should apply online and upload an up-to-date C.V.\u00a0 Review of applications will start on November 8, 2021 and continue until\u00a0January 31, 2022, or until the posts are filled, whichever is earlier.", "employment_types": ["Full Time", "Permanent"], "selling_points": [], "locations": ["Tai Po Area"], "categories": ["Sciences, Lab, R&D", "Life Science", "Medical Services", "Pharmaceutical", "Manufacturing", "Quality Assurance, Control & Testing / ISO"], "post_time": "2022-01-14T01:03:57Z", "salary": {"currency": null, "max": null, "min": null, "period": "monthly", "term": null}, "salary_visible": false, "title_keywords": ["regulatory affairs assistant"], "responsibilities": [], "requirements": {"degrees": ["degree"], "majors": [], "languages": [], "language_level": [], "hard_skills": ["animal work"], "soft_skills": [], "languages_combined": []}, "experience_required": {"duration": [], "field": ["related", "medical"]}}, {"job_id": "100003009047583", "location_code": "hk", "company": "The University of Hong Kong", "job_title": "Post-doctoral Fellow (several posts)  (508654)", "description": "InvivoGen is currently looking for a\u00a0Technical Sales Specialist\u00a0in order to support our fast-growing of Asian-Pacific headquarters that was incorporated in 2014. This position is ideal for talented and open-minded candidates who are keen to keep chasing the frontier of life science and have interests in business development. As a regional headquarters, you will have a chance to interact with scientists from pharmaceuticals, institutes and universities in China, Japan, Korea, Singapore as well as other regions. You will have a chance to develop business opportunities in the\u00a0life science market with business partners from Asian-Pacific region.\n\nJob Description:\n\nAssist InvivoGen distributors by providing advanced technical and sales support.\nImplement marketing strategy to improve InvivoGen brand awareness by attending relevant event in immunology all over Asia-Pacific region.\nPresenting advanced information by giving regular lectures, training courses and experimental support to customers and distributors.\nConnect with life-science key opinion leaders and laboratories stakeholders.\nProactively build an extensive network to extend our customer database.\nOverseeing cell line based screening service which includes communicating with customers, designing the protocols and translating test results into reports.\nImplement marketing strategy by translating R&D data to marketing materials.\nJob Requirement:\n\nPh. D. degree in immunology or oncology.\nFluent English and Mandarin.\nAt least 4 years extensive laboratory experience in immunology or oncology.\nYou have good communication and presentation skills and are able to connect and clearly communicate complex information.\nYou are organized and autonomous and know how to independently prioritizing tasks in order to meet your objectives.\nWorking experience in Mainland China is a plus.\nMust be willing to travel frequently throughout China, Japan, Korea and potentially other regions in Asia-Pacific.\n\nBenefits:\n\nCompensation package composed by a 12 months-based salary and performance bonus\nHealth and Dental Insurance", "employment_types": ["Full Time"], "selling_points": [], "locations": ["Pok Fu Lam"], "categories": ["Sciences, Lab, R&D", "Life Science", "Research & Development (R&D)"], "post_time": "2022-01-14T03:30:21Z", "salary": {"currency": null, "max": null, "min": null, "period": "monthly", "term": null}, "salary_visible": false, "title_keywords": [], "responsibilities": ["data", "communicating with", "reports", "database", "designing", "marketing materials"], "requirements": {"degrees": ["degree"], "majors": [], "languages": ["english", "mandarin"], "language_level": ["fluent"], "hard_skills": ["plus"], "soft_skills": ["organized", "independently", "communication", "presentation skills", "autonomous", "extensive", "prioritizing"], "languages_combined": [{"language": "english", "language_level": ["fluent"]}, {"language": "mandarin", "language_level": ["fluent"]}]}, "experience_required": {"duration": ["at least 4 years"], "field": ["laboratory"]}}, {"job_id": "100003009047423", "location_code": "hk", "company": "Prism Technologies Limited", "job_title": "Sr Service Engineer / Service Engineer (Medical Equipment)", "description": "HealthCore is a professional recruitment company specializing in the healthcare & life science industry. HealthCore is currently helping one of its clients, a multi-national pharmaceutical company, to recruit a Regulatory Affairs Specialist.\n\nGeneral\u00a0Job Responsibilities:\n\nManage and ensure compliance for all regulatory affairs / product registration related issues & activities\nMeet expected\u00a0product registration timelines\nKeep updated with regulatory affairs trend & development; evaluate, design and implement effective strategies\nMaintain excellent communication and relation with related external authorities and internal parties\nKeep proper and updated documentation and records\u00a0\n\nQualifications / Skills:\n\n1+ year related work experience\u00a0\nUniversity degree holder\nExcellent communication and organizational skills\nGood command of English and Chinese\u00a0\n\nInterested candidates please send CV\u00a0via the \"Apply Now\" button. Personal data collected will be used for recruitment purposes only.", "employment_types": ["Full Time", "Permanent"], "selling_points": ["Good career prospect, training provided", "Medical, dental and life insurance", "Double pay + very attractive bonus"], "locations": ["Cheung Sha Wan"], "categories": ["Engineering", "Electrical / Electronics", "Sciences, Lab, R&D", "Life Science", "Medical Services", "Medical Services Technician"], "post_time": "2022-01-14T03:02:40Z", "salary": {"currency": null, "max": null, "min": null, "period": "monthly", "term": null}, "salary_visible": false, "title_keywords": ["service engineer"], "responsibilities": ["design", "ensure compliance", "evaluate", "communication", "maintain", "recruitment", "documentation", "internal parties"], "requirements": {"degrees": ["university degree"], "majors": [], "languages": ["english", "chinese"], "language_level": ["good command"], "hard_skills": ["documentation"], "soft_skills": ["communication", "organizational skills"], "languages_combined": [{"language": "english", "language_level": ["good command"]}, {"language": "chinese", "language_level": ["good command"]}]}, "experience_required": {"duration": ["1+ year"], "field": ["related"]}}, {"job_id": "100003009044866", "location_code": "hk", "company": "Hai Kang Life Corporation Ltd", "job_title": "Process Engineer", "description": "Overview\n\nWe are looking for responsible nice working attitude high ethical standard persons to join our new highly sophisticated and automation laboratory.\u00a0Numerous full-time and part-time posts with attractive salaries depend on experience.\n\n\u00a0Medical Lab Technologist\n\nPart1/Part2 registration with a valid practising certificate issued by the HKMLT Board.\u00a0 Experience or interest in molecular testing is preferred\nProficiency in PC, Microsoft Excel and typing Chinese\nGood communication skills in Cantonese, Mandarin and English\u00a0\n\nWe offer an attractive basic salary, on-the-job training and career advancement opportunity to the right candidates.\u00a0 Please send full resume with availability and expected salary by clicking \"Apply Now\"\u00a0\n\n\u00a0\u00a0Benefits\n\nBank Holidays\nMedical Insurance\n12+ Days Annual leave\nPaid Marriage Leave\nBirthday Leave\n\n(Personal data collected will be used for recruitment purpose only.)", "employment_types": ["Full Time", "Permanent"], "selling_points": ["Process Engineer", "R&D", "engineering"], "locations": ["Shatin Area"], "categories": ["Engineering", "Electrical / Electronics", "Sciences, Lab, R&D", "Life Science", "Research & Development (R&D)"], "post_time": "2022-01-13T06:29:47Z", "salary": {"currency": null, "max": null, "min": null, "period": "monthly", "term": null}, "salary_visible": false, "title_keywords": ["process engineer"], "responsibilities": ["communication", "testing"], "requirements": {"degrees": ["certificate"], "majors": [], "languages": ["cantonese", "english", "chinese", "mandarin"], "language_level": ["proficiency", "good"], "hard_skills": ["pc", "nice", "typing", "microsoft excel"], "soft_skills": ["sophisticated", "communication skills", "ethical", "responsible"], "languages_combined": [{"language": "cantonese", "language_level": ["good"]}, {"language": "english", "language_level": ["good"]}, {"language": "chinese", "language_level": ["proficiency"]}, {"language": "mandarin", "language_level": ["good"]}]}, "experience_required": {"duration": [], "field": ["testing"]}}, {"job_id": "100003009050333", "location_code": "hk", "company": "Healthcore Consultancy Limited", "job_title": "Regulatory Affairs Specialist (pharmaceutical company)", "description": "Job Description\n\nThe company is now looking for an Application Specialist /Technical Officer to drive research & development, troubleshoot and demonstrate on new and existing analytical technology to hospitals in Hong Kong & Macau.\n\nRequirement\n\nPerform clinical evaluation and driving research and development of new In-Vitro Diagnostics (IVD) technologies.\nPerform validation studies and acceptance test in compliance with accreditation requirement.\nOngoing development of the application specialist team to expand the skills, expertise and knowledge to provide scientific support to customers & other departments\nAdvise laboratory the design & planning in meeting safety & international standards\u00a0of good laboratory environment.\nProvide training to users on operation of analytical instruments & reagent adhering to manufacturer 's instruction.\nIdentify, troubleshoot and prevent point of failures by root cause analysis\nHandle ad-hoc duties assigned by the geeky director.\nCareer Growth\n\nBenefit from culture exposure to partners in Germany, the United States, Korea and other countries.\nRare opportunity to be trained by top specialist abroad or coming to Hong Kong would be provided upon individual cases.\nClear Career Path Start out in an entry level / graduate position, moving through Assistant Application Specialist ->\u00a0Application Specialist -> Team Leader , Application Support-> Assistant Department Manager, Technical Support and beyond.\nRequirement\n\nBachelor Degree or Higher Diploma in Medical Laboratory Sciences, Biological Science or Life Science, related or non-related disciplines.\nSomeone who has unbridled passion for something (work preferably), or things, defines who they are as a person without fear of other's view.\u00a0 Proud to be nerdy.\nGood analytical skills, and familiar with Microsoft Excel or other tools.\nExperience in routine lab work\u00a0would be an advantage.\nCandidate with lower qualifications will be considered as assistant application specialist.\nAbility to maintain strict confidentiality and apply discretion and judgment in sensitive information.\n\nRemuneration\u00a0\n\nThis is an excellent career progression opportunity in our global medical principal brands. The company offers a comprehensive product training to the candidates.\n\nWe offer attractive remuneration package, 5-day work per week, bank holidays, medical scheme and MPF to the successful candidates.\u00a0Business travels are required.\n\nInterested parties please send your resume with expected salary, contact telephone number by clicking 'Apply Now' for an interview.\u00a0\n\nAll personal data collected will be used for recruitment purpose only.\n\nPlease visit our website at\u00a0http://www.potus.com.hk\u00a0for more information about us.", "employment_types": ["Full Time"], "selling_points": ["Regulatory Affairs Specialist", "Pharmaceuticals", "Multi-National company"], "locations": ["Not Specified"], "categories": ["Professional Services", "Legal & Compliance", "Sciences, Lab, R&D", "Life Science", "Medical Services", "Pharmaceutical"], "post_time": "2022-01-14T10:08:54Z", "salary": {"currency": null, "max": null, "min": null, "period": "monthly", "term": null}, "salary_visible": false, "title_keywords": ["specialist"], "responsibilities": ["troubleshoot"], "requirements": {"degrees": ["diploma", "degree", "bachelor"], "majors": ["related disciplines", "science", "biological science"], "languages": [], "language_level": [], "hard_skills": ["analysis", "microsoft excel", "analytical skills"], "soft_skills": ["passion for", "analytical skills", "clear", "comprehensive", "troubleshoot", "ad-hoc duties", "sensitive"], "languages_combined": []}, "experience_required": {"duration": [], "field": []}}, {"job_id": "100003009036696", "location_code": "hk", "company": "Phase Scientific International Limited", "job_title": "Medical Lab Technologist I / II", "description": "The Job:\n\nResponsible for protein drug development\nResponsible for protein purification process and relevant in-process control\nLead and supervise the technicians on manufacturing process optimization and validation based on the international guidelines\nWork with other parties to resolve the technical issues related to in-process control, process optimization and improvements in product quality\u00a0\nTo prepare the SOP documents for manufacturing process and in-process control tests\nTo prepare the relevant documentation for new drug registration\nThe\u00a0Person:\nPh.D/ Master in Biology, Biochemistry, Biotechnology or relevant discipline\nMinimum of 4-5 years of working experience in protein field (especially the purification) and\u00a0 process development\nExperiences of handling biopharmaceutical process in industrial scale and working in GMP environment are preferred\nAdvance knowledge or experience in process development and scale-up are preferred\nHave good time management and organization skills with ability to function independently, with little supervision\nIndependent and enthusiastic, with good communication skills and team spirit\nHave good analytical and problem solving skills\nProficiency in spoken and written English and Chinese\nTravelling to PRC and overseas as well as stationing for a short period may be required\nCandidate with less experience will be considered as Assistant Manager\nCandidate with more experience will be considered as Senior Manager\nWe offer attractive remuneration and benefits, 5-day work week, annual leave, medical scheme, comprehensive training and career development opportunities to the qualified candidates.\nPlease send your application with full resume stating your present and expected salary to the Company by clicking\u00a0on the \"Apply now\" or by following methods.\u00a0Please quote the\u00a0reference number\u00a0of the applied position in the subject field.\u00a0\nMail:\u00a0Human Resources Department, New\u00a0Zeta Innovation Limited, 18 Chevalier Commercial Centre, 8 Wang Hoi Road, Kowloon Bay, Kowloon, Hong Kong.\nPersonal data collected will be used for recruitment purpose only.", "employment_types": ["Full Time", "Part Time", "Permanent"], "selling_points": ["Medical Lab Technologist", "Lab Assistant / Technician", "Molecular testing"], "locations": ["Kwun Tong"], "categories": ["Sciences, Lab, R&D", "Laboratory", "Life Science", "Others"], "post_time": "2022-01-10T12:46:09Z", "salary": {"currency": null, "max": null, "min": null, "period": "monthly", "term": null}, "salary_visible": false, "title_keywords": [], "responsibilities": ["guidelines", "control", "documentation", "quality"], "requirements": {"degrees": ["master"], "majors": ["biology"], "languages": ["english", "chinese"], "language_level": ["proficiency"], "hard_skills": ["problem solving skills", "scheme"], "soft_skills": ["communication skills", "independently", "independent", "team spirit", "analytical and problem solving skills", "comprehensive", "enthusiastic", "organization skills", "time management"], "languages_combined": [{"language": "english", "language_level": ["proficiency"]}, {"language": "chinese", "language_level": ["proficiency"]}]}, "experience_required": {"duration": ["minimum of 4-5 years"], "field": ["development", "biopharmaceutical"]}}, {"job_id": "100003009036208", "location_code": "hk", "company": "Potus Medical (Hong Kong) Limited", "job_title": "Assistant Application Specialist / Technical Officer, 5-day work, Expense Reimbursement", "description": "Job Description\n\n\nWork close with Sales Team to complete the tasks\nAssist in organizing and coordinating various sales and marketing activities\nAssist in design of marketing materials and preparation of promotion leaflets\nResponsible for tender preparation\nHandle customer\u2019s inquiry and daily correspondence through phone and email\nPrepare quotation through system\nAssist Sales Team and handle administrative work\nResponsible for data input, data consolidation, price calculation\nOther ad-hoc assignments\nSkills & Requirements\n\nDegree in Life Sciences or Chemistry related discipline is a MUST\nFamiliar with word processing, spreadsheet and presentation software\nGood command of spoken/written English, Cantonese & Mandarin\nWell organized, mature and self-motivated, able to develop work independently as well as a team;\nCandidate with some research background will be an advantage", "employment_types": ["Full Time"], "selling_points": ["5-day work, expense reimbursement, clear path", "Science or related, training abroad (when safe)", "Lab bench work (LA/RA) exp a plus"], "locations": ["Kwai Hing"], "categories": ["Sciences, Lab, R&D", "Life Science", "Medical Services", "Medical Services Technician", "Research & Development (R&D)"], "post_time": "2022-01-10T09:39:23Z", "salary": {"currency": null, "max": null, "min": null, "period": "monthly", "term": null}, "salary_visible": false, "title_keywords": ["technical officer", "assistant", "application specialist"], "responsibilities": ["administrative work", "data", "leaflets", "ad-hoc assignments", "quotation", "data input", "design", "sales team", "tender preparation", "marketing materials"], "requirements": {"degrees": ["degree"], "majors": ["chemistry"], "languages": ["cantonese", "english", "mandarin"], "language_level": ["good command"], "hard_skills": ["spreadsheet", "word processing"], "soft_skills": ["self-motivated", "work independently", "well organized", "mature", "presentation"], "languages_combined": [{"language": "cantonese", "language_level": ["good command"]}, {"language": "english", "language_level": ["good command"]}, {"language": "mandarin", "language_level": ["good command"]}]}, "experience_required": {"duration": [], "field": []}}, {"job_id": "100003009044186", "location_code": "hk", "company": "Tin Hang Technology Limited", "job_title": "Sales Support Specialist", "description": "Job Specification\n\nConduct sales & marketing activities for Life Science Research to Universities, biotechnology laboratories and Government Departments for capital equipment\nReporting to the Division Manager to implement sales and marketing plans designed to achieve sales goals for a specific focused product range\nPro-actively out-reach and explore opportunity with customers and develop new markets for new product lines\nWorking closely with the sales team, support team and various Business Divisions to achieve business objectives\nOn-the-Job, Overseas and/or local professional trainings will be provided irregularly\nGood promotion and career development opportunities\n\nRequirements:\n\nBachelor Degree or above in\u00a0Biochemistry, Biology, Biomedical Science, Biomedical Engineering or related disciplines\nMinimum 2\u00a0years\u00a0sales experience in life science products is\u00a0highly preferable\nProactive, outgoing and positive attitude\nGood team player with strong sense of responsibility\nGood interpersonal, communication, negotiation and presentation skills in English and Cantonese, fluency in Mandarin will be an advantage\nCandidate with less experience will be considered as Marketing Specialist\n\nWe offer attractive remuneration package to the right candidate, including basic salary (13 months), commission, travel allowance,\u00a05-day work per week, medical insurance, MPF \u2026etc. Interested parties please send resume with expected salary by clicking \"APPLY NOW\".\n\n(All personal information will be kept for a maximum of three months and will be used for employment purpose only.)", "employment_types": ["Full Time"], "selling_points": [], "locations": ["Sheung Wan"], "categories": ["Sciences, Lab, R&D", "Life Science", "Sales, CS & Business Devpt", "Direct Sales"], "post_time": "2022-01-13T03:34:57Z", "salary": {"currency": null, "max": null, "min": null, "period": "monthly", "term": null}, "salary_visible": false, "title_keywords": ["specialist", "sales"], "responsibilities": ["reporting", "marketing plans", "develop", "sales team", "career development", "sales & marketing activities"], "requirements": {"degrees": ["degree or above", "bachelor"], "majors": ["biomedical science", "biomedical engineering", "biology", "related disciplines"], "languages": ["cantonese", "english", "mandarin"], "language_level": ["fluency", "advantage", "good"], "hard_skills": ["basic"], "soft_skills": ["outgoing", "good team player", "negotiation", "sense of responsibility", "positive attitude", "communication", "presentation skills", "proactive", "interpersonal"], "languages_combined": [{"language": "cantonese", "language_level": ["advantage", "good"]}, {"language": "english", "language_level": ["advantage", "good"]}, {"language": "mandarin", "language_level": ["fluency", "advantage", "good"]}]}, "experience_required": {"duration": ["minimum 2 years"], "field": ["marketing"]}}, {"job_id": "100003009040020", "location_code": "hk", "company": "Bio-Gene Technology Limited", "job_title": "Senior Marketing  Specialist  (Equipment Division)", "description": "Overview:\nWe are looking for responsible nice working attitude high ethical standard persons to join our new highly sophisticated and automation laboratory.\u00a0Numerous full-time posts with attractive salaries depend on experience.\n\nLaboratory Assistant\n\nDegree Holder, Higher Diploma holder in a Medical Laboratory, Biology Studies, or BSc equivalent\nShift Duties\nproviding support for the medical laboratory operation\nData entry, maintenance of supplies and equipment\nAssisting in initial specimen preparation and reports preparation\nOn the job training and opportunity to be recommended to study HTC at HKU SPACE\nFresh graduates are all welcome for the job application\n\nWe offer an attractive basic salary, on-the-job training and career advancement opportunity to the right candidates.\u00a0 Please send full resume with availability and expected salary by clicking \"Apply Now\"\u00a0\n\n\u00a0\u00a0Benefits\n\nBank Holidays\nMedical Insurance\n12 Days Annual leave\nPaid Marriage Leave\nBirthday Leave\n(Personal data collected will be used for recruitment purpose only.)", "employment_types": ["Full Time", "Permanent"], "selling_points": [], "locations": ["Shatin Area"], "categories": ["Sciences, Lab, R&D", "Life Science", "Medical Services", "Medical Services Technician", "Sales, CS & Business Devpt", "Technical Sales / Sales Engineer"], "post_time": "2022-01-12T00:34:36Z", "salary": {"currency": null, "max": null, "min": null, "period": "monthly", "term": null}, "salary_visible": false, "title_keywords": ["specialist"], "responsibilities": ["maintenance", "reports", "providing support", "data entry"], "requirements": {"degrees": ["higher diploma holder", "bsc", "degree holder"], "majors": ["biology"], "languages": [], "language_level": [], "hard_skills": ["nice", "maintenance"], "soft_skills": ["sophisticated", "ethical", "responsible"], "languages_combined": []}, "experience_required": {"duration": [], "field": []}}, {"job_id": "100003009036697", "location_code": "hk", "company": "Phase Scientific International Limited", "job_title": "Laboratory Assistant", "description": "Duties\n\nMonitor and manage the process of testing procedures, including reception, handling, processing, storage and testing of human blood according to the Standard Operation Procedure (SOP)\nEstablish new and review current SOP\nReview and approve quality control data for testing\nReview and approve laboratory report\nParticipate in-house and external training as required\nOther ad-hoc duties are also required\n\nRequirements\n\nValid Medical Laboratory Technologist Part I practicing cert issued by the HKMLT Board\nBachelor Degree or Higher Technical Certificate (HTC) in Biomedical Science, Medical Laboratory Sciences other related disciplines\nExperience in genetic/DNA analysis, including DNA extraction, sequencing, PCR etc. is preferable.\nStrong sense of responsibility\nMust be a good team worker with excellent communication skills as well as be able to work independently\nAble to communicate in Mandarin and Cantonese", "employment_types": ["Full Time", "Permanent"], "selling_points": ["Medical Lab Technologist", "Lab Assistant / Technician", "Molecular testing"], "locations": ["Kwun Tong"], "categories": ["Sciences, Lab, R&D", "Laboratory", "Life Science", "Others"], "post_time": "2022-01-10T12:46:09Z", "salary": {"currency": null, "max": null, "min": null, "period": "monthly", "term": null}, "salary_visible": false, "title_keywords": ["laboratory assistant"], "responsibilities": ["data", "review", "monitor", "procedures", "testing", "quality control", "ad-hoc duties", "report"], "requirements": {"degrees": ["certificate", "degree", "bachelor"], "majors": ["biomedical science", "related disciplines"], "languages": ["cantonese", "mandarin"], "language_level": [], "hard_skills": ["analysis"], "soft_skills": ["communication skills", "work independently", "sense of responsibility"], "languages_combined": [{"language": "cantonese", "language_level": []}, {"language": "mandarin", "language_level": []}]}, "experience_required": {"duration": [], "field": []}}, {"job_id": "100003009035412", "location_code": "hk", "company": "First Choice (Hong Kong) Medical Laboratory Limited", "job_title": "Medical Laboratory Technologist (Part I)", "description": "Responsibilities:\u00a0\n\nHandling of chemical tests related to routine sample;\nTest method development;\nInstrument calibration and maintenance;\nHandle any ad-hoc duties assigned.\n\nRequirements:\n\n\n\nHigher Diploma or above in Chemistry or relevant discipline;\nAt least 2 years working experience in testing laboratory;\nExperienced in analytical equipment (ICP-OES, ICP-MS) operation and maintenance\nFamiliar with HOKLAS requirements\nCandidate with less experience will be considered as Assistant Technical Officer\n\nWe offer attractive remuneration package and excellent career opportunities to the right candidates. Interested parties please send your full resume with availability, current and expected salary to\u00a0our HR department.\n\nWelcome to visit our company website\u00a0http://www.cmatesting.org/ or more information.\n\nWe are an Equal Opportunities Employer and welcome applications from all qualified candidates. All Personal data collected will be kept in strict confidence and used for recruitment purpose only.", "employment_types": ["Full Time", "Permanent"], "selling_points": [], "locations": ["Shatin Area"], "categories": ["Sciences, Lab, R&D", "Laboratory", "Life Science", "Medical Services", "Medical Services Technician"], "post_time": "2022-01-10T07:03:58Z", "salary": {"currency": "HKD", "max": 54999, "min": 35000, "period": "monthly", "term": null}, "salary_visible": true, "title_keywords": ["medical laboratory technologist"], "responsibilities": ["maintenance", "ad-hoc duties"], "requirements": {"degrees": ["higher diploma or above"], "majors": ["chemistry"], "languages": [], "language_level": [], "hard_skills": ["maintenance"], "soft_skills": [], "languages_combined": []}, "experience_required": {"duration": ["at least 2 years"], "field": ["laboratory", "testing"]}}, {"job_id": "100003009038267", "location_code": "hk", "company": "New Zeta Innoviation Limited", "job_title": "Senior Research Technician (Drug Efficacy research)", "description": "Assistant/Project Coordinator/ Arborist\n\nResponsibilities:\n\nAssist project manager to co-ordinate and monitor overall front-line soft landscape works to ensure works complying contract requirements;\nPrepare project documents, including method statements, work program, correspondences, tree survey reports, tree work proposals, etc.;\nAttend project progress/ coordination meeting;\nManage project operation in compliance with environmental and safety ordinance;\nCarry out tree survey& tree risk assessment and provide arboricultural treatment\n\nRecommendations to trees Qualification/ Requirements\n\nHigher diploma or bachelor degree (Major in biology, environmental science, or life science; arboriculture or plant biology would be an advantage)\nOne to two years or above solid work experience in landscape field would be an advantage\nWith driving license preferable\nProficiency in spoken & written English and Chinese preferable\nSound knowledge in MS office (Word, excel); AutoCAD preferable\nAble to work independently\n\nAttractive remuneration would be offered to suitable candidates. For application, please submit your resume to APPLY NOW,\u00a0attention to Ms. Rita Ng, along with a cover letter and expected remuneration.", "employment_types": ["Full Time", "Permanent"], "selling_points": ["Research Job in Professional firm", "Attractive remuneration and benefits", "5 days work and location closed to MTR"], "locations": ["Kowloon Bay"], "categories": ["Sciences, Lab, R&D", "Laboratory", "Life Science", "Research & Development (R&D)"], "post_time": "2022-01-11T06:23:59Z", "salary": {"currency": null, "max": null, "min": null, "period": "monthly", "term": null}, "salary_visible": false, "title_keywords": ["technician"], "responsibilities": ["compliance", "monitor", "project progress", "project documents", "reports", "coordination"], "requirements": {"degrees": ["diploma", "degree", "bachelor"], "majors": ["science", "biology", "environmental science"], "languages": ["english", "chinese"], "language_level": ["proficiency"], "hard_skills": ["excel", "autocad", "word", "ms office"], "soft_skills": ["work independently", "coordination"], "languages_combined": [{"language": "english", "language_level": ["proficiency"]}, {"language": "chinese", "language_level": ["proficiency"]}]}, "experience_required": {"duration": ["one to two years"], "field": []}}, {"job_id": "100003009039265", "location_code": "hk", "company": "CMA Testing and Certification Laboratories Limited", "job_title": "Technical Officer - Inorganic Division", "description": "The Responsibilities:\n\nTo promote our extensive range of clinical diagnostic products to HA hospitals, private hospitals, private laboratories and institutions\nTo execute the annual sales plan to achieve the goals\nTo identify new business opportunities to achieve the continuous growth\nTo establish and maintain good relationship with target accounts\nTo provide good after sales services to gain customer loyalty\n\nThe Requirements:\n\nBachelor Degree in Science, preferable in Biomedical Science, Biotechnology, Biology, Chemistry or healthcare related disciplines\nPreferable 1-2 years sales or marketing experience in healthcare industry\nExcellent in customer relationship management & interpersonal skills\nSelf-motivate, independent and able to work under pressure\nResult-oriented and have positive working attitude\nGood command of English, Cantonese and Mandarin\nFresh graduate with good personality and aggressive character shall also consider\n\nBenefit including,\n\n12 Annual Leave\nMedical Insurance\nDental Insurance\nLife & Critical Illness Insurance\nPerformance Bonus\nMedical check up\nCompany trip\nBank Holiday\n\nInterested parties, please send your CV and expected package to us either to Room 1602-3, 16/F., Tower 2, Silvercord, 30 Canton Road, T.S.T., Kowloon, Hong Kong.\n\nAttention: Ms. Wong or by clicking \"Apply Now\".\n\nAll Personal data collected will be used for recruitment purpose only.", "employment_types": ["Full Time", "Permanent"], "selling_points": ["Chemical testing, analytical instruments", "Sample preparation, Instrument maintenance", "5 days,Medical, OT Pay,Double pay,Free shuttle bus"], "locations": ["Shatin Area"], "categories": ["Sciences, Lab, R&D", "Chemical", "Laboratory", "Life Science"], "post_time": "2022-01-11T09:14:34Z", "salary": {"currency": null, "max": null, "min": null, "period": "monthly", "term": null}, "salary_visible": false, "title_keywords": ["technical officer"], "responsibilities": ["business opportunities", "plan", "maintain good relationship"], "requirements": {"degrees": ["degree", "bachelor", "fresh graduate"], "majors": ["biomedical science", "science", "chemistry", "related disciplines", "biology"], "languages": ["cantonese", "english", "mandarin"], "language_level": ["good command"], "hard_skills": [], "soft_skills": ["independent", "positive working attitude", "interpersonal skills", "result-oriented", "work under pressure"], "languages_combined": [{"language": "cantonese", "language_level": ["good command"]}, {"language": "english", "language_level": ["good command"]}, {"language": "mandarin", "language_level": ["good command"]}]}, "experience_required": {"duration": ["1-2 years"], "field": ["healthcare industry", "marketing"]}}, {"job_id": "100003009035395", "location_code": "hk", "company": "Asia Landscaping Limited", "job_title": "Assistant/Project Coordinator/ Arborist", "description": "Medikonia Limited, a leading and fast-growing life science distribution company based in Hong Kong, is looking for passionate and entrepreneurial professionals to join our expanding team.\n\nSales Executive / Account Manager\n\nJob Highlights:\n\nSell and promote scientific research products\nReport to the Sales Manager\nBachelor Degree or above in Biological Sciences, Biotechnology, Life Sciences, Medical Sciences or other related major\nJob Responsibility:\n\nMaintain good relationships with existing clients from Universities, Commercial Laboratories, and Government Laboratories\nDevelop new accounts and sales opportunities in assigned territories\nAssist marketing team in preparation and proposing of marketing activities\nSupport team and other staff in ad-hoc duties\n\nRequirements:\n\nBachelor Degree or above in Life Science, Biological Sciences, Medical Science, or other related majors\n1-2 years of work experience in the research team, clinical lab, or similar work is an advantage\nFresh graduates are also welcome\nHigh caliber, responsible, and sales oriented\nGood command of English & Chinese (Cantonese & Mandarin), in written and spoken\u00a0\nWe offer attractive remuneration packages to the right candidates, including basic salary, high commission, 5-day work per week, medical insurance, MPF and etc.\n\nInterested applicants please apply for the positions by clicking\u00a0Apply Now\u00a0and upload your full resume with the expected salary\u00a0in the application.\n\n\n\n\n", "employment_types": ["Full Time"], "selling_points": ["Higher diploma or bachelor degree", "One to two years or above solid work experience", "With driving license preferable"], "locations": ["Shatin Area"], "categories": ["Sciences, Lab, R&D", "Environmental Science / Waste Management", "Life Science", "Others", "Student / Fresh Graduate / No Experience"], "post_time": "2022-01-10T07:01:28Z", "salary": {"currency": null, "max": null, "min": null, "period": "monthly", "term": null}, "salary_visible": false, "title_keywords": ["project coordinator", "assistant"], "responsibilities": ["maintain", "ad-hoc duties", "develop"], "requirements": {"degrees": ["degree or above", "bachelor"], "majors": ["science"], "languages": ["cantonese", "english", "chinese", "mandarin"], "language_level": ["good command"], "hard_skills": ["basic"], "soft_skills": ["responsible"], "languages_combined": [{"language": "cantonese", "language_level": ["good command"]}, {"language": "english", "language_level": ["good command"]}, {"language": "chinese", "language_level": ["good command"]}, {"language": "mandarin", "language_level": ["good command"]}]}, "experience_required": {"duration": ["1-2 years"], "field": ["research team", "clinical"]}}, {"job_id": "100003009040524", "location_code": "hk", "company": "Sysmex Hong Kong Limited", "job_title": "Sales Executive/ Senior Sales Executive for In-vitro Diagnostics Products", "description": "Responsibilities\n\nDeliver good customer service to meet Company\u2019s service standard\nHandle and follow up enquires from Customers/ Business institutional \u00a0via different channels, such as phone calls, Whatsapp, and e-mail\nAct as the first contact point to handle customer inquiries through online platform or phone\nProvide consultations to introduce our services to customers through effective communication\nCommunicate with customers to plan & arrange photo shooting based on customers' needs\nPerform document entry, updates, filing regularly and work all around CS team\nPerform service evaluation and innovation\nPerform ad hoc duties as assigned\nRequirements\n\nUniversity graduate in science\u00a0or related disciplines\n1-2 years relevant working experience, medical clinic experience is highly preferred.\nProfessional telephone manner with excellent communication and interpersonal skills\nMature with a positive attitude, patient, self-motivated\nGood command of spoken and written English, Chinese and Mandarin\nProficient in MS Office (especially Excel)", "employment_types": ["Full Time", "Permanent"], "selling_points": ["Clinical Diagnostics Products", "To execute the annual sales plan", "Bachelor Degree in Science"], "locations": ["Tsim Sha Tsui"], "categories": ["Sales, CS & Business Devpt", "Customer Service - Supervisor / Officer", "Sciences, Lab, R&D", "Life Science", "Account Servicing"], "post_time": "2022-01-12T04:09:13Z", "salary": {"currency": null, "max": null, "min": null, "period": "monthly", "term": null}, "salary_visible": false, "title_keywords": ["senior sales executive", "sales executive"], "responsibilities": ["communicate with", "ad hoc duties", "service standard", "customer inquiries", "customers' needs", "communication", "customer service", "contact", "plan", "evaluation", "phone calls"], "requirements": {"degrees": ["university graduate"], "majors": ["related disciplines", "science"], "languages": ["english", "chinese", "mandarin"], "language_level": ["good command"], "hard_skills": ["excel", "ms office"], "soft_skills": ["self-motivated", "mature", "positive attitude", "communication and interpersonal skills", "patient", "telephone manner"], "languages_combined": [{"language": "english", "language_level": ["good command"]}, {"language": "chinese", "language_level": ["good command"]}, {"language": "mandarin", "language_level": ["good command"]}]}, "experience_required": {"duration": ["1-2 years"], "field": ["clinic", "relevant working experience", "medical"]}}, {"job_id": "100003009045111", "location_code": "hk", "company": "Medikonia Limited", "job_title": "Sales Executive / Account Manager", "description": "Responsibilities:\n\nParticipate in the development project of an in-vitro diagnostic device;\nResponsible for material choice and procurement, quality control for purchased materials;\nConduct manufacturability review for parts and system design;\nDevelop and review technical drawing and tolerance stacks;\nConduct design verification testing of developed prototype and to develop jig and fixtures;\nConduct design risk analysis and technical documentations as required;\nConduct patent / literature search on current and new material, technologies and processes.\nDetermine all reagents in the spotting solution and test compatibility.\n\nRequirements:\n\nBachelor degree or above in electronic engineering or related field;\n4\u00a0years relevant working experience preferred;\nPrevious experience in electro-mechanical\u00a0product design and development with medical device, diagnostic device, particularly in the areas of fluid management, microfluidics, pneumatic design, imaging is an advantage;\nExperience in mechanical design CAD tools such as SolidWorks is a MUST;\nGood technical experience in design, debug and problem solving;\nFamiliar with ISO13485 and CE/IVD directive is a PLUS.\nExperience in DFM, DFMEA is a MUST\nExperience in Heat and Fluid Simulation is a PLUS.\nMature, responsible, independent, detail-minded and able to work under pressure;\nPositive, self-starter and willing to take up and resolves technical challenges;\nSelf-motivated and able to work independently;\nGood command in both verbal and written Chinese and English.\n\nIf you are passionate, driven and looking for a new and exciting opportunity within a successful and growing company, this may be the right role for you.\n\nPlease click \u201cApply Now\u201d to submit your application.\n\nAll Personal data collected will be strictly confidential and used for recruitment purpose only. Applicants who are not invited to an interview within one month from the closing date should consider their applications unsuccessful. If you are not selected, all data will be destroyed within six months from the date you applied.\u00a0", "employment_types": ["Full Time", "Permanent"], "selling_points": [], "locations": ["Mong Kok"], "categories": ["Sciences, Lab, R&D", "Life Science", "Sales, CS & Business Devpt", "Account Servicing", "Technical Sales / Sales Engineer"], "post_time": "2022-01-13T18:55:06Z", "salary": {"currency": null, "max": null, "min": null, "period": "monthly", "term": null}, "salary_visible": false, "title_keywords": ["account manager", "sales executive"], "responsibilities": ["review", "design", "develop", "testing", "system design", "risk analysis", "quality control", "technical drawing"], "requirements": {"degrees": ["degree or above", "bachelor"], "majors": ["engineering"], "languages": ["english", "chinese"], "language_level": ["good command"], "hard_skills": ["problem solving", "cad", "plus", "solidworks"], "soft_skills": ["detail-minded", "passionate", "self-motivated", "work independently", "independent", "responsible", "mature", "problem solving", "driven", "positive", "work under pressure"], "languages_combined": [{"language": "english", "language_level": ["good command"]}, {"language": "chinese", "language_level": ["good command"]}]}, "experience_required": {"duration": ["4 years"], "field": ["management", "development", "relevant working experience", "design", "medical device", "product design"]}}, {"job_id": "100003009047404", "location_code": "hk", "company": "Hai Kang Life Corporation Ltd", "job_title": "Senior Mechanical Engineer", "description": "The Job\n\nYou will be expected to:\n\nPerform In-house and On-site pipette calibrations, repairs, and maintenance in accordance with standard operation procedures;\nPrepare calibration reports;\nCarry out maintenance of laboratory equipment, inventory control, QC/QA procedures;\nManage spare parts and consumables, sourcing and purchasing as needed;\nSupport the Laboratory\u2019s development, strategy planning and SOP setting;\nOther ad-hoc duties assigned by the Laboratory Manager\n\nThe Candidate\n\nYou should have:\n\n\nA higher diploma / associate degree / degree in science or engineering discipline;\n1-2 years working experiences in a laboratory (less experienced applicant with good academic results will also be considered);\nBasic understanding of HOKLAS / ISO 17025 requirements; measurement systems and metrology principles;\nFluent in English (both Oral and written) and Mandarin;\nProactive to learn and willing to pick up challenges;\nSelf-motivated, attention to details, problem-solving skills and good interpersonal skills.\nWe offer attractive remuneration package including five-day work week, bank holidays, medical insurance, double pay, performance bonus and excellent career opportunities to the right candidates. Interested parties please send your full resume with availability, current and expected salary to\u00a0our HR department.\n\nWelcome to visit our company website http://www.gilson.com/ or more information.\n\nWe are an Equal Opportunities Employer and welcome applications from all qualified candidates. All Personal data collected will be kept in strict confidence and used for recruitment purpose only.", "employment_types": ["Full Time", "Permanent"], "selling_points": ["Mechanical Engineer", "Comfortable working environment", "Compatitive Salary"], "locations": ["Shatin Area"], "categories": ["Engineering", "Electrical / Electronics", "Sciences, Lab, R&D", "Life Science", "Research & Development (R&D)"], "post_time": "2022-01-14T03:01:29Z", "salary": {"currency": null, "max": null, "min": null, "period": "monthly", "term": null}, "salary_visible": false, "title_keywords": ["senior mechanical engineer"], "responsibilities": ["maintenance", "systems", "procedures", "measurement", "inventory control", "reports", "ad-hoc duties", "insurance", "planning"], "requirements": {"degrees": ["associate degree", "diploma", "degree"], "majors": ["science", "engineering"], "languages": ["english", "mandarin"], "language_level": ["fluent"], "hard_skills": ["problem-solving skills", "basic", "maintenance"], "soft_skills": ["oral", "self-motivated", "interpersonal skills", "attention to details", "ad-hoc duties", "problem-solving skills", "proactive"], "languages_combined": [{"language": "english", "language_level": ["fluent"]}, {"language": "mandarin", "language_level": ["fluent"]}]}, "experience_required": {"duration": ["1-2 years"], "field": ["laboratory"]}}, {"job_id": "100003009037303", "location_code": "hk", "company": "Gilson China Limited", "job_title": "Service Technician (Calibration) - New headcount", "description": "Founded in 2014, Prenetics is a major global diagnostics and genetic testing company with the mission to bring health closer to millions of people globally and decentralize healthcare by making the three pillars \u2014 Prevention, Diagnostics and Personalized Care \u2014 comprehensive and accessible to anyone, at anytime and anywhere. Prenetics is led by visionary entrepreneur,\u00a0Danny Yeung, with a team of over 800 employees and operations across 9 locations, including\u00a0United Kingdom,\u00a0Hong Kong,\u00a0India,\u00a0South Africa, and\u00a0Southeast Asia. Prenetics develops consumer genetic testing and early colorectal cancer screening; provides COVID-19 testing, rapid point of care and at-home diagnostic testing and medical genetic testing.\n\nMost recently, Prenetics made\u00a0international headlines to become the first Unicorn in Hong Kong to publicly list on the Nasdaq via merger with\u00a02021 Adrian Cheng's Artisan Acquisition Corp, valuing Prenetics at approximately US $1.7b.\n\nMake a difference to the community! Let's fight COVID-19 together for Hong Kong and make Hong Kong safe again. This is a unique opportunity to make a difference to the community and to play a role to fight COVID-19 here in Hong Kong. The faster we identify, the faster we can stop the virus chain!\n\nResponsibilities\u00a0\n\nAssist Medical Laboratory Technicians and Assistant Technical Officers for the specimens pre-processing steps, e.g. equipment calibration and daily laboratory operational maintenance\nConduct assigned laboratory and administrative tasks to ensure timely delivery and accuracy of tests\nComply with all current best-in-class laboratory practices and laboratory standard operating procedure and company policies and procedures\nHandle ad hoc record data into the laboratory system and databases\u00a0\nPerform quality control and external proficiency testing\n\nOur ideal candidate will have\n\nExperience in processing of clinical laboratory testing would be an advantage\nFluent in Cantonese and English, writing and speaking, fluency in Mandarin a plus\nStrong sense of teamwork and able to work under pressure\nComfortable and flexible in a fast-paced, dynamic team environment\nShift and weekend duties are required, extra\u00a0monetary\u00a0incentives for overnight shifts\nStrong commitment to the vision and mission of Prenetics and our focus on Health and Wellness\nAbility to work independently\nSelected candidates will be offered HKD 100 per hour (plus overnight incentives\n\nOur DNA is\u00a0P-R-E-N-E-T-I-C-S.\u00a0See what each word of our company name means:\n\nPassion\n\nYou love what you do and accomplish amazing result\nYou spread positivity, bring enthusiasm to work and inspire team members\nYou drive team toward specific goals, even when they seem unlikely or difficult\n\nResilience\n\nYou embrace changes and be able to drive through uncertainty, ambiguity and uncomfortable situations\nYou bounce back quickly from setbacks and challenges\nYou are persistent and determined to achieve the desired outcome\n\nEmpowerment\n\nYou trust others to play their positions well like an elite sports team\nYou foster a strong team spirit while encouraging others to take initiatives and risks\nYou create a space to allow team to grow and hold each other accountable\n\niNtegrity\n\nYou are trustworthy and lead by example\nYou are consistent in your message and action all the times\nYou deliver what you have promised\n\nEpic\n\nYou challenge your own comfort zone and always outperform yourself\nYou make meaningful and amazing impact to the world\nYou dare to take risks\n\nTransparency\n\nYou are completely honest and committed to giving candid feedbacks, no matter how challenging it might be\nYou share ideas, knowledge and skills that empower others and create access to information with the wider team\nYou share wins and failures openly\n\nIngenuity\n\nYou make sound judgement and come up with solutions that are creative and smart. Copy when feasible\nYou challenge the status quo and question things that could be done differently for better. Modify the wheel if you can\u2019t change it\nYou think outside of the box and make value-based innovation\n\nCommunication\n\nYou articulate your thoughts and ideas effectively and respectfully\nYou know your audience and talk in a way they want to be told\nYou make sure communications happens, no matter where you are\n\nSelfless\n\nYou put the needs of others before one's own and find ways in helping other to succeed\nYou focus on team wins than personal wins and share credits\nYou act in the company's best interest\n\nWe are Prenetics, our people make us who we are.", "employment_types": ["Full Time", "Permanent"], "selling_points": ["non-testing laboratory technician", "Overseas training opportunity", "Five-day work week, Medical insurance, bonus"], "locations": ["Ngau Tau Kok"], "categories": ["Sciences, Lab, R&D", "Laboratory", "Life Science", "Others", "Technician"], "post_time": "2022-01-11T02:24:10Z", "salary": {"currency": null, "max": null, "min": null, "period": "monthly", "term": null}, "salary_visible": false, "title_keywords": ["technician"], "responsibilities": ["ad hoc", "ideas", "maintenance", "data", "operations", "policies", "procedures", "testing", "communication", "databases", "quality control", "administrative tasks", "work under pressure"], "requirements": {"degrees": [], "majors": [], "languages": ["cantonese", "english", "mandarin"], "language_level": ["fluency", "fluent"], "hard_skills": ["plus", "no", "maintenance", "word", "make", "safe", "dynamic", "c", "databases", "rapid", "r", "focus", "processing"], "soft_skills": ["team spirit", "trustworthy", "persistent", "communication", "comprehensive", "visionary", "articulate", "focus", "work under pressure", "determined", "integrity", "committed", "honest", "creative", "ideal", "work independently", "unique", "dynamic", "flexible", "timely", "teamwork", "accountable"], "languages_combined": [{"language": "cantonese", "language_level": ["fluent"]}, {"language": "english", "language_level": ["fluent"]}, {"language": "mandarin", "language_level": ["fluency"]}]}, "experience_required": {"duration": [], "field": ["laboratory testing", "clinical"]}}, {"job_id": "100003009034543", "location_code": "hk", "company": "Prenetics Limited", "job_title": "Part-time Laboratory Assistant", "description": "The appointee will assist in local and/or international clinical research and work under the Division of Gastroenterology and Hepatology, mainly at the Prince of Wales Hospital in Shatin or in the community.\n\nDuties include:\n\n\nwriting protocols and consent forms for ethics application and amendment;\u00a0\ncoordinating clinical research projects with tasks involving patient recruitment and follow-up and\nSpecimen and data collection and database management\nJob requirement:\n\na Bachelor\u2019s degree in Science or equivalent\nhave good interpersonal, organizational, and communication skills;\ngood command of both written and spoken English and Chinese (Cantonese and Putonghua);\nHaving clinical research experience will be an advantage.\n\nThe appointee will work mainly in Hong Kong Science Park and the Prince of Wales Hospital in Shatin.\n\nThe appointment will initially be made on a contract basis for one year, renewable subject to mutual agreement.", "employment_types": ["Part Time", "Permanent"], "selling_points": ["fast-paced, dynamic team environment", "Proactive, energetic and fun culture", "Part-time, HKD 100 per hour"], "locations": ["Quarry Bay"], "categories": ["Sciences, Lab, R&D", "Laboratory", "Life Science", "Research & Development (R&D)"], "post_time": "2022-01-10T03:37:44Z", "salary": {"currency": null, "max": null, "min": null, "period": "monthly", "term": null}, "salary_visible": false, "title_keywords": ["laboratory assistant"], "responsibilities": ["management", "research projects", "recruitment", "database", "data collection"], "requirements": {"degrees": ["degree", "bachelor"], "majors": ["science"], "languages": ["cantonese", "putonghua", "english", "chinese"], "language_level": ["good command"], "hard_skills": [], "soft_skills": ["communication skills", "organizational", "interpersonal"], "languages_combined": [{"language": "cantonese", "language_level": ["good command"]}, {"language": "putonghua", "language_level": ["good command"]}, {"language": "english", "language_level": ["good command"]}, {"language": "chinese", "language_level": ["good command"]}]}, "experience_required": {"duration": [], "field": ["research", "clinical"]}}, {"job_id": "100003009040432", "location_code": "hk", "company": "TR at CUHK Company Limited", "job_title": "Junior Research Assistant / Research Assistant", "description": "Responsibilities\n\nCoordinate product development projects of new health supplements, for instance, formulation design, ingredient research, production setup & monitoring, etc.\nConduct literature and market trend research such as overviews of disease management, latest research findings, competitor landscape, etc.\nDevelop educational materials on health, food and science that are on target per client needs and company\u2019s directions\nWork closely with internal stakeholders such as Marketing and Sales teams in market research and new product launch\nLiaise with CRO institutions on the project progress and results\n\nQualifications\n\nMaster's degree or above in Biological Sciences, Organic Chemistry, Immunology or medical-related disciplines, with at least 3 years work experience in healthcare/research industry\nExcellent written and verbal communications\u00a0in science\nSelf-motivated, well-organised and proactive\nProficiency in MS Office application - Excel, Word, PowerPoint, and key software applications relevant to literature research (e.g., EndNote, literature search indices, journal databases, BLAST, etc.)\nFluency in both written and spoken English & Chinese (Cantonese & Mandarin)", "employment_types": ["Full Time", "Contract"], "selling_points": [], "locations": ["Shatin Area"], "categories": ["Sciences, Lab, R&D", "Laboratory", "Life Science", "Research & Development (R&D)"], "post_time": "2022-01-12T02:34:28Z", "salary": {"currency": null, "max": null, "min": null, "period": "monthly", "term": null}, "salary_visible": false, "title_keywords": ["research assistant", "junior"], "responsibilities": ["management", "software", "monitoring", "teams", "market research", "design", "develop", "coordinate", "project progress", "databases", "liaise with", "setup"], "requirements": {"degrees": ["degree or above", "master"], "majors": ["related disciplines", "chemistry"], "languages": ["cantonese", "english", "chinese", "mandarin"], "language_level": ["fluency"], "hard_skills": ["excel", "word", "powerpoint", "databases", "ms office"], "soft_skills": ["well-organised", "self-motivated", "proactive"], "languages_combined": [{"language": "cantonese", "language_level": ["fluency"]}, {"language": "english", "language_level": ["fluency"]}, {"language": "chinese", "language_level": ["fluency"]}, {"language": "mandarin", "language_level": ["fluency"]}]}, "experience_required": {"duration": ["at least 3 years"], "field": ["related", "healthcare", "research", "medical"]}}, {"job_id": "100003009035649", "location_code": "hk", "company": "Prokentide Biotechnology Limited", "job_title": "Associate, Research & Development", "description": "Overview:\nThe position will be responsible for project planning, providing progress updates, and designing and performing experiments. We are a high energy biotech company that is driven by technological innovation, and therefore requires an R&D team that can manage a fast-paced environment, rapidly evolving project goals, and hitting critical deadlines. This position will be expected to handle working on multiple projects at a time, in both supportive and lead roles. Initially, the main efforts will be to develop our molecular sample preparation product line, as well as work on innovative research projects that investigate new uses for our technology. The position is expected to be able to work independently and to provide guidance to the junior research staff.\n\nSenior Research Associate\n\nResponsibilities:\n\n\nIndependently design protocols and perform experiments to achieve desired project objectives.\nSpend between 50-80% of working time at the lab bench performing experiments and generating data.\nBecome familiar with new experimental techniques and equipment. Develop sufficient knowledge to independently troubleshoot malfunctioning equipment and experimental processes, and to provide corrective action recommendations.\nAnalyze raw data from experiments, generate figures, and derive meaningful conclusions based on the results.\nPut together concise presentation slides on a regular basis to update the project managers and team members on project progress.\nClearly and succinctly present results and findings at group meetings.\nWrite reports to summarize and document the progress and outcomes of research projects.\nRead scientific literature to support fundamental understanding of technology and research projects.\nWork closely with chemistry and molecular biology groups to develop our molecular sample preparation kits and improve the resulting DNA sequencing performance.\nContribute to project planning, generating timelines, and objective formation.\nAssume responsibility for timely completion of projects, ensuring activities are consistent with project critical path, and responding appropriately to changing priorities. Ensure technical activities under delegated supervision are conducted within internal and external guidelines and regulations.\nDevelop, track, and manage detailed development program timelines, deliverables, and milestone progress.\nWork on multiple projects at a time, in either a supportive or lead role.\nAssist with general lab and equipment maintenance, and R&D material purchasing.\nProvide technical advice, guidance, and training to junior scientific staff, and serve as a role model.\n\nKnowledge and Skill Requirements:\n\nPh.D. in molecular biology, microbiology, biochemistry or related fields. 1-3 years of additional working experience in research and development is preferred. OR Bachelor\u2019s degree in molecular biology, microbiology, biochemistry or related fields with minimum 3 years working experience in research and development.\nAdvanced understanding of scientific processes and analysis of empirical data. Demonstrated ability to design and execute experimental protocols.\nExperience working with in-vitro diagnostics is preferred.\nAbility to work well in teams and across disciplines with complex systems.\nExcellent written and oral communication skills.\nHigh internal standard for quality of research.\nThe candidate should be passionate and self-motivated with a strong desire to acquire on-the-job training.\nScientist\u00a0\n\n\nResponsibilities:\n\nIndependently design protocols and perform experiments to achieve desired project objectives.\nSpend between 30-50% of working time at the lab bench performing experiments and generating data.\nBecome familiar with new experimental techniques and equipment. Develop sufficient knowledge to independently troubleshoot malfunctioning equipment and experimental processes, and to provide corrective action recommendations.\nDevelop a deep understanding of the company\u2019s core technology and the scientific principles that guide the technology\u2019s development.\nAnalyze raw data generated from a team\u2019s experiments, generate figures, and derive meaningful conclusions based on the results.\nPut together concise presentation slides on a regular basis to update the project managers and team members on project progress.\nClearly and succinctly present results and findings at group meetings.\nWrite reports to summarize and document the progress and outcomes of research projects.\nRead scientific literature to support fundamental understanding of technology and research projects.\nAct as the technical lead in the product development process. Take ownership of the R&D function\u2019s project planning, objective formation, and hitting deadlines.\nAct as the technical lead in contract research projects. Support management of the contract research projects, including application drafting, reporting writing, and contract research relationship management. \u00a0\nAssume responsibility for timely completion of projects, ensuring activities are consistent with project critical path, and responding appropriately to changing priorities. Ensure technical activities under delegated supervision are conducted within internal and external guidelines and regulations.\nDevelop, track, and manage detailed development program timelines, deliverables, and milestone progress.\nWork on multiple projects at a time, in either a supportive or lead role.\nManage general lab and equipment maintenance, and R&D material purchasing.\nProvide technical advice, guidance, and training to junior scientific staff, and serve as a role model.\n\nKnowledge and Skill Requirements:\u00a0\n\nPh.D. in molecular biology, microbiology, biochemistry or related fields with minimum 2 years of work experience OR post-doctoral experience in research and wet lab-related position.\nFamiliarity with product development and ISO 13485 design control process requirements is preferred.\nExperience working with in-vitro diagnostics is preferred.\nAdvanced understanding of scientific processes and analysis of empirical data. Demonstrated ability to design and execute experimental protocols.\nAbility to work well in teams and across disciplines with complex systems.\nAbility to manage small project teams.\nExcellent written and oral communication skills.\nHigh internal standard for quality of research.\nThe candidate should be passionate and self-motivated with a strong desire to acquire on-the-job training.\n\nWe offer an attractive basic salary, 5-day work, on-the-job training and career advancement opportunity to the right candidates.\u00a0 Please send full resume with availability, current and expected salary by clicking \"Apply Now\"\u00a0\n\n\n(Personal data collected will be used for recruitment purpose only.)", "employment_types": ["Full Time"], "selling_points": ["3+ years in healthcare/research", "New product development in health supplements", "Fast-paced, startup-like environment"], "locations": ["Hung Hom"], "categories": ["Sciences, Lab, R&D", "Food Science", "Life Science", "Research & Development (R&D)"], "post_time": "2022-01-10T08:01:55Z", "salary": {"currency": null, "max": null, "min": null, "period": "monthly", "term": null}, "salary_visible": false, "title_keywords": ["associate"], "responsibilities": ["regulations", "guidance", "project planning", "maintenance", "data", "research projects", "sample preparation", "guidelines", "technical advice", "project progress", "design", "develop", "reports", "troubleshoot", "multiple projects"], "requirements": {"degrees": ["degree", "bachelor"], "majors": ["molecular biology", "microbiology"], "languages": [], "language_level": [], "hard_skills": ["r&d", "analysis", "small", "maintenance"], "soft_skills": ["passionate", "communication skills", "oral", "self-motivated", "independently", "advanced", "supportive", "timely", "deep", "troubleshoot", "presentation", "detailed"], "languages_combined": []}, "experience_required": {"duration": ["minimum 2 years", "1-3 years", "minimum 3 years"], "field": ["related", "development", "research"]}}, {"job_id": "100003009031766", "location_code": "hk", "company": "Phase Scientific International Limited", "job_title": "Senior Research Associate / Scientist", "description": "The Job:\nCoordinate and participate in preclinical and/or clinical research\nConduct cell culture experiments and support the drug mechanisms study\nConduct animal experiments to evaluate the drug efficacy & safety\nDesign, implementation and documentation of pre-clinical study\nSupport the samples testing for clinical trials\nDocumentation support for clinical trial application(s)\nThe Person:\nMaster/Mphil in Life Sciences, Biochemistry, Biotechnology, Biology or related disciplines\nExperience in animal study is preferred\nExperience in cell culture and basic biochemical technique (Western blot, qPCR, immunostaining) is preferred\nHighly proficient in spoken & written English and Chinese\nGood interpersonal, communications and presentation skills are essential\nCandidate with less experience will be considered as Research Technician\nWe offer attractive remuneration and benefits, 5-day work week, annual leave, medical scheme, comprehensive training and career development opportunities to the qualified candidates.\nPlease send your application with full resume stating your present and expected salary to the Company by clicking\u00a0on the \"Apply now\" or by following methods.\u00a0Please quote the\u00a0reference number\u00a0of the applied position in the subject field.\u00a0\nMail:\u00a0Human Resources Department, New\u00a0Zeta Innovation Limited, 18 Chevalier Commercial Centre, 8 Wang Hoi Road, Kowloon Bay, Kowloon, Hong Kong.\nPersonal data collected will be used for recruitment purpose only.", "employment_types": ["Full Time", "Permanent"], "selling_points": ["Research and Development", "Project planning,designing & performing experiment", "Develop molecular sample preparation product"], "locations": ["Kwun Tong"], "categories": ["Sciences, Lab, R&D", "Laboratory", "Life Science", "Research & Development (R&D)"], "post_time": "2022-01-07T09:44:16Z", "salary": {"currency": null, "max": null, "min": null, "period": "monthly", "term": null}, "salary_visible": false, "title_keywords": ["research associate", "scientist"], "responsibilities": ["implementation", "design", "testing", "coordinate", "evaluate", "documentation"], "requirements": {"degrees": ["master"], "majors": ["related disciplines", "biology"], "languages": ["english", "chinese"], "language_level": ["proficient"], "hard_skills": ["basic", "scheme"], "soft_skills": ["presentation skills", "comprehensive", "interpersonal"], "languages_combined": [{"language": "english", "language_level": ["proficient"]}, {"language": "chinese", "language_level": ["proficient"]}]}, "experience_required": {"duration": [], "field": ["research"]}}, {"job_id": "100003009037285", "location_code": "hk", "company": "Smart Cells (H.K.) Limited", "job_title": "Sales Consultant", "description": "Job description\n\n\nKey responsibilities\n\n\nTo promote and sell umbilical cord blood and cord banking services to customers\nTo achieve pre-set sales targets and prepare sales forecast\nTo prepare quotations, proposals to customers\nTo maintain good after-sales service and excellent relationship with customers and healthcare professionals\n\n\nRequirements\n\n\nUniversity graduate in Science or related disciplines\nPreferably with 1-2 years of sales experience\nExcellent communication, interpersonal and negotiation skills\nAccountable, self-motivated and a good team player\nGood command of written and spoken English and Chinese\nProficient in MS Office applications\nCandidates with more experience will be considered as \"Senior Sales Executive\"\nFresh graduates are also encouraged to apply\n\n\nYour role at Smart Cells is integral to helping the world meet the breakthroughs of stem cells. We are company that is for life.\n\n\nInterested parties, please send your resume with expected salary by clicking APPLY NOW.\n", "employment_types": ["Full Time"], "selling_points": ["University graduate in Science", "Preferably with 1-2 years of sales experience", "Fresh graduates are also encouraged to apply"], "locations": ["Central"], "categories": ["Sales, CS & Business Devpt", "Business Development", "Sciences, Lab, R&D", "Life Science", "Medical Services", "Others"], "post_time": "2022-01-11T02:19:40Z", "salary": {"currency": null, "max": null, "min": null, "period": "monthly", "term": null}, "salary_visible": false, "title_keywords": ["sales consultant"], "responsibilities": ["prepare sales", "after-sales service", "maintain", "forecast", "banking"], "requirements": {"degrees": ["university graduate"], "majors": ["related disciplines", "science"], "languages": ["english", "chinese"], "language_level": ["good command"], "hard_skills": ["ms office"], "soft_skills": ["self-motivated", "good team player", "accountable", "communication", "negotiation skills", "interpersonal"], "languages_combined": [{"language": "english", "language_level": ["good command"]}, {"language": "chinese", "language_level": ["good command"]}]}, "experience_required": {"duration": ["1-2 years"], "field": []}}, {"job_id": "100003009039904", "location_code": "hk", "company": "Online Marketing Genius Company Limited", "job_title": "Scientific content / medical writer", "description": "Responsibilities:\n\n\nContent development for promotional materials including prints and multimedia projects\nSymposium highlight or case sharing with reference support\nEngage in writing, editing and cross checking materials both in English and Chinese\nScientific support for multimedia project and creative storyboard for patient education program\nWork with teams to ensure all the projects/materials are accurate and on time\nFresh graduates are welcome\nRequirements:\n\nExcellent in English and Chinese writing\nFluent in English and Cantonese\nWilling to share knowledge or expereince and work as a team\nStrong background in science and pharmaceutical knowledge\nIndependent and able to work multi-task\nGood interpersonal skills to work with clients, healthcare professional and medical societies\nBenefit:\n\n5 days' work\nFlexible working hours\nBank holiday\nYear-end bonus\nOn the job training will be provided\n\nPlease email your CV and expected salary, as well as their earliest availability date if you are interested.\u00a0", "employment_types": ["Full Time", "Permanent"], "selling_points": ["Excellent in English and Chinese writing", "Strong science/research background", "Degree in Pharmacy/Bio-Science /Public Health"], "locations": ["Kwai Hing"], "categories": ["Sciences, Lab, R&D", "Life Science", "Medical Services", "Pharmaceutical", "Research & Development (R&D)"], "post_time": "2022-01-11T14:34:58Z", "salary": {"currency": null, "max": null, "min": null, "period": "monthly", "term": null}, "salary_visible": false, "title_keywords": [], "responsibilities": ["editing", "promotional materials", "teams", "checking"], "requirements": {"degrees": [], "majors": [], "languages": ["cantonese", "english", "chinese"], "language_level": ["excellent", "fluent"], "hard_skills": [], "soft_skills": ["multi-task", "independent", "work as a team", "interpersonal skills"], "languages_combined": [{"language": "cantonese", "language_level": ["fluent"]}, {"language": "english", "language_level": ["excellent", "fluent"]}, {"language": "chinese", "language_level": ["excellent"]}]}, "experience_required": {"duration": [], "field": []}}, {"job_id": "100003009036626", "location_code": "hk", "company": "STA Pacific Limited", "job_title": "(Senior) Product Specialist, Global Medical Device Company (Surgical/Medical Devices/Consumables)", "description": "We have multiple well-known global medical device clients that are looking for Sales talents to join their teams to promote various types of products, including:\n\nmedical devices\nmedical consumables\ndiagnostic\nmedical aesthetic\n\n\u00a0Key Responsibilities:\n\nPromote product portfolio in an assigned territories\nDrive sales growth and meet business targets\nEstablish solid relationship with medical professionals with technical selling skills and product knowledge\nFoster relationship with key accounts\nGather intelligence of competitive activities and feedback to management\nEnsure adherence to company policies, procedures and business ethics\n\nRequirements:\n\n1-2 years of sales experience in healthcare industry is an advantage.\nGood communication and interpersonal skills\nIndependent and like to take challenges\u00a0\nCandidates with more experience will be consider for\u00a0Senior title\n\nInterested parties please send your CV by clicking \"Apply Now\".\u00a0 All personal information will be used strictly for recruitment purpose.\u00a0 Please assume your application has not been successful if you have not heard from us in two weeks' time.", "employment_types": ["Full Time", "Permanent"], "selling_points": ["pharmaceutical MNC", "Good development platform", "5 days work and competitive package"], "locations": ["Not Specified"], "categories": ["Sciences, Lab, R&D", "Life Science", "Medical Services", "Pharmaceutical", "Sales, CS & Business Devpt", "Direct Sales"], "post_time": "2022-01-10T11:25:53Z", "salary": {"currency": null, "max": null, "min": null, "period": "monthly", "term": null}, "salary_visible": false, "title_keywords": ["product specialist"], "responsibilities": ["management", "policies", "ensure adherence", "procedures", "drive sales", "promote product"], "requirements": {"degrees": [], "majors": [], "languages": [], "language_level": [], "hard_skills": [], "soft_skills": ["communication and interpersonal skills", "independent"], "languages_combined": []}, "experience_required": {"duration": ["1-2 years"], "field": ["healthcare industry"]}}, {"job_id": "100003009029461", "location_code": "hk", "company": "China Inspection Medical Laboratories Limited", "job_title": "Medical Technologist & Associate Medical Technologist (MPS 13-28)", "description": "Overview:\n\nThe position will be responsible for assisting the R&D team with day to day laboratory operations to support product development efforts. In addition, the role will be responsible for quality control documentation and maintaining laboratory best practices.\u00a0\u00a0\u00a0The position will have the opportunity to tackle a number of different projects with the potential for increased responsibilities, based on performance. The successful candidate will be expected to in a rapidly evolving and demanding fast growing environment.\n\nResearch Assistant\n\u00a0\nResponsibilities:\n\nLaboratory supply purchasing and inventory\nEquipment operation and maintenance\nFollow and perform experiments on the bench\nPreparation of research materials (e.g., buffers, product components, intermediates, supplies)\nQuality documentation and maintenance (e.g., inventory, record keeping, etc.)\n\nKnowledge and Skill Requirements:\n\nBachelor's or Higher diploma with work experience at a research laboratory\nFast learner with high attention to detail\nTeam oriented and places high value on developing a positive company culture\nAbility to grow from constructive criticism and mentorship\nDesire to work in a fast pace and demanding start-up environment (weekend hours when needed)\nEnjoys problem solving and critical thinking with an inquisitive mindset\nFresh graduates are welcome\nResearch Associate\n\nResponsibilities:\n\nWorking as a member of the R&D team to execute experiments for product development and optimization\nCollect and log experimental data\nContribute to experimental design and tactical direction of studies\nPerform relevant literature searches to elucidate and generate novel ideas\nReport and communicate all results and progress to supervisor and management on a regular basis\nOperate and maintain laboratory equipment\nPrepare laboratory and test materials (e.g., buffers, product components, intermediates)\nMaintain Laboratory documentation and operations (e.g., inventory, record keeping, basic maintenance)\n\nKnowledge and Skill Requirements:\n\nMaster's degree from an accredited university.\nPrevious laboratory experience (minimum 2 years) either in an academic life science or at a biotechnology company is an advantage\u00a0\nFast learner who can follow instructions closely and perform complex protocols with high attention to detail\nSelf-motivated with capability to take initiative\nTeam-oriented and places high value on developing a strong team culture\nEffectively communicates scientific ideas and results\nAbility to grow from constructive feedback and mentorship\n\n\nWe offer an attractive basic salary, 5-day work, on-the-job training and career advancement opportunity to the right candidates.\u00a0 Please send full resume with availability, current and expected salary by clicking \"Apply Now\"\u00a0\n\n\u00a0Benefits\n\n\u00a0\u00a0\u00a0\u00a0\u00a0\u00a0\u00a0\u00a0 Five-day work\n\u00a0\u00a0\u00a0\u00a0\u00a0\u00a0\u00a0\u00a0 Bank Holidays\n\u00a0\u00a0\u00a0\u00a0\u00a0\u00a0\u00a0\u00a0 Medical Insurance\n\u00a0\u00a0\u00a0\u00a0\u00a0\u00a0\u00a0\u00a0 12+ Days Annual leave\n\u00a0\u00a0\u00a0\u00a0\u00a0\u00a0\u00a0\u00a0 Paid Marriage Leave\n\u00a0\u00a0\u00a0\u00a0\u00a0\u00a0\u00a0\u00a0 Birthday Leave\n\n\u00a0(Personal data collected will be used for recruitment purpose only.)", "employment_types": ["Full Time", "Permanent"], "selling_points": [], "locations": ["Yuen Long"], "categories": ["Sciences, Lab, R&D", "Life Science", "Medical Services", "Medical Services Technician", "Others"], "post_time": "2022-01-07T05:19:14Z", "salary": {"currency": null, "max": null, "min": null, "period": "monthly", "term": null}, "salary_visible": false, "title_keywords": ["associate medical technologist", "medical technologist"], "responsibilities": ["documentation", "inventory", "quality", "maintenance"], "requirements": {"degrees": ["diploma", "degree", "bachelor", "master"], "majors": [], "languages": [], "language_level": [], "hard_skills": ["r&d", "basic", "maintenance", "problem solving", "documentation"], "soft_skills": ["self-motivated", "problem solving", "attention to detail", "novel", "initiative", "fast learner", "constructive", "positive"], "languages_combined": []}, "experience_required": {"duration": ["minimum 2 years"], "field": ["laboratory", "research"]}}, {"job_id": "100003009031673", "location_code": "hk", "company": "Phase Scientific International Limited", "job_title": "Research Assistant / Research Associate", "description": "\nPosition Summary:\n\nManage sales territories to sell Invitrogen biotech products. Understand and communicate customer requirements. Grow new clients as well as manage and retain the current customer base.\n\nResponsibilities:\n\n1. Implement sales strategies in coordination with Sales Manager. Develop sales strategies to increase market share.\n\n2. Plan, organize and manage a sales territory and balance the requirements of multiple business units. Identify and target new business/sales opportunities within the marketplace. Manage the sales cycle.\n\n3. Effectively communicate and negotiate sales contracts with customers/dealers .Educate customers/dealers on new products and product enhancements.\n\n4. Understand and communicate customer issues, current prospects and marketing events to sales management. Accurately articulate and present product features and benefits.\n\n5. Interpret and manage key financial result areas, i.e. revenues, volume, margins, days outstanding and forecasting.\n\nRequirements:\n\n1. Degree in Bioscience is a must. 2 years selling experience in biotech industry.\n\n2. Molecular biology experience is preferable.\n\n3. Good English communications in both oral and written.\n\n4. Result-oriented, hands-on\n\n5. Capability in handling both customers and dealers.\n\nPosition Summary:\n\nManage sales territories to sell Invitrogen biotech products. Understand and communicate customer requirements. Grow new clients as well as manage and retain the current customer base.\n\nResponsibilities:\n\n1. Implement sales strategies in coordination with Sales Manager. Develop sales strategies to increase market share.\n\n2. Plan, organize and manage a sales territory and balance the requirements of multiple business units. Identify and target new business/sales opportunities within the marketplace. Manage the sales cycle.\n\n3. Effectively communicate and negotiate sales contracts with customers/dealers .Educate customers/dealers on new products and product enhancements.\n\n4. Understand and communicate customer issues, current prospects and marketing events to sales management. Accurately articulate and present product features and benefits.\n\n5. Interpret and manage key financial result areas, i.e. revenues, volume, margins, days outstanding and forecasting.\n\nRequirements:\n\n1. Degree in Bioscience is a must. 2 years selling experience in biotech industry.\n\n2. Molecular biology experience is preferable.\n\n3. Good English communications in both oral and written.\n\n4. Result-oriented, hands-on\n\n5. Capability in handling both customers and dealers.\n\nPosition Summary:\n\nManage sales territories to sell Invitrogen biotech products. Understand and communicate customer requirements. Grow new clients as well as manage and retain the current customer base.\n\nResponsibilities:\n\n1. Implement sales strategies in coordination with Sales Manager. Develop sales strategies to increase market share.\n\n2. Plan, organize and manage a sales territory and balance the requirements of multiple business units. Identify and target new business/sales opportunities within the marketplace. Manage the sales cycle.\n\n3. Effectively communicate and negotiate sales contracts with customers/dealers .Educate customers/dealers on new products and product enhancements.\n\n4. Understand and communicate customer issues, current prospects and marketing events to sales management. Accurately articulate and present product features and benefits.\n\n5. Interpret and manage key financial result areas, i.e. revenues, volume, margins, days outstanding and forecasting.\n\nRequirements:\n\n1. Degree in Bioscience is a must. 2 years selling experience in biotech industry.\n\n2. Molecular biology experience is preferable.\n\n3. Good English communications in both oral and written.\n\n4. Result-oriented, hands-on\n\n5. Capability in handling both customers and dealers.\n\nPosition Summary:\n\nManage sales territories to sell Invitrogen biotech products. Understand and communicate customer requirements. Grow new clients as well as manage and retain the current customer base.\n\nResponsibilities:\n\n1. Implement sales strategies in coordination with Sales Manager. Develop sales strategies to increase market share.\n\n2. Plan, organize and manage a sales territory and balance the requirements of multiple business units. Identify and target new business/sales opportunities within the marketplace. Manage the sales cycle.\n\n3. Effectively communicate and negotiate sales contracts with customers/dealers .Educate customers/dealers on new products and product enhancements.\n\n4. Understand and communicate customer issues, current prospects and marketing events to sales management. Accurately articulate and present product features and benefits.\n\n5. Interpret and manage key financial result areas, i.e. revenues, volume, margins, days outstanding and forecasting.\n\nRequirements:\n\n1. Degree in Bioscience is a must. 2 years selling experience in biotech industry.\n\n2. Molecular biology experience is preferable.\n\n3. Good English communications in both oral and written.\n\n4. Result-oriented, hands-on\n\n5. Capability in handling both customers and dealers.\n\nPosition Summary:\n\nManage sales territories to sell Invitrogen biotech products. Understand and communicate customer requirements. Grow new clients as well as manage and retain the current customer base.\n\nResponsibilities:\n\n1. Implement sales strategies in coordination with Sales Manager. Develop sales strategies to increase market share.\n\n2. Plan, organize and manage a sales territory and balance the requirements of multiple business units. Identify and target new business/sales opportunities within the marketplace. Manage the sales cycle.\n\n3. Effectively communicate and negotiate sales contracts with customers/dealers .Educate customers/dealers on new products and product enhancements.\n\n4. Understand and communicate customer issues, current prospects and marketing events to sales management. Accurately articulate and present product features and benefits.\n\n5. Interpret and manage key financial result areas, i.e. revenues, volume, margins, days outstanding and forecasting.\n\nRequirements:\n\n1. Degree in Bioscience is a must. 2 years selling experience in biotech industry.\n\n2. Molecular biology experience is preferable.\n\n3. Good English communications in both oral and written.\n\n4. Result-oriented, hands-on\n\n5. Capability in handling both customers and dealers.", "employment_types": ["Full Time", "Permanent"], "selling_points": ["Assisting the R&D team", "Support product development", "Perform experiments on the bench"], "locations": ["Kwun Tong"], "categories": ["Sciences, Lab, R&D", "Laboratory", "Life Science", "Research & Development (R&D)"], "post_time": "2022-01-07T09:38:37Z", "salary": {"currency": null, "max": null, "min": null, "period": "monthly", "term": null}, "salary_visible": false, "title_keywords": ["research associate", "research assistant"], "responsibilities": ["marketing events", "contracts", "coordination with", "sales management", "develop", "plan", "customer issues"], "requirements": {"degrees": [], "majors": [], "languages": [], "language_level": [], "hard_skills": [], "soft_skills": [], "languages_combined": []}, "experience_required": {"duration": [], "field": []}}, {"job_id": "100003009030769", "location_code": "hk", "company": "Thermo Fisher Scientific (Hong Kong) Limited", "job_title": "Sales Specialist - Genetic Science", "description": "Job Duties:\n\n\nComply with company policies and procedures\nComply with laboratory safety process and analyze clinical specimens via molecular testing etc.\nPerform maintenance and calibration of laboratory equipment\nFollow quality control programs\nOther duties as assigned\nRequirements:\n\n\nRegistered Medical Laboratory Technologist in Part I or Part II with a valid practicing licence\nHigher Diploma or above\nHands-on working experience in molecular testing is preferable\nGenuine interest in medical laboratory sciences for career advancement\nPC knowledge in MS Word & Excel etc.\nGood command of Cantonese, English and Mandarin\nGood personal integrity, hardworking and trustworthy\nResponsible & Good team player, with good interpersonal and leadership skills\nImmediately available is highly preferred\nBenefits:\n\n\nCompetitive Salary + Double Pay + Overtime Allowance\nDental and Medical Benefits\nAnnual Leave, Marriage Leave and Maternity Leave\nFree Lunch Provided\nFree Shuttle Bus Service\nOn Job Training Provided\nCareer Advancement Opportunities\nPlease apply with full resume, present & expected salary via email. (Personal data will be used for recruitment purpose only.)", "employment_types": ["Full Time", "Permanent"], "selling_points": ["Life Science (qPCR & NGS)", "Instrument Sales", "Account Servicing"], "locations": ["Not Specified"], "categories": ["Sciences, Lab, R&D", "Life Science", "Sales, CS & Business Devpt", "Account Servicing", "Direct Sales"], "post_time": "2022-01-07T08:17:48Z", "salary": {"currency": null, "max": null, "min": null, "period": "monthly", "term": null}, "salary_visible": false, "title_keywords": ["sales specialist"], "responsibilities": ["maintenance", "other duties", "policies", "procedures", "testing", "quality control"], "requirements": {"degrees": ["higher diploma or above"], "majors": [], "languages": ["cantonese", "english", "mandarin"], "language_level": ["good command"], "hard_skills": ["excel", "pc knowledge", "ms word"], "soft_skills": ["good team player", "trustworthy", "responsible", "leadership skills", "integrity", "hands-on", "genuine", "interpersonal", "hardworking"], "languages_combined": [{"language": "cantonese", "language_level": ["good command"]}, {"language": "english", "language_level": ["good command"]}, {"language": "mandarin", "language_level": ["good command"]}]}, "experience_required": {"duration": [], "field": ["testing"]}}, {"job_id": "100003009025684", "location_code": "hk", "company": "The Hong Kong Standards And Testing Centre Ltd", "job_title": "Assistant Manager (Microbiology Team)", "description": "Job Description\n\nPerform microbiology and parasitology testing on samples from a wide range of animal species for the diagnosis of animal diseases. This includes culture, parasite, bacterial and fungal isolation and identification, plus antimicrobial sensitivity testing.\nProvide technical support to veterinary diagnosticians\nCarry out laboratory administrative work (including procurement, inventory management, sample and case filing)\nAssist in evaluation of new diagnostic methods\nCompile laboratory documentation\nPrepare and maintain the quality system of the laboratory and equipment\nPerform other duties as assigned\n\nHoliday and weekend rotations are required.\n\nRequirements\n\nDegree in Biomedical Science/Medical Laboratory Science or related disciplines with Registration from the Hong Kong Medical Laboratory Technologists Board (Part II) or above and relevant working experience in a diagnostic laboratory\nGood written and spoken English\nProficiency in computer skills\nAbility to meet deadlines\nWork independently as well as with laboratory teams\nFresh graduates are welcome to apply\nShift-duty is required\n\nPlease submit your resume stating expected salary by \"Apply Now\".\n\nCityU VDL is an Equal Opportunities Employer.\u00a0 Personal data provided by job applicant will be treated in strict confidence and used for recruitment related purpose only.", "employment_types": ["Full Time"], "selling_points": ["Degree holder in Microbiology/ Biotechnology/", "Medical Sciences/ Biochemistry or Life Sciences", "5-day Work Week"], "locations": ["Tai Po Area"], "categories": ["Sciences, Lab, R&D", "Food Science", "Laboratory", "Life Science"], "post_time": "2022-01-06T06:12:37Z", "salary": {"currency": null, "max": null, "min": null, "period": "monthly", "term": null}, "salary_visible": false, "title_keywords": ["assistant manager"], "responsibilities": ["perform other duties", "administrative work", "technical support", "quality", "testing", "inventory management", "maintain", "evaluation", "documentation"], "requirements": {"degrees": ["degree"], "majors": ["biomedical science", "related disciplines", "medical laboratory science"], "languages": ["english"], "language_level": ["good"], "hard_skills": ["computer skills"], "soft_skills": ["meet deadlines", "confidence", "work independently"], "languages_combined": [{"language": "english", "language_level": ["good"]}]}, "experience_required": {"duration": [], "field": ["related", "laboratory", "relevant working experience", "medical"]}}, {"job_id": "100003009026087", "location_code": "hk", "company": "CityU Veterinary Diagnostic Laboratory Company Limited", "job_title": "Laboratory Technologist, Microbiology", "description": "Position Summary:\n\nThe company is looking for several talented postdoctoral scientists.\u00a0The ideal candidates must have extensive experience in molecular and cellular biology, cancer immunology, TCR T and CAR T-cell development, flow cytometry, and cell culture. Highly motivated and self-directed applicants interested in translational research in immuno-oncology are strongly encouraged to apply. However, applicants with related training and experience will be given priority.\n\n\n\nKey Responsibilities include:\n\nThe positions are capable to lead, support the research activities and independently complete individual projects under the direction of CSO in the company.\u00a0These positions will interact and collaborate with a number of scientists and associates highly trained in translational research of immuno-oncology.\u00a0The persons will bring their skills, knowledge, and experience to be actively involved in the development of immunotherapies for a variety of cancers.\n\n\nBasic education, experience and skills required for consideration:\n\nA Ph.D. degree in life or biomedical sciences, or a related discipline is required, with 0-3 years of research experience;\nA track record of publications in peer-reviewed scientific journals;\nSolid knowledge in cancer immunology, molecular and cell biology, and biochemistry;\nExperience in various genomic analytical platforms, such as NGS, RNA-sequencing, etc. is a plus;\nExcellent communication skills (written and verbal in English and Chinese) with the ability to work independently and as part of a team;\nEffectively lead a project in a translational research environment in order to successfully meet project goals;\nAbility to perform and prioritize multiple simultaneous tasks;\nAbility to design and execute experiments, critically interpret experimental results, and present data in a cogent and meaningful manner;\nAbility to participate in the preparation of grant applications and publications.\n\nPreferred experience and skills:\n\nExperienced in gene cloning/re-engineering, antibody engineering, T cell-based therapy and CAR/TCR-T cell development is preferred;\nExperience in handling mice, and PDX mouse models;\nExperience in immunofluorescent staining, imaging/fluorescent microscopy, multi-parameter flow cytometry is preferred;\n\nSalaries and Benefits\nSalary and rank will be commensurate with qualifications and experience and the benefit are very competitive internationally.\n\nOur company\n\nYou will be working within a company in Hong Kong Science and Technology Park. The company will recognize and reward you for your talent and commitment. If you have ability and desire to work among a community of professionals who will both challenge and develop your skill set, then we want to hear from you. Please submit your curriculum vitae, a statement detailing your research experience and skill, contact information (email address and phone number) and three professional references to Dr. Hua Zhang.\u00a0For inquiry, Tel. (852) 56968321.", "employment_types": ["Full Time"], "selling_points": ["MLT (Part II)", "Perform microbiology and parasitology testing", "Provide technical support"], "locations": ["Kowloon City"], "categories": ["Sciences, Lab, R&D", "Laboratory", "Life Science"], "post_time": "2022-01-06T07:18:07Z", "salary": {"currency": null, "max": null, "min": null, "period": "monthly", "term": null}, "salary_visible": false, "title_keywords": [], "responsibilities": ["collaborate with", "data", "design", "communication", "re-engineering"], "requirements": {"degrees": ["degree"], "majors": [], "languages": ["english", "chinese"], "language_level": ["excellent"], "hard_skills": ["mouse", "plus", "basic"], "soft_skills": ["communication skills", "work independently", "independently", "capable", "interested in", "prioritize", "motivated", "extensive", "ideal"], "languages_combined": [{"language": "english", "language_level": ["excellent"]}, {"language": "chinese", "language_level": ["excellent"]}]}, "experience_required": {"duration": ["0-3 years"], "field": ["research", "training", "analytical", "related", "development", "education"]}}, {"job_id": "100003009025770", "location_code": "hk", "company": "Page Group Hong Kong", "job_title": "Laboratory Assistant", "description": "\u00a0Responsibilities:\n\nTo coordinate the team of technical staff to fulfill the operational activities\nTo ensure proper work schedules to meet clients' needs by appropriate job allocation\nTo ensure that results of analysis are checked before admitted for reporting\nTo provide technical support to sales team for the current/potential clients\nTo review and update current testing methods as new standards or technical progress have been made\nTo manage the set-up of new equipment and the development in new testing activities\nTo periodically review and monitor operating procedures and resources to ensure high level of competence of work\nTo assist internal audit and implement corrective actions\nTo ensure the laboratory quality complying to ISO 17025/ HOKLAS / CNAS / IAS requirement\nTo perform other necessary duties as directed by superiors\n\nRequirements:\n\nDegree holder or above in Microbiology, Biotechnology, Medical Sciences, Biochemistry or Life Sciences related disciplines with at least 5-year related experience\nObtained Certification in Microbiology Testing will be an advantage\nProficient in microbiology tests for food, pharmaceutical, consumer products, environmental samples and pathogen confirmation techniques; experience in handling anti-microbial test is an advantage\nSolid experience in handling culture\u00a0and method verification, test confirmations, equipment maintenance and calibration\nFundamental research background in bacteriology, virology or other related disciplines\nKnowledge of molecular tests in food and environmental samples will be advantageous\nWell organizational skills to manage multiple projects\nProblem-solving skills and capable of independent in-depth research\n\nBenefits:\n\n5-day Work Week\nDouble Pay & Performance Bonus\nEducation & Training Allowance\nMedical Benefits\nFree Shuttle Bus\nBirthday Leave\nMarriage Leave, Maternity Leave & Paternity Leave etc\nCompany Activities\n\nInterested parties please send your resume with availability, present salary and expected salary to our Human Resources Department by clicking APPLY NOW .\n\nWelcome to visit our company website www.stc.group for corporate information.\n\n\n\n\n(All personal data collected are for recruitment purposes only.)", "employment_types": ["Full Time", "Permanent"], "selling_points": ["Fast-growing biotech company", "Fair and competitive salary package", "Fresh graduate welcomed"], "locations": ["Not Specified"], "categories": ["Sciences, Lab, R&D", "Laboratory", "Life Science", "Others"], "post_time": "2022-01-06T06:27:16Z", "salary": {"currency": null, "max": null, "min": null, "period": "monthly", "term": null}, "salary_visible": false, "title_keywords": ["laboratory assistant"], "responsibilities": ["reporting", "internal audit", "schedules", "technical support", "analysis", "review", "monitor", "procedures", "testing activities", "testing", "coordinate", "quality", "sales team"], "requirements": {"degrees": ["degree holder"], "majors": ["related disciplines", "microbiology"], "languages": [], "language_level": [], "hard_skills": ["problem-solving skills", "maintenance"], "soft_skills": ["problem-solving skills", "organizational skills", "independent", "capable"], "languages_combined": []}, "experience_required": {"duration": ["at least 5-year"], "field": ["related", "maintenance", "medical"]}}, {"job_id": "100003009017276", "location_code": "hk", "company": "SPH Biotherapeutics (HK) Limited", "job_title": "RESEARCH SCIENTISTS", "description": "Regulatory Affairs\n\nDrive drug & medical device registrations and variations in accordance with relevant regulations and develop the strategy to obtain the product approval within target timeframe.\nRegister and keep maintenance of Guerbet products\u2019 licenses in responsible countries\nKeep abreast of regulatory procedures and product changes to ensure products documents are maintained in compliance with local and corporate instruction.\nEffectively communicate and collaborate with Regional/Corporate RA and Pharmaceuticals team in order to develop Regulatory Strategies & to provide local regulation intelligence to internal stakeholders\nMaintenance of registration data base locally\nSupport other regulatory topics in collaboration with cross-functional team\nEnsure scientific and regulatory intelligence related to this field of activity\nProvide regulatory input and support for clinical trials for responsible countries\nCompliance and Administrative Duties\n\nEnsure company\u2019s products comply with the regulations\nPlan and coordinate packing changes with related department\nEnsure validation of promotional materials and packaging materials in compliance with local regulation and corporate policy.\nMaintain accurate information of packaging materials and artworks with collaboration with GAP\u2019s distributors to be compliant with responsible countries requirements\n\nEducations & Experiences\n\n\nBachelor\u2019s degree in health-related science, life science; Pharmacist or related academic background is preferred\nAt least 3 years of relevant experience in pharmaceutical registration and experience in medical device registration in ASEAN countries and/or Hong Kong is preferred\nCandidate with more experience will be considered as Senior Regulatory Affairs Specialist, whilst less experience will be considered as Regulatory Affairs Specialist\n\nSkills & Qualifications\n\n\nExcellent verbal and written communication skills in English and Cantonese\u00a0\nProficient in MS Office, including Word, Excel and PowerPoint\nPrevious experience in a multinational environment\nEffective communication and interpersonal skills\nDetail-oriented and cross-functional team player\nWork precisely according to procedures, rules and regulations\nRecognize recurring issues and analyse their causes in order to reach a solution\n\nInterested parties please send full resume with your availability, present and expected salary, and date of availability by clicking \"Apply Now\".\n\nAll information received will be kept in strict confidence and will be treated only for employment related purposes.", "employment_types": ["Full Time"], "selling_points": [], "locations": ["Shatin Area"], "categories": ["Sciences, Lab, R&D", "Laboratory", "Life Science", "Research & Development (R&D)"], "post_time": "2022-01-05T07:55:45Z", "salary": {"currency": null, "max": null, "min": null, "period": "monthly", "term": null}, "salary_visible": false, "title_keywords": [], "responsibilities": ["regulations", "collaborate with", "maintenance", "data", "compliance", "procedures", "plan and coordinate", "develop", "communication", "promotional materials", "administrative duties", "maintain", "analyse"], "requirements": {"degrees": ["degree", "bachelor"], "majors": ["science"], "languages": ["cantonese", "english"], "language_level": ["excellent"], "hard_skills": ["excel", "maintenance", "gap", "word", "powerpoint", "ms office"], "soft_skills": ["communication skills", "responsible", "detail-oriented", "communication and interpersonal skills", "team player", "accurate"], "languages_combined": [{"language": "cantonese", "language_level": ["excellent"]}, {"language": "english", "language_level": ["excellent"]}]}, "experience_required": {"duration": ["at least 3 years"], "field": ["pharmaceutical", "relevant experience", "regulatory affairs", "medical device"]}}, {"job_id": "100003009031056", "location_code": "hk", "company": "Guerbet Asia Pacific Limited", "job_title": "Regulatory Affairs Specialist", "description": "Job Title:\u00a0\u00a0\u00a0\u00a0\u00a0\u00a0\u00a0\u00a0\u00a0\u00a0Assistant Project Manager\nDepartment:\u00a0 \u00a0 \u00a0Division of Life Science\nJob ID:\u00a0 \u00a0 \u00a0 \u00a0 \u00a0 \u00a0 \u00a0 7028\n\nJob Posting Details\n\nWe are seeking a highly enthusiastic and self-motivated candidate to fill the Assistant Project Manager position in the main laboratory of the Division of Life Science.\u00a0 The applicant will partner with Senior Technical Officers in the overall management of an approved open-lab renovation project. \u00a0He/She will liaise with internal and external parties, monitor the project progress, handle inquiries, and perform other duties as assigned.\n\nApplicants should possess a bachelor\u2019s degree or above in life science, biomedical science or other related disciplines.\u00a0 He/She should have an excellent command of written and spoken English and Chinese, as well as good coordination, communication and interpersonal skills. Experience of working in a laboratory setting is preferred. (Duration: 1 year)\n\n(Applicants who have applied earlier to the same position need not re-apply.)\n\nStarting salary will be commensurate with qualifications and experience.\u00a0 Fringe benefits including annual leave, medical and dental benefits will be provided.\n\nApplication Procedure\nIn support of a green work environment, we accept applications submitted online only. \u00a0To apply, please complete an online application form through the HKUST Careers website (https://hkustcareers.ust.hk) and return it online to the Human Resources Office on or before Thursday, 20 January 2022. \u00a0Applicants will receive an acknowledgement by email upon successful submission. \u00a0\u00a0\u00a0We thank applicants for their interest, but advise that only shortlisted candidates will be notified of the result of the application.\n\n\n(Information provided by applicants will be used for recruitment and other employment-related purposes only.)\n\nHKUST is an equal opportunities employer and is committed to our core values of\ninclusiveness, diversity, and respect.", "employment_types": ["Full Time", "Permanent"], "selling_points": ["MNC & international working environment", "Flexible working hour & work life balance", "Drug & medical device registrations"], "locations": ["Hung Hom"], "categories": ["Sciences, Lab, R&D", "Life Science", "Medical Services", "Pharmaceutical", "Others"], "post_time": "2022-01-07T08:53:27Z", "salary": {"currency": null, "max": null, "min": null, "period": "monthly", "term": null}, "salary_visible": false, "title_keywords": ["specialist"], "responsibilities": ["management", "perform other duties", "renovation", "internal and external parties", "monitor", "project progress", "communication", "coordination", "liaise with"], "requirements": {"degrees": ["degree or above", "bachelor"], "majors": ["biomedical science", "science", "related disciplines"], "languages": ["english", "chinese"], "language_level": ["excellent", "good"], "hard_skills": ["id"], "soft_skills": ["self-motivated", "communication and interpersonal skills", "coordination", "enthusiastic"], "languages_combined": [{"language": "english", "language_level": ["excellent", "good"]}, {"language": "chinese", "language_level": ["excellent", "good"]}]}, "experience_required": {"duration": [], "field": ["laboratory"]}}, {"job_id": "100003009027300", "location_code": "hk", "company": "The Hong Kong University of Science and Technology", "job_title": "Assistant Project Manager (Job ID: 7028)", "description": "Responsibilities\n\n\u2022 Generate sales through leads generation, sales visit and product presentation and demonstration\n\u2022 Liaise with customers for price negotiation, packages confirmation and contract preparations\n\u2022 Coordinate with other internal teams to fulfil orders\n\u2022 Provide customer services, maintain good relationships and generate further sales with existing customers\n\u2022 Perform any ad hoc duties or assignments\n\nKnowledge\n\n\u2022 Degree or Diploma holder\u00a0\n\u2022\u00a0Fluent in Cantonese, English and Mandarin\n\u2022 1-3 years of work experiences in sales is preferred\n\u2022 Sales-driven, self-motivated, independent, hardworking, flexible and able to multi-task\n\n\n\nWe offer an attractive basic salary plus attractive commission, 5-day work, on-the-job training and career advancement opportunity to the right candidates.\u00a0 Please send full resume with availability, current and expected salary by clicking \"Apply Now\"\u00a0\n\n\u00a0Benefits\n\n\u00a0\u00a0\u00a0\u00a0\u00a0\u00a0\u00a0\u00a0 Five-day work\n\u00a0\u00a0\u00a0\u00a0\u00a0\u00a0\u00a0\u00a0 Bank Holidays\n\u00a0\u00a0\u00a0\u00a0\u00a0\u00a0\u00a0\u00a0 Medical Insurance\n\u00a0\u00a0\u00a0\u00a0\u00a0\u00a0\u00a0\u00a0 12+ Days Annual leave\n\u00a0\u00a0\u00a0\u00a0\u00a0\u00a0\u00a0\u00a0 Paid Marriage Leave\n\u00a0\u00a0\u00a0\u00a0\u00a0\u00a0\u00a0\u00a0 Birthday Leave\n\n\u00a0(Personal data collected will be used for recruitment purpose only.)", "employment_types": ["Full Time"], "selling_points": ["assist Senior Technical Officers", "liaise with internal and external parties", "monitor the project progress"], "locations": ["Sai Kung"], "categories": ["Admin & HR", "Administration / Operation Manager", "Education", "Others", "Sciences, Lab, R&D", "Life Science"], "post_time": "2022-01-06T09:39:13Z", "salary": {"currency": null, "max": null, "min": null, "period": "monthly", "term": null}, "salary_visible": false, "title_keywords": ["assistant project manager"], "responsibilities": ["ad hoc duties", "price negotiation", "coordinate with", "teams", "customer services", "maintain", "liaise with"], "requirements": {"degrees": ["diploma holder", "degree"], "majors": [], "languages": ["cantonese", "english", "mandarin"], "language_level": ["fluent"], "hard_skills": ["plus", "basic"], "soft_skills": ["flexible", "self-motivated", "independent", "negotiation", "multi-task", "presentation", "driven", "hardworking"], "languages_combined": [{"language": "cantonese", "language_level": ["fluent"]}, {"language": "english", "language_level": ["fluent"]}, {"language": "mandarin", "language_level": ["fluent"]}]}, "experience_required": {"duration": ["1-3 years"], "field": []}}, {"job_id": "100003009029336", "location_code": "hk", "company": "Phase Scientific International Limited", "job_title": "Sales Executive", "description": "You will be responsible for sample handling and basic documentation.\n\nClient Details\n\nOur client is a growing biotech company that focuses on diagnostics and medical devices manufacturing & commercialization.\n\nDescription\n\nSample handling and preparation\nData entry and documentation\nSupport Medical Laboratory Technologists in daily duties\n\nProfile\n\nDiploma or Degree holder in Medical Laboratory Sciences or Science related fields\nPassionate in developing their career in the biotech/medical laboratory science industry\nResponsible and detail-minded\nFresh graduates welcomed\nShift duty required\n\nJob Offer\n\nFuture continuous study opportunities\nOn-the-job training\nFair and competitive salary package\n\nTo apply online please click the 'Apply' button below. For a confidential discussion about this role please contact Heart Kwok on +852 2848 9583.", "employment_types": ["Full Time", "Permanent"], "selling_points": ["Generate sales", "Liaise with customers", "Coordinate with other internal teams"], "locations": ["Kwun Tong"], "categories": ["Sciences, Lab, R&D", "Life Science", "Sales, CS & Business Devpt", "Retail Sales", "Direct Sales"], "post_time": "2022-01-08T21:06:43Z", "salary": {"currency": null, "max": null, "min": null, "period": "monthly", "term": null}, "salary_visible": false, "title_keywords": ["sales executive"], "responsibilities": ["data entry", "developing", "commercialization", "contact", "documentation"], "requirements": {"degrees": ["diploma", "degree holder"], "majors": ["science"], "languages": [], "language_level": [], "hard_skills": ["documentation", "basic"], "soft_skills": ["passionate", "detail-minded", "responsible"], "languages_combined": []}, "experience_required": {"duration": [], "field": []}}, {"job_id": "100003009024802", "location_code": "hk", "company": "SGS Hong Kong Limited", "job_title": "Biologist (Technical Development)", "description": "Research and develop test method/approach to examine\u00a0antimicrobial and microbial filtration efficiency performance of consumer product and novel material\nAssist in SOP development\nEstimate and monitor the effort required on projects and respond promptly to deviations from estimate\nEnsure adequate facilities exist for the conduct of laboratory activities and purchase management\nBe responsible for the quality of work produced by the laboratory and to ensure the quality management system is in compliance to ISO 17025 standard\nFor joint projects, ensure liaison with scientific personnel in other laboratory to ensure projects proceed in a satisfactory manner\nKeep abreast of the scientific literature relevant to the laboratory\u2019s activities\nProvide specialist advice, opinions and information to other laboratory and to clients\nUndertake other such tasks as might reasonably requested from time to time by his/her supervisor\nFor any renovation and design of laboratory, estimate the effort and monitor the project progress\nSupport frontline and business unit for any enquiry on anti-microorganism and filtration efficiency performance\nAssist in preparing technical sales kit to promote service on anti-microorganism and filtration efficiency performance\n\n\nQualifications\n\n\nBachelor degree or above, majoring in Cell biology, Virology or relevant Biological sciences\nEquip with hands-on experience on manipulating tissue culture of mammalian cell lines and propagation of viral culture as well as virus titre quantification by plaque assay and TCID50 methods would be of great advantage\nComputer knowledge in Windows application\nKnowledge in laboratory quality system requirement or familiar with ISO 17025 is of advantage\nGood command of spoken and written English\nExperience as Project leader\nStrong critical thinking & problem solving skills\nAble to work independently with minimal supervision\n\n\n\nAdditional Information\n\n\n5-day Work Week\u00a0\u00a0\u00a0\u00a0\u00a0\u00a0\u00a0\u00a0\u00a0\u00a0\u00a0\u00a0\u00a0\u00a0\u00a0\u00a0\u00a0\u00a0\u00a0\u00a0\u00a0\u00a0\u00a0\u00a0\u00a0\u00a0\u00a0\u00a0\u00a0\u00a0\u00a0\u00a0\u00a0\u00a0\u00a0\u00a0\u00a0\u00a0\u00a0\u00a0\u00a0\u00a0\u00a0\u00a0\u00a0\u00a0\u00a0\u00a0\nDouble Pay and Performance Bonus\nDental and Medical Benefits\nAccident Insurance and Life Insurance\nAnnual Leave\nBirthday Leave\nPaid Maternity Leave, Paternity Leave, and Marriage Leave\nCareer Advancement Opportunities\nOn-the-Job Training\u00a0\u00a0\u00a0\u00a0\u00a0\u00a0\u00a0\u00a0\u00a0\u00a0\u00a0\u00a0\u00a0\u00a0\u00a0\u00a0\u00a0\u00a0\u00a0\u00a0\u00a0\u00a0\u00a0\u00a0\u00a0\u00a0\u00a0\u00a0\u00a0\u00a0\u00a0\u00a0\u00a0\u00a0\nEducation and Training Subsidies\nFree shuttle service\nEmployee Assistance Program (EAP)\nStaff Activities", "employment_types": ["Full Time", "Permanent"], "selling_points": ["Biologist; Technical Development; R&D", "Testing lab; Biology; Virology; Cell biology", "Birthday leave; Performance bonus"], "locations": ["Fanling"], "categories": ["Sciences, Lab, R&D", "Laboratory", "Life Science", "Research & Development (R&D)"], "post_time": "2022-01-06T02:32:38Z", "salary": {"currency": null, "max": null, "min": null, "period": "monthly", "term": null}, "salary_visible": false, "title_keywords": [], "responsibilities": ["management", "compliance", "quality", "monitor", "renovation", "develop", "design", "project progress", "purchase", "sales kit"], "requirements": {"degrees": ["degree or above", "bachelor"], "majors": ["biology"], "languages": ["english"], "language_level": ["good command"], "hard_skills": ["problem solving skills"], "soft_skills": ["work independently", "responsible", "hands-on", "problem solving skills", "novel"], "languages_combined": [{"language": "english", "language_level": ["good command"]}]}, "experience_required": {"duration": [], "field": []}}, {"job_id": "100003009032537", "location_code": "hk", "company": "A. R. Medicom Inc. (Asia) Limited", "job_title": "Product Specialist (Scientific Products)", "description": "Responsibilities:\n\nPlan, execute and monitor in developing markets for assigned products\nInvolve in coordinating and planning demonstrations\nProvide basic technical and application supports to customers\nProvide pre-sale support to sales team\nImplement sales initiatives to achieve corporate assigned sales target\n\n\u00a0Requirements:\n\nA Master\u2019s degree or above in biotechnology/biochemistry/relevant subjects\nKnowledge in genomics, cell culture, Next Generation Sequencing and flow cytometry or relevant subjects\nPreferable 3 - 5 years relevant working experience\nDedicated and self-motivated with strong interpersonal skills\nA fast learner and good team player\nFluent in Cantonese, English and Putonghua preferable\n\n\u00a0Relevant job trainings will be provided for the incumbent. Please visit website www.bioarrow.com for further information.\n\n\u00a0We Offer\n\nCareer advancement opportunities\nAttractive remuneration package\nKey Performance Incentive Bonus\n5-day work week and bank holiday\nAnnual leave and birthday leave\nCompany medical, accidental and life insurance\nFriendly working environment\n\nInterested candidates please click \"Apply Now\" to submit\u00a0your resume and covering letter together with availability, current and expected salary details.\n\n\u00a0All personal data collected will be kept strictly confidential and will be only used for recruitment purpose only.", "employment_types": ["Full Time", "Permanent"], "selling_points": [], "locations": ["North Point"], "categories": ["Sciences, Lab, R&D", "Chemical", "Laboratory", "Life Science"], "post_time": "2022-01-07T19:21:12Z", "salary": {"currency": null, "max": null, "min": null, "period": "monthly", "term": null}, "salary_visible": false, "title_keywords": ["product specialist"], "responsibilities": ["sales target", "monitor", "developing", "sales team", "plan", "planning"], "requirements": {"degrees": ["degree or above", "master"], "majors": [], "languages": ["cantonese", "putonghua", "english"], "language_level": ["fluent"], "hard_skills": [], "soft_skills": ["good team player", "self-motivated", "interpersonal skills", "fast learner"], "languages_combined": [{"language": "cantonese", "language_level": ["fluent"]}, {"language": "putonghua", "language_level": ["fluent"]}, {"language": "english", "language_level": ["fluent"]}]}, "experience_required": {"duration": ["3 - 5 years"], "field": ["relevant working experience"]}}, {"job_id": "100003009027427", "location_code": "hk", "company": "Center Point Personnel", "job_title": "Administrative Support Clerk (Gov/ 21K/ 3-mth contract/ Environmental Science)", "description": "Job Description\n\nProvide administrative support services\nAssist in outdoor data collecting\nPerform other clerical duties assigned by supervisors\nJob Requirement\n\nHigher Diploma or above in Biology, Medical Laboratory Science, Mechanical, Electrical, Electronic or Civil Engineering, Chemical Technology, Computer Science, Water Pollution Control, Waste Management, Environmental Studies\nPassed in Chinese Language and English Language in HKDSE/HKCEE\nProficient in common office software including MS Word, PowerPoint, Excel\nProficient in Chinese and English word processing\nPolite and responsible", "employment_types": ["Full Time", "Contract"], "selling_points": [], "locations": ["Tsuen Wan Area"], "categories": ["Admin & HR", "Clerical / Admin Staff", "Sciences, Lab, R&D", "Environmental Science / Waste Management", "Life Science"], "post_time": "2022-01-06T09:57:45Z", "salary": {"currency": null, "max": null, "min": null, "period": "monthly", "term": null}, "salary_visible": false, "title_keywords": ["clerk"], "responsibilities": ["provide administrative support", "data"], "requirements": {"degrees": ["higher diploma or above", "hkdse"], "majors": ["computer science", "biology", "medical laboratory science", "civil engineering"], "languages": ["english", "chinese"], "language_level": ["proficient"], "hard_skills": ["excel", "chinese and english word processing", "powerpoint", "office software", "ms word"], "soft_skills": ["polite", "responsible"], "languages_combined": [{"language": "english", "language_level": ["proficient"]}, {"language": "chinese", "language_level": ["proficient"]}]}, "experience_required": {"duration": [], "field": []}}, {"job_id": "100003009019999", "location_code": "hk", "company": "ALS Technichem (HK) Pty Limited", "job_title": "Laboratory Technician (Sampling & Micro Testing) - 6 Months Contract", "description": "About the Position\n\nThe position will be responsible for:\n\nConducting sampling on sites and performing outdoor work\nPreparing and performing testing for environmental, food and pharmaceutical samples\nFinishing require work to fulfil turnaround time requirement\nPerforming housekeeping duties as required\nPerforming calculations as required when conducting analytical methods\nPerforming other tasks as directed by the supervisors\n\nAbout you\n\nTo be successful in this role you will have:\n\nRequired Knowledge, Skills & Abilities:\n\nGood computer skill with knowledge of Excel, Word\nProficient Chinese/ English verbal and written communication skills\nKnowledge/ experience on using laboratory equipment are advantages\nAbility to learn and work under pressure\nGood physical condition\nWillingness to work outdoor\n\nRequired Qualifications:\n\nHigher Diploma/Degree in Environmental, Biology or other science related subjects\n0-1 years working experience\nEnvironmental/food laboratory experience preferable but not a must\n\nBenefits:\n\n6 days Annual Leave and 6 days Full Paid Sick Leave\u00a0\nHigh overtime pay\u00a0rate\nEnd contract bonus\nOn-job training\n\nPlease select your prefer position and specify job reference number on your application letter. Application without this information will not be considered.\n\nSampling & Microbiology Testing (Job Ref: T-MB-01/22)\n\nThis is an excellent opportunity for a motivated and skilled person looking to develop their career in an international company.\u00a0 Attractive remuneration and benefits are available dependant on performance.\n\nPlease address your cover letter and resume by clicking \"Apply Now\"\n\nFor more information about ALS \u2013 W: www.alsglobal.com\n", "employment_types": ["Full Time", "Permanent"], "selling_points": ["On Site Sampling for Env/Food sample; Lab Testing", "HD/Degree in Env/Bio; 0-1 year lab testing exp.", "High OT pay; End Contract Bonus; Near MTR Station"], "locations": ["Kwai Tsing Area"], "categories": ["Sciences, Lab, R&D", "Laboratory", "Life Science", "Others", "Technician"], "post_time": "2022-01-04T09:39:49Z", "salary": {"currency": null, "max": null, "min": null, "period": "monthly", "term": null}, "salary_visible": false, "title_keywords": ["laboratory technician"], "responsibilities": ["outdoor work", "housekeeping", "testing", "communication", "other tasks", "work under pressure"], "requirements": {"degrees": ["diploma", "degree"], "majors": ["science", "biology"], "languages": ["english", "chinese"], "language_level": ["proficient"], "hard_skills": ["excel", "computer skill", "word"], "soft_skills": ["communication skills", "willingness to work", "responsible", "work under pressure"], "languages_combined": [{"language": "english", "language_level": ["proficient"]}, {"language": "chinese", "language_level": ["proficient"]}]}, "experience_required": {"duration": ["0-1 years"], "field": ["laboratory", "environmental", "food"]}}, {"job_id": "100003009021568", "location_code": "hk", "company": "Nestle Hong Kong Ltd", "job_title": "Senior Laboratory Technician", "description": "Position Summary\n\n\nWorking Location: Yuen Long (Shuttle bus provided)\n\nDuty Pattern: 8:00am - 4:30pm or 11:00am - 7:30pm\n(5.5 days per week, alternative Saturday)\n\u00a0\u00a0Responsibilities:\n\nSampling and testing food and beverage raw materials and finished products\nAnalyze test data, verify results and prepare reports\nSAP system preparation work\nParcel packing, agar preparation and material purchasing\nConduct equipment maintenance and calibration\nMonitor factory environment and hygiene conditions\n\n\u00a0\u00a0Requirements:\u00a0\n\nHigher Diploma or above in Food Technology, Food Science, Chemistry, Biology or Biochemistry\nWith 4 years relevant experience\nGood analytical and organizational skills\nGood communication skills in both written and spoken English and Chinese\n\nCandidate with less experience / fresh graduates will be considered as Laboratory Technician.\u00a0\n\nPlease submit\u00a0 application with your resume stating the employment history, present and expected salary by clicking \"Apply Now\".\n\nWe, at all levels, are strongly committed to the Company, its development and its culture. We practice what we preach and give great importance to training and development of people. We offer excellent career development opportunities, attractive remuneration package, comprehensive fringe benefits and wellness programs to the right candidates\n\nWe are an equal opportunity employer and committed to workforce diversity with opportunity for continuous development and growth to all employees.\n\n(All information will be treated in strict confidence and will be used exclusively for recruitment related purpose only. Information of unsuccessful applicants will be destroyed upon completion of the recruitment process.)", "employment_types": ["Full Time", "Permanent"], "selling_points": ["Great opportunity in FMCG/F&B", "World No.1 F&B company with collaborative culture", "Laboratory Testing"], "locations": ["Yuen Long"], "categories": ["Hospitality / F & B", "Food & Beverage", "Sciences, Lab, R&D", "Laboratory", "Life Science"], "post_time": "2022-01-05T04:16:46Z", "salary": {"currency": null, "max": null, "min": null, "period": "monthly", "term": null}, "salary_visible": false, "title_keywords": ["laboratory technician"], "responsibilities": ["maintenance", "data", "monitor", "testing", "hygiene", "prepare reports"], "requirements": {"degrees": ["higher diploma or above"], "majors": ["biology", "chemistry", "food science"], "languages": ["english", "chinese"], "language_level": ["good"], "hard_skills": [], "soft_skills": ["communication skills", "organizational skills", "confidence", "committed", "comprehensive"], "languages_combined": [{"language": "english", "language_level": ["good"]}, {"language": "chinese", "language_level": ["good"]}]}, "experience_required": {"duration": ["4 years"], "field": ["laboratory", "relevant experience"]}}, {"job_id": "100003009032324", "location_code": "hk", "company": "Hays", "job_title": "Key Account Manager (Team Lead Role)", "description": "Top 10 biopharmaceutical focusing on research, development, and commercialization of prescription medicines\n\nYour new company\nA global leading biopharmaceutical focusing on the research, development, and commercialization of prescription medicines that is global, science-led, and patient-centered.\n\nYour new role\nResponsible for sales activities in assigned accounts or regions. Managed quality and consistency of product and service delivery.\n\nPromoting key products to current and new clients in the private and public sectors\nIdentify potential clients and collect market intelligence\nActively manage and grow dedicated sales territory in product pipeline\nHelping with the team by providing different coaching and support\nCo-operate with marketing team to do promotion for growth of business\nBuild and maintain a good relationship with medical and pharmaceutical KOLs.\n\n\n\nWhat you'll need to succeed\n\nBachelor's degree or above in life science related disciplines\nMinimum 3 years sales experience in pharmaceutical or medical company\nStrong communication, interpersonal and presentation skills\nSales driven and customer focus to enhance good relationship with different parties\nProactive, self-motivated with passion to overcome challenges\nFluent in English and Cantonese, fluent in Mandarin will be an advantage\n\n\nWhat you need to do now\nIf you are interested in the above opportunity, please forward your latest resume to rooney.wu@hays.com.hk or contact Rooney at +852 2230 7913 for more information.\n\nIf this role isn't quite right for you but you are looking to explore new opportunities in the life science sector, please contact Rooney for a confidential discussion about your options.", "employment_types": ["Full Time", "Permanent"], "selling_points": ["Managing Key Account", "People Management", "Competitive salary package"], "locations": ["Not Specified"], "categories": ["Sciences, Lab, R&D", "Life Science", "Medical Services", "Pharmaceutical", "Others"], "post_time": "2022-01-07T10:45:43Z", "salary": {"currency": "HKD", "max": 34999, "min": 20000, "period": "monthly", "term": null}, "salary_visible": true, "title_keywords": ["account manager", "lead"], "responsibilities": ["service delivery", "sales activities", "quality", "good relationship", "communication", "commercialization", "co-operate with", "maintain", "contact"], "requirements": {"degrees": ["degree or above", "bachelor"], "majors": ["related disciplines", "science"], "languages": ["cantonese", "english", "mandarin"], "language_level": ["advantage", "fluent"], "hard_skills": ["focus"], "soft_skills": ["self-motivated", "responsible", "interested in", "driven", "communication", "presentation skills", "customer focus", "patient", "proactive", "interpersonal"], "languages_combined": [{"language": "cantonese", "language_level": ["advantage"]}, {"language": "english", "language_level": ["advantage"]}, {"language": "mandarin", "language_level": ["fluent", "advantage"]}]}, "experience_required": {"duration": ["minimum 3 years"], "field": ["pharmaceutical", "medical"]}}, {"job_id": "100003009026956", "location_code": "hk", "company": "Hong Kong HybriBio Limited", "job_title": "International Sales and Marketing Representative (5 days)", "description": "Hong Kong Hybribio Limited\n\nWe invite high caliber talent to apply for\u00a0International Sales and Marketing Executive\u00a0to join our international business development team in Hong Kong to supports our global market.\n\nResponsibilities :\n\nCoordinate customers inquiry, orders and daily correspondence\nMonitor and execute strategic marketing plans for any assigned overseas countries\u00a0\nProvide after-sale and technical support and training\nExecute marketing activities and events, such as exhibitions, international conferences or visiting customers on-site\u00a0\nProactively build a good relationship with KOLs / distributors of assigned countries\nRegular sales record tracking and report to the supervisor\nHandle any ad-hoc duties as assigned\n\nRequirements :\n\nA bachelor degree in\u00a0Science backgroundwith a minimum of ONE year of working experience is preferable.\nFresh graduates\u00a0can also be considered as a trainee\nSelf-initiative, aggressive and\u00a0well-organized working attitude\u00a0\nHigh problem-solving skill for challenges\nA cheerful personality with an excellent presentation and interpersonal skills\nTravel to overseas occasionally\u00a0\nGood comment in spoken and written in English and Mandarin\nProficiency in MS Office and Chinese Word Processing\nImmediate available is preferred\n\nWe offer on-the-job-training, competitive remuneration packages with medical insurance, annual leave, 5-day work, travel allowance, double pay and performance bonus.", "employment_types": ["Full Time", "Permanent"], "selling_points": ["Double pay, Bonus", "Life Science background (with 1 yr working exp.)", "Build a good relationship with KOLs"], "locations": ["Kowloon Bay"], "categories": ["Sales, CS & Business Devpt", "Business Development", "Sciences, Lab, R&D", "Life Science", "Marketing / Public Relations", "Marketing - Direct Marketing"], "post_time": "2022-01-06T08:56:17Z", "salary": {"currency": null, "max": null, "min": null, "period": "monthly", "term": null}, "salary_visible": false, "title_keywords": ["representative", "sales"], "responsibilities": ["marketing plans", "technical support", "monitor", "coordinate", "good relationship", "conferences", "ad-hoc duties", "report", "tracking"], "requirements": {"degrees": ["degree", "bachelor"], "majors": ["science"], "languages": ["english", "chinese", "mandarin"], "language_level": ["proficiency", "good"], "hard_skills": ["problem-solving", "chinese word processing", "ms office"], "soft_skills": ["cheerful", "problem-solving", "well-organized", "self-initiative", "interpersonal skills", "presentation"], "languages_combined": [{"language": "english", "language_level": ["good"]}, {"language": "chinese", "language_level": ["proficiency"]}, {"language": "mandarin", "language_level": ["good"]}]}, "experience_required": {"duration": ["minimum of one year"], "field": []}}, {"job_id": "100003009015966", "location_code": "hk", "company": "Cordlife (Hong Kong) Limited", "job_title": "Deputy Laboratory and Technical Director", "description": "Job Requirements\n\nPhD in Biomedical/ Biotechnology or any other life sciences.\nExperience and strong technical knowledge in stem cells, or genetics/molecular diagnostics.\nProject, laboratory and team management experience is preferable.\nExperience working in a commercial / hospital laboratory and/or an AABB-accredited laboratory advantageous.\nMust be Hepatitis B immunized.\n\nJob Description\n\nProvide directions and advice to Management, Lab Managers on all technical & lab operational aspects.\nLead technical and/or laboratory operational developments for the validation and integration of new products, services and processes.\nImplementation of new products and initiatives for the company as directed.\nScouting and assessments of potential new products, services, technologies and processes for the company.\nEvaluate processing data, ensure product safety, efficacy and endpoints met.\nEnsure daily aspects of laboratory processes are performed in accordance with SOPs and quality standards met.,\nOperational responsibility as Laboratory Director of Cordlife facilities as designated; ensure adherence to internal policies and operating procedures, AABB (or other applicable international) standards and local authority regulations.\nResponsible for lab operations budget planning, and implementation.\nProvide training & development, continuing education including speaking engagements.\nOversees cord blood unit releases.\nInterface with Country Director(s), Medical Director and Senior Management on new initiatives.\nInterface with Doctors, clients, health authorities and accrediting bodies.", "employment_types": ["Full Time"], "selling_points": ["Fast-growing biotech company/ Biomedical", "stem cells, genetics/molecular diagnostics", "PhD in Biomedical/ Biotechnology"], "locations": ["Shatin Area"], "categories": ["Sciences, Lab, R&D", "Laboratory", "Life Science", "Others"], "post_time": "2022-01-03T07:59:54Z", "salary": {"currency": null, "max": null, "min": null, "period": "monthly", "term": null}, "salary_visible": false, "title_keywords": ["director"], "responsibilities": ["regulations", "provide training", "management", "budget planning", "data", "policies", "ensure adherence", "operations", "quality", "implementation", "procedures", "evaluate", "sops", "senior management"], "requirements": {"degrees": [], "majors": [], "languages": [], "language_level": [], "hard_skills": [], "soft_skills": [], "languages_combined": []}, "experience_required": {"duration": [], "field": ["laboratory", "management", "commercial", "team"]}}, {"job_id": "100003009032691", "location_code": "hk", "company": "Hays", "job_title": "IVD & Life Sciences Sales Representative - Multiple Openings", "description": "Your new company\nUS listed and global market leader in field of IVD & Life Sciences is now looking for high calibre to join their high performing sales team to continue expanding their business as well as maintain their market leader position in Hong Kong.\n\nYour new role\n\nTo promote the extensive range of clinical diagnostic or life sciences products to HA hospitals, private hospitals, private laboratories and institutions\nTo execute the annual sales plan and achieve the goals\nTo identify new business opportunities to achieve the continuous growth\nTo establish and maintain good relationship with target accounts\nTo provide good after sales services and gain customer loyalty\n\n\nWhat you'll need to succeed\n\nBachelor Degree in Science, preferable in Biomedical Science, Biotechnology, Biology or healthcare related disciplines\nPreferable 2-3 years sales or marketing experience in healthcare industry\nExcellent in customer relationship management & interpersonal skills\nSelf-motivate, independent and able to work under pressure\nResult-oriented and have positive working attitude\nGood command of English, Cantonese and Mandarin\nFresh graduate with good personality and aggressive character shall also consider in Sales Executive position\n\n\nWhat you need to do now\nIf you're interested in this role, click 'apply now' or forward your updated Resume to email: charles.cheang@hays.com.hk, or contract Charles Phone Number: 2230 7422 for more information in a confidential discussion.\n\nIf this job isn't quite right for you but you are looking for a new position, please contact us for a confidential discussion on your career.", "employment_types": ["Full Time", "Permanent"], "selling_points": ["US listed World Top 10 Diagnostics Company", "Excellent Career Development", "Competitive Package"], "locations": ["Not Specified"], "categories": ["Sciences, Lab, R&D", "Laboratory", "Life Science", "Others"], "post_time": "2022-01-07T14:44:47Z", "salary": {"currency": "HKD", "max": 29999, "min": 25000, "period": "monthly", "term": null}, "salary_visible": true, "title_keywords": ["sales representative"], "responsibilities": ["management", "business opportunities", "maintain good relationship", "maintain", "sales team", "contact", "plan", "work under pressure"], "requirements": {"degrees": ["degree", "bachelor", "fresh graduate"], "majors": ["biomedical science", "science", "biology", "related disciplines"], "languages": ["cantonese", "english", "mandarin"], "language_level": ["good command"], "hard_skills": [], "soft_skills": ["independent", "interested in", "positive working attitude", "interpersonal skills", "extensive", "result-oriented", "work under pressure"], "languages_combined": [{"language": "cantonese", "language_level": ["good command"]}, {"language": "english", "language_level": ["good command"]}, {"language": "mandarin", "language_level": ["good command"]}]}, "experience_required": {"duration": ["2-3 years"], "field": ["healthcare industry", "marketing"]}}, {"job_id": "100003009029316", "location_code": "hk", "company": "Nan Fung Development Limited", "job_title": "ASSOCIATE - GROUP CEO'S OFFICE", "description": "Responsibilities:\n\nFacilitate the Group CEO's office in planning, driving and marketing new initiatives by conducting research and providing business, operational and organizational analysis on initiatives driven by the Group CEO's office to facilitate top management's decision making\nResponsible for preparing marketing materials for some of the group's strategic initiatives\nAssist with implementation of strategic and operational plans of the group's life sciences business unit\nPerform any ad hoc responsibilities as assigned\n\n\u00a0Requirements:\u00a0\n\nDegree in Finance/ Economics/ Business Administration/ Accounting or related disciplines\nMinimum 3 years' experience in consulting firms or investment banks (IBD or research)\nAbility to work independently, strong commercial sense, meticulous, dedicated and self-motivated\nExtremely proficient in PowerPoint presentation, preparing marketing materials and able to do research independently\nExcellent command of both written and spoken English and Chinese including Mandarin\nCandidates with more experience will be considered as Assistant Vice President\n\nWe provide generous compensation and fringe benefits to the right candidate. Please send your resume with salary expected to The Human Resources Manager, 23/F., Nan Fung Tower, 88 Connaught Road C, Central, HK or by e-mail: hr @nanfung.com or by clicking \u201cApply Now\u201d below (We are an equal opportunity employer. All applications will be treated in strict confidence and only be used for selection purpose.)\n\n\u00a0Nan Fung Group\u201d and \u201cthe Group\u201d mean Nan Fung Group Holdings Limited and its subsidiaries.", "employment_types": ["Full Time", "Permanent"], "selling_points": ["Exp. in consulting firms or investment banks", "Business, operational and organizational analysis", "Life Science backgrounds"], "locations": ["Central & Western Area"], "categories": ["Banking / Finance", "Analyst", "Professional Services", "Business Analysis / Data Analysis", "Sciences, Lab, R&D", "Life Science"], "post_time": "2022-01-07T04:41:56Z", "salary": {"currency": null, "max": null, "min": null, "period": null, "term": null}, "salary_visible": false, "title_keywords": ["associate", "ceo"], "responsibilities": ["ad hoc responsibilities", "management", "analysis", "implementation", "marketing materials", "plans", "planning"], "requirements": {"degrees": ["degree"], "majors": ["business administration", "finance", "economics", "related disciplines", "accounting"], "languages": ["english", "chinese", "mandarin"], "language_level": ["excellent"], "hard_skills": ["powerpoint"], "soft_skills": ["meticulous", "work independently", "independently", "self-motivated", "presentation"], "languages_combined": [{"language": "english", "language_level": ["excellent"]}, {"language": "chinese", "language_level": ["excellent"]}, {"language": "mandarin", "language_level": ["excellent"]}]}, "experience_required": {"duration": ["minimum 3 years"], "field": ["consulting firms", "research", "investment banks"]}}, {"job_id": "100003009020283", "location_code": "hk", "company": "PIT Limited", "job_title": "Assistant Manager (Quality Control & Assurance)", "description": "Job Description\n\nSupervise and maintain the routine quality control & assurance activities;\n\nCommunicate with HKAS for HOKLAS & HKIAS assessment;\n\nOn-site internal/external inspection of related tasks;\n\nOn-job training will be provided;\n\nPerhaps to require to perform ad-hoc tasks.\n\nRequirements\n\nBachelor degree or above in Science/QA&QC discipline;\n\nResponsible, hardworking, team working with positive working attitude;\n\n3-5 years or more experiences in laboratory and/or factory are advantages;\n\nImmediately available is highly preferred.", "employment_types": ["Full Time"], "selling_points": [], "locations": ["Tsuen Wan Area"], "categories": ["Sciences, Lab, R&D", "Environmental Science / Waste Management", "Laboratory", "Life Science"], "post_time": "2022-01-04T16:20:21Z", "salary": {"currency": null, "max": null, "min": null, "period": "monthly", "term": null}, "salary_visible": false, "title_keywords": ["assistant manager"], "responsibilities": ["communicate with", "ad-hoc tasks", "inspection", "maintain", "quality control"], "requirements": {"degrees": ["degree or above", "bachelor"], "majors": ["science"], "languages": [], "language_level": [], "hard_skills": [], "soft_skills": ["team working", "hardworking", "responsible", "positive working attitude"], "languages_combined": []}, "experience_required": {"duration": ["3-5 years"], "field": ["laboratory"]}}, {"job_id": "100003009020278", "location_code": "hk", "company": "PIT Limited", "job_title": "Technical Officer / Senior Technical Officer (Indoor Air Quality / Environmental)", "description": "Job Description\n\nPerform on-site Indoor Air Quality inspection;\n\nConduct sampling and handle related tasks;\n\nTraining will be provided;\n\nPerform any other ad hoc tasks assigned.\n\nRequirements\n\nHigher Diploma or above in any program of Science & Engineering (Environmental, Building Service & etc.) disciplines;\n\nResponsible, hardworking with positive working attitude;\n\n1 year or more Indoor Air Quality\u00a0experiences\u00a0 are advantages;\n\nImmediately available is highly preferred;\n\nTravel to China and Overseas may require with compensation;", "employment_types": ["Full Time"], "selling_points": [], "locations": ["Tsuen Wan Area"], "categories": ["Sciences, Lab, R&D", "Environmental Science / Waste Management", "Laboratory", "Life Science"], "post_time": "2022-01-04T16:20:21Z", "salary": {"currency": null, "max": null, "min": null, "period": "monthly", "term": null}, "salary_visible": false, "title_keywords": ["technical officer", "senior technical officer"], "responsibilities": ["ad hoc tasks", "quality", "inspection"], "requirements": {"degrees": ["higher diploma or above"], "majors": ["science", "engineering"], "languages": [], "language_level": [], "hard_skills": [], "soft_skills": ["positive working attitude", "hardworking", "responsible"], "languages_combined": []}, "experience_required": {"duration": ["1 year"], "field": []}}, {"job_id": "100003009015836", "location_code": "hk", "company": "Cordlife (Hong Kong) Limited", "job_title": "Laboratory Technician / Medical Laboratory Technician (MLT Part II)", "description": "Job Responsibilities:\n\nDirectly responsible for the processing and storage preparation of cord blood and umbilical cord units according to laboratory Standard Operation Procedures\nPlan, set up and undertake controlled experiments and trials\nMonitor the laboratory consumables in stock are well organized\u00a0\nHandle and accurate recording laboratory data, present results to Lab Manager/ Lab Director\nDemonstrate of procedures and scientific analysis\nReceive and accept of incoming materials\nPerform maintenance and calibration of laboratory equipment\nWrite reports, reviews and summaries\nParticipate in-house and external training as required\nMaintain safe and clean working environment in the lab\n5-day week (09:00 - 18:00), roster duty on Saturday, Sunday and Public Holiday required\n\nJob Requirements:\n\nBachelor Degree or Higher Diploma in Medical Laboratory Sciences, Biological Science, Biotechnology or Life Science related disciplines.\u00a0Fresh graduates are also welcome.\nExperience in processing of cord blood or performing laboratory testing would be an advantage, but not a must\u00a0\nExperience in phlebotomy would be an advantage\nHigh sense of responsibility and teamwork\nAble to work independently and without supervision\nGood command of written and spoken English, Cantonese and Mandarin\nMust be Hepatitis B immunized\nCandidate with Registered Part II MLT will be considered as Medical Laboratory Technician\n\nWe offer:\u00a0\n\nAttractive remuneration package and staff benefits\nShuttle bus provided by Hong Kong Science Park\nComprehensive on-the-job and continuous trainings\nOpportunities for professional and personal development\nFriendly working environment\n\nIf you are interested in this position, please send your resume with details of qualification, experience, present and expected salary, address and contact number to HR by clicking \u201cAPPLY NOW\u201d.\n\nAll personal data collected would be used for recruitment purpose.", "employment_types": ["Full Time", "Permanent"], "selling_points": ["Fast-growing biotech company/ Biomedical", "5-day work week(9:00-18:00), Double pay and bonus", "Dental, medical and life insurance, birthday leave"], "locations": ["Shatin Area"], "categories": ["Sciences, Lab, R&D", "Laboratory", "Life Science", "Others"], "post_time": "2022-01-03T07:43:31Z", "salary": {"currency": null, "max": null, "min": null, "period": "monthly", "term": null}, "salary_visible": false, "title_keywords": ["laboratory technician", "medical laboratory technician"], "responsibilities": ["maintenance", "data", "analysis", "monitor", "procedures", "maintain", "reports", "plan"], "requirements": {"degrees": ["diploma", "degree", "bachelor"], "majors": ["related disciplines", "science", "biological science"], "languages": ["cantonese", "english", "mandarin"], "language_level": ["good command"], "hard_skills": ["processing"], "soft_skills": ["work independently", "high sense of responsibility and teamwork"], "languages_combined": [{"language": "cantonese", "language_level": ["good command"]}, {"language": "english", "language_level": ["good command"]}, {"language": "mandarin", "language_level": ["good command"]}]}, "experience_required": {"duration": [], "field": ["laboratory testing"]}}, {"job_id": "100003009019399", "location_code": "hk", "company": "New Beta Innovation Limited", "job_title": "Senior Manager/ Manager, Product and Process Development (Method Development)", "description": "The Job:\n\nProvide guidance and hands-on assistance with biochemistry and molecular biology assays, including: column chromatography, proteomics techniques, PCR methods (extraction of residual DNA, primer design, quantitative PCR), mass spectrometric techniques and immunoassays etc.\nPlan, execute and interpret experiments on pre-clinical safety and efficacy studies.\nLead a team in testing method development, and coordinate analytical support for technology transfer and method validation in a cross function matrix team environment.\nMaintain proficiency in the biological drug development process including a thorough understanding of the molecular attributes, target quality profiles and linking them to patient safety and efficacy aspects.\nThe Person:\nPhD in Biology, Biochemistry, Biotechnology or equivalent discipline with minimum of 3 years experience in development of therapeutic protein or 5 years experience in protein research.\nUnderstanding with hands on experience of analytical techniques using physical and biochemical characterization methods.\nExperience in drug safety and efficacy testing for protein drug development.\nExperience in drug substance and drug product manufacturing as well as method development, technology transfer and method validation preferred.\nExperience managing research associates and technicians.\nAdequate knowledge of regulatory guidelines related to biologic pharmaceutical development, characterization, and comparability including ICH guidance.\nStrong organizational, leadership, and managerial skills.\nExcellent trouble-shooting capabilities.\nStrong interpersonal and written and oral communication skills.\nCandidate with less experience will be considered as Assistant Manager\nCandidate with more\u00a0experience will be considered as Senior Manager\nWe offer attractive remuneration and benefits, 5-day work week, annual leave, medical scheme, comprehensive training and career development opportunities to the qualified candidates.\n\nPlease send your application with full resume stating your present and expected salary to the Company by clicking\u00a0on the \"Apply now\" or by following methods.\u00a0Please quote the\u00a0reference number\u00a0of the applied position in the subject field.\u00a0\n\nMail:\u00a0Human Resources Department, New\u00a0Beta Innovation Limited, 18 Chevalier Commercial Centre, 8 Wang Hoi Road, Kowloon Bay, Kowloon, Hong Kong.\n\nPersonal data collected will be used for recruitment purpose only.", "employment_types": ["Full Time", "Permanent"], "selling_points": ["Research Job in Professional firm", "Attractive remuneration and benefits", "5 days work and location closed to MTR"], "locations": ["Kowloon Bay"], "categories": ["Sciences, Lab, R&D", "Life Science", "Medical Services", "Pharmaceutical", "Research & Development (R&D)"], "post_time": "2022-01-04T07:33:35Z", "salary": {"currency": null, "max": null, "min": null, "period": "monthly", "term": null}, "salary_visible": false, "title_keywords": ["senior manager", "manager"], "responsibilities": ["quality", "design", "testing", "coordinate", "lead a team", "maintain", "plan", "provide guidance"], "requirements": {"degrees": [], "majors": [], "languages": [], "language_level": [], "hard_skills": ["beta", "scheme"], "soft_skills": ["communication skills", "oral", "organizational", "hands on", "comprehensive", "leadership", "interpersonal"], "languages_combined": []}, "experience_required": {"duration": ["5 years", "minimum of 3 years"], "field": ["manufacturing", "research", "analytical", "development", "testing"]}}, {"job_id": "100003009020082", "location_code": "hk", "company": "InvivoGen Limited", "job_title": "Project Specialist (Cell Biology)", "description": "InvivoGen is currently looking for a\u00a0Project Specialist (Cell Biology)\u00a0in order to support the our fast-growing of Asian-Pacific headquarters that was incorporated in 2014. This position is ideal for a talented and open mind professional candidates who are keen to keep interests in science, laboratory works and marketing. You will have chance to involve in business development of InvivoGen in Asian regional market.\n\nResponsibilities:\n\nOverseeing cell line based screening service which includes communicating with customers, designing the protocols and translating test results into reports.\nImplement marketing strategy by translating R&D data to marketing materials.\nAssist InvivoGen distributors by providing advanced technical support.\nPresenting advanced information by giving regular lectures, training courses and experimental support to customers and distributors.\nConnect with life-science key opinion leaders and laboratories stakeholders.\nInteract in a team with multicultural background and communicate with working partners from China, Japan, Korea, Singapore, France, U.S.A etc.\u00a0\n\nJob Requirement:\n\nPh. D. degree in immunology or oncology\nFluent English and Mandarin\nGood communication and presentation skills\nMust be willing to travel frequently throughout China, Japan, Korea and potentially other countries in Asia-Pacific.\n\nBenefits:\n\nCompensation package composed by a 12 months-based salary and performance bonus\nHealth and Dental Insurance\nFlexitime Working Hours", "employment_types": ["Full Time", "Permanent", "Contract"], "selling_points": ["Salary, Performance Bonus, Medical Insurance", "French Biotech Company", "Non-experienced Ph.D. Is Considered"], "locations": ["Shatin Area"], "categories": ["Sciences, Lab, R&D", "Life Science"], "post_time": "2022-01-04T09:52:18Z", "salary": {"currency": null, "max": null, "min": null, "period": "monthly", "term": null}, "salary_visible": false, "title_keywords": ["specialist"], "responsibilities": ["communicate with", "data", "technical support", "communicating with", "reports", "designing", "marketing materials"], "requirements": {"degrees": ["degree"], "majors": [], "languages": ["english", "mandarin"], "language_level": ["fluent"], "hard_skills": [], "soft_skills": ["communication", "presentation skills"], "languages_combined": [{"language": "english", "language_level": ["fluent"]}, {"language": "mandarin", "language_level": ["fluent"]}]}, "experience_required": {"duration": [], "field": []}}, {"job_id": "100003009020973", "location_code": "hk", "company": "Smart Cells (H.K.) Limited", "job_title": "Sales Consultant", "description": "Job description\n\n\nKey responsibilities\n\n\nTo promote and sell umbilical cord blood and cord banking services to customers\nTo achieve pre-set sales targets and prepare sales forecast\nTo prepare quotations, proposals to customers\nTo maintain good after-sales service and excellent relationship with customers and healthcare professionals\n\n\nRequirements\n\n\nUniversity graduate in Science or related disciplines\nPreferably with 1-2 years of sales experience\nExcellent communication, interpersonal and negotiation skills\nAccountable, self-motivated and a good team player\nGood command of written and spoken English and Chinese\nProficient in MS Office applications\nCandidates with more experience will be considered as \"Senior Sales Executive\"\nFresh graduates are also encouraged to apply\n\n\nYour role at Smart Cells is integral to helping the world meet the breakthroughs of stem cells. We are company that is for life.\n\n\nInterested parties, please send your resume with expected salary by clicking APPLY NOW.\n", "employment_types": ["Full Time"], "selling_points": ["University graduate in Science", "Preferably with 1-2 years of sales experience", "Fresh graduates are also encouraged to apply"], "locations": ["Central"], "categories": ["Sales, CS & Business Devpt", "Business Development", "Sciences, Lab, R&D", "Life Science", "Medical Services", "Others"], "post_time": "2022-01-05T02:44:15Z", "salary": {"currency": null, "max": null, "min": null, "period": "monthly", "term": null}, "salary_visible": false, "title_keywords": ["sales consultant"], "responsibilities": ["prepare sales", "after-sales service", "maintain", "forecast", "banking"], "requirements": {"degrees": ["university graduate"], "majors": ["related disciplines", "science"], "languages": ["english", "chinese"], "language_level": ["good command"], "hard_skills": ["ms office"], "soft_skills": ["self-motivated", "good team player", "accountable", "communication", "negotiation skills", "interpersonal"], "languages_combined": [{"language": "english", "language_level": ["good command"]}, {"language": "chinese", "language_level": ["good command"]}]}, "experience_required": {"duration": ["1-2 years"], "field": []}}, {"job_id": "100003009021326", "location_code": "hk", "company": "Life Length Anti-Aging Center (H.K.) Limited", "job_title": "Quality Control Manager (Key Person)", "description": "Responsibilities:\n\nReview and improve protocols and other associated GMP documentation which related to QC.\nAnalysis of raw material, in-process and final bulk cell therapy / gene product samples according to Standard Operating Procedures (SOP) and test methods.\nSupervise team and/or perform tests of quality control: one or more of the following analytical techniques: flow cytometry, blood culture test, cell culture, sterility test, mycoplasma test, and tests specific to cell-based products.\nReview and fine tuning of quality control workflow.\n\nQualification and requirements:\n\nBachelor degree in biotechnology, biomedical engineering, medical laboratory science, pharmacy or other similar disciplines with 2+ yrs relevant working experience in PIC/S GMP quality control; or\nPostgraduate degree of science relevant to cell therapy, gene therapy, regenerative medicines or tissue engineering, or other similar sciences with 2+ yrs of working experience at managerial or supervisory level in GMP manufacturing or quality control of ATPs; or\nStudents who are attending Dip. course of UCL-HKU on Pharmaceutical Development and Regulation of Advanced Therapy Products course of CUHK are encouraged.\nPreferably with practical experience in PIC/S GMP QC testing of sterile products e.g., sterility test, endotoxin test, mycoplasma test, and specific tests to cell-based products .\n\nWe offer 5.5-day work with good career prospects and excellent fringe benefits to the right candidates.\n\nInterested person please send your full resume with your current and expected salary and date of availability to the Human Resources Department.", "employment_types": ["Full Time", "Permanent"], "selling_points": ["Manufacturer of ATPs, PIC/S GMP;", "QC-SOPs, PQS, Sterility Test, Microbial Limit Test", "Professional training for ATP will be provided"], "locations": ["Kowloon Bay"], "categories": ["Sciences, Lab, R&D", "Life Science", "Medical Services", "Pharmaceutical", "Manufacturing", "Quality Assurance, Control & Testing / ISO"], "post_time": "2022-01-05T03:38:15Z", "salary": {"currency": null, "max": null, "min": null, "period": "monthly", "term": null}, "salary_visible": false, "title_keywords": ["manager"], "responsibilities": ["analysis", "review", "procedures", "quality control", "documentation"], "requirements": {"degrees": ["degree", "bachelor", "dip"], "majors": ["biomedical engineering", "science", "manufacturing", "engineering", "medical laboratory science"], "languages": [], "language_level": [], "hard_skills": [], "soft_skills": ["advanced"], "languages_combined": []}, "experience_required": {"duration": [], "field": ["laboratory", "managerial", "engineering", "gmp manufacturing", "relevant working experience", "testing", "quality control", "supervisory level", "medical"]}}, {"job_id": "100003009020063", "location_code": "hk", "company": "Life Length Anti-Aging Center (H.K.) Limited", "job_title": "Authorized Person (ATP)", "description": "Key Roles and Responsibilities:\n\nCertify and ensure ATP batch produced and controlled under the requirements of the Drug office and any other regulations relevant to the production, control and release of medicinal products (PIC/S Guide to GMP);\nKnowledgeable of the regulations and standards of advanced therapy products in Hong Kong;\nKeep knowledge up to date in accordance with the PQS, in light of both: technical and scientific progress, changes in quality management relevant to the products they release;\nParticipate in quality assurance monitoring program, validation and qualification work of facilities, equipment, to ensure compliance with GMP standards;\nInvolve in document control by executing the issuance, distribution, withdrawal of document and maintain the document index database correspondingly;\nRelease finished product;\nAny other duties and responsibilities as an Authorized Person.\n\n\u00a0Qualification and Experience:\n\nDegree holder in Biological Science/Biomedical Engineering, Medical Laboratory Science or similar disciplines; OR Advanced degree in cell therapy, gene therapy or regenerative medicine; and with at least 1 year of working experience at managerial level in GMP quality control of ATPs;\nAuthorized Person for pharmaceutical manufacturers/ATP preferred;\nWithout the above experience, students who are studying Diploma course (Pharmaceutical-quality-regulation) of UCL-HKU and Pharmaceutical Development and Regulation of Advanced Therapy Products course of CUHK are encouraged;\nFluent spoken and written English and Chinese\nIndependent, hardworking, detailed minded, organized, self-motivated and willing to learn\nGood interpersonal skills and able to communicate with different levels of staff.\n\nWe offer 5.5-day work with good career prospects and excellent fringe benefits to the right candidates.\u00a0Interested person please send your full resume with your current and expected salary and date of availability to the Human Resources Department.", "employment_types": ["Full Time", "Permanent"], "selling_points": ["Authorized Person of ATP/Pharmaceutical industry", "QA, QRM, SOPs, PQS, PQRS", "Professional Training for ATP will be provided"], "locations": ["Kowloon Bay"], "categories": ["Sciences, Lab, R&D", "Life Science", "Medical Services", "Pharmaceutical"], "post_time": "2022-01-04T09:50:49Z", "salary": {"currency": null, "max": null, "min": null, "period": "monthly", "term": null}, "salary_visible": false, "title_keywords": [], "responsibilities": ["regulations", "any other duties", "control", "management", "communicate with", "monitoring", "quality", "ensure compliance", "maintain", "executing", "database", "quality control"], "requirements": {"degrees": ["diploma", "degree", "degree holder"], "majors": ["medical laboratory science", "biomedical engineering", "biological science"], "languages": ["english", "chinese"], "language_level": ["fluent"], "hard_skills": ["batch"], "soft_skills": ["organized", "self-motivated", "independent", "advanced", "willing to learn", "interpersonal skills", "controlled", "hardworking", "detailed"], "languages_combined": [{"language": "english", "language_level": ["fluent"]}, {"language": "chinese", "language_level": ["fluent"]}]}, "experience_required": {"duration": ["at least 1 year"], "field": ["pharmaceutical", "managerial", "development", "quality control"]}}, {"job_id": "100003008997662", "location_code": "hk", "company": "Abbott Laboratories Ltd.", "job_title": "Regional Education and Training Manager", "description": "An opportunity has arisen for a passionate Regional Education and Training Manager to join our company in a medical device team.\u00a0 Key job responsibilities are as follows:\n\nDesign, develop and deliver technical training to field people on Abbott\u2019s technology.\nProvide guidance and advice to customers during device implantation.\nAssess training needs and build alignment with countries on training plans and priorities.\nEstablish Centers of Excellence on Abbott technology in partnership with professional societies and key opinion leaders.\nIdentify and develop new learning platforms with the application of virtual technologies to enhance learning outcomes in remote education.\nCollaborate with sale training and marketing to enhance the delivery of marketing messages and the ability to handle objections.\n\nRequirements\n\nBachelor's Degree in health science related field.\n8-10 years of experience in managing cardiac arrhythmia patients.\nIBHRE Certification\nTravel will be required\n\nInterested parties, please send your profile with present and expected salary to Apply Now\n\nPlease visit our website www.abbott.com for more information about our Company or to explore other Abbott opportunities at www.abbottcareers.com\n\nPersonal data collected will be used for recruitment purposes only.", "employment_types": ["Full Time", "Permanent"], "selling_points": [], "locations": ["Kowloon Bay"], "categories": ["Education", "Others", "Sciences, Lab, R&D", "Life Science", "Medical Services", "Medical Services Technician"], "post_time": "2021-12-29T03:38:35Z", "salary": {"currency": null, "max": null, "min": null, "period": "monthly", "term": null}, "salary_visible": false, "title_keywords": ["manager"], "responsibilities": ["collaborate with", "design", "develop", "plans", "provide guidance"], "requirements": {"degrees": ["degree", "bachelor"], "majors": ["science"], "languages": [], "language_level": [], "hard_skills": [], "soft_skills": [], "languages_combined": []}, "experience_required": {"duration": ["8-10 years"], "field": []}}, {"job_id": "100003009002608", "location_code": "hk", "company": "New Epsilon Innovation Limited", "job_title": "Senior Manager (Drug Development)", "description": "Responsibilities:\n\nTo perform field preventive maintenance and repair service of medical devices\nTo provide in-service training to customers\nTo provide technical support to sales team\nTo coordinate with suppliers and customers\n\nRequirements:\n\nDiploma/Higher Diploma in Biomedical/Electronic/Electrical Engineering\u00a0\n2 years' relevant\u00a0working experience in medical equipment industry is preferred, but not a must\nSelf-motivated, hard working and strong analytical thinking\nPleasant personality with good interpersonal skills\nGood command of Chinese and English\nGood computer skills, i.e, Microsoft Word, Excel, Powerpoint, Outlook\nGood command of AutoCad is preferred but not a must\n\n(Interested candidates may visit our company website www.prismtech.com.hk)\n\nWe offer competitive remuneration package, double pay, medical and dental plan for staff, spouse and dependents, life insurance plan and attractive bonus scheme, 14 days annual leave, public holiday and 5 days work week. Please apply with full resume stating current & expected salary and available date by email.", "employment_types": ["Full Time", "Permanent"], "selling_points": ["Research Job in Professional firm", "Attractive remuneration and benefits", "5 days work and location closed to MTR"], "locations": ["Kowloon Bay"], "categories": ["Sciences, Lab, R&D", "Laboratory", "Life Science", "Research & Development (R&D)"], "post_time": "2021-12-28T06:32:22Z", "salary": {"currency": null, "max": null, "min": null, "period": "monthly", "term": null}, "salary_visible": false, "title_keywords": ["senior manager"], "responsibilities": ["maintenance", "technical support", "coordinate with", "repair", "sales team"], "requirements": {"degrees": ["diploma"], "majors": ["electrical engineering"], "languages": ["english", "chinese"], "language_level": ["good command"], "hard_skills": ["excel", "microsoft word", "powerpoint", "computer skills", "outlook", "autocad"], "soft_skills": ["pleasant", "self-motivated", "interpersonal skills", "hard working"], "languages_combined": [{"language": "english", "language_level": ["good command"]}, {"language": "chinese", "language_level": ["good command"]}]}, "experience_required": {"duration": ["2 years"], "field": ["medical equipment", "relevant working experience"]}}, {"job_id": "100003009003580", "location_code": "hk", "company": "Prism Technologies Limited", "job_title": "Sr Service Engineer / Service Engineer (Medical Equipment)", "description": "My client is an innovative manufacturer, they are producing high standard medical device for global market. Currently they are now inviting a high caliber talent to join their group.\n\nResponsibilities:\n\nPlan and implement product promotion strategy to maximize the revenue\nManage product-life-cycle and understand demand in the market\nKeep the market intelligent and search for product up trend\nDrive and organize HCP event and exhibition in the region\n\nRequirements:\n\nDegree or above in Science or related disciplines\nOver 9 years in Medical Product management experience preferable in regional background\nStrong communication skill and details minded\nGood commands in spoken and written in English and Chinese\n\nAPPLY FOR THIS JOB\nInterested candidate please CLICK apply button to apply online or send your resume in MS word format to Hillman Ross Recruitment Solution Professional\n\nPlease note that only shortlisted candidate will be notified. All information will be treated in strict confidence and solely used for recruitment purposes.", "employment_types": ["Full Time", "Permanent"], "selling_points": ["Good career prospect, training provided", "Medical, dental and life insurance", "Double pay + very attractive bonus"], "locations": ["Cheung Sha Wan"], "categories": ["Engineering", "Electrical / Electronics", "Sciences, Lab, R&D", "Life Science", "Medical Services", "Medical Services Technician"], "post_time": "2021-12-28T09:38:11Z", "salary": {"currency": null, "max": null, "min": null, "period": "monthly", "term": null}, "salary_visible": false, "title_keywords": ["service engineer"], "responsibilities": ["plan"], "requirements": {"degrees": ["degree or above"], "majors": ["related disciplines", "science"], "languages": ["english", "chinese"], "language_level": ["good"], "hard_skills": ["ms word"], "soft_skills": ["communication skill", "confidence"], "languages_combined": [{"language": "english", "language_level": ["good"]}, {"language": "chinese", "language_level": ["good"]}]}, "experience_required": {"duration": ["9 years"], "field": ["product management", "medical"]}}, {"job_id": "100003008998925", "location_code": "hk", "company": "Prenetics Limited", "job_title": "Research Associate, Next Generation Sequencing", "description": "Founded in 2014, Prenetics is a major global diagnostics and genetic testing company with the mission to bring health closer to millions of people globally and decentralize healthcare by making the three pillars \u2014 Prevention, Diagnostics and Personalized Care \u2014 comprehensive and accessible to anyone, at anytime and anywhere. Prenetics is led by visionary entrepreneur,\u00a0Danny Yeung, with a team of over 800 employees and operations across 9 locations, including\u00a0United Kingdom,\u00a0Hong Kong,\u00a0India,\u00a0South Africa, and\u00a0Southeast Asia. Prenetics develops consumer genetic testing and early colorectal cancer screening; provides COVID-19 testing, rapid point of care and at-home diagnostic testing and medical genetic testing.\n\nMost recently, Prenetics made\u00a0international headlines to become the first Unicorn in Hong Kong to publicly list on the Nasdaq via merger with\u00a02021 Adrian Cheng's Artisan Acquisition Corp, valuing Prenetics at approximately US $1.7b.\n\nTo further scale up these efforts, we are looking to develop new testing methods and platforms so that more can be helped. In this position, you will play a critical role in development of such testing platforms and technologies under the guidance of our senior scientist. This role would involve running and optimizing different NGS and PacBio protocols, validating the tests and providing the documentation. The candidate will work in close collaboration with other members of our scientific team.\n\n\n\n\nThe candidate should have a solid track record of next-generation sequencing wet-bench working experience, have good attention to detail and be able to adapt quickly and be part of a cross-functional team in a rapidly changing environment. This is a great opportunity to work to make an impact on the NGS- and long-read-based genetic test.\n\nResponsibilities\n\n\n\nExecute experiments including DNA/RNA extraction, preparation of NGS and long-read sequencing library, operate and perform routine maintenance for Illumina, PacBio, and Nanopore sequencers under the supervision of senior scientist.\nAssist day to day running of the research laboratory, e.g. reagent ordering, managing inventory\u00a0\nAssist new product development and implementation\nPrepare scientific documentation and record of the experiments\nMaintain different experimental and R&D databases\nPresent results and progress at regular team and other internal team meetings\nAssist abstract, figure, manuscript, report and proposal preparation for publication and grant application\n\nOur ideal candidate will have\n\n\n\nBachelor degree or above in molecular biology, biochemistry or related discipline\u00a0\nWorking experience in academic or commercial laboratory strongly preferred\nExperience in molecular biology techniques desirable\nSolid track record of NGS wet-bench experience\nExperience in operation and maintenance of Illumina sequencer will be an advantage\nExcellent communication, both written and verbal\nDemonstrated attention to detail and analytical skills\nHighly adaptive, flexible and committed to translational research\nHighly collaborative and able to work well in a team\nStrong organization skill and self-motivated\n\n\n\n\nOur DNA is\u00a0P-R-E-N-E-T-I-C-S.\u00a0See what each word of our company name means:\n\nPassion\n\nYou love what you do and accomplish amazing result\nYou spread positivity, bring enthusiasm to work and inspire team members\nYou drive team toward specific goals, even when they seem unlikely or difficult\n\nResilience\n\nYou embrace changes and be able to drive through uncertainty, ambiguity and uncomfortable situations\nYou bounce back quickly from setbacks and challenges\nYou are persistent and determined to achieve the desired outcome\n\nEmpowerment\n\nYou trust others to play their positions well like an elite sports team\nYou foster a strong team spirit while encouraging others to take initiatives and risks\nYou create a space to allow team to grow and hold each other accountable\n\niNtegrity\n\nYou are trustworthy and lead by example\nYou are consistent in your message and action all the times\nYou deliver what you have promised\n\nEpic\n\nYou challenge your own comfort zone and always outperform yourself\nYou make meaningful and amazing impact to the world\nYou dare to take risks and you move fast\n\nTransparency\n\nYou are completely honest and committed to giving candid feedbacks, no matter how challenging it might be\nYou share ideas, knowledge and skills that empower others and create access to information with the wider team\nYou share wins and failures openly\n\nIngenuity\n\nYou make sound judgement and come up with solutions that are creative and smart. Copy when feasible\nYou challenge the status quo and question things that could be done differently for better. Modify the wheel if you can\u2019t change it\nYou think outside of the box and make value-based innovation\n\nCommunications\n\nYou articulate your thoughts and ideas effectively and respectfully\nYou know your audience and talk in a way they want to be told\nYou make sure communications happens, no matter where you are\n\nSelflessness\n\nYou put the needs of others before one's own and find ways in helping other to succeed\nYou focus on team wins than personal wins and share credits\nYou act in the company's best interest\nWe are Prenetics, our people make us who we are.", "employment_types": ["Full Time", "Permanent"], "selling_points": ["Next Generation Seqeuncing", "Illumina, PacBio, Nanopore Sequencers", "Molecular Testing"], "locations": ["Quarry Bay"], "categories": ["Sciences, Lab, R&D", "Laboratory", "Life Science", "Research & Development (R&D)"], "post_time": "2021-12-24T04:43:29Z", "salary": {"currency": null, "max": null, "min": null, "period": "monthly", "term": null}, "salary_visible": false, "title_keywords": ["research associate"], "responsibilities": ["guidance", "ideas", "maintenance", "operations", "inventory", "implementation", "develop", "testing", "communication", "maintain", "databases", "documentation", "publication", "report"], "requirements": {"degrees": ["degree or above", "bachelor"], "majors": ["molecular biology"], "languages": [], "language_level": [], "hard_skills": ["r&d", "no", "maintenance", "word", "analytical skills", "make", "c", "databases", "rapid", "documentation", "r", "focus"], "soft_skills": ["team spirit", "trustworthy", "persistent", "collaborative", "communication", "comprehensive", "visionary", "articulate", "focus", "determined", "organization skill", "integrity", "committed", "honest", "creative", "ideal", "analytical skills", "attention to detail", "flexible", "self-motivated", "accountable"], "languages_combined": []}, "experience_required": {"duration": [], "field": ["commercial laboratory", "operation", "maintenance", "team"]}}, {"job_id": "100003009005194", "location_code": "hk", "company": "Hillman Ross", "job_title": "Regional Product Manager (Medical device)", "description": "Responsibilities\nConduct sales and marketing activities for life science research products, focusing on biological and medical laboratories in various fields including universities, college, biotech company and governmental organizations.\nResponsible for reagent and consumable sales in respective territories\nDevelop professionalism in technology presentation and technical advisory service, become knowledgeable about new technology and market trend\nMaintain good customer relationship and achieve high customer satisfaction\nRequirements\n\nBachelor's Degree in biological science or related disciplines\nKnowledgeable about basic research techniques in genomics, PCR, microarray and proteomics, experience on laboratory work will be an advantage\nWorking experience is preferred.\nAbility to work under pressure, self-motivated, with good problem solving skills and goal-focused\nGood interpersonal skills, able to work as a team\nProficient in MS Office and basic graphic design\nGood command in oral and written English, Mandarin is a plus\nImmediate availability is preferred\nPlease click \"Apply Now\" to submit your application.\n\nPersonal data collected will be used for recruitment purpose only", "employment_types": ["Full Time", "Permanent"], "selling_points": ["Great career development", "Regional exposure", "Attractive salary package"], "locations": ["Not Specified"], "categories": ["Sciences, Lab, R&D", "Laboratory", "Life Science", "Medical Services", "Specialist"], "post_time": "2021-12-29T03:35:02Z", "salary": {"currency": null, "max": null, "min": null, "period": "monthly", "term": null}, "salary_visible": false, "title_keywords": ["product manager"], "responsibilities": ["maintain", "develop"], "requirements": {"degrees": ["degree", "bachelor"], "majors": ["related disciplines", "biological science"], "languages": ["english", "mandarin"], "language_level": ["good command"], "hard_skills": ["plus", "basic", "goal", "problem solving skills", "ms office"], "soft_skills": ["self-motivated", "oral", "focused", "work as a team", "interpersonal skills", "problem solving skills", "work under pressure"], "languages_combined": [{"language": "english", "language_level": ["good command"]}, {"language": "mandarin", "language_level": ["good command"]}]}, "experience_required": {"duration": [], "field": ["laboratory", "research"]}}, {"job_id": "100003008978526", "location_code": "hk", "company": "Genetimes Excell International Holdings Limited", "job_title": "Account Manager (5 days)", "description": "The Job:\nResponsible for protein drug development, relevant quality control tests development and characterization studies\nResponsible for formulation development and protein drug stability study\nResponsible foranimal efficacy study\nLead and supervise the technicians on quality control tests development based on the international guidelines\nTo prepare the standard operating procedure documents for quality control tests\nTo participate in the relevant documentation for new drug registration\n\nThe Person:\nPh.D/ Master in Biology, Biochemistry, Biotechnology or relevant discipline\nMinimum of 3-5 years of working experience in protein field and relevant quality control tests development\nExperiences of handling biopharmaceutical process in industrial scale and working in GMP environment are preferred\nHave good time management and organization skills with ability to function independently, with little supervision\nIndependent and enthusiastic, with good communication skills and team spirit\nHave good analytical and problem solving skills\nProficiency in spoken and written English and Chinese\nTravelling to PRC and overseas as well as stationing for a short period may be required\u00a0\nWe offer attractive remuneration and benefits,\u00a05-day work week, annual leave, medical scheme, comprehensive training and career development opportunities to the qualified candidates.\nPlease send your application with full resume stating your present and expected salary to the Company by clicking\u00a0on the \"Apply now\" or by following methods.\u00a0Please quote the\u00a0reference number\u00a0of the applied position in the subject field.\u00a0\nMail:\u00a0Human Resources Department, New\u00a0Epsilon Innovation Limited, 18 Chevalier Commercial Centre, 8 Wang Hoi Road, Kowloon Bay, Kowloon, Hong Kong.\nPersonal data collected will be used for recruitment purpose only.", "employment_types": ["Full Time", "Permanent"], "selling_points": ["Responsible for reagent and consumable sales", "Conduct sales and marketing activities", "Bachelor's Degree in biological science"], "locations": ["Not Specified"], "categories": ["Sales, CS & Business Devpt", "Business Development", "Sciences, Lab, R&D", "Laboratory", "Life Science"], "post_time": "2021-12-29T01:44:36Z", "salary": {"currency": null, "max": null, "min": null, "period": "monthly", "term": null}, "salary_visible": false, "title_keywords": ["account manager"], "responsibilities": ["guidelines", "documentation", "quality control"], "requirements": {"degrees": ["master"], "majors": ["biology"], "languages": ["english", "chinese"], "language_level": ["proficiency"], "hard_skills": ["problem solving skills", "scheme"], "soft_skills": ["communication skills", "independently", "independent", "team spirit", "analytical and problem solving skills", "comprehensive", "enthusiastic", "organization skills", "time management"], "languages_combined": [{"language": "english", "language_level": ["proficiency"]}, {"language": "chinese", "language_level": ["proficiency"]}]}, "experience_required": {"duration": ["minimum of 3-5 years"], "field": ["development", "biopharmaceutical", "quality control"]}}, {"job_id": "100003008978525", "location_code": "hk", "company": "Genetimes Excell International Holdings Limited", "job_title": "Account Manager (5 days)", "description": "Responsibilities\nConduct sales and marketing activities for life science research products, focusing on biological and medical laboratories in various fields including universities, college, biotech company and governmental organizations.\nResponsible for reagent and consumable sales in respective territories\nDevelop professionalism in technology presentation and technical advisory service, become knowledgeable about new technology and market trend\nMaintain good customer relationship and achieve high customer satisfaction\nRequirements\n\nBachelor's Degree in biological science or related disciplines\nKnowledgeable about basic research techniques in genomics, PCR, microarray and proteomics, experience on laboratory work will be an advantage\nWorking experience is preferred.\nAbility to work under pressure, self-motivated, with good problem solving skills and goal-focused\nGood interpersonal skills, able to work as a team\nProficient in MS Office and basic graphic design\nGood command in oral and written English, Mandarin is a plus\nImmediate availability is preferred\nPlease click \"Apply Now\" to submit your application.\n\nPersonal data collected will be used for recruitment purpose only", "employment_types": ["Full Time", "Permanent"], "selling_points": ["Responsible for reagent and consumable sales", "Conduct sales and marketing activities", "Bachelor's Degree in biological science"], "locations": ["Not Specified"], "categories": ["Sales, CS & Business Devpt", "Business Development", "Sciences, Lab, R&D", "Laboratory", "Life Science"], "post_time": "2021-12-27T16:03:51Z", "salary": {"currency": null, "max": null, "min": null, "period": "monthly", "term": null}, "salary_visible": false, "title_keywords": ["account manager"], "responsibilities": ["maintain", "develop"], "requirements": {"degrees": ["degree", "bachelor"], "majors": ["related disciplines", "biological science"], "languages": ["english", "mandarin"], "language_level": ["good command"], "hard_skills": ["plus", "basic", "goal", "problem solving skills", "ms office"], "soft_skills": ["self-motivated", "oral", "focused", "work as a team", "interpersonal skills", "problem solving skills", "work under pressure"], "languages_combined": [{"language": "english", "language_level": ["good command"]}, {"language": "mandarin", "language_level": ["good command"]}]}, "experience_required": {"duration": [], "field": ["laboratory", "research"]}}, {"job_id": "100003008998599", "location_code": "hk", "company": "Vanny Science Development Limited", "job_title": "Assistant Laboratory Manager/Senior Laboratory Officer", "description": "Vanny Science is currently recruiting for an Assistant Laboratory Manager/Senior Laboratory Officer. \u00a0The successful candidate will assist his/her superior in overseeing laboratory activities of the Company\u2019s operations in the PRC and Cambodia.\n\nMajor responsibilities:\n\nAssist with designing lab processes and procedures to ensure efficient operations and accuracy of results\nConsort testing activities for quality assurance, including coordination of both internal and external testing, verification of results, data summarization, and troubleshooting\nCoordinate document collection for quality assurance of pre-clinical products, including review and assessment of internal compliance documents, development of sample test plans, and data summarisation\nValidate bioinformatics data using various techniques, such as PCR, qRT-PCR, ELISA kits, and Northern analysis\nMonitor the operations of the laboratory and provide support to maintain the quality standard\nPerform other job-related duties as assigned\nRegular travel might be required\n\nRequirements:\n\nMaster or above degree in molecular biology, biochemistry, genetics, biomedical sciences/life sciences or related field\nAdvanced knowledge in molecular biology techniques including cloning, primer/probe design, sequencing and PCR assay development\n2+ years of managerial roles and a total of 6+ years industry experience\nKnowledge of GLP and AAALAC standards are preferred\nProficiency in Cantonese, Mandarin and English\nProficiency with Microsoft Office suite, and key software applications relevant to publication planning and implementation, such as EndNote, literature search indices, journal databases, etc.\nPositive, true team player, open-minded and possess a strong sense of responsibility\nShort notice period or immediately available is preferred\n\n\nInterested candidates, please forward your detailed resume with date available, present and expected salary by clicking \u201cApply now\u201d.\n\nAll personal data collected will be treated in strict confidence and will only be used for recruitment purpose.\n\n\n\n\n\n", "employment_types": ["Full Time"], "selling_points": [], "locations": ["Hung Hom"], "categories": ["Sciences, Lab, R&D", "Laboratory", "Life Science", "Research & Development (R&D)"], "post_time": "2021-12-24T03:50:33Z", "salary": {"currency": null, "max": null, "min": null, "period": "monthly", "term": null}, "salary_visible": false, "title_keywords": ["officer", "manager", "assistant"], "responsibilities": ["provide support", "data", "operations", "analysis", "review", "quality", "procedures", "testing activities", "testing", "troubleshooting", "coordinate", "compliance", "monitor", "maintain", "coordination", "designing", "plans"], "requirements": {"degrees": ["degree", "master"], "majors": ["molecular biology", "genetics"], "languages": ["cantonese", "english", "mandarin"], "language_level": ["proficiency"], "hard_skills": ["microsoft office suite", "databases"], "soft_skills": ["advanced", "sense of responsibility", "open-minded", "team player", "positive"], "languages_combined": [{"language": "cantonese", "language_level": ["proficiency"]}, {"language": "english", "language_level": ["proficiency"]}, {"language": "mandarin", "language_level": ["proficiency"]}]}, "experience_required": {"duration": ["of 6+ years", "2+ years"], "field": ["managerial"]}}, {"job_id": "100003008997886", "location_code": "hk", "company": "Ocean Park Corporation", "job_title": "Part Time Conservation Assistant", "description": "Responsibilities\n\nThe incumbent will be responsible for supporting the scientific and public awareness programmes for Ocean Park Conservation Foundation, Hong Kong. S/he will need to suuport the marine animal stranding programme, community education and fundraising campaigns as well as office administration.\u00a0S/he is also required to support the AFCD\u00a0boat trips, hourseshoe crab rearing programme, coporate activities,\u00a0donation collection and counting.\n\nRequirement\n\n-\u00a0Degree in Ecology, Biology, Environmental Science or related disciplines\n-\u00a0Ability to conduct field work and handle stranding case independently\n-\u00a0Experience in animal handling is an advantage\n-\u00a0Good presentation and interpretation of conservation/environmental knowledge\n\n\n\nApplications including details of qualifications, working experience, expected salary, contact telephone number and address should be applied via:\u00a0http://careers.oceanpark.com.hk\u00a0--> Job opening --> Full time/ Long-term.\n\nApplicants not contacted within six weeks may consider their application unsuccessful. Personal data collected will be used for recruitment-related purpose only.", "employment_types": ["Part Time"], "selling_points": ["Conservation", "Part Time", "marine animal"], "locations": ["Aberdeen"], "categories": ["Sciences, Lab, R&D", "Life Science", "Research & Development (R&D)", "Others"], "post_time": "2021-12-24T01:59:39Z", "salary": {"currency": null, "max": null, "min": null, "period": "hourly", "term": null}, "salary_visible": false, "title_keywords": ["assistant"], "responsibilities": ["office administration"], "requirements": {"degrees": ["degree"], "majors": ["related disciplines", "biology", "ecology", "environmental science"], "languages": [], "language_level": [], "hard_skills": ["animal handling"], "soft_skills": ["independently", "presentation"], "languages_combined": []}, "experience_required": {"duration": [], "field": []}}, {"job_id": "100003008997929", "location_code": "hk", "company": "Prenetics Limited", "job_title": "Assistant Technical Officer", "description": "Founded in 2014, Prenetics is a major global diagnostics and genetic testing company with the mission to bring health closer to millions of people globally and decentralize healthcare by making the three pillars \u2014 Prevention, Diagnostics and Personalized Care \u2014 comprehensive and accessible to anyone, at anytime and anywhere. Prenetics is led by visionary entrepreneur,\u00a0Danny Yeung, with a team of over 800 employees and operations across 9 locations, including\u00a0United Kingdom,\u00a0Hong Kong,\u00a0India,\u00a0South Africa, and\u00a0Southeast Asia. Prenetics develops consumer genetic testing and early colorectal cancer screening; provides COVID-19 testing, rapid point of care and at-home diagnostic testing and medical genetic testing.\n\nMost recently, Prenetics made\u00a0international headlines to become the first Unicorn in Hong Kong to publicly list on the Nasdaq via merger with\u00a02021 Adrian Cheng's Artisan Acquisition Corp, valuing Prenetics at approximately US $1.7b.\n\nMake a difference to the community! Let's fight COVID-19 together for Hong Kong and make Hong Kong safe again. This is a unique opportunity to make a difference to the community and to play a role to fight COVID-19 here in Hong Kong. The faster we identify, the faster we can stop the virus chain!\n\nThe ideal candidate will thrive on working within a start-up\u00a0biotech\u00a0environment, where your science academic background and hands on experience in processing of clinical laboratory testing will contribute to our effort in Covid-19 fighting.\u00a0Please note that all safety guidelines and protocols will be met to ensure safety for everyone. Join us as an Assistant\u00a0Technical Officer\u00a0and make a difference today!\u00a0\n\nMost importantly, you MUST be passionate about health & wellness. Individuals which do not meet this requirement will not be considered.\n\nResponsibilities\u00a0\n\nAssist Medical Laboratory Technician for the specimens pre-processing steps, equipment calibration, solution preparation and daily operational maintenance\nConduct assigned laboratory and administrative tasks to ensure timely delivery and accuracy of tests\nComply with all current best-in-class laboratory practices and laboratory standard operating procedure and company policies and procedures\nHandle ad hoc record data into the laboratory system and databases\u00a0\nPerform quality control and external proficiency testing\nOur ideal candidate will have\n\nBachelor Degree in Biomedical Science / Medical Laboratory Science or related field e.g. Molecular Biology / Genomics / Biochemistry\nExperience in processing of clinical laboratory testing would be an advantage\nFluent in Cantonese and English, writing and speaking, fluency in Mandarin a plus\nStrong sense of teamwork and able to work under pressure\nComfortable and flexible in a fast-paced, dynamic team environment\nShift and weekend duties are required, extra monetary\u00a0incentives for overnight shifts\nStrong commitment to the vision and mission of Prenetics and our focus on Health and Wellness\nAbility to work independently\nCandidates with more than 5+ years experience in a related field will be considered as a Technical Officer\nCandidates with limited availability will be considered for part-time hires\n\nOur DNA is\u00a0P-R-E-N-E-T-I-C-S.\u00a0See what each word of our company name means:\n\nPassion\n\nYou love what you do and accomplish amazing result\nYou spread positivity, bring enthusiasm to work and inspire team members\nYou drive team toward specific goals, even when they seem unlikely or difficult\n\nResilience\n\nYou embrace changes and be able to drive through uncertainty, ambiguity and uncomfortable situations\nYou bounce back quickly from setbacks and challenges\nYou are persistent and determined to achieve the desired outcome\n\nEmpowerment\n\nYou trust others to play their positions well like an elite sports team\nYou foster a strong team spirit while encouraging others to take initiatives and risks\nYou create a space to allow team to grow and hold each other accountable\n\niNtegrity\n\nYou are trustworthy and lead by example\nYou are consistent in your message and action all the times\nYou deliver what you have promised\n\nEpic\n\nYou challenge your own comfort zone and always outperform yourself\nYou make meaningful and amazing impact to the world\nYou dare to take risks and you move fast\n\nTransparency\n\nYou are completely honest and committed to giving candid feedbacks, no matter how challenging it might be\nYou share ideas, knowledge and skills that empower others and create access to information with the wider team\nYou share wins and failures openly\n\nIngenuity\n\nYou make sound judgement and come up with solutions that are creative and smart. Copy when feasible\nYou challenge the status quo and question things that could be done differently for better. Modify the wheel if you can\u2019t change it\nYou think outside of the box and make value-based innovation\n\nCommunications\n\nYou articulate your thoughts and ideas effectively and respectfully\nYou know your audience and talk in a way they want to be told\nYou make sure communications happens, no matter where you are\n\nSelflessness\n\nYou put the needs of others before one's own and find ways in helping other to succeed\nYou focus on team wins than personal wins and share credits\nYou act in the company's best interest\nWe are Prenetics, our people make us who we are.", "employment_types": ["Full Time", "Part Time"], "selling_points": ["Great opportunities for science graduates", "Hands-on laboratory exposure", "Great chance to work at a start up culture"], "locations": ["Quarry Bay"], "categories": ["Sciences, Lab, R&D", "Laboratory", "Life Science", "Medical Services", "Medical Services Technician"], "post_time": "2021-12-24T02:06:13Z", "salary": {"currency": null, "max": null, "min": null, "period": "monthly", "term": null}, "salary_visible": false, "title_keywords": ["assistant technical officer"], "responsibilities": ["ad hoc", "ideas", "maintenance", "data", "guidelines", "operations", "policies", "procedures", "testing", "databases", "quality control", "administrative tasks", "work under pressure"], "requirements": {"degrees": ["degree", "bachelor"], "majors": ["biomedical science", "medical laboratory science"], "languages": ["cantonese", "english", "mandarin"], "language_level": ["fluency", "fluent"], "hard_skills": ["plus", "no", "maintenance", "word", "make", "safe", "dynamic", "c", "databases", "rapid", "r", "focus", "processing"], "soft_skills": ["team spirit", "trustworthy", "persistent", "comprehensive", "visionary", "articulate", "focus", "passionate about", "work under pressure", "determined", "integrity", "committed", "honest", "creative", "ideal", "work independently", "unique", "hands on", "dynamic", "flexible", "timely", "teamwork", "accountable"], "languages_combined": [{"language": "cantonese", "language_level": ["fluent"]}, {"language": "english", "language_level": ["fluent"]}, {"language": "mandarin", "language_level": ["fluency"]}]}, "experience_required": {"duration": ["5+ years"], "field": ["related", "laboratory testing", "clinical"]}}]