[{"job_id": "100003009054298", "location_code": "hk", "company": "K. Wah International Holdings Ltd", "job_title": "Customer Service Officer (Property Handover)", "description": "Job Responsibilities:\u00a0\u00a0\n\n\nAssist with handover logistics, and work with internal/ external parties to ensure timely and effective service to customers\nProvide after-sales services and follow up proactively\nHandle and respond to customer enquire\nAssist in sales activities and operations\nProvide tours for potential buyers inside property, common area and recreational facilities\nSupport on-site logistics\nCompile operation reports on number of visitors and customer feedback\nMaintain inventory of materials and others upon request\n\nJob Requirements:\u00a0\u00a0\n\n\nDiploma holder or above\n1 to 2 years of relevant experience in particular handover of residential properties or client-facing customer service role\nGood command of spoken & written Cantonese and English, basic skills in Mandarin\nGood interpersonal and communication skills, good telephone manner and responsive to clients\u2019 enquiries\nPositive working attitude, responsible and result-oriented\nGood listener\nProficient in MS Office application (Excel, Word, PowerPoint and Chinese Word Processing)\n\nInterested parties please send resume with salary expectation and availability to\u00a0Human Resources Department, K. Wah International Holdings Limited, 29/F, K. Wah Centre, 191 Java Rd., North Point, H.K.\u00a0or by clicking\u00a0Apply Now.\n\nAll Personal data collected will be used for recruitment purpose only. All applications will be retained for a maximum period of 2 years and may be considered for other suitable positions within the Group.", "employment_types": ["Full Time", "Permanent"], "selling_points": ["Handle all inquiries in a courtesy way", "Identify and deal with customer complaints", "Collect customer feedback on service excellence"], "locations": ["North Point"], "categories": ["Sales, CS & Business Devpt", "Customer Service - Supervisor / Officer", "Property / Real Estate", "Others", "Sales - Real Estate"], "post_time": "2022-01-17T09:05:23Z", "salary": {"currency": null, "max": null, "min": null, "period": "monthly", "term": null}, "salary_visible": false, "title_keywords": ["customer service officer"], "responsibilities": ["sales activities", "operations", "inventory", "external parties", "maintain", "logistics", "reports"], "requirements": {"degrees": ["diploma holder"], "majors": [], "languages": ["cantonese", "english", "chinese", "mandarin"], "language_level": ["good command", "proficient", "basic"], "hard_skills": ["excel", "basic", "chinese word processing", "word", "powerpoint", "ms office"], "soft_skills": ["result-oriented", "communication skills", "responsible", "positive working attitude", "customer service", "interpersonal", "telephone manner", "client-facing", "responsive"], "languages_combined": [{"language": "cantonese", "language_level": ["good command", "basic"]}, {"language": "english", "language_level": ["good command", "basic"]}, {"language": "chinese", "language_level": ["proficient"]}, {"language": "mandarin", "language_level": ["good command", "basic"]}]}, "experience_required": {"duration": ["1 to 2 years"], "field": ["customer service", "relevant experience", "client-facing"]}}, {"job_id": "100003009034675", "location_code": "hk", "company": "S.H.K. Real Estate Management Company Limited", "job_title": "\u7269\u696d\u52a9\u7406\u54e1(\u4e2d\u73ed: 14:30 - 23:30)", "description": "\u5354\u52a9\u57f7\u884c\u9ad8\u7d1a\u5546\u696d\u5927\u5ec8\u4e4b\u65e5\u5e38\u7ba1\u7406\u53ca\u4e8b\u52d9\n\u6bcf\u5929\u5de5\u4f5c9\u5c0f\u6642\n\u4e0d\u9700\u8f2a\u73ed\u5de5\u4f5c\n\u4e2d\u4e94\u7a0b\u5ea6\u6216\u5177\u8cc7\u6b77\u67b6\u69cb\u540c\u7b49\u8cc7\u6b77\n\u9808\u6301\u6709\u6709\u6548\u300c\u4fdd\u5b89\u4eba\u54e1\u8a31\u53ef\u8b49\u300d\u53ca\u8a8d\u53efQAS\u8a3c\u66f8\n\u6b61\u8fce\u7121\u76f8\u95dc\u7d93\u9a57\u8005\u61c9\u5fb5\n\u85aa\u91d1\u53ef\u9ad8\u9054\u6bcf\u6708$17,000\n\n\u4ee5\u4e0a\u8077\u4f4d\u53ef\u4eab\u6709\u512a\u539a\u54e1\u5de5\u798f\u5229\uff0c\u5305\u62ec\u6709\u85aa\u5e74\u50479\u5929\u3001\u52e4\u5de5\u734e\u3001\u81b3\u98df\u6d25\u8cbc\u3001\u5e74\u7d42\u96d9\u7ce7\u3001\u5e74\u7d42\u734e\u91d1\u3001\u91ab\u7642\u798f\u5229\u3001\u5b8c\u5584\u57f9\u8a13\u53ca\u6649\u5347\u6a5f\u6703\u3002\n\n\u6709\u610f\u8005\uff0c\u8acb\u81f4\u96fb\u4ee5\u4e0b\u806f\u7d61\u4eba\u7533\u8acb\uff1a\n\n\u7063\u4ed4\u5340\uff1a\n\u96fb\u8a71\uff1a9710 0179 \u6e6f\u5148\u751f\n\n\u9664\u4e0a\u8ff0\u8077\u4f4d\u5916\uff0c\u5c1a\u6709\u5176\u4ed6\u7a7a\u7f3a\u3002\u8acb\u900f\u904e\u4ee5\u4e0b\u65b9\u6cd5\u5c07\u5c65\u6b77\u4ea4\u5230S.H.K.\u7269\u696d\u7ba1\u7406\u6709\u9650\u516c\u53f8\u4e4b\u4eba\u529b\u8cc7\u6e90\u53ca\u884c\u653f\u90e8\u3002\n\n\u90f5\u5bc4\uff1a\u89c0\u5858\u5de7\u660e\u885795\u865f\u4e16\u9054\u4e2d\u5fc316\u6a13\u3000\u50b3\u771f\uff1a2827 2125\n\n\nS.H.K. \u7269\u696d\u7ba1\u7406\u6709\u9650\u516c\u53f8\u4e43\u5e73\u7b49\u6a5f\u6703\u50f1\u4e3b\uff0c\u800c\u6240\u6709\u6536\u96c6\u8cc7\u6599\u7d55\u5c0d\u4fdd\u5bc6\u53ca\u53ea\u7528\u4f5c\u96c6\u5718\u5167\u90e8\u62db\u8058\u4e4b\u7528\u9014\u3002", "employment_types": ["Full Time", "Permanent"], "selling_points": ["\u4e0d\u9700\u8f2a\u73ed\u5de5\u4f5c", "\u53ef\u4eab9\u5929\u5e74\u5047\uff0c\u91ab\u7642\u798f\u5229\u7b49", "\u6bcf\u5929\u5de5\u4f5c9\u5c0f\u6642"], "locations": ["Not Specified"], "categories": ["Property / Real Estate", "Property Management", "Others", "Others", "Security / Safety Control"], "post_time": "2022-01-16T21:50:10Z", "salary": {"currency": null, "max": null, "min": null, "period": "monthly", "term": null}, "salary_visible": false, "title_keywords": [], "responsibilities": [], "requirements": {"degrees": [], "majors": [], "languages": [], "language_level": [], "hard_skills": [], "soft_skills": [], "languages_combined": []}, "experience_required": {"duration": [], "field": []}}, {"job_id": "100003009053243", "location_code": "hk", "company": "Jones Lang LaSalle Management Services Ltd", "job_title": "\u4e2d\u74b0\u5546\u5ec8 - \u56fa\u5b9a\u65e9\u6216\u591c\u66f4\u7269\u696d\u52a9\u7406 12 \u5c0f\u6642 (\u5168\u8077)", "description": "\u8077\u8cac:\n\n\u5de1\u8996\u7269\u696d\n\u78ba\u4fdd\u6240\u6709\u8a2d\u65bd\u904b\u4f5c\u6b63\u5e38\n\u8655\u7406\u9867\u5ba2\u67e5\u8a62\n\u5354\u52a9\u4e0a\u53f8\u8ddf\u9032\u6295\u8a34\u53ca\u8655\u7406\u7dca\u6025\u4e8b\u6545\n\u4e3b\u52d5\u8207\u696d\u6236\u63a5\u89f8\n\u7dad\u6301\u826f\u597d\u95dc\u4fc2\n\n\u8981\u6c42:\n\n\u4e2d\u4e94\u6216\u4ee5\u4e0a\u7a0b\u5ea6\n\u4e00\u5e74\u6216\u4ee5\u4e0a\u7269\u696d\u7ba1\u7406\u7d93\u9a57\u512a\u5148\n\u6210\u719f, \u6709\u826f\u597d\u7d44\u7e54\u80fd\u529b, \u6709\u8cac\u4efb\n\u57fa\u672c\u82f1\u8a9e\u53ca\u570b\u8a9e\u3001\u826f\u597d\u7cb5\u8a9e\u7684\u8a00\u8a9e\u80fd\u529b\n\u6a02\u89c0\u6027\u683c \u53ca \u5177\u7368\u7acb\u80fd\u529b\n\u6709\u4e00\u822c\u96fb\u8166\u77e5\u8b58\u512a\u5148\n\u5de5\u4f5c\u6642\u9593: \u65e9\u73ed(0700-1900) \u591c\u73ed (1900-0700)\n\n\u6b61\u8fce\u76f4\u63a5\u81f4\u96fb 2117 8010\u67e5\u8a62\u3002\n\nWe offer attractive remuneration package and good career prospect for the right applicant.\n\nPlease apply by clicking\u00a0\"Apply Now\", or submit full resume and expected salary to the\u00a0HR Department, Room 1402, 14/F, Dorset House, Taikoo Place, 979 King's Road, Quarry Bay, HK\u00a0or\u00a0fax to 2968-4177.\u00a0\n\n(Please quote the reference number on the subject of email)\n\nApplicants not invited for interviews within 6 weeks may consider their applications unsuccessful. Information provided will be treated with strict confidential and be used for the purpose of employment only.", "employment_types": ["Full Time", "Permanent"], "selling_points": ["F.5 or above", "Min. 1 year's experience", "Luxurious Residential Building"], "locations": ["Central & Western Area"], "categories": ["Property / Real Estate", "Property Management", "Others", "Building & Construction", "Others"], "post_time": "2022-01-17T08:07:19Z", "salary": {"currency": null, "max": null, "min": null, "period": "monthly", "term": null}, "salary_visible": false, "title_keywords": [], "responsibilities": [], "requirements": {"degrees": [], "majors": [], "languages": [], "language_level": [], "hard_skills": [], "soft_skills": [], "languages_combined": []}, "experience_required": {"duration": [], "field": []}}, {"job_id": "100003009034667", "location_code": "hk", "company": "S.H.K. Real Estate Management Company Limited", "job_title": "\u5ba2\u6236\u670d\u52d9\u54e1 (\u65e9\u73ed\uff1a11:00-20:00/\u4e2d\u73ed: 14:00-23:00/\u591c\u73ed\uff1a22:30 - 07:30)", "description": "\u5354\u52a9\u57f7\u884c\u9ad8\u7d1a\u5546\u696d\u5927\u5ec8\u4e4b\u65e5\u5e38\u7ba1\u7406\u53ca\u4e8b\u52d9\n\u6bcf\u5929\u5de5\u4f5c9\u5c0f\u6642\n\u4e0d\u9700\u8f2a\u73ed\u5de5\u4f5c\n\u4e2d\u4e94\u7a0b\u5ea6\u6216\u5177\u8cc7\u6b77\u67b6\u69cb\u540c\u7b49\u8cc7\u6b77\n\u9808\u6301\u6709\u6709\u6548\u300c\u4fdd\u5b89\u4eba\u54e1\u8a31\u53ef\u8b49\u300d\u53ca\u8a8d\u53efQAS\u8a3c\u66f8\n\u6b61\u8fce\u7121\u76f8\u95dc\u7d93\u9a57\u8005\u61c9\u5fb5\n\u85aa\u91d1\u53ef\u9ad8\u9054\u6bcf\u6708$17,000\n\n\u4ee5\u4e0a\u8077\u4f4d\u53ef\u4eab\u6709\u512a\u539a\u54e1\u5de5\u798f\u5229\uff0c\u5305\u62ec\u6709\u85aa\u5e74\u50479\u5929\u3001\u52e4\u5de5\u734e\u3001\u5e74\u7d42\u734e\u91d1\u3001\u91ab\u7642\u798f\u5229\u3001\u5b8c\u5584\u57f9\u8a13\u53ca\u6649\u5347\u6a5f\u6703\u3002\n\n\u6709\u610f\u8005\uff0c\u8acb\u81f4\u96fb\u4ee5\u4e0b\u806f\u7d61\u4eba\u7533\u8acb\uff1a\n\n\u8354\u679d\u89d2\u5340\uff1a\n\n\u96fb\u8a71\uff1a2307 6909\u00a0\u7f85\u5c0f\u59d0\n\n\u5c16\u6c99\u5480\uff1a\n\n\u96fb\u8a71\uff1a2312 2110 \u5468\u5c0f\u59d0\n\n\u00a0\n\u9664\u4e0a\u8ff0\u8077\u4f4d\u5916\uff0c\u5c1a\u6709\u5176\u4ed6\u7a7a\u7f3a\u3002\u8acb\u900f\u904e\u4ee5\u4e0b\u65b9\u6cd5\u5c07\u5c65\u6b77\u4ea4\u5230S.H.K.\u7269\u696d\u7ba1\u7406\u6709\u9650\u516c\u53f8\u4e4b\u4eba\u529b\u8cc7\u6e90\u53ca\u884c\u653f\u90e8\u3002\n\n\u90f5\u5bc4\uff1a\u89c0\u5858\u5de7\u660e\u885795\u865f\u4e16\u9054\u4e2d\u5fc316\u6a13\u3000\u50b3\u771f\uff1a2827 2125\n\n\nS.H.K. \u7269\u696d\u7ba1\u7406\u6709\u9650\u516c\u53f8\u4e43\u5e73\u7b49\u6a5f\u6703\u50f1\u4e3b\uff0c\u800c\u6240\u6709\u6536\u96c6\u8cc7\u6599\u7d55\u5c0d\u4fdd\u5bc6\u53ca\u53ea\u7528\u4f5c\u96c6\u5718\u5167\u90e8\u62db\u8058\u4e4b\u7528\u9014\u3002", "employment_types": ["Full Time", "Permanent"], "selling_points": ["\u4e0d\u9700\u8f2a\u73ed\u5de5\u4f5c", "\u53ef\u4eab9\u5929\u5e74\u5047\uff0c\u91ab\u7642\u798f\u5229\u7b49", "\u6bcf\u5929\u5de5\u4f5c9\u5c0f\u6642"], "locations": ["Not Specified"], "categories": ["Property / Real Estate", "Property Management", "Others", "Others", "Security / Safety Control"], "post_time": "2022-01-16T21:50:10Z", "salary": {"currency": null, "max": null, "min": null, "period": "monthly", "term": null}, "salary_visible": false, "title_keywords": [], "responsibilities": [], "requirements": {"degrees": [], "majors": [], "languages": [], "language_level": [], "hard_skills": [], "soft_skills": [], "languages_combined": []}, "experience_required": {"duration": [], "field": []}}, {"job_id": "100003009053255", "location_code": "hk", "company": "Jones Lang LaSalle Management Services Ltd", "job_title": "\u4e2d\u74b0\u5546\u5ec8 - \u56fa\u5b9a\u591c\u66f4\u7269\u696d\u52a9\u7406 12 \u5c0f\u6642 (\u5168\u8077)", "description": "\u8077\u8cac:\n\n\u5de1\u8996\u7269\u696d\n\u78ba\u4fdd\u6240\u6709\u8a2d\u65bd\u904b\u4f5c\u6b63\u5e38\n\u8655\u7406\u9867\u5ba2\u67e5\u8a62\n\u5354\u52a9\u4e0a\u53f8\u8ddf\u9032\u6295\u8a34\u53ca\u8655\u7406\u7dca\u6025\u4e8b\u6545\n\u4e3b\u52d5\u8207\u696d\u6236\u63a5\u89f8\n\u7dad\u6301\u826f\u597d\u95dc\u4fc2\n\n\u8981\u6c42:\n\n\u4e2d\u4e94\u6216\u4ee5\u4e0a\u7a0b\u5ea6\n\u4e00\u5e74\u6216\u4ee5\u4e0a\u7269\u696d\u7ba1\u7406\u7d93\u9a57\u512a\u5148\n\u6210\u719f, \u6709\u826f\u597d\u7d44\u7e54\u80fd\u529b, \u6709\u8cac\u4efb\n\u57fa\u672c\u82f1\u8a9e\u53ca\u570b\u8a9e\u3001\u826f\u597d\u7cb5\u8a9e\u7684\u8a00\u8a9e\u80fd\u529b\n\u6a02\u89c0\u6027\u683c \u53ca \u5177\u7368\u7acb\u80fd\u529b\n\u6709\u4e00\u822c\u96fb\u8166\u77e5\u8b58\u512a\u5148\n\u5de5\u4f5c\u6642\u9593: \u591c\u73ed (1900-0700)\n\n\u6b61\u8fce\u76f4\u63a5\u81f4\u96fb 2117 8010\u67e5\u8a62\u3002\n\nWe offer attractive remuneration package and good career prospect for the right applicant.\n\nPlease apply by clicking\u00a0\"Apply Now\", or submit full resume and expected salary to the\u00a0HR Department, Room 1402, 14/F, Dorset House, Taikoo Place, 979 King's Road, Quarry Bay, HK\u00a0or\u00a0fax to 2968-4177.\u00a0\n\n(Please quote the reference number on the subject of email)\n\nApplicants not invited for interviews within 6 weeks may consider their applications unsuccessful. Information provided will be treated with strict confidential and be used for the purpose of employment only.", "employment_types": ["Full Time", "Permanent"], "selling_points": ["F.5 or above", "Min. 1 year's experience", "Luxurious Residential Building"], "locations": ["Central & Western Area"], "categories": ["Property / Real Estate", "Property Management", "Others", "Building & Construction", "Others"], "post_time": "2022-01-17T08:06:44Z", "salary": {"currency": null, "max": null, "min": null, "period": "monthly", "term": null}, "salary_visible": false, "title_keywords": [], "responsibilities": [], "requirements": {"degrees": [], "majors": [], "languages": [], "language_level": [], "hard_skills": [], "soft_skills": [], "languages_combined": []}, "experience_required": {"duration": [], "field": []}}, {"job_id": "100003009051716", "location_code": "hk", "company": "Tung Wah Group of Hospitals", "job_title": "\u7269\u696d\u4fdd\u5b89\u54e1 (\u8077\u4f4d\u7de8\u865f\uff1aA3/BA/JOBS)", "description": "(\u8077\u4f4d\u7de8\u865f\uff1aA3/BA/JOBS)\n\n\u8077\u8cac\uff1a\n\n\u8ca0\u8cac\u8655\u7406\u4f4f\u5ba2\u6295\u8a34\uff0c\u5de1\u908f\u5927\u5ec8\u4ee5\u53ca\u57f7\u884c\u65e5\u5e38\u4fdd\u5b89\u5de5\u4f5c\u53ca\u7c21\u55ae\u7dad\u4fee\u5de5\u4f5c\uff0c\u9808\u8f2a\u73ed\u53ca\u7a7f\u5236\u670d\uff0c\u6bcf\u73ed\u5341\u4e8c\u5c0f\u6642\u3002\n\n\u7406\u60f3\u7684\u7533\u8acb\u8005\u61c9\u5177\u5099\uff1a\n\n\u4e2d\u5b78\u7a0b\u5ea6\u512a\u5148\u8003\u616e\uff0c\u64cd\u6d41\u5229\u7cb5\u8a9e\uff0c\u80fd\u66f8\u5beb\u7c21\u55ae\u5831\u544a\uff0c\u7121\u72af\u7f6a\u7d00\u9304\u53ca\u6301\u6709\u53ef\u57f7\u884c\u4e59\u985e\u4fdd\u5b89\u5de5\u4f5c\u7684\u4fdd\u5b89\u4eba\u54e1\u8a31\u53ef\u8b49(\u5c1a\u672a\u6301\u6709\u8005\u4ea6\u53ef\u7533\u8acb\uff0c\u4f46\u5fc5\u9808\u65bc\u5230\u8077\u524d\u5df2\u9818\u53d6\u8a72\u8b49)\uff1b\n\u9808\u65bc\u5230\u8077\u524d\u5df2\u5b8c\u6210\u7d93\u4fdd\u5b89\u53ca\u8b77\u885b\u696d\u7ba1\u7406\u59d4\u54e1\u6703\u8a8d\u53ef\u7684\u4fdd\u5b89\u57f9\u8a13\u8ab2\u7a0b\u53ca\u53d6\u5f97\u5408\u683c\u6210\u7e3e\uff1b\u53ca\n\u5177\u6709\u95dc\u5de5\u4f5c\u7d93\u9a57\u8005\u5c07\u7372\u512a\u5148\u8003\u616e\u3002\n\n\u85aa\u916c\u53ca\u8058\u7528\u689d\u4ef6\uff1a\n\n\u7372\u9078\u7684\u7533\u8acb\u4eba\u5c07\u4ee5\u5408\u7d04\u689d\u6b3e\u53d7\u8058\u3002\u6bcf\u6708\u85aa\u91d1\u73fe\u6642\u70ba$16,490(\u6771\u83ef\u7b2c\u4e00\u6a19\u6e96\u85aa\u7d1a\u8868\u7b2c\u4e5d\u9ede)\u3002\u6709\u95dc\u85aa\u91d1\u6703\u6309\u6771\u83ef\u898f\u5b9a\u53ca/\u6216\u53c3\u7167\u516c\u52d9\u54e1\u85aa\u916c\u6aa2\u8a0e\u800c\u5411\u4e0a/\u4e0b\u8abf\u6574\u6216\u51cd\u7d50\u3002\u54e1\u5de5\u798f\u5229\u5305\u62ec\u6709\u85aa\u5047\u671f\u3001\u9032\u4fee\u6d25\u8cbc\u3001\u91ab\u7642\u53ca\u7259\u9f52\u4fdd\u5065\u3002\n\n\u7533\u8acb\u7a0b\u5e8f\uff1a\n\n\u8acb\u5c07\u500b\u4eba\u5c65\u6b77\u6216\u586b\u59a5\u7533\u8acb\u8868\u683c<\u8868\u865f\uff1aF601>(\u53ef\u89aa\u81e8\u7d22\u53d6\u6216\u5f9e\u672c\u9662\u7684\u7db2\u9801http://www.tungwah.org.hk\u4e0b\u8f09)\uff0c\u5bc4\u9999\u6e2f\u4e0a\u74b0\u666e\u4ec1\u8857\u5341\u4e8c\u865f\u6771\u83ef\u4e09\u9662\u9ec3\u9cf3\u7fce\u7d00\u5ff5\u5927\u6a13\u56db\u6a13\u4eba\u529b\u8cc7\u6e90\u79d1\u4e3b\u7ba1\u6536\uff0c\u4fe1\u5167\u53ca\u4fe1\u5c01\u9762\u8acb\u8a3b\u660e\u7533\u8acb\u7684\u8077\u4f4d\u53ca\u8077\u4f4d\u7de8\u865f\u3002\u6771\u83ef\u4e09\u9662\u4e0d\u6703\u63a5\u6536\u90f5\u8cc7\u4e0d\u8db3\u7684\u4fe1\u4ef6\u3002\u70ba\u78ba\u4fdd\u90f5\u905e\u7121\u8aa4\uff0c\u8acb\u5728\u6295\u5bc4\u90f5\u4ef6\u6642\u652f\u4ed8\u8db3\u984d\u90f5\u8cc7\u53ca\u8a3b\u660e\u56de\u90f5\u5730\u5740\u3002\u6771\u83ef\u4e09\u9662\u5728\u4f7f\u7528\u6c42\u8077\u8005\u63d0\u4f9b\u7684\u500b\u4eba\u8cc7\u6599\u6642\uff0c\u53ea\u6703\u5c07\u8cc7\u6599\u4f5c\u6709\u95dc\u62db\u8058\u7528\u9014\uff0c\u4e26\u6703\u56b4\u683c\u9075\u5b88\u9662\u65b9\u500b\u4eba\u8cc7\u6599\u653f\u7b56\u7684\u898f\u5b9a\u3002\n\n\u6211\u5011\u662f\u5e73\u7b49\u6a5f\u6703\u50f1\u4e3b", "employment_types": ["Full Time", "Contract"], "selling_points": [], "locations": ["Not Specified"], "categories": ["Property / Real Estate", "Property Management", "Others", "Public / Civil", "Social Services - Community / Non-profit Organization"], "post_time": "2022-01-16T21:51:05Z", "salary": {"currency": null, "max": null, "min": null, "period": "monthly", "term": null}, "salary_visible": false, "title_keywords": [], "responsibilities": [], "requirements": {"degrees": [], "majors": [], "languages": [], "language_level": [], "hard_skills": [], "soft_skills": [], "languages_combined": []}, "experience_required": {"duration": [], "field": []}}, {"job_id": "100003009055363", "location_code": "hk", "company": "Centaline Property Agency Ltd", "job_title": "\u6301\u724c\u71df\u696d\u54e1 / \u6301\u724c\u5730\u7522\u4ee3\u7406 (\u8dd1\u99ac\u5730/\u9ec3\u7af9\u5751/\u5929\u540e)", "description": "\u8077\u8cac:\n\n\n\u641c\u96c6\u6709\u95dc\u51fa\u552e\u6216\u79df\u8cc3\u7269\u696d\u8cc7\u8a0a\n\u4e86\u89e3\u6f5b\u5728\u7684\u8cb7\u5bb6\u548c\u79df\u6236\u7684\u9700\u6c42\n\u4fc3\u6210\u6a13\u76e4\u4e4b\u8cb7\u8ce3\u53ca\u79df\u8cc3\n\u5411\u5ba2\u6236\u4ecb\u7d39\u9280\u884c\u6309\u63ed\u670d\u52d9\n\n\u8981\u6c42:\n\n\u9808\u6301\u6709\u6548\u71df\u696d\u54e1\u00a0/\u00a0\u5730\u7522\u4ee3\u7406\u724c\u7167\n\u7a4d\u6975\u4e3b\u52d5, \u826f\u597d\u6e9d\u901a\u6280\u5de7\n\n\u00a0\u798f\u5229:\n\n\u5e95\u85aa + \u4f63\u91d1 + \u734e\u91d1\n\u514d\u8cbb\u4e2d\u539f\u8a13\u7df4\u5b78\u9662\u57f9\u8a13\u5404\u985e\u5c08\u696d\u77e5\u8b58\n\u6709\u85aa\u5e74\u5047\u53ca\u75c5\u5047\n\u5a5a\u5047\u53ca\u6069\u6064\u5047\n\u5f37\u7a4d\u91d1\n\u91ab\u7642\u6d25\u8cbc\n\u9032\u4fee\u6d25\u8cbc\n\u4ecb\u7d39\u65b0\u4eba\u734e\u91d1\n\u50f1\u54e1\u8cb7\u6a13/\u79df\u6a13\u514d\u4f63\n\u54e1\u5de5\u8cfc\u7269\u512a\u60e0\n\u5f37\u5927\u96fb\u8166\u8cc7\u6599\u5eab\u53ca\u5f8c\u52e4\u652f\u63f4\uff0c\u52a9\u8f15\u9b06\u5b8c\u6210\u4ea4\u6613\n\u5b8c\u5584\u798f\u5229\u5236\u5ea6\uff0c\u826f\u597d\u6649\u5347\u6a5f\u6703\n\u6709\u610f\u8acb\u806f\u7d61\u4eba\u529b\u8cc7\u6e90\u90e8Whatsapp\u71b1\u7dda: 5941 9906\u67e5\u8a62\u3002\n\n(\u4e00\u5207\u8cc7\u6599\u4fdd\u5bc6\u53ca\u53ea\u4f5c\u62db\u8058\u7528\u9014)", "employment_types": ["Full Time", "Permanent"], "selling_points": ["company training school, education subsidies", "Staff waive housing agency fees, staff discount", "sales, property agent, license agent, real estate"], "locations": ["Not Specified"], "categories": ["Sales, CS & Business Devpt", "Business Development", "Property / Real Estate", "Property Consultancy", "Others"], "post_time": "2022-01-18T02:19:46Z", "salary": {"currency": null, "max": null, "min": null, "period": "monthly", "term": null}, "salary_visible": false, "title_keywords": [], "responsibilities": [], "requirements": {"degrees": [], "majors": [], "languages": [], "language_level": [], "hard_skills": [], "soft_skills": [], "languages_combined": []}, "experience_required": {"duration": [], "field": []}}, {"job_id": "100003009053181", "location_code": "hk", "company": "Synergis Management Services Limited", "job_title": "Property Assistant (Kwai Tsing)", "description": "Responsibilities:\n\nTo assist in daily property operations and management, like collect property management fee, bank in\nTo handle clients\u2019 inquires and deliver quality service\nTo monitor contractors work and manage daily property operations including cleaning and security teams\nTo organize property activities\nTo perform ad hoc duties assigned by the supervisor\n\nRequirements:\n\nDiploma or above in property management or related disciplines;\nMinimum 1 year or above relevant experience in property management;\nProficiency in both written and spoken English and Chinese;\nWell experienced in using computer software, including Word, Excel & Chinese Word Processing\n\n*Recent graduates will be considered\n\n\nFor interested applicants, please send your resume with\u00a0availability,\u00a0present\u00a0and\u00a0expected salary\u00a0by clicking \u201cAPPLY NOW\u201d button below.\n\n(Personal data collected will be used for recruitment purpose only)", "employment_types": ["Full Time", "Permanent"], "selling_points": ["Diploma or above", "Minimum 1 year or above relevant experience", "Recent graduates will be considered"], "locations": ["Kwai Tsing Area"], "categories": ["Property / Real Estate", "Property Consultancy", "Property Management", "Others"], "post_time": "2022-01-17T06:26:50Z", "salary": {"currency": null, "max": null, "min": null, "period": "monthly", "term": null}, "salary_visible": false, "title_keywords": ["property assistant"], "responsibilities": ["ad hoc duties", "management", "operations", "quality", "monitor", "teams", "cleaning"], "requirements": {"degrees": ["diploma or above"], "majors": ["related disciplines"], "languages": ["english", "chinese"], "language_level": ["proficiency"], "hard_skills": ["excel", "chinese word processing", "word"], "soft_skills": [], "languages_combined": [{"language": "english", "language_level": ["proficiency"]}, {"language": "chinese", "language_level": ["proficiency"]}]}, "experience_required": {"duration": ["minimum 1 year"], "field": ["management", "relevant experience"]}}, {"job_id": "100003009048999", "location_code": "hk", "company": "Hongkong Land Group Limited", "job_title": "\u7ba1\u696d\u4e3b\u4efb (\u4fdd\u5b89\u4e3b\u7ba1) (Ref: PM-BS-JDB)", "description": "\u4e3b\u8981\u8077\u52d9\u5305\u62ec\uff1a\n\n\u8ca0\u8cac\u5354\u52a9\u7269\u696d\u7ba1\u7406\u7d93\u7406\u53ca\u9ad8\u7d1a\u7ba1\u696d\u4e3b\u4efb\u57f7\u884c\u5546\u5834\u53ca\u5546\u5ec8\u7ba1\u7406\u4e8b\u5b9c\n\u7ba1\u7406\u53ca\u5e36\u9818\u7ba1\u696d\u670d\u52d9\u5718\u968a\uff0c\u4ee5\u78ba\u4fdd\u512a\u8cea\u5ba2\u6236\u670d\u52d9\n\n\u61c9\u5fb5\u8005\u9808\u5177\u5099\u4ee5\u4e0b\u689d\u4ef6\uff1a\n\n\u5177\u5099\u4e94\u5e74\u6216\u4ee5\u4e0a\u5546\u5834\u6216\u5546\u5ec8\u7ba1\u7406\u7d93\u9a57\uff0c\u53ca\u76f8\u95dc\u4e3b\u7ba1\u7d93\u9a57\n\u4e2d\u4e94\u7a0b\u5ea6\u6216\u4ee5\u4e0a\uff0c\u6301\u6709\u6709\u6548\u4fdd\u5b89\u4eba\u54e1\u8a31\u53ef\u8b49\uff0c\u5df2\u8003\u7372\u76f8\u95dc\u7269\u696d\u7ba1\u7406\u8b49\u66f8\u8005\u512a\u5148\n\u80fd\u4ee5\u82f1\u8a9e\u3001\u5ee3\u6771\u8a71\u53ca\u666e\u901a\u8a71\u6e9d\u901a\n\u9808\u7a7f\u8457\u516c\u53f8\u5236\u670d\n\u80fd\u56fa\u5b9a\u7576\u503c\u65e5\u6216\u4e2d\u73ed\u6642\u9593:\n\u65e9\u73ed\uff1a\u4e0a\u5348 7:45 - \u4e0b\u5348 4:15\n\u4e2d\u73ed\uff1a\u4e0b\u5348 3:15 - \u665a\u4e0a 11:45 (\u53ef\u4eab\u6709\u4e2d\u73ed\u7279\u5225\u6d25\u8cbc)\n\n\u5b8c\u5584\u54e1\u5de5\u798f\u5229\uff1a\n\n\u53ef\u4eab\u6709\u6bcf\u67086\u5929\u4f8b\u5047\n\u85aa\u512a\u53e6\u52a0\u82b1\u7d05\uff0c\u6bcf\u6708\u624b\u6a5f\u6d25\u8cbc\u53ca\u51fa\u52e4\u6d25\u8cbc\n\u91ab\u7642\u798f\u5229\u300112\u5929\u6709\u85aa\u5e74\u5047\u3001\u514d\u4f9b\u6b3e\u516c\u7a4d\u91d1\u53ca\u54e1\u5de5\u6e21\u5047\u5c4b\n\u4ee3\u7533\u8acb\u53ca\u652f\u4ed8\u500b\u4eba\u4fdd\u5b89\u724c\u7167\u8cbb\u7528\n\u5165\u8077\u57f9\u8a13\u8ab2\u7a0b\u53ca\u5c08\u696d\u5728\u8077\u57f9\u8a13\n\u5b8c\u5584\u7684\u5167\u90e8\u6649\u5347\u5236\u5ea6\uff0c\u63d0\u4f9b\u767c\u5c55\u53ca\u6649\u5347\u6a5f\u6703\n\n\u6709\u610f\u61c9\u5fb5\u8005\uff0c\u8acb\u5c07\u500b\u4eba\u5c65\u6b77 (\u8acb\u8a3b\u660e\u7533\u8acb\u8077\u4f4d\u3001\u806f\u7d61\u96fb\u8a71\u53ca\u8981\u6c42\u5f85\u9047)\u4ee5WhatsApp\u50b3\u9001\u81f39223 7989\u00a0\u6216\u00a0\u9ede\u64ca\u00a0\"Apply Now\"\u00a0\u7acb\u5373\u7533\u8acb\u3002\n\n\u6709\u95dc\u7f6e\u5730\u516c\u53f8\u8cc7\u6599\uff0c\u8acb\u700f\u89bd http://www.hkland.com\u3002\u00a0\n\n\u95a3\u4e0b\u6240\u63d0\u4f9b\u4e4b\u500b\u4eba\u8cc7\u6599\u53ea\u4f5c\u70ba\u6b64\u8077\u4f4d\u62db\u8058\u4e4b\u7528\uff0c\u65bc\u56db\u661f\u671f\u5167\u4e0d\u7372\u7d04\u898b\u8005\uff0c\u7576\u4f5c\u4e0d\u88ab\u53d6\u9304\uff0c\u5176\u6240\u905e\u4ea4\u4e4b\u500b\u4eba\u8cc7\u6599\u4ea6\u96a8\u5373\u92b7\u6bc1\u3002", "employment_types": ["Full Time", "Permanent"], "selling_points": ["\u65e5\u73ed/\u4e2d\u73ed\u4e3b\u7ba1(8.5\u5c0f\u6642\u5b9a\u66f4)  shift in-charge", "\u4e94\u5e74\u6216\u4ee5\u4e0a\u5546\u5ec8\u7ba1\u7406\u7d93\u9a57\uff0c\u53ca\u76f8\u95dc\u4e3b\u7ba1\u7d93\u9a57", "\u6301PMSA\u7269\u696d\u7ba1\u7406\u4eba\u724c\u7167\u8005\u512a\u5148\u8003\u616e"], "locations": ["Central"], "categories": ["Property / Real Estate", "Property Management", "Others", "Others", "Security / Safety Control"], "post_time": "2022-01-14T07:52:52Z", "salary": {"currency": null, "max": null, "min": null, "period": "monthly", "term": null}, "salary_visible": false, "title_keywords": [], "responsibilities": [], "requirements": {"degrees": [], "majors": [], "languages": [], "language_level": [], "hard_skills": [], "soft_skills": [], "languages_combined": []}, "experience_required": {"duration": [], "field": []}}, {"job_id": "100003009034643", "location_code": "hk", "company": "S.H.K. Real Estate Management Company Limited", "job_title": "\u9ad8\u7d1a\u6280\u8853\u54e1/ \u6280\u8853\u54e1- \u6a5f\u96fb/\u51b7\u6c23/\u6c34\u5589 (5.5\u59299\u5c0f\u6642 / \u8f2a\u73ed)", "description": "\u8ca0\u8cac\u5546\u696d\u5927\u5ec8\u51b7\u6c23\u6216\u6c34\u5589\u7dad\u4fee\u53ca\u4fdd\u990a\n\u521d\u4e2d\u7a0b\u5ea6\u6216\u5177\u8cc7\u6b77\u67b6\u69cb\u540c\u7b49\u8cc7\u6b77\uff0c\u5177\u76f8\u95dc\u5de5\u7a0b\u8b49\u66f8\u66f4\u4f73\n\u5177\u76f8\u95dc\u5de5\u7a0b\u7d93\u9a57\u512a\u5148\u8003\u616e\uff0c\u7d93\u9a57\u8f03\u591a\u8005\u53ef\u8058\u7528\u70ba\u9ad8\u7d1a\u6280\u8853\u54e1\n\u85aa\u91d1\u53ef\u9054\u6bcf\u6708 $19,000 - $23,500\n\n\u4ee5\u4e0a\u8077\u4f4d\u53ef\u4eab\u6709\u512a\u539a\u54e1\u5de5\u798f\u5229\uff0c\u5305\u62ec\u6bcf\u67086\u5929\u6709\u85aa\u4f11\u606f\u65e5\u3001\u6709\u85aa\u5e74\u50479\u5929\u3001\u52e4\u5de5\u734e\u3001\u5e74\u7d42\u96d9\u7ce7\u3001\u91ab\u7642\u798f\u5229\u3001\u5b8c\u5584\u57f9\u8a13\u53ca\u6649\u5347\u6a5f\u6703\u7b49\u3002\n\n\u6709\u610f\u8005\uff0c\u8acb\u900f\u904e\u4ee5\u4e0b\u65b9\u6cd5\u7533\u8acb\uff1a\n\n\u7063\u4ed4\u5340\uff1a3766 6155\u00a0\u5f35\u5c0f\u59d0\n\u8343\u7063\u5340\uff1a2412 5772 \u6c60\u5148\u751f\n\u5c16\u6c99\u5480\u5340\uff1a2312 2110 \u5468\u5c0f\u59d0\n\n\u9664\u4e0a\u8ff0\u8077\u4f4d\u5916\uff0c\u5c1a\u6709\u5176\u4ed6\u7a7a\u7f3a\u3002\u8acb\u900f\u904e\u4ee5\u4e0b\u65b9\u6cd5\u5c07\u5c65\u6b77\u4ea4\u5230S.H.K. \u7269\u696d\u7ba1\u7406\u6709\u9650\u516c\u53f8\u4e4b\u4eba\u529b\u8cc7\u6e90\u53ca\u884c\u653f\u90e8\u3002\n\n\u90f5\u5bc4\uff1a\u89c0\u5858\u5de7\u660e\u885795\u865f\u4e16\u9054\u4e2d\u5fc316\u6a13\u3000\u50b3\u771f\uff1a2827 2125\n\nS.H.K. \u7269\u696d\u7ba1\u7406\u6709\u9650\u516c\u53f8\u4e43\u5e73\u7b49\u6a5f\u6703\u50f1\u4e3b\uff0c\u800c\u6240\u6709\u6536\u96c6\u8cc7\u6599\u7d55\u5c0d\u4fdd\u5bc6\u53ca\u53ea\u7528\u4f5c\u96c6\u5718\u5167\u90e8\u62db\u8058\u4e4b\u7528\u9014\u3002", "employment_types": ["Full Time", "Permanent"], "selling_points": ["\u8ca0\u8cac\u5546\u696d\u5927\u5ec8\u51b7\u6c23\u6216\u6a5f\u96fb\u7dad\u4fee\u53ca\u4fdd\u990a", "\u521d\u4e2d\u7a0b\u5ea6\uff0c\u5177\u76f8\u95dc\u5de5\u7a0b\u7d93\u9a57\u53ca\u8b49\u66f8\u66f4\u4f73", "9\u5c0f\u6642\u8f2a\u73ed\u5de5\u4f5c"], "locations": ["Not Specified"], "categories": ["Engineering", "Mechanical", "Others", "Property / Real Estate", "Others"], "post_time": "2022-01-16T21:50:09Z", "salary": {"currency": null, "max": null, "min": null, "period": "monthly", "term": null}, "salary_visible": false, "title_keywords": ["\u6280\u8853\u54e1"], "responsibilities": [], "requirements": {"degrees": [], "majors": [], "languages": [], "language_level": [], "hard_skills": [], "soft_skills": [], "languages_combined": []}, "experience_required": {"duration": [], "field": []}}, {"job_id": "100003009050048", "location_code": "hk", "company": "Shun Tak Property Management Limited", "job_title": "Property Assistant (Commercial)", "description": "Job Duties:\n\nTo be responsible for day-to-day operation of a designated property portfolio\nTo handle complaints and enquiries of the customer\nTo oversee the repair and maintenance conditions of the properties\nTo supervise the performance of cleaning, security and other maintenance contractors\nTo attend regular meetings with Owners Committee and liaise with government bodies\n\n\u00a0Requirements:\n\nDiploma or above,\u00a0preferably in Property /Housing Management or\u00a0related disciplines\u00a0\nMinimum 1\u00a0 year relevant working experience in management of large scale commercial premises\nPossess hands-on experience in MS Office & Chinese Word Processing\nCustomer-oriented and able to work under pressure\nWork independently and good communication skills\u00a0\n\nWe will offer attractive compensation package to the right candidate. Please send application enclosing resume stating career and salary history, expected salary and date of availability to\u00a0The HR Dept, Rooms 908-11, 9/F, West Tower, Shun Tak Centre, 200 Connaught Road Central, Hong Kong by email to pm_hr(at)shuntakgroup.com\u00a0 (in Word format).\u00a0\u00a0Please quote the reference of the position you apply for in all correspondences.\n\nThe information supplied by the applicants will be used in accordance with the Personal Data (Privacy) Policy of Shun Tak Group (a copy of which will be provided upon request). Only shortlisted candidates will be notified. www.shuntakgroup.com", "employment_types": ["Full Time", "Permanent"], "selling_points": ["Diploma or above, preferably in Property /Housing", "Min 1 yr working exp in commercial premises", "Hands-on experience in MS Office"], "locations": ["Sheung Wan"], "categories": ["Property / Real Estate", "Property Management", "Others", "Others", "Others"], "post_time": "2022-01-14T09:41:07Z", "salary": {"currency": null, "max": null, "min": null, "period": "monthly", "term": null}, "salary_visible": false, "title_keywords": ["property assistant"], "responsibilities": ["maintenance", "handle complaints", "repair", "cleaning", "liaise with", "day-to-day operation"], "requirements": {"degrees": ["diploma or above"], "majors": ["related disciplines"], "languages": ["chinese"], "language_level": [], "hard_skills": ["chinese word processing", "word", "ms office"], "soft_skills": ["communication skills", "work independently", "hands-on", "customer-oriented", "work under pressure"], "languages_combined": [{"language": "chinese", "language_level": []}]}, "experience_required": {"duration": [], "field": ["commercial", "management", "relevant working experience"]}}, {"job_id": "100003009053838", "location_code": "hk", "company": "Konew Financial Express Ltd", "job_title": "\u7269\u696d\u8abf\u67e5\u54e1", "description": "\u8077\u8cac\uff1a\n\u5354\u52a9\u516c\u53f8\u9032\u884c\u5ba2\u6236\u7684\u7269\u696d\u67e5\u8a2a\n\u7d00\u9304\u9280\u4e3b\u76e4\u7684\u60c5\u6cc1\u53ca\u6e05\u7406\u7576\u4e2d\u96dc\u7269\n\u76e3\u5bdf\u9280\u4e3b\u76e4\u7684\u7dad\u4fee\u53ca\u7ffb\u65b0\n\u57f7\u884c\u884c\u653f\u90e8\u6307\u6d3e\u7684\u8077\u52d9\n\n\u8981\u6c42\uff1a\n\n\nHKCEE / HKDSE\u7a0b\u5ea6\u6216\u4ee5\u4e0a\n\u61c2\u5e73\u677f\u96fb\u8166\u64cd\u4f5c\n\u826f\u597d\u5ee3\u6771\u8a71\u3001\u7c21\u55ae\u82f1\u6587\n\u4e00\u5e74\u6216\u4ee5\u4e0a\u5ba2\u6236\u670d\u52d9\u7d93\u9a57\n\u614b\u5ea6\u8aa0\u61c7\u89aa\u5207\uff0c\u52e4\u596e\u5b88\u6642\uff0c\u6709\u8cac\u4efb\u611f\n\u6301 1\u30012 \u865f\u724c\u512a\u5148\u8003\u616e\n\n\u5f85\u9047\uff1a\n\n\u661f\u671f\u4e00\u81f3\u4e94\uff0c\u671d\u4e5d\u665a\u516d\n\u52e4\u5de5\u596c\u91d1\n\u914c\u60c5\u6027\u82b1\u7d05\n\u6709\u85aa\u5e74\u5047\n\u751f\u65e5\u5047\n\u5165\u8077\u5468\u5e74\u5047\n\u734e\u52f5\u5047\u671f\n\u91ab\u7642\u4fdd\u96aa\u798f\u5229\u53ca\u7259\u79d1\u798f\n\n\u7533\u8acb\u65b9\u6cd5\uff1a\u6709\u8208\u8da3\u7533\u8acb\u7684\u4eba\u58eb\uff0c\u8acb\u6309 'Apply Now'\u3002\n\n<\u6240\u6536\u96c6\u7684\u500b\u4eba\u8cc7\u6599\u7d55\u5c0d\u4fdd\u5bc6\u53ca\u53ea\u4f5c\u62db\u8058\u7528\u9014>", "employment_types": ["Full Time"], "selling_points": ["\u5354\u52a9\u516c\u53f8\u9032\u884c\u7269\u696d\u67e5\u8a2a", "\u6301 1\u30012 \u865f\u724c\u512a\u5148\u8003\u616e", "\u826f\u597d\u5de5\u4f5c\u798f\u5229"], "locations": ["Central"], "categories": ["Transportation & Logistics", "Others", "Banking / Finance", "Others", "Property / Real Estate", "Others"], "post_time": "2022-01-17T07:36:09Z", "salary": {"currency": null, "max": null, "min": null, "period": "monthly", "term": null}, "salary_visible": false, "title_keywords": [], "responsibilities": [], "requirements": {"degrees": [], "majors": [], "languages": [], "language_level": [], "hard_skills": [], "soft_skills": [], "languages_combined": []}, "experience_required": {"duration": [], "field": []}}, {"job_id": "100003009054196", "location_code": "hk", "company": "Discovery Park Commercial Services Limited", "job_title": "Assistant, Leasing (Part-time)", "description": "Job Responsibilities:\n\nAssist to handle leasing documents;\nProvide full spectrum of administrative support to\u00a0 Leasing Department;\nHandle ad-hoc tasks as assigned\n\nJob Requirements:\n\nHKDSE/ Form 7 graduate or above\n1 years working experience in administration field in office environment\nexperience in handling leasing and legal documents is preferred\nGood command of written and spoken English and Chinese\nProficient in MS Office (Words, Excel (v-lookup & pivot table), PowerPoint) and Chinese word processing\n\n(Personal data will be collected for recruitment purpose only)", "employment_types": ["Part Time"], "selling_points": ["Assist to handle leasing documents;", "Provide full spectrum of administrative support;", "Handle ad-hoc tasks as assigned"], "locations": ["Tsuen Wan Area"], "categories": ["Admin & HR", "Clerical / Admin Staff", "Property / Real Estate", "Others"], "post_time": "2022-01-17T08:46:43Z", "salary": {"currency": null, "max": null, "min": null, "period": "hourly", "term": null}, "salary_visible": false, "title_keywords": ["assistant"], "responsibilities": ["ad-hoc tasks", "administrative support"], "requirements": {"degrees": ["hkdse"], "majors": [], "languages": ["english", "chinese"], "language_level": ["good command", "proficient"], "hard_skills": ["excel", "chinese word processing", "words", "pivot table", "powerpoint", "ms office"], "soft_skills": [], "languages_combined": [{"language": "english", "language_level": ["good command"]}, {"language": "chinese", "language_level": ["good command", "proficient"]}]}, "experience_required": {"duration": ["1 years"], "field": ["legal", "administration"]}}, {"job_id": "100003009051961", "location_code": "hk", "company": "Kai Fu Property Services Co Ltd", "job_title": "Estate Management Assistant/ Assistant Property Officer", "description": "Relevant experience NOT required. \u00a0Comprehensive one year training on property management provided. Candidate is eligible to be promoted as Property Officer upon completion of one year\u2019s satisfactory service.\n\nResponsibilities\n\nAssist in the daily operations of property management in government public housing estate\nHandle enquiries and complaints of the tenants and tenancy related matters\n\nRequirements\n\nHolder of a Degree/Associate Degree/Higher Diploma with grade E or above in Chinese Language in\u00a0Advanced Level HKALE or equivalent, OR\nDSE or above with Level 3 or above in five subjects, which should include Chinese Language and English Language\nService-oriented with good communications and interpersonal skills\nA team player, fast learner and capable of working under pressure\u00a0\nProficient in Microsoft Office applications such as Word, Excel and PowerPoint\nHolder of Certificate in Public Housing Agency Management an added advantage\n\nWork Location: Tin Shui Wai, Ma On Shan, Kowloon East\n\nExcellent career development opportunities to the right candidates.\n\nFRESH GRADUATES and GRADUATES WITH INTEREST IN PROPERTY MANAGEMENT ARE WELCOMED.\n\n\u00a0Interested parties please click the\u00a0\"APPLY NOW\"\u00a0to submit your application with\u00a0full resume including\u00a0contact phone\u00a0number,\u00a0date\u00a0available\u00a0in MS Word format to us.\u00a0\n\n<Personal data collected will be treated in strictest confidence\u00a0for recruitment related purposes only>", "employment_types": ["Full Time", "Permanent"], "selling_points": [], "locations": ["Not Specified"], "categories": ["Property / Real Estate", "Property Management", "Others", "Management", "Management Trainee"], "post_time": "2022-01-17T01:39:16Z", "salary": {"currency": null, "max": null, "min": null, "period": "monthly", "term": null}, "salary_visible": false, "title_keywords": ["assistant property officer", "assistant"], "responsibilities": ["daily operations", "management", "handle enquiries and complaints"], "requirements": {"degrees": ["associate degree", "certificate", "diploma", "degree", "dse"], "majors": [], "languages": ["english", "chinese"], "language_level": [], "hard_skills": ["excel", "word", "powerpoint", "microsoft office"], "soft_skills": ["under pressure", "advanced", "capable", "service-oriented", "interpersonal skills", "team player", "fast learner"], "languages_combined": [{"language": "english", "language_level": []}, {"language": "chinese", "language_level": []}]}, "experience_required": {"duration": [], "field": []}}, {"job_id": "100003009052226", "location_code": "hk", "company": "NAN FUNG GROUP", "job_title": "PROPERTY MANAGER / ASSISTANT PROPERTY MANAGER", "description": "Requirement:\n\nDegree in Property Management or related disciplines\nMember of HKIH or CIH with at least\u00a06-8 years of experience in property management, 3 years of which at managerial level, 4 years of which at supervisory level\nHolder of the Property Management Practitioner (Tier 1) License is preferred\nProficient in Building Management Ordinance, DMC and/or related ordinances\nStrong leadership abilities with uncompromising integrity and passion for excellence\nResult-driven, flexible with excellent communication skills\nExcellent interpersonal skills, able to maintain good relationship with all internal and external customers\nService oriented and energetic\nGood PC skills in MS Words, Excel and Chinese Word-processing etc\nGood command of both written and spoken English and Chinese\nCandidate with less experience will be considered as Assistant Property Manager\n\nKey Responsibility:\n\nTake charge of the day-to-day operation and management of a property or a group of properties, including budget preparation and control, service standard and property maintenance, etc\nSupervise a team of officers and technical staff in the daily management duties to ensure meeting with requirements of clients\nMaintain a good relationship with owners/tenants and Owners' Committee/ Corporation ensuring their needs are taken care of\nEnsure compliance with relevant ordinance and regulations\nMonitor the performance of maintenance, security and cleaning teams, etc\nPerform related internal audit in different aspects including ISO, safety and security, etc\n\nWe provide generous compensation and fringe benefits to the right candidates. Please send your full resume with salary expected to The Human Resources Manager, 23/F., Nan Fung Tower,\u00a088 Connaught\u00a0Road C, Central, HK or by E-mail\uff1a\u00a0hr @ pm.nanfung.com or by clicking \"Apply Now\" below\u00a0(We are an equal opportunity employer. All applications will be treated in strict confidence and only be used for selection purpose.)\n\nFor further information about Personal Information Collection Statement (\u201cPICS\u201d) Pertaining to Recruitment, please click the link below\u00a0www.nanfung.com/en/common/pics/.\n\n\"Nan Fung Group\" and \"the Group\" mean Nan Fung Group Holdings Limited and its subsidiaries.", "employment_types": ["Full Time", "Permanent"], "selling_points": ["Degree in Property Management", "6-8 years of experience in property management", "3 years managerial level experience"], "locations": ["Not Specified"], "categories": ["Property / Real Estate", "Property Management", "Others"], "post_time": "2022-01-17T02:30:45Z", "salary": {"currency": null, "max": null, "min": null, "period": null, "term": null}, "salary_visible": false, "title_keywords": ["assistant property manager", "property manager"], "responsibilities": ["regulations", "management", "control", "service standard", "maintenance", "internal audit", "budget", "teams", "ensure compliance", "good relationship", "maintain", "monitor the performance", "cleaning", "day-to-day operation"], "requirements": {"degrees": ["degree"], "majors": ["related disciplines"], "languages": ["english", "chinese"], "language_level": ["good command", "good"], "hard_skills": ["excel", "pc skills", "chinese word-processing", "ms words"], "soft_skills": ["flexible", "communication skills", "passion for", "integrity", "interpersonal skills", "energetic", "leadership", "driven"], "languages_combined": [{"language": "english", "language_level": ["good command", "good"]}, {"language": "chinese", "language_level": ["good command", "good", "good"]}]}, "experience_required": {"duration": ["3 years", "4 years", "at least 6-8 years"], "field": ["managerial", "management", "supervisory level"]}}, {"job_id": "100003009053087", "location_code": "hk", "company": "Loyal Link (HK) Limited", "job_title": "\u79d8\u66f8\u517c\u52a9\u7406", "description": "The Job\n\nTo handle routine/ ad hoc maintenance and manage planned preventive maintenance work for chain retail stores and warehouses\nTo handle and coordinate emergency repair requests\nTo be responsible for the planning, sourcing, procurement, logistic management of supplies and building materials.\nTo handle tender documents independently and execute contract administration accordingly.\nSupport and assist the FM Director in the coordination of work between business units and external parties.\nTo interface with all relevant parties including contractors, landlords, government authorities and internal departments, to ensure works are executed according to business plan and pre-determined service level.\nTo issue and manage work orders through in-house systems\nProvide administrative support and record maintenance\nPerform emergency duty out of official working hour as required\nHandle ad-hoc projects as assigned\n\n\u00a0The Person\n\nDiploma holder in Property / Facilities Management, Building Services Engineering or related disciplines\n3-5 years practical experience in providing maintenance services in Facility / Property Management\nExperience in retail store operations is preferred\nStrong communication skills and interpersonal skills with all levels\nGood command of written and spoken English and Chinese\nGood PC knowledge in MS Office and Chinese word processing\nA detail minded, strong team player with a positive attitude\nAbility to work under pressure\u00a0\n\nDFI Retail Group is an equal opportunity employer and responsible for ensuring that all personal information collected from each Candidate presented to DFI Retail Group is used for recruitment purposes only and the personal data will be kept and handled confidentially. We will retain the applications of candidates not selected for a period of no more than 24 months. The data collection process is in accordance with all applicable laws and compliant with the Code of Practice on Human Resource Management.\n\nTo find out more about Our Businesses and Our People, please visit our website: https://www.DFIretailgroup.com\n\n\u00a0\nIssued by The Dairy Farm Company, Limited", "employment_types": ["Full Time"], "selling_points": [], "locations": ["Kwai Hing"], "categories": ["Property / Real Estate", "Others"], "post_time": "2022-01-17T05:43:22Z", "salary": {"currency": null, "max": null, "min": null, "period": null, "term": null}, "salary_visible": false, "title_keywords": [], "responsibilities": ["management", "ad hoc", "maintenance", "tender documents", "contract administration", "external parties", "systems", "coordinate", "repair", "coordination", "business plan", "ad-hoc projects", "provide administrative support", "planning"], "requirements": {"degrees": ["diploma holder"], "majors": ["related disciplines", "building services", "engineering"], "languages": ["english", "chinese"], "language_level": ["good command", "good"], "hard_skills": ["no", "chinese word processing", "maintenance", "facilities management", "code", "pc knowledge", "ms office"], "soft_skills": ["communication skills", "responsible", "positive attitude", "interpersonal skills", "team player", "work under pressure"], "languages_combined": [{"language": "english", "language_level": ["good command", "good"]}, {"language": "chinese", "language_level": ["good command", "good", "good"]}]}, "experience_required": {"duration": ["3-5 years"], "field": ["management", "retail", "maintenance"]}}, {"job_id": "100003009056082", "location_code": "hk", "company": "DFI Retail Group DFI\u96f6\u552e\u96c6\u5718", "job_title": "Department Administrator - Facilities", "description": "Job Duties:\n\nUnder the reliever team to provide support in different office sites as scheduled\u00a0\nOversee daily routine facilities management and ensure the operation of office equipment and office environment are in good condition\nPerform logistics and administration support to the team, including but not limited to arrange ordering for office equipment and facilities, set up meeting rooms and manage access card for staff/visitors\nSupervise and monitor in house and outsourced teams with diverse trades to ensure the facilities services including customer relation, security, cleaning, and facilities maintenance and repair are delivered effectively and cost efficiently\nCoordinate minor project works e.g. renovation, relocation, moves etc.\u00a0\nEnsure vendors submit invoices in timely manner\nEnsure all work carried out in compliance with standards and Health & Safety Regulation\nReport to Account Manager for special feedback and key account management\nPerform other duties assigned by\u00a0Supervisor\n\nJob Requirements:\n\nHigher diploma holder in Facilities Management or Service related disciplines\nMinimum 5\u00a0years of working experience in Facilities Management\nStrong computer skills\nGood command of spoken and written English and Chinese\nProfessional appearance and demeanor, strong interpersonal skills and excellent communication skills\n\nPlace of Work and Working Hours:\n\nHong Kong Island (Monday to Friday, 9:00a.m. to 6:00p.m.)\n\nBenefits:\n\nPublic Holiday\nBirthday Leave\nMedical benefits\nA fun and lively working environment where you will be valued and developed\n\nWe offer competitive remuneration to the right candidates. Please apply with detailed resume and\u00a0salary expectation\u00a0to Human Resources Department, Sodexo (Hong Kong) Limited by clicking\u00a0Apply Now.\n\n*Personal data collected is for recruitment purposes only.", "employment_types": ["Full Time"], "selling_points": ["Department Coordination and Administrative Support", "Strong in Excel, fast paced working environment", "Dynamic team, great career development"], "locations": ["Quarry Bay"], "categories": ["Property / Real Estate", "Others"], "post_time": "2022-01-18T03:15:24Z", "salary": {"currency": null, "max": null, "min": null, "period": "monthly", "term": null}, "salary_visible": false, "title_keywords": ["administrator"], "responsibilities": ["provide support", "management", "cost", "invoices", "maintenance", "perform other duties", "renovation", "monitor", "teams", "compliance", "coordinate", "repair", "logistics", "cleaning", "report", "administration"], "requirements": {"degrees": ["higher diploma holder"], "majors": ["related disciplines"], "languages": ["english", "chinese"], "language_level": ["good command"], "hard_skills": ["facilities management", "computer skills"], "soft_skills": ["communication skills", "interpersonal skills"], "languages_combined": [{"language": "english", "language_level": ["good command"]}, {"language": "chinese", "language_level": ["good command"]}]}, "experience_required": {"duration": ["minimum 5 years"], "field": ["management"]}}, {"job_id": "100003009052549", "location_code": "hk", "company": "Sodexo (Hong Kong) Limited", "job_title": "Facilities Officer (Office)", "description": "\u8077\u8cac :\u4e00\u822c\u4fdd\u5b89\u5de5\u4f5c\n\u8cc7\u6b77 :\u5c0f\u516d\u7a0b\u5ea6; 1\u5e74\u7d93\u9a57; \u826f\u597d\u7cb5\u8a9e; \u61c2\u8b80\u5beb\u4e2d\u6587; \u6301\u6709\u4fdd\u5b89\u57f9\u8a13\u8ab2\u7a0b\u8b49\u66f8(QAS); \u6301\u6709\u4fdd\u5b89\u4eba\u54e1\u8a31\u53ef\u8b49\n\u5f85\u9047 :\u6bcf\u6708$13,500 - $14,000, \u6709\u6bcf\u6708\u52e4\u5de5\u734e\u91d1$300, \u8d85\u6642\u5de5\u4f5c\u6d25\u8cbc, \u914c\u60c5\u6027\u82b1\u7d05 \u53ca\u91ab\u7642\u4fdd\u96aa, \u4e0b\u53488\u6642\u81f3\u4e0a\u53488\u6642, \u6bcf\u9031\u5de5\u4f5c6\u5929,\u8f2a\u4f11, \u6bcf\u5929\u5de5\u4f5c 12 \u5c0f\u6642\n\u7533\u8acb\u9808\u77e5 :\u6c42\u8077\u8005\u53ef\u6309 APPLY NOW\u7533\u8acb\u6216\u81f4\u96fb31011000\u8207\u4fdd\u5f97\u7269\u696d\u7ba1\u7406\u6709\u9650\u516c\u53f8\u65bd\u5c0f\u59d0\u806f\u7d61\u3002", "employment_types": ["Full Time", "Permanent"], "selling_points": ["FM role in Corporate Office", "Report to Account Manager", "5-day work week"], "locations": ["Central"], "categories": ["Admin & HR", "Administration / Operation Manager", "Others", "Property / Real Estate", "Others"], "post_time": "2022-01-17T03:23:43Z", "salary": {"currency": null, "max": null, "min": null, "period": "monthly", "term": null}, "salary_visible": false, "title_keywords": ["officer"], "responsibilities": [], "requirements": {"degrees": [], "majors": [], "languages": [], "language_level": [], "hard_skills": [], "soft_skills": [], "languages_combined": []}, "experience_required": {"duration": [], "field": []}}, {"job_id": "100003009055362", "location_code": "hk", "company": "Protech Property Management Ltd", "job_title": "\u4fdd\u5b89\u54e1 - \u591c\u73ed (\u7063\u4ed4)", "description": "\u300a\u5bcc\u7238\u7238\uff0e\u7aae\u7238\u7238\u300b\u4f5c\u8005\u7f85\u4f2f\u7279\u6e05\u5d0e\u8b1b\u904e\uff1a\u300c\u592a\u591a\u4eba\u5fd8\u4e86\u53bb\u95dc\u6ce8\u81ea\u5df1\u7684\u4e8b\u696d\uff0c\u4ed6\u5011\u8017\u76e1\u4e00\u4e16\u53bb\u95dc\u6ce8\u5225\u4eba\u7684\u4e8b\u696d\uff0c\u4e26\u4f7f\u4ed6\u4eba\u81f4\u5bcc\u3002\u300d\u6211\u5011\u5e0c\u671b\u5c0b\u627e\u6240\u6709\u60f3\u70ba\u81ea\u5df1\u5275\u4e8b\u696d\u52aa\u529b\u62fc\u535a\u7684\u4eba\u3002\n\n\u751f\u65bc\u9019\u500b\u659c\u69d3\u65b0\u4e16\u4ee3\uff0c\u6bcf\u4eba\u8981\u64c1\u6709\u4e26\u4e0d\u662f\u5341\u9805\u5168\u80fd\uff0c\u800c\u662f\u8981\u69cb\u5efa\u81ea\u6211\u5275\u696d\u601d\u7dad\u3002\u52a0\u5165AXA\u9577\u76db\u7406\u8ca1\u5718\u968a\uff0c\u4f60\u6703\u57f9\u990a\u51fa\u505a\u751f\u610f\u7684\u5275\u696d\u982d\u8166\uff0c\u8df3\u51fa\u807d\u4e0a\u53f8\u6307\u4ee4\u7684\u6253\u5de5\u4ed4\u751f\u6daf\uff0c\u8e0f\u5be6\u800c\u9577\u9060\u5efa\u7acb\u5c6c\u65bc\u60a8\u7684\u500b\u4eba\u4fdd\u96aa\u4e8b\u696d\u3002\n\n\u5340\u57df\u80cc\u666f\uff1a\n\n- \u8d85\u904e20\u5e74\u767c\u5c55\u5927\u4e2d\u83ef\u5730\u5340\u5e02\u5834\u7d93\u9a57\uff0c\u5340\u57df\u4eba\u6578\u9054200\u4eba\n- \u6210\u54e1\u4f86\u81ea\u4e0d\u540c\u5c08\u696d\u80cc\u666f\uff0c\u6709\u524d\u5f8b\u5e2b\uff0c\u9280\u884c\u5bb6\uff0c\u5546\u4eba\uff0cIT\u5c08\u696d\u4eba\u58eb\u7b49\u7b49\uff0c\u7121\u8ad6\u5c0d\u9ad8\u7aef\u5ba2\u6236\u6216\u662f\u4e2d\u7522\u5ba2\u6236\u92b7\u552e\u90fd\u6709\u8c50\u5bcc\u7d93\u9a57\u3002\n\n\u5718\u968a\u80cc\u666f\uff1a\n\n\u9577\u76db\u7406\u8ca1\u5275\u8fa6\u4ebaSam\u7576\u521d\u6c7a\u5b9a\u88f8\u8fad\u5275\u696d\uff0c\u4e8b\u696d\u9054\u5230\u985b\u5cf0\u6210\u5c31\u5230\u751f\u610f\u5931\u6557\u5f8c\uff0c\u4f46\u537b\u7121\u640d\u5efa\u7acb\u4e8b\u696d\u738b\u570b\u7684\u9b25\u5fc3\uff0c\u6c7a\u5b9a\u7531\u4fdd\u96aa\u696d\u958b\u59cb\u6771\u5c71\u518d\u8d77\uff0c\u4e26\u6700\u5f8c\u50c5\u7528\u4e86\u5169\u5e74\u6642\u9593\u9054\u5230COT \uff08\u53733\u500dMDRT\uff09\u3002\n\n\u806f\u5408\u5275\u8fa6\u4ebaCharlotte\u5f9e\u4e8b\u7532\u7d1a\u5546\u5834\u79df\u52d9\u8d85\u904e10\u5e74\uff0c\u6709\u611f\u7121\u9650OT\u7684\u6253\u5de5\u4ed4\u751f\u6d3b\u672a\u80fd\u517c\u9867\u7167\u9867\u5169\u500b\u5e74\u5e7c\u5152\u5b50\uff0c\u65bc\u662f\u4e0b\u5b9a\u6c7a\u5fc3\u8df3\u51facomfort zone\u52a0\u5165\u7406\u8ca1\u7b56\u5283\u884c\u696d, \u81ea\u7531\u5de5\u4f5c\u6a21\u5f0f\u8b93\u5979\u5de5\u4f5c\u66f4\u6709\u62fc\u52c1\u53c8\u591a\u4e86\u6642\u9593\u7167\u9867\u5bb6\u5ead\uff0c\u5165\u8077\u77ed\u77ed5\u500b\u6708\u4fbf\u9054\u6a19MDRT 2021, \u4eca\u5e74\u4ea6\u5df2\u5b8c\u6210MDRT 2022\uff01\n\n\u9577\u76db\u7406\u8ca1\u5718\u968a\u6df1\u4fe1\u4fdd\u96aa\u4e0d\u53ea\u662f\u4e00\u500b\u7406\u8ca1\u7b56\u5283\u7684\u884c\u696d\uff0c\u800c\u662f\u8b93\u6bcf\u4eba\u5efa\u7acb\u500b\u4eba\u751f\u610f\u7684\u8d77\u6b65\u9ede\u3002\u5718\u968a\u6210\u54e1\u4f86\u81ea\u9999\u6e2f\uff0c\u83f2\u5f8b\u8cd3\uff0c\u97d3\u570b\uff0c\u5370\u5ea6\u7b49\u7b49\uff0c\u4e0d\u540c\u6587\u5316\u601d\u7dad\u52a9\u4f60\u958b\u62d3\u65b0\u601d\u7dad\uff01\u6211\u5011\u6574\u500b\u5718\u968a\u6703\u4e00\u76f4\u4f5c\u70ba\u60a8\u7684\u5275\u696d\u540c\u8def\u4eba\u652f\u63f4\u4f60\u548c\u5354\u52a9\u4f60\u9054\u6210\u500b\u4eba\u751f\u610f\u76ee\u6a19\uff0c\u5efa\u7acb\u81ea\u5df1\u7684\u4e8b\u696d\u738b\u570b\u3002\n\n\u4f60\u6703\u7372\u5f97\u4ec0\u9ebc\uff1f\n\n\u6bcf\u6708\u6d25\u8cbc\u4e0a\u9650HK$50,000\uff0c\u6700\u9ad8\u53ef\u9054\u904e\u5f80\u6708\u85aa\u4e4b100%\n\u5b8c\u5584\u4f63\u91d1\u5236\u5ea6\u53ca\u71df\u92b7\u734e\u8cde\uff0c\u5305\u62ec\u6bcf\u6708\u4f63\u91d1\uff0c\u6bcf\u5b63\u734e\u91d1\uff0c\u5e74\u7d42\u734e\u91d1\uff0c\u6d77\u5916\u696d\u52d9\u6703\u8b70\u7b49\uff0c\u734e\u52f5\u5091\u51fa\u8868\u73fe\n\u5168\u9762\u57f9\u8a13\u8ab2\u7a0b\uff0c\u63d0\u5347\u500b\u4eba\u7af6\u722d\u529b\uff0c\u5e6b\u52a9\u7a4d\u6975\u8f49\u884c\u4eba\u58eb\n\u6e05\u6670\u6649\u5347\u968e\u68af\uff0c\u7a4d\u6975\u914d\u5408\u4e8b\u696d\u767c\u5c55\n\u81ea\u4e3b\u5de5\u4f5c\u6642\u9593\uff0c\u5e73\u8861\u5bb6\u5ead\u548c\u751f\u6d3b\n\n\u5de5\u4f5c\u7bc4\u570d\uff1a\n\n\u70ba\u5ba2\u6236\u63d0\u4f9b\u5404\u9805\u5c08\u696d\u7684\u7406\u8ca1\u65b9\u6848\uff0c\u5982\u5065\u5eb7\u4fdd\u969c\u3001\u98a8\u96aa\u7ba1\u7406\u3001\u9000\u4f11\u57fa\u91d1\u3001\u6559\u80b2\u57fa\u91d1\u8cc7\u7522\u914d\u7f6e\u7b49\n\u5efa\u7acb\u826f\u597d\u5ba2\u6236\u95dc\u4fc2\uff0c\u62d3\u5c55\u5ba2\u6236\u7db2\u7d61\uff0c\u5b9a\u671f\u4e86\u89e3\u4ed6\u5011\u7684\u8ca1\u653f\u9700\u8981\u53ca\u6aa2\u8a0e\u73fe\u6709\u7406\u8ca1\u8a08\u5283\n\u70ba\u73fe\u6709\u5ba2\u6236\u63d0\u4f9b\u512a\u8cea\u552e\u5f8c\u670d\u52d9\u53ca\u8655\u7406\u7406\u8ce0\u4e8b\u9805\n\n\u5165\u8077\u8981\u6c42:\n\n\u5927\u5b78\u5b78\u58eb\u7562\u696d\u6216\u4ee5\u4e0a\n\u6216\u4e2d\u4e94\u6703\u8003\u6216\u4e2d\u5b78\u6587\u6191\u8003\u8a665\u79d1\u5408\u683c(\u5305\u62ec\u4e2d\uff0c\u82f1\uff0c\u6578)\u6216\u540c\u7b49\u7a0b\u5ea6\u4ee5\u4e0a\n\u6e34\u671b\u4ee5\u5408\u4f19\u4eba\u7684\u8eab\u4efd\u53c3\u8207\u4f4e\u6210\u672c\u3001\u4f4e\u98a8\u96aa\u7684\u5275\u696d\u9805\u76ee\uff0c\u6253\u9020\u5c6c\u65bc\u500b\u4eba\u7684\u54c1\u724c\u548c\u696d\u52d9\u5718\u968a\n\u8655\u4e8b\u6210\u719f\uff0c\u5177\u826f\u597d\u4eba\u969b\u6280\u5de7\n\n\u5982\u6709\u8208\u8da3\u8acbwhatsapp\u4f60\u7684CV\u52309150 3700 (\u8d99\u5c0f\u59d0)", "employment_types": ["Full Time"], "selling_points": [], "locations": ["Wan Chai"], "categories": ["Property / Real Estate", "Property Management", "Others", "Others", "Security / Safety Control"], "post_time": "2022-01-18T02:19:11Z", "salary": {"currency": null, "max": null, "min": null, "period": "monthly", "term": null}, "salary_visible": false, "title_keywords": ["\u4fdd\u5b89\u54e1"], "responsibilities": [], "requirements": {"degrees": [], "majors": [], "languages": [], "language_level": [], "hard_skills": [], "soft_skills": [], "languages_combined": []}, "experience_required": {"duration": [], "field": []}}, {"job_id": "100003009054130", "location_code": "hk", "company": "AXA China Region Insurnace Company Limited", "job_title": "Wealth Management Manager \u8ca1\u5bcc\u7ba1\u7406\u7d93\u7406\uff08\u8df3\u51fa\u6253\u5de5\u4ed4\u6846\u6846\uff0c\u6b61\u8fce\u8f49\u884c/\u517c\u8077\u4eba\u58eb)", "description": "Employer Ref: SPA_20211215\nRecruit Ref: L0536923\nPosting Date: 2022-01-11\n\nMetro Property Management Limited\n\n\u9ad8\u7d1a\u7269\u696d\u52a9\u7406 / Senior Property Assistant\n\n\u4e3b\u8981\u8077\u8cac :\n\n\u4e00\u822c\u524d\u67b1\u5de5\u4f5c\uff1b\n\n\u57fa\u672c\u6587\u66f8\u8655\u7406\uff1b\n\n\u56de\u8986\u96fb\u90f5\u3001\u96fb\u8a71\u3001\u5ee3\u544a\u7db2\u9801\u7b49\uff1b\n\n\u8ddf\u9032\u4f4f\u6236\u67e5\u8a62\u53ca\u8655\u7406\u6295\u8a34\uff1b\n\n\u652f\u63f4\u7269\u696d\u7ba1\u7406\u670d\u52d9\uff0c\u5305\u62ec\u884c\u653f\u3001\u7dad\u4fee\u53ca\u6e05\u6f54\n\n\n\n\n\u5165\u8077\u8981\u6c42\uff1a\n\n\u4e2d5\u7a0b\u5ea6\uff1b\u51771\u5e74\u5de5\u4f5c\u7d93\u9a57\uff1b\n\n\u6709\u8cac\u4efb\u611f\uff0c\u5177\u826f\u597d\u6e9d\u901a\u80fd\u529b\u53ca\u4eba\u969b\u95dc\u4fc2\u6280\u5de7\uff1b\n\n\u5177\u826f\u597d\u670d\u52d9\u614b\u5ea6\uff1b\n\n\u64cd\u6d41\u5229\u5ee3\u6771\u8a71\u53ca\u4e00\u822c\u82f1\u8a9e\u53ca\u666e\u901a\u8a71\uff1b\n\n\u5177\u6709\u57fa\u672c\u96fb\u8166\u64cd\u4f5c\u77e5\u8b58\uff1b\u61c2\u96fb\u8166\u6587\u66f8\u8655\u7406\n\n\n\n\n\u5de5\u4f5c\u6642\u9593\uff1a\n\n\u661f\u671f\u4e00\u81f3\u4e94\uff1a\u4e0a\u53489:30 - \u4e0b\u53486:30\n\n\u661f\u671f\u516d\uff1a\u4e0a\u53489:30 - \u4e0b\u53481:30\n\n\uff08\u6709\u9700\u8981\u6642\u8f2a\u4f11\uff09\n\n\n\n\n\u6709\u610f\u61c9\u5fb5\u8005\u8acb\u5c07\u500b\u4eba\u5c65\u6b77\u3001\u671f\u671b\u85aa\u916c\u53ca\u65e5\u9593\u806f\u7d61\u96fb\u8a71\u96fb\u90f5\u81f3 APPLY NOW\n\n\n\nSummary\nIndustry:\nReal Estate / Property Management\nJob Category / Function:\nProperty / Estate Management / Security (Property / Estate Management)\nJob Position Level:\nGeneral\nEmployment Term:\nFull Time\nMin. Edu. Level Req:\nF.5 / HKCEE\nMinimum QF Level attained:\n-\nTotal Working Exp:\n1\nSalary(HKD):\n-\nLocation:\nWanchai District / Causeway Bay\nBenefits:\nBank Holiday\nDouble Pay\nMedical Insurance", "employment_types": ["Full Time", "Part Time", "Internship", "Freelance"], "selling_points": ["\u4e0d\u518d\u88ab\u7121\u9650OT \u548c\u7121\u804a\u7684\u8fa6\u516c\u5ba4\u653f\u6cbb\u6346\u7d81\u4f60\u7684\u6f5b\u80fd\uff0c\u771f\u6b63work life balance", "\u4e00\u4efd\u8b93\u4f60\u53ef\u4ee5\u81ea\u5df1\u6c7a\u5b9a\u9000\u4f11\u5e74\u9f61\u7684\u7d42\u8eab\u4e8b\u696d\uff0c\u52a9\u4f60\u5be6\u8e10\u7f6e\u696d\u5922\u60f3\uff0c\u8ca1\u52d9\u81ea\u7531\u3002", "\u6b61\u8fce\u5927\u5b78\u751f\uff0c\u65b0\u6642\u4ee3slasher, \u60f3\u8f49\u63db\u4e8b\u696d\u8dd1\u5230\u7684\u4f60"], "locations": ["Kwun Tong"], "categories": ["Property / Real Estate", "Property Consultancy", "Property Management", "Others"], "post_time": "2022-01-17T08:30:29Z", "salary": {"currency": "HKD", "max": 34999, "min": 25000, "period": "monthly", "term": null}, "salary_visible": true, "title_keywords": ["wealth management manager"], "responsibilities": ["management"], "requirements": {"degrees": [], "majors": [], "languages": [], "language_level": [], "hard_skills": [], "soft_skills": [], "languages_combined": []}, "experience_required": {"duration": [], "field": []}}, {"job_id": "100003009054297", "location_code": "hk", "company": "K. Wah International Holdings Ltd", "job_title": "Customer Service Ambassador (Full-time / Part-time)", "description": "Job Responsibilities\n\nAssist with handover logistics, and work with internal/ external parties to ensure timely and effective service to customers\nProvide after-sales services and follow up proactively\nHandle and respond to customer enquiry\nAssist in sales activities and operations\nProvide tours for potential buyers inside property, common area, and recreational facilities\nSupport on-site logistics\nCompile operation reports on number of visitors and customer feedback\nMaintain inventory of materials and others upon request\n\nJob Requirements\n\nDiploma holder or above\n1 year of relevant experience in particular handover of residential properties or client-facing customer service role\nGood command of spoken & written Cantonese and English, basic skills in Mandarin\nGood interpersonal and communication skills, good telephone manner, and responsive to clients\u2019 enquiries\nPositive working attitude, responsible and result-oriented\nGood listener\nProficient in MS Office application (Excel, Word, PowerPoint, and Chinese Word Processing)\n6 months renewable contract with satisfaction gratuity\n12 days annual leave\nInterested parties please send resume with salary expectation and availability to\u00a0Human Resources Department, K. Wah International Holdings Limited, 29/F, K. Wah Centre, 191 Java Rd., North Point, H.K.,\u00a0or by clicking\u00a0Apply Now.\n\nAll Personal data collected will be used for recruitment purpose only. All applications will be retained for a maximum period of 2 years and may be considered for other suitable positions within the Group.", "employment_types": ["Part Time", "Temporary", "Contract"], "selling_points": ["12 days annual leave", "Attractive Gratuity provided", "Renewable Contract"], "locations": ["North Point"], "categories": ["Sales, CS & Business Devpt", "Customer Service - Supervisor / Officer", "Property / Real Estate", "Others", "Sales - Real Estate"], "post_time": "2022-01-17T09:05:23Z", "salary": {"currency": null, "max": null, "min": null, "period": "monthly", "term": null}, "salary_visible": false, "title_keywords": ["customer service ambassador"], "responsibilities": ["sales activities", "operations", "inventory", "external parties", "maintain", "logistics", "reports"], "requirements": {"degrees": ["diploma holder"], "majors": [], "languages": ["cantonese", "english", "chinese", "mandarin"], "language_level": ["good command", "proficient", "basic"], "hard_skills": ["excel", "basic", "chinese word processing", "word", "powerpoint", "ms office"], "soft_skills": ["result-oriented", "communication skills", "responsible", "positive working attitude", "customer service", "interpersonal", "telephone manner", "client-facing", "responsive"], "languages_combined": [{"language": "cantonese", "language_level": ["good command", "basic"]}, {"language": "english", "language_level": ["good command", "basic"]}, {"language": "chinese", "language_level": ["proficient"]}, {"language": "mandarin", "language_level": ["good command", "basic"]}]}, "experience_required": {"duration": ["1 year"], "field": ["customer service", "relevant experience", "client-facing"]}}, {"job_id": "100003009053222", "location_code": "hk", "company": "Jones Lang LaSalle Management Services Ltd", "job_title": "\u4e2d\u74b0\u5546\u5ec8 - \u56fa\u5b9a\u65e9\u66f4\u7269\u696d\u52a9\u7406 12 \u5c0f\u6642 (\u5168\u8077)", "description": "\u8077\u8cac:\n\n\u5de1\u8996\u7269\u696d\n\u78ba\u4fdd\u6240\u6709\u8a2d\u65bd\u904b\u4f5c\u6b63\u5e38\n\u8655\u7406\u9867\u5ba2\u67e5\u8a62\n\u5354\u52a9\u4e0a\u53f8\u8ddf\u9032\u6295\u8a34\u53ca\u8655\u7406\u7dca\u6025\u4e8b\u6545\n\u4e3b\u52d5\u8207\u696d\u6236\u63a5\u89f8\n\u7dad\u6301\u826f\u597d\u95dc\u4fc2\n\n\u8981\u6c42:\n\n\u4e2d\u4e94\u6216\u4ee5\u4e0a\u7a0b\u5ea6\n\u4e00\u5e74\u6216\u4ee5\u4e0a\u7269\u696d\u7ba1\u7406\u7d93\u9a57\u512a\u5148\n\u6210\u719f, \u6709\u826f\u597d\u7d44\u7e54\u80fd\u529b, \u6709\u8cac\u4efb\n\u57fa\u672c\u82f1\u8a9e\u53ca\u570b\u8a9e\u3001\u826f\u597d\u7cb5\u8a9e\u7684\u8a00\u8a9e\u80fd\u529b\n\u6a02\u89c0\u6027\u683c \u53ca \u5177\u7368\u7acb\u80fd\u529b\n\u6709\u4e00\u822c\u96fb\u8166\u77e5\u8b58\u512a\u5148\n\u5de5\u4f5c\u6642\u9593: \u65e9\u73ed(0700-1900)\u00a0\n\n\u6b61\u8fce\u76f4\u63a5\u81f4\u96fb 2117 8010\u67e5\u8a62\u3002\n\nWe offer attractive remuneration package and good career prospect for the right applicant.\n\nPlease apply by clicking\u00a0\"Apply Now\", or submit full resume and expected salary to the\u00a0HR Department, Room 1402, 14/F, Dorset House, Taikoo Place, 979 King's Road, Quarry Bay, HK\u00a0or\u00a0fax to 2968-4177.\u00a0\n\n(Please quote the reference number on the subject of email)\n\nApplicants not invited for interviews within 6 weeks may consider their applications unsuccessful. Information provided will be treated with strict confidential and be used for the purpose of employment only.", "employment_types": ["Full Time", "Permanent"], "selling_points": ["F.5 or above", "Min. 1 year's experience", "Luxurious Residential Building"], "locations": ["Central & Western Area"], "categories": ["Property / Real Estate", "Property Management", "Others", "Building & Construction", "Others"], "post_time": "2022-01-17T08:08:55Z", "salary": {"currency": null, "max": null, "min": null, "period": "monthly", "term": null}, "salary_visible": false, "title_keywords": [], "responsibilities": [], "requirements": {"degrees": [], "majors": [], "languages": [], "language_level": [], "hard_skills": [], "soft_skills": [], "languages_combined": []}, "experience_required": {"duration": [], "field": []}}, {"job_id": "100003009054390", "location_code": "hk", "company": "S.F. Express (Hong Kong) Limited", "job_title": "Administration Executive (Leasing Team)", "description": "Responsibilities:\n\nProvide clerical support in leasing team, such as leasing documents preparation\nAssist to monitor performance of vendors, liaises with internal parties to ensure projects\u2019 delivery are meet with company requirements and timeline\nMaintain the good communication and work flow between the team, make sure the documents are in good orders\nHandle any ad-hoc duties assigned\n\nRequirement:\n\nHolder of high-diploma or above in Business Administration, Real Estate, Property / Facility Management, Surveying or related disciplines is highly preferred\n1 year of administration work experience, fresh graduate with clerical work knowledge will also be considered\nIndependent, responsible, detail-minded and well-organized\nProficient in MS Office, Excel, PowerPoint and Chinese word processing\nGood command of spoken and written English and Chinese\nImmediate candidate is preferable\nCandidate with more experience will be considered as\u00a0Assistant Leasing Officer", "employment_types": ["Full Time", "Permanent"], "selling_points": ["Free shuttle bus coverage", "Attractive remuneration package", "2 months or above performance bonus"], "locations": ["Tsing Yi"], "categories": ["Property / Real Estate", "Others"], "post_time": "2022-01-17T09:20:17Z", "salary": {"currency": null, "max": null, "min": null, "period": "monthly", "term": null}, "salary_visible": false, "title_keywords": ["administration executive"], "responsibilities": ["provide clerical support", "monitor performance", "communication", "maintain", "ad-hoc duties", "internal parties"], "requirements": {"degrees": ["fresh graduate", "diploma or above"], "majors": ["related disciplines", "business administration", "surveying"], "languages": ["english", "chinese"], "language_level": ["good command", "proficient"], "hard_skills": ["excel", "chinese word processing", "powerpoint", "ms office"], "soft_skills": ["detail-minded", "independent", "well-organized", "responsible"], "languages_combined": [{"language": "english", "language_level": ["good command"]}, {"language": "chinese", "language_level": ["good command", "proficient"]}]}, "experience_required": {"duration": ["1 year"], "field": ["clerical", "administration"]}}, {"job_id": "100003009055078", "location_code": "hk", "company": "Newtech Management Services Ltd", "job_title": "\u6280\u8853\u54e1 / \u52a9\u7406\u4e3b\u7ba1 (\u51b7\u6c23) Technician / Assistant Supervisor (Air-Conditioning)", "description": "Responsibilities &\u00a0Requirements:\n\n\nHandle air-conditioning maintenance in data centre for our clients;\nMinimum 2 years\u2019 solid experience in air-conditioning;\nKnowledge in CRAC/Chiller system is preferable;\nGood communication skills, customer-oriented;\nCandidate with data centre experience will be an advantage;\nCandidate with more experience will be considered as Senior\u00a0Technician/Assistant Supervisor\n\u8077\u8cac\u53ca\u8cc7\u6b77:\n\n\u8ca0\u8cac\u6578\u64da\u4e2d\u5fc3\u5916\u52e4\u4fdd\u990a\u53ca\u7dad\u4fee\u51b7\u6c23\u7cfb\u7d71;\n\u5177\u5099\u6700\u5c112\u5e74\u51b7\u6c23\u4fdd\u990a\u53ca\u7dad\u4fee\u6216\u76f8\u95dc\u7d93\u9a57;\n\u61c2CRAC\u8207\u4e2d\u592e\u51b7\u6c34\u6a5f\u7cfb\u7d71\u512a\u5148\u8003\u616e;\n\u826f\u597d\u6e9d\u901a\u53ca\u9867\u5ba2\u670d\u52d9\u6280\u5de7;\n\u6709\u6578\u64da\u4e2d\u5fc3\u7dad\u4fee\u670d\u52d9\u7d93\u9a57\u8005\u66f4\u4f73;\n\u8f03\u591a\u7d93\u9a57\u8005\u5c07\u6703\u8003\u616e\u70ba\u9ad8\u7d1a\u6280\u8853\u54e1\u6216\u52a9\u7406\u4e3b\u7ba1\n\u6709\u82b1\u7d05, \u7259\u79d1\u798f\u5229, \u91ab\u7642\u4fdd\u96aa, \u8d85\u6642\u5de5\u4f5c\u6d25\u8cbc, \u6649\u5347\u6a5f\u6703\u53ca\u9032\u4fee\u6d25\u8cbc, \u4e0a\u73ed\u6642\u9593\u4e0a\u53489\u6642\u81f3\u4e0b\u53486\u6642, \u6bcf\u9031\u5de5\u4f5c6\u5929, \u6bcf\u5929\u5de5\u4f5c 8 \u5c0f\u6642, \u4eab\u6709\u516c\u8846\u5047\u671f;\u00a0\n\n\nAn attractive remuneration package and fringe benefit will be offered to the right candidate. Interested parties, please send\u00a0your resume stating with current and expected salary\u00a0to the Human Resources Department by clicking Apply Now.\n\nFor more information, please visit the corporate website at\u00a0http://www.newtechapac.com\n\n\u00a0All information received will be kept confidential and for recruitment purposes only. Response will only be given to short-listed candidates.", "employment_types": ["Full Time", "Permanent"], "selling_points": [], "locations": ["Kowloon Bay"], "categories": ["Engineering", "Others", "Property / Real Estate", "Others", "Others", "Technician"], "post_time": "2022-01-18T01:10:16Z", "salary": {"currency": null, "max": null, "min": null, "period": "monthly", "term": null}, "salary_visible": false, "title_keywords": ["\u6280\u8853\u54e1", "technician", "assistant supervisor"], "responsibilities": [], "requirements": {"degrees": [], "majors": [], "languages": [], "language_level": [], "hard_skills": ["maintenance"], "soft_skills": ["communication skills", "customer-oriented"], "languages_combined": []}, "experience_required": {"duration": ["minimum 2 years"], "field": ["air-conditioning"]}}, {"job_id": "100003009054929", "location_code": "hk", "company": "Sun Hung Kai Properties Ltd", "job_title": "ASSISTANT MANAGER \u2013 INDUSTRIAL PORTFOLIO LEASING", "description": "Sun Hung Kai Properties Limited owns an industrial & logistics portfolio with GFA over 5 million sq.ft. and a parking portfolio. We are now seeking for high caliber candidates to join us to grow the portfolios and participate in the leasing, acquisition and disposal management activities along the life cycle of various asset classes.\n\n\nRequirements:\n\n\nBachelor\u2019s degree in business, logistics, surveying or related disciplines\nMinimum 5 years experiences in leasing & marketing of logistics, industrial or commercial properties\nExperiences in relationship development and management with logistics players and MNCs will be an advantage\nProven track record in partnership development, new tenant sourcing & retention\nProactive individual with good understandings of corporate real estate and logistics industry\nFluent in English, Mandarin and Cantonese\n\nResponsibilities:\n\n\nResponsible for the leasing activities including new lettings, renewal, budget preparation, tenancy liaison and administration\nParticipate in planning and coordination of portfolio enhancement & asset disposal\nConduct market research, financial analysis and compile various reports\nAcquire new potential tenants through marketing events, referrals and business connections\nManage relationship with clients and property agencies\nPrepare pitching proposal and response RFPs for corporate clients\nPlan and execute marketing and promotional activities\n\n(Candidates with more experience will be considered for more senior positions.)\u00a0\n\nGood remuneration and attractive fringe benefits will be offered to the successful applicant. Interested parties please apply with full resume, present and expected salary, available date by clicking \"Apply Now\".\n\nWe are an equal opportunity employer and welcome applications from all qualified candidates. All personal data collected will be used for recruitment purpose only.\u00a0 Applicants not hearing from us within 3 months may consider their applications unsuccessful.\u00a0 All personal data collected will be destroyed within 24 months.", "employment_types": ["Full Time", "Permanent"], "selling_points": ["Exp in leasing of industrial/ commercial portfolio", "Partnership development, new tenant sourcing", "Marketing and promotional activities"], "locations": ["Wan Chai"], "categories": ["Sales, CS & Business Devpt", "Business Development", "Marketing / Public Relations", "Marketing - Marketing Communication", "Property / Real Estate", "Others"], "post_time": "2022-01-17T14:16:59Z", "salary": {"currency": null, "max": null, "min": null, "period": null, "term": null}, "salary_visible": false, "title_keywords": ["assistant manager"], "responsibilities": ["administration", "marketing events", "conduct market research", "budget", "financial analysis", "reports", "promotional activities", "coordination", "plan", "planning"], "requirements": {"degrees": ["degree", "bachelor"], "majors": ["related disciplines", "business", "surveying"], "languages": ["cantonese", "english", "mandarin"], "language_level": ["fluent"], "hard_skills": [], "soft_skills": ["proactive"], "languages_combined": [{"language": "cantonese", "language_level": ["fluent"]}, {"language": "english", "language_level": ["fluent"]}, {"language": "mandarin", "language_level": ["fluent"]}]}, "experience_required": {"duration": ["minimum 5 years"], "field": ["management", "development", "commercial", "marketing", "logistics"]}}, {"job_id": "100003009053788", "location_code": "hk", "company": "Hysan Development Co. Ltd.", "job_title": "(\u9ad8\u7d1a) \u5ba2\u6236\u670d\u52d9\u54e1 - \u5beb\u5b57\u6a13\u53ca\u5546\u5834", "description": "\u8077\u8cac:\n\n\u8ca0\u8cac\u5354\u52a9\u53ca\u8655\u7406\u65e5\u5e38\u7269\u696d\u7ba1\u7406\u5de5\u4f5c\uff0c\u5305\u62ec\u5ba2\u6236\u67fb\u8a62\u53ca\u6295\u8a34\uff0c\u5546\u5834\u63a8\u5ee3\u6d3b\u52d5\u4e4b\u4eba\u6d41\u7ba1\u5236\uff0c\u5371\u6a5f\u8655\u7406\u7b49\u63d0\u4f9b\u512a\u8cea\u5ba2\u6236\u670d\u52d9\u53ca\u4fdd\u5b89\u5de5\u4f5c\u3002\n\n\n\n\u5165\u8077\u8981\u6c42:\n\n\n\u4e2d\u4e94\u6216\u4ee5\u4e0a\u7a0b\u5ea6\n\u4e00\u5e74\u6216\u4ee5\u4e0a\u76f8\u95dc\u7269\u696d\u7ba1\u7406 / \u5ba2\u6236\u670d\u52d9\u7d93\u9a57\u512a\u5148\n\u6301\u6709\u6548\u4fdd\u5b89\u4eba\u54e1\u8a31\u53ef\u8b49\u53caQAS\u8b49\u66f8\u00a0\n\u61c2\u96fb\u8166\u57fa\u672c\u64cd\u4f5c\n\u826f\u597d\u7cb5\u8a9e\u53ca\u666e\u901a\u8a71\uff0c\u80fd\u4ee5\u7c21\u55ae\u82f1\u8a9e\u6e9d\u901a\n\u65bc\u9285\u947c\u7063\u5340\u8f2a\u73ed\u5de5\u4f5c (9\u5c0f\u6642/5.5\u5929)\n\u7d93\u9a57\u8f03\u591a\u4e4b\u6c42\u8077\u8005\u53ef\u7372\u8003\u616e\u70ba\u9ad8\u7d1a\u5ba2\u6236\u670d\u52d9\u54e1\n\u00a0\n\n\u798f\u5229:\n\n\n\u5e74\u7d42\u96d9\u7ce7\n\u914c\u60c5\u82b1\u7d05\n\u6709\u85aa\u5e74\u5047\n\u65b0\u5a5a\u5047\n\u751f\u65e5\u5047\n\u5b78\u7fd2\u5047\n\u8003\u8a66\u5047\n\u6069\u6064\u5047\n\u9032\u4fee\u8cc7\u52a9\n\u81b3\u98df\u6d25\u8cbc\n\u8f2a\u73ed\u6d25\u8cbc\n\u8d85\u6642\u88dc\u85aa\n\u5728\u8077\u57f9\u8a13\n\u7259\u79d1\u91ab\u7642\n\u4e2d\u897f\u91ab\u91ab\u7642\n\u5718\u9ad4\u4eba\u58fd\u4fdd\u96aa\n\u826f\u597d\u6649\u5347\u6a5f\u6703\n\u63a8\u85a6\u65b0\u4eba\u734e\u91d1\n\u516c\u53f8\u5eb7\u6a02\u6d3b\u52d5\n\n\u6709\u610f\u61c9\u5fb5\u8005\u53ef\u9ede\u64ca\u201cAPPLY NOW\u201d\u6309\u9215\u905e\u4ea4\u5c65\u6b77\n\n\u5982\u6709\u4efb\u4f55\u7591\u554f\uff0c\u53ef\u81f4\u96fb\u62db\u8058\u71b1\u7dda / WhatsApp: 9760 3380\n\n\n\n\u7533\u8acb\u4eba\u63d0\u4f9b\u4e4b\u500b\u4eba\u8cc7\u6599\u5c07\u53ea\u7528\u4f5c\u62db\u8058\u7528\u9014\u53ca\u6703\u7d55\u5c0d\u4fdd\u5bc6\n\nHysan is an equal opportunity employer.\u00a0 All information collected will be kept in strict confidence and used solely for recruitment related purposes within the Hysan Group Companies.\n\nYou may get to know more about us through www.hysan.com.hk", "employment_types": ["Full Time", "Permanent"], "selling_points": ["\u8ca0\u8cac\u63d0\u4f9b\u512a\u8cea\u5ba2\u6236\u670d\u52d9\u53ca\u4fdd\u5b89\u5de5\u4f5c", "\u4e2d\u4e94\u6216\u4ee5\u4e0a\u7a0b\u5ea6\u53ca\u6301\u6709\u6548\u4fdd\u5b89\u4eba\u54e1\u8a31\u53ef\u8b49\u53caQAS\u8b49\u66f8", "\u96d9\u7ce7 / \u82b1\u7d05 / \u8d85\u6642\u88dc\u85aa / \u751f\u65e5\u5047 / \u65b0\u5a5a\u5047 / \u4e2d\u897f\u91ab\u7259\u79d1\u91ab\u7642 / \u9032\u4fee\u8cc7\u52a9 / \u81b3\u98df\u6d25\u8cbc"], "locations": ["Causeway Bay"], "categories": ["Property / Real Estate", "Property Management", "Others"], "post_time": "2022-01-17T07:30:51Z", "salary": {"currency": "HKD", "max": 16999, "min": 14000, "period": "monthly", "term": null}, "salary_visible": true, "title_keywords": [], "responsibilities": ["recruitment"], "requirements": {"degrees": [], "majors": [], "languages": [], "language_level": [], "hard_skills": ["whatsapp"], "soft_skills": ["confidence"], "languages_combined": []}, "experience_required": {"duration": [], "field": []}}, {"job_id": "100003009055355", "location_code": "hk", "company": "Protech Property Management Ltd", "job_title": "\u4fdd\u5b89\u54e1 - \u65e5\u73ed (\u65fa\u89d2)", "description": "\u8077\u8cac :\u4e00\u822c\u4fdd\u5b89\u5de5\u4f5c\n\u8cc7\u6b77 :\u5c0f\u516d\u7a0b\u5ea6; 1\u5e74\u7d93\u9a57; \u826f\u597d\u7cb5\u8a9e; \u61c2\u8b80\u5beb\u4e2d\u6587; \u6301\u6709\u4fdd\u5b89\u57f9\u8a13\u8ab2\u7a0b\u8b49\u66f8(QAS); \u6301\u6709\u4fdd\u5b89\u4eba\u54e1\u8a31\u53ef\u8b49\n\u5f85\u9047 :\u6bcf\u6708$13,000, \u6709\u91ab\u7642\u4fdd\u96aa \u53ca\u8d85\u6642\u5de5\u4f5c\u6d25\u8cbc, \u4e0a\u534810\u6642\u81f3\u4e0b\u534810\u6642,\u4e0a\u53488\u6642\u81f3\u4e0b\u53488\u6642\u6216\u4e2d\u534812\u6642\u81f3\u51cc\u666812\u6642, \u6bcf\u9031\u5de5\u4f5c6\u5929,\u8f2a\u73ed,\u8f2a\u4f11, \u6bcf\u5929\u5de5\u4f5c 12 \u5c0f\u6642\n\u7533\u8acb\u9808\u77e5 :\u6c42\u8077\u8005\u53ef\u6309 APPLY NOW\u7533\u8acb\u6216\u81f4\u96fb31011000\u8207\u4fdd\u5f97\u7269\u696d\u7ba1\u7406\u6709\u9650\u516c\u53f8\u65bd\u5c0f\u59d0\u806f\u7d61\u3002", "employment_types": ["Full Time"], "selling_points": [], "locations": ["Mong Kok"], "categories": ["Property / Real Estate", "Property Management", "Others", "Others", "Security / Safety Control"], "post_time": "2022-01-18T02:17:32Z", "salary": {"currency": null, "max": null, "min": null, "period": "monthly", "term": null}, "salary_visible": false, "title_keywords": ["\u4fdd\u5b89\u54e1"], "responsibilities": [], "requirements": {"degrees": [], "majors": [], "languages": [], "language_level": [], "hard_skills": [], "soft_skills": [], "languages_combined": []}, "experience_required": {"duration": [], "field": []}}, {"job_id": "100003009056378", "location_code": "hk", "company": "\u6607\u6377\u7ba1\u7406\u670d\u52d9\u6709\u9650\u516c\u53f8", "job_title": "\u591c\u66f4\u4fdd\u5b89\u54e1", "description": "\u8077\u8cac :\u65e5\u5e38\u4fdd\u5b89\u5de5\u4f5c/\u5de1\u908f\n\u8cc7\u6b77 :\u6c92\u6709\u5b78\u6b77\u8981\u6c42; 1\u5e74\u7d93\u9a57; \u4e00\u822c\u7cb5\u8a9e; \u7565\u61c2\u8b80\u5beb\u4e2d\u6587; \u6301\u6709\u4fdd\u5b89\u57f9\u8a13\u8ab2\u7a0b\u8b49\u66f8(QAS); \u6301\u6709\u4fdd\u5b89\u4eba\u54e1\u8a31\u53ef\u8b49\n\u5f85\u9047 :\u6bcf\u6708$10,300 - $10,750, \u4e0b\u534811\u6642\u81f3\u4e0a\u53487\u6642, \u6bcf\u9031\u5de5\u4f5c6\u5929,\u8f2a\u4f11, \u6bcf\u5929\u5de5\u4f5c 8 \u5c0f\u6642\n\u7533\u8acb\u9808\u77e5 :\u6c42\u8077\u8005\u53ef\u6309 APPLY NOW\u7533\u8acb\u6216\u81f4\u96fb26182979\u8207\u6607\u6377\u7ba1\u7406\u670d\u52d9\u6709\u9650\u516c\u53f8\u9673\u5148\u751f\u806f\u7d61\u3002", "employment_types": ["Full Time"], "selling_points": ["\u65e5\u5e38\u4fdd\u5b89\u5de5\u4f5c/\u5de1\u908f", "\u6c92\u6709\u5b78\u6b77\u8981\u6c42", "1\u5e74\u7d93\u9a57"], "locations": ["Shatin Area"], "categories": ["Property / Real Estate", "Property Management", "Others", "Others", "Security / Safety Control"], "post_time": "2022-01-18T04:06:46Z", "salary": {"currency": null, "max": null, "min": null, "period": "monthly", "term": null}, "salary_visible": false, "title_keywords": [], "responsibilities": [], "requirements": {"degrees": [], "majors": [], "languages": [], "language_level": [], "hard_skills": [], "soft_skills": [], "languages_combined": []}, "experience_required": {"duration": [], "field": []}}, {"job_id": "100003009056413", "location_code": "hk", "company": "\u6607\u6377\u7ba1\u7406\u670d\u52d9\u6709\u9650\u516c\u53f8", "job_title": "\u591c\u66f4\u4fdd\u5b89\u54e1", "description": "\u8077\u8cac :\u4e00\u822c\u5c4b\u82d1\u4fdd\u5b89\u5de5\u4f5c\n\u8cc7\u6b77 :\u5c0f\u516d\u7a0b\u5ea6; \u826f\u597d\u7cb5\u8a9e; \u7565\u61c2\u8b80\u5beb\u4e2d\u6587; \u6301\u6709\u4fdd\u5b89\u57f9\u8a13\u8ab2\u7a0b\u8b49\u66f8(QAS); \u6301\u6709\u4fdd\u5b89\u4eba\u54e1\u8a31\u53ef\u8b49; \u6709\u8cac\u4efb\u611f\n\u5f85\u9047 :\u6bcf\u6708$14,500, \u6709\u5728\u8077\u57f9\u8a13 \u53ca\u91ab\u7642\u798f\u5229, \u4e0b\u53487\u6642\u81f3\u4e0a\u53487\u6642, \u6bcf\u9031\u5de5\u4f5c6\u5929,\u8f2a\u4f11, \u6bcf\u5929\u5de5\u4f5c 12 \u5c0f\u6642\n\u7533\u8acb\u9808\u77e5 :\u6c42\u8077\u8005\u53ef\u6309 APPLY NOW\u7533\u8acb\u6216\u81f4\u96fb23522124\u8207\u6607\u6377\u7ba1\u7406\u670d\u52d9\u6709\u9650\u516c\u53f8\u9ea5\u5148\u751f\u806f\u7d61\u3002", "employment_types": ["Full Time"], "selling_points": ["\u4e00\u822c\u5c4b\u82d1\u4fdd\u5b89\u5de5\u4f5c", "\u5c0f\u516d\u7a0b\u5ea6; \u826f\u597d\u7cb5\u8a9e", "\u6301\u6709\u4fdd\u5b89\u4eba\u54e1\u8a31\u53ef\u8b49"], "locations": ["Wong Tai Sin Area"], "categories": ["Property / Real Estate", "Property Management", "Others", "Others", "Security / Safety Control"], "post_time": "2022-01-18T04:13:21Z", "salary": {"currency": null, "max": null, "min": null, "period": "monthly", "term": null}, "salary_visible": false, "title_keywords": [], "responsibilities": [], "requirements": {"degrees": [], "majors": [], "languages": [], "language_level": [], "hard_skills": [], "soft_skills": [], "languages_combined": []}, "experience_required": {"duration": [], "field": []}}, {"job_id": "100003009048987", "location_code": "hk", "company": "Hongkong Land Group Limited", "job_title": "\u7ba1\u696d\u670d\u52d9\u54e1 (Ref: PM-BA-JDB)", "description": "\u4e3b\u8981\u8077\u52d9\u5305\u62ec\uff1a\u00a0\n\n\u8ca0\u8cac\u65e5\u5e38\u5546\u5834\u53ca\u5546\u5ec8\u7269\u696d\u7ba1\u7406\u5de5\u4f5c\uff0c\u53ca\u63d0\u4f9b\u512a\u8cea\u5ba2\u6236\u670d\u52d9\n\u61c9\u5fb5\u8005\u9808\u5177\u5099\u4ee5\u4e0b\u689d\u4ef6\uff1a\u00a0\n\n\u4e2d\u4e94\u7a0b\u5ea6\u6216\u4ee5\u4e0a\uff0c\u6301\u6709\u6709\u6548\u4fdd\u5b89\u4eba\u54e1\u8a31\u53ef\u8b49\u512a\u5148\n\u7d93\u9a57\u4e0d\u62d8\uff0c\u71b1\u8877\u5b78\u7fd2\uff0c\u4e26\u6709\u5fd7\u65bc\u7269\u696d\u7ba1\u7406\u884c\u696d\u767c\u5c55\n\u4ee5\u5ba2\u70ba\u5148\u53ca\u5177\u5718\u968a\u7cbe\u795e\uff0c\u6709\u5ba2\u6236\u670d\u52d9\u7d93\u9a57\u8005\u70ba\u4f73\n\u80fd\u4ee5\u82f1\u8a9e\u3001\u5ee3\u6771\u8a71\u53ca\u666e\u901a\u8a71\u6e9d\u901a\u00a0\n\u9808\u7a7f\u8457\u516c\u53f8\u5236\u670d\u00a0\n\u65e9\u73ed\uff1a\u4e0a\u53487:45\u2013 \u4e0b\u53484:15\n\u591c\u73ed\uff1a\u665a\u4e0a\u00a011:30 - \u4e0a\u53488:00\n\n\u5b8c\u5584\u54e1\u5de5\u798f\u5229\uff1a\n\n\u53ef\u4eab\u6709\u6bcf\u67086\u5929\u4f8b\u5047\n\u85aa\u512a\u53e6\u52a0\u82b1\u7d05\uff0c\u6bcf\u6708\u624b\u6a5f\u6d25\u8cbc\u53ca\u51fa\u52e4\u6d25\u8cbc\n\u91ab\u7642\u798f\u5229\u300112\u5929\u6709\u85aa\u5e74\u5047\u3001\u514d\u4f9b\u6b3e\u516c\u7a4d\u91d1\u53ca\u54e1\u5de5\u6e21\u5047\u5c4b\n\u4ee3\u7533\u8acb\u53ca\u652f\u4ed8\u500b\u4eba\u4fdd\u5b89\u724c\u7167\u8cbb\u7528\n\u5165\u8077\u57f9\u8a13\u8ab2\u7a0b\u53ca\u5c08\u696d\u5728\u8077\u57f9\u8a13\n\u5b8c\u5584\u7684\u5167\u90e8\u6649\u5347\u5236\u5ea6\uff0c\u63d0\u4f9b\u767c\u5c55\u53ca\u6649\u5347\u6a5f\u6703\n\n\u6709\u610f\u61c9\u5fb5\u8005\uff0c\u8acb\u5c07\u500b\u4eba\u5c65\u6b77 (\u8acb\u8a3b\u660e\u7533\u8acb\u8077\u4f4d\u3001\u806f\u7d61\u96fb\u8a71\u53ca\u8981\u6c42\u5f85\u9047) \u4ee5WhatsApp\u50b3\u9001\u81f39223 7989 \u6216\u00a0\u9ede\u64ca\u00a0\"Apply Now\"\u00a0\u7acb\u5373\u7533\u8acb\u3002\n\n\u6709\u95dc\u7f6e\u5730\u516c\u53f8\u8cc7\u6599\uff0c\u8acb\u700f\u89bd\u00a0http://www.hkland.com/\u00a0\n\n\u95a3\u4e0b\u6240\u63d0\u4f9b\u4e4b\u500b\u4eba\u8cc7\u6599\u53ea\u4f5c\u70ba\u6b64\u8077\u4f4d\u62db\u8058\u4e4b\u7528\uff0c\u65bc\u56db\u661f\u671f\u5167\u4e0d\u7372\u7d04\u898b\u8005\uff0c\u7576\u4f5c\u4e0d\u88ab\u53d6\u9304\uff0c\u5176\u6240\u905e\u4ea4\u4e4b\u500b\u4eba\u8cc7\u6599\u4ea6\u96a8\u5373\u92b7\u6bc1\u3002", "employment_types": ["Full Time", "Permanent"], "selling_points": ["\u7ba1\u696d\u670d\u52d9\u54e1 (8.5\u5c0f\u6642\u5b9a\u66f4)", "\u6b61\u8fce\u6709\u5fd7\u65bc\u7269\u696d\u7ba1\u7406\u884c\u696d\u767c\u5c55\u8005\u61c9\u8058", "\u53ef\u4eab\u6709\u6bcf\u6708\u9ad8\u9054 6\u5929\u4f8b\u5047"], "locations": ["Central"], "categories": ["Property / Real Estate", "Property Management", "Others", "Others", "Security / Safety Control"], "post_time": "2022-01-14T07:50:16Z", "salary": {"currency": null, "max": null, "min": null, "period": "monthly", "term": null}, "salary_visible": false, "title_keywords": [], "responsibilities": [], "requirements": {"degrees": [], "majors": [], "languages": [], "language_level": [], "hard_skills": [], "soft_skills": [], "languages_combined": []}, "experience_required": {"duration": [], "field": []}}, {"job_id": "100003009053649", "location_code": "hk", "company": "Vineberg Property Management Limited", "job_title": "\u5ba2\u6236\u670d\u52d9\u76e3\u7763", "description": "\n\u8077\u8cac :\u8ca0\u8cac\u4fdd\u5b89\u76e3\u7763\u5de5\u4f5c, \u5305\u62ec\u4e00\u822c\u4fdd\u5b89\u54e1\u8077\u8cac, \u8a18\u9304\u53ca\u586b\u5beb\u5831\u544a, \u8655\u7406\u5ba2\u6236\u67e5\u8a62\u53ca\u6295\u8a34, \u8655\u7406\u53ca\u8ddf\u9032\u7dca\u6025\u7a81\u767c\u4e8b\u4ef6, \u5236\u5b9a\u4eba\u624b\u914d\u7f6e\u53ca\u7de8\u66f4, \u7763\u5c0e\u53ca\u57f9\u8a13\u4e0b\u5c6c\u7b49\u5de5\u4f5c\n\n\u8cc7\u6b77 :\u4e2d\u4e94\u7a0b\u5ea6; 5\u5e74\u7d93\u9a57; \u826f\u597d\u7cb5\u8a9e; \u4e00\u822c\u666e\u901a\u8a71; \u4e00\u822c\u82f1\u8a9e; \u61c2\u8b80\u5beb\u4e2d\u6587; \u7565\u61c2\u8b80\u5beb\u82f1\u6587; \u61c2\u96fb\u8166\u6587\u66f8\u8655\u7406; \u6301\u6709\u4fdd\u5b89\u57f9\u8a13\u8ab2\u7a0b\u8b49\u66f8(QAS); \u6301\u6709\u4fdd\u5b89\u4eba\u54e1\u8a31\u53ef\u8b49; \u6301\u6709\u6548\u5e73\u5b89\u54ad/\u6025\u6551\u8b49\u66f8\u512a\u5148\n\n\u5f85\u9047 :\u6bcf\u6708$21,000, \u6709\u751f\u65e5\u5047, \u91ab\u7642\u798f\u5229 \u53ca\u6bcf\u6708\u8868\u73fe\u734e\u91d1$1400, 7:30AM-4:30PM/ 2:30PM-11:30PM/ 11:00PM-8:00AM, \u6bcf\u9031\u5de5\u4f5c6\u5929, \u8f2a\u4f11, \u6bcf\u5929\u5de5\u4f5c 9 \u5c0f\u6642\n\n\u7533\u8acb\u9808\u77e5 :\u6c42\u8077\u8005\u53ef\u81f4\u96fb22074388\u8207\u842c\u5bf6\u7269\u696d\u7ba1\u7406\u6709\u9650\u516c\u53f8\u7a0b\u5148\u751f\u806f\u7d61\u3002\n\n", "employment_types": ["Full Time"], "selling_points": [], "locations": ["Tseung Kwan O"], "categories": ["Property / Real Estate", "Property Management", "Others", "Others", "Security / Safety Control"], "post_time": "2022-01-17T07:17:33Z", "salary": {"currency": null, "max": null, "min": null, "period": "monthly", "term": null}, "salary_visible": false, "title_keywords": [], "responsibilities": [], "requirements": {"degrees": [], "majors": [], "languages": [], "language_level": [], "hard_skills": [], "soft_skills": [], "languages_combined": []}, "experience_required": {"duration": [], "field": []}}, {"job_id": "100003009055491", "location_code": "hk", "company": "Keysen Property Management Services Limited", "job_title": "\u7269\u696d\u7ba1\u7406\u54e1/\u4fdd\u5b89\u54e1 (\u591c\u73ed)", "description": "\u8077\u8cac :\u8ca0\u8cac\u4e00\u822c\u7269\u696d\u7ba1\u7406\u54e1/\u4fdd\u5b89\u54e1\u5de5\u4f5c,\u8655\u7406\u5927\u5ec8\u65e5\u5e38\u4fdd\u5b89\u5de5\u4f5c\n\u8cc7\u6b77 :\u5c0f\u516d\u7a0b\u5ea6; 1\u5e74\u7d93\u9a57; \u826f\u597d\u7cb5\u8a9e; \u7565\u61c2\u8b80\u5beb\u4e2d\u6587; \u6301\u6709\u4fdd\u5b89\u57f9\u8a13\u8ab2\u7a0b\u8b49\u66f8(QAS); \u6301\u6709\u4fdd\u5b89\u4eba\u54e1\u8a31\u53ef\u8b49; \u5177\u76f8\u95dc\u5de5\u4f5c\u7d93\u9a57\n\u5f85\u9047 :\u6bcf\u6708$15,000 - $16,000, \u6709\u914c\u60c5\u6027\u82b1\u7d05, \u4e0b\u53487\u6642\u534a\u81f3\u4e0a\u53487\u6642\u534a, \u6bcf\u9031\u5de5\u4f5c6\u5929,\u8f2a\u4f11, \u6bcf\u5929\u5de5\u4f5c 12 \u5c0f\u6642\n\u7533\u8acb\u9808\u77e5 :\u6c42\u8077\u8005\u53ef\u6309 APPLY NOW\u7533\u8acb\u6216\u81f4\u96fb28792156\u8207\u5805\u4fe1\u7269\u696d\u7ba1\u7406\u670d\u52d9\u6709\u9650\u516c\u53f8\u9673 \u5c0f\u59d0\u806f\u7d61\u3002", "employment_types": ["Full Time"], "selling_points": ["\u8ca0\u8cac\u4e00\u822c\u7269\u696d\u7ba1\u7406\u54e1/\u4fdd\u5b89\u54e1\u5de5\u4f5c", "\u8655\u7406\u5927\u5ec8\u65e5\u5e38\u4fdd\u5b89\u5de5\u4f5c", "\u5c0f\u516d\u7a0b\u5ea6; 1\u5e74\u7d93\u9a57"], "locations": ["Shatin Area"], "categories": ["Property / Real Estate", "Property Management", "Others", "Others", "Security / Safety Control"], "post_time": "2022-01-18T02:39:13Z", "salary": {"currency": null, "max": null, "min": null, "period": "monthly", "term": null}, "salary_visible": false, "title_keywords": ["\u4fdd\u5b89\u54e1"], "responsibilities": [], "requirements": {"degrees": [], "majors": [], "languages": [], "language_level": [], "hard_skills": [], "soft_skills": [], "languages_combined": []}, "experience_required": {"duration": [], "field": []}}, {"job_id": "100003009052387", "location_code": "hk", "company": "Simatelex Manufactory Co., Ltd.", "job_title": "Project Clerk", "description": "Responsible for providing clerical support such as data entry, filing, etc. to the Property Department.\n\n\nF.5 or above\nAt least 1 year relevant experience\nComputer literate in MS Word, Excel & Chinese Word Processing\nGood command of English and Chinese\nSound analytical, communication and negotiation skill\nExperience in coordinating property related project is preferable\nWorking location: Wanchai\nFor more details, please visit our web-site at www.simatelex.com.hk", "employment_types": ["Full Time", "Permanent"], "selling_points": [], "locations": ["Wan Chai"], "categories": ["Admin & HR", "Clerical / Admin Staff", "Others", "Property / Real Estate", "Others"], "post_time": "2022-01-17T02:55:24Z", "salary": {"currency": null, "max": null, "min": null, "period": null, "term": null}, "salary_visible": false, "title_keywords": ["project clerk"], "responsibilities": ["communication", "clerical support", "data entry"], "requirements": {"degrees": [], "majors": [], "languages": ["english", "chinese"], "language_level": ["good command"], "hard_skills": ["excel", "chinese word processing", "web", "ms word"], "soft_skills": ["communication", "negotiation skill", "responsible"], "languages_combined": [{"language": "english", "language_level": ["good command"]}, {"language": "chinese", "language_level": ["good command"]}]}, "experience_required": {"duration": ["at least 1 year"], "field": ["related", "relevant experience"]}}, {"job_id": "100003009052201", "location_code": "hk", "company": "Citybase Property Management Limited", "job_title": "Concierge Officer (Shopping Mall)", "description": "Responsibilities\n\nProvide customer service to occupants and visitors at concierge\nHandle telephone and walk-in enquiries\nProvide administrative support\n\n\u00a0Requirements\n\nDSE\u00a0or above, preferably with Certificate / Diploma in service management\nAt least 5\u00a0years relevant experience in Customer Service field\nFluent in spoken English, Cantonese and Mandarin\nProficient in MS word, Excel and Chinese Word Processing\nCustomer oriented with pleasant personality and good interpersonal skill\nMature, independent and able to work under pressure\n\nWe will offer attractive compensation package to the right candidate. Please send application enclosing resume stating career and salary history, expected salary and date of availability to The Human Resources Manager, Citybase Property Management Limited, Unit No.1, 6/F, Hampton Loft, 11 Hoi Fan Road, Tai Kok Tsui, Kowloon by fax at 2717 4717 or by clicking ''Apply Now'' (in Word format). Please quote the reference of the position you apply for in all correspondences.\n\nWe are an equal opportunity employer and welcome applications from all qualified candidates. Personal data collected will be treated in strictest confidence and handled confidentially by authorized personnel for recruitment-related purposes within the Group. Applicants not hearing from us within six weeks from the date of advertisement may consider their applications unsuccessful.", "employment_types": ["Full Time", "Permanent"], "selling_points": ["DSE or above", "At least 5 years exp in CS field", "Fluent in spoken English, Cantonese"], "locations": ["Tsuen Wan Area"], "categories": ["Sales, CS & Business Devpt", "Customer Service - Supervisor / Officer", "Property / Real Estate", "Property Management", "Others"], "post_time": "2022-01-17T16:21:06Z", "salary": {"currency": null, "max": null, "min": null, "period": "monthly", "term": null}, "salary_visible": false, "title_keywords": ["concierge officer"], "responsibilities": ["provide customer service", "provide administrative support"], "requirements": {"degrees": ["certificate", "diploma", "dse"], "majors": [], "languages": ["cantonese", "english", "chinese", "mandarin"], "language_level": ["proficient", "fluent"], "hard_skills": ["excel", "no", "chinese word processing", "word", "ms word"], "soft_skills": ["confidence", "independent", "mature", "interpersonal skill", "pleasant", "customer service", "work under pressure"], "languages_combined": [{"language": "cantonese", "language_level": ["fluent"]}, {"language": "english", "language_level": ["fluent"]}, {"language": "chinese", "language_level": ["proficient"]}, {"language": "mandarin", "language_level": ["fluent"]}]}, "experience_required": {"duration": ["at least 5 years"], "field": ["customer service", "relevant experience"]}}, {"job_id": "100003009053784", "location_code": "hk", "company": "Hysan Development Co Ltd", "job_title": "Administrator, Projects", "description": "Job Purpose\n\n\nProvide secretarial and general administrative support to the Projects Department.\n\nKey Responsibilities\n\nPerform secretarial and day-to-day administrative support to the Projects Department including appointments, meetings and associated facilities set-up, travel arrangement, typing, photocopying, scanning, maintaining diaries and contacts, etc.\nHandle incoming and outgoing correspondence and documents and their associated internal circulation.\nMaintain an effective correspondence and document central filing and record system for assigned projects.\nHandle administrative tasks within the department.\nPerform any other ad hoc duties as assigned.\n\nSkills, Qualifications and Experience Requirements\n\nHKDSE or above, with formal secretarial training\nAt least 3 years\u2019 relevant experience, preferably in real estate industry\nGood in document control, filing and collaboration, especially in electronic format\nProficient in MS Outlook, Word, Excel and PowerPoint\nResponsible, organized and able to work independently\nFluent in both spoken and written English and Chinese\n\nAn attractive remuneration package will be offered to the right candidate. \u00a0Interested parties please press \"Apply now\".\u00a0\n\n\nHysan is an equal opportunity employer. \u00a0All information collected will be kept in strict confidence and used solely for recruitment related purposes within the Hysan Group Companies.\n\nYou may get to know more about us through www.hysan.com.hk", "employment_types": ["Full Time", "Permanent"], "selling_points": ["Provide administrative support to Projects Dept.", "HKDSE or above, with 3 years\u2019 relevant exp", "5-day work, 12-day AL, Dental, Double Pay + Bonus"], "locations": ["Causeway Bay"], "categories": ["Admin & HR", "Clerical / Admin Staff", "Secretary", "Property / Real Estate", "Others"], "post_time": "2022-01-17T07:30:50Z", "salary": {"currency": null, "max": null, "min": null, "period": "monthly", "term": null}, "salary_visible": false, "title_keywords": ["administrator"], "responsibilities": ["scanning", "ad hoc duties", "control", "maintaining", "administrative support", "general administrative support", "diaries", "maintain", "travel arrangement", "administrative tasks"], "requirements": {"degrees": ["hkdse"], "majors": [], "languages": ["english", "chinese"], "language_level": ["fluent"], "hard_skills": ["excel", "typing", "powerpoint", "word", "outlook"], "soft_skills": ["outgoing", "organized", "work independently", "responsible"], "languages_combined": [{"language": "english", "language_level": ["fluent"]}, {"language": "chinese", "language_level": ["fluent"]}]}, "experience_required": {"duration": ["at least 3 years"], "field": ["relevant experience"]}}, {"job_id": "100003009054933", "location_code": "hk", "company": "Sun Hung Kai Properties Ltd", "job_title": "SENIOR RESEARCH MANAGER", "description": "Requirements:\n\n\nBachelor\u2019s degree in Statistics, Psychology, Sociology, Languages, Marketing or related disciplines\nMinimum 15 years\u2019 quantitative & qualitative research experience with at least 5 years at managerial level\nGood knowledge on property & retail markets and social analytics in HK & Mainland China\nStrong leadership skills, self-motivated, good work ethnic with positive attitude\nGood project management skills including planning & execution\nGood presentation and report writing skills\nProven English proficiency and fluent Putonghua\nProficiency with SPSS, Excel & PowerPoint. Knowledge on SQL and VBA an advantage\nWilling to work overtime and on public holidays, as well as under pressure\n\nResponsibilities:\n\n\nLead the research & fieldwork team to conduct quantitative, qualitative & social analytics research projects for Hong Kong, Mainland China & Overseas markets in a quality, timely and cost-effective manner\nLead & manage regular customer research reports, ad hoc & new projects and social & digital data analysis to provide findings, insights and recommendations for management or other business units of the Group\nLiaise and coordinate with external vendors/agencies to conduct quantitative and qualitative market research projects in Mainland China\n\nGood remuneration and attractive fringe benefits will be offered to the successful applicant. Interested parties please apply with full resume, present and expected salary, available date by clicking \"Apply Now\".\n\nWe are an equal opportunity employer and welcome applications from all qualified candidates. All personal data collected will be used for recruitment purpose only.\u00a0 Applicants not hearing from us within 3 months may consider their applications unsuccessful.\u00a0 All personal data collected will be destroyed within 24 months.", "employment_types": ["Full Time", "Permanent"], "selling_points": ["Lead research & fieldwork team for HK & PRC proj", "Manage social & digital data analysis", "Willing to work overtime and on public holidays"], "locations": ["Wan Chai"], "categories": ["Professional Services", "Business Analysis / Data Analysis", "Marketing / Public Relations", "Marketing - Market Research", "Property / Real Estate", "Others"], "post_time": "2022-01-17T14:23:18Z", "salary": {"currency": null, "max": null, "min": null, "period": null, "term": null}, "salary_visible": false, "title_keywords": ["manager"], "responsibilities": ["liaise", "cost", "management", "ad hoc", "research projects", "quality", "coordinate with", "market research", "data analysis", "reports"], "requirements": {"degrees": ["degree", "bachelor"], "majors": ["sociology", "psychology", "statistics", "related disciplines", "marketing"], "languages": ["putonghua", "english"], "language_level": ["proficiency", "fluent"], "hard_skills": ["excel", "vba", "powerpoint", "writing skills", "sql", "project management"], "soft_skills": ["self-motivated", "work overtime", "under pressure", "project management skills", "leadership skills", "writing skills", "positive attitude", "presentation"], "languages_combined": [{"language": "putonghua", "language_level": ["fluent", "proficiency"]}, {"language": "english", "language_level": ["proficiency"]}]}, "experience_required": {"duration": ["at least 5 years", "minimum 15 years"], "field": ["managerial", "research"]}}, {"job_id": "100003009054942", "location_code": "hk", "company": "Sun Hung Kai Properties Ltd", "job_title": "MANAGER / ASSISTANT MANAGER \u2013 OFFICE LEASING", "description": "Requirements:\n\n\nBachelor's degree, preferably in marketing or business administration\n6 - 10 years' experience in office leasing with major developers\nGood understanding of the office leasing market\nFamiliar with leasing procedures and relevant legal documentation\nStrong interpersonal skills and able to communicate well with business partners\nProven English proficiency and good Putonghua will be an advantage\nPro-active attitude and good team player\n\n\nResponsibilities:\n\n\nResponsible for handling daily leasing enquiries, lease negotiation, marketing, tenancy administration, co-ordination with property management and other related duties for a portfolio of office premises\n\n(Candidates with less experience will be considered for more junior positions.)\n\nGood remuneration and attractive fringe benefits will be offered to the successful applicant. Interested parties please apply with full resume, present and expected salary, available date by clicking \u201cApply Now\u201d.\n\nFor further information, please visit our company website: http://www.shkp.com/.\n\n\nWe are an equal opportunity employer and welcome applications from all qualified candidates. All personal data collected will be used for recruitment purpose only.\u00a0 Applicants not hearing from us within 3 months may consider their applications unsuccessful.\u00a0 All personal data collected will be destroyed within 24 months.", "employment_types": ["Full Time", "Permanent"], "selling_points": ["Bachelor degree with exp in office leasing", "Office leasing, tenancy administration, marketing", "Co-ordination with property management"], "locations": ["Wan Chai"], "categories": ["Marketing / Public Relations", "Marketing - Marketing Communication", "Property / Real Estate", "Property Management", "Others"], "post_time": "2022-01-17T14:33:35Z", "salary": {"currency": null, "max": null, "min": null, "period": null, "term": null}, "salary_visible": false, "title_keywords": ["assistant manager", "manager"], "responsibilities": ["management", "administration"], "requirements": {"degrees": ["degree", "bachelor"], "majors": ["marketing", "business administration"], "languages": ["putonghua", "english"], "language_level": ["advantage", "proficiency", "good"], "hard_skills": ["documentation"], "soft_skills": ["good team player", "interpersonal skills", "pro-active"], "languages_combined": [{"language": "putonghua", "language_level": ["good", "proficiency", "advantage"]}, {"language": "english", "language_level": ["proficiency", "advantage"]}]}, "experience_required": {"duration": ["6 - 10 years"], "field": []}}, {"job_id": "100003009054028", "location_code": "hk", "company": "Citybase Property Management Limited", "job_title": "Property Officer / Assistant Property Officer", "description": "Responsibilities\n\nAssist the Property Manager to oversee and monitor the day-to-day property management functions\n\nRequirements\n\nDiploma or above in Property Management or related disciplines\nMinimum 3 years solid experience in property management\nGood command of both written and spoken English and Chinese\nStrong leadership, communication and interpersonal skills\nAble to work under pressure and independently\nCandidates with less experience will be considered as Assistant Property Officer\n\nWe will offer attractive compensation package to the right candidate. Please send application enclosing resume stating career and salary history, expected salary and date of availability to The Human Resources Manager, Citybase Property Management Limited, Unit No.1, 6/F, Hampton Loft, 11 Hoi Fan Road, Tai Kok Tsui, Kowloon by fax at 2717 4717 or by clicking ''Apply Now'' (in Word format). Please quote the reference of the position you apply for in all correspondences.\n\nWe are an equal opportunity employer and welcome applications from all qualified candidates. Personal data collected will be treated in strictest confidence and handled confidentially by authorized personnel for recruitment-related purposes within the Group. Applicants not hearing from us within six weeks from the date of advertisement may consider their applications unsuccessful.", "employment_types": ["Full Time", "Permanent"], "selling_points": ["Diploma holder or above in Property Mgt", "Minimum 3 years experience in property management", "Good command of both spoken & written English"], "locations": ["Tin Shui Wai"], "categories": ["Property / Real Estate", "Property Consultancy", "Property Management", "Others"], "post_time": "2022-01-17T09:50:04Z", "salary": {"currency": null, "max": null, "min": null, "period": null, "term": null}, "salary_visible": false, "title_keywords": ["property officer", "assistant property officer"], "responsibilities": ["management", "monitor"], "requirements": {"degrees": ["diploma or above"], "majors": ["related disciplines"], "languages": ["english", "chinese"], "language_level": ["good command"], "hard_skills": ["no", "word"], "soft_skills": ["independently", "confidence", "communication and interpersonal skills", "leadership", "work under pressure"], "languages_combined": [{"language": "english", "language_level": ["good command"]}, {"language": "chinese", "language_level": ["good command"]}]}, "experience_required": {"duration": ["minimum 3 years"], "field": ["management"]}}, {"job_id": "100003009056355", "location_code": "hk", "company": "\u6607\u6377\u7ba1\u7406\u670d\u52d9\u6709\u9650\u516c\u53f8", "job_title": "\u517c\u8077\u4fdd\u5b89\u54e1", "description": "\u8077\u8cac :\u4e00\u822c\u4fdd\u5b89\u5de5\u4f5c\n\u8cc7\u6b77 :\u4e2d\u4e00\u7a0b\u5ea6; 1\u5e74\u7d93\u9a57; \u4e00\u822c\u7cb5\u8a9e\u512a\u5148; \u4e00\u822c\u666e\u901a\u8a71; \u4e00\u822c\u82f1\u8a9e; \u61c2\u8b80\u5beb\u4e2d\u6587; \u7565\u61c2\u8b80\u5beb\u82f1\u6587; \u6301\u6709\u4fdd\u5b89\u57f9\u8a13\u8ab2\u7a0b\u8b49\u66f8(QAS); \u6301\u6709\u4fdd\u5b89\u4eba\u54e1\u8a31\u53ef\u8b49\n\u5f85\u9047 :\u6bcf\u65e5$450.00, \u4e0a\u53487\u6642\u81f3\u4e0b\u53483\u6642\u534a/\u4e0b\u53483\u6642\u81f3\u4e0b\u534811\u6642\u534a/\u4e0b\u534811\u6642\u81f3\u4e0a\u53487\u6642\u534a, \u6bcf\u9031\u5de5\u4f5c4\u5929\u81f36\u5929,\u8f2a\u4f11, \u6bcf\u5929\u5de5\u4f5c 8.5 \u5c0f\u6642\n\u7533\u8acb\u9808\u77e5 :\u6c42\u8077\u8005\u53ef\u6309 APPLY NOW\u7533\u8acb\u6216\u81f4\u96fb28993723\u8207\u6607\u6377\u7ba1\u7406\u670d\u52d9\u6709\u9650\u516c\u53f8\u90ed\u5148\u751f\u806f\u7d61\u3002", "employment_types": ["Part Time"], "selling_points": ["\u4e00\u822c\u4fdd\u5b89\u5de5\u4f5c", "\u4e2d\u4e00\u7a0b\u5ea6; 1\u5e74\u7d93\u9a57", "\u4e00\u822c\u7cb5\u8a9e\u512a\u5148"], "locations": ["North Point"], "categories": ["Property / Real Estate", "Property Management", "Others", "Others", "Security / Safety Control"], "post_time": "2022-01-18T04:03:45Z", "salary": {"currency": null, "max": null, "min": null, "period": "hourly", "term": null}, "salary_visible": false, "title_keywords": [], "responsibilities": [], "requirements": {"degrees": [], "majors": [], "languages": [], "language_level": [], "hard_skills": [], "soft_skills": [], "languages_combined": []}, "experience_required": {"duration": [], "field": []}}, {"job_id": "100003009056387", "location_code": "hk", "company": "\u6607\u6377\u7ba1\u7406\u670d\u52d9\u6709\u9650\u516c\u53f8", "job_title": "\u517c\u8077\u4fdd\u5b89\u54e1", "description": "\u8077\u8cac :\u8ca0\u8cac\u4e00\u822c\u5c4b\u82d1\u4fdd\u5b89\u5de5\u4f5c\u53ca\u7368\u7acb\u8655\u7406\u4e8b\u4ef6\n\u8cc7\u6b77 :\u6c92\u6709\u5b78\u6b77\u8981\u6c42; 1\u5e74\u7d93\u9a57; \u826f\u597d\u7cb5\u8a9e; \u4e00\u822c\u666e\u901a\u8a71; \u4e00\u822c\u82f1\u8a9e; \u61c2\u8b80\u5beb\u4e2d\u6587; \u7565\u61c2\u8b80\u5beb\u82f1\u6587; \u6301\u6709\u4fdd\u5b89\u57f9\u8a13\u8ab2\u7a0b\u8b49\u66f8(QAS); \u6301\u6709\u4fdd\u5b89\u4eba\u54e1\u8a31\u53ef\u8b49\n\u5f85\u9047 :\u6bcf\u65e5$650.00, \u4e0a\u53487\u6642\u81f3\u4e0b\u53487\u6642\u6216\u4e0b\u53487\u6642\u81f3\u4e0a\u53487\u6642, \u6bcf\u9031\u5de5\u4f5c1\u5929\u81f36\u5929,\u8f2a\u4f11, \u6bcf\u5929\u5de5\u4f5c 12 \u5c0f\u6642\n\u7533\u8acb\u9808\u77e5 :\u6c42\u8077\u8005\u53ef\u6309 APPLY NOW\u7533\u8acb\u6216\u81f4\u96fb26522362\u8207\u6607\u6377\u7ba1\u7406\u670d\u52d9\u6709\u9650\u516c\u53f8\u6881\u5148\u751f\u806f\u7d61\u3002", "employment_types": ["Part Time"], "selling_points": ["\u8ca0\u8cac\u4e00\u822c\u5c4b\u82d1\u4fdd\u5b89\u5de5\u4f5c", "\u6c92\u6709\u5b78\u6b77\u8981\u6c42; 1\u5e74\u7d93\u9a57", "\u6301\u6709\u4fdd\u5b89\u4eba\u54e1\u8a31\u53ef\u8b49"], "locations": ["Tai Po Area"], "categories": ["Property / Real Estate", "Property Management", "Others", "Others", "Security / Safety Control"], "post_time": "2022-01-18T04:08:06Z", "salary": {"currency": null, "max": null, "min": null, "period": "hourly", "term": null}, "salary_visible": false, "title_keywords": [], "responsibilities": [], "requirements": {"degrees": [], "majors": [], "languages": [], "language_level": [], "hard_skills": [], "soft_skills": [], "languages_combined": []}, "experience_required": {"duration": [], "field": []}}, {"job_id": "100003009053791", "location_code": "hk", "company": "Hysan Development Co Ltd", "job_title": "Property Officer - Commercial Properties", "description": "\u200b\u200b\u200b\u200b\u200b\u200b\u200bJob Purpose\nAssisting the Senior Property Manager / Property Manager for overall management duties of one or more properties within the Company's portfolios.\n\nKey Responsibilities\n\n\nSupport the Senior Property Manager / Property Manager in executing various strategy and operational policies / procedures in assigned portfolios.\nCoordinate for the procurement of services / materials / equipment.\nMonitor the day-to-day operation for property management, technical services, security.\nMonitor / coordinate repair & maintenance work, improvement projects, interior fitting out work / reinstatement work.\nAssist in property handover / take back.\nConstantly review and monitor the provision of tenant support service.\nAssist in preparing management budgets.\nAssist in monitoring income and expenditure of the building accounts.\nAssist in staff performance monitoring.\nPerform all other duties as assigned by the seniors.\n\nSkills, Qualifications and Experience Requirements\n\n\nDegree holder, preferably in Property Management or related discipline\nMinimum 3 years\u2019 experience in property management in leased properties\nPossess good supervisory skill, interpersonal and communication skill\nSelf-motivated with strong sense of responsibilities\nFluent in both spoken and written English and Chinese\n\nCandidate with less experience will be considered as Assistant Officer, Property Management.\n\n\n\nAn attractive remuneration package will be offered to the right candidate. \u00a0Interested parties please press \"Apply now\".\n\nFor enquiries, please call/whatsapp:\u00a09760 3380.\n\nHysan is an equal opportunity employer.\u00a0 All information collected will be kept in strict confidence and used solely for recruitment related purposes within the Hysan Group Companies.\n\n\nYou may get to know more about us through\u00a0www.hysan.com.hk\n", "employment_types": ["Full Time", "Permanent"], "selling_points": ["Monitor the day-to-day operation", "Degree Holder with 2 years\u2019 PM experience", "5-day work, 14-day AL, Dental, Double Pay + Bonus"], "locations": ["Causeway Bay"], "categories": ["Property / Real Estate", "Property Management", "Others"], "post_time": "2022-01-17T07:30:52Z", "salary": {"currency": null, "max": null, "min": null, "period": "monthly", "term": null}, "salary_visible": false, "title_keywords": ["property officer"], "responsibilities": ["budgets", "management", "maintenance", "other duties", "policies", "review", "procedures", "monitor", "monitoring", "coordinate", "communication", "repair", "executing", "day-to-day operation"], "requirements": {"degrees": ["degree holder"], "majors": [], "languages": ["english", "chinese"], "language_level": ["fluent"], "hard_skills": ["maintenance"], "soft_skills": ["self-motivated", "communication skill", "interpersonal", "sense of responsibilities"], "languages_combined": [{"language": "english", "language_level": ["fluent"]}, {"language": "chinese", "language_level": ["fluent"]}]}, "experience_required": {"duration": ["minimum 3 years"], "field": ["management"]}}, {"job_id": "100003009038531", "location_code": "hk", "company": "Kai Shing Management Services Ltd", "job_title": "Property Assistant (Tuen Mun)", "description": "What will you do?\n\n\n\nHandle clerical works, including data input, filing,\u00a0preparing report,\u00a0etc.\nProvide administrative support to the management team\nAssist in promotion activities and special events\nPerform ad hoc duties assigned\u00a0from the management team\n\nDo you have a right\u00a0profile?\n\nF.5 or above with at least 2 years of relevant experience\nCertificate in Property Management is preferred\nGood interpersonal and communication skill\nGood command of both Chinese and English, spoken Mandarin is an advantage\nProficient in MS Word, Excel and Chinese Word Processing\nAble to work independently with strong sense of responsibility\n\nWhat do we offer?\n\nAttractive remuneration package\nGreat promotion ladder\nReferral reward\nMedical benefit\nPaid marriage leave, birthday leave, well-being leave and annual leave\nEducation subsidy\nChildren scholarship\nCompany trip\n\nHow to apply?\n\nInterested parties, please apply once with application quoting job reference number, detailed resume, contact telephone number and expected salary by:\n\nClicking the \u201cApply Now\u201d button\nMail to:\u00a0Human Resources Department,\u00a0Unit 301-303, 3/F, Apec Plaza, 49 Hoi Yuen Road, Kwun Tong, Hong Kong\nFax to: (852) 2827 8608\nCall: (852)\u00a03703 5460\n\n(Attached resume should be in MS Word for Windows)\n\n\n(Data collected would be used for recruitment purpose only)", "employment_types": ["Full Time", "Permanent"], "selling_points": ["Form 5 or above with Certificate in Property Mgt", "At least 2 years relevant experience", "Able to work under pressure"], "locations": ["Tuen Mun Area"], "categories": ["Property / Real Estate", "Property Management", "Others", "Others", "Security / Safety Control"], "post_time": "2022-01-11T07:15:27Z", "salary": {"currency": null, "max": null, "min": null, "period": "monthly", "term": null}, "salary_visible": false, "title_keywords": ["property assistant"], "responsibilities": ["ad hoc duties", "management team", "management", "data input", "communication", "provide administrative support", "report"], "requirements": {"degrees": ["certificate"], "majors": [], "languages": ["english", "chinese", "mandarin"], "language_level": ["advantage", "good command", "proficient"], "hard_skills": ["excel", "chinese word processing", "ms word"], "soft_skills": ["work independently", "communication skill", "interpersonal", "sense of responsibility"], "languages_combined": [{"language": "english", "language_level": ["good command"]}, {"language": "chinese", "language_level": ["good command", "proficient"]}, {"language": "mandarin", "language_level": ["advantage", "good command"]}]}, "experience_required": {"duration": ["at least 2 years"], "field": ["relevant experience"]}}, {"job_id": "100003009048396", "location_code": "hk", "company": "Henderson Land Development Company Limited", "job_title": "PROPERTY OFFICER", "description": "Ref. No.: JDB/GWM/PO\n\nOur subsidiary, Goodwill Management Limited, continuously dedicates to providing excellent and valued-added property management services for our landlords and customers and now invites high\u00a0caliber\u00a0candidates for the position of :-\n\nDegree holder in any discipline\nMinimum 2 years' experience in Property Management\nGood command of English and Chinese\nShift duty is required\u00a0\u00a0\nCandidates with less experience will be considered for the post of Assistant Property Officer\n\nAttractive salary and fringe benefits will be offered to the successful candidates. Please apply with full resume by mail to\u00a0Personnel Section, Goodwill Management Limited, 9/F., Golden Centre, 188 Des Voeux Road C., Hong Kong\u00a0or by fax at\u00a02530 2528\u00a0or\u00a0visit our homepage at\u00a0http://www.hld.com/management/goodwill/\u00a0or\u00a0by\u00a0clicking \"Apply Now\".\n\n(Please quote the ref. no. on letter)\n\nPersonal data provided by job applicants will be used for recruitment purpose only.", "employment_types": ["Full Time", "Permanent"], "selling_points": ["Medical Allowance", "Education Allowance", "MPF"], "locations": ["Not Specified"], "categories": ["Property / Real Estate", "Property Management", "Others", "Others", "Others"], "post_time": "2022-01-14T06:28:04Z", "salary": {"currency": null, "max": null, "min": null, "period": "monthly", "term": null}, "salary_visible": false, "title_keywords": ["property officer"], "responsibilities": ["management"], "requirements": {"degrees": ["degree holder"], "majors": [], "languages": ["english", "chinese"], "language_level": ["good command"], "hard_skills": ["no"], "soft_skills": [], "languages_combined": [{"language": "english", "language_level": ["good command"]}, {"language": "chinese", "language_level": ["good command"]}]}, "experience_required": {"duration": ["minimum 2 years"], "field": ["management"]}}, {"job_id": "100003009038409", "location_code": "hk", "company": "Kai Shing Management Services Ltd", "job_title": "Property Assistant (Tsing Yi)", "description": "What will you do?\n\n\n\nHandle clerical works, including data input, filing,\u00a0preparing report,\u00a0etc.\nProvide administrative support to the management team\nAssist in promotion activities and special events\nPerform ad hoc duties assigned\u00a0from the management team\n\nDo you have a right\u00a0profile?\n\nF.5 or above with at least 2 years of relevant experience\nCertificate in Property Management is preferred\nGood interpersonal and communication skill\nGood command of both Chinese and English, spoken Mandarin is an advantage\nProficient in MS Word, Excel and Chinese Word Processing\nAble to work independently with strong sense of responsibility\n\nWhat do we offer?\n\nAttractive remuneration package\nGreat promotion ladder\nReferral reward\nMedical benefit\nPaid marriage leave, birthday leave, well-being leave and annual leave\nEducation subsidy\nChildren scholarship\nCompany trip\n\nHow to apply?\n\nInterested parties, please apply once with application quoting job reference number, detailed resume, contact telephone number and expected salary by:\n\nClicking the \u201cApply Now\u201d button\nMail to:\u00a0Human Resources Department,\u00a0Unit 301-303, 3/F, Apec Plaza, 49 Hoi Yuen Road, Kwun Tong, Hong Kong\nFax to: (852) 2827 8608\nCall: (852)\u00a03703 5460\n\n(Attached resume should be in MS Word for Windows)\n\n\n(Data collected would be used for recruitment purpose only)", "employment_types": ["Full Time", "Permanent"], "selling_points": ["Form 5 or above with Certificate in Property Mgt", "At least 2 years relevant experience", "Able to work under pressure"], "locations": ["Tsing Yi"], "categories": ["Property / Real Estate", "Property Management", "Others", "Others", "Security / Safety Control"], "post_time": "2022-01-11T16:01:44Z", "salary": {"currency": null, "max": null, "min": null, "period": "monthly", "term": null}, "salary_visible": false, "title_keywords": ["property assistant"], "responsibilities": ["ad hoc duties", "management team", "management", "data input", "communication", "provide administrative support", "report"], "requirements": {"degrees": ["certificate"], "majors": [], "languages": ["english", "chinese", "mandarin"], "language_level": ["advantage", "good command", "proficient"], "hard_skills": ["excel", "chinese word processing", "ms word"], "soft_skills": ["work independently", "communication skill", "interpersonal", "sense of responsibility"], "languages_combined": [{"language": "english", "language_level": ["good command"]}, {"language": "chinese", "language_level": ["good command", "proficient"]}, {"language": "mandarin", "language_level": ["advantage", "good command"]}]}, "experience_required": {"duration": ["at least 2 years"], "field": ["relevant experience"]}}, {"job_id": "100003009044979", "location_code": "hk", "company": "Harbour City Estates Ltd", "job_title": "\u517c\u8077\u7ba1\u696d\u7763\u5bdf PART-TIME BUILDING INSPECTOR (\u6642\u85aaHK$70)", "description": "\u8077\u8cac\uff1a\n\n\u8ca0\u8cac\u5de1\u8996\u5546\u5ec8\u53ca\u5354\u52a9\u57f7\u884c\u65e5\u5e38\u5546\u5ec8 / \u505c\u8eca\u5834\u7ba1\u7406\u4e8b\u52d9\n\u53ef\u65bc\u9031\u672b\u53ca\u516c\u773e\u5047\u671f\u5de5\u4f5c\u70ba\u4f73\n\n\u5165\u8077\u8981\u6c42\uff1a\n\n\u4e2d\u4e94\u7a0b\u5ea6\n\u4e00\u5e74\u6216\u4ee5\u4e0a\u7ba1\u7406\u5927\u578b\u5546\u5ec8 / \u9152\u5e97 / \u5546\u696d\u6a13\u5b87\u8a2d\u65bd\u5de5\u4f5c\u7d93\u9a57\n\u5177\u826f\u597d\u5ba2\u6236\u670d\u52d9\u614b\u5ea6\n\u826f\u597d\u7cb5\u8a9e\u3001\u82f1\u8a9e\u53ca\u666e\u901a\u8a71\n\n\u6b61\u8fce\u6295\u5bc4\u500b\u4eba\u5c65\u6b77\u81f3\u516c\u53f8\u96fb\u90f5\uff08\u8acb\u5217\u660e\u7533\u8acb\u8077\u4f4d\uff09\u6216\n\u50b3\u771f\u81f3 2118 8689\n\n\n(\u7533\u8acb\u4eba\u63d0\u4f9b\u4e4b\u5168\u90e8\u8cc7\u6599\u7d55\u5c0d\u4fdd\u5bc6\u53ca\u53ea\u4f5c\u62db\u8058\u4e4b\u7528)", "employment_types": ["Part Time"], "selling_points": ["\u8ca0\u8cac\u5de1\u8996\u5546\u5ec8\u53ca\u5354\u52a9\u57f7\u884c\u65e5\u5e38\u5546\u5ec8 / \u505c\u8eca\u5834\u7ba1\u7406\u4e8b\u52d9", "\u4e2d\u4e94\u7a0b\u5ea6", "\u5177\u826f\u597d\u5ba2\u6236\u670d\u52d9\u614b\u5ea6"], "locations": ["Tsim Sha Tsui"], "categories": ["Property / Real Estate", "Property Management", "Others", "Others", "Security / Safety Control"], "post_time": "2022-01-15T03:49:27Z", "salary": {"currency": null, "max": null, "min": null, "period": null, "term": null}, "salary_visible": false, "title_keywords": ["building inspector"], "responsibilities": [], "requirements": {"degrees": [], "majors": [], "languages": [], "language_level": [], "hard_skills": [], "soft_skills": [], "languages_combined": []}, "experience_required": {"duration": [], "field": []}}, {"job_id": "100003009049510", "location_code": "hk", "company": "Jones Lang LaSalle Ltd", "job_title": "Assistant Facilities Officer", "description": "Assistant Facilities Officer\n\nAbout JLL \u2013\n\nWe\u2019re JLL. We\u2019re a professional services and investment management firm specializing in real estate. As a Fortune 500 company, we help real estate owners, occupiers and investors achieve their business ambitions.\n\nIf you\u2019re looking to step up your career, JLL is the perfect professional home. With us, you\u2019ll have a chance to innovate with the world\u2019s leading businesses, put that expertise into action on landmark projects, and work on game-changing real estate initiatives. You\u2019ll also make long-lasting professional connections and be inspired by the best. We\u2019re focused on opportunity and want to help you make the most of yours. Achieve your ambitions - join us at JLL!\n\nAbout the role:\n\nAssistant Facilities Officer will be the gatekeeper of the site, he/she will be working closely with our security guards, receptionists and tea attendants, overseeing them and ensuring they carry out all works to a high standard to the client site. He/she will be looking after the relationship with all stakeholders \u2013 management, clients, vendors and landlords.\n\nWhat this job involves:\n\nHow can you help make employees and visitors alike love our office? You\u2019ll do so by arranging for regular preventative maintenance and repairs for our facilities. Scheduling for regular cleaning services and ensuring all office equipment are in good working order are a few of the tasks you\u2019ll do to spruce up the office.\nYou\u2019ll keep an eye out for potential emergencies and carry out steps for managing such situations. You\u2019ll also perform established escalation and incident reporting procedures should such an event take place. Being on the lookout for opportunities to reduce costs and improve our operational standards should also come instinctively to you.\nHow important is security to you?\u00a0 Security is a tall order and calls for an all-hands-on-deck approach. As such, we are always on the lookout for people for whom attention to security details comes naturally. In this role, you\u2019ll help give an extra layer of protection by doing regular checks of our CCTV systems to review the need for maintenance and repairs. You\u2019ll oversee visitor access\u2014clients, contractors, vendors\u2014and maintain logs and filing work of such information on a regular basis. You\u2019ll not only be the \u201cgatekeeper,\u201d but also the \u201cface of JLL,\u201d acting as a back-up receptionist as needed.\nAs you perform a juggling act between helping safeguard our premises and giving a warm reception to our guests, you\u2019ll be working closely with our security guards, receptionists and tea attendants, overseeing them and ensuring they carry out all work to a high standard.\nEvery business aims for client satisfaction\u2014but we take it up a notch! If you can take in the same passion for looking after our relationship with all our stakeholders\u2014management, clients, vendors, landlords\u2014we\u2019ll be more than happy to work with you. Because in this role, you\u2019ll be a vital element in keeping our communication lines with them open and strong. One way to do so is to ensure everyone follows the established key operating procedures to achieve standards. Another way is to schedule regular meetings to understand stakeholder\u2019s needs.\n\nSound like you? To apply you will have:\n\nDo you have more than two years\u2019 experience in facilities management? Are you driven by service excellence? Are you knowledgeable in budgeting and facilities security? We\u2019d love to speak with you!\nExcellent communication skills are vital\u2014both spoken and written\u2014as we\u2019ll expect you to work independently in cascading high-level communications and boosting staff/client satisfaction. And if you know both the English and Chinese languages, that would be super! If you think you possess all these, then let\u2019s work together and explore opportunities.\n\nWhat you can expect from us\n\nWe\u2019re an entrepreneurial, inclusive culture. We succeed together - across the desk and around the globe. We believe the best inspire the best, so we invest in supporting each other, learning together and celebrating our success.\n\nOur Total Rewards program reflects our commitment to helping you achieve your ambitions in career, recognition, well-being, benefits and pay. We\u2019ll offer you a competitive salary and benefits package.\n\nWith us, you\u2019ll develop your strengths and enjoy a career full of varied experiences. We can\u2019t wait to see where your ambitions take you at JLL.\n\n\nApply today!", "employment_types": ["Full Time", "Permanent"], "selling_points": ["Facilities Management", "Several Openings", "Excellent Opportunities"], "locations": ["Others"], "categories": ["Property / Real Estate", "Property Management", "Others"], "post_time": "2022-01-14T08:46:28Z", "salary": {"currency": null, "max": null, "min": null, "period": "monthly", "term": null}, "salary_visible": false, "title_keywords": ["assistant facilities officer"], "responsibilities": ["reporting", "management", "maintenance", "budgeting", "systems", "procedures", "review", "communication", "scheduling", "maintain", "schedule", "cleaning", "costs"], "requirements": {"degrees": [], "majors": [], "languages": ["english", "chinese"], "language_level": [], "hard_skills": ["tea", "maintenance", "cctv", "make", "facilities management"], "soft_skills": ["communication skills", "work independently", "focused", "passion for", "communication", "hands-on", "learning", "driven"], "languages_combined": [{"language": "english", "language_level": []}, {"language": "chinese", "language_level": []}]}, "experience_required": {"duration": ["two years"], "field": ["management", "security"]}}, {"job_id": "100003009056363", "location_code": "hk", "company": "\u6607\u6377\u7ba1\u7406\u670d\u52d9\u6709\u9650\u516c\u53f8", "job_title": "\u4e8c\u7d1a\u9ad8\u7d1a\u4fdd\u5b89\u54e1(\u65e5\u66f4)", "description": "\u8077\u8cac :\u8ca0\u8cac\u4e00\u822c\u5c4b\u82d1\u4fdd\u5b89\u5de5\u4f5c\uff0c\u8655\u7406\u4e00\u822c\u7a81\u767c\u4e8b\u4ef6\u3002\n\u8cc7\u6b77 :\u5c0f\u516d\u7a0b\u5ea6; \u4e00\u822c\u7cb5\u8a9e; \u7565\u61c2\u8b80\u5beb\u4e2d\u6587; \u6301\u6709\u4fdd\u5b89\u57f9\u8a13\u8ab2\u7a0b\u8b49\u66f8(QAS); \u6301\u6709\u4fdd\u5b89\u4eba\u54e1\u8a31\u53ef\u8b49; \u5177\u826f\u597d\u6e9d\u901a\u6280\u5de7\u53ca\u5ba2\u6236\u670d\u52d9\u614b\u5ea6\n\u5f85\u9047 :\u6bcf\u6708$15,450, \u6709\u6bcf\u6708\u52e4\u5de5\u734e\u91d1$1000 \u53ca\u6649\u5347\u6a5f\u6703 (\u8996\u4e4e\u5de5\u4f5c\u8868\u73fe\u800c\u5b9a), \u4e0a\u53486\u664245\u5206\u81f3\u4e0b\u53486\u664245\u5206, \u6bcf\u9031\u5de5\u4f5c6\u5929,\u8f2a\u4f11, \u6bcf\u5929\u5de5\u4f5c 12 \u5c0f\u6642\n\u7533\u8acb\u9808\u77e5 :\u6c42\u8077\u8005\u53ef\u6309 APPLY NOW\u7533\u8acb\u6216\u81f4\u96fb24575061\u8207\u6607\u6377\u7ba1\u7406\u670d\u52d9\u6709\u9650\u516c\u53f8\u5f35\u5c0f\u59d0\u806f\u7d61\u3002", "employment_types": ["Full Time"], "selling_points": ["\u8ca0\u8cac\u4e00\u822c\u5c4b\u82d1\u4fdd\u5b89\u5de5\u4f5c", "\u6301\u6709\u4fdd\u5b89\u57f9\u8a13\u8ab2\u7a0b\u8b49\u66f8(QAS)", "\u6301\u6709\u4fdd\u5b89\u4eba\u54e1\u8a31\u53ef\u8b49"], "locations": ["Tuen Mun Area"], "categories": ["Property / Real Estate", "Property Management", "Others", "Others", "Security / Safety Control"], "post_time": "2022-01-18T04:05:12Z", "salary": {"currency": null, "max": null, "min": null, "period": "monthly", "term": null}, "salary_visible": false, "title_keywords": [], "responsibilities": [], "requirements": {"degrees": [], "majors": [], "languages": [], "language_level": [], "hard_skills": [], "soft_skills": [], "languages_combined": []}, "experience_required": {"duration": [], "field": []}}, {"job_id": "100003009052547", "location_code": "hk", "company": "Crown Worldwide (HK) Ltd", "job_title": "Administration Assistant", "description": "Maintain the safety in the designated property, monitor and prevent damage, hazards and breaches of security, report to Building Supervisor directly.\n\nKey Responsibilities\n\n-\u00a0Perform office administrative duties and back up reception duties including handling phone calls and greeting / serving clients\n-\u00a0Monitor maintenance and repair services of all office equipment, facilities and furniture\n-\u00a0Provide full spectrum of office administrative services including but not limited to office management, supplies & procurement, facility management, etc.\n-\u00a0Assist to draft both English and Chinese correspondence.\n-\u00a0Assist in organizing function i.e. Christmas Party, Annual Dinner, etc.\n-\u00a0Participate ad-hoc projects as assigned by Manager\n\n\n\u00a0Professional Skills & Qualifications\n\n-\u00a0Diploma or above in Facility Management and/or Administrative Management or related studies.\n-\u00a0Proficiency in MS Word, Excel, Power Point and Chinese Word Processing.\n\n\nWhat we offer\n- Work in a friendly team & role\n- Offering development path\n- 15 annual leave\n- Volunteer Leave\n- Wedding leave, maternity leave,\u00a0bereavement leave, birthday leave\n- Dental insurance\n- Medical insurance\n- Life insurance\n- Performance bonus\n\n\u00a0\nCompany Values\u00a0\n\n\n\u00a0At Crown we pride ourselves with the quality we deliver and values we stand by.\n\nWe are CARING about people and their experience\nAlways DETERMINED to do our best and to always keep improving\n\u00a0We are genuinely THERE when our customers and colleagues need us\n\u00a0We encourage the SHARING of knowledge amongst each other\n\u00a0We continuously remain OPEN-MINDED to stay innovative\n\nIntroduction to Crown\n\nhttps://www.youtube.com/watch?v=OJ2NMk90g0s&t=2s\n\nWorking at Crown\n\nhttps://www.youtube.com/watch?v=9hcb8QXumGA\n\nEqual Employment Opportunity\u00a0\u00a0\n\nCrown is an equal opportunities employer.\u00a0 We are committed to providing equal employment opportunities to all qualified individuals without regard to race, religion, sex, pregnancy, national origin, age, physical and mental disability,\u00a0marital status, sexual orientation, gender identity, military/veteran status, or any other characteristic protected by law.\n\nCrown welcomes applications from all suitably qualified candidates eligible to live and work in the designated geographical region.\u00a0 We are committed to diversity, and to employee well-being, engagement and development.\n\nAll information gathered will be treated in strict confidence and solely used for recruitment purposes. Personal data of unsuccessful applicant will be destroyed within 24 months.", "employment_types": ["Full Time"], "selling_points": [], "locations": ["Shatin Area"], "categories": ["Property / Real Estate", "Others"], "post_time": "2022-01-17T03:23:15Z", "salary": {"currency": null, "max": null, "min": null, "period": "monthly", "term": null}, "salary_visible": false, "title_keywords": ["administration assistant"], "responsibilities": ["management", "maintenance", "monitor", "repair", "maintain", "administrative duties", "ad-hoc projects", "phone calls", "report"], "requirements": {"degrees": ["diploma or above"], "majors": [], "languages": ["english", "chinese"], "language_level": ["proficiency"], "hard_skills": ["excel", "chinese word processing", "maintenance", "power point", "ms word"], "soft_skills": [], "languages_combined": [{"language": "english", "language_level": []}, {"language": "chinese", "language_level": ["proficiency"]}]}, "experience_required": {"duration": [], "field": []}}, {"job_id": "100003009044800", "location_code": "hk", "company": "Hong Yip Service Company Limited", "job_title": "Estate Assistant (5-day work) - Hung Hom", "description": "Job Responsibilities:\nHandle general customers' enquiries\nPerform clerical duties related to property management\nProvide support on ad-hoc assignments\u00a0\nJob Requirements:\nForm 5 or above or qualification equivalent to\u00a0Qualifications Framework Level 3\nMinimum 1 year's customer service experience, preferably in property management industry\nPleasant personality with good communication skills\nGood command of both spoken and written Chinese and English\nComputer literate in Ms Word, Excel and Chinese Word Processing\n\nWe provide attractive remuneration package and fringe benefits for the right candidate.\u00a0 Interested parties please send detailed resume with current & expected salaries via \u201cApply Now\u201d or send in your application through the Careers section in our Corporate Website: http://www.hongyip.com/Careers.\n\nHong Yip is an Equal Opportunity Employer.\u00a0 Personal data collected will be used for recruitment purpose only.\u00a0", "employment_types": ["Full Time", "Permanent"], "selling_points": ["Wholly owned subsidiary of Sun Hung Kai Properties", "Form 5 or above or qualification equivalent", "Minimum 1 year's customer service experience"], "locations": ["Not Specified"], "categories": ["Admin & HR", "Clerical / Admin Staff", "Property / Real Estate", "Property Management", "Others"], "post_time": "2022-01-13T18:55:03Z", "salary": {"currency": null, "max": null, "min": null, "period": "monthly", "term": null}, "salary_visible": false, "title_keywords": ["assistant"], "responsibilities": ["ad-hoc assignments", "management", "provide support"], "requirements": {"degrees": ["form 5 or above"], "majors": [], "languages": ["english", "chinese"], "language_level": ["good command"], "hard_skills": ["excel", "chinese word processing", "ms word"], "soft_skills": ["communication skills", "customer service", "pleasant"], "languages_combined": [{"language": "english", "language_level": ["good command"]}, {"language": "chinese", "language_level": ["good command"]}]}, "experience_required": {"duration": ["minimum 1 year"], "field": ["management", "customer service"]}}, {"job_id": "100003009039171", "location_code": "hk", "company": "Harbourfront Landmark Premium Services Limited", "job_title": "\u9867\u5ba2\u670d\u52d9\u52a9\u7406 [Ref. HL-CSA]", "description": "\u7d05\u78e1\u6d77\u540d\u8ed2\n\n\u8aa0 \u8058\u00a0\n\n\u4e2d\u4e94\u6216\u4ee5\u4e0a\u7a0b\u5ea6\n\u5177\u4e00\u5e74\u6216\u4ee5\u4e0a\u76f8\u95dc\u5ba2\u6236\u670d\u52d9\u5de5\u4f5c\u7d93\u9a57\n\u9808\u6301\u6709\u6548\u4fdd\u5b89\u4eba\u54e1\u8a31\u53ef\u8b49\u4e59\u985e\u724c\u7167\n\u64cd\u6d41\u5229\u5ee3\u6771\u8a71\uff0c\u7565\u61c2\u82f1\u8a9e\u53ca\u666e\u901a\u8a71\n\u6bcf\u5929\u5de5\u4f5c9\u5c0f\u6642\uff0c\u9700\u8f2a\u73ed\u00a0 \u00a0(\u8f2a\u73ed\u6642\u9593\u00a0 :\u00a0 \u00a0\u4e0a\u53488\u6642\u81f3\u4e0b\u534810\u6642)\n\n\u672c\u516c\u53f8\u63d0\u4f9b12\u5929\u6709\u85aa\u5e74\u5047\u3001\u91ab\u7642\u8a08\u5283\u3001\u914c\u60c5\u82b1\u7d05\u53ca\u6649\u5347\u6a5f\u6703\u7b49\u3002\u6709\u610f\u8005\u8acb\u81f4\u96fb3157 1129\u8207\u51bc\u5c0f\u59d0\u806f\u7d61\u6216\u6309\"Apply Now\"\u905e\u4ea4\u7533\u8acb\u3002\n\n\u7533\u8acb\u4eba\u63d0\u4f9b\u4e4b\u5168\u90e8\u8cc7\u6599\u7d55\u5c0d\u4fdd\u5bc6\u53ca\u53ea\u4f5c\u62db\u8058\u4e4b\u7528", "employment_types": ["Full Time", "Permanent"], "selling_points": ["\u4e2d\u4e94\u6216\u4ee5\u4e0a\u7a0b\u5ea6", "\u5177\u4e00\u5e74\u6216\u4e0a\u76f8\u95dc\u5ba2\u6236\u670d\u52d9\u5de5\u4f5c\u7d93\u9a57", "\u9808\u6301\u6709\u6548\u4fdd\u5b89\u4eba\u54e1\u8a31\u53ef\u8b49\u4e59\u985e\u724c\u7167"], "locations": ["Hung Hom"], "categories": ["Property / Real Estate", "Property Management", "Others"], "post_time": "2022-01-13T18:54:30Z", "salary": {"currency": null, "max": null, "min": null, "period": null, "term": null}, "salary_visible": false, "title_keywords": ["\u9867\u5ba2\u670d\u52d9\u52a9\u7406"], "responsibilities": [], "requirements": {"degrees": [], "majors": [], "languages": [], "language_level": [], "hard_skills": [], "soft_skills": [], "languages_combined": []}, "experience_required": {"duration": [], "field": []}}, {"job_id": "100003009055426", "location_code": "hk", "company": "Trinity Search Limited", "job_title": "Retail Leasing Manager - Renowned Property Developer", "description": "Our client is a well established property developer that has launched a new progressive expansion plan for the re-positioning of their retail assets in Hong Kong. They are currently seeking for high caliber Retail Leasing specialist in their team to take up the position as \u00a0Retail Leasing Manager.\n\nResponsibilities:\nDevise and implement leasing strategies and tenant mix\nFormulate retail concepts and target prospective tenants with creative retail concepts\nMonitor and keep abreast of market conditions and retail trends across different countries\nProspecting/leasing of spaces and conduct viewing of available spaces\nMonitor all current and future vacancies to ensure full occupancy of the mall\nPrepare annual rental budget and projection and monthly reporting\nNegotiate new and renewal of leases with tenants\nAccount management of tenants and tenancy liaison, handling tenancy-related issues and maintain good landlord-tenant relationships\nWork with relevant departments to meet tenant's needs and drive traffic into the malls.\n\u00a0Requirements:\nDegree holder in Real Estate/ Business / Finance or other related disciplines\nMinimum 8 years of relevant experience in retail leasing, experience gained from working with retailer brands, property developer / landlords or leasing consultancies would be advantageous\nEncompass a creative and entrepreneurial mindset\nExcellent communication and interpersonal skills\nFluency in English and Chinese", "employment_types": ["Full Time"], "selling_points": ["Iconic Retail Asset", "Hong Kong Based", "Top-tier Real Estate portfolio"], "locations": ["Central & Western Area"], "categories": ["Property / Real Estate", "Property Consultancy", "Property Management", "Others"], "post_time": "2022-01-18T02:48:07Z", "salary": {"currency": null, "max": null, "min": null, "period": "monthly", "term": null}, "salary_visible": false, "title_keywords": ["developer", "leasing manager"], "responsibilities": ["reporting", "management", "budget", "monitor", "maintain"], "requirements": {"degrees": ["degree holder"], "majors": ["related disciplines", "finance", "business"], "languages": ["english", "chinese"], "language_level": ["fluency"], "hard_skills": [], "soft_skills": ["creative", "communication and interpersonal skills"], "languages_combined": [{"language": "english", "language_level": ["fluency"]}, {"language": "chinese", "language_level": ["fluency"]}]}, "experience_required": {"duration": ["minimum 8 years"], "field": ["developer", "retail", "relevant experience"]}}, {"job_id": "100003009055071", "location_code": "hk", "company": "Newtech Management Services Ltd", "job_title": "\u6280\u8853\u54e1 (\u6d88\u9632) Technician (Fire service)", "description": "Responsibilities &\u00a0Requirements:\n\n\nHandle fire service maintenance in data centre for our clients;\nExperience in Fire Services or related area;\nGood communication skills, customer-oriented;\nCandidate with data centre experience will be an advantage;\nCandidate with less or no relevant experience will be considered as Junior Technician.\n\u8077\u8cac\u53ca\u8cc7\u6b77:\n\n\u8ca0\u8cac\u5916\u52e4\u4fdd\u990a\u6d88\u9632\u8a2d\u5099\u7cfb\u7d71;\n\u5177\u5099\u6d88\u9632\u4fdd\u990a\u7dad\u4fee\u76f8\u95dc\u7d93\u9a57;\n\u826f\u597d\u6e9d\u901a\u53ca\u9867\u5ba2\u670d\u52d9\u6280\u5de7;\n\u6709\u6578\u64da\u4e2d\u5fc3\u7dad\u4fee\u670d\u52d9\u7d93\u9a57\u8005\u512a\u5148\u8003\u616e;\n\u672a\u6709\u76f8\u95dc\u5de5\u4f5c\u7d93\u9a57\u7684\u61c9\u5fb5\u8005\u5c07\u6703\u8003\u616e\u70ba\u521d\u7d1a\u6280\u8853\u54e1.\n\u82b1\u7d05, \u7259\u79d1\u798f\u5229, \u91ab\u7642\u4fdd\u96aa, \u8d85\u6642\u5de5\u4f5c\u6d25\u8cbc, \u6649\u5347\u6a5f\u6703\u53ca\u9032\u4fee\u6d25\u8cbc, \u4e0a\u73ed\u6642\u9593\u4e0a\u53489\u6642\u81f3\u4e0b\u53486\u6642, \u6bcf\u9031\u5de5\u4f5c6\u5929, \u6bcf\u5929\u5de5\u4f5c 8 \u5c0f\u6642, \u4eab\u6709\u516c\u8846\u5047\u671f;\u00a0\n\n\nAn attractive remuneration package and fringe benefit will be offered to the right candidate. Interested parties, please send\u00a0your resume stating with current and expected salary\u00a0to the Human Resources Department by clicking Apply Now.\n\nFor more information, please visit the corporate website at\u00a0http://www.newtechapac.com\n\n\u00a0All information received will be kept confidential and for recruitment purposes only. Response will only be given to short-listed candidates.", "employment_types": ["Full Time", "Permanent"], "selling_points": [], "locations": ["Kowloon Bay"], "categories": ["Property / Real Estate", "Others", "Others", "Technician", "Building & Construction", "Others"], "post_time": "2022-01-18T01:09:38Z", "salary": {"currency": null, "max": null, "min": null, "period": "monthly", "term": null}, "salary_visible": false, "title_keywords": ["\u6280\u8853\u54e1", "technician"], "responsibilities": [], "requirements": {"degrees": [], "majors": [], "languages": [], "language_level": [], "hard_skills": ["no", "maintenance"], "soft_skills": ["communication skills", "customer-oriented"], "languages_combined": []}, "experience_required": {"duration": [], "field": ["related", "relevant experience"]}}, {"job_id": "100003009054340", "location_code": "hk", "company": "CITIC Pacific Limited", "job_title": "Senior Officer - Property Development", "description": "Responsibilities\n\nAssist the feasibility studies to explore property investment and development opportunities\nCarry out site visits, due diligence exercises, conduct market research for in-depth review and analysis\nProvide professional support in managing the leasing portfolio and develpment projects\nPrepare investment appraisals, management reports and presentations and etc\nReview and analyze market information, news on town planning and property developments\nRequirements\n\nDegree holder or above in Surveying\nMHKIS or relevant professional qualifications\nMinimum 5 years' relevant experience with at least 3 years in property developers\nFamiliar with planning and land policies in Hong Kong\nProficiency in both spoken and written Chinese and English. Fluent in Putonghua\nAnalytical, attention to details, willing to learn and good interpersonal skills\nPlease visit our\u00a0Career Website\u00a0for more information.\n\nInterested parties may submit your application by clicking the\u00a0\"Apply Now\"\u00a0button.\n\n\nAll information provided by applicants will be treated in strict confidence and used only for recruitment purpose. Applicants who are not contacted may consider their application unsuccessful. CITIC Pacific will retain the applications for a maximum period of one year during which applications may also be referred to other vacancies of CITIC Pacific Limited including its subsidiaries or affiliates.", "employment_types": ["Full Time", "Permanent"], "selling_points": ["5-day work, from 9am to 5pm", "Attractive remuneration package", "Comprehensive medical plan covering dependents"], "locations": ["Admiralty"], "categories": ["Building & Construction", "Building / Construction / QS", "Marketing / Public Relations", "Marketing - Market Research", "Property / Real Estate", "Others"], "post_time": "2022-01-17T09:12:27Z", "salary": {"currency": null, "max": null, "min": null, "period": "monthly", "term": null}, "salary_visible": false, "title_keywords": ["senior officer"], "responsibilities": ["due diligence", "market information", "conduct market research", "review", "analysis", "presentations", "management reports", "planning"], "requirements": {"degrees": ["degree holder"], "majors": ["surveying"], "languages": ["putonghua", "english", "chinese"], "language_level": ["proficiency", "fluent"], "hard_skills": ["professional qualifications"], "soft_skills": ["willing to learn", "attention to details", "interpersonal skills"], "languages_combined": [{"language": "putonghua", "language_level": ["fluent"]}, {"language": "english", "language_level": ["proficiency"]}, {"language": "chinese", "language_level": ["proficiency"]}]}, "experience_required": {"duration": ["at least 3 years", "minimum 5 years"], "field": ["property developers", "relevant experience"]}}, {"job_id": "100003009048793", "location_code": "hk", "company": "South Horizons Management Limited", "job_title": "ESTATE OFFICER [Ref. SH-EO]", "description": "Degree or Diploma holder, preferably in Estate Management or related disciplines\nMinimum\u00a03 years' experience in Estate Management\nGood management and interpersonal skills\nFluent in written and spoken English and Chinese\n\nWe offer salary and benefits commensurate with qualifications and experience. Please send a full resume with contact telephone number and expected salary to Senior Estate Manager - South Horizons Management Limited, Management Office, G/F., Block 33A, South Horizons, Ap Lei Chau, Hong Kong (Please quote reference on envelope) or by clicking \"Apply now\".\n\nWe are an equal opportunity employer and welcome applications from all qualified candidates. The information provided will be treated in strict confidence and be used only for consideration of your application for relevant/similar post(s).\n\nApplicants not hearing from us within six weeks from the date of advertisement may consider their applications unsuccessful. All personal data of unsuccessful applicants will be destroyed after the recruitment exercise when no longer required.", "employment_types": ["Full Time", "Permanent"], "selling_points": ["Degree or Diploma holder", "3 years' relevant experience", "Good management and interpersonal skills"], "locations": ["Aberdeen"], "categories": ["Property / Real Estate", "Property Management", "Others"], "post_time": "2022-01-17T06:19:06Z", "salary": {"currency": null, "max": null, "min": null, "period": null, "term": null}, "salary_visible": false, "title_keywords": ["estate officer"], "responsibilities": ["management"], "requirements": {"degrees": ["diploma holder", "degree"], "majors": ["related disciplines"], "languages": ["english", "chinese"], "language_level": ["fluent"], "hard_skills": [], "soft_skills": ["interpersonal skills"], "languages_combined": [{"language": "english", "language_level": ["fluent"]}, {"language": "chinese", "language_level": ["fluent"]}]}, "experience_required": {"duration": ["minimum 3 years"], "field": ["management"]}}, {"job_id": "100003009055094", "location_code": "hk", "company": "OneAsia Network Limited", "job_title": "Data Centre Technician / Operator", "description": "Responsibilities:\n\nResponsible for day-to-day operations support in data centre;\nIncident handling, problem troubleshooting and escalation to upper tier;\nOperate computer equipment;\nMaintain log books and records;\nCoordinate and support external customers as needed\nRequirements:\n\nKnowledge\u00a0in Electrical / Mechanical / Fire Services / Building Services Engineering or related disciplines;\nWith minimum 2 years related experience;\nExposure in data centre will be an advantage;\nBasic knowledge in PC skills;\nResponsible, willing to learn and with positive attitude;\nGood communication skills, customer-oriented;\n12-hour shift / flexible working between 2 to 4 days a week\nCandidate with no working experience will be considered as Trainee Technician;\u00a0\nFresh Graduates are also welcome\nYou have a career opportunity in gaining knowledge and experience in serving one of the largest Data Center providers for local and international enterprise.\n\nAttractive remuneration package and fringe benefit will be offered to the right candidate. Interested parties, we appreciate if you\u00a0must send your resume stating with cover letter, current and expected salary\u00a0to the Human Resources & Administration Department\u00a0by clicking\u00a0Apply Now.\n\nFor more information, please visit our website at\u00a0http://www.oneas1a.com\nAll information collected will be kept strictly confidential and for recruitment purpose only.", "employment_types": ["Full Time", "Permanent"], "selling_points": [], "locations": ["Kowloon Bay"], "categories": ["Property / Real Estate", "Others", "Others", "Technician", "Building & Construction", "Others"], "post_time": "2022-01-18T01:14:17Z", "salary": {"currency": null, "max": null, "min": null, "period": "monthly", "term": null}, "salary_visible": false, "title_keywords": ["operator", "technician"], "responsibilities": ["data", "day-to-day operations", "troubleshooting", "coordinate", "maintain"], "requirements": {"degrees": [], "majors": [], "languages": [], "language_level": [], "hard_skills": ["no", "pc skills", "basic"], "soft_skills": ["flexible", "communication skills", "responsible", "willing to learn", "positive attitude", "customer-oriented"], "languages_combined": []}, "experience_required": {"duration": ["minimum 2 years"], "field": ["related"]}}, {"job_id": "100003009052157", "location_code": "hk", "company": "Citybase Property Management Limited", "job_title": "Assistant Property Officer / Property Assistant (Shopping Mall)", "description": "Responsibilities\n\nManage Customer relationship with tenants and handle requests and inquiries in a professional manner\nCo-ordination for implementation of promotional activities\nResponsible for service delivery including premises handover / takeover execution, tenancy fitting out / reinstatement co-ordination\nOversee property maintenance, security and cleaning services\nSupport on property administration work\n\n\n\u00a0Requirements\n\nDiploma or above, preferably in Property Management or related disciplines\nAt least 2 years working experience in Property Management\nStrong\u00a0command of both written and spoken English and Chinese\nProficient in MS Word, Excel, Powerpoint\u00a0and Chinese Word Processing\nAble to work independently and under pressure\nPleasant personality and willing to meet challenges\nCandidates with less experience or qualification\u00a0will be considered as Property Assistant\n\nWe will offer attractive compensation package to the right candidate. Please send application enclosing resume stating career and salary history, expected salary and date of availability to The Human Resources Manager, Citybase Property Management Limited, Unit No.1, 6/F, Hampton Loft, 11 Hoi Fan Road, Tai Kok Tsui, Kowloon by fax at 2717 4717 or by clicking ''Apply Now'' (in Word format). Please quote the reference of the position you apply for in all correspondences.\n\nWe are an equal opportunity employer and welcome applications from all qualified candidates. Personal data collected will be treated in strictest confidence and handled confidentially by authorized personnel for recruitment-related purposes within the Group. Applicants not hearing from us within six weeks from the date of advertisement may consider their applications unsuccessful.", "employment_types": ["Full Time", "Permanent"], "selling_points": ["Diploma holder in Property Management", "At least 2 years exp in Property Management", "Strong command of written & spoken Eng & Chi"], "locations": ["Tsuen Wan Area"], "categories": ["Admin & HR", "Clerical / Admin Staff", "Property / Real Estate", "Property Management", "Others"], "post_time": "2022-01-17T16:21:07Z", "salary": {"currency": null, "max": null, "min": null, "period": null, "term": null}, "salary_visible": false, "title_keywords": ["property assistant", "assistant property officer"], "responsibilities": ["service delivery", "maintenance", "professional manner", "implementation", "promotional activities", "cleaning", "administration"], "requirements": {"degrees": ["diploma or above"], "majors": ["related disciplines"], "languages": ["english", "chinese"], "language_level": ["proficient"], "hard_skills": ["excel", "no", "chinese word processing", "word", "powerpoint", "ms word"], "soft_skills": ["work independently", "confidence", "under pressure", "pleasant"], "languages_combined": [{"language": "english", "language_level": []}, {"language": "chinese", "language_level": ["proficient"]}]}, "experience_required": {"duration": ["at least 2 years"], "field": ["management"]}}, {"job_id": "100003009047594", "location_code": "hk", "company": "Goodwell Property Management Ltd", "job_title": "Property Assistant (Ref: PA/J)", "description": "F.5 / HKDSEE or certificate in related disciplines\n1-2 years' working\u00a0experience, preferably\u00a0in property management industry\nHard-working with pleasant personality and being a good team-player\nProficient in MS Office and Chinese word processing\nGood command of\u00a0both written and spoken\u00a0English and Chinese\n\nWe will offer attractive compensation package to the right candidate. Please send application enclosing resume stating career and salary history, expected salary and date of availability to The Human Resources Manager, Goodwell Property Management Limited, 2/F New Treasure Centre, 10 Ng Fong Street, San Po Kong, Kowloon\u00a0or by clicking \u201cApply Now\u201d (in Word format). Please quote the reference of the position you apply for in all correspondences.\n\nWe are an equal opportunity employer and welcome applications from all qualified candidates.\u00a0 Personal data collected will be treated in strictest confidence and handled confidentially by authorized personnel for recruitment-related purposes within the Group. Applicants not hearing from us within six weeks from the date of\u00a0application may consider their applications unsuccessful.\n\n(Our website : http://www.goodwell.com.hk/)", "employment_types": ["Full Time", "Permanent"], "selling_points": ["1-2 years working experience", "Hard-working with pleasant personality", "Matriculated or above"], "locations": ["Not Specified"], "categories": ["Property / Real Estate", "Property Consultancy", "Property Management", "Others"], "post_time": "2022-01-15T03:49:44Z", "salary": {"currency": null, "max": null, "min": null, "period": null, "term": null}, "salary_visible": false, "title_keywords": ["property assistant"], "responsibilities": ["management", "recruitment", "website", "personal data"], "requirements": {"degrees": ["certificate"], "majors": ["related disciplines"], "languages": ["english", "chinese"], "language_level": ["good command", "proficient"], "hard_skills": ["chinese word processing", "word", "ms office"], "soft_skills": ["team-player", "confidence", "hard-working", "pleasant"], "languages_combined": [{"language": "english", "language_level": ["good command"]}, {"language": "chinese", "language_level": ["good command", "proficient"]}]}, "experience_required": {"duration": ["1-2 years"], "field": ["management"]}}, {"job_id": "100003009052051", "location_code": "hk", "company": "Whampoa Garden Management Limited", "job_title": "PR & PROMOTIONS OFFICER / ASSISTANT PR & PROMOTIONS OFFICER [Ref: WGML-PRO/APRO]", "description": "Degree holder in Marketing, Communications, Journalism or related disciplines\nMinimum 4 years' experience preferably in event marketing, public relations, promotions or advertising field\nTo plan and implement strategic advertising and promotional plans for shopping malls and other properties in HK\nProficient in using MS Word, Excel, PowerPoint and Chinese word processing\nKnowledge of Photoshop would be an advantage\nFluent in written and spoken English and Chinese\nWilling to work on Saturdays, Sundays and Public Holidays\nCandidates with less experience will be considered as Assistant PR & Promotions Officer\nWe offer salary and benefits commensurate with qualifications and experience. Please send a full resume with contact telephone number and expected salary to\u00a0General Manager - Human Resources & Administration, Whampoa Garden Management Limited, 3/F., One Harbourfront, 18 Tak Fung Street, Hunghom, Kowloon (Please quote reference on envelope) or by clicking \"Apply Now\".\nWe are an equal opportunity employer and welcome applications from all qualified candidates. The information provided will be treated in strict confidence and be used only for consideration of your application for relevant/similar post(s).\n\nApplicants not hearing from us within six weeks from the date of advertisement may consider their applications unsuccessful. All personal data of unsuccessful applicants will be destroyed after the recruitment exercise when no longer required.", "employment_types": ["Full Time", "Permanent"], "selling_points": ["Degree holder", "Minimum 4 years' experience", "To plan and implement advertising strategy"], "locations": ["Hung Hom"], "categories": ["Marketing / Public Relations", "Marketing - Marketing Communication", "Public Relations - Event Management", "Property / Real Estate", "Others"], "post_time": "2022-01-17T07:22:21Z", "salary": {"currency": null, "max": null, "min": null, "period": null, "term": null}, "salary_visible": false, "title_keywords": ["assistant", "pr & promotions officer"], "responsibilities": ["promotional plans", "advertising", "plan"], "requirements": {"degrees": ["degree holder"], "majors": ["journalism", "related disciplines", "marketing", "communications"], "languages": ["english", "chinese"], "language_level": ["fluent", "proficient"], "hard_skills": ["excel", "chinese word processing", "ms word", "powerpoint", "photoshop"], "soft_skills": [], "languages_combined": [{"language": "english", "language_level": ["fluent"]}, {"language": "chinese", "language_level": ["fluent", "proficient"]}]}, "experience_required": {"duration": ["minimum 4 years"], "field": ["public relations", "marketing", "advertising", "pr"]}}, {"job_id": "100003009051959", "location_code": "hk", "company": "Kai Fu Property Services Co Ltd", "job_title": "Senior Property Officer / Property Officer", "description": "\u00a0Responsibilities\n\n\n\nTo assist in the daily operations of managing a government public housing estate\nHandle tenancy matters\u00a0such as tenant enquiries / complaints, flat visits / investigations, etc.\nPerform routine property management duties\u00a0and\u00a0ad hoc duties as assigned by superiors\n\n\u00a0Requirements\n\nHolder of Higher Diploma / Associate Degree in Property Management or related disciplines;\u00a0OR\nLevel 3 or above in 5 subjects in HKDSE, which should include\u00a0Chinese\u00a0and English Language, or equivalent; OR\nGrade E or above in 2 subjects at Advanced Level in HKALE and Level 3 / Grade C or above in 3 other subjects in\u00a0HKCEE, which should include\u00a0Chinese\u00a0and English\u00a0Language or equivalent\nHolder of Certificate in Public Housing Agency Management an added advantage\nRelevant working experience\u00a0in\u00a0public rental housing\u00a0management in Hong Kong\u00a0\nProficient in MS Word, Excel,\u00a0PowerPoint and Chinese word processing\nIndependent, service-oriented with good communication and interpersonal\u00a0skills\n\nWorking Location:\u00a0\u00a0Tin Shui Wai, Ma On Shan\n\n**Salary and position will commensurate with\u00a0qualifications and\u00a0relevant working experiences.\u00a0\n\n\u00a0\u00a0Interested parties please click the \"APPLY NOW\" to submit your application with full resume including\u00a0contact telephone number,\u00a0expected salary and date available to us.\u00a0\u00a0\n\n<All data collected will be used for recruitment purpose only>", "employment_types": ["Full Time", "Permanent"], "selling_points": [], "locations": ["Not Specified"], "categories": ["Sales, CS & Business Devpt", "Customer Service - Supervisor / Officer", "Property / Real Estate", "Property Management", "Others"], "post_time": "2022-01-17T01:39:15Z", "salary": {"currency": null, "max": null, "min": null, "period": "monthly", "term": null}, "salary_visible": false, "title_keywords": ["property officer", "senior property officer"], "responsibilities": ["ad hoc duties", "daily operations", "management"], "requirements": {"degrees": ["associate degree", "diploma", "hkdse", "certificate"], "majors": ["related disciplines"], "languages": ["english", "chinese"], "language_level": ["proficient"], "hard_skills": ["excel", "chinese word processing", "powerpoint", "c", "ms word"], "soft_skills": ["service-oriented", "communication and interpersonal skills", "independent", "advanced"], "languages_combined": [{"language": "english", "language_level": []}, {"language": "chinese", "language_level": ["proficient"]}]}, "experience_required": {"duration": [], "field": ["management", "relevant working experience"]}}, {"job_id": "100003009054166", "location_code": "hk", "company": "Hong Yip Service Company Limited", "job_title": "(\u65e5/\u591c\u73ed)\u9ad8\u7d1a/\u5ba2\u6236\u670d\u52d9\u9577(6\u59299\u5c0f\u6642)", "description": "\u5165\u8077\u8981\u6c42\ufe55\n\u521d\u4e2d\u7a0b\u5ea6\u6216\u5177\u8cc7\u6b77\u67b6\u69cb\u540c\u7b49\u8cc7\u6b77\n\u5177\u56db\u5e74\u6216\u4ee5\u4e0a\u7269\u696d\u7ba1\u7406\u53ca\u5ba2\u6236\u670d\u52d9\u5de5\u4f5c\u7d93\u9a57\n\u9808\u6301\u6709\u6709\u6548\u4fdd\u5b89\u4eba\u54e1\u8a31\u53ef\u8b49\u53ca\u8a8d\u53efQAS\u8b49\u66f8\n\u5de5\u4f5c\u5730\u5340:\u00a0\u5317\u89d2\n\n\n\u4ee5\u4e0a\u8077\u4f4d\u53ef\u4eab\u6709\u512a\u539a\u798f\u5229\uff0c\u5305\u62ec\u6709\u85aa\u5e74\u504710\u5929\u3001\u5404\u7a2e\u7279\u5225\u5047\u671f\u3001\u91ab\u7642\u798f\u5229\u3001\u5b8c\u5584\u57f9\u8a13\u3001\u6649\u5347\u6a5f\u6703\u53ca\u50f1\u54e1\u652f\u63f4\u670d\u52d9\u3002\n\n\u6709\u610f\u8005\uff0c\u8acb\u81f4\u96fb2762 8300\u8207\u9127\u5c0f\u59d0\u7d04\u898b\u3002\n\n\u9664\u4e0a\u8ff0\u8077\u4f4d\u5916\uff0c\u5c1a\u6709\u5176\u4ed6\u7a7a\u7f3a\u3002\u8acb\u900f\u904e\u4ee5\u4e0b\u65b9\u6cd5\u5c07\u5c65\u6b77\u4ea4\u5230\u5eb7\u696d\u4eba\u529b\u8cc7\u6e90\u53ca\u884c\u653f\u90e8\u3002\n\n\u90f5\u5bc4\uff1a\u89c0\u5858\u5de7\u660e\u885795\u865f\u4e16\u9054\u4e2d\u5fc316\u6a13\n\n\u5eb7\u696d\u4e43\u5e73\u7b49\u6a5f\u6703\u50f1\u4e3b\uff0c\u800c\u6240\u6709\u6536\u96c6\u8cc7\u6599\u53ea\u7528\u4f5c\u96c6\u5718\u5167\u90e8\u62db\u8058\u4e4b\u7528\u9014\u3002", "employment_types": ["Full Time", "Permanent"], "selling_points": ["\u65b0\u9d3b\u57fa\u5730\u7522\u767c\u5c55\u6709\u9650\u516c\u53f8\u5168\u8cc7\u9644\u5c6c\u6a5f\u69cb", "\u51774\u5e74\u7269\u696d\u7ba1\u7406\u6216\u5ba2\u6236\u670d\u52d9\u5de5\u4f5c\u7d93\u9a57", "\u521d\u4e2d\u7a0b\u5ea6\u6216\u5177\u8cc7\u6b77\u67b6\u69cb\u540c\u7b49\u8cc7\u6b77"], "locations": ["North Point"], "categories": ["Property / Real Estate", "Property Management", "Others", "Others", "Security / Safety Control"], "post_time": "2022-01-17T08:38:29Z", "salary": {"currency": null, "max": null, "min": null, "period": "monthly", "term": null}, "salary_visible": false, "title_keywords": [], "responsibilities": [], "requirements": {"degrees": [], "majors": [], "languages": [], "language_level": [], "hard_skills": [], "soft_skills": [], "languages_combined": []}, "experience_required": {"duration": [], "field": []}}, {"job_id": "100003009054198", "location_code": "hk", "company": "RecruitFirst Limited", "job_title": "Assistant Arborist Support [20k/ Tree Risk/ Landscape/ 9 months contract/ Kowloon]", "description": "Duties:\u00a0\n\nAssisting in planning design, preparation and implementation of soft landscape works and vegetation maintenance under contract\nConducting site inspection, site supervision and preparing and maintaining site records under contracts\nConducting Tree Risk Assessment\nChecking or auditing Form 1, Form 1.5 and Form 2 records\nAssisting Landscape Architects to vet Tree Preservation and Removal Application including on site checking or auditing\nFollowing up with complaint cases related to vegetation maintenance\nProviding technical support and assistant to the Landscape Term Contract administration and contract document preparation\n\nRequirements:\u00a0\n\nGraduated from one of the arboriculture, horticulture, landscape management or tree management programmes at Level 3 to Level 5 of the Qualifications Framework in Hong Kong\nA diploma or higher certificate in management studies, natural science or related subjects from a Hong Kong university or HKIVE\nAt least 1 year of related practical experience on supervision of soft landscape work, woodland planting and management, or tree inspection and risk management", "employment_types": ["Full Time", "Contract"], "selling_points": [], "locations": ["Kwun Tong Area"], "categories": ["Transportation & Logistics", "Others", "Sciences, Lab, R&D", "Environmental Science / Waste Management", "Property / Real Estate", "Others"], "post_time": "2022-01-17T08:46:45Z", "salary": {"currency": null, "max": null, "min": null, "period": "monthly", "term": null}, "salary_visible": false, "title_keywords": ["assistant"], "responsibilities": ["site supervision", "maintenance", "maintaining", "technical support", "contracts", "contract administration", "implementation", "design", "site inspection", "checking", "auditing", "planning"], "requirements": {"degrees": ["diploma", "higher certificate"], "majors": ["science"], "languages": [], "language_level": [], "hard_skills": [], "soft_skills": [], "languages_combined": []}, "experience_required": {"duration": ["at least 1 year"], "field": ["related", "risk management", "management"]}}, {"job_id": "100003009054561", "location_code": "hk", "company": "Chinachem Group", "job_title": "Senior Officer - Leasing (Tenant Management & Marketing)", "description": "Responsibilities:\n\nAssist to strengthen and maintain tenant relationship by providing quality tenant services and support on sales action plan, service standards and operation efficiency\nAssist the Manager to organize tour activities, marketing campaign, digital marketing and PR events\nLiaise with both stakeholders and agencies to create all-rounded marketing collaterals\nImplement year-round retailing marketing campaign\nSolicit supports from potential partners and stakeholders for joint promotion\nHandle telephone enquiries and requests from tenants in a professional manner and take appropriate / necessary actions\nPrepare related reports and conduct relevant analysis\nCoordinate with different business units, tenants and external parties for smooth execution and high level of quality on all marketing activities\n\nRequirements:\n\nDegree holder in Marketing, Journalism, Business Administration or related disciplines\nMinimum 4 years' solid experience in event management / property leasing and marketing, preferably with property developers or event agencies\nCreative, responsible, dynamic, multi-tasking and good marketing sense\nAble to work independently to meet multiple project deadlines\nGood interpersonal, communication and presentation skills\nFluent in spoken and written English and Chinese\nWilling to work on weekends and public holidays when necessary\nInterested parties please send full resume stating current and expected salary, date available to:\u00a0Human Resources Manager, Chinachem Group, 35-38 Floor, Tower 2, Nina Tower, 8 Yeung Uk Road, Tsuen Wan, N.T.\u00a0or click \"Apply Now\" to submit your application.\n\nApplicants who fail to hear from the Chinachem Group within 8 weeks from the date of submitting applications should consider their applications unsuccessful. The personal data of unsuccessful candidates collected for this recruitment exercise will be kept for 2 years from its completion and thereafter destroyed.\n\nAll applications will be treated in the strictest confidence. Personal data provided will be used for recruitment purpose only and in accordance with the Code of Practice on Human Resource Management.", "employment_types": ["Full Time", "Permanent"], "selling_points": ["Tenant Management & Marketing", "Marketing campaign, digital marketing and PR event", "Event management / property leasing and marketing"], "locations": ["Central"], "categories": ["Marketing / Public Relations", "Public Relations - Event Management", "Property / Real Estate", "Others", "Digital Marketing"], "post_time": "2022-01-17T09:59:34Z", "salary": {"currency": null, "max": null, "min": null, "period": "monthly", "term": null}, "salary_visible": false, "title_keywords": ["senior officer"], "responsibilities": ["analysis", "marketing collaterals", "quality", "professional manner", "coordinate with", "external parties", "service standards", "maintain", "digital marketing", "reports", "plan", "liaise with"], "requirements": {"degrees": ["degree holder"], "majors": ["journalism", "related disciplines", "marketing", "business administration"], "languages": ["english", "chinese"], "language_level": ["fluent"], "hard_skills": ["dynamic"], "soft_skills": ["work independently", "marketing sense", "responsible", "communication", "multi-tasking", "dynamic", "presentation skills", "creative", "interpersonal"], "languages_combined": [{"language": "english", "language_level": ["fluent"]}, {"language": "chinese", "language_level": ["fluent"]}]}, "experience_required": {"duration": ["minimum 4 years"], "field": ["property developers", "management", "marketing"]}}, {"job_id": "100003009051850", "location_code": "hk", "company": "Cayley Property Management Limited", "job_title": "ASSISTANT ESTATE MANAGER [Ref. CPML-AEM]", "description": "Degree holder preferably in Property Management or related disciplines\nMinimum\u00a07 years' relevant working experience in supervisory level\nTo monitor the day-to-day property management functions, e.g. security, maintenance, cleaning, procurement, amenities and facilities management etc.\nTo monitor property management income and expenses to prepare annual property management budgets and other related financial duties\nTo liaise with Government departments and other departments of the company\nTo attend Owners' Committee meetings and maintain good relationship with the committees\nGood management and interpersonal skills\nFluent in spoken and written English and Chinese\n\nWe offer salary and benefits commensurate with qualifications and experience. Please send a full resume with contact telephone number and expected salary to\u00a0General Manager - Human Resources & Administration, Cayley Property Management Limited, 3/F., One Harbourfront, 18 Tak Fung Street, Hunghom, Kowloon\u00a0(Please quote reference on envelope) or by clicking \"Apply Now\".\n\n\nWe are an equal opportunity employer and welcome applicants from all qualified candidates. The information provided will be treated in strict confidence and be used only for consideration of your application for relevant/similar post(s).\n\nApplicants not hearing from us within six weeks from the date of advertisement may consider their applications unsuccessful. All personal data of unsuccessful applicants will be destroyed after the recruitment exercise when no longer required.", "employment_types": ["Full Time", "Permanent"], "selling_points": ["Degree holder", "Minimum 7 years' relevant working experience", "Good management and interpersonal skills"], "locations": ["Not Specified"], "categories": ["Property / Real Estate", "Property Management", "Others"], "post_time": "2022-01-17T07:31:04Z", "salary": {"currency": null, "max": null, "min": null, "period": null, "term": null}, "salary_visible": false, "title_keywords": ["assistant", "estate manager"], "responsibilities": ["budgets", "management", "maintenance", "expenses", "monitor", "maintain good relationship", "cleaning", "liaise with"], "requirements": {"degrees": ["degree holder"], "majors": ["related disciplines"], "languages": ["english", "chinese"], "language_level": ["fluent"], "hard_skills": ["facilities management", "maintenance"], "soft_skills": ["interpersonal skills"], "languages_combined": [{"language": "english", "language_level": ["fluent"]}, {"language": "chinese", "language_level": ["fluent"]}]}, "experience_required": {"duration": ["minimum 7 years"], "field": ["supervisory level", "relevant working experience"]}}, {"job_id": "100003009042311", "location_code": "hk", "company": "Chevalier Group - Property Management", "job_title": "Estate Assistant / Clerk", "description": "Chevalier Property Management Limited, a subsidiary of Chevalier Group, is now inviting high calibre persons to apply for this position:\n\nResponsibilities\n\nAssist Estate Officer\u00a0in monitioring daily\u00a0Property Management issues\nHandle complaints and enquiries of the customers\nProvide clerical support to estate management officer\nPerform ad hoc duties as assigned\n\nRequirements\n\nHKDSE or above\nMinimum 1 years' relevant working experience\nAble to work independently, with excellent communication and interpersonal skills\nGood command of both written and spoken English and Chinese\nProficient in MS Office including MS Word, MS Excel and Chinese word processing\n\nAttractive remuneration package will be offered to the right candidate. Interested parties, please send us your resume with current and expected salary (with reference number quoted) by clicking \"Apply Now\" or mail to:\n\nThe\u00a0Human Resources\u00a0Manager, Chevalier Group, 22/F, Chevalier\u00a0Commercial Centre,\u00a08 Wang Hoi Road, Kowloon Bay, Hong Kong\n\nWe are an equal opportunity employer and welcome applications from all qualified candidates.\u00a0 Personal data collected would be used for recruitment purpose only.\n\nWelcome to visit:www.chevalierpropmgt.com.hk", "employment_types": ["Full Time"], "selling_points": ["1 year relevant working experience", "Form 5 / DSE or above", "Proficient in MS Office"], "locations": ["Shatin Area"], "categories": ["Admin & HR", "Clerical / Admin Staff", "Property / Real Estate", "Property Management", "Others"], "post_time": "2022-01-14T10:03:01Z", "salary": {"currency": null, "max": null, "min": null, "period": null, "term": null}, "salary_visible": false, "title_keywords": ["clerk", "assistant"], "responsibilities": ["provide clerical support", "management", "ad hoc duties", "handle complaints"], "requirements": {"degrees": ["hkdse"], "majors": [], "languages": ["english", "chinese"], "language_level": ["good command", "proficient"], "hard_skills": ["ms word", "ms excel", "chinese word processing", "ms office"], "soft_skills": ["work independently", "communication and interpersonal skills"], "languages_combined": [{"language": "english", "language_level": ["good command"]}, {"language": "chinese", "language_level": ["good command", "proficient"]}]}, "experience_required": {"duration": ["minimum 1 years"], "field": ["relevant working experience"]}}, {"job_id": "100003009053410", "location_code": "hk", "company": "Full-Mark Property Agency", "job_title": "\u7269\u696d\u9867\u554f/\u4ee3\u7406**", "description": "\n\u8077\u8cac :\u8ca0\u8cac\u4e00\u4e8c\u624b\u6a13\u76e4\u92b7\u552e, \u7269\u696d\u79df\u8cc3, \u8ddf\u9032\u92b7\u552e\u6587\u4ef6\u53ca\u5408\u7d04\n\n\u8cc7\u6b77 :\u4e2d\u4e94\u7a0b\u5ea6; 1\u5e74\u7d93\u9a57; \u826f\u597d\u7cb5\u8a9e; \u4e00\u822c\u82f1\u8a9e; \u61c2\u8b80\u5beb\u4e2d\u6587; \u7565\u61c2\u8b80\u5beb\u82f1\u6587; \u5b88\u6642\u76e1\u8cac\n\n\u5f85\u9047 :\u6bcf\u6708$8,000, \u6709\u4f63\u91d1 \u53ca\u6649\u5347\u6a5f\u6703, \u4e0a\u534810\u6642\u81f3\u4e0b\u53488\u6642, \u6bcf\u9031\u5de5\u4f5c6\u5929,\u8f2a\u4f11, \u6bcf\u5929\u5de5\u4f5c 8 \u5c0f\u6642, \u5348\u81b3\u6642\u9593\u5169\u5c0f\u6642\n\n\u7533\u8acb\u9808\u77e5 :\u6c42\u8077\u8005\u53ef\u81f4\u96fb60729564\u8207\u5bcc\u8aa0\u5730\u7522\u4ee3\u7406\u516c\u53f8\u6797\u5148\u751f\u806f\u7d61\u3002\n\n", "employment_types": ["Full Time"], "selling_points": [], "locations": ["Wong Tai Sin Area"], "categories": ["Property / Real Estate", "Property Consultancy", "Others", "Sales, CS & Business Devpt", "Sales - Real Estate"], "post_time": "2022-01-17T06:56:50Z", "salary": {"currency": null, "max": null, "min": null, "period": "monthly", "term": null}, "salary_visible": false, "title_keywords": [], "responsibilities": [], "requirements": {"degrees": [], "majors": [], "languages": [], "language_level": [], "hard_skills": [], "soft_skills": [], "languages_combined": []}, "experience_required": {"duration": [], "field": []}}, {"job_id": "100003009055449", "location_code": "hk", "company": "Twin City Holdings Limited", "job_title": "Accounting Officer", "description": "Role:\n\nHandle full set of accounts and maintain daily operations of the team.\n\nJob description:\n\nHandle full set of books and daily accounting work including payment transactions, journal entries, AR, AP and reconciliations of accounts\nPreparation of invoice and settlement of accounts\nPrepare monthly financial statements and management reports\nPrepare accounting schedules for year end audit and tax computation\nHandle administrative and clerical duties\nAssist in ad hoc duties as required\nRequirements:\n\nDegree holder of accounting or related discipline and qualified CPA\n2 years full set accounting work experience\nResponsible,\u00a0detailed-minded\u00a0and well-organized\nGood computer skills including Excel and PowerPoint\nCandidate with higher experience level will be considered as Assistant Manager\nImmediate available is highly preferable", "employment_types": ["Full Time", "Permanent"], "selling_points": ["Daily accounting work", "Experience in Real Estate / property developer", "Qualified CPA"], "locations": ["Central"], "categories": ["Accounting", "Accountant", "Property / Real Estate", "Others"], "post_time": "2022-01-18T02:36:36Z", "salary": {"currency": null, "max": null, "min": null, "period": "monthly", "term": null}, "salary_visible": false, "title_keywords": ["accounting officer"], "responsibilities": ["ap", "ad hoc duties", "ar", "tax computation", "schedules", "daily accounting work", "payment transactions", "reconciliations of accounts", "audit", "settlement of accounts", "prepare monthly financial statements", "journal entries", "management reports", "preparation of invoice"], "requirements": {"degrees": ["degree holder"], "majors": ["accounting"], "languages": [], "language_level": [], "hard_skills": ["powerpoint", "cpa", "computer skills", "excel"], "soft_skills": ["well-organized", "responsible", "detailed"], "languages_combined": []}, "experience_required": {"duration": ["2 years"], "field": ["accounting"]}}, {"job_id": "100003009049851", "location_code": "hk", "company": "Urban Group", "job_title": "Assistant Property Officer", "description": "Responsibilities:\n\nHandle day-to-day property operations\nSupervise the services of, security, cleaning, repair and maintenance provided to owners / occupants\nBuild up and maintain good relationship with clients\nHandle enquiries and complaints from the owners / occupants\n\nRequirements:\n\nDegree / Higher Diploma / Diploma\u00a0in housing management / property management / facility management or related disciplines\nGood communication and interpersonal skills\nGood command of both English and Chinese\nFresh graduates are welcome to apply\n\nInterested parties please\u00a0send\u00a0application letter with detailed resume, current and expected salary to\u00a0Group Manager \u2013 Human Capital & Training\u00a0through one of the following means:\n\n\nMail:\u00a016/F., Chevalier Commercial Centre, 8 Wang Hoi Road, Kowloon Bay,\u00a0Kowloon,\u00a0Hong Kong\n\nEmail: Click 'Apply Now'\n\n\nAll personal data collected will be used for employment-related purposes only.", "employment_types": ["Full Time", "Permanent"], "selling_points": [], "locations": ["Not Specified"], "categories": ["Property / Real Estate", "Property Management", "Others"], "post_time": "2022-01-14T09:19:05Z", "salary": {"currency": null, "max": null, "min": null, "period": "monthly", "term": null}, "salary_visible": false, "title_keywords": ["assistant property officer"], "responsibilities": ["maintenance", "operations", "handle enquiries and complaints", "maintain good relationship", "repair", "cleaning"], "requirements": {"degrees": ["diploma", "degree"], "majors": ["related disciplines"], "languages": ["english", "chinese"], "language_level": ["good command"], "hard_skills": [], "soft_skills": ["communication and interpersonal skills"], "languages_combined": [{"language": "english", "language_level": ["good command"]}, {"language": "chinese", "language_level": ["good command"]}]}, "experience_required": {"duration": [], "field": []}}, {"job_id": "100003009044773", "location_code": "hk", "company": "Jones Lang LaSalle Management Services Ltd", "job_title": "Management Surveyor/ Property Officer/ Assistant Property Officer - Portfolio (5-day work)", "description": "You are required to report to Manager and provide professional advice to the clients in the aspect of property management of the Firm's managed buildings. Your key accountabilities are:\n\n\n\nAdminister a property portfolio of commercial, residential and industrial buildings\nWork closely with the building-in-charge to ensure the quality of service delivered to our clients and tenants\nAct as the company's representative to deal with the enquiries of the clients and tenants\n\n\nRequirements:\n\n\nDegree holder in real estate, building management or related discipline\nMin.\u00a02\u00a0years' relevant experience in sizable property management company. Candidate with less experience will be considered as Assistant Property Officer/ Assistant Management Surveyor\nKnowledge of Building Management Ordinance, Landlord & Tenant (Consolidation) (Amendment) Ordinance, DMC and related ordinances\nExcellent client relationship management\nInitiative and able to work independently\nExcellent command of both\u00a0written and spoken English and Chinese\nValid Hong Kong Estate Agents License will be a definite advantage\n\nWe offer 5-day work week, attractive remuneration packages and good career prospects for the right applicant. Please apply by clicking \"APPLY NOW\", or submit your full resume and expected salary to the PM-HR Department, 14/F, Dorset House, Taikoo Place, Quarry Bay, or fax to 2968-4177.\n\n(Please quote the reference number on the envelope/subject of email.)\n\nApplicants not invited for interviews within 6 weeks may consider their applications unsuccessful. Information provided will be treated with strict confidential and be used for the purpose of employment only.", "employment_types": ["Full Time", "Permanent"], "selling_points": ["Degree holder in real estate related discipline", "Min. 2 years' relevant experience", "Initiative and able to work independently"], "locations": ["Quarry Bay"], "categories": ["Property / Real Estate", "Property Management", "Others"], "post_time": "2022-01-15T03:49:19Z", "salary": {"currency": null, "max": null, "min": null, "period": null, "term": null}, "salary_visible": false, "title_keywords": ["property officer", "management surveyor", "assistant property officer"], "responsibilities": ["building management", "management", "quality", "report"], "requirements": {"degrees": ["degree holder"], "majors": ["building management"], "languages": ["english", "chinese"], "language_level": ["excellent"], "hard_skills": [], "soft_skills": ["work independently", "initiative"], "languages_combined": [{"language": "english", "language_level": ["excellent"]}, {"language": "chinese", "language_level": ["excellent"]}]}, "experience_required": {"duration": ["2 years"], "field": ["management", "relevant experience"]}}, {"job_id": "100003009054554", "location_code": "hk", "company": "China Merchants Property Management (Overseas) Limited", "job_title": "Senior Property Manager / Property Manager", "description": "Responsibilities:\n\nIn charge of the day-to-day operations and management of a mixed portfolio of properties\nProvide professional advice on pre-property management and headcount planning for a constructing intelligent and environmentally friendly Grade A commercial building\nSolid experience in takeover of newly built intelligent and environmentally friendly Grade A commercial buildings with internal and external parties\nPrepare the management budget and monitor the expenditures of properties\nEnsure the operations of properties are in compliance with company policies and procedures\nMonitor the service standards of maintenance, security, cleaning services and contractors of properties\nExperienced in operating the internal and external audit work for ISO9001:2015 quality management system\nImplement property management operation safety system and safety training\nHandle emergency incidents, tenants\u2019 inquiries and complaints\nAct as focal point to communicate with Shen Zhen head office for the Company\u2019s management issues\nManage both Hong Kong head office and on-site managements of the existing and upcoming properties\nPrepare property management proposals for marketing development and safety related issues and reports\nPerform ad hoc duties as assigned\n\n\u00a0Requirements:\n\nDegree holder or above in Property Management, Housing, Hospitality Management or related disciplines\nMinimum 5 years\u2019 relevant experiences in Grade A commercial buildings, hotels and serviced apartments\nHolder of PMP License Tier 1 is required\nGood understanding of Building Management Ordinance / Deed of Mutual Covenant\nMember of MHKIH / MCIH / MRICS / HKIS / RPHM is an advantage\nStrong leadership with good communication and interpersonal skills\nMature, self-motivated and able to work under pressure\nGood command of both spoken and written English, Cantonese and Mandarin, especially Chinese writing\nFamiliar with PC operations, MS Office and Chinese word processing\nRecognize Chinese state-owned enterprises culture\nCandidate with less experience / qualifications will be considered as Property Manager\nWe offer good benefits with 5 days work, medical & life insurance, double pay and discretionary bonus.\nInterested parties please send your full resume with current salary, expected salary and available date to us via \u201cApply Now\u201d.", "employment_types": ["Full Time", "Permanent"], "selling_points": [], "locations": ["Sheung Wan"], "categories": ["Sales, CS & Business Devpt", "Business Development", "Property / Real Estate", "Property Management", "Others"], "post_time": "2022-01-17T09:58:22Z", "salary": {"currency": null, "max": null, "min": null, "period": "monthly", "term": null}, "salary_visible": false, "title_keywords": ["senior property manager", "property manager"], "responsibilities": ["operations", "internal and external parties", "day-to-day operations", "budget", "audit", "quality", "inquiries and complaints", "service standards", "ad hoc duties", "compliance", "monitor", "reports", "management", "procedures", "cleaning", "communicate with", "maintenance", "policies", "planning"], "requirements": {"degrees": ["degree holder"], "majors": ["hospitality management", "related disciplines"], "languages": ["cantonese", "english", "chinese", "mandarin"], "language_level": ["good command"], "hard_skills": ["chinese word processing", "hkis", "pc operations", "pmp", "ms office"], "soft_skills": ["self-motivated", "mature", "communication and interpersonal skills", "leadership", "work under pressure"], "languages_combined": [{"language": "cantonese", "language_level": ["good command"]}, {"language": "english", "language_level": ["good command"]}, {"language": "chinese", "language_level": ["good command"]}, {"language": "mandarin", "language_level": ["good command"]}]}, "experience_required": {"duration": ["minimum 5 years"], "field": ["commercial", "hotels"]}}, {"job_id": "100003009051317", "location_code": "hk", "company": "List Sotheby's International Realty", "job_title": "Client Service Assistant", "description": "DUTIES AND RESPONSIBILITIES\n\nProvide high quality service to internal & external client\nWork closely with other client service officers as a central supporting team for the operation of the whole office\nSupport all kinds of sales and leasing supporting matters including but not limited to updating, hand over, appointment making, initial negotiations, explanation of contract terms, photo-taking and webpage preparation\nMaintain and update of system, data entry and checking\nAssist in preparation of Sales Event, Venue Set-up & After Sales Follow-Up\nHandle office administrative duties, including office & facilities management, fixed assets procurement\nManage office stationery, equipment and inventory, etc\nCarry out ad-hoc duties and work outdoor if necessary\n\nJOB REQUIREMENTS\n\nUniversity graduate, Fresh grad also welcome\nExperience in related position\nProactive, detail oriented and able to work independently\nPassionate on Real Estate industry\nGood verbal and written communication skills in English and Chinese\nSystematic, organizational skills and able to prioritize and handle multiple tasks\nProficient in Microsoft Outlook, Excel and Word\nInterested parties please send your\u00a0full resume with expected salary\u00a0and\u00a0your availability\u00a0to us.", "employment_types": ["Full Time", "Permanent"], "selling_points": ["Real Estate Industry", "Provide Support in Local & Overseas Property", "Attractive Packages"], "locations": ["Central"], "categories": ["Admin & HR", "Clerical / Admin Staff", "Property / Real Estate", "Others"], "post_time": "2022-01-15T08:10:50Z", "salary": {"currency": null, "max": null, "min": null, "period": "monthly", "term": null}, "salary_visible": false, "title_keywords": ["assistant"], "responsibilities": ["management", "data entry", "inventory", "quality", "checking", "stationery", "maintain", "administrative duties", "ad-hoc duties"], "requirements": {"degrees": ["university graduate"], "majors": [], "languages": ["english", "chinese"], "language_level": ["good"], "hard_skills": ["excel", "outlook", "word"], "soft_skills": ["passionate", "communication skills", "work independently", "organizational skills", "able to prioritize", "detail oriented", "systematic", "handle multiple tasks", "proactive"], "languages_combined": [{"language": "english", "language_level": ["good"]}, {"language": "chinese", "language_level": ["good"]}]}, "experience_required": {"duration": [], "field": ["related"]}}, {"job_id": "100003009055516", "location_code": "hk", "company": "KOS International Limited", "job_title": "Property Manager (Developer, Residential)", "description": "About our Client\n\nMy client is a Hong Kong listed developer with diversified residential and commercial assets in Hong Kong and overseas. In order to maintain premium quality of services, they are looking for a Property Manager to join their team.\n\nAbout the Role\n\nLead a team to monitor and supervise colleagues and frontline staff (e.g. cleaning staff, security) to handle daily operation\nCoordinate with technical team to ensure maintenance work on schedule\nPrepare annual budget and procurement tendering\nHandle IO and OC for the management matters of the estates\n\nThe successful applicants\n\nHigh Diploma holder or above in Property Management, Facility Management, Real Estate\n7 years' or above experience in property management\nProfessional Qualification such as PMP Tier 1 is a plus\nProficient in using Microsoft Office\nFluent in written and spoken English and Chinese\n\nClick \"Apply Now\" to apply for this position or call Bryan Leung at +852 3180 4958 for a confidential discussion. All information collected will be kept in strict confidence and will be used for recruitment purpose only.", "employment_types": ["Full Time", "Permanent"], "selling_points": ["Large-scale of residential", "Attractive package and remuneration", "Open-minded, cheerful"], "locations": ["Not Specified"], "categories": ["Property / Real Estate", "Property Consultancy", "Property Management", "Others"], "post_time": "2022-01-18T02:40:26Z", "salary": {"currency": null, "max": null, "min": null, "period": "monthly", "term": null}, "salary_visible": false, "title_keywords": ["developer", "property manager"], "responsibilities": ["management", "maintenance", "budget", "monitor", "quality", "daily operation", "coordinate with", "tendering", "lead a team", "maintain", "recruitment", "schedule", "cleaning"], "requirements": {"degrees": ["high diploma"], "majors": [], "languages": ["english", "chinese"], "language_level": ["fluent"], "hard_skills": ["plus", "io", "maintenance", "microsoft office", "pmp"], "soft_skills": ["confidence"], "languages_combined": [{"language": "english", "language_level": ["fluent"]}, {"language": "chinese", "language_level": ["fluent"]}]}, "experience_required": {"duration": ["7 years"], "field": ["management"]}}, {"job_id": "100003009054891", "location_code": "hk", "company": "CBRE Limited", "job_title": "APAC Client Solutions Analyst", "description": "At CBRE, you are empowered to take your career path into your own hands. Our people enjoy workplace flexibility in a global organization with tremendous scale providing corporate real estate and property services. Each day you will work in an inclusive and collaborative environment with supportive teammates and be challenged to grow and be your best every day.\n\nBusiness Line:\n\nWorking collaboratively with the regional Advisory & Transaction Services Occupier Team, specifically supporting the growth of the Accounts and Multi Market space across the Asia Pacific region\nSupport the strategy of Cultivate, Win, Keep, Grow in Asia Pacific\nA&T ensures our clients get unequalled experience and knowledge from across our occupier platform, put to work for the benefit of their organization\nCollaborate with the other Occupier service lines within CBRE including (but not limited to) Facilities Management, Project Management, Capital Markets.\nResponsibilities:\n\nIntegral to the Advisory & Transactions regional business development opportunities and initiatives\nWorking directly with the A&T Occupier Accounts and Multi Market Leaders\nIdentify potential A&T clients from both internal and external sources\nCo-ordinate & produce client proposals and marketing materials to an exceptional standard\nUndertake and manage due diligence in respect of potential A&T clients\nTake an active part in the planning and implementation of the team\u2019s annual and on-going business development & marketing plan\nSupport internal and external communication initiatives including newsletters, client testimonials, thought leadership reports, and memo/updates\nTrack financial performance of the business by geography and service lines, both actuals and budgets\nInput to the pipeline and prospecting process ensuring accurate data capture and reporting procedures\nManage & contribute to essential BD materials for wider APAC business use\nRegional coordination of pursuits and assignments may require work with both regional and global teams, and associated travel.\nCreate, track, collect and analyze results to periodic client satisfaction and market sentiment surveys\nRequirements\n\nMinimum of Bachelor's degree from an accredited program in business, real estate or related disciplines\nMinimum 2 years working experience\nA working knowledge of accounting, budgeting, scheduling and process as they relate to corporate real estate\nExcellent verbal and written communication skills in English, professional manner and computer literacy\nStrong communication and teamwork skills\nSelf-motivated and proactive\nExcellent attitude, willingness to learn and develop\nCompetent in Excel and Microsoft packages (VBA Skills is a plus)\nMandarin and/or Cantonese is a bonus\n\nIf you are looking for a role that has high visibility and will help elevate your career then apply now.\n\nPlease note due to the volume of response anticipated for this role; only shortlisted candidates will be contacted.", "employment_types": ["Full Time"], "selling_points": ["Support growth of the Accounts and Multi Markets", "Collaborate across regions and functions", "APAC regional role with high visibility"], "locations": ["Admiralty"], "categories": ["Property / Real Estate", "Others"], "post_time": "2022-01-17T12:51:08Z", "salary": {"currency": null, "max": null, "min": null, "period": "monthly", "term": null}, "salary_visible": false, "title_keywords": ["analyst"], "responsibilities": ["due diligence", "budgets", "reporting", "memo", "data", "procedures", "implementation", "transactions", "teams", "communication", "marketing plan", "reports", "coordination", "marketing materials", "client proposals", "planning"], "requirements": {"degrees": ["degree", "bachelor"], "majors": ["related disciplines", "business"], "languages": ["cantonese", "english", "mandarin"], "language_level": ["excellent"], "hard_skills": ["excel", "vba", "plus"], "soft_skills": ["communication skills", "self-motivated", "competent", "teamwork", "communication", "computer literacy", "proactive"], "languages_combined": [{"language": "cantonese", "language_level": []}, {"language": "english", "language_level": ["excellent"]}, {"language": "mandarin", "language_level": []}]}, "experience_required": {"duration": ["minimum 2 years"], "field": []}}, {"job_id": "100003009056012", "location_code": "hk", "company": "Match Talent Limited", "job_title": "\u623f\u5730\u4ea7\u8425\u9500\u603b\u76d1", "description": "\u5c97\u4f4d\u804c\u8d23\uff1a\n\n1\u3001\u5236\u8ba2\u9500\u552e\u7b56\u7565\uff1a\u8fdb\u884c\u5e02\u573a\u9884\u6d4b\uff0c\u5236\u8ba2\u62d3\u5c55\u53ca\u92b7\u552e\u7b56\u7565\n\n2\u3001\u6267\u884c\u9500\u552e\u7b56\u7565\uff0c\u7ba1\u7406\u5e76\u6307\u5bfc\u9500\u552e\u56e2\u961f\uff0c\u8fbe\u6210\u5e02\u573a\u76ee\u6807\u3001\u5b8c\u6210\u56de\u6b3e\n\n3\u3001\u9500\u552e\u4f53\u7cfb\u7ba1\u7406\uff1a\u6839\u636e\u516c\u53f8\u9500\u552e\u7b56\u7565\uff0c\u5efa\u7acb\u9500\u552e\u7f51\u7edc\u53ca\u6e20\u9053\u7ba1\u7406\n\n4\u3001\u5e02\u573a\u63a8\u5e7f\uff1a\u5efa\u7acb\u7cbe\u51c6\u7684\u5e02\u573a\u63a8\u5e7f\u6d3b\u52a8\uff0c\u8425\u9020\u5e02\u573a\u73af\u5883\uff0c\u63d0\u5347\u9879\u76ee\u4e0e\u4ea7\u54c1\u54c1\u724c\uff0c\u652f\u6301\u9500\u552e\u589e\u957f\n\n5\u3001\u5ba2\u6237\u5173\u7cfb\u7ba1\u7406\uff1a\u901a\u8fc7\u5404\u79cd\u670d\u52a1\u6d3b\u52a8\u63d0\u9ad8\u5ba2\u6237\u6ee1\u610f\u5ea6\uff0c\u5de9\u56fa\u5ba2\u6237\u5173\u7cfb\u5e73\u53f0\uff0c\u638c\u63e1\u7ec8\u7aef\u5ba2\u6237\n\n\u4efb\u804c\u8981\u6c42\uff1a\n\n1\u3001\u672c\u79d1\u53ca\u4ee5\u4e0a\u5b66\u5386\uff0c5\u5e74\u4ee5\u4e0a\u5546\u4e1a\u9879\u76ee\u3001\u516c\u5bd3\u8425\u9500\u8d1f\u8d23\u4eba\u7ecf\u9a8c\n\n2\u3001\u5177\u77e5\u540d\u5f00\u53d1\u5546\u4e00\u3001\u4e8c\u7ebf\u57ce\u5e02\u5927\u578b\u7efc\u5408\u4f53\u9879\u76ee\u7d93\u9a57\n\n3\u3001\u654f\u9510\u7684\u5e02\u573a\u610f\u8bc6\u3001\u5e94\u53d8\u80fd\u529b\u3001\u72ec\u7acb\u5f00\u62d3\u5e02\u573a\u7684\u80fd\u529b\n\n4\u3001\u4f18\u79c0\u7684\u56e2\u961f\u80fd\u529b\u3001\u5b66\u4e60\u80fd\u529b\u3001\u6c9f\u901a\u80fd\u529b\u3001\u534f\u8c03\u80fd\u529b\u548c\u9886\u5bfc\u6c34\u5e73\uff0c\u5584\u4e8e\u534f\u8c03\u8425\u9500\u56e2\u961f\n\n5\u3001\u5177\u5907\u77e5\u540d\u623f\u5730\u4ea7\u9805\u76ee\u6210\u529f\u64cd\u76e4\u53ca\u9500\u552e\u4e1a\u7ee9\u80cc\u666f\u8005\u4f18\u5148", "employment_types": ["Full Time", "Permanent"], "selling_points": ["Strong Real Estate Company", "13 months pay", "Five-day work"], "locations": ["Others - China"], "categories": ["Marketing / Public Relations", "Management", "Marketing - Marketing Communication", "Property / Real Estate", "Others"], "post_time": "2022-01-18T03:11:30Z", "salary": {"currency": "HKD", "max": 159999, "min": 120000, "period": "monthly", "term": null}, "salary_visible": true, "title_keywords": [], "responsibilities": [], "requirements": {"degrees": [], "majors": [], "languages": [], "language_level": [], "hard_skills": [], "soft_skills": [], "languages_combined": []}, "experience_required": {"duration": [], "field": []}}, {"job_id": "100003009043642", "location_code": "hk", "company": "Royal Elite Service Company Limited", "job_title": "\u4fdd\u5b89\u4e3b\u4efb(\u65e5/\u591c\u73ed) \uff0d 5\u5929\u5de5\u4f5c", "description": "\u5165\u8077\u8981\u6c42\ufe55\n\n\u521d\u4e2d\u7a0b\u5ea6\u6216\u5177\u8cc7\u6b77\u67b6\u69cb\u540c\u7b49\u8cc7\u6b77\n\u5177\u5ba2\u6236\u670d\u52d9\u5de5\u4f5c\u7d93\u9a57\u8005\u512a\u5148\n\u9808\u6301\u6709\u4fdd\u5b89\u4eba\u54e1\u8a31\u53ef\u8b49\u53caQAS\u8b49\u66f8\n12\u5c0f\u6642\u53ca5\u5929\u5de5\u4f5c\n\u6708\u85aa\u6700\u9ad8\u53ef\u9054$17,000\n\u5982\u7d93\u9a57\u8f03\u591a\u8005\uff0c\u53ef\u8003\u616e\u8058\u7528\u70ba\u52a9\u7406\u4fdd\u5b89\u7e3d\u76e3\n\n\u00a0\u5de5\u4f5c\u5730\u9ede\ufe55\u99ac\u978d\u5c71\u5340\u4f4f\u5b85\n\n\u4ee5\u4e0a\u8077\u4f4d\u53ef\u4eab\u6709\u512a\u539a\u798f\u5229\uff0c\u5305\u62ec\u6709\u85aa\u5e74\u50479\u5929\u3001\u52e4\u5de5\u734e\u3001\u5404\u7a2e\u7279\u5225\u5047\u671f\u3001\u91ab\u7642\u798f\u5229\u3001\u5b8c\u5584\u57f9\u8a13\u3001\u6649\u5347\u6a5f\u6703\u53ca\u50f1\u54e1\u652f\u63f4\u670d\u52d9\u3002\u500b\u5225\u5c4b\u82d1\u66f4\u8a2d\u6709\u65b0\u5165\u8077\u54e1\u5de5\u734e\u91d1\u548c\u54e1\u5de5\u63a8\u85a6\u734e\u91d1\u7b49\u3002\n\n\u6709\u610f\u8005\uff0c\u8acb\u81f4\u96fb2656 6133\u8207\u90b1\u5c0f\u59d0\u7d04\u898b\u3002\n\n\u9664\u4e0a\u8ff0\u8077\u4f4d\u5916\uff0c\u5c1a\u6709\u5176\u4ed6\u7a7a\u7f3a\u3002\u8acb\u900f\u904e\u4ee5\u4e0b\u65b9\u6cd5\u5c07\u5c65\u6b77\u4ea4\u5230\u5e1d\u8b7d\u4eba\u529b\u8cc7\u6e90\u53ca\u884c\u653f\u90e8\u3002\n\u90f5\u5bc4\uff1a\u89c0\u5858\u5de7\u660e\u885795\u865f\u4e16\u9054\u4e2d\u5fc316\u6a13\n\n\u5e1d\u8b7d\u670d\u52d9\u6709\u9650\u516c\u53f8\u4e43\u5e73\u7b49\u6a5f\u6703\u50f1\u4e3b\uff0c\u800c\u6240\u6709\u6536\u96c6\u8cc7\u6599\u53ea\u7528\u4f5c\u96c6\u5718\u5167\u90e8\u62db\u8058\u4e4b\u7528\u9014\u3002", "employment_types": ["Full Time", "Permanent"], "selling_points": ["\u5177\u5ba2\u6236\u670d\u52d9\u5de5\u4f5c\u7d93\u9a57\u8005\u512a\u5148", "12\u5c0f\u6642\u53ca5\u5929\u5de5\u4f5c", "\u6708\u85aa\u6700\u9ad8\u53ef\u9054$17,000"], "locations": ["Not Specified"], "categories": ["Property / Real Estate", "Property Management", "Others"], "post_time": "2022-01-16T21:50:13Z", "salary": {"currency": null, "max": null, "min": null, "period": "monthly", "term": null}, "salary_visible": false, "title_keywords": [], "responsibilities": [], "requirements": {"degrees": [], "majors": [], "languages": [], "language_level": [], "hard_skills": [], "soft_skills": [], "languages_combined": []}, "experience_required": {"duration": [], "field": []}}, {"job_id": "100003009047090", "location_code": "hk", "company": "Jones Lang LaSalle Ltd", "job_title": "Assistant Facilities Officer", "description": "Assistant Facilities Officer\n\nAbout JLL \u2013\nWe\u2019re JLL. We\u2019re a professional services and investment management firm specializing in real estate. As a Fortune 500 company, we help real estate owners, occupiers and investors achieve their business ambitions.\n\nIf you\u2019re looking to step up your career, JLL is the perfect professional home. With us, you\u2019ll have a chance to innovate with the world\u2019s leading businesses, put that expertise into action on landmark projects, and work on game-changing real estate initiatives. You\u2019ll also make long-lasting professional connections and be inspired by the best. We\u2019re focused on opportunity and want to help you make the most of yours. Achieve your ambitions - join us at JLL!\n\nAbout the role:\n\nAssistant Facilities Officer will be the gatekeeper of the site, he/she will be working closely with our security guards, receptionists and tea attendants, overseeing them and ensuring they carry out all works to a high standard to the client site. He/she will be looking after the relationship with all stakeholders \u2013 management, clients, vendors and landlords.\n\nWhat this job involves:\n\nHow can you help make employees and visitors alike love our office? You\u2019ll do so by arranging for regular preventative maintenance and repairs for our facilities. Scheduling for regular cleaning services and ensuring all office equipment are in good working order are a few of the tasks you\u2019ll do to spruce up the office.\nYou\u2019ll keep an eye out for potential emergencies and carry out steps for managing such situations. You\u2019ll also perform established escalation and incident reporting procedures should such an event take place. Being on the lookout for opportunities to reduce costs and improve our operational standards should also come instinctively to you.\nHow important is security to you?\u00a0 Security is a tall order and calls for an all-hands-on-deck approach. As such, we are always on the lookout for people for whom attention to security details comes naturally. In this role, you\u2019ll help give an extra layer of protection by doing regular checks of our CCTV systems to review the need for maintenance and repairs. You\u2019ll oversee visitor access\u2014clients, contractors, vendors\u2014and maintain logs and filing work of such information on a regular basis. You\u2019ll not only be the \u201cgatekeeper,\u201d but also the \u201cface of JLL,\u201d acting as a back-up receptionist as needed.\nAs you perform a juggling act between helping safeguard our premises and giving a warm reception to our guests, you\u2019ll be working closely with our security guards, receptionists and tea attendants, overseeing them and ensuring they carry out all work to a high standard.\nEvery business aims for client satisfaction\u2014but we take it up a notch! If you can take in the same passion for looking after our relationship with all our stakeholders\u2014management, clients, vendors, landlords\u2014we\u2019ll be more than happy to work with you. Because in this role, you\u2019ll be a vital element in keeping our communication lines with them open and strong. One way to do so is to ensure everyone follows the established key operating procedures to achieve standards. Another way is to schedule regular meetings to understand stakeholder\u2019s needs.\n\nSound like you? To apply you will have:\n\nDo you have more than two years\u2019 experience in facilities management? Are you driven by service excellence? Are you knowledgeable in budgeting and facilities security? We\u2019d love to speak with you!\nExcellent communication skills are vital\u2014both spoken and written\u2014as we\u2019ll expect you to work independently in cascading high-level communications and boosting staff/client satisfaction. And if you know both the English and Chinese languages, that would be super! If you think you possess all these, then let\u2019s work together and explore opportunities.\n\nWhat you can expect from us\n\nWe\u2019re an entrepreneurial, inclusive culture. We succeed together - across the desk and around the globe. We believe the best inspire the best, so we invest in supporting each other, learning together and celebrating our success.\n\nOur Total Rewards program reflects our commitment to helping you achieve your ambitions in career, recognition, well-being, benefits and pay. We\u2019ll offer you a competitive salary and benefits package.\n\nWith us, you\u2019ll develop your strengths and enjoy a career full of varied experiences. We can\u2019t wait to see where your ambitions take you at JLL.\n\n\nApply today!", "employment_types": ["Full Time", "Permanent"], "selling_points": ["Facilities Management", "Several Openings", "Excellent Opportunities"], "locations": ["Airport Area"], "categories": ["Property / Real Estate", "Property Management", "Others"], "post_time": "2022-01-14T02:17:02Z", "salary": {"currency": null, "max": null, "min": null, "period": "monthly", "term": null}, "salary_visible": false, "title_keywords": ["assistant facilities officer"], "responsibilities": ["reporting", "management", "maintenance", "budgeting", "systems", "procedures", "review", "communication", "scheduling", "maintain", "schedule", "cleaning", "costs"], "requirements": {"degrees": [], "majors": [], "languages": ["english", "chinese"], "language_level": [], "hard_skills": ["tea", "maintenance", "cctv", "make", "facilities management"], "soft_skills": ["communication skills", "work independently", "focused", "passion for", "communication", "hands-on", "learning", "driven"], "languages_combined": [{"language": "english", "language_level": []}, {"language": "chinese", "language_level": []}]}, "experience_required": {"duration": ["two years"], "field": ["management", "security"]}}, {"job_id": "100003009039189", "location_code": "hk", "company": "Harbourfront Landmark Premium Services Limited", "job_title": "\u7ba1\u696d\u52a9\u7406 (\u591c\u73ed) [Ref. HL-BA]", "description": "\u7d05\u78e1\u6d77\u540d\u8ed2\n\n\u8aa0\u8058\n\n\n\n\u4e2d\u5b78\u7a0b\u5ea6\n\u5177\u4fdd\u5b89\u5de5\u4f5c\u7d93\u9a57\u8005\u512a\u5148\u8003\u616e\n\u9808\u6301\u6709\u6548\u4fdd\u5b89\u4eba\u54e1\u8a31\u53ef\u8b49\u4e59\u985e\u724c\u7167\n\u7565\u61c2\u96fb\u8166\u64cd\u4f5c\n\u6bcf\u5929\u5de5\u4f5c9\u5c0f\u6642\uff0c\u9700\u8f2a\u4f11\n\n\u672c\u516c\u53f8\u63d0\u4f9b12\u5929\u6709\u85aa\u5e74\u5047\u3001\u91ab\u7642\u8a08\u5283\u3001\u914c\u60c5\u82b1\u7d05\u53ca\u6649\u5347\u6a5f\u6703\u7b49\u3002\u6709\u610f\u8005\u8acb\u81f4\u96fb3157 1129 \u8207\u51bc\u5c0f\u59d0\u806f\u7d61\u6216\u6309 \"Apply Now\" \u905e\u4ea4\u7533\u8acb\u3002\n\n\u7533\u8acb\u4eba\u63d0\u4f9b\u4e4b\u5168\u90e8\u8cc7\u6599\u7d55\u5c0d\u4fdd\u5bc6\u53ca\u53ea\u4f5c\u62db\u8058\u4e4b\u7528", "employment_types": ["Full Time", "Permanent"], "selling_points": ["\u4e2d\u5b78\u7a0b\u5ea6", "\u5177\u4fdd\u5b89\u5de5\u4f5c\u7d93\u9a57\u8005\u512a\u5148\u8003\u616e", "\u6301\u6709\u6548\u4fdd\u5b89\u4eba\u54e1\u8a31\u53ef\u8b49\u4e59\u985e\u724c\u7167"], "locations": ["Hung Hom"], "categories": ["Property / Real Estate", "Property Management", "Others"], "post_time": "2022-01-13T18:54:30Z", "salary": {"currency": null, "max": null, "min": null, "period": null, "term": null}, "salary_visible": false, "title_keywords": [], "responsibilities": [], "requirements": {"degrees": [], "majors": [], "languages": [], "language_level": [], "hard_skills": [], "soft_skills": [], "languages_combined": []}, "experience_required": {"duration": [], "field": []}}, {"job_id": "100003009046234", "location_code": "hk", "company": "Eternity Consultants (HK) Ltd", "job_title": "Leasing and Property Officer (Residential) (double pay+ bonus)", "description": "Our client is a sizable finance company with offices in HK (500+ staff in HK). It is looking for qualified candidates to fill the following post:\n\nResponsibilities:\n\nl\u00a0\u00a0 Handle daily leasing matters for residential properties for boss\n\nl\u00a0\u00a0 Responsible for new lease, renewal and expiration, follow up and documentation\n\nl\u00a0\u00a0 Liaise with real estate agents, prospective and current tenants for new lettings and lease renewals.\n\nl\u00a0\u00a0 Build good relationship with tenants and handle tenant\u2019s enquiries and complaints\n\nRequirements:\n\nl\u00a0\u00a0 Degree holder in Business Administration, Real Estate, or related disciplines\n\nl\u00a0\u00a0 At least 3 years\u2019 relevant experience in leasing and tenancy matters\n\nl\u00a0\u00a0 Good time management, interpersonal, presentation and work independently\n\nl\u00a0\u00a0 Good command of both written and spoken in English and Chinese\n\nFor more jobs, please visit our website:\u00a0www.hketernity.com\n\n\u00a0(Personal data submitted are for recruitment purpose only.)", "employment_types": ["Full Time", "Permanent"], "selling_points": ["Handle residential properties for boss", "-", "-"], "locations": ["Not Specified"], "categories": ["Admin & HR", "Others", "Property / Real Estate", "Property Management", "Others"], "post_time": "2022-01-13T10:03:14Z", "salary": {"currency": null, "max": null, "min": null, "period": "monthly", "term": null}, "salary_visible": false, "title_keywords": ["property officer"], "responsibilities": ["documentation", "liaise with", "good relationship"], "requirements": {"degrees": ["degree holder"], "majors": ["related disciplines", "business administration"], "languages": ["english", "chinese"], "language_level": ["good command"], "hard_skills": [], "soft_skills": ["presentation", "work independently", "time management", "interpersonal"], "languages_combined": [{"language": "english", "language_level": ["good command"]}, {"language": "chinese", "language_level": ["good command"]}]}, "experience_required": {"duration": ["at least 3 years"], "field": ["relevant experience"]}}, {"job_id": "100003009052937", "location_code": "hk", "company": "CK Asset Holdings Limited", "job_title": "Leasing Officer (Fortune Reit)", "description": "Degree in Business or property-related disciplines\nAt least 3 years' experience in\u00a0retail\u00a0leasing, preferably gained from property developer /\u00a0agency\nGood business network with\u00a0retail tenants\u00a0/\u00a0property agencies\nGood negotiation, analytical and presentation skills\nGood command of written and spoken English and Mandarin\u00a0\n\nCandidates with less experience will be considered as Assistant Leasing Officer\n\n\nWe will offer attractive compensation package to the right candidate. Please send application enclosing resume stating career and salary history, expected salary and date of availability to The Senior Manager, Human Resources Department, CK Asset Holdings Limited, 7/F Cheung Kong Center, 2 Queen\u2019s Road Central, Hong Kong or by clicking \u201cApply Now\u201d (in Word format). Please quote the reference of the position you apply for in all correspondences.\n\nWe are an equal opportunity employer and welcome applications from all qualified candidates. Personal data collected will be treated in strictest confidence and handled confidentially by authorized personnel for recruitment-related purposes within the Group. Applicants not hearing from us within six weeks from the date of advertisement may consider their applications unsuccessful.", "employment_types": ["Full Time", "Permanent"], "selling_points": ["Degree in Business or property-related disciplines", "At least 3 years' experience in retail leasing", "Good business network w/ retail tenants/properties"], "locations": ["Shatin Area"], "categories": ["Property / Real Estate", "Property Consultancy", "Property Management", "Others"], "post_time": "2022-01-17T04:36:47Z", "salary": {"currency": null, "max": null, "min": null, "period": null, "term": null}, "salary_visible": false, "title_keywords": ["leasing officer"], "responsibilities": ["personal data", "recruitment"], "requirements": {"degrees": ["degree"], "majors": ["related disciplines", "business"], "languages": ["english", "mandarin"], "language_level": ["good command"], "hard_skills": ["word"], "soft_skills": ["presentation skills", "confidence", "negotiation"], "languages_combined": [{"language": "english", "language_level": ["good command"]}, {"language": "mandarin", "language_level": ["good command"]}]}, "experience_required": {"duration": ["at least 3 years"], "field": ["agency", "developer", "retail"]}}, {"job_id": "100003009048403", "location_code": "hk", "company": "Henderson Land Development Company Limited", "job_title": "MAINTENANCE MANAGER - THE HENDERSON", "description": "Ref. No.: JDB/GWM/MM-TH\n\nOur subsidiary, Goodwill Management Limited, continuously dedicates to providing excellent and valued-added property management services for our landlords and customers\u00a0and now invites high\u00a0caliber\u00a0candidates for the position of :-\u00a0\n\nResponsibilities:\n\n\nSupervising site maintenance team and overseeing all maintenance and operation of facilities for The Henderson\nSetting up the maintenance policies and maintaining the system as per the company\u2019s requirements and statutory requirements\nSetting up the site maintenance team and preparing takeover plan based on the construction progress\nSupervising the site maintenance team to take over the building and carrying out testing and commissioning work\nMonitoring the performance of the site maintenance team and contract-out services\nProviding technical support to the Leasing Team for tenant\u2019s fitout and feasibility study\nVetting tenants\u2019 fitout proposal and monitoring renovation\nCarrying out other duties assigned by supervisor\n\nRequirements:\n\nDegree holder in Building Services or related discipline\nWith professional qualifications such as Chartered Engineer or equivalent\n8 years\u2019 post-qualification experience in commercial developments and at\u00a0least 3 years of which are at managerial level\nKnowledge in BIM is preferred\nGood command of written and spoken Chinese and English\nExcellent communication and interpersonal skills\nMature, able to work independently and under pressure\n\nAttractive salary and fringe benefits will be offered to the successful candidates. Please apply with full resume by mail to\u00a0Personnel Section, Goodwill Management Limited, 9/F., Golden Centre, 188 Des Voeux Road C., Hong Kong\u00a0or by fax at\u00a02530 2528\u00a0or\u00a0visit our homepage at\u00a0http://www.hld.com/management/goodwill/\u00a0or\u00a0by\u00a0clicking\u00a0\"Apply Now\".\n\n\n(Please quote the ref. no. on letter)\n\nPersonal data provided by job applicants will be used for recruitment purpose only.", "employment_types": ["Full Time", "Permanent"], "selling_points": ["Medical Allowance", "Education Allowance", "MPF"], "locations": ["Others"], "categories": ["Property / Real Estate", "Property Management", "Others", "Others", "Others"], "post_time": "2022-01-14T06:28:41Z", "salary": {"currency": null, "max": null, "min": null, "period": "monthly", "term": null}, "salary_visible": false, "title_keywords": ["manager"], "responsibilities": ["supervising", "commissioning", "maintaining", "maintenance", "technical support", "policies", "other duties", "monitoring", "renovation", "testing", "statutory requirements", "plan"], "requirements": {"degrees": ["degree holder"], "majors": ["building services"], "languages": ["english", "chinese"], "language_level": ["good command"], "hard_skills": ["bim", "professional qualifications"], "soft_skills": ["work independently", "communication and interpersonal skills", "under pressure", "mature"], "languages_combined": [{"language": "english", "language_level": ["good command"]}, {"language": "chinese", "language_level": ["good command"]}]}, "experience_required": {"duration": ["at least 3 years", "8 years"], "field": ["commercial", "post-qualification", "managerial"]}}, {"job_id": "100003009048108", "location_code": "hk", "company": "Chinachem Group", "job_title": "Manager - Real Estate", "description": "Responsibilities\nReporting to Senior Manager of real estate division office, the candidate will be responsible for assisting in operation of the Real Estate Division and a viable acquisition strategy that meets the needs of the business.\nPerform market analysis and feasibility study.\nPrepare and evaluate business plans and proposals prepared by the business units / subsidiaries.\nActively source investment opportunities in UK and Greater China. The ideal candidate should have a track record of acquiring and divesting assets in Greater China and UK.\nExecute investments from origination to closing and exit.\nTake a leading role to oversee team members and present investment opportunities to the investment committee.\nRequirements\nDegree qualified in Real Estate/Accounting/Finance.\nProfessional qualifications including RICS / CFA / CPA preferred.\nMinimum 5 years of real estate experience with developers or a leading investment manager. Candidates with less experience may be considered for an assistant manager position.\nExisting network in the advisory, banking, owners/operators in Real Estate\nStrong track record of deal execution in Greater China and UK\nFluent in English and Cantonese and/or Mandarin\nHighly reliable, diligent, meticulous to details and a team player.\nHK office based", "employment_types": ["Full Time", "Permanent"], "selling_points": ["Perform market analysis and feasibility study", "Degree qualified in Real Estate/Accounting", "Minimum 5 years of real estate experience"], "locations": ["Not Specified"], "categories": ["Property / Real Estate", "Property Consultancy", "Property Management", "Others"], "post_time": "2022-01-14T06:29:08Z", "salary": {"currency": null, "max": null, "min": null, "period": "monthly", "term": null}, "salary_visible": false, "title_keywords": ["manager"], "responsibilities": ["evaluate", "reporting", "market analysis", "business plans"], "requirements": {"degrees": ["degree"], "majors": ["finance", "accounting"], "languages": ["cantonese", "english", "mandarin"], "language_level": ["fluent"], "hard_skills": ["cfa", "cpa", "rics", "professional qualifications"], "soft_skills": ["meticulous", "team player", "reliable", "diligent"], "languages_combined": [{"language": "cantonese", "language_level": ["fluent"]}, {"language": "english", "language_level": ["fluent"]}, {"language": "mandarin", "language_level": ["fluent"]}]}, "experience_required": {"duration": ["minimum 5 years"], "field": ["investment"]}}, {"job_id": "100003009051081", "location_code": "hk", "company": "Wharf China Development Limited", "job_title": "Administration Assistant/ Clerk", "description": "Responsibilities:\nHandling clerical duties for the Personnel & Administration Team including assisting in checking/vetting submissions, monthly payroll and related payments, and recruitment requisitions from our Mainland HR offices\nAssisting in performing market research; \u00a0reviewing and controlling administration expenditures and other works as assigned\nRequirements:\n\nA pass in English and Chinese Languages and Mathematics in HKCEE/HKDSE\nWith at least 1 to 2 years clerical relevant experience\u00a0\nSelf-motivated, result-oriented, with good communication and organization skillS\nMeticulous, hardworking and a team player\nFluent spoken English, Cantonese and Putonghua\nProficient in MS Word and Excel\nCandidate with more experience will be considered as Administration Assistant\nWe work 5 days per week.\nInterested parties, please click \"APPLY NOW\" and attach with your application letter and full resume.\u00a0\n\nFor further information of the Wharf Group, please visit our website:\u00a0www.wharfholdings.com", "employment_types": ["Full Time", "Permanent"], "selling_points": [], "locations": ["Tsim Sha Tsui"], "categories": ["Admin & HR", "Others", "HR Supporting Staff", "Property / Real Estate", "Others"], "post_time": "2022-01-15T01:55:40Z", "salary": {"currency": null, "max": null, "min": null, "period": null, "term": null}, "salary_visible": false, "title_keywords": ["administration assistant", "clerk"], "responsibilities": ["hr", "checking", "market research", "recruitment", "payments", "payroll", "administration"], "requirements": {"degrees": ["hkdse"], "majors": ["mathematics"], "languages": ["cantonese", "putonghua", "english", "chinese"], "language_level": ["fluent"], "hard_skills": ["excel", "ms word"], "soft_skills": ["meticulous", "self-motivated", "communication", "organization skills", "team player", "result-oriented", "hardworking"], "languages_combined": [{"language": "cantonese", "language_level": ["fluent"]}, {"language": "putonghua", "language_level": ["fluent"]}, {"language": "english", "language_level": ["fluent"]}, {"language": "chinese", "language_level": []}]}, "experience_required": {"duration": ["at least 1 to 2 years"], "field": ["relevant experience", "clerical", "administration"]}}, {"job_id": "100003009042567", "location_code": "hk", "company": "Guardian Property Management Ltd", "job_title": "Club House Assistant", "description": "F.5 or above\nGood command of spoken and written Chinese and English\nGood PC knowledge in MS Office,\u00a0English typing\u00a0and\u00a0Chinese word processing\nHard working, Good interpersonal skills and able to work independently\nApplicant has customer service experience would be\u00a0an advantage\nShift duty is required\u00a0\nWork Location : Sham Shui Po\n\nApplicants are requested to submit detailed resume with personal particulars, qualifications and experience, present and expected salary by clicking \"Apply Now\"\n\nPlease Quote Job Ref. : CHA/TT/012022\n\n[Personal data provided will be used strictly in accordance with our personal data policies, a copy which will be provided immediately upon request.]", "employment_types": ["Full Time", "Permanent"], "selling_points": [], "locations": ["Sham Shui Po"], "categories": ["Admin & HR", "Clerical / Admin Staff", "Property / Real Estate", "Property Management", "Others"], "post_time": "2022-01-12T08:00:45Z", "salary": {"currency": null, "max": null, "min": null, "period": "monthly", "term": null}, "salary_visible": false, "title_keywords": ["assistant"], "responsibilities": ["customer service experience"], "requirements": {"degrees": [], "majors": [], "languages": ["english", "chinese"], "language_level": ["good command", "good"], "hard_skills": ["pc knowledge", "chinese word processing", "typing", "ms office"], "soft_skills": ["hard working", "customer service", "interpersonal skills", "work independently"], "languages_combined": [{"language": "english", "language_level": ["good command", "good", "good"]}, {"language": "chinese", "language_level": ["good command", "good", "good"]}]}, "experience_required": {"duration": [], "field": ["customer service"]}}, {"job_id": "100003009045765", "location_code": "hk", "company": "Protech Property Management Ltd", "job_title": "Property Officer (with Double Pay)", "description": "Responsible for the general property management duties, handling complaints, liaison with owners and tenants, assist property manager to monitor daily property management issues\nDiploma or above in Property Management or related disciplines\nAt least\u00a04 years' relevant working experience with 2 years in supervisory level\nLess than 4 years' relevant working experience will be considered as Assistant Property Officer\nWell versed in BMO and DMC\nGood command of spoken and written English and Chinese\nCustomer-orientated, good leadership and communication skills\nWorking location:\u00a0 Central / Kowloon Tong\n\nInterested parties please send application with present salary and expected salary by email to Human Resources Department, Room 3501, China Online Centre, 333 Lockhart Road, Wanchai, Hong Kong.", "employment_types": ["Full Time", "Permanent"], "selling_points": [], "locations": ["Others"], "categories": ["Property / Real Estate", "Property Management", "Others"], "post_time": "2022-01-13T08:35:59Z", "salary": {"currency": null, "max": null, "min": null, "period": "monthly", "term": null}, "salary_visible": false, "title_keywords": ["property officer"], "responsibilities": ["communication", "management", "monitor"], "requirements": {"degrees": ["diploma or above"], "majors": ["related disciplines"], "languages": ["english", "chinese"], "language_level": ["good command"], "hard_skills": [], "soft_skills": ["communication skills", "leadership", "responsible"], "languages_combined": [{"language": "english", "language_level": ["good command"]}, {"language": "chinese", "language_level": ["good command"]}]}, "experience_required": {"duration": ["4 years", "at least 4 years", "2 years"], "field": ["supervisory level", "relevant working experience"]}}, {"job_id": "100003009043662", "location_code": "hk", "company": "Royal Elite Service Company Limited", "job_title": "\u6280\u5de5 (Fitter)", "description": "\u5165\u8077\u8981\u6c42\ufe55\n\n\u521d\u4e2d\u7a0b\u5ea6\u6216\u5177\u8cc7\u6b77\u67b6\u69cb\u540c\u7b49\u8cc7\u6b77\n\u51771\u5e74\u6216\u4ee5\u4e0a\u6c34/\u96fb/\u51b7\u6c23/\u6cb9\u6f06\u7d93\u9a57\n\u9808\u6301\u6709\u5e73\u5b89\u54ad\n\u6708\u85aa\u6700\u9ad8\u53ef\u9054$18,000\n\n\u00a0\u5de5\u4f5c\u5730\u9ede\ufe55\u99ac\u978d\u5c71\u5340\u4f4f\u5b85\u00a0\n\n\u4ee5\u4e0a\u8077\u4f4d\u53ef\u4eab\u6709\u512a\u539a\u798f\u5229\uff0c\u5305\u62ec\u6709\u85aa\u5e74\u50479\u5929\u3001\u52e4\u5de5\u734e\u3001\u5404\u7a2e\u7279\u5225\u5047\u671f\u3001\u91ab\u7642\u798f\u5229\u3001\u5b8c\u5584\u57f9\u8a13\u3001\u6649\u5347\u6a5f\u6703\u53ca\u50f1\u54e1\u652f\u63f4\u670d\u52d9\u3002\u500b\u5225\u5c4b\u82d1\u66f4\u8a2d\u6709\u65b0\u5165\u8077\u54e1\u5de5\u734e\u91d1\u548c\u54e1\u5de5\u63a8\u85a6\u734e\u91d1\u7b49\u3002\n\n\u6709\u610f\u8005\uff0c\u8acb\u81f4\u96fb2656 6133\u8207\u90b1\u5c0f\u59d0\u7d04\u898b\u3002\n\n\u9664\u4e0a\u8ff0\u8077\u4f4d\u5916\uff0c\u5c1a\u6709\u5176\u4ed6\u7a7a\u7f3a\u3002\u8acb\u900f\u904e\u4ee5\u4e0b\u65b9\u6cd5\u5c07\u5c65\u6b77\u4ea4\u5230\u5e1d\u8b7d\u4eba\u529b\u8cc7\u6e90\u53ca\u884c\u653f\u90e8\u3002\n\n\u90f5\u5bc4\uff1a\u89c0\u5858\u5de7\u660e\u885795\u865f\u4e16\u9054\u4e2d\u5fc316\u6a13\n\n\u5e1d\u8b7d\u670d\u52d9\u6709\u9650\u516c\u53f8\u4e43\u5e73\u7b49\u6a5f\u6703\u50f1\u4e3b\uff0c\u800c\u6240\u6709\u6536\u96c6\u8cc7\u6599\u53ea\u7528\u4f5c\u96c6\u5718\u5167\u90e8\u62db\u8058\u4e4b\u7528\u9014\u3002", "employment_types": ["Full Time", "Permanent"], "selling_points": ["\u9808\u6301\u6709\u5e73\u5b89\u54ad", "\u51771\u5e74\u6216\u4ee5\u4e0a\u6c34/\u96fb/\u51b7\u6c23/\u6cb9\u6f06\u7d93\u9a57", "\u6708\u85aa\u6700\u9ad8\u53ef\u9054$18,000"], "locations": ["Not Specified"], "categories": ["Engineering", "Others", "Property / Real Estate", "Property Management", "Others"], "post_time": "2022-01-16T21:50:13Z", "salary": {"currency": null, "max": null, "min": null, "period": "monthly", "term": null}, "salary_visible": false, "title_keywords": ["\u6280\u5de5"], "responsibilities": [], "requirements": {"degrees": [], "majors": [], "languages": [], "language_level": [], "hard_skills": [], "soft_skills": [], "languages_combined": []}, "experience_required": {"duration": [], "field": []}}, {"job_id": "100003009048709", "location_code": "hk", "company": "Redpath Partners Limited", "job_title": "General Manager", "description": "Our client is a well-established property management and real estate business in Hong Kong, with extensive market coverage in Hong Kong and Overseas.\n\nKey Mission:\n\nParticipate in defining company\u2019s vision and objectives for development and business expansion in collaboration with the Board of Directors.\nEnsure that company\u2019s objectives are professionally executed and achieved.\nInspire managers and employees to act on the vision and investment objectives of the Board of Directors.\n\nREQUIREMENT\n\nA degree holder in a recognized University, MBA holder or CPA preferred.\nProfessional qualifications in accounting, finance or other business disciplines would be ideal.\nAt least 20 years relevant professional experience in sizable businesses.\nExcellent people management and stakeholder management skills.\nCapable of executive leadership with experience in Hong Kong is critical.\nProven record of achieving desired outcomes including financial returns.\nExtensive knowledge and experience across all critical disciplines of business management, exposure to \u00a0Real Estate or operationally intense business including retail and hospitality would be advantageous but not essential.\u00a0\nGood command of spoken and written Chinese, English and Cantonese is essential.\n\nTo explore this opportunity further please contact Fay Li (fay @ redpathpartners.com).\n\nPlease email CV to us in Word. All applications will be treated with strict confidentiality.\n\nFor more live vacancies please visit www.redpathpartners.com#LI-FL", "employment_types": ["Full Time", "Permanent"], "selling_points": ["Strategic hire reporting to Executive Director", "Hong Kong based newly created position", "Open to current CFO/COO candidates"], "locations": ["Central & Western Area"], "categories": ["Property / Real Estate", "Others", "Building & Construction", "Others"], "post_time": "2022-01-14T07:07:10Z", "salary": {"currency": null, "max": null, "min": null, "period": "monthly", "term": null}, "salary_visible": false, "title_keywords": ["general manager"], "responsibilities": ["management", "contact"], "requirements": {"degrees": ["degree holder"], "majors": [], "languages": ["cantonese", "english", "chinese"], "language_level": ["good command"], "hard_skills": ["business management", "professional qualifications", "word", "cpa", "fl"], "soft_skills": ["extensive", "capable", "leadership", "ideal"], "languages_combined": [{"language": "cantonese", "language_level": ["good command"]}, {"language": "english", "language_level": ["good command"]}, {"language": "chinese", "language_level": ["good command"]}]}, "experience_required": {"duration": ["at least 20 years"], "field": ["management", "business", "retail"]}}, {"job_id": "100003009043755", "location_code": "hk", "company": "Centaline Property Agency Ltd", "job_title": "\u6301\u724c\u71df\u696d\u54e1 / \u6301\u724c\u5730\u7522\u4ee3\u7406 (\u9577\u6c99\u7063/\u5967\u904b\u7ad9/\u85cd\u7530)", "description": "\u8077\u8cac:\n\n\n\u641c\u96c6\u6709\u95dc\u51fa\u552e\u6216\u79df\u8cc3\u7269\u696d\u8cc7\u8a0a\n\u4e86\u89e3\u6f5b\u5728\u7684\u8cb7\u5bb6\u548c\u79df\u6236\u7684\u9700\u6c42\n\u4fc3\u6210\u6a13\u76e4\u4e4b\u8cb7\u8ce3\u53ca\u79df\u8cc3\n\u5411\u5ba2\u6236\u4ecb\u7d39\u9280\u884c\u6309\u63ed\u670d\u52d9\n\n\u8981\u6c42:\n\n\u9808\u6301\u6709\u6548\u71df\u696d\u54e1\u00a0/\u00a0\u5730\u7522\u4ee3\u7406\u724c\u7167\n\u7a4d\u6975\u4e3b\u52d5, \u826f\u597d\u6e9d\u901a\u6280\u5de7\n\n\u00a0\u798f\u5229:\n\n\u5e95\u85aa + \u4f63\u91d1 + \u734e\u91d1\n\u514d\u8cbb\u4e2d\u539f\u8a13\u7df4\u5b78\u9662\u57f9\u8a13\u5404\u985e\u5c08\u696d\u77e5\u8b58\n\u6709\u85aa\u5e74\u5047\u53ca\u75c5\u5047\n\u5a5a\u5047\u53ca\u6069\u6064\u5047\n\u5f37\u7a4d\u91d1\n\u91ab\u7642\u6d25\u8cbc\n\u9032\u4fee\u6d25\u8cbc\n\u4ecb\u7d39\u65b0\u4eba\u734e\u91d1\n\u50f1\u54e1\u8cb7\u6a13/\u79df\u6a13\u514d\u4f63\n\u54e1\u5de5\u8cfc\u7269\u512a\u60e0\n\u5f37\u5927\u96fb\u8166\u8cc7\u6599\u5eab\u53ca\u5f8c\u52e4\u652f\u63f4\uff0c\u52a9\u8f15\u9b06\u5b8c\u6210\u4ea4\u6613\n\u5b8c\u5584\u798f\u5229\u5236\u5ea6\uff0c\u826f\u597d\u6649\u5347\u6a5f\u6703\n\u6709\u610f\u8acb\u806f\u7d61\u4eba\u529b\u8cc7\u6e90\u90e8Whatsapp\u71b1\u7dda: 5941 9906\u67e5\u8a62\u3002\n\n(\u4e00\u5207\u8cc7\u6599\u4fdd\u5bc6\u53ca\u53ea\u4f5c\u62db\u8058\u7528\u9014)", "employment_types": ["Full Time", "Permanent"], "selling_points": ["company training school, education subsidies", "Staff waive housing agency fees, staff discount", "sales, property agent, license agent, real estate"], "locations": ["Not Specified"], "categories": ["Sales, CS & Business Devpt", "Business Development", "Property / Real Estate", "Property Consultancy", "Others"], "post_time": "2022-01-13T01:50:26Z", "salary": {"currency": null, "max": null, "min": null, "period": "monthly", "term": null}, "salary_visible": false, "title_keywords": [], "responsibilities": [], "requirements": {"degrees": [], "majors": [], "languages": [], "language_level": [], "hard_skills": [], "soft_skills": [], "languages_combined": []}, "experience_required": {"duration": [], "field": []}}, {"job_id": "100003009043757", "location_code": "hk", "company": "China Resources Vanguard (Hong Kong) Co Ltd", "job_title": "Leasing Manager / Assistant Leasing Manager", "description": "Job Duties:\n\nIdentify, source, evaluate and secure suitable new site for store expansion\nLease renewals of existing stores and ensure new store openings meet timelines set\nLiaison with internal departments, landlords, property developers, property agents, government bodies and external contractors, etc.\nConduct marketing research on the retail landscape of Hong Kong including existing stores mix and competitor\u2019s stores mix and formulate long term development strategy accordingly\n\nRequirements:\n\nForm 7 or above\nMinimum 5 years relevant experience preferably in retailers, property developers or property agents in which 3 years are managerial level\nGood network of Hong Kong major property developers and agents\nExcellent negotiation, communication and presentation skills\nPro-active, strong business sense and analytical mind\nGood command of spoken and written English, Cantonese and Mandarin\nProficient in PC skills (MS Word/ Excel/ PowerPoint / Chinese Word Processing)\nMore experience candidate would be considered as Senior Leasing Manager\n\nCompetitive remuneration package and benefits will be offered to the successful candidate.\n\n(All information collected will be used for recruitment related purpose only.)", "employment_types": ["Full Time", "Permanent"], "selling_points": ["Form 7 or above", "5 years relevant exp. in retailer or property", "Less experience candidate would be also considered"], "locations": ["Shatin Area"], "categories": ["Property / Real Estate", "Property Consultancy", "Property Management", "Others"], "post_time": "2022-01-13T01:50:25Z", "salary": {"currency": null, "max": null, "min": null, "period": "monthly", "term": null}, "salary_visible": false, "title_keywords": ["leasing manager", "assistant leasing manager"], "responsibilities": ["evaluate", "marketing research"], "requirements": {"degrees": [], "majors": [], "languages": ["cantonese", "english", "chinese", "mandarin"], "language_level": ["good command", "proficient"], "hard_skills": ["excel", "chinese word processing", "powerpoint", "pc skills", "ms word"], "soft_skills": ["negotiation", "business sense", "communication", "presentation skills", "analytical mind", "pro-active"], "languages_combined": [{"language": "cantonese", "language_level": ["good command"]}, {"language": "english", "language_level": ["good command"]}, {"language": "chinese", "language_level": ["proficient"]}, {"language": "mandarin", "language_level": ["good command"]}]}, "experience_required": {"duration": ["3 years", "minimum 5 years"], "field": ["managerial", "property developers", "relevant experience"]}}, {"job_id": "100003009046538", "location_code": "hk", "company": "Sun Hung Kai Properties Ltd", "job_title": "ADMINISTRATIVE ASSISTANT / SECRETARY", "description": "Requirements:\n\n\nDiploma or above\nMinimum 4 years\u2019 administrative experience\nFamiliar with PC software e.g. MS Word, Excel, PowerPoint & Chinese Word Processing\nGood organizational skill and detail-minded\nPolite, pleasant and mature\nHardworking and able to work under pressure\n\nResponsibilities:\n\n\nPerform general team administration duties and secretarial support to the manager\nPrepare payment and handle system data entry\nPerform ad hoc assignments as required\n\nGood remuneration and attractive fringe benefits will be offered to the successful applicant. Interested parties please apply with full resume, present and expected salary, available date by clicking \"Apply Now\".\n\nFor further information, please visit our company website:\u00a0www.shkp.com.\n\n\nWe are an equal opportunity employer and welcome applications from all qualified candidates. All personal data collected will be used for recruitment purpose only.\u00a0 Applicants not hearing from us within 3 months may consider their applications unsuccessful.\u00a0 All personal data collected will be destroyed within 24 months.", "employment_types": ["Full Time", "Permanent"], "selling_points": ["Diploma or above with 4 yrs' administrative exp", "Perform general team administration duties", "Perform secretarial support to manager"], "locations": ["Wan Chai"], "categories": ["Admin & HR", "Clerical / Admin Staff", "Secretary", "Property / Real Estate", "Others"], "post_time": "2022-01-13T13:33:26Z", "salary": {"currency": null, "max": null, "min": null, "period": null, "term": null}, "salary_visible": false, "title_keywords": ["administrative assistant", "secretary"], "responsibilities": ["system data", "payment", "ad hoc assignments", "secretarial support", "administration"], "requirements": {"degrees": ["diploma or above"], "majors": [], "languages": ["chinese"], "language_level": [], "hard_skills": ["excel", "chinese word processing", "powerpoint", "pc", "ms word"], "soft_skills": ["detail-minded", "organizational skill", "polite", "mature", "pleasant", "hardworking", "work under pressure"], "languages_combined": [{"language": "chinese", "language_level": []}]}, "experience_required": {"duration": ["minimum 4 years"], "field": ["administrative"]}}, {"job_id": "100003009054356", "location_code": "hk", "company": "Nice Property Management Limited", "job_title": "Assistant Maintenance Officer (Building Services) / Technical Assistant", "description": "Holder of Diploma or Higher Certificate in Electrical Engineering or Mechanical Engineering or Building Services Engineering from a Hong Kong polytechnic university / polytechnic, the Hong Kong Institute of Vocational Education (IVE) or a technical institute / technical college, or equivalent\n\n\nPlease send resume & expected salary to HR Dept., Nice Property Management Ltd., Room 2-4, 18/F, New Trend Centre, 704 Prince Edward Road East, Kowloon or fax to 21947804, or email\n\nPersonal data collected will be used for recruitment purpose only.", "employment_types": ["Full Time"], "selling_points": [], "locations": ["Hung Hom"], "categories": ["Engineering", "Electrical / Electronics", "Mechanical", "Property / Real Estate", "Others"], "post_time": "2022-01-17T09:15:43Z", "salary": {"currency": null, "max": null, "min": null, "period": "monthly", "term": null}, "salary_visible": false, "title_keywords": ["maintenance officer", "assistant", "technical assistant"], "responsibilities": ["hr", "recruitment", "management", "personal data"], "requirements": {"degrees": ["diploma", "higher certificate"], "majors": ["engineering", "building services", "electrical engineering", "mechanical engineering"], "languages": [], "language_level": [], "hard_skills": ["nice"], "soft_skills": [], "languages_combined": []}, "experience_required": {"duration": [], "field": []}}, {"job_id": "100003009042488", "location_code": "hk", "company": "SAVILLS GUARDIAN", "job_title": "PROPERTY OFFICER", "description": "F.5 or above\nMinimum\u00a02 year\u00a0experience\u00a0in Property Management\nGood command of spoken and written Chinese and English\nGood PC knowledge in MS Office,\u00a0English typing\u00a0and\u00a0Chinese word processing\nThe successful candidate will be responsible for assisting all property management related duties ,clerical work, customer services works and other ad hoc duties assigned by the site manager\n\nWe offer competitive salary package to the right appointee.\u00a0 Applicants are requested to submit detailed resume with present and expected salary by\u00a0 clicking \"Apply Now\" .\n\nPlease Quote Job Ref. : PO/ECC/012022\n\n[Personal data provided will be used strictly in accordance with our personal data policies, a copy which will be provided immediately upon request.]", "employment_types": ["Full Time", "Permanent"], "selling_points": [], "locations": ["Central & Western Area"], "categories": ["Admin & HR", "Clerical / Admin Staff", "Property / Real Estate", "Property Management", "Others"], "post_time": "2022-01-12T07:42:54Z", "salary": {"currency": null, "max": null, "min": null, "period": "monthly", "term": null}, "salary_visible": false, "title_keywords": ["property officer"], "responsibilities": ["ad hoc duties", "management", "customer services"], "requirements": {"degrees": [], "majors": [], "languages": ["english", "chinese"], "language_level": ["good command", "good"], "hard_skills": ["pc knowledge", "chinese word processing", "typing", "ms office"], "soft_skills": ["responsible"], "languages_combined": [{"language": "english", "language_level": ["good command", "good", "good"]}, {"language": "chinese", "language_level": ["good command", "good", "good"]}]}, "experience_required": {"duration": ["minimum 2 year"], "field": ["management"]}}, {"job_id": "100003009048402", "location_code": "hk", "company": "Henderson Land Development Company Limited", "job_title": "SENIOR ASSISTANT MAINTENANCE MANAGER", "description": "Ref. No.: JDB/GWM/SAMM\nOur subsidiary, Goodwill Management Limited, continuously dedicates to providing excellent and valued-added property management services for our landlords and customers\u00a0and now invites high\u00a0caliber\u00a0candidates for the position of:-\n\n\nDegree holder in Building Services Engineering or related discipline\nHolder of professional qualification preferred (e.g. HKIE, CIBSE etc.)\nHolder of Registration Certificate of Electrical Worker (Grade B or above)\nMinimum 11 years\u2019 solid experience in planning, implementing and monitoring building maintenance with 6 years\u2019 supervisory experience inclusive\nLead the technical team to carry out routine and preventive maintenance\nProficiency in both written Chinese and English\nStrong leadership and interpersonal skills and able to work under pressure\nAttractive salary and fringe benefits will be offered to the successful candidates. Please apply with full resume by mail to\u00a0Personnel Section, Goodwill Management Limited, 9/F., Golden Centre, 188 Des Voeux Road C., Hong Kong\u00a0or by fax at\u00a02530 2528\u00a0or\u00a0visit our homepage at\u00a0http://www.hld.com/management/goodwill/\u00a0or\u00a0by\u00a0clicking \"Apply Now\".\n(Please quote the ref. no. on letter)\nPersonal data provided by job applicants will be used for recruitment purpose only.", "employment_types": ["Full Time", "Permanent"], "selling_points": ["Medical Allowance", "Education Allowance", "MPF"], "locations": ["Others"], "categories": ["Property / Real Estate", "Property Management", "Others", "Others", "Others"], "post_time": "2022-01-14T06:28:40Z", "salary": {"currency": null, "max": null, "min": null, "period": "monthly", "term": null}, "salary_visible": false, "title_keywords": ["manager", "assistant"], "responsibilities": ["management", "maintenance", "monitoring", "planning", "work under pressure"], "requirements": {"degrees": ["certificate", "degree holder"], "majors": ["building services", "engineering"], "languages": ["english", "chinese"], "language_level": ["proficiency"], "hard_skills": ["no", "hkie", "maintenance"], "soft_skills": ["leadership", "interpersonal skills", "work under pressure"], "languages_combined": [{"language": "english", "language_level": ["proficiency"]}, {"language": "chinese", "language_level": ["proficiency"]}]}, "experience_required": {"duration": ["6 years", "minimum 11 years"], "field": ["supervisory experience", "maintenance", "planning"]}}, {"job_id": "100003009034672", "location_code": "hk", "company": "S.H.K. Real Estate Management Company Limited", "job_title": "\u7269\u696d\u52a9\u7406\u54e1(\u4e2d\u73ed: 14:30 - 23:30)", "description": "\u5354\u52a9\u57f7\u884c\u9ad8\u7d1a\u5546\u696d\u5927\u5ec8\u4e4b\u65e5\u5e38\u7ba1\u7406\u53ca\u4e8b\u52d9\n\u6bcf\u5929\u5de5\u4f5c9\u5c0f\u6642\n\u4e0d\u9700\u8f2a\u73ed\u5de5\u4f5c\n\u4e2d\u4e94\u7a0b\u5ea6\u6216\u5177\u8cc7\u6b77\u67b6\u69cb\u540c\u7b49\u8cc7\u6b77\n\u9808\u6301\u6709\u6709\u6548\u300c\u4fdd\u5b89\u4eba\u54e1\u8a31\u53ef\u8b49\u300d\u53ca\u8a8d\u53efQAS\u8a3c\u66f8\n\u6b61\u8fce\u7121\u76f8\u95dc\u7d93\u9a57\u8005\u61c9\u5fb5\n\u85aa\u91d1\u53ef\u9ad8\u9054\u6bcf\u6708$17,000\n\n\u4ee5\u4e0a\u8077\u4f4d\u53ef\u4eab\u6709\u512a\u539a\u54e1\u5de5\u798f\u5229\uff0c\u5305\u62ec\u6709\u85aa\u5e74\u50479\u5929\u3001\u52e4\u5de5\u734e\u3001\u81b3\u98df\u6d25\u8cbc\u3001\u5e74\u7d42\u96d9\u7ce7\u3001\u5e74\u7d42\u734e\u91d1\u3001\u91ab\u7642\u798f\u5229\u3001\u5b8c\u5584\u57f9\u8a13\u53ca\u6649\u5347\u6a5f\u6703\u3002\n\n\u6709\u610f\u8005\uff0c\u8acb\u81f4\u96fb\u4ee5\u4e0b\u806f\u7d61\u4eba\u7533\u8acb\uff1a\n\n\u7063\u4ed4\u5340\uff1a\n\u96fb\u8a71\uff1a9710 0179 \u6e6f\u5148\u751f\n\n\u9664\u4e0a\u8ff0\u8077\u4f4d\u5916\uff0c\u5c1a\u6709\u5176\u4ed6\u7a7a\u7f3a\u3002\u8acb\u900f\u904e\u4ee5\u4e0b\u65b9\u6cd5\u5c07\u5c65\u6b77\u4ea4\u5230S.H.K.\u7269\u696d\u7ba1\u7406\u6709\u9650\u516c\u53f8\u4e4b\u4eba\u529b\u8cc7\u6e90\u53ca\u884c\u653f\u90e8\u3002\n\n\u90f5\u5bc4\uff1a\u89c0\u5858\u5de7\u660e\u885795\u865f\u4e16\u9054\u4e2d\u5fc316\u6a13\u3000\u50b3\u771f\uff1a2827 2125\n\n\nS.H.K. \u7269\u696d\u7ba1\u7406\u6709\u9650\u516c\u53f8\u4e43\u5e73\u7b49\u6a5f\u6703\u50f1\u4e3b\uff0c\u800c\u6240\u6709\u6536\u96c6\u8cc7\u6599\u7d55\u5c0d\u4fdd\u5bc6\u53ca\u53ea\u7528\u4f5c\u96c6\u5718\u5167\u90e8\u62db\u8058\u4e4b\u7528\u9014\u3002", "employment_types": ["Full Time", "Permanent"], "selling_points": ["\u4e0d\u9700\u8f2a\u73ed\u5de5\u4f5c", "\u53ef\u4eab9\u5929\u5e74\u5047\uff0c\u91ab\u7642\u798f\u5229\u7b49", "\u6bcf\u5929\u5de5\u4f5c9\u5c0f\u6642"], "locations": ["Not Specified"], "categories": ["Property / Real Estate", "Property Management", "Others", "Others", "Security / Safety Control"], "post_time": "2022-01-10T03:54:13Z", "salary": {"currency": null, "max": null, "min": null, "period": "monthly", "term": null}, "salary_visible": false, "title_keywords": [], "responsibilities": [], "requirements": {"degrees": [], "majors": [], "languages": [], "language_level": [], "hard_skills": [], "soft_skills": [], "languages_combined": []}, "experience_required": {"duration": [], "field": []}}, {"job_id": "100003009047640", "location_code": "hk", "company": "Goodwell Property Management Ltd", "job_title": "Recreation Assistant (Ref: RA/J)", "description": "F.5 / HKDSEE\u00a0or certificate in related disciplines\nAssist daily operation, organize activities and handle customer enquiries\nSelf-motivated, diligent, able to work independently and under pressure\nProficient in MS Office and Chinese word processing\nGood command of both\u00a0written and spoken\u00a0English and Chinese\nShift duty and work on weekends and Public Holidays is required\n\nWe will offer attractive compensation package to the right candidate. Please send application enclosing resume stating career and salary history, expected salary and date of availability to The Human Resources Manager, Goodwell Property Management Limited, 2/F New Treasure Centre, 10 Ng Fong Street, San Po Kong, Kowloon\u00a0or\u00a0by clicking \u201cApply Now\u201d (in Word format). Please quote the reference of the position you apply for in all correspondences.\n\nWe are an equal opportunity employer and welcome applications from all qualified candidates.\u00a0 Personal data collected will be treated in strictest confidence and handled confidentially by authorized personnel for recruitment-related purposes within the Group. Applicants not hearing from us within six weeks from the date of\u00a0application may consider their applications unsuccessful.\n\n(Our website : http://www.goodwell.com.hk/)", "employment_types": ["Full Time", "Permanent"], "selling_points": ["Diploma holder or above", "Assist daily operation, organize activities", "Perform daily clerical duties"], "locations": ["Kwai Hing"], "categories": ["Beauty Care / Health", "Athletics / Fitness / Sports & Recreation", "Property / Real Estate", "Property Management", "Others"], "post_time": "2022-01-15T03:49:46Z", "salary": {"currency": null, "max": null, "min": null, "period": null, "term": null}, "salary_visible": false, "title_keywords": ["recreation assistant"], "responsibilities": ["management", "handle customer enquiries", "daily operation", "website", "recruitment", "personal data"], "requirements": {"degrees": ["certificate"], "majors": ["related disciplines"], "languages": ["english", "chinese"], "language_level": ["good command", "proficient"], "hard_skills": ["chinese word processing", "word", "ms office"], "soft_skills": ["self-motivated", "confidence", "under pressure", "work independently", "diligent"], "languages_combined": [{"language": "english", "language_level": ["good command"]}, {"language": "chinese", "language_level": ["good command", "proficient"]}]}, "experience_required": {"duration": [], "field": []}}, {"job_id": "100003009048829", "location_code": "hk", "company": "Hong Kong Air Cargo Terminals Limited (Hactl)", "job_title": "Technical Supervisor (Building Facilities) \u6280\u8853\u4e3b\u4efb (\u5c4b\u5b87\u8a2d\u65bd)", "description": "\u8077\u8cac\n\n\u8ca0\u8cac\u8ca8\u7ad9\u5167\u5c4b\u5b87\u8a2d\u65bd\u5305\u62ec\u6ce5\u6c34\u3001\u9580\u9396\u3001\u4f9b\u6c34\u53ca\u6392\u6c34\u7cfb\u7d71\u7b49\u9805\u76ee\u7684\u7dad\u4fee\u53ca\u4fdd\u990a\n\u5206\u6790\u640d\u58de\u6210\u56e0\u4e26\u4f7f\u7528\u9069\u7576\u7684\u7dad\u4fee\u5668\u68b0\u3001\u5de5\u5177\u548c\u6750\u6599\n\u5354\u52a9\u5236\u5b9a\u53ca\u8ddf\u9032\u7dad\u4fee\u5de5\u4f5c\u9032\u5ea6\u8868\n\u53ef\u7368\u7acb\u8655\u7406\u7dad\u4fee\u5de5\u4f5c\n\u6307\u6d3e\u53ca\u76e3\u7763\u516c\u53f8\u5167\u90e8\u6280\u8853\u54e1\u4e26\u78ba\u4fdd\u5176\u4f9d\u7167\u516c\u53f8\u8981\u6c42\u53ca\u5b89\u5168\u6e96\u5247\u9032\u884c\u7dad\u4fee\u5de5\u4f5c\n\u76e3\u7763\u5de5\u7a0b\u627f\u8fa6\u5546\u4e26\u78ba\u4fdd\u5176\u4f9d\u7167\u516c\u53f8\u8981\u6c42\u53ca\u5b89\u5168\u6e96\u5247\u65bd\u5de5\n\u5354\u52a9\u4e0a\u7d1a\u8ddf\u9032\u3001\u6e2c\u8a66\u548c\u9a57\u6536\u9805\u76ee\u5de5\u7a0b\n\u6574\u7406\u53ca\u59a5\u5584\u5132\u5b58\u7dad\u4fee\u8207\u4fdd\u990a\u7684\u6587\u4ef6\u53ca\u8cc7\u6599\n\u4f9d\u7167\u516c\u53f8\u5b89\u5168\u653f\u7b56\u548c\u7a0b\u5e8f\u9032\u884c\u5176\u4ed6\u5c4b\u5b87\u8a2d\u65bd\u76f8\u95dc\u5de5\u4f5c\n\n\u5165\u8077\u8981\u6c42\n\n\u51775\u5e74\u6709\u95dc\u5c4b\u5b87\u8a2d\u65bd\u7dad\u4fee\u4fdd\u990a\u7d93\u9a57 \u00a0\n\u6301\u6709\u5c4b\u5b87\u8a2d\u65bd\u76f8\u95dc\u5de5\u7a0b\u4e4b\u8b49\u66f8\u6216\u6587\u6191\n\u61c2\u57fa\u672c\u82f1\u8a9e\u6703\u8a71\uff0c\u80fd\u95b1\u8b80\u53ca\u66f8\u5beb\u7c21\u55ae\u82f1\u6587\n\u53ef\u5373\u6642\u4e0a\u73ed\u512a\u5148\u8003\u616e\n\n\u5de5\u4f5c\u6642\u9593\u00a0\u00a0\n\n\u8f2a\u73ed\u5236\uff0c\u4e00\u661f\u671f\u5de5\u4f5c\u516d\u5929\uff0c\u6bcf\u73ed8\u5c0f\u664215\u5206\u9418 (\u5305\u62ec1\u5c0f\u6642\u7528\u81b3\u6642\u9593)\n\n\u798f\u5229\n\n\u8fb2\u66c6\u5e74\u82b1\u7d05\u3001\u914c\u60c5\u82b1\u7d05\u3001\u4ea4\u901a\u6d25\u8cbc\u3001\u52a0\u73ed\u6d25\u8cbc\u3001\u5e74\u5ea6\u5b89\u5168\u734e\u91d1\u3001\u5b63\u5ea6\u7279\u5225\u51fa\u52e4\u734e\u91d1\u3001\u50f1\u4e3b\u984d\u5916\u5f37\u7a4d\u91d1\u4f9b\u6b3e\u3001\u91ab\u7642\u4fdd\u969c \u2013 \u5305\u62ec\u5bb6\u5c6c\u3001\u81ea\u9858\u6027\u7259\u79d1\u4fdd\u5065 \u2013 \u5305\u62ec\u5bb6\u5c6c\u3001\u4eba\u58fd\u4fdd\u96aa\u3001\u751f\u65e5\u5047\u671f\u3001\u984d\u5916\u6709\u85aa\u5e74\u5047\u3001\u52de\u5de5\u53ca\u516c\u773e\u5047\u671f\u3001\u5a5a\u5047\u3001\u7522\u5047\u3001\u4f8d\u7522\u5047\u3001\u521d\u751f\u5b30\u5152\u79ae\u7269\u3001\u9ad4\u80b2\u9928\u3001\u514d\u8cbb\u7a7f\u68ad\u5df4\u58eb\n\n\u7533\u8acb\u8fa6\u6cd5\n\n\u7533\u8acb\u8005\u8acb\u628a\u7533\u8acb\u4fe1\u53ca\u5c65\u6b77\u50b3\u771f\u81f32753 2244\uff1b\u6216\u96fb\u90f5\u81f3\u516c\u53f8\u96fb\u90f5\uff1b\u6216\u5bc4\u5f80\u9999\u6e2f\u570b\u969b\u6a5f\u5834\u8d85\u7d1a\u4e00\u865f\u8ca8\u7ad9\u8fa6\u516c\u5927\u6a13\u5317\u5ea7\u516d\u6a13\u4eba\u529b\u8cc7\u6e90\u90e8\u6536 (\u8acb\u8a3b\u660e\u7533\u8acb\u8077\u4f4d\u53ca\u53c3\u8003\u7de8\u865f)\n\n\u00a0\u672c\u516c\u53f8\u7db2\u5740:\u00a0https://careers.hactl.com/\n\n\u00a0\u5982\u7533\u8acb\u4eba\u65bc\u56db\u661f\u671f\u5167\u672a\u7372\u9762\u8a66\u901a\u77e5\uff0c\u5373\u8868\u793a\u8a72\u7533\u8acb\u672a\u80fd\u6210\u529f\u3002\u7533\u8acb\u4eba\u6240\u63d0\u4f9b\u4e4b\u500b\u4eba\u8cc7\u6599\u53ea\u4f9b\u62db\u8058\u4e4b\u7528\uff0c\u672a\u88ab\u8058\u7528\u4eba\u58eb\u4e4b\u8cc7\u6599\u6703\u5728\u516d\u500b\u6708\u5167\u88ab\u92b7\u6bc0\u3002", "employment_types": ["Full Time", "Permanent"], "selling_points": ["\u7269\u696d\u6a13\u5b87\u8a2d\u65bd\u4e4b\u7dad\u4fee\u3001\u4fdd\u990a", "\u63d0\u4f9b\u4ea4\u901a\u6d25\u8cbc\u53ca\u514d\u8cbb\u7a7f\u68ad\u5df4\u58eb", "\u4eab\u6709\u96d9\u7ce7\u53ca\u82b1\u7d05 / \u6d25\u8cbc"], "locations": ["Airport Area"], "categories": ["Building & Construction", "Architectural Services", "Building / Construction / QS", "Property / Real Estate", "Others"], "post_time": "2022-01-14T07:22:15Z", "salary": {"currency": null, "max": null, "min": null, "period": "monthly", "term": null}, "salary_visible": false, "title_keywords": ["\u6280\u8853\u4e3b\u4efb", "technical supervisor"], "responsibilities": [], "requirements": {"degrees": [], "majors": [], "languages": [], "language_level": [], "hard_skills": [], "soft_skills": [], "languages_combined": []}, "experience_required": {"duration": [], "field": []}}, {"job_id": "100003009051514", "location_code": "hk", "company": "Rectrix Group Limited", "job_title": "Senior Manager - Office Leasing (Reputable Property Developer in HK)", "description": "About Rectrix\u00a0\nRectrix is specialist recruitment consultancy formed by a team of highly diligent recruiters with a proven track record in end-to-end delivery from mid\u00a0to senior placements within the built\u00a0environment industry.\n\nAbout this Employer\nPrestigious property developer based in Hong Kong with a brand which is reputable for developing and managing a premium commercial complex in Hong Kong. Upon recent business expansion, the Group is going to look for a Senior Leasing Manager to be responsible for the full-spectrum leasing management of the commercial portfolio for the Group.\u00a0\n\nResponsibilities:\n\n\nAccountable for the overall formulation of leasing & marketing strategies for office leasing portfolio in Hong Kong.\nManage and facilitate all leasing liaisons and coordination with internal and external parties including tenant management, leasing enquiry, pre-leasing administration, new lettings, rent reviews, leasing negotiation and documentation of the leasing proposal.\nPrepare\u00a0regular report on the overall leasing performance and business plan.\nUndergo market research on the rental trend & occupancy rate.\nPerform rental forecast, budgeting and expenses from agency, fitting-out and marketing activities.\u00a0\n\nRequirements:\n\nDegree holder in Real Estate, Surveying, Business Administration or related disciplines.\nAt least 12 years of solid experiences in leasing management of office portfolio in Hog Kong and preferably with over 5 years working at managerial grade.\u00a0\nProven track record working in renowned property developers with office leasing in Hong Kong.\u00a0\nStrong networks with real estate agents and potential tenants.\u00a0\nEnergetic, highly motivated, strive for excellence and high level of accountability.\nExcellent in inter-personal communication skill.\nProficient in both written and spoken English and Chinese.\nLess experienced applicant would be considered as Leasing Manager.\nThis is an unique opportunity to work for a renowned property developer that continually drives and offers the upward potential for strong career progression throughout the organisation. \u00a0\nIn return, successful applicant will be offered a permanent position and receive a highly\u00a0competitive\u00a0salary package alongside market\u00a0leading\u00a0benefits with attractive performance bonus. If you are interested in this position, please send your updated resume to info @ rectrix-group.com", "employment_types": ["Full Time"], "selling_points": ["Leasing Management, Office Portfolio", "Reputable Developer, Attractive Package", "Excellent Career Prospect & Sustainable"], "locations": ["Not Specified"], "categories": ["Sales, CS & Business Devpt", "Business Development", "Property / Real Estate", "Property Consultancy", "Others"], "post_time": "2022-01-16T07:08:26Z", "salary": {"currency": null, "max": null, "min": null, "period": "monthly", "term": null}, "salary_visible": false, "title_keywords": ["senior manager", "developer"], "responsibilities": ["management", "marketing strategies", "budgeting", "internal and external parties", "coordination with", "market research", "expenses", "business plan", "forecast", "documentation", "prepare regular report", "administration"], "requirements": {"degrees": ["degree holder"], "majors": ["related disciplines", "business administration", "surveying"], "languages": ["english", "chinese"], "language_level": ["proficient"], "hard_skills": [], "soft_skills": ["accountability", "inter-personal", "communication skill", "interested in", "unique", "energetic", "motivated", "organisation", "strive for excellence"], "languages_combined": [{"language": "english", "language_level": ["proficient"]}, {"language": "chinese", "language_level": ["proficient"]}]}, "experience_required": {"duration": ["5 years", "at least 12 years"], "field": ["managerial", "management"]}}, {"job_id": "100003009047940", "location_code": "hk", "company": "Jones Lang LaSalle Ltd", "job_title": "Facilities Officer", "description": "\u201cPosition\u201d\n\nAbout JLL \u2013\n\nWe\u2019re JLL. We\u2019re a professional services and investment management firm specializing in real estate. As a Fortune 500 company, we help real estate owners, occupiers and investors achieve their business ambitions.\n\nIf you\u2019re looking to step up your career, JLL is the perfect professional home. With us, you\u2019ll have a chance to innovate with the world\u2019s leading businesses, put that expertise into action on landmark projects, and work on game-changing real estate initiatives. You\u2019ll also make long-lasting professional connections and be inspired by the best. We\u2019re focused on opportunity and want to help you make the most of yours. Achieve your ambitions - join us at JLL!\n\nAbout the role:\n\nTo support deliver high quality, prompt and courteous Facility Management services in support of Client's business needs in a safe working environment.\n\nWhat this job involves:\n\nChase daily work order status\nAd-hoc operation works Assistance\nSupport HACCP document preparation\nRespond for housekeeping and daily building operation\nPerform regular visual inspection to assure building condition in good shape\nRespond stakeholders\u2019 requests\nRespond for supervising the daily supportive functions, including cleaning services, security services, repairs etc\nEnsure day-to-day operation in managing portfolio in smooth and zero accident condition\nLiaise with contractors and end-users for the implementation of repair and maintenance of building services\nManage and monitor the performance of service providers.\nSupport the general administration function of the team\nBe Frist Aider\n\nSound like you? To apply you will have:\n\nHigher Diploma / Degree in Building Studies, Facility Management and Property Management\nA minimum of 2 years relevant working experience in the corporate real estate, facilities\nStrong customer service and interpersonal skills\nGood understanding of facilities / housekeeping management\nGood command of both spoken and written English and Chinese\nBasic computer skills in Microsoft Office, MS project, powerpoint, excel and Autocad\nIndependent, self-motivated, flexible, responsible and willing to work under pressure\n\n\n\u00a0What you can expect from us\n\nWe\u2019re an entrepreneurial, inclusive culture. We succeed together - across the desk and around the globe. We believe the best inspire the best, so we invest in supporting each other, learning together and celebrating our success.\n\nOur Total Rewards program reflects our commitment to helping you achieve your ambitions in career, recognition, well-being, benefits and pay. We\u2019ll offer you a competitive salary and benefits package.\n\nWith us, you\u2019ll develop your strengths and enjoy a career full of varied experiences. We can\u2019t wait to see where your ambitions take you at JLL.\n\nApply today!", "employment_types": ["Temporary"], "selling_points": ["Facilities Management", "Vendor Management", "Good Opportunities"], "locations": ["Shatin Area"], "categories": ["Property / Real Estate", "Others"], "post_time": "2022-01-14T04:19:40Z", "salary": {"currency": null, "max": null, "min": null, "period": "monthly", "term": null}, "salary_visible": false, "title_keywords": ["officer"], "responsibilities": ["ad-hoc", "management", "supervising", "maintenance", "housekeeping", "work under pressure", "quality", "implementation", "inspection", "repair", "customer service", "monitor the performance", "cleaning", "visual", "liaise with contractors", "day-to-day operation", "administration"], "requirements": {"degrees": ["diploma", "degree"], "majors": ["building studies"], "languages": ["english", "chinese"], "language_level": ["good command"], "hard_skills": ["excel", "basic", "maintenance", "microsoft office", "powerpoint", "make", "safe", "computer skills", "visual inspection", "autocad"], "soft_skills": ["flexible", "supportive", "courteous", "independent", "self-motivated", "focused", "responsible", "prompt", "customer service", "interpersonal skills", "learning", "smooth", "work under pressure"], "languages_combined": [{"language": "english", "language_level": ["good command"]}, {"language": "chinese", "language_level": ["good command"]}]}, "experience_required": {"duration": ["minimum of 2 years"], "field": ["relevant working experience"]}}, {"job_id": "100003009046412", "location_code": "hk", "company": "Harriman Property Management Limited", "job_title": "Senior Officer (Business Development)", "description": "Responsibilities\n\n\nImplement leasing services for the Company portfolio of luxury residential buildings\nLiaise with owners, tenants, property agents and other relevant parties for new lease and tenancy renewal;\nPrepare, review, negotiate and finalize contracts/agreements and legal documentations with legal counsels and property agents\nHandle tenant related inquiries, complaints and emergency issues\nExplore what new services are popular to the residents\nLiaise with market qualified service providers to explore any cooperation opportunity\nDevelop and execute new services implementation plan\nCoordinate with PM team to ensure smooth new services implementation\nRegularly review and evaluate the new services provision result and make improvement\nRequirements\n\nTertiary educated in Property / Housing Management or related disciplines with at least 5 years\u2019 relevant experience in property and/or clubhouse management\nEAA license is an advantage\nOutgoing with good negotiation, interpersonal and communication skills\nSelf-motivated, detail-oriented, proactive and able to work under pressure\nSound PC knowledge on MS Word, Excel and PowerPoint\nGood command of both spoken and written English and Chinese including Putonghua\nOutdoor work and shift duty on weekend and public holidays are required\nWe offer ample opportunities for career development and attractive salary package commensurate with experience and qualifications. \u00a0Interested parties please apply with full resume via\u00a0\u201cAPPLY NOW\u201d.\u00a0\n\nFor further information on Wheelock Properties (Hong Kong) Limited, please visit our website:\u00a0www.wheelockpropertieshk.com.\n\nWe are an equal opportunities employer and invite applications from all qualified candidates. Personal data collected will be treated in strict confidence and handled by authorized persons for recruitment-related purposes only within The Wheelock & Wharf Group. Applicants not hearing from us within 2 months may consider their applications unsuccessful.\u00a0", "employment_types": ["Full Time", "Permanent"], "selling_points": [], "locations": ["Kwun Tong"], "categories": ["Property / Real Estate", "Property Consultancy", "Others", "Sales, CS & Business Devpt", "Sales - Real Estate"], "post_time": "2022-01-13T18:55:22Z", "salary": {"currency": null, "max": null, "min": null, "period": null, "term": null}, "salary_visible": false, "title_keywords": ["senior officer"], "responsibilities": ["contracts", "review", "coordinate with", "implementation", "develop", "evaluate", "plan", "liaise with"], "requirements": {"degrees": [], "majors": [], "languages": ["putonghua", "english", "chinese"], "language_level": ["good command"], "hard_skills": ["excel", "pc knowledge", "powerpoint", "ms word"], "soft_skills": ["outgoing", "communication skills", "self-motivated", "negotiation", "detail-oriented", "proactive", "interpersonal", "work under pressure"], "languages_combined": [{"language": "putonghua", "language_level": ["good command"]}, {"language": "english", "language_level": ["good command"]}, {"language": "chinese", "language_level": ["good command"]}]}, "experience_required": {"duration": ["at least 5 years"], "field": ["related", "management", "relevant experience"]}}, {"job_id": "100003009051513", "location_code": "hk", "company": "Rectrix Group Limited", "job_title": "Assistant Leasing Manager - Retail Mall (Reputable Property Developer in HK)", "description": "About Rectrix\u00a0\nRectrix is specialist recruitment consultancy formed by a team of highly diligent recruiters with a proven track record in end-to-end delivery from mid\u00a0to senior placements within the built\u00a0environment industry.\n\nAbout this Employer\nPrestigious property developer based in Hong Kong with a brand which is reputable for developing a variety of premium commercial complexes and shopping malls in Hong Kong. Upon recent business expansion, the Group is going to look for an Assistant Leasing Manager to be responsible for the leasing management of the premium retail portfolio in Hong Kong.\n\nResponsibilities:\n\nManage and facilitate leasing liaisons and coordination including\u00a0new lettings, rent renewal, tenant management, leasing enquiry, leasing negotiation and documentation of the leasing proposal.\nBuild and maintain healthy relationship\u00a0with tenants, customers and property agencies\nCoordinate with internal and external parties for portfolio planning, new built development and asset enhancement projects.\u00a0\nPrepare reports offer letters, tenancy agreement and leasing performance and business plan when necessary.\nUndergo market research on the rental trend & occupancy rate.\nPerform rental forecast, budgeting and expenses from agency, fitting-out and marketing activities.\u00a0\n\nRequirements:\n\nDegree holder in Real Estate/ Marketing/Business Administration or related disciplines.\nAt least 5 years of solid experiences in leasing management of high-end retail portfolio in Hog Kong.\nPrevious working experiences in sizeable property developers are preferred.\nProven track record in identifying new tenants and retaining high quality tenants.\u00a0\u00a0\nEnergetic, highly motivated, strive for excellence and high level of accountability.\nExcellent in negotiation and inter-personal communication skill.\nProficient in both written and spoken English and Chinese.\nLess experienced applicant would be considered as Senior Leasing Officer.\u00a0\nThis is an unique opportunity to work for a renowned property developer that continually drives and offers the upward potential for strong career progression throughout the organisation. \u00a0\nIn return, successful applicant will be offered a permanent position and receive a highly\u00a0competitive\u00a0salary package alongside market\u00a0leading\u00a0benefits with attractive performance bonus. If you are interested in this position, please send your updated resume to info @ rectrix-group.com", "employment_types": ["Full Time"], "selling_points": ["Leasing, High-end Retail Portfolio", "Reputable Developer, Attractive Package", "Good Career Prospect & Sustainable Development"], "locations": ["Not Specified"], "categories": ["Sales, CS & Business Devpt", "Business Development", "Property / Real Estate", "Property Consultancy", "Others"], "post_time": "2022-01-16T07:07:12Z", "salary": {"currency": null, "max": null, "min": null, "period": "monthly", "term": null}, "salary_visible": false, "title_keywords": ["developer", "assistant leasing manager"], "responsibilities": ["management", "prepare reports", "budgeting", "internal and external parties", "coordinate with", "letters", "market research", "expenses", "maintain", "coordination", "business plan", "documentation", "forecast", "enhancement projects", "planning"], "requirements": {"degrees": ["degree holder"], "majors": ["related disciplines", "marketing", "business administration"], "languages": ["english", "chinese"], "language_level": ["proficient"], "hard_skills": [], "soft_skills": ["negotiation", "accountability", "inter-personal", "communication skill", "interested in", "unique", "energetic", "motivated", "organisation", "strive for excellence"], "languages_combined": [{"language": "english", "language_level": ["proficient"]}, {"language": "chinese", "language_level": ["proficient"]}]}, "experience_required": {"duration": ["at least 5 years"], "field": ["property developers", "management", "retail"]}}, {"job_id": "100003009034457", "location_code": "hk", "company": "Savills Guardian", "job_title": "Facilities Officer", "description": "F.5 or above\nMinimum 1\u00a0year of experience\u00a0in Facility\u00a0Management\nGood command of spoken and written Chinese and English\nGood PC knowledge in MS Office\nThe successful candidate will be responsible for handling all the property related duties and ad. hoc duties assigned by the manager\nWork Location : Tung Chung\n\nWe offer competitive salary package to the right appointee.\u00a0 Applicants are requested to submit detailed resume with present and expected salary by clicking \"Apply Now\".\n\nPlease Quote Job Ref. : FO/HZMB/01012022\n\nPersonal data provided will be used strictly in accordance with our personal data policies, a copy which will be provided immediately upon request.", "employment_types": ["Full Time", "Permanent"], "selling_points": [], "locations": ["Tung Chung"], "categories": ["Property / Real Estate", "Property Consultancy", "Property Management", "Others"], "post_time": "2022-01-11T16:01:34Z", "salary": {"currency": null, "max": null, "min": null, "period": "monthly", "term": null}, "salary_visible": false, "title_keywords": ["officer"], "responsibilities": ["management"], "requirements": {"degrees": [], "majors": [], "languages": ["english", "chinese"], "language_level": ["good command"], "hard_skills": ["pc knowledge", "ms office"], "soft_skills": ["responsible"], "languages_combined": [{"language": "english", "language_level": ["good command"]}, {"language": "chinese", "language_level": ["good command"]}]}, "experience_required": {"duration": ["minimum 1 year"], "field": ["management"]}}, {"job_id": "100003009047172", "location_code": "hk", "company": "G4S Secure Solutions (Hong Kong) Limited", "job_title": "Scheduling Administrator", "description": "Job duties:\n\nTo handle scheduling issue of our frontline security guards\nArrange manpower to cover ad-hoc operations request within a tight time frame\nAllocate rest day, holiday and requested annual leaves within a limited resources\nPerform\u00a0duties with good integrity and manner\nAble to work on Saturday / Sunday (if necessary)\n10 working hrs per day\n\nRequirements:\n\nF.5 or above\nGood customer services / communication skill\nGood command of spoken & written English and Chinese\nGood computer skill (e.g. Word, Excel, Outlook...)\nGood sense of responsibility and accountability\n\n\u00a0Fresh graduate will also be considered.\n\nInterested and suitably qualified candidates should send their applications and resumes including present and expected salary to:\n\nThe Human Resources Department\n\nG4S Secure Solutions\u00a0(Hong Kong) Limited\n\n1st Floor The Securicor Centre\n\n481 Castle Peak Road, Hong Kong\n\nor you may visit our career center website http://greaterchinajobs.g4s.com\u00a0or http://jobs.g4s.com (mobile)\n\nOur Company is an equal opportunity employer and welcomes applications from all qualified candidates. \u00a0The personal data provided will be used for consideration in your application for the applied post and other suitable positions in the G4S. \u00a0Applications who are not invited for interview within 6 weeks may consider their applications unsuccessful. \u00a0All personal data of unsuccessful candidates will be destroyed after 6 months.", "employment_types": ["Full Time", "Permanent"], "selling_points": ["F.5 or above", "Good communication and customer services skills", "10 working hrs per day"], "locations": ["Lai Chi Kok"], "categories": ["Property / Real Estate", "Others", "Others", "Security / Safety Control", "Student / Fresh Graduate / No Experience"], "post_time": "2022-01-14T02:30:45Z", "salary": {"currency": null, "max": null, "min": null, "period": "monthly", "term": null}, "salary_visible": false, "title_keywords": ["administrator"], "responsibilities": ["ad-hoc", "scheduling", "operations"], "requirements": {"degrees": ["fresh graduate"], "majors": [], "languages": ["english", "chinese"], "language_level": ["good command"], "hard_skills": ["excel", "word", "mobile", "computer skill", "outlook"], "soft_skills": ["communication skill", "accountability", "sense of responsibility"], "languages_combined": [{"language": "english", "language_level": ["good command"]}, {"language": "chinese", "language_level": ["good command"]}]}, "experience_required": {"duration": [], "field": []}}]