[{"job_id": "100003009054554", "location_code": "hk", "company": "China Merchants Property Management (Overseas) Limited", "job_title": "Senior Property Manager / Property Manager", "description": "Responsibilities:\n\nIn charge of the day-to-day operations and management of a mixed portfolio of properties\nProvide professional advice on pre-property management and headcount planning for a constructing intelligent and environmentally friendly Grade A commercial building\nSolid experience in takeover of newly built intelligent and environmentally friendly Grade A commercial buildings with internal and external parties\nPrepare the management budget and monitor the expenditures of properties\nEnsure the operations of properties are in compliance with company policies and procedures\nMonitor the service standards of maintenance, security, cleaning services and contractors of properties\nExperienced in operating the internal and external audit work for ISO9001:2015 quality management system\nImplement property management operation safety system and safety training\nHandle emergency incidents, tenants\u2019 inquiries and complaints\nAct as focal point to communicate with Shen Zhen head office for the Company\u2019s management issues\nManage both Hong Kong head office and on-site managements of the existing and upcoming properties\nPrepare property management proposals for marketing development and safety related issues and reports\nPerform ad hoc duties as assigned\n\n\u00a0Requirements:\n\nDegree holder or above in Property Management, Housing, Hospitality Management or related disciplines\nMinimum 5 years\u2019 relevant experiences in Grade A commercial buildings, hotels and serviced apartments\nHolder of PMP License Tier 1 is required\nGood understanding of Building Management Ordinance / Deed of Mutual Covenant\nMember of MHKIH / MCIH / MRICS / HKIS / RPHM is an advantage\nStrong leadership with good communication and interpersonal skills\nMature, self-motivated and able to work under pressure\nGood command of both spoken and written English, Cantonese and Mandarin, especially Chinese writing\nFamiliar with PC operations, MS Office and Chinese word processing\nRecognize Chinese state-owned enterprises culture\nCandidate with less experience / qualifications will be considered as Property Manager\nWe offer good benefits with 5 days work, medical & life insurance, double pay and discretionary bonus.\nInterested parties please send your full resume with current salary, expected salary and available date to us via \u201cApply Now\u201d.", "employment_types": ["Full Time", "Permanent"], "selling_points": [], "locations": ["Sheung Wan"], "categories": ["Sales, CS & Business Devpt", "Business Development", "Property / Real Estate", "Property Management", "Others"], "post_time": "2022-01-17T09:58:22Z", "salary": {"currency": null, "max": null, "min": null, "period": "monthly", "term": null}, "salary_visible": false, "title_keywords": ["senior property manager", "property manager"], "responsibilities": ["operations", "internal and external parties", "day-to-day operations", "budget", "audit", "quality", "inquiries and complaints", "service standards", "ad hoc duties", "compliance", "monitor", "reports", "management", "procedures", "cleaning", "communicate with", "maintenance", "policies", "planning"], "requirements": {"degrees": ["degree holder"], "majors": ["hospitality management", "related disciplines"], "languages": ["cantonese", "english", "chinese", "mandarin"], "language_level": ["good command"], "hard_skills": ["chinese word processing", "hkis", "pc operations", "pmp", "ms office"], "soft_skills": ["self-motivated", "mature", "communication and interpersonal skills", "leadership", "work under pressure"], "languages_combined": [{"language": "cantonese", "language_level": ["good command"]}, {"language": "english", "language_level": ["good command"]}, {"language": "chinese", "language_level": ["good command"]}, {"language": "mandarin", "language_level": ["good command"]}]}, "experience_required": {"duration": ["minimum 5 years"], "field": ["commercial", "hotels"]}}, {"job_id": "100003009053189", "location_code": "hk", "company": "Jones Lang LaSalle Management Services Ltd", "job_title": "Property Officer / Assistant Property Officer", "description": "You are required to provide professional advice to the clients in the aspect of property management of the Firm's managed buildings. You are responsible to administer a property portfolio of commercial, residential and industrial buildings.\u00a0\n\nRequirements:\n\nDiploma/Degree holder in Property Management\u00a0or related discipline\nAt least 3 years\u2019 relevant experience in property management\nExcellent client servicing skill and ability to handle clients and tenants independently\nStrong interpersonal skill and be able to work under pressure\nExcellent command of written and spoken English and Chinese\nStrong in report writing\nFamiliar with DMC, BMO and tenancy management\nHands on PC skills including MS\u00a0Word,\u00a0Excel and\u00a0Power Point\u00a0etc\nCandidates with less experiences will also be considered as Assistant Property Officer\nFresh Graduate or no experience in Property Management can also be considered\n\nWe offer attractive remuneration packages and good career prospects for the right applicant. Please apply by clicking the \"APPLY NOW\" button or mail your full resume and expected salary to the PM-HR Department, 14/F, Dorset House, Taikoo Place, Quarry Bay or fax to 2968-4177.\n\n(Please quote the reference number on the envelope/subject of email)\n\nApplicants not invited for interviews within 6 weeks may consider their applications unsuccessful. Information provided will be treated with strict confidential and be used for the purpose of employment only.", "employment_types": ["Full Time", "Permanent"], "selling_points": ["Dip/ Degree holder in Property Mgt/ related fields", "Min.3 yrs of rel. exp", "Knowlege of related ordinance"], "locations": ["Others"], "categories": ["Property / Real Estate", "Property Management", "Others", "Others", "Security / Safety Control"], "post_time": "2022-01-17T06:22:21Z", "salary": {"currency": null, "max": null, "min": null, "period": "monthly", "term": null}, "salary_visible": false, "title_keywords": ["property officer", "assistant property officer"], "responsibilities": ["report", "management", "work under pressure"], "requirements": {"degrees": ["diploma", "fresh graduate", "degree holder"], "majors": [], "languages": ["english", "chinese"], "language_level": ["excellent"], "hard_skills": ["excel", "no", "power point", "pc skills", "ms word"], "soft_skills": ["independently", "responsible", "interpersonal skill", "hands on", "work under pressure"], "languages_combined": [{"language": "english", "language_level": ["excellent"]}, {"language": "chinese", "language_level": ["excellent"]}]}, "experience_required": {"duration": ["at least 3 years"], "field": ["management", "relevant experience"]}}, {"job_id": "100003009055491", "location_code": "hk", "company": "Keysen Property Management Services Limited", "job_title": "\u7269\u696d\u7ba1\u7406\u54e1/\u4fdd\u5b89\u54e1 (\u591c\u73ed)", "description": "Role Objective:\nTo participate in strengthening the cybersecurity team capacity and capability to carry out information security functions and activities.\n\nJob Duties:\n\nAssist in develop IT security architecture and implement security policies, protocols and procedures\nAssist in security risk assessment, IT audit and daily support of information security related systems\nAssist in software and Cloud service security review\nConducts security assessments (Penetration test, red-team (attack simulation) with an external consultant to identify security risks and follow up mitigation items\nConducts regular review of security control and comply with the company's security policy\nAssist in Implementation and delivery of Cybersecurity solutions and services\nResponsible for operating, administering and serving as a subject matter expert on security tools including but not limited to:\nIdentity and access management tools\nVulnerability management tools\nEndpoint Detection and Response tools\nNetwork security tools\nNetwork behavior anomaly detection tools\nUser and Entity Behavior Analytics tools\nApplication security tools\nResearch on cyber resilience maturity model, information security governance mechanism, and other related topics\nAssist in promotion of cyber security awareness\nPerform vendor and contract management during the procurement\nWork with matrix-ed system engineer to review significant changes\nParticipate in information security related projects\nCoordinate with internal and external auditors to perform information system audits\nPerform vulnerability assessment for major OS platforms and technologies\nHandle daily operation and security event with Security Operation Centre\nDevelop and implement appropriate recovery plans for resilience and to restore IT services that were impaired due to a security incident\nAssist in any security reports, trend analysis and documents preparation\nRequirements:\n\nMinimum 5 years of relevant experience in IT security areas.\nFamiliar with frameworks such as ISO27001, NIST, COBIT, ITIL, PCI\nKnowledge or experience in formulating cyber resilience maturity or management model\nGood knowledge and experience with vulnerability and compliance management products\nGood knowledge and experience with security monitoring, automation products and forensic tools\nGood knowledge and experience with security infrastructure products\nIndependent, self-motivated, and able to work under pressure\nProfessional qualifications and/or certifications holder would be preferred (e.g. CEH, CISM, CISA, CISSP, ISO/IEC 27001 lead auditor, etc.)\nCandidates with less experience may be considered for the System Analyst position\nRemuneration\n\n\nWe offer a 5-day work week and an attractive remuneration package commensurate to the right candidates with qualifications and working experience. Fringe benefits for staff include annual leave, paternity leave, birthday leave, volunteering leave, medical scheme, life insurance, Employee Unit Purchase Plan and performance-based incentives.\n\nApplication\n\nIf you resonate with Link's vision and aspire to develop a rewarding career with us, please apply by clicking \"Apply Now\".\n\nWe are an equal opportunity employer. Personal data provided by job applicants will be treated in strict confidence and used strictly in accordance with our Privacy Policy Statement for recruitment purpose only. A copy of the Statement is available on our website (Linkreit.com). Applicants not hearing from us within 6 months may consider their applications unsuccessful.", "employment_types": ["Full Time"], "selling_points": ["\u8ca0\u8cac\u4e00\u822c\u7269\u696d\u7ba1\u7406\u54e1/\u4fdd\u5b89\u54e1\u5de5\u4f5c", "\u8655\u7406\u5927\u5ec8\u65e5\u5e38\u4fdd\u5b89\u5de5\u4f5c", "\u5c0f\u516d\u7a0b\u5ea6; 1\u5e74\u7d93\u9a57"], "locations": ["Shatin Area"], "categories": ["Property / Real Estate", "Property Management", "Others", "Others", "Security / Safety Control"], "post_time": "2022-01-18T02:39:13Z", "salary": {"currency": null, "max": null, "min": null, "period": "monthly", "term": null}, "salary_visible": false, "title_keywords": ["\u4fdd\u5b89\u54e1"], "responsibilities": ["software", "information security", "cyber security", "audit", "regular review", "plans", "control", "implementation", "develop", "reports", "vulnerability management", "architecture", "management", "review", "procedures", "coordinate with", "security operation", "audits", "analytics tools", "policies", "analysis", "systems", "daily operation", "subject matter expert", "contract management", "external auditors"], "requirements": {"degrees": [], "majors": [], "languages": [], "language_level": [], "hard_skills": ["itil", "professional qualifications"], "soft_skills": ["self-motivated", "independent", "work under pressure"], "languages_combined": []}, "experience_required": {"duration": ["minimum 5 years"], "field": ["management", "compliance", "infrastructure", "it", "relevant experience", "security", "system analyst"]}}, {"job_id": "100003009053241", "location_code": "hk", "company": "Link Asset Management Limited", "job_title": "Assistant Manager - FMIT (Property Management System)  (Ref. No.: L22/01-0291)", "description": "Our Vision\n\nWe strive to be a world class real estate investor and manager serving and improving the lives of those around us.\u00a0 To support business expansion under Vision 2025, we are seeking a high caliber talent to join our dynamic team. To learn more about Vision 2025, please visit (https://www.linkreit.com/en/ourVision/).\n\nResponsibilities\n\nAssist in new tenancy liaison, renewal negotiation, marketing analysis compilation\nMonitor variances in various leasing control parameters such as income receivable, vacancy, trends, price, competition and customer turnover\n\nRequirements\n\nDegree holder in Real Estate, Property Management or related disciplines\nMinimum 6 years solid experience in property leasing\nStrong knowledge in tenancy and facilities management with shopping mall experience is advantageous\nProactive and have good connections with retailers and property agencies\nStrong negotiation and communication skills\nGood command of spoken and written English & Chinese\nCandidate with less experience will be considered for the position of Senior Officer \u2013 Leasing.\u00a0\n\n\n\nRemuneration\n\nWe offer a 5-day work week and an attractive remuneration package commensurate to the right candidates with qualifications and working experience. Fringe benefits for staff include annual leave, paternity leave, birthday leave, volunteering leave, medical scheme, life insurance, Employee Unit Purchase Plan and performance-based incentives.\n\nApplication\n\nIf you resonate with Link's vision and aspire to develop a rewarding career with us, please apply by clicking \"Apply Now\".\n\nWe are an equal opportunity employer. Personal data provided by job applicants will be treated in strict confidence and used strictly in accordance with our Privacy Policy Statement for recruitment purpose only. A copy of the Statement is available on our website (Linkreit.com). Applicants not hearing from us within 6 months may consider their applications unsuccessful.", "employment_types": ["Full Time", "Permanent"], "selling_points": ["Provide support to end users and stakeholders", "Degree / Higher Diploma holder in Computer Science", "5 to 7 years\u2019 experience in property management"], "locations": ["Not Specified"], "categories": ["Information Technology (IT)", "Support", "Network & System", "Property / Real Estate", "Property Management"], "post_time": "2022-01-17T06:35:55Z", "salary": {"currency": null, "max": null, "min": null, "period": "monthly", "term": null}, "salary_visible": false, "title_keywords": ["assistant manager"], "responsibilities": ["analysis", "monitor", "control"], "requirements": {"degrees": ["degree holder"], "majors": ["related disciplines"], "languages": ["english", "chinese"], "language_level": ["good command"], "hard_skills": ["facilities management"], "soft_skills": ["communication skills", "proactive", "negotiation"], "languages_combined": [{"language": "english", "language_level": ["good command"]}, {"language": "chinese", "language_level": ["good command"]}]}, "experience_required": {"duration": ["minimum 6 years"], "field": ["management"]}}, {"job_id": "100003009053791", "location_code": "hk", "company": "Hysan Development Co Ltd", "job_title": "Property Officer - Commercial Properties", "description": "Our Vision\n\nWe strive to be a world class real estate investor and manager serving and improving the lives of those around us.\u00a0 To support business expansion under Vision 2025, we are seeking a high caliber talent to join our dynamic team. To learn more about Vision 2025, please visit (https://www.linkreit.com/en/ourVision/).\n\nResponsibilities\n\nAssist in new tenancy liaison, renewal negotiation, marketing analysis compilation\nMonitor variances in various leasing control parameters such as income receivable, vacancy, trends, price, competition and customer turnover\n\nRequirements\n\nDegree holder or above\nMinimum 1 years solid experience in property leasing\nStrong knowledge in tenancy and facilities management with shopping mall or fresh market experience is advantageous\nProactive and have good connections with retailers and property agencies\nStrong negotiation and communication skills\nGood command of spoken and written English & Chinese\n\nCandidate with more experience will be considered for the position of Officer - Leasing.\n\nRemuneration\n\nWe offer a 5-day work week and an attractive remuneration package commensurate to the right candidates with qualifications and working experience. Fringe benefits for staff include annual leave, paternity leave, birthday leave, volunteering leave, medical scheme, life insurance, Employee Unit Purchase Plan and performance-based incentives.\n\nApplication\n\nIf you resonate with Link's vision and aspire to develop a rewarding career with us, please apply by clicking \"Apply Now\".\n\nWe are an equal opportunity employer. Personal data provided by job applicants will be treated in strict confidence and used strictly in accordance with our Privacy Policy Statement for recruitment purpose only. A copy of the Statement is available on our website (Linkreit.com). Applicants not hearing from us within 6 months may consider their applications unsuccessful.", "employment_types": ["Full Time", "Permanent"], "selling_points": ["Monitor the day-to-day operation", "Degree Holder with 2 years\u2019 PM experience", "5-day work, 14-day AL, Dental, Double Pay + Bonus"], "locations": ["Causeway Bay"], "categories": ["Property / Real Estate", "Property Management", "Others"], "post_time": "2022-01-17T07:30:52Z", "salary": {"currency": null, "max": null, "min": null, "period": "monthly", "term": null}, "salary_visible": false, "title_keywords": ["property officer"], "responsibilities": ["analysis", "monitor", "control"], "requirements": {"degrees": ["degree holder"], "majors": [], "languages": ["english", "chinese"], "language_level": ["good command"], "hard_skills": ["facilities management"], "soft_skills": ["communication skills", "proactive", "negotiation"], "languages_combined": [{"language": "english", "language_level": ["good command"]}, {"language": "chinese", "language_level": ["good command"]}]}, "experience_required": {"duration": ["minimum 1 years"], "field": ["management"]}}, {"job_id": "100003009055262", "location_code": "hk", "company": "Cushman & Wakefield Property Management Limited", "job_title": "Property Officer", "description": "Our Vision\nWe strive to be a world class real estate investor and manager serving and improving the lives of those around us.\u00a0 To support business expansion under Vision 2025, we are seeking a high caliber talent to join our dynamic team. To learn more about Vision 2025, please visit (https://www.linkreit.com/en/ourVision/).\nResponsibilities\nResponsible for end-to-end recruitment process from proactive sourcing, screening, interviewing to onboarding of candidates\nDevelop and adopt effective hiring channels or methods to source for the right talents, e.g. Job posting, LinkedIn, direct sourcing, etc.\nRecruitment meeting arrangement and coordination\nPrepare monthly and ad-hoc recruitment related statistics and reports\nParticipate in ad-hoc HR projects, e.g. ERP UAT, etc.\nRequirements\nBachelor\u2019s Degree in Human Resources, Business Administration or any related disciplines\nAt least 2 year working experience as a recruiter (in-house or agency)\nGood PC skills including MS PowerPoint, Excel and Chinese word processing\nExcellent interpersonal and communication skills\nGood command of written and spoken English and Chinese\nAble to work under pressure and meet tight deadline\nImmediate availability preferred\nRemuneration\nWe offer a 5-day work week and an attractive remuneration package commensurate to the right candidates with qualifications and working experience. Fringe benefits for staff include annual leave, paternity leave, birthday leave, volunteering leave, medical scheme, life insurance, Employee Unit Purchase Plan and performance-based incentives.\nApplication\nIf you resonate with Link's vision and aspire to develop a rewarding career with us, please apply by clicking \"Apply Now\".\nWe are an equal opportunity employer. Personal data provided by job applicants will be treated in strict confidence and used strictly in accordance with our Privacy Policy Statement for recruitment purpose only. A copy of the Statement is available on our website (Linkreit.com). Applicants not hearing from us within 6 months may consider their applications unsuccessful.", "employment_types": ["Full Time", "Permanent"], "selling_points": ["Monitor the day-to-day Property Management", "Liaise with Service Contractors", "Residential Properties working experience"], "locations": ["Kwun Tong"], "categories": ["Property / Real Estate", "Property Management"], "post_time": "2022-01-18T01:58:06Z", "salary": {"currency": null, "max": null, "min": null, "period": "monthly", "term": null}, "salary_visible": false, "title_keywords": ["property officer"], "responsibilities": ["ad-hoc", "uat", "hr", "develop", "recruitment", "reports", "coordination", "recruitment process"], "requirements": {"degrees": ["degree", "bachelor"], "majors": ["related disciplines", "business administration"], "languages": ["english", "chinese"], "language_level": ["good command", "good"], "hard_skills": ["excel", "ms powerpoint", "pc skills", "chinese word processing"], "soft_skills": ["communication skills", "interpersonal", "meet tight deadline", "work under pressure"], "languages_combined": [{"language": "english", "language_level": ["good command", "good"]}, {"language": "chinese", "language_level": ["good command", "good", "good"]}]}, "experience_required": {"duration": ["at least 2 year"], "field": ["agency"]}}, {"job_id": "100003009055540", "location_code": "hk", "company": "Hong Kong Housing Society", "job_title": "Assistant Manager (Property Management) - Estate", "description": "Our Vision\nWe strive to be a world class real estate investor and manager serving and improving the lives of those around us.\u00a0 To support business expansion under Vision 2025, we are seeking a high caliber talent to join our dynamic team. To learn more about Vision 2025, please visit (https://www.linkreit.com/en/ourVision/).\nResponsibilities\nPerform all-rounded receptionist duties and coordinate with departments to deliver full spectrum of office administrative function\nHandle company vehicle reservation, conference room and facilities booking\nResponsible for greeting visitors, managing mailing and delivery services\nAssist in organizing business meeting and company event\nPerform ad-hoc projects as assigned\nRequirements\nHigher Diploma or above\nMinimum 5 years of relevant experience at headquarters level with leading MNCs / sizeable corporations\nMust be dependable, well organized, mature and be able to take direction and work independently\nExcellent communication (written and oral) and stakeholder management skills\nProfessional planning, organizing and time management skills\nStrong critical thinking and problem-solving capabilities\nProficiency in PC skills, particularly in Microsoft Office, Excel and Chinese Word Processing\nRemuneration\nWe offer a 5-day work week and an attractive remuneration package commensurate to the right candidates with qualifications and working experience. Fringe benefits for staff include annual leave, paternity leave, birthday leave, volunteering leave, medical scheme, life insurance, Employee Unit Purchase Plan and performance-based incentives.\nApplication\nIf you resonate with Link's vision and aspire to develop a rewarding career with us, please apply by clicking \"Apply Now\".\nWe are an equal opportunity employer. Personal data provided by job applicants will be treated in strict confidence and used strictly in accordance with our Privacy Policy Statement for recruitment purpose only. A copy of the Statement is available on our website (Linkreit.com). Applicants not hearing from us within 6 months may consider their applications unsuccessful.", "employment_types": ["Permanent"], "selling_points": ["Holding a valid Property Management License", "5 years\u2019 experience in property management", "Conversant with BMO, DMC and relevant ordinances"], "locations": ["Others"], "categories": ["Property / Real Estate", "Property Management"], "post_time": "2022-01-18T02:41:26Z", "salary": {"currency": null, "max": null, "min": null, "period": "monthly", "term": null}, "salary_visible": false, "title_keywords": ["assistant manager"], "responsibilities": ["ad-hoc projects", "coordinate with", "booking", "greeting visitors"], "requirements": {"degrees": ["higher diploma or above"], "majors": [], "languages": ["chinese"], "language_level": ["proficiency"], "hard_skills": ["excel", "chinese word processing", "microsoft office", "problem-solving", "pc skills"], "soft_skills": ["work independently", "oral", "time management skills", "problem-solving", "well organized", "mature", "communication"], "languages_combined": [{"language": "chinese", "language_level": ["proficiency"]}]}, "experience_required": {"duration": ["minimum 5 years"], "field": ["relevant experience"]}}, {"job_id": "100003009048688", "location_code": "hk", "company": "Main Shine Development Limited", "job_title": "Property Officer", "description": "Job Duties :\nAssist the on-site Manager to oversee and monitor day to day property management issues.\n\nRequirements :\n\nMinimun 3 years' working relevant experience\nDegree in Property Management or related disciplines\nKnowledge in Building Management Ordinance and DMC\nService Oriented and self-motivated\nGood PC skills in MS Words, Excel and Chinese Word-processing etc.\nGood command of borth written and spoken English and Chinese\nCanditates with less experience will be considered as Assistant Property Officer\n\nBenefits :\n\nDouble pay\nMeical Insurance\n14 days annual leave\n5 day works\nAttractive salary\nContact Person : Ms. Vivian Law\n\u00a0\nContact No. : 2452 3786\n", "employment_types": ["Full Time"], "selling_points": [], "locations": ["Tuen Mun Area"], "categories": ["Property / Real Estate", "Property Management"], "post_time": "2022-01-16T21:50:21Z", "salary": {"currency": null, "max": null, "min": null, "period": "monthly", "term": null}, "salary_visible": false, "title_keywords": ["property officer"], "responsibilities": ["management", "monitor"], "requirements": {"degrees": ["degree"], "majors": ["related disciplines"], "languages": ["english", "chinese"], "language_level": ["good command", "good"], "hard_skills": ["excel", "pc skills", "chinese word-processing", "ms words"], "soft_skills": ["self-motivated"], "languages_combined": [{"language": "english", "language_level": ["good command", "good"]}, {"language": "chinese", "language_level": ["good command", "good", "good"]}]}, "experience_required": {"duration": ["3 years"], "field": ["relevant experience"]}}, {"job_id": "100003009056217", "location_code": "hk", "company": "Trinity Search Limited", "job_title": "Facilities Manager (Commercial Assets) - Property Developer", "description": "Our client is a leading real estate developer in the region with property assets in Hong Kong and South East Asia. They are currently seeking for a high caliber Facilities Manager to oversee and manage a commercial property portfolio and daily operations, whilst leading a team of sizeable professionals.\n\nResponsibilities:\n\nResponsible for overseeing daily operations management including facilities management, health & safety, cleaning, pest control, move add & changes, project management, engineering services, budget and finance management etc.\nPrepare and develop annual property budgets and forecasts (revenue, operating expenses, repair & maintenance, OPEX and CAPEX works) for Senior Management approval.\nEnsure quality of services delivered and to meet with the agreed SLA and KPI.\nSupervising multi-disciplinary teams of staff including cleaning, maintenance, grounds and security etc.\nEnhancing asset value for the group and closely work with senior management, through the implementation of the strategic business and financial plan including annual operating and capital plans, operating initiatives, corporate objectives.\nEnsure that facilities meet government regulations and environmental, health and security standards\nProvide proactive feedback to senior management and ensure working relationships at all levels of the business are in place and effective\nCoordinate with Project Team on facilities planning for new developments\n\nRequirements:\n\nDegree holder in Facility Management / Building Services / Surveying or related disciplines\nMinimum 10 years\u2019 experience in facility/ property management (preferably in high-end properties/ Commercial portfolios) and with at least 4 years\u2019 experience at managerial grade\nHolder of relevant professional qualification (e.g., HKIS / HKIFM / CFM / HKIE / CIBSE / HKIH / CIH)\nStrong leadership, communication and problem-solving skills, self-motivated, customer-oriented and achievement-driven\nProficiency in both written and spoken English and Chinese", "employment_types": ["Full Time", "Permanent"], "selling_points": ["Reputable Property Developer", "Commercial Assets", "Minimum 10 Years Relevant Experience"], "locations": ["Central & Western Area"], "categories": ["Building & Construction", "Architectural Services", "Engineering", "Engineering Project Management", "Property / Real Estate", "Property Management"], "post_time": "2022-01-18T03:35:25Z", "salary": {"currency": null, "max": null, "min": null, "period": "monthly", "term": null}, "salary_visible": false, "title_keywords": ["developer", "manager"], "responsibilities": ["regulations", "supervising", "budget", "capex", "quality", "opex", "plan", "plans", "senior management", "control", "expenses", "teams", "implementation", "develop", "management", "coordinate with", "daily operations", "cleaning", "budgets", "maintenance", "project management", "repair", "working relationships", "planning"], "requirements": {"degrees": ["degree holder"], "majors": ["related disciplines", "building services", "surveying"], "languages": ["english", "chinese"], "language_level": ["proficiency"], "hard_skills": ["problem-solving skills", "hkie", "hkis"], "soft_skills": ["self-motivated", "communication", "customer-oriented", "problem-solving skills", "leadership", "driven"], "languages_combined": [{"language": "english", "language_level": ["proficiency"]}, {"language": "chinese", "language_level": ["proficiency"]}]}, "experience_required": {"duration": ["at least 4 years", "minimum 10 years"], "field": ["commercial", "management", "managerial"]}}, {"job_id": "100003009053633", "location_code": "hk", "company": "Vineberg Property Management Limited", "job_title": "\u52a9\u7406\u5ba2\u6236\u670d\u52d9\u76e3\u7763**", "description": "Responsibilities\n\nHandle full set of books and produce month-end accounts for each of the properties\nProvide timely and accurate financial reports and analysis for management and other internal stakeholders\nAssist in new accounting system (Flexsystem) implementation\nLiaise with incorporated owners, tenants and landlords from time to time on the property accounts\nMake recommendations to improve accounting processes to ensure efficient operations and good credit control\n\nRequirements\n\nLCC Intermediate, Diploma in Accounting, or related discipline\nMinimum of 3 years' relevant experience, preferably in the property management field but it is not a must\nExperience in systems implementation or Flexsystem are added advantages\nAble to work independently, and as part of a team\nSelf-motivated, hardworking and willing to learn\nProficient in written English and Chinese\nProficient in MS Word, Excel, and Chinese word processing\n\nWe will offer an attractive remuneration package to the right candidate. Interested parties please click \"Apply Now\" below to submit your full r\u00e9sum\u00e9 with available date, and current and expected salaries to the Human Resources Department.\n\nTo learn more about working at Knight Frank, please click here to view our corporate video.\n\nYou are encouraged to read our digital brochure \u201cWhy Knight Frank\u201d to understand how we attract and inspire people to join our exceptional firm.\n\nKnight Frank is an equal opportunity employer. All information submitted will be treated in the strictest confidence and used only for recruitment purposes in accordance with our personal data policy.", "employment_types": ["Full Time"], "selling_points": [], "locations": ["Tseung Kwan O"], "categories": ["Sales, CS & Business Devpt", "Customer Service - Supervisor / Officer", "Property / Real Estate", "Property Management", "Others", "Security / Safety Control"], "post_time": "2022-01-17T07:16:20Z", "salary": {"currency": null, "max": null, "min": null, "period": "monthly", "term": null}, "salary_visible": false, "title_keywords": [], "responsibilities": ["make recommendations", "financial reports", "management", "control", "operations", "analysis", "month-end", "implementation", "liaise with"], "requirements": {"degrees": ["diploma"], "majors": ["accounting"], "languages": ["english", "chinese"], "language_level": ["proficient"], "hard_skills": ["excel", "chinese word processing", "flexsystem", "lcc", "ms word"], "soft_skills": ["work independently", "hardworking", "willing to learn", "self-motivated"], "languages_combined": [{"language": "english", "language_level": []}, {"language": "chinese", "language_level": ["proficient"]}]}, "experience_required": {"duration": ["minimum of 3 years"], "field": ["management", "it", "relevant experience"]}}, {"job_id": "100003009055536", "location_code": "hk", "company": "Lab312 Limited", "job_title": "Property Officer/\u6a13\u5b87\u904b\u4f5c\u4e3b\u4efb/Apartment Operation Officer", "description": "\n\u8077\u8cac :\u76e3\u5bdf\u627f\u8fa6\u5546\u5230\u52e4,\u8655\u7406\u5ba2\u6236\u6295\u8a34\uff0c\u67e5\u8a62\u53ca\u7a81\u767c\u4e8b\u4ef6,\u5236\u5b9a\u4eba\u624b\u914d\u7f6e\u53ca\u7de8\u66f4,\u8655\u7406\u7a81\u767c\u4e8b\u4ef6\uff0c\u4e00\u822c\u6587\u66f8\u8655\u7406\u53ca\u64b0\u5beb\u5831\u544a\n\n\u8cc7\u6b77 :\u4e2d\u4e09\u7a0b\u5ea6; 3\u5e74\u7d93\u9a57; \u826f\u597d\u7cb5\u8a9e; \u4e00\u822c\u82f1\u8a9e; \u61c2\u8b80\u5beb\u4e2d\u6587; \u7565\u61c2\u8b80\u5beb\u82f1\u6587; \u6301\u6709\u4fdd\u5b89\u57f9\u8a13\u8ab2\u7a0b\u8b49\u66f8(QAS); \u6301\u6709\u4fdd\u5b89\u4eba\u54e1\u8a31\u53ef\u8b49; \u6301\u6709\u6548\u5e73\u5b89\u54ad/\u6025\u6551\u8b49\u66f8\u512a\u5148\n\n\u5f85\u9047 :\u6bcf\u6708$18,500, \u6709\u751f\u65e5\u5047, \u91ab\u7642\u798f\u5229 \u53ca\u6bcf\u6708\u8868\u73fe\u734e\u91d1$1400, \u4e0a\u53487\u6642\u534a\u81f3\u4e0b\u53484\u6642\u534a,\u4e0b\u53482\u6642\u81f3\u4e0b\u534811\u6642\u534a\u6216\u4e0b\u534811\u6642\u81f3\u4e0a\u53488\u6642, \u6bcf\u9031\u5de5\u4f5c6\u5929,\u8f2a\u73ed,\u8f2a\u4f11, \u6bcf\u5929\u5de5\u4f5c 9 \u5c0f\u6642\n\n\u7533\u8acb\u9808\u77e5 :\u6c42\u8077\u8005\u53ef\u81f4\u96fb22074388\u8207\u842c\u5bf6\u7269\u696d\u7ba1\u7406\u6709\u9650\u516c\u53f8\u7a0b \u5148\u751f\u806f\u7d61\u3002\n\n", "employment_types": ["Full Time", "Permanent"], "selling_points": [], "locations": ["Yau Ma Tei"], "categories": ["Hospitality / F & B", "Hospitality / Hotel Services", "Property / Real Estate", "Property Management"], "post_time": "2022-01-18T02:41:15Z", "salary": {"currency": null, "max": null, "min": null, "period": "monthly", "term": null}, "salary_visible": false, "title_keywords": ["property officer", "operation officer"], "responsibilities": [], "requirements": {"degrees": [], "majors": [], "languages": [], "language_level": [], "hard_skills": [], "soft_skills": [], "languages_combined": []}, "experience_required": {"duration": [], "field": []}}, {"job_id": "100003009053490", "location_code": "hk", "company": "Arup", "job_title": "Assistant | Administration (Facilities Management)", "description": "Job Duties:\n\n\nPerform the day-to-day operational duties of residence building.\n\nProvide services to tenants by phone calls or online message.\u00a0\nEnsure satisfaction of current tenants by providing maintaining services and subsequent visits.\nConduct tenancy matters and solve relevant problems for current customers.\nMaintain daily services of all the common areas of residence building.\nOther ad-hoc duties as assigned by supervisor.\n\nRequirements:\n\n\n\nDiploma / Degree holder in Property Management\u00a0or related discipline\nAt least 1-2 year experience in Service apartment/Hotel/Hospitality\nCustomer service-oriented and ability to handle clients and tenants independently\nProactive, high sense of responsibility, well organized and strong interpersonal skill\nGood command of written and spoken English, Cantonese and Mandarin\n\nPackage\uff1a\nFive-day work\n10-14 days Annual Leave\nOT Pay\nPublic holiday\nMedical Insurance\n\nInterested parties please send your CV to us with your last and expected salaries and availability.\u00a0\n\n*All information provided by applicants will be treated in strict confidence and used only for recruitment purposes.\u00a0*", "employment_types": ["Full Time", "Permanent"], "selling_points": [], "locations": ["Kowloon City"], "categories": ["Admin & HR", "Clerical / Admin Staff", "Property / Real Estate", "Property Management"], "post_time": "2022-01-17T07:03:07Z", "salary": {"currency": null, "max": null, "min": null, "period": null, "term": null}, "salary_visible": false, "title_keywords": ["assistant"], "responsibilities": ["phone calls", "maintaining", "maintain", "ad-hoc duties", "ensure satisfaction", "operational duties"], "requirements": {"degrees": ["diploma", "degree holder"], "majors": [], "languages": ["cantonese", "english", "mandarin"], "language_level": ["good command"], "hard_skills": [], "soft_skills": ["independently", "service-oriented", "high sense of responsibility", "well organized", "interpersonal skill", "proactive"], "languages_combined": [{"language": "cantonese", "language_level": ["good command"]}, {"language": "english", "language_level": ["good command"]}, {"language": "mandarin", "language_level": ["good command"]}]}, "experience_required": {"duration": ["at least 1-2 year"], "field": []}}, {"job_id": "100003009055249", "location_code": "hk", "company": "Alexis Services Limited", "job_title": "Head of Administration & Facilities Management - Financial Institution", "description": "Responsibilities:\nFollow up building maintenance orders and monitor the progress\nAssign tasks and prepare work schedule to the technicians\nPerform preventive and regular checking for meeting room facilities\nUpdate office map drawing and diagrams\nCoordinate with vendors and Building Management Office on repairing and maintenance work\nMaintain inventory record of consumable items\nPerform ad hoc tasks, such as minor A&A works, restacking projects\u00a0\n\nQualifications & Experience required:\n\nDiploma in Facility / Property Management or related discipline\n2 years of relevant working experience, preferably in sizable company\nProficiency in Microsoft Office applications\nResponsible, good interpersonal skills and attend to details\nProficiency in both written and spoken English and Chinese\nFresh graduates will also be considered\n\nWe offer a competitive remuneration package commensurate with qualifications and experience to the right candidate including Global Profit Share scheme, additional fringe benefits of maternity / paternity leave and long-term career development opportunities.\n\nFor interested applicants, please click \u201cApply Now\u201d to submit your online application.\n\nPersonal data collected will be used for recruitment purpose only. Applicants not contacted within 8 weeks may consider their applications unsuccessful.", "employment_types": ["Full Time"], "selling_points": ["Responsible for renovation projects", "Atleast 10 year experience in office admin", "facilities management"], "locations": ["Others"], "categories": ["Admin & HR", "Others", "Property / Real Estate", "Property Management"], "post_time": "2022-01-18T01:55:13Z", "salary": {"currency": null, "max": null, "min": null, "period": "monthly", "term": null}, "salary_visible": false, "title_keywords": [], "responsibilities": ["management", "maintenance", "assign tasks", "monitor", "checking", "coordinate with", "inventory record", "ad hoc tasks", "building management", "maintain", "recruitment", "schedule", "career development", "personal data"], "requirements": {"degrees": ["diploma"], "majors": [], "languages": ["english", "chinese"], "language_level": ["proficiency"], "hard_skills": ["scheme", "maintenance", "microsoft office"], "soft_skills": ["interpersonal skills", "responsible"], "languages_combined": [{"language": "english", "language_level": ["proficiency"]}, {"language": "chinese", "language_level": ["proficiency"]}]}, "experience_required": {"duration": ["2 years"], "field": ["development", "relevant working experience"]}}, {"job_id": "100003009052201", "location_code": "hk", "company": "Citybase Property Management Limited", "job_title": "Concierge Officer (Shopping Mall)", "description": "Responsible for full round office administration duties but not limited to office renovation, facilities management, vendor management, central procurement, lease management, and general office administration\nManage various vendor contracts and leasing agreements for all branches & offices in Hong Kong;\nManage the central procurement and tendering agreement for Company expenses, incl, office renovation, IT equipment and systems\nCoordinates with external supplier / vendor of different office systems (e.g. telephone system, photocopier, office furniture, office equipment; security system);\nAssist senior management in formulating, implementing and reviewing administration policies, procedures and guidelines;\nAssist in budget preparation and control to ensure smooth operations in a cost-effective manner;\nDevelopment needs and to ensure compliance of Environmental , Health & Safety regulations;\nWork closely with internal & external parties on coordination of business assignments;\nHandle ad hoc projects as assigned by management;\nConsults with insurance consultant to arrange suitable insurance policies for head office and branches in Hong Kong. Handles and follows up claim cases.\nReview China projects related to office renovation and operation of Admin Department in China office\n\nJob Requirements:\n\nHigher Diploma/ Associate Degree holder in Facilities Management / Property Management / Business Administration or equivalent\nAtleast 10 year experience in office admin / facilities management services.\nPeople Management experienced is a must\nCandidate with Financial Institution, MNC is preferred\nAbility to deal with different levels of external business partners / contractors\nAbility to work independently and able to work under pressure\nHave knowledge of central procurement will be an advantage\nGood command of spoken English, Cantonese and Putonghua a plus", "employment_types": ["Full Time", "Permanent"], "selling_points": ["DSE or above", "At least 5 years exp in CS field", "Fluent in spoken English, Cantonese"], "locations": ["Tsuen Wan Area"], "categories": ["Sales, CS & Business Devpt", "Customer Service - Supervisor / Officer", "Property / Real Estate", "Property Management", "Others"], "post_time": "2022-01-17T16:21:06Z", "salary": {"currency": null, "max": null, "min": null, "period": "monthly", "term": null}, "salary_visible": false, "title_keywords": ["concierge officer"], "responsibilities": ["regulations", "renovation", "budget", "tendering", "external parties", "senior management", "administration", "work under pressure", "control", "contracts", "office administration", "expenses", "telephone system", "management", "cost", "review", "procedures", "ensure smooth operations", "office administration duties", "guidelines", "policies", "systems", "ensure compliance", "ad hoc projects", "coordination", "it equipment", "insurance"], "requirements": {"degrees": ["associate degree", "diploma"], "majors": ["business administration"], "languages": ["cantonese", "putonghua", "english"], "language_level": ["good command"], "hard_skills": ["facilities management", "plus", "vendor"], "soft_skills": ["work independently", "responsible", "coordination", "smooth", "work under pressure"], "languages_combined": [{"language": "cantonese", "language_level": ["good command"]}, {"language": "putonghua", "language_level": ["good command"]}, {"language": "english", "language_level": ["good command"]}]}, "experience_required": {"duration": ["10 year"], "field": ["management", "admin"]}}, {"job_id": "100003009052579", "location_code": "hk", "company": "Hong Kong Housing Society", "job_title": "Senior Officer / Officer (Property Management) - Estate (5-day week)", "description": "Responsibilities\n\nProvide customer service to occupants and visitors at concierge\nHandle telephone and walk-in enquiries\nProvide administrative support\n\n\u00a0Requirements\n\nDSE\u00a0or above, preferably with Certificate / Diploma in service management\nAt least 5\u00a0years relevant experience in Customer Service field\nFluent in spoken English, Cantonese and Mandarin\nProficient in MS word, Excel and Chinese Word Processing\nCustomer oriented with pleasant personality and good interpersonal skill\nMature, independent and able to work under pressure\n\nWe will offer attractive compensation package to the right candidate. Please send application enclosing resume stating career and salary history, expected salary and date of availability to The Human Resources Manager, Citybase Property Management Limited, Unit No.1, 6/F, Hampton Loft, 11 Hoi Fan Road, Tai Kok Tsui, Kowloon by fax at 2717 4717 or by clicking ''Apply Now'' (in Word format). Please quote the reference of the position you apply for in all correspondences.\n\nWe are an equal opportunity employer and welcome applications from all qualified candidates. Personal data collected will be treated in strictest confidence and handled confidentially by authorized personnel for recruitment-related purposes within the Group. Applicants not hearing from us within six weeks from the date of advertisement may consider their applications unsuccessful.", "employment_types": ["Permanent"], "selling_points": ["Provide value-added property management services", "Administer tenancy issues", "Maintain excellent relations with tenants"], "locations": ["Others"], "categories": ["Property / Real Estate", "Property Management"], "post_time": "2022-01-17T03:28:01Z", "salary": {"currency": null, "max": null, "min": null, "period": "monthly", "term": null}, "salary_visible": false, "title_keywords": ["senior officer", "officer"], "responsibilities": ["provide customer service", "provide administrative support"], "requirements": {"degrees": ["certificate", "diploma", "dse"], "majors": [], "languages": ["cantonese", "english", "chinese", "mandarin"], "language_level": ["proficient", "fluent"], "hard_skills": ["excel", "no", "chinese word processing", "word", "ms word"], "soft_skills": ["confidence", "independent", "mature", "interpersonal skill", "pleasant", "customer service", "work under pressure"], "languages_combined": [{"language": "cantonese", "language_level": ["fluent"]}, {"language": "english", "language_level": ["fluent"]}, {"language": "chinese", "language_level": ["proficient"]}, {"language": "mandarin", "language_level": ["fluent"]}]}, "experience_required": {"duration": ["at least 5 years"], "field": ["customer service", "relevant experience"]}}, {"job_id": "100003009042373", "location_code": "hk", "company": "Chevalier Group - Property Management", "job_title": "Maintenance Officer", "description": "[Ref:\u00a0SO/O(PM)]The Job\nProvide value-added property management services and maintain excellent relations with tenants / owners.\nAdminister tenancy issues and ensure compliance with tenancy regulations and Deed of Mutual Covenant Clauses.\nIdentify areas requiring preventive or remedial actions in respect of cleaning, repairs and security; liaise with relevant parties and monitor the implementation of such actions.\nThe Person\n5 passes in HKCEE / DSE, including English (Syl. B) and Chinese Language or with qualification equivalent to Qualifications Framework or above with minimum 4 year's relevant experience in property management.\nHolding a valid Property Management Licence is preferred.\nGood service concept, strong communication and interpersonal skills.\nCandidates with less experiences will be considered as Officer.\u00a0\n\nAttractive remuneration package will be offered to suitable candidates. To apply, please submit online application: https://careers.hkhs.com/ or send your application with full resume and reference quoted to Human Resources Manager by fax: 2882 4466.\n\nYou are welcome to visit our website www.hkhs.com to learn more about us.\nApplicants not invited for interview within 8 weeks may consider their applications unsuccessful.\n\nPersonal data provided by job applicants will be used strictly in accordance with the Housing Society\u2019s personal data policies which is available in our website and obtainable upon request. Please refer to the Policy Statement on Employment Related Data under Personal Data (Privacy) Ordinance in our website.", "employment_types": ["Full Time"], "selling_points": ["Higher Diploma or above", "3 years relevant working experience", "Knowledge in facility and maintenance works"], "locations": ["Shatin Area"], "categories": ["Building & Construction", "Building / Construction / QS", "Engineering", "Electrical / Electronics", "Property / Real Estate", "Property Management"], "post_time": "2022-01-17T05:42:09Z", "salary": {"currency": null, "max": null, "min": null, "period": null, "term": null}, "salary_visible": false, "title_keywords": ["maintenance officer"], "responsibilities": ["regulations", "management", "monitor", "implementation", "ensure compliance", "maintain", "cleaning", "liaise with"], "requirements": {"degrees": ["dse"], "majors": [], "languages": ["english", "chinese"], "language_level": [], "hard_skills": [], "soft_skills": ["communication and interpersonal skills"], "languages_combined": [{"language": "english", "language_level": []}, {"language": "chinese", "language_level": []}]}, "experience_required": {"duration": ["minimum 4 year"], "field": ["chinese language", "management", "relevant experience"]}}, {"job_id": "100003009050657", "location_code": "hk", "company": "SOGO Hong Kong Co Ltd", "job_title": "SENIOR PROPERTY MANAGER / PROPERTY MANAGER (COMMERCIAL)", "description": "Chevalier Property Management Limited, a subsidiary of Chevalier Group, is now inviting high calibre persons to apply for this position:\n\nResponsibilities\n\nOversee and monitor the day-to-day operation of large-scale residential estate such as cleaning, security, maintenance works, etc.\nEnforcement of BMO, DMC and related regulations\nAttend IO meetings and liaise with government bodies\nPerform ad-hoc projects and event assigned\nRequirements\n\n\nDiploma\u00a0holder\u00a0with professional qualification in Property Management (e.g. MHKIH, MCIH, RPHM) will be an advantage\n3\u00a0years or above relevant working experience in property management field\nHolder of valid Property Management License (Tier 2) or above\nGood customer service skills and customer oriented\nMature, independent and strong sense of responsibility\nProficient in MS Office including MS Word, MS Excel and Chinese Word Processing\n\nAttractive remuneration package will be offered to the right candidate.\nInterested parties, please send your resume with current and expected salary by clicking \"Apply Now\" or mail to:\u00a0\n\nThe Human Resource Manager, Chevalier Group, 22/F, Chevalier Commerical Centre, 8 Wang Hoi Road, Kowloon Bay, Hong Kong\u00a0\n\nWe are an equal opportunity employer and welcome applications from all qualified candidates.\u00a0 Personal data collected would be used for recruitment purpose only\n\nWelcome to visit http://www.chevalierpropmgt.com.hk", "employment_types": ["Full Time", "Permanent"], "selling_points": [], "locations": ["Others"], "categories": ["Property / Real Estate", "Property Management"], "post_time": "2022-01-14T11:10:23Z", "salary": {"currency": null, "max": null, "min": null, "period": "monthly", "term": null}, "salary_visible": false, "title_keywords": ["senior property manager", "property manager"], "responsibilities": ["regulations", "maintenance", "monitor", "cleaning", "liaise with", "ad-hoc projects", "day-to-day operation"], "requirements": {"degrees": ["diploma holder"], "majors": [], "languages": ["chinese"], "language_level": ["proficient"], "hard_skills": ["ms word", "ms excel", "chinese word processing", "ms office"], "soft_skills": ["customer service skills", "independent", "mature", "sense of responsibility"], "languages_combined": [{"language": "chinese", "language_level": ["proficient"]}]}, "experience_required": {"duration": ["3 years"], "field": ["management", "relevant working experience"]}}, {"job_id": "100003009054028", "location_code": "hk", "company": "Citybase Property Management Limited", "job_title": "Property Officer / Assistant Property Officer", "description": "Responsibilities:\n\nLeading a team of building management staff to provide professional property management services for the commercial building\nTaking overall responsibility in managing and overseeing the daily operations of property services and customer to provide quality services\nLiaise with different stakeholders in all property management-related matters\nMaintain good relationship with clients / tenants\nMonitor and oversee staff and contractors\u2019 performance to ensure the compliance of statutory requirements and meet the standard of the Company\nHandling services request, complaints and emergency incidents\nDevelop operational policies and procedures\n\nRequirement:\n\nDegree holder, preferably in Property Management or related discipline\nMember of HKIH, CIH or RPHM with at least 10 years of experience in property management of commercial buildings, 5 years of which at managerial level\nProficient in Building Management Ordinance, DMC and/or related ordinances\nExcellent organizational, leadership, communication and interpersonal skills, able to maintain good relationship with all internal and external customers\nProficiency in Microsoft Office including Words, Excel and PowerPoint etc.\nGood command of both written and spoken English and Chinese (including Putonghua)\nApplicant with Opening and Pre-opening experiences of commercial building is an added advantage", "employment_types": ["Full Time", "Permanent"], "selling_points": ["Diploma holder or above in Property Mgt", "Minimum 3 years experience in property management", "Good command of both spoken & written English"], "locations": ["Tin Shui Wai"], "categories": ["Property / Real Estate", "Property Consultancy", "Property Management", "Others"], "post_time": "2022-01-17T09:50:04Z", "salary": {"currency": null, "max": null, "min": null, "period": null, "term": null}, "salary_visible": false, "title_keywords": ["property officer", "assistant property officer"], "responsibilities": ["management", "policies", "compliance", "quality", "monitor", "procedures", "maintain good relationship", "develop", "building management", "daily operations", "statutory requirements", "liaise with"], "requirements": {"degrees": ["degree holder"], "majors": [], "languages": ["putonghua", "english", "chinese"], "language_level": ["good command"], "hard_skills": ["powerpoint", "excel", "words", "microsoft office"], "soft_skills": ["organizational", "communication and interpersonal skills", "leadership"], "languages_combined": [{"language": "putonghua", "language_level": ["good command"]}, {"language": "english", "language_level": ["good command"]}, {"language": "chinese", "language_level": ["good command"]}]}, "experience_required": {"duration": ["at least 10 years", "5 years"], "field": ["commercial", "management", "managerial"]}}, {"job_id": "100003009049720", "location_code": "hk", "company": "Don Nelson Recruitment Limited", "job_title": "Assistant Property Manager/ Senior Property Officer (Luxury Property, Up to 40K)", "description": "Responsibilities\n\nAssist the Property Manager to oversee and monitor the day-to-day property management functions\n\nRequirements\n\nDiploma or above in Property Management or related disciplines\nMinimum 3 years solid experience in property management\nGood command of both written and spoken English and Chinese\nStrong leadership, communication and interpersonal skills\nAble to work under pressure and independently\nCandidates with less experience will be considered as Assistant Property Officer\n\nWe will offer attractive compensation package to the right candidate. Please send application enclosing resume stating career and salary history, expected salary and date of availability to The Human Resources Manager, Citybase Property Management Limited, Unit No.1, 6/F, Hampton Loft, 11 Hoi Fan Road, Tai Kok Tsui, Kowloon by fax at 2717 4717 or by clicking ''Apply Now'' (in Word format). Please quote the reference of the position you apply for in all correspondences.\n\nWe are an equal opportunity employer and welcome applications from all qualified candidates. Personal data collected will be treated in strictest confidence and handled confidentially by authorized personnel for recruitment-related purposes within the Group. Applicants not hearing from us within six weeks from the date of advertisement may consider their applications unsuccessful.", "employment_types": ["Full Time", "Permanent"], "selling_points": ["Sizable Property Developer", "Good Benefits: shuttle bus, meal, medical coverage", "Good Career Prospect"], "locations": ["Central & Western Area"], "categories": ["Property / Real Estate", "Property Consultancy", "Property Management", "Others"], "post_time": "2022-01-15T19:11:38Z", "salary": {"currency": null, "max": null, "min": null, "period": "monthly", "term": null}, "salary_visible": false, "title_keywords": ["senior property officer", "assistant property manager"], "responsibilities": ["management", "monitor"], "requirements": {"degrees": ["diploma or above"], "majors": ["related disciplines"], "languages": ["english", "chinese"], "language_level": ["good command"], "hard_skills": ["no", "word"], "soft_skills": ["independently", "confidence", "communication and interpersonal skills", "leadership", "work under pressure"], "languages_combined": [{"language": "english", "language_level": ["good command"]}, {"language": "chinese", "language_level": ["good command"]}]}, "experience_required": {"duration": ["minimum 3 years"], "field": ["management"]}}, {"job_id": "100003009048396", "location_code": "hk", "company": "Henderson Land Development Company Limited", "job_title": "PROPERTY OFFICER", "description": "Our client is a listed Property Developer, they are looking for high calibre candidates to fill the following vacancy:\n\nResponsibilities:\u00a0\n\nManage and oversee the day-to-day operation of a luxury property\nProvide excellent customer services and handle complaints / enquiries of residents\nSupervise on-site team including security, cleaning and contractor\u00a0\nMonitor the maintenance works and responsible for budget preparation\nLiaise and communicate with Owners' Committee and attend meeting\n\n\u00a0Requirements:\u00a0\n\nDegree in Property, Facility, Housing Management or related discipline\n6 years\u2019 experience in property / facility management, with 2 years in managerial level\nProactive and customer-orientated with good communication skills\nGood negotiation and interpersonal skill\nProficient in spoken and written English and Chinese, including Putonghua\nHands-on PC knowledge including Word and Excel\n\nPersonal data provided by job applicants will be used strictly in accordance with the employer's personal data policies and for recruitment purposes only.\n", "employment_types": ["Full Time", "Permanent"], "selling_points": ["Medical Allowance", "Education Allowance", "MPF"], "locations": ["Not Specified"], "categories": ["Property / Real Estate", "Property Management", "Others", "Others", "Others"], "post_time": "2022-01-14T06:28:04Z", "salary": {"currency": null, "max": null, "min": null, "period": "monthly", "term": null}, "salary_visible": false, "title_keywords": ["property officer"], "responsibilities": ["liaise", "communicate with", "maintenance", "budget", "monitor", "handle complaints", "customer services", "cleaning", "day-to-day operation"], "requirements": {"degrees": ["degree"], "majors": [], "languages": ["putonghua", "english", "chinese"], "language_level": ["proficient"], "hard_skills": ["excel", "pc knowledge", "word"], "soft_skills": ["communication skills", "negotiation", "interpersonal skill", "hands-on", "proactive"], "languages_combined": [{"language": "putonghua", "language_level": ["proficient"]}, {"language": "english", "language_level": ["proficient"]}, {"language": "chinese", "language_level": ["proficient"]}]}, "experience_required": {"duration": ["6 years", "2 years"], "field": ["managerial", "management"]}}, {"job_id": "100003009056165", "location_code": "hk", "company": "Cathay Pacific Catering Services (H.K.) Limited", "job_title": "Duty Manager", "description": "Ref. No.: JDB/GWM/PO\n\nOur subsidiary, Goodwill Management Limited, continuously dedicates to providing excellent and valued-added property management services for our landlords and customers and now invites high\u00a0caliber\u00a0candidates for the position of :-\n\nDegree holder in any discipline\nMinimum 2 years' experience in Property Management\nGood command of English and Chinese\nShift duty is required\u00a0\u00a0\nCandidates with less experience will be considered for the post of Assistant Property Officer\n\nAttractive salary and fringe benefits will be offered to the successful candidates. Please apply with full resume by mail to\u00a0Personnel Section, Goodwill Management Limited, 9/F., Golden Centre, 188 Des Voeux Road C., Hong Kong\u00a0or by fax at\u00a02530 2528\u00a0or\u00a0visit our homepage at\u00a0http://www.hld.com/management/goodwill/\u00a0or\u00a0by\u00a0clicking \"Apply Now\".\n\n(Please quote the ref. no. on letter)\n\nPersonal data provided by job applicants will be used for recruitment purpose only.", "employment_types": ["Full Time", "Permanent"], "selling_points": ["Ensure a smooth operation", "Make decision when handles accidents", "Perform patrolling"], "locations": ["Airport Area"], "categories": ["Manufacturing", "Manufacturing Management", "Property / Real Estate", "Property Management", "Others", "Security / Safety Control"], "post_time": "2022-01-18T03:27:30Z", "salary": {"currency": null, "max": null, "min": null, "period": "monthly", "term": null}, "salary_visible": false, "title_keywords": ["manager"], "responsibilities": ["management"], "requirements": {"degrees": ["degree holder"], "majors": [], "languages": ["english", "chinese"], "language_level": ["good command"], "hard_skills": ["no"], "soft_skills": [], "languages_combined": [{"language": "english", "language_level": ["good command"]}, {"language": "chinese", "language_level": ["good command"]}]}, "experience_required": {"duration": ["minimum 2 years"], "field": ["management"]}}, {"job_id": "100003009049065", "location_code": "hk", "company": "ACTS Consulting Co", "job_title": "Property Manager", "description": "Responsibilities\n\n\nAct as a leader of Duty Office to ensure a smooth operation and take necessary follow-up action as required\nPerform in-house and airport ramp areas patrolling and report irregularities\nMake decision when handles accidents, irregularities and emergency cases and perform investigations and follow up actions\nServe as the key coordinator to handle flight movement to ensure timely information and service quality\nExecute company\u2019s BCP when applicable to minimize impact on operations\nUnderstand and uphold company quality standards in terms of hygiene, safety and security requirement\nCoordinate transportation service arrangement and answer enquiries from customers\nRequirements\n\nTertiary educated, preferably related to operations or facilities management\nAt least 7 years\u2019 relevant working experience, preferably in airline or transportation industry\nHands-on experience in crisis/risk management, handling of emergency cases, facility management or execution of business continuity plan is an advantage\nHolder of driving license no. 1 or/and 2\nProficiency in MS Office\nGood command of written and spoken English and Chinese\nStrong problem solving and interpersonal skills\n24-hours shift duty is required\nWe offer a competitive remuneration package and a full range of benefits. Interested parties please send\u00a0your resume\u00a0with\u00a0your current and expected salary\u00a0to Head of People,11 Catering Road East, Hong Kong International Airport, Lantau, Hong Kong or by clicking the \"Apply Now\" button\u00a0on or before 10 February 2022.\n\n\nPersonal data collected will be treated in the strictest confidence and only be used for recruitment related purpose. Applicants who do not receive notification for interview within six weeks may consider their application unsuccessful.", "employment_types": ["Full Time"], "selling_points": ["Handle the daily operation and management", "Good career development opportunity", "Competitive remuneration"], "locations": ["Not Specified"], "categories": ["Property / Real Estate", "Property Management"], "post_time": "2022-01-14T08:02:00Z", "salary": {"currency": null, "max": null, "min": null, "period": "monthly", "term": null}, "salary_visible": false, "title_keywords": ["property manager"], "responsibilities": ["irregularities", "operations", "quality", "coordinate", "hygiene", "security requirement", "report irregularities"], "requirements": {"degrees": [], "majors": [], "languages": ["english", "chinese"], "language_level": ["good command"], "hard_skills": ["no", "airline", "problem solving", "facilities management", "ms office"], "soft_skills": ["problem solving", "hands-on", "interpersonal skills"], "languages_combined": [{"language": "english", "language_level": ["good command"]}, {"language": "chinese", "language_level": ["good command"]}]}, "experience_required": {"duration": ["at least 7 years"], "field": ["risk management", "management", "business", "relevant working experience"]}}, {"job_id": "100003009052584", "location_code": "hk", "company": "Hong Kong Housing Society", "job_title": "Senior Officer / Officer (Property Management - IT Service Admin)", "description": "Property Management Manager (Ref-75207A)\n\n\nOur client is a property listed company now looking for an experienced Property Management Manager to join their expanding property management team.\u00a0 This role will focus to handle luxury residential in Hong Kong Island and will have exposure to other projects in the future.\n\nRequirements :\n\nDegree or diploma in Property management, facilities management or related studies\nPossess a valid property management licence\u00a0\u00a0\nRecent 3-4 years relevant experience at managerial level in residential property management, exposure in luxury housing will be an added advantage\nHas good communication and interpersonal skills with capability to handle ad hoc cases\nMature, independent, responsible and with initiative and strong customer service attitude\nGood command of both spoken and written English and Chinese\nProficient in MS Office\n\n\u00a0Duties :\n\nHandle the daily operation and management of the properties or other projects in the future, including budget preparation and control, service standard and property maintenance, etc\nMonitor the performance of repairs, maintenance, security and cleaning, etc.\u00a0 Identify areas requiring preventive or remedial actions\nSupervise the overall performance of contractors to ensure their services are properly provided\nDeal with the enquiries, requests or even complaints from clients/tenants and ensure theirs needs are well taken care of\nEnsure compliance with relevant laws and regulations\nAny other ad hoc work tasks", "employment_types": ["Permanent"], "selling_points": ["Maintain the daily operations of computer systems", "Build and compile statistic and analytic reports", "Good at Excel (Pivot Table, Formulas etc.)"], "locations": ["Causeway Bay"], "categories": ["Property / Real Estate", "Property Management"], "post_time": "2022-01-17T03:28:41Z", "salary": {"currency": null, "max": null, "min": null, "period": "monthly", "term": null}, "salary_visible": false, "title_keywords": ["senior officer", "admin", "officer"], "responsibilities": ["regulations", "management", "control", "ad hoc", "service standard", "maintenance", "budget", "daily operation", "ensure compliance", "monitor the performance", "cleaning"], "requirements": {"degrees": ["diploma", "degree"], "majors": [], "languages": ["english", "chinese"], "language_level": ["good command"], "hard_skills": ["facilities management", "ms office"], "soft_skills": ["independent", "responsible", "mature", "communication and interpersonal skills", "customer service", "initiative"], "languages_combined": [{"language": "english", "language_level": ["good command"]}, {"language": "chinese", "language_level": ["good command"]}]}, "experience_required": {"duration": ["3-4 years"], "field": ["managerial", "management", "relevant experience"]}}, {"job_id": "100003009053787", "location_code": "hk", "company": "Hysan Development Co. Ltd.", "job_title": "(\u9ad8\u7d1a) \u5ba2\u6236\u670d\u52d9\u4e3b\u7ba1 - \u5beb\u5b57\u6a13\u53ca\u5546\u5834", "description": "[Ref: SO/O(PM)(ITSA)]\n\n\nThe Job\n\nMaintain the daily operations of computer systems or services related to property management or housing applications.\nBuild and compile statistic and analytic reports.\nCarry out system\u2019s developments, tests and enhancements.\nMaintain data integrity and accuracy.\nConduct trainings and prepare system manuals for users.\nPerform ad hoc duties as assigned by supervisor.\n\nThe Person\n\n5 passes in HKCEE / DSE, including English (Syl. B) and Chinese Language or with qualification equivalent to Qualifications Framework or above with minimum 2 to 3 years\u2019 relevant experience in IT or property management industry.\nGood at Excel (Pivot Table, Formulas,\u00a0 e-form etc.).\nFamiliar with the software: Microsoft Word and Power Point, and Chinese Word Processing.\nStrong communication, interpersonal and presentation skills.\nSelf-motivated, willing to work under pressure and being a good team player.\n\nAttractive remuneration package will be offered to suitable candidates. To apply, please submit online application: https://careers.hkhs.com/ or send your application with full resume and reference quoted to Human Resources Manager by fax: 2882 4466.\n\nYou are welcome to visit our website www.hkhs.com to learn more about us.\nApplicants not invited for interview within 8 weeks may consider their applications unsuccessful.\n\nPersonal data provided by job applicants will be used strictly in accordance with the Housing Society\u2019s personal data policies which is available in our website and obtainable upon request. Please refer to the Policy Statement on Employment Related Data under Personal Data (Privacy) Ordinance in our website.", "employment_types": ["Full Time", "Permanent"], "selling_points": ["\u8ca0\u8cac\u7ba1\u7406\u5927\u5ec8\u65e5\u5e38\u7684\u904b\u4f5c", "\u4e09\u5e74\u6216\u4ee5\u4e0a\u76f8\u95dc\u7269\u696d\u7ba1\u7406 / \u5ba2\u6236\u670d\u52d9\u7d93\u9a57\u512a\u5148", "\u96d9\u7ce7 / \u82b1\u7d05 / \u8d85\u6642\u88dc\u5047 / \u751f\u65e5\u5047 / \u65b0\u5a5a\u5047 / \u4e2d\u897f\u91ab\u7259\u79d1\u91ab\u7642 / \u9032\u4fee\u8cc7\u52a9 / \u81b3\u98df\u6d25\u8cbc"], "locations": ["Causeway Bay"], "categories": ["Property / Real Estate", "Property Management", "Others"], "post_time": "2022-01-17T07:30:51Z", "salary": {"currency": "HKD", "max": 24999, "min": 17000, "period": "monthly", "term": null}, "salary_visible": true, "title_keywords": [], "responsibilities": ["ad hoc duties", "management", "computer systems", "daily operations", "maintain", "reports", "maintain data"], "requirements": {"degrees": ["dse"], "majors": [], "languages": ["english", "chinese"], "language_level": [], "hard_skills": ["excel", "microsoft word", "chinese word processing", "pivot table", "power point"], "soft_skills": ["self-motivated", "good team player", "communication", "presentation skills", "interpersonal", "work under pressure"], "languages_combined": [{"language": "english", "language_level": []}, {"language": "chinese", "language_level": []}]}, "experience_required": {"duration": ["minimum 2 to 3 years"], "field": ["chinese language", "management", "it", "relevant experience"]}}, {"job_id": "100003009034675", "location_code": "hk", "company": "S.H.K. Real Estate Management Company Limited", "job_title": "\u7269\u696d\u52a9\u7406\u54e1(\u4e2d\u73ed: 14:30 - 23:30)", "description": "Chevalier Property Management Limited, a subsidiary of Chevalier Group, is now inviting high calibre persons to apply for this position:\n\nResponsibilities\n\nOversee and monitor the day-to-day operation of large-scale residential estate such as cleaning, security, maintenance works, etc.\nResponsible for budget control and budget preparation\nEnforcement of BMO, DMC and related regulations\nAttend IO meetings and maintain good relationship with the Incorporated Owners\nPerform ad-hoc\u00a0projects and event\u00a0as assigned\nRequirements\n\n\nDiploma holder\u00a0with professional qualification in Property Management (e.g. MHKIH, MCIH, RPHM) will be an advantage\n3\u00a0years or above relevant working experience in property management of which\u00a02 years in large-scale of residential estate\nHolder of valid Property Management License (Tier 1)\nCustomer oriented, pleasant personality, excellent communication and interpersonal skills\nAble to work under pressure and work independently\nFluent in both written and spoken English and Chinese\n\nAttractive remuneration package will be offered to the right candidate.\nInterested parties, please send your resume with current and expected salary by clicking \"Apply Now\" or mail to:\u00a0\n\nThe Human Resource Manager, Chevalier Group, 22/F, Chevalier Commerical Centre, 8 Wang Hoi Road, Kowloon Bay, Hong Kong\u00a0\n\nWe are an equal opportunity employer and welcome applications from all qualified candidates.\u00a0 Personal data collected would be used for recruitment purpose only\n\nWelcome to visit http://www.chevalierpropmgt.com.hk", "employment_types": ["Full Time", "Permanent"], "selling_points": ["\u4e0d\u9700\u8f2a\u73ed\u5de5\u4f5c", "\u53ef\u4eab9\u5929\u5e74\u5047\uff0c\u91ab\u7642\u798f\u5229\u7b49", "\u6bcf\u5929\u5de5\u4f5c9\u5c0f\u6642"], "locations": ["Not Specified"], "categories": ["Property / Real Estate", "Property Management", "Others", "Others", "Security / Safety Control"], "post_time": "2022-01-16T21:50:10Z", "salary": {"currency": null, "max": null, "min": null, "period": "monthly", "term": null}, "salary_visible": false, "title_keywords": [], "responsibilities": ["regulations", "maintenance", "budget", "monitor", "maintain good relationship", "cleaning", "ad-hoc projects", "budget control", "day-to-day operation"], "requirements": {"degrees": ["diploma holder"], "majors": [], "languages": ["english", "chinese"], "language_level": ["fluent"], "hard_skills": [], "soft_skills": ["work under pressure", "work independently", "communication and interpersonal skills", "pleasant"], "languages_combined": [{"language": "english", "language_level": ["fluent"]}, {"language": "chinese", "language_level": ["fluent"]}]}, "experience_required": {"duration": ["3 years", "2 years"], "field": ["management", "relevant working experience"]}}, {"job_id": "100003009051850", "location_code": "hk", "company": "Cayley Property Management Limited", "job_title": "ASSISTANT ESTATE MANAGER [Ref. CPML-AEM]", "description": "\u8077\u8cac:\n\n\u8ca0\u8cac\u7ba1\u7406\u5927\u5ec8\u65e5\u5e38\u7684\u904b\u4f5c\n\u7559\u610f\u7576\u503c\u670d\u52d9\u54e1\u7684\u5de5\u4f5c\u8868\u73fe\u4ee5\u63d0\u4f9b\u512a\u8cea\u53ca\u6709\u52b9\u7387\u7684\u5ba2\u6236\u670d\u52d9\n\u8655\u7406\u6587\u66f8\u5de5\u4f5c\n\n\u5165\u8077\u8981\u6c42:\n\n\u4e2d\u4e03\u6216\u4ee5\u4e0a\u7a0b\u5ea6\n\u4e09\u5e74\u6216\u4ee5\u4e0a\u76f8\u95dc\u7269\u696d\u7ba1\u7406 / \u5ba2\u6236\u670d\u52d9\u7d93\u9a57\u512a\u5148\n\u826f\u597d\u6e9d\u901a\u53ca\u9818\u5c0e\u624d\u80fd\uff0c\u8655\u4e8b\u7368\u7acb\n\u80fd\u66f8\u5beb\u53ca\u64cd\u6d41\u5229\u82f1\u8a9e\uff0c\u7cb5\u8a9e\u53ca\u666e\u901a\u8a71\n\u6301\u6709\u6548\u4fdd\u5b89\u4eba\u54e1\u8a31\u53ef\u8b49\u53caQAS\u8b49\u66f8\u00a0\n\u61c2\u96fb\u8166\u57fa\u672c\u64cd\u4f5c\n\u65bc\u9285\u947c\u7063\u5340\u8f2a\u73ed\u5de5\u4f5c (9\u5c0f\u6642/5.5\u5929)\n\u7d93\u9a57\u8f03\u591a\u4e4b\u6c42\u8077\u8005\u53ef\u7372\u8003\u616e\u70ba\u9ad8\u7d1a\u5ba2\u6236\u670d\u52d9\u4e3b\u7ba1\u00a0\n\n\n\u798f\u5229:\n\n\u5e74\u7d42\u96d9\u7ce7\n\u914c\u60c5\u82b1\u7d05\n\u6709\u85aa\u5e74\u5047\n\u65b0\u5a5a\u5047\n\u751f\u65e5\u5047\n\u5b78\u7fd2\u5047\n\u8003\u8a66\u5047\n\u6069\u6064\u5047\n\u9032\u4fee\u8cc7\u52a9\n\u81b3\u98df\u6d25\u8cbc\n\u8f2a\u73ed\u6d25\u8cbc\n\u8d85\u6642\u88dc\u5047\n\u5728\u8077\u57f9\u8a13\n\u7259\u79d1\u91ab\u7642\n\u4e2d\u897f\u91ab\u91ab\u7642\n\u5718\u9ad4\u4eba\u58fd\u4fdd\u96aa\n\u826f\u597d\u6649\u5347\u6a5f\u6703\n\u63a8\u85a6\u65b0\u4eba\u734e\u91d1\n\u516c\u53f8\u5eb7\u6a02\u6d3b\u52d5\n\n\u6709\u610f\u61c9\u5fb5\u8005\u53ef\u9ede\u64ca\u201cApply Now\u201d\u6309\u9215\u905e\u4ea4\u5c65\u6b77\n\n\u5982\u6709\u4efb\u4f55\u7591\u554f\uff0c\u53ef\u81f4\u96fb\u62db\u8058\u71b1\u7dda / WhatsApp: 9760 3380\n\n\u7533\u8acb\u4eba\u63d0\u4f9b\u4e4b\u500b\u4eba\u8cc7\u6599\u5c07\u53ea\u7528\u4f5c\u62db\u8058\u7528\u9014\u53ca\u6703\u7d55\u5c0d\u4fdd\u5bc6\n\nHysan is an equal opportunity employer.\u00a0 All information collected will be kept in strict confidence and used solely for recruitment related purposes within the Hysan Group Companies.\n\nYou may get to know more about us through www.hysan.com.hk", "employment_types": ["Full Time", "Permanent"], "selling_points": ["Degree holder", "Minimum 7 years' relevant working experience", "Good management and interpersonal skills"], "locations": ["Not Specified"], "categories": ["Property / Real Estate", "Property Management", "Others"], "post_time": "2022-01-17T07:31:04Z", "salary": {"currency": null, "max": null, "min": null, "period": null, "term": null}, "salary_visible": false, "title_keywords": ["assistant", "estate manager"], "responsibilities": ["recruitment"], "requirements": {"degrees": [], "majors": [], "languages": [], "language_level": [], "hard_skills": ["whatsapp"], "soft_skills": ["confidence"], "languages_combined": []}, "experience_required": {"duration": [], "field": []}}, {"job_id": "100003009055948", "location_code": "hk", "company": "Worldwide Cruise Terminals (Hong Kong) Limited", "job_title": "Senior Facility Officer / Facility Officer - Cruise Terminals", "description": "\u5354\u52a9\u57f7\u884c\u9ad8\u7d1a\u5546\u696d\u5927\u5ec8\u4e4b\u65e5\u5e38\u7ba1\u7406\u53ca\u4e8b\u52d9\n\u6bcf\u5929\u5de5\u4f5c9\u5c0f\u6642\n\u4e0d\u9700\u8f2a\u73ed\u5de5\u4f5c\n\u4e2d\u4e94\u7a0b\u5ea6\u6216\u5177\u8cc7\u6b77\u67b6\u69cb\u540c\u7b49\u8cc7\u6b77\n\u9808\u6301\u6709\u6709\u6548\u300c\u4fdd\u5b89\u4eba\u54e1\u8a31\u53ef\u8b49\u300d\u53ca\u8a8d\u53efQAS\u8a3c\u66f8\n\u6b61\u8fce\u7121\u76f8\u95dc\u7d93\u9a57\u8005\u61c9\u5fb5\n\u85aa\u91d1\u53ef\u9ad8\u9054\u6bcf\u6708$17,000\n\n\u4ee5\u4e0a\u8077\u4f4d\u53ef\u4eab\u6709\u512a\u539a\u54e1\u5de5\u798f\u5229\uff0c\u5305\u62ec\u6709\u85aa\u5e74\u50479\u5929\u3001\u52e4\u5de5\u734e\u3001\u81b3\u98df\u6d25\u8cbc\u3001\u5e74\u7d42\u96d9\u7ce7\u3001\u5e74\u7d42\u734e\u91d1\u3001\u91ab\u7642\u798f\u5229\u3001\u5b8c\u5584\u57f9\u8a13\u53ca\u6649\u5347\u6a5f\u6703\u3002\n\n\u6709\u610f\u8005\uff0c\u8acb\u81f4\u96fb\u4ee5\u4e0b\u806f\u7d61\u4eba\u7533\u8acb\uff1a\n\n\u7063\u4ed4\u5340\uff1a\n\u96fb\u8a71\uff1a9710 0179 \u6e6f\u5148\u751f\n\n\u9664\u4e0a\u8ff0\u8077\u4f4d\u5916\uff0c\u5c1a\u6709\u5176\u4ed6\u7a7a\u7f3a\u3002\u8acb\u900f\u904e\u4ee5\u4e0b\u65b9\u6cd5\u5c07\u5c65\u6b77\u4ea4\u5230S.H.K.\u7269\u696d\u7ba1\u7406\u6709\u9650\u516c\u53f8\u4e4b\u4eba\u529b\u8cc7\u6e90\u53ca\u884c\u653f\u90e8\u3002\n\n\u90f5\u5bc4\uff1a\u89c0\u5858\u5de7\u660e\u885795\u865f\u4e16\u9054\u4e2d\u5fc316\u6a13\u3000\u50b3\u771f\uff1a2827 2125\n\n\nS.H.K. \u7269\u696d\u7ba1\u7406\u6709\u9650\u516c\u53f8\u4e43\u5e73\u7b49\u6a5f\u6703\u50f1\u4e3b\uff0c\u800c\u6240\u6709\u6536\u96c6\u8cc7\u6599\u7d55\u5c0d\u4fdd\u5bc6\u53ca\u53ea\u7528\u4f5c\u96c6\u5718\u5167\u90e8\u62db\u8058\u4e4b\u7528\u9014\u3002", "employment_types": ["Full Time", "Permanent"], "selling_points": [], "locations": ["Kowloon Bay"], "categories": ["Hospitality / F & B", "Hospitality / Hotel Services", "Property / Real Estate", "Property Management", "Tourism / Travel Agency"], "post_time": "2022-01-18T03:07:10Z", "salary": {"currency": null, "max": null, "min": null, "period": "monthly", "term": null}, "salary_visible": false, "title_keywords": ["officer", "senior facility officer"], "responsibilities": [], "requirements": {"degrees": [], "majors": [], "languages": [], "language_level": [], "hard_skills": [], "soft_skills": [], "languages_combined": []}, "experience_required": {"duration": [], "field": []}}, {"job_id": "100003009052338", "location_code": "hk", "company": "Whampoa Garden Management Limited", "job_title": "ASSISTANT ESTATE MANAGER [Ref. WGML-AEM]", "description": "Degree holder preferably in Property Management or related disciplines\nMinimum\u00a07 years' relevant working experience in supervisory level\nTo monitor the day-to-day property management functions, e.g. security, maintenance, cleaning, procurement, amenities and facilities management etc.\nTo monitor property management income and expenses to prepare annual property management budgets and other related financial duties\nTo liaise with Government departments and other departments of the company\nTo attend Owners' Committee meetings and maintain good relationship with the committees\nGood management and interpersonal skills\nFluent in spoken and written English and Chinese\n\nWe offer salary and benefits commensurate with qualifications and experience. Please send a full resume with contact telephone number and expected salary to\u00a0General Manager - Human Resources & Administration, Cayley Property Management Limited, 3/F., One Harbourfront, 18 Tak Fung Street, Hunghom, Kowloon\u00a0(Please quote reference on envelope) or by clicking \"Apply Now\".\n\n\nWe are an equal opportunity employer and welcome applicants from all qualified candidates. The information provided will be treated in strict confidence and be used only for consideration of your application for relevant/similar post(s).\n\nApplicants not hearing from us within six weeks from the date of advertisement may consider their applications unsuccessful. All personal data of unsuccessful applicants will be destroyed after the recruitment exercise when no longer required.", "employment_types": ["Full Time", "Permanent"], "selling_points": ["Degree Holder", "Minimum 5 years' relevant working experience", "Good management and interpersonal skills"], "locations": ["Hung Hom"], "categories": ["Property / Real Estate", "Property Management", "Others"], "post_time": "2022-01-17T07:14:59Z", "salary": {"currency": null, "max": null, "min": null, "period": null, "term": null}, "salary_visible": false, "title_keywords": ["assistant", "estate manager"], "responsibilities": ["budgets", "management", "maintenance", "expenses", "monitor", "maintain good relationship", "cleaning", "liaise with"], "requirements": {"degrees": ["degree holder"], "majors": ["related disciplines"], "languages": ["english", "chinese"], "language_level": ["fluent"], "hard_skills": ["facilities management", "maintenance"], "soft_skills": ["interpersonal skills"], "languages_combined": [{"language": "english", "language_level": ["fluent"]}, {"language": "chinese", "language_level": ["fluent"]}]}, "experience_required": {"duration": ["minimum 7 years"], "field": ["supervisory level", "relevant working experience"]}}, {"job_id": "100003009048397", "location_code": "hk", "company": "Henderson Land Development Company Limited", "job_title": "PROPERTY MANAGER \u2013 COMMERCIAL TOWER", "description": "Key Responsibilities:\u00a0\n\nSupervise and leading the Facility Officer(s) to execute the daily working tasks\nCoordinate with the Technician to oversee the repairing and maintenance work of the facilities\nCommunicate and coordinate with the Government departments (EMSTF, ASD and CEDD) to oversee the repairing and maintenance work of the facilities in Kai Tak Cruise Terminal\nAssist in managing planned maintenance, repair and operation of the facilities in the cruise terminal\nSource quotations, prepare procurement, and compile paperwork for maintenance, addition & alteration, fitting-out and improvement works\nConduct regular site walk, identify and report possible health and safety hazards and come up with precautionary measures\nMonitor, organize and supervise contractors\u2019 performance including outsourced cleaning and security team\nCoordinate site, exhibition halls setup and events arrangement for all events\nSupport the ship call operations in Kai Tak Cruise Terminal\nPerform other duties as assigned by the Operations Manager and Facility Manager\n\n\u00a0Requirements:\u00a0\n\nDiploma holder in Property/Facilities Management, Building Surveying, Building Services Engineering or related disciplines is preferable\nMinimum 3 - 5 year of work experience in\u00a0school, property or facilities management\nGood initiative and strong interpersonal and communication skills\nGood command of both written and spoken English and Chinese\nWilling to work on shifts\nCandidate with less work experience will be considered as Facility Officer\n\n\n\n\nWe offer attractive remuneration package, medical and insurance benefits, annual leave and provident fund. Please respond in complete confidence with a cover letter, detailed resume, current and expected salary by\u00a0e-mail.\n\nAll information collected will be kept in strict confidence and only for employment-related purposes.", "employment_types": ["Full Time", "Permanent"], "selling_points": ["Medical Allowance", "Education Allowance", "MPF"], "locations": ["Central"], "categories": ["Property / Real Estate", "Property Management", "Others", "Others", "Others"], "post_time": "2022-01-14T06:28:05Z", "salary": {"currency": null, "max": null, "min": null, "period": "monthly", "term": null}, "salary_visible": false, "title_keywords": ["property manager"], "responsibilities": ["perform other duties", "supervise contractors", "maintenance", "operations", "coordinate with", "monitor", "coordinate", "repair", "cleaning", "setup", "report"], "requirements": {"degrees": ["diploma holder"], "majors": ["related disciplines", "building surveying", "building services", "engineering"], "languages": ["english", "chinese"], "language_level": ["good command"], "hard_skills": ["facilities management"], "soft_skills": ["communication skills", "interpersonal", "initiative"], "languages_combined": [{"language": "english", "language_level": ["good command"]}, {"language": "chinese", "language_level": ["good command"]}]}, "experience_required": {"duration": ["minimum 3 - 5 year"], "field": ["management"]}}, {"job_id": "100003009051116", "location_code": "hk", "company": "Sun Yu Mang Svs Co. Ltd", "job_title": "Assistant Property Officer (Administrative Support)", "description": "Degree holder preferably in Property Management or related disciplines\nMinimum 5\u00a0years' relevant working experience in supervisory level\nTo oversee and monitor the day-to-day property management functions, e.g. security, maintenance, cleaning, procurement, amenities and facilities management etc.\nTo monitor property management income and expenses to prepare annual property management budgets and other related financial duties\nTo liaise with Government departments and other departments of the company\nTo attend Owners' Committee meetings and maintain good relationship with the committees\nGood management and interpersonal skills\nFluent in spoken and written English and Chinese\nWe offer salary and benefits commensurate with qualifications and experience. Please send a full resume with contact telephone number and expected salary to General Manager - Human Resources & Administration, Whampoa Garden Management Limited, 3/F., One Harbourfront, 18 Tak Fung Street, Hunghom, Kowloon\u00a0(Please quote reference on envelope) or\u00a0by clicking \"Apply Now\".\nWe are an equal opportunity employer and welcome applications from all qualified candidates. The information provided will be treated in strict confidence and be used only for consideration of your application for relevant/similar post(s).\nApplicants not hearing from us within six weeks from the date of advertisement may consider their applications unsuccessful. All personal data of unsuccessful applicants will be destroyed after the recruitment exercise when no longer required.", "employment_types": ["Full Time"], "selling_points": [], "locations": ["Wan Chai"], "categories": ["Property / Real Estate", "Property Management"], "post_time": "2022-01-15T03:02:42Z", "salary": {"currency": null, "max": null, "min": null, "period": "monthly", "term": null}, "salary_visible": false, "title_keywords": ["assistant property officer"], "responsibilities": ["budgets", "management", "maintenance", "expenses", "monitor", "maintain good relationship", "cleaning", "liaise with"], "requirements": {"degrees": ["degree holder"], "majors": ["related disciplines"], "languages": ["english", "chinese"], "language_level": ["fluent"], "hard_skills": ["facilities management", "maintenance"], "soft_skills": ["interpersonal skills"], "languages_combined": [{"language": "english", "language_level": ["fluent"]}, {"language": "chinese", "language_level": ["fluent"]}]}, "experience_required": {"duration": ["minimum 5 years"], "field": ["supervisory level", "relevant working experience"]}}, {"job_id": "100003009051962", "location_code": "hk", "company": "Kai Fu Property Services Co Ltd", "job_title": "SENIOR ESTATE MANAGER / ESTATE MANAGER", "description": "Ref. No: JDB/GWM/PM-CT\n\nOur subsidiary, Goodwill Management Limited, continuously dedicates to providing excellent and valued-added property management services for our landlords and customers\u00a0and now invites high\u00a0caliber\u00a0candidates for the position of :-\u00a0\n\nResponsibilities:\n\n\nLeading a team to provide professional property management services for\u00a0 commercial tower\nTaking overall responsibility in managing and overseeing the daily operations of property services and customer to provide all-round property management services\nMaintaining good relationship with tenants by rendering prompt services at all times\nManaging and monitoring the performance of contractors, suppliers and service providers\nHandling complaints and emergency incidents\nEnforcing the improvement or renovation programs when necessary\n\nRequirements:\n\n\nDegree holder, preferably major in Property Management or other related discipline\nHolder of professional qualification (e.g. MCIH, MHKIH, etc.) or eligible to hold the Property Management Practitioner (Tier 1) Licence\nMinimum 8 years\u2019 experience in management of shopping arcade and Grade-A office building, with 4 years\u2019 supervisory experience inclusive\nProficiency in both Chinese and English\nStrong leadership with good interpersonal skills and able to work under pressure\nShift duty is required\nVacancies : Central (H Queen\u2019s & H Code) / Tsim Sha Tsui (H Zentre) / Kwun Tong (Manulife Financial Centre)\n\nAttractive salary and fringe benefits will be offered to the successful candidates. Please apply with full resume by mail to\u00a0Personnel Section, Goodwill Management Limited, 9/F., Golden Centre, 188 Des Voeux Road C., Hong Kong\u00a0or by fax at\u00a02530 2528\u00a0or\u00a0visit our homepage at\u00a0http://www.hld.com/management/goodwill/\u00a0or\u00a0by\u00a0clicking\u00a0\"Apply Now\".\n\n(Please quote the ref. no. on letter)\n\nPersonal data provided by job applicants will be used for recruitment purpose only.", "employment_types": ["Full Time"], "selling_points": [], "locations": ["Not Specified"], "categories": ["Property / Real Estate", "Property Management"], "post_time": "2022-01-17T01:39:17Z", "salary": {"currency": null, "max": null, "min": null, "period": "monthly", "term": null}, "salary_visible": false, "title_keywords": ["estate manager"], "responsibilities": ["management", "maintaining", "monitoring", "renovation", "good relationship", "daily operations"], "requirements": {"degrees": ["degree holder"], "majors": [], "languages": ["english", "chinese"], "language_level": ["proficiency"], "hard_skills": ["code"], "soft_skills": ["leadership", "interpersonal skills", "work under pressure"], "languages_combined": [{"language": "english", "language_level": ["proficiency"]}, {"language": "chinese", "language_level": ["proficiency"]}]}, "experience_required": {"duration": ["4 years", "minimum 8 years"], "field": ["management", "supervisory experience"]}}, {"job_id": "100003009053800", "location_code": "hk", "company": "Hysan Development Co Ltd", "job_title": "Hysan Management Trainee Program 2022", "description": "1. Participate in ad hoc projects and tasks as assigned by the superior.\n2. To assist the daily operation and administration of the building.\n3. To handle enquiry from clients.\u00a0\n4. To coordinate with I.O. and attend meeting with I.O. members.", "employment_types": ["Contract"], "selling_points": ["17-month intensive and fast-track career develop", "Cross-function learning opportunities", "Excellent working environment in prime location"], "locations": ["Causeway Bay"], "categories": ["Property / Real Estate", "Property Management"], "post_time": "2022-01-17T07:31:56Z", "salary": {"currency": null, "max": null, "min": null, "period": "monthly", "term": null}, "salary_visible": false, "title_keywords": ["management trainee"], "responsibilities": ["daily operation", "coordinate with", "handle enquiry", "ad hoc projects", "administration"], "requirements": {"degrees": [], "majors": [], "languages": [], "language_level": [], "hard_skills": [], "soft_skills": ["superior"], "languages_combined": []}, "experience_required": {"duration": [], "field": []}}, {"job_id": "100003009049796", "location_code": "hk", "company": "Man Hing Hong Properties Company Limited", "job_title": "Assistant Property Manager (Central, 5-day work)", "description": "Responsibilities\u00a0\n\nOverall monitoring a team of staff in handling property management matters including tenancy documentation, tenant enquiries / complaints, flat visits / investigations, rent collection, etc. of a public rental housing estate\nTo supervise the performance of cleansing and security staff, repairs and maintenance contractors, etc.\nTo liaise with clients, tenants' representatives, district councilors, political parties, etc.\n\nRequirements\n\nA practicing member of the Hong Kong Institute of Housing / the Chartered Institute of Housing / Housing Managers Registration Board with a minimum of 5 years' post qualification experience in property management in Hong Kong, or\nHaving at least 20 years\u2019 experience in property management with not less than 6 years in the capacity of managerial post in a public housing organization in Hong Kong\u00a0\n\nInterested parties please click the \"APPLY NOW\" to submit your application with\u00a0full resume including\u00a0contact phone\u00a0number,\u00a0date\u00a0available\u00a0in MS Word format to us.\u00a0\n\n<Personal data collected will be treated in strictest confidence\u00a0for recruitment related purposes only>", "employment_types": ["Full Time"], "selling_points": ["Degree Holder", "Property management experience", "Experience in grade A commercial properties"], "locations": ["Central"], "categories": ["Management", "General Management", "Property / Real Estate", "Property Management", "Others"], "post_time": "2022-01-14T09:14:46Z", "salary": {"currency": null, "max": null, "min": null, "period": "monthly", "term": null}, "salary_visible": false, "title_keywords": ["assistant property manager"], "responsibilities": ["liaise with clients", "management", "maintenance", "cleansing", "monitoring", "documentation"], "requirements": {"degrees": [], "majors": [], "languages": [], "language_level": [], "hard_skills": [], "soft_skills": [], "languages_combined": []}, "experience_required": {"duration": ["6 years", "at least 20 years", "minimum of 5 years"], "field": ["managerial", "management"]}}, {"job_id": "100003009017737", "location_code": "hk", "company": "Henderson Sunlight Property Management Limited", "job_title": "Senior Leasing Officer (Ref.:2022/HSAM/PM/LS02)", "description": "Hysan Management Trainee Program 2022\n\nWhat Hysan is doing?\n\nRooted in Causeway Bay for nearly a hundred years, Hysan is a leading property investment, management, and development company in Hong Kong.\u00a0 Our Lee Gardens, located at the heart of Causeway Bay, is one of Hong Kong\u2019s premier work, lifestyle and shopping destinations.\u00a0 Hysan\u2019s balanced dual-engine office-retail portfolio has provided a stable foundation for us to explore new and exciting \u201cpillars\u201d to inspire and power our business growth.\n\nHow will you evolve?\n\nUpon joining Hysan\u2019s MT program, you will enjoy a 17-month intensive development programme to stretch your capabilities, unleash your potential and ignite your passion.\u00a0 While developing your professional career, you will also be expected to play a vital role in contributing to the growth and success of Hysan.\n\nThe program is subdivided into 3 main stages:\n\n12-month rotation within Hysan\u2019s core departments\n4-month senior executive shadowing to experience leadership\u2019s daily life and challenges firsthand\n1-month immersion into a chosen business function before placement\n\nTo enrich your learning and exposure, you will also be involved in different business projects beyond your daily assignments\u00a0\n\nOf course, you will be guided, coached and mentored throughout the journey.\u00a0\n\nWhat are we looking for?\n\nBeside possessing a bachelor\u2019s degree or above from an accredited university but with less than 2 years of full-time working experience, you need to be\u2026\n\nDedicated \u2013 Be committed and dedicated to a business running round-the-clock and efficiently provide SMART solutions\nCourageous - Speak Up!\u00a0 Be bold to challenge status quo.\u00a0 Bring in new ideas and new ways of working\nAction-Oriented \u2013 Be diplomatic and possess problem-solving and execution abilities and great project management skill\nResilient - Spring back quickly when encountering difficulties and failure. Maintain a positive mindset\nCollaborative \u2013 Be able to work with and respect people from different backgrounds and of different styles and able to defuse high-tension situations comfortably\u00a0\n\nIf you are driven by a desire to achieve and aim for excellence, please click through the \u201cApply Now\u201d to upload your CV and share your details with us.\u00a0\n\nInformation Session:\n\nDate: February 9, 2022 (Wednesday)\nTime: 11:30am - 12:30pm\nVenue: Hysan's Headquarter at Lee Garden One, Causeway Bay\nLanguage: Cantonese\nClick \u201cApply Now\u201d to register.\n\n\n\nHysan is an equal opportunity employer.\u00a0 All information collected will be kept in strict confidence and used solely for recruitment related purposes within the Hysan Group Companies.\n\nYou may get to know more about us through\u00a0www.hysan.com.hk", "employment_types": ["Full Time", "Permanent"], "selling_points": [], "locations": ["Mong Kok"], "categories": ["Property / Real Estate", "Property Consultancy", "Property Management", "Sales, CS & Business Devpt", "Sales - Real Estate"], "post_time": "2022-01-17T16:20:52Z", "salary": {"currency": null, "max": null, "min": null, "period": "monthly", "term": null}, "salary_visible": false, "title_keywords": ["senior leasing officer"], "responsibilities": ["management", "ideas", "business projects", "developing", "project management", "maintain", "recruitment"], "requirements": {"degrees": ["degree or above", "bachelor"], "majors": [], "languages": ["cantonese"], "language_level": [], "hard_skills": ["project management", "problem-solving", "spring"], "soft_skills": ["confidence", "positive mindset", "problem-solving", "diplomatic", "collaborative", "bold", "committed", "learning", "project management skill", "stable", "leadership", "driven"], "languages_combined": [{"language": "cantonese", "language_level": []}]}, "experience_required": {"duration": ["2 years"], "field": []}}, {"job_id": "100003009053955", "location_code": "hk", "company": "The Hong Kong Jockey Club", "job_title": "\u517c\u8077\u8a2d\u65bd\u670d\u52d9\u52a9\u7406(\u505c\u8eca\u5834\u670d\u52d9)", "description": "Reporting to the Senior Property Manager, the incumbent will assume overall responsibility for the management and operation of a diverse portfolio of the Group including office buildings, shopping malls, commercial buildings and serviced apartments in Hong Kong.\u00a0 He/She will oversee the day-to-day Estate Management and Technical Services, to provide a full range of services in the highest standard.\n\nRequirements:\n\nDegree or above in Surveying, Facilities Management, Property/Housing Management or related disciplines;\n6 years of property management experience for established developers, 3 years of which at\u00a0supervisory level;\nLess experience candidates will be considered for Senior Property Officer role;\nHands on experience in managing grade A commercial properties are essential;\nGood communication, presentation and interpersonal skills;\nSelf-motivated and attentive to details are required.\n\nWe offer attractive remuneration package to the right candidate.\u00a0 Interested parties please send full resume including current and expected salaries to the Head of Human Resources & Administration, Man Hing Hong Group, 31/F Man Yee Building, 68 Des Voeux Road Central, Hong Kong (website: www.mhh.com.hk)\n\n(All personal data collected will be used for recruitment purpose only)", "employment_types": ["Part Time", "Temporary", "Freelance"], "selling_points": ["\u505c\u8eca\u5834\u5de1\u67e5", "\u78ba\u8a8d\u5408\u9069\u6cca\u8eca\u8a3c\u53ca\u5b89\u6392\u9069\u7576\u6cca\u8eca\u4f4d\u7f6e", "\u63a7\u5236\u4ea4\u901a\uff0c\u4ee4\u884c\u4eba\u53ca\u8eca\u8f1b\u66a2\u9806"], "locations": ["Causeway Bay"], "categories": ["Hospitality / F & B", "Hospitality / Hotel Services", "Property / Real Estate", "Property Management", "Transportation & Logistics", "Private Transportation"], "post_time": "2022-01-17T07:50:40Z", "salary": {"currency": null, "max": null, "min": null, "period": null, "term": null}, "salary_visible": false, "title_keywords": [], "responsibilities": ["communication", "reporting", "management"], "requirements": {"degrees": ["degree or above"], "majors": ["related disciplines", "surveying"], "languages": [], "language_level": [], "hard_skills": ["facilities management"], "soft_skills": ["self-motivated", "attentive to details", "communication", "diverse", "hands on", "interpersonal skills", "presentation"], "languages_combined": []}, "experience_required": {"duration": ["6 years", "3 years"], "field": ["supervisory level", "management", "commercial"]}}, {"job_id": "100003009044542", "location_code": "hk", "company": "Tung Wah College", "job_title": "Assistant Facilities Manager, Facilities Management Office (TWC/22/007/FMO/AFM)", "description": "Responsibilities:\n\nAssist the Leasing Manager in handling daily leasing enquiries, marketing, lease negotiation, tenancy administration, co-ordination with property management and other related duties for a portfolio of shopping malls, office towers and retail shops\n\nRequirements:\n\nBachelor\u2019s degree with at least 2-3 years solid working experience in property leasing\nFamiliar with Landlord & Tenant (Cons.) Ordinance and leasing procedures\nCustomer-oriented and with good interpersonal and communication skills\nProactive attitude and strong business senses\nHolder of valid EAA licence is preferred\nGood command of both written and spoken English and Chinese\nKnowledge in PC applications, such as Word, Excel, Chinese Word-processing\nCandidate with less experience will be considered as Leasing Officer\n\nAttractive salary and fringe benefits package will be offered to the right candidates. Interested parties please apply with full resume stating current and expected salary by clicking \"APPLY NOW\" (Please quote the reference no.).\n\nPersonal data provided by job applicants will be used for recruitment purpose only.", "employment_types": ["Full Time"], "selling_points": ["Cleaning, security, catering, landscaping", "Facilities services and administrative services", "Tertiary Education"], "locations": ["Mong Kok"], "categories": ["Property / Real Estate", "Property Management"], "post_time": "2022-01-13T04:32:02Z", "salary": {"currency": null, "max": null, "min": null, "period": "monthly", "term": null}, "salary_visible": false, "title_keywords": ["manager", "assistant"], "responsibilities": ["management", "administration"], "requirements": {"degrees": ["degree", "bachelor"], "majors": [], "languages": ["english", "chinese"], "language_level": ["good command"], "hard_skills": ["excel", "chinese word-processing", "word", "pc applications"], "soft_skills": ["communication skills", "customer-oriented", "proactive", "interpersonal"], "languages_combined": [{"language": "english", "language_level": ["good command"]}, {"language": "chinese", "language_level": ["good command"]}]}, "experience_required": {"duration": ["at least 2-3 years"], "field": []}}, {"job_id": "100003009049518", "location_code": "hk", "company": "K11 Concepts Limited", "job_title": "11 SKIES - Senior Officer, Property Management (Housekeeping)", "description": "Job Responsibilities:\n\nMonitor the maintenance, security and cleaning services of\u00a0properties\nHandle enquiries, complaints and emergency incidents\nPerform administrative duties\n\nJob Requirements:\n\nHigher Diploma / Certificate in Property and Facility Management or qualification equivalent to Qualifications Framework\nAt least 4 years of\u00a0relevant experience in property\u00a0management\nGood analytical, communication and leadership skills\nMature, independent and able to work under pressure\nGood command of both written and spoken English and Chinese\nComputer literate in Ms Word, Excel and Chinese Word Processing\nCandidates with less experience will be considered as Assistant Estate Officer.\n\n\nWe provide attractive remuneration package and fringe benefits for the right candidate.\u00a0 Interested parties please send detailed resume with current & expected salaries via \u201cApply Now\u201d or send in your application through the Careers section in our Corporate Website: http://www.hongyip.com/Careers.\n\nHong Yip is an Equal Opportunity Employer.\u00a0 Personal data collected will be used for recruitment purpose only.\u00a0", "employment_types": ["Full Time", "Permanent"], "selling_points": ["New Project at Airport", "At least 3-5 years\u2019 relevant experience", "Good in report writing and procedure planning"], "locations": ["Airport Area"], "categories": ["Property / Real Estate", "Property Management"], "post_time": "2022-01-14T08:47:39Z", "salary": {"currency": null, "max": null, "min": null, "period": "monthly", "term": null}, "salary_visible": false, "title_keywords": ["housekeeping", "senior officer"], "responsibilities": ["maintenance", "monitor", "handle enquiries", "administrative duties", "cleaning"], "requirements": {"degrees": ["certificate", "diploma"], "majors": [], "languages": ["english", "chinese"], "language_level": ["good command"], "hard_skills": ["excel", "chinese word processing", "ms word"], "soft_skills": ["independent", "leadership skills", "mature", "communication", "work under pressure"], "languages_combined": [{"language": "english", "language_level": ["good command"]}, {"language": "chinese", "language_level": ["good command"]}]}, "experience_required": {"duration": ["at least 4 years"], "field": ["management", "relevant experience"]}}, {"job_id": "100003009055489", "location_code": "hk", "company": "Hong Kong Housing Society", "job_title": "Assistant Manager / Senior Officer (Planning & Development)", "description": "What You'll Do\n\nTo provide quality services to our residents and guests\nTo be responsible for daily operation of the property, including but not limited to office administration, procurement, customer services, complaint handling etc.\nTo supervise the overall performance of contractors to ensure their services\u00a0properly provided\nTo direct and supervise building staff\nTo perform other duties as assigned by supervisor\u00a0\n\nWho You\u2019ll Work With\n\nYou will work with the property services team and external contractors to provide excellent services to all residents and guests.\u00a0\u00a0\n\nWho You Are\n\nCompetencies:\n\nCustomer Oriented\nBuilds Teams\nDevelops Solutions\nPersonally Accountable\u00a0\n\nQualifications and Requirements:\n\nDegree / Diploma holder in Property Management, Facilities Management or related disciplines\nAt least 5 years' relevant experience in\u00a0residential building\nCandidates with Senior Officer title will also be considered\nMember of a professional body recognized by the\u00a0PMSA\u00a0is an advantage\nGood command of both spoken and written English and Chinese\nProficient in MS Office\n\u00a0", "employment_types": ["Permanent"], "selling_points": ["Formulate the overall sales exercises", "Co-ordinate a flats handover team", "Sale/leasing of residential/elderly projects"], "locations": ["Quarry Bay"], "categories": ["Property / Real Estate", "Property Management"], "post_time": "2022-01-18T02:39:01Z", "salary": {"currency": null, "max": null, "min": null, "period": "monthly", "term": null}, "salary_visible": false, "title_keywords": ["assistant manager", "senior officer"], "responsibilities": ["perform other duties", "management", "office administration", "daily operation", "quality", "teams", "customer services"], "requirements": {"degrees": ["diploma holder", "degree"], "majors": ["related disciplines"], "languages": ["english", "chinese"], "language_level": ["good command"], "hard_skills": ["facilities management", "ms office"], "soft_skills": ["accountable", "responsible"], "languages_combined": [{"language": "english", "language_level": ["good command"]}, {"language": "chinese", "language_level": ["good command"]}]}, "experience_required": {"duration": ["at least 5 years"], "field": ["relevant experience"]}}, {"job_id": "100003009055355", "location_code": "hk", "company": "Protech Property Management Ltd", "job_title": "\u4fdd\u5b89\u54e1 - \u65e5\u73ed (\u65fa\u89d2)", "description": "\u8077\u8cac :\u8ca0\u8cac\u4e00\u822c\u5c4b\u82d1\u4fdd\u5b89\u5de5\u4f5c\uff0c\u8ca0\u8cac\u65bc\u63a7\u5236\u5ba4\u7576\u503c\u53ca\u8655\u7406\u7a81\u767c\u4e8b\u4ef6\n\u8cc7\u6b77 :\u5c0f\u516d\u7a0b\u5ea6; 1\u5e74\u7d93\u9a57; \u826f\u597d\u7cb5\u8a9e; \u61c2\u8b80\u5beb\u4e2d\u6587; \u6301\u6709\u4fdd\u5b89\u57f9\u8a13\u8ab2\u7a0b\u8b49\u66f8(QAS); \u6301\u6709\u4fdd\u5b89\u4eba\u54e1\u8a31\u53ef\u8b49; \u5177\u826f\u597d\u6e9d\u901a\u6280\u5de7\u53ca\u5ba2\u6236\u670d\u52d9\u614b\u5ea6\n\u5f85\u9047 :\u6bcf\u6708$16,000 - $17,000, \u6709\u6bcf\u6708\u52e4\u5de5\u734e\u91d1$1000, \u8d85\u6642\u5de5\u4f5c\u6d25\u8cbc \u53ca\u6649\u5347\u6a5f\u6703, \u4e0a\u53487\u6642\u81f3\u4e0b\u53487\u6642, \u4e0b\u53487\u6642\u81f3\u4e0a\u53487\u6642, \u6bcf\u9031\u5de5\u4f5c6\u5929,\u8f2a\u73ed,\u8f2a\u4f11, \u6bcf\u5929\u5de5\u4f5c 12 \u5c0f\u6642\n\u7533\u8acb\u9808\u77e5 :\u6c42\u8077\u8005\u53ef\u6309 APPLY NOW\u7533\u8acb\u6216\u81f4\u96fb26522362\u8207\u6607\u6377\u7ba1\u7406\u670d\u52d9\u6709\u9650\u516c\u53f8\u6881\u5148\u751f\u806f\u7d61\u3002", "employment_types": ["Full Time"], "selling_points": [], "locations": ["Mong Kok"], "categories": ["Property / Real Estate", "Property Management", "Others", "Others", "Security / Safety Control"], "post_time": "2022-01-18T02:17:32Z", "salary": {"currency": null, "max": null, "min": null, "period": "monthly", "term": null}, "salary_visible": false, "title_keywords": ["\u4fdd\u5b89\u54e1"], "responsibilities": [], "requirements": {"degrees": [], "majors": [], "languages": [], "language_level": [], "hard_skills": [], "soft_skills": [], "languages_combined": []}, "experience_required": {"duration": [], "field": []}}, {"job_id": "100003009056378", "location_code": "hk", "company": "\u6607\u6377\u7ba1\u7406\u670d\u52d9\u6709\u9650\u516c\u53f8", "job_title": "\u591c\u66f4\u4fdd\u5b89\u54e1", "description": "\u8077\u8cac :\u4e00\u822c\u5c4b\u82d1\u4fdd\u5b89\u5de5\u4f5c\n\u8cc7\u6b77 :\u5c0f\u516d\u7a0b\u5ea6; \u826f\u597d\u7cb5\u8a9e; \u7565\u61c2\u8b80\u5beb\u4e2d\u6587; \u6301\u6709\u4fdd\u5b89\u57f9\u8a13\u8ab2\u7a0b\u8b49\u66f8(QAS); \u6301\u6709\u4fdd\u5b89\u4eba\u54e1\u8a31\u53ef\u8b49; \u6709\u8cac\u4efb\u611f\n\u5f85\u9047 :\u6bcf\u6708$14,500, \u6709\u5728\u8077\u57f9\u8a13 \u53ca\u91ab\u7642\u798f\u5229, \u4e0b\u53487\u6642\u81f3\u4e0a\u53487\u6642, \u6bcf\u9031\u5de5\u4f5c6\u5929,\u8f2a\u4f11, \u6bcf\u5929\u5de5\u4f5c 12 \u5c0f\u6642\n\u7533\u8acb\u9808\u77e5 :\u6c42\u8077\u8005\u53ef\u6309 APPLY NOW\u7533\u8acb\u6216\u81f4\u96fb23522124\u8207\u6607\u6377\u7ba1\u7406\u670d\u52d9\u6709\u9650\u516c\u53f8\u9ea5\u5148\u751f\u806f\u7d61\u3002", "employment_types": ["Full Time"], "selling_points": ["\u65e5\u5e38\u4fdd\u5b89\u5de5\u4f5c/\u5de1\u908f", "\u6c92\u6709\u5b78\u6b77\u8981\u6c42", "1\u5e74\u7d93\u9a57"], "locations": ["Shatin Area"], "categories": ["Property / Real Estate", "Property Management", "Others", "Others", "Security / Safety Control"], "post_time": "2022-01-18T04:06:46Z", "salary": {"currency": null, "max": null, "min": null, "period": "monthly", "term": null}, "salary_visible": false, "title_keywords": [], "responsibilities": [], "requirements": {"degrees": [], "majors": [], "languages": [], "language_level": [], "hard_skills": [], "soft_skills": [], "languages_combined": []}, "experience_required": {"duration": [], "field": []}}, {"job_id": "100003009048111", "location_code": "hk", "company": "Kerry Properties Limited", "job_title": "(Senior) Officer, Property Services (Central Mid-level)", "description": "Chevalier Property Management Limited, a subsidiary of Chevalier Group, is now inviting high calibre persons to apply for this position:\n\nResponsibilities\n\nOversee and monitor the day-to-day operation of mixed portfolio with small scale residential / industrial / commercial buildings\nOversee the performance of security and cleaning service\nAttend I.O. Meeting and/or Annual General Meeting\nArrange repair and maintenance work\nHandle complaints and enquiries of the customers\n\n\u00a0Requirements\n\nDiploma holder or above in Housing Management, Estate Management, Property Management or related disciplines\nHolder of valid Property Management License (Tier 1) will be an advantage\nAt least 3 years or above relevant working experience in property management field\nExperience in administration\u00a0will be an advantage\nMature, independent and strong sense of responsibility\nGood\u00a0command of both spoken and written English and Chinese\nProficient in MS Office including MS Word, MS Excel and Chinese word processing etc.\n\nCandidate with less qualification and experience will be considered for the position of Estate Officer\n\nAttractive remuneration package will be offered to the right candidate.\nInterested parties, please send your resume with current and expected salary by clicking \"Apply Now\" or mail to:\u00a0\n\nThe Human Resources Manager, Chevalier Group, 22/F Chevalier Commercial Centre, 8 Wang Hoi Road, Kowloon Bay, Hong Kong.\n\nWe are an equal opportunity employer and welcome applications from all qualified candidates.\u00a0 Personal data collected would be used for recruitment purpose only.\n\n\nWelcome to visit http://www.chevalierpropmgt.com.hk\u00a0", "employment_types": ["Permanent"], "selling_points": ["Top-tier Properties Management Company", "Promising Career Path", "Competitive Compensation Package"], "locations": ["Central"], "categories": ["Property / Real Estate", "Property Management"], "post_time": "2022-01-14T04:57:12Z", "salary": {"currency": null, "max": null, "min": null, "period": "monthly", "term": null}, "salary_visible": false, "title_keywords": ["officer"], "responsibilities": ["maintenance", "monitor", "handle complaints", "repair", "cleaning", "day-to-day operation"], "requirements": {"degrees": ["diploma holder"], "majors": ["related disciplines"], "languages": ["english", "chinese"], "language_level": ["good command", "proficient"], "hard_skills": ["ms word", "ms excel", "chinese word processing", "ms office"], "soft_skills": ["independent", "mature", "sense of responsibility"], "languages_combined": [{"language": "english", "language_level": ["good command"]}, {"language": "chinese", "language_level": ["good command", "proficient"]}]}, "experience_required": {"duration": ["at least 3 years"], "field": ["management", "relevant working experience", "administration"]}}, {"job_id": "100003009044926", "location_code": "hk", "company": "Well Sight Property Management Limited", "job_title": "Property Officer/Assistant Property Officer", "description": "Responsibilities\n\nAssist the Manager to monitor the execution of brand book, policies and strategies instituted by the company and Senior Management, and to supervise daily operations of the housekeeping vendors and sundry items suppliers\nConduct housekeeping standard check and review and manage the housekeep vendors\u2019 performance\nCoordinate all building maintenance, fitting-out, contract works, improvement, decoration, renovation and ad hoc projects\nAdminister and coordinate all properties functions, maintaining intimate relationship with tenants, and reply enquires and complaints from tenant, customer and media if needed\nReview and recommend enhancement of existing building management system and green management system for improving performance, reliability, durability and energy conservation\nIdentify problem / risk areas in management and recommend improvement / contingency plans to not only maximize the efficiency of management but also avoid potential dangers for assigned portfolio\nExecute all standard procedures and emergency handling\n\n\u00a0Requirements\n\nAt least 3-5 years\u2019 relevant experience in Property Management\nMember of professional organization (eg. RPHM, HKIH, CIH) preferred\nStrong and effective leadership with solid people and team management\nResults-driven, flexible with good interpersonal skills and ability to multi-task projects\nGood command of English and Chinese. Proficiency in Putonghua an advantage\nGood in report writing and procedure planning", "employment_types": ["Full Time", "Permanent"], "selling_points": ["14 Annual Leave, Medical Insurance", "Public Holiday", "Performance Bonus"], "locations": ["Chai Wan"], "categories": ["Property / Real Estate", "Property Management"], "post_time": "2022-01-13T06:39:46Z", "salary": {"currency": null, "max": null, "min": null, "period": "monthly", "term": null}, "salary_visible": false, "title_keywords": ["property officer", "assistant property officer"], "responsibilities": ["management", "maintenance", "maintaining", "housekeeping", "policies", "review", "monitor", "renovation", "procedures", "coordinate", "building management", "daily operations", "ad hoc projects", "plans", "senior management"], "requirements": {"degrees": [], "majors": [], "languages": ["putonghua", "english", "chinese"], "language_level": ["advantage", "proficiency", "good command"], "hard_skills": [], "soft_skills": ["flexible", "multi-task", "interpersonal skills", "leadership", "driven"], "languages_combined": [{"language": "putonghua", "language_level": ["proficiency", "advantage"]}, {"language": "english", "language_level": ["good command"]}, {"language": "chinese", "language_level": ["good command"]}]}, "experience_required": {"duration": ["at least 3-5 years"], "field": ["management", "relevant experience"]}}, {"job_id": "100003009049519", "location_code": "hk", "company": "K11 Concepts Limited", "job_title": "11 SKIES - Duty Property Officer \u503c\u73ed\u7269\u696d\u4e3b\u4efb", "description": "[Ref: AMSO(P&D)]\n\n\nThe Job\n\nProvide comprehensive professional support in market research, critically examine restrictions and opportunities on land and planning issues and prudent calculations on financial commitment and results on new initiatives feasibilities studies.\nLiaise with planning environmental and other consultants to prepare Master layout Plan for new projects and associated planning submissions.\nAssist to formulate the overall sales exercises for sales projects including preparation of pricing structure and coordination with architects, advertising consultants and solicitors on sales matters etc.\nCo-ordinate a flats handover team to execute the logistics of the whole handover process and to follow up with all defect rectifications with various stakeholders.\nHandle all building defects requests, enquiries and/or complaint received from the owners and Estate Management Office after the expiry of defect liability period.\nAdvice to all stakeholders and process all applications on various consents related to Flat-for-Sales Scheme secondary market, consent to assign, and re-financing etc.\nPrepare valuation reports on all HS investment properties for reference on market rental levels and annual asset valuation.\nAssist in the sale/leasing of residential/elderly projects and other duties assigned.\n\nThe Person\n\nDegree holder in Surveying, Real Estate, Land Management, Property Management or related disciplines, with minimum 4 years relevant experience OR Diploma/Certificate holder with minimum 8 years relevant experience.\nExperience in valuation and feasibility studies, property development, town planning, sales and marketing of properties will be a definite advantage.\nPreferably with professional qualification of the RICS or HKIS or equivalent.\nStrong communication, interpersonal and organization skills.\nExcellent spoken and written English and Chinese. Good spoken Mandarin is an advantage.\nProficiency in MS Windows application, including Excel, Word, PowerPoint and Chinese Word Processing.\nCandidates with less experience will be considered as Senior Officer (Planning & Development).\n\nAttractive remuneration package will be offered to suitable candidates. To apply, please submit online application: https://careers.hkhs.com/ or send your application with full resume and reference quoted to Human Resources Manager by fax: 2882 4466.\n\nYou are welcome to visit our website www.hkhs.com to learn more about us.\nApplicants not invited for interview within 8 weeks may consider their applications unsuccessful.\n\nPersonal data provided by job applicants will be used strictly in accordance with the Housing Society\u2019s personal data policies which is available in our website and obtainable upon request. Please refer to the Policy Statement on Employment Related Data under Personal Data (Privacy) Ordinance in our website.", "employment_types": ["Full Time", "Permanent"], "selling_points": ["At least 2 years at supervisory level", "Holder of Security Personnel Permit", "Work on shift and call, Airport Area"], "locations": ["Airport Area"], "categories": ["Property / Real Estate", "Property Management"], "post_time": "2022-01-14T08:47:40Z", "salary": {"currency": null, "max": null, "min": null, "period": "monthly", "term": null}, "salary_visible": false, "title_keywords": ["property officer"], "responsibilities": ["valuation", "management", "advertising", "other duties", "coordination with", "market research", "logistics", "reports", "plan", "liaise with", "planning"], "requirements": {"degrees": ["certificate", "diploma", "degree holder"], "majors": ["related disciplines", "surveying"], "languages": ["english", "chinese", "mandarin"], "language_level": ["advantage", "excellent", "proficiency", "good"], "hard_skills": ["excel", "chinese word processing", "hkis", "ms windows", "word", "rics", "powerpoint"], "soft_skills": ["communication", "organization skills", "interpersonal"], "languages_combined": [{"language": "english", "language_level": ["excellent"]}, {"language": "chinese", "language_level": ["excellent", "proficiency"]}, {"language": "mandarin", "language_level": ["good", "advantage"]}]}, "experience_required": {"duration": ["minimum 4 years", "minimum 8 years"], "field": ["management", "related", "development", "marketing", "relevant experience", "planning"]}}, {"job_id": "100003009050052", "location_code": "hk", "company": "Hong Yip Service Company Limited", "job_title": "Property and Facility Officer (5-day work) - North Point", "description": "\u8077\u8cac :\u4e00\u822c\u4fdd\u5b89\u5de5\u4f5c\n\u8cc7\u6b77 :\u5c0f\u516d\u7a0b\u5ea6; 1\u5e74\u7d93\u9a57; \u826f\u597d\u7cb5\u8a9e; \u61c2\u8b80\u5beb\u4e2d\u6587; \u6301\u6709\u4fdd\u5b89\u57f9\u8a13\u8ab2\u7a0b\u8b49\u66f8(QAS); \u6301\u6709\u4fdd\u5b89\u4eba\u54e1\u8a31\u53ef\u8b49\n\u5f85\u9047 :\u6bcf\u6708$13,000, \u6709\u91ab\u7642\u4fdd\u96aa \u53ca\u8d85\u6642\u5de5\u4f5c\u6d25\u8cbc, \u4e0a\u534810\u6642\u81f3\u4e0b\u534810\u6642,\u4e0a\u53488\u6642\u81f3\u4e0b\u53488\u6642\u6216\u4e2d\u534812\u6642\u81f3\u51cc\u666812\u6642, \u6bcf\u9031\u5de5\u4f5c6\u5929,\u8f2a\u73ed,\u8f2a\u4f11, \u6bcf\u5929\u5de5\u4f5c 12 \u5c0f\u6642\n\u7533\u8acb\u9808\u77e5 :\u6c42\u8077\u8005\u53ef\u6309 APPLY NOW\u7533\u8acb\u6216\u81f4\u96fb31011000\u8207\u4fdd\u5f97\u7269\u696d\u7ba1\u7406\u6709\u9650\u516c\u53f8\u65bd\u5c0f\u59d0\u806f\u7d61\u3002", "employment_types": ["Full Time", "Permanent"], "selling_points": ["Wholly owned subsidiary of Sun Hung Kai Properties", "Holder of a recognized degree", "At least 2 years' relevant working experience"], "locations": ["Not Specified"], "categories": ["Sales, CS & Business Devpt", "Customer Service - Supervisor / Officer", "Property / Real Estate", "Property Management", "Others"], "post_time": "2022-01-15T03:50:48Z", "salary": {"currency": null, "max": null, "min": null, "period": "monthly", "term": null}, "salary_visible": false, "title_keywords": ["officer"], "responsibilities": [], "requirements": {"degrees": [], "majors": [], "languages": [], "language_level": [], "hard_skills": [], "soft_skills": [], "languages_combined": []}, "experience_required": {"duration": [], "field": []}}, {"job_id": "100003009056387", "location_code": "hk", "company": "\u6607\u6377\u7ba1\u7406\u670d\u52d9\u6709\u9650\u516c\u53f8", "job_title": "\u517c\u8077\u4fdd\u5b89\u54e1", "description": "\u8077\u8cac :\u65e5\u5e38\u4fdd\u5b89\u5de5\u4f5c/\u5de1\u908f\n\u8cc7\u6b77 :\u6c92\u6709\u5b78\u6b77\u8981\u6c42; 1\u5e74\u7d93\u9a57; \u4e00\u822c\u7cb5\u8a9e; \u7565\u61c2\u8b80\u5beb\u4e2d\u6587; \u6301\u6709\u4fdd\u5b89\u57f9\u8a13\u8ab2\u7a0b\u8b49\u66f8(QAS); \u6301\u6709\u4fdd\u5b89\u4eba\u54e1\u8a31\u53ef\u8b49\n\u5f85\u9047 :\u6bcf\u6708$10,300 - $10,750, \u4e0b\u534811\u6642\u81f3\u4e0a\u53487\u6642, \u6bcf\u9031\u5de5\u4f5c6\u5929,\u8f2a\u4f11, \u6bcf\u5929\u5de5\u4f5c 8 \u5c0f\u6642\n\u7533\u8acb\u9808\u77e5 :\u6c42\u8077\u8005\u53ef\u6309 APPLY NOW\u7533\u8acb\u6216\u81f4\u96fb26182979\u8207\u6607\u6377\u7ba1\u7406\u670d\u52d9\u6709\u9650\u516c\u53f8\u9673\u5148\u751f\u806f\u7d61\u3002", "employment_types": ["Part Time"], "selling_points": ["\u8ca0\u8cac\u4e00\u822c\u5c4b\u82d1\u4fdd\u5b89\u5de5\u4f5c", "\u6c92\u6709\u5b78\u6b77\u8981\u6c42; 1\u5e74\u7d93\u9a57", "\u6301\u6709\u4fdd\u5b89\u4eba\u54e1\u8a31\u53ef\u8b49"], "locations": ["Tai Po Area"], "categories": ["Property / Real Estate", "Property Management", "Others", "Others", "Security / Safety Control"], "post_time": "2022-01-18T04:08:06Z", "salary": {"currency": null, "max": null, "min": null, "period": "hourly", "term": null}, "salary_visible": false, "title_keywords": [], "responsibilities": [], "requirements": {"degrees": [], "majors": [], "languages": [], "language_level": [], "hard_skills": [], "soft_skills": [], "languages_combined": []}, "experience_required": {"duration": [], "field": []}}, {"job_id": "100003009055543", "location_code": "hk", "company": "Hong Kong Housing Society", "job_title": "Property Manager / Assistant Manager (Maintenance-Building Services)", "description": "(Working Location:\u00a0 Chai Wan)\n\nResponsibilities\n\u00a0\n\nAssist the Property Manager to oversee and monitor the day-to-day property\u00a0 management functions\n\u00a0Requirements:\n\nHolder of Degree or Diploma in Property Management or related disciplines\nProperty Officer at least 3 years working experience in property management\nAssistant Property Officer at least 1 year working experience in property management\nBe responsible and good interpersonal skills\nGood command of spoken & written skills in both English & Chinese\nPC literature, typing skill both in English & Chinese etc.\nProficient in MS Word, Excel Processing\nWe offer generous remuneration package and excellent career development to the right candidates.\u00a0 Shall you have any queries; please feel free to contact Ms. Chan at 2781 2208. Please apply now.\n\n\n(All data collected will be used for recruitment purpose only.)", "employment_types": ["Permanent"], "selling_points": ["Urgent repairs in building services installations", "Recommend the improvement program", "8 years\u2019 exp. in building services maintenance"], "locations": ["Others"], "categories": ["Property / Real Estate", "Property Management"], "post_time": "2022-01-18T02:41:36Z", "salary": {"currency": null, "max": null, "min": null, "period": "monthly", "term": null}, "salary_visible": false, "title_keywords": ["assistant manager", "property manager"], "responsibilities": ["management", "monitor"], "requirements": {"degrees": ["diploma", "degree"], "majors": ["related disciplines"], "languages": ["english", "chinese"], "language_level": ["good command"], "hard_skills": ["excel", "typing", "pc", "processing", "ms word"], "soft_skills": ["interpersonal skills", "responsible"], "languages_combined": [{"language": "english", "language_level": ["good command"]}, {"language": "chinese", "language_level": ["good command"]}]}, "experience_required": {"duration": ["at least 3 years", "at least 1 year"], "field": ["management"]}}, {"job_id": "100003009055946", "location_code": "hk", "company": "Waihong Environmental Services Limited", "job_title": "Assistant Operations Manager (Ref: OPS0101)", "description": "\u300a\u5bcc\u7238\u7238\uff0e\u7aae\u7238\u7238\u300b\u4f5c\u8005\u7f85\u4f2f\u7279\u6e05\u5d0e\u8b1b\u904e\uff1a\u300c\u592a\u591a\u4eba\u5fd8\u4e86\u53bb\u95dc\u6ce8\u81ea\u5df1\u7684\u4e8b\u696d\uff0c\u4ed6\u5011\u8017\u76e1\u4e00\u4e16\u53bb\u95dc\u6ce8\u5225\u4eba\u7684\u4e8b\u696d\uff0c\u4e26\u4f7f\u4ed6\u4eba\u81f4\u5bcc\u3002\u300d\u6211\u5011\u5e0c\u671b\u5c0b\u627e\u6240\u6709\u60f3\u70ba\u81ea\u5df1\u5275\u4e8b\u696d\u52aa\u529b\u62fc\u535a\u7684\u4eba\u3002\n\n\u751f\u65bc\u9019\u500b\u659c\u69d3\u65b0\u4e16\u4ee3\uff0c\u6bcf\u4eba\u8981\u64c1\u6709\u4e26\u4e0d\u662f\u5341\u9805\u5168\u80fd\uff0c\u800c\u662f\u8981\u69cb\u5efa\u81ea\u6211\u5275\u696d\u601d\u7dad\u3002\u52a0\u5165AXA\u9577\u76db\u7406\u8ca1\u5718\u968a\uff0c\u4f60\u6703\u57f9\u990a\u51fa\u505a\u751f\u610f\u7684\u5275\u696d\u982d\u8166\uff0c\u8df3\u51fa\u807d\u4e0a\u53f8\u6307\u4ee4\u7684\u6253\u5de5\u4ed4\u751f\u6daf\uff0c\u8e0f\u5be6\u800c\u9577\u9060\u5efa\u7acb\u5c6c\u65bc\u60a8\u7684\u500b\u4eba\u4fdd\u96aa\u4e8b\u696d\u3002\n\n\u5340\u57df\u80cc\u666f\uff1a\n\n- \u8d85\u904e20\u5e74\u767c\u5c55\u5927\u4e2d\u83ef\u5730\u5340\u5e02\u5834\u7d93\u9a57\uff0c\u5340\u57df\u4eba\u6578\u9054200\u4eba\n- \u6210\u54e1\u4f86\u81ea\u4e0d\u540c\u5c08\u696d\u80cc\u666f\uff0c\u6709\u524d\u5f8b\u5e2b\uff0c\u9280\u884c\u5bb6\uff0c\u5546\u4eba\uff0cIT\u5c08\u696d\u4eba\u58eb\u7b49\u7b49\uff0c\u7121\u8ad6\u5c0d\u9ad8\u7aef\u5ba2\u6236\u6216\u662f\u4e2d\u7522\u5ba2\u6236\u92b7\u552e\u90fd\u6709\u8c50\u5bcc\u7d93\u9a57\u3002\n\n\u5718\u968a\u80cc\u666f\uff1a\n\n\u9577\u76db\u7406\u8ca1\u5275\u8fa6\u4ebaSam\u7576\u521d\u6c7a\u5b9a\u88f8\u8fad\u5275\u696d\uff0c\u4e8b\u696d\u9054\u5230\u985b\u5cf0\u6210\u5c31\u5230\u751f\u610f\u5931\u6557\u5f8c\uff0c\u4f46\u537b\u7121\u640d\u5efa\u7acb\u4e8b\u696d\u738b\u570b\u7684\u9b25\u5fc3\uff0c\u6c7a\u5b9a\u7531\u4fdd\u96aa\u696d\u958b\u59cb\u6771\u5c71\u518d\u8d77\uff0c\u4e26\u6700\u5f8c\u50c5\u7528\u4e86\u5169\u5e74\u6642\u9593\u9054\u5230COT \uff08\u53733\u500dMDRT\uff09\u3002\n\n\u806f\u5408\u5275\u8fa6\u4ebaCharlotte\u5f9e\u4e8b\u7532\u7d1a\u5546\u5834\u79df\u52d9\u8d85\u904e10\u5e74\uff0c\u6709\u611f\u7121\u9650OT\u7684\u6253\u5de5\u4ed4\u751f\u6d3b\u672a\u80fd\u517c\u9867\u7167\u9867\u5169\u500b\u5e74\u5e7c\u5152\u5b50\uff0c\u65bc\u662f\u4e0b\u5b9a\u6c7a\u5fc3\u8df3\u51facomfort zone\u52a0\u5165\u7406\u8ca1\u7b56\u5283\u884c\u696d, \u81ea\u7531\u5de5\u4f5c\u6a21\u5f0f\u8b93\u5979\u5de5\u4f5c\u66f4\u6709\u62fc\u52c1\u53c8\u591a\u4e86\u6642\u9593\u7167\u9867\u5bb6\u5ead\uff0c\u5165\u8077\u77ed\u77ed5\u500b\u6708\u4fbf\u9054\u6a19MDRT 2021, \u4eca\u5e74\u4ea6\u5df2\u5b8c\u6210MDRT 2022\uff01\n\n\u9577\u76db\u7406\u8ca1\u5718\u968a\u6df1\u4fe1\u4fdd\u96aa\u4e0d\u53ea\u662f\u4e00\u500b\u7406\u8ca1\u7b56\u5283\u7684\u884c\u696d\uff0c\u800c\u662f\u8b93\u6bcf\u4eba\u5efa\u7acb\u500b\u4eba\u751f\u610f\u7684\u8d77\u6b65\u9ede\u3002\u5718\u968a\u6210\u54e1\u4f86\u81ea\u9999\u6e2f\uff0c\u83f2\u5f8b\u8cd3\uff0c\u97d3\u570b\uff0c\u5370\u5ea6\u7b49\u7b49\uff0c\u4e0d\u540c\u6587\u5316\u601d\u7dad\u52a9\u4f60\u958b\u62d3\u65b0\u601d\u7dad\uff01\u6211\u5011\u6574\u500b\u5718\u968a\u6703\u4e00\u76f4\u4f5c\u70ba\u60a8\u7684\u5275\u696d\u540c\u8def\u4eba\u652f\u63f4\u4f60\u548c\u5354\u52a9\u4f60\u9054\u6210\u500b\u4eba\u751f\u610f\u76ee\u6a19\uff0c\u5efa\u7acb\u81ea\u5df1\u7684\u4e8b\u696d\u738b\u570b\u3002\n\n\u4f60\u6703\u7372\u5f97\u4ec0\u9ebc\uff1f\n\n\u6bcf\u6708\u6d25\u8cbc\u4e0a\u9650HK$50,000\uff0c\u6700\u9ad8\u53ef\u9054\u904e\u5f80\u6708\u85aa\u4e4b100%\n\u5b8c\u5584\u4f63\u91d1\u5236\u5ea6\u53ca\u71df\u92b7\u734e\u8cde\uff0c\u5305\u62ec\u6bcf\u6708\u4f63\u91d1\uff0c\u6bcf\u5b63\u734e\u91d1\uff0c\u5e74\u7d42\u734e\u91d1\uff0c\u6d77\u5916\u696d\u52d9\u6703\u8b70\u7b49\uff0c\u734e\u52f5\u5091\u51fa\u8868\u73fe\n\u5168\u9762\u57f9\u8a13\u8ab2\u7a0b\uff0c\u63d0\u5347\u500b\u4eba\u7af6\u722d\u529b\uff0c\u5e6b\u52a9\u7a4d\u6975\u8f49\u884c\u4eba\u58eb\n\u6e05\u6670\u6649\u5347\u968e\u68af\uff0c\u7a4d\u6975\u914d\u5408\u4e8b\u696d\u767c\u5c55\n\u81ea\u4e3b\u5de5\u4f5c\u6642\u9593\uff0c\u5e73\u8861\u5bb6\u5ead\u548c\u751f\u6d3b\n\n\u5de5\u4f5c\u7bc4\u570d\uff1a\n\n\u70ba\u5ba2\u6236\u63d0\u4f9b\u5404\u9805\u5c08\u696d\u7684\u7406\u8ca1\u65b9\u6848\uff0c\u5982\u5065\u5eb7\u4fdd\u969c\u3001\u98a8\u96aa\u7ba1\u7406\u3001\u9000\u4f11\u57fa\u91d1\u3001\u6559\u80b2\u57fa\u91d1\u8cc7\u7522\u914d\u7f6e\u7b49\n\u5efa\u7acb\u826f\u597d\u5ba2\u6236\u95dc\u4fc2\uff0c\u62d3\u5c55\u5ba2\u6236\u7db2\u7d61\uff0c\u5b9a\u671f\u4e86\u89e3\u4ed6\u5011\u7684\u8ca1\u653f\u9700\u8981\u53ca\u6aa2\u8a0e\u73fe\u6709\u7406\u8ca1\u8a08\u5283\n\u70ba\u73fe\u6709\u5ba2\u6236\u63d0\u4f9b\u512a\u8cea\u552e\u5f8c\u670d\u52d9\u53ca\u8655\u7406\u7406\u8ce0\u4e8b\u9805\n\n\u5165\u8077\u8981\u6c42:\n\n\u5927\u5b78\u5b78\u58eb\u7562\u696d\u6216\u4ee5\u4e0a\n\u6216\u4e2d\u4e94\u6703\u8003\u6216\u4e2d\u5b78\u6587\u6191\u8003\u8a665\u79d1\u5408\u683c(\u5305\u62ec\u4e2d\uff0c\u82f1\uff0c\u6578)\u6216\u540c\u7b49\u7a0b\u5ea6\u4ee5\u4e0a\n\u6e34\u671b\u4ee5\u5408\u4f19\u4eba\u7684\u8eab\u4efd\u53c3\u8207\u4f4e\u6210\u672c\u3001\u4f4e\u98a8\u96aa\u7684\u5275\u696d\u9805\u76ee\uff0c\u6253\u9020\u5c6c\u65bc\u500b\u4eba\u7684\u54c1\u724c\u548c\u696d\u52d9\u5718\u968a\n\u8655\u4e8b\u6210\u719f\uff0c\u5177\u826f\u597d\u4eba\u969b\u6280\u5de7\n\n\u5982\u6709\u8208\u8da3\u8acbwhatsapp\u4f60\u7684CV\u52309150 3700 (\u8d99\u5c0f\u59d0)", "employment_types": ["Full Time", "Permanent"], "selling_points": [], "locations": ["Not Specified"], "categories": ["Management", "General Management", "Property / Real Estate", "Property Management", "Others", "Others"], "post_time": "2022-01-18T03:07:17Z", "salary": {"currency": null, "max": null, "min": null, "period": "monthly", "term": null}, "salary_visible": false, "title_keywords": ["assistant operations manager"], "responsibilities": [], "requirements": {"degrees": [], "majors": [], "languages": [], "language_level": [], "hard_skills": [], "soft_skills": [], "languages_combined": []}, "experience_required": {"duration": [], "field": []}}, {"job_id": "100003009056355", "location_code": "hk", "company": "\u6607\u6377\u7ba1\u7406\u670d\u52d9\u6709\u9650\u516c\u53f8", "job_title": "\u517c\u8077\u4fdd\u5b89\u54e1", "description": "Responsibilities\n\n\nServe as the shift-in-charge to ensure smooth day-to-day operation of specific assigned building facilities (including carpark) and management services which include: tenant and customer services, maintenance, cleaning, security, traffic control etc., so as to deliver first class services to all tenants\nEnforce landlord\u2019s rights and statutory requirements\nMonitor the performance of contractors together with technical team as and when required\nMotivate and monitor staff members supervised to work closely with other internal departments like Leasing, Security, Technical and CS teams to ensure smooth daily operations, marketing and company activities\nHandle complaints, requests and enquiries, issue complaint-handling forms/work orders to respective departments concerned, support marketing activities and continuously strengthen relations with tenants\nSupport the management in implementing the company policies such as customer services, safety, health and environmental as directed, ensuring initiatives are effectively carried out\n\nRequirements\u00a0\n\nAt least 5 years property management experience of which 2 years at supervisory level\nGood leadership, interpersonal and communications skills\nCan deliver clear instructions\nExcellent customer service attitude\nWork on 24 hours shift and call\nHolder of Security Personnel Permit\nMember (or student member) of CIH / HKIH preferred (but not compulsory)", "employment_types": ["Part Time"], "selling_points": ["\u4e00\u822c\u4fdd\u5b89\u5de5\u4f5c", "\u4e2d\u4e00\u7a0b\u5ea6; 1\u5e74\u7d93\u9a57", "\u4e00\u822c\u7cb5\u8a9e\u512a\u5148"], "locations": ["North Point"], "categories": ["Property / Real Estate", "Property Management", "Others", "Others", "Security / Safety Control"], "post_time": "2022-01-18T04:03:45Z", "salary": {"currency": null, "max": null, "min": null, "period": "hourly", "term": null}, "salary_visible": false, "title_keywords": [], "responsibilities": ["management", "control", "maintenance", "policies", "monitor", "teams", "customer services", "handle complaints", "statutory requirements", "daily operations", "monitor the performance", "cleaning", "day-to-day operation"], "requirements": {"degrees": [], "majors": [], "languages": [], "language_level": [], "hard_skills": ["security personnel permit"], "soft_skills": ["clear", "customer service", "leadership", "interpersonal"], "languages_combined": []}, "experience_required": {"duration": ["2 years", "at least 5 years"], "field": ["supervisory level", "management"]}}, {"job_id": "100003009048999", "location_code": "hk", "company": "Hongkong Land Group Limited", "job_title": "\u7ba1\u696d\u4e3b\u4efb (\u4fdd\u5b89\u4e3b\u7ba1) (Ref: PM-BS-JDB)", "description": "Job Responsibilities:\n\nAssist the area manager in providing high-quality property management services\nOrganize meetings and carry out administrative duties for Incorporated Owners\nEstablish and maintain good relationship with tenants\nHandle emergency incidents, customer inquiries and complaints\nMonitor the standards of maintenance, security and cleaning services of properties\u00a0\n\nJob Requirements:\n\nHolder of a recognized degree or qualification equivalent to Qualifications Framework Level 5\nAt least 2 years' relevant working experience\u00a0preferably in\u00a0residential property\nCustomer service-oriented and able to work under pressure\nGood command of spoken and written English and Chinese\nComputer literate in Ms Word, Excel and Chinese Word Processing\nCandidates with less experience will be considered as Assistant\u00a0Property and Facility Officer.\n\n\nWe provide attractive remuneration package and fringe benefits for the right candidate.\u00a0 Interested parties please send detailed resume with current & expected salaries via \u201cApply Now\u201d or send in your application through the Careers section in our Corporate Website: http://www.hongyip.com/Careers.\n\nHong Yip is an Equal Opportunity Employer.\u00a0 Personal data collected will be used for recruitment purpose only.\u00a0", "employment_types": ["Full Time", "Permanent"], "selling_points": ["\u65e5\u73ed/\u4e2d\u73ed\u4e3b\u7ba1(8.5\u5c0f\u6642\u5b9a\u66f4)  shift in-charge", "\u4e94\u5e74\u6216\u4ee5\u4e0a\u5546\u5ec8\u7ba1\u7406\u7d93\u9a57\uff0c\u53ca\u76f8\u95dc\u4e3b\u7ba1\u7d93\u9a57", "\u6301PMSA\u7269\u696d\u7ba1\u7406\u4eba\u724c\u7167\u8005\u512a\u5148\u8003\u616e"], "locations": ["Central"], "categories": ["Property / Real Estate", "Property Management", "Others", "Others", "Security / Safety Control"], "post_time": "2022-01-14T07:52:52Z", "salary": {"currency": null, "max": null, "min": null, "period": "monthly", "term": null}, "salary_visible": false, "title_keywords": [], "responsibilities": ["management", "maintenance", "quality", "monitor", "maintain good relationship", "inquiries and complaints", "administrative duties", "cleaning"], "requirements": {"degrees": ["degree"], "majors": [], "languages": ["english", "chinese"], "language_level": ["good command"], "hard_skills": ["excel", "chinese word processing", "ms word"], "soft_skills": ["service-oriented", "work under pressure"], "languages_combined": [{"language": "english", "language_level": ["good command"]}, {"language": "chinese", "language_level": ["good command"]}]}, "experience_required": {"duration": ["at least 2 years"], "field": ["relevant working experience"]}}, {"job_id": "100003009052554", "location_code": "hk", "company": "Shun Tak Property Management Ltd", "job_title": "Assistant Officer - Administration & Quality Assurance (Ref: STPML1696)", "description": "\u8077\u8cac :\u8ca0\u8cac\u4e00\u822c\u5c4b\u82d1\u4fdd\u5b89\u5de5\u4f5c\u53ca\u7368\u7acb\u8655\u7406\u4e8b\u4ef6\n\u8cc7\u6b77 :\u6c92\u6709\u5b78\u6b77\u8981\u6c42; 1\u5e74\u7d93\u9a57; \u826f\u597d\u7cb5\u8a9e; \u4e00\u822c\u666e\u901a\u8a71; \u4e00\u822c\u82f1\u8a9e; \u61c2\u8b80\u5beb\u4e2d\u6587; \u7565\u61c2\u8b80\u5beb\u82f1\u6587; \u6301\u6709\u4fdd\u5b89\u57f9\u8a13\u8ab2\u7a0b\u8b49\u66f8(QAS); \u6301\u6709\u4fdd\u5b89\u4eba\u54e1\u8a31\u53ef\u8b49\n\u5f85\u9047 :\u6bcf\u65e5$650.00, \u4e0a\u53487\u6642\u81f3\u4e0b\u53487\u6642\u6216\u4e0b\u53487\u6642\u81f3\u4e0a\u53487\u6642, \u6bcf\u9031\u5de5\u4f5c1\u5929\u81f36\u5929,\u8f2a\u4f11, \u6bcf\u5929\u5de5\u4f5c 12 \u5c0f\u6642\n\u7533\u8acb\u9808\u77e5 :\u6c42\u8077\u8005\u53ef\u6309 APPLY NOW\u7533\u8acb\u6216\u81f4\u96fb26522362\u8207\u6607\u6377\u7ba1\u7406\u670d\u52d9\u6709\u9650\u516c\u53f8\u6881\u5148\u751f\u806f\u7d61\u3002", "employment_types": ["Full Time", "Permanent"], "selling_points": ["General office administration & clerical supports", "Assist in the service & internal operation audit", "Assist in ISO Quality Management System"], "locations": ["Central & Western Area"], "categories": ["Accounting", "Audit", "Admin & HR", "Clerical / Admin Staff", "Property / Real Estate", "Property Management"], "post_time": "2022-01-17T03:24:26Z", "salary": {"currency": null, "max": null, "min": null, "period": "monthly", "term": null}, "salary_visible": false, "title_keywords": ["assistant officer"], "responsibilities": [], "requirements": {"degrees": [], "majors": [], "languages": [], "language_level": [], "hard_skills": [], "soft_skills": [], "languages_combined": []}, "experience_required": {"duration": [], "field": []}}, {"job_id": "100003009049809", "location_code": "hk", "company": "Tai Sang Estate Agency Limited", "job_title": "Assistant Property Officer (Fresh Graduates are considered)", "description": "[Ref: PM/AM(M-BS)]\n\n\nThe Job\n\nTo solve technical problems independently and deal with urgent/emergency repairs concerning building services installations.\nTo prepare design, budgets, estimates, drawings, specifications and tender document for maintenance works for senior\u2019s approval.\nTo review the estates facilities, recommend the improvement program for estates/ properties. To monitor and supervise the improvement works to assure quality of works and upgrade the standard of living.\nTo administer the tendering and contract administration process which includes drafting letters to invite quotations, obtaining and evaluating quotations, preparing tender documents and issuing works orders for maintenance and improvement works.\nTo provide technical advice on materials, tools etc. to PM staff and co-ordinate repair\u00a0 works carried out by technicians or contractors. To supervise and monitor work progress site and certify work completion.\nTo inspect tenants\u2019 fixtures and various installations and recommend for repairs and improvement as necessary.\nTo comment the design drawings, specifications, manual; estimate running cost for building services installations for new development projects; conduct inspections and testings to identify defects during take over of new projects; and liaise / co-ordinate with Projects Division accordingly.\nTo liaise and coordinate with consultants, utility companies, government departments and other parties concerned on progress of works in estate areas.\nTo lead and supervise Senior Maintenance Officer to carry out special projects which may result in impact on all estates, such as recommending new products and carrying out study on new materials.\nTo act as a mentor for Senior Maintenance colleagues.\u00a0\nTo attend meetings and handle enquiries from tenants / owners / residents\u2019 association/ District Council/ contractors.\n\nThe Person\n\nHolders of Degree / Higher Diploma in Building Services, Electrical Engineering or related disciplines, and Certificate of Registration of Electrical Worker (Grade B) or equivalent.\nMember of professional bodies in HKIS/RICS/HKIE/RIBA or equivalent preferred.\n8 years\u2019 experience in building services maintenance or 10 years\u2019 experience for Higher Certificate in Building Services Engineering.\nIn-depth knowledge of relevant regulations and professional maintenance practices.\nCandidate will less experience will be considered for the post of Assistant Manager (Maintenance-Building Services).\n\nAttractive remuneration package will be offered to suitable candidates. To apply, please submit online application: https://careers.hkhs.com/ or send your application with full resume and reference quoted to Human Resources Manager by fax: 2882 4466.\n\nYou are welcome to visit our website www.hkhs.com to learn more about us.\nApplicants not invited for interview within 8 weeks may consider their applications unsuccessful.\n\nPersonal data provided by job applicants will be used strictly in accordance with the Housing Society\u2019s personal data policies which is available in our website and obtainable upon request. Please refer to the Policy Statement on Employment Related Data under Personal Data (Privacy) Ordinance in our website.", "employment_types": ["Full Time", "Permanent"], "selling_points": ["HKDSE or above", "Fresh Graduates is considered", "Public Holidays,  Medical & Dental"], "locations": ["Tsing Yi"], "categories": ["Property / Real Estate", "Property Management", "Others"], "post_time": "2022-01-14T09:15:27Z", "salary": {"currency": null, "max": null, "min": null, "period": "monthly", "term": null}, "salary_visible": false, "title_keywords": ["assistant property officer"], "responsibilities": ["liaise", "co-ordinate with", "technical advice", "quality", "tendering", "design", "drawings", "attend meetings", "tender document", "monitor", "handle enquiries", "cost", "coordinate with consultants", "design drawings", "contract administration", "review", "specifications", "solve technical problems", "budgets", "maintenance", "letters", "invite quotations", "preparing tender", "repair"], "requirements": {"degrees": ["higher certificate", "certificate", "diploma", "degree"], "majors": ["related disciplines", "building services", "electrical engineering", "engineering"], "languages": [], "language_level": [], "hard_skills": ["hkie", "maintenance", "hkis", "rics", "certificate of registration of electrical worker"], "soft_skills": [], "languages_combined": []}, "experience_required": {"duration": ["10 years", "8 years"], "field": ["building services", "engineering", "maintenance"]}}, {"job_id": "100003009034667", "location_code": "hk", "company": "S.H.K. Real Estate Management Company Limited", "job_title": "\u5ba2\u6236\u670d\u52d9\u54e1 (\u65e9\u73ed\uff1a11:00-20:00/\u4e2d\u73ed: 14:00-23:00/\u591c\u73ed\uff1a22:30 - 07:30)", "description": "\u8077\u8cac :\u4e00\u822c\u4fdd\u5b89\u5de5\u4f5c\n\u8cc7\u6b77 :\u4e2d\u4e00\u7a0b\u5ea6; 1\u5e74\u7d93\u9a57; \u4e00\u822c\u7cb5\u8a9e\u512a\u5148; \u4e00\u822c\u666e\u901a\u8a71; \u4e00\u822c\u82f1\u8a9e; \u61c2\u8b80\u5beb\u4e2d\u6587; \u7565\u61c2\u8b80\u5beb\u82f1\u6587; \u6301\u6709\u4fdd\u5b89\u57f9\u8a13\u8ab2\u7a0b\u8b49\u66f8(QAS); \u6301\u6709\u4fdd\u5b89\u4eba\u54e1\u8a31\u53ef\u8b49\n\u5f85\u9047 :\u6bcf\u65e5$450.00, \u4e0a\u53487\u6642\u81f3\u4e0b\u53483\u6642\u534a/\u4e0b\u53483\u6642\u81f3\u4e0b\u534811\u6642\u534a/\u4e0b\u534811\u6642\u81f3\u4e0a\u53487\u6642\u534a, \u6bcf\u9031\u5de5\u4f5c4\u5929\u81f36\u5929,\u8f2a\u4f11, \u6bcf\u5929\u5de5\u4f5c 8.5 \u5c0f\u6642\n\u7533\u8acb\u9808\u77e5 :\u6c42\u8077\u8005\u53ef\u6309 APPLY NOW\u7533\u8acb\u6216\u81f4\u96fb28993723\u8207\u6607\u6377\u7ba1\u7406\u670d\u52d9\u6709\u9650\u516c\u53f8\u90ed\u5148\u751f\u806f\u7d61\u3002", "employment_types": ["Full Time", "Permanent"], "selling_points": ["\u4e0d\u9700\u8f2a\u73ed\u5de5\u4f5c", "\u53ef\u4eab9\u5929\u5e74\u5047\uff0c\u91ab\u7642\u798f\u5229\u7b49", "\u6bcf\u5929\u5de5\u4f5c9\u5c0f\u6642"], "locations": ["Not Specified"], "categories": ["Property / Real Estate", "Property Management", "Others", "Others", "Security / Safety Control"], "post_time": "2022-01-16T21:50:10Z", "salary": {"currency": null, "max": null, "min": null, "period": "monthly", "term": null}, "salary_visible": false, "title_keywords": [], "responsibilities": [], "requirements": {"degrees": [], "majors": [], "languages": [], "language_level": [], "hard_skills": [], "soft_skills": [], "languages_combined": []}, "experience_required": {"duration": [], "field": []}}, {"job_id": "100003009056363", "location_code": "hk", "company": "\u6607\u6377\u7ba1\u7406\u670d\u52d9\u6709\u9650\u516c\u53f8", "job_title": "\u4e8c\u7d1a\u9ad8\u7d1a\u4fdd\u5b89\u54e1(\u65e5\u66f4)", "description": "\u4e3b\u8981\u8077\u52d9\u5305\u62ec\uff1a\n\n\u8ca0\u8cac\u5354\u52a9\u7269\u696d\u7ba1\u7406\u7d93\u7406\u53ca\u9ad8\u7d1a\u7ba1\u696d\u4e3b\u4efb\u57f7\u884c\u5546\u5834\u53ca\u5546\u5ec8\u7ba1\u7406\u4e8b\u5b9c\n\u7ba1\u7406\u53ca\u5e36\u9818\u7ba1\u696d\u670d\u52d9\u5718\u968a\uff0c\u4ee5\u78ba\u4fdd\u512a\u8cea\u5ba2\u6236\u670d\u52d9\n\n\u61c9\u5fb5\u8005\u9808\u5177\u5099\u4ee5\u4e0b\u689d\u4ef6\uff1a\n\n\u5177\u5099\u4e94\u5e74\u6216\u4ee5\u4e0a\u5546\u5834\u6216\u5546\u5ec8\u7ba1\u7406\u7d93\u9a57\uff0c\u53ca\u76f8\u95dc\u4e3b\u7ba1\u7d93\u9a57\n\u4e2d\u4e94\u7a0b\u5ea6\u6216\u4ee5\u4e0a\uff0c\u6301\u6709\u6709\u6548\u4fdd\u5b89\u4eba\u54e1\u8a31\u53ef\u8b49\uff0c\u5df2\u8003\u7372\u76f8\u95dc\u7269\u696d\u7ba1\u7406\u8b49\u66f8\u8005\u512a\u5148\n\u80fd\u4ee5\u82f1\u8a9e\u3001\u5ee3\u6771\u8a71\u53ca\u666e\u901a\u8a71\u6e9d\u901a\n\u9808\u7a7f\u8457\u516c\u53f8\u5236\u670d\n\u80fd\u56fa\u5b9a\u7576\u503c\u65e5\u6216\u4e2d\u73ed\u6642\u9593:\n\u65e9\u73ed\uff1a\u4e0a\u5348 7:45 - \u4e0b\u5348 4:15\n\u4e2d\u73ed\uff1a\u4e0b\u5348 3:15 - \u665a\u4e0a 11:45 (\u53ef\u4eab\u6709\u4e2d\u73ed\u7279\u5225\u6d25\u8cbc)\n\n\u5b8c\u5584\u54e1\u5de5\u798f\u5229\uff1a\n\n\u53ef\u4eab\u6709\u6bcf\u67086\u5929\u4f8b\u5047\n\u85aa\u512a\u53e6\u52a0\u82b1\u7d05\uff0c\u6bcf\u6708\u624b\u6a5f\u6d25\u8cbc\u53ca\u51fa\u52e4\u6d25\u8cbc\n\u91ab\u7642\u798f\u5229\u300112\u5929\u6709\u85aa\u5e74\u5047\u3001\u514d\u4f9b\u6b3e\u516c\u7a4d\u91d1\u53ca\u54e1\u5de5\u6e21\u5047\u5c4b\n\u4ee3\u7533\u8acb\u53ca\u652f\u4ed8\u500b\u4eba\u4fdd\u5b89\u724c\u7167\u8cbb\u7528\n\u5165\u8077\u57f9\u8a13\u8ab2\u7a0b\u53ca\u5c08\u696d\u5728\u8077\u57f9\u8a13\n\u5b8c\u5584\u7684\u5167\u90e8\u6649\u5347\u5236\u5ea6\uff0c\u63d0\u4f9b\u767c\u5c55\u53ca\u6649\u5347\u6a5f\u6703\n\n\u6709\u610f\u61c9\u5fb5\u8005\uff0c\u8acb\u5c07\u500b\u4eba\u5c65\u6b77 (\u8acb\u8a3b\u660e\u7533\u8acb\u8077\u4f4d\u3001\u806f\u7d61\u96fb\u8a71\u53ca\u8981\u6c42\u5f85\u9047)\u4ee5WhatsApp\u50b3\u9001\u81f39223 7989\u00a0\u6216\u00a0\u9ede\u64ca\u00a0\"Apply Now\"\u00a0\u7acb\u5373\u7533\u8acb\u3002\n\n\u6709\u95dc\u7f6e\u5730\u516c\u53f8\u8cc7\u6599\uff0c\u8acb\u700f\u89bd http://www.hkland.com\u3002\u00a0\n\n\u95a3\u4e0b\u6240\u63d0\u4f9b\u4e4b\u500b\u4eba\u8cc7\u6599\u53ea\u4f5c\u70ba\u6b64\u8077\u4f4d\u62db\u8058\u4e4b\u7528\uff0c\u65bc\u56db\u661f\u671f\u5167\u4e0d\u7372\u7d04\u898b\u8005\uff0c\u7576\u4f5c\u4e0d\u88ab\u53d6\u9304\uff0c\u5176\u6240\u905e\u4ea4\u4e4b\u500b\u4eba\u8cc7\u6599\u4ea6\u96a8\u5373\u92b7\u6bc1\u3002", "employment_types": ["Full Time"], "selling_points": ["\u8ca0\u8cac\u4e00\u822c\u5c4b\u82d1\u4fdd\u5b89\u5de5\u4f5c", "\u6301\u6709\u4fdd\u5b89\u57f9\u8a13\u8ab2\u7a0b\u8b49\u66f8(QAS)", "\u6301\u6709\u4fdd\u5b89\u4eba\u54e1\u8a31\u53ef\u8b49"], "locations": ["Tuen Mun Area"], "categories": ["Property / Real Estate", "Property Management", "Others", "Others", "Security / Safety Control"], "post_time": "2022-01-18T04:05:12Z", "salary": {"currency": null, "max": null, "min": null, "period": "monthly", "term": null}, "salary_visible": false, "title_keywords": [], "responsibilities": [], "requirements": {"degrees": [], "majors": [], "languages": [], "language_level": [], "hard_skills": [], "soft_skills": [], "languages_combined": []}, "experience_required": {"duration": [], "field": []}}, {"job_id": "100003009055513", "location_code": "hk", "company": "Hong Kong Housing Society", "job_title": "Temporary Concierge Officer (11-month Contract)", "description": "Key Responsibilities\n\nProvide general office administration and clerical supports;\nAssist in the service and internal operation audit for HK and Macau property portfolio;\nProvide support and participate in the electronic procurement system;\nAssist in ISO Quality Management System;\nAssist ad-hoc duties as assigned.\n\nRequirements\n\nDegree in Business Administration, Journalism or related disciplines are preferred;\n1-2 years' relevant experience in commercial or public sectors;\nGood command of both spoken and written English and Chinese;\nProficiency in computer knowledge.\n\nWe offer long-term career prospect and competitive remuneration package to the appointed candidate. Please apply in confidence with your detailed resume stating your current and expected salary to Group Human Resources Department\n\nby email to\u00a0recruit(at)shuntakgroup.com\n\nor mail to Penthouse 39/F, West Tower, Shun Tak Centre, 200 Connaught Road Central, Hong Kong\n\n(Please quote reference number and applied position)\n\nThe information supplied by the applicants will be used for recruitment purpose and in accordance with the Personal Data (Privacy) Policy of Shun Tak Group (a copy of which will be provided upon request). Personal data of the unsuccessful applicants will be destroyed in twelve months from the date of application. Only shortlisted candidates will be notified.\n\nwww.shuntakgroup.com", "employment_types": ["Temporary"], "selling_points": ["Provide clerical support for elderly services", "Arrange for concierge services", "Shift duty is required"], "locations": ["North Point"], "categories": ["Property / Real Estate", "Property Management"], "post_time": "2022-01-18T02:40:16Z", "salary": {"currency": null, "max": null, "min": null, "period": "monthly", "term": null}, "salary_visible": false, "title_keywords": ["concierge officer"], "responsibilities": ["provide support", "management", "office administration", "quality", "audit", "ad-hoc duties"], "requirements": {"degrees": ["degree"], "majors": ["journalism", "related disciplines", "business administration"], "languages": ["english", "chinese"], "language_level": ["good command"], "hard_skills": [], "soft_skills": [], "languages_combined": [{"language": "english", "language_level": ["good command"]}, {"language": "chinese", "language_level": ["good command"]}]}, "experience_required": {"duration": ["1-2 years"], "field": ["commercial", "relevant experience"]}}, {"job_id": "100003009047373", "location_code": "hk", "company": "Synergis Management Services Limited", "job_title": "Senior Property Officer / Assistant Property Manager (Kwai Tsing Area)", "description": "Duties\nThe appointee will be required but not limited to:\nlead a service team to handle a full range of duties related to facilities management, such as cleaning, security, catering, landscaping, etc.;\ndevelop and implement office administrative systems and procedures;\ndevelop and monitor annual operating expense budgets;\nhandle facilities services and administrative services requests;\nmonitor the performance of vendors, suppliers, facilities management service providers;\nprepare services contracts, proposals, reports, policies and procedures;\nsupervise and manage in-house and outsourced teams to provide administrative and facilities management support;\nprovide support services on space planning and minor maintenance and improvement projects; and\nwork on irregular hours including Saturdays, Sundays and Public Holidays if needed.\nRequirements\nApplicants should:\npossess a recognized Bachelor\u2019s degree with at least 5 years of relevant experience preferably in Facilities Management / Housing Management / Surveying or related disciplines;\nhave the ability to perform multi-tasks;\nbe able to work independently and have good leadership and coordination skills;\nbe self-motivated with positive work attitude and have good team spirit;\npossess good planning, problem-solving, interpersonal and organization skills;\nhave excellent computer literacy in MS applications including Chinese word processing;\nhave good command of both written and spoken in English and Chinese; and\npreferably be a member of\u00a0HKIS / RICS / HKIH / Registered Professional Housing Manager or other related professional qualification is preferred.\nSalary will be competitive and commensurate with qualifications and experience.\nTo apply, please submit your application letter, resume and a completed application form (available at http://www.twc.edu.hk/en/Administration_Units/hro/career/application_guideline) by mail to the Human Resources Office, Tung Wah College Cheung Kung Hai Memorial Building, 90A Shantung Street, Mongkok, Kowloon.\u00a0 Please quote the reference number of the post in the application letter and on the envelope.\u00a0 The College reserves the right to fill or not to fill the post.\u00a0 Applicants who are not contacted by the College 4 months after the application deadline may consider their applications unsuccessful.\nApplication Deadline: 27 January 2022 (Thursday)\nAll information and personal data collected will be used solely for recruitment related purposes. For more information about the College, please visit our website: http://www.twc.edu.hk.\nWE ARE AN EQUAL OPPORTUNITIES EMPLOYER", "employment_types": ["Full Time", "Permanent"], "selling_points": ["Diploma or above", "5 years' relevant experience", "Provisional PMP License (Tier 1) is preferred"], "locations": ["Kwai Tsing Area"], "categories": ["Property / Real Estate", "Property Consultancy", "Property Management", "Others"], "post_time": "2022-01-14T02:56:33Z", "salary": {"currency": null, "max": null, "min": null, "period": "monthly", "term": null}, "salary_visible": false, "title_keywords": ["senior property officer", "assistant property manager"], "responsibilities": ["budgets", "management", "provide support", "maintenance", "contracts", "policies", "systems", "procedures", "monitor", "teams", "develop", "planning", "reports", "landscaping", "monitor the performance", "cleaning", "catering"], "requirements": {"degrees": ["degree", "bachelor"], "majors": ["related disciplines", "surveying"], "languages": ["english", "chinese"], "language_level": ["excellent", "good command"], "hard_skills": ["chinese word processing", "ms applications", "hkis", "problem-solving", "rics", "facilities management"], "soft_skills": ["self-motivated", "work independently", "team spirit", "coordination skills", "multi-tasks", "positive work attitude", "problem-solving", "computer literacy", "organization skills", "leadership", "interpersonal"], "languages_combined": [{"language": "english", "language_level": ["good command"]}, {"language": "chinese", "language_level": ["excellent", "good command"]}]}, "experience_required": {"duration": ["at least 5 years"], "field": ["related", "management", "relevant experience"]}}, {"job_id": "100003009050124", "location_code": "hk", "company": "Hong Yip Service Company Limited", "job_title": "Assistant Property and Facility Officer (5-day work) - Tuen Mun", "description": "Assistant Property Officer\n(Reference No.: JEA/APO0062201)\n\nResponsibilities:\n\nMonitor the day-to-day operation for property management, technical services, security\nConstantly review and monitor the provision of tenant support service\nMonitor / coordinate repair & maintenance work, improvement projects, interior fitting out work / reinstatement work\nLiaise with internal and external parties to provide smooth operation in daily management\nResponsible for service delivery including premises handover / takeover execution\n\nRequirements:\n\nHKDSE or above, preferably with High Diploma in Property Management\nAt least 1 year experience in Property Management\nGood command of both written and spoken English and Chinese\nAs well as hands-on experience in various software applications including Words, Excel and Chinese word processing\nPossess good interpersonal and communication skill\nImmediately available is preferred\nFresh Graduates are also considered\n\nWe offer competitive salary and benefits package. Interested parties please send\u00a0full resume quoting our job reference number together with expected salary\u00a0by clicking 'Apply Now' or by fax to 2280-9780.\n\nAll information received will be kept in strictly confidential and used for recruitment purposes only.", "employment_types": ["Full Time", "Permanent"], "selling_points": ["Wholly owned subsidiary of Sun Hung Kai Properties", "1 year's working experience in property management", "Degree holder in any disciplines"], "locations": ["Not Specified"], "categories": ["Sales, CS & Business Devpt", "Customer Service - Supervisor / Officer", "Property / Real Estate", "Property Management", "Others", "Student / Fresh Graduate / No Experience"], "post_time": "2022-01-15T03:50:50Z", "salary": {"currency": null, "max": null, "min": null, "period": "monthly", "term": null}, "salary_visible": false, "title_keywords": ["officer", "assistant"], "responsibilities": ["service delivery", "management", "maintenance", "review", "monitor", "internal and external parties", "coordinate", "repair", "liaise with", "day-to-day operation"], "requirements": {"degrees": ["high diploma", "hkdse"], "majors": [], "languages": ["english", "chinese"], "language_level": ["good command"], "hard_skills": ["excel", "chinese word processing", "words"], "soft_skills": ["hands-on", "communication skill", "interpersonal"], "languages_combined": [{"language": "english", "language_level": ["good command"]}, {"language": "chinese", "language_level": ["good command"]}]}, "experience_required": {"duration": ["at least 1 year"], "field": ["management"]}}, {"job_id": "100003009049837", "location_code": "hk", "company": "Urban Group", "job_title": "Officer - Property", "description": "Requirements:\n\nAt least Level 2 in five subjects including English Language and Chinese Language in the Hong Kong Diploma of Secondary Education Examination (HKDSEE) or equivalent or a pass in 5 subjects including EnglishLanguage (Syllabus B) and Chinese Language in the Hong Kong Certificate of Education Examination or equivalent; and\nPossesses a recognized certificate in Property Management or above\nAt least 1 years working experience in the field of property management in Hong Kong;\nExperience in management of shopping centre is preferable; and\nShift duty is required\n\nWe offer attractive remuneration package & good career prospects to the right candidate. Please apply with full resume including date available, current and expected salary to the Personnel Manager, 37/F., Cosco Tower, Grand Millennium Plaza, 183 Queen\u2019s Road Central, HK or visit our website www.sunbaseprop.com for contact details.\n\n(All data collected will be treated in strict confidence and used for recruitment purpose within the Sunbase Group Companies.)", "employment_types": ["Full Time", "Permanent"], "selling_points": [], "locations": ["Not Specified"], "categories": ["Sales, CS & Business Devpt", "Customer Service - Supervisor / Officer", "Building & Construction", "Building / Construction / QS", "Property / Real Estate", "Property Management"], "post_time": "2022-01-14T09:18:41Z", "salary": {"currency": null, "max": null, "min": null, "period": "monthly", "term": null}, "salary_visible": false, "title_keywords": ["officer"], "responsibilities": ["management"], "requirements": {"degrees": ["certificate", "diploma", "secondary education"], "majors": [], "languages": ["english", "chinese"], "language_level": [], "hard_skills": [], "soft_skills": [], "languages_combined": [{"language": "english", "language_level": []}, {"language": "chinese", "language_level": []}]}, "experience_required": {"duration": ["at least 1 years"], "field": ["management"]}}, {"job_id": "100003009053243", "location_code": "hk", "company": "Jones Lang LaSalle Management Services Ltd", "job_title": "\u4e2d\u74b0\u5546\u5ec8 - \u56fa\u5b9a\u65e9\u6216\u591c\u66f4\u7269\u696d\u52a9\u7406 12 \u5c0f\u6642 (\u5168\u8077)", "description": "\u5354\u52a9\u57f7\u884c\u9ad8\u7d1a\u5546\u696d\u5927\u5ec8\u4e4b\u65e5\u5e38\u7ba1\u7406\u53ca\u4e8b\u52d9\n\u6bcf\u5929\u5de5\u4f5c9\u5c0f\u6642\n\u4e0d\u9700\u8f2a\u73ed\u5de5\u4f5c\n\u4e2d\u4e94\u7a0b\u5ea6\u6216\u5177\u8cc7\u6b77\u67b6\u69cb\u540c\u7b49\u8cc7\u6b77\n\u9808\u6301\u6709\u6709\u6548\u300c\u4fdd\u5b89\u4eba\u54e1\u8a31\u53ef\u8b49\u300d\u53ca\u8a8d\u53efQAS\u8a3c\u66f8\n\u6b61\u8fce\u7121\u76f8\u95dc\u7d93\u9a57\u8005\u61c9\u5fb5\n\u85aa\u91d1\u53ef\u9ad8\u9054\u6bcf\u6708$17,000\n\n\u4ee5\u4e0a\u8077\u4f4d\u53ef\u4eab\u6709\u512a\u539a\u54e1\u5de5\u798f\u5229\uff0c\u5305\u62ec\u6709\u85aa\u5e74\u50479\u5929\u3001\u52e4\u5de5\u734e\u3001\u5e74\u7d42\u734e\u91d1\u3001\u91ab\u7642\u798f\u5229\u3001\u5b8c\u5584\u57f9\u8a13\u53ca\u6649\u5347\u6a5f\u6703\u3002\n\n\u6709\u610f\u8005\uff0c\u8acb\u81f4\u96fb\u4ee5\u4e0b\u806f\u7d61\u4eba\u7533\u8acb\uff1a\n\n\u8354\u679d\u89d2\u5340\uff1a\n\n\u96fb\u8a71\uff1a2307 6909\u00a0\u7f85\u5c0f\u59d0\n\n\u5c16\u6c99\u5480\uff1a\n\n\u96fb\u8a71\uff1a2312 2110 \u5468\u5c0f\u59d0\n\n\u00a0\n\u9664\u4e0a\u8ff0\u8077\u4f4d\u5916\uff0c\u5c1a\u6709\u5176\u4ed6\u7a7a\u7f3a\u3002\u8acb\u900f\u904e\u4ee5\u4e0b\u65b9\u6cd5\u5c07\u5c65\u6b77\u4ea4\u5230S.H.K.\u7269\u696d\u7ba1\u7406\u6709\u9650\u516c\u53f8\u4e4b\u4eba\u529b\u8cc7\u6e90\u53ca\u884c\u653f\u90e8\u3002\n\n\u90f5\u5bc4\uff1a\u89c0\u5858\u5de7\u660e\u885795\u865f\u4e16\u9054\u4e2d\u5fc316\u6a13\u3000\u50b3\u771f\uff1a2827 2125\n\n\nS.H.K. \u7269\u696d\u7ba1\u7406\u6709\u9650\u516c\u53f8\u4e43\u5e73\u7b49\u6a5f\u6703\u50f1\u4e3b\uff0c\u800c\u6240\u6709\u6536\u96c6\u8cc7\u6599\u7d55\u5c0d\u4fdd\u5bc6\u53ca\u53ea\u7528\u4f5c\u96c6\u5718\u5167\u90e8\u62db\u8058\u4e4b\u7528\u9014\u3002", "employment_types": ["Full Time", "Permanent"], "selling_points": ["F.5 or above", "Min. 1 year's experience", "Luxurious Residential Building"], "locations": ["Central & Western Area"], "categories": ["Property / Real Estate", "Property Management", "Others", "Building & Construction", "Others"], "post_time": "2022-01-17T08:07:19Z", "salary": {"currency": null, "max": null, "min": null, "period": "monthly", "term": null}, "salary_visible": false, "title_keywords": [], "responsibilities": [], "requirements": {"degrees": [], "majors": [], "languages": [], "language_level": [], "hard_skills": [], "soft_skills": [], "languages_combined": []}, "experience_required": {"duration": [], "field": []}}, {"job_id": "100003009052514", "location_code": "hk", "company": "Hong Kong Adventist Hospital - Stubbs Road", "job_title": "\u65e5\u66f4\u4fdd\u5b89\u52a9\u7406\ufe5d\u5168\u8077\ufe5e\u8a2d\u65bd\u7ba1\u7406\u90e8 (\u6708\u85aa\u7531HK$17,116\u81f3 HK$22,038)", "description": "\u8077\u8cac :\u8ca0\u8cac\u4e00\u822c\u5c4b\u82d1\u4fdd\u5b89\u5de5\u4f5c\uff0c\u8655\u7406\u4e00\u822c\u7a81\u767c\u4e8b\u4ef6\u3002\n\u8cc7\u6b77 :\u5c0f\u516d\u7a0b\u5ea6; \u4e00\u822c\u7cb5\u8a9e; \u7565\u61c2\u8b80\u5beb\u4e2d\u6587; \u6301\u6709\u4fdd\u5b89\u57f9\u8a13\u8ab2\u7a0b\u8b49\u66f8(QAS); \u6301\u6709\u4fdd\u5b89\u4eba\u54e1\u8a31\u53ef\u8b49; \u5177\u826f\u597d\u6e9d\u901a\u6280\u5de7\u53ca\u5ba2\u6236\u670d\u52d9\u614b\u5ea6\n\u5f85\u9047 :\u6bcf\u6708$15,450, \u6709\u6bcf\u6708\u52e4\u5de5\u734e\u91d1$1000 \u53ca\u6649\u5347\u6a5f\u6703 (\u8996\u4e4e\u5de5\u4f5c\u8868\u73fe\u800c\u5b9a), \u4e0a\u53486\u664245\u5206\u81f3\u4e0b\u53486\u664245\u5206, \u6bcf\u9031\u5de5\u4f5c6\u5929,\u8f2a\u4f11, \u6bcf\u5929\u5de5\u4f5c 12 \u5c0f\u6642\n\u7533\u8acb\u9808\u77e5 :\u6c42\u8077\u8005\u53ef\u6309 APPLY NOW\u7533\u8acb\u6216\u81f4\u96fb24575061\u8207\u6607\u6377\u7ba1\u7406\u670d\u52d9\u6709\u9650\u516c\u53f8\u5f35\u5c0f\u59d0\u806f\u7d61\u3002", "employment_types": ["Full Time"], "selling_points": [], "locations": ["Wan Chai Area"], "categories": ["Medical Services", "Others", "Property / Real Estate", "Property Management", "Others", "Security / Safety Control"], "post_time": "2022-01-17T03:23:44Z", "salary": {"currency": null, "max": null, "min": null, "period": "monthly", "term": null}, "salary_visible": false, "title_keywords": [], "responsibilities": [], "requirements": {"degrees": [], "majors": [], "languages": [], "language_level": [], "hard_skills": [], "soft_skills": [], "languages_combined": []}, "experience_required": {"duration": [], "field": []}}, {"job_id": "100003009049851", "location_code": "hk", "company": "Urban Group", "job_title": "Assistant Property Officer", "description": "[Ref: TTH-TCO]\n\n\nThe Job\n\nProvide clerical support to the daily operation of the new projects for elderly services.\nProvide quality services and enhance relationship with members by handling telephone enquiries, referring emergencies to appropriate staff, drafting notices / replies to tenants promptly / taking meeting minutes and organising activities, festive functions, interest classes , facilities booking etc.\nProvide customer services to members and arrange for concierge services.\nAssist in logistics by providing counter servicing, filing, typing, maintaining & updating filing system and to prepare correspondence, reports and etc.\nHandle tenants and passers-by\u2019s enquiries by explaining relevant policies and procedures, referring to factual information.\nHandle members\u2019 complaints or requests.\nHandle fees, petty cash, repair charges and miscellaneous charges accurately.\nPrepare correspondence and reports in a correct and standard documents or new formats as prescribed by the superior.\nCoordinate and liaise various parties to complete the activities smoothly.\nShift duty is required.\n\nThe Person\n\nDiploma/Degree Holder with at least 1 year customer services experience OR F.5 or 5 subjects obtained Level 2 or above in HKDSEE and above with extensive customer services experience preferred.\nAttentive to details, systematic and willing to follow through tasks independently.\nService oriented, effective typing, communication and interpersonal skills.\nMature, service-oriented, good telephone manner and a team player.\nHands-on experience in using MS Word, Excel and Chinese Word processing.\n\nAttractive remuneration package will be offered to suitable candidates. To apply, please submit online application: https://careers.hkhs.com/ or send your application with full resume and reference quoted to Human Resources Manager by fax: 2882 4466.\n\nYou are welcome to visit our website www.hkhs.com to learn more about us.\nApplicants not invited for interview within 8 weeks may consider their applications unsuccessful.\n\nPersonal data provided by job applicants will be used strictly in accordance with the Housing Society\u2019s personal data policies which is available in our website and obtainable upon request. Please refer to the Policy Statement on Employment Related Data under Personal Data (Privacy) Ordinance in our website.", "employment_types": ["Full Time", "Permanent"], "selling_points": [], "locations": ["Not Specified"], "categories": ["Property / Real Estate", "Property Management", "Others"], "post_time": "2022-01-14T09:19:05Z", "salary": {"currency": null, "max": null, "min": null, "period": "monthly", "term": null}, "salary_visible": false, "title_keywords": ["assistant property officer"], "responsibilities": ["provide clerical support", "liaise", "maintaining", "policies", "quality", "daily operation", "procedures", "customer services", "coordinate", "repair", "logistics", "booking", "reports"], "requirements": {"degrees": ["diploma", "degree holder"], "majors": [], "languages": ["chinese"], "language_level": [], "hard_skills": ["excel", "chinese word processing", "typing", "ms word"], "soft_skills": ["independently", "attentive to details", "telephone manner", "service-oriented", "systematic", "mature", "hands-on", "communication and interpersonal skills", "team player", "extensive"], "languages_combined": [{"language": "chinese", "language_level": []}]}, "experience_required": {"duration": ["at least 1 year"], "field": ["customer services"]}}, {"job_id": "100003009053255", "location_code": "hk", "company": "Jones Lang LaSalle Management Services Ltd", "job_title": "\u4e2d\u74b0\u5546\u5ec8 - \u56fa\u5b9a\u591c\u66f4\u7269\u696d\u52a9\u7406 12 \u5c0f\u6642 (\u5168\u8077)", "description": "Responsibilities\n\nManage and oversee the operations of property management services;\nSupervise a team to provide quality property management services to clients;\nEnsure compliance with relevant ordinance and regulations;\nLiaise with clients, supplier and internal parties;\nHandle ad hoc assignments as required\n\nRequirements\n\nDegree holder or above in property management or related disciplines;\nMember of CIH / HKIH is preferred or other recognized professional bodies;\nHolder of provisional PMP License (Tier 1) is preferred;\n5 years or above relevant experience in property management of which\u00a02 years should be at managerial level;\nStrong leadership, communication, and interpersonal skills;\nProficient in both written and spoken English and Chinese\n\nCandidates\u00a0with\u00a0less\u00a0experience will be considered\u00a0for the post of\u00a0Senior Property Officer.", "employment_types": ["Full Time", "Permanent"], "selling_points": ["F.5 or above", "Min. 1 year's experience", "Luxurious Residential Building"], "locations": ["Central & Western Area"], "categories": ["Property / Real Estate", "Property Management", "Others", "Building & Construction", "Others"], "post_time": "2022-01-17T08:06:44Z", "salary": {"currency": null, "max": null, "min": null, "period": "monthly", "term": null}, "salary_visible": false, "title_keywords": [], "responsibilities": ["regulations", "liaise with clients", "management", "operations", "quality", "ensure compliance", "ad hoc assignments", "internal parties"], "requirements": {"degrees": ["degree holder"], "majors": ["related disciplines"], "languages": ["english", "chinese"], "language_level": ["proficient"], "hard_skills": ["pmp"], "soft_skills": ["communication", "leadership", "interpersonal skills"], "languages_combined": [{"language": "english", "language_level": ["proficient"]}, {"language": "chinese", "language_level": ["proficient"]}]}, "experience_required": {"duration": ["5 years", "2 years"], "field": ["managerial", "management", "relevant experience"]}}, {"job_id": "100003009053222", "location_code": "hk", "company": "Jones Lang LaSalle Management Services Ltd", "job_title": "\u4e2d\u74b0\u5546\u5ec8 - \u56fa\u5b9a\u65e9\u66f4\u7269\u696d\u52a9\u7406 12 \u5c0f\u6642 (\u5168\u8077)", "description": "Job Responsibilities:\n\nAssist the area manager in providing high-quality property management services\nOrganize meetings and carry out administrative duties for Incorporated Owners\nEstablish and maintain good relationship with tenants\nHandle\u00a0emergency incidents, customer inquiries and complaints\nMonitor the standards of maintenance, security and cleaning services of properties\n\nJob Requirements:\n\nDegree holder in any disciplines\n1 year's working experience in property management or customer service preferred\nExcellent command of spoken and written English and Chinese\nStrong interpersonal and communication skills\nMature, independent and self-motivated\nProficient in Microsoft applications and Chinese Word Processing\n\nWe provide attractive remuneration package and fringe benefits for the right candidate.\u00a0 Interested parties please send detailed resume with current & expected salaries via \u201cApply Now\u201d or send in your application through the Careers section in our Corporate Website: http://www.hongyip.com/Careers.\n\nHong Yip is an Equal Opportunity Employer.\u00a0 Personal data collected will be used for recruitment purpose only.\u00a0\n", "employment_types": ["Full Time", "Permanent"], "selling_points": ["F.5 or above", "Min. 1 year's experience", "Luxurious Residential Building"], "locations": ["Central & Western Area"], "categories": ["Property / Real Estate", "Property Management", "Others", "Building & Construction", "Others"], "post_time": "2022-01-17T08:08:55Z", "salary": {"currency": null, "max": null, "min": null, "period": "monthly", "term": null}, "salary_visible": false, "title_keywords": [], "responsibilities": ["management", "maintenance", "quality", "monitor", "maintain good relationship", "inquiries and complaints", "administrative duties", "cleaning"], "requirements": {"degrees": ["degree holder"], "majors": ["any disciplines"], "languages": ["english", "chinese"], "language_level": ["excellent", "proficient"], "hard_skills": ["chinese word processing", "microsoft applications"], "soft_skills": ["communication skills", "self-motivated", "independent", "mature", "customer service", "interpersonal"], "languages_combined": [{"language": "english", "language_level": ["excellent"]}, {"language": "chinese", "language_level": ["excellent", "proficient"]}]}, "experience_required": {"duration": ["1 year"], "field": ["management", "customer service"]}}, {"job_id": "100003009055494", "location_code": "hk", "company": "Hong Kong Housing Society", "job_title": "Sales & Marketing Manager - Property Development", "description": "Responsibilities:\n\nHandle day-to-day property operations\nSupervise the cleaning, repair and maintenance service provided to residents / owners\nSupervises junior operational staff\nBuild up and maintain good relationship with clients\nPreparation of the administration,\u00a0financial reports and etc\nHandle enquiries and complaints from the owners / tenants\n\nRequirements:\n\nDegree / Higher Diploma holder in Property Management / Hotel Management is preferable\n2-3 years\u2019 work experience in property management\nIndependent, strong supervisory and leadership skills\nKnowledge of BMO, DMC and related ordinances\nGood command of both written and spoken English and Chinese\nQualifications Framework-recognized qualifications in property management is preferable\nHas technical knowledge is an advantage\n5-day work week (subject to the site's operation guideline)\nCandidates with less experience will be considered as\u00a0Assistant Property Asset Officer\n\nInterested parties please\u00a0send\u00a0application letter with detailed resume, current and expected salary\u00a0to\u00a0Group Manager \u2013 Human Capital & Training\u00a0through one of the following means:\n\nMail:\u00a016/F., Chevalier Commercial Centre, 8 Wang Hoi Road, Kowloon Bay,\u00a0Kowloon,\u00a0Hong Kong\n\nEmail: Click 'Apply Now'\n\nAll personal data collected will be used for employment-related purposes only.", "employment_types": ["Permanent"], "selling_points": ["Prepare the overall sales and marketing strategy", "Assist in handling tendering process", "Willing to work on irregular hours"], "locations": ["Quarry Bay"], "categories": ["Property / Real Estate", "Property Management"], "post_time": "2022-01-18T02:39:21Z", "salary": {"currency": null, "max": null, "min": null, "period": "monthly", "term": null}, "salary_visible": false, "title_keywords": ["sales & marketing manager"], "responsibilities": ["financial reports", "maintenance", "operations", "handle enquiries and complaints", "maintain good relationship", "repair", "cleaning", "administration"], "requirements": {"degrees": ["degree", "higher diploma holder"], "majors": ["hotel"], "languages": ["english", "chinese"], "language_level": ["good command"], "hard_skills": [], "soft_skills": ["leadership skills", "independent"], "languages_combined": [{"language": "english", "language_level": ["good command"]}, {"language": "chinese", "language_level": ["good command"]}]}, "experience_required": {"duration": ["2-3 years"], "field": ["management"]}}, {"job_id": "100003009051472", "location_code": "hk", "company": "Casey Company Limited", "job_title": "Assistant to General Manager of Properties Department", "description": "\u8077\u8cac:\n\n\u5de1\u8996\u7269\u696d\n\u78ba\u4fdd\u6240\u6709\u8a2d\u65bd\u904b\u4f5c\u6b63\u5e38\n\u8655\u7406\u9867\u5ba2\u67e5\u8a62\n\u5354\u52a9\u4e0a\u53f8\u8ddf\u9032\u6295\u8a34\u53ca\u8655\u7406\u7dca\u6025\u4e8b\u6545\n\u4e3b\u52d5\u8207\u696d\u6236\u63a5\u89f8\n\u7dad\u6301\u826f\u597d\u95dc\u4fc2\n\n\u8981\u6c42:\n\n\u4e2d\u4e94\u6216\u4ee5\u4e0a\u7a0b\u5ea6\n\u4e00\u5e74\u6216\u4ee5\u4e0a\u7269\u696d\u7ba1\u7406\u7d93\u9a57\u512a\u5148\n\u6210\u719f, \u6709\u826f\u597d\u7d44\u7e54\u80fd\u529b, \u6709\u8cac\u4efb\n\u57fa\u672c\u82f1\u8a9e\u53ca\u570b\u8a9e\u3001\u826f\u597d\u7cb5\u8a9e\u7684\u8a00\u8a9e\u80fd\u529b\n\u6a02\u89c0\u6027\u683c \u53ca \u5177\u7368\u7acb\u80fd\u529b\n\u6709\u4e00\u822c\u96fb\u8166\u77e5\u8b58\u512a\u5148\n\u5de5\u4f5c\u6642\u9593: \u65e9\u73ed(0700-1900) \u591c\u73ed (1900-0700)\n\n\u6b61\u8fce\u76f4\u63a5\u81f4\u96fb 2117 8010\u67e5\u8a62\u3002\n\nWe offer attractive remuneration package and good career prospect for the right applicant.\n\nPlease apply by clicking\u00a0\"Apply Now\", or submit full resume and expected salary to the\u00a0HR Department, Room 1402, 14/F, Dorset House, Taikoo Place, 979 King's Road, Quarry Bay, HK\u00a0or\u00a0fax to 2968-4177.\u00a0\n\n(Please quote the reference number on the subject of email)\n\nApplicants not invited for interviews within 6 weeks may consider their applications unsuccessful. Information provided will be treated with strict confidential and be used for the purpose of employment only.", "employment_types": ["Full Time", "Permanent"], "selling_points": [], "locations": ["Aberdeen"], "categories": ["Property / Real Estate", "Property Management"], "post_time": "2022-01-16T03:39:06Z", "salary": {"currency": null, "max": null, "min": null, "period": "monthly", "term": null}, "salary_visible": false, "title_keywords": ["general manager", "assistant"], "responsibilities": [], "requirements": {"degrees": [], "majors": [], "languages": [], "language_level": [], "hard_skills": [], "soft_skills": [], "languages_combined": []}, "experience_required": {"duration": [], "field": []}}, {"job_id": "100003009050196", "location_code": "hk", "company": "New World Facilities Management Company Limited", "job_title": "Assistant Manager, Venue Services", "description": "\u8ca0\u8cac\u91ab\u9662\u65e5\u5e38\u4fdd\u5b89\u5de5\u4f5c\uff0c \u5305\u62ec\u5de1\u908f\u3001 \u76e3\u5bdf\u4fdd\u5b89\u7cfb\u7d71\u3001\u8a2a\u5ba2\u767b\u8a18\u7b49\n\u6307\u63ee\u4ea4\u901a\uff0c\u70ba\u5ba2\u4eba\u53ec\u559a\u7684\u58eb\u3001\u5354\u52a9\u8f2a\u6905\u4e0a\u843d\u3001\u505c\u8eca\u57f8\u7ba1\u7406\u7b49\n\u4e2d\u5b78\u7a0b\u5ea6\n\u9700\u6301\u6709\u6548\u300c\u4fdd\u5b89\u4eba\u54e1\u8a31\u53ef\u8b49\u300d\u53ca\u5b8c\u6210\u300cQAS\u4fdd\u5b89\u8b49\u66f8\u8ab2\u7a0b\u300d\n\u6301\u6709\u6548I\u53caII\u99d5\u99db\u57f7\u7167\u512a\u5148\u8003\u616e\n\u9700\u6709\u79ae\uff0c\u5177\u8cac\u4efb\u611f\u53ca\u826f\u597d\u6e9d\u901a\u6280\u5de7\n\u80fd\u64cd\u6d41\u5229\u5ee3\u6771\u8a71\u3001\u7565\u61c2\u82f1\u8a9e\uff0c\u4e26\u5177\u4e2d\u6587\u66f8\u5beb\u80fd\u529b\n\u9700\u5177\u6709\u4e00\u5e74\u6216\u4ee5\u4e0a\u4fdd\u5b89\u5de5\u4f5c\u7d93\u9a57\n\u9700\u8f2a\u73ed\u5de5\u4f5c\u3001\u6bcf\u5929\u5de5\u4f5c12\u5c0f\u6642(\u5305\u62ec1\u5c0f\u6642\u7528\u81b3)\u53ca\u6bcf\u9031\u5de5\u4f5c6\u65e5\n\u798f\u5229\u5305\u62ec\u81b3\u98df\u6d25\u8cbc\u3001\u914c\u60c5\u6027\u5e74\u7d42\u82b1\u7d05\u3001\u91ab\u7642\u53ca\u7259\u79d1\u798f\u5229\u3001\u5341\u516b\u5929\u5e74\u5047\u3001\u5341\u4e03\u5929\u516c\u773e\u5047\u671f\n\n\u6709\u610f\u61c9\u5fb5\u8005\uff0c\u8acb\u5c07\u500b\u4eba\u5c65\u6b77\u53ca\u8981\u6c42\u85aa\u916c\u9023\u540c\u7533\u8acb\u8077\u4f4d\u540d\u7a31\uff0c\u90f5\u5bc4\u3001\u96fb\u90f5\u6216\u50b3\u771f\u81f3\u672c\u9662\u4eba\u529b\u8cc7\u6e90\u90e8\u3002\n\n\u90f5\u5bc4\uff1a\u00a0 \u00a0 \u00a0 \u00a0 \u9999\u6e2f\u6e2f\u5b89\u91ab\u9662 \u53f8\u5f92\u62d4\u905340\u865f \u4eba\u529b\u8cc7\u6e90\u90e8\u6536\n\u96fb\u90f5\uff1a\u00a0 \u00a0 \u00a0 \u00a0 Apply Now\n\u50b3\u771f\uff1a\u00a0\u00a0\u00a0\u00a0\u00a0\u00a0\u00a0 3651 8865\n\n\u5982\u5728\u63d0\u4ea4\u7533\u8acb\u5f8c\u7684\u56db\u661f\u671f\u5167\u672a\u6709\u6536\u5230\u9762\u8a66\u901a\u77e5\uff0c\u5373\u8868\u793a\u9019\u9805\u7533\u8acb\u4e0d\u7372\u63a5\u7d0d\u3002\u7533\u8acb\u4eba\u7684\u8cc7\u6599\u53ea\u6703\u7528\u65bc\u6709\u95dc\u672c\u9662\u7684\u4eba\u4e8b\u62db\u8058\u4e8b\u5b9c\u53ca\u5c07\u6703\u5728\u516d\u500b\u6708\u5167\u92b7\u6bc0\u3002", "employment_types": ["Full Time", "Permanent"], "selling_points": [], "locations": ["Chai Wan"], "categories": ["Property / Real Estate", "Property Management"], "post_time": "2022-01-14T09:55:35Z", "salary": {"currency": null, "max": null, "min": null, "period": "monthly", "term": null}, "salary_visible": false, "title_keywords": ["assistant manager,"], "responsibilities": [], "requirements": {"degrees": [], "majors": [], "languages": [], "language_level": [], "hard_skills": [], "soft_skills": [], "languages_combined": []}, "experience_required": {"duration": [], "field": []}}, {"job_id": "100003009054942", "location_code": "hk", "company": "Sun Hung Kai Properties Ltd", "job_title": "MANAGER / ASSISTANT MANAGER \u2013 OFFICE LEASING", "description": "[Ref: S&MM-PD]\n\nThe Job\n\nMonitor the team to conduct market research on the demand and conditions of the target customers.\nFacilitate to prepare the overall sales and marketing strategy for housing projects.\nPrepare sales and marketing literatures and legal documents in accordance with the requirements of the Residential Properties (First-hand Sales) Ordinance and relevant regulations.\nLiaise with consultants for setting up of show flat, call centre and other sales matters as well as supervise the sales flow and logistics.\nAssist in formulating the flats handover standard and determine the handover procedure, flow and logistics.\nCoordinate with consultants for setting up of handover office, development of defect logging system and supervise the handover team to ensure a smooth operation of handover of flats.\nAssist in handling tendering process of recruiting appropriate business partners, staff recruitment and training, cash flow forecasts and budgets preparation.\n\nThe Person\n\nDegree holder with minimum 5-years\u2019 relevant experience OR Diploma / Certificate holder with minimum 7-years\u2019 relevant experience.\nStrong leadership, dedicated to work, good communication, interpersonal and organization skills.\nExcellent spoken and written English and Chinese (Cantonese and Mandarin).\nProficiency in MS Windows application, including Excel, Word, PowerPoint and Chinese Word processing.\nWilling to work on irregular hours and weekend / public holiday.\nCandidates with less experience will be considered for the post of Assistant Manager (Sales & Marketing).\n\nAttractive remuneration package will be offered to suitable candidates. To apply, please submit online application: https://careers.hkhs.com/ or send your application with full resume and reference quoted to Human Resources Manager by fax: 2882 4466.\n\nYou are welcome to visit our website www.hkhs.com to learn more about us.\nApplicants not invited for interview within 8 weeks may consider their applications unsuccessful.\n\nPersonal data provided by job applicants will be used strictly in accordance with the Housing Society\u2019s personal data policies which is available in our website and obtainable upon request. Please refer to the Policy Statement on Employment Related Data under Personal Data (Privacy) Ordinance in our website.", "employment_types": ["Full Time", "Permanent"], "selling_points": ["Bachelor degree with exp in office leasing", "Office leasing, tenancy administration, marketing", "Co-ordination with property management"], "locations": ["Wan Chai"], "categories": ["Marketing / Public Relations", "Marketing - Marketing Communication", "Property / Real Estate", "Property Management", "Others"], "post_time": "2022-01-17T14:33:35Z", "salary": {"currency": null, "max": null, "min": null, "period": null, "term": null}, "salary_visible": false, "title_keywords": ["assistant manager", "manager"], "responsibilities": ["regulations", "budgets", "coordinate with consultants", "conduct market research", "prepare sales", "monitor", "tendering", "cash flow", "logistics", "recruitment", "liaise with consultants"], "requirements": {"degrees": ["certificate", "diploma", "degree holder"], "majors": [], "languages": ["cantonese", "english", "chinese", "mandarin"], "language_level": ["excellent", "proficiency"], "hard_skills": ["excel", "chinese word processing", "ms windows", "word", "powerpoint"], "soft_skills": ["communication", "leadership", "interpersonal", "organization skills"], "languages_combined": [{"language": "cantonese", "language_level": ["excellent"]}, {"language": "english", "language_level": ["excellent"]}, {"language": "chinese", "language_level": ["excellent", "proficiency"]}, {"language": "mandarin", "language_level": ["excellent"]}]}, "experience_required": {"duration": [], "field": ["marketing", "relevant experience"]}}, {"job_id": "100003009047594", "location_code": "hk", "company": "Goodwell Property Management Ltd", "job_title": "Property Assistant (Ref: PA/J)", "description": "Our Properties Department is responsible for :\n\nRental of our two commercial buildings;\nDirect management of our own buildings, with our sister \u201cBuilding Services\u201d department maintaining all essential building services.\n\nThe successful candidate will assist the department head to fulfill the department\u2019s responsibility, with the help of two building officers.\n\nThis position entails the regular performance of (but NOT limited to) the following :\n\nLiaise with agents for potential tenants;\nNegotiate with potential tenants for new rentals and existing tenants for renewals;\nSupervise our own building-management staff;\nClosely monitor new tenants\u2019 fitting-out process to ensure strict adherence to renovation restrictions.\n\nThis position will have the prospect of promotion to Assistant Manager on proven performance of his/her duties.\n\nMinimum requirements:\n\nHolder of an associate degree or equivalent.\u00a0 Holder of the Hong Kong Institute of Real Estate Administrators accreditation\u00a0will have an advantage;\n3 years\u2019 relevant experience in rental of commercial space & building management;\nProficiency in both English & Chinese (Cantonese and Putonghua);\nGood computer skills for MS office, especially with Excel, and Chinese input.\n\nWe are looking for an individual who has substantial hands-on experience, pays meticulous attention to details and accuracy, is not afraid to ask questions, is proactive by temperament and is able to see beyond his/her own department and understand the priorities of the company as a whole. \u00a0In addition, if your past or current work can show that you have good communication, interpersonal & supervisory skills, you will have an advantage.\n\nInterested parties should email full resume, including HKCEE/DSE and HKAL results or equivalent, current and expected annual salary and availability by clicking \"Apply Now\".\n\nAll personal data will be treated in strict confidence and used for this recruitment only.", "employment_types": ["Full Time", "Permanent"], "selling_points": ["1-2 years working experience", "Hard-working with pleasant personality", "Matriculated or above"], "locations": ["Not Specified"], "categories": ["Property / Real Estate", "Property Consultancy", "Property Management", "Others"], "post_time": "2022-01-15T03:49:44Z", "salary": {"currency": null, "max": null, "min": null, "period": null, "term": null}, "salary_visible": false, "title_keywords": ["property assistant"], "responsibilities": ["management", "maintaining", "renovation", "monitor", "communication", "building management", "liaise with"], "requirements": {"degrees": ["associate degree"], "majors": [], "languages": ["cantonese", "putonghua", "english", "chinese"], "language_level": ["proficiency", "good"], "hard_skills": ["chinese input", "excel", "computer skills", "ms office"], "soft_skills": ["meticulous", "responsible", "communication", "hands-on", "attention to details", "proactive", "interpersonal"], "languages_combined": [{"language": "cantonese", "language_level": []}, {"language": "putonghua", "language_level": []}, {"language": "english", "language_level": ["proficiency"]}, {"language": "chinese", "language_level": ["proficiency", "good"]}]}, "experience_required": {"duration": ["3 years"], "field": ["commercial", "management", "relevant experience"]}}, {"job_id": "100003009056403", "location_code": "hk", "company": "\u6607\u6377\u7ba1\u7406\u670d\u52d9\u6709\u9650\u516c\u53f8", "job_title": "\u65e5\u66f4\u4fdd\u5b89\u54e1", "description": "Job Description\n\nThe Data Center Operation Engineer is members of 24x7 Data Center Operations team and reports to Data Center Operation Manager. The DC Operation Engineer is tier 1 support for on-premises data center services operation and requests fulfillment in Colocation services, Cross-connect services, and Remote-Hands / Smart-Hands services.\n\nResponsibilities\n\nThis role will be responsible for a variety of data center functions, including:\n\n\nProvide installation of power strips, equipment rack, rack shelving, cables, and customer equipment\n\u00a0Physical / visual inspections, troubleshooting of issues for IT equipment\n\u00a0Provide regular reporting on progress as required by Data Center customers\n\u00a0Monitoring the Data Centre infrastructures (Power, cooling, etc.) and engaging the respective specialized team\nCoordination/communications tasks for Change Management Process, Incident Management Process, Physical access control processes and request management, and support for Procurement processes\nManagement of Inventory records and regular asset inventory accuracy inspections\nEnsure established policies and procedures are followed and compliance requirements are met\nAbility to handle multiple tasks and prioritize work in a fast-paced, high-pressure environment\n\nMinimum qualifications\n\nDiploma / Degree holders in Computer Science or equivalent work experience\u00a0\nAt least 3 years\u2019 experience working in the Data Center operations space\nCandidate with\u00a0more experience will be considered\u00a0as Senior Operation Engineer\nCCNA / MCSE certification highly desirable\nUnderstanding of DC Space, Power, Cooling management\nGood communication skills in spoken and written English and Cantonese\n\nPreferred qualifications:\u00a0\n\nKnowledge of ISO 27001 & PCI DSS, TVRA\n\nWe offer competitive salary package and career development opportunity. Interested parties, please quote our reference number and apply with full resume,\u00a0present and expected salary, by clicking \"APPLY NOW\".\u00a0\n\nWe are an equal opportunity employer and welcome applications from all qualified candidates. Information provided will be treated in strict confidence and only be used for consideration of your application for the relevant post within BDx (HK) Limited. Personal data provided by job applicants will be used strictly according to our Personal Information Collection Statement, a copy of which will be available upon written request. Information of unsuccessful candidates will be destroyed within six months.", "employment_types": ["Full Time"], "selling_points": ["\u8ca0\u8cac\u5de1\u8996\u7269\u696d", "\u78ba\u4fdd\u6240\u6709\u8a2d\u65bd\u904b\u4f5c\u6b63\u5e38", "\u6c92\u6709\u5b78\u6b77\u8981\u6c42; 1\u5e74\u7d93\u9a57"], "locations": ["Wong Tai Sin Area"], "categories": ["Property / Real Estate", "Property Management", "Others", "Others", "Security / Safety Control"], "post_time": "2022-01-18T04:10:55Z", "salary": {"currency": null, "max": null, "min": null, "period": "monthly", "term": null}, "salary_visible": false, "title_keywords": [], "responsibilities": ["data", "operations", "fulfillment", "inventory", "troubleshooting", "communication", "asset inventory", "compliance", "reports", "visual", "installation", "reporting", "management", "change management", "monitoring", "procedures", "procurement processes", "policies", "coordination", "it equipment", "access control"], "requirements": {"degrees": ["diploma", "degree"], "majors": ["computer science"], "languages": ["cantonese", "english"], "language_level": ["good"], "hard_skills": ["dc", "mcse", "ccna"], "soft_skills": ["communication skills", "responsible", "troubleshooting", "prioritize", "handle multiple tasks", "coordination"], "languages_combined": [{"language": "cantonese", "language_level": ["good"]}, {"language": "english", "language_level": ["good"]}]}, "experience_required": {"duration": ["at least 3 years"], "field": ["operation"]}}, {"job_id": "100003009055509", "location_code": "hk", "company": "Hong Kong Housing Society", "job_title": "Assistant Contract Management Manager (3-year Contract)", "description": "Responsibilities:\n\nAssist supervisors in formulating operational strategies with a view to maintaining operational productivity and efficiency in a full spectrum of operational services including but not limited to customer service standard, sales target, theatrical efficiency, work safety and performance of systems\nAssist supervisors in setting up departmental KPIs to achieve company goals and objectives including but not limited to sales target, sales strategies, maintenance plan, filler programs benefiting stakeholders of the property\nAssist supervisors in preparing operational budget and management analysis and monitor operating costs to ensure effective utilization of resources\u00a0\nManage and co-ordinate with various functions of the Operations Department in the preparation of monthly, quarterly, annual and ad hoc reports\nPlan and review the daily manpower deployment by managing staff roster and coordinating with\u00a0various functions of the Operations Department in handling related administrative work for the\u00a0requisition of casual labour to ensure smooth operation, timely payment and achieve optimal\u00a0utilization of resources and an effective cost control mechanism\nMonitor venue usage, revenue and traffic records and coordinate with various functions of the\u00a0Operations Department in the preparation of reports and analysis\nPerform the role of Duty Officer as circumstances required to oversee all on-day event, monitor\u00a0and direct cross team staff to address as hoc requests and monitor and report abnormalities\nManage and co-ordinate with various functions of the Operations Department in the handling of\u00a0customer feedback, enquiry, complaints and lost & found cases with a view to ensuring timely\u00a0and appropriate response by written and verbal means\nCoordinate with various functions of the Operations Department in the liaison with hirers,\u00a0contractors and in-house staff on site visit requests, booking matters and event requirements,\u00a0technical feasibilities, venue set up, signage, technical requirements, equipment, rundown and\u00a0compliance to house rules and statutory requirements to ensure smooth operation\nAssist booking applications of multi-purpose areas/rooms and co-ordinate with various function\u00a0of the Operations Department to handle with the corresponding operation services\nHandle ad hoc tasks as assigned\n\nRequirements:\n\nDegree or above in business management, venue management or related disciplines\nAt least\u00a03 years\u2019 relevant experiences with 2 years\u2019 in supervisory level, exposure in Venue Services is preferred\nIndependent, well organized and able to work under pressure\nGood command of both spoken and written English & Chinese\nProficiency in Microsoft Office applications\nImmediate available is preferred\n\nWe offer competitive salary and attractive benefits to the right candidates. Interested parties please send resume with\u00a0expected salary\u00a0to Human Resources and Administration Department, New World Facilities Management Company Limited by clicking \"Apply Now\".\n\nFor details of the company, please visit website\u00a0https://www.youthsquare.hk/", "employment_types": ["Contract"], "selling_points": ["Carry out pre and post contract administration", "Conduct vetting of final accounts", "Degree in Quantity Surveying or equivalent"], "locations": ["Quarry Bay"], "categories": ["Property / Real Estate", "Property Management"], "post_time": "2022-01-18T02:39:56Z", "salary": {"currency": null, "max": null, "min": null, "period": "monthly", "term": null}, "salary_visible": false, "title_keywords": ["assistant contract management manager"], "responsibilities": ["co-ordinate with", "operations", "budget", "statutory requirements", "payment", "customer service", "plan", "costs", "ad hoc", "administrative work", "maintaining", "sales target", "compliance", "monitor", "reports", "kpis", "report", "management", "review", "coordinate with", "ad hoc tasks", "booking", "maintenance", "analysis", "systems", "cost control"], "requirements": {"degrees": ["degree or above"], "majors": ["related disciplines", "business"], "languages": ["english", "chinese"], "language_level": ["good command"], "hard_skills": ["business management", "microsoft office"], "soft_skills": ["independent", "well organized", "work under pressure"], "languages_combined": [{"language": "english", "language_level": ["good command"]}, {"language": "chinese", "language_level": ["good command"]}]}, "experience_required": {"duration": ["at least 3 years", "2 years"], "field": ["supervisory level"]}}, {"job_id": "100003009055537", "location_code": "hk", "company": "Hong Kong Housing Society", "job_title": "Senior Officer / Officer (Maintenance-Building)", "description": "Requirements:\n\n\nBachelor's degree, preferably in marketing or business administration\n6 - 10 years' experience in office leasing with major developers\nGood understanding of the office leasing market\nFamiliar with leasing procedures and relevant legal documentation\nStrong interpersonal skills and able to communicate well with business partners\nProven English proficiency and good Putonghua will be an advantage\nPro-active attitude and good team player\n\n\nResponsibilities:\n\n\nResponsible for handling daily leasing enquiries, lease negotiation, marketing, tenancy administration, co-ordination with property management and other related duties for a portfolio of office premises\n\n(Candidates with less experience will be considered for more junior positions.)\n\nGood remuneration and attractive fringe benefits will be offered to the successful applicant. Interested parties please apply with full resume, present and expected salary, available date by clicking \u201cApply Now\u201d.\n\nFor further information, please visit our company website: http://www.shkp.com/.\n\n\nWe are an equal opportunity employer and welcome applications from all qualified candidates. All personal data collected will be used for recruitment purpose only.\u00a0 Applicants not hearing from us within 3 months may consider their applications unsuccessful.\u00a0 All personal data collected will be destroyed within 24 months.", "employment_types": ["Permanent"], "selling_points": ["Carrying out design and detailing of building work", "Certificate in Building/Construction", "PC applications and CAD"], "locations": ["Cheung Sha Wan"], "categories": ["Property / Real Estate", "Property Management"], "post_time": "2022-01-18T02:41:16Z", "salary": {"currency": null, "max": null, "min": null, "period": "monthly", "term": null}, "salary_visible": false, "title_keywords": ["senior officer", "officer"], "responsibilities": ["management", "administration"], "requirements": {"degrees": ["degree", "bachelor"], "majors": ["marketing", "business administration"], "languages": ["putonghua", "english"], "language_level": ["advantage", "proficiency", "good"], "hard_skills": ["documentation"], "soft_skills": ["good team player", "interpersonal skills", "pro-active"], "languages_combined": [{"language": "putonghua", "language_level": ["good", "proficiency", "advantage"]}, {"language": "english", "language_level": ["proficiency", "advantage"]}]}, "experience_required": {"duration": ["6 - 10 years"], "field": []}}, {"job_id": "100003009054591", "location_code": "hk", "company": "", "job_title": "Leasing Officer (Residential) - Basic Salary plus discretionary bonus", "description": "F.5 / HKDSEE or certificate in related disciplines\n1-2 years' working\u00a0experience, preferably\u00a0in property management industry\nHard-working with pleasant personality and being a good team-player\nProficient in MS Office and Chinese word processing\nGood command of\u00a0both written and spoken\u00a0English and Chinese\n\nWe will offer attractive compensation package to the right candidate. Please send application enclosing resume stating career and salary history, expected salary and date of availability to The Human Resources Manager, Goodwell Property Management Limited, 2/F New Treasure Centre, 10 Ng Fong Street, San Po Kong, Kowloon\u00a0or by clicking \u201cApply Now\u201d (in Word format). Please quote the reference of the position you apply for in all correspondences.\n\nWe are an equal opportunity employer and welcome applications from all qualified candidates.\u00a0 Personal data collected will be treated in strictest confidence and handled confidentially by authorized personnel for recruitment-related purposes within the Group. Applicants not hearing from us within six weeks from the date of\u00a0application may consider their applications unsuccessful.\n\n(Our website : http://www.goodwell.com.hk/)", "employment_types": ["Full Time", "Permanent"], "selling_points": [], "locations": ["Central"], "categories": ["Sales, CS & Business Devpt", "Business Development", "Property / Real Estate", "Property Management", "Sales - Real Estate"], "post_time": "2022-01-17T10:25:16Z", "salary": {"currency": null, "max": null, "min": null, "period": "monthly", "term": null}, "salary_visible": false, "title_keywords": ["leasing officer"], "responsibilities": ["management", "recruitment", "website", "personal data"], "requirements": {"degrees": ["certificate"], "majors": ["related disciplines"], "languages": ["english", "chinese"], "language_level": ["good command", "proficient"], "hard_skills": ["chinese word processing", "word", "ms office"], "soft_skills": ["team-player", "confidence", "hard-working", "pleasant"], "languages_combined": [{"language": "english", "language_level": ["good command"]}, {"language": "chinese", "language_level": ["good command", "proficient"]}]}, "experience_required": {"duration": ["1-2 years"], "field": ["management"]}}, {"job_id": "100003009050036", "location_code": "hk", "company": "Hong Yip Service Company Limited", "job_title": "Estate Officer (5-day work) - North Point", "description": "\u8077\u8cac :\u8ca0\u8cac\u5de1\u8996\u7269\u696d, \u78ba\u4fdd\u6240\u6709\u8a2d\u65bd\u904b\u4f5c\u6b63\u5e38; \u8655\u7406\u9867\u5ba2\u67e5\u8a62, \u5354\u52a9\u4e0a\u53f8\u8ddf\u9032\u6295\u8a34\u53ca\u8655\u7406\u7dca\u6025\u4e8b\u6545; \u4e3b\u52d5\u8207\u696d\u6236\u63a5\u89f8, \u7dad\u6301\u826f\u597d\u95dc\u4fc2 (\u56fa\u5b9a\u5de5\u4f5c\u5730\u9ede)\n\u8cc7\u6b77 :\u6c92\u6709\u5b78\u6b77\u8981\u6c42; 1\u5e74\u7d93\u9a57; \u4e00\u822c\u7cb5\u8a9e; \u4e00\u822c\u666e\u901a\u8a71; \u4e00\u822c\u82f1\u8a9e; \u61c2\u95b1\u8b80\u4e2d\u6587; \u61c2\u95b1\u8b80\u82f1\u6587; \u6301\u6709\u4fdd\u5b89\u4eba\u54e1\u8a31\u53ef\u8b49\n\u5f85\u9047 :\u6bcf\u6708$14,500, \u4e0a\u53487\u6642\u81f3\u4e0b\u53487\u6642, \u6bcf\u9031\u5de5\u4f5c6\u5929,\u8f2a\u4f11, \u6bcf\u5929\u5de5\u4f5c 12 \u5c0f\u6642\n\u7533\u8acb\u9808\u77e5 :\u6c42\u8077\u8005\u53ef\u6309 APPLY NOW\u7533\u8acb\u6216\u81f4\u96fb23522124\u8207\u6607\u6377\u7ba1\u7406\u670d\u52d9\u6709\u9650\u516c\u53f8\u9ea5\u5148\u751f\u806f\u7d61\u3002", "employment_types": ["Full Time", "Permanent"], "selling_points": ["Wholly owned subsidiary of Sun Hung Kai Properties", "Minimun 4 years' relevant experience", "Form 5 or above with Diploma / Certificate"], "locations": ["Not Specified"], "categories": ["Sales, CS & Business Devpt", "Customer Service - Supervisor / Officer", "Hospitality / F & B", "Hospitality / Hotel Services", "Property / Real Estate", "Property Management"], "post_time": "2022-01-15T03:50:47Z", "salary": {"currency": null, "max": null, "min": null, "period": "monthly", "term": null}, "salary_visible": false, "title_keywords": ["estate officer"], "responsibilities": [], "requirements": {"degrees": [], "majors": [], "languages": [], "language_level": [], "hard_skills": [], "soft_skills": [], "languages_combined": []}, "experience_required": {"duration": [], "field": []}}, {"job_id": "100003009048522", "location_code": "hk", "company": "Savills Property Management Limited", "job_title": "\u7269\u696d\u7ba1\u7406\u54e1/\u4fdd\u5b89\u54e1 (\u591c\u73ed)", "description": "[Ref: ACMM(Contract)]\n\n\nThe Job\n\nAssist the contract management team to carry out pre and post contract administration functions for cost monitoring/control and in compliance with HKHS\u2019s policies and procedures.\nPrepare draft bidding documents for procurement of consultancies.\nConduct pre contract cost control particularly on preparation/technical checking of cost estimates, cost plans and cost analysis.\nMonitor tender exercise and vet tender documents and tender reports for compliance with HKHS's requirements.\nMonitor post contract administration including checking of payment valuation and cost estimates of variation works.\nConduct vetting of final accounts.\nAssemble, collate and administer project cost data and assist preparation of annual budget.\n\nThe Person\n\nDegree in Quantity Surveying or equivalent.\nMinimum 5 years post-graduation experience in quantity surveying practice, particularly tender documentation, contract management, estimation, cost planning and control, preferably with local experience in large scale residential and commercial projects.\nPreferably with professional qualification of MHKIS (QS) or equivalent.\nGood understanding and knowledge of pre and post contract quantity surveying professional practices.\nGood command of written and spoken English and Chinese.\nHands-on experience in general computer application.\nGood understanding of current construction industry and property market.\n\nAttractive remuneration package will be offered to suitable candidates. To apply, please submit online application: https://careers.hkhs.com/ or send your application with full resume and reference quoted to Human Resources Manager by fax: 2882 4466.\n\nYou are welcome to visit our website www.hkhs.com to learn more about us.\nApplicants not invited for interview within 8 weeks may consider their applications unsuccessful.\n\nPersonal data provided by job applicants will be used strictly in accordance with the Housing Society\u2019s personal data policies which is available in our website and obtainable upon request. Please refer to the Policy Statement on Employment Related Data under Personal Data (Privacy) Ordinance in our website.", "employment_types": ["Full Time"], "selling_points": [], "locations": ["Kwun Tong"], "categories": ["Property / Real Estate", "Property Management", "Others", "Others", "Security / Safety Control"], "post_time": "2022-01-14T06:44:41Z", "salary": {"currency": null, "max": null, "min": null, "period": "monthly", "term": null}, "salary_visible": false, "title_keywords": ["\u4fdd\u5b89\u54e1"], "responsibilities": ["data", "budget", "payment", "plans", "control", "tender documents", "compliance", "monitor", "tender", "valuation", "cost", "contract administration", "monitoring", "procedures", "checking", "tender reports", "cost analysis", "policies", "contract management", "cost control"], "requirements": {"degrees": ["degree"], "majors": ["surveying"], "languages": ["english", "chinese"], "language_level": ["good command"], "hard_skills": ["documentation"], "soft_skills": ["hands-on"], "languages_combined": [{"language": "english", "language_level": ["good command"]}, {"language": "chinese", "language_level": ["good command"]}]}, "experience_required": {"duration": ["minimum 5 years"], "field": ["commercial", "management", "planning"]}}, {"job_id": "100003009055511", "location_code": "hk", "company": "Hong Kong Housing Society", "job_title": "Assistant Manager (Maintenance-Building)", "description": "[Ref: SO/O(M-B)]\n\nThe Job\n\nAssist in carrying out design and detailing of building works and service installation works to satisfy user requirements.\nPrepare record drawings, working drawings, specifications, tender documents and contract documents.\nAssist in analyzing all tenders, preparing tender reports, and contract administration.\nAssist in preparing estimates, budgets, and evaluation for maintenance contracts.\nAssist in planning, co-ordinating and supervising contract works related to maintenance, alteration and improvement of properties.\nAssist in inspecting, testing and taking over of the Housing Society's new properties.\nFiling of drawings, manual and technical literature.\n\nThe Person\n\nHolders of Higher Diploma/Higher Certificate in Building/Construction or related disciplines.\nKnowledge of Government regulations on building or construction.\nMinimum 3 years' experience in maintenance of Building installations.\nBasic knowledge of relevant regulations.\nPC applications and CAD.\nCandidates with less experience will be considered\u00a0as Officer (Maintenance-Building).\n\nAttractive remuneration package will be offered to suitable candidates. To apply, please submit online application: https://careers.hkhs.com/ or send your application with full resume and reference quoted to Human Resources Manager by fax: 2882 4466.\n\nYou are welcome to visit our website www.hkhs.com to learn more about us.\nApplicants not invited for interview within 8 weeks may consider their applications unsuccessful.\n\nPersonal data provided by job applicants will be used strictly in accordance with the Housing Society\u2019s personal data policies which is available in our website and obtainable upon request. Please refer to the Policy Statement on Employment Related Data under Personal Data (Privacy) Ordinance in our website.", "employment_types": ["Permanent"], "selling_points": ["Emergency repairs for designated estates", "Tendering and contract administration process", "3 years\u2019 experience in building maintenance"], "locations": ["Others"], "categories": ["Property / Real Estate", "Property Management"], "post_time": "2022-01-18T02:40:06Z", "salary": {"currency": null, "max": null, "min": null, "period": "monthly", "term": null}, "salary_visible": false, "title_keywords": ["assistant manager"], "responsibilities": ["installation", "budgets", "supervising", "maintenance", "tender documents", "contract administration", "contracts", "design", "drawings", "preparing tender", "testing", "specifications", "reports", "evaluation", "planning"], "requirements": {"degrees": ["diploma", "higher certificate"], "majors": ["related disciplines"], "languages": [], "language_level": [], "hard_skills": ["cad", "basic", "maintenance", "pc applications"], "soft_skills": [], "languages_combined": []}, "experience_required": {"duration": ["minimum 3 years"], "field": ["maintenance"]}}, {"job_id": "100003009047492", "location_code": "hk", "company": "Goodwell Property Management Ltd", "job_title": "Assistant Property Manager", "description": "Job Highlights\n\nLeasing, Deluxe residential complex in The Peak\nAnnual Leave, Medical\nGood Career Prospect & Sustainable Development\n\nJob Description\n\nResponsibilities :\n\nScout and identify prospective tenants looking to lease a property\nOversee the processing and approval of tenant applications and lease documents\nMaintain contact with tenants to oversee their welfare and help resolve property issues\nOrganize meetings with Landlord and Estate manager are to identify solutions necessary for achieving occupancy targets\nConduct survey of the property market on competing lease rates and other trends that affect occupancy/rental\nDevelop and implement policies necessary for improving profitability\nOversee marketing and advertising of vacancies on media/advert channels to attract potential tenants\n\nRequirements :\n\nDiploma holder in Marketing, Business Administration or related discipline\nHolder of EAA licence is an advantage.\nAt least 3 years of relevant leasing experience.\nAble to work independently, good inter-personal and communication skills and detail-minded.\nGood common of spoken and written English.\nLocation: The Peak\nIMMEDIATE AVAILABLE\u00a0is highly preferred.\n\nBenefits :\nDiscretionary bonus\nMedical Insurance\nTravel allowance (Transportation commute from Central in the morning is provided)\n\nCandidate with more experience will be considered as Assistant Leasing Manager.\n\nFor interested parties, please contact Mr Vick Ma at Tel. 9270 4684.\u00a0\n\nPersonal data collected would be used for recruitment purposes only.", "employment_types": ["Full Time", "Permanent"], "selling_points": ["Degree in Housing / Facilities Management", "Member of RPHM, CIH or HKIH is preferable", "Conversant with BMO, DMC and related ordinances"], "locations": ["Not Specified"], "categories": ["Property / Real Estate", "Property Consultancy", "Property Management", "Others"], "post_time": "2022-01-15T03:49:41Z", "salary": {"currency": null, "max": null, "min": null, "period": null, "term": null}, "salary_visible": false, "title_keywords": ["assistant property manager"], "responsibilities": ["advertising", "policies", "develop", "maintain", "contact"], "requirements": {"degrees": ["diploma holder"], "majors": ["marketing", "business administration"], "languages": ["english"], "language_level": ["good"], "hard_skills": [], "soft_skills": ["detail-minded", "communication skills", "work independently", "inter-personal"], "languages_combined": [{"language": "english", "language_level": ["good"]}]}, "experience_required": {"duration": ["at least 3 years"], "field": []}}, {"job_id": "100003009048510", "location_code": "hk", "company": "Harbour City Estates Ltd", "job_title": "MANAGER \u2013 CENTRE OPERATIONS", "description": "Job Responsibilities:\n\nMonitor the maintenance, security and cleaning services of\u00a0properties\nHandle enquiries, complaints and emergency incidents\nPerform administrative duties\n\nJob Requirements:\n\nForm 5 or above with Diploma / Certificate in Property and Facility Management or qualification equivalent to Qualifications Framework Level 3\nAt least 4 years of\u00a0relevant experience in property\u00a0management\nGood analytical, communication and leadership skills\nMature, independent and able to work under pressure\nGood command of both written and spoken English and Chinese\nComputer literate in Ms Word, Excel and Chinese Word Processing\nCandidates with less experience will be considered as Assistant Estate Officer.\n\n\nWe provide attractive remuneration package and fringe benefits for the right candidate.\u00a0 Interested parties please send detailed resume with current & expected salaries via \u201cApply Now\u201d or send in your application through the Careers section in our Corporate Website: http://www.hongyip.com/Careers.\n\nHong Yip is an Equal Opportunity Employer.\u00a0 Personal data collected will be used for recruitment purpose only.\u00a0", "employment_types": ["Full Time", "Permanent"], "selling_points": ["Should be university graduates in property", "10 years\u2019 proven management experience", "Should be a self-starter who works independently"], "locations": ["Tsim Sha Tsui"], "categories": ["Building & Construction", "Building / Construction / QS", "Management", "General Management", "Property / Real Estate", "Property Management"], "post_time": "2022-01-15T03:50:01Z", "salary": {"currency": null, "max": null, "min": null, "period": "monthly", "term": null}, "salary_visible": false, "title_keywords": ["operations", "manager"], "responsibilities": ["maintenance", "monitor", "handle enquiries", "administrative duties", "cleaning"], "requirements": {"degrees": ["certificate", "diploma", "form 5 or above"], "majors": [], "languages": ["english", "chinese"], "language_level": ["good command"], "hard_skills": ["excel", "chinese word processing", "ms word"], "soft_skills": ["independent", "leadership skills", "mature", "communication", "work under pressure"], "languages_combined": [{"language": "english", "language_level": ["good command"]}, {"language": "chinese", "language_level": ["good command"]}]}, "experience_required": {"duration": ["at least 4 years"], "field": ["management", "relevant experience"]}}, {"job_id": "100003009049295", "location_code": "hk", "company": "HARRIMAN PROPERTY MANAGEMENT LIMITED", "job_title": "PROPERTY OFFICER / ASSISTANT PROPERTY OFFICER (Ngau Tau Kok)", "description": "\u8077\u8cac :\u4e00\u822c\u7269\u696d\u7ba1\u7406\u54e1/\u4fdd\u5b89\u54e1\u5de5\u4f5c, \u5de1\u908f, \u8a2a\u5ba2\u767b\u8a18, \u8655\u7406\u5ba2\u6236\u6295\u8a34\u53ca\u67e5\u8a62\n\u8cc7\u6b77 :\u5c0f\u516d\u7a0b\u5ea6; \u826f\u597d\u7cb5\u8a9e; \u61c2\u8b80\u5beb\u4e2d\u6587; \u6301\u6709\u4fdd\u5b89\u57f9\u8a13\u8ab2\u7a0b\u8b49\u66f8(QAS); \u6301\u6709\u4fdd\u5b89\u4eba\u54e1\u8a31\u53ef\u8b49\n\u5f85\u9047 :\u6bcf\u6708$15,000, \u6709\u734e\u52f5\u6027\u82b1\u7d05, \u91ab\u7642\u4fdd\u96aa, \u5728\u8077\u57f9\u8a13 \u53ca\u6649\u5347\u6a5f\u6703, \u4e0b\u53487\u6642\u534a\u81f3\u4e0a\u53487\u6642\u534a, \u6bcf\u9031\u5de5\u4f5c6\u5929,\u8f2a\u4f11, \u6bcf\u5929\u5de5\u4f5c 12 \u5c0f\u6642\n\u7533\u8acb\u9808\u77e5 :\u6c42\u8077\u8005\u53ef\u6309 APPLY NOW\u7533\u8acb\u6216\u81f4\u96fb31053008\u8207\u7b2c\u4e00\u592a\u5e73\u6234\u7dad\u65af\u7269\u696d\u7ba1\u7406\u6709\u9650\u516c\u53f8\u90ed \u5c0f\u59d0\u806f\u7d61\u3002", "employment_types": ["Full Time", "Permanent"], "selling_points": [], "locations": ["Ngau Tau Kok"], "categories": ["Admin & HR", "Clerical / Admin Staff", "Marketing / Public Relations", "Public Relations - Event Management", "Property / Real Estate", "Property Management"], "post_time": "2022-01-14T08:24:01Z", "salary": {"currency": null, "max": null, "min": null, "period": null, "term": null}, "salary_visible": false, "title_keywords": ["property officer", "assistant property officer"], "responsibilities": [], "requirements": {"degrees": [], "majors": [], "languages": [], "language_level": [], "hard_skills": [], "soft_skills": [], "languages_combined": []}, "experience_required": {"duration": [], "field": []}}, {"job_id": "100003009047502", "location_code": "hk", "company": "Goodwell Property Management Ltd", "job_title": "Assistant Property Manager - (Hotel)", "description": "[Ref: AM(M-B)]\n\n\nThe Job\n\nTo solve technical problems independently and deal with urgent/emergency repairs for designated estates/properties.\nTo prepare design, budgets, estimates, drawings, specifications and tender document for maintenance works for senior\u2019s approval.\nTo review the estates facilities, recommend the improvement program for estates/ properties. To monitor and supervise the improvement works independently to assure quality of works and upgrade the standard of living.\nTo administer the tendering and contract administration process which includes drafting letters to invite quotations, obtaining and evaluating quotations, preparing tender documents and issuing works orders for maintenance and improvement works.\nTo provide technical advice on materials, tools, etc. to PM staff and co-ordinate repair works carried out by technicians or contractors. To supervise and monitor work progress on site and certify work completion.\nTo conduct regular survey and report of estates and properties not limited to slopes, roads, grounds and underground services.\nTo inspect tenants\u2019 fixtures and various installations and recommend for repairs and improvement as necessary.\nTo comment the design drawings, specifications, manual; estimate maintenance cost for building elements for new development projects; conduct inspections and testings to identify defects during take over of new projects and liaise / co-ordinate with Projects Division accordingly.\nTo liaise and coordinate with consultants, utility companies, government departments and other parties concerned on progress of works in estate areas.\nTo act as a mentor for Senior Maintenance colleagues.\nTo attend meetings and handle enquiries from tenants / owners / residents\u2019 association/ District Council/ contractors.\n\nThe Person\n\nDegree / Higher Diploma in Building / Construction or equivalent.\n3 years\u2019 experience in construction or building maintenance or 5 years' experience for Higher Certificate in Building Studies.\nIn-depth knowledge of relevant regulations and professional maintenance policies.\n\nAttractive remuneration package will be offered to suitable candidates. To apply, please submit online application: https://careers.hkhs.com/ or send your application with full resume and reference quoted to Human Resources Manager by fax: 2882 4466.\n\nYou are welcome to visit our website www.hkhs.com to learn more about us.\nApplicants not invited for interview within 8 weeks may consider their applications unsuccessful.\n\nPersonal data provided by job applicants will be used strictly in accordance with the Housing Society\u2019s personal data policies which is available in our website and obtainable upon request. Please refer to the Policy Statement on Employment Related Data under Personal Data (Privacy) Ordinance in our website.", "employment_types": ["Full Time", "Permanent"], "selling_points": ["Degree in Housing / Facilities Management", "Member of RPHM, CIH or HKIH is preferable", "Conversant with BMO, DMC and related ordinances"], "locations": ["Not Specified"], "categories": ["Property / Real Estate", "Property Consultancy", "Property Management", "Others"], "post_time": "2022-01-15T03:49:42Z", "salary": {"currency": null, "max": null, "min": null, "period": null, "term": null}, "salary_visible": false, "title_keywords": ["assistant property manager"], "responsibilities": ["liaise", "co-ordinate with", "technical advice", "quality", "tendering", "design", "drawings", "attend meetings", "tender document", "monitor", "handle enquiries", "report", "cost", "coordinate with consultants", "design drawings", "contract administration", "review", "specifications", "solve technical problems", "budgets", "maintenance", "letters", "invite quotations", "preparing tender", "repair"], "requirements": {"degrees": ["higher certificate", "diploma", "degree"], "majors": ["building studies"], "languages": [], "language_level": [], "hard_skills": ["maintenance"], "soft_skills": [], "languages_combined": []}, "experience_required": {"duration": ["3 years", "5 years"], "field": ["construction", "maintenance"]}}, {"job_id": "100003009052681", "location_code": "hk", "company": "Securitas Security Services (Hong Kong) Limited", "job_title": "Security Manger - Investment Bank (Central)", "description": "Degree in Property / Facilities Management or related disciplines\nAt least 5 years\u2019 relevant experience with at least 1 years at managerial level\nMember of RPHM, CIH or HKIH preferred\nConversant with BMO, DMC and related ordinances\nGood command of both written and spoken English and Chinese\nStrong leadership,\u00a0with good communication and interpersonal skills\n\nWe will offer attractive compensation package to the right candidate. Please send application enclosing resume stating career and salary history, expected salary and date of availability to\u00a0The Human Resources Manager, Goodwell Property Management Limited, 2/F New Treasure Centre, 10 Ng Fong Street, San Po Kong, Kowloon or by clicking \u201cApply Now\u201d (in Word format). Please quote the reference of the position you apply for in all correspondences.\u00a0\n\nWe are an equal opportunity employer and welcome applications from all qualified candidates.\u00a0 Personal data collected will be treated in strictest confidence and handled confidentially by authorized personnel for recruitment-related purposes within the\u00a0Group. Applicants not hearing from us within six weeks from the date of\u00a0application may consider their applications unsuccessful.\n\n(Our website : http://www.goodwell.com.hk/)", "employment_types": ["Full Time", "Permanent"], "selling_points": ["5 Days shift, 9 hours", "Investment Bank", "Security Manager"], "locations": ["Central"], "categories": ["Property / Real Estate", "Property Consultancy", "Property Management", "Others", "Security / Safety Control"], "post_time": "2022-01-17T03:41:34Z", "salary": {"currency": null, "max": null, "min": null, "period": "monthly", "term": null}, "salary_visible": false, "title_keywords": [], "responsibilities": ["management", "website", "communication", "recruitment", "personal data"], "requirements": {"degrees": ["degree"], "majors": ["related disciplines"], "languages": ["english", "chinese"], "language_level": ["good command"], "hard_skills": ["facilities management", "word"], "soft_skills": ["communication and interpersonal skills", "leadership", "confidence"], "languages_combined": [{"language": "english", "language_level": ["good command"]}, {"language": "chinese", "language_level": ["good command"]}]}, "experience_required": {"duration": ["at least 5 years", "at least 1 years"], "field": ["managerial", "relevant experience"]}}, {"job_id": "100003009046768", "location_code": "hk", "company": "Hong Yip Service Company Limited", "job_title": "Estate Officer (5-day work) - Yuen Long", "description": "The successful candidate will oversee the center operations of a prestigious shopping mall \u2013 Harbour City to ensure delivery of the highest service standards.\u00a0 He/she will manage a sizable team of building management, customer service and carpark staff and appointed contractors in daily operations including security, crowd control, traffic management, carpark operation, cleaning, landscaping, customer service and statutory compliance. \u00a0\nCandidates should be university graduates in property, facility management or related discipline with at least 10 years\u2019 proven management experience in managing large commercial complex with proven leadership skills in a highly disciplined environment.\u00a0 He/She should be a self-starter who works independently, resourceful in problem-solving, equipped with excellent organization and people management skills and is proficient in spoken and written English and Chinese.\u00a0 Previous training in risk assessment and management, as well as experience in crowd control would be a definite advantage.\nWe offer competitive remuneration package that commensurate with experience and qualifications.\u00a0 Interested parties are invited to send full resume stating contact telephone number, date available, present and expected salary to our recruitment email address.\n(Personal data provided will be used strictly in accordance with the Company\u2019s personal data policy which is available upon request.)", "employment_types": ["Full Time", "Permanent"], "selling_points": ["Wholly owned subsidiary of Sun Hung Kai Properties", "Minimun 4 years' relevant experience", "Form 5 or above with Diploma / Certificate"], "locations": ["Not Specified"], "categories": ["Sales, CS & Business Devpt", "Customer Service - Supervisor / Officer", "Property / Real Estate", "Property Management", "Others"], "post_time": "2022-01-14T00:58:00Z", "salary": {"currency": null, "max": null, "min": null, "period": "monthly", "term": null}, "salary_visible": false, "title_keywords": ["estate officer"], "responsibilities": ["crowd control", "traffic management", "management", "statutory compliance", "operations", "building management", "service standards", "customer service", "daily operations", "landscaping", "cleaning", "carpark operation"], "requirements": {"degrees": [], "majors": [], "languages": ["english", "chinese"], "language_level": ["excellent", "proficient"], "hard_skills": ["problem-solving", "harbour"], "soft_skills": ["independently", "resourceful", "problem-solving", "leadership skills", "customer service"], "languages_combined": [{"language": "english", "language_level": ["excellent", "proficient"]}, {"language": "chinese", "language_level": ["excellent", "proficient"]}]}, "experience_required": {"duration": ["at least 10 years"], "field": ["related", "commercial", "management", "training"]}}, {"job_id": "100003009056225", "location_code": "hk", "company": "Yue Xiu Apt Parking Limited", "job_title": "\u5e02\u52d9\u4e3b\u4efb", "description": "Responsibilities :\n\n\nResponsible for assisting in the day-to-day management of a newly developed Grade A commercial building located in Ngau Tau Kok\nAssist in the overall property management functions of the site management office, including handling telephone inquiries / complaints, co-ordination with contractors and performing administrative / clerical duties e.g Monthly reports, Income & Marketing analysis\nAssist in planning and executing marketing plans & activities\nRequirements :\n\n\nDegree or Diploma Holder in Property / Housing Management or related disciplines with at least 3 years\u2019 relevant experience in property management\nHard working, mature, independent with cheerful character\nGood problem-solving, communication & presentation skill\nProficient in both written & spoken English & Chinese\nGood PC skills and knowledge in Chinese word processing is a must\n5 days work week\nFresh graduates will also be considered\n\nWe offer ample opportunities for career development and attractive salary package commensurate with experience and qualifications. \u00a0Interested parties please apply with full resume via\u00a0\u201cAPPLY NOW\u201d.\u00a0\n\nFor further information, please visit our company website:\u00a0\nhttps://www.harriman.com.hk/en/career_with_us/join_our_team.\u00a0\n\n(All information provided by applicants will be treated in strict confidence and be used for recruitment purpose only)", "employment_types": ["Full Time", "Permanent"], "selling_points": ["\u767c\u6398\u65b0\u5e02\u5834\u53ca\u65b0\u5ba2\u6236\uff0c\u4e26\u767c\u5c55\u7dad\u8b77\u5ba2\u6236\u95dc\u4fc2\uff0c\u8ca0\u8cac\u9032\u884c\u505c\u8eca\u5834\u5e02\u5834\u8abf\u7814\u4e26\u5236\u5b9a\u5e02\u5834\u7b56\u7565", "\u8ca0\u8cac\u5354\u52a9\u8eca\u5834\u6295\u6a19\u3001\u6210\u672c\u8a08\u7b97\u53ca\u5408\u540c\u7ba1\u7406\uff0c\u8655\u7406\u696d\u4e3b\u53ca\u5ba2\u6236\u7684\u8aee\u8a62\u3001\u6295\u8a34\uff0c\u78ba\u4fdd\u5340\u57df\u505c\u8eca\u5834\u7684\u65e5\u5e38\u71df\u904b", "1\u5e74\u4ee5\u4e0a\u5de5\u4f5c\u7d93\u9a57\uff0c\u5177\u505c\u8eca\u5834\u7ba1\u7406\u3001\u7269\u696d\u7ba1\u7406\u8005\u53ca\u5e02\u5834\u7d93\u9a57\u8005\u512a\u5148\uff0c\u9700\u5177\u76f8\u95dc\u7ba1\u7406\u6587\u6191\u53ca\u5b78\u6b77\u8b49\u66f8"], "locations": ["Not Specified"], "categories": ["Sales, CS & Business Devpt", "Business Development", "Marketing / Public Relations", "Marketing - Market Research", "Property / Real Estate", "Property Management"], "post_time": "2022-01-18T03:39:23Z", "salary": {"currency": null, "max": null, "min": null, "period": "monthly", "term": null}, "salary_visible": false, "title_keywords": [], "responsibilities": ["management", "monthly reports", "marketing plans", "analysis", "site management", "day-to-day management", "executing", "planning"], "requirements": {"degrees": ["diploma holder", "degree"], "majors": ["related disciplines"], "languages": ["english", "chinese"], "language_level": ["good", "proficient"], "hard_skills": ["presentation skill", "problem-solving", "pc skills", "chinese word processing"], "soft_skills": ["presentation skill", "cheerful", "independent", "problem-solving", "hard working", "mature", "communication"], "languages_combined": [{"language": "english", "language_level": ["proficient"]}, {"language": "chinese", "language_level": ["good", "proficient"]}]}, "experience_required": {"duration": ["at least 3 years"], "field": ["related", "management", "relevant experience"]}}, {"job_id": "100003009044770", "location_code": "hk", "company": "Jones Lang LaSalle Management Services Ltd", "job_title": "Assistant Property Manager (Quarry Bay Commercial Building)", "description": "Degree in Property / Facilities Management or related disciplines\nAt least 5 years\u2019 relevant experience with at least 1 years at managerial level\nMember of RPHM, CIH or HKIH preferred\nConversant with BMO, DMC and related ordinances\nGood command of both written and spoken English and Chinese\nStrong leadership,\u00a0with good communication and interpersonal skills\n\nWe will offer attractive compensation package to the right candidate. Please send application enclosing resume stating career and salary history, expected salary and date of availability to\u00a0The Human Resources Manager, Goodwell Property Management Limited, 2/F New Treasure Centre, 10 Ng Fong Street, San Po Kong, Kowloon or by clicking \u201cApply Now\u201d (in Word format). Please quote the reference of the position you apply for in all correspondences.\u00a0\n\nWe are an equal opportunity employer and welcome applications from all qualified candidates.\u00a0 Personal data collected will be treated in strictest confidence and handled confidentially by authorized personnel for recruitment-related purposes within the\u00a0Group. Applicants not hearing from us within six weeks from the date of\u00a0application may consider their applications unsuccessful.\n\n(Our website : http://www.goodwell.com.hk/)", "employment_types": ["Full Time", "Permanent"], "selling_points": ["Dip/ Degree holder in Property/Facility Management", "Minimum 5 years of relevant experience", "Knowledge of related ordinance"], "locations": ["Quarry Bay"], "categories": ["Property / Real Estate", "Property Management", "Others", "Others", "Security / Safety Control"], "post_time": "2022-01-13T06:13:00Z", "salary": {"currency": null, "max": null, "min": null, "period": null, "term": null}, "salary_visible": false, "title_keywords": ["assistant property manager"], "responsibilities": ["management", "website", "communication", "recruitment", "personal data"], "requirements": {"degrees": ["degree"], "majors": ["related disciplines"], "languages": ["english", "chinese"], "language_level": ["good command"], "hard_skills": ["facilities management", "word"], "soft_skills": ["communication and interpersonal skills", "leadership", "confidence"], "languages_combined": [{"language": "english", "language_level": ["good command"]}, {"language": "chinese", "language_level": ["good command"]}]}, "experience_required": {"duration": ["at least 5 years", "at least 1 years"], "field": ["managerial", "relevant experience"]}}, {"job_id": "100003009055366", "location_code": "hk", "company": "Kai Shing Management Services Ltd", "job_title": "Club Assistant (Shatin District)", "description": "Job Description\n\n\u2022 Manage the on-site team and develop protocol, practice align with policies to perform the security & service\n\n\u2022 Partner with business units to identify security deficiencies, and develop customized policies and procedures to gain compliance with regulations\n\n\u2022 Provide advice and counsel on complex physical security, internal fraud investigations, prevention, life safety risk, fire safety, crisis management, and emergency response issues\n\n\u2022 Handle and manage securing classified and sensitive information from the work environment and assigned task\n\n\u2022 Prepare and present collected data, information, report and documentation for the scope related, including invoice and accruals\n\n\u2022 To conduct threat assessment to the business, event activity and site\n\n\u2022 Maintains a positive, professional environment in full compliance with applicable laws, regulations, policies and procedures; ensures that security force understand and comply with applicable laws, regulations, policies and procedure\n\nRequirement\n\n\u2022 Degree holder in any discipline;\n\n\u2022 A minimum 3 years of experience in a supervisory position in the corporate security industry;\n\n\u2022 Strong sense of security awareness, tough and with good communication and interpersonal skill\n\n\u2022 Good knowledge in health, safety and environment;\n\n\u2022 Proficient in both written and spoken English and Chinese;\n\n\u2022 Strong prioritizing abilities, analytical and problem-solving skills;\n\n\u2022 Must be competent and literate with computers;\n\n\u2022 Immediate available is a definite advantage", "employment_types": ["Full Time", "Permanent"], "selling_points": ["At least 1 year's experience in Club Mgt preferred", "Hard working and willing to learn", "Shift duty required"], "locations": ["Shatin Area"], "categories": ["Beauty Care / Health", "Athletics / Fitness / Sports & Recreation", "Property / Real Estate", "Property Management", "Others", "Others"], "post_time": "2022-01-18T02:20:36Z", "salary": {"currency": null, "max": null, "min": null, "period": "monthly", "term": null}, "salary_visible": false, "title_keywords": ["club assistant"], "responsibilities": ["regulations", "data", "invoice", "policies", "compliance", "procedures", "develop", "provide advice", "documentation", "crisis management", "report"], "requirements": {"degrees": ["degree holder"], "majors": [], "languages": ["english", "chinese"], "language_level": ["proficient"], "hard_skills": ["problem-solving skills"], "soft_skills": ["competent", "interpersonal skill", "communication", "problem-solving skills", "prioritizing"], "languages_combined": [{"language": "english", "language_level": ["proficient"]}, {"language": "chinese", "language_level": ["proficient"]}]}, "experience_required": {"duration": ["minimum 3 years"], "field": ["supervisory", "security"]}}, {"job_id": "100003009055754", "location_code": "hk", "company": "Citybase Property Management Limited", "job_title": "Internal Auditor", "description": "\u8077\u8cac\uff1a\n\n\u767c\u6398\u65b0\u5e02\u5834\u53ca\u65b0\u5ba2\u6236\uff0c\u4e26\u767c\u5c55\u7dad\u8b77\u5ba2\u6236\u95dc\u4fc2\n\u8ca0\u8cac\u9032\u884c\u505c\u8eca\u5834\u5e02\u5834\u8abf\u7814\u4e26\u5236\u5b9a\u5e02\u5834\u7b56\u7565\n\u8ca0\u8cac\u5354\u52a9\u8eca\u5834\u6295\u6a19\u3001\u6210\u672c\u8a08\u7b97\u53ca\u5408\u540c\u7ba1\u7406\n\u8655\u7406\u696d\u4e3b\u53ca\u5ba2\u6236\u7684\u8aee\u8a62\u3001\u6295\u8a34\uff0c\u78ba\u4fdd\u5340\u57df\u505c\u8eca\u5834\u7684\u65e5\u5e38\u71df\u904b\n\u5728\u9810\u7b97\u7bc4\u570d\u5167\u63a7\u5236\u5730\u5340\u505c\u8eca\u5834\u7684\u71df\u904b\u6210\u672c\n\u6d41\u7a0b\u4e8b\u9805\u7684\u5448\u5831\uff0c\u4e00\u822c\u6587\u66f8\u8655\u7406\n\n\u8981\u6c42\uff1a\n\n1\u5e74\u4ee5\u4e0a\u5de5\u4f5c\u7d93\u9a57\uff0c\u5177\u505c\u8eca\u5834\u7ba1\u7406\u3001\u7269\u696d\u7ba1\u7406\u8005\u53ca\u5e02\u5834\u7d93\u9a57\u8005\u512a\u5148\n\u9700\u5177\u76f8\u95dc\u7ba1\u7406\u6587\u6191\u53ca\u5b78\u6b77\u8b49\u66f8\n\u5177\u4e00\u822c\u96fb\u8166\u64cd\u4f5c\u77e5\u8b58\u53ca\u4f7f\u7528\n\u826f\u597d\u4e2d\u3001\u82f1\u6587\u66f8\u5beb\u53ca\u8a9e\u8a00\u80fd\u529b\n\u6709\u99d5\u99db\u57f7\u7167\u53ca\u6709\u79c1\u5bb6\u8eca\u512a\u5148\u8003\u616e\n\u80fd\u7acb\u5373\u4e0a\u73ed\u8005\u512a\u5148\u8003\u616e\n\n\u6709\u610f\u8005\u8acb\u5c07\u500b\u4eba\u4e2d\u3001\u82f1\u6587\u7c21\u6b77\u96fb\u90f5\u81f3\"Apply Now\"\n\n\u6240\u6709\u7533\u8acb\u53ea\u4f5c\u62db\u8058\u4e4b\u7528\u4e26\u5c07\u4e88\u7d55\u5c0d\u4fdd\u5bc6\uff1b\u672a\u7372\u53d6\u9304\u8005\u7684\u6240\u6709\u8cc7\u6599\u5c07\u65bc 6\u500b\u5167\u92b7\u6bc0\u3002", "employment_types": ["Full Time", "Permanent"], "selling_points": ["University graduated", "Internal Audit", "External Audit"], "locations": ["Mong Kok"], "categories": ["Accounting", "Audit", "Property / Real Estate", "Property Management"], "post_time": "2022-01-18T02:55:40Z", "salary": {"currency": null, "max": null, "min": null, "period": "monthly", "term": null}, "salary_visible": false, "title_keywords": ["internal auditor"], "responsibilities": [], "requirements": {"degrees": [], "majors": [], "languages": [], "language_level": [], "hard_skills": [], "soft_skills": [], "languages_combined": []}, "experience_required": {"duration": [], "field": []}}, {"job_id": "100003009050251", "location_code": "hk", "company": "Chevalier Group - Property Management", "job_title": "Estate Manager", "description": "Responsibilities\n\nTo oversee the daily operation of the Commercial property including maintenance, cleaning, security, financial control, etc.\nTo maintain good relationship with occupants by rendering prompt service at all times\nTo supervise an on-site team to ensure it meets the Company\u2019s requirements\nTo monitor the quality of work of service contractors\nRequirements:\n\nDegree / Diploma holder in property management\nHolder of MCIH /MHKIH / EAA license is preferable\nAt least 5 years\u2019 experience of which 2 years must be at supervisory level\nKnowledge of BMO, DMC & tenancy management \u00a0\nCustomer-oriented, with excellent interpersonal and communication skill\nStrong in leadership\nExcellent command of both spoken and written English and Chinese\nHands on PC skills\n\nWe offer attractive remuneration packages and good career prospects for the right applicant. Please apply by clicking the \"APPLY NOW\" button or mail your full resume and expected salary to the PM-HR Department, 14/F, Dorset House, Taikoo Place, Quarry Bay or fax to 2968-4177.\n\n(Please quote the reference number on the envelope/subject of email)\n\nApplicants not invited for interviews within 6 weeks may consider their applications unsuccessful. Information provided will be treated with strict confidential and be used for the purpose of employment only.", "employment_types": ["Full Time"], "selling_points": ["Degree in Property Management", "Minimum 7 years property management experience", "Holder of valid Property Management License"], "locations": ["Not Specified"], "categories": ["Property / Real Estate", "Property Management", "Others"], "post_time": "2022-01-14T10:01:20Z", "salary": {"currency": null, "max": null, "min": null, "period": null, "term": null}, "salary_visible": false, "title_keywords": ["estate manager"], "responsibilities": ["control", "maintenance", "daily operation", "monitor", "quality", "maintain good relationship", "cleaning"], "requirements": {"degrees": ["diploma holder", "degree"], "majors": [], "languages": ["english", "chinese"], "language_level": ["excellent"], "hard_skills": ["pc skills"], "soft_skills": ["communication skill", "customer-oriented", "hands on", "leadership", "interpersonal"], "languages_combined": [{"language": "english", "language_level": ["excellent"]}, {"language": "chinese", "language_level": ["excellent"]}]}, "experience_required": {"duration": ["2 years", "at least 5 years"], "field": ["supervisory level"]}}, {"job_id": "100003009043190", "location_code": "hk", "company": "Hutchison Property Group Limited", "job_title": "SENIOR MARKETING MANAGER \u2013 OFFICE LEASING [Ref. SMM-OFFICE]", "description": "What will you do?\n\nAssist Clubhouse Manager to ensure\u00a0smooth and efficient operation of a sizable residential clubhouse\nHandle enquiries and provide excellent services to customers\u00a0\nAssist in organization and promotion of the clubhouse activities and special events for residents\nResponsible for administration duties of general recreational facilities and other ad hoc duties assigned\n\nDo you have a right profile?\n\nForm 5 or above\nCertificate/Diploma in Recreation & Sports, Club House or Hotel Management preferred\nAt least 1 - 2 year's experience in Club or Hotel management preferred\nGood command of both written and spoken English and Chinese\nGood communication skills and interpersonal skills with pleasant and outgoing personality\nShift duty is required\nFresh graduate will also be considered\n\nWhat do we offer?\n\nAttractive remuneration package\nGreat promotion ladder\nNew joiner bonus\nReferral reward\nMedical benefit\nPaid marriage leave, birthday leave, well-being leave and annual leave\nEducation subsidy\nChildren scholarship\nCompany trip\n\nHow to apply?\n\nInterested parties, please apply once with application quoting job reference number, detailed resume, contact telephone number and expected salary by:\n\nClicking the \u201cApply Now\u201d button\nMail to: Human Resources Department,\u00a0Unit 301-303, 3/F, Apec Plaza, 49 Hoi Yuen Road, Kwun Tong, Hong Kong\nFax to:\u00a0 (852) 2827 8608\nCall: (852)3703 5460\n\n(Attached resume should be in MS Word for Windows)\n\n(Data collected would be used for recruitment purpose only)", "employment_types": ["Full Time", "Permanent"], "selling_points": ["Degree holder", "15 years' relevant experience", "Leasing of HK office properties"], "locations": ["Hung Hom"], "categories": ["Property / Real Estate", "Property Consultancy", "Property Management", "Sales, CS & Business Devpt", "Sales - Real Estate"], "post_time": "2022-01-17T11:25:57Z", "salary": {"currency": null, "max": null, "min": null, "period": null, "term": null}, "salary_visible": false, "title_keywords": ["senior marketing manager"], "responsibilities": ["ad hoc duties", "management", "communication", "handle enquiries", "administration"], "requirements": {"degrees": ["certificate", "diploma", "form 5 or above", "fresh graduate"], "majors": ["hotel"], "languages": ["english", "chinese"], "language_level": ["good command"], "hard_skills": [], "soft_skills": ["efficient", "communication skills", "outgoing personality", "responsible", "pleasant", "interpersonal skills", "smooth"], "languages_combined": [{"language": "english", "language_level": ["good command"]}, {"language": "chinese", "language_level": ["good command"]}]}, "experience_required": {"duration": ["at least 1 - 2 year"], "field": ["hotel management"]}}, {"job_id": "100003009047358", "location_code": "hk", "company": "CBRE Limited", "job_title": "Senior Property Officer (Grade A Commercial Building)", "description": "Chevalier Property Management Limited, a subsidiary of Chevalier Group, is now inviting high calibre persons to apply for this position:\n\nResponsibilities\n\nAssist Estate Officer\u00a0in monitioring daily\u00a0Property Management issues\nHandle complaints and enquiries of the customers\nProvide clerical support to estate management officer\nPerform ad hoc duties as assigned\n\nRequirements\n\nHKDSE or above\nMinimum 1 years' relevant working experience\nAble to work independently, with excellent communication and interpersonal skills\nGood command of both written and spoken English and Chinese\nProficient in MS Office including MS Word, MS Excel and Chinese word processing\n\nAttractive remuneration package will be offered to the right candidate. Interested parties, please send us your resume with current and expected salary (with reference number quoted) by clicking \"Apply Now\" or mail to:\n\nThe\u00a0Human Resources\u00a0Manager, Chevalier Group, 22/F, Chevalier\u00a0Commercial Centre,\u00a08 Wang Hoi Road, Kowloon Bay, Hong Kong\n\nWe are an equal opportunity employer and welcome applications from all qualified candidates.\u00a0 Personal data collected would be used for recruitment purpose only.\n\nWelcome to visit:www.chevalierpropmgt.com.hk", "employment_types": ["Full Time", "Permanent"], "selling_points": ["5 years rel. experience", "Prior exp. in Grade A commercial building", "Solid exp. in Mgt Office & Building Operation work"], "locations": ["Central"], "categories": ["Property / Real Estate", "Property Consultancy", "Property Management"], "post_time": "2022-01-14T02:54:02Z", "salary": {"currency": null, "max": null, "min": null, "period": "monthly", "term": null}, "salary_visible": false, "title_keywords": ["senior property officer"], "responsibilities": ["provide clerical support", "management", "ad hoc duties", "handle complaints"], "requirements": {"degrees": ["hkdse"], "majors": [], "languages": ["english", "chinese"], "language_level": ["good command", "proficient"], "hard_skills": ["ms word", "ms excel", "chinese word processing", "ms office"], "soft_skills": ["work independently", "communication and interpersonal skills"], "languages_combined": [{"language": "english", "language_level": ["good command"]}, {"language": "chinese", "language_level": ["good command", "proficient"]}]}, "experience_required": {"duration": ["minimum 1 years"], "field": ["relevant working experience"]}}, {"job_id": "100003009043872", "location_code": "hk", "company": "Citybase Property Management Limited", "job_title": "Property Assistant", "description": "Chevalier Property Management Limited, a subsidiary of Chevalier Group, is now inviting high calibre persons to apply for this position:\n\nResponsibilities\n\nOversee and monitor the day-to-day operation of residential estate such as cleaning, security, maintenance works, etc.\nResponsible for budget control and enforcement of DMC\nAttend IO meetings and maintain good relationship with the Incorporated Owners\nRequirements\n\n\nDegree holder\u00a0with professional qualification in Property Management (e.g. MHKIH, MCIH, RPHM) will be an advantage\n7 years or above relevant working experience in property management of which 3 years in managerial level\nHolder of valid Property Management License (Tier 1)\nCustomer oriented, pleasant personality, excellent communication and interpersonal skills\nAble to work under pressure and work independently\nFluent in both written and spoken English and Chinese\nProficient in MS Office including MS Word and Excel\nWorking Location:\u00a0Tseung Kwan O\u00a0or Siu Sai Wan\n\nAttractive remuneration package will be offered to the right candidate.\nInterested parties, please send your resume with current and expected salary by clicking \"Apply Now\" or mail to:\u00a0\n\nThe Human Resource Manager, Chevalier Group, 22/F, Chevalier Commerical Centre, 8 Wang Hoi Road, Kowloon Bay, Hong Kong\u00a0\n\nWe are an equal opportunity employer and welcome applications from all qualified candidates.\u00a0 Personal data collected would be used for recruitment purpose only\n\nWelcome to visit http://www.chevalierpropmgt.com.hk", "employment_types": ["Full Time", "Permanent"], "selling_points": ["HKDSE/above, preferably Cert/Dip in Property Mgnt", "1 yr exp in property mgt of residential properties", "Hard-working, pleasant personality, gd team player"], "locations": ["Tin Shui Wai"], "categories": ["Admin & HR", "Clerical / Admin Staff", "Property / Real Estate", "Property Management", "Others"], "post_time": "2022-01-14T09:39:53Z", "salary": {"currency": null, "max": null, "min": null, "period": null, "term": null}, "salary_visible": false, "title_keywords": ["property assistant"], "responsibilities": ["maintenance", "monitor", "maintain good relationship", "cleaning", "budget control", "day-to-day operation"], "requirements": {"degrees": ["degree holder"], "majors": [], "languages": ["english", "chinese"], "language_level": ["fluent"], "hard_skills": ["ms word", "excel", "wan", "ms office"], "soft_skills": ["work under pressure", "work independently", "communication and interpersonal skills", "pleasant"], "languages_combined": [{"language": "english", "language_level": ["fluent"]}, {"language": "chinese", "language_level": ["fluent"]}]}, "experience_required": {"duration": ["7 years", "3 years"], "field": ["managerial", "management", "relevant working experience"]}}, {"job_id": "100003009048585", "location_code": "hk", "company": "Angelita Property Co Ltd", "job_title": "Leasing and Property Officer", "description": "\nYou will be assisting the Property Manager to provide property management services in a Grade-A commercial building in CENTRAL, including but not limited to the supervision of front-line staff, management of daily operation & site, and maintaining a good relationship with tenants.\n\nWe are looking for candidates with:\nDegree or above in Property Management/Housing Studies related discipline\nAt least 5 years\u2019 relevant experience in Property Management/Facilities Management.\u00a0\nPrior experience gained from managing Grade A Commercial Building(s) is required\nSound Knowledge of Building Management Ordinance\nMore experienced candidate will be considered as Assistant Property Manager\nImmediate Available candidate is highly preferred\nInterested parties please click \"APPLY NOW\" and remark your expected salary in the application.\u00a0", "employment_types": ["Full Time"], "selling_points": [], "locations": ["Causeway Bay"], "categories": ["Property / Real Estate", "Property Management"], "post_time": "2022-01-14T06:51:32Z", "salary": {"currency": "HKD", "max": 24999, "min": 20000, "period": "monthly", "term": null}, "salary_visible": true, "title_keywords": ["property officer"], "responsibilities": ["management", "maintaining", "daily operation", "good relationship", "building management"], "requirements": {"degrees": ["degree or above"], "majors": [], "languages": [], "language_level": [], "hard_skills": ["facilities management"], "soft_skills": [], "languages_combined": []}, "experience_required": {"duration": ["at least 5 years"], "field": ["commercial", "management", "relevant experience"]}}, {"job_id": "100003009051252", "location_code": "hk", "company": "Grand Wise Asia Pacific Limited (Property Management & Security Company)", "job_title": "8\u5c0f\u6642\u5236\u7269\u696d\u5ba2\u6237\u670d\u52d9\u54e1 (\u4fdd\u5b89\u54e1) / Property Services Assistant [\u6b61\u8fce\u65b0\u5165\u884c\uff0c\u7121\u9808\u6709\u95dc\u7d93\u9a57\uff0c\u6708\u85aaHK$17,000\u6216\u4ee5\u4e0a]", "description": "Degree holder or above with at least 3 years working experience, preferably in residential field.\nKnowledge in BMO & DMC, as well as other related ordinances and regulations\nGood command of both written and spoken English and Chinese.\nGood communication skill, responsible, well-organized, independent,\u00a0self-motivated\u00a0self-motivated\u00a0and services oriental.\nCandidates lack of experience will be considered as Property Officer.\nWe offer career development subsidy to the right candidate.\u00a0 Interested parties please e-mail full resume with expected salary by clicking \"Apply Now\"\n\n\nWebsite : www.newgem.com.hk", "employment_types": ["Full Time", "Permanent"], "selling_points": [], "locations": ["Not Specified"], "categories": ["Property / Real Estate", "Property Management", "Sales, CS & Business Devpt", "Retail Sales", "Others", "Security / Safety Control"], "post_time": "2022-01-15T06:21:25Z", "salary": {"currency": "HKD", "max": 19999, "min": 17000, "period": "monthly", "term": null}, "salary_visible": true, "title_keywords": ["property services assistant", "\u4fdd\u5b89\u54e1"], "responsibilities": ["regulations", "communication"], "requirements": {"degrees": ["degree holder"], "majors": [], "languages": ["english", "chinese"], "language_level": ["good command"], "hard_skills": [], "soft_skills": ["self-motivated", "independent", "responsible", "communication skill", "well-organized"], "languages_combined": [{"language": "english", "language_level": ["good command"]}, {"language": "chinese", "language_level": ["good command"]}]}, "experience_required": {"duration": ["at least 3 years"], "field": []}}, {"job_id": "100003009043199", "location_code": "hk", "company": "Hutchison Property Group Limited", "job_title": "SENIOR MARKETING OFFICER / MARKETING OFFICER \u2013 OFFICE LEASING [Ref. SMO/MO-OFFICE]", "description": "Responsibilities\n\n\nAssist daily operations, liaison, administration & handling documents\n\nRequirements\n\nHKDSE or above, preferably with Certificate / Diploma in Property Management or related disciplines\nAt least 1 year working experience in property management of residential properties is preferable\nFamiliar with MS Word, Excel and Chinese Word Processing\nGood command of both written and spoken English and Chinese\nHard-working with pleasant personality and being a good team-player\nCandidates with less experience or qualification will be considered as Clerk\n\nWe will offer attractive compensation package to the right candidate. Please send application enclosing resume stating career and salary history, expected salary and date of availability to The Human Resources Manager, Citybase Property Management Limited, Unit No.1, 6/F, Hampton Loft, 11 Hoi Fan Road, Tai Kok Tsui, Kowloon by fax at 2717 4717 or by clicking ''Apply Now'' (in word format). Please quote the reference of the position you apply for in all correspondences.\n\nWe are an equal opportunity employer and welcome applications from all qualified candidates. Personal data collected will be treated in strictest confidence and handled confidentially by authorized personnel for recruitment-related purposes within the Group. Applicants not hearing from us within six weeks from the date of advertisement may consider their applications unsuccessful.", "employment_types": ["Full Time", "Permanent"], "selling_points": ["Degree holder", "6 years' relevant experience", "Assist in leasing of HK office properties"], "locations": ["Hung Hom"], "categories": ["Property / Real Estate", "Property Consultancy", "Property Management", "Sales, CS & Business Devpt", "Sales - Real Estate"], "post_time": "2022-01-17T11:25:22Z", "salary": {"currency": null, "max": null, "min": null, "period": null, "term": null}, "salary_visible": false, "title_keywords": ["senior marketing officer", "marketing officer"], "responsibilities": ["handling documents", "daily operations", "administration"], "requirements": {"degrees": ["certificate", "diploma", "hkdse"], "majors": ["related disciplines"], "languages": ["english", "chinese"], "language_level": ["good command"], "hard_skills": ["excel", "no", "chinese word processing", "word", "ms word"], "soft_skills": ["team-player", "confidence", "hard-working", "pleasant"], "languages_combined": [{"language": "english", "language_level": ["good command"]}, {"language": "chinese", "language_level": ["good command"]}]}, "experience_required": {"duration": ["at least 1 year"], "field": ["management"]}}, {"job_id": "100003009054166", "location_code": "hk", "company": "Hong Yip Service Company Limited", "job_title": "(\u65e5/\u591c\u73ed)\u9ad8\u7d1a/\u5ba2\u6236\u670d\u52d9\u9577(6\u59299\u5c0f\u6642)", "description": "[Ref: SM/M(M-B)]\n\n\nThe Job\n\nPlan and monitor the overall maintenance/improvement program for rental estates/managed properties/aged buildings.\nReview design, budget, estimates, drawing, specifications, tender proposals for maintenance and improvement works.\nLead a team of professional, co-ordinate and oversee the provision of professional advice to property owners on maintenance of buildings and other related issues.\nAttend meetings and handle enquiries from owners'/residents' associations, District Board and etc.\nProvide input to the design of new development projects to assure quality of work and minimize future maintenance cost.\n\nThe Person\n\nMember of professional bodies in HKIS / RICS / HKIA / RIBA / HKIE / CIBSE / IEE/ IMechE or equivalent, with minimum 10 years\u2019 experience, 5 of which must be post-qualification experience.\nSound knowledge of related ordinances and professional maintenance practices.\nCandidates with less experience will be considered as Manager (Maintenance-Building).\n\nAttractive remuneration package will be offered to suitable candidates. To apply, please submit online application: https://careers.hkhs.com/ or send your application with full resume and reference quoted to Human Resources Manager by fax: 2882 4466.\n\nYou are welcome to visit our website www.hkhs.com to learn more about us.\nApplicants not invited for interview within 8 weeks may consider their applications unsuccessful.\n\nPersonal data provided by job applicants will be used strictly in accordance with the Housing Society\u2019s personal data policies which is available in our website and obtainable upon request. Please refer to the Policy Statement on Employment Related Data under Personal Data (Privacy) Ordinance in our website.", "employment_types": ["Full Time", "Permanent"], "selling_points": ["\u65b0\u9d3b\u57fa\u5730\u7522\u767c\u5c55\u6709\u9650\u516c\u53f8\u5168\u8cc7\u9644\u5c6c\u6a5f\u69cb", "\u51774\u5e74\u7269\u696d\u7ba1\u7406\u6216\u5ba2\u6236\u670d\u52d9\u5de5\u4f5c\u7d93\u9a57", "\u521d\u4e2d\u7a0b\u5ea6\u6216\u5177\u8cc7\u6b77\u67b6\u69cb\u540c\u7b49\u8cc7\u6b77"], "locations": ["North Point"], "categories": ["Property / Real Estate", "Property Management", "Others", "Others", "Security / Safety Control"], "post_time": "2022-01-17T08:38:29Z", "salary": {"currency": null, "max": null, "min": null, "period": "monthly", "term": null}, "salary_visible": false, "title_keywords": [], "responsibilities": ["cost", "maintenance", "review", "monitor", "budget", "design", "quality", "lead a team", "handle enquiries", "specifications", "plan", "tender", "attend meetings"], "requirements": {"degrees": [], "majors": [], "languages": [], "language_level": [], "hard_skills": ["maintenance", "rics", "hkie", "hkis"], "soft_skills": [], "languages_combined": []}, "experience_required": {"duration": ["minimum 10 years"], "field": ["post-qualification", "maintenance"]}}, {"job_id": "100003009046895", "location_code": "hk", "company": "KONG SHUM UNION PROPERTY MANAGEMENT CO., LTD.", "job_title": "Assistant Property Manager-Grenville House", "description": "Responsibilities:\n\nMaintain and operate the facilities of data center\nEscalate issues to external facility contractors and internal customers\nSupervise external facility contractors to carry out scheduled maintenance activities\nReview the vendors' maintenance reports\nReinforce the maintenance regime according to the contract\nProvide installation of power strips, equipment rack, rack shelving, cables and customer equipment\nRespond to emergencies in an on-call rotation\n\u64cd\u4f5c\u53ca\u7dad\u4fee\u6578\u64da\u4e2d\u5fc3\u8a2d\u5099\n\u9032\u884c\u6bcf\u5929\u4f8b\u884c\u6aa2\u67e5,\u00a0\u4f8b\u5982\u6545\u969c\u8abf\u67e5,\u6a5f\u4ef6\u7dad\u4fee\u53ca\u64b0\u5beb\u6709\u95dc\u5831\u544a\n\u76e3\u7763\u627f\u5305\u5546\u9032\u884c\u5b9a\u671f\u8a2d\u5099\u4fdd\u990a\u5de5\u4f5c\n\u5b89\u88dd\u6578\u64da\u4e2d\u5fc3\u8a2d\u5099,\u4f8b\u5982\u96fb\u6e90\u62d6\u677f,\u5668\u6750\u67b6,\u6a5f\u67dc\u5c64\u677f,\u6574\u7406\u96fb\u7dda\u7b49\n\u8f2a\u6d41\u63a5\u807d\u53ca\u8655\u7406\u7dca\u6025\u4e8b\u6545\u67e5\u8a62\n\nRequirements:\n\nCertificate in Electrical/ Mechanical/ Building Service Engineering or equivalent\nAt least 2 years of experience in building / construction / hotel / property industry environment\nExperience in data center/telecommunications industry is an advantage\nHolder of registered Electrical worker license A\nGood PC knowledge of MS Word, Excel, AutoCAD etc\nShift duty is required\n\u6a5f\u96fb/\u6a13\u5b87\u8a2d\u5099\u5de5\u7a0b\u8a3c\u66f8\u6216\u540c\u7b49\u5b78\u6b77\n\u5169\u5e74\u4ee5\u4e0a\u6a5f\u96fb\u6216\u51b7\u6c23\u7cfb\u7d71\u53ca\u6a13\u5b87\u8a2d\u5099\u4e4b\u76f8\u95dc\u7d93\u99ed,\u00a0\u66fe\u4efb\u8077\u65bc\u6578\u64da\u4e2d\u5fc3\u66f4\u4f73\n\u6301\u6709\u8a3b\u518a\u96fb\u5de5a\u724c\u6216\u4ee5\u4e0a\n\u8a8d\u8b58\u5b89\u88dd\u53ca\u7dad\u4fee\u6a13\u5b87\u8a2d\u5099\u4e4b\u6cd5\u4f8b\u8981\u6c42\n\u719f\u6089\u96fb\u8166\u8edf\u4ef6\u5982MS WORD, MS EXCEL\u00a0\u53ca\u00a0AutoCAD\u7b49\n\u9700\u8f2a\u73ed\u5de5\u4f5c (7x24)\n\nWorking Location:\nKwai Hing \u8475\u8208 / Wong Chuk Hang \u9ec3\u7af9\u5751\n(Fixed Location \u56fa\u5b9a\u4e0a\u73ed\u5730\u9ede)\n\nWe offer competitive salary package and career development opportunity. Interested parties, please quote our reference number and apply with full resume,\u00a0present and expected salary, by clicking \"APPLY NOW\".\u00a0\n\nWe are an equal opportunity employer and welcome applications from all qualified candidates. Information provided will be treated in strict confidence and only be used for consideration of your application for the relevant post within BDx (HK) Limited. Personal data provided by job applicants will be used strictly according to our Personal Information Collection Statement, a copy of which will be available upon written request. Information of unsuccessful candidates will be destroyed within six months.", "employment_types": ["Full Time", "Permanent"], "selling_points": [], "locations": ["Central"], "categories": ["Property / Real Estate", "Property Management", "Others"], "post_time": "2022-01-14T01:38:45Z", "salary": {"currency": null, "max": null, "min": null, "period": "monthly", "term": null}, "salary_visible": false, "title_keywords": ["assistant property manager"], "responsibilities": ["installation", "maintenance", "data", "review", "maintain", "reports"], "requirements": {"degrees": ["certificate"], "majors": ["engineering"], "languages": [], "language_level": [], "hard_skills": ["excel", "ms word", "word", "ms excel", "pc knowledge", "autocad"], "soft_skills": [], "languages_combined": []}, "experience_required": {"duration": ["at least 2 years"], "field": ["telecommunications", "construction"]}}, {"job_id": "100003009052797", "location_code": "hk", "company": "Hong Kong Housing Society", "job_title": "Assistant Manager / Senior Officer (Planning & Development)", "description": "Job Highlights\u00a0\n\nResponsible for managing properties as assigned\u00a0\n3-6 years' relevant experience\u00a0\nHK$20,000-$25,000 per month\u00a0\n\nJob Description\u00a0\nResponsibilities:\u00a0\n\n\nResponsible for managing properties as assigned;\u00a0\nLiaise with owners and tenants/ contractors;\u00a0\nSupervise and monitor the contractors and technicians about the repair work and renovation projects\u00a0\nRequirements:\u00a0\n\nDegree or Diploma holder, preferably in property management;\u00a0\nHolding an Estate Agent's Licence or a Salesperson's Licence (Preferable);\u00a0\nProficient in BMO, DMC and/ or related ordinances;\u00a0\nGood knowledge on property market;\u00a0\nCan anticipate potential issue and make precaution;\u00a0\nMinimum 3-6 years' relevant working experience;\u00a0\nGood interpersonal skill, proactive, innovative and problem solving ability;\u00a0\nGood command of both written and spoken English and Chinese.\u00a0\n\nWorking Location: Causeway Bay\u00a0\nWorking Hours: Monday- Friday 10AM- 6PM ; Saturday 10AM-1PM\u00a0\nBenefits: Bank Holidays, Lunch Meal\u00a0", "employment_types": ["Permanent"], "selling_points": ["Flat-for-Sales Scheme secondary market", "Co-ordinate a flats handover team", "Experience in valuation and feasibility studies"], "locations": ["Quarry Bay"], "categories": ["Property / Real Estate", "Property Management"], "post_time": "2022-01-17T04:06:02Z", "salary": {"currency": null, "max": null, "min": null, "period": "monthly", "term": null}, "salary_visible": false, "title_keywords": ["assistant manager", "senior officer"], "responsibilities": ["liaise with", "repair", "renovation", "monitor"], "requirements": {"degrees": ["diploma holder", "degree"], "majors": [], "languages": ["english", "chinese"], "language_level": ["good command"], "hard_skills": ["problem solving", "make"], "soft_skills": ["innovative", "proactive", "problem solving", "interpersonal skill"], "languages_combined": [{"language": "english", "language_level": ["good command"]}, {"language": "chinese", "language_level": ["good command"]}]}, "experience_required": {"duration": ["minimum 3-6 years"], "field": ["relevant working experience"]}}, {"job_id": "100003009049507", "location_code": "hk", "company": "Jones Lang LaSalle Ltd", "job_title": "Senior Facilities Manager", "description": "\u4e09\u73ed\u5236\u5de5\u4f5c\u798f\u5229\uff1a\n\n\u5168\u5e74\u914c\u60c5\u6027\u82b1\u7d051\u500b\u6708\u4eba\u5de5\u6216\u4ee5\u4e0a\uff1b\n\u6708\u85aa HK$17,000 (\u5e95\u85aa\u53ca\u734e\u91d1\u7b49)\u6216\u4ee5\u4e0a\uff1b\n\u500d\u534a\u8d85\u6642\u88dc\u85aa (\u6642\u85aaHK$ 100)\uff0c\u6708\u5165\u53ef\u9054HK$18,500\u6216\u4ee5\u4e0a\n\u6bcf\u73ed\u00a08\u00a0\u5c0f\u6642\u5de5\u4f5c\uff0c\u5c08\u696d\u5728\u8077\u57f9\u8a13\uff1b\n\u5fc5\u9808\u8f2a\u4e09\u73ed (\u4e09\u73ed\u5236\uff1a\u65e9/\u4e2d/\u591c)\uff1b\u00a0\n\u63d0\u4f9b\u897f\u88dd\u5236\u670d\uff0c\u9580\u8a3a\u53ca\u4f4f\u9662\u91ab\u7642\u798f\u5229\u3002\n\n\u5de5\u4f5c\u5167\u5bb9\ufe30\n\n\u8ca0\u8cac\u4f4f\u5b85\u6216\u5546\u696d\u6a13\u5b87\u7684\u7269\u696d\u7ba1\u7406\u5de5\u4f5c(\u5305\u62ec\u4fdd\u5b89\u53ca\u5de1\u908f\u5de5\u4f5c)\uff1b\n\u63d0\u4f9b\u512a\u8cea\u5ba2\u6237\u670d\u52d9\u3002\n\n\u5de5\u4f5c\u8981\u6c42\u00a0:\n\n\u5fc5\u9808\u6301\u6709\u6709\u6548\u4fdd\u5b89\u54e1\u8b49\u6216\u4fee\u8b80\u7576\u4e2d\uff1b\n\u7121\u9808\u7d93\u9a57\uff0c\u6b61\u8fce\u65b0\u5165\u884c\u4eba\u4ed5\uff1b\n\u80fd\u64cd\u6d41\u5229\u5ee3\u6771\u8a71\uff0c\u7c21\u55ae\u82f1\u8a9e\u6e9d\u901a\uff0c\u8aa0\u5be6\u53ef\u9760\uff0c\u6709\u8cac\u4efb\u5fc3\u3002\n\n\u6c42\u8077\u8005\u8acb\u900f\u904e\u00a0\"Apply Now\"\u00a0\u6309\u626d\u7533\u8acb\u8a72\u8077\u4f4d\uff0c\u6216\u628a\u7c21\u6b74\u96fb\u90f5\u81f3 mshui @ talentcl.com\u3002\n\n\u5982\u6709\u4efb\u4f55\u7591\u554f\uff0cWhatsApp\u00a097906633\u00a0\u67e5\u8a62\u00a0(\u4f46\u4e0d\u63a5\u807d\u96fb\u8a71)\u3002\n\n\u5982\u6c42\u8077\u8005\u5728\u4e09\u661f\u671f\u5167\u672a\u6536\u5230\u4eba\u4e8b\u90e8\u7684\u898b\u5de5\u901a\u77e5\uff0c\u5247\u8996\u70ba\u4e0d\u9069\u5408\u6b64\u5de5\u4f5c\uff0c\u672c\u516c\u53f8\u4e0d\u9042\u4e00\u56de\u8986\uff0c\u656c\u5e0c\u898b\u8ad2\u3002\u00a0\n\nAll data collected will be used for recruitment purpose only", "employment_types": ["Full Time", "Permanent"], "selling_points": ["Po Fu Lam / Integrated Facilities Management", "Challenging Role", "Oversee Cleaning, Security & Landscaping Teams"], "locations": ["Pok Fu Lam"], "categories": ["Engineering", "Others", "Hospitality / F & B", "Others", "Property / Real Estate", "Property Management"], "post_time": "2022-01-14T08:46:27Z", "salary": {"currency": null, "max": null, "min": null, "period": "monthly", "term": null}, "salary_visible": false, "title_keywords": ["manager"], "responsibilities": ["recruitment", "data"], "requirements": {"degrees": [], "majors": [], "languages": [], "language_level": [], "hard_skills": [], "soft_skills": [], "languages_combined": []}, "experience_required": {"duration": [], "field": []}}, {"job_id": "100003009043058", "location_code": "hk", "company": "Urban Group", "job_title": "Property Asset Manager / Assistant Property Asset Manager", "description": "Degree holder in Real Estate, Surveying, Marketing, Business or related disciplines\n6 years' relevant experience in leasing and tenancy administration of Grade A office properties in Hong Kong\nRelevant experience with major developers an advantage\u00a0\nTo assist in implementing leasing strategies, tenants liaison and tenancy administration of office properties in Hong Kong\nTo conduct market research\nSelf-motivated and dynamic with good communication and presentation skills\nProficient in MS Word, Excel and PowerPoint\nFluent in written and spoken English and Chinese, including Putonghua\n\nCandidates with less experience will be considered as Marketing Officer\nWe offer salary and benefits commensurate with qualifications and experience. Please send a full resume with contact number and expected salary to General Manager - Human Resources & Administration, Hutchison Property Group Limited, 3/F., One Harbourfront, 18 Tak Fung Street, Hunghom, Kowloon (Please quote reference on envelope) or by clicking \"Apply Now\".\nWe are an equal opportunity employer and welcome applications from all qualified candidates. The information provided will be treated in strict confidence and be used only for consideration of your application for relevant/similar post(s).\n\nApplicants not hearing from us within six weeks from the date of advertisement may consider their applications unsuccessful. All personal data of unsuccessful applicants will be destroyed after the recruitment exercise when no longer required.", "employment_types": ["Full Time", "Permanent"], "selling_points": [], "locations": ["Not Specified"], "categories": ["Sales, CS & Business Devpt", "Customer Service - Supervisor / Officer", "Building & Construction", "Building / Construction / QS", "Property / Real Estate", "Property Management"], "post_time": "2022-01-12T09:40:50Z", "salary": {"currency": null, "max": null, "min": null, "period": "monthly", "term": null}, "salary_visible": false, "title_keywords": ["manager", "assistant"], "responsibilities": ["communication", "conduct market research", "administration"], "requirements": {"degrees": ["degree holder"], "majors": ["business", "related disciplines", "marketing", "surveying"], "languages": ["putonghua", "english", "chinese"], "language_level": ["fluent"], "hard_skills": ["excel", "dynamic", "powerpoint", "ms word"], "soft_skills": ["communication", "self-motivated", "dynamic", "presentation skills"], "languages_combined": [{"language": "putonghua", "language_level": ["fluent"]}, {"language": "english", "language_level": ["fluent"]}, {"language": "chinese", "language_level": ["fluent"]}]}, "experience_required": {"duration": ["6 years"], "field": ["marketing", "relevant experience", "leasing and tenancy administration"]}}, {"job_id": "100003009055476", "location_code": "hk", "company": "Craigengower Cricket Club", "job_title": "(Building Services) Asst Club Manager", "description": "Degree holder in Real Estate, Surveying or related disciplines\nMember of HKIS or RICS\nMinimum 8 years' experience in valuation, real estate development and investment appraisals\nRelevant experience in property market of HK and UK\nTo assist in conducting valuation on property development and investment appraisals\nTo carry out market research and feasibility studies on property and business-related topics\nFluent in written and spoken English and Chinese\nCandidates with less experience will be considered as Senior Officer \u2013 Business Development\n\nWe offer salary and benefits commensurate with qualifications and experience. Please send a full resume with contact number and expected salary to General Manager - Human Resources & Administration, Hutchison Property Group Limited, 3/F., One Harbourfront, 18 Tak Fung Street, Hunghom, Kowloon (Please quote reference on envelope) or by clicking \"Apply Now\".\n\nWe are an equal opportunity employer and welcome applications from all qualified candidates. The information provided will be treated in strict confidence and be used only for consideration of your application for relevant/similar post(s).\n\nApplicants not hearing from us within six weeks from the date of advertisement may consider their applications unsuccessful. All personal data of unsuccessful applicants will be destroyed after the recruitment exercise when no longer required.", "employment_types": ["Full Time"], "selling_points": [], "locations": ["Causeway Bay"], "categories": ["Property / Real Estate", "Property Management", "Building & Construction", "Others"], "post_time": "2022-01-18T02:40:02Z", "salary": {"currency": null, "max": null, "min": null, "period": "monthly", "term": null}, "salary_visible": false, "title_keywords": ["manager"], "responsibilities": ["valuation", "market research"], "requirements": {"degrees": ["degree holder"], "majors": ["related disciplines", "surveying"], "languages": ["english", "chinese"], "language_level": ["fluent"], "hard_skills": ["rics", "hkis"], "soft_skills": [], "languages_combined": [{"language": "english", "language_level": ["fluent"]}, {"language": "chinese", "language_level": ["fluent"]}]}, "experience_required": {"duration": ["minimum 8 years"], "field": ["development", "business development", "relevant experience", "investment"]}}, {"job_id": "100003009051955", "location_code": "hk", "company": "Jones Lang LaSalle Management Services Ltd", "job_title": "Senior Recreation Officer/ Recreation Officer - Residential Building in Wan Chai", "description": "What You'll Do\n\nTo provide quality services to our residents and guests\nTo be responsible for daily operation of the property, including but not limited to office administration, procurement, customer services, complaint handling etc.\nTo supervise the overall performance of contractors to ensure their services\u00a0properly provided\nTo direct and supervise building staff\nTo perform other duties as assigned by supervisor\u00a0\n\nWho You\u2019ll Work With\n\nYou will work with the property services team and external contractors to provide excellent services to all residents and guests.\u00a0\u00a0\n\nWho You Are\n\nCompetencies:\n\nCustomer Oriented\nBuilds Teams\nDevelops Solutions\nPersonally Accountable\u00a0\n\nQualifications and Requirements:\n\nDegree / Diploma holder in Property Management, Facilities Management or related disciplines\nAt least 3 years' relevant experience in\u00a0luxury residential building;\u00a0Candidates with less experience will also be considered for\u00a0Officer\u00a0title\nMember of a professional body recognized by the\u00a0PMSA\u00a0is an advantage\nGood command of both spoken and written English and Chinese\nProficient in MS Office\n\u00a0", "employment_types": ["Full Time", "Permanent"], "selling_points": ["Organize Recreation/Club House activities", "Supervisory Level", "Hospitality or club house experience is preferred"], "locations": ["Wan Chai"], "categories": ["Beauty Care / Health", "Athletics / Fitness / Sports & Recreation", "Hospitality / F & B", "Others", "Property / Real Estate", "Property Management"], "post_time": "2022-01-17T01:37:57Z", "salary": {"currency": null, "max": null, "min": null, "period": null, "term": null}, "salary_visible": false, "title_keywords": ["recreation officer"], "responsibilities": ["perform other duties", "management", "office administration", "daily operation", "quality", "teams", "customer services"], "requirements": {"degrees": ["diploma holder", "degree"], "majors": ["related disciplines"], "languages": ["english", "chinese"], "language_level": ["good command"], "hard_skills": ["facilities management", "ms office"], "soft_skills": ["accountable", "responsible"], "languages_combined": [{"language": "english", "language_level": ["good command"]}, {"language": "chinese", "language_level": ["good command"]}]}, "experience_required": {"duration": ["at least 3 years"], "field": ["relevant experience"]}}, {"job_id": "100003009052603", "location_code": "hk", "company": "Hong Kong Housing Society", "job_title": "Property Manager / Assistant Manager (Maintenance-Building Services)", "description": "Responsibilities\n\nManage and oversee daily operations of deluxe properties;\nBeing the 2nd in-charge of the management team to provide quality service to clients;\nEnsure compliance with DMC and relevant ordinances;\nAttend meetings with Management Committee members of The Incorporated Owners to maintain good relationship;\nLiaise with clients, suppliers and contractors;\nHandle ad hoc assignments, as required.\n\nRequirements\n\nDegree holder or above in property management or related disciplines;\nMember of CIH / HKIH or other recognized professional bodies;\nPossession of Property Management Practitioner (Tier 1) License being an advantage;\nAt least 7 years' solid experience in luxurious residential property management;\nStrong leadership with good communication and interpersonal skills;\nEnthusiastic to work and self-motivating;\nFluent in oral English & Cantonese;\nProficient in written English & Chinese;\nImmediate availability is highly preferred.\n\nInterested parties please send resume with expected salary by e-mail to: Apply Now\n(All personal data collected will be used for recruitment purpose only.)", "employment_types": ["Permanent"], "selling_points": ["Urgent repairs in building services installations", "Recommend the improvement program", "8 years\u2019 exp. in building services maintenance"], "locations": ["Others"], "categories": ["Property / Real Estate", "Property Management"], "post_time": "2022-01-17T03:30:50Z", "salary": {"currency": null, "max": null, "min": null, "period": "monthly", "term": null}, "salary_visible": false, "title_keywords": ["assistant manager", "property manager"], "responsibilities": ["liaise with clients", "management team", "management", "quality", "ensure compliance", "maintain good relationship", "daily operations", "ad hoc assignments", "attend meetings"], "requirements": {"degrees": ["degree holder"], "majors": ["related disciplines"], "languages": ["cantonese", "english", "chinese"], "language_level": ["proficient", "fluent"], "hard_skills": [], "soft_skills": ["oral", "communication and interpersonal skills", "leadership", "enthusiastic"], "languages_combined": [{"language": "cantonese", "language_level": ["fluent"]}, {"language": "english", "language_level": ["proficient", "fluent"]}, {"language": "chinese", "language_level": ["proficient"]}]}, "experience_required": {"duration": ["at least 7 years"], "field": ["management"]}}, {"job_id": "100003009042017", "location_code": "hk", "company": "Savills Guardian", "job_title": "Property Officer / Assistant Property Officer", "description": "[Ref: AMSO(P&D)]\n\nThe Job\n\nProvide comprehensive professional support in market research, critically examine restrictions and opportunities on land and planning issues and prudent calculations on financial commitment and results on new initiatives feasibilities studies.\nLiaise with planning environmental and other consultants to prepare Master layout Plan for new projects and associated planning submissions.\nAssist to formulate the overall sales exercises for sales projects including preparation of pricing structure and coordination with architects, advertising consultants and solicitors on sales matters etc.\nCo-ordinate a flats handover team to execute the logistics of the whole handover process and to follow up with all defect rectifications with various stakeholders.\nHandle all building defects requests, enquiries and/or complaint received from the owners and Estate Management Office after the expiry of defect liability period.\nAdvice to all stakeholders and process all applications on various consents related to Flat-for-Sales Scheme secondary market, consent to assign, and re-financing etc.\nPrepare valuation reports on all HS investment properties for reference on market rental levels and annual asset valuation.\nAssist in the sale/leasing of residential/elderly projects and other duties assigned.\n\nThe Person\n\nDegree holder in Surveying, Real Estate, Land Management, Property Management or related disciplines, with minimum 4 years relevant experience OR Diploma/Certificate holder with minimum 8 years relevant experience.\nExperience in valuation and feasibility studies, property development, town planning, sales and marketing of properties will be a definite advantage.\nPreferably with professional qualification of the RICS or HKIS or equivalent.\nStrong communication, interpersonal and organization skills.\nExcellent spoken and written English and Chinese. Good spoken Mandarin is an advantage.\nProficiency in MS Windows application, including Excel, Word, PowerPoint and Chinese Word Processing.\nCandidates with less experience will be considered as Senior Officer (Planning & Development).\n\nAttractive remuneration package will be offered to suitable candidates. To apply, please submit online application: https://careers.hkhs.com/ or send your application with full resume and reference quoted to Human Resources Manager by fax: 2882 4466.\n\nYou are welcome to visit our website www.hkhs.com to learn more about us.\nApplicants not invited for interview within 8 weeks may consider their applications unsuccessful.\n\nPersonal data provided by job applicants will be used strictly in accordance with the Housing Society\u2019s personal data policies which is available in our website and obtainable upon request. Please refer to the Policy Statement on Employment Related Data under Personal Data (Privacy) Ordinance in our website.", "employment_types": ["Full Time", "Permanent"], "selling_points": [], "locations": ["Shatin Area"], "categories": ["Admin & HR", "Clerical / Admin Staff", "Property / Real Estate", "Property Management", "Others"], "post_time": "2022-01-12T05:16:48Z", "salary": {"currency": null, "max": null, "min": null, "period": "monthly", "term": null}, "salary_visible": false, "title_keywords": ["property officer", "assistant property officer"], "responsibilities": ["valuation", "management", "advertising", "other duties", "coordination with", "market research", "logistics", "reports", "plan", "liaise with", "planning"], "requirements": {"degrees": ["certificate", "diploma", "degree holder"], "majors": ["related disciplines", "surveying"], "languages": ["english", "chinese", "mandarin"], "language_level": ["advantage", "excellent", "proficiency", "good"], "hard_skills": ["excel", "chinese word processing", "hkis", "ms windows", "word", "rics", "powerpoint"], "soft_skills": ["communication", "organization skills", "interpersonal"], "languages_combined": [{"language": "english", "language_level": ["excellent"]}, {"language": "chinese", "language_level": ["excellent", "proficiency"]}, {"language": "mandarin", "language_level": ["good", "advantage"]}]}, "experience_required": {"duration": ["minimum 4 years", "minimum 8 years"], "field": ["management", "related", "development", "marketing", "relevant experience", "planning"]}}]