[{"job_id": "100003009053794", "location_code": "hk", "company": "IMY Media Limited", "job_title": "\u63d2\u82b1\u5e2b", "description": "\u8077\u8cac :\u4e00\u822c\u6e05\u6f54\u53ca\u5712\u85dd\u5de5\u4f5c\n\u8cc7\u6b77 :\u6c92\u6709\u5b78\u6b77\u8981\u6c42; \u4e00\u822c\u7cb5\u8a9e; \u7565\u61c2\u8b80\u5beb\u4e2d\u6587\n\u5f85\u9047 :\u6bcf\u5c0f\u6642$47.00, \u4e0a\u53487\u6642\u81f3\u4e0a\u534811\u6642\u6216\u4e0b\u53482\u6642\u81f3\u4e0b\u53486\u6642, \u6bcf\u9031\u5de5\u4f5c6\u5929,\u8f2a\u4f11, \u6bcf\u5929\u5de5\u4f5c 4 \u5c0f\u6642, \u661f\u671f\u65e5\u8f2a\u4f11\n\u7533\u8acb\u9808\u77e5 :\u53ef\u50b3\u771f(24360463)\u6216\u96fb\u90f5[via APPLY NOW]\u00a0\u5c65\u6b77\u8868\u7d66\u5b9c\u5c45\u9867\u554f\u670d\u52d9\u6709\u9650\u516c\u53f8\u3002\u5982\u8981\u7d22\u53d6\u6536\u96c6\u500b\u4eba\u8cc7\u6599\u8072\u660e, \u8acb\u8207\u674e\u5c0f\u59d0(Tel:24955225)\u806f\u7d61\u3002", "employment_types": ["Part Time"], "selling_points": [], "locations": ["Tin Hau"], "categories": ["Others", "Agriculture / Forestry / Fishing", "Design", "Interior", "Others"], "post_time": "2022-01-17T07:31:32Z", "salary": {"currency": null, "max": null, "min": null, "period": "hourly", "term": null}, "salary_visible": false, "title_keywords": [], "responsibilities": [], "requirements": {"degrees": [], "majors": [], "languages": [], "language_level": [], "hard_skills": [], "soft_skills": [], "languages_combined": []}, "experience_required": {"duration": [], "field": []}}, {"job_id": "100003009053674", "location_code": "hk", "company": "PPW", "job_title": "Deputy General Manager", "description": "\n\u8077\u8cac :\u8ca0\u8cac\u63d2\u82b1\u53ca\u92b7\u552e\u82b1\u54c1\n\n\u8cc7\u6b77 :\u5c0f\u516d\u7a0b\u5ea6; 2\u5e74\u7d93\u9a57; \u4e00\u822c\u7cb5\u8a9e; \u4e00\u822c\u666e\u901a\u8a71; \u4e00\u822c\u82f1\u8a9e\n\n\u5f85\u9047 :\u6bcf\u5c0f\u6642$80.00 - $100.00, \u4e0a\u53489\u6642\u81f3\u4e0b\u534811\u6642, \u6bcf\u9031\u5de5\u4f5c5\u5929\u81f36\u5929,\u8f2a\u4f11, \u6bcf\u5929\u5de5\u4f5c 5 - 10 \u5c0f\u6642\n\n\u7533\u8acb\u9808\u77e5 :\u6c42\u8077\u8005\u53ef\u81f4\u96fb56143678\u8207\u570b\u4ed5\u5ee3\u544a\u50b3\u5a92\u6709\u9650\u516c\u53f8\u90ed\u5c0f\u59d0\u806f\u7d61\u3002\n\n", "employment_types": ["Full Time"], "selling_points": [], "locations": ["Not Specified"], "categories": ["Others", "Agriculture / Forestry / Fishing", "Building & Construction", "Others"], "post_time": "2022-01-17T07:20:00Z", "salary": {"currency": null, "max": null, "min": null, "period": "monthly", "term": null}, "salary_visible": false, "title_keywords": ["general manager"], "responsibilities": [], "requirements": {"degrees": [], "majors": [], "languages": [], "language_level": [], "hard_skills": [], "soft_skills": [], "languages_combined": []}, "experience_required": {"duration": [], "field": []}}, {"job_id": "100003009051384", "location_code": "hk", "company": "The Floristry", "job_title": "Freelance Florists (For Valentine's Day period)", "description": "\nDeputy General Manager\nToo experienced and aggressive to be just a management employee?\nEager for an opportunity to be a business minor partner?\nBasic income needed instead of taking total risk to be a sole proprietor?\nA fast expanding & reforming SME (ocadhk.com & \u62cd\u7247\u738b.com), focusing on high-to-low-end professional TV commercial production & video content marketing services, headquartered in Tai Kok Tsui, 10-mins walk from Prince Edward MTR station, with licensed Guangzhou branch serving Mainland market, is inviting experienced, energetic & dedicated key leader to join our management team.\nJob Highlight :\n\u2022 A key leader to reform a 20-person company\n\u2022 Golden opportunity of promotion to Managing Director\n\u2022 Co-founding employee may become minor partner in future\nJob Duties :\nCompany systems reformation \u2014 Establishing standards and procedures on operation & management systems; setting office policies, targets & deadlines, measuring results\n\u2022 To lead & manage company operations\n\u2022 To lead HRM, ICT, administration & accounting\n\u2022 To remotely manage Guangzhou branch\n\u2022 To plan & execute financial operation\nJob Requirements :\n\u2022 University degree holder in Business Management/Administration or relevant discipline\n\u2022 5 years or above experience in company management with all-round experiences\n\u2022 Knowledge & experience in ICT is a MUST\n\u2022 Knowledge & experience in HRM, HK labor law, basic accounting, administration\n\u2022 Extensive knowledge of eMarketing, marketing strategies, channels, and branding will be preferred\n\u2022 Experience in managing advertising or on-line marketing agency is a plus\n\u2022 Heavy responsibilities, complicated management work, flexible hours, NOT 9-5-office-job\n\u2022 Excellent command of spoken and written English, Cantonese & Mandarin\n\u2022 Occasional short trip to China\n\u2022 Immediately available or short notice is preferred\nPersonality :\n\u2022 LEADERSHIP capabilities, Ambitious\n\u2022 Work under pressure, Can-do attitude\n\u2022 Perseverance on targets & deadlines, Flexible on solutions\n\u2022 Self-motivated, Result-oriented & Highly responsible\n\u2022 Fast learner, Positive attitude towards corrective feedback, Open-minded, Active listener\n\u2022 Well-organised, prioritise multi-tasks, time-management & attention to details\n\u2022 Negotiation and presentation skills\n\u2022 Spirit of work ethics & mutual loyalty with employer\nJob Targets:\n\u2022 Maximize the profitability of the portfolio\n\u2022 Effective financial control\n\u2022 Max office efficiency & productivity\nJob Benefits:\n2-week training & exam period with $10k salary\n\u2022 10-week probation period with unlimited salary adjustment\n\u2022 Salary plus bonus after probation\nCompany Highlights :\n\u2022 An employer with top-1 portfolio in HK in a fast growing industry with great prospect\n\u2022 A 20-persons SME undergoing reformation & expansion\n\u2022 With licensed Guangzhou branch serving Mainland market\n\u2022 Highly digitalised daily operation, ICT intensive, Mac-based & paperless office\nApplication :\nInterested, please email full resume and application letter to our HR email or apply from Indeed\nPrivacy Statement :\nData collected will be used for recruitment purposes only. Personal data provided will be used strictly in accordance with the relevant data protection law and privacy policy.\n\u5de5\u4f5c\u985e\u578b: \u5168\u8077, \u9577\u5de5\n\u85aa\u916c: $20,000.00\u81f3$45,000.00(\u6bcf\u6708)\n\u6642\u9593:\n\u2022 \u65e5\u73ed\n\u2022 \u65e9\u73ed\n\u2022 \u5f48\u6027\u6642\u9593\n\u798f\u5229:\n\u2022 \u5728\u8077\u5c08\u696d\u57f9\u8a13\n\u2022 \u6649\u5347\u6a5f\u6703\n\u88dc\u5145\u85aa\u916c:\n\u2022 \u5e74\u7d42\u734e\u91d1\n\u9060\u7a0b\u5de5\u4f5c:\n\u2022 \u5426\n\n", "employment_types": ["Temporary"], "selling_points": ["Freelance Position", "Date: 11 - 14 Feb 2022", "Salary: $300/hr"], "locations": ["Sheung Wan"], "categories": ["Others", "Agriculture / Forestry / Fishing", "Design", "Others"], "post_time": "2022-01-15T13:21:59Z", "salary": {"currency": "HKD", "max": 369, "min": 290, "period": "hourly", "term": null}, "salary_visible": true, "title_keywords": [], "responsibilities": ["management", "policies", "operations", "systems", "procedures", "plan", "administration"], "requirements": {"degrees": ["university degree"], "majors": ["business"], "languages": ["cantonese", "english", "mandarin"], "language_level": ["excellent"], "hard_skills": ["business management", "max", "plus", "basic"], "soft_skills": ["flexible", "self-motivated", "negotiation", "responsible", "can-do attitude", "multi-tasks", "open-minded", "fast learner", "prioritise", "positive attitude", "presentation skills", "leadership", "attention to details", "well-organised", "active", "extensive", "result-oriented", "work under pressure"], "languages_combined": [{"language": "cantonese", "language_level": ["excellent"]}, {"language": "english", "language_level": ["excellent"]}, {"language": "mandarin", "language_level": ["excellent"]}]}, "experience_required": {"duration": ["5 years"], "field": ["management", "advertising", "agency", "marketing", "accounting", "administration"]}}, {"job_id": "100003009049674", "location_code": "hk", "company": "HKB International (HK) Company Limited", "job_title": "\u82b1\u85dd\u8a2d\u8a08\u5e2b", "description": "About Us\nThe Floristry is Hong Kong's leading floral lifestyle brand. We celebrate wild-inspired living and offer a curated assortment of flowers, homeware and lifestyle objects with a newly opened store and coffee bar in central.\u00a0\n\nWe're on the lookout for eager and passionate florists to join our friendly teams both in our studio and store for Valentine's Day period (11 - 14 Feb 2022).\n\nSalary: $300/hr + bonus\n\nThe position will include assisting in making bouquets, flower jars and general day-to-day florist duties.\n\nAPPLY\n\nInterested candidates please submit your CV by clicking Apply Now!\n\n*Due to the amount of applications we receive, we are not able to reply to every one. Unfortunately if you do not hear back from us, your application has not been successful.", "employment_types": ["Full Time"], "selling_points": [], "locations": ["Tsim Sha Tsui"], "categories": ["Others", "Agriculture / Forestry / Fishing", "Building & Construction", "Others"], "post_time": "2022-01-14T09:03:43Z", "salary": {"currency": null, "max": null, "min": null, "period": "monthly", "term": null}, "salary_visible": false, "title_keywords": [], "responsibilities": ["hr", "teams"], "requirements": {"degrees": [], "majors": [], "languages": [], "language_level": [], "hard_skills": [], "soft_skills": ["passionate", "friendly"], "languages_combined": []}, "experience_required": {"duration": [], "field": []}}, {"job_id": "100003009045625", "location_code": "hk", "company": "\u78a7\u7464\u7da0\u8272\u96c6\u5718", "job_title": "\u6500\u6a39\u54e1\u898b\u7fd2\u751f", "description": "\n\u8077\u8cac :\u8ca0\u8cac\u4fdd\u9bae\u82b1,\u9bae\u82b1\uff0c\u4e7e\u82b1,\u591a\u8089\u76c6\u683d,\u82b1\u7403,\u5a5a\u6176\u82b1\u7c43\uff0c\u7bc0\u65e5\u82b1\u675f\uff0c\u958b\u696d\u82b1\u7c43\u7b49\u88fd\u4f5c\uff0c\u92b7\u552e\u53ca\u5f8c\u671f\u7dad\u8b77\n\n\u8cc7\u6b77 :\u6c92\u6709\u5b78\u6b77\u8981\u6c42; 4\u5e746\u500b\u6708\u7d93\u9a57; \u826f\u597d\u7cb5\u8a9e; \u4e00\u822c\u666e\u901a\u8a71; \u826f\u597d\u82f1\u8a9e; \u61c2\u8b80\u5beb\u4e2d\u6587; \u61c2\u8b80\u5beb\u82f1\u6587; \u6709\u9152\u5e97\uff0c\u82b1\u5e97\u5de5\u4f5c\u76f8\u95dc\u7d93\u9a57\n\n\u5f85\u9047 :\u6bcf\u6708$13,000 - $16,000, \u4e2d\u534812\u6642\u81f3\u4e0b\u534810\u6642, \u6bcf\u9031\u5de5\u4f5c6\u5929,\u8f2a\u4f11, \u6bcf\u5929\u5de5\u4f5c 9 \u5c0f\u6642\n\n\u7533\u8acb\u9808\u77e5 :\u6c42\u8077\u8005\u53ef\u50b3\u771f(21918611)\u6216\u96fb\u90f5(Apply Now)\u5c65\u6b77\u8868\u7d66\u6e2f\u85dd\u570b\u969b (\u9999\u6e2f) \u6709\u9650\u516c\u53f8\u3002\u5982\u8981\u7d22\u53d6\u6536\u96c6\u500b\u4eba\u8cc7\u6599\u8072\u660e, \u8acb\u8207\u674e\u5c0f\u59d0(Tel:55732199)\u806f\u7d61\u3002\n\n", "employment_types": ["Full Time", "Permanent"], "selling_points": ["\u898b\u7fd2\u671f\u5f8c\uff0c\u53ef\u7372\u8a8d\u53ef\u6500\u6a39\u54e1\u7684\u5c08\u696d\u8cc7\u683c", "\u5fc5\u9808\u6301\u6709\u5e73\u5b89\u54ad\u53ca\u5efa\u9020\u696d\u5de5\u4eba\u8a3b\u518a\u8b49", "\u71b1\u8877\u5f9e\u4e8b\u6a39\u6728\u8b77\u990a\u7684\u5de5\u4f5c"], "locations": ["Lai Chi Kok"], "categories": ["Others", "Agriculture / Forestry / Fishing", "Sciences, Lab, R&D", "Environmental Science / Waste Management", "Others"], "post_time": "2022-01-13T08:13:43Z", "salary": {"currency": null, "max": null, "min": null, "period": "monthly", "term": null}, "salary_visible": false, "title_keywords": [], "responsibilities": [], "requirements": {"degrees": [], "majors": [], "languages": [], "language_level": [], "hard_skills": [], "soft_skills": [], "languages_combined": []}, "experience_required": {"duration": [], "field": []}}, {"job_id": "100003009045188", "location_code": "hk", "company": "Amgen Asia Holding Limited", "job_title": "Sr Biopharmaceutical Rep - General Medicine", "description": "\u6500\u6a39\u54e1\u898b\u7fd2\u751f\n\n\u8077\u8cac\n- \u9700\u6236\u5916\u5de5\u4f5c\uff0c\u5354\u52a9\u8655\u7406\u65e5\u5e38\u4e00\u822c\u5712\u85dd\u5de5\u4f5c\u5305\u62ec\u7a2e\u690d\u3001\u4fee\u526a\u53ca\u6253\u8349\n- \u53c3\u8207\u4fee\u6a39\u3001\u79fb\u9664\u6a39\u6728\u53ca\u6e05\u7406\u73fe\u5834\u7b49\u5de5\u4f5c\n- \u5b8c\u6210 \u4e0a\u53f8\u6307\u6d3e \u5176\u4ed6\u7684 \u5de5\u4f5c\n- \u6bcf\u661f\u671f \u516d\u5929\u5de5\u4f5c\n\n\u5165\u8077\u8981\u6c42\n- \u9999\u6e2f\u6c38\u4e45\u6027\u5c45\u6c11\n- \u672c\u6e2f\u8cc7\u6b77\u67b6\u69cb\u7b2c\u4e09\u81f3\u7b2c\u56db\u7d1a\u7684\u6a39\u6728\u5de5\u4f5c\u53ca\u6500\u6a39\u8ab2\u7a0b\u7684\u7562\u696d\u751f\n- \u672a\u66fe\u64c1\u6709\u7372\u8a8d\u53ef\u6500\u6a39\u54e1\u7684\u5c08\u696d\u8cc7\u683c\n- \u6301\u6709\u5e73\u5b89\u54ad\u53ca\u5efa\u9020\u696d\u5de5\u4eba\u8a3b\u518a\u8b49\n- \u5177\u8cac\u4efb\u611f\u3001\u4e3b\u52d5\u6027\n- \u71b1\u8877\u5f9e\u4e8b\u6a39\u6728\u8b77\u990a\u7684\u5de5\u4f5c\n\n\u7533\u8acb\u65b9\u6cd5:\u8acb\u6309\u7db2\u4e0a\u7533\u8acb\u905e\u4ea4\u500b\u4eba\u5c65\u6b77\u8868\uff0c \u5c65\u6b77\u8868\u4e0a\u9808\u5beb\u660e\u73fe\u6642\u53ca\u9810\u671f\u85aa\u91d1 \u3002\n\n\u6536\u96c6\u7684\u500b\u4eba\u8cc7\u6599\u5c07\u50c5\u7528\u65bc\u62db\u8058\u76ee\u7684\u3002\n\n", "employment_types": ["Full Time"], "selling_points": [], "locations": ["Not Specified"], "categories": ["Others", "Agriculture / Forestry / Fishing", "Building & Construction", "Others"], "post_time": "2022-01-13T07:24:16Z", "salary": {"currency": null, "max": null, "min": null, "period": "monthly", "term": null}, "salary_visible": false, "title_keywords": [], "responsibilities": [], "requirements": {"degrees": [], "majors": [], "languages": [], "language_level": [], "hard_skills": [], "soft_skills": [], "languages_combined": []}, "experience_required": {"duration": [], "field": []}}, {"job_id": "100003009047067", "location_code": "hk", "company": "The University of Hong Kong", "job_title": "Tenure-Track Assistant Professor in Architectural Design ( 509120)", "description": "\nAccountabilities to the District Sales Manager\n\u2022 Maximizes sales of Amgen\u2019s products in territory\n\u2022 Achieves sales targets\n\u2022 Delivers key messages\n\u2022 Collaborates with manager to implement agreed POA in line with marketing strategy\n\u2022 Identifies and establishes high quality customer relationships and internal collaboration\nKnows in-depth knowledge of the product(s), market , stakeholders and competitors\n\u2022 Works within agreed budgets\n\u2022 Understands the patient journey\n\u2022 Lives the Amgen Values\nResponsibilities\n\u2022 Collaborates with manager to develop and implement territory POA and key account plans . Achieve POA\n\u2022 Evaluates progress vs. plan monthly and agrees to course corrections with manager\nContributes to Cluster/Territory Teams Collaborates (Medical Affairs/Key Account Manager, etc.) to agree on key account plan objectives/responsibilities\n\u2022 Engages with peers and District Manager to learn best practices\n\u2022 Demonstrates an understanding of industry and healthcare trends, of how retail practices, clinics and hospitals operate.\n\u2022 Identify and gather competitive information with sound knowledge of the competitive landscape\n\u2022 Follows through on customer commitments and requests in a timely fashion. Actively gains customer insights\n\u2022 Reports customer activity in the CRM system and ensures customer profiles are kept up-to-date\n\u2022 Demonstrates an understanding of Amgen Performance 4 selling platform to satisfy customer and Amgen needs\n\u2022 Operates within the agreed expense budget aligned with POA priorities\n\u2022 Seeks advise and assistance to organize activities\n\u2022 Continuously develops and improves product knowledge, communication and selling skills through self-learning and active participation in agreed training programs. Drives own development\nQualifications\n\nThe knowledge and skills necessary to perform the duties of this position are typically acquired through the following combination of education, experience and knowledge, or the equivalent.\n\nMinimum Requirements\n\u2022 Minimum 3 to 5 years of experience in the pharmaceutical industry in a sales-related job\nBasic knowledge of and experience in a hospital environment (not for specialist Sales Reps)\nSome experience with computer systems (CRM databases and MS Office)\n\u2022 Fluency in local language, both in oral and written communication\n\u2022 Relevant local legal qualification\n\u2022 Clear understanding of the importance if compliance practices\nPreferred Requirements\nBachelor\u2019s degree in life science or (bio) medical sciences\n\u2022 Knowledge of Customer Relation Management principles\n\u2022 Exposure to interactions with various disciplines and organizational levels\n\u2022 Exposure to project management principles\n\u2022 Experience in one or more of the following customer groups Orthopaedics, Endocrinologists, Rheumatologists, Cardiovascular surgeons or Cardiologists.\nDesired behaviours\n\nCore Knowledge Demonstrates an understanding of the sales cycles, hospital environment & industry environment and applies this knowledge in day to day practice. Knows Amgen/competitor product s and services.\n\nProblem-Solving Breaks issues down into major components that reflect basic understanding of the relevant issues.\n\nGoal Setting & Tracking Holds self accountable for achieving established goals.\n\nTailored messages & Influencing skills Interactions with others (customers, peer, manager, etc.) is open, honest and cooperative.\n\nCompelling Messages Able to deliver the selling message in a clear and assertive way . Appropriately uses Amgen\u2019s Marketing and Sales tools to support the sales process.\n\nCall Planning and Execution Develops pre-call plans and uses plans in customer interactions. Demonstrates basic time management skills in terms of prioritizing activities and completing work in a timely manner; meets deadlines.\n\nRigorous Planning & Execution Able to seek out information, both on specific issues and on a more general, or territory level, and to use this information to analyze, identify implications and set priorities. Ensure actions are inline with strategies\n\nJoin Us\n\nIf you're seeking a career where you can truly make a difference in the lives of others, a career where you can work at the absolute forefront of biotechnology with the top minds in the field, you'll find it at Amgen.\n\nAmgen, a biotechnology pioneer, discovers, develops and delivers innovative human therapeutics. Our medicines have helped millions of patients in the fight against cancer, kidney disease, rheumatoid arthritis and other serious illnesses.\n\nAs an organization dedicated to improving the quality of life for people around the world, Amgen fosters an inclusive environment of diverse, ethical, committed and highly accomplished people who respect each other but compete intensely to win. Together, we live the Amgen values as we continue advancing science to serve patients.\n\n", "employment_types": ["Full Time"], "selling_points": ["supervise thesis for postgraduate students", "teach lecture courses or seminars", "demonstrate an established record of research"], "locations": ["Pok Fu Lam"], "categories": ["Others", "Agriculture / Forestry / Fishing", "Education", "Lecturer / Professor", "Tutor / Instructor"], "post_time": "2022-01-14T02:14:00Z", "salary": {"currency": null, "max": null, "min": null, "period": "monthly", "term": null}, "salary_visible": false, "title_keywords": ["assistant professor"], "responsibilities": ["budget", "customer insights", "teams", "develop", "communication", "reports", "plan", "plans"], "requirements": {"degrees": ["degree", "bachelor"], "majors": ["science"], "languages": [], "language_level": [], "hard_skills": ["basic", "problem-solving", "computer systems", "project management", "goal", "make", "databases", "ms office"], "soft_skills": ["oral", "assertive", "time management skills", "organizational", "problem-solving", "cooperative", "timely", "accountable", "communication", "project management", "clear", "diverse", "committed", "ethical", "honest", "innovative", "prioritizing"], "languages_combined": []}, "experience_required": {"duration": ["minimum 3 to 5 years"], "field": ["pharmaceutical", "related"]}}, {"job_id": "100003009046227", "location_code": "hk", "company": "Baguio Green Group Limited", "job_title": "Arborist Trainee", "description": "Applications are invited for appointment as\u00a0Tenure-Track Assistant Professor in Architectural Design in the Department of Architecture\u00a0(Ref. 509120), to commence on September 1, 2022 or as soon as possible thereafter, on a three-year fixed-term basis, with the possibility of renewal and consideration for tenure before the expiry of a second three-year fixed-term contract.\n\nThe Department of Architecture is internationally recognised as one of the world's best architectural schools. \u00a0Design thinking is at the core of its values and the Department prides itself on providing an active and dynamic research environment. \u00a0The scholars and professionals who constitute the teaching staff of the Department represent a diversity of research interests. \u00a0The scale and breadth of case studies in the region offers a potential portfolio of exciting research projects and a laboratory structure offers opportunities to pool efforts, cross disciplinary boundaries and develop forums for exchange. \u00a0The Department offers both undergraduate and postgraduate programmes in an intense and demanding environment where staff members take an active part in shaping the Department's culture through both teaching and administrative responsibilities. \u00a0The promising and energetic community of students come from Hong Kong, Mainland China, Asia, and across the world. Information about the Department can be obtained at\u00a0http://arch.hku.hk.\n\nApplicants should possess a postgraduate and professional degree in Architecture. \u00a0Preference will be given to those holding professional qualifications and/or a Ph.D. degree in Architecture or an affiliated discipline, and to those who have experience in teaching and practicing design in a multidisciplinary context. \u00a0They should demonstrate an established record of research, teaching and critical practice in the form of design projects or creative work, and the capacity to integrate different elements of their research and practice into teaching. \u00a0\u00a0As the Department moves towards strengthening international links with academic institutions and innovators in design throughout Asia and the world, applicants who have a record of building such partnerships are encouraged to apply. \u00a0Strong writing skills and grant-writing experience are also desirable, as staff are expected to pursue funding opportunities to advance their research.\n\nThe appointee will be required to conduct research, teach architectural design studios at undergraduate and postgraduate levels, and supervise thesis for postgraduate students. \u00a0In addition, he/she may be required to teach lecture courses and/or seminars in one or more of the following subject areas: architectural history and theory, building technology, and sustainable architecture.\n\nFor enquiries about the post, please write to Dr. Eric H. Schuldenfrei, Head of the Department of Architecture\u00a0[via APPLY NOW]\n\nA highly competitive salary commensurate with qualifications and experience will be offered, in addition to annual leave and medical benefits.\u00a0 At current rates, salaries tax does not exceed 15% of gross income.\u00a0 The appointment will attract a contract-end gratuity and University contribution to a retirement benefits scheme, totalling up to 15% of basic salary.\u00a0 Housing benefits will be provided as applicable.\n\nThe University only accepts online application for the above post.\u00a0 Applicants should apply online and upload an up-to-date C.V., a cover letter, a one-page teaching statement, a one-page statement on advancing diversity and inclusion, contact information of three senior academics who are familiar with the applicant's teaching background and experience, and a research and teaching portfolio\u00a0(less than 20MB, 20 pages maximum).\u00a0 Closes\u00a0January 31, 2022.\n\n\u6709\u610f\u7533\u8acb\u8005\u8acb \u6309 APPLY NOW\u7533\u8acb\n\n", "employment_types": ["Full Time", "Permanent"], "selling_points": ["12+AL, Birthday Leave, 5-day work", "Friendly Working Environment", "Passion on Arboricultural Field"], "locations": ["Lai Chi Kok"], "categories": ["Others", "Agriculture / Forestry / Fishing", "Sciences, Lab, R&D", "Environmental Science / Waste Management", "Others"], "post_time": "2022-01-13T10:01:41Z", "salary": {"currency": null, "max": null, "min": null, "period": "monthly", "term": null}, "salary_visible": false, "title_keywords": ["trainee"], "responsibilities": ["research projects", "conduct research", "design", "develop", "architecture"], "requirements": {"degrees": ["degree"], "majors": ["architecture", "design"], "languages": [], "language_level": [], "hard_skills": ["dynamic", "professional qualifications", "writing skills", "exchange"], "soft_skills": ["active", "creative", "writing skills", "dynamic", "energetic"], "languages_combined": []}, "experience_required": {"duration": [], "field": ["research", "teaching", "writing", "design"]}}, {"job_id": "100003009045145", "location_code": "hk", "company": "The Hong Kong Jockey Club", "job_title": "\u99ac\u623f\u96dc\u52d9\u54e1 (\u6e05\u6f54\u53ca\u6a5f\u68b0\u64cd\u4f5c)", "description": "Responsibilities:\n\n\nAssist Arborists to carry out tree survey/inventory, inspection and tree risk assessments for projects\nBe responsible for outdoor work, site inspections and project administrative works\nHandle any ad-hoc tasks assigned by superiors.\n\nRequirements:\n\nHold a recognized qualification at Hong Kong Qualification Framework level 3 or above in Arboriculture, landscape management, tree management and tree work programs.\nWilling to learn, multi-tasking, self-motivated with positive working attitude\nGood command of both written and spoken English & Chinese and excellent communication skills\nProficient in MS Office and familiar with AUTOCAD is a plus\nFresh graduates are welcome. Immediate available is preferable\nInterested parties please send your full resume with availability, current and expected salary to us.\n\n\n*Personal data collected will be used for recruitment purposes only.", "employment_types": ["Full Time"], "selling_points": ["\u8ca0\u8cac\u6e05\u6f54\u99ac\u623f", "\u4e2d\u4e09\u7a0b\u5ea6; 1\u5e74\u7d93\u9a57", "\u5177\u642c\u904b\u53ca\u6e05\u6f54\u76f8\u95dc\u5de5\u4f5c\u7d93\u9a57\u512a\u5148"], "locations": ["Not Specified"], "categories": ["Others", "Agriculture / Forestry / Fishing", "Others"], "post_time": "2022-01-13T07:18:29Z", "salary": {"currency": null, "max": null, "min": null, "period": "monthly", "term": null}, "salary_visible": false, "title_keywords": [], "responsibilities": ["outdoor work", "inventory", "ad-hoc tasks", "inspection", "site inspections"], "requirements": {"degrees": [], "majors": [], "languages": ["english", "chinese"], "language_level": ["excellent", "good command"], "hard_skills": ["plus", "autocad", "ms office"], "soft_skills": ["communication skills", "self-motivated", "willing to learn", "positive working attitude", "multi-tasking"], "languages_combined": [{"language": "english", "language_level": ["excellent", "good command"]}, {"language": "chinese", "language_level": ["excellent", "good command"]}]}, "experience_required": {"duration": [], "field": []}}, {"job_id": "100003009045527", "location_code": "hk", "company": "Hong Kong Island Landscape Co Ltd", "job_title": "\u5712\u85dd\u670d\u52d9\u5927\u4f7f", "description": "Responsibilities:\n\n\nOversee arboriculture related projects, carry out tree inspection, tree risk assessment and arboriculture works\nPrepare project documents for submission, liaise with external and internal parties to follow up all aspects of projects\nBe responsible for outdoor work, site inspections and project administrative works\nPerform ad-hoc tasks as required\n\nRequirements:\n\n\nHold a recognized qualification at Hong Kong Qualification Framework level 3 or above in Arboriculture, Tree Management or Landscape Management or equivalent\nPossess qualification of Certified Arborist of The International Society of Arboriculture; or Technician Member of the Arboriculture Association of the United Kingdom; or Accredited Arborist of the Hong Kong Institute of Landscape Architects or equivalent\nCompleted and passed recognized training programs in tree risk assessment such as Tree Risk Assessment Qualification by the International Society of Arboriculture or Professional Tree Inspection by Lantra Awards\nHave at least 3 years of relevant post-professional qualification work experience\nProficiency in MS Office applications, familiar with AUTOCAD is preferred\nGood command of both written and spoken English & Chinese and excellent communication skills\nWell organized, multi-tasking, self-motivated with positive working attitude\nCandidate with less experience may consider as Assistant Arborist\nInterested parties please send your full resume with availability, current and expected salary to us.\n\n\n*Personal data collected will be used for recruitment purposes only.", "employment_types": ["Full Time"], "selling_points": [], "locations": ["Wan Chai"], "categories": ["Others", "Agriculture / Forestry / Fishing", "Building & Construction", "Others"], "post_time": "2022-01-13T08:01:32Z", "salary": {"currency": null, "max": null, "min": null, "period": "monthly", "term": null}, "salary_visible": false, "title_keywords": [], "responsibilities": ["outdoor work", "ad-hoc tasks", "inspection", "project documents", "site inspections", "liaise with", "internal parties"], "requirements": {"degrees": [], "majors": [], "languages": ["english", "chinese"], "language_level": ["excellent", "good command"], "hard_skills": ["autocad", "ms office"], "soft_skills": ["communication skills", "self-motivated", "well organized", "positive working attitude", "multi-tasking"], "languages_combined": [{"language": "english", "language_level": ["excellent", "good command"]}, {"language": "chinese", "language_level": ["excellent", "good command"]}]}, "experience_required": {"duration": ["at least 3 years"], "field": []}}, {"job_id": "100003009043648", "location_code": "hk", "company": "Planter Pro Limited", "job_title": "\u690d\u7269\u8b77\u7406\u5de5\u4eba Plant Caregiver", "description": "Applications are invited for appointment as\u00a0Tenure-Track Assistant Professor in Architectural Environmental Technology in the Department of Architecture\u00a0(Ref. 509119), to commence on September 1, 2022 or as soon as possible thereafter, on a three-year fixed-term basis, with the possibility of renewal and consideration for tenure before the expiry of a second three-year fixed-term contract.\n\nThe Department of Architecture is internationally recognised as one of the world's best architectural schools. \u00a0Design thinking is at the core of its values and the Department prides itself on providing an active and dynamic research environment. \u00a0The scholars and professionals who constitute the teaching staff of the Department represent a diversity of research interests. \u00a0The scale and breadth of case studies in the region offers a potential portfolio of exciting research projects and a laboratory structure offers opportunities to pool efforts, cross disciplinary boundaries and develop forums for exchange. \u00a0The Department offers both undergraduate and postgraduate programmes in an intense and demanding environment where staff members take an active part in shaping the Department's culture through both teaching and administrative responsibilities. \u00a0The promising and energetic community of students come from Hong Kong, Mainland China, Asia, and across the world. Information about the Department can be obtained at\u00a0http://arch.hku.hk.\n\nApplicants should possess a postgraduate and professional degree in the relevant field. \u00a0Preference will be given to those holding professional qualifications and/or a Ph.D. degree in Architecture, Environmental Engineering, or an affiliated discipline, and to those who have experience in teaching and practicing in a multidisciplinary context. \u00a0Applicants should demonstrate an established record of teaching and research in sustainable design strategies with a focus on fully integrated human, social, environmental, and economic sustainability in the constructed environment. \u00a0They should have experience in developing technical projects related to environmental performance as well as the ability to innovatively address climate change through speculative design research. \u00a0Candidates with a Ph.D. in the history of science or materials, history and theory of architecture with a focus on environmental humanities, or science and technology studies, are welcome to apply. \u00a0As the Department moves towards strengthening international links with academic institutions and innovators in design throughout Asia and the world, applicants who have a record of building such partnerships are encouraged to apply. \u00a0Strong writing skills and grant-writing experience are also desirable, as staff are expected to pursue funding opportunities to advance their research.\n\nThe appointee will be required to conduct research, teach relevant postgraduate and undergraduate courses, and lead a research team on related studies. \u00a0He/She may be required to teach studios, lecture courses, or seminars, in one or more of the following subject areas: design studios, history of the environment, and building technology.\n\nFor enquiries about the post, please write to Dr. Eric H. Schuldenfrei, Head of the Department of Architecture\u00a0[via APPLY NOW]\n\nA highly competitive salary commensurate with qualifications and experience will be offered, in addition to annual leave and medical benefits.\u00a0 At current rates, salaries tax does not exceed 15% of gross income.\u00a0 The appointment will attract a contract-end gratuity and University contribution to a retirement benefits scheme, totalling up to 15% of basic salary.\u00a0 Housing benefits will be provided as applicable.\n\nThe University only accepts online application for the above post.\u00a0 Applicants should apply online and upload an up-to-date C.V., a cover letter, a one-page teaching statement, a one-page statement on advancing diversity and inclusion, contact information of three senior academics who are familiar with the applicant's teaching background and experience, and a research and teaching portfolio\u00a0(less than 20MB, 20 pages maximum).\u00a0 Closes\u00a0January 31, 2022.\n\n\u6709\u610f\u7533\u8acb\u8005\u8acb\u6309 APPLY NOW\u7533\u8acb \u00a0\u00a0\u00a0\n\n", "employment_types": ["Full Time"], "selling_points": [], "locations": ["Not Specified"], "categories": ["Others", "Agriculture / Forestry / Fishing", "Others"], "post_time": "2022-01-13T01:18:38Z", "salary": {"currency": null, "max": null, "min": null, "period": "monthly", "term": null}, "salary_visible": false, "title_keywords": [], "responsibilities": ["research projects", "developing", "design", "develop", "conduct research", "architecture"], "requirements": {"degrees": ["degree"], "majors": ["environmental engineering", "architecture"], "languages": [], "language_level": [], "hard_skills": ["professional qualifications", "writing skills", "dynamic", "focus", "exchange"], "soft_skills": ["active", "writing skills", "dynamic", "focus", "energetic"], "languages_combined": []}, "experience_required": {"duration": [], "field": ["research", "engineering", "related", "developing", "design", "environmental", "writing", "teaching"]}}, {"job_id": "100003009046949", "location_code": "hk", "company": "Fairview Park Property Management Limited", "job_title": "\u5712\u85dd\u96dc\u5de5 (\u517c\u8077)", "description": "\n\u8077\u8cac :\u5230\u5ba2\u6236\u516c\u53f8, \u690d\u7269\u6dcb\u6c34, \u62b9\u8449, \u4fee\u526a\u53ca\u4e00\u822c\u5712\u85dd\u4fdd\u990a\u5de5\u4f5c\n\n\u8cc7\u6b77 :\u6c92\u6709\u5b78\u6b77\u8981\u6c42;\u00a0\u826f\u597d\u7cb5\u8a9e,\u00a0\u61c2\u95b1\u8b80\u53ca\u66f8\u5beb\u4e2d\u6587,\u00a0\u61c2\u5f97\u8207\u5ba2\u6236\u6e9d\u901a, \u6709\u79ae\u8c8c, \u52e4\u596e, \u5c0d\u690d\u7269\u6709\u8208\u8da3\n\n\u5f85\u9047 :\u6bcf\u6708$11,000\u00a0 \u6709\u4ea4\u901a\u6d25\u8cbc,\u00a0\u5e74\u7d42\u734e\u91d1,\u00a0\u751f\u65e5\u5229\u662f,\u00a0\u661f\u671f\u4e00\u81f3\u516d: 08:00 \u81f3 17:00,\u00a0\u9700\u8f2a\u73ed\u7533\u8acb\u9808\u77e5 :\u6c42\u8077\u8005\u53ef\u81f4\u96fb26573910\u8207\u5229\u751f\u5712\u6709\u9650\u516c\u53f8\u5289\u5c0f\u59d0\u806f\u7d61\u3002", "employment_types": ["Part Time"], "selling_points": [], "locations": ["Yuen Long"], "categories": ["Others", "Agriculture / Forestry / Fishing", "Property / Real Estate", "Others", "Others"], "post_time": "2022-01-14T01:50:24Z", "salary": {"currency": null, "max": null, "min": null, "period": "hourly", "term": null}, "salary_visible": false, "title_keywords": [], "responsibilities": [], "requirements": {"degrees": [], "majors": [], "languages": [], "language_level": [], "hard_skills": [], "soft_skills": [], "languages_combined": []}, "experience_required": {"duration": [], "field": []}}, {"job_id": "100003009045135", "location_code": "hk", "company": "The Hong Kong Jockey Club", "job_title": "\u9ad8\u7d1a\u8dd1\u9053\u8b77\u990a\u54e1(\u6a5f\u68b0)", "description": "\u8077\u8cac :\u8ca0\u8cac\u5c4b\u82d1\u5167\u5712\u85dd\u5de5\u4f5c\uff0c\u5305\u62ec\u7a2e\u690d\u3001\u9664\u8349\u3001\u9664\u87f2\u3001\u704c\u6e89\u3001\u65bd\u80a5\u3001\u4fee\u526a\u690d\u7269\u53ca\u6a39\u6728\u7b49\n\u8cc7\u6b77 :\u5c0f\u516d\u7a0b\u5ea6; \u826f\u597d\u7cb5\u8a9e; \u7565\u61c2\u8b80\u5beb\u4e2d\u6587; \u5177\u76f8\u95dc\u5de5\u4f5c\u7d93\u9a57\u512a\u5148\uff0c\u52e4\u52de\uff0c\u4e0d\u6015\u592a\u967d\u66ec\n\u5f85\u9047 :\u6bcf\u5c0f\u6642$60.00 - $65.00, \u4e0a\u53488\u6642\u81f3\u4e0b\u53484\u6642\u534a\u6216\u4e0a\u53488\u6642\u81f3\u4e2d\u534812\u6642, \u6bcf\u9031\u5de5\u4f5c2\u5929\u81f34\u5929,\u8f2a\u4f11, \u6bcf\u5929\u5de5\u4f5c 4 - 8.5 \u5c0f\u6642, \u6bcf\u661f\u671f\u5de5\u4f5c\u4e0d\u591a\u65bc18\u5c0f\u6642\n\u7533\u8acb\u9808\u77e5 :\u6c42\u8077\u8005\u53ef\u6309 APPLY NOW\u7533\u8acb\u6216\u81f4\u96fb24711301\u8207\u9326\u7d89\u82b1\u5712\u7269\u696d\u7ba1\u7406\u6709\u9650\u516c\u53f8\u694a\u5c0f\u59d0\u806f\u7d61\u3002", "employment_types": ["Full Time"], "selling_points": ["\u8ca0\u8cac\u7dad\u4fee\u53ca\u4fdd\u990a\u5404\u985e\u8dd1\u9053\u4fdd\u990a\u6a5f\u68b0", "\u4e2d\u4e09\u7a0b\u5ea6; 5\u5e74\u7d93\u9a57;", "\u826f\u597d\u7cb5\u8a9e"], "locations": ["Wan Chai Area"], "categories": ["Others", "Agriculture / Forestry / Fishing", "Others"], "post_time": "2022-01-13T07:16:26Z", "salary": {"currency": null, "max": null, "min": null, "period": "monthly", "term": null}, "salary_visible": false, "title_keywords": [], "responsibilities": [], "requirements": {"degrees": [], "majors": [], "languages": [], "language_level": [], "hard_skills": [], "soft_skills": [], "languages_combined": []}, "experience_required": {"duration": [], "field": []}}, {"job_id": "100003009038701", "location_code": "hk", "company": "WAYFOONG NURSERY SCHOOL", "job_title": "\u5e7c\u7a1a\u5712\u6559\u5e2b**", "description": "Summary\nIndustry:\nReal Estate / Property Management\nJob Category / Function:\nProperty / Estate Management / Security / Gardener\nJob Category / Function:\nProperty / Estate Management / Security / Others\nJob Position Level:\n-\nEmployment Term:\n-\nMin. Edu. Level Req:\n-\nTotal Working Exp:\n-\nSalary(HKD):\n21,000\nLocation:\nOutlying Islands / Lantau Island\nBenefits:\nDental Insurance\nMeal Allowance\nMedical Insurance\nPerformance Bonus\nTransportation Allowance\n\n\u6709\u610f\u7533\u8acb\u8005\u8acb \u6309 APPLY NOW\u7533\u8acb\n\n", "employment_types": ["Full Time"], "selling_points": [], "locations": ["Mong Kok"], "categories": ["Others", "Agriculture / Forestry / Fishing", "Building & Construction", "Others"], "post_time": "2022-01-11T07:39:46Z", "salary": {"currency": null, "max": null, "min": null, "period": "monthly", "term": null}, "salary_visible": false, "title_keywords": [], "responsibilities": ["management"], "requirements": {"degrees": [], "majors": [], "languages": [], "language_level": [], "hard_skills": [], "soft_skills": [], "languages_combined": []}, "experience_required": {"duration": [], "field": []}}, {"job_id": "100003009041685", "location_code": "hk", "company": "Christian Family Service Centre", "job_title": "\u5712\u4e01(SRGARDENER-SKGS)", "description": "\n\u8077\u8cac :\u4e00\u822c\u5e7c\u7a1a\u5712\u6559\u5e2b\u5de5\u4f5c, \u6e96\u5099\u6559\u6750, \u6559\u5c0e\u53ca\u7167\u98672-6\u6b72\u5e7c\u5152, \u8a08\u5283\u8ab2\u5ba4\u6d3b\u52d5\u53ca\u65e5\u7a0b\u3002\u6e96\u50f1\u54e1\u9700\u81ea\u9858\u9032\u884c\u300a\u6027\u7f6a\u884c\u5b9a\u7f6a\u7d00\u9304\u67e5\u6838\u300b\u3002\n\n\u8cc7\u6b77 :\u5c08\u4e0a\u6559\u80b2\uff1a\u526f\u5b78\u4f4d; \u4e00\u822c\u7cb5\u8a9e; \u4e00\u822c\u666e\u901a\u8a71; \u4e00\u822c\u82f1\u8a9e; \u7565\u61c2\u8b80\u5beb\u4e2d\u6587; \u7565\u61c2\u8b80\u5beb\u82f1\u6587; \u61c2\u96fb\u8166\u6587\u66f8\u8655\u7406; \u5177\u6709\u57fa\u672c\u96fb\u8166\u64cd\u4f5c\u77e5\u8b58; \u5fc5\u9808\u6301\u6709\u6559\u80b2\u5c40\u6559\u5e2b\u8a3b\u518a\u8b49\u660e\n\n\u5f85\u9047 :\u6bcf\u6708$22,970 - $40,515 (\u8996\u4e4e\u7d93\u9a57\u800c\u5b9a), \u6709\u7259\u79d1\u798f\u5229, \u91ab\u7642\u798f\u5229, \u9032\u4fee\u6d25\u8cbc \u53ca\u4f9b\u81b3\u98df, \u4e00\u81f3\u4e94:\u4e0a\u53488\u6642\u534a\u81f3\u4e0b\u53485\u664215\u5206\u53ca\u516d:\u4e0a\u53489\u6642\u81f3\u4e0b\u53481\u6642,\u6bcf\u9031\u5de5\u4f5c5-5\u5929\u534a,\u8f2a\u73ed,\u6bcf\u5929\u5de5\u4f5c 8 - 8.5 \u5c0f\u6642,\u661f\u671f\u516d\u9577\u77ed\u9031\n\n\u7533\u8acb\u9808\u77e5 :\u6c42\u8077\u8005\u53ef\u96fb\u90f5(Apply Now)\u5c65\u6b77\u8868\u7d66\u6ed9\u8c50\u5e7c\u5152\u5b78\u6821\u3002\u5982\u8981\u7d22\u53d6\u6536\u96c6\u500b\u4eba\u8cc7\u6599\u8072\u660e, \u8acb\u8207\u694a\u5c0f\u59d0(Fax:22694528)\u806f\u7d61\u3002\n\n", "employment_types": ["Full Time"], "selling_points": [], "locations": ["Tseung Kwan O"], "categories": ["Others", "Agriculture / Forestry / Fishing", "Building & Construction", "Others"], "post_time": "2022-01-12T04:13:08Z", "salary": {"currency": null, "max": null, "min": null, "period": "monthly", "term": null}, "salary_visible": false, "title_keywords": [], "responsibilities": [], "requirements": {"degrees": [], "majors": [], "languages": [], "language_level": [], "hard_skills": [], "soft_skills": [], "languages_combined": []}, "experience_required": {"duration": [], "field": []}}, {"job_id": "100003009041582", "location_code": "hk", "company": "Melofield Nursery and Landscape Contractor Limited", "job_title": "\u5712\u85dd\u5de5\u4eba**", "description": "\n\u8077\u8cac :\u7ba1\u7406\u4e2d\u5fc3\u7bc4\u570d\u5167\u5916\u7684\u690d\u7269\u3001\u7167\u9867\u548c\u8b77\u7406\u4e2d\u5fc3\u5167\u7684\u690d\u7269\u3001\u82b1\u5349\u7b49\uff1b \u8ca0\u8cac\u4e2d\u5fc3\u7684\u6e05\u6f54\u5de5\u4f5c\u53ca\u65bc\u4e2d\u5fc3\u5167\u5354\u52a9\u8655\u7406\u53ca\u5206\u985e\u56de\u6536\u7269\uff1b\u57f7\u884c\u4e0a\u53f8\u6240\u6307\u6d3e\u4e4b\u5176\u4ed6\u6709\u95dc\u4efb\u52d9\n\n\u8cc7\u6b77 :\u5c0f\u516d\u7a0b\u5ea6; 2\u5e74\u7d93\u9a57; \u4e00\u822c\u7cb5\u8a9e; \u61c2\u8b80\u5beb\u4e2d\u6587; \u6709\u6e05\u6f54\u5de5\u4f5c\u7d93\u9a57\u512a\u5148\n\n\u5f85\u9047 :\u6bcf\u6708$14,810\u6216\u4ee5\u4e0a (\u8996\u4e4e\u7d93\u9a57\u800c\u5b9a), \u6709\u5e74\u504714\u5929, \u5728\u8077\u57f9\u8a13, \u91ab\u7642\u798f\u5229, \u4e0a\u53488\u6642\u81f3\u4e0b\u53486\u6642, \u6bcf\u9031\u5de5\u4f5c5\u5929\u81f35\u5929\u534a,\u8f2a\u73ed,\u8f2a\u4f11, \u6bcf\u5929\u5de5\u4f5c 8 - 9 \u5c0f\u6642, \u6bcf\u9031\u5e73\u5747\u5de5\u4f5c49.5\u5c0f\u6642(\u5305\u62ec\u7528\u81b3\u6642\u9593)\n\n\u7533\u8acb\u9808\u77e5 :\u96fb\u90f5(Apply Now)/\u90f5\u5bc4(\u89c0\u5858\u7fe0\u5c4f\u90533\u865f10\u6a13\u4eba\u529b\u8cc7\u6e90\u90e8)\u5c65\u6b77\u8868\u7d66\u57fa\u7763\u6559\u5bb6\u5ead\u670d\u52d9\u4e2d\u5fc3\u3002\u7d22\u53d6\u6536\u96c6\u500b\u4eba\u8cc7\u6599\u8072\u660e,\u8acb\u806f\u7d61\u4eba\u529b\u8cc7\u6e90\u90e8(Fax:21112785)\n\n", "employment_types": ["Full Time"], "selling_points": [], "locations": ["Sai Kung"], "categories": ["Others", "Agriculture / Forestry / Fishing", "Building & Construction", "Others"], "post_time": "2022-01-12T04:04:08Z", "salary": {"currency": null, "max": null, "min": null, "period": "monthly", "term": null}, "salary_visible": false, "title_keywords": [], "responsibilities": [], "requirements": {"degrees": [], "majors": [], "languages": [], "language_level": [], "hard_skills": [], "soft_skills": [], "languages_combined": []}, "experience_required": {"duration": [], "field": []}}, {"job_id": "100003009041258", "location_code": "hk", "company": "Happy Lemon HK Limited", "job_title": "\u5168\u8077\u6d17\u7897\u54e1", "description": "\n\u8077\u8cac :\u4e00\u822c\u5712\u85dd\u5de5\u4f5c, \u5305\u62ec\u7a2e\u690d, \u9664\u87f2\u9664\u8349, \u6f86\u6c34, \u65bd\u80a5\u7b49, \u5712\u85dd\u6a5f\u68b0\u64cd\u4f5c\u7b49\n\n\u8cc7\u6b77 :\u6c92\u6709\u5b78\u6b77\u8981\u6c42; \u826f\u597d\u7cb5\u8a9e; \u4e00\u822c\u666e\u901a\u8a71; \u61c2\u8b80\u5beb\u4e2d\u6587; \u719f\u6089\u5712\u85dd\u6a5f\u68b0\u64cd\u4f5c\n\n\u5f85\u9047 :\u6bcf\u6708$12,000 - $13,000, \u4e0a\u53488\u6642\u81f3\u4e0b\u53485\u6642, \u6bcf\u9031\u5de5\u4f5c6\u5929,\u8f2a\u4f11\n\n\u7533\u8acb\u9808\u77e5 :\u6c42\u8077\u8005\u53ef\u81f4\u96fb25720048\u8207\u7d93\u7def\u5712\u85dd\u6709\u9650\u516c\u53f8\u9673\u5148\u751f\u806f\u7d61\u3002\n\n", "employment_types": ["Full Time"], "selling_points": [], "locations": ["Yau Tsim Mong Area"], "categories": ["Others", "Agriculture / Forestry / Fishing", "Hospitality / F & B", "Food & Beverage", "Others"], "post_time": "2022-01-12T03:40:01Z", "salary": {"currency": null, "max": null, "min": null, "period": "monthly", "term": null}, "salary_visible": false, "title_keywords": ["\u5168\u8077\u6d17\u7897\u54e1"], "responsibilities": [], "requirements": {"degrees": [], "majors": [], "languages": [], "language_level": [], "hard_skills": [], "soft_skills": [], "languages_combined": []}, "experience_required": {"duration": [], "field": []}}, {"job_id": "100003009046070", "location_code": "hk", "company": "Ocean Park Corporation", "job_title": "\u7dad\u751f\u7cfb\u7d71\u64cd\u4f5c\u54e1 / Life Support Operations Operator", "description": "\n\u8077\u8cac :\u8655\u7406\u6e05\u6f54\u9910\u5ef3\u7684\u9910\u5177\u3001\u7897\u789f\u3001\u7528\u5177, \u9700\u64cd\u4f5c\u6d17\u7897\u6a5f, \u6642\u523b\u4fdd\u6301\u5de5\u4f5c\u5d17\u4f4d\u53ca\u9910\u5177\u6e05\u6f54\u885b\u751f, \u6309\u7167\u516c\u53f8\u6d41\u7a0b\u6d17\u7897\u6e05\u6f54\n\n\u8cc7\u6b77 :\u6c92\u6709\u5b78\u6b77\u8981\u6c42; \u4e00\u822c\u7cb5\u8a9e; \u4e00\u822c\u666e\u901a\u8a71; \u4e00\u822c\u82f1\u8a9e\n\n\u5f85\u9047 :\u6bcf\u6708$14,000, \u6709\u6bcf\u6708\u52e4\u5de5\u734e\u91d1$1000, \u6bcf\u6708\u4f9b\u81b3\u98df, \u6bcf\u6708\u8d85\u6642\u5de5\u4f5c\u88dc\u5047 \u53ca\u6bcf\u6708\u8d85\u6642\u5de5\u4f5c\u6d25\u8cbc, \u4e0b\u53481\u6642\u81f3\u4e0b\u534810\u6642\u534a, \u6bcf\u9031\u5de5\u4f5c5\u5929\u81f36\u5929,\u8f2a\u73ed,\u8f2a\u4f11\n\n\u7533\u8acb\u9808\u77e5 :\u6c42\u8077\u8005\u8acb\u89aa\u81e8\u592a\u5b50\u5f4c\u6566\u9053750\u865f\u59cb\u5275\u4e2d\u5fc32\u6a13232\u865f\u8216\u5feb\u6a02\u6ab8\u6aac\u9999\u6e2f\u6709\u9650\u516c\u53f8\u9762\u8a66\u3002\u67e5\u8a62\u8acb\u81f4\u96fb95021990\u8207\u9673\u5148\u751f\u806f\u7d61\u3002\n\n", "employment_types": ["Full Time", "Contract"], "selling_points": ["\u6cf5\u623f\u8a2d\u65bd\u64cd\u4f5c", "\u52d5\u7269\u6c34\u6c60\u5faa\u74b0\u3001\u904e\u6ffe\u3001\u6bba\u83cc\u3001\u51b7\u51cd\u52a0\u71b1\u7cfb\u7d71", "\u6c34\u548c\u7a7a\u6c23\u8cea\u7d20\u63a7\u5236"], "locations": ["Aberdeen"], "categories": ["Others", "Agriculture / Forestry / Fishing", "Engineering", "Electrical / Electronics", "Mechanical"], "post_time": "2022-01-13T09:31:56Z", "salary": {"currency": null, "max": null, "min": null, "period": "monthly", "term": null}, "salary_visible": false, "title_keywords": ["operations", "operator"], "responsibilities": [], "requirements": {"degrees": [], "majors": [], "languages": [], "language_level": [], "hard_skills": [], "soft_skills": [], "languages_combined": []}, "experience_required": {"duration": [], "field": []}}, {"job_id": "100003009035739", "location_code": "hk", "company": "Easy Living Consultant Limited", "job_title": "\u82b1\u738b", "description": "\u5de5\u4f5c\u6027\u8cea:\n(\u9577\u671f\u5408\u7d04)(\u6708\u85aa$12,700\u8d77\uff1b\u901a\u5bb5\u73ed\u53e6\u52a0\u7576\u503c\u6d25\u8cbc)\u00a0\n\u8ca0\u8cac\u6cf5\u623f\u8a2d\u65bd\u53ca\u52d5\u7269\u6c34\u6c60\u5faa\u74b0\u3001\u904e\u6ffe\u3001\u6bba\u83cc\u3001\u51b7\u51cd\u52a0\u71b1\u7cfb\u7d71\u4e4b\u64cd\u4f5c,\u00a0\u6c34\u548c\u7a7a\u6c23\u8cea\u7d20\u63a7\u5236\n\n\u5de5\u4f5c\u8981\u6c42:\n-\u00a0\u7121\u9700\u76f8\u95dc\u5de5\u4f5c\u7d93\u9a57,\u00a0\u5165\u8077\u5f8c\u63a5\u53d7\u5728\u8077\u57f9\u8a13\n-\u00a0\u52e4\u596e\u7a4d\u6975\u3001\u80fd\u7368\u7acb\u5de5\u4f5c\u53ca\u5177\u826f\u597d\u6e9d\u901a\u6280\u5de7\n-\u00a0\u5177\u57fa\u672c\u6a5f\u96fb\u5de5\u7a0b\u77e5\u8b58\u66f4\u4f73\n-\u00a0\u9808\u6236\u5916\u53ca\u4e8c\u5341\u56db\u5c0f\u6642\u8f2a\u73ed\n\n\u61c9\u5fb5\u8005\u53ef\u5f9e\u4ee5\u4e0b\u65b9\u6cd5\u767b\u5165\u6d77\u6d0b\u516c\u5712\u7db2\u9801\u7533\u8acb\u6b64\u8077\u4f4d\uff0chttp://careers.oceanpark.com.hk\u00a0>> \u8077\u4f4d\u7a7a\u7f3a>> \u9577\u671f\u5168\u8077\uff0c\u4ea6\u53ef\u5c07\u7c21\u55ae\u5c65\u6b77\u3001\u5e0c\u671b\u5f85\u9047\u3001\u901a\u8a0a\u5730\u5740\u3001\u806f\u7d61\u96fb\u8a71\u50b3\u771f\u81f32553 0777\u3002\n\n\u61c9\u5fb5\u8005\u5982\u5728\u516d\u661f\u671f\u5167\u672a\u7372\u9080\u8acb\u9762\u8a66\uff0c\u5c07\u4f5c\u843d\u9078\u8ad6\u3002\u6240\u6709\u6536\u96c6\u8cc7\u6599\u53ea\u4f5c\u62db\u8058\u7528\u9014 \u3002", "employment_types": ["Full Time"], "selling_points": [], "locations": ["Tsing Yi"], "categories": ["Others", "Agriculture / Forestry / Fishing", "Others"], "post_time": "2022-01-10T08:20:00Z", "salary": {"currency": null, "max": null, "min": null, "period": "monthly", "term": null}, "salary_visible": false, "title_keywords": [], "responsibilities": [], "requirements": {"degrees": [], "majors": [], "languages": [], "language_level": [], "hard_skills": [], "soft_skills": [], "languages_combined": []}, "experience_required": {"duration": [], "field": []}}, {"job_id": "100003009040841", "location_code": "hk", "company": "Casetagram Limited", "job_title": "General Manager, Taiwan", "description": "\u8077\u8cac :\u4e00\u822c\u5712\u4e01\u5de5\u4f5c\uff0c\u8ca0\u8cac\u6dcb\u6c34\uff0c\u4fee\u526a\uff0c\u7ffb\u571f\uff0c\u9664\u87f2\uff0c\u65bd\u80a5\uff0c\u6e05\u7406\u82b1\u57fa\uff0c\u7a2e\u690d\u7b49\n\u8cc7\u6b77 :\u6c92\u6709\u5b78\u6b77\u8981\u6c42; \u4e00\u822c\u7cb5\u8a9e; \u7565\u61c2\u8b80\u5beb\u4e2d\u6587\n\u5f85\u9047 :\u6bcf\u6708$11,320, \u6709\u4ea4\u901a\u6d25\u8cbc, \u4e0a\u53487\u6642\u534a\u81f3\u4e0a\u534811\u6642\u534a\u53ca\u4e0b\u53481\u6642\u81f3\u4e0b\u53485\u6642, \u6bcf\u9031\u5de5\u4f5c6\u5929,\u8f2a\u4f11, \u6bcf\u5929\u5de5\u4f5c 8 \u5c0f\u6642\n\u7533\u8acb\u9808\u77e5 :\u6c42\u8077\u8005\u53ef\u6309 APPLY NOW\u7533\u8acb", "employment_types": ["Full Time"], "selling_points": [], "locations": ["Not Specified"], "categories": ["Others", "Agriculture / Forestry / Fishing", "Building & Construction", "Others"], "post_time": "2022-01-12T03:08:49Z", "salary": {"currency": null, "max": null, "min": null, "period": "monthly", "term": null}, "salary_visible": false, "title_keywords": ["general manager"], "responsibilities": [], "requirements": {"degrees": [], "majors": [], "languages": [], "language_level": [], "hard_skills": [], "soft_skills": [], "languages_combined": []}, "experience_required": {"duration": [], "field": []}}, {"job_id": "100003009040857", "location_code": "hk", "company": "Casetagram Limited", "job_title": "General Manager, UK", "description": "\nPosition Overview & Purpose\n\u2022 CASETiFY is the fastest growing global tech accessories brand, reaching 1 in 7 millennials. We have become the publisher and platform for creativity and self-expression to connect individuals.\n\u2022 We are growing aggressively globally and we are looking for a general manager for our up-and-coming markets. This GM will be responsible for the P&L of the country in addition to partnerships and marketing. In most cases, this GM would be the first hire specifically for that country.\n\nJob Description\n\u2022 Empower CASETiFY to grow 10x in 4 years\n\u2022 Develop and execute strategies to elevate CASETiFY\u2019s brand to a household brand and be loved by millions in Taiwan\n\u2022 Identify and develop growth strategies including but not limited to key partnerships for collabs and growing the retail and wholesales businesses to drive a 9-figure sales goal\n\u2022 Test and scale other world-wide and country specific business initiatives such as our own retail store\n\u2022 Manage all country specific operations including but not limited to design, marketing, operations, finance and retail operations\n\u2022 Recruit, grow, mentor and operate the regional teams to achieve sales & business objectives\n\u2022 Initiate and drive country specific products/projects, establish frameworks to evaluate the results and proactively take necessary actions\n\u2022 Collaborate with HQ team on executing world-wide collaboration\n\u2022 Promote CASETiFY\u2019s culture and strive to create the best-in-class employee experience and regional office operational standards\n\nRequirements:\n\u2022 Worked as a leader in a remote working environment\n\u2022 Experience in building, managing and leading multiple functional units\n\u2022 Successfully managed P&L over millions of TWD\n\u2022 Number-oriented with an aptitude in decision making, problem solving, analytical skills and critical thinking\n\u2022 Evangelist and partitioner of using decision-making frameworks and standard operating procedures to communicate and drive business outcomes\n\u2022 Strong marketing and business background, with an eye for design\n\u2022 A change maker with the ability to inspire and execute\n\u2022 Passionate about growing as a team\n\u2022 Excellent interpersonal and public speaking skills\n\u2022 Native in spoken and written English\n\u2022 Experience with Direct-To-Consumer startups and acquisitions from both side of the table are big plus\n\n", "employment_types": ["Full Time"], "selling_points": [], "locations": ["Not Specified"], "categories": ["Others", "Agriculture / Forestry / Fishing", "Building & Construction", "Others"], "post_time": "2022-01-12T03:09:44Z", "salary": {"currency": null, "max": null, "min": null, "period": "monthly", "term": null}, "salary_visible": false, "title_keywords": ["general manager"], "responsibilities": ["collaborate with", "business initiatives", "operations", "teams", "design", "develop", "evaluate", "executing"], "requirements": {"degrees": [], "majors": [], "languages": ["english"], "language_level": ["native"], "hard_skills": ["problem solving", "plus", "analytical skills"], "soft_skills": ["analytical skills", "problem solving", "interpersonal", "passionate about", "decision making"], "languages_combined": [{"language": "english", "language_level": ["native"]}]}, "experience_required": {"duration": [], "field": []}}, {"job_id": "100003009040807", "location_code": "hk", "company": "Casetagram Limited", "job_title": "General Manager, Europe", "description": "\nPosition Overview & Purpose\n\u2022 CASETiFY is the fastest growing global tech accessories brand, reaching 1 in 7 millennials. We have become the publisher and platform for creativity and self-expression to connect individuals.\n\u2022 We are growing aggressively globally and we are looking for a general manager for our up-and-coming markets. This GM will be responsible for the P&L of the country in addition to partnerships and marketing. In most cases, this GM would be the first hire specifically for that country.\n\nJob Description\n\u2022 Empower CASETiFY to grow 10x in 4 years\n\u2022 Develop and execute strategies to elevate CASETiFY\u2019s brand to a household brand and be loved by millions in the UK\n\u2022 Identify and develop growth strategies including but not limited to key partnerships for collabs and growing the retail and wholesales businesses to drive a 9-figure sales goal\n\u2022 Test and scale other world-wide and country specific business initiatives such as our own retail store\n\u2022 Manage all country specific operations including but not limited to design, marketing, operations, finance and retail operations\n\u2022 Recruit, grow, mentor and operate the regional teams to achieve sales & business objectives\n\u2022 Initiate and drive country specific products/projects, establish frameworks to evaluate the results and proactively take necessary actions\n\u2022 Collaborate with HQ team on executing world-wide collaboration\n\u2022 Promote CASETiFY\u2019s culture and strive to create the best-in-class employee experience and regional office operational standards\n\nRequirements:\n\u2022 Worked as a leader in a remote working environment\n\u2022 Experience in building, managing and leading multiple functional units\n\u2022 Successfully managed P&L over millions of GBP\n\u2022 Number-oriented with an aptitude in decision making, problem solving, analytical skills and critical thinking\n\u2022 Evangelist and partitioner of using decision-making frameworks and standard operating procedures to communicate and drive business outcomes\n\u2022 Strong marketing and business background, with an eye for design\n\u2022 A change maker with the ability to inspire and execute\n\u2022 Passionate about growing as a team\n\u2022 Excellent interpersonal and public speaking skills\n\u2022 Native in spoken and written English\n\u2022 Experience with Direct-To-Consumer startups and acquisitions from both side of the table are big plus\n\n", "employment_types": ["Full Time"], "selling_points": [], "locations": ["Not Specified"], "categories": ["Others", "Agriculture / Forestry / Fishing", "Building & Construction", "Others"], "post_time": "2022-01-12T03:06:09Z", "salary": {"currency": null, "max": null, "min": null, "period": "monthly", "term": null}, "salary_visible": false, "title_keywords": ["general manager"], "responsibilities": ["collaborate with", "business initiatives", "operations", "teams", "design", "develop", "evaluate", "executing"], "requirements": {"degrees": [], "majors": [], "languages": ["english"], "language_level": ["native"], "hard_skills": ["problem solving", "plus", "analytical skills"], "soft_skills": ["analytical skills", "problem solving", "interpersonal", "passionate about", "decision making"], "languages_combined": [{"language": "english", "language_level": ["native"]}]}, "experience_required": {"duration": [], "field": []}}, {"job_id": "100003009040819", "location_code": "hk", "company": "Casetagram Limited", "job_title": "General Manager, Australia", "description": "\nPosition Overview & Purpose\n\u2022 CASETiFY is the fastest growing global tech accessories brand, reaching 1 in 7 millennials. We have become the publisher and platform for creativity and self-expression to connect individuals.\n\u2022 We are growing aggressively globally and we are looking for a general manager for our up-and-coming markets. This GM will be responsible for the P&L of the country in addition to partnerships and marketing. In most cases, this GM would be the first hire specifically for that country.\n\nJob Description\n\u2022 Empower CASETiFY to grow 10x in 4 years\n\u2022 Develop and execute strategies to elevate CASETiFY\u2019s brand to a household brand and be loved by millions in Europe\n\u2022 Identify and develop growth strategies including but not limited to key partnerships for collabs and growing the retail and wholesales businesses to drive a 9-figure sales goal\n\u2022 Test and scale other world-wide and country specific business initiatives such as our own retail store\n\u2022 Manage all country specific operations including but not limited to design, marketing, operations, finance and retail operations\n\u2022 Recruit, grow, mentor and operate the regional teams to achieve sales & business objectives\n\u2022 Initiate and drive country specific products/projects, establish frameworks to evaluate the results and proactively take necessary actions\n\u2022 Collaborate with HQ team on executing world-wide collaboration\n\u2022 Promote CASETiFY\u2019s culture and strive to create the best-in-class employee experience and regional office operational standards\n\nRequirements:\n\u2022 Worked as a leader in a remote working environment\n\u2022 Experience in building, managing and leading multiple functional units\n\u2022 Successfully managed P&L over millions of EURO\n\u2022 Number-oriented with an aptitude in decision making, problem solving, analytical skills and critical thinking\n\u2022 Evangelist and partitioner of using decision-making frameworks and standard operating procedures to communicate and drive business outcomes\n\u2022 Strong marketing and business background, with an eye for design\n\u2022 A change maker with the ability to inspire and execute\n\u2022 Passionate about growing as a team\n\u2022 Excellent interpersonal and public speaking skills\n\u2022 Native in spoken and written English\n\u2022 Experience with Direct-To-Consumer startups and acquisitions from both side of the table are big plus\n\n", "employment_types": ["Full Time"], "selling_points": [], "locations": ["Not Specified"], "categories": ["Others", "Agriculture / Forestry / Fishing", "Building & Construction", "Others"], "post_time": "2022-01-12T03:07:02Z", "salary": {"currency": null, "max": null, "min": null, "period": "monthly", "term": null}, "salary_visible": false, "title_keywords": ["general manager"], "responsibilities": ["collaborate with", "business initiatives", "operations", "teams", "design", "develop", "evaluate", "executing"], "requirements": {"degrees": [], "majors": [], "languages": ["english"], "language_level": ["native"], "hard_skills": ["problem solving", "plus", "analytical skills"], "soft_skills": ["analytical skills", "problem solving", "interpersonal", "passionate about", "decision making"], "languages_combined": [{"language": "english", "language_level": ["native"]}]}, "experience_required": {"duration": [], "field": []}}, {"job_id": "100003009040829", "location_code": "hk", "company": "Casetagram Limited", "job_title": "General Manager, South-east Asia", "description": "\nPosition Overview & Purpose\n\u2022 CASETiFY is the fastest growing global tech accessories brand, reaching 1 in 7 millennials. We have become the publisher and platform for creativity and self-expression to connect individuals.\n\u2022 We are growing aggressively globally and we are looking for a general manager for our up-and-coming markets. This GM will be responsible for the P&L of the country in addition to partnerships and marketing. In most cases, this GM would be the first hire specifically for that country.\n\nJob Description\n\u2022 Empower CASETiFY to grow 10x in 4 years\n\u2022 Develop and execute strategies to elevate CASETiFY\u2019s brand to a household brand and be loved by millions in Australia\n\u2022 Identify and develop growth strategies including but not limited to key partnerships for collabs and growing the retail and wholesales businesses to drive a 9-figure sales goal\n\u2022 Test and scale other world-wide and country specific business initiatives such as our own retail store\n\u2022 Manage all country specific operations including but not limited to design, marketing, operations, finance and retail operations\n\u2022 Recruit, grow, mentor and operate the regional teams to achieve sales & business objectives\n\u2022 Initiate and drive country specific products/projects, establish frameworks to evaluate the results and proactively take necessary actions\n\u2022 Collaborate with HQ team on executing world-wide collaboration\n\u2022 Promote CASETiFY\u2019s culture and strive to create the best-in-class employee experience and regional office operational standards\n\nRequirements:\n\u2022 Worked as a leader in a remote working environment\n\u2022 Experience in building, managing and leading multiple functional units\n\u2022 Successfully managed P&L over millions of AUD\n\u2022 Number-oriented with an aptitude in decision making, problem solving, analytical skills and critical thinking\n\u2022 Evangelist and partitioner of using decision-making frameworks and standard operating procedures to communicate and drive business outcomes\n\u2022 Strong marketing and business background, with an eye for design\n\u2022 A change maker with the ability to inspire and execute\n\u2022 Passionate about growing as a team\n\u2022 Excellent interpersonal and public speaking skills\n\u2022 Native in spoken and written English\n\u2022 Experience with Direct-To-Consumer startups and acquisitions from both side of the table are big plus\n\n", "employment_types": ["Full Time"], "selling_points": [], "locations": ["Not Specified"], "categories": ["Others", "Agriculture / Forestry / Fishing", "Building & Construction", "Others"], "post_time": "2022-01-12T03:07:54Z", "salary": {"currency": null, "max": null, "min": null, "period": "monthly", "term": null}, "salary_visible": false, "title_keywords": ["general manager"], "responsibilities": ["collaborate with", "business initiatives", "operations", "teams", "design", "develop", "evaluate", "executing"], "requirements": {"degrees": [], "majors": [], "languages": ["english"], "language_level": ["native"], "hard_skills": ["problem solving", "plus", "analytical skills"], "soft_skills": ["analytical skills", "problem solving", "interpersonal", "passionate about", "decision making"], "languages_combined": [{"language": "english", "language_level": ["native"]}]}, "experience_required": {"duration": [], "field": []}}, {"job_id": "100003009038006", "location_code": "hk", "company": "Hong Kong Disneyland", "job_title": "\u5712\u85dd\u52a9\u7406 - \u5168\u8077 (Ref:769004BR)", "description": "\nPosition Overview & Purpose\n\u2022 CASETiFY is the fastest growing global tech accessories brand, reaching 1 in 7 millennials. We have become the publisher and platform for creativity and self-expression to connect individuals.\n\u2022 We are growing aggressively globally and we are looking for a general manager for our up-and-coming markets. This GM will be responsible for the P&L of the country in addition to partnerships and marketing. In most cases, this GM would be the first hire specifically for that country.\n\nJob Description\n\u2022 Empower CASETiFY to grow 10x in 4 years\n\u2022 Develop and execute strategies to elevate CASETiFY\u2019s brand to a household brand and be loved by millions in South-east Asia\n\u2022 Identify and develop growth strategies including but not limited to key partnerships for collabs and growing the retail and wholesales businesses to drive a 9-figure sales goal\n\u2022 Test and scale other world-wide and country specific business initiatives such as our own retail store\n\u2022 Manage all country specific operations including but not limited to design, marketing, operations, finance and retail operations\n\u2022 Recruit, grow, mentor and operate the regional teams to achieve sales & business objectives\n\u2022 Initiate and drive country specific products/projects, establish frameworks to evaluate the results and proactively take necessary actions\n\u2022 Collaborate with HQ team on executing world-wide collaboration\n\u2022 Promote CASETiFY\u2019s culture and strive to create the best-in-class employee experience and regional office operational standards\n\nRequirements:\n\u2022 Worked as a leader in a remote working environment\n\u2022 Experience in building, managing and leading multiple functional units\n\u2022 Successfully managed P&L over millions of Thai Baht\n\u2022 Number-oriented with an aptitude in decision making, problem solving, analytical skills and critical thinking\n\u2022 Evangelist and partitioner of using decision-making frameworks and standard operating procedures to communicate and drive business outcomes\n\u2022 Strong marketing and business background, with an eye for design\n\u2022 A change maker with the ability to inspire and execute\n\u2022 Passionate about growing as a team\n\u2022 Excellent interpersonal and public speaking skills\n\u2022 Native in spoken and written English\n\u2022 Experience with Direct-To-Consumer startups and acquisitions from both side of the table are big plus\n\n", "employment_types": ["Full Time", "Permanent"], "selling_points": ["\u4e00\u822c\u5712\u85dd\u4fdd\u990a\u8b77\u7406\u5de5\u4f5c", "\u4e00\u822c\u5de5\u4f5c\u6642\u9593\uff1a\u65e9\u66f4(07:30\u81f317:30) \uff1b\u901a\u5bb5\u66f4(23:30\u81f3\u7fcc\u65e509:30)", "\u9808\u8f2a\u73ed\u5de5\u4f5c"], "locations": ["Lantau Island"], "categories": ["Others", "Agriculture / Forestry / Fishing", "Hospitality / F & B", "Others", "Integrated Resort / Casino"], "post_time": "2022-01-11T04:32:07Z", "salary": {"currency": null, "max": null, "min": null, "period": "monthly", "term": null}, "salary_visible": false, "title_keywords": [], "responsibilities": ["collaborate with", "business initiatives", "operations", "teams", "design", "develop", "evaluate", "executing"], "requirements": {"degrees": [], "majors": [], "languages": ["thai", "english"], "language_level": ["native"], "hard_skills": ["problem solving", "plus", "analytical skills"], "soft_skills": ["analytical skills", "problem solving", "interpersonal", "passionate about", "decision making"], "languages_combined": [{"language": "thai", "language_level": []}, {"language": "english", "language_level": ["native"]}]}, "experience_required": {"duration": [], "field": []}}, {"job_id": "100003009046002", "location_code": "hk", "company": "Maxgrand Limited", "job_title": "Draftsman (5 days work)", "description": "\u5de5\u4f5c\u6982\u8981:\u8ca0\u8cac\u70ba\u5ea6\u5047\u5340\u5167\u6240\u6709\u5730\u65b9\u5305\u62ec\u6a02\u5712\u3001\u5ea6\u5047\u5340\u5169\u9593\u9152\u5e97\u3001\u516c\u5171\u4ea4\u901a\u4ea4\u532f\u8655\u3001\u8fea\u6b23\u6e56\u6d3b\u52d5\u4e2d\u5fc3\u63d0\u4f9b\u5712\u85dd\u670d\u52d9\u3002\n\n\u6b64\u8077\u4f4d\u9700\u8981\u8f2a\u73ed\u5de5\u4f5c\u3002\n\u4e00\u822c\u5de5\u4f5c\u6642\u9593\uff1a\u65e9\u66f4(07:30\u81f317:30) \uff1b\u901a\u5bb5\u66f4(23:30\u81f3\u7fcc\u65e509:30)\n\u8077\u8cac:\n\u4e00\u822c\u5712\u85dd\u4fdd\u990a\u8b77\u7406\u5de5\u4f5c\n\u57fa\u672c\u689d\u4ef6:\n\u9808\u8f2a\u73ed\u5de5\u4f5c\n\u5176\u4ed6\u8cc7\u8a0a:\u5de5\u4f5c\u6642\u9593\uff1a\u6211\u5011\u7684\u4e3b\u984c\u6a02\u5712\u53ca\u5ea6\u5047\u5340\u9152\u5e97\u5168\u5e74365\u5929\u904b\u4f5c\uff0c\u56e0\u6b64\u672c\u8077\u4f4d\u9700\u8981\u6309\u7167\u7531\u516c\u53f8\u7de8\u8a02\u7684\u66f4\u8868\u8f2a\u73ed\u3002\n", "employment_types": ["Full Time", "Permanent"], "selling_points": ["experience with  AutoCAD", "electrical / electronic / product field", "double pay, medical, special bonus"], "locations": ["Kwai Tsing Area"], "categories": ["Others", "Agriculture / Forestry / Fishing", "Engineering", "Draftsman", "Electrical / Electronics"], "post_time": "2022-01-13T18:55:11Z", "salary": {"currency": null, "max": null, "min": null, "period": "monthly", "term": null}, "salary_visible": false, "title_keywords": ["draftsman"], "responsibilities": [], "requirements": {"degrees": [], "majors": [], "languages": [], "language_level": [], "hard_skills": [], "soft_skills": [], "languages_combined": []}, "experience_required": {"duration": [], "field": []}}, {"job_id": "100003009038002", "location_code": "hk", "company": "Hong Kong Disneyland", "job_title": "\u6a39\u85dd\u5e2b - \u5168\u8077 (Ref:900779BR)", "description": "\u00a0Requirements:\n\nF.5\u00a0or above.\n1 year or above experience with AutoCAD.\n\u00a0Fresh\u00a0Graduate will be considered.\nGood computer skills on MS Word, Excel.\nProficient in PC skills, MS Office\nHardworking, responsible\nResponsibilities:\n\nPrepare drawings and calculations for the sales team.\nAssist in generate lighting measurement data for sales team.\n\n\u00a0We offer attractive\u00a0remuneration package\u00a0with\u00a0double pay,\u00a0bonus\u00a0and\u00a0medical \u00a0insurance\u00a0to the right candidate. Please send your CV with expected salary stated\u00a0by clicking APPLY NOW.", "employment_types": ["Full Time", "Permanent"], "selling_points": ["\u4e00\u822c\u5de5\u4f5c\u6642\u9593\uff1a\u65e9\u66f4(07:30\u81f317:15) \u6216 (08:00\u81f317:45)\uff1b\u901a\u5bb5\u66f4", "\u9032\u884c\u6a39\u6728\u98a8\u96aa\u8a55\u4f30\u3001\u6a39\u6728\u666e\u67e5\u3001\u652f\u63f4\u6a39\u6728\u4fee\u526a\u6216\u79fb\u9664\u5de5\u4f5c", "\u5177\u6709\u4e09\u5e74\u6216\u4ee5\u4e0a\u6a39\u85dd\u5de5\u4f5c\u7d93\u9a57"], "locations": ["Lantau Island"], "categories": ["Others", "Agriculture / Forestry / Fishing", "Sciences, Lab, R&D", "Environmental Science / Waste Management", "Hospitality / F & B", "Integrated Resort / Casino"], "post_time": "2022-01-11T04:31:19Z", "salary": {"currency": null, "max": null, "min": null, "period": "monthly", "term": null}, "salary_visible": false, "title_keywords": [], "responsibilities": ["measurement", "sales team", "data", "drawings"], "requirements": {"degrees": ["fresh graduate"], "majors": [], "languages": [], "language_level": [], "hard_skills": ["excel", "autocad", "computer skills", "pc skills", "ms office", "ms word"], "soft_skills": ["hardworking", "responsible"], "languages_combined": []}, "experience_required": {"duration": ["1 year"], "field": []}}, {"job_id": "100003009056913", "location_code": "hk", "company": "Easy Living Consultant Limited", "job_title": "\u6e05\u6f54\u517c\u5712\u85dd\u5de5\u4eba", "description": "\u8077\u8cac :\u4e00\u822c\u6e05\u6f54\u53ca\u5712\u85dd\u5de5\u4f5c\n\u8cc7\u6b77 :\u6c92\u6709\u5b78\u6b77\u8981\u6c42; \u4e00\u822c\u7cb5\u8a9e; \u7565\u61c2\u8b80\u5beb\u4e2d\u6587\n\u5f85\u9047 :\u6bcf\u5c0f\u6642$47.00, \u4e0a\u53487\u6642\u81f3\u4e0a\u534811\u6642\u6216\u4e0b\u53482\u6642\u81f3\u4e0b\u53486\u6642, \u6bcf\u9031\u5de5\u4f5c6\u5929,\u8f2a\u4f11, \u6bcf\u5929\u5de5\u4f5c 4 \u5c0f\u6642, \u661f\u671f\u65e5\u8f2a\u4f11\n\u7533\u8acb\u9808\u77e5 :\u53ef\u50b3\u771f(24360463)\u6216\u96fb\u90f5[via APPLY NOW]\u00a0\u5c65\u6b77\u8868\u7d66\u5b9c\u5c45\u9867\u554f\u670d\u52d9\u6709\u9650\u516c\u53f8\u3002\u5982\u8981\u7d22\u53d6\u6536\u96c6\u500b\u4eba\u8cc7\u6599\u8072\u660e, \u8acb\u8207\u674e\u5c0f\u59d0(Tel:24955225)\u806f\u7d61\u3002", "employment_types": ["Part Time"], "selling_points": [], "locations": ["Tsing Yi"], "categories": ["Others", "Agriculture / Forestry / Fishing", "Others"], "post_time": "2022-01-18T06:48:47Z", "salary": {"currency": null, "max": null, "min": null, "period": "hourly", "term": null}, "salary_visible": false, "title_keywords": [], "responsibilities": [], "requirements": {"degrees": [], "majors": [], "languages": [], "language_level": [], "hard_skills": [], "soft_skills": [], "languages_combined": []}, "experience_required": {"duration": [], "field": []}}, {"job_id": "100003009046168", "location_code": "hk", "company": "Baguio Green Group Limited", "job_title": "Arborist II", "description": "Responsibilities:\n\n\nOversee arboriculture related projects, carry out tree inspection, tree risk assessment and arboriculture works\nPrepare project documents for submission, liaise with external and internal parties to follow up all aspects of projects\nBe responsible for outdoor work, site inspections and project administrative works\nPerform ad-hoc tasks as required\n\nRequirements:\n\n\nHold a recognized qualification at Hong Kong Qualification Framework level 3 or above in Arboriculture, Tree Management or Landscape Management or equivalent\nPossess qualification of Certified Arborist of The International Society of Arboriculture; or Technician Member of the Arboriculture Association of the United Kingdom; or Accredited Arborist of the Hong Kong Institute of Landscape Architects or equivalent\nCompleted and passed recognized training programs in tree risk assessment such as Tree Risk Assessment Qualification by the International Society of Arboriculture or Professional Tree Inspection by Lantra Awards\nHave at least 3 years of relevant post-professional qualification work experience\nProficiency in MS Office applications, familiar with AUTOCAD is preferred\nGood command of both written and spoken English & Chinese and excellent communication skills\nWell organized, multi-tasking, self-motivated with positive working attitude\nCandidate with less experience may consider as Assistant Arborist\nInterested parties please send your full resume with availability, current and expected salary to us.\n\n\n*Personal data collected will be used for recruitment purposes only.", "employment_types": ["Full Time", "Permanent"], "selling_points": ["14+AL, Birthday Leave, 5-day work", "Friendly Working Environment", "Passion on Arboricultural Field"], "locations": ["Lai Chi Kok"], "categories": ["Others", "Agriculture / Forestry / Fishing", "Sciences, Lab, R&D", "Environmental Science / Waste Management", "Others"], "post_time": "2022-01-13T09:49:04Z", "salary": {"currency": null, "max": null, "min": null, "period": "monthly", "term": null}, "salary_visible": false, "title_keywords": ["arborist ii"], "responsibilities": ["outdoor work", "ad-hoc tasks", "inspection", "project documents", "site inspections", "liaise with", "internal parties"], "requirements": {"degrees": [], "majors": [], "languages": ["english", "chinese"], "language_level": ["excellent", "good command"], "hard_skills": ["autocad", "ms office"], "soft_skills": ["communication skills", "self-motivated", "well organized", "positive working attitude", "multi-tasking"], "languages_combined": [{"language": "english", "language_level": ["excellent", "good command"]}, {"language": "chinese", "language_level": ["excellent", "good command"]}]}, "experience_required": {"duration": ["at least 3 years"], "field": []}}, {"job_id": "100003009047043", "location_code": "hk", "company": "The University of Hong Kong", "job_title": "Tenure-Track Assistant Professor in Architectural Environmental Technology(509119)", "description": "Applications are invited for appointment as\u00a0Tenure-Track Assistant Professor in Architectural Environmental Technology in the Department of Architecture\u00a0(Ref. 509119), to commence on September 1, 2022 or as soon as possible thereafter, on a three-year fixed-term basis, with the possibility of renewal and consideration for tenure before the expiry of a second three-year fixed-term contract.\n\nThe Department of Architecture is internationally recognised as one of the world's best architectural schools. \u00a0Design thinking is at the core of its values and the Department prides itself on providing an active and dynamic research environment. \u00a0The scholars and professionals who constitute the teaching staff of the Department represent a diversity of research interests. \u00a0The scale and breadth of case studies in the region offers a potential portfolio of exciting research projects and a laboratory structure offers opportunities to pool efforts, cross disciplinary boundaries and develop forums for exchange. \u00a0The Department offers both undergraduate and postgraduate programmes in an intense and demanding environment where staff members take an active part in shaping the Department's culture through both teaching and administrative responsibilities. \u00a0The promising and energetic community of students come from Hong Kong, Mainland China, Asia, and across the world. Information about the Department can be obtained at\u00a0http://arch.hku.hk.\n\nApplicants should possess a postgraduate and professional degree in the relevant field. \u00a0Preference will be given to those holding professional qualifications and/or a Ph.D. degree in Architecture, Environmental Engineering, or an affiliated discipline, and to those who have experience in teaching and practicing in a multidisciplinary context. \u00a0Applicants should demonstrate an established record of teaching and research in sustainable design strategies with a focus on fully integrated human, social, environmental, and economic sustainability in the constructed environment. \u00a0They should have experience in developing technical projects related to environmental performance as well as the ability to innovatively address climate change through speculative design research. \u00a0Candidates with a Ph.D. in the history of science or materials, history and theory of architecture with a focus on environmental humanities, or science and technology studies, are welcome to apply. \u00a0As the Department moves towards strengthening international links with academic institutions and innovators in design throughout Asia and the world, applicants who have a record of building such partnerships are encouraged to apply. \u00a0Strong writing skills and grant-writing experience are also desirable, as staff are expected to pursue funding opportunities to advance their research.\n\nThe appointee will be required to conduct research, teach relevant postgraduate and undergraduate courses, and lead a research team on related studies. \u00a0He/She may be required to teach studios, lecture courses, or seminars, in one or more of the following subject areas: design studios, history of the environment, and building technology.\n\nFor enquiries about the post, please write to Dr. Eric H. Schuldenfrei, Head of the Department of Architecture\u00a0[via APPLY NOW]\n\nA highly competitive salary commensurate with qualifications and experience will be offered, in addition to annual leave and medical benefits.\u00a0 At current rates, salaries tax does not exceed 15% of gross income.\u00a0 The appointment will attract a contract-end gratuity and University contribution to a retirement benefits scheme, totalling up to 15% of basic salary.\u00a0 Housing benefits will be provided as applicable.\n\nThe University only accepts online application for the above post.\u00a0 Applicants should apply online and upload an up-to-date C.V., a cover letter, a one-page teaching statement, a one-page statement on advancing diversity and inclusion, contact information of three senior academics who are familiar with the applicant's teaching background and experience, and a research and teaching portfolio\u00a0(less than 20MB, 20 pages maximum).\u00a0 Closes\u00a0January 31, 2022.\n\n\u6709\u610f\u7533\u8acb\u8005\u8acb\u6309 APPLY NOW\u7533\u8acb \u00a0\u00a0\u00a0\n\n", "employment_types": ["Full Time"], "selling_points": [], "locations": ["Aberdeen"], "categories": ["Others", "Agriculture / Forestry / Fishing", "Education", "Lecturer / Professor", "Tutor / Instructor"], "post_time": "2022-01-14T02:10:06Z", "salary": {"currency": null, "max": null, "min": null, "period": "monthly", "term": null}, "salary_visible": false, "title_keywords": ["assistant professor"], "responsibilities": ["research projects", "developing", "design", "develop", "conduct research", "architecture"], "requirements": {"degrees": ["degree"], "majors": ["environmental engineering", "architecture"], "languages": [], "language_level": [], "hard_skills": ["professional qualifications", "writing skills", "dynamic", "focus", "exchange"], "soft_skills": ["active", "writing skills", "dynamic", "focus", "energetic"], "languages_combined": []}, "experience_required": {"duration": [], "field": ["research", "engineering", "related", "developing", "design", "environmental", "writing", "teaching"]}}, {"job_id": "100003009043860", "location_code": "hk", "company": "HKR International Ltd", "job_title": "\u4e09\u7d1a/\u4e8c\u7d1a\u8349\u576a\u8b77\u7406\u54e1", "description": "Summary\nIndustry:\nReal Estate / Property Management\nJob Category / Function:\nProperty / Estate Management / Security / Gardener\nJob Category / Function:\nProperty / Estate Management / Security / Others\nJob Position Level:\n-\nEmployment Term:\n-\nMin. Edu. Level Req:\n-\nTotal Working Exp:\n-\nSalary(HKD):\n21,000\nLocation:\nOutlying Islands / Lantau Island\nBenefits:\nDental Insurance\nMeal Allowance\nMedical Insurance\nPerformance Bonus\nTransportation Allowance\n\n\u6709\u610f\u7533\u8acb\u8005\u8acb \u6309 APPLY NOW\u7533\u8acb\n\n", "employment_types": ["Full Time"], "selling_points": ["Dental Insurance", "Meal Allowance", "Medical Insurance"], "locations": ["Not Specified"], "categories": ["Others", "Agriculture / Forestry / Fishing", "Property / Real Estate", "Others", "Others"], "post_time": "2022-01-13T02:12:09Z", "salary": {"currency": null, "max": null, "min": null, "period": "monthly", "term": null}, "salary_visible": false, "title_keywords": [], "responsibilities": ["management"], "requirements": {"degrees": [], "majors": [], "languages": [], "language_level": [], "hard_skills": [], "soft_skills": [], "languages_combined": []}, "experience_required": {"duration": [], "field": []}}, {"job_id": "100003009034673", "location_code": "hk", "company": "Greenfingers Florist Company Limited", "job_title": "\u82b1\u85dd\u5e2b", "description": "\u5de5\u4f5c\u6982\u8981:\u8ca0\u8cac\u5ea6\u5047\u5340\u5167\u5305\u62ec\u6a02\u5712\u3001\u9152\u5e97\u3001\u516c\u5171\u4ea4\u901a\u4ea4\u532f\u8655\u3001\u8fea\u6b23\u6e56\u6d3b\u52d5\u4e2d\u5fc3\u7684\u5712\u85dd\u670d\u52d9\u3002\n\n\u6b64\u8077\u4f4d\u9700\u8981\u8f2a\u73ed\u5de5\u4f5c\u3002\n\u4e00\u822c\u5de5\u4f5c\u6642\u9593\uff1a\u65e9\u66f4(07:30\u81f317:15) \u6216 (08:00\u81f317:45)\uff1b\u901a\u5bb5\u66f4(11:30\u81f3\u7fcc\u65e509:15)\u8077\u8cac:\u2022 \u9032\u884c\u6a39\u6728\u98a8\u96aa\u8a55\u4f30\u3001\u6a39\u6728\u666e\u67e5\u3001\u652f\u63f4\u6a39\u6728\u4fee\u526a\u6216\u79fb\u9664\u5de5\u4f5c\n\u2022 \u9808\u4f7f\u7528\u5c08\u696d\u5100\u5668\u6e2c\u91cf\u6a39\u6728\n\u2022 \u9700\u8981\u6236\u5916\u5de5\u4f5c\uff0c\u6a39\u4e0a\u5de5\u4f5c\uff08\u6a39\u6728\u4fee\u526a\u548c\u79fb\u9664\u7b49\uff09\u548c\u8aee\u8a62\u5de5\u4f5c\uff08\u6a39\u6728\u98a8\u96aa\u8a55\u4f30\u548c\u6a39\u6728\u666e\u67e5\u7b49\uff09\u57fa\u672c\u689d\u4ef6:\u2022 \u6c42\u8077\u8005\u6301\u6709ISA\u8a3b\u518a\u6a39\u85dd\u5e2b\u6216\u8a3b\u518a\u6500\u6a39\u5e2b\u6216\u6a39\u6728\u98a8\u96aa\u8a55\u4f30\u8cc7\u683c\u53ef\u7372\u512a\u5148\u8003\u616e\n\u2022 \u5177\u6709\u4e09\u5e74\u6216\u4ee5\u4e0a\u6a39\u85dd\u5de5\u4f5c\u7d93\u9a57\n\u2022 \u5177\u5099\u826f\u597d\u5b89\u5168\u53ca\u6b63\u78ba\u6a39\u6728\u4fee\u526a\u77e5\u8b58\n\u2022 \u5177\u64cd\u4f5c\u96fb\u52d5\u5de5\u5177\u4e4b\u7d93\u9a57\uff0c\u4f8b\u5982\u96fb\u92f8\u3001\u4fee\u679d\u526a\u5200\u7b49\n\u2022 \u9808\u8655\u7406\u9ad8\u7a7a\u5de5\u4f5c\u53ca\u6309\u8f2a\u73ed\u5236\u5ea6\u4e0d\u5b9a\u6642\u6578\u4e0a\u73ed\n\u2022 \u6301\u6709\u99d5\u99db\u57f7\u7167(\u985e\u52252) \u7372\u512a\u5148\u8003\u616e\n\u2022 \u826f\u597d\u7d44\u7e54\u80fd\u529b\u548c\u6e9d\u901a\u6280\u5de7\n\u2022 \u61c2\u5f97\u4f7f\u7528Microsoft Office\u7522\u54c1\uff1aWord\u3001Excel\u548cOutlook\n\u2022 \u5982\u7d93\u99db\u8c50\u5bcc\u8005\u6703\u7372\u8003\u616e\u70ba\u9ad8\u7d1a\u6a39\u85dd\u6280\u8853\u54e1\u5176\u4ed6\u8cc7\u8a0a:\u5de5\u4f5c\u6642\u9593\uff1a\u00a0\u6211\u5011\u7684\u4e3b\u984c\u6a02\u5712\u53ca\u5ea6\u5047\u5340\u9152\u5e97\u5168\u5e74365\u5929\u904b\u4f5c\uff0c\u56e0\u6b64\u672c\u8077\u4f4d\u9700\u8981\u6309\u7167\u7531\u516c\u53f8\u7de8\u8a02\u7684\u66f4\u8868\u8f2a\u73ed\uff0c\u4e26\u9700\u8981\u5728\u661f\u671f\u516d\u3001\u661f\u671f\u65e5\u53ca\u516c\u773e\u5047\u671f\u5de5\u4f5c\u3002\n\n\u905e\u4ea4\u7533\u8acb\uff1a\u00a0\u8acb\u9ede\u6483\u4e0b\u65b9\u7684\u300c\u7533\u8acb\u5de5\u4f5c\u300d\u9023\u7d50\uff0c\u6709\u95dc\u8077\u4f4d\u7533\u8acb\u8868\u683c\u5c07\u65bc\u65b0\u7684\u8996\u7a97\u958b\u5553\u3002\u5728\u586b\u5beb\u8868\u683c\u6642\uff0c\u8acb\u4ee5\u82f1\u6587\u586b\u5beb\uff0c\u4e26\u65bc\u5b8c\u6210\u6bcf\u4e00\u9801\u5f8c\u6309\u9801\u5e95\u7684\u300c\u4e0b\u4e00\u9801\u300d\u6309\u9215\uff0c\u4ee5\u7e7c\u7e8c\u586b\u5beb\u8868\u683c\u5167\u7684\u6240\u6709\u9801\u9762\u3002\u586b\u59a5\u5f8c\uff0c\u8a18\u7dca\u6309\u8868\u683c\u6700\u5f8c\u4e00\u9801\u7684\u300c\u7533\u8acb\u300d\u6309\u9215\uff0c\u4ee5\u905e\u4ea4\u7533\u8acb\u3002", "employment_types": ["Full Time"], "selling_points": [], "locations": ["Central"], "categories": ["Others", "Agriculture / Forestry / Fishing", "Building & Construction", "Others"], "post_time": "2022-01-10T03:54:29Z", "salary": {"currency": null, "max": null, "min": null, "period": "monthly", "term": null}, "salary_visible": false, "title_keywords": [], "responsibilities": [], "requirements": {"degrees": [], "majors": [], "languages": [], "language_level": [], "hard_skills": [], "soft_skills": [], "languages_combined": []}, "experience_required": {"duration": [], "field": []}}, {"job_id": "100003009015926", "location_code": "hk", "company": "Agnes b. HK Limited", "job_title": "\u77ed\u671f\u82b1\u85dd\u52a9\u7406 / \u77ed\u671f\u6587\u54e1 Temporary Helper / Temporary Clerk (Fleuriste)", "description": "\n\u8077\u8cac :\u8655\u7406\u82b1\u5e97\u65e5\u5e38\u904b\u4f5c\uff0c\u5305\u62ec\u82b1\u85dd\u8a2d\u8a08\uff0c\u8ddf\u9032\u8a02\u55ae\uff0c\u8655\u7406\u82b1\u6750\u3001\u8449\u6750\u3001\u82b1\u5668\u53ca\u690d\u7269\u7b49\uff0c\u5b89\u6392\u51fa\u8ca8\uff0c\u8ddf\u9032\u51fa\u8ca8\u7b49\u3002(\u64c1\u6709\u5c08\u696d\u82b1\u85dd\u6587\u6191)\n\n\u8cc7\u6b77 :\u5c08\u4e0a\u6559\u80b2\uff1a\u6587\u6191/\u8b49\u66f8; 2\u5e74\u7d93\u9a57; \u826f\u597d\u7cb5\u8a9e; \u4e00\u822c\u666e\u901a\u8a71; \u4e00\u822c\u82f1\u8a9e; \u61c2\u8b80\u5beb\u4e2d\u6587; \u61c2\u8b80\u5beb\u82f1\u6587; 2\u5e74\u6216\u4ee5\u4e0a\u82b1\u5e97\u5de5\u4f5c\u7d93\u9a57\uff0c\u66fe\u4fee\u8b80\u5c08\u696d\u82b1\u85dd\u8a3c\u66f8\u8ab2\u7a0b\u53ca\u559c\u611b\u5712\u85dd\u5de5\u4f5c\u3002\n\n\u5f85\u9047 :\u6bcf\u6708$14,000 - $18,000, \u6709\u96d9\u7ce7 \u53ca\u8868\u73fe\u734e\u91d1, \u661f\u671f\u4e00\u81f3\u516d: \u4e0a\u53489\u6642\u81f3\u4e0b\u53487\u6642, \u6bcf\u9031\u5de5\u4f5c5\u5929\u81f36\u5929, \u6bcf\u5929\u5de5\u4f5c 10 \u5c0f\u6642\n\n\u7533\u8acb\u9808\u77e5 :\u6c42\u8077\u8005\u53ef\u96fb\u90f5(Apply Now)\u5c65\u6b77\u8868\u7d66\u7da0\u82b7\u82b1\u85dd\u6709\u9650\u516c\u53f8\u3002\u5982\u8981\u7d22\u53d6\u6536\u96c6\u500b\u4eba\u8cc7\u6599\u8072\u660e, \u8acb\u8207\u9673 \u592a(Email)\u806f\u7d61\u3002\n\n", "employment_types": ["Part Time", "Temporary", "Contract", "Freelance"], "selling_points": ["\u77ed\u671f\u82b1\u85dd\u52a9\u7406 / \u77ed\u671f\u6587\u54e1 Temporary Helper / Temporary Clerk", "2022\u5e741\u670820\u65e5\u81f32\u670814\u65e5", "\u5de5\u4f5c\u5730\u9ede : \u4e2d\u74b0 / \u592a\u53e4\u57ce / \u5c16\u6c99\u5480 / \u4e5d\u9f8d\u5858"], "locations": ["Not Specified"], "categories": ["Others", "Agriculture / Forestry / Fishing", "Design", "Others", "Sales, CS & Business Devpt", "Retail Sales"], "post_time": "2022-01-10T02:26:55Z", "salary": {"currency": null, "max": null, "min": null, "period": null, "term": null}, "salary_visible": false, "title_keywords": ["temporary clerk", "helper"], "responsibilities": [], "requirements": {"degrees": [], "majors": [], "languages": [], "language_level": [], "hard_skills": [], "soft_skills": [], "languages_combined": []}, "experience_required": {"duration": [], "field": []}}, {"job_id": "100003009033182", "location_code": "hk", "company": "RecruitFirst Limited", "job_title": "*Engineering/ Landscape* Supervisor Assistant [50k/Civil Engineering/ Landscape/ 9 months contract ]", "description": "1) \u77ed\u671f\u6587\u54e1\n\u65e5\u671f\u53ca\u6642\u9593 : 1\u670820\u65e5\u81f32\u670814\u65e5 (10:00 \u2013 18:00)\n\u5de5\u4f5c\u5730\u9ede : \u592a\u53e4\u57ce\n\u5de5\u4f5c\u5167\u5bb9 : \u6587\u66f8\u8655\u7406\uff0c\u78ba\u8a8d\u82b1\u5e97\u8a02\u55ae\u7b49\uff0c\u6216\u6709\u9700\u8981\u5230\u5e97\u8216\u5354\u52a9\u3002\n\n2) \u77ed\u671f\u82b1\u5e97\u52a9\u7406\n\u65e5\u671f\u53ca\u6642\u9593 :\n1\u670824\u65e5\u81f32\u670813\u65e5 (10:00 \u2013 19:00)\n2\u670814\u65e5 (9:00 \u2013 16:00\uff0c\u5168\u65e5\u9001\u82b1)\n\u5de5\u4f5c\u5730\u9ede : \u4e2d\u74b0 / \u592a\u53e4\u57ce / \u5c16\u6c99\u5480 / \u4e5d\u9f8d\u5858\n\u5de5\u4f5c\u5167\u5bb9 : \u5354\u52a9\u82b1\u5e97\u65e5\u5e38\u904b\u4f5c\uff0c\u5305\u62ec\u5916\u51fa\u9001\u82b1\u3001\u5e97\u8216\u6e05\u6f54\u3001\u8655\u7406\u82b1\u6750\u53ca\u9867\u5ba2\u670d\u52d9\u7b49\u5de5\u4f5c\u3002\n\n3) \u77ed\u671f\u82b1\u85dd\u52a9\u7406 (\u5de5\u5834)\n\u65e5\u671f\u53ca\u6642\u9593 :\n2\u67084\u65e5\u81f312\u65e5 (11:00 \u2013 18:00)\n2\u670813\u65e5 (10:00 \u2013 20:00)\n2\u670814\u65e5 (7:00 \u2013 16:00\uff0c\u5168\u65e5\u9001\u82b1)\n\u5de5\u4f5c\u5730\u9ede : \u5c0f\u897f\u7063\n\u5de5\u4f5c\u5167\u5bb9 : \u5354\u52a9\u82b1\u85dd\u5e2b\u8655\u7406\u5927\u91cf\u82b1\u6750\u3001\u88fd\u4f5c\u82b1\u85dd\u7522\u54c1\u3001\u5834\u5730\u6e05\u6f54\u53ca\u5916\u51fa\u9001\u82b1\u7b49\u5de5\u4f5c\u3002\n\n4) \u60c5\u4eba\u7bc0\u9001\u82b1\u54e1 (\u82b1\u5e97\u53ca\u5de5\u5834)\n\u65e5\u671f : 2\u670814\u65e5\n\u5730\u9ede\u53ca\u6642\u9593 : \u5404\u5340\u82b1\u5e97 (9:00 \u2013 16:00) / \u5de5\u5834 : (7:00 \u2013 16:00\uff0c\u8ddf\u8eca\u9001\u82b1)\n\u5de5\u4f5c\u5167\u5bb9 : \u8ca0\u8cac\u5916\u51fa\u904b\u9001\u5927\u91cf\u82b1\u85dd\u7522\u54c1\u3002\n\n\u4ee5\u4e0a\u8077\u4f4d\u6642\u85aa\u8a08\u7b97\uff0c\u5177\u76f8\u95dc\u5de5\u4f5c\u512a\u5148\u3002\u7533\u8acb\u8005\u5fc5\u9808\u53ef\u57282\u670812\u81f314\u65e5\u51fa\u52e4\u3002\n\n\u7533\u8acb\u8005\u8acb\u900f\u904e Apply Now \u905e\u4ea4\u5c65\u6b77\u8868\uff0c\u8a73\u7d30\u5217\u660e\u7533\u8acb\u8077\u4f4d\u53ca\u8cc7\u6b77\u3002\u4eba\u529b\u8cc7\u6e90\u90e8\u6703\u4ee5\u96fb\u8a71\u65b9\u5f0f\u806f\u7d61\u5408\u9069\u7684\u7533\u8acb\u8005\u3002\n\n\u67e5\u8a62\u96fb\u8a71\uff1a2894 2779 (\u8fa6\u516c\u6642\u9593)\n\nonlineshop.agnesb.com.hk | facebook.com/agnesb.cafefleuriste | instagram.com/agnesb_cafefleuriste\n\n*\u6240\u6709\u6536\u96c6\u4e4b\u500b\u4eba\u8cc7\u6599\u53ea\u4f5c\u62db\u8058\u7528\u9014", "employment_types": ["Full Time", "Contract"], "selling_points": [], "locations": ["Kwun Tong Area"], "categories": ["Others", "Agriculture / Forestry / Fishing", "Engineering", "Engineering Project Management", "Sciences, Lab, R&D", "Environmental Science / Waste Management"], "post_time": "2022-01-08T13:24:31Z", "salary": {"currency": null, "max": null, "min": null, "period": "monthly", "term": null}, "salary_visible": false, "title_keywords": ["supervisor", "assistant"], "responsibilities": ["facebook"], "requirements": {"degrees": [], "majors": [], "languages": [], "language_level": [], "hard_skills": ["facebook"], "soft_skills": [], "languages_combined": []}, "experience_required": {"duration": [], "field": []}}, {"job_id": "100003009030533", "location_code": "hk", "company": "Yee Sun Garden Limited", "job_title": "Arborist", "description": "Duties:\u00a0\n\nProviding support to the Landscape Term Contract administration, such as preparing works order, cost estimate and related contract documents\nCarrying out site inspection and supervision of works, preparing reports and cost estimates of works, and keeping records\nConducting site tests and supervising the operation of equipment and plants\nAssisting in the planning and implementation of programmes for landscape/ maintenance works\nArranging relevant safety- related training\nRequirements:\u00a0\n\u00a0\nObtained a Certificate in civil engineering from a Hong Kong University or HKIVE\nCompleted a recognized Technician Apprenticeship in civil engineering\nAt least 5 years experience as a skilled worker in civil engineering\nA good command of written and spoken English and Chinese and have met the language proficiency requirements of Level 2 or above English Language in the HKDSE\nHaving basic knowledge on MS word, Excel and Powerpoint Presentation", "employment_types": ["Full Time", "Permanent"], "selling_points": ["Vegetation Maintenance Works Kln & Lantau", "At least 5 yrs practical tree works experience", "Very preferable 7 yrs tree works experience"], "locations": ["Not Specified"], "categories": ["Others", "Agriculture / Forestry / Fishing", "Sciences, Lab, R&D", "Environmental Science / Waste Management", "Others"], "post_time": "2022-01-07T07:41:31Z", "salary": {"currency": null, "max": null, "min": null, "period": "monthly", "term": null}, "salary_visible": false, "title_keywords": [], "responsibilities": ["cost", "supervising", "maintenance", "contract administration", "implementation", "site inspection", "preparing reports", "providing support", "planning"], "requirements": {"degrees": ["certificate", "hkdse"], "majors": ["civil engineering"], "languages": ["english", "chinese"], "language_level": ["proficiency", "good command"], "hard_skills": ["excel", "basic", "powerpoint", "ms word"], "soft_skills": ["presentation"], "languages_combined": [{"language": "english", "language_level": ["proficiency", "good command"]}, {"language": "chinese", "language_level": ["proficiency", "good command"]}]}, "experience_required": {"duration": ["at least 5 years"], "field": ["engineering"]}}, {"job_id": "100003009027789", "location_code": "hk", "company": "River Forest Landscape Limited", "job_title": "Project Manager/Director Assistant & Landscape Worker(Long Term Part Time) \u9805\u76ee\u7d93\u7406/\u8463\u4e8b\u52a9\u7406\u517c\u5712\u85dd\u5de5\u4eba(\u9577\u671f\u517c\u8077)", "description": "Job Descriptions\n\n-\u00a0\u00a0\u00a0\u00a0\u00a0\u00a0\u00a0\u00a0\u00a0 Plan , supervise Inspection and Operation Team to carry out tree inspections with tree risk assessment / tree survey and horticultural / arboricultural maintenance works\n\n-\u00a0\u00a0\u00a0\u00a0\u00a0\u00a0\u00a0\u00a0\u00a0 Prepare planting proposals, liaise with employer who is responsible for the approval, plan and execute the planting works and by then carry out the establishment work and submit the respective reports\n\n-\u00a0\u00a0\u00a0\u00a0\u00a0\u00a0\u00a0\u00a0\u00a0 Prepare woodland thinning proposals when necessary, liaise with employer who is responsible for the approval, plan and supervise the thinning works and by then submit the reports to the employer\n\n-\u00a0\u00a0\u00a0\u00a0\u00a0\u00a0\u00a0\u00a0\u00a0 Work with a team of experienced staff\n\n-\u00a0\u00a0\u00a0\u00a0\u00a0\u00a0\u00a0\u00a0\u00a0 Handle complaints and provide vegetation related advice / mitigation measures\n\n-\u00a0\u00a0\u00a0\u00a0\u00a0\u00a0\u00a0\u00a0\u00a0 Use advanced technical instruments for tree risk assessment including sonic tomograph, resistograph, tree motion sensor, tree radar, UAV, LiDAR, Laser Scan when necessary\n\n-\u00a0\u00a0\u00a0\u00a0\u00a0\u00a0\u00a0\u00a0\u00a0 Drive Company assigned car to perform duties as appropriate\n\n-\u00a0\u00a0\u00a0\u00a0\u00a0\u00a0\u00a0\u00a0\u00a0 Execute tasks as assigned by superior staff\n\nRequirements\n\n-\u00a0\u00a0\u00a0\u00a0\u00a0\u00a0\u00a0\u00a0\u00a0 Positive work attitude, enthusiasm in work, cooperative to perform duties with colleagues / team members, be responsible, proactive, willing to work outdoor, eager to solve problem, hard-working\n\n-\u00a0\u00a0\u00a0\u00a0\u00a0\u00a0\u00a0\u00a0\u00a0 Have a recognised Bachelor Degree or above in a discipline such as arboriculture, horticulture, natural science, agriculture, botany, forestry, vegetation, landscape architecture, landscape management, or a related field, or equivalent, to the standards of Level 5 or above in Hong Kong Qualifications Framework (HKQF)\n\n-\u00a0\u00a0\u00a0\u00a0\u00a0\u00a0\u00a0\u00a0\u00a0 Preferably, completed an appropriate training course provided for Safety Supervisors to attain knowledge in occupational safety and health relating to tree work operation covering hazard identification, risk assessment and supervision\n\n-\u00a0\u00a0\u00a0\u00a0\u00a0\u00a0\u00a0\u00a0\u00a0 have attended and completed the following training courses organised by the TMO:\n\nComprehensive Tree Risk Assessment and Management Training Course with assessment\n\nOr\n\nRefresher Course with assessment\n\nOr\n\nequivalent departmental training recognised by the TMO\n\nOr\n\ncompleted and passed training programmes in tree risk assessment recognised by the TMO, such as Tree Risk Assessment Qualification (TRAQ) organised by the ISA or Professional Tree Inspection by Lantra Awards\n\n-\u00a0\u00a0\u00a0\u00a0\u00a0\u00a0\u00a0\u00a0\u00a0 have a qualification or certification awarded by a professional institution or industry organization on arboriculture after successful completion of examination or assessment process conducted or accredited by the institution or organization, such as Certified Arborist or above qualifications of the ISA, Professional Member or above qualifications of the Arboricultural Association of the UK, or equivalent.\n\n-\u00a0\u00a0\u00a0\u00a0\u00a0\u00a0\u00a0\u00a0\u00a0 be a registered Arborist and Tree Risk Assessor under The Registration Scheme for Tree Management Personnel of the Development Bureau.\n\n-\u00a0\u00a0\u00a0\u00a0\u00a0\u00a0\u00a0\u00a0\u00a0 have at least seven (7) years of practical experience in tree works and three (3) cumulative years of post-qualification practical experience within the immediate past five (5) years in tree works and Tree Risk Assessment (TRA)\n\n-\u00a0\u00a0\u00a0\u00a0\u00a0\u00a0\u00a0\u00a0\u00a0 Valid driving license\n\n-\u00a0\u00a0\u00a0\u00a0\u00a0\u00a0\u00a0\u00a0\u00a0 Having background knowledge / basic experience in Land Survey skills and / or Building Information Modeling (BIM) technique is preferable\n\n-\u00a0\u00a0\u00a0\u00a0\u00a0\u00a0\u00a0\u00a0\u00a0 Proficiency in spoken Cantonese and written Chinese and English\n\n-\u00a0\u00a0\u00a0\u00a0\u00a0\u00a0\u00a0\u00a0\u00a0 Candidates with less qualification will be considered for junior arboriculture post\n\nInterested parties please send your full CV with your current and expected salary and available reporting date", "employment_types": ["Part Time", "Permanent"], "selling_points": [], "locations": ["Yuen Long Area"], "categories": ["Others", "Agriculture / Forestry / Fishing", "Building & Construction", "Others"], "post_time": "2022-01-07T07:51:34Z", "salary": {"currency": null, "max": null, "min": null, "period": "hourly", "term": null}, "salary_visible": false, "title_keywords": ["project manager", "director", "assistant"], "responsibilities": ["maintenance", "inspection", "handle complaints", "reports", "plan", "liaise with"], "requirements": {"degrees": ["degree or above", "bachelor"], "majors": ["science", "architecture", "forestry", "botany"], "languages": ["cantonese", "english", "chinese"], "language_level": ["proficiency"], "hard_skills": ["bim", "basic", "scheme"], "soft_skills": ["responsible", "perform duties", "cooperative", "comprehensive", "hard-working", "organised", "proactive", "positive work attitude"], "languages_combined": [{"language": "cantonese", "language_level": ["proficiency"]}, {"language": "english", "language_level": []}, {"language": "chinese", "language_level": []}]}, "experience_required": {"duration": [], "field": ["post-qualification"]}}, {"job_id": "100003009029739", "location_code": "hk", "company": "St. Stephen's Catholic Kindergarten", "job_title": "\u5e7c\u7a1a\u5712\u8001\u5e2b (2/3\u8077)", "description": "Position Introduction\u00a0\n\n\u9019\u662f\u4e00\u500b\u6587\u3001\u6b66\u3001\u5546 \u5168\u7684\u8077\u4f4d\n\u9700\u5177\u6709\u57fa\u672c\u7684\u5b78\u8853\u3001\u9ad4\u80fd\u53ca\u89e3\u6c7a\u5712\u85dd\u5de5\u7a0b\u9805\u76ee\u53ca\u5546\u696d\u5be6\u969b\u554f\u984c\u7684\u80fd\u529b\u3002\n\nJob Content\n\nDifferent kinds of landscape project including horticulture, arboriculture and relevant project may involved. Multiple\u00a0extent and wide range of works of a landscape contractor company may involved.\n\nWork Location\n\n- Mainly work in Yuen Long District, North District, Sometime in Kowloon.\n\n- Mainly work in river, riverside, wetland, slope and construction site.\n\nJob Requirement\u00a0\n\n-Education and\u00a0Work Experience\n\n- Possess relevant academic certification and have relevant work experience is preferable.\u00a0\n\nPaperwork\n\n- Have basic paperwork and computer skill.\n\nPhysical Fitness\u00a0\n\n- Able to to work in outdoor and wild environment.\n\n- Have basic physical strength and endurance.\u00a0\n\nOther\n\n- Possess Green Card, Construction Workers Registration Card.\n\nJob Information\n\nWork Day\n\n- 3-5.5 days each week\n\nWork Hour\n\n- 1 Day - 8 hours with 1 hours lunch time,\u00a0in daytime.\n\n- Half\u00a0 Day - 3.5 hours,\u00a0in daytime.\n\nSalary\u00a0\n\n- 1 Day\u00a0- $700 UP\n\n- Half\u00a0 Day - $400 UP\n\n- Payment Period - Monthly\n\n- Have yearly commission according to the performance of employee and company's profit.\n\nRemark\n\n-The personal information only for job application purpose.", "employment_types": ["Full Time"], "selling_points": [], "locations": ["Kwai Tsing Area"], "categories": ["Others", "Agriculture / Forestry / Fishing", "Building & Construction", "Others"], "post_time": "2022-01-07T06:04:10Z", "salary": {"currency": null, "max": null, "min": null, "period": "monthly", "term": null}, "salary_visible": false, "title_keywords": [], "responsibilities": [], "requirements": {"degrees": [], "majors": [], "languages": [], "language_level": [], "hard_skills": [], "soft_skills": [], "languages_combined": []}, "experience_required": {"duration": [], "field": []}}, {"job_id": "100003009030500", "location_code": "hk", "company": "Manpower Services (Hong Kong) Limited", "job_title": "Billing Officer (Contract, Up to 18k, Welcome fresh grads)", "description": "Responsibilities:\n\nSupport day to day operation of billing and data management\nSupport account receivable transactions and debt collection\nMonitor billing profiles for accurate, timely & efficient billing\nHandle client billing queries and ensure accuracy and completeness\nPerform other ad-hoc assignments as required\n\nQualifications / Skills:\u00a0\n\nDiploma or above in any disciplines\nWelcome fresh graduates\nProactive with good interpersonal, communication and problem-solving skills\nExcellent in accounting system and MS Office, including MS Word and Excel\n\nAny interested parties, please click \u201cApply Now\u201d or send your resume to\u00a0carrie.yim@manpowergrc.hk", "employment_types": ["Contract"], "selling_points": ["Diploma or above", "Billing & Credit", "5 day work"], "locations": ["Kwai Hing"], "categories": ["Accounting", "Others", "Others", "Agriculture / Forestry / Fishing"], "post_time": "2022-01-07T07:35:41Z", "salary": {"currency": null, "max": null, "min": null, "period": "monthly", "term": null}, "salary_visible": false, "title_keywords": ["billing officer"], "responsibilities": ["management", "data", "ad-hoc assignments", "monitor", "transactions", "communication", "debt collection"], "requirements": {"degrees": ["diploma or above"], "majors": ["any disciplines"], "languages": [], "language_level": [], "hard_skills": ["excel", "data management", "accounting system", "problem-solving skills", "ms office", "ms word"], "soft_skills": ["efficient", "proactive", "timely", "communication", "problem-solving skills", "accurate", "interpersonal"], "languages_combined": []}, "experience_required": {"duration": [], "field": []}}, {"job_id": "100003009028660", "location_code": "hk", "company": "\u963f\u4fe1\u5712\u85dd\u6709\u9650\u516c\u53f8", "job_title": "Arborist Assistant", "description": "\u00a0Job Descriptions:\n\nOversee and supervise landscape works related to arboricultural, horticultural operations and preservation of trees within the Site\nConduct the tree survey or assessment\nProvide advice and supervise planting, transplanting, tree surgery work and control of pest and disease affecting trees on the Site and local nursery\nResponsible for procurement of nursery stock\nHandle ad hoc duties and assignments as required\u00a0\n\nJob Requirements:\n\nCertificate / diploma / degree in arboriculture or equivalent\nQualified Arborist or equivalent of recognized arboriculture organization\nTree Risk Assessment Qualification or equivalent of recognized organization\nReceived relevant training in occupational safety and health relating to tree work operation\nMinimum 1 year' experience in tree care and familiar with tree risk assessment/ Management\nProficiency in English and Chinese", "employment_types": ["Full Time"], "selling_points": [], "locations": ["Tuen Mun Area"], "categories": ["Others", "Agriculture / Forestry / Fishing"], "post_time": "2022-01-07T02:46:30Z", "salary": {"currency": null, "max": null, "min": null, "period": "monthly", "term": null}, "salary_visible": false, "title_keywords": ["arborist assistant"], "responsibilities": ["ad hoc duties", "operations", "control", "provide advice"], "requirements": {"degrees": ["certificate", "diploma", "degree"], "majors": [], "languages": ["english", "chinese"], "language_level": ["proficiency"], "hard_skills": [], "soft_skills": [], "languages_combined": [{"language": "english", "language_level": ["proficiency"]}, {"language": "chinese", "language_level": ["proficiency"]}]}, "experience_required": {"duration": ["minimum 1 year"], "field": ["management"]}}, {"job_id": "100003009028924", "location_code": "hk", "company": "Transport Infrastructure Management Limited", "job_title": "\u52a9\u7406\u82b1\u738b", "description": "\u8077\u8cac :\n\n\u8ca0\u8cac\u6574\u7406\u96a7\u9053\u7ba1\u5236\u5340\u5167\u82b1\u5703\u53ca\u659c\u5761\u4e0a\u6a39\u6728\u4fee\u847a\u7684\u5de5\u4f5c\n\u8cc7\u6b77 :\n\n\u6c92\u6709\u5b78\u6b77\u8981\u6c42; 1\u5e74\u7d93\u9a57; \u826f\u597d\u7cb5\u8a9e; \u7565\u61c2\u8b80\u5beb\u4e2d\u6587; \u6301\u6709\u5e73\u5b89\u54ad; \u6301\u6709\u5efa\u9020\u696d\u5de5\u4eba\u8a3b\u518a\u8b49; \u5177\u5712\u85dd\u7d93\u9a57\u512a\u5148\n\u5f85\u9047 :\n\n\u6bcf\u6708$12,500, \u6709\u5e74\u504711\u5929, \u914c\u60c5\u6027\u82b1\u7d05, \u91ab\u7642\u798f\u5229, \u5ec9\u50f9\u98ef\u5802\u53ca\u7a7f\u68ad\u5df4\u58eb\u670d\u52d9, \u661f\u671f\u4e00\u81f3\u516d: \u4e0a\u53487\u6642\u534a\u81f3\u4e0b\u53484\u6642\u534a, \u6bcf\u9031\u5de5\u4f5c5\u5929\u81f36\u5929\n\u7533\u8acb\u9808\u77e5 :\u6c42\u8077\u8005\u53ef\u81f4\u96fb24838819\u8207\u4ea4\u901a\u57fa\u5efa\u7ba1\u7406\u6709\u9650\u516c\u53f8\u9673\u5c0f\u59d0\u806f\u7d61\u3002\n\n\u6709\u610f\u7533\u8acb\u8005\u8acb \u6309 APPLY NOW\u7533\u8acb\u00a0", "employment_types": ["Full Time"], "selling_points": [], "locations": ["Not Specified"], "categories": ["Transportation & Logistics", "Others", "Others", "Agriculture / Forestry / Fishing", "Others"], "post_time": "2022-01-07T03:35:51Z", "salary": {"currency": null, "max": null, "min": null, "period": "monthly", "term": null}, "salary_visible": false, "title_keywords": [], "responsibilities": [], "requirements": {"degrees": [], "majors": [], "languages": [], "language_level": [], "hard_skills": [], "soft_skills": [], "languages_combined": []}, "experience_required": {"duration": [], "field": []}}, {"job_id": "100003009022309", "location_code": "hk", "company": "Advance Engineering (Development) Ltd", "job_title": "\u82b1\u738b**", "description": "\n\u8077\u8cac :\u7167\u9867\u53ca\u6559\u5c0e2-6\u6b72\u5e7c\u5152\uff0c\u7de8\u5beb\u6559\u6848\u3001\u63a8\u884c\u5404\u985e\u8ab2\u5802\u6d3b\u52d5\u3001\u88fd\u4f5c\u6559\u6750\u3001\u74b0\u5883\u4f48\u7f6e\u53ca\u7de8\u5beb\u5152\u7ae5\u5b78\u7fd2\u6b77\u7a0b\u6a94\u6848\u5de5\u4f5c\u7b49\uff1b\u8a08\u5283\u548c\u63a8\u884c\u5b78\u6821\u6d3b\u52d5\uff1b\u8207\u5bb6\u9577\u6e9d\u901a\u806f\u7d61\u3002\n\n\u8cc7\u6b77 :\u5c08\u4e0a\u6559\u80b2\uff1a\u6587\u6191/\u8b49\u66f8; \u6703\u8003\u4e94\u79d1\u5408\u683c; 1\u5e74\u7d93\u9a57; \u826f\u597d\u7cb5\u8a9e; \u826f\u597d\u666e\u901a\u8a71; \u826f\u597d\u82f1\u8a9e; \u61c2\u8b80\u5beb\u4e2d\u6587; \u61c2\u8b80\u5beb\u82f1\u6587; \u6703\u8003/\u6587\u6191\u8a66\u4e2d\u82f1\u6578\u5408\u683c; \u5177\u5e7c\u5152\u6559\u80b2\u5b78\u4f4d\u8cc7\u6b77\u512a\u5148\n\n\u5f85\u9047 :\u6bcf\u6708$14,000 - $15,000, \u661f\u671f\u4e00\u81f3\u4e94: \u4e0a\u53488\u664220\u5206\u81f3\u4e0b\u53482\u664220\u5206\u53ca\u661f\u671f\u516d: \u4e0a\u53489\u6642\u81f3\u4e0b\u53481\u6642, \u6bcf\u9031\u5de5\u4f5c5\u5929\n\n\u7533\u8acb\u9808\u77e5 :\u6c42\u8077\u8005\u53ef\u96fb\u90f5(Apply Now)\u5c65\u6b77\u8868\u7d66\u8056\u65af\u5fb7\u671b\u5929\u4e3b\u6559\u5e7c\u7a1a\u5712\u3002\u5982\u8981\u7d22\u53d6\u6536\u96c6\u500b\u4eba\u8cc7\u6599\u8072\u660e, \u8acb\u8207\u694a\u5c0f\u59d0(Tel: 24872723)\u806f\u7d61\u3002\n\n", "employment_types": ["Full Time"], "selling_points": [], "locations": ["Tsing Yi"], "categories": ["Others", "Agriculture / Forestry / Fishing", "Others"], "post_time": "2022-01-05T05:23:59Z", "salary": {"currency": null, "max": null, "min": null, "period": "monthly", "term": null}, "salary_visible": false, "title_keywords": [], "responsibilities": [], "requirements": {"degrees": [], "majors": [], "languages": [], "language_level": [], "hard_skills": [], "soft_skills": [], "languages_combined": []}, "experience_required": {"duration": [], "field": []}}, {"job_id": "100003009026289", "location_code": "hk", "company": "City Landscaping Co. Limited", "job_title": "Arborist", "description": "Job responsibilities\n\nTo oversee and manager the project progress\u00a0\nTo prepare project submissions\nTo conduct tree risk assessment and tree survey\nTo conduct site inspection\nOther tasks relevant to management of arboricultural projects\n\nJob requirements\n\nCertificate / diploma or other equivalent qualification in arboriculture, tree management,\u00a0 or equivalent, up to or above the standard of HKQF Level 3\nISA Certified Arborist or equivalent\nISA TRAQ, LANTRA, or equivalent\nreceived training in OSH for Arboriculture\nholder of a driving license is preferred\n\nInterested parties please send your resume to us and indicate your expected salary and availability for starting work.", "employment_types": ["Full Time"], "selling_points": [], "locations": ["Not Specified"], "categories": ["Others", "Agriculture / Forestry / Fishing"], "post_time": "2022-01-06T07:53:47Z", "salary": {"currency": null, "max": null, "min": null, "period": "monthly", "term": null}, "salary_visible": false, "title_keywords": [], "responsibilities": ["other tasks", "management", "project progress", "site inspection"], "requirements": {"degrees": ["certificate", "diploma"], "majors": [], "languages": [], "language_level": [], "hard_skills": ["osh"], "soft_skills": [], "languages_combined": []}, "experience_required": {"duration": [], "field": []}}, {"job_id": "100003009026396", "location_code": "hk", "company": "Happy Lemon HK Limited", "job_title": "\u5168\u8077\u6d17\u7897\u54e1**", "description": "\n\u8077\u8cac :\u8655\u7406\u6e05\u6f54\u9910\u5ef3\u7684\u9910\u5177\u3001\u7897\u789f\u3001\u7528\u5177, \u9700\u64cd\u4f5c\u6d17\u7897\u6a5f, \u6642\u523b\u4fdd\u6301\u5de5\u4f5c\u5d17\u4f4d\u53ca\u9910\u5177\u6e05\u6f54\u885e\u751f, \u6309\u7167\u516c\u53f8\u6d41\u7a0b\u6d17\u7897\u6e05\u6f54\n\n\u8cc7\u6b77 :\u6c92\u6709\u5b78\u6b77\u8981\u6c42; \u4e00\u822c\u7cb5\u8a9e; \u4e00\u822c\u666e\u901a\u8a71; \u4e00\u822c\u82f1\u8a9e\n\n\u5f85\u9047 :\u6bcf\u6708$14,000, \u6709\u6bcf\u6708\u52e4\u5de5\u734e\u91d1$1000, \u4f9b\u81b3\u98df, \u8d85\u6642\u5de5\u4f5c\u6d25\u8cbc, \u8d85\u6642\u5de5\u4f5c\u88dc\u5047 \u53ca\u6bcf\u6708\u4ea4\u901a\u6d25\u8cbc$600, \u4e00\u81f3\u4e94: \u4e0b\u53481\u6642\u81f3\u4e0b\u534810\u6642\u534a,\u516d\u53ca\u65e5: \u4e2d\u534812\u6642\u81f3\u4e0b\u534810\u6642\u534a, \u6bcf\u9031\u5de5\u4f5c5\u5929\u81f36\u5929,\u8f2a\u73ed,\u8f2a\u4f11, \u6bcf\u5929\u5de5\u4f5c 9-10 \u5c0f\u6642\n\n\u7533\u8acb\u9808\u77e5 :\u6c42\u8077\u8005\u8acb\u89aa\u81e8\u9285\u947c\u7063\u8ed2\u5c3c\u8a69\u9053489\u865f\u9285\u947c\u7063\u5ee3\u5834\u4e00\u671f2\u6a13202-203\u865f\u8216\u5feb\u6a02\u6ab8\u6aac\u9999\u6e2f\u6709\u9650\u516c\u53f8\u9762\u8a66\u3002\u67e5\u8a62\u8acb\u81f4\u96fb95021990\u8207\u9673\u5148\u751f\u806f\u7d61\u3002\n\n", "employment_types": ["Full Time"], "selling_points": [], "locations": ["Causeway Bay"], "categories": ["Others", "Agriculture / Forestry / Fishing", "Hospitality / F & B", "Food & Beverage", "Others"], "post_time": "2022-01-06T08:05:43Z", "salary": {"currency": null, "max": null, "min": null, "period": "monthly", "term": null}, "salary_visible": false, "title_keywords": ["\u5168\u8077\u6d17\u7897\u54e1"], "responsibilities": [], "requirements": {"degrees": [], "majors": [], "languages": [], "language_level": [], "hard_skills": [], "soft_skills": [], "languages_combined": []}, "experience_required": {"duration": [], "field": []}}, {"job_id": "100003009026797", "location_code": "hk", "company": "Noble Diamond Jewellery & Gold Company Limited", "job_title": "\u99d0\u5e97\u8216\u5de5\u85dd\u5e2b", "description": "\n\u8077\u4f4d\u8981\u6c42:\n\u2022 \u61c2\u9472\u5d4c\uff0c\u6539\u5708\u53ca\u96fb\u91d1\n\u2022 \u5177\u5e97\u8216\u5de5\u4f5c\u7d93\u9a57\u8005\u512a\u5148\u00a0\n(\u5e95\u85aa + \u52e4\u5de5) + (\u5206\u5e97\u4f63\u91d1) \u6bcf\u6708\u4e03\u5929\u4f8b\u5047\n( $11,000 - $13,000 ) + ( \u4f63\u91d1 )\n\n", "employment_types": ["Full Time"], "selling_points": [], "locations": ["Kwun Tong"], "categories": ["Others", "Agriculture / Forestry / Fishing", "Building & Construction", "Others"], "post_time": "2022-01-06T08:40:15Z", "salary": {"currency": null, "max": null, "min": null, "period": "monthly", "term": null}, "salary_visible": false, "title_keywords": [], "responsibilities": [], "requirements": {"degrees": [], "majors": [], "languages": [], "language_level": [], "hard_skills": [], "soft_skills": [], "languages_combined": []}, "experience_required": {"duration": [], "field": []}}, {"job_id": "100003009026243", "location_code": "hk", "company": "The Hong Kong Cricket Club", "job_title": "Grounds Manager", "description": "\n\u8077\u8cac :\u8ca0\u8cac\u5c4b\u82d1\u6216\u5546\u5ec8\u7684\u5712\u85dd\u4fdd\u990a, \u57f9\u690d\u82d7\u5703, \u5305\u62ec\u6dcb\u6c34\u3001\u4fee\u526a\u3001\u65bd\u80a5\u3001\u8655\u7406\u87f2\u5bb3\u53ca\u4e0a\u53f8\u6307\u6d3e\u4e4b\u5712\u85dd\u5de5\u4f5c\u7b49\n\n\u8cc7\u6b77 :\u6c92\u6709\u5b78\u6b77\u8981\u6c42; 1\u5e74\u7d93\u9a57; \u826f\u597d\u7cb5\u8a9e; \u6301\u6709\u5e73\u5b89\u54ad; \u9700\u7a7f\u5236\u670d\u5de5\u4f5c\u53ca\u6709\u79ae\u8c8c\n\n\u5f85\u9047 :\u6bcf\u6708$14,000, \u6709\u5e74\u504710\u5929 \u53ca\u91ab\u7642\u798f\u5229, \u4e0a\u53488\u6642\u534a\u81f3\u4e0b\u53485\u6642\u534a, \u6bcf\u9031\u5de5\u4f5c6\u5929,\u8f2a\u4f11\n\n\u7533\u8acb\u9808\u77e5 :\u50f1\u4e3b\u5c07\u65bc1\u670813\u65e5(2pm-4:30pm)\u65bc\u52de\u5de5\u8655\u6771\u6d8c\u5c31\u696d\u4e2d\u5fc3\u8209\u884c\u62db\u8058\u65e5,\u6709\u8208\u8da3\u8005,\u8acb\u81f4\u96fb3428 2942 \u5411\u6771\u6d8c\u5c31\u696d\u4e2d\u5fc3\u8077\u54e1\u9810\u7d04\u9762\u8a66\u3002\u540d\u984d\u6709\u9650,\u8acb\u5148\u9810\u7d04\u3002\n\n", "employment_types": ["Full Time", "Permanent"], "selling_points": [], "locations": ["Wan Chai Area"], "categories": ["Others", "Agriculture / Forestry / Fishing"], "post_time": "2022-01-06T07:43:49Z", "salary": {"currency": null, "max": null, "min": null, "period": "monthly", "term": null}, "salary_visible": false, "title_keywords": ["manager"], "responsibilities": [], "requirements": {"degrees": [], "majors": [], "languages": [], "language_level": [], "hard_skills": [], "soft_skills": [], "languages_combined": []}, "experience_required": {"duration": [], "field": []}}, {"job_id": "100003009021965", "location_code": "hk", "company": "Chun Hing Landscaping Company Limited", "job_title": "\u5712\u85dd\u5de5\u4eba**", "description": "\n\u8077\u8cac :\u4e00\u822c\u5712\u4e01\u5de5\u4f5c\uff0c\u5712\u85dd\u5de5\u4f5c\uff0c\u5305\u62ec\u7a2e\u690d\u3001 \u9664\u87f2\u9664 \u8349\u3001\u6f86\u6c34\u3001\u65bd\u80a5\u7b49\uff0c\u4e00\u822c\u82b1\u738b\u5de5\u4f5c\n\n\u8cc7\u6b77 :\u4e2d\u4e09\u7a0b\u5ea6; \u826f\u597d\u7cb5\u8a9e; \u61c2\u95b1\u8b80\u4e2d\u6587\n\n\u5f85\u9047 :\u6bcf\u6708$13,000 - $13,500, \u6709\u5e74\u504712\u5929, \u91ab\u7642\u798f\u5229, \u6649\u5347\u6a5f\u6703 \u53ca\u4eba\u58fd\u4fdd\u96aa, \u661f\u671f\u4e00\u81f3\u516d: \u4e0a\u53488\u6642\u81f3\u4e0b\u53485\u6642, \u6bcf\u9031\u5de5\u4f5c6\u5929, \u6bcf\u5929\u5de5\u4f5c 9 \u5c0f\u6642\n\n\u7533\u8acb\u9808\u77e5 :\u6c42\u8077\u8005\u53ef\u81f4\u96fb56416018\u8207\u4ef2\u91cf\u806f\u884c\u6709\u9650\u516c\u53f8\u674e\u5148\u751f\u806f\u7d61\u3002\n\n", "employment_types": ["Full Time"], "selling_points": [], "locations": ["Sheung Shui"], "categories": ["Others", "Agriculture / Forestry / Fishing", "Building & Construction", "Others"], "post_time": "2022-01-05T04:48:11Z", "salary": {"currency": null, "max": null, "min": null, "period": "hourly", "term": null}, "salary_visible": false, "title_keywords": [], "responsibilities": [], "requirements": {"degrees": [], "majors": [], "languages": [], "language_level": [], "hard_skills": [], "soft_skills": [], "languages_combined": []}, "experience_required": {"duration": [], "field": []}}, {"job_id": "100003009017939", "location_code": "hk", "company": "The Hong Kong Jockey Club", "job_title": "\u5712\u85dd\u8b77\u990a\u54e1", "description": "\n\u8077\u8cac :\u4e00\u822c\u5712\u85dd\u5de5\u4eba\u5de5\u4f5c\n\n\u8cc7\u6b77 :\u6c92\u6709\u5b78\u6b77\u8981\u6c42; 1\u5e74\u7d93\u9a57; \u4e00\u822c\u7cb5\u8a9e; \u6301\u6709\u5e73\u5b89\u54ad; \u6301\u6709\u5efa\u9020\u696d\u5de5\u4eba\u8a3b\u518a\u8b49; \u523b\u82e6, \u6709\u8cac\u4efb\u5fc3, \u5177\u5712\u85dd\u5de5\u4f5c\u7d93\u9a57\u512a\u5148\n\n\u5f85\u9047 :\u6bcf\u65e5$710.00, \u6709\u4f9b\u81b3\u98df, \u4e0a\u53487\u6642\u534a\u81f3\u4e0b\u53485\u6642, \u6bcf\u9031\u5de5\u4f5c6\u5929\n\n\u7533\u8acb\u9808\u77e5 :\u6c42\u8077\u8005\u53ef\u81f4\u96fb26685959\u8207\u632f\u8208\u5712\u85dd\u5de5\u7a0b\u6709\u9650\u516c\u53f8\u6881\u5c0f\u59d0\u806f\u7d61\u3002\n\n", "employment_types": ["Full Time", "Contract"], "selling_points": ["\u5177\u8349\u5730\u4fdd\u990a\u3001\u5efa\u9020\u3001\u7da0\u5316\u3001\u5712\u85dd\u5de5\u4f5c\u6216\u8eca\u8f1b\u7dad\u4fee\u7d93\u9a57", "\u5712\u85dd\u4fdd\u990a\u5de5\u4f5c, \u5305\u62ec\u6dcb\u6c34\u3001\u7a2e\u690d\u3001\u4fee\u526a\u3001\u65bd\u80a5\u3001\u5674\u85e5\u3001\u9664\u8349", "\u5354\u52a9\u4e3b\u7ba1\u8655\u7406\u5712\u85dd\u666f\u89c0\u8a2d\u8a08\u82b1\u64fa\u8a2d\u5de5\u4f5c"], "locations": ["Shatin Area"], "categories": ["Others", "Agriculture / Forestry / Fishing", "Property / Real Estate", "Property Management", "Public / Civil", "Utilities"], "post_time": "2022-01-04T02:30:59Z", "salary": {"currency": null, "max": null, "min": null, "period": null, "term": null}, "salary_visible": false, "title_keywords": [], "responsibilities": [], "requirements": {"degrees": [], "majors": [], "languages": [], "language_level": [], "hard_skills": [], "soft_skills": [], "languages_combined": []}, "experience_required": {"duration": [], "field": []}}, {"job_id": "100003008985279", "location_code": "hk", "company": "Kim Fai Landscaping Limited", "job_title": "Arborist / Arborist Assistant", "description": "\u5de5\u4f5c\u6027\u8cea\n\n\u8ca0\u8cac\u5712\u85dd\u4fdd\u990a\u5de5\u4f5c, \u5305\u62ec\u6dcb\u6c34\u3001\u7a2e\u690d\u3001\u4fee\u526a\u3001\u65bd\u80a5\u3001\u5674\u85e5\u3001\u9664\u8349\n\u5354\u52a9\u4e3b\u7ba1\u8655\u7406\u5712\u85dd\u666f\u89c0\u8a2d\u8a08\u82b1\u64fa\u8a2d\u5de5\u4f5c\n\n\n\u5de5\u4f5c\u5730\u9ede\u53ca\u6642\u9593\n\n\u6c99\u7530\u99ac\u5834 -\u4e0a\u5348\u4e5d\u6642\u81f3\u4e0b\u5348\u516d\u6642\n\n\u6bcf\u9031\u5de5\u4f5c\u516d\u5929\uff0c\u9808\u65bc\u661f\u671f\u65e5\u53ca\u516c\u773e\u5047\u671f\u8f2a\u73ed\u7576\u503c\u3002\u5de5\u4f5c\u6642\u9593\u4ea6\u6703\u6309\u904b\u4f5c\u4e0a\u9700\u8981\u800c\u4f5c\u51fa\u8abf\u52d5\n\n\n\u5165\u8077\u8981\u6c42\n\n\u5177\u54e5\u723e\u592b\u7403\u5834 / \u8db3\u7403\u5834 / \u5404\u985e\u8349\u5730\u4fdd\u990a\u3001\u5efa\u9020\u3001\u7da0\u5316\u3001\u5712\u85dd\u5de5\u4f5c\u6216\u8eca\u8f1b\u7dad\u4fee\u7d93\u9a57\uff0c\u4e26\u80fd\u7368\u7acb\u4f7f\u7528\u5c0f\u578b\u6a5f\u68b0\u8005\u5247\u4f5c\u512a\u5148\u8003\u616e\n\u4e2d\u4e09\u6216\u4ee5\u4e0a\u7a0b\u5ea6\n\u6301\u6709\u65481\u30012\u865f\u99d5\u99db\u57f7\u7167\u8005\u512a\u5148\u8003\u616e\n\u9808\u9577\u6642\u9593\u5728\u6237\u5916\u5de5\u4f5c", "employment_types": ["Full Time", "Permanent"], "selling_points": [], "locations": ["Shatin Area"], "categories": ["Others", "Agriculture / Forestry / Fishing", "Public / Civil", "Civil Services", "Building & Construction", "Others"], "post_time": "2022-01-02T22:54:01Z", "salary": {"currency": null, "max": null, "min": null, "period": "monthly", "term": null}, "salary_visible": false, "title_keywords": ["arborist assistant"], "responsibilities": [], "requirements": {"degrees": [], "majors": [], "languages": [], "language_level": [], "hard_skills": [], "soft_skills": [], "languages_combined": []}, "experience_required": {"duration": [], "field": []}}, {"job_id": "100003009023039", "location_code": "hk", "company": "Kowloon Cricket Club", "job_title": "Grounds Manager", "description": "Responsibilities:\n\nDevelop and implement plans for the successful maintenance of the\u00a0Club\u2019s Cricket Outfield, Turf Cricket Wickets, and Lawn Bowling Greens to the highest standard\nRestore fields damaged by weather, use, or other conditions to a level commensurate with that expected athletic grounds\nResponsible for routine turf maintenance including seeding, fertilizing, mowing, trimming, irrigation\nMake recommendation on planning the appropriate use of all turf surfaces including access for sporting sections for training and other promotional, non-game day activities\nKnowledge in irrigation systems, soil and other turf trades experience\nConduct on-the-job\u00a0training to the team on grounds equipment, power tools and work methods\nPlan and direct the work of all Grounds personnel involved in the maintenance activities\n\n\u00a0Requirements:\n\nA tertiary qualification / Higher Diploma / Graduate Certificate in Turf Management or other relevant discipline\n3 to 5 years supervisory experience in turf maintenance\nGood understanding of Cricket, Lawn Bowls, Soccer, Hockey and other field sports\nSound knowledge of turf management trends & programs\nDemonstrated thorough knowledge of lawns, plant materials, athletic turf (natural & synthetic), irrigation systems and general landscape and grounds maintenance work scheduling\u00a0\n\nPlease visit our website \u2013\u00a0www.kcc.org.hk\u00a0for particulars of KCC facilities.\n\nThe Club offers an attractive remuneration package to the successful candidate.\u00a0 Interested parties please send your full resume with expected salary and date available to Human Resources Department, Kowloon Cricket Club, 10 Cox\u2019s Road, Kowloon, Hong Kong or click \"APPLY NOW\".\u00a0", "employment_types": ["Full Time"], "selling_points": [], "locations": ["Tsim Sha Tsui"], "categories": ["Others", "Agriculture / Forestry / Fishing", "Hospitality / F & B", "Integrated Resort / Casino"], "post_time": "2022-01-05T07:15:38Z", "salary": {"currency": null, "max": null, "min": null, "period": "monthly", "term": null}, "salary_visible": false, "title_keywords": ["manager"], "responsibilities": ["make recommendation", "maintenance", "systems", "develop", "plan", "plans", "planning"], "requirements": {"degrees": ["certificate", "diploma"], "majors": [], "languages": [], "language_level": [], "hard_skills": ["maintenance"], "soft_skills": ["thorough"], "languages_combined": []}, "experience_required": {"duration": ["3 to 5 years"], "field": ["maintenance", "supervisory experience"]}}, {"job_id": "100003009006636", "location_code": "hk", "company": "Smart Farming HK Limited", "job_title": "Project Senior Officer", "description": "Requirements\n\nDiploma from an agriculture or forestry school/college, or in horticultural-related discipline from Hong Kong Polytechnic University/Hong Kong Institute of Vocational Education; or equivalent; and\n\nGrade E or above in Chinese Language and English Language (Syllabus B) in the HKCEE, or equivalent; and\n\nPreferably obtained anyone certification as stated below:\n\n(a) Certified Arborist qualification of International Society of Arboriculture; or\n\n(b) Technician Member, Professional Member or Fellow of the Arboricultural Association of the UK; or\n\n(c) European Tree Technician of the European Arboricultural Council; or\n\n(d) General Member of the National Arborists Association of Australia or equivalent.\n\nBe conversant with computer software of word processing, GIS and spreadsheet database in both Chinese and English documents;\n\nWorking at Cheung Sha Wan.\n\nImmediate available will be an advantage\n\nDuties:\n\nTo assist the Engineer in tree risk assessment, tree management and greening works to prepare relevant records as instructed by the Engineer.\n\n\n\n\nPlease click \u201cApply Now\u201d to submit your application. Applicants are required to send their full resume and expected salary to the attention of Ms Edith LEE for interview.\n\nAll personal information submitted by job applicants will be used for recruitment purposes and we reserve the rights to consider the applications for other positions in our Group.", "employment_types": ["Full Time"], "selling_points": ["5 days working week", "5yrs experience in project implementation", "Location: Admiralty, Tin Shui Wai & Sha Tau Kok"], "locations": ["Tin Shui Wai"], "categories": ["Others", "Agriculture / Forestry / Fishing", "Sales, CS & Business Devpt", "Business Development", "Sales Administration"], "post_time": "2021-12-29T09:39:50Z", "salary": {"currency": null, "max": null, "min": null, "period": "monthly", "term": null}, "salary_visible": false, "title_keywords": ["senior officer"], "responsibilities": ["management", "recruitment"], "requirements": {"degrees": ["diploma"], "majors": ["forestry"], "languages": ["english", "chinese"], "language_level": [], "hard_skills": ["wan", "c", "word processing", "spreadsheet"], "soft_skills": [], "languages_combined": [{"language": "english", "language_level": []}, {"language": "chinese", "language_level": []}]}, "experience_required": {"duration": [], "field": []}}, {"job_id": "100003009003948", "location_code": "hk", "company": "The Floristry", "job_title": "Full-time Florist", "description": "Responsibilities:\n\nAssist CTO in business development and project preparation; coordinate with various departments on a variety of projects;\nCooperate with internal and external parties in organizing, executing and completing the project milestones;\nIssue invoice, input sales record and review contract;\nKeep track and maintain good relationship with contractors;\nCarry out tasks assigned by CTO;\nOutdoor work is required;\nHandle ad hoc duties as assigned;\n\n\u00a0Requirements:\n\n5 years working experience, agricultural or fishery field is an advantage;\nHave a passion for local agriculture development;\nStrong people skill;\nProficiency in PC applications, e.g. Excel, Word Processing, Chinese word processing;\nGood command of written and spoken English and Mandarin;\n\nWe offer competitive salary package to suitable candidate.\u00a0 Interested parties, please send email for application form.", "employment_types": ["Full Time"], "selling_points": ["Creative Florist", "Excellent career progression opportunities", "Creative environment"], "locations": ["Sheung Wan"], "categories": ["Others", "Agriculture / Forestry / Fishing", "Design", "Others", "E-commerce", "Others"], "post_time": "2021-12-28T12:50:24Z", "salary": {"currency": null, "max": null, "min": null, "period": "monthly", "term": null}, "salary_visible": false, "title_keywords": [], "responsibilities": ["ad hoc duties", "outdoor work", "invoice", "internal and external parties", "coordinate with", "review", "maintain good relationship", "executing", "cooperate with"], "requirements": {"degrees": [], "majors": [], "languages": ["english", "chinese", "mandarin"], "language_level": ["good command"], "hard_skills": ["excel", "chinese word processing", "word processing", "pc applications"], "soft_skills": ["passion for"], "languages_combined": [{"language": "english", "language_level": ["good command"]}, {"language": "chinese", "language_level": []}, {"language": "mandarin", "language_level": ["good command"]}]}, "experience_required": {"duration": ["5 years"], "field": []}}, {"job_id": "100003009013777", "location_code": "hk", "company": "The Incorporated Owners of Wah Yuen Chuen", "job_title": "\u82b1\u738b", "description": "About Us\nThe Floristry is Hong Kong's leading floral lifestyle brand. We celebrate wild-inspired living and offer a curated assortment of flowers, homeware and lifestyle objects with a newly opened store and coffee bar in central.\n\nWe're currently on the look out for florist to assist with daily operations and seasonal flower designs.\u00a0We are expanding rapidly and in exchange for your passion for the brand we offer excellent career progression.\n\n\n\n\nDaily Operations\n\nAssisting in making bouquets, flower jars and general day-to-day florist duties.\nFloral Design\n\nAssist in designing and creating seasonal floral designs and products in line with The Floristry brand.\nEnsure all products are being made correctly.\nWork with buying team to ensure seasonal flower varieties are ordered and high quality of stock is maintained.\nStyling\n\nAssist in styling flowers on set during video and photoshoots in various locations.\nEnsure all shoot flowers are delivered on time and ready on set.\nStyle monthly product photography in our studio.\nAssist in creating seasonal installations and displays\nREQUIREMENTS\n\n1+ years experience\nStrong\u00a0floral design skills & creative eye.\n\nGood team player and enjoy mentoring junior members of the team.\nCreative and passionate about The Floristry brand.\nHighly organised.\nEnjoy a fast paced start-up environment.\nInterested candidates please submit your CV with expected salary by clicking Apply Now!\n\u00a0", "employment_types": ["Full Time"], "selling_points": [], "locations": ["Kwai Tsing Area"], "categories": ["Others", "Agriculture / Forestry / Fishing", "Others"], "post_time": "2022-01-03T02:42:34Z", "salary": {"currency": null, "max": null, "min": null, "period": "monthly", "term": null}, "salary_visible": false, "title_keywords": [], "responsibilities": ["daily operations"], "requirements": {"degrees": [], "majors": [], "languages": [], "language_level": [], "hard_skills": [], "soft_skills": [], "languages_combined": []}, "experience_required": {"duration": [], "field": []}}, {"job_id": "100003009004897", "location_code": "hk", "company": "Advance Engineering (Development) Ltd", "job_title": "\u82b1\u738b**", "description": "\n\u8077\u8cac :\u82b1\u738b\u5712\u85dd\u5de5\u4f5c\n\n\u8cc7\u6b77 :\u5c0f\u516d\u7a0b\u5ea6; 2\u5e74\u7d93\u9a57; \u4e00\u822c\u7cb5\u8a9e; \u4e00\u822c\u666e\u901a\u8a71; \u61c2\u95b1\u8b80\u4e2d\u6587\n\n\u5f85\u9047 :\u6bcf\u6708$14,500, \u6709\u4ea4\u901a\u6d25\u8cbc, \u4e0a\u53488\u6642\u81f3\u4e0b\u53485\u6642\u534a, \u6bcf\u9031\u5de5\u4f5c6\u5929,\u8f2a\u4f11, \u6bcf\u5929\u5de5\u4f5c 8.5 \u5c0f\u6642\n\n\u7533\u8acb\u9808\u77e5 :\u6c42\u8077\u8005\u53ef\u81f4\u96fb27432261\u8207\u83ef\u54e1\u90a8\u696d\u4e3b\u7acb\u6848\u6cd5\u5718\u4f0d\u5c0f\u59d0\u806f\u7d61\u3002\n\n", "employment_types": ["Full Time"], "selling_points": [], "locations": ["Tsing Yi"], "categories": ["Others", "Agriculture / Forestry / Fishing", "Others"], "post_time": "2021-12-29T03:11:27Z", "salary": {"currency": null, "max": null, "min": null, "period": "monthly", "term": null}, "salary_visible": false, "title_keywords": [], "responsibilities": [], "requirements": {"degrees": [], "majors": [], "languages": [], "language_level": [], "hard_skills": [], "soft_skills": [], "languages_combined": []}, "experience_required": {"duration": [], "field": []}}, {"job_id": "100003008996138", "location_code": "hk", "company": "Anglo Chinese Florist Limited", "job_title": "\u82b1\u85dd\u5e2b", "description": "\n\u8077\u8cac :\u8ca0\u8cac\u4e00\u822c\u5712\u4e01\u5de5\u4f5c\uff0c\u5712\u5703\u4e4b\u88c1\u7a2e\u4fdd\u990a\u5de5\u4f5c\uff0c\u5305\u62ec\u7a2e\u690d\uff0c\u6f86\u6c34\uff0c\u65bd\u80a5\uff0c\u4fee\u526a\u690d\u7269\uff0c\u4fee\u92f8\u6a39\u6728\uff0c\u9664\u8349\uff0c\u9664\u87f2\uff0c\u88c1\u7a2e\uff0c\u642c\u904b\u76c6\u683d\uff0c\u5712\u85dd\u6a5f\u68b0\u64cd\u4f5c\u7b49\u5de5\u4f5c\n\n\u8cc7\u6b77 :\u6c92\u6709\u5b78\u6b77\u8981\u6c42; 3\u5e74\u7d93\u9a57; \u826f\u597d\u7cb5\u8a9e; \u7565\u61c2\u8b80\u5beb\u4e2d\u6587\n\n\u5f85\u9047 :\u6bcf\u6708$13,500, \u6709\u9280\u884c\u5047\u671f, \u91ab\u7642\u798f\u5229\u53ca\u7a7f\u68ad\u5df4\u58eb\u670d\u52d9, \u661f\u671f\u4e00\u81f3\u516d: \u4e0a\u53488\u6642\u534a\u81f3\u4e0b\u53485\u6642, \u6bcf\u9031\u5de5\u4f5c5\u5929\u81f36\u5929, \u6bcf\u5929\u5de5\u4f5c 8.5 \u5c0f\u6642, \u661f\u671f\u516d\u9577\u77ed\u9031\n\n\u7533\u8acb\u9808\u77e5 :\u6c42\u8077\u8005\u53ef\u81f4\u96fb31231037\u8207\u90b5\u6c0f\u5f71\u57ce\u9999\u6e2f\u6709\u9650\u516c\u53f8\u5468\u5148\u751f\u806f\u7d61\u3002\n\n", "employment_types": ["Full Time"], "selling_points": [], "locations": ["Central"], "categories": ["Others", "Agriculture / Forestry / Fishing", "Building & Construction", "Others"], "post_time": "2021-12-23T05:36:04Z", "salary": {"currency": null, "max": null, "min": null, "period": "monthly", "term": null}, "salary_visible": false, "title_keywords": [], "responsibilities": [], "requirements": {"degrees": [], "majors": [], "languages": [], "language_level": [], "hard_skills": [], "soft_skills": [], "languages_combined": []}, "experience_required": {"duration": [], "field": []}}, {"job_id": "100003008993140", "location_code": "hk", "company": "euro go go Limited", "job_title": "\u5168\u8077\u6d17\u7897\u54e1", "description": "\n\u8077\u8cac :\u5354\u52a9\u4e00\u822c\u82b1\u5e97\u65e5\u5e38\u904b\u4f5c, \u63d0\u4f9b\u512a\u826f\u9867\u5ba2\u670d\u52d9, \u5982: \u88fd\u4f5c\u9bae\u82b1\u690d\u7269\u862d\u82b1; \u9700\u8981\u5076\u723e\u5728\u5916\u5de5\u4f5c, \u4f8b\u5982: \u5728\u5ba2\u6236\u7684\u8655\u6240\u5de5\u4f5c; \u9700\u5354\u52a9\u8a13\u7df4\u898b\u7fd2\u540c\u4e8b\n\n\u8cc7\u6b77 :\u4e2d\u4e94\u7a0b\u5ea6; 3\u5e74\u7d93\u9a57; \u826f\u597d\u7cb5\u8a9e\u512a\u5148; \u4e00\u822c\u666e\u901a\u8a71\u512a\u5148; \u4e00\u822c\u82f1\u8a9e\u512a\u5148; \u61c2\u8b80\u5beb\u4e2d\u6587; \u7565\u61c2\u8b80\u5beb\u82f1\u6587; \u5de5\u4f5c\u4e3b\u52d5, \u826f\u597d\u6e9d\u901a\u6280\u5de7, \u53cb\u5584\u5b88\u6642, \u5de5\u4f5c\u52e4\u596e\u7d30\u5fc3\n\n\u5f85\u9047 :\u6bcf\u6708$15,000 - $20,000, \u6709\u6bcf\u6708\u52e4\u5de5\u734e\u91d1$500, \u5e74\u50479\u5929, \u9280\u884c\u5047\u671f, \u914c\u60c5\u6027\u82b1\u7d05, \u8d85\u6642\u5de5\u4f5c\u6d25\u8cbc \u53ca\u71df\u696d\u734e\u91d1, \u661f\u671f\u4e00\u81f3\u516d: \u4e0a\u53488\u6642\u81f3\u4e0b\u53486\u6642/ \u4e0a\u53489\u6642\u81f3\u4e0b\u53487\u6642,\u661f\u671f\u65e5: \u4e0a\u53489\u6642\u81f3\u4e0b\u53487\u6642, \u6bcf\u9031\u5de5\u4f5c5\u5929\u81f36\u5929,\u8f2a\u4f11, \u6bcf\u5929\u5de5\u4f5c9\u5c0f\u6642, \u6bcf\u67086\u5929\u4f8b\u5047; \u9808\u65bc\u7bc0\u65e5\u5de5\u4f5c\n\n\u7533\u8acb\u9808\u77e5 :\u6c42\u8077\u8005\u53ef\u81f4\u96fb94422998\u8207\u4e2d\u897f\u82b1\u5e97\u6709\u9650\u516c\u53f8\u694a \u5c0f\u59d0\u806f\u7d61\u3002\n\n", "employment_types": ["Full Time"], "selling_points": [], "locations": ["Mong Kok"], "categories": ["Others", "Agriculture / Forestry / Fishing", "Hospitality / F & B", "Food & Beverage", "Others"], "post_time": "2021-12-22T07:05:16Z", "salary": {"currency": null, "max": null, "min": null, "period": "monthly", "term": null}, "salary_visible": false, "title_keywords": ["\u5168\u8077\u6d17\u7897\u54e1"], "responsibilities": [], "requirements": {"degrees": [], "majors": [], "languages": [], "language_level": [], "hard_skills": [], "soft_skills": [], "languages_combined": []}, "experience_required": {"duration": [], "field": []}}, {"job_id": "100003008992449", "location_code": "hk", "company": "Aquaculture Technologies Asia Limited", "job_title": "\u5ba4\u5167\u6f01\u5834\u990a\u6b96\u54e1", "description": "Responsibilities & Requirement:\n\nMin. 1+ year floral and gifts experience in retail or related products\nCreative, artificial flower, seasonal decor and home ware\nPassionate and sincere\nEfficient and well-organized\nWilling to work hard in any peak seasons\nGood team player\nWork in Sheung Wan Shop\nWork in creative environment\nFull-time package\n\nIf interested in the position please let us know your expected salary & floral portfolio and click \"Apply Now \"\n\n*Simple floral test at store is needed during interview", "employment_types": ["Full Time"], "selling_points": [], "locations": ["Not Specified"], "categories": ["Others", "Agriculture / Forestry / Fishing", "Others"], "post_time": "2021-12-22T04:57:37Z", "salary": {"currency": null, "max": null, "min": null, "period": "monthly", "term": null}, "salary_visible": false, "title_keywords": [], "responsibilities": [], "requirements": {"degrees": [], "majors": [], "languages": [], "language_level": [], "hard_skills": ["simple", "wan"], "soft_skills": ["passionate", "efficient", "good team player", "sincere", "interested in", "well-organized", "creative"], "languages_combined": []}, "experience_required": {"duration": ["1+ year"], "field": ["related", "retail"]}}, {"job_id": "100003008993928", "location_code": "hk", "company": "Toby World Limited", "job_title": "Florist / Senior Florist", "description": "\n\u8077\u8cac :\u4e00\u822c\u6e05\u6f54\u53ca\u5712\u85dd\u5de5\u4f5c\n\n\u8cc7\u6b77 :\u6c92\u6709\u5b78\u6b77\u8981\u6c42; \u4e00\u822c\u7cb5\u8a9e; \u7565\u61c2\u8b80\u5beb\u4e2d\u6587\n\n\u5f85\u9047 :\u6bcf\u5c0f\u6642$42.00, \u4e0a\u53487\u6642\u81f3\u4e0a\u534811\u6642\u6216\u4e0b\u53482\u6642\u81f3\u4e0b\u53486\u6642, \u6bcf\u9031\u5de5\u4f5c6\u5929,\u8f2a\u4f11, \u6bcf\u5929\u5de5\u4f5c 4 \u5c0f\u6642, \u661f\u671f\u65e5\u8f2a\u4f11\n\n\u7533\u8acb\u9808\u77e5 :\u6c42\u8077\u8005\u53ef\u50b3\u771f(24360463)\u6216\u96fb\u90f5(Apply Now)\u5c65\u6b77\u8868\u7d66\u5b9c\u5c45\u9867\u554f\u670d\u52d9\u6709\u9650\u516c\u53f8\u3002\u5982\u8981\u7d22\u53d6\u6536\u96c6\u500b\u4eba\u8cc7\u6599\u8072\u660e, \u8acb\u8207\u674e\u5c0f\u59d0(Tel:24955225)\u806f\u7d61\n\n", "employment_types": ["Full Time", "Part Time"], "selling_points": ["Sheung Wan", "Full-time package", "Work in creative environment"], "locations": ["Sheung Wan"], "categories": ["Others", "Agriculture / Forestry / Fishing", "Design", "Others", "Sales, CS & Business Devpt", "Retail Sales"], "post_time": "2021-12-22T09:49:58Z", "salary": {"currency": null, "max": null, "min": null, "period": "monthly", "term": null}, "salary_visible": false, "title_keywords": [], "responsibilities": [], "requirements": {"degrees": [], "majors": [], "languages": [], "language_level": [], "hard_skills": [], "soft_skills": [], "languages_combined": []}, "experience_required": {"duration": [], "field": []}}, {"job_id": "100003008992857", "location_code": "hk", "company": "Advance Engineering (Development) Ltd", "job_title": "\u82b1\u738b (\u77ed\u671f)", "description": "\n\u8077\u8cac :\u8ca0\u8cac\u5712\u85dd\u4fdd\u990a\u5de5\u4f5c\uff0c\u5305\u62ec\u6dcb\u6c34\u3001\u7a2e\u690d\u3001\u4fee\u526a\u3001\u65bd\u80a5\u3001\u5674\u85e5\u3001\u9664\u8349\u7b49\uff1b\u63a1\u8cfc\u53ca\u4f48\u7f6e\u82b1\u5349\u690d\u7269\uff1b\u5354\u52a9\u8655\u7406\u96dc\u52d9\uff1b\u57f7\u884c\u5176\u4ed6\u7372\u59d4\u6d3e\u7684\u5de5\u4f5c\n\n\u8cc7\u6b77 :\u5c0f\u516d\u7a0b\u5ea6; 5\u5e74\u7d93\u9a57; \u826f\u597d\u7cb5\u8a9e; \u61c2\u8b80\u5beb\u4e2d\u6587; \u61c2\u5712\u85dd\u7a2e\u690d\u53ca\u4e86\u89e3\u690d\u7269\u7279\u6027\uff1b\u61c2\u64cd\u4f5c\u5712\u85dd\u6a5f\u5668\uff0c\u5982\u6253\u8349\u6a5f\uff1b\u5fc5\u9808\u5177\u5099\u76f8\u95dc\u5de5\u4f5c\u8b49\u660e\u6587\u4ef6\uff1b\u8aa0\u5be6\u6709\u79ae\u53ca\u6709\u8cac\u4efb\u611f\n\n\u5f85\u9047 :\u6bcf\u6708$16,000 - $18,000, \u6709\u5e74\u504714\u5929, \u914c\u60c5\u6027\u82b1\u7d05, \u91ab\u7642\u798f\u5229 \u53ca\u8d85\u6642\u5de5\u4f5c\u6d25\u8cbc, \u661f\u671f\u4e00\u81f3\u516d: \u4e0a\u53488\u6642\u534a\u81f3\u4e0b\u53485\u6642\u534a, \u6bcf\u9031\u5de5\u4f5c6\u5929\n\n\u7533\u8acb\u9808\u77e5 :\u6c42\u8077\u8005\u53ef\u81f4\u96fb28791798\u8207\u745e\u5b89\u96c6\u5718\u7ba1\u7406\u6709\u9650\u516c\u53f8\u4f0d \u5c0f\u59d0\u806f\u7d61\u3002\n\n", "employment_types": ["Contract"], "selling_points": [], "locations": ["Tseung Kwan O"], "categories": ["Others", "Agriculture / Forestry / Fishing", "Others"], "post_time": "2021-12-22T06:25:59Z", "salary": {"currency": null, "max": null, "min": null, "period": "monthly", "term": null}, "salary_visible": false, "title_keywords": [], "responsibilities": [], "requirements": {"degrees": [], "majors": [], "languages": [], "language_level": [], "hard_skills": [], "soft_skills": [], "languages_combined": []}, "experience_required": {"duration": [], "field": []}}, {"job_id": "100003008995049", "location_code": "hk", "company": "Easy Living Consultant Limited", "job_title": "\u6e05\u6f54\u517c\u5712\u85dd\u5de5\u4eba", "description": "Responsibilities:\n\nAssist CTO in business development and project preparation; coordinate with various departments on a variety of projects;\nCooperate with internal and external parties in organizing, executing and completing the project milestones;\nIssue invoice, input sales record and review contract;\nKeep track and maintain good relationship with contractors;\nCarry out tasks assigned by CTO;\nOutdoor work is required;\nHandle ad hoc duties as assigned;\n\n\u00a0Requirements:\n\n5 years working experience, agricultural or fishery field is an advantage;\nHave a passion for local agriculture development;\nStrong people skill;\nProficiency in PC applications, e.g. Excel, Word Processing, Chinese word processing;\nGood command of written and spoken English and Mandarin;\n\nWe offer competitive salary package to suitable candidate.\u00a0 Interested parties, please send email for application form.", "employment_types": ["Part Time"], "selling_points": [], "locations": ["Tsing Yi"], "categories": ["Others", "Agriculture / Forestry / Fishing", "Building & Construction", "Others"], "post_time": "2021-12-23T02:52:55Z", "salary": {"currency": null, "max": null, "min": null, "period": "hourly", "term": null}, "salary_visible": false, "title_keywords": [], "responsibilities": ["ad hoc duties", "outdoor work", "invoice", "internal and external parties", "coordinate with", "review", "maintain good relationship", "executing", "cooperate with"], "requirements": {"degrees": [], "majors": [], "languages": ["english", "chinese", "mandarin"], "language_level": ["good command"], "hard_skills": ["excel", "chinese word processing", "word processing", "pc applications"], "soft_skills": ["passion for"], "languages_combined": [{"language": "english", "language_level": ["good command"]}, {"language": "chinese", "language_level": []}, {"language": "mandarin", "language_level": ["good command"]}]}, "experience_required": {"duration": ["5 years"], "field": []}}, {"job_id": "100003008985621", "location_code": "hk", "company": "Sun Hing City Limited", "job_title": "Shipping Clerk / Coordinator", "description": "\n\u8077\u8cac :\u8ca0\u8cac\u4ee5\u6d17\u7897\u789f\u6a5f\u6e05\u6d17\u9910\u5177\u53ca\u5eda\u623f\u5668\u5177,\u8ca0\u8cac\u4e00\u822c\u7c21\u55ae\u6e05\u6f54(\u8a66\u7528\u671f\u5f8c\u53ef\u7372\u5206\u6bcf\u6708\u9054\u6a19\u82b1\u7d05)\n\n\u8cc7\u6b77 :\u6c92\u6709\u5b78\u6b77\u8981\u6c42; \u4e00\u822c\u7cb5\u8a9e; \u7565\u61c2\u8b80\u5beb\u4e2d\u6587; \u6ce8\u91cd\u885b\u751f, \u6709\u79ae\u8c8c, \u5de5\u4f5c\u7a4d\u6975, \u5c0d\u5de5\u4f5c\u6709\u71b1\u8aa0\n\n\u5f85\u9047 :\u6bcf\u6708$15,000, \u6709\u71df\u696d\u734e\u91d1, \u54e1\u5de5\u8cfc\u7269\u512a\u60e0, \u4f9b\u81b3\u98df, \u8d85\u6642\u5de5\u4f5c\u6d25\u8cbc, \u6649\u5347\u6a5f\u6703, \u751f\u65e5\u734e\u8cde\u53ca\u4ecb\u7d39\u4eba\u734e\u91d1, \u4e0a\u534811\u6642\u81f3\u4e0b\u534811\u6642, \u6bcf\u9031\u5de5\u4f5c6\u5929,\u8f2a\u73ed,\u8f2a\u4f11, \u6bcf\u5929\u5de5\u4f5c 8 \u5c0f\u6642\n\n\u7533\u8acb\u9808\u77e5 :\u6c42\u8077\u8005\u53ef\u81f4\u96fb23579080\u8207EURO GO GO (09) LIMITED\u9673\u5148\u751f\u806f\u7d61\u3002\n\n", "employment_types": ["Full Time"], "selling_points": ["Working Area: Kwai Chung", "5.5 working days", "Immediate available is highly preferred"], "locations": ["Kwai Hing"], "categories": ["Others", "Agriculture / Forestry / Fishing", "Hospitality / F & B", "Food & Beverage", "Merchandising & Purchasing", "Procurement / Purchasing / Sourcing"], "post_time": "2021-12-19T08:34:30Z", "salary": {"currency": null, "max": null, "min": null, "period": "monthly", "term": null}, "salary_visible": false, "title_keywords": ["coordinator", "shipping clerk"], "responsibilities": [], "requirements": {"degrees": [], "majors": [], "languages": [], "language_level": [], "hard_skills": ["go"], "soft_skills": [], "languages_combined": []}, "experience_required": {"duration": [], "field": []}}, {"job_id": "100003008991714", "location_code": "hk", "company": "Watami (China) Co. Ltd", "job_title": "(\u6025\u8acb)\u5168\u8077\u6d17\u7897\u54e1", "description": "\n\u8077\u8cac :\u6f01\u5834\u6046\u5e38\u5de5\u4f5c (\u9935\u9b5a, \u6e05\u6f54, \u9700\u9ad4\u529b\u52de\u52d5\u5de5\u4f5c\u7b49) (\u5de5\u4f5c\u6642\u6709\u6a5f\u6703\u6cbe\u6fd5\u8eab\u9ad4)\n\n\u8cc7\u6b77 :\u4e2d\u4e00\u7a0b\u5ea6; \u4e00\u822c\u7cb5\u8a9e; \u61c2\u8b80\u5beb\u4e2d\u6587\n\n\u5f85\u9047 :\u6bcf\u6708$13,000 - $13,500, \u6709\u96d9\u7ce7, \u81b3\u98df\u6d25\u8cbc, \u8d85\u6642\u5de5\u4f5c\u6d25\u8cbc \u53ca\u8f2a\u73ed\u6d25\u8cbc, \u4e0a\u53488\u6642\u534a\u81f3\u4e0b\u53486\u6642, \u6bcf\u9031\u5de5\u4f5c6\u5929,\u8f2a\u73ed,\u8f2a\u4f11, \u6bcf\u5929\u5de5\u4f5c 8.5 \u5c0f\u6642\n\n\u7533\u8acb\u9808\u77e5 :\u6c42\u8077\u8005\u53ef\u81f4\u96fb24723188\u8207\u4e9e\u6d32\u6c34\u7522\u990a\u6b96\u79d1\u6280\u6709\u9650\u516c\u53f8\u7c21 \u5c0f\u59d0\u806f\u7d61\u3002\n\n", "employment_types": ["Full Time"], "selling_points": [], "locations": ["Not Specified"], "categories": ["Others", "Agriculture / Forestry / Fishing", "Hospitality / F & B", "Food & Beverage", "Others"], "post_time": "2021-12-22T03:49:58Z", "salary": {"currency": null, "max": null, "min": null, "period": "monthly", "term": null}, "salary_visible": false, "title_keywords": [], "responsibilities": [], "requirements": {"degrees": [], "majors": [], "languages": [], "language_level": [], "hard_skills": [], "soft_skills": [], "languages_combined": []}, "experience_required": {"duration": [], "field": []}}, {"job_id": "100003008994734", "location_code": "hk", "company": "Yangtzekiang Garment Ltd", "job_title": "General Manager", "description": "\nLQV was created in Paris in 2010 by a group of wine & food lovers.\nSuccess quickly happened and four years later, LQV expanded in Hong Kong with a first Wine Bar in Wan Chai. Now, LQV Group runs a total of 7 outlets in Hong Kong including wine bars, restaurants, retail shops and bakeries with the same philosophy as its early days: import the finest products directly from France.\nLQV is looking for his new General Manager for his Brand new created Flagship Wine and Dine Concept in the heart of Central that is set to rock the hospitality scene in Hong Kong with classy yet relax place where client will enjoy an exceptional French wine selection (+1500 French Wines) to pair with Fine French food.\nResponsibilities:\n\u00b7 Manage daily operations for the Restaurant\n\u00b7 Deliver superior service and maximize customer satisfaction\n\u00b7 Respond efficiently and accurately to customer complaints\n\u00b7 Organize and supervise shifts\n\u00b7 Appraise staff performance and provide feedback to improve productivity\n\u00b7 Ensure compliance with sanitation and safety regulations\n\u00b7 Organize weekly event around French food and wine\n\u00b7 Manage restaurant\u2019s good image and suggest ways to improve it\n\u00b7 Promote the brand in the local community through word-of-mouth and restaurant events\n\u00b7 Train new and current employees on proper customer service practices\n\u00b7 Implement policies and protocols that will maintain future restaurant operations\nRequirement:\n\u00b7 4+ years of experience relevant working background with at least 3 years' management experience leading a team\n\u00b7 Proficient in managing the floor during busy services without compromising the quality of the service standard set by the company.\n\u00b7 Strong operational skills in a customer service environment\n\u00b7 Good communication & motivational skills\n\u00b7 Proactive, disciplined and punctual\n\u00b7 English speaking is a must, French speaking is a plus\nBenefit\nStaff Discount in all of our Establishments\n500HKD of Christmas Voucher\nAttractive salary and benefits for the right candidate + Tips\nAre you ready to begin a new professional challenge and join LQV's family ? Don't hesitate and apply !\nJob Type: Full-time\nSalary: From $30,000.00 per month\n\n", "employment_types": ["Contract"], "selling_points": [], "locations": ["Not Specified"], "categories": ["Others", "Agriculture / Forestry / Fishing", "Building & Construction", "Others"], "post_time": "2021-12-23T02:24:24Z", "salary": {"currency": null, "max": null, "min": null, "period": "monthly", "term": null}, "salary_visible": false, "title_keywords": ["general manager"], "responsibilities": ["regulations", "customer complaints", "policies", "operations", "ensure compliance", "customer service", "maintain", "manage daily operations"], "requirements": {"degrees": [], "majors": [], "languages": ["english", "french"], "language_level": [], "hard_skills": ["plus"], "soft_skills": ["communication", "customer service", "proactive"], "languages_combined": [{"language": "english", "language_level": []}, {"language": "french", "language_level": []}]}, "experience_required": {"duration": ["at least 3 years", "4+ years"], "field": ["management", "team"]}}, {"job_id": "100003008991411", "location_code": "hk", "company": "Le Quinze Vins Limited", "job_title": "General Manager", "description": "\n\u8077\u8cac :\u8ca0\u8cac\u4e00\u822c\u5712\u85dd\u53f8\u6a5f\u5de5\u4f5c, \u99d5\u99db5.5\u5678\u8ca8\u8eca, \u65bc\u4e0a\u6c34\u53d6\u8eca\n\n\u8cc7\u6b77 :\u5c0f\u516d\u7a0b\u5ea6; 1\u5e74\u7d93\u9a57; \u826f\u597d\u7cb5\u8a9e; \u61c2\u8b80\u5beb\u4e2d\u6587; \u6301\u6709\u5e73\u5b89\u54ad; \u6301\u6709\u8f15\u578b\u8ca8\u8eca\u99d5\u99db\u57f7\u7167; \u6301\u6709\u79c1\u5bb6\u8eca\u99d5\u99db\u57f7\u7167; \u6301\u6709\u5efa\u9020\u696d\u5de5\u4eba\u8a3b\u518a\u8b49; \u523b\u82e6, \u6709\u8cac\u4efb\u5fc3, \u5177\u5712\u85dd\u5de5\u4f5c\u7d93\u9a57\u512a\u5148\n\n\u5f85\u9047 :\u6bcf\u65e5$720.00 - $750.00, \u6709\u4f9b\u81b3\u98df, \u4e0a\u53487\u6642\u534a\u81f3\u4e0b\u53485\u6642, \u6bcf\u9031\u5de5\u4f5c6\u5929\n\n\u7533\u8acb\u9808\u77e5 :\u6c42\u8077\u8005\u53ef\u81f4\u96fb26685959\u8207\u632f\u8208\u5712\u85dd\u5de5\u7a0b\u6709\u9650\u516c\u53f8\u6881\u5c0f\u59d0\u806f\u7d61\u3002\n\n", "employment_types": ["Full Time"], "selling_points": [], "locations": ["Central"], "categories": ["Others", "Agriculture / Forestry / Fishing", "Building & Construction", "Others"], "post_time": "2021-12-22T03:24:21Z", "salary": {"currency": null, "max": null, "min": null, "period": "monthly", "term": null}, "salary_visible": false, "title_keywords": ["general manager"], "responsibilities": [], "requirements": {"degrees": [], "majors": [], "languages": [], "language_level": [], "hard_skills": [], "soft_skills": [], "languages_combined": []}, "experience_required": {"duration": [], "field": []}}, {"job_id": "100003008991906", "location_code": "hk", "company": "Hong Kong Food Services Limited", "job_title": "\u5168\u8077\u6d17\u7897\u54e1", "description": "\n\u8077\u8cac :\u8ca0\u8cac\u82b1\u5712\u5712\u85dd (\u5305\u62ec\u6dcb\u6c34\u3001\u4fee\u526a\u3001\u65bd\u80a5\u3001\u8655\u7406\u87f2\u5bb3\u7b49); \u7c21\u55ae\u7dad\u4fee\u53ca\u4e0a\u53f8\u6307\u6d3e\u4e4b\u6709\u95dc\u5de5\u4f5c\n\n\u8cc7\u6b77 :\u6c92\u6709\u5b78\u6b77\u8981\u6c42; \u826f\u597d\u7cb5\u8a9e; \u61c2\u8b80\u5beb\u4e2d\u6587; \u6301\u6709\u5e73\u5b89\u54ad; \u523b\u82e6, \u6709\u79ae\n\n\u5f85\u9047 :\u6bcf\u6708$12,000 - $14,000, \u6709\u5e74\u504710\u5929, \u914c\u60c5\u6027\u82b1\u7d05 \u53ca\u91ab\u7642\u798f\u5229, \u4e0a\u53488\u6642\u534a\u81f3\u4e0b\u53485\u6642\u534a, \u6bcf\u9031\u5de5\u4f5c6\u5929,\u8f2a\u4f11, \u5de5\u4f5c\u671f2\u500b\u6708, \u6bcf\u5929\u5de5\u4f5c 9 \u5c0f\u6642\n\n\u7533\u8acb\u9808\u77e5 :\u6c42\u8077\u8005\u53ef\u81f4\u96fb21511717\u8207\u9818\u99ff\u5de5\u7a0b\u767c\u5c55\u6709\u9650\u516c\u53f8\u694a\u5148\u751f\u806f\u7d61\u3002\n\n", "employment_types": ["Full Time"], "selling_points": [], "locations": ["Kwai Hing"], "categories": ["Others", "Agriculture / Forestry / Fishing", "Hospitality / F & B", "Food & Beverage", "Others"], "post_time": "2021-12-22T04:05:50Z", "salary": {"currency": null, "max": null, "min": null, "period": "monthly", "term": null}, "salary_visible": false, "title_keywords": ["\u5168\u8077\u6d17\u7897\u54e1"], "responsibilities": [], "requirements": {"degrees": [], "majors": [], "languages": [], "language_level": [], "hard_skills": [], "soft_skills": [], "languages_combined": []}, "experience_required": {"duration": [], "field": []}}, {"job_id": "100003008993210", "location_code": "hk", "company": "OnTheList Limited", "job_title": "General Manager", "description": "\n\u8077\u8cac :\u6e05\u6d17\u7897\u789f, \u9910\u5ef3\u6d17\u7897, \u6e05\u6f54\u9910\u5177\u53ca\u5eda\u5177, \u6e05\u6f54\u5eda\u623f, \u64cd\u4f5c\u6d17\u7897\u789f\u6a5f, \u65e5\u5e38\u9910\u5ef3\u6e05\u6f54\n\n\u8cc7\u6b77 :\u5c0f\u4e09\u7a0b\u5ea6; 1\u5e74\u7d93\u9a57; \u826f\u597d\u7cb5\u8a9e; \u4e00\u822c\u666e\u901a\u8a71; \u61c2\u95b1\u8b80\u4e2d\u6587; \u61c2\u95b1\u8b80\u82f1\u6587\n\n\u5f85\u9047 :\u6bcf\u6708$14,500 - $15,000, \u6709\u5e74\u504710\u5929, \u91ab\u7642\u798f\u5229, \u4f9b\u81b3\u98df \u53ca\u8d85\u6642\u5de5\u4f5c\u88dc\u5047, \u661f\u671f\u4e00\u81f3\u516d: \u4e0a\u534811\u6642\u81f3\u4e0b\u534810\u6642, \u661f\u671f\u65e5: \u4e0a\u534811\u6642\u81f3\u4e0b\u534811\u6642, \u6bcf\u9031\u5de5\u4f5c6\u5929, \u8f2a\u73ed, \u8f2a\u4f11, \u6bcf\u5929\u5de5\u4f5c 8 \u5c0f\u6642\n\n\u7533\u8acb\u9808\u77e5 :\u6c42\u8077\u8005\u53ef\u81f4\u96fb37582163\u8207\u4f73\u5049\u9910\u98f2\u6709\u9650\u516c\u53f8\u5bb9\u5c0f\u59d0\u806f\u7d61\u3002\n\n", "employment_types": ["Full Time"], "selling_points": [], "locations": ["Not Specified"], "categories": ["Others", "Agriculture / Forestry / Fishing", "Building & Construction", "Others"], "post_time": "2021-12-22T07:15:32Z", "salary": {"currency": null, "max": null, "min": null, "period": "monthly", "term": null}, "salary_visible": false, "title_keywords": ["general manager"], "responsibilities": [], "requirements": {"degrees": [], "majors": [], "languages": [], "language_level": [], "hard_skills": [], "soft_skills": [], "languages_combined": []}, "experience_required": {"duration": [], "field": []}}]