[{"job_id": "100003009055157", "location_code": "hk", "company": "Hong Kong Arts Development Council", "job_title": "International Programmes Officer (Job ref: IPO-2207-JDB)", "description": "Responsible for supporting Team Supervisor in the implementation of various projects, in particular cultural exchange projects.\u00a0 Duties include project coordination and logistics, liaison with artists and different parties, preparation of online and offline publicity materials, committee papers and meetings, as well as general administrative work.\n\nRequirements:\n\nA university degree with at least 3-year experience in project coordination, preferably in arts sectors\nStrong analytical skill, well-organised and detail-oriented\nAble to work under pressure and strong adaptability to situations\nA good team player with good interpersonal and communication skills\nGood command of written and spoken English, Cantonese and Putonghua\nProficiency in PC operations (MS based applications and Chinese Word Processing)\nWell understanding and strong interest in arts scene in Hong Kong will be an advantage\n\nSalary offered will be commensurate with qualifications and experience. Interested persons, please send CV with details on education and work experience, stating salary history and expected salary, and indicating your earliest availability to the Human Resources Department, 10/F, 1063 King\u2019s Road, Quarry Bay, Hong Kong no later than 7 February 2022.\u00a0 Please quote the job reference on the envelope.\n\n\u00a0Applicants not invited for interview within 16 weeks from the closing date for application may assume that their applications are unsuccessful.\u00a0 Personal data collected will be treated in strictest confidence and will only be used for recruitment purposes. HKADC reserves the right to consider late applications and not to make appointment for the post advertised.\u00a0 We do not accept applications through e-mail or fax.\n\n\u00a0\nHKADC is an Equal Opportunities Employer", "employment_types": ["Full Time", "Permanent"], "selling_points": [], "locations": ["Quarry Bay"], "categories": ["Admin & HR", "Clerical / Admin Staff", "Others", "Entertainment - Artists / Singers / Musicians", "Marketing / Public Relations", "Marketing - General / Support"], "post_time": "2022-01-18T03:27:39Z", "salary": {"currency": null, "max": null, "min": null, "period": "monthly", "term": null}, "salary_visible": false, "title_keywords": ["officer"], "responsibilities": ["administrative work", "project coordination", "operations", "implementation", "communication", "logistics", "recruitment", "personal data", "work under pressure"], "requirements": {"degrees": ["university degree"], "majors": [], "languages": ["cantonese", "putonghua", "english", "chinese"], "language_level": ["proficiency", "good command"], "hard_skills": ["analytical skill", "no", "chinese word processing", "pc operations", "make", "ms based applications", "exchange"], "soft_skills": ["communication skills", "analytical skill", "good team player", "confidence", "responsible", "detail-oriented", "adaptability", "coordination", "well-organised", "interpersonal", "work under pressure"], "languages_combined": [{"language": "cantonese", "language_level": ["good command"]}, {"language": "putonghua", "language_level": ["good command"]}, {"language": "english", "language_level": ["good command"]}, {"language": "chinese", "language_level": ["proficiency"]}]}, "experience_required": {"duration": ["at least 3-year"], "field": ["human resources", "education"]}}, {"job_id": "100003009056325", "location_code": "hk", "company": "Asia Innovations HK Limited", "job_title": "Entertainment Talent Manager", "description": "We are Leading live streaming company in the world. Now we are looking for:\n\nEntertainment Talent Manager\n\nResponsibilities:\n\nPerform end-to-end recruitment of live streamer and KOL including sourcing, CV screening, interviewing, etc.\n\nAssist in streamers management, training, communication, coordination and casting\nMonitor, measure and review streamers\u2019 and KOL\u2019s performance timely\nCoordinating and liaising with marketing and operation teams for sales campaign\nConsolidate and prepare various streamers\u2019 and KOL\u2019s performance analytics reports and presentations for management review\nProvide on-site support during events or company promotions\n\nRequirements:\n\n1-2 years' relevant work experience in business development or similar field preferred\nSounds knowledgeable in entertainment trend and live streaming business\nSensitive on marketing trend and numbers\nExcellent communication and interpersonal skills with positive and \u201ccan-do\u201d attitudes\nAble to work independent, under pressure and adopt fast pace environment\nGood command in both written and spoken English, Chinese and Mandarin\nImmediate available will be an advantage\n\n\nWe Offer:\n\n\u00a0Basic Salary with Commission Package\nAttractive bonus or project bonus (depends on performance)\nFriendly and professional working environment\nExcellent career path\nWell-structured on-job training program\u00a0\n\nWelcome young, energetic and strong motivation candidates!\u00a0", "employment_types": ["Full Time"], "selling_points": [], "locations": ["Tsim Sha Tsui"], "categories": ["Sales, CS & Business Devpt", "Business Development", "Others", "Entertainment - Artists / Singers / Musicians", "Media & Advertising", "Broadcasting - TV / Radio"], "post_time": "2022-01-18T03:57:54Z", "salary": {"currency": null, "max": null, "min": null, "period": "monthly", "term": null}, "salary_visible": false, "title_keywords": ["manager"], "responsibilities": ["management", "cv screening", "review", "monitor", "liaising with", "teams", "presentations", "communication", "recruitment", "reports", "coordination", "management review"], "requirements": {"degrees": [], "majors": [], "languages": ["english", "chinese", "mandarin"], "language_level": ["good command"], "hard_skills": [], "soft_skills": ["independent", "under pressure", "communication and interpersonal skills", "can-do", "sensitive", "positive"], "languages_combined": [{"language": "english", "language_level": ["good command"]}, {"language": "chinese", "language_level": ["good command"]}, {"language": "mandarin", "language_level": ["good command"]}]}, "experience_required": {"duration": ["1-2 years"], "field": ["business development"]}}, {"job_id": "100003009051714", "location_code": "hk", "company": "Promotion", "job_title": "Online\u5ee3\u544a\u6f14\u54e1,Online\u7522\u54c1model,\u96fb\u8996\u5ee3\u544a\u6f14\u54e1,Part time model", "description": "\n\n\u8ca0\u8cac\u62cd\u651donline\u5ee3\u544a,\u96fb\u8996\u5ee3\u544a,\u5ba3\u50b3\u63a8\u5ee3,hair show, Event \u5de5\u4f5c\u7b49\u7b49.\n\u6c42\u8077\u8005\u78ba\u5be6\u5c0d\u9019\u9805\u5de5\u4f5c\u6709\u8208\u8da3\u624d\u7533\u8acb\u9019\u8077\u4f4d,\u8b1d\u8b1d!\n\u5de5\u4f5c\u985e\u578b: \u517c\u8077,\u9577\u671f\u5408\u4f5c\n\u85aa\u916c: \u6bcf\u65e5 $1,000.00-$3,000.00\n\u8ca0\u8cac\u63a8\u5ee3\u4e16\u754c\u77e5\u540d\u54c1\u724c:\nwebsite: www.online-entertainmenthk.com\nJob reference: https://www.online-entertainmenthk.com/index.php/job-reference\n\n\u9700\u52e4\u596e\u6e96\u6642:\n\u6b61\u8fce\u4efb\u4f55\u5e74\u9f61 : \u7537\u5973 /\u5152\u7ae5 /\u9752\u5c11\u5e74\n\u6d3b\u6f51\u958b\u6717,\u53c3\u8207\u8868\u6f14\n\n*\u63d0\u4f9b\u514d\u8cbb\u5728\u8077\u57f9\u8a13,\u672c\u516c\u53f8\u4e0d\u6703\u6536\u53d6\u4efb\u4f55\u8cbb\u7528\n\u8acb\u9810\u5099\u5c08\u696d\u7167\u7247\u53ca\u5c08\u696d\u8996\u983b,\u5982\u672a\u80fd\u63d0\u4f9b,\u672c\u516c\u53f8\u4ea6\u53ef\u7d66\u4e88\u5354\u52a9.\n\n\u6b32\u4e86\u89e3\u8a73\u60c5,\u8acb\u6e9c\u7060\u672c\u516c\u53f8\u7db2\u7ad9\u6709\u95dc\u516c\u53f8\u80cc\u666f,\u4f01\u696d\u5408\u4f5c\u5925\u4f34\u53ca\u5de5\u4f5c\u6027\u8cea:\n\u2606\u6c42\u8077\u8005\u78ba\u5be6\u5c0d\u9019\u9805\u5de5\u4f5c\u6709\u8208\u8da3\u624d\u7533\u8acb\u9019\u8077\u4f4d,\u8b1d\u8b1d!\n\n\u806f\u7e6b\u4eba: \u4eba\u529b\u8cc7\u6e90\u90e8\n\u96fb\u8a71: (852) 9602 4283\n\u5de5\u4f5c\u985e\u578b: \u5168\u8077, \u517c\u8077, \u81e8\u6642\n\u85aa\u916c:\u6bcf\u65e5 $1,000.00-$3,000.00", "employment_types": ["Full Time", "Part Time", "Temporary", "Freelance"], "selling_points": [], "locations": ["Not Specified"], "categories": ["Others", "Entertainment - Artists / Singers / Musicians", "Media & Advertising", "Photography / Video"], "post_time": "2022-01-16T21:51:04Z", "salary": {"currency": null, "max": null, "min": null, "period": "hourly", "term": null}, "salary_visible": false, "title_keywords": ["\u96fb\u8996\u5ee3\u544a\u6f14\u54e1", "part time model"], "responsibilities": ["website"], "requirements": {"degrees": [], "majors": [], "languages": [], "language_level": [], "hard_skills": ["php"], "soft_skills": [], "languages_combined": []}, "experience_required": {"duration": [], "field": []}}, {"job_id": "100003009051160", "location_code": "hk", "company": "The Hong Kong Philharmonic Society Limited", "job_title": "Arts Administration Trainee", "description": "Fresh graduates who are passionate about classical music and wish to pursue a career in arts administration are welcome to apply.\u00a0The successful applicant will have the opportunity to gain on-the-job experience in different functions of the HK Phil Management Office.\n\nAttributes:\n\nHong Kong permanent resident with a university degree in arts or music, or a related field;\nA team player with strong interpersonal and presentation skills;\nExcellent command of spoken and written English and Chinese;\nKnowledge of and interest in classical music;\nKnowledge and/or experience in performing arts a definite advantage.\n\nThis position is supported under the Leisure and Cultural Services Department\u2019s Arts Administrator Trainee Programme. The successful applicant will be appointed on a 1-year fixed-term contract with renewal possibility of not more than 3 years.\u00a0 Applicants should send a detailed resume\u00a0indicating current and expected salaries to email.\n\nApplication deadline: 24 January 2022.\u00a0 All applications will be treated in the strictest confidence.\n\n\n\u00a0\u00a0www.hkphil.org\n\n(Personal data collected will be used for recruitment purpose only)", "employment_types": ["Full Time", "Contract"], "selling_points": [], "locations": ["Tsim Sha Tsui"], "categories": ["Others", "Entertainment - Artists / Singers / Musicians", "Marketing / Public Relations", "Marketing - General / Support", "Student / Fresh Graduate / No Experience"], "post_time": "2022-01-15T03:48:52Z", "salary": {"currency": null, "max": null, "min": null, "period": "monthly", "term": null}, "salary_visible": false, "title_keywords": ["trainee"], "responsibilities": ["recruitment", "management", "personal data", "administration"], "requirements": {"degrees": ["university degree"], "majors": ["music"], "languages": ["english", "chinese"], "language_level": ["excellent"], "hard_skills": [], "soft_skills": ["confidence", "presentation skills", "team player", "interpersonal", "passionate about", "detailed"], "languages_combined": [{"language": "english", "language_level": ["excellent"]}, {"language": "chinese", "language_level": ["excellent"]}]}, "experience_required": {"duration": [], "field": ["management"]}}, {"job_id": "100003009046186", "location_code": "hk", "company": "Hong Kong Arts Development Council", "job_title": "Business Development & International Programmes Senior Manager (Job ref: BDIPSM-2205-JDB)", "description": "The successful candidate will be responsible for supporting the team supervisor in handling grant schemes and pro-active projects. Duties include but are not limited to processing grant applications, communicating with stakeholders in the arts sector, drafting correspondences, discussion papers and minutes of meetings, and coordinating general administrative work as directed by the team supervisor.\n\nRequirements:\n\nUniversity degree with minimum 4 years full-time working experience. \u00a0Candidates with less experience will be considered as Arts Development Officer\nPleasant personality with tactful and professional communication skills. Good writing skills in both English and Chinese. Proficiency in Putonghua will be an advantage\nProficiency in PC operations (MS Office applications and Chinese Word Processing)\nStrong analytical skills and ability to handle numerical data\nStrong sense of responsibility, self-motivated, detail-oriented and well-organised\nKnowledge and interest in Drama and /or Xiqu are a definite advantage\n\nSalary offered will be commensurate with qualifications and experience. Interested persons may send their CV with details on education and work experience, on salary history and expected salary, and indication of the earliest availability to the Human Resources Department, 10/F, 1063 King\u2019s Road, Quarry Bay, Hong Kong no later than 26 January 2022. Please quote the job reference on the envelope.\n\nApplicants not invited for interview within 16 weeks from the closing date for application may assume that their applications are unsuccessful.\u00a0 Personal data collected will be treated in strictest confidence and will only be used for recruitment purposes. HKADC reserves the right to consider late applications and not to make appointment for the post advertised.\u00a0 We do not accept applications through e-mail or fax.\n\nHKADC is an Equal Opportunities Employer", "employment_types": ["Full Time", "Permanent"], "selling_points": [], "locations": ["Quarry Bay"], "categories": ["Sales, CS & Business Devpt", "Business Development", "Others", "Entertainment - Artists / Singers / Musicians", "Management", "General Management"], "post_time": "2022-01-14T06:46:35Z", "salary": {"currency": null, "max": null, "min": null, "period": "monthly", "term": null}, "salary_visible": false, "title_keywords": ["senior manager"], "responsibilities": ["administrative work", "data", "operations", "communication", "communicating with", "recruitment", "personal data"], "requirements": {"degrees": ["university degree"], "majors": [], "languages": ["putonghua", "english", "chinese"], "language_level": ["advantage", "proficiency", "good"], "hard_skills": ["no", "chinese word processing", "pc operations", "writing skills", "analytical skills", "make", "processing", "ms office"], "soft_skills": ["communication skills", "self-motivated", "confidence", "responsible", "sense of responsibility", "writing skills", "pleasant", "analytical skills", "detail-oriented", "pro-active", "well-organised", "tactful"], "languages_combined": [{"language": "putonghua", "language_level": ["proficiency", "advantage"]}, {"language": "english", "language_level": ["good"]}, {"language": "chinese", "language_level": ["good"]}]}, "experience_required": {"duration": ["minimum 4 years"], "field": ["development", "human resources", "education"]}}, {"job_id": "100003009045080", "location_code": "hk", "company": "Hong Kong Dance Alliance Limited", "job_title": "Editorial Trainee / Assistant", "description": "We are now looking for a Senior Manager who will be responsible for business development and international programmes of the Hong Kong Arts Development Council. He/she reports directly to the Chief Executive and assists in devising, implementing and evaluation of large-scale activities. He/she will be a leader of several teams in carrying out proactive projects and schemes under his/her charge.\n\nRequirements:\n\nUniversity degree with at least 8 years of relevant full-time working experience in arts and culture, including project management experience;\nStrong administrative, analytical and strategy development capacity and skills;\nExcellent communication skills in both written and spoken English and Chinese;\nStrong sense of responsibility, self-motivation and an aptitude for innovation and change;\nProven achievements that demonstrate professional capabilities in organization, arts administration, proactiveness and people management;\nReadiness to work under pressure and deliver work of the highest quality;\nProficiency in PC operations (MS Office applications and Chinese Word Processing);\nPrevious experience with NGOs and public organisations will be an added value\n\nSalary offered will be commensurate with qualifications and experience. Interested persons please send CV with details on education and work experience, stating salary history and expected salary, and indicating your earliest availability to the Human Resources Department, 10/F, 1063 King\u2019s Road, Quarry Bay, Hong Kong no later than 4 February 2022. Please quote the job reference on the envelope.\n\nApplicants not invited for interview within 16 weeks from the closing date for application may assume that their applications are unsuccessful. Personal data collected will be treated in strictest confidence and will only be used for recruitment purposes. HKADC reserves the right to consider late applications and not to make appointment for the post advertised. We do not accept applications through e-mail or fax.\n\nHKADC is an Equal Opportunities Employer", "employment_types": ["Full Time"], "selling_points": [], "locations": ["Sheung Wan"], "categories": ["Media & Advertising", "Editorial / Journalism", "Others", "Entertainment - Artists / Singers / Musicians", "Student / Fresh Graduate / No Experience"], "post_time": "2022-01-13T07:06:49Z", "salary": {"currency": null, "max": null, "min": null, "period": "monthly", "term": null}, "salary_visible": false, "title_keywords": ["assistant", "trainee"], "responsibilities": ["management", "work under pressure", "operations", "teams", "quality", "communication", "project management", "reports", "recruitment", "evaluation", "personal data", "administration"], "requirements": {"degrees": ["university degree"], "majors": ["project management"], "languages": ["english", "chinese"], "language_level": ["excellent", "proficiency"], "hard_skills": ["no", "chinese word processing", "pc operations", "project management", "make", "ms office"], "soft_skills": ["communication skills", "confidence", "responsible", "sense of responsibility", "project management", "self-motivation", "proactive", "work under pressure"], "languages_combined": [{"language": "english", "language_level": ["excellent"]}, {"language": "chinese", "language_level": ["excellent", "proficiency"]}]}, "experience_required": {"duration": ["at least 8 years"], "field": ["project management", "human resources", "education"]}}, {"job_id": "100003009044071", "location_code": "hk", "company": "Hong Kong Arts Development Council", "job_title": "Arts Development Senior Officer/ Officer (Job Ref: ADSO-2204-JDB)", "description": "Hong Kong Dance Alliance Limited\nThe Hong Kong Dance Alliance is a non-profit-making body that supports and promotes all forms of dance in Hong Kong. Our projects include publishing the bi-monthly periodical dance journal/hk, presenting new works by young choreographers in \u2018New Force in Motion\u2019 Series and organizing the annual Hong Kong Dance Awards.\n\ndance journal/hk\nAs the only printed periodical devoted exclusively to dance in Hong Kong, it provides a platform for reviews, in-depth critiques, regular columns and feature articles on dance, dancers, dance educators, dance audiences, and the broader Hong Kong dance industry.\u00a0\n\nWe are looking for a full-time Editorial Trainee / Assistant to assist the editorial team in shaping and implementing the publication and publicity for the Alliance.\n\nDuties include:\n\nWorking closely with the editorial team to formulate the editorial direction of every issue and corresponding articles of dance journal/hk\nHandling the production and distribution of dance journal/hk, such as coordinating interviews, articles write-up and translation, managing online publications, contacting designers, printing houses and distribution points\nAdministering the online platforms of dance journal/hk\nAssisting in monitoring the production schedule and maintaining accurate documentation\nSupporting the logistics of advertisement services to deliver promotional packages for clients\nCollaborating with the office team to produce publicity materials for the Alliance as necessary\n\nSuitable candidates should:\n\nBe a Hong Kong permanent resident of age 18 or above possessing a recognised university degree in journalism / arts administration / cultural studies / languages / communications, which was obtained within the past 3 years\nPreferably have 1-2 year(s) of work experience; fresh graduates are also welcome\nBe a responsible and self-motivated team player who is able to work independently and under pressure\nBe comfortable with meeting tight schedules and possible follow-up work during unconventional hours\nBe detail-oriented and always strive for accuracy and precision\nDemonstrate strong communication, organizational and interpersonal skills\nBe familiar with and interested in the publishing and/or performing arts industry\u00a0\u00a0\nWrite and speak fluent English and Chinese\nHave elementary knowledge in creating content for social media\n\nCandidates with less experience may be considered for the position of Editorial Trainee. Immediate availability is highly preferred.\n\nInterested parties are invited to send in a detailed CV with a cover letter in English indicating current and expected salaries along with the earliest available date. Shortlisted candidates will be invited for an interview.\u00a0\n\nFurther details can be found at\u00a0http://www.hkdanceall.org/?a=doc&id=890.\n\nRecruitment will close once the position is filled.\n\n\nPersonal data collected will be used for recruitment purposes only and will be treated confidentially.\n\nThis position is supported by the Arts Production Internship Scheme of the Hong Kong Arts Development Council.\n\n", "employment_types": ["Full Time", "Permanent"], "selling_points": [], "locations": ["Quarry Bay"], "categories": ["Admin & HR", "Clerical / Admin Staff", "Others", "Entertainment - Artists / Singers / Musicians", "Public / Civil", "Social Services - Community / Non-profit Organization"], "post_time": "2022-01-13T03:52:54Z", "salary": {"currency": null, "max": null, "min": null, "period": "monthly", "term": null}, "salary_visible": false, "title_keywords": ["senior officer", "officer"], "responsibilities": ["social media", "maintaining", "schedules", "monitoring", "communication", "logistics", "schedule", "documentation", "publication", "administration"], "requirements": {"degrees": ["university degree"], "majors": ["journalism", "communications"], "languages": ["english", "chinese"], "language_level": ["fluent"], "hard_skills": ["documentation", "translation", "bi"], "soft_skills": ["self-motivated", "work independently", "under pressure", "responsible", "organizational", "interested in", "detail-oriented", "communication", "interpersonal skills", "devoted", "team player", "accurate"], "languages_combined": [{"language": "english", "language_level": ["fluent"]}, {"language": "chinese", "language_level": ["fluent"]}]}, "experience_required": {"duration": [], "field": ["editorial"]}}, {"job_id": "100003009031174", "location_code": "hk", "company": "initial Fashion Co Limited", "job_title": "Part-time Fitting Model (Womenswear)", "description": "Measurement Required\n\nWomenswear\n\nHeight : 166 - 168cm\nShoulder : 38 cm\u00a0/ 15\u201d\nChest : 85 cm\u00a0/ 33\u00bd\u201d\nWaist :\u00a067 cm\u00a0/ 26\u00bd\u201d\nHip:\u00a093 cm\u00a0/\u00a036\u00bd\u201d\nNeck width: 37 cm\u00a0/ 14\u215d\u201d\n\nInterested parties please send your RESUME with EXPECTED SALARY and YOUR MEASUREMENT to Human Resources Department via APPLY NOW.\n\nPlease visit our company website\u00a0http://www.initialfashion.com\u00a0for more company information.\n\nAll information received will be treated in strict confidence and for recruitment purpose only.", "employment_types": ["Part Time", "Temporary", "Contract", "Freelance"], "selling_points": [], "locations": ["Kwun Tong Area"], "categories": ["Design", "Others", "Others", "Entertainment - Artists / Singers / Musicians", "Others"], "post_time": "2022-01-13T18:48:29Z", "salary": {"currency": null, "max": null, "min": null, "period": "hourly", "term": null}, "salary_visible": false, "title_keywords": ["model"], "responsibilities": ["measurement"], "requirements": {"degrees": [], "majors": [], "languages": [], "language_level": [], "hard_skills": [], "soft_skills": [], "languages_combined": []}, "experience_required": {"duration": [], "field": []}}, {"job_id": "100003009045093", "location_code": "hk", "company": "Hong Kong Dance Alliance Limited", "job_title": "Administration and Project Manager", "description": "The Hong Kong Dance Alliance is a non-profit-making body that supports and promotes all forms of dance in Hong Kong. Our projects include publishing the bi-monthly periodical dance journal/hk, presenting new works by young choreographers and organizing the annual Hong Kong Dance Awards.\n\nWe are looking for an Administration and Project Manager.\n\nJob Descriptions\n\n\nTo lead the team in delivering projects\nTo handle administrative tasks for the organization including preparing budgets, grant proposals and project applications\nTo work with the editorial team for the bi-monthly publication dance journal/hk\nTo liaise with the Government and a diverse range of stakeholders as a primary voice for the dance industry in Hong Kong\nTo organize meetings and report to the Board regularly\nTo maintain financial records and monitor expenses\nTo supervise supporting staff\n\nQualifications and Criteria\n\n\nMinimum 4 years relevant working experience in performing arts-related field\nInterest in dance is essential while existing network in the dance field is strongly preferred\nStrong administrative and organizational skills, with proven ability to use initiative, work independently, multi-task and meet deadlines\nExcellent interpersonal and communication skills with fluent spoken and written Cantonese and English\nProficiency in MS Office and fundamental knowledge of book-keeping\nExperience in editing/layout and knowledge of InDesign and Photoshop would be an advantage\nImmediate availability preferred\n\nTo learn more about us, please refer to the Alliance\u2019s website and Facebook page:\nWebsite: http://www.hkdanceall.org/\nFacebook: https://www.facebook.com/hkdancealliance\n\nRemuneration will be based on working experience. Interested candidates are invited to send in their full resume with a cover letter stating their current and expected salaries along with the date of availability.\u00a0Recruitment will close once the position is filled.\n\nFurther details can be found at\u00a0http://www.hkdanceall.org/?a=doc&id=889.\n\nHong Kong Dance Alliance is financially supported by the HKADC\n\u9999\u6e2f\u821e\u8e48\u806f\u76df\u70ba\u85dd\u767c\u5c40\u8cc7\u52a9\u5718\u9ad4", "employment_types": ["Full Time"], "selling_points": [], "locations": ["Sheung Wan"], "categories": ["Others", "Entertainment - Artists / Singers / Musicians", "Management", "General Management", "Public / Civil", "Social Services - Community / Non-profit Organization"], "post_time": "2022-01-13T07:08:57Z", "salary": {"currency": null, "max": null, "min": null, "period": "monthly", "term": null}, "salary_visible": false, "title_keywords": ["project manager"], "responsibilities": ["budgets", "expenses", "monitor", "website", "communication", "liaise with", "maintain", "book-keeping", "administrative tasks", "report", "editing", "facebook", "publication", "administration"], "requirements": {"degrees": [], "majors": [], "languages": ["cantonese", "english"], "language_level": ["excellent", "fluent"], "hard_skills": ["bi", "indesign", "facebook", "ms office", "photoshop"], "soft_skills": ["organizational skills", "work independently", "communication skills", "multi-task", "diverse", "meet deadlines", "interpersonal", "initiative"], "languages_combined": [{"language": "cantonese", "language_level": ["excellent", "fluent"]}, {"language": "english", "language_level": ["excellent", "fluent"]}]}, "experience_required": {"duration": ["minimum 4 years"], "field": ["related", "editing", "relevant working experience"]}}, {"job_id": "100003009033328", "location_code": "hk", "company": "Asia Innovations HK Limited", "job_title": "Entertainment Talent Manager", "description": "We are Leading live streaming company in the world. Now we are looking for:\n\nEntertainment Talent Manager\n\nResponsibilities:\n\nPerform end-to-end recruitment of live streamer and KOL including sourcing, CV screening, interviewing, etc.\n\nAssist in streamers management, training, communication, coordination and casting\nMonitor, measure and review streamers\u2019 and KOL\u2019s performance timely\nCoordinating and liaising with marketing and operation teams for sales campaign\nConsolidate and prepare various streamers\u2019 and KOL\u2019s performance analytics reports and presentations for management review\nProvide on-site support during events or company promotions\n\nRequirements:\n\n1-2 years' relevant work experience in business development or similar field preferred\nSounds knowledgeable in entertainment trend and live streaming business\nSensitive on marketing trend and numbers\nExcellent communication and interpersonal skills with positive and \u201ccan-do\u201d attitudes\nAble to work independent, under pressure and adopt fast pace environment\nGood command in both written and spoken English, Chinese and Mandarin\nImmediate available will be an advantage\n\n\nWe Offer:\n\n\u00a0Basic Salary with Commission Package\nAttractive bonus or project bonus (depends on performance)\nFriendly and professional working environment\nExcellent career path\nWell-structured on-job training program\u00a0\n\nWelcome young, energetic and strong motivation candidates!\u00a0", "employment_types": ["Full Time"], "selling_points": [], "locations": ["Tsim Sha Tsui"], "categories": ["Sales, CS & Business Devpt", "Business Development", "Others", "Entertainment - Artists / Singers / Musicians", "Media & Advertising", "Broadcasting - TV / Radio"], "post_time": "2022-01-09T08:50:23Z", "salary": {"currency": null, "max": null, "min": null, "period": "monthly", "term": null}, "salary_visible": false, "title_keywords": ["manager"], "responsibilities": ["management", "cv screening", "review", "monitor", "liaising with", "teams", "presentations", "communication", "recruitment", "reports", "coordination", "management review"], "requirements": {"degrees": [], "majors": [], "languages": ["english", "chinese", "mandarin"], "language_level": ["good command"], "hard_skills": [], "soft_skills": ["independent", "under pressure", "communication and interpersonal skills", "can-do", "sensitive", "positive"], "languages_combined": [{"language": "english", "language_level": ["good command"]}, {"language": "chinese", "language_level": ["good command"]}, {"language": "mandarin", "language_level": ["good command"]}]}, "experience_required": {"duration": ["1-2 years"], "field": ["business development"]}}, {"job_id": "100003009035504", "location_code": "hk", "company": "Baron's School Of Music Ltd", "job_title": "Marketing Executive", "description": "Job Description\n\n\nResponsibilities\n\n-Develop marketing strategies\n-Identify new strategic opportunities for potential and untapped market segments\n-Develop marketing strategies to sustain the growth of business and to gain market share\n-Create revenue-generating programs with our potential & existing partners\n-Update website and social media platform\n-Provide support on daily operation, marketing research & promotion activities\n-Ad hoc task assigned Requirements\n- Degree holder or above\u00a0\n- 5 years or above of working experience in marketing or other related area\u00a0\n- Mature, responsible, proactive & high flexibility\n- Capable to work independently\n- Proficient in both written and spoken English and Chinese (Cantonese and Mandarin)\n- Immediate available is highly preferred", "employment_types": ["Full Time"], "selling_points": [], "locations": ["Wan Chai"], "categories": ["Others", "Entertainment - Artists / Singers / Musicians", "Marketing / Public Relations", "Marketing - Brand / Product Management"], "post_time": "2022-01-10T07:29:23Z", "salary": {"currency": null, "max": null, "min": null, "period": "monthly", "term": null}, "salary_visible": false, "title_keywords": ["marketing executive"], "responsibilities": ["social media", "marketing strategies", "daily operation", "website", "marketing research"], "requirements": {"degrees": ["degree holder"], "majors": [], "languages": ["cantonese", "english", "chinese", "mandarin"], "language_level": ["proficient"], "hard_skills": [], "soft_skills": ["work independently", "capable", "responsible", "mature", "proactive"], "languages_combined": [{"language": "cantonese", "language_level": []}, {"language": "english", "language_level": ["proficient"]}, {"language": "chinese", "language_level": ["proficient"]}, {"language": "mandarin", "language_level": []}]}, "experience_required": {"duration": ["5 years"], "field": ["related", "marketing"]}}, {"job_id": "100003009030258", "location_code": "hk", "company": "Miracle Workshop", "job_title": "\u517c\u8077\u4ee3\u5531\u6b4c\u624b", "description": "Responsibilities\n\n\u00a0\u00a0\u00a0 Assist in managing Opera Hong Kong Children Chorus\n\u00a0\u00a0\u00a0 Assist in managing Education and Outreach programmes\n\u00a0\u00a0\u00a0 Provide administrative support in general\n\u00a0\u00a0\u00a0 Working on Saturdays required\n\u00a0\u00a0\u00a0 Five-day work job\nRequirement\n\n\u00a0\u00a0\u00a0 Recognised tertiary education qualification or equivalent\n\u00a0\u00a0\u00a0 Two years or above working experience; preferably related working experience\n\u00a0\u00a0\u00a0 Good PC skills and well versed with Microsoft Office applications\n\u00a0\u00a0\u00a0 Fluency in English and Mandarin is preferable\n\u00a0\u00a0\u00a0 Pro-active, responsible, willing to learn and detail-minded\n\u00a0\u00a0 \u00a0Good interpersonal and communications skills\n\u00a0\u00a0 \u00a0Able to work independently under pressure and minimal supervision\nInterested parties please send your CV with cover letter and expected salary to Opera Hong Kong Ltd, Room 1907, Pacific Plaza, 410 Des Voeux Road West, Hong Kong (mark \u2018Confidential\u2019 on envelop), or via email on or before 26 Jan 2022.\n\n\nAll information received will be kept in strict confidence and only for employment-related purpose. Applicants who do not hear from us within 8 weeks may consider their applications unsuccessful and their data will be destroyed within 12 months of receipt.", "employment_types": ["Part Time", "Freelance"], "selling_points": ["\u5ee3\u544a\u96fb\u5f71\u6b4c\u66f2/\u5361\u62c9OK\u5e55\u5f8c\u4ee3\u5531", "\u80fd\u64cd\u6d41\u5229\u5ee3\u6771\u8a71\uff0c\u7537\u5973\u5747\u53ef\uff0c\u5e74\u9f61\u4e0d\u9650", "\u7d93\u9a57\u4e0d\u62d8\u3001\u5de5\u4f5c\u6642\u9593\u4efb\u64c7\u3001\u85aa\u916c\u9762\u8b70"], "locations": ["Not Specified"], "categories": ["Media & Advertising", "Production", "Others", "Others", "Entertainment - Artists / Singers / Musicians"], "post_time": "2022-01-07T07:05:59Z", "salary": {"currency": null, "max": null, "min": null, "period": "hourly", "term": null}, "salary_visible": false, "title_keywords": [], "responsibilities": ["provide administrative support"], "requirements": {"degrees": [], "majors": [], "languages": ["english", "mandarin"], "language_level": ["fluency"], "hard_skills": ["pc skills", "microsoft office"], "soft_skills": ["detail-minded", "work independently", "under pressure", "responsible", "willing to learn", "pro-active", "interpersonal"], "languages_combined": [{"language": "english", "language_level": ["fluency"]}, {"language": "mandarin", "language_level": ["fluency"]}]}, "experience_required": {"duration": ["two years"], "field": ["related"]}}, {"job_id": "100003009030213", "location_code": "hk", "company": "Time Auction Limited", "job_title": "Volunteer Music Mentors for Under Production HK", "description": "Project Details\nWhat we need\nTime commitment will be around 1-2 hours per month, lasting for around 3 months\nLooking for professionals within the music industry (ex. music producers and composers)\nProvide advice for the youth with little experience but passionate in music / creative industry\nBackground\n\nWe are having a project that needs professionals in creative industry like directors, musics producers to be the mentors to provide some advice for the youth with little experience yet passionate in creative industry. We are flexible and open to any ways of collaboration.\n\nWhat we have\n\nOur team will guide you through the process and will match you with one of our youths for you to mentor.\n\nWhy this is important\n\nUnder Production, established in 2015, has devoted to continuously bring new blood to the creative industry. Believe in the youth\u2019s power and creativity, Under Production acts as a platform that equip the youth with practical skills and job opportunities.\n\nProject Period\n\n15 Jan 2022 - 30 Apr 2022\n\nLocation\n\nRemote\n\n\n\nRequirements\n\n2 hours per month\n\nTime Commitment\nSkills\nCoaching\nMentorship\nYouth Mentorship\nMusic\nLanguage\nChinese (Cantonese)\nEnglish", "employment_types": ["Part Time", "Freelance"], "selling_points": [], "locations": ["Not Specified"], "categories": ["Others", "Entertainment - Artists / Singers / Musicians"], "post_time": "2022-01-07T06:58:53Z", "salary": {"currency": null, "max": null, "min": null, "period": "monthly", "term": null}, "salary_visible": false, "title_keywords": [], "responsibilities": ["provide advice"], "requirements": {"degrees": [], "majors": [], "languages": ["cantonese", "english", "chinese"], "language_level": [], "hard_skills": [], "soft_skills": ["passionate", "creative", "flexible", "devoted"], "languages_combined": [{"language": "cantonese", "language_level": []}, {"language": "english", "language_level": []}, {"language": "chinese", "language_level": []}]}, "experience_required": {"duration": [], "field": []}}, {"job_id": "100003009030243", "location_code": "hk", "company": "Murine Tsui Modelling Agency Ltd", "job_title": "Part-time Modelling and KOL \u517c\u8077BB \u3001\u5152\u7ae5 \u3001 \u6210\u4eba\u6a21\u7279\u5152 / \u7db2\u7d05\u3001\u4e3b\u64ad\u3001\u7db2\u7d61\u85dd\u4eba", "description": "Job Description\n\n\u00a0Greet visitors and handle telephone enquiries\n\u00a0Provide administrative support including meeting room reservation, procurement of\u00a0 \u00a0stationery and office supplies, courier arrangement, etc.\n\u00a0Handle data input, filing and administrative duties.\n\u00a0Other works assign by the company\n\n\u00a0Requirements\n\n\n\u00a0 DSE or above\n\n\u00a0 Multi-tasking, organised and proactive\n\u00a0 Excellent communication and interpersonal skills\n\u00a0 Fluent in Mandarin, Cantonese & English\n\u00a0 Proficient in MS Office, Word, Excel, Chinese word Processing\n\u00a0 Immediately available preferred\n\nWe provide an open and friendly environment to the right candidate.\u00a0Please also visit us at\u00a0www.bsm.com.hk\u00a0for more information.", "employment_types": ["Part Time"], "selling_points": ["model\u3001\u7db2\u7d05\uff0c\u7db2\u7d61\u85dd\u4eba", "Welcome Fresh Grad", "photo shooting"], "locations": ["Mong Kok"], "categories": ["Others", "Entertainment - Artists / Singers / Musicians", "Student / Fresh Graduate / No Experience", "Others"], "post_time": "2022-01-07T07:05:23Z", "salary": {"currency": "HKD", "max": null, "min": 470, "period": "hourly", "term": null}, "salary_visible": true, "title_keywords": [], "responsibilities": ["office supplies", "stationery", "data input", "administrative duties", "provide administrative support"], "requirements": {"degrees": ["dse"], "majors": [], "languages": ["cantonese", "english", "chinese", "mandarin"], "language_level": ["proficient", "fluent"], "hard_skills": ["excel", "chinese word processing", "word", "ms office"], "soft_skills": ["multi-tasking", "proactive", "communication and interpersonal skills", "organised"], "languages_combined": [{"language": "cantonese", "language_level": ["fluent"]}, {"language": "english", "language_level": ["fluent"]}, {"language": "chinese", "language_level": ["proficient"]}, {"language": "mandarin", "language_level": ["fluent"]}]}, "experience_required": {"duration": [], "field": []}}, {"job_id": "100003009024016", "location_code": "hk", "company": "Baron's School Of Music Ltd", "job_title": "Receptionist", "description": "Job Responsibilities:\nPerform end-to-end recruitment of live streamer and KOL including screening, approaching, interviewing and closing\nAssist in streamers management, training, communication, coordination and casting\nMaintain a good relationship with streamers and KOL\nMonitor, measure and review streamers\u2019 and KOL\u2019s performance timely\nConsolidate and prepare various streamers\u2019 and KOL\u2019s performance analytics reports and presentations for management review\nCooperate with various internal teams to implement streamers\u2019 and KOL\u2019s promotion and interview with media\nCoordinate with social media platform and arrange broadcast activities for streamers and KOL to increase social media presence\nCooperate with various internal teams to organize offline activities and arrange streamers and KOL to participate\nPerform other ad-hoc projects if necessary\n\n\u00a0Requirements:\n\nMinimum 3 years work experience in Media, Entertainment, Broadcasting industry or related disciplines\nExcellent skill in communication, interpersonal and social networking\nFluency in written and spoken\u00a0Cantonese, Putonghua\u00a0and English\nFamiliar with Social Media Platform\nGood presentation and negotiation skills, flexible and be able to work under pressure\nResponsible, strong execution, team player, well-organized, equipped with aesthetic sense\nExperience in Model Management, Artist Management, or any media related disciplines would be an advantage\nImmediate available is highly preferred", "employment_types": ["Full Time"], "selling_points": [], "locations": ["Wan Chai"], "categories": ["Admin & HR", "Clerical / Admin Staff", "Receptionist", "Others", "Entertainment - Artists / Singers / Musicians"], "post_time": "2022-01-05T10:24:09Z", "salary": {"currency": null, "max": null, "min": null, "period": "monthly", "term": null}, "salary_visible": false, "title_keywords": ["receptionist"], "responsibilities": ["social media", "management", "review", "monitor", "teams", "presentations", "coordinate with", "communication", "good relationship", "maintain", "recruitment", "reports", "coordination", "ad-hoc projects", "cooperate with", "management review"], "requirements": {"degrees": [], "majors": [], "languages": ["cantonese", "putonghua", "english"], "language_level": ["fluency"], "hard_skills": [], "soft_skills": ["flexible", "responsible", "well-organized", "communication", "negotiation skills", "team player", "interpersonal", "presentation", "work under pressure"], "languages_combined": [{"language": "cantonese", "language_level": ["fluency"]}, {"language": "putonghua", "language_level": ["fluency"]}, {"language": "english", "language_level": ["fluency"]}]}, "experience_required": {"duration": ["minimum 3 years"], "field": ["related", "management", "media"]}}, {"job_id": "100003009021067", "location_code": "hk", "company": "Multi Channel Network Limited", "job_title": "Live Stream KOL Manager \u7db2\u7d05\u7ba1\u7406\u53ca\u62d3\u5c55\u7d93\u7406", "description": "\u5177\u670926\u5e74\u821e\u53f0\u6f14\u85dd\u53ca\u5ee3\u544a\u7d93\u9a57 \u5c08\u696d\u6a21\u7279\u5152\u8a13\u7df4\u73ed\u73fe\u6b63\u62db\u751f\n\nBB / \u5152\u7ae5 / \u9752\u5c11\u5e74\u6a21\u7279\u5152\n3\u500b\u6708\u6216\u4ee5\u4e0aBB\u81f315\u6b72\u5152\u7ae5\u53ca\u9752\u5c11\u5e74\uff0c\u7cbe\u9748\u6d3b\u6f51\uff0c\u6027\u683c\u958b\u6717\uff0c\u6709\u6f14\u85dd\u5929\u4efd\u3002\n\n\u7522\u54c1\u4ee3\u8a00\u4eba\u53ca\u6a21\u7279\u5152\n\u5c07\u53c3\u8207\u8b77\u819a\u54c1 / \u6d17\u982d\u6c34 / \u5065\u5eb7\u7522\u54c1\u4ee3\u8a00\u4eba\u53ca\u96fb\u8996 / \u96dc\u8a8c\u5ee3\u544a / \u6642\u88dd\u8868\u6f14 / \u8a66\u8eab\u6a21\u7279\u5152\u3002\n\n\u56e0\u61c9\u77ac\u606f\u842c\u8b8a\u7684\u6578\u4f4d\u6642\u4ee3\u53ca\u5168\u7403\u5316\u8da8\u52e2\uff0c\u672c\u516c\u53f8\u5c07\u5354\u52a9\u65d7\u4e0b\u85dd\u4eba\u4e8e\u7db2\u7d61\u5e73\u53f0\u7684\u767c\u5c55\u3002\n\n\u517c\u8077\u7db2\u7d05\u3001\u4e3b\u64ad\u3001\u7db2\u7d61\u85dd\u4eba\u62db\u8058\n\u00a0\u6211\u5011\u64c1\u6709\u5f37\u5927\u7684\u884c\u92b7\u5718\u968a\uff0c\u4ee5\u5c08\u696d\u7684\u5e02\u5834\u5206\u6790\u53ca\u7d93\u9a57\uff0c \u8b93\u4e3b\u64ad\u5011\u66dd\u5149\u65bc\u5404\u985e\u7db2\u7ad9\u3001FB\u3001Instagram\u3001TikTok\u7b49\uff0c\u6d3b\u7d61\u65bc\u5404\u793e\u7fa4\u8edf\u9ad4\uff0c\u63d0\u5347\u77e5\u540d\u5ea6\u3002\n\u4efb\u8077\u8cc7\u683c \u7537\u5973\u4e0d\u62d8\uff0c\u4e0d\u9650\u5e74\u9f61\u3002\n\u4e0d\u8ad6\u7d20\u4eba\u3001\u7db2\u7d05\uff0c\u53ea\u8981\u662f\u559c\u611b\u8868\u6f14\u3001\u80fd\u8aaa\u6703\u5531\u3001\u80fd\u5920\u6d3b\u8e8d\u73fe\u5834\u6c23\u6c1b\uff0c \u6027\u683c\u6d3b\u6f51\u958b\u6717\uff0c\u5584\u7528\u8868\u73fe\u81ea\u6211\uff0c\u6709\u624d\u85dd\u8457\u512a\u5148 \u3002\n\n\u5982\u9700\u7d04\u898b\u9762\u8a66\uff0c\u8acb\u81f4\u96fb\u00a02740 9059 \uff0812:00-18:00\uff09\u8521\u5c0f\u59d0\u6d3d\u6216 WhatsApp 5626 0238\u00a0\n\uff0819\u6b72\u6216\u4ee5\u4e0b\u9762\u8a66\u8005\uff0c\u5fc5\u9808\u7531\u5bb6\u9577\u966a\u540c\u9762\u8a66\uff09\n\u6216\u8005\u901a\u904e\u96fb\u5b50\u90f5\u4ef6\u63a5\u6536\u7533\u8acb\nIG/Facebook: Murine Tsui Modelling Agency Ltd.", "employment_types": ["Full Time", "Permanent"], "selling_points": ["Asia Leading KOL Company", "3 years experience in Media or Entertainment", "Target Global Market"], "locations": ["Lai Chi Kok"], "categories": ["Others", "Entertainment - Artists / Singers / Musicians", "Media & Advertising", "Print Media", "Broadcasting - TV / Radio"], "post_time": "2022-01-05T02:59:25Z", "salary": {"currency": "HKD", "max": 24999, "min": 17000, "period": "monthly", "term": null}, "salary_visible": true, "title_keywords": ["manager"], "responsibilities": ["facebook"], "requirements": {"degrees": [], "majors": [], "languages": [], "language_level": [], "hard_skills": ["facebook", "whatsapp"], "soft_skills": [], "languages_combined": []}, "experience_required": {"duration": [], "field": []}}, {"job_id": "100003009014894", "location_code": "hk", "company": "The Star Overseas Limited", "job_title": "Project Assistant (Movie Production)", "description": "Responsibilities\n\nLiaise with frontline staff and follow up all aspects of film and television projects such as material handling, administrative support, and follow-up procedure, etc.\nProvide support and assist the Producer in all stages from pre-production through to post production, distribution and promotion\nPrepare materials and documents for production, distribution and promotion\nAssist the supervisor in other Ad-hoc tasks\nRequirements\n\nDegree holder or above\nAt least 2 years\u2019 experiences in clerical or administration field\nHigh proficiency in both written and spoken English, Chinese and Putonghua\nGood PC knowledge of MS Word, Excel, Outlooks, Photoshop and editing software\nMore advanced applications such as Powerpoint, adobe illustrator, adobe premiere, adobe Photoshop and Final Cut Pro will be an advantage\nWell-organized, hardworking, independent, attentive to details, good communication skills, strong sense of responsibility\nTeam player and can work under pressure\nImmediate available is preferred", "employment_types": ["Full Time", "Permanent"], "selling_points": [], "locations": ["Wan Chai Area"], "categories": ["Admin & HR", "Clerical / Admin Staff", "Media & Advertising", "Production", "Others", "Entertainment - Artists / Singers / Musicians"], "post_time": "2022-01-03T09:19:31Z", "salary": {"currency": null, "max": null, "min": null, "period": "monthly", "term": null}, "salary_visible": false, "title_keywords": ["project assistant"], "responsibilities": ["provide support", "administrative support", "ad-hoc tasks", "liaise with", "pre-production"], "requirements": {"degrees": ["degree holder"], "majors": [], "languages": ["putonghua", "english", "chinese"], "language_level": ["proficiency"], "hard_skills": ["final cut pro", "excel", "ms word", "adobe photoshop", "powerpoint", "adobe illustrator", "adobe premiere", "pc knowledge", "photoshop"], "soft_skills": ["communication skills", "independent", "advanced", "attentive to details", "sense of responsibility", "well-organized", "team player", "hardworking", "work under pressure"], "languages_combined": [{"language": "putonghua", "language_level": ["proficiency"]}, {"language": "english", "language_level": ["proficiency"]}, {"language": "chinese", "language_level": ["proficiency"]}]}, "experience_required": {"duration": ["at least 2 years"], "field": ["clerical", "administration"]}}, {"job_id": "100003009019326", "location_code": "hk", "company": "Bravo Personnel Consultancy Limited", "job_title": "Dance Teacher / \u821e\u8e48\u5c0e\u5e2b (18K-20K)", "description": "Job requirements:\n\n\u6559\u63882\u6b72\u6216\u4ee5\u4e0a\u7684\u82ad\u857e\u821e\u3001\u7235\u58eb\u821e\u6216\u85dd\u8853\u9ad4\u64cd\u8ab2\u7a0b\n\u5354\u52a9\u5b78\u6821\u6d3b\u52d5\uff0c\u5305\u62ec\uff1a\u8003\u8a66\u3001\u6bd4\u8cfd\u53ca\u8868\u6f14\u7b49\n\u5177\u6559\u5b78\u71b1\u8aa0\uff0c\u4e26\u6301\u76f8\u95dc\u7d93\u9a57\u53ca\u8cc7\u6b77\uff0c\u5305\u62ec\u6301\u67091\u5e74\u6216\u4ee5\u4e0a\u6559\u5b78\u7d93\u9a57\n\u6bcf\u661f\u671f\u5de5\u4f5c\u516d\u5929\uff0c\u9700\u65bc\u661f\u671f\u516d\u53ca\u65e5\u5de5\u4f5c\n\u53e6\u6709\u5e74\u7d42\u82b1\u7d05\u53ca\u91ab\u7642\u4fdd\u96aa\n\nInterested parties, please contact Ms LEE at 2881 6923 during office hours or email your CV by clicking \"Apply Now\"\u00a0or fax your resume to 2576 8026. All the personal data collected will be used for recruitment purpose only. \u00a0", "employment_types": ["Full Time", "Permanent"], "selling_points": [], "locations": ["Not Specified"], "categories": ["Education", "Teacher", "Tutor / Instructor", "Others", "Entertainment - Artists / Singers / Musicians"], "post_time": "2022-01-05T00:22:16Z", "salary": {"currency": null, "max": null, "min": null, "period": "monthly", "term": null}, "salary_visible": false, "title_keywords": ["teacher"], "responsibilities": [], "requirements": {"degrees": [], "majors": [], "languages": [], "language_level": [], "hard_skills": [], "soft_skills": [], "languages_combined": []}, "experience_required": {"duration": [], "field": []}}, {"job_id": "100003009013634", "location_code": "hk", "company": "Mouton Photography", "job_title": "\u651d\u5f71\u5e2b Photographer \uff08\u5168\u8077\u6216Freelance\uff09", "description": "Mouton Photography\u7531\u570b\u969b\u5f97\u734e\u5973\u651d\u5f71\u5e2bCoral Poon\u4e3b\u7406\uff0c\u662f\u9999\u6e2f\u7684\u5b55\u651d\u53ca\u521d\u751f\u651d\u5f71\u5c08\u5bb6\uff0c\u4ea6\u64c5\u9577\u5152\u7ae5\u3001\u5bb6\u5ead\u4eba\u50cf\u53ca\u5bf5\u7269\u62cd\u651d\u3002\u6211\u5011\u73fe\u6b63\u62db\u8058\u4e00\u540d\u651d\u5f71\u5e2b\uff0c\u7d66\u4f60\u4e00\u500b\u767c\u63ee\u6f5b\u80fd\u3001\u5be6\u8e10\u5922\u60f3\u826f\u6a5f\u3002\u5168\u8077\u6216Freelance\u5747\u53ef\u8003\u616e \u3002\n\n\u524d\u9014\n\n\u521d\u7d1a\u651d\u5f71\u5e2b - \u8cc7\u6df1\u651d\u5f71\u5e2b - \u5408\u4f5c\u4f19\u4f34\n\n\u53e6\u4eab\u696d\u7e3e\u8868\u73fe\u5206\u7d05\uff0c\u696d\u52d9\u4f63\u91d1\u53ca\u54e1\u5de5\u512a\u60e0\u3002\n\n\u8077\u4f4d\u8981\u6c42\n\n\n\u5fc5\u9808\u71b1\u611b\u7167\u9867\u521d\u751f\u5b30\u5152\u53ca\u8207\u5152\u7ae5\u4e92\u52d5\n\u62cd\u651d\u6642\u6709\u80fd\u529b\u6c39\u5c0f\u670b\u53cb\u7b11\u53ca\u671b\u93e1\u982d\n\u5f85\u4eba\u8aa0\u61c7\u6709\u79ae\n\u5bcc\u8cac\u4efb\u611f\uff0c\u5de5\u4f5c\u52e4\u596e\u4e3b\u52d5\n\u80fd\u6b63\u78ba\u5206\u8fa8\u9854\u8272\uff0c\u9808\u6709\u85dd\u8853\u7f8e\u611f\n\u5fc5\u9808\u61c2\u5f97\u4e2d\u6587\u6253\u5b57\uff0c\u9808\u61c2\u7cb5\u8a9e\u53ca\u57fa\u672c\u82f1\u8a9e\u53ca\u666e\u901a\u8a71\n\u9031\u672a\u5047\u65e5\u901a\u5e38\u9700\u8981\u8fd4\u5de5\n\u9858\u610f\u4e0a\u9580\u5de5\u4f5c\n\u4e0d\u5c11\u65bc\u4e09\u5e74\u5168\u8077\u5152\u7ae5\u651d\u5f71\u7d93\u9a57\uff0c\u53ca\u719f\u6089\u5404\u6b3eAdobe\u5f71\u50cf\u8655\u7406\u8edf\u4ef6\u4f7f\u7528\n\u5de5\u4f5c\u7bc4\u570d\n\u65bc\u5f71\u6a13\u6216\u4e0a\u9580\u9032\u884c\u62cd\u651d\uff0c\u5ba2\u6236\u4ee5\u5152\u7ae5\u53ca\u5bb6\u9577\u70ba\u4e3b\n\u62cd\u651d\u5f8c\u5411\u5ba2\u4eba\u4ecb\u7d39\u7522\u54c1\n\u4f7f\u7528Adobe \u5f71\u50cf\u8655\u7406\u8edf\u4ef6\u5f8c\u88fd\u76f8\u7247\n\u6709\u521d\u751f\u5b30\u5152\u651d\u5f71\u7d93\u9a57\u53ef\u7372\u512a\u5148\u8003\u616e\n\u5168\u8077\u6216Freelance\u5de5\u4f5c\u5f62\u5f0f\u5747\u53ef\n\u6709\u8208\u8da3\u6c42\u8077\u8005\u8acb\u65bc1\u670816\u65e5\u524d\u7533\u8acb\uff0c\u4e26\u8acb\u5217\u660e\u76f8\u95dc\u5de5\u4f5c\u7d93\u9a57\u3001\u8fd1\u7167\u53ca\u9810\u671f\u85aa\u91d1\u3002\n\u516c\u53f8\u7db2\u9801\uff1a www.moutonphotogrpahy.net", "employment_types": ["Full Time", "Part Time", "Permanent", "Temporary", "Freelance"], "selling_points": ["\u9999\u6e2f\u5b55\u651d\u53ca\u521d\u751f\u651d\u5f71\u5c08\u5bb6", "\u826f\u597d\u6649\u5347\u6a5f\u6703\uff0c\u53ef\u6210\u70ba\u696d\u52d9\u5408\u4f5c\u4f19\u4f34", "\u5168\u8077\u6216Freelance\u5747\u53ef\u8003\u616e"], "locations": ["Kwai Hing"], "categories": ["Others", "Entertainment - Artists / Singers / Musicians"], "post_time": "2022-01-03T02:33:31Z", "salary": {"currency": null, "max": null, "min": null, "period": "monthly", "term": null}, "salary_visible": false, "title_keywords": ["\u651d\u5f71\u5e2b", "photographer"], "responsibilities": [], "requirements": {"degrees": [], "majors": [], "languages": [], "language_level": [], "hard_skills": [], "soft_skills": [], "languages_combined": []}, "experience_required": {"duration": [], "field": []}}, {"job_id": "100003009007899", "location_code": "hk", "company": "The One Academy of Music And Arts", "job_title": "\u5c07\u8ecd\u6fb3\u5927\u578b\u97f3\u6a02\u85dd\u8853\u5b78\u9662 - \u5168\u8077/\u517c\u8077\u4e2d\u897f\u6a02\u5668\u5c0e\u5e2b // Full-Time/Part-Time Music Tutor (\u667a\u80fd\u92fc\u7434/\u92fc\u7434/\u5404\u985e\u4e2d\u897f\u6a02\u5668/\u8072\u6a02/\u6b4c\u5531\u5c0e\u5e2b)", "description": "\u5168\u8077\u6216\u517c\u8077\u4e2d\u897f\u6a02\u5668/\u8072\u6a02/\u6b4c\u5531\u5c0e\u5e2b\u00a0// Full-Time/Part-Time Music Tutor\n(\u5305\u62ec : \u667a\u80fd\u92fc\u7434 / \u92fc\u7434 / \u8c4e\u7434 / \u53e3\u7434 / \u63da\u7434 / \u67f3\u7434 / \u53e4\u7b8f / \u4e8c\u80e1 / \u7435\u7436 / \u82d7\u5b50 / \u5c0f\u63d0\u7434/ \u4e2d\u63d0\u7434 / \u5927\u63d0\u7434 / \u6728\u7ba1\u6a02\u5668 / \u9285\u7ba1\u6a02\u5668 / \u6572\u6483\u6a02\u5668 / \u5e7c\u5152\u97f3\u6a02 / \u53e4\u5178\u7d50\u4ed6 / \u6d41\u884c\u7d50\u4ed6 / \u4f4e\u97f3\u7d50\u4ed6 / \u6d41\u884c\u9f13 / \u975e\u6d32\u9f13 / \u7235\u58eb\u9f13 / \u8072\u6a02\u00a0/\u00a0Ukulele \u7b49)\n\n- \u8ca0\u8cac\u900f\u904e\u667a\u80fd\u92fc\u7434\u7cfb\u7d71\u6559\u6388\u5c0f\u670b\u53cb\u521d\u7d1a\u92fc\u7434\u8ab2\u7a0b\u53ca\u6a02\u7406\u8a8d\u8b58 (\u667a\u80fd\u92fc\u7434)\n- \u6559\u6388\u4e0d\u540c\u6a02\u5668\u53ca\u6a02\u7406\u8a8d\u8b58 (\u5176\u4ed6\u4e2d\u897f\u6a02\u5668/\u8072\u6a02)\n\n\u5b78\u6b77\u53ca\u8981\u6c42 :\n\u6301\u6709\u82f1\u570b\u7687\u5bb6\u97f3\u6a02\u5b78\u9662\u516b\u7d1a\u6216\u540c\u7b49\u8cc7\u6b77\u6216\u4ee5\u4e0a\u6216\u540c\u7b49\u7a0b\u5ea6\n\u5177\u6559\u5b78\u7d93\u9a57/\u5e7c\u5152\u6559\u80b2\u7d93\u9a57/\u6559\u6388\u5e7b\u5152\u97f3\u6a02\u73ed\u8005/\u76f8\u95dc\u8b49\u66f8\u512a\u5148\u8003\u616e\n\u672c\u5b78\u9662\u6703\u63d0\u4f9b\u5c08\u696d\u57f9\u8a13, \u61c9\u5c46\u7562\u696d\u751f\u4ea6\u8003\u616e (\u667a\u80fd\u92fc\u7434\u5c0e\u5e2b\u9069\u7528)\n\n\u6240\u6709\u5c0e\u5e2b\u7684\u57fa\u672c\u8981\u6c42 :\n- \u826f\u597d\u7cb5\u8a9e, \u4e00\u822c\u82f1\u8a9e\u53ca\u666e\u901a\u8a71\n- \u826f\u597d\u6e9d\u901a\u6280\u5de7\n- \u6709\u8cac\u4efb\u5fc3\u53ca\u5b88\u6642\n- \u5c0d\u5e7c\u5152\u6559\u80b2\u6709\u71b1\u8aa0\n- \u89aa\u5207\u53cb\u5584, \u5c0d\u5c0f\u670b\u53cb\u6709\u611b\u5fc3\u53ca\u8010\u6027\n\n\u5de5\u4f5c\u5730\u9ede :\n- \u5c07\u8ecd\u6fb3\n\n\u5de5\u4f5c\u985e\u578b/\u6642\u9593 :\n- \u5168\u8077 : \u6bcf\u9031\u5de5\u4f5c\u516d\u5929, \u6bcf\u6708\u516d\u5929\u8f2a\u4f11\u5047\u671f (\u5168\u8077\u5c0e\u5e2b\u9700\u517c\u9867\u5b78\u9662\u65e5\u5e38\u884c\u653f\u5de5\u4f5c)\n- \u517c\u8077 : \u8acb\u5217\u51fa\u53ef\u4e0a\u73ed\u6642\u9593\uff0c\u65b9\u4fbf\u672c\u5b78\u9662\u4f5c\u51fa\u4e0a\u73ed\u65e5\u6578\u53ca\u6642\u6578\u5b89\u6392\n\n\u798f\u5229\u5f85\u9047:\n- \u5168\u8077\u6708\u85aa : \u57fa\u672c\u6708\u85aa (negotiable) + \u5b78\u751f\u6307\u5b9a\u5206\u6210\u53ca\u82b1\u7d05, \u6708\u85aa\u53ef\u9054\u5169\u842c\u5143\u6216\u4ee5\u4e0a\u00a0\n- \u517c\u8077\u6642\u85aa : \u9762\u8b70 (\u6309\u8cc7\u6b77\u6216\u5de5\u4f5c\u7d93\u9a57\u800c\u5b9a)\n- \u5168\u5e74\u5341\u5929\u6216\u4ee5\u4e0a\u6709\u85aa\u5e74\u5047 (\u5982: \u751f\u65e5\u5047)\n- \u63d0\u4f9b\u5728\u8077\u57f9\u8a13\n- \u5f37\u7a4d\u91d1\n- \u54e1\u5de5\u512a\u60e0\n- \u91ab\u7642\u798f\u5229\n- \u5bb6\u5ead\u53cb\u5584\u5236\u5ea6\n(* \u90e8\u4efd\u798f\u5229\u5f85\u9047\u53ea\u9650\u65bc\u5168\u8077\u54e1\u5de5)\n\n\u00a0 \u00a0 \u00a0 \u00a0 \u00a0 \u00a0 \u00a0 \u00a0 \u00a0 \u00a0 \u00a0 \u00a0 \u00a0 \u00a0 \u00a0 \u00a0 \u00a0 \u00a0 \u00a0 \u00a0 \u00a0 \u00a0 \u00a0 \u00a0 \u00a0 \u00a0 \u00a0 \u00a0 \u00a0 \u00a0 \u00a0 \u00a0 \u00a0 \u00a0 \u00a0 \u00a0 \u00a0 \u00a0 \u00a0 \u00a0 \u00a0< \u6691\u5047\u5de5\u514d\u554f >>\n\n\u5982\u60a8\u5c0d\u6b64\u8077\u4f4d\u611f\u8208\u8da3\uff0c \u8acb\u5c07\u60a8\u5b8c\u6574\u7684\u7c21\u6b77\u5305\u62ec\u76ee\u524d\u548c\u671f\u671b\u7684\u85aa\u91d1, \u7533\u8acb\u8077\u4f4d(\u5168\u8077/\u517c\u8077) \u767c\u9001\u81f3 Apply Now\u3002\n\n\uff08\u6240\u6709\u7533\u8acb\u90fd\u5c07\u53d7\u5230\u4fdd\u5bc6\u8655\u7406\uff0c\u6240\u6709\u6536\u96c6\u7684\u500b\u4eba\u8cc7\u6599\u50c5\u7528\u65bc\u62db\u8058\u76ee\u7684\u3002\uff09", "employment_types": ["Full Time", "Part Time", "Permanent", "Freelance"], "selling_points": [], "locations": ["Tseung Kwan O"], "categories": ["Education", "Tutor / Instructor", "Others", "Entertainment - Artists / Singers / Musicians"], "post_time": "2021-12-30T05:15:32Z", "salary": {"currency": null, "max": null, "min": null, "period": "monthly", "term": null}, "salary_visible": false, "title_keywords": ["music tutor"], "responsibilities": [], "requirements": {"degrees": [], "majors": [], "languages": [], "language_level": [], "hard_skills": ["tutor"], "soft_skills": [], "languages_combined": []}, "experience_required": {"duration": [], "field": []}}, {"job_id": "100003009007922", "location_code": "hk", "company": "Greenery Music Limited", "job_title": "\u5404\u985e\u7e6a\u756b\u53ca\u624b\u5de5\u85dd\u5c0e\u5e2b  - \u9ecf\u571f / \u5152\u7ae5\u756b / \u6c34\u5f69 / \u7d20\u63cf\u7b49 (Art Tutor)", "description": "\u5de5\u4f5c :\n\n\u6559\u6388\u5404\u985e\u7e6a\u756b\u53ca\u624b\u5de5\u6280\u5de7 (\u9ecf\u571f\u3001\u5152\u7ae5\u756b\u3001\u6c34\u5f69\u3001\u7d20\u63cf\u7b49)\n\u6e96\u5099\u8ab2\u7a0b\u6559\u6848\u53ca\u6559\u6750\n\u8cc7\u6b77\u53ca\u8981\u6c42 :\n\u5177\u76f8\u95dc\u5de5\u4f5c\u7d93\u9a57\u512a\u5148\n\u4fee\u8b80\u85dd\u8853\u76f8\u95dc\u5c08\u4e0a\u6559\u80b2\u3001\u6587\u6191\u6216\u8b49\u66f8\u8ab2\u7a0b\u512a\u5148\n\u6301\u6709\u76f8\u95dc\u7f8e\u8853\u5b78\u9662\u8b49\u66f8/\u5176\u4ed6\u7e6a\u756b\u6216\u624b\u5de5\u85dd\u8b49\u66f8\u512a\u5148\n\u6709\u8010\u6027,\u76e1\u8cac\u5b88\u6642,\u559c\u6b61\u8207\u5c0f\u670b\u53cb\u63a5\u89f8\u53ca\u6e9d\u901a\n\u80fd\u5920\u7368\u7acb\u8655\u4e8b,\u6709\u6548\u7ba1\u7406\u8ab2\u5802\u79e9\u5e8f\n\u826f\u597d\u7cb5\u8a9e;\u4e00\u822c\u82f1\u8a9e\u53ca\u666e\u901a\u8a71\n\u5de5\u4f5c\u5730\u5340\u53ca\u6642\u9593:\u00a0\n\n\u5730\u5340 :\u00a0\n\u00a0 \u00a0 \u00a0 \u00a0 \u00a0 \u00a0 \u00a0 \u00a0 - \u65b0\u754c\u6216\u4e5d\u9f8d\n\n\n\u6642\u9593:\n\u00a0 \u00a0 \u00a0 \u00a0 \u00a0 \u00a0 \u00a0- \u661f\u671f\u4e00\u81f3\u4e94: 11:00 - 21:00\n\n\u00a0 \u00a0 \u00a0 \u00a0 \u00a0 \u00a0 \u00a0- \u661f\u671f\u516d: 09:00 - 21:00\n\u00a0 \u00a0 \u00a0 \u00a0 \u00a0 \u00a0 \u00a0- \u661f\u671f\u65e5: 09:00-18:00\n\n*** \u8acb\u5217\u51fa\u53ef\u4efb\u6559\u6642\u9593\u53ca\u5730\u5340\uff0c\u65b9\u4fbf\u7434\u884c\u4f5c\u51fa\u4e0a\u73ed\u6642\u6578/\u65e5\u6578\u5b89\u6392\u53ca\u5de5\u4f5c\u5730\u9ede\u4e4b\u5b89\u6392 ***\n\u00a0 \u00a0 \u00a0 \u00a0 \u00a0 \u00a0 \u00a0 \u00a0 \u00a0 \u00a0 \u00a0 \u00a0 \u00a0 \u00a0 \u00a0 \u00a0 \u00a0 \u00a0 \u00a0 \u00a0 \u00a0 \u00a0 \u00a0 \u00a0 \u00a0 \u00a0 \u00a0 \u00a0 \u00a0\uff08*** \u8acb\u9078\u64c7\u6700\u5c11\u5169\u5929\u4efb\u6559 ***)\n\u00a0 \u00a0 \u00a0 \u00a0\u00a0\n\u00a0\u6642\u85aa :\u00a0\n$80-120/hr\n\u5982\u60a8\u5c0d\u6b64\u8077\u4f4d\u611f\u8208\u8da3\uff0c\u00a0\u8acb\u5c07\u5c65\u6b77 (\u8a3b\u660e\u7533\u8acb\u8077\u4f4d) \u767c\u9001\u81f3 Apply Now.\n\n**\u8acb\u65bc\u5c65\u6b77\u4e0a\u8a3b\u660e\u53ef\u4efb\u6559\u7684\u5730\u5340,\u65e5\u671f\u53ca\u6642\u9593, \u4ee5\u4fbf\u4f5c\u51fa\u4e0a\u73ed\u65e5\u6578\u53ca\u6642\u6578\u5b89\u6392\n\n\uff08\u6240\u6709\u7533\u8acb\u90fd\u5c07\u53d7\u5230\u4fdd\u5bc6\u8655\u7406\uff0c\u6240\u6709\u6536\u96c6\u7684\u500b\u4eba\u8cc7\u6599\u50c5\u7528\u65bc\u62db\u8058\u76ee\u7684\u3002\uff09\n", "employment_types": ["Part Time", "Freelance"], "selling_points": [], "locations": ["Others"], "categories": ["Education", "Tutor / Instructor", "Others", "Entertainment - Artists / Singers / Musicians"], "post_time": "2021-12-30T05:40:04Z", "salary": {"currency": null, "max": null, "min": null, "period": "hourly", "term": null}, "salary_visible": false, "title_keywords": ["tutor"], "responsibilities": ["hr"], "requirements": {"degrees": [], "majors": [], "languages": [], "language_level": [], "hard_skills": [], "soft_skills": [], "languages_combined": []}, "experience_required": {"duration": [], "field": []}}, {"job_id": "100003009007921", "location_code": "hk", "company": "Greenery Music Limited", "job_title": "\u5404\u985e\u4e2d\u897f\u6a02\u5668\u5c0e\u5e2b - \u5c0f\u63d0\u7434 / \u6d41\u884c\u9f13 / \u92fc\u7434 / \u6728\u7d50\u4ed6 / \u96fb\u7d50\u4ed6 / \u4f4e\u97f3\u7d50\u4ed6 / Ukulele \u7b49 (Music Tutor)", "description": "\u5de5\u4f5c :\n- \u6559\u6388\u4e0d\u540c\u6a02\u5668\u53ca\u6a02\u7406\u8a8d\u8b58\n\u00a0 (\u5404\u985e\u4e2d\u897f\u6a02\u5668/\u8072\u6a02, \u5305\u62ec : \u92fc\u7434 / \u5c0f\u63d0\u7434 / \u9577\u7b1b / \u6728\u7d50\u4ed6 / \u96fb\u7d50\u4ed6 / \u6d41\u884c\u9f13 / \u4f4e\u97f3\u7d50\u4ed6 / Ukulele \u7b49)\n\u5b78\u6b77\u53ca\u8981\u6c42 :\n- \u6301\u6709\u82f1\u570b\u7687\u5bb6\u97f3\u6a02\u5b78\u9662\u516b\u7d1a\u6216\u540c\u7b49\u8cc7\u6b77\u6216\u4ee5\u4e0a/\u540c\u7b49\u7a0b\u5ea6\n- \u5177\u76f8\u95dc\u6559\u5b78\u7d93\u9a57\n- \u5177\u5e7c\u5152\u6559\u80b2\u7d93\u9a57/\u6559\u6388\u5e7c\u5152\u97f3\u6a02\u73ed/\u76f8\u95dc\u8b49\u66f8\u8005\u512a\u5148\u8003\u616e\n\u6240\u6709\u5c0e\u5e2b\u7684\u57fa\u672c\u8981\u6c42 :\n- \u826f\u597d\u7cb5\u8a9e, \u4e00\u822c\u82f1\u8a9e\u53ca\u666e\u901a\u8a71\n- \u826f\u597d\u6e9d\u901a\u6280\u5de7\n- \u6709\u8cac\u4efb\u5fc3\u53ca\u5b88\u6642\n- \u5c0d\u5e7c\u5152\u6559\u80b2\u6709\u71b1\u8aa0\n- \u89aa\u5207\u53cb\u5584, \u5c0d\u5c0f\u670b\u53cb\u6709\u611b\u5fc3\u53ca\u8010\u6027\n\u5de5\u4f5c\u5730\u9ede :\n- \u4e5d\u9f8d/\u65b0\u754c\n\u5de5\u4f5c\u6642\u9593 :\n- \u8acb\u5217\u51fa\u53ef\u4efb\u6559\u6642\u9593\u53ca\u5730\u5340\uff0c\u65b9\u4fbf\u7434\u884c\u4f5c\u51fa\u4e0a\u73ed\u6642\u6578/\u65e5\u6578\u5b89\u6392\u53ca\u5de5\u4f5c\u5730\u9ede\u4e4b\u5b89\u6392\n- \u661f\u671f\u4e00\u81f3\u4e94: 11:00-21:00\n- \u661f\u671f\u516d: 09:00 - 21:00\n- \u661f\u671f\u65e5: 09:00-18:00\n\n\u6642\u85aa :\n$100-480/hr [\u85aa\u91d1\u8996\u4e4e\u5c0e\u5e2b\u8cc7\u6b77\u53ca\u6559\u5b78\u7d93\u9a57\u800c\u5b9a]\u00a0\n\n\u5982\u60a8\u5c0d\u6b64\u8077\u4f4d\u611f\u8208\u8da3\uff0c\u00a0\u8acb\u5c07\u5c65\u6b77 (\u8a3b\u660e\u7533\u8acb\u8077\u4f4d) \u767c\u9001\u81f3 Apply Now.\n\n**\u8acb\u65bc\u5c65\u6b77\u4e0a\u8a3b\u660e\u53ef\u4efb\u6559\u7684\u5730\u5340,\u65e5\u671f\u53ca\u6642\u9593, \u4ee5\u4fbf\u4f5c\u51fa\u4e0a\u73ed\u65e5\u6578\u53ca\u6642\u6578\u5b89\u6392\n\n\uff08\u6240\u6709\u7533\u8acb\u90fd\u5c07\u53d7\u5230\u4fdd\u5bc6\u8655\u7406\uff0c\u6240\u6709\u6536\u96c6\u7684\u500b\u4eba\u8cc7\u6599\u50c5\u7528\u65bc\u62db\u8058\u76ee\u7684\u3002\uff09\n", "employment_types": ["Part Time", "Freelance"], "selling_points": [], "locations": ["Others"], "categories": ["Education", "Tutor / Instructor", "Others", "Entertainment - Artists / Singers / Musicians"], "post_time": "2021-12-30T05:40:03Z", "salary": {"currency": null, "max": null, "min": null, "period": "hourly", "term": null}, "salary_visible": false, "title_keywords": ["music tutor"], "responsibilities": ["hr"], "requirements": {"degrees": [], "majors": [], "languages": [], "language_level": [], "hard_skills": [], "soft_skills": [], "languages_combined": []}, "experience_required": {"duration": [], "field": []}}, {"job_id": "100003008998292", "location_code": "hk", "company": "Spectrum Lounge", "job_title": "Full Time Store Associate (Art & Retail) (Start-Up Creative Company)", "description": "We are currently looking for a Full Time Store Associate, who loves art and meeting new people.\n\nAbout Spectrum Lounge:\nSpectrum is a start-up company, our Lounge mainly provide art-crafting experience (Workshop) for customers to enjoy, which aims to bring a layered shopping experience to everyone.\n\nResponsibilities:\n\nLead and highly responsible for store Daily Operation of Store\nCommunicate with back office team for front retail arrangement\nMeet and greet the customers:\u00a0handle customers' enquiries and correspondence.\nConduct Art-craft experience class\nAssist in Events if necessary\n\nRequirements:\n\nResponsible\u00a0\nLoves art and design\nRetail Experience is highly preferred\nLove meeting new people\nSeeking for new changes\nFluent in spoken Cantonese, English and Mandarin\n*** Art-related experience is not necessary.\n\nInfo:\u00a0\n\n7 Day off a month with Public Holiday\nAttractive Salary with Target Bonus\nYearly Performance-based Salary\n\nStore Location:\u00a0L201, Eslite, Star House, 3 Salisbury Road, Tsim Sha Tsui\nWebsite:\u00a0www.spectrumloungehk.com\nFacebook:\u00a0SpectrumLounge HK\nInstagram:\u00a0SpectrumLounge.HK", "employment_types": ["Full Time"], "selling_points": [], "locations": ["Tsim Sha Tsui"], "categories": ["Sales, CS & Business Devpt", "Customer Service - Supervisor / Officer", "Others", "Entertainment - Artists / Singers / Musicians", "Retail Sales"], "post_time": "2021-12-29T01:44:41Z", "salary": {"currency": null, "max": null, "min": null, "period": "monthly", "term": null}, "salary_visible": false, "title_keywords": ["associate", "creative"], "responsibilities": ["communicate with", "daily operation", "back office"], "requirements": {"degrees": [], "majors": [], "languages": ["cantonese", "english", "mandarin"], "language_level": ["fluent"], "hard_skills": ["facebook"], "soft_skills": ["responsible"], "languages_combined": [{"language": "cantonese", "language_level": ["fluent"]}, {"language": "english", "language_level": ["fluent"]}, {"language": "mandarin", "language_level": ["fluent"]}]}, "experience_required": {"duration": [], "field": ["related", "retail"]}}, {"job_id": "100003008998548", "location_code": "hk", "company": "Spectrum Lounge", "job_title": "Part Time Store Associate (Art & Retail) (Start-Up Creative Company)", "description": "We are currently looking for a Part Time Store Associate, who loves art and meeting new people.\n\nAbout Spectrum Lounge:\nSpectrum is a start-up creative company, our Lounge mainly provide art-crafting experience (Workshop) for customers to enjoy, which aims to bring a layered shopping experience to everyone.\n\nResponsibilities:\n\nAssist in Daily Operation of Store\nMeet and greet the customers:\u00a0handle customers' enquiries and correspondence.\nAssist in conducting Art-craft experience class (Workshop) for customers.\nAssist in Events if necessary\n\nRequirements:\n\nLoves art and design\nRetail Experience is highly preferred\nLove meeting new people\nSeeking for new changes\nFluent in spoken Cantonese, English and Mandarin\n*** Art-related experience is not necessary.\n\nInfo:\u00a0\n\n7 Day off a month with Public Holiday\nAttractive Salary with Target Bonus\nYearly Performance-based Salary\n\nStore Location:\u00a0L201, Eslite, Star House, 3 Salisbury Road, Tsim Sha Tsui\nOffice Location: Kwun Tong\u00a0\nWebsite:\u00a0www.spectrumloungehk.com\nFacebook:\u00a0SpectrumLounge HK\nInstagram:\u00a0SpectrumLounge.HK", "employment_types": ["Part Time"], "selling_points": [], "locations": ["Tsim Sha Tsui"], "categories": ["Sales, CS & Business Devpt", "Customer Service - Supervisor / Officer", "Others", "Entertainment - Artists / Singers / Musicians", "Retail Sales"], "post_time": "2021-12-27T16:04:04Z", "salary": {"currency": null, "max": null, "min": null, "period": "monthly", "term": null}, "salary_visible": false, "title_keywords": ["associate", "creative"], "responsibilities": ["workshop", "daily operation"], "requirements": {"degrees": [], "majors": [], "languages": ["cantonese", "english", "mandarin"], "language_level": ["fluent"], "hard_skills": ["facebook"], "soft_skills": [], "languages_combined": [{"language": "cantonese", "language_level": ["fluent"]}, {"language": "english", "language_level": ["fluent"]}, {"language": "mandarin", "language_level": ["fluent"]}]}, "experience_required": {"duration": [], "field": ["related", "retail"]}}, {"job_id": "100003008996716", "location_code": "hk", "company": "JNP Fashion Limited", "job_title": "Full-time / Part-time retail SALES (Fashion Advisor) - Ladies' wear", "description": "JOB LOCATION: ( CENTRAL / TSIM SHA TSUI )\n\nTAV (JNP fashion limited) \u2013 Hong Kong based Korean fashion brand is actively seeking for a retail sales (Fashion Advisor)\u00a0in Central and TST shop.\n\nResponsibilities:\n\n\u25cfMaximize sales opportunities to achieve monthly sales targets\n\u25cfHandle daily operation activities in the shop\n\u25cfProvide excellent service and quality shopping experience to customers\n\u25cfAssist marketing team in promoting the brand (e.g. In-house Model)\n\nRequirements:\n\n\u25cfExcellent communication and interpersonal skills\n\u25cfPleasant, presentable and well-groomed with good fashion sense\n\u25cfWork with passion; high team spirit; independent; responsible\n\u25cfFluent in Cantonese, Mandarin, English, or Korean\n\u25cfAdvanced computer knowledge, especially in MS Excel\n\nWe're hiring both Full-time and Part-time.\n\nPlease write your expected salary on resume.", "employment_types": ["Full Time", "Part Time", "Permanent", "Temporary", "Contract", "Internship"], "selling_points": ["Handle daily operation activities in retail shop", "In-house Model / Marketing associate(Korean brand)", "Have good communication skills in ladies' wear"], "locations": ["Tsim Sha Tsui"], "categories": ["Others", "Entertainment - Artists / Singers / Musicians", "Sales, CS & Business Devpt", "Retail Sales", "Student / Fresh Graduate / No Experience"], "post_time": "2021-12-23T08:21:20Z", "salary": {"currency": null, "max": null, "min": null, "period": "monthly", "term": null}, "salary_visible": false, "title_keywords": ["fashion advisor", "retail sales"], "responsibilities": ["quality", "daily operation"], "requirements": {"degrees": [], "majors": [], "languages": ["cantonese", "english", "mandarin", "korean"], "language_level": ["fluent"], "hard_skills": ["ms excel"], "soft_skills": ["team spirit", "independent", "advanced", "responsible", "presentable", "pleasant", "communication and interpersonal skills"], "languages_combined": [{"language": "cantonese", "language_level": ["fluent"]}, {"language": "english", "language_level": ["fluent"]}, {"language": "mandarin", "language_level": ["fluent"]}, {"language": "korean", "language_level": ["fluent"]}]}, "experience_required": {"duration": [], "field": []}}, {"job_id": "100003009002368", "location_code": "hk", "company": "Hong Kong Funky Dance Centre", "job_title": "Dance Instructor / Instructor Trainee", "description": "You must be\n\nPassionate about dance and fitness\nAn expert in Fitness Dance / Jazz / Latin / Street Dance\nAt least 3 years experience in dance teaching and choreography\nAt least 5 years experience in dancing and dance performance\nWith good academic background in dancing preferred\nEnergetic, charming and patient\n\nWe provide\n\nProfessional instructor trainings\nOpportunities to achieve international qualifications\nAttractive remuneration packages\nGood career prospects\u00a0\n\nInterested parties, please send full CV and expected salary by clicking \"Apply Now\". You are invited to visit our website at www.funkydance.com.hk.\n\n(All applications will be treated in strict confidence and being used for recruitment purpose only. Unsuccessful applications will be destroyed within 12 months.)\n", "employment_types": ["Full Time", "Part Time", "Permanent"], "selling_points": ["Passionate about dance and fitness", "An expert in Fitness Dance/ Jazz/ Latin/ Hip Hop", "At least 3 years experience in dance teaching"], "locations": ["Not Specified"], "categories": ["Beauty Care / Health", "Athletics / Fitness / Sports & Recreation", "Education", "Tutor / Instructor", "Others", "Entertainment - Artists / Singers / Musicians"], "post_time": "2021-12-28T04:52:17Z", "salary": {"currency": null, "max": null, "min": null, "period": "monthly", "term": null}, "salary_visible": false, "title_keywords": ["trainee"], "responsibilities": [], "requirements": {"degrees": [], "majors": [], "languages": [], "language_level": [], "hard_skills": [], "soft_skills": ["patient", "energetic", "passionate about"], "languages_combined": []}, "experience_required": {"duration": ["at least 3 years", "at least 5 years"], "field": ["teaching"]}}, {"job_id": "100003008989643", "location_code": "hk", "company": "Hong Kong Dance Alliance Limited", "job_title": "Editorial Trainee / Assistant", "description": "Hong Kong Dance Alliance Limited\nThe Hong Kong Dance Alliance is a non-profit-making body that supports and promotes all forms of dance in Hong Kong. Our projects include publishing the bi-monthly periodical dance journal/hk, presenting new works by young choreographers in \u2018New Force in Motion\u2019 Series and organizing the annual Hong Kong Dance Awards.\n\ndance journal/hk\nAs the only printed periodical devoted exclusively to dance in Hong Kong, it provides a platform for reviews, in-depth critiques, regular columns and feature articles on dance, dancers, dance educators, dance audiences, and the broader Hong Kong dance industry.\u00a0\n\nWe are looking for a full-time Editorial Trainee / Assistant to assist the editorial team in shaping and implementing the publication and publicity for the Alliance.\n\nDuties include:\n\nWorking closely with the editorial team to formulate the editorial direction of every issue and corresponding articles of dance journal/hk\nHandling the production and distribution of dance journal/hk, such as coordinating interviews, articles write-up and translation, managing online publications, contacting designers, printing houses and distribution points\nAdministering the online platforms of dance journal/hk\nAssisting in monitoring the production schedule and maintaining accurate documentation\nSupporting the logistics of advertisement services to deliver promotional packages for clients\nCollaborating with the office team to produce publicity materials for the Alliance as necessary\n\nSuitable candidates should:\n\nBe a Hong Kong permanent resident of age 18 or above possessing a recognised university degree in journalism / arts administration / cultural studies / languages / communications, which was obtained within the past 3 years\nPreferably have 1-2 year(s) of work experience; fresh graduates are also welcome\nBe a responsible and self-motivated team player who is able to work independently and under pressure\nBe comfortable with meeting tight schedules and possible follow-up work during unconventional hours\nBe detail-oriented and always strive for accuracy and precision\nDemonstrate strong communication, organizational and interpersonal skills\nBe familiar with and interested in the publishing and/or performing arts industry\u00a0\u00a0\nWrite and speak fluent English and Chinese\nHave elementary knowledge in creating content for social media\n\nCandidates with less experience may be considered for the position of Editorial Trainee. Immediate availability is preferred.\n\nInterested parties are invited to send in a detailed CV with a cover letter in English indicating current and expected salaries along with the earliest available date. Shortlisted candidates will be invited for an interview.\u00a0\n\nFurther details can be found at\u00a0http://www.hkdanceall.org/?a=doc&id=890.\n\nPersonal data collected will be used for recruitment purposes only and will be treated confidentially.\n\nThis position is supported by the Arts Production Internship Scheme of the Hong Kong Arts Development Council.\n\n", "employment_types": ["Full Time"], "selling_points": [], "locations": ["Sheung Wan"], "categories": ["Media & Advertising", "Editorial / Journalism", "Others", "Entertainment - Artists / Singers / Musicians", "Student / Fresh Graduate / No Experience"], "post_time": "2021-12-21T04:52:18Z", "salary": {"currency": null, "max": null, "min": null, "period": "monthly", "term": null}, "salary_visible": false, "title_keywords": ["assistant", "trainee"], "responsibilities": ["social media", "maintaining", "schedules", "monitoring", "communication", "logistics", "schedule", "documentation", "publication", "administration"], "requirements": {"degrees": ["university degree"], "majors": ["journalism", "communications"], "languages": ["english", "chinese"], "language_level": ["fluent"], "hard_skills": ["documentation", "translation", "bi"], "soft_skills": ["self-motivated", "work independently", "under pressure", "responsible", "organizational", "interested in", "detail-oriented", "communication", "interpersonal skills", "devoted", "team player", "accurate"], "languages_combined": [{"language": "english", "language_level": ["fluent"]}, {"language": "chinese", "language_level": ["fluent"]}]}, "experience_required": {"duration": [], "field": ["editorial"]}}, {"job_id": "100003008989029", "location_code": "hk", "company": "Ocean Park Corporation", "job_title": "Project Supervisor", "description": "(Long-term Contract)\n\nReporting to the Project Manager, the incumbent will assist to produce the seasonal events, sales projects and shows from concept development to actual execution and dismantle of the event. He/she will assist the Project Manager to prepare the tender package for procurement, deal with the contractors and suppliers in all matters related to the events preparation, and monitor the petty cash spending for each event. \u00a0 He/she will also need to prepare the staff plan and show schedule for the seasonal events, and coordinate with other departments to ensure the smooth operations of the events.\n\nRequirements:\n\nDegree holder in Theatrical or Event Management from HKAPA is preferred\nWith at least 2 to 4 years\u2019 experience in entertainment business or project management\nWith strong connections with local vendors in related business will be an advantage\nFamiliar with the Park's festival events and standard will be an advantage\nGood leadership and communication skills\nGood command of both spoken and written English and Cantonese\nWilling to work on weekends and public holidays\nWilling to work night shifts\n\nApplications including details of qualifications, working experience, expected salary, contact telephone number and address should be applied via:\u00a0http://careers.oceanpark.com.hk\u00a0--> Job opening --> Full time/ Long-term.\n\nApplicants not contacted within six weeks may consider their application unsuccessful. Personal data collected will be used for recruitment-related purpose only.", "employment_types": ["Full Time", "Contract"], "selling_points": ["Assist to produce the seasonal events", "Prepare the staff plan and show schedule", "Actual execution and dismantle of the event"], "locations": ["Aberdeen"], "categories": ["Others", "Entertainment - Artists / Singers / Musicians", "Marketing / Public Relations", "Public Relations - Event Management"], "post_time": "2021-12-21T02:26:50Z", "salary": {"currency": null, "max": null, "min": null, "period": "monthly", "term": null}, "salary_visible": false, "title_keywords": ["project supervisor"], "responsibilities": ["reporting", "management", "operations", "monitor", "coordinate with", "communication", "project management", "recruitment", "schedule", "tender", "plan", "contact", "personal data"], "requirements": {"degrees": ["degree holder"], "majors": [], "languages": ["cantonese", "english"], "language_level": ["good command"], "hard_skills": ["project management"], "soft_skills": ["communication skills", "project management", "leadership", "smooth"], "languages_combined": [{"language": "cantonese", "language_level": ["good command"]}, {"language": "english", "language_level": ["good command"]}]}, "experience_required": {"duration": ["at least 2 to 4 years"], "field": ["project management", "business"]}}, {"job_id": "100003008987689", "location_code": "hk", "company": "Cool Style Talent Management Limited", "job_title": "Artiste Assistant", "description": "Job Responsibilities:\n\nProvide administrative support to artiste team\nAssist Artiste Managers to manage artiste daily schedule\nFollow up a variety of assigned job tasks in a comprehensive and reliable manner\nHandle ad hoc duties as assigned\n\nRequirements:\n\nHKCEE / HKDSE or above\nExcellent communication and interpersonal skills\nWell organized, attentive to details with strong sense of responsibility\nKnowledge of photography & video editing, post-production is preferred\nExcellent command of spoken and written English and Chinese, including Putonghua\nWork irregular hours as assigned\nImmediate availability is preferred\n\nWe offer attractive remuneration to successful candidates. To apply, please send your full resume stating date available, present and expected salary by mail to Group Human Resources & Administration Controller, Media Asia Group Holdings Limited, 11/F Lai Sun Commercial Centre, 680 Cheung Sha Wan Road, Kowloon or click the button \"APPLY NOW\" shown below to send your application via email.\u00a0\n\nWebsite:\u00a0www.mediaasia.com\u00a0\n\nPersonal data provided in the employment applications will be treated in strict confidence and used only for recruitment purpose by the Lai Sun Group Companies. All unsuccessful applications will be destroyed upon completion of the process.\n\nA member of the Lai Sun Group", "employment_types": ["Full Time", "Permanent"], "selling_points": ["Provide administrative support to artiste team", "HKCEE / HKDSE or above", "Passion in entertainment industry"], "locations": ["Chai Wan"], "categories": ["Others", "Entertainment - Artists / Singers / Musicians"], "post_time": "2021-12-20T07:34:51Z", "salary": {"currency": null, "max": null, "min": null, "period": "monthly", "term": null}, "salary_visible": false, "title_keywords": ["assistant"], "responsibilities": ["provide administrative support", "schedule", "ad hoc duties"], "requirements": {"degrees": ["hkdse"], "majors": [], "languages": ["putonghua", "english", "chinese"], "language_level": ["excellent"], "hard_skills": ["video editing"], "soft_skills": ["communication and interpersonal skills", "well organized", "attentive to details", "sense of responsibility"], "languages_combined": [{"language": "putonghua", "language_level": ["excellent"]}, {"language": "english", "language_level": ["excellent"]}, {"language": "chinese", "language_level": ["excellent"]}]}, "experience_required": {"duration": [], "field": []}}, {"job_id": "100003009034701", "location_code": "hk", "company": "Opera Hong Kong Limited", "job_title": "Officer (Education and Outreach)", "description": "Responsibilities\n\n\u00a0\u00a0\u00a0 Assist in managing Opera Hong Kong Children Chorus\n\u00a0\u00a0\u00a0 Assist in managing Education and Outreach programmes\n\u00a0\u00a0\u00a0 Provide administrative support in general\n\u00a0\u00a0\u00a0 Working on Saturdays required\n\u00a0\u00a0\u00a0 Five-day work job\nRequirement\n\n\u00a0\u00a0\u00a0 Recognised tertiary education qualification or equivalent\n\u00a0\u00a0\u00a0 Two years or above working experience; preferably related working experience\n\u00a0\u00a0\u00a0 Good PC skills and well versed with Microsoft Office applications\n\u00a0\u00a0\u00a0 Fluency in English and Mandarin is preferable\n\u00a0\u00a0\u00a0 Pro-active, responsible, willing to learn and detail-minded\n\u00a0\u00a0 \u00a0Good interpersonal and communications skills\n\u00a0\u00a0 \u00a0Able to work independently under pressure and minimal supervision\nInterested parties please send your CV with cover letter and expected salary to Opera Hong Kong Ltd, Room 1907, Pacific Plaza, 410 Des Voeux Road West, Hong Kong (mark \u2018Confidential\u2019 on envelop), or via email on or before 26 Jan 2022.\n\n\nAll information received will be kept in strict confidence and only for employment-related purpose. Applicants who do not hear from us within 8 weeks may consider their applications unsuccessful and their data will be destroyed within 12 months of receipt.", "employment_types": ["Full Time"], "selling_points": ["Children Chorus, Training, Opera, Concert", "Education, Administration, Music Centre, Singing", "Musical, Class managment"], "locations": ["Sai Ying Pun"], "categories": ["Education", "Others", "Others", "Entertainment - Artists / Singers / Musicians", "Management", "General Management"], "post_time": "2022-01-10T03:59:26Z", "salary": {"currency": null, "max": null, "min": null, "period": "monthly", "term": null}, "salary_visible": false, "title_keywords": ["officer"], "responsibilities": ["provide administrative support"], "requirements": {"degrees": [], "majors": [], "languages": ["english", "mandarin"], "language_level": ["fluency"], "hard_skills": ["pc skills", "microsoft office"], "soft_skills": ["detail-minded", "work independently", "under pressure", "responsible", "willing to learn", "pro-active", "interpersonal"], "languages_combined": [{"language": "english", "language_level": ["fluency"]}, {"language": "mandarin", "language_level": ["fluency"]}]}, "experience_required": {"duration": ["two years"], "field": ["related"]}}]